Workbook

Sheet Unplanned leaves
A1: Total Leaves | B1: =SUM(B21:F21) -> 4
B2: Resource Name
A3: Sprint | B3: Prisla Sabatini | C3: Mahesh Muppala | D3: Nithish Manian | E3: Vinoth Vedapuri | F3: Aravindh Jayapal | G3: Remarks
A4: 26.3 DS Sprint 3(6-Feb-2026 to 19-Feb-2026) | B4: 0 | C4: 0 | D4: 0 | E4: 0 | F4: 0
A5: 26.4 DS Sprint 1(20-Feb-2026 to 05-Mar-2026) | B5: 0 | C5: 0 | D5: 0 | E5: 0 | F5: 0
A6: 26.4 DS Sprint 2(06-Mar-2026 to 19-Mar-2026) | B6: 1 | C6: 0 | D6: 0 | E6: 0 | F6: 0
A7: 26.4 DS Sprint 3(20-Mar-2026 to 02-Apr-2026) | B7: 0 | C7: 0 | D7: 1 | E7: 0 | F7: 0
A8: 26.5 DS Sprint 1(03-Apr-2026 to 16-Apr-2026) | B8: 0 | C8: 0 | D8: 0 | E8: 0 | F8: 0
A9: 26.5 DS Sprint 2(17-Apr-2026 to 30-Apr-2026) | B9: 0 | C9: 0 | D9: 0 | E9: 0 | F9: 0
A10: 26.5 DS Sprint 3(01-May-2026 to 14-May-2026) | B10: 1 | C10: 0 | D10: 0 | E10: 0 | F10: 0
A11: 26.7 DS Sprint 1(15-May-2026 to 28-May-2026) | B11: 0 | C11: 0 | D11: 0 | E11: 1 | F11: 0
A21: Total | B21: =SUM(B4:B20) -> 2 | C21: =SUM(C4:C20) -> 0 | D21: =SUM(D4:D20) -> 1 | E21: =SUM(E4:E20) -> 1 | F21: =SUM(F4:F20) -> 0

Sheet Dashboard
A1: Current Sprint | B1: {=INDEX($B$2:$B$101,MATCH(1,(($D$2:$D$101 >=TODAY())*($C$2:$C$101<=TODAY())),0))} -> 26.7 DS Sprint 1 | C1: Current Sprint Sheet | D1: =CONCATENATE(B1,"-Status") -> 26.7 DS Sprint 1-Status | E1: Sprint Start Date | F1: =VLOOKUP($B$1,$B$1:$C$101,2) -> 46157 | G1: Sprint End Date | H1: =VLOOKUP($B$1,$B$1:$D$101,3) -> 46170 | I1: Application Name | J1: MSB Dev | K1: Users | L1: prislasabatini.irudayaraj@relevantz.com;mahesh.chandrasekharraju@relevantz.com;aravindh.jayapal@relevantz.com;nithish.manian@relevantz.com;vinothkumar.vedapuri@relevantz.com | M1: Teams Name(GP-MSB.PartnerIntegrations (PI)) | N1: 19:bd003fe8174540cbb372a488e0fe06dd@thread.v2
A2: Sprint Type | B2: Sprint # | C2: Sprint Start Date | D2: Sprint End Date | E2: Assigned | F2: Completed | G2: Story points introduced/removed | H2: Sprint Summary | I2: Accomplishments | J2: Remarks | K2: Retro Points (Internal & External) | L2: Unplanned Leaves | M2: Data sanity Audit Status | N2: AuditDate | O2: Backlog Health
A3: =IF(AND($D$1>=C3,$D$1<=D3),"CurrentSprint","NA") -> NA | B3: 13.5 DS Sprint 2 | C3: 45303 | D3: 45316 | E3: 20 | F3: 21 | J3: Stretch Story completed with points - 1 | K3: Internal: External:
A4: =IF(AND($D$1>=C4,$D$1<=D4),"CurrentSprint","NA") -> NA | B4: 13.5 DS Sprint 3 | C4: 45317 | D4: 45330 | E4: 31 | F4: 30 | J4: Stretch Story completed with points - 2 | K4: Internal: External:
A5: =IF(AND($D$1>=C5,$D$1<=D5),"CurrentSprint","NA") -> NA | B5: 13.6 DS Sprint 1 | C5: 45331 | D5: 45344 | E5: 33 | F5: 33 | G5: 26sp - On Hold | J5: Two 13 sp Stories went on Hold [Epic story splitted into 6 stories from client side] | K5: Internal: External:
A6: =IF(AND($D$1>=C6,$D$1<=D6),"CurrentSprint","NA") -> NA | B6: 13.6 DS Sprint 2 | C6: 45345 | D6: 45358 | E6: 35 | F6: 22 | J6: Development completed and Testing is inprogress (Story-43092 with 13sp) | K6: Internal: External:
A7: =IF(AND($D$1>=C7,$D$1<=D7),"CurrentSprint","NA") -> NA | B7: 13.6 DS Sprint 3 | C7: 45359 | D7: 45372 | E7: 47 | F7: 47 | J7: Regression sprint | K7: Internal: External:
A8: =IF(AND($D$1>=C8,$D$1<=D8),"CurrentSprint","NA") -> NA | B8: 13.7 DS Sprint 1 | C8: 45373 | D8: 45386 | E8: 25 | F8: 10 | J8: Stretch Story completed with 2sp Development completed and Testing is inprogress (Story-43584 & 43693 with 16sp) Automation story was going to carry with 1sp | K8: Internal: External:
A9: =IF(AND($D$1>=C9,$D$1<=D9),"CurrentSprint","NA") -> NA | B9: 13.7 DS Sprint 2 | C9: 45387 | D9: 45400 | E9: 26 | F9: 21 | G9: 5sp - On Hold | J9: Stretch Stories completed with 7sp 5sp story is on hold [Development completed and not able to test because Destiny(Vendor) side getting error for refund payments] | K9: Internal: External:
A10: =IF(AND($D$1>=C10,$D$1<=D10),"CurrentSprint","NA") -> NA | B10: 13.7 DS Sprint 3 | C10: 45401 | D10: 45414 | E10: 43 | F10: 29 | G10: 9-SP Stretch | J10: Regression sprint. Stretch Stories completed with 6sp. Regression story(QA) get carry forwarded with 20SP because new code build not yet deployed(May-1st) on Staging & Staging CA. New story 44472 was picked up on the last day of the sprint. | K10: Internal: External:
A11: =IF(AND($D$1>=C11,$D$1<=D11),"CurrentSprint","NA") -> NA | B11: 13.8 DS Sprint 1 | C11: 45415 | D11: 45428 | E11: 18 | F11: 23 | G11: 3 - SP On Hold 25 - SP Stretch | J11: 3sp story is on hold [The whole EPIC-43987 is going to revisit with new solution]. Stretch Stories: 8sp are completed 7sp are raised PR's (carry forwarded) 10sp are inprogress (carry forwarded) | K11: Internal: External:
A12: =IF(AND($D$1>=C12,$D$1<=D12),"CurrentSprint","NA") -> NA | B12: 13.8 DS Sprint 2 | C12: 45429 | D12: 45442 | E12: 31 | F12: 25 | G12: 9 - SP Stretch | J12: One committed story get carry forwarded with 8SP because client kept PR on hold and to revisit on API query with new pattern. Stretch Stories: 2sp are completed 3sp are Testing 4sp are inprogress (carry forwarded) | K12: Internal: External:
A13: =IF(AND($D$1>=C13,$D$1<=D13),"CurrentSprint","NA") -> NA | B13: 13.8 DS Sprint 3 | C13: 45443 | D13: 45456 | E13: 36 | F13: 36 | G13: 2- SP Strech On Hold | J13: Regression sprint. | K13: Internal: External:
A14: =IF(AND($D$1>=C14,$D$1<=D14),"CurrentSprint","NA") -> NA | B14: 14.0 DS Sprint 1 | C14: 45457 | D14: 45470 | E14: 29 | F14: 32 | G14: 7 - SP Stretch | J14: Stretch Stories: 45092 & 45127 Partially completed. Total 4SP carry forwarded. | K14: Internal: External:
A15: =IF(AND($D$1>=C15,$D$1<=D15),"CurrentSprint","NA") -> NA | B15: 14.0 DS Sprint 2 | C15: 45471 | D15: 45484 | E15: 27 | F15: 32 | G15: 16 - SP Stretch | J15: Stretch Stories: 5sp are completed 11sp are inprogress (carry forwarded) | K15: Internal: External:
A16: =IF(AND($D$1>=C16,$D$1<=D16),"CurrentSprint","NA") -> NA | B16: 14.0 DS Sprint 3 | C16: 45485 | D16: 45498 | E16: 40 | F16: 56 | G16: 24 - SP Stretch | J16: Regression sprint. Stretch Stories: 16sp are completed 8sp are inprogress (carry forwarded) | K16: Internal: External:
A17: =IF(AND($D$1>=C17,$D$1<=D17),"CurrentSprint","NA") -> NA | B17: 14.1 DS Sprint 1 | C17: 45499 | D17: 45512 | E17: 36 | F17: 41 | G17: 20 - SP Stretch | J17: Stretch Stories: 1) 5sp are completed 2) 13sp are Testing 3)2sp defect taken on last day of the sprint. We fixed and testing pending. | K17: Internal: External:
A18: =IF(AND($D$1>=C18,$D$1<=D18),"CurrentSprint","NA") -> NA | B18: 14.1 DS Sprint 2 | C18: 45513 | D18: 45526 | E18: 36 | F18: 49 | G18: 20 - SP Stretch | J18: Stretch Stories: 1) 13sp are completed 2) 7sp are inprogress | K18: Internal: External:
A19: =IF(AND($D$1>=C19,$D$1<=D19),"CurrentSprint","NA") -> NA | B19: 14.1 DS Sprint 3 | C19: 45527 | D19: 45540 | E19: 36 | F19: 23 | J19: Regression sprint. REgression story is carry forwarded due to hot fixes | K19: Internal: External:
A20: =IF(AND($D$1>=C20,$D$1<=D20),"CurrentSprint","NA") -> NA | B20: 14.2 DS Sprint 1 | C20: 45541 | D20: 45554 | E20: 28 | F20: 28 | G20: 13 - SP Stretch | J20: One committed story get carry forwarded with 8SP(Development completed and code merged, Only testing need to be done). Stretch Stories: 1) 8sp are completed 2) 5sp are inprogress (carry forwarded) | K20: Internal: External:
A21: =IF(AND($D$1>=C21,$D$1<=D21),"CurrentSprint","NA") -> NA | B21: 14.2 DS Sprint 2 | C21: 45555 | D21: 45568 | E21: 33 | F21: 22 | G21: 10 - SP Stretch | J21: Three committed story got carry forwarded with 16SP(1 story is on review with 5sp and 2 stories are on testing with 11sp) - Due to Hotfix Stretch Stories: 1) 5sp are Completed 2) 5sp are Testing (carry forwarded) Internal CRC - 2 External CRC - 3 QA Defects - 6 Escaped Defects - 0 | K21: Internal: External:
A22: =IF(AND($D$1>=C22,$D$1<=D22),"CurrentSprint","NA") -> NA | B22: 14.2 DS Sprint 3 | C22: 45569 | D22: 45582 | E22: 36 | F22: 41 | G22: Introduced - 5 | I22: Regression Sprint | J22: Regression sprint. Stretch Stories: 5sp are completed 7sp are PR's raised (carry forwarded) Internal CRC - 0 External CRC - 1 QA Defects - 4 Escaped Defects - 0 | K22: Internal: External:
A23: =IF(AND($D$1>=C23,$D$1<=D23),"CurrentSprint","NA") -> NA | B23: 14.3 DS Sprint 1 | C23: 45583 | D23: 45596 | E23: 23 | F23: 44 | G23: Introduced - 21 | I23: DataHub MSBP Api's | J23: Stretch Stories: 21sp are completed 2sp are Testing (carry forwarded) - Stretch 3sp are inprogress (carry forwarded) - Stretch Internal CRC - 0 External CRC - 3 QA Defects - 3 Escaped Defects - 7 | K23: Internal: External:
A24: =IF(AND($D$1>=C24,$D$1<=D24),"CurrentSprint","NA") -> NA | B24: 14.3 DS Sprint 2 | C24: 45597 | D24: 45610 | E24: 23 | F24: 18 | I24: MSB-Web UserHub DataHub | J24: One Story and One Defect is Carry Forwarded. Internal CRC - 0 External CRC - 0 QA Defects - 2 Escaped Defects - 1 | K24: Internal: External:
A25: =IF(AND($D$1>=C25,$D$1<=D25),"CurrentSprint","NA") -> NA | B25: 14.3 DS Sprint 3 | C25: 45611 | D25: 45624 | E25: 37 | F25: 39 | G25: Introduced - 7 | I25: Regression Sprint | J25: Regression sprint and One Story is Carry Forwarded. Stretch Stories: 7sp are completed Internal CRC - 0 External CRC - 0 QA Defects - 1 Escaped Defects -2 | K25: Internal: External:
A26: =IF(AND($D$1>=C26,$D$1<=D26),"CurrentSprint","NA") -> NA | B26: 14.4 DS Sprint 1 | C26: 45625 | D26: 45638 | E26: 21 | F26: 27 | G26: Introduced - 14 | I26: DataHub MSBP Api's Mobilepay Api's | J26: MSB DevServices team name got changed to MSB PartnerIntegrations (msb-pi) One committed story got carry forwarded with 8SP(Development completed and testing need to be done). Stretch Stories: 14sp are completed 13sp are Code Review (carry forwarded) - Stretch Internal CRC - 0 External CRC - 0 QA Defects - 1 Escaped Defects - 4 | K26: Internal: External:
A27: =IF(AND($D$1>=C27,$D$1<=D27),"CurrentSprint","NA") -> NA | B27: 14.4 DS Sprint 2 | C27: 45639 | D27: 45666 | E27: 38 | F27: 41 | G27: Introduced - 3 | I27: DataHub MSB-Web MSBP Api's Mobilepay Api's | J27: Stretch Stories: 3sp are completed 3sp are Testing (carry forwarded) - Stretch 5sp are Review (carry forwarded) - Stretch 13sp are inprogress (carry forwarded) - Stretch Internal CRC - 0 External CRC - 2 QA Defects - 3 Escaped Defects - 0 | K27: Internal: External:
A28: =IF(AND($D$1>=C28,$D$1<=D28),"CurrentSprint","NA") -> NA | B28: 14.4 DS Sprint 3 | C28: 45667 | D28: 45680 | E28: 45 | F28: 45 | I28: Regression Sprint | J28: Internal CRC - 0 External CRC - 0 QA Defects - 1 Escaped Defects - 1 | K28: Internal: External:
A29: =IF(AND($D$1>=C29,$D$1<=D29),"CurrentSprint","NA") -> NA | B29: 14.5 DS Sprint 1 | C29: 45681 | D29: 45694 | E29: 37 | F29: 34 | G29: Introduced - 2 | I29: UserHub DataHub | J29: One committed story got carry forwarded with 5SP(Development completed and testing need to be done). Stretch Stories: 2sp are completed 1sp are Review (carry forwarded) - Stretch 29sp are inprogress (carry forwarded) - Stretch Internal CRC - 4 External CRC - 7 QA Defects - 2 Escaped Defects - 1 | K29: Internal: External:
A30: =IF(AND($D$1>=C30,$D$1<=D30),"CurrentSprint","NA") -> NA | B30: 14.5 DS Sprint 2 | C30: 45695 | D30: 45708 | E30: 29 | F30: 48 | G30: Introduced - 19 | I30: DataHub REST Api's Integration Api's | J30: Stretch Stories: 19sp are completed 2sp are Review (carry forwarded) - Stretch 5sp are inprogress (carry forwarded) - Stretch Internal CRC - 8 External CRC - 1 QA Defects - 4 Escaped Defects - 3 | K30: Internal: External:
A31: =IF(AND($D$1>=C31,$D$1<=D31),"CurrentSprint","NA") -> NA | B31: 14.5 DS Sprint 3 | C31: 45709 | D31: 45722 | E31: 44 | F31: 50 | G31: Introduced - 6 | I31: Regression Sprint | J31: Stretch Stories: 6sp are completed Internal CRC - 7 External CRC - 1 QA Defects - 0 Escaped Defects - 1 | K31: Internal: External:
A32: =IF(AND($D$1>=C32,$D$1<=D32),"CurrentSprint","NA") -> NA | B32: 14.6 DS Sprint 1 | C32: 45723 | D32: 45736 | E32: 31 | F32: 47 | G32: Introduced - 16 | I32: DataHub MSB-Web MSB Pay Api's PowerSchool Data Plugin | J32: Stretch Stories: 16sp are completed 3sp are Testing (carry forwarded) - Stretch Peer Test Defects - 5 Internal CRC - 10 External CRC - 0 QA Defects - 0 Escaped Defects - 1 | K32: Internal: External:
A33: =IF(AND($D$1>=C33,$D$1<=D33),"CurrentSprint","NA") -> NA | B33: 14.6 DS Sprint 2 | C33: 45737 | D33: 45750 | E33: 47 | F33: 41 | G33: Introduced - 7 | I33: DataHub UserHub MSB-Web MSB Pay Api's PowerSchool Data Plugin | J33: One committed story got carry forwarded with 13SP. Stretch Stories: 7sp are completed 2sp are Review (carry forwarded) - Stretch Peer Test Defects - 3 Internal CRC - 6 External CRC - 3 QA Defects - 1 Escaped Defects - 1 | K33: Internal: External:
A34: =IF(AND($D$1>=C34,$D$1<=D34),"CurrentSprint","NA") -> NA | B34: 14.6 DS Sprint 3 | C34: 45751 | D34: 45764 | E34: 81 | F34: 78 | I34: Regression Sprint | J34: One committed story (development completed but not merged) was carried forward with 3 story points because it was moved to the 14.7 release. Peer Test Defects - 0 Internal CRC - 10 External CRC - 4 QA Defects - 1 Escaped Defects - 2 | K34: Internal: External:
A35: =IF(AND($D$1>=C35,$D$1<=D35),"CurrentSprint","NA") -> NA | B35: 14.7 DS Sprint 1 | C35: 45765 | D35: 45778 | E35: 43 | F35: 46 | G35: Introduced - 6 | I35: DataHub MSB-Web MSB Dev Portal MSBP Api's REST Api's | J35: One committed story got carry forwarded with 3SP(Due to BB and BB also fixed. Testing need to be done). Stretch Stories: 6sp are completed 5sp are Testing (carry forwarded) - Stretch 4sp are Review (carry forwarded) - Stretch 4sp are Development (carry forwarded) - Stretch Peer Test Defects - 0 Internal CRC - 3 External CRC - 5 QA Defects - 2 Escaped Defects - 1 | K35: Internal: External:
A36: =IF(AND($D$1>=C36,$D$1<=D36),"CurrentSprint","NA") -> NA | B36: 14.7 DS Sprint 2 | C36: 45779 | D36: 45792 | E36: 11 | F36: 23 | G36: Introduced - 12 | I36: DataHub REST Api's | J36: Stretch Stories: 12sp are completed 3sp are Testing (carry forwarded) - Stretch Peer Test Defects - 0 Internal CRC - 7 External CRC - 3 QA Defects - 2 Escaped Defects - 1 | K36: Internal: External:
A37: =IF(AND($D$1>=C37,$D$1<=D37),"CurrentSprint","NA") -> NA | B37: 14.7 DS Sprint 3 | C37: 45793 | D37: 45806 | E37: 37 | F37: 37 | I37: Regression Sprint | J37: Peer Test Defects - 0 Internal CRC - 1 External CRC - 0 QA Defects - 0 Escaped Defects - 2 | K37: Internal: External:
A38: =IF(AND($D$1>=C38,$D$1<=D38),"CurrentSprint","NA") -> NA | B38: 15.0 DS Sprint 1 | C38: 45807 | D38: 45820 | E38: 16 | F38: 23 | G38: Introduced - 7 | H38: 1) Implemented batch deletion records on full sync for both student & enrollment. 2) Included the fee attributes in Export file. 3) Added new two columns(Last Student Sync & Last Fee Sync) on Integrations page. 4) Couple of defect fixed on DH. | I38: 1) Implemented batch deletion records on full sync for both student & enrollment. 2) Included the fee attributes in Export file. 3) Added new two columns(Last Student Sync & Last Fee Sync) on Integrations page. 4) Couple of defect fixed on DH. | J38: Stretch Stories: 7sp are completed Peer Test Defects - 0 Internal CRC - 1 External CRC - 2 QA Defects - 4 Escaped Defects - 0 | K38: Internal: What went well? Completed committed stories and pulled the additional stretch stories. What didn't go well? None Challenges None
A39: =IF(AND($D$1>=C39,$D$1<=D39),"CurrentSprint","NA") -> NA | B39: 15.0 DS Sprint 2 | C39: 45821 | D39: 45834 | E39: 14 | F39: 14 | G39: Introduced - 5 | H39: 1) Updated the default behavior to enable Update Fees Real-Time option Datahub to IncidentIQ Provider 2) Included the fee attributes in Destiny 3) Added Modules options to the Payment Method REST API endpoints | I39: 1) Updated the default behavior to enable Update Fees Real-Time option Datahub to IncidentIQ Provider 2) Included the fee attributes in Destiny 3) Added Modules options to the Payment Method REST API endpoints | J39: One committed defect got carry forwarded with 5SP(Due to relying on George and he is busy with release, this has caused a delay in resolving the defect.). Peer Test Defects - 0 Internal CRC - 3 External CRC - 4 QA Defects - 1 Escaped Defects - 0 | K39: Internal: What went well? Completed 90% committed stories What didn't go well? One committed defect got carry forwarded. The issue is only observed in the test environment, whereas other environments are functioning correctly. Challenges None
A40: =IF(AND($D$1>=C40,$D$1<=D40),"CurrentSprint","NA") -> NA | B40: 15.0 DS Sprint 3 | C40: 45835 | D40: 45848 | E40: 32 | F40: 35 | G40: Introduced - 3 | H40: 1) Added new automation 2) Fixed automation failures 3) Regression testing | I40: 1) Added new automation 2) Fixed automation failures 3) Regression testing | J40: Stretch Stories: 3sp are completed Peer Test Defects - 0 Internal CRC - 0 External CRC - 0 QA Defects - 1 Escaped Defects - 0 | K40: Internal: What went well? 1)Completed regression testing in all environments 2)Wrote the new automation and also fixed the failures What didn't go well? None Challenges None
A41: =IF(AND($D$1>=C41,$D$1<=D41),"CurrentSprint","NA") -> NA | B41: 15.1 DS Sprint 1 | C41: 45849 | D41: 45862 | E41: 13 | F41: 16 | G41: Introduced - 3 | H41: 1) Added last 4 digits of DDA to payment gateway model 2) Added a custom District Logo on MSBP API's 3) Improved the performance on GET districts endpoint on REST API | I41: 1) Added last 4 digits of DDA to payment gateway model 2) Added a custom District Logo on MSBP API's 3) Improved the performance on GET districts endpoint on REST API | J41: Peer Test Defects - 0 Internal CRC - 3 External CRC - 4 QA Defects - 1 Escaped Defects - 2 | K41: Internal: What went well? 1) Completed committed stories and pulled the additional strech stories. 2) QA has conducted proper validation by following every scenario. What didn't go well? None Challenges? None External: What went well: 1) Prisla shared that internal retro discussions helped the team improve on developer testing. 2) Matt mentioned that the main commit stories went smoothly. 3) Carmin gave shoutouts to Mahesh for his great work on performance stories. What didn’t go well: None
A42: =IF(AND($D$1>=C42,$D$1<=D42),"CurrentSprint","NA") -> NA | B42: 15.1 DS Sprint 2 | C42: 45863 | D42: 45876 | E42: 9 | F42: 17 | G42: Introduced - 8 | H42: 1) Done adjustments on Manage Developer Accounts page 2) Provider access of Developer Portal - PowerSchool page for all 3) Added Developer Portal – Contact Us 4) Added Datahub - Manage Students - Show provider and inactive status in school dropdown list 5) Post OrderID to iiQ payments for all payments to Incident IQ | I42: 1) Done adjustments on Manage Developer Accounts page 2) Provider access of Developer Portal - PowerSchool page for all 3) Added Developer Portal – Contact Us 4) Added Datahub - Manage Students - Show provider and inactive status in school dropdown list 5) Post OrderID to iiQ payments for all payments to Incident IQ | J42: Peer Test Defects - 0 Internal CRC - 2 External CRC - 1 QA Defects - 1 Escaped Defects - 0 | K42: Internal: What went well? 1) Completed committed stories and pulled the additional strech stories. 2) QA involved and supporting to WAVE team What didn't go well? 1) We were unable to connect to the IncidentIQ provider from our local environment, so we couldn't test the story locally and received a BB Challenges? 1) The IncidentIQ provider is not connecting from the local environment, which poses challenges for development and testing External: What went well: 1) The team saw strong collaboration this sprint. 2) Prisla noted that internal POV and peer reviews reduced bouncebacks 3) George appreciated everyone’s efforts and team spirit.. What didn’t go well: None
A43: =IF(AND($D$1>=C43,$D$1<=D43),"CurrentSprint","NA") -> NA | B43: 15.1 DS Sprint 3 | C43: 45877 | D43: 45890 | E43: 39 | F43: 39 | H43: 1) Added new Integration API's to support student meal balance 2) Added new automation 3) Fixed automation failures 4) Regression testing | I43: 1) Added new Integration API's to support student meal balance 2) Added new automation 3) Fixed automation failures 4) Regression testing | J43: Peer Test Defects - 0 Internal CRC - 0 External CRC - 1 QA Defects - 1 Escaped Defects - 0 | K43: Internal: What went well? 1) Completed committed stories. 2) Wrote the new automation and also fixed the failures 3) Completed regression testing in all environments 4) Accepted the new Meal Balance API story during the regression sprint and completed its implementation and testing What didn't go well? 1) Scenarios were missing in the new automation Challenges? 1) Mahesh: Receiving pull requests for peer review late in the evening is acceptable in rare cases, but it's becoming a regular occurrence. The review and testing process takes considerable time, which often extends my working hours. 2) Nivetha: Faced local test build issue which was resolved later External: What went well: 1) The client appreciated the progress this sprint, highlighting that almost all automation stories were completed successfully. 2) Strong contribution of QAs, which ensured smooth delivery and left them very satisfied with the outcome. What didn’t go well: None
A44: =IF(AND($D$1>=C44,$D$1<=D44),"CurrentSprint","NA") -> NA | B44: 15.2 DS Sprint 1 | C44: 45891 | D44: 45904 | E44: 14 | F44: 19 | G44: Introduced - 5 | H44: 1) Add new Integration API's to allow batch Confirm of Payments 2) Add new Integration API's to allow batch Deactivate of Fees 3) Add Optionally exclude and remove inactive enrollments from student records 4) Optionally include meal balance and invoices in the REST 'Get Household' API response 5) Disable the school appropriately when school filters are set in Infinite Campus OR | I44: 1) Add new Integration API's to allow batch Confirm of Payments 2) Add new Integration API's to allow batch Deactivate of Fees 3) Add Optionally exclude and remove inactive enrollments from student records 4) Optionally include meal balance and invoices in the REST 'Get Household' API response 5) Disable the school appropriately when school filters are set in Infinite Campus OR | J44: Peer Test Defects - 0 Internal CRC - 3 External CRC - 1 QA Defects - 0 Escaped Defects - 0 | K44: Internal: What went well? 1) Completed committed stories(4) and pulled the additional strech stories(2). 2) QA has conducted proper validation by following every scenario. 3) Great to see there have been no bounce backs during this sprint What didn't go well? None Challenges? None External: What went well: 1) The team showed strong collaboration this sprint, completing committed stories and even stretch goals with solid support across Dev and QA. 2) Capturing analysis docs in Axosoft is a good step, though it needs fine-tuning when existing functionality is affected. What didn’t go well: None
A45: =IF(AND($D$1>=C45,$D$1<=D45),"CurrentSprint","NA") -> NA | B45: 15.2 DS Sprint 2 | C45: 45905 | D45: 45918 | E45: 17 | F45: 24 | G45: Introduced - 7 | H45: 1) Add batch implementation for Class enrollment, Classes, Courses, Terms on Full Sync 2) Remove the deprecated MSBP endpoints in v9 3) Add student information to the payment model 4) Add to support student provider to the Meal Balance Integration API 5) Remove the leadnig and trailing spaces in all ID fields for Oneroster file import | I45: 1) Add batch implementation for Class enrollment, Classes, Courses, Terms on Full Sync 2) Remove the deprecated MSBP endpoints in v9 3) Add student information to the payment model 4) Add to support student provider to the Meal Balance Integration API 5) Remove the leadnig and trailing spaces in all ID fields for Oneroster file import | J45: Peer Test Defects - 0 Internal CRC - 1 External CRC - 1 QA Defects - 0 Escaped Defects - 1 | K45: Internal: What went well? 1) Completed committed stories(5) and pulled the additional strech stories(3). 2) QA has conducted proper validation by following every scenario. 3) Great to see there have been no bounce backs during this sprint What didn't go well? None Challenges? None External:
A46: =IF(AND($D$1>=C46,$D$1<=D46),"CurrentSprint","NA") -> NA | B46: 15.2 DS Sprint 3 | C46: 45919 | D46: 45932 | E46: 34 | F46: 34 | H46: 1) Added new automation 2) Fixed automation failures 3) Regression testing | I46: 1) Added new automation 2) Fixed automation failures 3) Regression testing | J46: Peer Test Defects - 0 Internal CRC - 0 External CRC - 0 QA Defects - 0 Escaped Defects - 0 | K46: Internal: What went well? 1) Completed committed stories(3). 2) Wrote the new automation and also fixed the failures 3) Completed regression testing in all environments What didn't go well? None Challenges? None External:
A47: =IF(AND($D$1>=C47,$D$1<=D47),"CurrentSprint","NA") -> NA | B47: 15.3 DS Sprint 1 | C47: 45933 | D47: 45946 | E47: 17 | F47: 16 | H47: 1) MSBP-Added user log for Meals AutoPay settings API if any changes had done 2) MSB-Added Alias on payment method and also its override the RTF payment methods if any alias matched. 3) Datahub-Support Student Number source override option for Aeries | I47: 1) MSBP-Added user log for Meals AutoPay settings API if any changes had done 2) MSB-Added Alias on payment method and also its override the RTF payment methods if any alias matched. 3) Datahub-Support Student Number source override option for Aeries | J47: One committed defect was carried forward with 1SP to the next sprint due to the inability to test in the test environment caused by a proxy issue. This was also communicated to the client. Peer Test Defects - 0 Internal CRC - 0 External CRC - 1 QA Defects - 1 Escaped Defects - 2 | K47: Internal: What went well? 1) Completed committed stories(5). 2) QA has conducted proper validation by following every scenario. What didn't go well? None Challenges? None External:
A48: =IF(AND($D$1>=C48,$D$1<=D48),"CurrentSprint","NA") -> NA | B48: 15.3 DS Sprint 2 | C48: 45947 | D48: 45960 | E48: 21 | F48: 20 | G48: Introduced - 2 | H48: 1) REST–Invoicing documentation for V1 & V2 2) MSBA-Student search to return only pending status invoices also include the payable invoices 3) Datahub-Change encoding for ID fields on Aspen OR 4) DataHub-Fee attributes generated with spaces and replace with special char | I48: 1) REST–Invoicing documentation for V1 & V2 2) MSBA-Student search to return only pending status invoices also include the payable invoices 3) Datahub-Change encoding for ID fields on Aspen OR 4) DataHub-Fee attributes generated with spaces and replace with special char | J48: One committed story was carried forward with 3 story points. We requested more information but cannot proceed due to insufficient API response. Peer Test Defects - 0 Internal CRC - 1 External CRC - 1 QA Defects - 0 Escaped Defects - 4 | K48: Internal: What went well? 1) Completed committed stories(5). 2) QA has conducted proper validation by following every scenario. What didn't go well? None Challenges? Local environment issue is still not fixed External: Shoutouts Prisla - Aspen encoding looks great, thank you Mahesh & Prisla - Team support during leaves Mahesh - Thanks for making sense of invoicing via REST API
A49: =IF(AND($D$1>=C49,$D$1<=D49),"CurrentSprint","NA") -> NA | B49: 15.3 DS Sprint 3 | C49: 45961 | D49: 45974 | E49: 27 | F49: 29 | G49: Introduced - 2 | H49: 1) Added new automation 2) Fixed automation failures 3) Regression testing | I49: 1) Added new automation 2) Fixed automation failures 3) Regression testing | J49: Peer Test Defects - 0 Internal CRC - 0 External CRC - 1 QA Defects - 1 Escaped Defects - 2 | K49: What went well? 1) Completed committed stories 2) Wrote the new automation and also fixed the failures 3) Completed regression testing in all environments What didn't go well? None Challenges? Local environment issues due to recent changes made by client
A50: =IF(AND($D$1>=C50,$D$1<=D50),"CurrentSprint","NA") -> NA | B50: 26.1 DS Sprint 1 | C50: 45975 | D50: 45992 | E50: 12 | F50: 21 | G50: Introduced - 9 | H50: 1) MSBP-Get full mark up for Messages/Announcements 2) Datahub-Student enrollments show primary school enrollments first in UI and API response 3) MSBCheckout-return only eligible records on GET GL Accounts API 4) REST-Support Store availability on GL Accounts API's 5) Datahub-Auto confirm payments without matching fees in provider | I50: 1) MSBP-Get full mark up for Messages/Announcements 2) Datahub-Student enrollments show primary school enrollments first in UI and API response 3) MSBCheckout-return only eligible records on GET GL Accounts API 4) REST-Support Store availability on GL Accounts API's 5) Datahub-Auto confirm payments without matching fees in provider | J50: Peer Test Defects - 0 Internal CRC - 3 External CRC - 0 QA Defects - 1 Escaped Defects - 4 | K50: What went well? 1) Completed committed stories 2) Review and peer testing was done properly so that quality deliverables was achieved 3) Nithish has done a good job. He analyzed the existing functionality, compared it with the current story AC, and came up with a couple of clarifications at the very beginning What didn't go well? Unplanned Leave Challenges? Testing is delayed due to deployment issues in the test environment
A51: =IF(AND($D$1>=C51,$D$1<=D51),"CurrentSprint","NA") -> NA | B51: 26.1 DS Sprint 2 | C51: 45993 | D51: 46002 | E51: 13 | F51: 27 | G51: Introduced - 14 | H51: 1) Datahub: Improve the PERFORMANCE for the end syncs for Schools, Students, Contacts, Rostering, Fees & Meals 2) Datahub: Auto confirm payments without matching fees in provider 3) MSBA: Add preview & checkout controls for store products 4) MobilePay: Add order model to Cart Process response 5) MobilePay: Add Gateway DBA name to Cart Process response | I51: 1) Datahub: Improve the PERFORMANCE for the end syncs for Schools, Students, Contacts, Rostering, Fees & Meals 2) Datahub: Auto confirm payments without matching fees in provider 3) MSBA: Add preview & checkout controls for store products 4) MobilePay: Add order model to Cart Process response 5) MobilePay: Add Gateway DBA name to Cart Process response | J51: Peer Test Defects - 0 Internal CRC - 0 External CRC - 3 QA Defects - 0 Escaped Defects - 0 | K51: What went well? 1) Completed committed stories 2) Review and peer testing was done properly so that quality deliverables was achieved 3) Pulled couple of stretch stories and completed What didn't go well? None Challenges? None
A52: =IF(AND($D$1>=C52,$D$1<=D52),"CurrentSprint","NA") -> NA | B52: 26.1 DS Sprint 3 | C52: 46003 | D52: 46030 | E52: 28 | F52: 28 | H52: 1) Added new REST API to Create District 2) Added data table to list the MSB - Developer Accounts 3) Added new automation 4) Regression testing | I52: 1) Added new REST API to Create District 2) Added data table to list the MSB - Developer Accounts 3) Added new automation 4) Regression testing | J52: Peer Test Defects - 0 Internal CRC - 0 External CRC - 1 QA Defects - 0 Escaped Defects - 0 | K52: What went well? 1) Completed committed stories. 2) Completed the regression What didn't go well? Taking more time to complete the automation stories due to environment issue Challenges? Unable to run the automation due to environment issue
A53: =IF(AND($D$1>=C53,$D$1<=D53),"CurrentSprint","NA") -> NA | B53: 26.3 DS Sprint 1 | C53: 46031 | D53: 46044 | E53: 19 | F53: 16 | H53: 1) Added new REST API to Create District 2) Support Eligibility option on Integration API 3) Allow user to reset password without opting into SMS 4) Support Meal Payments in GET payments on Integration API 5) MobilePay: Add Gateway DBA name to Cart Process response | I53: 1) Added new REST API to Create District 2) Support Eligibility option on Integration API 3) Allow user to reset password without opting into SMS 4) Support Meal Payments in GET payments on Integration API 5) MobilePay: Add Gateway DBA name to Cart Process response | J53: One committed story was carried forward with 3SP to the next sprint due to the client raised a bounceback that was not related to this story, as it was pre-existing. However, the client requested that it be covered in this story(50965). Peer Test Defects - 0 Internal CRC - 0 External CRC - 1 QA Defects - 3 Escaped Defects - 1 | K53: What went well? Completed the committed stories, except for one that had a BB and was pre-existing. The client requested that this be covered in the same story. What didn't go well? None Challenges? Facing the local env issue Action Items? Again, we need to show the POV if there are any AC changes or issue fixes.
A54: =IF(AND($D$1>=C54,$D$1<=D54),"CurrentSprint","NA") -> NA | B54: 26.3 DS Sprint 2 | C54: 46045 | D54: 46058 | E54: 21 | F54: 21 | H54: 1) Allow user to reset password without opting into SMS 2) Added new REST API to update user 3) Added Collection Type Filter on DH providers 4) Added Support School filters | I54: 1) Allow user to reset password without opting into SMS 2) Added new REST API to update user 3) Added Collection Type Filter on DH providers 4) Added Support School filters | J54: Peer Test Defects - 0 Internal CRC - 7 External CRC - 0 QA Defects - 2 Escaped Defects - 0 | K54: What went well? 1) Completed committed stories 2) Review and peer testing was done properly so that quality deliverables was achieved What didn't go well? None Challenges? None
A55: =IF(AND($D$1>=C55,$D$1<=D55),"CurrentSprint","NA") -> NA | B55: 26.3 DS Sprint 3 | C55: 46059 | D55: 46072 | E55: 45 | F55: 40 | H55: 1) Added to support date filter for fee providers 2) Added new automation 3) Fixed automation failures 4) Regression testing | I55: 1) Added to support date filter for fee providers 2) Added new automation 3) Fixed automation failures 4) Regression testing | J55: One committed story was carried forward with 5SP to the next sprint due to the story has been moved to the next release (26.4). Peer Test Defects - 0 Internal CRC - 0 External CRC - 5 QA Defects - 4 Escaped Defects - 1 | K55: What went well? 1) Completed committed stories 2) Covered new automation for the completed for this release stories 3) Completed the regression testing What didn't go well? 1) Manage integration page issues were identified during regression testing, and some acceptance criteria were not clearly defined. During development, the developer did not raise any questions or clarifications. Even during testing, no bugs were reported and QA missed some test cases, issues arose in regression testing. This has resulted in rework on certain parts of the story 2) The school filters story(51205) was carried across multiple sprints, with one entire sprint taken to development testing and issue resolution. But, it still received review comments, which raised concerns about quality. As a result, the story was moved to the next release. 3) The Wave team was removed, which meant QA was unavailable to test the Wave stories. This resulted in an overload, and the PI QA had to step in to handle the Wave story testing as well. Challenges? Unable to run the automation due to environment issue.
A56: =IF(AND($D$1>=C56,$D$1<=D56),"CurrentSprint","NA") -> NA | B56: 26.4 DS Sprint 1 | C56: 46073 | D56: 46086 | E56: 29 | F56: 36 | G56: Introduced - 7 | H56: 1) Added Support School filters 2) Added new View page for MSB Provider from Integration List 3) REST: Create invoice for inactive students 4) REST: Added store availability for fees created with POST Invoice Template 5) Added new "Invoice by Email" Page on Developer Portal | I56: 1) Added Support School filters 2) Added new View page for MSB Provider from Integration List 3) REST: Create invoice for inactive students 4) REST: Added store availability for fees created with POST Invoice Template 5) Added new "Invoice by Email" Page on Developer Portal | J56: Peer Test Defects - 1 Internal CRC - 0 External CRC - 5 QA Defects - 5 Escaped Defects - 3 | K56: What went well? 1) Completed committed stories 2) Pulled couple of stretch stories and completed What didn't go well? Unable to close the Bounceback for story 51205 because it works fine locally, and the issue only appears in the test environment. This makes it difficult to identify the root cause. Challenges? Regarding story 51205, the issue occurs only in the test environment. To analyze it, we requested server logs, but no one—including the client’s development manager—has access to them. Only high-level access is available. Since the client also requested the logs, there has been a delay in obtaining them from the test environment.
A57: =IF(AND($D$1>=C57,$D$1<=D57),"CurrentSprint","NA") -> NA | B57: 26.4 DS Sprint 2 | C57: 46087 | D57: 46100 | E57: 27 | F57: 30 | G57: Introduced - 3 | H57: 1) Updated Financial Data on Developer Portal 2) Updated District SSO Data on Developer Portal 3) Datahub: Cleanup on developer account 4) Added data summary view for Fees on Manage Integrations 5) Show Single Sign On integrations on Manage Integrations 6) Show the data based on clientID override & providerID override on Manage Integrations | I57: 1) Updated Financial Data on Developer Portal 2) Updated District SSO Data on Developer Portal 3) Datahub: Cleanup on developer account 4) Added data summary view for Fees on Manage Integrations 5) Show Single Sign On integrations on Manage Integrations 6) Show the data based on clientID override & providerID override on Manage Integrations | J57: Peer Test Defects - 1 Internal CRC - 0 External CRC - 0 QA Defects - 1 Escaped Defects - 3 | K57: What went well? 1) Completed committed stories 2) Pulled couple of stretch stories 3) Review and peer testing was done properly so that quality deliverables was achieved What didn't go well? None Challenges? Unable to run the automation due to environment issue.
A58: =IF(AND($D$1>=C58,$D$1<=D58),"CurrentSprint","NA") -> NA | B58: 26.4 DS Sprint 3 | C58: 46101 | D58: 46114 | E58: 34 | F58: 36 | G58: Introduced - 2 | H58: 1) Added data summary view for Fees respect school filters on Manage Integrations 2) Added new automation 3) Fixed automation failures 4) Regression testing | I58: 1) Added data summary view for Fees respect school filters on Manage Integrations 2) Added new automation 3) Fixed automation failures 4) Regression testing | J58: Peer Test Defects - 0 Internal CRC - 0 External CRC - 0 QA Defects - 0 Escaped Defects - 1 | K58: What went well? 1) Completed committed stories 2) Covered new automation for the completed for this release stories 3) Completed the regression testing What didn't go well? None Challenges? Unable to run the automation due to environment issue.
A59: =IF(AND($D$1>=C59,$D$1<=D59),"CurrentSprint","NA") -> NA | B59: 26.5 DS Sprint 1 | C59: 46115 | D59: 46128 | E59: 24 | F59: 26 | G59: Introduced - 2 | H59: 1) MobilePay API: Added new Student Number search filter on GET payments API 2) MobilePay API: Added new ShiftKey search filter on GET payments API 3) MobilePay API: Documented the Close Out behavior 4) MSB: Added UserHub API page on Dev Portal 5) MSB: Show REST API integrations on Manage Integrations | I59: 1) MobilePay API: Added new Student Number search filter on GET payments API 2) MobilePay API: Added new ShiftKey search filter on GET payments API 3) MobilePay API: Documented the Close Out behavior 4) MSB: Added UserHub API page on Dev Portal 5) MSB: Show REST API integrations on Manage Integrations | J59: Peer Test Defects - 0 Internal CRC - 0 External CRC - 0 QA Defects - 4 Escaped Defects - 0 | K59: What went well? 1) Completed committed stories 2) Pulled couple of stretch stories 3) Review and peer testing was done properly so that quality deliverables was achieved What didn't go well? None Challenges? The application was upgraded the Java and JBoss versions, which impacted the local environment. Fixing the local environment took additional time. | O59: 104
A60: =IF(AND($D$1>=C60,$D$1<=D60),"CurrentSprint","NA") -> NA | B60: 26.5 DS Sprint 2 | C60: 46129 | D60: 46142 | E60: 36 | F60: 39 | G60: Introduced - 16 | H60: 1) DataHub: Deprecated the HSSConnect API v1 2) DataHub: Export Classes and Terms to XLSX 3) MobilePay: Add Credit card subtotals to Close Out 4) Checkout API: Add DBA Name as separate field in process cart response 5) Checkout API: Create Cart performance 6) REST API: Block Archived GL Accounts for Invoice Template, Invoices and Fees 7) REST API: Validate GL Account status for Stores and Products 8) NotificationHub: Add new Email and SMS API to Get notifications by userID 9) UserHub: Strip or ignore extra characters on configure SAML PowerSchool 10) UserHub: Export Identity Providers to XLSX 11) UserHub: Add validations on create and update the Identity Providers | I60: 1) DataHub: Deprecated the HSSConnect API v1 2) DataHub: Export Classes and Terms to XLSX 3) MobilePay: Add Credit card subtotals to Close Out 4) Checkout API: Add DBA Name as separate field in process cart response 5) Checkout API: Create Cart performance 6) REST API: Block Archived GL Accounts for Invoice Template, Invoices and Fees 7) REST API: Validate GL Account status for Stores and Products 8) NotificationHub: Add new Email and SMS API to Get notifications by userID 9) UserHub: Strip or ignore extra characters on configure SAML PowerSchool 10) UserHub: Export Identity Providers to XLSX 11) UserHub: Add validations on create and update the Identity Providers | J60: Two committed stories were carried forward with a total of 13 story points. The performance story(52897) is awaiting logs, while the notification story(52895) was carried forward due to bouncebacks. Peer Test Defects - 3 Internal CRC - 7 External CRC - 1 QA Defects - 2 Escaped Defects - 1 | K60: What went well? 1) Completed majority of the committed stories. 2) Pulled couple of stretch stories and completed. What didn't go well? 1) A single story(52895) came for pear review & testing for multiple times. 2) Two committed stories were carried forward. 3) The NH story(52895) had its AC changed a couple of times. Challenges? Aravindh: Facing local environment issue after upgrading the Java and JBoss versions. | O60: 117
A61: =IF(AND($D$1>=C61,$D$1<=D61),"CurrentSprint","NA") -> NA | B61: 26.5 DS Sprint 3 | C61: 46143 | D61: 46156 | E61: 29 | F61: 33 | G61: Introduced - 4 | H61: 1) Added new automation 2) Fixed automation failures 3) Regression testing | I61: 1) Added new automation 2) Fixed automation failures 3) Regression testing | J61: Peer Test Defects - 1 Internal CRC - 3 External CRC - 1 QA Defects - 1 Escaped Defects - 1 | K61: What went well? 1) Completed committed stories 2) Covered new automation for the completed for this release stories 3) Completed the regression testing What didn't go well? None Challenges? Unable to run the automation due to environment issue.
A62: =IF(AND($D$1>=C62,$D$1<=D62),"CurrentSprint","NA") -> NA | B62: 26.7 DS Sprint 1 | C62: 46157 | D62: 46170 | E62: 29 | J62: Peer Test Defects - 0 Internal CRC - 0 External CRC - 0 QA Defects - 0 Escaped Defects - 0

Sheet Defect-template
A1: S.No | B1: Sprint # | C1: Story/Defect ID | D1: Parent Story | E1: Developer | F1: Issue Type | G1: Issue Description | H1: Priority | I1: Defect Source | J1: Type | K1: Status | L1: Root Cause Category | M1: Comments

Sheet 26.7 DS Sprint 1-Status
A1: S.No | B1: Application Name | C1: Sprint Start Date | D1: Sprint End Date | E1: Sprint | F1: Developer | G1: Story ID/Defect ID | H1: Description | I1: Status | J1: Estimated(hrs/sp) | K1: Actual(hrs/sp) | L1: Actual Hours Worklog | M1: Dev start date | N1: Dev end date | O1: Unit testing | P1: Peer Tested By | Q1: Peer Tested Defects, if any | R1: Peer Reviewed By | S1: Peer Code Review Comments, if any | T1: PR Number/Link | U1: PR Created Date | V1: Reviewer 1 | W1: PR Approved Date | X1: Code Review Comments, if any | Y1: Reviewer 2 | Z1: Approved Date | AA1: Code Review Comments, if any2 | AB1: Internal PO -POV Comments | AC1: Client PO -POV Comments | AD1: Comments
A2: 1 | B2: =Dashboard!$J$1 -> MSB Dev | C2: 46157 | D2: 46170 | E2: 26.7 DS Sprint 1 | F2: Mahesh | G2: 20633 | H2: Mobile Pay - API - Disallow payment if gateway is not set or store is disabled | I2: Defect Needs More Info | J2: 5 | K2: =Table14567891011121331415171816201921222324252627282930313233343536373839[[#This Row],[Actual Hours Worklog]] / 4 -> 0
A3: 2 | B3: =Dashboard!$J$1 -> MSB Dev | C3: 46157 | D3: 46170 | E3: 26.7 DS Sprint 1 | F3: Mahesh | G3: 53028 | H3: MobilePay - API - Disallow clerks from Settings or Invoices (Cherry Creek) | I3: Story Being Developed | J3: 3 | K3: =Table14567891011121331415171816201921222324252627282930313233343536373839[[#This Row],[Actual Hours Worklog]] / 4 -> 0 | M3: 46157
A4: 3 | B4: =Dashboard!$J$1 -> MSB Dev | C4: 46157 | D4: 46170 | E4: 26.7 DS Sprint 1 | F4: Mahesh | G4: 53125 | H4: MSB - REST API - POST Invoice - Remove Provider Restriction on GL Account Selection | I4: Story Approved | J4: 3 | K4: =Table14567891011121331415171816201921222324252627282930313233343536373839[[#This Row],[Actual Hours Worklog]] / 4 -> 0
A5: 4 | B5: =Dashboard!$J$1 -> MSB Dev | C5: 46157 | D5: 46170 | E5: 26.7 DS Sprint 1 | F5: Prisla | G5: 27214 | H5: Datahub - Housekeeping Setup - Client Not Persisting | I5: Defect Found | J5: 1 | K5: =Table14567891011121331415171816201921222324252627282930313233343536373839[[#This Row],[Actual Hours Worklog]] / 4 -> 0
A6: 5 | B6: =Dashboard!$J$1 -> MSB Dev | C6: 46157 | D6: 46170 | E6: 26.7 DS Sprint 1 | F6: Prisla | G6: 27224 | H6: MSB Login – MFA Email Code Not Received on Multiple Resend Attempts | I6: Defect Found | J6: 1 | K6: =Table14567891011121331415171816201921222324252627282930313233343536373839[[#This Row],[Actual Hours Worklog]] / 4 -> 0
A7: 6 | B7: =Dashboard!$J$1 -> MSB Dev | C7: 46157 | D7: 46170 | E7: 26.7 DS Sprint 1 | F7: Prisla | G7: 53027 | H7: Datahub - Manage Fees - Change default for fee create date filter | I7: Story Approved | J7: 1 | K7: =Table14567891011121331415171816201921222324252627282930313233343536373839[[#This Row],[Actual Hours Worklog]] / 4 -> 0
A8: 7 | B8: =Dashboard!$J$1 -> MSB Dev | C8: 46157 | D8: 46170 | E8: 26.7 DS Sprint 1 | F8: Prisla | G8: 51192 | H8: MSB - Checkout API - Cart Cache cart webhook configuration (Performance) | I8: Story Approved | J8: 3 | K8: =Table14567891011121331415171816201921222324252627282930313233343536373839[[#This Row],[Actual Hours Worklog]] / 4 -> 0
A9: 8 | B9: =Dashboard!$J$1 -> MSB Dev | C9: 46157 | D9: 46170 | E9: 26.7 DS Sprint 1 | F9: Prisla | G9: 53180 | H9: MSB - REST API - Invoicing - Clean Up Postman Collection and Dev Portal | I9: Story Need More Info | J9: 2 | K9: =Table14567891011121331415171816201921222324252627282930313233343536373839[[#This Row],[Actual Hours Worklog]] / 4 -> 0
A10: 9 | B10: =Dashboard!$J$1 -> MSB Dev | C10: 46157 | D10: 46170 | E10: 26.7 DS Sprint 1 | F10: Aravindh | G10: 52899 | H10: Developer Portal - Notification Hub - Add swagger content | I10: Story Being Developed | J10: 2 | K10: =Table14567891011121331415171816201921222324252627282930313233343536373839[[#This Row],[Actual Hours Worklog]] / 4 -> 0
A11: 10 | B11: =Dashboard!$J$1 -> MSB Dev | C11: 46157 | D11: 46170 | E11: 26.7 DS Sprint 1 | F11: Aravindh | G11: 52958 | H11: UserHub - Identity Provider - Improve logging | I11: Story Approved | J11: 3 | K11: =Table14567891011121331415171816201921222324252627282930313233343536373839[[#This Row],[Actual Hours Worklog]] / 4 -> 0
A12: 11 | B12: =Dashboard!$J$1 -> MSB Dev | C12: 46157 | D12: 46170 | E12: 26.7 DS Sprint 1 | F12: Aravindh | G12: 52961 | H12: UserHub - Identity Providers - UI enhancements | I12: Story Need More Info | J12: 5 | K12: 0
A13: 12 | B13: =Dashboard!$J$1 -> MSB Dev | C13: 46157 | D13: 46170
A14: 13 | B14: =Dashboard!$J$1 -> MSB Dev | C14: 46157 | D14: 46170

Sheet 26.7 DS Sprint 1-Defect
A1: S.No | B1: Sprint # | C1: Story/Defect ID | D1: Parent Story | E1: Developer | F1: Issue Type | G1: Issue Description | H1: Priority | I1: Defect Source | J1: Type | K1: Status | L1: Root Cause Category | M1: Comments
B2: 26.7 DS Sprint 1 | C2: 20633 | E2: Mahesh | F2: Defect | G2: Mobile Pay - API - Disallow payment if gateway is not set or store is disabled | H2: Minor | I2: Manual | J2: External | K2: Inprogress
B3: 26.7 DS Sprint 1 | C3: 27214 | E3: Prisla | F3: Defect | G3: Datahub - Housekeeping Setup - Client Not Persisting | H3: Minor | I3: Manual | J3: External | K3: Inprogress
B4: 26.7 DS Sprint 1 | C4: 27224 | E4: Prisla | F4: Defect | G4: MSB Login – MFA Email Code Not Received on Multiple Resend Attempts | H4: Minor | I4: Manual | J4: External | K4: Inprogress

Sheet 26.5 DS Sprint 3-Status
A1: S.No | B1: Application Name | C1: Sprint Start Date | D1: Sprint End Date | E1: Sprint | F1: Developer | G1: Story ID/Defect ID | H1: Description | I1: Status | J1: Estimated(hrs/sp) | K1: Actual(hrs/sp) | L1: Actual Hours Worklog | M1: Dev start date | N1: Dev end date | O1: Unit testing | P1: Peer Tested By | Q1: Peer Tested Defects, if any | R1: Peer Reviewed By | S1: Peer Code Review Comments, if any | T1: PR Number/Link | U1: PR Created Date | V1: Reviewer 1 | W1: PR Approved Date | X1: Code Review Comments, if any | Y1: Reviewer 2 | Z1: Approved Date | AA1: Code Review Comments, if any2 | AB1: Internal PO -POV Comments | AC1: Client PO -POV Comments | AD1: Comments
A2: 1 | B2: =Dashboard!$J$1 -> MSB Dev | C2: 46143 | D2: 46156 | E2: 26.5 DS Sprint 3 | F2: Mahesh | G2: 53068 | H2: MSB - Partner Integrations - New Automation [26.5] | I2: Story Completed | J2: 13 | K2: =Table145678910111213314151718162019212223242526272829303132333435363738[[#This Row],[Actual Hours Worklog]] / 4 -> 30.5 | L2: 122 | M2: 46146 | N2: 46156 | O2: NA | P2: Prisla | Q2: None | R2: Prisla | S2: No Comments | T2: https://dev.azure.com/heartlandschools/MySchoolBucks/_git/MSBAutomation/pullrequest/48901 https://dev.azure.com/heartlandschools/MySchoolBucks/_git/MSBAutomation/pullrequest/48989 https://dev.azure.com/heartlandschools/MySchoolBucks/_git/MSBAutomation/pullrequest/49019 https://dev.azure.com/heartlandschools/MySchoolBucks/_git/MSBAutomation/pullrequest/49053 https://dev.azure.com/heartlandschools/MySchoolBucks/_git/MSBAutomation/pullrequest/48964 https://dev.azure.com/heartlandschools/MySchoolBucks/_git/MSBAutomation/pullrequest/48947 https://dev.azure.com/heartlandschools/MySchoolBucks/_git/MSBAutomation/pullrequest/49003 https://dev.azure.com/heartlandschools/MySchoolBucks/_git/MSBAutomation/pullrequest/48955 | U2: 46149 | V2: Prisla | W2: 46150 | X2: No Comments | Y2: Alex | Z2: 46150 | AA2: No Comments | AB2: NA | AC2: NA | AD2: Comments : The story was created as a common task to implement automation for this release stories. Facing environment issue to run the automation and that is the reason took more time to complete the automation for all the members. Time Entries : Aravindh:39hrs Prisla: 35hrs Mahesh:48hrs
A3: 2 | B3: =Dashboard!$J$1 -> MSB Dev | C3: 46143 | D3: 46156 | E3: 26.5 DS Sprint 3 | F3: Nithish | G3: 53072 | H3: MSB - Partner Integrations - Regression [26.5] | I3: Story Completed | J3: 13 | K3: =Table145678910111213314151718162019212223242526272829303132333435363738[[#This Row],[Actual Hours Worklog]] / 4 -> 11.125 | L3: 44.5 | M3: NA | N3: NA | O3: NA | P3: NA | Q3: NA | R3: NA | S3: NA | T3: NA | U3: NA | V3: NA | W3: NA | X3: NA | Y3: NA | Z3: NA | AA3: NA | AB3: NA | AC3: NA | AD3: Comments : Added only for testing purpose Time Entries: Nithish: 44.5 hr
A4: 3 | B4: =Dashboard!$J$1 -> MSB Dev | C4: 46143 | D4: 46156 | E4: 26.5 DS Sprint 3 | F4: Aravindh | G4: 52895 | H4: Notification Hub - API - Get notifications by userID (Client Services) | I4: Story Completed | J4: 2 | K4: =Table145678910111213314151718162019212223242526272829303132333435363738[[#This Row],[Actual Hours Worklog]] / 4 -> 5.625 | L4: 22.5 | M4: 46146 | N4: 46147 | O4: Manual (TestCases-50) | P4: Mahesh | Q4: 1. If provider createdstartdate and createdenddate as null. throw exception | R4: Mahesh | S4: 1. change to valid error messages 2. change to "GetEmailsResponse" 3. change validation and throw valid error | T4: https://dev.azure.com/heartlandschools/MySchoolBucks/_git/SchoolBucks/pullrequest/48839 | U4: 46147 | V4: Prisla | W4: 46148 | X4: No Comments | Y4: Alex | Z4: 46148 | AA4: No Comments | AB4: NA | AC4: NA | AD4: Comments : The story was carried over from the last sprint due to bouncebacks. Time Entries : Aravindh:15hr Prisla: 4hr Nithish:3.5hr
A5: 4 | B5: =Dashboard!$J$1 -> MSB Dev | C5: 46143 | D5: 46156 | E5: 26.5 DS Sprint 3 | F5: Prisla | G5: 52897 | H5: MSB - Checkout API - Create Cart performance (Destiny Fundraising Mgr) | I5: Story Completed | J5: 1 | K5: =Table145678910111213314151718162019212223242526272829303132333435363738[[#This Row],[Actual Hours Worklog]] / 4 -> 3 | L5: 12 | M5: 46147 | N5: 46148 | O5: Manual (TestCases-10) | P5: Mahesh | Q5: None | R5: Mahesh | S5: No Comments | T5: https://dev.azure.com/heartlandschools/MySchoolBucks/_git/SchoolBucks/pullrequest/48866 | U5: 46148 | V5: Alex | W5: 46148 | X5: No Comments | Y5: NA | Z5: NA | AA5: NA | AB5: NA | AC5: NA | AD5: Comments : The story was carried over from the last sprint due to an investigation into performance issues. Done some tuning on the code to improve performance and now waiting for the logs to verify. Time Entries: Prisla: 9hr Nithish: 3hr
A6: 5 | B6: =Dashboard!$J$1 -> MSB Dev | C6: 46143 | D6: 46156 | E6: 26.5 DS Sprint 3 Stretch | F6: Ken | G6: 27360 | H6: MSB - WEb - Course Fee Import option always shown, even when FF disabled | I6: Defect Fixed | J6: 1 | K6: =Table145678910111213314151718162019212223242526272829303132333435363738[[#This Row],[Actual Hours Worklog]] / 4 -> 0.75 | L6: 3 | M6: NA | N6: NA | O6: NA | P6: NA | Q6: NA | R6: NA | S6: NA | T6: NA | U6: NA | V6: NA | W6: NA | X6: NA | Y6: NA | Z6: NA | AA6: NA | AB6: NA | AC6: NA | AD6: Comments : Client fixed this defect added only for testing purpose Time Entries: Nithish: 3hr
A7: 6 | B7: =Dashboard!$J$1 -> MSB Dev | C7: 46143 | D7: 46156 | E7: 26.5 DS Sprint 3 Stretch | F7: Mahesh | G7: 27375 | H7: DataHub – Enrollment Full Sync Not Working for All OneRoster Provider Types | I7: Defect Fixed | J7: 2 | K7: =Table145678910111213314151718162019212223242526272829303132333435363738[[#This Row],[Actual Hours Worklog]] / 4 -> 2.25 | L7: 9 | M7: 46150 | N7: 46150 | O7: Manual (TestCases-10) | P7: Aravindh | Q7: None | R7: Aravindh | S7: No Comments | T7: https://dev.azure.com/heartlandschools/MySchoolBucks/_git/SchoolBucks/pullrequest/48938 | U7: 46150 | V7: Prisla | W7: 46153 | X7: No Comments | Y7: Ken | Z7: 46153 | AA7: Don't instantiate a new object mapper. We should already have one at the (super) class level. | AB7: NA | AC7: NA | AD7: Time Entries: Mahesh: 6hr Nithish: 3hr
A8: 7 | B8: =Dashboard!$J$1 -> MSB Dev | C8: 46143 | D8: 46156 | E8: 26.5 DS Sprint 3 Stretch | F8: Ken | G8: 27361 | H8: MSB - Course Fee Import Default Value Incorrect | I8: Defect Fixed | J8: 1 | K8: =Table145678910111213314151718162019212223242526272829303132333435363738[[#This Row],[Actual Hours Worklog]] / 4 -> 0.75 | L8: 3 | M8: NA | N8: NA | O8: NA | P8: NA | Q8: NA | R8: NA | S8: NA | T8: NA | U8: NA | V8: NA | W8: NA | X8: NA | Y8: NA | Z8: NA | AA8: NA | AB8: NA | AC8: NA | AD8: Comments : Client fixed this defect added only for testing purpose Time Entries: Nithish: 3hr
A9: 8 | B9: =Dashboard!$J$1 -> MSB Dev | C9: 46143 | D9: 46156 | K9: =Table145678910111213314151718162019212223242526272829303132333435363738[[#This Row],[Actual Hours Worklog]] / 4 -> 0
A10: 9 | B10: =Dashboard!$J$1 -> MSB Dev | C10: 46143 | D10: 46156 | K10: =Table145678910111213314151718162019212223242526272829303132333435363738[[#This Row],[Actual Hours Worklog]] / 4 -> 0
A11: 10 | B11: =Dashboard!$J$1 -> MSB Dev | C11: 46143 | D11: 46156 | K11: =Table145678910111213314151718162019212223242526272829303132333435363738[[#This Row],[Actual Hours Worklog]] / 4 -> 0

Sheet 26.5 DS Sprint 3-Defect
A1: S.No | B1: Sprint # | C1: Story/Defect ID | D1: Parent Story | E1: Developer | F1: Issue Type | G1: Issue Description | H1: Priority | I1: Defect Source | J1: Type | K1: Status | L1: Root Cause Category | M1: Comments
B2: 26.5 DS Sprint 3 | C2: 52895 | E2: Aravindh | F2: Bounceback | G2: Get SMS by UserID, passing only the UserID returns an error "Filter rowCount value must be in range [1..1000]" | H2: Minor | I2: Manual | J2: Internal | K2: Closed | L2: Development | M2: Missed in development
B3: 26.5 DS Sprint 3 Stretch | C3: 27375 | E3: Mahesh | F3: Defect | G3: DataHub – Enrollment Full Sync Not Working for All OneRoster Provider Types | H3: Major | I3: Manual | J3: Internal | K3: Closed | L3: Development | M3: JSON response was not mapped to the Enrollment object

Sheet 26.5 DS Sprint 2-Status
A1: S.No | B1: Application Name | C1: Sprint Start Date | D1: Sprint End Date | E1: Sprint | F1: Developer | G1: Story ID/Defect ID | H1: Description | I1: Status | J1: Estimated(hrs/sp) | K1: Actual(hrs/sp) | L1: Actual Hours Worklog | M1: Dev start date | N1: Dev end date | O1: Unit testing | P1: Peer Tested By | Q1: Peer Tested Defects, if any | R1: Peer Reviewed By | S1: Peer Code Review Comments, if any | T1: PR Number/Link | U1: PR Created Date | V1: Reviewer 1 | W1: PR Approved Date | X1: Code Review Comments, if any | Y1: Reviewer 2 | Z1: Approved Date | AA1: Code Review Comments, if any2 | AB1: Internal PO -POV Comments | AC1: Client PO -POV Comments | AD1: Comments
A2: 1 | B2: =Dashboard!$J$1 -> MSB Dev | C2: 46129 | D2: 46142 | E2: 26.5 DS Sprint 2 | F2: Mahesh | G2: 52444 | H2: DataHub - API - deprecate HSSConnect API v1 | I2: Story Completed | J2: 1 | K2: =Table1456789101112133141517181620192122232425262728293031323334353637[[#This Row],[Actual Hours Worklog]] / 4 -> 1 | L2: 4 | M2: 46125 | N2: 46127 | O2: Manual (TestCases-30) | P2: Aravindh | Q2: None | R2: Aravindh | S2: No Comments | T2: https://dev.azure.com/heartlandschools/MySchoolBucks/_git/SchoolBucks/pullrequest/48419 | U2: 46127 | V2: Prisla | W2: 46127 | X2: No Comments | Y2: Ken | Z2: 46127 | AA2: No Comments | AB2: NA | AC2: NA | AD2: Last sprint development was completed and QA need to test. Time Entries: Nithish: 4hrs
A3: 2 | B3: =Dashboard!$J$1 -> MSB Dev | C3: 46129 | D3: 46142 | E3: 26.5 DS Sprint 2 | F3: Mahesh | G3: 52063 | H3: MobilePay - API - Shifts - Add Credit card subtotals to Close Out (Clark Cty) | I3: Story Completed | J3: 3 | K3: =Table1456789101112133141517181620192122232425262728293031323334353637[[#This Row],[Actual Hours Worklog]] / 4 -> 1.75 | L3: 7 | M3: 46129 | N3: 46129 | O3: Manual (TestCases-10) | P3: Aravindh | Q3: None | R3: Aravindh | S3: No Comments | T3: https://dev.azure.com/heartlandschools/MySchoolBucks/_git/SchoolBucks/pullrequest/48493 | U3: 46129 | V3: Prisla | W3: 46132 | X3: No Comments | Y3: Alex | Z3: 46132 | AA3: No Comments | AB3: No Comments | AC3: No Comments | AD3: Time Entries: Mahesh: 5hrs Nithish: 2hrs
A4: 3 | B4: =Dashboard!$J$1 -> MSB Dev | C4: 46129 | D4: 46142 | E4: 26.5 DS Sprint 2 | F4: Mahesh | G4: 52858 | H4: MSB - Checkout API - Process Cart - Add DBA Name as separate field in response (Destiny Fundraising Mgr) | I4: Story Completed | J4: 2 | K4: =Table1456789101112133141517181620192122232425262728293031323334353637[[#This Row],[Actual Hours Worklog]] / 4 -> 2.25 | L4: 9 | M4: 46132 | N4: 46132 | O4: Manual (TestCases-10) | P4: Aravindh | Q4: None | R4: Aravindh | S4: No Comments | T4: https://dev.azure.com/heartlandschools/MySchoolBucks/_git/SchoolBucks/pullrequest/48513 | U4: 46132 | V4: Prisla | W4: 46132 | X4: No Comments | Y4: Ken | Z4: 46132 | AA4: No Comments | AB4: No Comments | AC4: No Comments | AD4: Time Entries: Mahesh: 6hrs Prisla: 1hrs Nithish: 2hrs
A5: 4 | B5: =Dashboard!$J$1 -> MSB Dev | C5: 46129 | D5: 46142 | E5: 26.5 DS Sprint 2 | F5: Mahesh | G5: 52891 | H5: UserHub - Configure SAML PowerSchool - strip or ignore extra characters | I5: Story Completed | J5: 1 | K5: =Table1456789101112133141517181620192122232425262728293031323334353637[[#This Row],[Actual Hours Worklog]] / 4 -> 1 | L5: 4 | M5: 46132 | N5: 46132 | O5: Manual (TestCases-10) | P5: Aravindh | Q5: None | R5: Aravindh | S5: No Comments | T5: https://dev.azure.com/heartlandschools/MySchoolBucks/_git/SchoolBucks/pullrequest/48516 | U5: 46132 | V5: Prisla | W5: 46132 | X5: No Comments | Y5: Ken | Z5: 46132 | AA5: No Comments | AB5: No Comments | AC5: No Comments | AD5: Time Entries: Mahesh: 3hrs Prisla: 1hrs
A6: 5 | B6: =Dashboard!$J$1 -> MSB Dev | C6: 46129 | D6: 46142 | E6: 26.5 DS Sprint 2 | F6: Mahesh | G6: 52897 | H6: MSB - Checkout API - Create Cart performance (Destiny Fundraising Mgr) | I6: Story Being Developed | J6: 5 | K6: =Table1456789101112133141517181620192122232425262728293031323334353637[[#This Row],[Actual Hours Worklog]] / 4 -> 0 | M6: 46133 | N6: 46135 | O6: NA | P6: Prisla | Q6: None | R6: Prisla | S6: No Comments | T6: https://dev.azure.com/heartlandschools/MySchoolBucks/_git/SchoolBucks/pullrequest/48614 https://dev.azure.com/heartlandschools/MySchoolBucks/_git/SchoolBucks/pullrequest/48719 | U6: 46135 | V6: Prisla | W6: 46135 | X6: No Comments | Y6: George | Z6: 46139 | AA6: Requested to add more logs and also in Update cart API | AB6: NA | AC6: NA | AD6: The story requested an investigation into performance issues. After analysis, no tuning opportunities were found, and no delays were observed in local, test, or staging environments. The issue occurs only in the production environment, so additional logs were added to the full cart creation process for further analysis. The story has been carried forward as we need to check the logs. We are awaiting the logs and have also informed the client.
A7: 6 | B7: =Dashboard!$J$1 -> MSB Dev | C7: 46129 | D7: 46142 | E7: 26.5 DS Sprint 2 | F7: Prisla | G7: 52537 | H7: MSB - REST API - Block "Archived" GL Accounts on POST/PUT (Invoice Template, Invoices, Fees) | I7: Story Completed | J7: 8 | K7: =Table1456789101112133141517181620192122232425262728293031323334353637[[#This Row],[Actual Hours Worklog]] / 4 -> 7.25 | L7: 29 | M7: 46129 | N7: 46133 | O7: Manual (TestCases-30) | P7: Mahesh | Q7: None | R7: Mahesh | S7: No Comments | T7: https://dev.azure.com/heartlandschools/MySchoolBucks/_git/SchoolBucks/pullrequest/48530 | U7: 46133 | V7: Ken | W7: 46133 | X7: No Comments | Y7: NA | Z7: NA | AA7: NA | AB7: No Comments | AC7: No Comments | AD7: Time Entries: Prisla: 14hrs Nithish: 15hrs
A8: 7 | B8: =Dashboard!$J$1 -> MSB Dev | C8: 46129 | D8: 46142 | E8: 26.5 DS Sprint 2 | F8: Aravindh | G8: 52831 | H8: MSB – DataHub – Export Classes and Terms to XLSX | I8: Story Completed | J8: 5 | K8: =Table1456789101112133141517181620192122232425262728293031323334353637[[#This Row],[Actual Hours Worklog]] / 4 -> 4.5 | L8: 18 | M8: 46129 | N8: 46129 | O8: Manual (TestCases-10) | P8: Mahesh | Q8: None | R8: Mahesh | S8: No Comments | T8: https://dev.azure.com/heartlandschools/MySchoolBucks/_git/SchoolBucks/pullrequest/48495 | U8: 46129 | V8: Prisla | W8: 46132 | X8: No Comments | Y8: Alex | Z8: 46132 | AA8: No Comments | AB8: No Comments | AC8: No Comments | AD8: Time Entries: Aravindh:18hrs
A9: 8 | B9: =Dashboard!$J$1 -> MSB Dev | C9: 46129 | D9: 46142 | E9: 26.5 DS Sprint 2 | F9: Aravindh | G9: 52895 | H9: Notification Hub - API - Get notifications by userID (Client Services) | I9: Story Being Tested | J9: 8 | K9: =Table1456789101112133141517181620192122232425262728293031323334353637[[#This Row],[Actual Hours Worklog]] / 4 -> 0 | M9: 46134 | N9: 46140 | O9: Manual (TestCases-60) | P9: Mahesh | Q9: 1. ApplicationId filter is not working properly when developerAcct is not system Level 2. Page and rowcount should be integer in collection insteadOf string 3. Only userId id mandatory. Other field should be set default. If not provided | R9: Mahesh | S9: 1. Should be else if insteadOf if condition 2. It should be SMS attributes insteadOf email 3.No need the filterParams instead you can add UserRequest | T9: https://dev.azure.com/heartlandschools/MySchoolBucks/_git/SchoolBucks/pullrequest/48679 | U9: 46140 | V9: Prisla | W9: 46141 | X9: 1. log message should be sms instead of email 2. Add Separate common method for date validation 3. use the same error message as email "UserId is required" 4. method name should start with lowercase | Y9: Alex | Z9: 46141 | AA9: No Comments | AB9: No Comments | AC9: The result should be show last 7 day data by default | AD9: Comments : The implementation was completed based on the acceptance criteria (AC), and a proof of value (POV) was presented to the client. During the POV, the client requested a few additional changes, after which the AC was updated accordingly. The developer submitted the code for peer review more than three times, and the peer reviewer identified several issues. Some testing scenarios were missed during testing and the internal POV. During the peer review process, the peer reviewer identified and consolidated the issues and communicated them to the team. After code implementation Alex requested to change some requestBody [Differ from Story AC] and we worked on it. The story has been carried forward because of bouncebacks Time Entries : Aravindh : 24hrs
A10: 9 | B10: =Dashboard!$J$1 -> MSB Dev | C10: 46129 | D10: 46142 | E10: 26.5 DS Sprint 2 | F10: Ken | G10: 51604 | H10: MSB - Course Fees - handle import from file | I10: Story Completed | J10: 2 | K10: =Table1456789101112133141517181620192122232425262728293031323334353637[[#This Row],[Actual Hours Worklog]] / 4 -> 1 | L10: 4 | M10: NA | N10: NA | O10: NA | P10: NA | Q10: NA | R10: NA | S10: NA | T10: NA | U10: NA | V10: NA | W10: NA | X10: NA | Y10: NA | Z10: NA | AA10: NA | AB10: NA | AC10: NA | AD10: Client developed the story added only for testing purpose Time Entries: Nithish: 4hrs
A11: 10 | B11: =Dashboard!$J$1 -> MSB Dev | C11: 46129 | D11: 46142 | E11: 26.5 DS Sprint 2 | F11: Alex | G11: 27089 | H11: MSB - MFA - Unable to add MFA method on login | I11: Defect Fixed | J11: 1 | K11: =Table1456789101112133141517181620192122232425262728293031323334353637[[#This Row],[Actual Hours Worklog]] / 4 -> 0.75 | L11: 3 | M11: NA | N11: NA | O11: NA | P11: NA | Q11: NA | R11: NA | S11: NA | T11: NA | U11: NA | V11: NA | W11: NA | X11: NA | Y11: NA | Z11: NA | AA11: NA | AB11: NA | AC11: NA | AD11: Client fixed the defect added only for testing purpose Time Entries: Nithish: 3hrs
A12: 11 | B12: =Dashboard!$J$1 -> MSB Dev | C12: 46129 | D12: 46142 | E12: 26.5 DS Sprint 2 Stretch | F12: Mahesh | G12: 27223 | H12: MSB – Getting Started – Developer Account Confirmation Email Not Received in NH | I12: Defect Rejected | J12: 1 | K12: =Table1456789101112133141517181620192122232425262728293031323334353637[[#This Row],[Actual Hours Worklog]] / 4 -> 1.5 | L12: 6 | M12: 46136 | N12: 46136 | O12: NA | P12: NA | Q12: NA | R12: NA | S12: NA | T12: NA | U12: NA | V12: NA | W12: NA | X12: NA | Y12: NA | Z12: NA | AA12: NA | AB12: NA | AC12: NA | AD12: Issue not able to reproduce and rejected Time Entries: Mahesh: 6hrs
A13: 12 | B13: =Dashboard!$J$1 -> MSB Dev | C13: 46129 | D13: 46142 | E13: 26.5 DS Sprint 2 Stretch | F13: Mahesh | G13: 52962 | H13: UserHub - Identity Providers - Export | I13: Story Completed | J13: 3 | K13: =Table1456789101112133141517181620192122232425262728293031323334353637[[#This Row],[Actual Hours Worklog]] / 4 -> 3.25 | L13: 13 | M13: 46139 | N13: 46140 | O13: Manual (TestCases-10) | P13: Aravindh | Q13: None | R13: Aravindh | S13: No Comments | T13: https://dev.azure.com/heartlandschools/MySchoolBucks/_git/SchoolBucks/pullrequest/48683 | U13: 46140 | V13: Prisla | W13: 46140 | X13: No Comments | Y13: Alex | Z13: 46140 | AA13: No Comments | AB13: No Comments | AC13: No Comments | AD13: Time Entries: Mahesh: 11hrs Prisla: 1hrs Nithish: 1hrs
A14: 13 | B14: =Dashboard!$J$1 -> MSB Dev | C14: 46129 | D14: 46142 | E14: 26.5 DS Sprint 2 Stretch | F14: Prisla | G14: 52903 | H14: MSB - REST API - Validate GL Account status on POST/PUT (Stores, Products) | I14: Story Completed | J14: 8 | K14: =Table1456789101112133141517181620192122232425262728293031323334353637[[#This Row],[Actual Hours Worklog]] / 4 -> 5.5 | L14: 22 | M14: 46133 | N14: 46133 | O14: Manual (TestCases-20) | P14: Mahesh | Q14: None | R14: Mahesh | S14: No Comments | T14: https://dev.azure.com/heartlandschools/MySchoolBucks/_git/SchoolBucks/pullrequest/48568 | U14: 46134 | V14: Ken | W14: 46134 | X14: No Comments | Y14: NA | Z14: NA | AA14: NA | AB14: No Comments | AC14: No Comments | AD14: Time Entries: Prisla: 13hrs Nithish: 9hrs
A15: 14 | B15: =Dashboard!$J$1 -> MSB Dev | C15: 46129 | D15: 46142 | E15: 26.5 DS Sprint 2 Stretch | F15: Prisla | G15: 52963 | H15: UserHub - Identity Providers - Add/ Edit validations | I15: Story Completed | J15: 1 | K15: =Table1456789101112133141517181620192122232425262728293031323334353637[[#This Row],[Actual Hours Worklog]] / 4 -> 1.75 | L15: 7 | M15: 46139 | N15: 46140 | O15: Manual (TestCases-5) | P15: Mahesh | Q15: None | R15: Mahesh | S15: No Comments | T15: https://dev.azure.com/heartlandschools/MySchoolBucks/_git/SchoolBucks/pullrequest/48670 | U15: 46139 | V15: Ken | W15: 46140 | X15: No Comments | Y15: NA | Z15: NA | AA15: NA | AB15: No Comments | AC15: No Comments | AD15: Time Entries: Prisla: 6hrs Nithish: 1hrs
A16: 15 | B16: =Dashboard!$J$1 -> MSB Dev | C16: 46129 | D16: 46142 | E16: 26.5 DS Sprint 2 Stretch | F16: Ken | G16: 27235 | H16: MSBP - API - Incorrect Greenlight registration status returned for new sign up | I16: Defect Fixed | J16: 3 | K16: =Table1456789101112133141517181620192122232425262728293031323334353637[[#This Row],[Actual Hours Worklog]] / 4 -> 1 | L16: 4 | M16: NA | N16: NA | O16: NA | P16: NA | Q16: NA | R16: NA | S16: NA | T16: NA | U16: NA | V16: NA | W16: NA | X16: NA | Y16: NA | Z16: NA | AA16: NA | AB16: NA | AC16: NA | AD16: Client fixed the defect added only for testing purpose Time Entries: Nithish: 4hrs

Sheet 26.5 DS Sprint 2-Defect
A1: S.No | B1: Sprint # | C1: Story/Defect ID | D1: Parent Story | E1: Developer | F1: Issue Type | G1: Issue Description | H1: Priority | I1: Defect Source | J1: Type | K1: Status | L1: Root Cause Category | M1: Comments
B2: 26.5 DS Sprint 2 | C2: 52537 | E2: Prisla | F2: Bounceback | G2: POST Invoice: Even when passing a valid glSalesTaxAcctID value, an incorrect validation message is returned: "FAILED CREATION: GL Sales Tax Account [glacct10] is not of type [expenditure] and cannot be used." Instead, the invoice should be created successfully. | H2: Minor | I2: Manual | J2: Internal | K2: Closed | L2: Development | M2: Missed in development
B3: 26.5 DS Sprint 2 | C3: 52537 | E3: Prisla | F3: Bounceback | G3: POST Invoice: When passing a disabled or archived value in the glExpenditureAcctID field, the invoice is created incorrectly. Instead throw validation message "FAILED CREATION: GL Expenditure Account [glacct14] is not active and cannot be used." is missing. | H3: Minor | I3: Manual | J3: Internal | K3: Closed | L3: Development | M3: Missed in development
B4: 26.5 DS Sprint 2 Stretch | C4: 27223 | E4: Mahesh | F4: Defect | G4: MSB – Getting Started – Developer Account Confirmation Email Not Received in NH | H4: Minor | I4: Manual | J4: Internal | K4: Closed | L4: Existing_Issues | M4: Issue not able to reproduce and rejected

Sheet 26.5 DS Sprint 1-Status
A1: S.No | B1: Application Name | C1: Sprint Start Date | D1: Sprint End Date | E1: Sprint | F1: Developer | G1: Story ID/Defect ID | H1: Description | I1: Status | J1: Estimated(hrs/sp) | K1: Actual(hrs/sp) | L1: Actual Hours Worklog | M1: Dev start date | N1: Dev end date | O1: Unit testing | P1: Peer Tested By | Q1: Peer Tested Defects, if any | R1: Peer Reviewed By | S1: Peer Code Review Comments, if any | T1: PR Number/Link | U1: PR Created Date | V1: Reviewer 1 | W1: PR Approved Date | X1: Code Review Comments, if any | Y1: Reviewer 2 | Z1: Approved Date | AA1: Code Review Comments, if any2 | AB1: Internal PO -POV Comments | AC1: Client PO -POV Comments | AD1: Comments
A2: 1 | B2: =Dashboard!$J$1 -> MSB Dev | C2: 46115 | D2: 46128 | E2: 26.5 DS Sprint 1 | F2: Mahesh | G2: 52428 | H2: MobilePay - API - GET /payments & GET /payments/subtotal - Support search by Student Number | I2: Story Completed | J2: 5 | K2: =Table14567891011121331415171816201921222324252627282930313233343536[[#This Row],[Actual Hours Worklog]] / 4 -> 4 | L2: 16 | M2: 46115 | N2: 46119 | O2: Manual (TestCases-10) | P2: Aravindh | Q2: None | R2: Aravindh | S2: No Comments | T2: https://dev.azure.com/heartlandschools/MySchoolBucks/_git/SchoolBucks/pullrequest/48265 | U2: 46119 | V2: Prisla | W2: 46120 | X2: No Comments | Y2: Ken | Z2: 46120 | AA2: No Comments | AB2: No Comments | AC2: No Comments | AD2: Time Enrties : Mahesh: 11hrs Prisla: 1hrs Nithish: 4hrs
A3: 2 | B3: =Dashboard!$J$1 -> MSB Dev | C3: 46115 | D3: 46128 | E3: 26.5 DS Sprint 1 | F3: Mahesh | G3: 52429 | H3: MobilePay - API - GET /payments & GET /payments/subtotal - Support filter by ShiftKey (Multiple Values) | I3: Story Completed | J3: 5 | K3: =Table14567891011121331415171816201921222324252627282930313233343536[[#This Row],[Actual Hours Worklog]] / 4 -> 4.75 | L3: 19 | M3: 46120 | N3: 46120 | O3: Manual (TestCases-10) | P3: Prisla | Q3: None | R3: Prisla | S3: No Comments | T3: https://dev.azure.com/heartlandschools/MySchoolBucks/_git/SchoolBucks/pullrequest/48290 | U3: 46120 | V3: Prisla | W3: 46120 | X3: No Comments | Y3: Ken | Z3: 46121 | AA3: No Comments | AB3: No Comments | AC3: No Comments | AD3: Time Enrties : Mahesh: 12hrs Prisla: 1hrs Nithish: 6hrs
A4: 3 | B4: =Dashboard!$J$1 -> MSB Dev | C4: 46115 | D4: 46128 | E4: 26.5 DS Sprint 1 | F4: Prisla | G4: 52336 | H4: MSB - Mobile Pay API - Document Close Out behavior R&D | I4: Story Completed | J4: 3 | K4: =Table14567891011121331415171816201921222324252627282930313233343536[[#This Row],[Actual Hours Worklog]] / 4 -> 5.75 | L4: 23 | M4: 46115 | N4: 46126 | O4: NA | P4: NA | Q4: NA | R4: NA | S4: NA | T4: NA | U4: NA | V4: NA | W4: NA | X4: NA | Y4: NA | Z4: NA | AA4: NA | AB4: NA | AC4: NA | AD4: Apr-13: This story was part of R&D for Shift Close Out behavior and required documentation. The documentation has been completed, and a discussion was held with the PO regarding the current API behavior. Next, we need to discuss with the mobile team to understand how they have implemented the logic on their side, and then finalize the approach for handling batchId in payments. Time Enrties : Prisla: 23hrs
A5: 4 | B5: =Dashboard!$J$1 -> MSB Dev | C5: 46115 | D5: 46128 | E5: 26.5 DS Sprint 1 | F5: Prisla | G5: 27100 | H5: DH - HSS Connect - Include/Exclude filter school not respecting properly after running full sync without any filter | I5: Defect Fixed | J5: 1 | K5: =Table14567891011121331415171816201921222324252627282930313233343536[[#This Row],[Actual Hours Worklog]] / 4 -> 3.25 | L5: 13 | M5: 46115 | N5: 46115 | O5: Manual (TestCases-5) | P5: Aravindh | Q5: None | R5: Aravindh | S5: No Comments | T5: https://dev.azure.com/heartlandschools/MySchoolBucks/_git/SchoolBucks/pullrequest/48180 | U5: 46113 | V5: Ken | W5: 46120 | X5: No Comments | Y5: NA | Z5: NA | AA5: NA | AB5: NA | AC5: NA | AD5: Testing took longer because there were more scenarios to cover, and each sync run requires time to complete. Time Enrties : Prisla: 8hrs Nithish: 5hrs
A6: 5 | B6: =Dashboard!$J$1 -> MSB Dev | C6: 46115 | D6: 46128 | E6: 26.5 DS Sprint 1 | F6: Aravindh | G6: 52251 | H6: MSB - Dev Portal - Add UserHub API page | I6: Story Completed | J6: 5 | K6: =Table14567891011121331415171816201921222324252627282930313233343536[[#This Row],[Actual Hours Worklog]] / 4 -> 7.25 | L6: 29 | M6: 46115 | N6: 46120 | O6: Manual (TestCases-5) | P6: Mahesh | Q6: None | R6: Mahesh | S6: No Comments | T6: https://dev.azure.com/heartlandschools/MySchoolBucks/_git/SchoolBucks/pullrequest/48361 | U6: 46122 | V6: Prisla | W6: 46122 | X6: No Comments | Y6: Alex | Z6: 46125 | AA6: No Comments | AB6: No Comments | AC6: No Comments | AD6: Comment: We upgraded the Java version from 17 to 21. Due to this change, we are facing issues in the local environment. This has increased the time required for development and testing. Time Entries: Aravindh : 21hrs Prisla : 3hrs Nithish : 5hrs
A7: 6 | B7: =Dashboard!$J$1 -> MSB Dev | C7: 46115 | D7: 46128 | E7: 26.5 DS Sprint 1 | F7: Aravindh | G7: 52054 | H7: MSB - Manage Integrations - Add new customer self service page - View REST API integrations | I7: Story Completed | J7: 3 | K7: =Table14567891011121331415171816201921222324252627282930313233343536[[#This Row],[Actual Hours Worklog]] / 4 -> 6.75 | L7: 27 | M7: 46126 | N7: 46121 | O7: Manual (TestCases-5) | P7: Mahesh | Q7: None | R7: Mahesh | S7: No Comments | T7: https://dev.azure.com/heartlandschools/MySchoolBucks/_git/SchoolBucks/pullrequest/48358 https://dev.azure.com/heartlandschools/MySchoolBucks/_git/SchoolBucks/pullrequest/48402 | U7: 46122 | V7: Prisla | W7: 46122 | X7: No Comments | Y7: Alex | Z7: 46125 | AA7: No Comments | AB7: No Comments | AC7: No Comments | AD7: Comment: We upgraded the Java version from 17 to 21. Due to this change, we are facing issues in the local environment. This has increased the time required for development and testing. Time Entries: Aravindh : 18hrs Prisla : 7hrs Nithish : 2hrs
A8: 7 | B8: =Dashboard!$J$1 -> MSB Dev | C8: 46115 | D8: 46128 | E8: 26.5 DS Sprint 1 | F8: Aravindh | G8: 26980 | H8: Datahub - Integration API - Post/PUT fee does not allow $0 fee amount (Tracks) | I8: Defect Fixed | J8: 2 | K8: =Table14567891011121331415171816201921222324252627282930313233343536[[#This Row],[Actual Hours Worklog]] / 4 -> 4.5 | L8: 18 | M8: 46126 | N8: 46127 | O8: Manual (TestCases-35) | P8: Mahesh | Q8: None | R8: Mahesh | S8: No Comments | T8: https://dev.azure.com/heartlandschools/MySchoolBucks/_git/SchoolBucks/pullrequest/48421 | U8: 46127 | V8: Prisla | W8: 46127 | X8: No Comments | Y8: Ken | Z8: 46127 | AA8: No Comments | AB8: The team asked: If we already have a FeeAmount value and the OriginalFeeAmount is 0 or null, why do we need to update the OriginalFeeAmount to 0 or null? when update fee call | AC8: The client’s suggested fee amount is greater than the original fee amount, so we should set the original fee amount to the fee amount. | AD8: Comment: 1. Aravindh has completed his implementation for the committed stories and is currently running out of work, so this committed defect was assigned to him on Apr-14. 2. The acceptance criteria for this defect were not clear, and we had a couple of doubts during the analysis. We requested clarification from the client, and after the acceptance criteria were updated, we started working on it. Time Entries: Aravindh : 12hrs Prisla : 4hrs Nithish : 2hrs
A9: 8 | B9: =Dashboard!$J$1 -> MSB Dev | C9: 46115 | D9: 46128 | E9: 26.5 DS Sprint 1 Stretch | F9: Mahesh | G9: 52426 | H9: MSB - Developer Portal - Update Developer Account ID generation | I9: Story Completed | J9: 2 | K9: =Table14567891011121331415171816201921222324252627282930313233343536[[#This Row],[Actual Hours Worklog]] / 4 -> 4 | L9: 16 | M9: 46121 | N9: 46122 | O9: Manual (TestCases-5) | P9: Prisla | Q9: None | R9: Prisla | S9: No Comments | T9: https://dev.azure.com/heartlandschools/MySchoolBucks/_git/SchoolBucks/pullrequest/48347 | U9: 46122 | V9: Prisla | W9: 46122 | X9: No Comments | Y9: Alex | Z9: 46125 | AA9: No Comments | AB9: No Comments | AC9: No Comments | AD9: The application was upgraded the Java and JBoss versions, which impacted the local environment. Fixing the local environment took additional time, and this was the reason for the delay in implementing the story Time Enrties : Mahesh: 12hrs Prisla: 2hrs Nithish: 2hrs
A10: 9 | B10: =Dashboard!$J$1 -> MSB Dev | C10: 46115 | D10: 46128 | E10: 26.5 DS Sprint 1 Stretch | F10: Mahesh | G10: 52444 | H10: DataHub - API - deprecate HSSConnect API v1 | I10: Story Ready For Testing | J10: 3 | K10: =Table14567891011121331415171816201921222324252627282930313233343536[[#This Row],[Actual Hours Worklog]] / 4 -> 0 | M10: 46125 | N10: 46127 | O10: Manual (TestCases-30) | P10: Aravindh | Q10: None | R10: Aravindh | S10: No Comments | T10: https://dev.azure.com/heartlandschools/MySchoolBucks/_git/SchoolBucks/pullrequest/48419 | U10: 46127 | V10: Prisla | W10: 46127 | X10: No Comments | Y10: Ken | Z10: 46127 | AA10: No Comments | AB10: NA | AC10: NA
A11: 10 | B11: =Dashboard!$J$1 -> MSB Dev | C11: 46115 | D11: 46128 | E11: 26.5 DS Sprint 1 Stretch | F11: Mahesh | G11: 52063 | H11: MobilePay - API - Shifts - Add Credit card subtotals to Close Out (Clark Cty) | I11: Story Being Developed | J11: 3 | K11: =Table14567891011121331415171816201921222324252627282930313233343536[[#This Row],[Actual Hours Worklog]] / 4 -> 0 | M11: 46128
A12: 11 | B12: =Dashboard!$J$1 -> MSB Dev | C12: 46115 | D12: 46128 | E12: 26.5 DS Sprint 1 Stretch | F12: Aravindh | G12: 52831 | H12: MSB – DataHub – Export Classes and Terms to XLSX | I12: Story Being Developed | J12: 5 | K12: =Table14567891011121331415171816201921222324252627282930313233343536[[#This Row],[Actual Hours Worklog]] / 4 -> 0 | M12: 46128

Sheet 26.5 DS Sprint 1-Defect
A1: S.No | B1: Sprint # | C1: Story/Defect ID | D1: Parent Story | E1: Developer | F1: Issue Type | G1: Issue Description | H1: Priority | I1: Defect Source | J1: Type | K1: Status | L1: Root Cause Category | M1: Comments
B2: 26.5 DS Sprint 1 | C2: 27100 | E2: Prisla | F2: Defect | G2: DH - HSS Connect - Include/Exclude filter school not respecting properly after running full sync without any filter | I2: Manual | J2: Internal | K2: Closed | L2: Existing_Issues | M2: Existing issue DH - include/exclude filter school not respecting properly for adapter type HSS Connect
B3: 26.5 DS Sprint 1 | C3: 26980 | E3: Aravindh | F3: Defect | G3: 26980Datahub - Integration API - Post/PUT fee does not allow $0 fee amount (Tracks) | I3: Manual | J3: Internal | K3: Closed | L3: Existing_Issues | M3: Tracks team want to allow $0 fee amount when POST replace existing param as true & PUTfFee
B4: 26.5 DS Sprint 1 | C4: 52054 | E4: Aravindh | F4: Bounceback | G4: In the MSB Dev Portal – Getting Started, a new Integration Type named “MySchoolBucks API,Single Sign-on” is displayed, which is not part of the story requirements. It has been removed | I4: Manual | J4: Internal | K4: Closed | L4: Development | M4: Missed in development
B5: 26.5 DS Sprint 1 | C5: 52054 | E5: Aravindh | F5: Bounceback | G5: If the developer account has both MSB Checkout and REST API, it currently shows “MySchoolBucks, MSB Checkout”. Instead, it should display “MSB Checkout, MySchoolBucks API | I5: Manual | J5: Internal | K5: Closed | L5: Development | M5: Missed in development

Sheet 26.4 DS Sprint 3-Status
A1: S.No | B1: Application Name | C1: Sprint Start Date | D1: Sprint End Date | E1: Sprint | F1: Developer | G1: Story ID/Defect ID | H1: Description | I1: Status | J1: Estimated(hrs/sp) | K1: Actual(hrs/sp) | L1: Actual Hours Worklog | M1: Dev start date | N1: Dev end date | O1: Unit testing | P1: Peer Tested By | Q1: Peer Tested Defects, if any | R1: Peer Reviewed By | S1: Peer Code Review Comments, if any | T1: PR Number/Link | U1: PR Created Date | V1: Reviewer 1 | W1: PR Approved Date | X1: Code Review Comments, if any | Y1: Reviewer 2 | Z1: Approved Date | AA1: Code Review Comments, if any2 | AB1: Internal PO -POV Comments | AC1: Client PO -POV Comments | AD1: Comments
A2: 1 | B2: =Dashboard!$J$1 -> MSB Dev | C2: 46101 | D2: 46114 | E2: 26.4 DS Sprint 3 | F2: Mahesh | G2: 52364 | H2: MSB - REST API - POST/PUT Invoice - Allow create/update for inactive students (MSB Activities)-Automation (26.4) | I2: Story Completed | J2: 2 | K2: =Table145678910111213314151718162019212223242526272829303132333435[[#This Row],[Actual Hours Worklog]] / 4 -> 1.5 | L2: 6 | M2: 46104 | N2: 46105 | O2: NA | P2: Aravindh | Q2: None | R2: Aravindh | S2: No Comments | T2: https://dev.azure.com/heartlandschools/MySchoolBucks/_git/MSBAutomation/pullrequest/47954 | U2: 46104 | V2: Alex | W2: 46105 | X2: No Comments | Y2: NA | Z2: NA | AA2: NA | AB2: NA | AC2: NA | AD2: Time Enrties : Mahesh: 6hrs
A3: 2 | B3: =Dashboard!$J$1 -> MSB Dev | C3: 46101 | D3: 46114 | E3: 26.4 DS Sprint 3 | F3: Mahesh | G3: 52384 | H3: MSB - Manage Integrations - Fee integrations - Respect School filters in data summary | I3: Story Completed | J3: 3 | K3: =Table145678910111213314151718162019212223242526272829303132333435[[#This Row],[Actual Hours Worklog]] / 4 -> 3 | L3: 12 | M3: 46101 | N3: 46101 | O3: Manual (TestCases-10) | P3: Aravindh | Q3: None | R3: Aravindh | S3: No Comments | T3: https://dev.azure.com/heartlandschools/MySchoolBucks/_git/SchoolBucks/pullrequest/47929 | U3: 46101 | V3: George | W3: 46101 | X3: No Comments | Y3: Alex | Z3: 46101 | AA3: No Comments | AB3: No Comments | AC3: No Comments | AD3: Time Enrties : Mahesh: 6hrs Nithish: 6hrs
A4: 3 | B4: =Dashboard!$J$1 -> MSB Dev | C4: 46101 | D4: 46114 | E4: 26.4 DS Sprint 3 | F4: Aravindh | G4: 52369 | H4: Datahub - Developer Account Cleanup - Automation (26.4) | I4: Story Completed | J4: 2 | K4: =Table145678910111213314151718162019212223242526272829303132333435[[#This Row],[Actual Hours Worklog]] / 4 -> 1.5 | L4: 6 | M4: 46099 | N4: 46099 | O4: NA | P4: Mahesh | Q4: No Comments | R4: Mahesh | S4: No Comments | T4: https://dev.azure.com/heartlandschools/MySchoolBucks/_git/MSBAutomation/pullrequest/47847 | U4: 46098 | V4: Alex | W4: 46105 | X4: No Comments | Y4: NA | Z4: NA | AA4: NA | AB4: NA | AC4: NA | AD4: Time Enrties : Aravindh: 6hrs
A5: 4 | B5: =Dashboard!$J$1 -> MSB Dev | C5: 46101 | D5: 46114 | E5: 26.4 DS Sprint 3 | F5: Aravindh | G5: 52362 | H5: MSB - Developer Portal - Add content for District SSO - Automation [26.4] | I5: Story Completed | J5: 1 | K5: =Table145678910111213314151718162019212223242526272829303132333435[[#This Row],[Actual Hours Worklog]] / 4 -> 1.5 | L5: 6 | M5: 46098 | N5: 46099 | O5: NA | P5: Mahesh | Q5: No Comments | R5: Mahesh | S5: No Comments | T5: https://dev.azure.com/heartlandschools/MySchoolBucks/_git/MSBAutomation/pullrequest/47982 | U5: 46105 | V5: Alex | W5: 46106 | X5: No Comments | Y5: NA | Z5: NA | AA5: NA | AB5: NA | AC5: NA | AD5: Comments : Due to local environment issue. we are unable to run automations. so it took time for testing. Time Entries : Aravindh : 6hrs
A6: 5 | B6: =Dashboard!$J$1 -> MSB Dev | C6: 46101 | D6: 46114 | E6: 26.4 DS Sprint 3 | F6: Mahesh | G6: 52421 | H6: MSB - Partner Integrations - New Automation [26.4] | I6: Story Completed | J6: 13 | K6: =Table145678910111213314151718162019212223242526272829303132333435[[#This Row],[Actual Hours Worklog]] / 4 -> 22.5 | L6: 90 | M6: 46105 | N6: 46114 | O6: NA | P6: Aravindh | Q6: None | R6: Aravindh | S6: No Comments | T6: https://dev.azure.com/heartlandschools/MySchoolBucks/_git/MSBAutomation/pullrequest/47365 https://dev.azure.com/heartlandschools/MySchoolBucks/_git/MSBAutomation/pullrequest/48044 https://dev.azure.com/heartlandschools/MySchoolBucks/_git/MSBAutomation/pullrequest/48137 https://dev.azure.com/heartlandschools/MySchoolBucks/_git/MSBAutomation/pullrequest/48043 https://dev.azure.com/heartlandschools/MySchoolBucks/_git/MSBAutomation/pullrequest/47373 https://dev.azure.com/heartlandschools/MySchoolBucks/_git/MSBAutomation/pullrequest/47954 https://dev.azure.com/heartlandschools/MySchoolBucks/_git/MSBAutomation/pullrequest/48161 | U6: 46107 | V6: Alex | W6: 46107 | X6: No Comments | Y6: NA | Z6: NA | AA6: NA | AB6: NA | AC6: NA | AD6: Comments : The story was created as a common task to implement automation for this release stories. We have covered almost all of them. Time Entries : Prisla : 6hrs Mahesh : 42hrs Aravindh : 42hrs
A7: 6 | B7: =Dashboard!$J$1 -> MSB Dev | C7: 46101 | D7: 46114 | E7: 26.4 DS Sprint 3 | F7: Nithish | G7: 52424 | H7: MSB - Partner Integrations - Regression [26.4] | I7: Story Completed | J7: 13 | K7: =Table145678910111213314151718162019212223242526272829303132333435[[#This Row],[Actual Hours Worklog]] / 4 -> 10.75 | L7: 43 | M7: NA | N7: NA | O7: NA | P7: NA | Q7: NA | R7: NA | S7: NA | T7: NA | U7: NA | V7: NA | W7: NA | X7: NA | Y7: NA | Z7: NA | AA7: NA | AB7: NA | AC7: NA | AD7: Comments : Added only for testing purpose Time Entries : Nithish : 43hrs
A8: 7 | B8: =Dashboard!$J$1 -> MSB Dev | C8: 46101 | D8: 46114 | E8: 26.4 DS Sprint 3 Stretch | F8: Aravindh | G8: 27046 | H8: MSB - Dev Portal - Cannot submit developer account request for Student Fee integration | I8: Defect Fixed | J8: 2 | K8: =Table145678910111213314151718162019212223242526272829303132333435[[#This Row],[Actual Hours Worklog]] / 4 -> 2.75 | L8: 11 | M8: 46106 | N8: 46106 | O8: Manual (TestCases-10) | P8: Mahesh | Q8: No Comments | R8: Mahesh | S8: No Comments | T8: https://dev.azure.com/heartlandschools/MySchoolBucks/_git/SchoolBucks/pullrequest/48012 | U8: 46105 | V8: Alex | W8: 46106 | X8: No Comments | Y8: NA | Z8: NA | AA8: NA | AB8: No Comments | AC8: No Comments | AD8: Comments : Testing this defect took significant time because it required covering many test scenarios. Time Entries : Aravindh : 6hrs Nithish : 5hrs

Sheet 26.4 DS Sprint 3-Defect
A1: S.No | B1: Sprint # | C1: Story/Defect ID | D1: Parent Story | E1: Developer | F1: Issue Type | G1: Issue Description | H1: Priority | I1: Defect Source | J1: Type | K1: Status | L1: Root Cause Category | M1: Comments
B2: 26.4 DS Sprint 3 Stretch | C2: 27046 | E2: Aravindh | F2: Defect | G2: MSB - Dev Portal - Cannot submit developer account request for Student Fee integration | H2: Significant | I2: Manual | J2: External | K2: Closed | L2: Existing_Issues | M2: In the Developer Portal ‘Getting Started - Request Developer Account’ page, the Submit button is not working when selecting ‘Student Fee’ as the Integration Type

Sheet 26.4 DS Sprint 2-Status
A1: S.No | B1: Application Name | C1: Sprint Start Date | D1: Sprint End Date | E1: Sprint | F1: Developer | G1: Story ID/Defect ID | H1: Description | I1: Status | J1: Estimated(hrs/sp) | K1: Actual(hrs/sp) | L1: Actual Hours Worklog | M1: Dev start date | N1: Dev end date | O1: Unit testing | P1: Peer Tested By | Q1: Peer Tested Defects, if any | R1: Peer Reviewed By | S1: Peer Code Review Comments, if any | T1: PR Number/Link | U1: PR Created Date | V1: Reviewer 1 | W1: PR Approved Date | X1: Code Review Comments, if any | Y1: Reviewer 2 | Z1: Approved Date | AA1: Code Review Comments, if any2 | AB1: Internal PO -POV Comments | AC1: Client PO -POV Comments | AD1: Comments
A2: 1 | B2: =Dashboard!$J$1 -> MSB Dev | C2: 46087 | D2: 46100 | E2: 26.4 DS Sprint 2 | F2: Prisla | G2: 52208 | H2: MSB - Developer Portal - Updates to Financial Data pages | I2: Story Completed | J2: 1 | K2: =Table1456789101112133141517181620192122232425262728293031323334[[#This Row],[Actual Hours Worklog]] / 4 -> 1.25 | L2: 5 | M2: 46087 | N2: 46087 | O2: Manual (TestCases-5) | P2: Aravindh | Q2: None | R2: Aravindh | S2: No Comments | T2: https://dev.azure.com/heartlandschools/MySchoolBucks/_git/SchoolBucks/pullrequest/47635 | U2: 46087 | V2: Ken | W2: 46087 | X2: No Comments | Y2: NA | Z2: NA | AA2: NA | AB2: No Comments | AC2: No Comments | AD2: Time Enrties : Prisla: 3hrs Nithish: 2hrs
A3: 2 | B3: =Dashboard!$J$1 -> MSB Dev | C3: 46087 | D3: 46100 | E3: 26.4 DS Sprint 2 | F3: Prisla | G3: 26835 | H3: MSB - REST API - Update swagger for GET payments paymentType param | I3: Defect Fixed | J3: 1 | K3: =Table1456789101112133141517181620192122232425262728293031323334[[#This Row],[Actual Hours Worklog]] / 4 -> 1.25 | L3: 5 | M3: 46087 | N3: 46087 | O3: Manual (TestCases-3) | P3: Aravindh | Q3: None | R3: Aravindh | S3: No Comments | T3: https://dev.azure.com/heartlandschools/MySchoolBucks/_git/SchoolBucks/pullrequest/47637 | U3: 46087 | V3: Alex | W3: 46087 | X3: No Comments | Y3: NA | Z3: NA | AA3: NA | AB3: NA | AC3: NA | AD3: Time Enrties : Prisla: 2hrs Nithish: 3hrs
A4: 3 | B4: =Dashboard!$J$1 -> MSB Dev | C4: 46087 | D4: 46100 | E4: 26.4 DS Sprint 2 | F4: Prisla | G4: 24954 | H4: MSB - UH - Users Module Export Not Working When Entering Username in Search | I4: Defect Fixed | J4: 3 | K4: =Table1456789101112133141517181620192122232425262728293031323334[[#This Row],[Actual Hours Worklog]] / 4 -> 3.25 | L4: 13 | M4: 46090 | N4: 46091 | O4: Manual (TestCases-5) | P4: Mahesh | Q4: None | R4: Aravindh | S4: No Comments | T4: https://dev.azure.com/heartlandschools/MySchoolBucks/_git/SchoolBucks/pullrequest/47722 | U4: 46091 | V4: Ken | W4: 46092 | X4: No Comments | Y4: NA | Z4: NA | AA4: NA | AB4: NA | AC4: NA | AD4: Time Enrties : Prisla: 10hrs Nithish: 3hrs
A5: 4 | B5: =Dashboard!$J$1 -> MSB Dev | C5: 46087 | D5: 46100 | E5: 26.4 DS Sprint 2 | F5: Prisla | G5: 26912 | H5: Datahub - School Filters - Remaining issues for Synergy, Aspen OR, Skyward OR and File Import | I5: Defect Fixed | J5: 5 | K5: =Table1456789101112133141517181620192122232425262728293031323334[[#This Row],[Actual Hours Worklog]] / 4 -> 6.75 | L5: 27 | M5: 46091 | N5: 46093 | O5: Manual (TestCases-10) | P5: Aravindh | Q5: None | R5: Aravindh | S5: No Comments | T5: https://dev.azure.com/heartlandschools/MySchoolBucks/_git/SchoolBucks/pullrequest/47768 | U5: 46093 | V5: Alex | W5: 46093 | X5: No Comments | Y5: NA | Z5: NA | AA5: NA | AB5: NA | AC5: NA | AD5: Comments: There are multiple providers and additional scenarios to cover. Since each sync run takes time, the overall effort required to cover all scenarios for testing was significant.. Time Enrties : Prisla: 13hrs Mahesh: 3hrs Nithish: 11hrs
A6: 5 | B6: =Dashboard!$J$1 -> MSB Dev | C6: 46087 | D6: 46100 | E6: 26.4 DS Sprint 2 | F6: Mahesh | G6: 52144 | H6: MSB - Manage Integrations - Show accurate Integration type for DH payment integrations | I6: Story Completed | J6: 3 | K6: =Table1456789101112133141517181620192122232425262728293031323334[[#This Row],[Actual Hours Worklog]] / 4 -> 4.75 | L6: 19 | M6: 46087 | N6: 46090 | O6: Manual (TestCases-10) | P6: Prisla | Q6: None | R6: Prisla | S6: No Comments | T6: https://dev.azure.com/heartlandschools/MySchoolBucks/_git/SchoolBucks/pullrequest/47665 | U6: 46090 | V6: Prisla | W6: 46090 | X6: No Comments | Y6: Ken | Z6: 46090 | AA6: No Comments | AB6: No Comments | AC6: No Comments | AD6: Comments: Time was taken for dev testing to cover all scenarios. Time Enrties : Mahesh: 11hrs Prisla: 2hrs Nithish: 6hrs
A7: 6 | B7: =Dashboard!$J$1 -> MSB Dev | C7: 46087 | D7: 46100 | E7: 26.4 DS Sprint 2 | F7: Mahesh | G7: 52037 | H7: MSB - Manage Integrations - Show Single Sign On integrations | I7: Story Completed | J7: 5 | K7: =Table1456789101112133141517181620192122232425262728293031323334[[#This Row],[Actual Hours Worklog]] / 4 -> 6.5 | L7: 26 | M7: 46091 | N7: 46094 | O7: Manual (TestCases-20) | P7: Aravindh | Q7: None | R7: Aravindh | S7: No Comments | T7: https://dev.azure.com/heartlandschools/MySchoolBucks/_git/SchoolBucks/pullrequest/47799 | U7: 46094 | V7: Prisla | W7: 46094 | X7: No Comments | Y7: Alex | Z7: 46094 | AA7: No Comments | AB7: No Comments | AC7: No Comments | AD7: Comments: In offshore, no one has an SSO setup or SSO users. Therefore, it took time to analyze the code, insert the required data directly into the database, and then implement and perform development testing.. Time Enrties : Mahesh: 20hrs Prisla: 3hrs Nithish: 3hrs
A8: 7 | B8: =Dashboard!$J$1 -> MSB Dev | C8: 46087 | D8: 46100 | E8: 26.4 DS Sprint 2 | F8: Aravindh | G8: 51185 | H8: MSB - Manage Integrations - Add Data summary View - Fees | I8: Story Completed | J8: 2 | K8: =Table1456789101112133141517181620192122232425262728293031323334[[#This Row],[Actual Hours Worklog]] / 4 -> 5 | L8: 20 | M8: 46080 | N8: 46090 | O8: Manual (TestCases-10) | P8: Mahesh | Q8: 1. Total Paid Fees: <count>(Paid Fees have a payment in DH and remaining amount =0) Even partially paid fees, meaning payments that are not completed in full, are also included in the count. | R8: Mahesh | S8: No Comments | T8: https://dev.azure.com/heartlandschools/MySchoolBucks/_git/SchoolBucks/pullrequest/47622 | U8: 46086 | V8: Prisla | W8: 46094 | X8: No Comments | Y8: Alex | Z8: 46095 | AA8: No Comments | AB8: No Comments | AC8: No Comments | AD8: Comments : During the last sprint, the development was completed, but in the current sprint an issue was raised during peer testing. We then realized there was a misunderstanding of the AC. While fixing the issue, we faced a couple of challenges in showing the paid fees. We discussed this with the client, who suggested that the simpler approach would be to show the payment count instead of the paid fee. Time Enrties : Aravindh : 6hrs Prisla : 6hrs Nithish : 8hrs
A9: 8 | B9: =Dashboard!$J$1 -> MSB Dev | C9: 46087 | D9: 46100 | E9: 26.4 DS Sprint 2 | F9: Aravindh | G9: 52121 | H9: Datahub - Developer Account Cleanup | I9: Story Completed | J9: 2 | K9: =Table1456789101112133141517181620192122232425262728293031323334[[#This Row],[Actual Hours Worklog]] / 4 -> 2.25 | L9: 9 | M9: 46087 | N9: 46087 | O9: Manual (TestCases-10) | P9: Mahesh | Q9: None | R9: Mahesh | S9: No Comments | T9: https://dev.azure.com/heartlandschools/MySchoolBucks/_git/SchoolBucks/pullrequest/47710 | U9: 46091 | V9: Prisla | W9: 46091 | X9: No Comments | Y9: Ken | Z9: 46092 | AA9: No Comments | AB9: No Comments | AC9: Suggestion : Need to show inactive text format (Not In AC. after POV client updated AC Point.) | AD9: Comments : From the client’s POV, they provided some suggestions, and we addressed those suggestions accordingly. As a result, it took a little extra time to complete. Time Enrties : Aravindh : 6hrs Prisla : 1hrs Nithish : 2hrs
A10: 9 | B10: =Dashboard!$J$1 -> MSB Dev | C10: 46087 | D10: 46100 | E10: 26.4 DS Sprint 2 | F10: Aravindh | G10: 48868 | H10: MSB - Developer Portal - Add content for District SSO | I10: Story Completed | J10: 5 | K10: =Table1456789101112133141517181620192122232425262728293031323334[[#This Row],[Actual Hours Worklog]] / 4 -> 5.25 | L10: 21 | M10: 46090 | N10: 46091 | O10: Manual (TestCases-10) | P10: Mahesh | Q10: None | R10: Mahesh | S10: No Comments | T10: https://dev.azure.com/heartlandschools/MySchoolBucks/_git/SchoolBucks/pullrequest/47709 | U10: 46091 | V10: Prisla | W10: 46091 | X10: No Comments | Y10: Ken | Z10: 46092 | AA10: No Comments | AB10: No Comments | AC10: While POV Client suggestion the UI alignment design | AD10: Comments : From the client’s POV, they provided some suggestions, and we addressed those suggestions accordingly. As a result, it took a little extra time to complete. Time Enrties : Aravindh : 18hrs Prisla : 1hrs Nithish : 2hrs
A11: 10 | B11: =Dashboard!$J$1 -> MSB Dev | C11: 46087 | D11: 46100 | E11: 26.4 DS Sprint 2 Stretch | F11: Mahesh | G11: 51962 | H11: MSB – Manage Integrations – Respect Client ID Override & Provider ID Override | I11: Story Completed | J11: 3 | K11: =Table1456789101112133141517181620192122232425262728293031323334[[#This Row],[Actual Hours Worklog]] / 4 -> 4.25 | L11: 17 | M11: 46097 | N11: 46097 | O11: Manual (TestCases-10) | P11: Aravindh | Q11: None | R11: Aravindh | S11: No Comments | T11: https://dev.azure.com/heartlandschools/MySchoolBucks/_git/SchoolBucks/pullrequest/47821 | U11: 46097 | V11: Prisla | W11: 46105 | X11: No Comments | Y11: Alex | Z11: 46098 | AA11: No Comments | AB11: No Comments | AC11: No Comments | AD11: Comments: Time was taken for testing to cover all scenarios. Time Enrties : Mahesh: 6hrs Prisla: 4hrs Nithish: 7hrs
A12: 11 | B12: =Dashboard!$J$1 -> MSB Dev | C12: 46087 | D12: 46100 | E12: 26.4 DS Sprint 2 Stretch | F12: Mahesh | G12: 52364 | H12: MSB - REST API - POST/PUT Invoice - Allow create/update for inactive students (MSB Activities)-Automation (26.4) | I12: Story Being Developed | J12: 2 | K12: =Table1456789101112133141517181620192122232425262728293031323334[[#This Row],[Actual Hours Worklog]] / 4 -> 0 | M12: 46099 | O12: NA | AB12: NA | AC12: NA
A13: 12 | B13: =Dashboard!$J$1 -> MSB Dev | C13: 46087 | D13: 46100 | E13: 26.4 DS Sprint 2 Stretch | F13: Aravindh | G13: 52362 | H13: MSB - Developer Portal - Add content for District SSO- Automation [26.4] | I13: Story Being Developed | J13: 2 | K13: =Table1456789101112133141517181620192122232425262728293031323334[[#This Row],[Actual Hours Worklog]] / 4 -> 5.75 | L13: 23 | M13: 46094 | N13: 46097 | O13: NA | AB13: NA | AC13: NA | AD13: Comments: We completed the code implementation. but we’re currently unable to run the automations in our local environment. Therefore, this item will be carried forward to peer testing. Time entries : Aravindh : 18hrs Prisla : 5hrs
A14: 13 | B14: =Dashboard!$J$1 -> MSB Dev | C14: 46087 | D14: 46100 | E14: 26.4 DS Sprint 2 Stretch | F14: Aravindh | G14: 52369 | H14: Datahub - Developer Account Cleanup- Automation (26.4) | I14: Story Being Developed | J14: 2 | K14: =Table1456789101112133141517181620192122232425262728293031323334[[#This Row],[Actual Hours Worklog]] / 4 -> 3.75 | L14: 15 | M14: 46098 | N14: 46098 | O14: NA | T14: https://dev.azure.com/heartlandschools/MySchoolBucks/_git/MSBAutomation/pullrequest/47847 | U14: 46098 | AB14: NA | AC14: NA | AD14: Comments: We completed the code implementation, but we’re currently unable to run the automations in our local environment. Therefore, this item will be carried forward to peer testing. Time entries : Aravindh : 12hrs Prisla : 3hrs

Sheet 26.4 DS Sprint 2-Defect
A1: S.No | B1: Sprint # | C1: Story/Defect ID | D1: Parent Story | E1: Developer | F1: Issue Type | G1: Issue Description | H1: Priority | I1: Defect Source | J1: Type | K1: Status | L1: Root Cause Category | M1: Comments
B2: 26.4 DS Sprint 2 | C2: 24954 | E2: Prisla | F2: Defect | G2: MSB - UH - Users Module Export Not Working When Entering Username in Search | H2: Minor | I2: Manual | J2: Internal | K2: Closed | L2: Existing_Issues | M2: Existing issue not able to export when using username in search filter
B3: 26.4 DS Sprint 2 | C3: 26835 | E3: Prisla | F3: Defect | G3: MSB - REST API - Update swagger for GET payments paymentType param | H3: Minor | I3: Manual | J3: External | K3: Closed | L3: Existing_Issues | M3: Existing issue to change payment type param textbox input to allow multiple values
B4: 26.4 DS Sprint 2 | C4: 26912 | E4: Prisla | F4: Defect | G4: Datahub - School Filters - Remaining issues for Synergy, Aspen OR, Skyward OR and File Import | H4: Minor | I4: Manual | J4: Internal | K4: Closed | L4: Existing_Issues | M4: Based on story :51205 bouncebacks were consolidated and created a new defect:26912 due to the issue occurs only in the test environment and there is delayed to getting server logs from client
B5: 26.4 DS Sprint 2 | C5: 48868 | E5: Aravindh | F5: Bounceback | G5: Without logging in, the District SSO page document does not open | H5: Minor | I5: Manual | J5: Internal | K5: Closed | L5: Development | M5: Missed in development

Sheet 26.4 DS Sprint 1-Status
A1: S.No | B1: Application Name | C1: Sprint Start Date | D1: Sprint End Date | E1: Sprint | F1: Developer | G1: Story ID/Defect ID | H1: Description | I1: Status | J1: Estimated(hrs/sp) | K1: Actual(hrs/sp) | L1: Actual Hours Worklog | M1: Dev start date | N1: Dev end date | O1: Unit testing | P1: Peer Tested By | Q1: Peer Tested Defects, if any | R1: Peer Reviewed By | S1: Peer Code Review Comments, if any | T1: PR Number/Link | U1: PR Created Date | V1: Reviewer 1 | W1: PR Approved Date | X1: Code Review Comments, if any | Y1: Reviewer 2 | Z1: Approved Date | AA1: Code Review Comments, if any2 | AB1: Internal PO -POV Comments | AC1: Client PO -POV Comments | AD1: Comments
A2: 1 | B2: =Dashboard!$J$1 -> MSB Dev | C2: 46073 | D2: 46086 | E2: 26.4 DS Sprint 1 | F2: Prisla | G2: 51205 | H2: [WAVE] Datahub - Providers - Support School filters | I2: Story Completed | J2: 5 | K2: =Table14567891011121331415171816201921222324252627282930313233[[#This Row],[Actual Hours Worklog]] / 4 -> 12.875 | L2: 51.5 | M2: 46031 | N2: 46036 | O2: Manual (TestCases-80) | P2: Aravindh | Q2: None | R2: Aravindh | S2: No Comments | T2: https://dev.azure.com/heartlandschools/MySchoolBucks/_git/SchoolBucks/pullrequest/46663 https://dev.azure.com/heartlandschools/MySchoolBucks/_git/SchoolBucks/pullrequest/47307 https://dev.azure.com/heartlandschools/MySchoolBucks/_git/SchoolBucks/pullrequest/47584 https://dev.azure.com/heartlandschools/MySchoolBucks/_git/SchoolBucks/pullrequest/47590 | U2: 46037 | V2: Prisla | W2: 46059 | X2: No Comments | Y2: George | Z2: 46078 | AA2: 1. Need to add validation for null check 2. We should give precedence for excludeschoolNumber 3. Remove unwanted import 4. For avoiding the multiple loadschoolNumber call. we should handle in generatePostParamsRequest() 5. Remove schoolNumberNotInIncludeList unwanted code | AB2: No Comments | AC2: No Comments | AD2: Comments : 26.3 DS Sprint 1: The stretch story was picked up by Prisla. hence, this is a Wave team story, and development was completed. 26.3 DS Sprint 2: The story was assigned to Aravindh for dev-testing and to fix any issues found during testing, but the work was not completed, Because of found some issues, so the story was carried forward to the next sprint. 26.3 DS Sprint 3: The story has been moved to the next release (26.4), which is why the code has not yet been merged and this is kept it on hold for this sprint. 26.4 DS Sprint 1: The client reassigned the task to Prisla, but most comments weren’t related to the current story changes—they were about existing code that needed fixes. The issue occurs only in the test environment. To analyze it, we requested server logs, but no one—including the client’s development manager—has access to them. Only high-level access is available. Since the client also requested the logs, there has been a delay in obtaining them from the test environment. Therefore, all Bouncebacks were consolidated, a defect (26912) was created, and this story was closed. Time Entries : Prisla - 24hrs Mahesh - 6hrs Nithish - 21.5hrs
A3: 2 | B3: =Dashboard!$J$1 -> MSB Dev | C3: 46073 | D3: 46086 | E3: 26.4 DS Sprint 1 | F3: Prisla | G3: 51977 | H3: MSB – Manage Integrations – Display & View MSB Provider from Integration List | I3: Story Completed | J3: 2 | K3: =Table14567891011121331415171816201921222324252627282930313233[[#This Row],[Actual Hours Worklog]] / 4 -> 3 | L3: 12 | M3: 46078 | N3: 46078 | O3: Manual (TestCases-10) | P3: Aravindh | Q3: None | R3: Aravindh | S3: No Comments | T3: https://dev.azure.com/heartlandschools/MySchoolBucks/_git/SchoolBucks/pullrequest/47501 | U3: 46078 | V3: Alex | W3: 46079 | X3: No Comments | Y3: George | Z3: 46079 | AA3: No Comments | AB3: No Comments | AC3: No Comments | AD3: Time Entries : Prisla - 10hrs Matthew - 2hrs
A4: 3 | B4: =Dashboard!$J$1 -> MSB Dev | C4: 46073 | D4: 46086 | E4: 26.4 DS Sprint 1 | F4: Prisla | G4: 26796 | H4: MSB - Partner - Manage Integration page does not display providers when MSB and DH provider id differ only by case sensitivity | I4: Defect Fixed | J4: 2 | K4: =Table14567891011121331415171816201921222324252627282930313233[[#This Row],[Actual Hours Worklog]] / 4 -> 2 | L4: 8 | M4: 46073 | N4: 46073 | O4: Manual (TestCases-10) | P4: Aravindh | Q4: None | R4: Aravindh | S4: No Comments | T4: https://dev.azure.com/heartlandschools/MySchoolBucks/_git/SchoolBucks/pullrequest/47384 | U4: 46073 | V4: Alex | W4: 46073 | X4: No Comments | Y4: NA | Z4: NA | AA4: NA | AB4: NA | AC4: NA | AD4: Time Entries : Prisla - 2hrs Nithish - 6hrs
A5: 4 | B5: =Dashboard!$J$1 -> MSB Dev | C5: 46073 | D5: 46086 | E5: 26.4 DS Sprint 1 | F5: Mahesh | G5: 26804 | H5: DataHub - Integration API - fee sync settings are reverting after edit | I5: Defect Fixed | J5: 2 | K5: =Table14567891011121331415171816201921222324252627282930313233[[#This Row],[Actual Hours Worklog]] / 4 -> 2.5 | L5: 10 | M5: 46070 | N5: 46070 | O5: Manual (TestCases-15) | P5: Aravindh | Q5: None | R5: Aravindh | S5: No Comments | T5: https://dev.azure.com/heartlandschools/MySchoolBucks/_git/SchoolBucks/pullrequest/47289 | U5: 46070 | V5: Prisla | W5: 46070 | X5: No Comments | Y5: Alex | Z5: 46070 | AA5: No Comments | AB5: NA | AC5: NA | AD5: Last sprint development was completed and testing also completed on Test env. Need to test it on Staging env and waiting for build deployment. Time Entries : Nithish - 10hrs
A6: 5 | B6: =Dashboard!$J$1 -> MSB Dev | C6: 46073 | D6: 46086 | E6: 26.4 DS Sprint 1 | F6: Mahesh | G6: 51754 | H6: MSB - REST API - POST/PUT Invoice - Allow create/update for inactive students (MSB Activities) | I6: Story Completed | J6: 2 | K6: =Table14567891011121331415171816201921222324252627282930313233[[#This Row],[Actual Hours Worklog]] / 4 -> 2.5 | L6: 10 | M6: 46073 | N6: 46073 | O6: Manual (TestCases-10) | P6: Aravindh | Q6: None | R6: Aravindh | S6: No Comments | T6: https://dev.azure.com/heartlandschools/MySchoolBucks/_git/SchoolBucks/pullrequest/47404 | U6: 46073 | V6: Prisla | W6: 46073 | X6: No Comments | Y6: Alex | Z6: 46073 | AA6: No Comments | AB6: No Comments | AC6: No Comments | AD6: Time Entries : Mahesh - 5hrs Prisla - 1.5hrs Nithish - 3.5hrs
A7: 6 | B7: =Dashboard!$J$1 -> MSB Dev | C7: 46073 | D7: 46086 | E7: 26.4 DS Sprint 1 | F7: Mahesh | G7: 51919 | H7: Datahub - PowerSchool 13 provider - Show customer Data Plugin filters | I7: Story Completed | J7: 10 | K7: =Table14567891011121331415171816201921222324252627282930313233[[#This Row],[Actual Hours Worklog]] / 4 -> 9.5 | L7: 38 | M7: 46076 | N7: 46083 | O7: Manual (TestCases-15) | P7: Prisla | Q7: None | R7: Prisla | S7: No Comments | T7: https://dev.azure.com/heartlandschools/MySchoolBucks/_git/SchoolBucks/pullrequest/47563 | U7: 46083 | V7: Prisla | W7: 46083 | X7: No Comments | Y7: Ken | Z7: 46084 | AA7: No Comments | AB7: No Comments | AC7: 25-Feb: Based on the AC shown in the POV, the client requested a few additional changes and also updated the AC. 02-Mar: No Comments | AD7: Based on the requested AC, the changes were implemented and demonstrated in the POV. The client then realized and requested a few more additional changes, and also updated the AC. As a result, the story points also revisited since the AC has changed. (Initially, the story points were estimated at 5. After the AC changed, the story was again assigned 5 story points). Time Entries : Mahesh - 30hrs Prisla - 1hrs Nithish - 7hrs
A8: 7 | B8: =Dashboard!$J$1 -> MSB Dev | C8: 46073 | D8: 46086 | E8: 26.4 DS Sprint 1 | F8: Aravindh | G8: 51963 | H8: MSB - Developer Portal - Update PowerSchool page content | I8: Story Completed | J8: 1 | K8: =Table14567891011121331415171816201921222324252627282930313233[[#This Row],[Actual Hours Worklog]] / 4 -> 2.25 | L8: 9 | M8: 46073 | N8: 46073 | O8: Manual (TestCases-10) | P8: Mahesh | Q8: None | R8: Mahesh | S8: No Comments | T8: https://dev.azure.com/heartlandschools/MySchoolBucks/_git/SchoolBucks/pullrequest/47398 | U8: 46073 | V8: Prisla | W8: 46073 | X8: No Comments | Y8: Alex | Z8: 46074 | AA8: No Comments | AB8: No Comments | AC8: No Comments | AD8: Comments : I completed code implemented on my first day. but nithish also put time entry for his testing. Time Entries : Aravindh - 6hrs Prisla - 1.5hrs Nithish - 1.5hrs
A9: 8 | B9: =Dashboard!$J$1 -> MSB Dev | C9: 46073 | D9: 46086 | E9: 26.4 DS Sprint 1 | F9: Aravindh | G9: 51902 | H9: MSB - REST API - Respect store availability for fees created with POST Invoice or POST Invoice Template (ICON Store Agent) | I9: Story Completed | J9: 5 | K9: =Table14567891011121331415171816201921222324252627282930313233[[#This Row],[Actual Hours Worklog]] / 4 -> 8.5 | L9: 34 | M9: 46076 | N9: 46079 | O9: Manual (TestCases-30) | P9: Mahesh | Q9: None | R9: Mahesh | S9: No Comments | T9: https://dev.azure.com/heartlandschools/MySchoolBucks/_git/SchoolBucks/pullrequest/47512 | U9: 46079 | V9: Prisla | W9: 46083 | X9: No Comments | Y9: Ken | Z9: 46084 | AA9: No Comments | AB9: After verifying the requirement with the Product Owner and the tester, I proceeded with the implementation. During our internal point‑of‑view review, we identified another perspective related to that acceptance‑criteria point, which led us to adjust the implementation. The actual issue was: When allStore is set to true and no values are provided in storeIds, the fee was incorrectly displayed with districtWide = false. After clarification, we decided that in this scenario, districtWide should be shown as true. | AC9: No Comments | AD9: Comments : While working on this story. after my analysis I found we cannot work in invoice endpoint. so I raised concern and after discussion with client . AC point is updated. Its took time for developmant and testing Time Entries : Aravindh - 24hrs Prisla - 3hrs Nithish - 7hrs
A10: 9 | B10: =Dashboard!$J$1 -> MSB Dev | C10: 46073 | D10: 46086 | E10: 26.4 DS Sprint 1 Stretch | F10: Mahesh | G10: 26899 | H10: DH - Unable to Add/Edit OneRoster Provider | I10: Defect Fixed | J10: 2 | K10: =Table14567891011121331415171816201921222324252627282930313233[[#This Row],[Actual Hours Worklog]] / 4 -> 2.5 | L10: 10 | M10: 46085 | N10: 46085 | O10: Manual (TestCases-10) | P10: Prisla | Q10: None | R10: Prisla | S10: No Comments | T10: https://dev.azure.com/heartlandschools/MySchoolBucks/_git/SchoolBucks/pullrequest/47611 | U10: 46085 | V10: Prisla | W10: 46085 | X10: No Comments | Y10: Ken | Z10: 46085 | AA10: No Comments | AB10: NA | AC10: NA | AD10: Time Entries : Mahesh - 6hrs Prisla - 2hrs Nithish - 2hrs
A11: 10 | B11: =Dashboard!$J$1 -> MSB Dev | C11: 46073 | D11: 46086 | E11: 26.4 DS Sprint 1 Stretch | F11: Mahesh | G11: 51340 | H11: MSB - Dev Portal - Add “Invoice by Email” Page to Developer Portal | I11: Story Completed | J11: 5 | K11: =Table14567891011121331415171816201921222324252627282930313233[[#This Row],[Actual Hours Worklog]] / 4 -> 3 | L11: 12 | M11: 46084 | N11: 46085 | O11: Manual (TestCases-10) | P11: Aravindh | Q11: None | R11: Aravindh | S11: No Comments | T11: https://dev.azure.com/heartlandschools/MySchoolBucks/_git/SchoolBucks/pullrequest/47596 | U11: 46085 | V11: Prisla | W11: 46085 | X11: No Comments | Y11: Ken | Z11: 46085 | AA11: No Comments | AB11: No Comments | AC11: No Comments | AD11: Time Entries : Mahesh - 6hrs Prisla - 3hrs Nithish - 3hrs
A12: 11 | B12: =Dashboard!$J$1 -> MSB Dev | C12: 46073 | D12: 46086 | E12: 26.4 DS Sprint 1 Stretch | F12: Aravindh | G12: 51185 | H12: MSB - Manage Integrations - Add Data summary View - Fees | I12: Story Being Developed | J12: 3 | K12: 6 | L12: 25 | M12: 46080 | N12: 46086 | O12: Manual (TestCases-10) | P12: Mahesh | R12: Mahesh | T12: https://dev.azure.com/heartlandschools/MySchoolBucks/_git/SchoolBucks/pullrequest/47622 | U12: 46086 | V12: Prisla | AD12: Comments : While working on this story. I had lots of doubts and we dont have get endpoint in hssconnect. So I used integrtaion api and I added hssconnect endpoint too. finally george suggested we can use integration api Time Entries : Aravindh - 24hrs Prisla - 1hrs
A13: 12 | B13: =Dashboard!$J$1 -> MSB Dev | C13: 46073 | D13: 46086

Sheet 26.4 DS Sprint 1-Defect
A1: S.No | B1: Sprint # | C1: Story/Defect ID | D1: Parent Story | E1: Developer | F1: Issue Type | G1: Issue Description | H1: Priority | I1: Defect Source | J1: Type | K1: Status | L1: Root Cause Category | M1: Comments
B2: 26.4 DS Sprint 1 | C2: 26804 | E2: Mahesh | F2: Defect | G2: DataHub - Integration API - fee sync settings are reverting after edit | H2: Minor | I2: Manual | J2: Internal | K2: Closed | L2: Development | M2: Client asked to include collectionType on Integration API
B3: 26.4 DS Sprint 1 | C3: 26796 | E3: Prisla | F3: Defect | G3: MSB - Partner - Manage Integration page does not display providers when MSB and DH provider id differ only by case sensitivity | H3: Minor | I3: Manual | J3: Internal | K3: Closed | L3: Development | M3: Provider is not shown due to a case sensitivity mismatch between MSB and DH
B4: 26.4 DS Sprint 1 | C4: 51205 | E4: Prisla | F4: Bounceback | G4: Synergy Include/Exclude setting not working for fees | H4: Minor | I4: Manual | J4: Internal | K4: Closed | L4: Development | M4: Missed in development
B5: 26.4 DS Sprint 1 | C5: 51205 | E5: Prisla | F5: Bounceback | G5: Synergy is running a full sync without include/exclude settings. After setting a school number in the include list and running the school and student sync, students from other schools are not deleted in the UI and DSL. | H5: Minor | I5: Manual | J5: Internal | K5: Inprogress | L5: Development | M5: The issue occurs only in the test environment. To analyze it, we requested server logs, but no one—including the client’s development manager—has access to them. Only high-level access is available. Since the client also requested the logs, there has been a delay in obtaining them from the test environment. Therefore, all Bouncebacks were consolidated, a defect (26912) was created, and this story was closed.
B6: 26.4 DS Sprint 1 | C6: 51205 | E6: Prisla | F6: Bounceback | G6: Powerschool 13 is running a full sync without include/exclude settings. After setting a school number in the include list and running the school and student,term sync, students from other schools are not deleted in student,term | H6: Minor | I6: Manual | J6: Internal | K6: Inprogress | L6: Development | M6: The issue occurs only in the test environment. To analyze it, we requested server logs, but no one—including the client’s development manager—has access to them. Only high-level access is available. Since the client also requested the logs, there has been a delay in obtaining them from the test environment. Therefore, all Bouncebacks were consolidated, a defect (26912) was created, and this story was closed.
B7: 26.4 DS Sprint 1 | C7: 51205 | E7: Prisla | F7: Bounceback | G7: OR File Import, when a school is excluded: the school is disabled but the students remain active in DH | H7: Minor | I7: Manual | J7: External | K7: Inprogress | L7: Development | M7: The issue occurs only in the test environment. To analyze it, we requested server logs, but no one—including the client’s development manager—has access to them. Only high-level access is available. Since the client also requested the logs, there has been a delay in obtaining them from the test environment. Therefore, all Bouncebacks were consolidated, a defect (26912) was created, and this story was closed.
B8: 26.4 DS Sprint 1 | C8: 51205 | E8: Prisla | F8: Bounceback | G8: OR File Import, when a school is included: the school is correctly enabled while the others aren't but students enrolled in the school are being deleted when they should remain active (DSL counts are incorrect as well) | H8: Minor | I8: Manual | J8: External | K8: Inprogress | L8: Development | M8: The issue occurs only in the test environment. To analyze it, we requested server logs, but no one—including the client’s development manager—has access to them. Only high-level access is available. Since the client also requested the logs, there has been a delay in obtaining them from the test environment. Therefore, all Bouncebacks were consolidated, a defect (26912) was created, and this story was closed.
B9: 26.4 DS Sprint 1 Stretch | C9: 26899 | E9: Mahesh | F9: Defect | G9: DH - Unable to Add/Edit OneRoster Provider | H9: Minor | I9: Manual | J9: Internal | K9: Closed | L9: Development | M9: Missed in development

Sheet 26.3 DS Sprint 3-Status
A1: S.No | B1: Application Name | C1: Sprint Start Date | D1: Sprint End Date | E1: Sprint | F1: Developer | G1: Story ID/Defect ID | H1: Description | I1: Status | J1: Estimated(hrs/sp) | K1: Actual(hrs/sp) | L1: Actual Hours Worklog | M1: Dev start date | N1: Dev end date | O1: Unit testing | P1: Peer Tested By | Q1: Peer Tested Defects, if any | R1: Peer Reviewed By | S1: Peer Code Review Comments, if any | T1: PR Number/Link | U1: PR Created Date | V1: Reviewer 1 | W1: PR Approved Date | X1: Code Review Comments, if any | Y1: Reviewer 2 | Z1: Approved Date | AA1: Code Review Comments, if any2 | AB1: Internal PO -POV Comments | AC1: Client PO -POV Comments | AD1: Comments
A2: 1 | B2: =Dashboard!$J$1 -> MSB Dev | C2: 46059 | D2: 46072 | E2: 26.3 DS Sprint 3 | F2: Prisla | G2: 26743 | H2: MSB - Advanced Configuration - Manage Integration page - quick search is not working | I2: Defect Fixed | J2: 2 | K2: =Table145678910111213314151718162019212223242526272829303132[[#This Row],[Actual Hours Worklog]] / 4 -> 1.75 | L2: 7 | M2: 46059 | N2: 46059 | O2: Manual (TestCases-10) | P2: NA | Q2: NA | R2: NA | S2: NA | T2: https://dev.azure.com/heartlandschools/MySchoolBucks/_git/SchoolBucks/pullrequest/47113 https://dev.azure.com/heartlandschools/MySchoolBucks/_git/SchoolBucks/pullrequest/47140 | U2: 46059 | V2: Ken | W2: 46059 | X2: No Comments | Y2: NA | Z2: NA | AA2: NA | AB2: NA | AC2: NA | AD2: Time Entries : Prisla - 3hrs Nithish - 4hrs
A3: 2 | B3: =Dashboard!$J$1 -> MSB Dev | C3: 46059 | D3: 46072 | E3: 26.3 DS Sprint 3 | F3: Prisla | G3: 51366 | H3: [WAVE] HSS Connect API – Fee Providers – Support Date Filter for Fees | I3: Story Completed | J3: 2 | K3: =Table145678910111213314151718162019212223242526272829303132[[#This Row],[Actual Hours Worklog]] / 4 -> 4.75 | L3: 19 | M3: 46052 | N3: 46056 | O3: Manual (TestCases-15) | P3: Mahesh | Q3: No Comments | R3: Mahesh | S3: No Comments | T3: https://dev.azure.com/heartlandschools/MySchoolBucks/_git/SchoolBucks/pullrequest/46971 https://dev.azure.com/heartlandschools/MySchoolBucks/_git/SchoolBucks/pullrequest/47138 | U3: 46056 | V3: Alex | W3: 46056 | X3: No Comments | Y3: NA | Z3: NA | AA3: Na | AB3: No Comments | AC3: No Comments | AD3: Comments : 1. Assigned developer Suresh took several unplanned leaves and permissions during the last sprint, and he has not yet worked on this task. Prisla started and completed the development in the last sprint, and it has been carried over to the current sprint for testing. 2. Took time to fix the bouceBack and testing Time Entries : Prisla - 13hrs Nithish - 2hrs
A4: 3 | B4: =Dashboard!$J$1 -> MSB Dev | C4: 46059 | D4: 46072 | E4: 26.3 DS Sprint 3 | F4: Mahesh | G4: 49921 | H4: MSB - REST API - GET Household - Optionally include Meal balance & Invoices in response (Activities)- Automation | I4: Story Completed | J4: 2 | K4: =Table145678910111213314151718162019212223242526272829303132[[#This Row],[Actual Hours Worklog]] / 4 -> 0.75 | L4: 3 | M4: 46059 | N4: 46059 | O4: NA | P4: NA | Q4: NA | R4: NA | S4: NA | T4: NA | U4: NA | V4: NA | W4: NA | X4: NA | Y4: NA | Z4: NA | AA4: NA | AB4: NA | AC4: NA | AD4: Comments : Automation already covered Time Entries : Mahesh - 3hrs
A5: 4 | B5: =Dashboard!$J$1 -> MSB Dev | C5: 46059 | D5: 46072 | E5: 26.3 DS Sprint 3 | F5: Mahesh | G5: 51798 | H5: MSB - Partner Integrations - New Automation [26.3] | I5: Story Completed | J5: 5 | K5: =Table145678910111213314151718162019212223242526272829303132[[#This Row],[Actual Hours Worklog]] / 4 -> 16 | L5: 64 | M5: 46059 | N5: 46072 | O5: NA | P5: Aravindh | Q5: None | R5: Aravindh | S5: No Comments | T5: https://dev.azure.com/heartlandschools/MySchoolBucks/_git/MSBAutomation/pullrequest/47146 https://dev.azure.com/heartlandschools/MySchoolBucks/_git/MSBAutomation/pullrequest/47320 https://dev.azure.com/heartlandschools/MySchoolBucks/_git/MSBAutomation/pullrequest/47332 https://dev.azure.com/heartlandschools/MySchoolBucks/_git/MSBAutomation/pullrequest/47320 https://dev.azure.com/heartlandschools/MySchoolBucks/_git/MSBAutomation/pullrequest/47151 https://dev.azure.com/heartlandschools/MySchoolBucks/_git/MSBAutomation/pullrequest/47267 | U5: 46063 | V5: Prisla | W5: 46071 | X5: No Comments | Y5: Alex | Z5: 46071 | AA5: No Comments | AB5: NA | AC5: NA | AD5: The story was created as a common task to implement automation for this release stories. We have covered almost all of them. Time Entries : Mahesh - 34hrs Prisla - 15hrs Aravindh - 15hrs
A6: 5 | B6: =Dashboard!$J$1 -> MSB Dev | C6: 46059 | D6: 46072 | E6: 26.3 DS Sprint 3 | F6: Nithish | G6: 51802 | H6: MSB - Partner Integrations - Regression [26.3] | I6: Story Completed | J6: 13 | K6: =Table145678910111213314151718162019212223242526272829303132[[#This Row],[Actual Hours Worklog]] / 4 -> 6 | L6: 24 | M6: NA | N6: NA | O6: NA | P6: NA | Q6: NA | R6: NA | S6: NA | T6: NA | U6: NA | V6: NA | W6: NA | X6: NA | Y6: NA | Z6: NA | AA6: NA | AB6: NA | AC6: NA | AD6: Added only for testing purpose Time Entries : Nithish - 24hrs
A7: 6 | B7: =Dashboard!$J$1 -> MSB Dev | C7: 46059 | D7: 46072 | E7: 26.3 DS Sprint 3 | F7: Nithish | G7: 51800 | H7: [WAVE] MSB - Partner Integrations - Regression [26.3] | I7: Story Completed | J7: 13 | K7: =Table145678910111213314151718162019212223242526272829303132[[#This Row],[Actual Hours Worklog]] / 4 -> 6 | L7: 24 | M7: NA | N7: NA | O7: NA | P7: NA | Q7: NA | R7: NA | S7: NA | T7: NA | U7: NA | V7: NA | W7: NA | X7: NA | Y7: NA | Z7: NA | AA7: NA | AB7: NA | AC7: NA | AD7: Added only for testing purpose Time Entries : Nithish - 24hrs
A8: 7 | B8: =Dashboard!$J$1 -> MSB Dev | C8: 46059 | D8: 46072 | E8: 26.3 DS Sprint 3 | F8: Aravindh | G8: 51708 | H8: [WAVE] MSB - Developer Portal - Online Payments - Add new page Certify Integration - Automation [26.3] | I8: Story Completed | J8: 1 | K8: =Table145678910111213314151718162019212223242526272829303132[[#This Row],[Actual Hours Worklog]] / 4 -> 4.75 | L8: 19 | M8: 46059 | N8: 46062 | O8: NA | P8: Mahesh | Q8: No Comments | R8: Mahesh | S8: No Comments | T8: https://dev.azure.com/heartlandschools/MySchoolBucks/_git/MSBAutomation/pullrequest/47151 | U8: 46062 | V8: Prisla | W8: 46071 | X8: No Comments | Y8: Alex | Z8: 46071 | AA8: No Comments | AB8: NA | AC8: NA | AD8: Comments : I completed code implementation in first day of sprint. but Due to local environment issue (Team also face issue). I am not able to test. so It took time for testing and Prisla also tested in her local before merge. Time Entries : Aravindh - 12hrs Prisla - 7hrs
A9: 8 | B9: =Dashboard!$J$1 -> MSB Dev | C9: 46059 | D9: 46072 | E9: 26.3 DS Sprint 3 | F9: Aravindh | G9: 51336 | H9: [WAVE] MSB - REST/PAY APIs-GET/users - Add fields to response and document in swagger - Automation [26.3] | I9: Story Completed | J9: 2 | K9: =Table145678910111213314151718162019212223242526272829303132[[#This Row],[Actual Hours Worklog]] / 4 -> 3.5 | L9: 14 | M9: 46064 | N9: 46069 | O9: NA | P9: Mahesh | Q9: No Comments | R9: Mahesh | S9: No Comments | T9: https://dev.azure.com/heartlandschools/MySchoolBucks/_git/MSBAutomation/pullrequest/47267 | U9: 46069 | V9: Prisla | W9: 46071 | X9: No Comments | Y9: Alex | Z9: 46071 | AA9: No Comments | AB9: NA | AC9: NA | AD9: Comments : I completed code implementation in first day of sprint. but Due to local environment issue (Team also face issue). I am not able to test. Time Entries : Aravindh - 12hrs Prisla - 2hrs
A10: 9 | B10: =Dashboard!$J$1 -> MSB Dev | C10: 46059 | D10: 46072 | E10: 26.3 DS Sprint 3 | F10: Aravindh | G10: 51205 | H10: [WAVE] Datahub - Providers - Support School filters | I10: Story Peer Review | J10: 5 | K10: =Table145678910111213314151718162019212223242526272829303132[[#This Row],[Actual Hours Worklog]] / 4 -> 3.5 | L10: 14 | M10: 46031 | N10: 46037 | O10: Manual (TestCases-80) | P10: Aravindh | Q10: No Comments | R10: Aravindh | S10: No Comments | T10: https://dev.azure.com/heartlandschools/MySchoolBucks/_git/SchoolBucks/pullrequest/46663 | U10: 46037 | V10: Prisla | W10: 46059 | X10: No Comments | Y10: Alex | Z10: 46059 | AA10: 1. Need to add validation for null check 2. We should give precedence for excludeschoolNumber 3. Remove unwanted import 4. For avoiding the multiple loadschoolNumber call. we should handle in generatePostParamsRequest() 5. Remove schoolNumberNotInIncludeList unwanted code | AB10: No Comments | AC10: No Comments | AD10: Comments : 26.3 DS Sprint 1: The stretch story was picked up by Prisla. hence, this is a Wave team story, and development was completed. 26.3 DS Sprint 2: The story was assigned to Aravindh for dev-testing and to fix any issues found during testing, but the work was not completed, Because of found some issues, so the story was carried forward to the next sprint. 26.3 DS Sprint 3: The story has been moved to the next release (26.4), which is why the code has not yet been merged and this is kept it on hold for this sprint. Reason for comments : Null pointer handling: The null pointer scenario is already handled in the existing code. Removed unwanted import: We always remove unused imports from all files. However, it was missed in SISAdapter, and it has now been cleaned up. Avoiding multiple calls: Initially, Prisla also gave the same review comment and explained that it was not doable. The same review comment came from the client, and the task was completed based on the client’s suggestion.. The client has now suggested a new approach to handle the include and exclude logic for schoolNumberNotInIncludeList. Removed schoolNumberNotInIncludeList code/comments: This parameter is already handled through a different workflow, so the previously added code and comments related to schoolNumberNotInIncludeList have been removed. Time Entries : Aravindh - 12hrs Prisla - 2hrs
A11: 10 | B11: =Dashboard!$J$1 -> MSB Dev | C11: 46059 | D11: 46072 | E11: 26.3 DS Sprint 3 Stretch | F11: Mahesh | G11: 26804 | H11: DataHub - Integration API - fee sync settings are reverting after edit | I11: Defect Being Tested | J11: 2 | K11: =Table145678910111213314151718162019212223242526272829303132[[#This Row],[Actual Hours Worklog]] / 4 -> 4 | L11: 16 | M11: 46070 | N11: 46070 | O11: Manual (TestCases-15) | P11: Aravindh | Q11: None | R11: Aravindh | S11: No Comments | T11: https://dev.azure.com/heartlandschools/MySchoolBucks/_git/SchoolBucks/pullrequest/47289 | U11: 46070 | V11: Prisla | W11: 46070 | X11: No Comments | Y11: Alex | Z11: 46070 | AA11: No Comments | AB11: NA | AC11: NA | AD11: The defect was raised two days ago, and it should ideally be treated as a new story implementation to add it to the API. Since the client requested that it be included in the current release, we accepted the change and completed the code accordingly. Successfully tested on Test env and need to test it on other env's and QA was waiting for next build deployment. Time Entries : Mahesh - 7hrs Prisla - 3hrs Nithish - 6hrs
A12: 11 | B12: =Dashboard!$J$1 -> MSB Dev | C12: 46059 | D12: 46072
A13: 12 | B13: =Dashboard!$J$1 -> MSB Dev | C13: 46059 | D13: 46072

Sheet 26.3 DS Sprint 3-Defect
A1: S.No | B1: Sprint # | C1: Story/Defect ID | D1: Parent Story | E1: Developer | F1: Issue Type | G1: Issue Description | H1: Priority | I1: Defect Source | J1: Type | K1: Status | L1: Root Cause Category | M1: Comments
B2: 26.3 DS Sprint 3 | C2: 26743 | E2: Prisla | F2: Defect | G2: MSB - Advanced Configuration - Manage Integration page - quick search is not working | H2: Minor | I2: Manual | J2: Internal | K2: Closed | L2: Development | M2: Quick search is not working in Integration page
B3: 26.3 DS Sprint 3 | C3: 26743 | E3: Prisla | F3: Bounceback | G3: Search with any valid value and filter the results, then refresh. After refresh, the search value becomes empty and only a single record is shown, instead of all records. | H3: Minor | I3: Manual | J3: Internal | K3: Closed | L3: Development | M3: Refresh the list integration grid on hard refresh and reset the search
B4: 26.3 DS Sprint 3 | C4: 51366 | E4: Prisla | F4: Bounceback | G4: When the feesSyncStartDate field is not passed, is empty, or is removed, validation is returned incorrectly for Skyward Qmlativ OneRoster, Skyward SMS OneRoster, Synergy OneRoster, OneRoster File, OneRoster Certification, Integration API, Infinite Campus OneRoster, HSS Connect, Genesis OneRoster Import Template, FACTS OneRoster, and ClassLink OneRoster. | H4: Minor | I4: Manual | J4: Internal | K4: Closed | L4: Development | M4: Missed in development
B5: 26.3 DS Sprint 3 | C5: 51366 | E5: Prisla | F5: Bounceback | G5: feeSyncStartDate": "01/01/2024 12:00:00 AM" instead it should be "2024-01-01 12:00:00 AM" -(YYYY-MM-DD) | H5: Minor | I5: Manual | J5: Internal | K5: Closed | L5: Development | M5: Missed in development
B6: 26.3 DS Sprint 3 | C6: 51366 | E6: Prisla | F6: Bounceback | G6: Integration API POST/PUT: Passed feeSyncStartDate as "2026-02-10T27:00:00.00Z", but the UI shows an incorrect time as "2026-02-11 09:00:00 PM" instead of "2026-02-11 03:00:00 AM." | H6: Minor | I6: Manual | J6: Internal | K6: Closed | L6: Development | M6: Missed in development
B7: 26.3 DS Sprint 3 Stretch | C7: 26804 | E7: Mahesh | F7: Defect | G7: DataHub - Integration API - fee sync settings are reverting after edit | H7: Minor | I7: Manual | J7: Internal | K7: Inprogress | L7: Development | M7: Client asked to include collectionType on Integration API

Sheet 26.3 DS Sprint 2-Status
A1: S.No | B1: Application Name | C1: Sprint Start Date | D1: Sprint End Date | E1: Sprint | F1: Developer | G1: Story ID/Defect ID | H1: Description | I1: Status | J1: Estimated(hrs/sp) | K1: Actual(hrs/sp) | L1: Actual Hours Worklog | M1: Dev start date | N1: Dev end date | O1: Unit testing | P1: Peer Tested By | Q1: Peer Tested Defects, if any | R1: Peer Reviewed By | S1: Peer Code Review Comments, if any | T1: PR Number/Link | U1: PR Created Date | V1: Reviewer 1 | W1: PR Approved Date | X1: Code Review Comments, if any | Y1: Reviewer 2 | Z1: Approved Date | AA1: Code Review Comments, if any2 | AB1: Internal PO -POV Comments | AC1: Client PO -POV Comments | AD1: Comments
A2: 1 | B2: =Dashboard!$J$1 -> MSB Dev | C2: 46045 | D2: 46058 | E2: 26.3 DS Sprint 2 | F2: Mahesh | G2: 50965 | H2: MSBP - API - Allow user to reset password without opting into SMS messaging | I2: Story Completed | J2: 2 | K2: 2 | L2: 8 | M2: 46045 | N2: 46045 | O2: Manual (TestCases-10) | P2: Prisla | Q2: None | R2: Prisla | S2: No Comments | T2: https://dev.azure.com/heartlandschools/MySchoolBucks/_git/SchoolBucks/pullrequest/46693 https://dev.azure.com/heartlandschools/MySchoolBucks/_git/SchoolBucks/pullrequest/46836 | U2: 46038 | V2: Prisla | W2: 46038 | X2: No Comments | Y2: Alex | Z2: 46039 | AA2: No Comments | AB2: No Comments | AC2: No Comments | AD2: Time Entries: Mahesh: 5hrs Nithish: 2hrs Prisla: 1hrs
A3: 2 | B3: =Dashboard!$J$1 -> MSB Dev | C3: 46045 | D3: 46058 | E3: 26.3 DS Sprint 2 | F3: Mahesh | G3: 51108 | H3: [WAVE] MSB - REST API - Assign Stores & PM to User accounts (Onboarding) | I3: Story Completed | J3: 8 | K3: 10 | L3: 42 | M3: 46050 | N3: 46055 | O3: Manual (TestCases-30) | P3: Nivetha | Q3: None | R3: Nivetha | S3: None | T3: https://dev.azure.com/heartlandschools/MySchoolBucks/_git/SchoolBucks/pullrequest/47010 | U3: 46055 | V3: Prisla | W3: 46055 | X3: No Comments | Y3: Alex | Z3: 46055 | AA3: No Comments | AB3: No Comments | AC3: No Comments | AD3: Time Entries: Mahesh: 38hrs Nithish: 3hrs Prisla: 1hrs
A4: 3 | B4: =Dashboard!$J$1 -> MSB Dev | C4: 46045 | D4: 46058 | E4: 26.3 DS Sprint 2 | F4: Nivetha | G4: 51461 | H4: Datahub - Destiny provider - Add Collection Type Filter (Huffman ISD) | I4: Story Completed | J4: 2 | K4: 5.5 | L4: 22 | M4: 46045 | N4: 46045 | O4: Manual (TestCases-15) | P4: Mahesh | Q4: 1. In the view of an existing Destiny provider, it shows "N/A" instead of displaying all collection types. 2 If I edit any provider (e.g., Aeries) and change it to Destiny, the collection types appear unchecked. | R4: Mahesh | S4: 1. Rename method to getPaymentsForFees() and moved to the provider class can be used in both DestinyAdapter and SISAdapter 2. Use only collectionType as the property name, and handle it in JSP to display all four collection types and no need to pass all 4 collectiontype here. | T4: https://dev.azure.com/heartlandschools/MySchoolBucks/_git/SchoolBucks/pullrequest/46837 | U4: 46045 | V4: Prisla | W4: 46056 | X4: 1. You need to include DSL log for the ignored fee 2. What will happen if both properties are set only one message will be added 3. Why this block is duplicated | Y4: Michael | Z4: 46056 | AA4: No Comments | AB4: No Comments | AC4: No Comments | AD4: While merging the story 51203 there were conflict and need to validate both stories so it took extra effort to complete. Time Entries: Nivetha: 15hrs Nithish: 2hrs Prisla: 5hrs
A5: 4 | B5: =Dashboard!$J$1 -> MSB Dev | C5: 46045 | D5: 46058 | E5: 26.3 DS Sprint 2 | F5: Nivetha | G5: 51365 | H5: [WAVE] HSS Connect API – GET/PUT Providers – Support School Filters | I5: Story Completed | J5: 5 | K5: 7.25 | L5: 29 | M5: 46048 | N5: 46052 | O5: Manual (TestCases-10) | P5: Mahesh | Q5: None | R5: Mahesh | S5: None | T5: https://dev.azure.com/heartlandschools/MySchoolBucks/_git/SchoolBucks/pullrequest/47001 | U5: 46052 | V5: Prisla | W5: 46056 | X5: No Comments | Y5: Michael | Z5: 46056 | AA5: No Comments | AB5: No Comments | AC5: No Comments | AD5: The story has impact on integration api, so i implemented in integration POST/PUT/GET endpoints. That's why it took extra effort to complete Time Entries: Nivetha: 18hrs Nithish: 8hrs Prisla: 3hrs
A6: 5 | B6: =Dashboard!$J$1 -> MSB Dev | C6: 46045 | D6: 46058 | E6: 26.3 DS Sprint 2 | F6: Nivetha | G6: 51620 | H6: Mobile Pay - API - Extend session when user is active | I6: Story Need More Info | J6: 2 | K6: NA | L6: NA | M6: 46056 | N6: NA | O6: NA | P6: NA | Q6: NA | R6: NA | S6: NA | T6: NA | U6: NA | V6: NA | W6: NA | X6: NA | Y6: NA | Z6: NA | AA6: NA | AB6: NA | AC6: NA | AD6: Working as expected and requested more info
A7: 6 | B7: =Dashboard!$J$1 -> MSB Dev | C7: 46045 | D7: 46058 | E7: 26.3 DS Sprint 2 | F7: Ken | G7: 51144 | H7: MSB - REST API - Product endpoints & model - Support new Product option restrictions for Invoice Due (QA only) | I7: Story Completed | J7: 2 | K7: NA | L7: NA | M7: NA | N7: NA | O7: NA | P7: NA | Q7: NA | R7: NA | S7: NA | T7: NA | U7: NA | V7: NA | W7: NA | X7: NA | Y7: NA | Z7: NA | AA7: NA | AB7: NA | AC7: NA | AD7: Added only for testing purpose Time Entries: Nithish: 6hrs
A8: 7 | B8: =Dashboard!$J$1 -> MSB Dev | C8: 46045 | D8: 46058
A9: 8 | B9: =Dashboard!$J$1 -> MSB Dev | C9: 46045 | D9: 46058
A10: 9 | B10: =Dashboard!$J$1 -> MSB Dev | C10: 46045 | D10: 46058
A11: 10 | B11: =Dashboard!$J$1 -> MSB Dev | C11: 46045 | D11: 46058

Sheet 26.3 DS Sprint 2-Defect
A1: S.No | B1: Sprint # | C1: Story/Defect ID | D1: Parent Story | E1: Developer | F1: Issue Type | G1: Issue Description | H1: Priority | I1: Defect Source | J1: Type | K1: Status | L1: Root Cause Category | M1: Comments
B2: 26.3 DS Sprint 2 | C2: 50965 | E2: Mahesh | F2: Bounceback | G2: on a NON Opt-In user, if the user initiates a SMS UPDATE, the confirm sms phone number is not allowing the user to then request a password reset via the SMS recovery option | H2: Minor | I2: Manual | J2: External | K2: Closed | L2: Development | M2: The client has requested that the existing issue be included in this bounceback
B3: 26.3 DS Sprint 2 | C3: 51108 | E3: Mahesh | F3: Bounceback | G3: API return 500 error for field storeIDs and invoiceStoreID when pass invalid data | H3: Minor | I3: Manual | J3: Internal | K3: Closed | L3: Development | M3: Missing validation for field storeIDs and invoiceStoreID

Sheet 26.3 DS Sprint 1-Status
A1: S.No | B1: Application Name | C1: Sprint Start Date | D1: Sprint End Date | E1: Sprint | F1: Developer | G1: Story ID/Defect ID | H1: Description | I1: Status | J1: Estimated(hrs/sp) | K1: Actual(hrs/sp) | L1: Actual Hours Worklog | M1: Dev start date | N1: Dev end date | O1: Unit testing | P1: Peer Tested By | Q1: Peer Tested Defects, if any | R1: Peer Reviewed By | S1: Peer Code Review Comments, if any | T1: PR Number/Link | U1: PR Created Date | V1: Reviewer 1 | W1: PR Approved Date | X1: Code Review Comments, if any | Y1: Reviewer 2 | Z1: Approved Date | AA1: Code Review Comments, if any2 | AB1: Internal PO -POV Comments | AC1: Client PO -POV Comments | AD1: Comments
A2: 1 | B2: =Dashboard!$J$1 -> MSB Dev | C2: 46031 | D2: 46044 | E2: 26.3 DS Sprint 1 | F2: Mahesh | G2: 51289 | H2: Datahub - Integration API Provider Type - Support Eligibility option (GST BOCES) | I2: Story Completed | J2: 5 | K2: 5.5 | L2: 22 | M2: 46031 | N2: 46034 | O2: Manual (TestCases-10) | P2: Nivetha | Q2: None | R2: Nivetha | S2: No Comments | T2: https://dev.azure.com/heartlandschools/MySchoolBucks/_git/SchoolBucks/pullrequest/46576 | U2: 46034 | V2: Prisla | W2: 46035 | X2: No Comments | Y2: Ken | Z2: 46035 | AA2: No Comments | AB2: No Comments | AC2: No Comments | AD2: Time Entries: Mahesh: 12hrs Nithish: 8hrs Prisla: 2hrs
A3: 2 | B3: =Dashboard!$J$1 -> MSB Dev | C3: 46031 | D3: 46044 | E3: 26.3 DS Sprint 1 | F3: Mahesh | G3: 51441 | H3: [WAVE] MSB - REST API - Create District (Onboarding) | I3: Story Completed | J3: 3 | K3: 3.5 | L3: 14 | M3: 46003 | N3: 46014 | O3: Manual (TestCases-50) | P3: Nivetha | Q3: None | R3: Nivetha | S3: No Comments | T3: https://dev.azure.com/heartlandschools/MySchoolBucks/_git/SchoolBucks/pullrequest/46346 | U3: 46014 | V3: Prisla | W3: 46015 | X3: No Comments | Y3: Geroge | Z3: 46021 | AA3: create a user log for the attempt to create a district | AB3: No Comments | AC3: No Comments | AD3: The development was completed in the last sprint and only development story(50779), This story is testing purposes only. Time Entries: Mahesh: 2hrs Nithish: 9hrs Prisla: 3hrs
A4: 3 | B4: =Dashboard!$J$1 -> MSB Dev | C4: 46031 | D4: 46044 | E4: 26.3 DS Sprint 1 | F4: Mahesh | G4: 26554 | H4: Notification Hub - Emails - Unable to download attachments (Tickets) | I4: Defect Fixed | J4: 3 | K4: 3 | L4: 13 | M4: 46038 | N4: 46041 | O4: Manual (TestCases-6) | P4: Nivetha | Q4: None | R4: Nivetha | S4: No Comments | T4: https://dev.azure.com/heartlandschools/MySchoolBucks/_git/SchoolBucks/pullrequest/46712 | U4: 46041 | V4: Prisla | W4: 46042 | X4: No Comments | Y4: Ken | Z4: 46043 | AA4: No Comments | AB4: No Comments | AC4: NA | AD4: Time Entries: Mahesh: 6hrs Nithish: 4hrs Prisla: 3hrs
A5: 4 | B5: =Dashboard!$J$1 -> MSB Dev | C5: 46031 | D5: 46044 | E5: 26.3 DS Sprint 1 | F5: Nivetha | G5: 51267 | H5: MSB - Checkout API - Cart / Process - Postpone DBA Name inclusion to 26.3 release (Destiny Fundraising Mgr) | I5: Story Completed | J5: 2 | K5: 2 | L5: 8 | M5: 46031 | N5: 46031 | O5: Manual (TestCases-10) | P5: Mahesh | Q5: None | R5: Mahesh | S5: No Comments | T5: https://dev.azure.com/heartlandschools/MySchoolBucks/_git/SchoolBucks/pullrequest/46546 | U5: 46031 | V5: Prisla | W5: 46035 | X5: No Comments | Y5: Ken | Z5: 46035 | AA5: No Comments | AB5: No Comments | AC5: No Comments | AD5: Time Entries: NIvetha: 5hrs Nithish: 3hrs
A6: 5 | B6: =Dashboard!$J$1 -> MSB Dev | C6: 46031 | D6: 46044 | E6: 26.3 DS Sprint 1 | F6: Nivetha | G6: 51404 | H6: Datahub - Integration API - Support Meal Payments in GET payments (GST BOCES) | I6: Story Completed | J6: 3 | K6: 3 | L6: 13 | M6: 46031 | N6: 46035 | O6: Manual (TestCases-10) | P6: Mahesh | Q6: None | R6: Mahesh | S6: No Comments | T6: https://dev.azure.com/heartlandschools/MySchoolBucks/_git/SchoolBucks/pullrequest/46610 | U6: 46035 | V6: Prisla | W6: 46037 | X6: No Comments | Y6: Ken | Z6: 46037 | AA6: No Comments | AB6: No Comments | AC6: No Comments | AD6: Time Entries: Nivetha: 6hrs Nithish: 5hrs Prisla: 2hrs
A7: 6 | B7: =Dashboard!$J$1 -> MSB Dev | C7: 46031 | D7: 46044 | E7: 26.3 DS Sprint 1 | F7: Mahesh | G7: 50965 | H7: MSBP - API - Allow user to reset password without opting into SMS messaging | I7: Story Being Tested | J7: 3 | K7: 3.5 | L7: 15 | M7: 46034 | N7: 46038 | O7: Manual (TestCases-10) | P7: Prisla | Q7: None | R7: Prisla | S7: No Comments | T7: https://dev.azure.com/heartlandschools/MySchoolBucks/_git/SchoolBucks/pullrequest/46693 | U7: 46038 | V7: Prisla | W7: 46038 | X7: No Comments | Y7: Alex | Z7: 46039 | AA7: No Comments | AB7: No Comments | AC7: No Comments | AD7: The client raised a bounceback that was not related to this story, as it was pre-existing. However, the client requested that it be covered in this story. Time Entries: Mahesh: 7hrs Nithish: 5hrs Prisla: 3hrs
A8: 7 | B8: =Dashboard!$J$1 -> MSB Dev | C8: 46031 | D8: 46044 | E8: 26.3 DS Sprint 1 Stretch | F8: Nivetha | G8: 51461 | H8: Datahub - Destiny provider - Add Collection Type Filter (Huffman ISD) | I8: Story Being Developed | J8: 5 | M8: 46038
A9: 8 | B9: =Dashboard!$J$1 -> MSB Dev | C9: 46031 | D9: 46044
A10: 9 | B10: =Dashboard!$J$1 -> MSB Dev | C10: 46031 | D10: 46044
A11: 10 | B11: =Dashboard!$J$1 -> MSB Dev | C11: 46031 | D11: 46044

Sheet 26.3 DS Sprint 1-Defect
A1: S.No | B1: Sprint # | C1: Story/Defect ID | D1: Parent Story | E1: Developer | F1: Issue Type | G1: Issue Description | H1: Priority | I1: Defect Source | J1: Type | K1: Status | L1: Root Cause Category | M1: Comments
B2: 26.3 DS Sprint 1 | C2: 26554 | E2: Mahesh | F2: Defect | G2: Notification Hub - Emails - Unable to download attachments (Tickets) | H2: Minor | I2: Manual | J2: External | K2: Closed | L2: Existing_Issues | M2: Unable to download the multiple email attachment CLI,PDF,XLSX
B3: 26.3 DS Sprint 1 | C3: 51441 | E3: Mahesh | F3: Bounceback | G3: When Allow All Districts are set to false, the api still allows the creation of a district. Instead, the api should throw proper validation | H3: Major | I3: Manual | J3: Internal | K3: Closed | L3: Development | M3: Missed developer account validation check for field "Allow All Districts" as "false"
B4: 26.3 DS Sprint 1 | C4: 51441 | E4: Mahesh | F4: Bounceback | G4: Removing the Region field still allows the creation of a district, even though it is a required field. The system should throw proper validation like "FAILED VALIDATION: Required data [region] was missing, null, or empty" | H4: Minor | I4: Manual | J4: Internal | K4: Closed | L4: Development | M4: Missed to handle the validation for field "Region"
B5: 26.3 DS Sprint 1 | C5: 50965 | E5: Mahesh | F5: Bounceback | G5: on a NON Opt-In user, if the user initiates a SMS UPDATE, the confirm sms phone number is not allowing the user to then request a password reset via the SMS recovery option | H5: Minor | I5: Manual | J5: External | K5: Inprogress | L5: Development | M5: The client has requested that the existing issue be included in this bounceback

Sheet 26.1 DS Sprint 3-Status
A1: S.No | B1: Application Name | C1: Sprint Start Date | D1: Sprint End Date | E1: Sprint | F1: Developer | G1: Story ID/Defect ID | H1: Description | I1: Status | J1: Estimated(hrs/sp) | K1: Actual(hrs/sp) | L1: Actual Hours Worklog | M1: Dev start date | N1: Dev end date | O1: Unit testing | P1: Peer Tested By | Q1: Peer Tested Defects, if any | R1: Peer Reviewed By | S1: Peer Code Review Comments, if any | T1: PR Number/Link | U1: PR Created Date | V1: Reviewer 1 | W1: PR Approved Date | X1: Code Review Comments, if any | Y1: Reviewer 2 | Z1: Approved Date | AA1: Code Review Comments, if any2 | AB1: Internal PO -POV Comments | AC1: Client PO -POV Comments | AD1: Comments
A2: 1 | B2: =Dashboard!$J$1 -> MSB Dev | C2: 46003 | D2: 46030 | E2: 26.1 DS Sprint 3 | F2: Mahesh | G2: 50490 | H2: MobilePay - API - POST Receipt - Add standard detailed response | I2: Story Completed | J2: 1 | K2: 1 | L2: 4 | M2: 46000 | N2: 46000 | O2: Manual (TestCases-5) | P2: Prisla | Q2: None | R2: Prisla | S2: No Comments | T2: https://dev.azure.com/heartlandschools/MySchoolBucks/_git/SchoolBucks/pullrequest/46127 | U2: 46000 | V2: Prisla | W2: 46001 | X2: No Comments | Y2: Ken | Z2: 46001 | AA2: No Comments | AB2: No Comments | AC2: No Comments | AD2: The development was completed in the last sprint, but since it was a stretch story, it has been carried over to this sprint for testing purposes only. Time Entries: Nithish: 4hrs
A3: 2 | B3: =Dashboard!$J$1 -> MSB Dev | C3: 46003 | D3: 46030 | E3: 26.1 DS Sprint 3 | F3: Mahesh | G3: 50779 | H3: [WAVE] MSB - REST API - Create District (Onboarding) [26.3] (Dev Only) | I3: Story Completed | J3: 5 | K3: 13.25 | L3: 53 | M3: 46003 | N3: 46014 | O3: Manual (TestCases-50) | P3: Nivetha | Q3: None | R3: Nivetha | S3: No Comments | T3: https://dev.azure.com/heartlandschools/MySchoolBucks/_git/SchoolBucks/pullrequest/46346 | U3: 46014 | V3: Prisla | W3: 46015 | X3: No Comments | Y3: Geroge | Z3: 46021 | AA3: create a user log for the attempt to create a district | AB3: No Comments | AC3: No Comments | AD3: Time was spent on analysis because many tasks are involved in creating a district, such as updating data in the primary and tenant databases, updating the UserHub, and initiating the core data. There are also issues faced while updating the UserHub. Time Entries: Mahesh: 48hrs Nithish: 2hrs Prisla: 3hrs
A4: 3 | B4: =Dashboard!$J$1 -> MSB Dev | C4: 46003 | D4: 46030 | E4: 26.1 DS Sprint 3 | F4: Nivetha | G4: 51154 | H4: [WAVE] MSB - Developer Accounts - Add Paging Options to View More Than 50 Records per Page | I4: Story Completed | J4: 2 | K4: 6 | L4: 24.5 | M4: 46007 | N4: 46010 | O4: Manual (TestCases-12) | P4: Mahesh | Q4: 1. Grid column order | R4: Mahesh | S4: No Comments | T4: https://dev.azure.com/heartlandschools/MySchoolBucks/_git/SchoolBucks/pullrequest/46317 | U4: 46010 | V4: Prisla | W4: 46014 | X4: No Comments | Y4: George | Z4: 46021 | AA4: No Comments | AB4: No Comments | AC4: No Comments | AD4: The actual implementation has lot of scenarios to cover, so it took additional time. Time Entries: Nivetha: 18hrs Nithish: 4hrs Prisla: 2.5hrs
A5: 4 | B5: =Dashboard!$J$1 -> MSB Dev | C5: 46003 | D5: 46030 | E5: 26.1 DS Sprint 3 | F5: Nivetha | G5: 51155 | H5: [WAVE] MSB - Developer Accounts – Add or Edit – Make Integrated Application Field Required | I5: Story Completed | J5: 1 | K5: 1 | L5: 4.5 | M5: 46007 | N5: 46007 | O5: Manual (TestCases-4) | P5: Mahesh | Q5: None | R5: Mahesh | S5: No Comments | T5: https://dev.azure.com/heartlandschools/MySchoolBucks/_git/SchoolBucks/pullrequest/46237 | U5: 46007 | V5: Prisla | W5: 46007 | X5: No Comments | Y5: George | Z5: 46007 | AA5: No Comments | AB5: Integration should be updated as Integrated in error msg | AC5: No Comments | AD5: Time Entries: Nivetha: 2hrs Nithish: 1hrs Prisla: 1.5hrs
A6: 5 | B6: =Dashboard!$J$1 -> MSB Dev | C6: 46003 | D6: 46030 | E6: 26.1 DS Sprint 3 | F6: Nivetha | G6: 51208 | H6: MSB - Partner Integrations - New Automation [26.1] | I6: Story Completed | J6: 5 | K6: 25 | L6: 150 | M6: 46013 | N6: 46030 | O6: NA | P6: Mahesh | Q6: None | R6: Mahesh | S6: No Comments | T6: https://dev.azure.com/heartlandschools/MySchoolBucks/_git/MSBAutomation/pullrequest/46365 https://dev.azure.com/heartlandschools/MySchoolBucks/_git/MSBAutomation/pullrequest/46404 https://dev.azure.com/heartlandschools/MySchoolBucks/_git/MSBAutomation/pullrequest/46415 https://dev.azure.com/heartlandschools/MySchoolBucks/_git/MSBAutomation/pullrequest/46446 | U6: 46027 | V6: Prisla | W6: 46029 | X6: No Comments | Y6: Ken | Z6: 46029 | AA6: No Comments | AB6: NA | AC6: NA | AD6: It is a common story for new automation. We covered multiple functional stories, but we are mainly facing issues with automation execution, and because of these issues, we have been delayed in completing the automation. Time Entries: Nivetha: 72hrs Mahesh: 54hrs Prisla: 24hrs
A7: 6 | B7: =Dashboard!$J$1 -> MSB Dev | C7: 46003 | D7: 46030 | E7: 26.1 DS Sprint 3 | F7: Nithish | G7: 51213 | H7: MSB - Partner Integrations - Regression [26.1] | I7: Story Completed | J7: 13 | K7: 14 | L7: 56 | M7: NA | N7: NA | O7: NA | P7: NA | Q7: NA | R7: NA | S7: NA | T7: NA | U7: NA | V7: NA | W7: NA | X7: NA | Y7: NA | Z7: NA | AA7: NA | AB7: NA | AC7: NA | AD7: Added only for testing purpose Time Entries: Nithish: 56hrs
A8: 7 | B8: =Dashboard!$J$1 -> MSB Dev | C8: 46003 | D8: 46030 | E8: 26.1 DS Sprint 3 | F8: Prisla | G8: 51245 | H8: MSB - REST API - Allow POST invoice for non-students using Additional Email field (Activities) | I8: Story Completed | J8: 1 | K8: 1 | L8: 5 | M8: 46003 | N8: 46003 | O8: Manual (TestCases-4) | P8: Mahesh | Q8: None | R8: Mahesh | S8: No Comments | T8: https://dev.azure.com/heartlandschools/MySchoolBucks/_git/SchoolBucks/pullrequest/46203 | U8: 46003 | V8: Ken | W8: 46007 | X8: No Comments | Y8: NA | Z8: NA | AA8: NA | AB8: No Comments | AC8: No Comments | AD8: Time Entries: Nithish: 3hrs Prisla: 2hrs
A9: 8 | B9: =Dashboard!$J$1 -> MSB Dev | C9: 46003 | D9: 46030
A10: 9 | B10: =Dashboard!$J$1 -> MSB Dev | C10: 46003 | D10: 46030
A11: 10 | B11: =Dashboard!$J$1 -> MSB Dev | C11: 46003 | D11: 46030

Sheet 26.1 DS Sprint 3-Defect
A1: S.No | B1: Sprint # | C1: Story/Defect ID | D1: Parent Story | E1: Developer | F1: Issue Type | G1: Issue Description | H1: Priority | I1: Defect Source | J1: Type | K1: Status | L1: Root Cause Category | M1: Comments
B2: 26.1 DS Sprint 3

Sheet 26.1 DS Sprint 2-Status
A1: S.No | B1: Application Name | C1: Sprint Start Date | D1: Sprint End Date | E1: Sprint | F1: Developer | G1: Story ID/Defect ID | H1: Description | I1: Status | J1: Estimated(hrs/sp) | K1: Actual(hrs/sp) | L1: Actual Hours Worklog | M1: Dev start date | N1: Dev end date | O1: Unit testing | P1: Peer Tested By | Q1: Peer Tested Defects, if any | R1: Peer Reviewed By | S1: Peer Code Review Comments, if any | T1: PR Number/Link | U1: PR Created Date | V1: Reviewer 1 | W1: PR Approved Date | X1: Code Review Comments, if any | Y1: Reviewer 2 | Z1: Approved Date | AA1: Code Review Comments, if any2 | AB1: Internal PO -POV Comments | AC1: Client PO -POV Comments | AD1: Comments
A2: 1 | B2: =Dashboard!$J$1 -> MSB Dev | C2: 45993 | D2: 46002 | E2: 26.1 DS Sprint 2 | F2: Mahesh | G2: 50021 | H2: Datahub - Syncs - Move sync calls from Agents to Query Agents (Schools, Students, Contacts) PERFORMANCE | I2: Story Completed | J2: 2 | K2: 3 | L2: 12 | M2: 45993 | N2: 45993 | O2: Manual (TestCases-10) | P2: Prisla | Q2: None | R2: Prisla | S2: No Comments | T2: https://dev.azure.com/heartlandschools/MySchoolBucks/_git/SchoolBucks/pullrequest/46005 | U2: 45993 | V2: Prisla | W2: 45993 | X2: No Comments | Y2: Ken | Z2: 45993 | AA2: 1. Change getPrimaryConnection to getReadOnlyPrimaryConnection | AB2: NA | AC2: NA | AD2: Unit testing took time because each sync required 10 minutes, and covering all scenarios needed multiple syncs Time Entries: Mahesh: 6hrs Prisla: 2hrs Nithish: 4hrs
A3: 2 | B3: =Dashboard!$J$1 -> MSB Dev | C3: 45993 | D3: 46002 | E3: 26.1 DS Sprint 2 | F3: Mahesh | G3: 50604 | H3: MSBA - API - Add preview & checkout controls for store products | I3: Story Completed | J3: 3 | K3: 4 | L3: 16 | M3: 45994 | N3: 45994 | O3: Manual (TestCases-10) | P3: Nivetha | Q3: None | R3: Nivetha | S3: No Comments | T3: https://dev.azure.com/heartlandschools/MySchoolBucks/_git/SchoolBucks/pullrequest/46032 | U3: 45994 | V3: Prisla | W3: 45995 | X3: No Comments | Y3: Ken | Z3: 45995 | AA3: No Comments | AB3: No Comments | AC3: No Comments | AD3: Unit testing took time because multiple scenarios need to cover Time Entries: Mahesh: 12hrs Prisla: 1hrs Nithish: 3hrs
A4: 3 | B4: =Dashboard!$J$1 -> MSB Dev | C4: 45993 | D4: 46002 | E4: 26.1 DS Sprint 2 | F4: Mahesh | G4: 50963 | H4: MSB - Checkout API - Add order model to Cart Process response (Tickets) | I4: Story Completed | J4: 3 | K4: 3 | L4: 13 | M4: 45995 | N4: 45996 | O4: Manual (TestCases-4) | P4: Nivetha | Q4: None | R4: Nivetha | S4: No Comments | T4: https://dev.azure.com/heartlandschools/MySchoolBucks/_git/SchoolBucks/pullrequest/46075 | U4: 45996 | V4: George | W4: 45997 | X4: No Comments | Y4: NA | Z4: NA | AA4: NA | AB4: No Comments | AC4: No Comments | AD4: Time Entries: Mahesh: 3hrs Prisla: 1hrs Nithish: 9hrs
A5: 4 | B5: =Dashboard!$J$1 -> MSB Dev | C5: 45993 | D5: 46002 | E5: 26.1 DS Sprint 2 | F5: Mahesh | G5: 49780 | H5: Datahub - Payments - Auto confirm payments without matching fees in provider | I5: Story Completed | J5: 1 | K5: 1 | L5: 4 | M5: 45986 | N5: 45987 | O5: Manual (TestCases-4) | P5: Nivetha | Q5: None | R5: Nivetha | S5: No Comments | T5: https://dev.azure.com/heartlandschools/MySchoolBucks/_git/SchoolBucks/pullrequest/45943 | U5: 45987 | V5: Prisla | W5: 45987 | X5: No Comments | Y5: George | Z5: 45989 | AA5: No Comments | AB5: No Comments | AC5: No Comments | AD5: The development was completed in the last sprint, but since it was a stretch story, it has been carried over to this sprint for testing purposes only. Time Entries: Nithish: 4hrs
A6: 5 | B6: =Dashboard!$J$1 -> MSB Dev | C6: 45993 | D6: 46002 | E6: 26.1 DS Sprint 2 | F6: Nivetha | G6: 32637 | H6: MobilePay - API - update tokenAuth user logging to indicate re-auth different from actual login | I6: Story Completed | J6: 2 | K6: 3 | L6: 12 | M6: 45993 | N6: 45994 | O6: Manual (TestCases-4) | P6: Mahesh | Q6: None | R6: Mahesh | S6: No Comments | T6: https://dev.azure.com/heartlandschools/MySchoolBucks/_git/SchoolBucks/pullrequest/46038 | U6: 45994 | V6: Prisla | W6: 45995 | X6: No Comments | Y6: Ken | Z6: 45995 | AA6: No Comments | AB6: No Comments | AC6: No Comments | AD6: I faced some local environment issue, which was resolved 2 days later, so it increased the time log. Time Entries: Nivetha: 9hrs Prisla: 1hrs Nithish: 2hrs
A7: 6 | B7: =Dashboard!$J$1 -> MSB Dev | C7: 45993 | D7: 46002 | E7: 26.1 DS Sprint 2 | F7: Nivetha | G7: 50788 | H7: MSB - Checkout API - Process Cart - Add Gateway DBA name to response (Destiny Fundraising Mgr) | I7: Story Completed | J7: 2 | K7: 3 | L7: 12.5 | M7: 45994 | N7: 45995 | O7: Manual (TestCases-3) | P7: Prisla | Q7: None | R7: Prisla | S7: No Comments | T7: https://dev.azure.com/heartlandschools/MySchoolBucks/_git/SchoolBucks/pullrequest/46054 | U7: 45995 | V7: Prisla | W7: 45995 | X7: No Comments | Y7: Ken | Z7: 45996 | AA7: 1. Consider passing a flag on what message to use, or that the locale == null as it is only passed from Pay API | AB7: No Comments | AC7: No Comments | AD7: Time Entries: Nivetha: 7hrs Prisla: 2hrs Nithish: 3.5hrs
A8: 7 | B8: =Dashboard!$J$1 -> MSB Dev | C8: 45993 | D8: 46002 | E8: 26.1 DS Sprint 2 Stretch | F8: Prisla | G8: 50022 | H8: Datahub - Syncs - Move sync calls from Agents to Query Agents (Rostering) PERFORMANCE | I8: Story Completed | J8: 3 | K8: 3 | L8: 12 | M8: 45994 | N8: 45994 | O8: Manual (TestCases-10) | P8: Mahesh | Q8: None | R8: Mahesh | S8: No Comments | T8: https://dev.azure.com/heartlandschools/MySchoolBucks/_git/SchoolBucks/pullrequest/46049 | U8: 45994 | V8: Ken | W8: 45995 | X8: 1. Change getPrimaryConnection to getReadOnlyPrimaryConnection | Y8: NA | Z8: NA | AA8: NA | AB8: NA | AC8: NA | AD8: Time Entries: Prisla: 7hrs Nithish: 5hrs
A9: 8 | B9: =Dashboard!$J$1 -> MSB Dev | C9: 45993 | D9: 46002 | E9: 26.1 DS Sprint 2 Stretch | F9: Nivetha | G9: 50023 | H9: Datahub - Syncs - Move sync calls from Agents to Query Agents (Fees & Meals) PERFORMANCE | I9: Story Completed | J9: 3 | K9: 3 | L9: 15.5 | M9: 45995 | N9: 45996 | O9: Manual (TestCases-3) | P9: Mahesh | Q9: None | R9: Mahesh | S9: No Comments | T9: https://dev.azure.com/heartlandschools/MySchoolBucks/_git/SchoolBucks/pullrequest/46078 | U9: 45996 | V9: Prisla | W9: 45996 | X9: No Comments | Y9: Ken | Z9: 45996 | AA9: No Comments | AB9: NA | AC9: NA | AD9: Time Entries: Nivetha: 7hrs Prisla: 1hrs Nithish: 7.5hrs
A10: 9 | B10: =Dashboard!$J$1 -> MSB Dev | C10: 45993 | D10: 46002 | E10: 26.1 DS Sprint 2 Stretch | F10: Nivetha | G10: 49972 | H10: UserHub - Identity Providers - Remember search filters | I10: Story Completed | J10: 2 | K10: 2 | L10: 9 | M10: 45999 | N10: 45999 | O10: Manual (TestCases-5) | P10: Mahesh | Q10: None | R10: Mahesh | S10: No Comments | T10: https://dev.azure.com/heartlandschools/MySchoolBucks/_git/SchoolBucks/pullrequest/46098 | U10: 45999 | V10: Prisla | W10: 46000 | X10: No Comments | Y10: Ken | Z10: 46000 | AA10: No Comments | AB10: No Comments | AC10: No Comments | AD10: Time Entries: Nivetha: 7hrs Prisla: 1hrs Nithish: 1hrs
A11: 10 | B11: =Dashboard!$J$1 -> MSB Dev | C11: 45993 | D11: 46002 | E11: 26.1 DS Sprint 2 Stretch | F11: Mahesh | G11: 51152 | H11: MSB - Checkout API - Add order model to Cart Process response- Automation [20.1] | I11: Story Completed | J11: 1 | K11: 1.5 | L11: 6 | M11: 45999 | N11: 45999 | O11: NA | P11: Prisla | Q11: None | R11: Prisla | S11: No Comments | T11: https://dev.azure.com/heartlandschools/MySchoolBucks/_git/MSBAutomation/pullrequest/46104 | U11: 45999 | V11: Prisla | W11: 45999 | X11: No Comments | Y11: Ken | Z11: 45999 | AA11: No Comments | AB11: NA | AC11: NA | AD11: Time Entries: Mahesh: 6hrs
A12: 11 | B12: =Dashboard!$J$1 -> MSB Dev | C12: 45993 | D12: 46002 | E12: 26.1 DS Sprint 2 Stretch | F12: Mahesh | G12: 50490 | H12: MobilePay - API - POST Receipt - Add standard detailed response | I12: Story Being Tested | J12: 3 | M12: 46000 | N12: 46000 | O12: Manual (TestCases-5) | P12: Prisla | Q12: None | R12: Prisla | S12: No Comments | T12: https://dev.azure.com/heartlandschools/MySchoolBucks/_git/SchoolBucks/pullrequest/46127 | U12: 46000 | V12: Prisla | W12: 46001 | X12: No Comments | Y12: Ken | Z12: 46001 | AA12: No Comments | AB12: No Comments | AC12: No Comments
A13: 12 | B13: =Dashboard!$J$1 -> MSB Dev | C13: 45993 | D13: 46002 | E13: 26.1 DS Sprint 2 Stretch | F13: Alex | G13: 50737 | H13: MSB - Checkout API - Resolve Create cart slowness (Destiny Fundraising Mgr) (Timeboxed) | I13: Story Completed | J13: 5 | K13: 2 | L13: 8.5 | M13: NA | N13: NA | O13: NA | P13: NA | Q13: NA | R13: NA | S13: NA | T13: NA | U13: NA | V13: NA | W13: NA | X13: NA | Y13: NA | Z13: NA | AA13: NA | AB13: NA | AC13: NA | AD13: Client developed this story and added only for testing purpose Time Entries: Alex: 5hrs Matthew: 1hrs Nithish: 2.5hrs

Sheet 26.1 DS Sprint 2-Defect
A1: S.No | B1: Sprint # | C1: Story/Defect ID | D1: Parent Story | E1: Developer | F1: Issue Type | G1: Issue Description | H1: Priority | I1: Defect Source | J1: Type | K1: Status | L1: Root Cause Category | M1: Comments
B2: 26.1 DS Sprint 2

Sheet 26.1 DS Sprint 1-Status
A1: S.No | B1: Application Name | C1: Sprint Start Date | D1: Sprint End Date | E1: Sprint | F1: Developer | G1: Story ID/Defect ID | H1: Description | I1: Status | J1: Estimated(hrs/sp) | K1: Actual(hrs/sp) | L1: Actual Hours Worklog | M1: Dev start date | N1: Dev end date | O1: Unit testing | P1: Peer Tested By | Q1: Peer Tested Defects, if any | R1: Peer Reviewed By | S1: Peer Code Review Comments, if any | T1: PR Number/Link | U1: PR Created Date | V1: Reviewer 1 | W1: PR Approved Date | X1: Code Review Comments, if any | Y1: Reviewer 2 | Z1: Approved Date | AA1: Code Review Comments, if any2 | AB1: Internal PO -POV Comments | AC1: Client PO -POV Comments | AD1: Comments
A2: 1 | B2: =Dashboard!$J$1 -> MSB Dev | C2: 45975 | D2: 45992 | E2: 26.1 DS Sprint 1 | F2: Nivetha | G2: 26161 | H2: MSB - REST API - Get payments - using param PaymentType=All will not return payments | I2: Defect Fixed | J2: 1 | K2: 2.75 | L2: 11 | M2: 45975 | N2: 45975 | O2: Manual (TestCases-4) | P2: Mahesh | Q2: None | R2: Mahesh | S2: No Comments | T2: https://dev.azure.com/heartlandschools/MySchoolBucks/_git/SchoolBucks/pullrequest/45725 | U2: 45975 | V2: Prisla | W2: 45979 | X2: No Comments | Y2: Ken | Z2: 45979 | AA2: No Comments | AB2: NA | AC2: No Comments | AD2: AC got updated, so it took additional time to complete. Time Entries: Nivetha: 6hrs Nithish: 4hrs Prisla: 1hrs
A3: 2 | B3: =Dashboard!$J$1 -> MSB Dev | C3: 45975 | D3: 45992 | E3: 26.1 DS Sprint 1 | F3: Nivetha | G3: 50283 | H3: MSBP - API - Get full mark up for Messages/Announcements | I3: Story Completed | J3: 3 | K3: 4.25 | L3: 17 | M3: 45978 | N3: 45979 | O3: Manual (TestCases-10) | P3: Prisla | Q3: None | R3: Mahesh | S3: No Comments | T3: https://dev.azure.com/heartlandschools/MySchoolBucks/_git/SchoolBucks/pullrequest/45811 | U3: 45980 | V3: Prisla | W3: 45981 | X3: 1.Add a comment why the same value is set but html tags are trimmed for message content and not for the markup attribute 2.Add comment what is the use of this new attribute | Y3: Michael | Z3: 45981 | AA3: No Comments | AB3: No Comments | AC3: No Comments | AD3: Time Entries: Nivetha: 12hrs Prisla: 3hrs Nithish: 2hrs
A4: 3 | B4: =Dashboard!$J$1 -> MSB Dev | C4: 45975 | D4: 45992 | E4: 26.1 DS Sprint 1 | F4: Nivetha | G4: 50716 | H4: Datahub - Student Enrollments - Show & return primary school enrollments first in UI and API response (Mosaic) | I4: Story Completed | J4: 3 | K4: 5 | L4: 20 | M4: 45980 | N4: 45981 | O4: Manual (TestCases-15) | P4: Mahesh | Q4: None | R4: Mahesh | S4: No Comments | T4: https://dev.azure.com/heartlandschools/MySchoolBucks/_git/SchoolBucks/pullrequest/45830 | U4: 45980 | V4: Prisla | W4: 45981 | X4: No Comments | Y4: Ken | Z4: 45981 | AA4: No Comments | AB4: No Comments | AC4: No Comments | AD4: It has 7 endpoints to cover and testing effort has increased the time. Time Entries: Nivetha: 12hrs Prisla: 2hrs Nithish: 6hrs
A5: 4 | B5: =Dashboard!$J$1 -> MSB Dev | C5: 45975 | D5: 45992 | E5: 26.1 DS Sprint 1 | F5: Prisla | G5: 50661 | H5: MSB - Checkout API - GET Payment Methods - Only return eligible records | I5: Story Completed | J5: 1 | K5: 1 | L5: 4 | M5: 45975 | N5: 45975 | O5: Manual (TestCases-4) | P5: Mahesh | Q5: None | R5: Mahesh | S5: No Comments | T5: https://dev.azure.com/heartlandschools/MySchoolBucks/_git/SchoolBucks/pullrequest/45711 | U5: 45975 | V5: Mahesh | W5: 45979 | X5: No Comments | Y5: Ken | Z5: 45979 | AA5: No Comments | AB5: NA | AC5: No Comments | AD5: Time Entries: Prisla: 2hrs Nithish: 2hrs
A6: 5 | B6: =Dashboard!$J$1 -> MSB Dev | C6: 45975 | D6: 45992 | E6: 26.1 DS Sprint 1 | F6: Prisla | G6: 26160 | H6: MSB - Developer Portal - MSB Checkout Swagger page - running GET GL Accounts from page returns error | I6: Defect Fixed | J6: 1 | K6: 1 | L6: 4 | M6: 45975 | N6: 45975 | O6: Manual (TestCases-4) | P6: Mahesh | Q6: None | R6: Mahesh | S6: No Comments | T6: https://dev.azure.com/heartlandschools/MySchoolBucks/_git/SchoolBucks/pullrequest/45710 | U6: 45975 | V6: Mahesh | W6: 45979 | X6: No Comments | Y6: Ken | Z6: 45979 | AA6: No Comments | AB6: NA | AC6: NA | AD6: Time Entries: Prisla: 2hrs Nithish: 2hrs
A7: 6 | B7: =Dashboard!$J$1 -> MSB Dev | C7: 45975 | D7: 45992 | E7: 26.1 DS Sprint 1 | F7: Mahesh | G7: 26314 | H7: DH - Infinite Campus OR - Enrollment sync creating duplicate records on every sync instead of ignoring existing ones | I7: Defect Rejected | J7: 3 | K7: 5.75 | L7: 23 | M7: 45981 | N7: 45985 | O7: NA | P7: NA | Q7: NA | R7: NA | S7: NA | T7: NA | U7: NA | V7: NA | W7: NA | X7: NA | Y7: NA | Z7: NA | AA7: NA | AB7: NA | AC7: NA | AD7: Upon investigation, I identified a data issue: a student had duplicate class enrollments within the same school. I documented the defect with comments and also explained it to QA. Time Entries: Mahesh: 21hrs Prisla: 2hrs
A8: 7 | B8: =Dashboard!$J$1 -> MSB Dev | C8: 45975 | D8: 45992 | E8: 26.1 DS Sprint 1 Stretch | F8: Prisla | G8: 50787 | H8: MSB - Checkout API - GET GL Accounts - Add GL Account Code to response (Destiny Fundraising Mgr) | I8: Story Completed | J8: 2 | K8: 2.5 | L8: 10 | M8: 45979 | N8: 45979 | O8: Manual (TestCases-2) | P8: Nivetha | Q8: None | R8: Nivetha | S8: No Comments | T8: https://dev.azure.com/heartlandschools/MySchoolBucks/_git/SchoolBucks/pullrequest/45804 | U8: 45979 | V8: Nivetha | W8: 45980 | X8: No Comments | Y8: Michael | Z8: 45980 | AA8: No Comments | AB8: No Comments | AC8: No Comments | AD8: Time Entries: Prisla: 6hrs Nithish: 2hrs
A9: 8 | B9: =Dashboard!$J$1 -> MSB Dev | C9: 45975 | D9: 45992 | E9: 26.1 DS Sprint 1 Stretch | F9: Prisla | G9: 26350 | H9: MSB - REST API - Collection Missing Parameters in GET Payment Count, GET Payment Count with Provider, and GET Payments with Provider | I9: Defect Fixed | J9: 2 | K9: 3.5 | L9: 14 | M9: 45981 | N9: 45981 | O9: Manual (TestCases-2) | P9: Nivetha | Q9: None | R9: Nivetha | S9: No Comments | T9: https://dev.azure.com/heartlandschools/MySchoolBucks/_git/SchoolBucks/pullrequest/45854 | U9: 45981 | V9: Mahesh | W9: 45982 | X9: No Comments | Y9: Ken | Z9: 45982 | AA9: No Comments | AB9: NA | AC9: NA | AD9: Time Entries: Prisla: 2hrs Nithish: 12hrs
A10: 9 | B10: =Dashboard!$J$1 -> MSB Dev | C10: 45975 | D10: 45992 | E10: 26.1 DS Sprint 1 Stretch | F10: Nivetha | G10: 50707 | H10: MSB - REST API - GET/POST/PUT GL Accounts - Support Store availability (Store Agent) | I10: Story Completed | J10: 5 | K10: 6.5 | L10: 26 | M10: 45982 | N10: 45985 | O10: Manual (TestCases-20) | P10: Mahesh | Q10: None | R10: Mahesh | S10: No Comments | T10: https://dev.azure.com/heartlandschools/MySchoolBucks/_git/SchoolBucks/pullrequest/45919 | U10: 45986 | V10: Prisla | W10: 45987 | X10: 1. add comments and method doc comments | Y10: George | Z10: 45987 | AA10: No Comments | AB10: No Comments | AC10: No Comments | AD10: Time Entries: Nivetha: 15hrs Prisla: 3hrs Nithish: 6hrs
A11: 10 | B11: =Dashboard!$J$1 -> MSB Dev | C11: 45975 | D11: 45992 | E11: 26.1 DS Sprint 1 Stretch | F11: Mahesh | G11: 49780 | H11: Datahub - Payments - Auto confirm payments without matching fees in provider | I11: Story Being Tested | J11: 1 | M11: 45986 | N11: 45987 | O11: Manual (TestCases-4) | P11: Nivetha | Q11: None | R11: Nivetha | S11: No Comments | T11: https://dev.azure.com/heartlandschools/MySchoolBucks/_git/SchoolBucks/pullrequest/45943 | U11: 45987 | V11: Prisla | W11: 45987 | X11: No Comments | Y11: George | Z11: 45989 | AA11: No Comments | AB11: No Comments | AC11: No Comments | AD11: TIme Entries: Mahesh: 6hrs Prisla: 1hrs Nithish: 4hrs
A12: 11 | B12: =Dashboard!$J$1 -> MSB Dev | C12: 45975 | D12: 45992 | E12: 26.1 DS Sprint 1 Stretch | F12: Nivetha | G12: 32637 | H12: MobilePay - API - update tokenAuth user logging to indicate re-auth different from actual login | I12: Story Being Developed | J12: 3 | M12: 45988 | AD12: Time Entries: Nivetha: 12hrs Prisla: 1hrs
A13: 12 | B13: =Dashboard!$J$1 -> MSB Dev | C13: 45975 | D13: 45992 | E13: 26.1 DS Sprint 1 Stretch | F13: Mahesh | G13: 50021 | H13: Datahub - Syncs - Move sync calls from Agents to Query Agents (Schools, Students, Contacts) PERFORMANCE | I13: Story Being Developed | J13: 3 | M13: 45988 | AD13: Time Entries: Mahesh: 12hrs Nithish: 2hrs

Sheet 26.1 DS Sprint 1-Defect
A1: S.No | B1: Sprint # | C1: Story/Defect ID | D1: Parent Story | E1: Developer | F1: Issue Type | G1: Issue Description | H1: Priority | I1: Defect Source | J1: Type | K1: Status | L1: Root Cause Category | M1: Comments
B2: 26.1 DS Sprint 1 | C2: 26160 | E2: Prisla | F2: Defect | G2: MSB - Developer Portal - MSB Checkout Swagger page - running GET GL Accounts from page returns error | H2: Minor | I2: Manual | J2: External | K2: Closed | L2: Existing_Issues | M2: Msb Pay api swagger - Execute GET GL Accounts return error instead shown proper response
B3: 26.1 DS Sprint 1 | C3: 26161 | E3: Nivetha | F3: Defect | G3: MSB - REST API - Get payments - using param PaymentType=All will not return payments | H3: Minor | I3: Manual | J3: External | K3: Closed | L3: Existing_Issues | M3: Rest Api - Run get payments - using param PaymentType=All retrun empty response
B4: 26.1 DS Sprint 1 | C4: 26314 | E4: Mahesh | F4: Defect | G4: DH - Infinite Campus OR - Enrollment sync creating duplicate records on every sync instead of ignoring existing ones | H4: Minor | I4: Manual | J4: Internal | K4: Closed | L4: Existing_Issues | M4: Upon investigation, Identified a data issue and rejected the defect
B5: 26.1 DS Sprint 1 Stretch | C5: 26350 | E5: Prisla | F5: Defect | G5: MSB - REST API - Collection Missing Parameters in GET Payment Count, GET Payment Count with Provider, and GET Payments with Provider | H5: Minor | I5: Manual | J5: Internal | K5: Closed | L5: Existing_Issues | M5: Existing Issue identified while testing defect : 26161
B6: 26.1 DS Sprint 1 Stretch | C6: 26350 | E6: Prisla | F6: Bounceback | G6: storeIdExclude & providerIdExclude missing in GET Payment Count swagger | H6: Minor | I6: Manual | J6: Internal | K6: Closed | L6: Development | M6: Missed to include storeIdExclude & providerIdExclude GET Payment Count Swagger

Sheet 15.3 DS Sprint 3-Status
A1: S.No | B1: Application Name | C1: Sprint Start Date | D1: Sprint End Date | E1: Sprint | F1: Developer | G1: Story ID/Defect ID | H1: Description | I1: Status | J1: Estimated(hrs/sp) | K1: Actual(hrs/sp) | L1: Actual Hours Worklog | M1: Dev start date | N1: Dev end date | O1: Unit testing | P1: Peer Tested By | Q1: Peer Tested Defects, if any | R1: Peer Reviewed By | S1: Peer Code Review Comments, if any | T1: PR Number/Link | U1: PR Created Date | V1: Reviewer 1 | W1: PR Approved Date | X1: Code Review Comments, if any | Y1: Reviewer 2 | Z1: Approved Date | AA1: Code Review Comments, if any2 | AB1: Internal PO -POV Comments | AC1: Client PO -POV Comments | AD1: Comments
A2: 1 | B2: =Dashboard!$J$1 -> MSB Dev | C2: 45961 | D2: 45974 | E2: 15.3 DS Sprint 3 | F2: Nivetha | G2: 26220 | H2: DataHub - Aspen OneRoster - View Classes: Class ID (Decoded) value not displayed correctly | I2: Defect Fixed | J2: 1 | K2: 1 | L2: 4 | M2: 45960 | N2: 45960 | O2: Manual (TestCases-2) | P2: Prisla | Q2: None | R2: Mahesh | S2: No Comments | T2: https://dev.azure.com/heartlandschools/MySchoolBucks/_git/SchoolBucks/pullrequest/45385 | U2: 45960 | V2: Prisla | W2: 45960 | X2: No Comments | Y2: Alex | Z2: 45960 | AA2: 1.Add a comment about why we're not setting the key inline. | AB2: NA | AC2: NA | AD2: The development was completed in the last sprint, but since it was a stretch story, it has been carried over to this sprint for testing purposes only. Time Entries: Nithish: 4hrs
A3: 2 | B3: =Dashboard!$J$1 -> MSB Dev | C3: 45961 | D3: 45974 | E3: 15.3 DS Sprint 3 | F3: Nivetha | G3: 50643 | H3: MSB - Partner Integrations - New Automation [15.3] | I3: Story Completed | J3: 5 | K3: 21.5 | L3: 86 | M3: 45961 | N3: 45974 | O3: NA | P3: Mahesh | Q3: None | R3: Mahesh | S3: No Comments | T3: https://dev.azure.com/heartlandschools/MySchoolBucks/_git/MSBAutomation/pullrequest/45531 https://dev.azure.com/heartlandschools/MySchoolBucks/_git/MSBAutomation/pullrequest/45567 https://dev.azure.com/heartlandschools/MySchoolBucks/_git/MSBAutomation/pullrequest/45694 | U3: 45967 | V3: Prisla | W3: 45973 | X3: No Comments | Y3: Ken | Z3: 45974 | AA3: No Comments | AB3: NA | AC3: NA | AD3: One day was spent resolving the environment issue on Oct-31. Subsequently, we encountered automation test setup failures, which were fixed by the client on Nov-7. These issues due to recent changes made by Doug and it is one of the cause to the delay on complete. Time Entries: Nivetha: 54hrs Mahesh: 30hrs Prisla: 2hrs
A4: 3 | B4: =Dashboard!$J$1 -> MSB Dev | C4: 45961 | D4: 45974 | E4: 15.3 DS Sprint 3 | F4: Mahesh | G4: 50636 | H4: MSB - Partner Integrations - Automation Repair [15.3] | I4: Story Completed | J4: 8 | K4: 8.7 | L4: 35 | M4: 45961 | N4: 45974 | O4: NA | P4: Nivetha | Q4: None | R4: Nivetha | S4: No Comments | T4: https://dev.azure.com/heartlandschools/MySchoolBucks/_git/MSBAutomation/pullrequest/45639 | U4: 45973 | V4: Prisla | W4: 45973 | X4: No Comments | Y4: Ken | Z4: 45974 | AA4: No Comments | AB4: NA | AC4: NA | AD4: One day was spent resolving the environment issue on Oct-31. Subsequently, we encountered automation test setup failures, which were fixed by the client on Nov-7. These issues due to recent changes made by Doug and it is one of the cause to the delay on complete. Time Entries: Mahesh: 30hrs Prisla: 5hrs
A5: 4 | B5: =Dashboard!$J$1 -> MSB Dev | C5: 45961 | D5: 45974 | E5: 15.3 DS Sprint 3 | F5: Nithish | G5: 50634 | H5: MSB - Partner Integrations - Regression [15.3] | I5: Story Completed | J5: 13 | K5: 12.75 | L5: 51 | M5: NA | N5: NA | O5: NA | P5: NA | Q5: NA | R5: NA | S5: NA | T5: NA | U5: NA | V5: NA | W5: NA | X5: NA | Y5: NA | Z5: NA | AA5: NA | AB5: NA | AC5: NA | AD5: Testing Purpose Only Time Entries: Nithish: 51hrs
A6: 5 | B6: =Dashboard!$J$1 -> MSB Dev | C6: 45961 | D6: 45974 | E6: 15.3 DS Sprint 3 Stretch | F6: Prisla | G6: 26245 | H6: DataHub - Class Sync - DSL shows classKey value incorrectly (displayed as empty) | I6: Defect Fixed | J6: 2 | K6: 2 | L6: 9 | M6: 45964 | N6: 45964 | O6: Manual (TestCases-2) | P6: Mahesh | Q6: None | R6: Mahesh | S6: No Comments | T6: https://dev.azure.com/heartlandschools/MySchoolBucks/_git/SchoolBucks/pullrequest/45440 | U6: 45964 | V6: NA | W6: 45964 | X6: No Comments | Y6: Ken | Z6: 45964 | AA6: No Comments | AB6: NA | AC6: NA | AD6: Time Entries: Prisla: 4hrs Nithish: 5hrs
A7: 6 | B7: =Dashboard!$J$1 -> MSB Dev | C7: 45961 | D7: 45974
A8: 7 | B8: =Dashboard!$J$1 -> MSB Dev | C8: 45961 | D8: 45974
A9: 8 | B9: =Dashboard!$J$1 -> MSB Dev | C9: 45961 | D9: 45974
A10: 9 | B10: =Dashboard!$J$1 -> MSB Dev | C10: 45961 | D10: 45974
A11: 10 | B11: =Dashboard!$J$1 -> MSB Dev | C11: 45961 | D11: 45974

Sheet 15.3 DS Sprint 3-Defect
A1: S.No | B1: Sprint # | C1: Story/Defect ID | D1: Parent Story | E1: Developer | F1: Issue Type | G1: Issue Description | H1: Priority | I1: Defect Source | J1: Type | K1: Status | L1: Root Cause Category | M1: Comments
B2: 15.3 DS Sprint 3 | C2: 26220 | E2: Nivetha | F2: Defect | G2: DH - Aspen OneRoster - View Classes: Class ID (Decoded) value not displayed correctly | H2: Minor | I2: Manual | J2: Internal | K2: Closed | L2: Existing_Issues | M2: The Class ID (Decoded) value is displayed incorrectly. For example, in the view screen, it shows sklSI000000706, but in the class list screen, the Class ID (Decoded) is shown as MST000000WNph
B3: 15.3 DS Sprint 3 Stretch | C3: 26245 | E3: Prisla | F3: Defect | G3: DataHub - Class Sync - DSL shows classKey value incorrectly (displayed as empty) | H3: Minor | I3: Manual | J3: Internal | K3: Closed | L3: Existing_Issues | M3: All Adapter after class sync Class Key shown as empty in DSL
B4: 15.3 DS Sprint 3 Stretch | C4: 26245 | E4: Prisla | F4: Bounceback | G4: classKey value is displayed as empty for powerschool adapter | H4: Minor | I4: Manual | J4: Internal | K4: Closed | L4: Existing_Issues | M4: Missed to set class key in powerschool adapter

Sheet 15.3 DS Sprint 2-Status
A1: S.No | B1: Application Name | C1: Sprint Start Date | D1: Sprint End Date | E1: Sprint | F1: Developer | G1: Story ID/Defect ID | H1: Description | I1: Status | J1: Estimated(hrs/sp) | K1: Actual(hrs/sp) | L1: Actual Hours Worklog | M1: Dev start date | N1: Dev end date | O1: Unit testing | P1: Peer Tested By | Q1: Peer Tested Defects, if any | R1: Peer Reviewed By | S1: Peer Code Review Comments, if any | T1: PR Number/Link | U1: PR Created Date | V1: Reviewer 1 | W1: PR Approved Date | X1: Code Review Comments, if any | Y1: Reviewer 2 | Z1: Approved Date | AA1: Code Review Comments, if any2 | AB1: Internal PO -POV Comments | AC1: Client PO -POV Comments | AD1: Comments
A2: 1 | B2: =Dashboard!$J$1 -> MSB Dev | C2: 45947 | D2: 45960 | E2: 15.3 DS Sprint 2 | F2: Mahesh | G2: 50179 | H2: [WAVE] MSB - REST API – Invoicing documentation (DEV ONLY) | I2: Story Completed | J2: 2 | K2: 1.5 | L2: 6 | M2: 45947 | N2: 45947 | O2: NA | P2: NA | Q2: NA | R2: NA | S2: NA | T2: NA | U2: NA | V2: NA | W2: NA | X2: NA | Y2: NA | Z2: NA | AA2: NA | AB2: NA | AC2: NA | AD2: This story is intended for preparing the functionality documentation. The relevant document has also been attached to the same story. Time entries: Mahesh: 6hrs
A3: 2 | B3: =Dashboard!$J$1 -> MSB Dev | C3: 45947 | D3: 45960 | E3: 15.3 DS Sprint 2 | F3: Mahesh | G3: 25976 | H3: MSBA - API - Group filters not showing the products when particular category is selected | I3: Defect Rejected | J3: 5 | K3: 1.75 | L3: 7 | M3: 45947 | N3: 45947 | O3: NA | P3: NA | Q3: NA | R3: NA | S3: NA | T3: NA | U3: NA | V3: NA | W3: NA | X3: NA | Y3: NA | Z3: NA | AA3: NA | AB3: NA | AC3: NA | AD3: The issue could not be reproduced on Test env. This has been communicated to the Mobile team, and they have also confirmed that they were unable to reproduce the issue on their end Time Entries: Nithish: 5hrs Prisla: 2hrs
A4: 3 | B4: =Dashboard!$J$1 -> MSB Dev | C4: 45947 | D4: 45960 | E4: 15.3 DS Sprint 2 | F4: Mahesh | G4: 26140 | H4: MSBA - Students returning in the invoices tab when not have active invoices | I4: Defect Fixed | J4: 5 | K4: 8.25 | L4: 33 | M4: 45951 | N4: 45957 | O4: Manual (TestCases-25) | P4: Nivetha | Q4: None | R4: Nivetha | S4: No Comments | T4: https://dev.azure.com/heartlandschools/MySchoolBucks/_git/SchoolBucks/pullrequest/45300 | U4: 45957 | V4: Prisla | W4: 45957 | X4: No Comments | Y4: Alex | Z4: 45957 | AA4: No Comments | AB4: No Comments | AC4: No Comments | AD4: The scope of the defect was only to show pending status invoices but later PO asked to include the payable invoices and for this reason tooks extra time. Time Entries: Mahesh: 21hrs Nithish: 10hrs Prisla: 2hrs
A5: 4 | B5: =Dashboard!$J$1 -> MSB Dev | C5: 45947 | D5: 45960 | E5: 15.3 DS Sprint 2 | F5: Nivetha | G5: 50157 | H5: Datahub - Aspen OR - Change encoding for ID fields (Marblehead SD) | I5: Story Completed | J5: 5 | K5: 11 | L5: 44 | M5: 45947 | N5: 45957 | O5: Manual (TestCases-15) | P5: Mahesh | Q5: None | R5: Mahesh | S5: 1)Need to add loggers in new created method | T5: https://dev.azure.com/heartlandschools/MySchoolBucks/_git/SchoolBucks/pullrequest/45306 | U5: 45957 | V5: Prisla | W5: 45957 | X5: No Comments | Y5: Ken | Z5: 45959 | AA5: No Comments | AB5: No Comments | AC5: Replace = with _ for decoded ids | AD5: Initially we didn't have the connection details. Later got the credentials but the studentId with $ symbol issue which was mentioned in the AC is not reproduced. And after discussion with client, all ids should be encoded with Base32, then we faced = sign issue while inserting in DB. Discussed with client and AC got updated. Time Entries: Nivetha : 36 hrs Prisla: 5 hrs Nithish: 3 hrs
A6: 5 | B6: =Dashboard!$J$1 -> MSB Dev | C6: 45947 | D6: 45960 | E6: 15.3 DS Sprint 2 | F6: Prisla | G6: 26018 | H6: DataHub - MBA provider - fee attributes generated with spaces (Elmwood Park 401) | I6: Defect Fixed | J6: 1 | K6: 1 | L6: 5 | M6: 45952 | N6: 45952 | O6: Manual (TestCases-5) | P6: NA | Q6: NA | R6: Mahesh | S6: No Comments | T6: https://dev.azure.com/heartlandschools/MySchoolBucks/_git/SchoolBucks/pullrequest/45238 | U6: 45952 | V6: NA | W6: NA | X6: NA | Y6: George | Z6: 45953 | AA6: 1. Add proper JavaDoc explaining the method | AB6: NA | AC6: NA | AD6: Time Entries: Prisla: 1hrs Nithish: 4hrs
A7: 6 | B7: =Dashboard!$J$1 -> MSB Dev | C7: 45947 | D7: 45960 | E7: 15.3 DS Sprint 2 | F7: Mahesh | G7: 50383 | H7: PowerSchool 13 - provider - DH populating Inactive student contacts (Jenks PS, New Fairfield) | I7: Story Need More Info | J7: 3 | M7: 45957 | AD7: In the PS Contact API response, the end date was not provided. As a result, we couldn't exclude contacts without an end date. We informed the client about the same, and they are currently reviewing it.
A8: 7 | B8: =Dashboard!$J$1 -> MSB Dev | C8: 45947 | D8: 45960 | E8: 15.3 DS Sprint 2 Stretch | F8: Prisla | G8: 26233 | H8: MSBA - Checkout - Returns java.lang.NullPointerException when passing payment method type Cash, Check, or MoneyOrder. | I8: Defect Fixed | J8: 2 | K8: 2.5 | L8: 11 | M8: NA | N8: NA | O8: NA | P8: NA | Q8: NA | R8: NA | S8: NA | T8: NA | U8: NA | V8: NA | W8: NA | X8: NA | Y8: NA | Z8: NA | AA8: NA | AB8: NA | AC8: NA | AD8: Time Entries: Prisla: 3 hrs Nithish: 8 hrs
A9: 8 | B9: =Dashboard!$J$1 -> MSB Dev | C9: 45947 | D9: 45960 | E9: 15.3 DS Sprint 2 Stretch | F9: Nivetha | G9: 26220 | H9: DH - Aspen OneRoster - View Classes: Class ID (Decoded) value not displayed correctly | I9: Defect Peer Review | J9: 2 | M9: 45960 | N9: 45960 | O9: Manual (TestCases-2) | P9: Prisla | Q9: None | R9: Mahesh | S9: No Comments | T9: https://dev.azure.com/heartlandschools/MySchoolBucks/_git/SchoolBucks/pullrequest/45385 | U9: 45960 | V9: Prisla | W9: 45960 | X9: No Comments | Y9: Michael | Z9: 45960 | AA9: NA | AB9: NA | AC9: NA
A10: 9 | B10: =Dashboard!$J$1 -> MSB Dev | C10: 45947 | D10: 45960
A11: 10 | B11: =Dashboard!$J$1 -> MSB Dev | C11: 45947 | D11: 45960

Sheet 15.3 DS Sprint 2-Defect
A1: S.No | B1: Sprint # | C1: Story/Defect ID | D1: Parent Story | E1: Developer | F1: Issue Type | G1: Issue Description | H1: Priority | I1: Defect Source | J1: Type | K1: Status | L1: Root Cause Category | M1: Comments
B2: 15.3 DS Sprint 2 | C2: 26140 | E2: Mahesh | F2: Defect | G2: MSBA - Students returning in the invoices tab when not have active invoices | H2: Significant | I2: Manual | J2: External | K2: Closed | L2: Existing_Issues | M2: API response shown both closed and pending invoice instead of pending
B3: 15.3 DS Sprint 2 | C3: 25976 | E3: Mahesh | F3: Defect | G3: MSBA - API - Group filters not showing the products when particular category is selected | H3: Major | I3: Manual | J3: External | K3: Closed | L3: Existing_Issues | M3: The issue could not be reproduced on Test env. This has been communicated to the Mobile team, and they have also confirmed that they were unable to reproduce the issue on their end
B4: 15.3 DS Sprint 2 | C4: 26018 | E4: Prisla | F4: Defect | G4: DataHub - MBA provider - fee attributes generated with spaces (Elmwood Park 401) | H4: Minor | I4: Manual | J4: External | K4: Closed | L4: Existing_Issues | M4: There is a data issue where spaces are being replaced with underscores
B5: 15.3 DS Sprint 2 Stretch | C5: 26233 | E5: Prisla | F5: Defect | G5: MSBA - Checkout - Returns java.lang.NullPointerException when passing payment method type Cash, Check, or MoneyOrder. | H5: Significant | I5: Manual | J5: Internal | K5: Closed | L5: Development | M5: The client disrupted the existing checkout process during the wallet transaction.

Sheet 15.3 DS Sprint 1-Status
A1: S.No | B1: Application Name | C1: Sprint Start Date | D1: Sprint End Date | E1: Sprint | F1: Developer | G1: Story ID/Defect ID | H1: Description | I1: Status | J1: Estimated(hrs/sp) | K1: Actual(hrs/sp) | L1: Actual Hours Worklog | M1: Dev start date | N1: Dev end date | O1: Unit testing | P1: Peer Tested By | Q1: Peer Tested Defects, if any | R1: Peer Reviewed By | S1: Peer Code Review Comments, if any | T1: PR Number/Link | U1: PR Created Date | V1: Reviewer 1 | W1: PR Approved Date | X1: Code Review Comments, if any | Y1: Reviewer 2 | Z1: Approved Date | AA1: Code Review Comments, if any2 | AB1: Internal PO -POV Comments | AC1: Client PO -POV Comments | AD1: Comments
A2: 1 | B2: =Dashboard!$J$1 -> MSB Dev | C2: 45933 | D2: 45946 | E2: 15.3 DS Sprint 1 | F2: Mahesh | G2: 50051 | H2: MSBP - API - Write user log when Meals AutoPay is enabled/updated/disabled | I2: Story Completed | J2: 2 | K2: 2.75 | L2: 11 | M2: 45933 | N2: 45936 | O2: Manual (TestCases-8) | P2: Nivetha | Q2: None | R2: Nivetha | S2: No Comments | T2: https://dev.azure.com/heartlandschools/MySchoolBucks/_git/SchoolBucks/pullrequest/44963 | U2: 45936 | V2: Prisla | W2: 45937 | X2: No Comments | Y2: George | Z2: 45938 | AA2: Update the log pattern to (class).(method): (log content) | AB2: No Comments | AC2: No Comments | AD2: Time entries: Mahesh: 7hrs Nithish: 3hrs Prisla: 1hrs
A3: 2 | B3: =Dashboard!$J$1 -> MSB Dev | C3: 45933 | D3: 45946 | E3: 15.3 DS Sprint 1 | F3: Mahesh | G3: 50085 | H3: [WAVE] MSB - Payment Methods - Add payment method Alias for Real Time Fee mappings | I3: Story Completed | J3: 8 | K3: 14 | L3: 56.5 | M3: 45936 | N3: 45940 | O3: Manual (TestCases-8) | P3: Nivetha | Q3: None | R3: Nivetha | S3: No Comments | T3: https://dev.azure.com/heartlandschools/MySchoolBucks/_git/SchoolBucks/pullrequest/45066 | U3: 45940 | V3: Prisla | W3: 45943 | X3: No Comments | Y3: Ken | Z3: 45943 | AA3: No Comments | AB3: No Comments | AC3: No Comments | AD3: The story was a bit complex and it took time for analysis and getting clarification from the PO. Also QA spent more time. The story impacts the payment function model, so testing will take time to cover both web and API (Parent, Mobile, and REST) Time entries: Mahesh: 29hrs Nithish: 25.5hrs Prisla: 2hrs
A4: 3 | B4: =Dashboard!$J$1 -> MSB Dev | C4: 45933 | D4: 45946 | E4: 15.3 DS Sprint 1 | F4: Nivetha | G4: 49974 | H4: Datahub - Aeries - Support Student Number Source override option and State ID (Black Oak Mine USD) | I4: Story Completed | J4: 3 | K4: 6.5 | L4: 26 | M4: 45933 | N4: 45937 | O4: Manual (TestCases-6) | P4: Prisla | Q4: None | R4: Prisla | S4: No Comments | T4: https://dev.azure.com/heartlandschools/MySchoolBucks/_git/SchoolBucks/pullrequest/45018 | U4: 45938 | V4: Prisla | W4: 45938 | X4: No Comments | Y4: Ken | Z4: 45938 | AA4: No Comments | AB4: No Comments | AC4: No Comments | AD4: We environment issue and it was resolved a day after by ITOps and the AC was updated once, so it got delayed from the actual estimate Time entries: Nivetha: 18hrs Nithish: 5hrs Prisla: 3hrs
A5: 4 | B5: =Dashboard!$J$1 -> MSB Dev | C5: 45933 | D5: 45946 | E5: 15.3 DS Sprint 1 | F5: Nivetha | G5: 25828 | H5: Datahub - Skyward Q OneRoster - not all contacts are being populated (Middleton SD, ID) | I5: Defect Fixed | J5: 3 | K5: 6 | L5: 24 | M5: 45938 | N5: 45940 | O5: Manual (TestCases-5) | P5: Mahesh | Q5: None | R5: Mahesh | S5: No Comments | T5: https://dev.azure.com/heartlandschools/MySchoolBucks/_git/SchoolBucks/pullrequest/45036 | U5: 45939 | V5: NA | W5: NA | X5: NA | Y5: Ken | Z5: 45943 | AA5: No Comments | AB5: NA | AC5: NA | AD5: We couldn't establish a connection in local, so it was taken prisla. Time entries: Nivetha: 6hrs Nithish: 11.5hrs Prisla: 8hrs
A6: 5 | B6: =Dashboard!$J$1 -> MSB Dev | C6: 45933 | D6: 45946 | E6: 15.3 DS Sprint 1 | F6: Prisla | G6: 26018 | H6: DataHub - MBA provider - fee attributes generated with spaces (Elmwood Park 401) | I6: Product Owner - Verify | J6: 1 | M6: 45937 | N6: 45937 | O6: Manual (TestCases-5) | P6: Mahesh | Q6: None | R6: Mahesh | S6: No Comments | T6: https://dev.azure.com/heartlandschools/MySchoolBucks/_git/SchoolBucks/pullrequest/44997 | U6: 45937 | V6: NA | W6: NA | X6: NA | Y6: George | Z6: 45938 | AA6: No Comments | AB6: NA | AC6: NA | AD6: Development is completed. While testing, I faced a proxy connectivity failure and informed Carmin on October 10. She raised a ticket with PlatOps, but I still faced the same proxy failure afterward. Hence, I was unable to test, and there’s a chance it may be carried over to the next sprint.
A7: 6 | B7: =Dashboard!$J$1 -> MSB Dev | C7: 45933 | D7: 45946 | E7: 15.3 DS Sprint 1 Stretch | F7: Mahesh | G7: 50179 | H7: [WAVE] MSB - REST API – Invoicing documentation (DEV ONLY) | I7: Story Being Developed | J7: 3 | M7: 45943
A8: 7 | B8: =Dashboard!$J$1 -> MSB Dev | C8: 45933 | D8: 45946
A9: 8 | B9: =Dashboard!$J$1 -> MSB Dev | C9: 45933 | D9: 45946
A10: 9 | B10: =Dashboard!$J$1 -> MSB Dev | C10: 45933 | D10: 45946
A11: 10 | B11: =Dashboard!$J$1 -> MSB Dev | C11: 45933 | D11: 45946

Sheet 15.3 DS Sprint 1-Defect
A1: S.No | B1: Sprint # | C1: Story/Defect ID | D1: Parent Story | E1: Developer | F1: Issue Type | G1: Issue Description | H1: Priority | I1: Defect Source | J1: Type | K1: Status | L1: Root Cause Category | M1: Comments
B2: 15.3 DS Sprint 1 | C2: 25828 | E2: Nivetha | F2: Defect | G2: Datahub - Skyward Q OneRoster - not all contacts are being populated (Middleton SD, ID) | H2: Minor | I2: Manual | J2: External | K2: Closed | L2: Existing_Issues | M2: Skyward Q OneRoster contacts are not being created when running the contact sync from DH
B3: 15.3 DS Sprint 1 | C3: 26018 | E3: Prisla | F3: Defect | G3: DataHub - MBA provider - fee attributes generated with spaces (Elmwood Park 401) | H3: Minor | I3: Manual | J3: External | K3: Inprogress | L3: Existing_Issues | M3: Marcia Brenner fee attributes were created with spaces, making them unusable for GL account mapping. The spaces should be replaced with underscores
B4: 15.3 DS Sprint 1 | C4: 50085 | E4: Mahesh | F4: Bounceback | G4: Validation is not handled when using alias values in the payment method ID to create a new payment method | H4: Minor | I4: Manual | J4: Internal | K4: Closed | L4: Development | M4: Its not mentioned in the acceptance criteria. While testing, I found it and informed to Carmin, suggesting that it be added to the validation.

Sheet 15.2 DS Sprint 3-Status
A1: S.No | B1: Application Name | C1: Sprint Start Date | D1: Sprint End Date | E1: Sprint | F1: Developer | G1: Story ID/Defect ID | H1: Description | I1: Status | J1: Estimated(hrs/sp) | K1: Actual(hrs/sp) | L1: Actual Hours Worklog | M1: Dev start date | N1: Dev end date | O1: Unit testing | P1: Peer Tested By | Q1: Peer Tested Defects, if any | R1: Peer Reviewed By | S1: Peer Code Review Comments, if any | T1: PR Number/Link | U1: PR Created Date | V1: Reviewer 1 | W1: PR Approved Date | X1: Code Review Comments, if any | Y1: Reviewer 2 | Z1: Approved Date | AA1: Code Review Comments, if any2 | AB1: Internal PO -POV Comments | AC1: Client PO -POV Comments | AD1: Comments
A2: 1 | B2: =Dashboard!$J$1 -> MSB Dev | C2: 45919 | D2: 45932 | E2: 15.2 DS Sprint 3 | F2: Nithish | G2: 50113 | H2: MSB - Partner Integrations - Regression [15.2] | I2: Story Completed | J2: 13 | K2: 10.5 | L2: 42 | M2: NA | N2: NA | O2: NA | P2: NA | Q2: NA | R2: NA | S2: NA | T2: NA | U2: NA | V2: NA | W2: NA | X2: NA | Y2: NA | Z2: NA | AA2: NA | AB2: NA | AC2: NA | AD2: Testing Purpose Only Time Entries: Nithish: 42hrs
A3: 2 | B3: =Dashboard!$J$1 -> MSB Dev | C3: 45919 | D3: 45932 | E3: 15.2 DS Sprint 3 | F3: Nivetha | G3: 50115 | H3: MSB - Partner Integrations - New Automation [15.2] | I3: Story Completed | J3: 13 | K3: 18 | L3: 72 | M3: 45919 | N3: 45930 | O3: NA | P3: Nivetha | Q3: None | R3: Nivetha | S3: No Comments | T3: https://dev.azure.com/heartlandschools/MySchoolBucks/_git/MSBAutomation/pullrequest/44676 https://dev.azure.com/heartlandschools/MySchoolBucks/_git/MSBAutomation/pullrequest/44674 https://dev.azure.com/heartlandschools/MySchoolBucks/_git/MSBAutomation/pullrequest/44706 https://dev.azure.com/heartlandschools/MySchoolBucks/_git/MSBAutomation/pullrequest/44839 https://dev.azure.com/heartlandschools/MySchoolBucks/_git/MSBAutomation/pullrequest/44891 | U3: 45922 | V3: Prisla | W3: 45930 | X3: No Comments | Y3: Ken | Z3: 45930 | AA3: No Comments | AB3: NA | AC3: NA | AD3: Comments: We covered five automation stories in this story. Some of them doesn't have a framework, so we added one, which is why it required extra effort. Time Entries: Nivetha: 30hrs Mahesh: 36hrs Prisla: 6hrs
A4: 3 | B4: =Dashboard!$J$1 -> MSB Dev | C4: 45919 | D4: 45932 | E4: 15.2 DS Sprint 3 | F4: Nivetha | G4: 50114 | H4: MSB - Partner Integrations - Automation Repair [15.2] | I4: Story Completed | J4: 8 | K4: 7 | L4: 28 | M4: 45926 | N4: 45930 | O4: NA | P4: Nivetha | Q4: None | R4: Nivetha | S4: No Comments | T4: https://dev.azure.com/heartlandschools/MySchoolBucks/_git/MSBAutomation/pullrequest/44889 | U4: 45930 | V4: Prisla | W4: 45930 | X4: No Comments | Y4: Ken | Z4: 45930 | AA4: No Comments | AB4: NA | AC4: NA | AD4: Time Entries: Nivetha: 12hrs Mahesh: 6hrs Prisla: 10hrs
A5: 4 | B5: =Dashboard!$J$1 -> MSB Dev | C5: 45919 | D5: 45932
A6: 5 | B6: =Dashboard!$J$1 -> MSB Dev | C6: 45919 | D6: 45932

Sheet 15.2 DS Sprint 3-Defect
A1: S.No | B1: Sprint # | C1: Story/Defect ID | D1: Parent Story | E1: Developer | F1: Issue Type | G1: Issue Description | H1: Priority | I1: Defect Source | J1: Type | K1: Status | L1: Root Cause Category | M1: Comments
B2: 15.2 DS Sprint 3

Sheet 15.2 DS Sprint 2-Status
A1: S.No | B1: Application Name | C1: Sprint Start Date | D1: Sprint End Date | E1: Sprint | F1: Developer | G1: Story ID/Defect ID | H1: Description | I1: Status | J1: Estimated(hrs/sp) | K1: Actual(hrs/sp) | L1: Actual Hours Worklog | M1: Dev start date | N1: Dev end date | O1: Unit testing | P1: Peer Tested By | Q1: Peer Tested Defects, if any | R1: Peer Reviewed By | S1: Peer Code Review Comments, if any | T1: PR Number/Link | U1: PR Created Date | V1: Reviewer 1 | W1: PR Approved Date | X1: Code Review Comments, if any | Y1: Reviewer 2 | Z1: Approved Date | AA1: Code Review Comments, if any2 | AB1: Internal PO -POV Comments | AC1: Client PO -POV Comments | AD1: Comments
A2: 1 | B2: =Dashboard!$J$1 -> MSB Dev | C2: 45905 | D2: 45918 | E2: 15.2 DS Sprint 2 | F2: Mahesh | G2: 49668 | H2: Datahub - Housekeeping - Batch delete records on full sync (Class enrollment, Classes, Courses, Terms) | I2: Story Completed | J2: 5 | K2: 6 | L2: 26.5 | M2: 45905 | N2: 45909 | O2: Manual (TestCases-30) | P2: Nivetha | Q2: None | R2: Nivetha | S2: No comments | T2: https://dev.azure.com/heartlandschools/MySchoolBucks/_git/SchoolBucks/pullrequest/44454 | U2: 45909 | V2: Prisla | W2: 45909 | X2: No comments | Y2: Ken | Z2: 45911 | AA2: Put the ClassKey, CourseKey, TermKey at the first param | AB2: NA | AC2: NA | AD2: The scope of the story was large, and we needed to implement bulk deletion for around 11 adapters. Most of the time was spent on testing them all Time Entries: Mahesh: 18 hrs Nithish: 6.5hrs Prisla: 2hrs
A3: 2 | B3: =Dashboard!$J$1 -> MSB Dev | C3: 45905 | D3: 45918 | E3: 15.2 DS Sprint 2 | F3: Nivetha | G3: 49928 | H3: MSB - DH Provider - Change default to Include Inactive Enrollments to YES | I3: Story Completed | J3: 1 | K3: 1.5 | L3: 7 | M3: 45905 | N3: 45905 | O3: Manual (TestCases-4) | P3: Mahesh | Q3: None | R3: Mahesh | S3: No comments | T3: https://dev.azure.com/heartlandschools/MySchoolBucks/_git/SchoolBucks/pullrequest/44383 | U3: 45905 | V3: Prisla | W3: 45905 | X3: No comments | Y3: Alex | Z3: 45905 | AA3: No comments | AB3: No comments | AC3: No comments | AD3: Time Entries: Nivetha: 2hrs Nithish: 4hrs Prisla: 1hrs
A4: 3 | B4: =Dashboard!$J$1 -> MSB Dev | C4: 45905 | D4: 45918 | E4: 15.2 DS Sprint 2 | F4: Nivetha | G4: 49745 | H4: MSBP - API - Remove deprecated endpoints in v9 swagger & collection | I4: Story Completed | J4: 2 | K4: 2.5 | L4: 10.5 | M4: 45908 | N4: 45908 | O4: Manual (TestCases-4) | P4: Mahesh | Q4: 1) missed to remove the API /parent/tosStatus/{status} | R4: Mahesh | S4: No comments | T4: https://dev.azure.com/heartlandschools/MySchoolBucks/_git/SchoolBucks/pullrequest/44419 | U4: 45908 | V4: NA | W4: NA | X4: NA | Y4: George | Z4: 45908 | AA4: No comments | AB4: No comments | AC4: No comments | AD4: Time Entries: Nivetha: 7hrs Nithish: 3.5hrs
A5: 4 | B5: =Dashboard!$J$1 -> MSB Dev | C5: 45905 | D5: 45918 | E5: 15.2 DS Sprint 2 | F5: Nivetha | G5: 49826 | H5: Datahub - HSSConnect/Integration API - Add student information to Payment model (RealTime SIS) | I5: Story Completed | J5: 8 | K5: 9 | L5: 38 | M5: 45909 | N5: 45911 | O5: Manual (TestCases-8) | P5: Mahesh | Q5: None | R5: Mahesh | S5: No comments | T5: https://dev.azure.com/heartlandschools/MySchoolBucks/_git/SchoolBucks/pullrequest/44487 | U5: 45911 | V5: Prisla | W5: 45911 | X5: No comments | Y5: Ken | Z5: 45911 | AA5: No comments | AB5: No comments | AC5: No comments | AD5: AC got updated twice, which made the development to rework. Time Entries: Nivetha: 24hrs Nithish: 10hrs Prisla: 4hrs
A6: 5 | B6: =Dashboard!$J$1 -> MSB Dev | C6: 45905 | D6: 45918 | E6: 15.2 DS Sprint 2 | F6: Nivetha | G6: 49682 | H6: MSB - Dev Portal - Add MBA plugin & install guide to PowerSchool page | I6: Story Completed | J6: 1 | K6: 1.5 | L6: 6 | M6: 45903 | N6: 45903 | O6: Manual (TestCases-4) | P6: Mahesh | Q6: None | R6: Mahesh | S6: No comments | T6: https://dev.azure.com/heartlandschools/MySchoolBucks/_git/SchoolBucks/pullrequest/44359 | U6: 45904 | V6: Prisla | W6: 45904 | X6: No comments | Y6: Ken | Z6: 45904 | AA6: No comments | AB6: No comments | AC6: No comments | AD6: Testing Purpose Only Time Entries: Nivetha: 2hrs Nithish: 4hrs
A7: 6 | B7: =Dashboard!$J$1 -> MSB Dev | C7: 45905 | D7: 45918 | E7: 15.2 DS Sprint 2 Stretch | F7: Nivetha | G7: 25898 | H7: MSB - Developer Portal - MSBP 9.0 Swagger – Resolver error displayed at the top of the header page when opening various endpoints | I7: Defect Fixed | J7: 1 | K7: 1.5 | L7: 6.5 | M7: 45908 | N7: 45908 | O7: Manual (TestCases-4) | P7: Mahesh | Q7: None | R7: Mahesh | S7: No comments | T7: https://dev.azure.com/heartlandschools/MySchoolBucks/_git/SchoolBucks/pullrequest/44419 | U7: 45908 | V7: NA | W7: NA | X7: NA | Y7: George | Z7: 45908 | AA7: No comments | AB7: NA | AC7: NA | AD7: Time Entries: Nivetha: 2hrs Nithish: 4.5hrs
