Workbook

Sheet Defect-template
A1: S.No | B1: Sprint # | C1: Story/Defect ID | D1: Parent Story | E1: Developer | F1: Issue Type | G1: Issue Description | H1: Priority | I1: Defect Source | J1: Type | K1: Status | L1: Root Cause Category | M1: Comments

Sheet Dashboard
A1: Current Sprint | B1: {=INDEX($B$2:$B$110,MATCH(1,(($D$2:$D$110 >=TODAY())*($C$2:$C$110<=TODAY())),0))} -> 26.07 Sprint 1 | C1: Current Sprint Sheet | D1: =CONCATENATE(B1,"-Status") -> 26.07 Sprint 1-Status | E1: Sprint Start Date | F1: =VLOOKUP($B$1,$B$1:$C$110,2) -> 46136 | G1: Sprint End Date | H1: =VLOOKUP($B$1,$B$1:$D$110,3) -> 46163 | I1: Application Name | J1: FOH | K1: Users | L1: ashwin.maheswaran@relevantz.com;jagan.selvaraj@relevantz.com;alpha.jose@relevantz.com;atchaiah.karumanchi@relevantz.com;arvinthabaskar.reddipalayam@relevantz.com;venkatesan.rangaraj@relevantz.com;sabir.shaikh@relevantz.com;subbulakshmi.namasivayam@relevantz.com;vidhya.subramani@relevantz.com;balamurugan.kandasamy@relevantz.com | M1: Teams Name(GP-Mosaic.FOH) | N1: 19:db174c78ee9b4c94bad431f6465b5e46@thread.v2
A2: Sprint Type | B2: Sprint # | C2: Sprint Start Date | D2: Sprint End Date | E2: Assigned | F2: Completed | G2: Story points introduced/removed | H2: Sprint Summary | I2: Accomplishments | J2: Remarks | K2: Retro Points (Internal & External) | L2: Planned Leaves | M2: Total Leaves | N2: Data sanity Audit Status | O2: AuditDate | P2: Backlog Health
A3: =IF(AND($D$1>=C3,$D$1<=D3),"CurrentSprint","NA") -> NA | B3: 4.15 - Sprint 4 | C3: 45296 | D3: 45309 | E3: 28 | F3: 28 | G3: 0 | J3: Regression Sprint so completed all the modules testing, No code review comments / Defects applicable. Also we fixed few regression defects. | K3: Internal: External:
A4: =IF(AND($D$1>=C4,$D$1<=D4),"CurrentSprint","NA") -> NA | B4: 4.16 - Sprint 1 | C4: 45310 | D4: 45323 | E4: 26 | F4: 23 | G4: 0 | J4: Developers supported to clear the QA backlogs. [Testing Stories = 18, Development Stories = 8 Total Sprint Stories =20 completed = 20; Stretch Stories = 6 completed = 3] | K4: Internal: External:
A5: =IF(AND($D$1>=C5,$D$1<=D5),"CurrentSprint","NA") -> NA | B5: 4.16 - Sprint 2 | C5: 45324 | D5: 45337 | E5: 41 | F5: 39 | G5: 0 | J5: Developers supported to clear the QA backlogs. | K5: Internal: External:
A6: =IF(AND($D$1>=C6,$D$1<=D6),"CurrentSprint","NA") -> NA | B6: 4.16 - Sprint 3 | C6: 45338 | D6: 45351 | E6: 35 | F6: 35 | G6: 0 | J6: Got appreciation for a feature developed in the sprint and also in the sprint review demo from stake holder (#42670) | K6: Internal: External:
A7: =IF(AND($D$1>=C7,$D$1<=D7),"CurrentSprint","NA") -> NA | B7: 4.16 - Sprint 4 | C7: 45352 | D7: 45365 | E7: 19 | F7: 30 | G7: 0 | J7: Stretch Story: 11-SP | K7: Internal: External:
A8: =IF(AND($D$1>=C8,$D$1<=D8),"CurrentSprint","NA") -> NA | B8: 4.16 - Sprint 5 | C8: 45366 | D8: 45379 | E8: 38 | F8: 38 | G8: 0 | J8: Regression Sprint so completed all the modules testing, No code review comments / Defects applicable. Also we fixed few regression defects. Appreciation on Retro:Regression went well | K8: Internal: External:
A9: =IF(AND($D$1>=C9,$D$1<=D9),"CurrentSprint","NA") -> NA | B9: 4.17 - Sprint 1 | C9: 45380 | D9: 45393 | E9: 32 | F9: 32 | J9: Regression wrap up was done in this sprint and along with that completed few stretch stories(Sprint Story only 13SP for the regression wrap up). | K9: Internal: External:
A10: =IF(AND($D$1>=C10,$D$1<=D10),"CurrentSprint","NA") -> NA | B10: 4.17 - Sprint 2 | C10: 45394 | D10: 45407 | E10: 21 | F10: 39 | G10: 0 | J10: Completed all the assigned stories and addition to that completed Stretch Stories - 18 SP. | K10: Internal: External:
A11: =IF(AND($D$1>=C11,$D$1<=D11),"CurrentSprint","NA") -> NA | B11: 4.17 - Sprint 3 | C11: 45408 | D11: 45421 | E11: 29 | F11: 10 | G11: 0 | J11: Completed all the stories - 29 SP in Sprint and 10 SP in stretch. Onsite team was on PTO, so no one there to approve the PR. Carryforwading 21 SP in sprint and 8 SP in stretch to next sprint as per Gary's suggestion. | K11: Internal: External:
A12: =IF(AND($D$1>=C12,$D$1<=D12),"CurrentSprint","NA") -> NA | B12: 4.17 - Sprint 4 | C12: 45422 | D12: 45435 | E12: 13 | F12: 13 | G12: 0 | J12: Regression Sprint(Targeted) so completed all the modules testing, Also we fixed few regression defects. Stretch Story: 5-SP Appreciation on Retro:Regression went well | K12: Internal: External:
A13: =IF(AND($D$1>=C13,$D$1<=D13),"CurrentSprint","NA") -> NA | B13: 4.18 - Sprint 1 | C13: 45436 | D13: 45449 | E13: 40 | F13: 32 | G13: 0 | J13: Carryforwaded one story 8 SP, as POV with onsite team need to done. | K13: Internal: External:
A14: =IF(AND($D$1>=C14,$D$1<=D14),"CurrentSprint","NA") -> NA | B14: 4.18 - Sprint 2 | C14: 45450 | D14: 45463 | E14: 13 | F14: 21 | G14: 0 | J14: Completed all the committed stories. Stretch Story: 8-SP | K14: Internal: External:
A15: =IF(AND($D$1>=C15,$D$1<=D15),"CurrentSprint","NA") -> NA | B15: 4.18 - Sprint 3 | C15: 45464 | D15: 45491 | E15: 44 | F15: 44 | G15: 22 | J15: Completed all the committed stories. Supported to clear the QA backlogs. Stretch Story: 22-SP. Appreciation on Retro: For helping on QA backlogs | K15: Internal: External:
A16: =IF(AND($D$1>=C16,$D$1<=D16),"CurrentSprint","NA") -> NA | B16: 4.18 - Sprint 4 | C16: 45492 | D16: 45505 | E16: 37 | F16: 37 | G16: 37 | J16: No delevopment stories added to sprint. Supported to clear the QA backlogs. Stretch Story: 37-SP. | K16: Internal: External:
A17: =IF(AND($D$1>=C17,$D$1<=D17),"CurrentSprint","NA") -> NA | B17: 4.18 - Sprint 5 | C17: 45506 | D17: 45519 | E17: 15 | F17: 15 | G17: 3 | J17: Completed the committed stories. Supported to clear the QA backlogs. 14-SP completed development and waiting to raise PR. Stretch Story: 3-SP. | K17: Internal: External:
A18: =IF(AND($D$1>=C18,$D$1<=D18),"CurrentSprint","NA") -> NA | B18: 4.18 - Sprint 6 | C18: 45520 | D18: 45533 | E18: 21 | F18: 21 | G18: 7 | J18: Completed the committed stories. Supported to clear the QA backlogs. Stretch Story: 11-SP. | K18: Internal: External:
A19: =IF(AND($D$1>=C19,$D$1<=D19),"CurrentSprint","NA") -> NA | B19: 4.18 - Sprint 7 | C19: 45534 | D19: 45547 | E19: 38 | F19: 38 | G19: 8 | J19: Note: 1. Related to fix for 4.17: There was an issue with Student Import potential match catch logic. From Steve: a parsing issue - the birthdate of 09112009 fails to parse w/the code being used. It's trying to parse with only this pattern MM/dd/yyyy (hardcoded) 2. Related to hotfix for CPS: There was an issue found at MSB end in their API. Data is not being sent to Mosaic due an issue with the date. It can be fixed at either end (MSB or Mosaic) but if is fixed in Mosaic it will be a simple fix because if MSB team fix it may take much more time. The real issue is MSB is expecting for a date time for start and end date. Currently we send only date and due to that data is not pulled properly. Completed all regression stories in sprint. Stretch Story: 8-SP | K19: Internal: External:
A20: =IF(AND($D$1>=C20,$D$1<=D20),"CurrentSprint","NA") -> NA | B20: 4.19 - Sprint 1 | C20: 45548 | D20: 45561 | E20: 31 | F20: 31 | G20: 0 | J20: CRC Internal -- 2 CRC External -- 0 QA Defects -- 3 (1-Rejected) Escaped Defects -- 0 Completed all the committed stories. Supported to clear the QA backlogs. Stretch Story: 18-SP. 45834 is POC which is Carry Forwarded | K20: Internal: External: Appreciation on Retro: For helping on QA backlogs
A21: =IF(AND($D$1>=C21,$D$1<=D21),"CurrentSprint","NA") -> NA | B21: 4.19 - Sprint 2 | C21: 45562 | D21: 45589 | E21: 33 | F21: 45.5 | G21: Introduced - 12.5 | J21: CRC Internal -- 4 CRC External -- 0 QA Defects -- 8 (2-Rejected) Escaped Defects -- 0 Supported to clear the QA backlogs. Stretch Story: 20-SP. | K21: Internal: Alpha recieved appreciation for support in dashboard. Jagan and Arvinth recieved appreciation for good presentation in sprint review. External: Recieved appreciation from Tino for Dashbord Story done by Subha. Appreciation on Retro: For helping on QA backlogs
A22: =IF(AND($D$1>=C22,$D$1<=D22),"CurrentSprint","NA") -> NA | B22: 4.19 - Sprint 3 | C22: 45590 | D22: 45603 | E22: 16 | F22: 35 | G22: Introduced - 19 | I22: Feature Flags, Student Barcode Report Update, Louisiana SFS-8A Report update, and Defects | J22: CRC Internal -- 0 CRC External -- 1 QA Defects -- 2 Escaped Defects -- 0 Supported to clear the QA backlogs. Stretch Story: 19-SP. | K22: Internal: External:
A23: =IF(AND($D$1>=C23,$D$1<=D23),"CurrentSprint","NA") -> NA | B23: 4.19 - Sprint 4 | C23: 45604 | D23: 45617 | E23: 25 | F23: 33 | G23: Introduced - 8 | I23: Improvements to Scheduler Task, Showing Actual Bank Deposit Amount in Online Payment Detail Report, Update to Alachua Meal Count export(2 decimal places to labor hours), and Defects | J23: CRC Internal -- 0 CRC External -- 0 QA Defects -- 3 (2-Rejected) Escaped Defects -- 0 Stretch Story: 8-SP. | K23: Internal: Online payment report story done without any deviation. External:
A24: =IF(AND($D$1>=C24,$D$1<=D24),"CurrentSprint","NA") -> NA | B24: 4.19 - Sprint 5 | C24: 45618 | D24: 45645 | E24: 60 | F24: 70 | G24: Introduced - 10 | I24: Add Ability to Print Machine Info, Add date of inactive to Student Maintenance, Add Notes to Elig Record Report, Add Active Filter to User Assignments Report, Defects, and then begin 4.19 Regression Testing. | J24: CRC Internal -- 2 CRC External -- 1 QA Defects -- 3 Escaped Defects -- 0 Stretch Story: 10-SP. | K24: Internal:Change comment,Change in adding the SQL paramer External:Merge conflict with revision history
A25: =IF(AND($D$1>=C25,$D$1<=D25),"CurrentSprint","NA") -> NA | B25: 4.20 - Sprint 1 | C25: 45646 | D25: 45673 | E25: 35 | F25: 46 | G25: Introduced - 12 | I25: multiple Defects for 4.19 and complete 4.19 Regression, Add report for “Schools not in School Group”, and Add new report type to POS Roster Reports | J25: Release Date - March 2025 (Tentative) CRC Internal -- 1 CRC External -- 0 QA Defects -- 15 (1-Rejected) Escaped Defects -- 0 Stretch Story: 12-SP. | K25: Internal: External: Appreciation on Retro: For helping on QA backlogs
A26: =IF(AND($D$1>=C26,$D$1<=D26),"CurrentSprint","NA") -> NA | B26: 4.20 - Sprint 2 | C26: 45674 | D26: 45687 | E26: 22 | F26: 27 | G26: Introduced - 5 | I26: Menu Management Improvements(Assign POS Menus to multiple POS numbers & Re-Alphabetize Menu Products), Dashboard update(CPS), Speed-e Mode option to fulfill Meal Order or not, and use CEP Reimbursement Calculations in Claim Report(KDE) | J26: Release Date - March 2025 (Tentative) CRC Internal -- 0 CRC External -- 0 QA Defects -- 0 Escaped Defects -- 0 Stretch Story: 5-SP. | K26: Internal: External: Appreciation on Retro: Mike(QA) appreciated for helping on QA backlogs
A27: =IF(AND($D$1>=C27,$D$1<=D27),"CurrentSprint","NA") -> NA | B27: 4.20 - Sprint 3 | C27: 45688 | D27: 45701 | E27: 25 | F27: 31 | G27: Introduced - 6 | I27: Add Student Effective Date and Eligibility Reason to Student Maint., Attaching Verification Reports, Add Serving Period Program and Serving Period droplist to Special Provision Edit Check Report, Performance Improvements to Imports(CPS), and Defect Fixes | J27: Release Date - March 2025 (Tentative) CRC Internal -- 0 CRC External -- 0 QA Defects -- 0 Escaped Defects -- 0 Stretch Story: 6-SP. | K27: Internal: External: Appreciation on Retro: Mike(QA) appreciated for helping on QA backlogs
A28: =IF(AND($D$1>=C28,$D$1<=D28),"CurrentSprint","NA") -> NA | B28: 4.20 - Sprint 4 | C28: 45702 | D28: 45715 | E28: 38 | F28: 38 | G28: Introduced - 0 | I28: 4.20 Regression Testing | J28: Release Date - March 2025 (Tentative) CRC Internal -- 0 CRC External -- 0 QA Defects -- 13 Escaped Defects -- 0 Stretch Story: 0 | K28: Internal: External: Appreciation on Retro: Mike(QA) appreciated for helping on QA backlogs and Regression Testing completion
A29: =IF(AND($D$1>=C29,$D$1<=D29),"CurrentSprint","NA") -> NA | B29: 4.21 - Sprint 1 | C29: 45716 | D29: 45729 | E29: 26 | F29: 31 | G29: Introduced - 5 | I29: Tyler-MUNIS Financial Export(NC), Adding Checks to Student Account Summary Report, Label Format Options to Barcode Report | J29: CRC Internal -- 4 CRC External -- 0 QA Defects -- 0 Escaped Defects -- 0 Stretch Story: 0 | K29: Internal: External:
A30: =IF(AND($D$1>=C30,$D$1<=D30),"CurrentSprint","NA") -> NA | B30: 4.21 - Sprint 2 | C30: 45730 | D30: 45743 | E30: 32 | F30: 32 | G30: Introduced - 0 | I30: North Carolina Export, Ability to see transactions marked for review(SL), A La Carte Report Update, Ability to Add Transactions after Re-opening a day, and adding CEP ISP calculations to Chartwell’s Export | J30: CRC Internal -- 1 CRC External -- 2 QA Defects -- 0 Escaped Defects -- 0 Stretch Story: 0 | K30: Internal: External: Appreciation on Retro: Mike(QA) appreciated for helping on QA backlogs
A31: =IF(AND($D$1>=C31,$D$1<=D31),"CurrentSprint","NA") -> NA | B31: 4.21 - Sprint 3 | C31: 45744 | D31: 45757 | E31: 31 | F31: 34 | G31: Introduced - 3 | I31: CPS Dashboard Improvements, IEG Updates, ‘Carryover Expiration Date’ added as Import field, adding, NC SFS-4 Export update, and Adding ISP values for Mult schools. | J31: CRC Internal -- 3 CRC External -- 1 QA Defects -- 0 Escaped Defects -- 0 Stretch Story: 0 | K31: Internal: External:
A32: =IF(AND($D$1>=C32,$D$1<=D32),"CurrentSprint","NA") -> NA | B32: 4.21 - Sprint 4 | C32: 45758 | D32: 45771 | E32: 41 | F32: 33 | G32: Introduced - 0 | I32: 4.21 Regression Testing | J32: CRC Internal -- 1 CRC External -- 0 QA Defects -- 3 Escaped Defects -- 0 Stretch Story: 0 | K32: Internal: External: Appreciation for completing most of the regression stories eventhough it is a full regression
A33: =IF(AND($D$1>=C33,$D$1<=D33),"CurrentSprint","NA") -> NA | B33: 4.22 - Sprint 1 | C33: 45772 | D33: 45785 | E33: 35 | F33: 31 | G33: Introduced - 3 | I33: Wrap up 4.21 Regression(Defects found), Adding new templates to Custom Reports, Tier Model, Add Menu Product Sold Qtys to Daily Sales Preview, and MSB Reconciliation. | J33: CRC Internal -- 5 CRC External -- 0 QA Defects -- 2 Escaped Defects -- 0 Stretch Story: 0 | K33: Internal: External:
... A44: =IF(AND($D$1>=C44,$D$1<=D44),"CurrentSprint","NA") -> NA | B44: 4.25 - Sprint 1 | C44: 45926 | D44: 45939 | E44: 22 | F44: 31 | G44: Introduced - 23 | I44: Modifications to Operating Days, new filter for ‘Participation by’ to Standard Claim Report | J44: CRC Internal -- 0 Peer testing - 0 CRC External -- 0 QA Defects --1 Escaped Defects -- 0 POV Comments - 0 Stretch Story: 7 | K44: Internal: External: What went well: Completed more than Forecast , Esclations (not too bad this week), mike completed testing before PTO, Team completed rest of testing after Mike PTO What didn't go well: Apigee issue (platformops and apigee team)
A45: =IF(AND($D$1>=C45,$D$1<=D45),"CurrentSprint","NA") -> NA | B45: 4.25 - Sprint 2 | C45: 45940 | D45: 45953 | E45: 26 | F45: 26 | G45: Introduced - 18 | H45: New Dashboard Widgets, Ability to flip between Apigee & Existing endpoints, ‘Participation By’ filter to Supplemental Programs Claim Report, Tyler Munis Export Modifications, update to VA SNP-12 Report, Add Active Flag to Student Export Setup, and 4.24 Release Prep | I45: New Dashboard Widgets, Ability to flip between Apigee & Existing endpoints,Tyler Munis Export Modifications, update to VA SNP-12 Report, Add Active Flag to Student Export Setup, and 4.24 Release Prep. | J45: CRC Internal -- 2 Peer testing - 0 CRC External -- 0 QA Defects -- 0 Escaped Defects -- 0 POV Comments - 0 Stretch Story: 4 | K45: Internal: External: completed more than forecast
A46: =IF(AND($D$1>=C46,$D$1<=D46),"CurrentSprint","NA") -> NA | B46: 4.25 - Sprint 3 | C46: 45954 | D46: 45967 | E46: 33 | F46: 38 | G46: Introduced - 21 | H46: Adding a Student Debt Chart to the Dashboard, Replacing Master Serving Period with Serving Period Program, New ‘Group By School’ filter to Students w/out an Elig. Determination Report, DC Import Improvements, and NJ Master Eligibility List report Modifications | I46: Adding a Student Debt Chart to the Dashboard, New ‘Group By School’ filter to Students w/out an Elig. Determination Report, DC Import Improvements, and NJ Master Eligibility List report Modifications | J46: CRC Internal -- 1 Peer testing - 0 CRC External -- 0 QA Defects -- 1 Escaped Defects -- 0 POV Comments - 0 Stretch Story: 9 | K46: Internal: External: What went well: Releases, Exceeded Forecast What didn't go well: Esclations (Note: Esclations from coustomer support are handled by client developer Steve)
A47: =IF(AND($D$1>=C47,$D$1<=D47),"CurrentSprint","NA") -> NA | B47: 4.25 - Sprint 4 | C47: 45968 | D47: 45981 | E47: 22 | F47: 28 | G47: Introduced - 11 | H47: IL WINS Export Scheduler Task, Importing Custom Report Format, Close Year Updates, New ‘Letter Sent Status’ filter to Student Letters, Defect Fixes | I47: Close Year screen updates, Letter sent status in student letter, Import Format in Custom report, MSA Client Communication, NSSID in Visual Report, Defect Fixes | J47: CRC Internal -- 3 Peer testing - 1 CRC External -- 0 QA Defects -- 0 Escaped Defects -- 0 POV Comments - 0 Stretch Story: 10 | K47: Internal: External: What went well: Hit Forecast, SYNK progress in stretch What didn't go well: CPS Release, Apigee work, MSB Endpoint Change.
A48: =IF(AND($D$1>=C48,$D$1<=D48),"CurrentSprint","NA") -> NA | B48: 4.25 - Sprint 5 | C48: 45982 | D48: 46009 | E48: 52 | F48: 57 | G48: Introduced - 13 | H48: Remediating SNYK Findings, New Templates for Custom Reports, New Data Sources for Report Designer, and 4.25 Regression Testing | I48: Completed Synk findings critical issues, completed 4.25 regression testing with defect fixes. | J48: CRC Internal -- 0 Peer testing - 1 CRC External -- 0 QA Defects -- 0 Escaped Defects -- 0 POV Comments - 0 Stretch Story: 6 | K48: Internal: External: What went well: Insane no.of stories completed(Sp's), started using Browser Stack for automation. What didn't go well: Escalations, MSB Endpoint Change.(Note: Esclations from coustomer support are handled by client developer Steve)
A49: =IF(AND($D$1>=C49,$D$1<=D49),"CurrentSprint","NA") -> NA | B49: 26.1 - Sprint 1 | C49: 46010 | D49: 46037 | E49: 33 | F49: 49 | G49: Introduced - 29 | H49: Support for Multiple Languages in SL, Add Report Type filter to Student Meal Report, Add ‘Student Notes’ and ‘Elig. Record Notes’ to Custom Student Report, Adding ‘Serving Line Note changes’ & ‘Grade changes’ to Event Type filter for Student History Report, and Automation | I49: Completed adding Report Type filter to Student Meal Report, Adding ‘Student Notes’ and ‘Elig. Record Notes’ to Custom Student Report, Adding ‘Serving Line Note changes’ & ‘Grade changes’ to Event Type filter for Student History Report, and Automation | J49: CRC Internal -- 1 Peer testing - 2 CRC External -- 0 QA Defects -- 0 Escaped Defects -- 0 POV Comments - 0 Stretch Story: 13 | K49: Internal: External: What went well: Completed the forecast and almost the same in the stretch. 2. Holidays. 3. 502 gateway Apigee issues solving (prod) What didn't go well: 365 migration, MSB from www to etransfer issue.
A50: =IF(AND($D$1>=C50,$D$1<=D50),"CurrentSprint","NA") -> NA | B50: 26.1 - Sprint 2 | C50: 46038 | D50: 46051 | E50: 35 | F50: 41 | G50: Introduced -17 | H50: Add “Required for all Students” to System Setting for MSB Spending Limits, New Report Type to Meal Report, Add Bank Deposit Report as a Close Day Report, and Mosaic BOH Knowledge transfer. | I50: Completed adding “Required for all Students” to System Setting for MSB Spending Limits, New Report Type to Meal Report, Bank Deposit Report as a Close Day Report | J50: CRC Internal -- 1 Peer testing - 1 CRC External -- 0 QA Defects -- 1 Escaped Defects -- 0 POV Comments - 1 Stretch Story: 10 CRC RC: update script was not included and the temp table was not dropped before initialization | K50: Internal: External: What went well: Completed commit and stretch items. 2. 4.24 Hot fix/4.25 Beta 3. BOH KT What didn't go well: 1. Vending QA, 2. Missing App switcher script in 4.25 Beta 3. App switcher button is not always working. Recieved appretiaton from QA during retro that offshore helped to close the testing stories during the sprint end.
A51: =IF(AND($D$1>=C51,$D$1<=D51),"CurrentSprint","NA") -> NA | B51: 26.1 - Sprint 3 | C51: 46052 | D51: 46065 | E51: 29 | F51: 36 | G51: Introduced - 19 | H51: Adding Grand Total pages to Extended Sales & Edit Check Worksheet Reports, Add Medical Alert changes to the Student History Report, and Defect Fixes. | I51: Completed the Grand Total pages to Extended Sales & Edit Check Worksheet Reports, Add Medical Alert changes to the Student History Report, and Defect Fixes. | J51: "CRC Internal -- 3 Peer testing - 1 CRC External -- 0 QA Defects -- 0 Escaped Defects -- 0 POV Comments - 0 Stretch Story: 8 CRC RC: Version history in one page, Suggestion to write the query in an another way, Insert to one detail table is not required." | K51: "Internal: External: What went well: 1. Exceeded the forcast story points. 2. 4.25 release. What didn't go well: 1. Escalation tickets, 2. 4.25 rused out(App switcher not working), 3. Dashboard issues." | L51: 2 | M51: 3
A52: =IF(AND($D$1>=C52,$D$1<=D52),"CurrentSprint","NA") -> NA | B52: 26.1 - Sprint 4 | C52: 46066 | D52: 46079 | E52: 37 | F52: 38 | G52: Introduced - 21 | H52: Regression Testing | I52: Completed all the commits | J52: "CRC Internal -- 0 Peer testing - 0 CRC External -- 0 QA Defects -- 0 Escaped Defects -- 0 POV Comments - 0 Stretch Story: 1 RC: 1) The testing support story was not completed as the team prioritized regression testing. As a result, testing for this item only began toward the end of the sprint. 2) All development activities from our side have been completed on time and it is pending with the Onsite QA." | K52: "Internal: External: What went well: 1. Offshore work on regression, 2. Hosted Test environment(Mike getting builds up) What didn't go well: 1. SQL cypher(Not working with .460) | L52: 3.5 | M52: 3.5
A53: =IF(AND($D$1>=C53,$D$1<=D53),"CurrentSprint","NA") -> NA | B53: 26.05 Sprint 1 | C53: 46080 | D53: 46093 | E53: 29 | F53: 34 | G53: 15 | H53: Wrap up 26.1 Regression Testing,Tyler Munis Export Modifications,Pendo Snippet update | I53: Completed 26.1 Regression and regression defects, Tyler Munis Export Modifications and Pendo Snippet update | J53: CRC Internal -- 0 Peer testing - 0 CRC External -- 0 QA Defects -- 0 Escaped Defects -- 0 POV Comments - 0 Stretch Story: 4 | K53: Internal: External: What went well: 1. Exceeded commit, 2. SQLCypher progress, 3. Regression completed on time | L53: 2 | M53: 2
A54: =IF(AND($D$1>=C54,$D$1<=D54),"CurrentSprint","NA") -> NA | B54: 26.05 Sprint 2 | C54: 46094 | D54: 46107 | E54: 32 | F54: 37 | G54: 23 | H54: Update to Dashboard Setup Maintenance (adding Widgets), Automation | I54: Completed Tyler Technologies Financial Export, Automation | J54: CRC Internal -- 1 Peer testing - 1 CRC External -- 0 QA Defects -- 0 Escaped Defects -- 0 POV Comments - 0 Stretch Story: 7 RC: Cosemetic changes, missed parameter | K54: Internal: External: What went well: 1. Exceeded commit, 2. 26.1 release What didn't go well: Apigee & WAF issues | L54: 2.5 | M54: 2.5
A55: =IF(AND($D$1>=C55,$D$1<=D55),"CurrentSprint","NA") -> NA | B55: 26.05 Sprint 3 | C55: 46108 | D55: 46121 | E55: 21 | F55: 46 | G55: 24 | H55: Update to Dashboard Setup Maintenance (adding Widgets), Testing Data file Imports from WebSMARTT, SNYK Remediation, and Mosaic BOH Wave(Bidding, Allergens, and User Tasks). | I55: Completed all the commits. Review Task in User Task,Bidding - Allow vendors to indicate "No Response",ER Improve the Search functionality | J55: CRC Internal -- 0 Peer testing -- 3 CRC External -- 0 QA Defects -- 0 Escaped Defects -- 0 POV Comments -- 0 Stretch Story: 5 Suggestions -- 5 Tasks -- 1 Peer testing RC: 1. 2 new peer testing comments; the new parameter name was not replaced in all the areas. Additionally, we have fixed the 3 existing issues as well. 2. Error during delete the existing entry. 3. UI issues | K55: What went well: 1. Completed committed and 3 stretch stories, 2. Defect fixes for 26.1 release, 3. QA support from the offshore team. What didn't go well: AG's workable. | L55: 13 | M55: 12
A56: =IF(AND($D$1>=C56,$D$1<=D56),"CurrentSprint","NA") -> NA | B56: 26.05 Sprint 4 | C56: 46122 | D56: 46135 | E56: 26 | F56: 26 | G56: 13 | H56: Review Task in User Task, Ingredients - Search Functionality, 26.5 Regression Testing, Bidding | I56: Completed 26.5 Regression Testing for Setup, F&R, Students, EoD and POS, User Tasks for Review Task, Ingredients - Search Functionality | J56: CRC Internal -- 0 Peer testing -- 0 CRC External -- 0 QA Defects -- 1 Escaped Defects -- 0 POV Comments -- 0 Stretch Story: 5 Suggestions -- 1 Tasks -- 0 Defect RC: Data not retaining while uploading image (Data Issue) | K56: What went well: 1. Completed Regression stories assigned in the sprint 2. Fixed all the regression defects 3. No review comments What didn't go well: Nil | L56: 7 | M56: 8
A57: =IF(AND($D$1>=C57,$D$1<=D57),"CurrentSprint","NA") -> NA | B57: 26.07 Sprint 1 | C57: 46136 | D57: 46163 | L57: 7

Sheet 26.07 Sprint 1-Status
A1: S.No | B1: Application Name | C1: Sprint Start Date | D1: Sprint End Date | E1: Sprint | F1: Developer | G1: Story ID/Defect ID | H1: Description | I1: Status | J1: Estimated(hrs/sp) | K1: Actual(hrs/sp) | L1: Actual Worklog (Hours) | M1: Dev Start Date | N1: Dev End Date | O1: Unit testing | P1: Peer Tested By | Q1: Peer Tested Comments, if any | R1: Peer Reviewed By | S1: Peer Code Review Comments, if any | T1: PR Number/Link | U1: PR Created Date | V1: PR Approved Date | W1: Onsite Lead Code Review | X1: Code Review Comments, if any | Y1: Client Code Review | Z1: Approved Date | AA1: Code Review Comments, if any2 | AB1: Internal PO -POV Comments | AC1: Client PO -POV Comments | AD1: Comments | AE1: Does this story meet expectations?
A2: 1 | B2: FOH | C2: 46136 | D2: 46163 | E2: 26.07 Sprint 1 | F2: Alpha/Atchaiah | G2: 52794 | H2: Mosaic - FOH 26.5 (Regression) - Reports - Eligibility (F&R) | I2: Story Completed | J2: 3 | K2: 6 | L2: 24 | M2: 46136 | N2: 46155 | O2: NA | P2: NA | Q2: NA | R2: NA | S2: NA | T2: NA | U2: NA | V2: NA | W2: NA | X2: NA | Y2: NA | Z2: NA | AA2: NA | AB2: NA | AC2: NA | AD2: Regression Testing
A3: 2 | B3: FOH | C3: 46136 | D3: 46163 | E3: 26.07 Sprint 1 | F3: Atchaiah/Alpha | G3: 52791 | H3: Mosaic - FOH 26.5(Regression) - Utilities | I3: Story Completed | J3: 5 | K3: 11 | L3: 44 | M3: 46136 | N3: 46155 | O3: NA | P3: NA | Q3: NA | R3: NA | S3: NA | T3: NA | U3: NA | V3: NA | W3: NA | X3: NA | Y3: NA | Z3: NA | AA3: NA | AB3: NA | AC3: NA | AD3: Regression Testing
A4: 3 | B4: FOH | C4: 46136 | D4: 46163 | E4: 26.07 Sprint 1 | F4: Arvinth | G4: 52796 | H4: Mosaic - FOH 26.5(Regression) - Reports - (Excluding Free/Reduced) | I4: Story Completed | J4: 8 | K4: 11.75 | L4: 47 | M4: 46136 | N4: 46155 | O4: NA | P4: NA | Q4: NA | R4: NA | S4: NA | T4: NA | U4: NA | V4: NA | W4: NA | X4: NA | Y4: NA | Z4: NA | AA4: NA | AB4: NA | AC4: NA | AD4: Regression Testing
A5: 4 | B5: FOH | C5: 46136 | D5: 46163 | E5: 26.07 Sprint 1 | F5: Atchaiah | G5: 52649 | H5: MFOH [BAU] - Automation (51453) | I5: Story Completed | J5: 1 | K5: 1 | L5: 4 | M5: 46140 | N5: 46140 | O5: NA | P5: NA | Q5: NA | R5: NA | S5: NA | T5: 48710 | U5: 46140 | V5: 46140 | W5: NA | X5: NA | Y5: Steve | Z5: 46140 | AA5: None | AB5: NA | AC5: NA
A6: 5 | B6: FOH | C6: 46136 | D6: 46163 | E6: 26.07 Sprint 1 | F6: Atchaiah | G6: 52650 | H6: MFOH [BAU] - Automation (50645) | I6: Story Completed | J6: 3 | K6: 3 | L6: 12 | M6: 46141 | N6: 46142 | O6: NA | P6: NA | Q6: NA | R6: NA | S6: NA | T6: 48889 | U6: 46148 | V6: 46148 | W6: NA | X6: NA | Y6: Steve | Z6: 46148 | AA6: None | AB6: NA | AC6: NA
A7: 8 | B7: FOH | C7: 46136 | D7: 46163 | E7: 26.07 Sprint 1 | F7: Alpha | G7: 52854 | H7: Mosaic FOH - Snyk Findings - Path Traversal - UtilitiesController.cs- Unsanitized input flows into global::System.IO.StreamWriter - Part 2 | I7: Story Completed | J7: 3 | K7: 2 | L7: 8 | M7: 46148 | N7: 46149 | O7: Alpha | P7: Arvinth | Q7: None | R7: Arvinth | S7: None | T7: 48960 | U7: 46153 | V7: 46153 | W7: NA | X7: NA | Y7: Ying | Z7: 46153 | AA7: None | AB7: NA | AC7: NA
A8: 10 | B8: FOH | C8: 46136 | D8: 46163 | E8: 26.07 Sprint 1 | F8: Alpha | G8: 52450 | H8: MFOH - Convert the Carriage return in the Serving Line Notes (Student Import) | I8: Story Being Developed | J8: 2 | K8: 1 | L8: 4 | M8: 46153
A9: 18 | B9: FOH | C9: 46136 | D9: 46163 | E9: 26.07 Sprint 1 | F9: Arvinth | G9: 52851 | H9: Mosaic FOH - Snyk Findings - Path Traversal - UtilitiesController.cs- Unsanitized input flows into global::System.IO.Directory.Exists- Part 2 | I9: Story Completed | J9: 3 | K9: 2.5 | L9: 10 | M9: 46149 | N9: 46150 | O9: Arvinth | P9: Alpha | Q9: None | R9: Alpha | S9: None | T9: 48966 | U9: 46153 | V9: 46153 | W9: Venkat | X9: None | Y9: Ying | Z9: 46153 | AA9: None | AB9: None | AC9: NA
A10: 21 | B10: FOH | C10: 46136 | D10: 46163 | E10: 26.07 Sprint 1 | F10: Arvinth | G10: 27157 | H10: MFoH - (Regression 26.5) Custom Report Import - Clicking Cancel button on import screen throws error | I10: Story Completed | J10: 3 | K10: 1.75 | L10: 7 | M10: 46150 | N10: 46153 | O10: Arvinth | P10: Alpha | Q10: None | R10: Alpha | S10: None | T10: 48991 | U10: 46154 | V10: 46154 | W10: Venkat | X10: None | Y10: Ying | Z10: 46154 | AA10: None | AB10: None | AC10: NA
A11: 6 | B11: FOH | C11: 46136 | D11: 46163 | E11: 26.07 Sprint 1 | F11: Alpha | G11: 27345 | H11: MFOH (26.5 Regression) - Error records are shown in Add count for Test Import Data | I11: Story Completed | J11: 0 | K11: 0 | L11: 0 | M11: 46146 | N11: 46147 | O11: Alpha | P11: Arvinth | Q11: None | R11: Arvinth | S11: Add conditional return ststement. | T11: 48881 | U11: 46148 | V11: 46148 | W11: Venkat | X11: None | Y11: Ying | Z11: 46148 | AA11: None | AB11: NA | AC11: NA | AD11: Regression Defects
A12: 7 | B12: FOH | C12: 46136 | D12: 46163 | E12: 26.07 Sprint 1 | F12: Alpha | G12: 27346 | H12: MFOH (26.5 Regression) - Import Name is partially displayed when there is a dot in the Name | I12: Story Completed | J12: 0 | K12: 0 | L12: 0 | M12: 46147 | N12: 46147 | O12: Alpha | P12: Arvinth | Q12: None | R12: Arvinth | S12: None | T12: 48882 | U12: 46148 | V12: 46148 | W12: Venkat | X12: None | Y12: Ying | Z12: 46148 | AA12: None | AB12: NA | AC12: NA | AD12: Regression Defects
A13: 11 | B13: FOH | C13: 46136 | D13: 46163 | E13: 26.07 Sprint 1 | F13: Arvinth | G13: 27336 | H13: MFOH (26.5 Regression) - Throwing error when Serving Line Note is more then 150 characters | I13: Story Completed | J13: 0 | K13: 0 | L13: 0 | M13: 46146 | N13: 46146 | O13: Arvinth | P13: Alpha | Q13: None | R13: Alpha | S13: None | T13: 48846 | U13: 46147 | V13: 46147 | W13: NA | X13: NA | Y13: Ying | Z13: 46147 | AA13: None | AB13: NA | AC13: NA | AD13: Regression Defects
A14: 12 | B14: FOH | C14: 46136 | D14: 46163 | E14: 26.07 Sprint 1 | F14: Arvinth | G14: 27340 | H14: MFOH (26.5 Regression) - Louisiana SFS-7 Report Data tab, table sort design issue | I14: Story Completed | J14: 0 | K14: 0 | L14: 0 | M14: 46146 | N14: 46146 | O14: Arvinth | P14: Alpha | Q14: None | R14: Alpha | S14: None | T14: 48847 | U14: 46147 | V14: 46147 | W14: NA | X14: NA | Y14: Ying | Z14: 46147 | AA14: None | AB14: NA | AC14: NA | AD14: Regression Defects
A15: 13 | B15: FOH | C15: 46136 | D15: 46163 | E15: 26.07 Sprint 1 | F15: Arvinth | G15: 27342 | H15: MFOH (26.5 Regression) - Getting console error in Report Sharing Setup | I15: Story Completed | J15: 0 | K15: 0 | L15: 0 | M15: 46146 | N15: 46146 | O15: Arvinth | P15: Alpha | Q15: None | R15: Alpha | S15: None | T15: 48848 | U15: 46147 | V15: 46147 | W15: NA | X15: NA | Y15: Ying | Z15: 46147 | AA15: None | AB15: NA | AC15: NA | AD15: Regression Defects
A16: 14 | B16: FOH | C16: 46136 | D16: 46163 | E16: 26.07 Sprint 1 | F16: Arvinth | G16: 27337 | H16: MFOH (26.5 Regression) - A console error occurs when values are entered into the text box in the Kentucky D2 Report | I16: Story Completed | J16: 0 | K16: 0 | L16: 0 | M16: 46147 | N16: 46147 | O16: Arvinth | P16: Alpha | Q16: None | R16: Alpha | S16: None | T16: 48885 | U16: 46148 | V16: 46148 | W16: NA | X16: NA | Y16: Ying | Z16: 46148 | AA16: None | AB16: NA | AC16: NA | AD16: Regression Defects
A17: 15 | B17: FOH | C17: 46136 | D17: 46163 | E17: 26.07 Sprint 1 | F17: Arvinth | G17: 27338 | H17: MFOH (26.5 Regression) - A console error occurs when values are entered into the text box in the Louisiana SFS-7 Report | I17: Story Completed | J17: 0 | K17: 0 | L17: 0 | M17: 46147 | N17: 46147 | O17: Arvinth | P17: Alpha | Q17: None | R17: Alpha | S17: None | T17: 48886 | U17: 46148 | V17: 46148 | W17: NA | X17: NA | Y17: Ying | Z17: 46148 | AA17: None | AB17: NA | AC17: NA | AD17: Regression Defects
A18: 16 | B18: FOH | C18: 46136 | D18: 46163 | E18: 26.07 Sprint 1 | F18: Arvinth | G18: 27339 | H18: MFOH (26.5 Regression) - A console error occurs when values are entered into the text box in the Louisiana SFS-8B Report | I18: Story Completed | J18: 0 | K18: 0 | L18: 0 | M18: 46147 | N18: 46147 | O18: Arvinth | P18: Alpha | Q18: None | R18: Alpha | S18: None | T18: 48887 | U18: 46148 | V18: 46148 | W18: NA | X18: NA | Y18: Ying | Z18: 46148 | AA18: None | AB18: NA | AC18: NA | AD18: Regression Defects
A19: 17 | B19: FOH | C19: 46136 | D19: 46163 | E19: 26.07 Sprint 1 | F19: Arvinth | G19: 27341 | H19: MFOH (26.5 Regression) - A console error occurs when values are entered into the text box in the Virginia SNP-14 Report | I19: Story Completed | J19: 0 | K19: 0 | L19: 0 | M19: 46147 | N19: 46147 | O19: Arvinth | P19: Alpha | Q19: None | R19: Alpha | S19: None | T19: 48888 | U19: 46148 | V19: 46148 | W19: NA | X19: NA | Y19: Ying | Z19: 46148 | AA19: None | AB19: NA | AC19: NA | AD19: Regression Defects
A20: 9 | B20: FOH | C20: 46136 | D20: 46163 | E20: 26.07 Sprint 1 Stretch | F20: Atchaiah | G20: 53167 | H20: MFOH [BAU] - Automation (51454) | I20: Story Being Developed | J20: 3 | M20: 46149
A21: 19 | B21: FOH | C21: 46136 | D21: 46163 | E21: 26.07 Sprint 1 Stretch | F21: Alpha | G21: 48515 | H21: MFOH [WAVE] - Add a Language tab to Student Status | I21: Story Being Developed | J21: 5 | K21: 2.5 | L21: 10
A22: 20 | B22: FOH | C22: 46136 | D22: 46163 | E22: 26.07 Sprint 1 Stretch | F22: Atchaiah | G22: 53272 | H22: MFOH - Automation (Kaleida Changes) | I22: Story Being Developed | J22: 3 | M22: 46155
A23: 22 | B23: FOH | C23: 46136 | D23: 46163 | E23: 26.07 Sprint 1 Stretch | F23: Arvinth | G23: 52175 | H23: [WAVE] Mosaic FOH - Language - Menu Product Translation | I23: Story Being Developed | J23: 13 | K23: 1.5 | L23: 6 | M23: 46156

Sheet 26.07 Sprint 1-Defect
A1: S.No | B1: Sprint # | C1: Story/Defect ID | D1: Parent Story | E1: Developer | F1: Issue Type | G1: Issue Description | H1: Priority | I1: Defect Source | J1: Type | K1: Status | L1: Root Cause Category | M1: Comments
B2: 26.07 Sprint 1 | D2: 51323 | E2: Sabir | F2: Defect | G2: The partial view 'VoidReasonMaintenance_General' was not found | H2: Major | I2: Manual | J2: External | K2: Defect Fixed | L2: Development | M2: Missed commiting file before PR

Sheet 26.05 Sprint 4-Status
A1: S.No | B1: Application Name | C1: Sprint Start Date | D1: Sprint End Date | E1: Sprint | F1: Developer | G1: Story ID/Defect ID | H1: Description | I1: Status | J1: Estimated(hrs/sp) | K1: Actual(hrs/sp) | L1: Actual Worklog (Hours) | M1: Dev Start Date | N1: Dev End Date | O1: Unit testing | P1: Peer Tested By | Q1: Peer Tested Comments, if any | R1: Peer Reviewed By | S1: Peer Code Review Comments, if any | T1: PR Number/Link | U1: PR Created Date | V1: PR Approved Date | W1: Onsite Lead Code Review | X1: Code Review Comments, if any | Y1: Client Code Review | Z1: Approved Date | AA1: Code Review Comments, if any2 | AB1: Internal PO -POV Comments | AC1: Client PO -POV Comments | AD1: Comments | AE1: Does this story meet expectations?
A2: 1 | B2: FOH | C2: 46122 | D2: 46135 | E2: 26.05 Sprint 4 | F2: Alpha/Atchaiah | G2: 52792 | H2: Mosaic - FOH 26.5 (Regression) - Eligibility (F&R) | I2: Story Completed | J2: 5 | K2: 7.75 | L2: 31 | M2: 46122 | N2: 46127 | O2: NA | P2: NA | Q2: NA | R2: NA | S2: NA | T2: NA | U2: NA | V2: NA | W2: NA | X2: NA | Y2: NA | Z2: NA | AA2: NA | AB2: NA | AC2: NA | AD2: We also fixed regression defects in this story
A3: 2 | B3: =Dashboard!$J$1 -> FOH | C3: 46122 | D3: 46135 | E3: 26.05 Sprint 4 | F3: Ashwin/Atchaiah | G3: 52788 | H3: Mosaic - FOH 26.5(Regression) - End of Day | I3: Story Completed | J3: 5 | K3: 5.75 | L3: 23 | M3: 46122 | N3: 46132 | O3: NA | P3: NA | Q3: NA | R3: NA | S3: NA | T3: NA | U3: NA | V3: NA | W3: NA | X3: NA | Y3: NA | Z3: NA | AA3: NA | AB3: NA | AC3: NA | AD3: We also fixed regression defects in this story
A4: 3 | B4: =Dashboard!$J$1 -> FOH | C4: 46122 | D4: 46135 | E4: 26.05 Sprint 4 | F4: Ashwin/Atchaiah | G4: 52790 | H4: Mosaic - FOH 26.5 (Regression) - POS(Menu Option) | I4: Story Completed | J4: 2 | K4: 2.75 | L4: 11 | M4: 46126 | N4: 46128 | O4: NA | P4: NA | Q4: NA | R4: NA | S4: NA | T4: NA | U4: NA | V4: NA | W4: NA | X4: NA | Y4: NA | Z4: NA | AA4: NA | AB4: NA | AC4: NA | AD4: We also fixed regression defects in this story
A5: 4 | B5: =Dashboard!$J$1 -> FOH | C5: 46122 | D5: 46135 | E5: 26.05 Sprint 4 | F5: Atchaiah/Venkat | G5: 52787 | H5: Mosaic - FOH 26.5(Regression) - Students | I5: Story Completed | J5: 5 | K5: 2.5 | L5: 30.5 | M5: 46122 | N5: 46129 | O5: NA | P5: NA | Q5: NA | R5: NA | S5: NA | T5: NA | U5: NA | V5: NA | W5: NA | X5: NA | Y5: NA | Z5: NA | AA5: NA | AB5: NA | AC5: NA | AD5: We also fixed regression defects in this story
A6: 5 | B6: =Dashboard!$J$1 -> FOH | C6: 46122 | D6: 46135 | E6: 26.05 Sprint 4 | F6: Atchaiah/Subbu | G6: 52797 | H6: Mosaic - FOH 26.5(Regression) - Setup | I6: Story Completed | J6: 8 | K6: 10.25 | L6: 41 | M6: 46122 | N6: 46129 | O6: NA | P6: NA | Q6: NA | R6: NA | S6: NA | T6: NA | U6: NA | V6: NA | W6: NA | X6: NA | Y6: NA | Z6: NA | AA6: NA | AB6: NA | AC6: NA | AD6: We also fixed regression defects in this story
A7: 6 | B7: FOH | C7: 46122 | D7: 46135 | E7: 26.05 Sprint 4 | F7: Alpha | G7: 52335 | H7: Mosaic FOH - QA/PM - Spending Limits from MSB - End-to-End Test in Prod | I7: Story Completed | J7: 1 | K7: 1 | L7: 4 | M7: NA | N7: NA | O7: NA | P7: NA | Q7: NA | R7: NA | S7: NA | T7: NA | U7: NA | V7: NA | W7: NA | X7: NA | Y7: NA | Z7: NA | AA7: NA | AB7: NA | AC7: NA | AD7: Manual Testing story
A8: 7 | B8: FOH | C8: 46122 | D8: 46135 | E8: 26.05 Sprint 4 | F8: Ashwin | G8: 27239 | H8: MFOH (26.5 Regression) - In Open Previous Day, apply filter is not working after clicking reset selection in any filter | I8: Defect Fixed | J8: 0 | K8: 0 | L8: 0 | M8: 46132 | N8: 46132 | O8: Ashwin | P8: Arvinth | Q8: None | R8: Alpha | S8: None | T8: 48589 | U8: 46134 | V8: 46134 | W8: NA | X8: NA | Y8: Ying | Z8: 46134 | AA8: None | AB8: NA | AC8: NA | AD8: Regression defect
A9: 8 | B9: FOH | C9: 46122 | D9: 46135 | E9: 26.05 Sprint 4 | F9: Ashwin | G9: 27240 | H9: MFOH (26.5 Regression) - Checkbox is unchecking after clicking cancel | I9: Defect Fixed | J9: 0 | K9: 0 | L9: 0 | M9: 46132 | N9: 46132 | O9: Ashwin | P9: Arvinth | Q9: None | R9: Alpha | S9: Remove unwanted code | T9: 48590 | U9: 46134 | V9: 46134 | W9: NA | X9: NA | Y9: Ying | Z9: 46134 | AA9: None | AB9: NA | AC9: NA | AD9: Regression defect
A10: 9 | B10: FOH | C10: 46122 | D10: 46135 | E10: 26.05 Sprint 4 | F10: Ashwin | G10: 27250 | H10: MFOH (26.5 Regression) - While trying to assign a Bus/Route using an existing Route Name, a validation message appears. After clicking OK on the error | I10: Defect Fixed | J10: 0 | K10: 0 | L10: 0 | M10: 46134 | N10: 46134 | O10: Ashwin | P10: Arvinth | Q10: None | R10: Alpha | S10: None | T10: 48593 | U10: 46134 | V10: 46134 | W10: NA | X10: NA | Y10: Ying | Z10: 46134 | AA10: None | AB10: NA | AC10: NA | AD10: Regression defect
A11: 10 | B11: FOH | C11: 46122 | D11: 46135 | E11: 26.05 Sprint 4 | F11: Arvinth | G11: 27242 | H11: MFOH (26.5 Regression) - Horizontal/VerticalScroll bar is showing in Employee screen | I11: Defect Fixed | J11: 0 | K11: 0 | L11: 0 | M11: 46132 | N11: 46132 | O11: Arvinth | P11: NA | Q11: NA | R11: NA | S11: NA | T11: 48544 | U11: 46133 | V11: 46133 | W11: NA | X11: NA | Y11: Ying | Z11: 46133 | AA11: None | AB11: NA | AC11: NA | AD11: Regression defect
A12: 11 | B12: FOH | C12: 46122 | D12: 46135 | E12: 26.05 Sprint 4 | F12: Arvinth | G12: 27244 | H12: MFOH (26.5 Regression) - Horizontal Scroll bar is showing in Meals Price Template popup | I12: Defect Fixed | J12: 0 | K12: 0 | L12: 0 | M12: 46132 | N12: 46132 | O12: Arvinth | P12: NA | Q12: NA | R12: NA | S12: NA | T12: 48545 | U12: 46133 | V12: 46133 | W12: NA | X12: NA | Y12: Ying | Z12: 46133 | AA12: None | AB12: NA | AC12: NA | AD12: Regression defect
A13: 12 | B13: FOH | C13: 46122 | D13: 46135 | E13: 26.05 Sprint 4 | F13: Arvinth/Venkat | G13: 27245 | H13: MFOH (26.5 Regression) - Meal Price Template is not showing while adding or updating the Menu product images | I13: Defect Fixed | J13: 0 | K13: 0 | L13: 0 | M13: 46134 | N13: 46134 | O13: Arvinth | P13: NA | Q13: NA | R13: NA | S13: NA | T13: 48599 | U13: 46134 | V13: 46134 | W13: NA | X13: NA | Y13: Ying | Z13: 46134 | AA13: None | AB13: NA | AC13: NA | AD13: Regression defect
A14: 13 | B14: FOH | C14: 46122 | D14: 46135 | E14: 26.05 Sprint 4 | F14: Arvinth | G14: 27246 | H14: MFOH (26.5 Regression) - In Vega UI, Not getting "No Manager Servers Found" error message popup | I14: Defect Fixed | J14: 0 | K14: 0 | L14: 0 | M14: 46132 | N14: 46132 | O14: Arvinth | P14: NA | Q14: NA | R14: NA | S14: NA | T14: 48546 | U14: 46134 | V14: 46134 | W14: NA | X14: NA | Y14: Ying | Z14: 46134 | AA14: None | AB14: NA | AC14: NA | AD14: Regression defect
A15: 14 | B15: FOH | C15: 46122 | D15: 46135 | E15: 26.05 Sprint 4 | F15: Venkat | G15: 27248 | H15: MFOH (26.5 Regression) - If I Uncheck any row checkbox then the header checkbox is unchecked | I15: Defect Fixed | J15: 0 | K15: 0 | L15: 0 | M15: 46132 | N15: 46132 | O15: Venkat | P15: Arvinth | Q15: None | R15: Arvinth | S15: None | T15: 48553 | U15: 46133 | V15: 46133 | W15: NA | X15: NA | Y15: Ying | Z15: 46133 | AA15: None | AB15: NA | AC15: NA | AD15: Regression defect
A16: 15 | B16: FOH | C16: 46122 | D16: 46135 | E16: 26.05 Sprint 4 | F16: Venkat | G16: 27249 | H16: MFOH (26.5 Regression) - Check all checkbox not unchecking when any of the below row checkbox is unchecked | I16: Defect Fixed | J16: 0 | K16: 0 | L16: 0 | M16: 46132 | N16: 46132 | O16: Venkat | P16: Arvinth | Q16: None | R16: Arvinth | S16: None | T16: 48554 | U16: 46133 | V16: 46133 | W16: NA | X16: NA | Y16: Ying | Z16: 46133 | AA16: None | AB16: NA | AC16: NA | AD16: Regression defect
A17: 16 | B17: FOH | C17: 46122 | D17: 46135 | E17: 26.05 Sprint 4 | F17: Venkat | G17: 27251 | H17: MFOH (26.5 Regression) - Sorting is not working properly in Student Search | I17: Defect Fixed | J17: 0 | K17: 0 | L17: 0 | M17: 46134 | N17: 46134 | O17: Venkat | P17: Arvinth | Q17: None | R17: Arvinth | S17: None | T17: 48592 | U17: 46134 | V17: 46134 | W17: NA | X17: NA | Y17: Ying | Z17: 46134 | AA17: None | AB17: NA | AC17: NA | AD17: Regression defect
A18: 17 | B18: FOH | C18: 46122 | D18: 46135 | E18: 26.05 Sprint 4 Stretch | F18: Alpha | G18: 27213 | H18: MFOH - Fix the dashboard issues with Save in Edit Mode and the character length of site | I18: Story Ready For Testing | J18: 2 | K18: 0.75 | L18: 3 | M18: 46128 | N18: 46128 | O18: Alpha | P18: NA | Q18: NA | R18: NA | S18: NA | T18: 48468 | U18: 46128 | V18: 46128 | W18: NA | X18: NA | Y18: Steve | Z18: 46128 | AA18: None | AB18: NA | AC18: NA
A19: 18 | B19: FOH | C19: 46122 | D19: 46135 | E19: 26.05 Sprint 4 Stretch | F19: Atchaiah | G19: 52649 | H19: MFOH [BAU] - Automation (51453) | I19: Story Being Developed | J19: 1 | M19: 46122 | AD19: Carry forward due to release regression.
A20: 19 | B20: FOH | C20: 46122 | D20: 46135 | E20: 26.05 Sprint 4 Stretch | F20: Venkat | G20: 52827 | H20: MFOH - Update Federal IEGs (2026-27) | I20: Story Ready For Testing | J20: 2 | K20: 1.5 | L20: 6 | M20: 46122 | N20: 46125 | O20: Venkat | P20: Alpha | Q20: None | R20: Alpha | S20: None | T20: 48388 | U20: 46125 | V20: 46125 | W20: NA | X20: NA | Y20: Steve | Z20: 46125 | AA20: None | AB20: None | AC20: None
A21: 20 | B21: FOH | C21: 46122 | D21: 46135 | E21: 26.05 Sprint 4 Stretch | F21: Alpha | G21: 52794 | H21: Mosaic - FOH 26.5 (Regression) - Reports - Eligibility (F&R) | I21: Story Being Tested | J21: 3 | M21: 46127
A22: 21 | B22: FOH | C22: 46122 | D22: 46135 | E22: 26.05 Sprint 4 Stretch | F22: Atchaiah | G22: 52791 | H22: Mosaic - FOH 26.5(Regression) - Utilities | I22: Story Being Tested | J22: 5 | K22: 1.5 | L22: 6

Sheet 26.05 Sprint 4-Defect
A1: S.No | B1: Sprint # | C1: Story/Defect ID | D1: Parent Story | E1: Developer | F1: Issue Type | G1: Issue Description | H1: Priority | I1: Defect Source | J1: Type | K1: Status | L1: Root Cause Category | M1: Comments
B2: 26.05 Sprint 4 | C2: 27245 | D2: NA | E2: Arvinth/Venkat | F2: Bounceback/Sub-Defect | G2: MFOH (26.5 Regression) - Meal Price Template is not showing while adding or updating the Menu product images | H2: Minor | I2: Manual | J2: Internal | K2: Defect Fixed | L2: Existing_Issues | M2: Data not retaining while uploading image

Sheet 26.05 Sprint 3-Status
A1: S.No | B1: Application Name | C1: Sprint Start Date | D1: Sprint End Date | E1: Sprint | F1: Developer | G1: Story ID/Defect ID | H1: Description | I1: Status | J1: Estimated(hrs/sp) | K1: Actual(hrs/sp) | L1: Actual Worklog (Hours) | M1: Dev Start Date | N1: Dev End Date | O1: Unit testing | P1: Peer Tested By | Q1: Peer Tested Comments, if any | R1: Peer Reviewed By | S1: Peer Code Review Comments, if any | T1: PR Number/Link | U1: PR Created Date | V1: PR Approved Date | W1: Onsite Lead Code Review | X1: Code Review Comments, if any | Y1: Client Code Review | Z1: Approved Date | AA1: Code Review Comments, if any2 | AB1: Internal PO -POV Comments | AC1: Client PO -POV Comments | AD1: Comments | AE1: Does this story meet expectations?
A2: 1 | B2: FOH | C2: 46108 | D2: 46121 | E2: 26.05 Sprint 3 | F2: Arvinth/Venkat | G2: 51698 | H2: Mosaic FOH - Snyk Findings - Path Traversal - UtilitiesController.cs- Unsanitized input flows into global::System.IO.Directory.Exists | I2: Story Completed | J2: 5 | K2: 4.75 | L2: 18 | M2: 46119 | N2: 46120 | O2: Venkat | P2: Ashwin | Q2: None | R2: Alpha | S2: None | T2: 48316 | U2: 46120 | V2: 46120 | W2: NA | X2: NA | Y2: Steve | Z2: 46120 | AA2: None | AB2: NA | AC2: NA
A3: 2 | B3: FOH | C3: 46108 | D3: 46121 | E3: 26.05 Sprint 3 | F3: Atchaiah | G3: 52527 | H3: MFOH-FOHBetaReleaseCheckOut Test changes update | I3: Story Completed | J3: 2 | K3: 2 | L3: 8 | M3: 46107 | N3: 46108 | O3: NA | P3: NA | Q3: NA | R3: NA | S3: NA | T3: 48057 | U3: 46108 | V3: 46108 | W3: NA | X3: NA | Y3: Steve | Z3: 46108 | AA3: None | AB3: NA | AC3: NA
A4: 3 | B4: FOH | C4: 46108 | D4: 46121 | E4: 26.05 Sprint 3 | F4: Ashwin | G4: 52372 | H4: MFOH [WAVE] - Add a 'Reimbursable Meal' column to Real Time Transactions grid | I4: Story Completed | J4: 3 | K4: 1.5 | L4: 6 | M4: 46108 | N4: 46111 | O4: Ashwin | P4: Arvinth | Q4: None | R4: Arvinth | S4: None | T4: 48169 | U4: 46113 | V4: 46113 | W4: NA | X4: NA | Y4: Steve | Z4: 46113 | AA4: None | AB4: NA | AC4: NA
A5: 4 | B5: FOH | C5: 46108 | D5: 46121 | E5: 26.05 Sprint 3 | F5: Alpha/Subbu | G5: 51891 | H5: MFOH [WAVE] - Modify the Dashboard Setup Maintenance (Allow to add Widgets one by one) | I5: Story Completed | J5: 5 | K5: 1.5 | L5: 6 | M5: 46108 | N5: 46111 | O5: Alpha | P5: Subbu | Q5: 2 new peer testing comments; the new parameter name was not replaced in all the areas. Additionally, we have fixed the 3 existing issues as well. | R5: NA | S5: NA | T5: NA | U5: NA | V5: NA | W5: NA | X5: NA | Y5: NA | Z5: NA | AA5: NA | AB5: NA | AC5: NA
A6: 5 | B6: FOH | C6: 46108 | D6: 46121 | E6: 26.05 Sprint 3 | F6: Ashwin | G6: 52328 | H6: MFOH - Modify the labels in the Home Site when the student has an offsite sale in a different school | I6: Story Completed | J6: 3 | K6: 1.25 | L6: 5 | M6: 46112 | N6: 46114 | O6: Ashwin | P6: Arvinth | Q6: None | R6: Arvinth | S6: None | T6: 48168 | U6: 46113 | V6: 46113 | W6: NA | X6: NA | Y6: Steve | Z6: 46113 | AA6: None | AB6: NA | AC6: NA
A7: 6 | B7: FOH | C7: 46108 | D7: 46121 | E7: 26.05 Sprint 3 | F7: Alpha | G7: 27127 | H7: MFOH - The SAVE is broken (Custom Reports) | I7: Story Being Tested | J7: 2 | K7: 0.75 | L7: 3 | M7: 46118 | N7: 46118 | O7: Alpha | P7: NA | Q7: NA | R7: Venkat | S7: None | T7: 48242 | U7: 46118 | V7: 46118 | W7: NA | X7: NA | Y7: Steve | Z7: 46118 | AA7: None | AB7: NA | AC7: NA | AD7: Testing is in progress by Oniste QA.
A8: 7 | B8: FOH | C8: 46108 | D8: 46121 | E8: 26.05 Sprint 3 | F8: Alpha | G8: 27136 | H8: MFOH - Custom Report Import Format is broken | I8: Story Completed | J8: 2 | K8: 0.75 | L8: 3 | M8: 46118 | N8: 46118 | O8: Alpha | P8: NA | Q8: NA | R8: Venkat | S8: None | T8: 48243 | U8: 46118 | V8: 46118 | W8: NA | X8: NA | Y8: Steve | Z8: 46118 | AA8: None | AB8: NA | AC8: NA
A9: 8 | B9: FOH | C9: 46108 | D9: 46121 | E9: 26.05 Sprint 3 | F9: Alpha | G9: 51697 | H9: Mosaic FOH - Snyk Findings - Path Traversal - UtilitiesController.cs- Unsanitized input flows into global::System.IO.StreamWriter | I9: Story Completed | J9: 2 | K9: 0 | L9: 0 | M9: NA | N9: NA | O9: NA | P9: NA | Q9: NA | R9: NA | S9: NA | T9: NA | U9: NA | V9: NA | W9: NA | X9: NA | Y9: NA | Z9: NA | AA9: NA | AB9: NA | AC9: NA
A10: 9 | B10: FOH | C10: 46108 | D10: 46121 | E10: 26.05 Sprint 3 | F10: Ashwin/Alpha | G10: 26996 | H10: MFOH - Daily School Attendance Import - Add support to import 0 as an attendance number | I10: Story Completed | J10: 1 | K10: 0.5 | L10: 2 | M10: 46119 | N10: 46119 | O10: Ashwin | P10: Alpha | Q10: None | R10: Arvinth | S10: None | T10: 48270 | U10: 46119 | V10: 46119 | W10: NA | X10: NA | Y10: Steve | Z10: 46119 | AA10: None | AB10: NA | AC10: NA
A11: 10 | B11: FOH | C11: 46108 | D11: 46121 | E11: 26.05 Sprint 3 | F11: Ashwin/Alpha | G11: 26902 | H11: MFOH - POS Roster Report Serving Line Note Length | I11: Story Completed | J11: 2 | K11: 2 | L11: 8 | M11: 46119 | N11: 46119 | O11: Ashwin | P11: Alpha | Q11: None | R11: Arvinth | S11: None | T11: 48271 | U11: 46119 | V11: 46119 | W11: NA | X11: NA | Y11: Steve | Z11: 46119 | AA11: None | AB11: NA | AC11: NA
A12: 11 | B12: FOH | C12: 46108 | D12: 46121 | E12: 26.05 Sprint 3 | F12: Atchaiah | G12: 49620 | H12: [WAVE] Mosaic FOH- Test Import of Student Application data into Mosaic from WebSMARTT | I12: Story Completed | J12: 2 | K12: 2 | L12: 8 | M12: 46119 | N12: 46120 | O12: NA | P12: NA | Q12: NA | R12: NA | S12: NA | T12: NA | U12: NA | V12: NA | W12: NA | X12: NA | Y12: NA | Z12: NA | AA12: NA | AB12: NA | AC12: NA
A13: 12 | B13: FOH | C13: 46108 | D13: 46121 | E13: 26.05 Sprint 3 | F13: Venkat | G13: 27125 | H13: MFOH - Meal Report - Aggerate Totals: No - Does not list schools in order | I13: Story Completed | J13: 2 | K13: 1.25 | L13: 5 | M13: 46120 | N13: 46120 | O13: Venkat | P13: Alpha | Q13: None | R13: Alpha | S13: None | T13: 48251 | U13: 46118 | V13: 46118 | W13: NA | X13: NA | Y13: Steve | Z13: 46118 | AA13: 46118 | AB13: NA | AC13: NA
A14: 13 | B14: FOH | C14: 46108 | D14: 46121 | E14: 26.05 Sprint 3 | F14: Atchaiah | G14: 49622 | H14: [WAVE] Mosaic FOH- Test Import of Student Application history data into Mosaic from WebSMARTT | I14: Story Completed | J14: 1 | K14: 1 | L14: 4 | M14: 46120 | N14: 46121 | O14: NA | P14: NA | Q14: NA | R14: NA | S14: NA | T14: NA | U14: NA | V14: NA | W14: NA | X14: NA | Y14: NA | Z14: NA | AA14: NA | AB14: NA | AC14: NA
A15: 14 | B15: FOH | C15: 46108 | D15: 46121 | E15: 26.05 Sprint 3 | F15: Atchaiah | G15: 49623 | H15: [WAVE] Mosaic FOH- Test Import of POS transactions data into Mosaic from WebSMARTT | I15: Story Completed | J15: 1 | K15: 1 | L15: 4 | M15: 46121 | N15: 46121 | O15: NA | P15: NA | Q15: NA | R15: NA | S15: NA | T15: NA | U15: NA | V15: NA | W15: NA | X15: NA | Y15: NA | Z15: NA | AA15: NA | AB15: NA | AC15: NA
A16: 15 | B16: FOH | C16: 46108 | D16: 46121 | E16: 26.05 Sprint 3 | F16: Atchaiah | G16: 49624 | H16: [WAVE] Mosaic FOH- Test Import of Student Record history data into Mosaic from WebSMARTT | I16: Story Completed | J16: 1 | K16: 1 | L16: 4 | M16: 46121 | N16: 46121 | O16: NA | P16: NA | Q16: NA | R16: NA | S16: NA | T16: NA | U16: NA | V16: NA | W16: NA | X16: NA | Y16: NA | Z16: NA | AA16: NA | AB16: NA | AC16: NA
A17: 16 | B17: FOH | C17: 46108 | D17: 46121 | E17: 26.05 Sprint 3 Stretch | F17: Venkat | G17: 52256 | H17: Mosaic FOH - Open Previous Day Maintenance - Add Multiselect Site & Convert Screen to Vega | I17: Story Being Developed | J17: 3 | K17: 2 | L17: 8 | M17: 46108 | N17: 46115 | O17: Venkat | P17: Alpha | Q17: Error during delete the existing entry. | R17: Alpha | S17: Revision histories, commented codes and formatting, unused codes and improvements to the codes. | AD17: Moved into stretch and worked on the remaining sprint items.
A18: 17 | B18: FOH | C18: 46108 | D18: 46121 | E18: 26.05 Sprint 3 Stretch | F18: Atchaiah | G18: 52569 | H18: MFOH [BAU] - Automation (51314) | I18: Story Completed | J18: 2 | K18: 2 | L18: 8 | M18: 46111 | N18: 46112 | O18: NA | P18: NA | Q18: NA | R18: NA | S18: NA | T18: 48162 | U18: 46113 | V18: 46113 | W18: NA | X18: NA | Y18: Steve | Z18: 46113 | AA18: None | AB18: NA | AC18: NA
A19: 18 | B19: FOH | C19: 46108 | D19: 46121 | E19: 26.05 Sprint 3 Stretch | F19: Atchaiah | G19: 52570 | H19: MFOH [BAU] - Automation (49449) | I19: Story Completed | J19: 1 | K19: 1 | L19: 4 | M19: 46113 | N19: 46114 | O19: NA | P19: NA | Q19: NA | R19: NA | S19: NA | T19: 48211 | U19: 46114 | V19: 46114 | W19: NA | X19: NA | Y19: Steve | Z19: 46114 | AA19: None | AB19: NA | AC19: NA
A20: 19 | B20: FOH | C20: 46108 | D20: 46121 | E20: 26.05 Sprint 3 Stretch | F20: Arvinth/Ashwin | G20: 51944 | H20: Mosaic FOH - Implement New Design for the Admin View of Real-time Transactions | I20: Story Completed | J20: 13 | K20: 8.5 | L20: 34 | M20: 46111 | N20: 46114 | O20: Arvinth/Ashwin | P20: Alpha | Q20: Increase the grid height. Apply filter is not enabling sometimes. | R20: Alpha | S20: None | T20: 48322 | U20: 46121 | V20: 46121 | W20: NA | X20: NA | Y20: Steve | Z20: 46121 | AA20: None | AB20: NA | AC20: NA
A21: 20 | B21: FOH | C21: 46108 | D21: 46121 | E21: 26.05 Sprint 3 Stretch | F21: Atchaiah | G21: 52649 | H21: MFOH [BAU] - Automation (51453) | I21: Story Being Developed | J21: 1 | K21: 0 | L21: 0 | M21: 46118 | AD21: Kept on hold due to test legacy import sprint items

Sheet 26.05 Sprint 3-Defect
A1: S.No | B1: Sprint # | C1: Story/Defect ID | D1: Parent Story | E1: Developer | F1: Issue Type | G1: Issue Description | H1: Priority | I1: Defect Source | J1: Type | K1: Status | L1: Root Cause Category | M1: Comments

Sheet 26.5 - Sprint 2-Status
A1: S.No | B1: Application Name | C1: Sprint Start Date | D1: Sprint End Date | E1: Sprint | F1: Developer | G1: Story ID/Defect ID | H1: Description | I1: Status | J1: Estimated(hrs/sp) | K1: Actual(hrs/sp) | L1: Actual Worklog (Hours) | M1: Dev Start Date | N1: Dev End Date | O1: Unit testing | P1: Peer Tested By | Q1: Peer Tested Comments, if any | R1: Peer Reviewed By | S1: Peer Code Review Comments, if any | T1: PR Number/Link | U1: PR Created Date | V1: PR Approved Date | W1: Onsite Lead Code Review | X1: Code Review Comments, if any | Y1: Client Code Review | Z1: Approved Date | AA1: Code Review Comments, if any2 | AB1: Internal PO -POV Comments | AC1: Client PO -POV Comments | AD1: Comments | AE1: Does this story meet expectations?
A2: 1 | B2: FOH | C2: 46094 | D2: 46107 | E2: 26.5 - Sprint 2 | F2: Arvinth | G2: 52287 | H2: Mosaic FOH - Exports - Tyler Technologies Financial Export (Cherokee County Schools, SC) | I2: Story Completed | J2: 13 | K2: 9 | L2: 36 | M2: 46094 | N2: 46106 | O2: Arvinth | P2: Ashwin | Q2: None | R2: Alpha | S2: None | T2: 48019 | U2: 46106 | V2: 46106 | W2: NA | X2: NA | Y2: Steve | Z2: 46106 | AA2: None | AB2: None | AC2: None | AE2: Meets Expectation
A3: 2 | B3: FOH | C3: 46094 | D3: 46107 | E3: 26.5 - Sprint 2 | F3: Atchaiah | G3: 52279 | H3: MFOH - Automation (Professional standards screens) | I3: Story Completed | J3: 2 | K3: 2 | L3: 8 | M3: 46094 | N3: 46097 | O3: NA | P3: NA | Q3: NA | R3: NA | S3: NA | T3: 47856 | U3: 46098 | V3: 46098 | W3: NA | X3: NA | Y3: Steve | Z3: 46098 | AA3: None | AB3: NA | AC3: NA | AE3: Meets Expectation
A4: 3 | B4: FOH | C4: 46094 | D4: 46107 | E4: 26.5 - Sprint 2 | F4: Ashwin | G4: 52229 | H4: Mosaic FOH - Custom Reports - Sort Alphabetically | I4: Story Completed | J4: 3 | K4: 1.5 | L4: 6 | M4: 46094 | N4: 46097 | O4: Ashwin | P4: Arvinth | Q4: None | R4: Arvinth | S4: None | T4: 47860 | U4: 46098 | V4: 46098 | W4: NA | X4: NA | Y4: Steve | Z4: 46098 | AA4: None | AB4: None | AC4: None | AE4: Meets Expectation
A5: 4 | B5: FOH | C5: 46094 | D5: 46107 | E5: 26.5 - Sprint 2 | F5: Ashwin | G5: 26967 | H5: MFOH (26.1) - Close Day - Reopened By does not list the User | I5: Story Completed | J5: 3 | K5: 1.5 | L5: 6 | M5: 46097 | N5: 46098 | O5: Ashwin | P5: Arvinth | Q5: None | R5: Arvinth | S5: None | T5: 47859 | U5: 46098 | V5: 46098 | W5: NA | X5: NA | Y5: Steve | Z5: 46098 | AA5: None | AB5: None | AC5: None | AE5: Meets Expectation
A6: 5 | B6: FOH | C6: 46094 | D6: 46107 | E6: 26.5 - Sprint 2 | F6: Atchaiah | G6: 52338 | H6: Mosaic FOH - QA - POS API Apigee; WAF (Time Log) | I6: Story Completed | J6: 8 | K6: 3.75 | L6: 15 | M6: 46101 | N6: 46105 | O6: NA | P6: NA | Q6: NA | R6: NA | S6: NA | T6: NA | U6: NA | V6: NA | W6: NA | X6: NA | Y6: NA | Z6: NA | AA6: NA | AB6: NA | AC6: NA | AD6: carryforwaded from the client as we get WAF issues in server
A7: 6 | B7: FOH | C7: 46094 | D7: 46107 | E7: 26.5 - Sprint 2 | F7: Venkat | G7: 52253 | H7: MFOH - Bundle Sites based on Site ID (Georgia DE106 Export) | I7: Story Completed | J7: 3 | K7: 2.87 | L7: 11.5 | M7: 46094 | N7: 46098 | O7: Venkat | P7: Ashwin | Q7: NA | R7: Arvinth | S7: NA | T7: 47932 | U7: 46101 | V7: 46101 | W7: NA | X7: NA | Y7: Steve | Z7: 46101 | AA7: None | AB7: None | AC7: None | AE7: Meets Expectation
A8: 7 | B8: FOH | C8: 46094 | D8: 46107 | E8: 26.5 - Sprint 2 Stretch | F8: Atchaiah | G8: 52331 | H8: MFOH - Automation - Kaleida changes update to the Report Scheduler | I8: Story Completed | J8: 2 | K8: 2 | L8: 12 | M8: 46098 | N8: 46099 | O8: NA | P8: NA | Q8: NA | R8: NA | S8: NA | T8: 47893 | U8: 46099 | V8: 46099 | W8: NA | X8: NA | Y8: Steve | Z8: 46099 | AA8: None | AB8: NA | AC8: NA | AD8: Worked on the Professional standards screens for 1SP additionally. | AE8: Meets Expectation
A9: 8 | B9: FOH | C9: 46094 | D9: 46107 | E9: 26.5 - Sprint 2 Stretch | F9: Arvinth | G9: 52420 | H9: MFOH - Create a Script to generate some sample data from Prod sites for Aramark | I9: Story Completed | J9: 3 | K9: 3 | L9: 12 | M9: 46099 | N9: 46100 | O9: Arvinth | P9: NA | Q9: NA | R9: NA | S9: NA | T9: NA | U9: NA | V9: NA | W9: NA | X9: NA | Y9: NA | Z9: NA | AA9: NA | AB9: NA | AC9: NA | AD9: Gary requested this script | AE9: Meets Expectation
A10: 9 | B10: FOH | C10: 46094 | D10: 46107 | E10: 26.5 - Sprint 2 Stretch | F10: Alpha | G10: 51891 | H10: MFOH [WAVE] - Modify the Dashboard Setup Maintenance (Allow to add Widgets one by one) | I10: Story Ready For Testing | J10: 13 | K10: 10.5 | L10: 42 | M10: 46094 | N10: 46106 | O10: Alpha | P10: Subbulakshmi | Q10: Cosmetic issues, existing Dashboard is not working properly for the new implementation | R10: Arvinth | S10: Label change, Missing parameter in one method. | T10: 48024 | U10: 46106 | V10: 46106 | W10: NA | X10: NA | Y10: Steve | Z10: 46106 | AA10: None
A11: 10 | B11: FOH | C11: 46094 | D11: 46107 | E11: 26.5 - Sprint 2 Stretch | F11: Venkat | G11: 52256 | H11: Mosaic FOH - Open Previous Day Maintenance - Add Multiselect Site & Convert Screen to Vega | I11: Story Being Developed | J11: 5 | K11: 4.5 | L11: 18 | M11: 46101
A12: 11 | B12: FOH | C12: 46094 | D12: 46107 | E12: 26.5 - Sprint 2 Stretch | F12: Ashwin | G12: 51944 | H12: [WAVE] Mosaic FOH - Implement New Design for the Admin View of Real-time Transactions | I12: Story Being Developed | J12: 13 | K12: 0 | L12: 0 | M12: 46098
A13: 12 | B13: FOH | C13: 46094 | D13: 46107 | E13: 26.5 - Sprint 2 Stretch | F13: Ashwin | G13: 26996 | H13: MFOH - Daily School Attendance Import - Add support to import 0 as an attendance number | I13: Story Being Developed | J13: 0 | K13: 0 | L13: 0 | M13: 46099
A14: 13 | B14: FOH | C14: 46094 | D14: 46107 | E14: 26.5 - Sprint 2 Stretch | F14: Ashwin | G14: 26902 | H14: MFOH - POS Roster Report Serving Line Note Length | I14: Story Being Developed | J14: 2 | K14: 0 | L14: 0 | M14: 46100

Sheet 26.5 - Sprint 2-Defect
A1: S.No | B1: Sprint # | C1: Story/Defect ID | D1: Parent Story | E1: Developer | F1: Issue Type | G1: Issue Description | H1: Priority | I1: Defect Source | J1: Type | K1: Status | L1: Root Cause Category | M1: Comments

Sheet 26.5 - Sprint 1-Status
A1: S.No | B1: Application Name | C1: Sprint Start Date | D1: Sprint End Date | E1: Sprint | F1: Developer | G1: Story ID/Defect ID | H1: Description | I1: Status | J1: Estimated(hrs/sp) | K1: Actual(hrs/sp) | L1: Actual Worklog (Hours) | M1: Dev Start Date | N1: Dev End Date | O1: Unit testing | P1: Peer Tested By | Q1: Peer Tested Comments, if any | R1: Peer Reviewed By | S1: Peer Code Review Comments, if any | T1: PR Number/Link | U1: PR Created Date | V1: PR Approved Date | W1: Onsite Lead Code Review | X1: Code Review Comments, if any | Y1: Client Code Review | Z1: Approved Date | AA1: Code Review Comments, if any2 | AB1: Internal PO -POV Comments | AC1: Client PO -POV Comments | AD1: Comments | AE1: Does this story meet expectations?
A2: 1 | B2: FOH | C2: 46080 | D2: 46093 | E2: 26.5 - Sprint 1 | F2: Alpha/Atchaiah | G2: 51934 | H2: Mosaic - FOH 26.1(Regression) - Reports - (Excluding Free/Reduced) | I2: Story Completed | J2: 8 | K2: 9.75 | L2: 39 | M2: 46080 | N2: 46092 | O2: NA | P2: NA | Q2: NA | R2: NA | S2: NA | T2: NA | U2: NA | V2: NA | W2: NA | X2: NA | Y2: NA | Z2: NA | AA2: NA | AB2: NA | AC2: NA | AD2: We also fixed regression defects in this story
A3: 2 | B3: FOH | C3: 46080 | D3: 46093 | E3: 26.5 - Sprint 1 | F3: Atchaiah | G3: 51931 | H3: Mosaic - FOH 26.1 (Regression) - Reports - Eligibility (F&R) | I3: Story Completed | J3: 3 | K3: 3.75 | L3: 15 | M3: 46080 | N3: 46092 | O3: NA | P3: NA | Q3: NA | R3: NA | S3: NA | T3: NA | U3: NA | V3: NA | W3: NA | X3: NA | Y3: NA | Z3: NA | AA3: NA | AB3: NA | AC3: NA | AD3: We also fixed regression defects in this story
A4: 3 | B4: FOH | C4: 46080 | D4: 46093 | E4: 26.5 - Sprint 1 | F4: Ashwin/Arvinth/Atchaiah | G4: 51938 | H4: Mosaic - FOH 26.1(Regression) - Setup | I4: Story Completed | J4: 8 | K4: 10.5 | L4: 42 | M4: 46080 | N4: 46092 | O4: NA | P4: NA | Q4: NA | R4: NA | S4: NA | T4: NA | U4: NA | V4: NA | W4: NA | X4: NA | Y4: NA | Z4: NA | AA4: NA | AB4: NA | AC4: NA | AD4: We also fixed regression defects in this story
A5: 4 | B5: FOH | C5: 46080 | D5: 46093 | E5: 26.5 - Sprint 1 | F5: Subha | G5: 26862 | H5: MFOH (26.1 release) - Dashboard resulted twice when searched through the search option | I5: Story Completed | J5: 2 | K5: 1.75 | L5: 7 | M5: 46080 | N5: 46080 | O5: Subha | P5: Alpha | Q5: None | R5: Alpha | S5: None | T5: 47629 | U5: 46086 | V5: 46086 | W5: NA | X5: NA | Y5: Steve | Z5: 46086 | AA5: None | AB5: None | AC5: NA
A6: 5 | B6: FOH | C6: 46080 | D6: 46093 | E6: 26.5 - Sprint 1 | F6: Alpha | G6: 52034 | H6: Mosaic FOH - Tyler Munis Financial Export - ROA/RFD Calculation Modification | I6: Story Completed | J6: 3 | K6: 2.5 | L6: 10 | M6: 46085 | N6: 46087 | O6: Alpha | P6: Ashwin | Q6: None | R6: Arvinth | S6: None | T6: 47673 | U6: 46090 | V6: 46090 | W6: NA | X6: NA | Y6: Steve | Z6: 46090 | AA6: None | AB6: None | AC6: NA
A7: 6 | B7: FOH | C7: 46080 | D7: 46093 | E7: 26.5 - Sprint 1 | F7: Arvinth | G7: 52026 | H7: Mosaic FOH - Add new field District.MSBID (to 26.5) | I7: Story Completed | J7: 2 | K7: 1.5 | L7: 6 | M7: 46086 | N7: 46087 | O7: Arvinth | P7: Ashwin | Q7: None | R7: Alpha | S7: None | T7: 47676 | U7: 46090 | V7: 46090 | W7: NA | X7: NA | Y7: Steve | Z7: 46090 | AA7: None | AB7: None | AC7: NA
A8: 7 | B8: FOH | C8: 46080 | D8: 46093 | E8: 26.5 - Sprint 1 | F8: Arvinth | G8: 52103 | H8: Mosaic FOH - Pendo Snippet Updates, Phase 1 | I8: Story Completed | J8: 3 | K8: 1.25 | L8: 5 | M8: 46090 | N8: 46091 | O8: Arvinth | P8: Ashwin | Q8: None | R8: Alpha | S8: None | T8: 47719 | U8: 46091 | V8: 46091 | W8: NA | X8: NA | Y8: Steve | Z8: 46091 | AA8: None | AB8: None | AC8: NA
A9: 8 | B9: FOH | C9: 46080 | D9: 46093 | E9: 26.5 - Sprint 1 | F9: Ashwin | G9: 26915 | H9: MFOH (26.1 Regression) - The language popup automatically gets closed | I9: Story Completed | J9: 0 | K9: 0 | L9: 0 | M9: 46090 | N9: 46090 | O9: Ashwin | P9: Arvinth | Q9: None | R9: Arvinth | S9: None | T9: 47675 | U9: 46090 | V9: 46090 | W9: NA | X9: NA | Y9: Steve | Z9: 46090 | AA9: None | AB9: None | AC9: NA
A10: 9 | B10: FOH | C10: 46080 | D10: 46093 | E10: 26.5 - Sprint 1 | F10: Ashwin | G10: 26916 | H10: MFOH (26.1 Regression) - Reimbursement Rate Update Failure due to an exception | I10: Story Completed | J10: 0 | K10: 0 | L10: 0 | M10: 46090 | N10: 46090 | O10: Ashwin | P10: Arvinth | Q10: None | R10: Arvinth | S10: None | T10: 47674 | U10: 46090 | V10: 46090 | W10: NA | X10: NA | Y10: Steve | Z10: 46090 | AA10: None | AB10: None | AC10: NA
A11: 10 | B11: FOH | C11: 46080 | D11: 46093 | E11: 26.5 - Sprint 1 | F11: Alpha | G11: 26917 | H11: MFOH (26.1 Regression) - Daily sales summary report is showing some blank pages | I11: Story Completed | J11: 0 | K11: 0 | L11: 0 | M11: 46090 | N11: 46090 | O11: Alpha | P11: Ashwin | Q11: None | R11: Ashwin | S11: None | T11: 47716 | U11: 46091 | V11: 46091 | W11: NA | X11: NA | Y11: Steve | Z11: 46091 | AA11: None | AB11: None | AC11: NA
A12: 11 | B12: FOH | C12: 46080 | D12: 46093 | E12: 26.5 - Sprint 1 | F12: Alpha | G12: 26918 | H12: MFOH (26.1 Regression) - Transaction History Report fails whenever check transactions contain the Check number that exceed the INT data type limit | I12: Story Completed | J12: 0 | K12: 0 | L12: 0 | M12: 46087 | N12: 46087 | O12: Alpha | P12: Ashwin | Q12: None | R12: Arvinth | S12: None | T12: 47677 | U12: 46090 | V12: 46090 | W12: NA | X12: NA | Y12: Steve | Z12: 46090 | AA12: None | AB12: NA | AC12: NA
A13: 12 | B13: FOH | C13: 46080 | D13: 46093 | E13: 26.5 - Sprint 1 | F13: Alpha | G13: 26919 | H13: MFOH (26.1 Regression) - Blank page shows up for User assignment report for specific number of data | I13: Story Completed | J13: 0 | K13: 0 | L13: 0 | M13: 46087 | N13: 46087 | O13: Alpha | P13: Ashwin | Q13: None | R13: Arvinth | S13: None | T13: 47678 | U13: 46090 | V13: 46090 | W13: NA | X13: NA | Y13: Steve | Z13: 46090 | AA13: None | AB13: NA | AC13: NA
A14: 13 | B14: FOH | C14: 46080 | D14: 46093 | E14: 26.5 - Sprint 1 | F14: Alpha | G14: 26920 | H14: MFOH (26.1 Regression) - Unable to create the report in the Custom Report Designer | I14: Story Completed | J14: 0 | K14: 0 | L14: 0 | M14: 46087 | N14: 46087 | O14: Alpha | P14: Ashwin | Q14: None | R14: Arvinth | S14: None | T14: 47679 | U14: 46090 | V14: 46090 | W14: NA | X14: NA | Y14: Steve | Z14: 46090 | AA14: None | AB14: NA | AC14: NA
A15: 14 | B15: FOH | C15: 46080 | D15: 46093 | E15: 26.5 - Sprint 1 Stretch | F15: Atchaiah | G15: 51805 | H15: MFOH - Automation (Regression) - Kaleida changes update to the close day Search screen & maintenance screen | I15: Story Completed | J15: 3 | K15: 3 | L15: 12 | M15: 46087 | N15: 46091 | O15: NA | P15: NA | Q15: NA | R15: NA | S15: NA | T15: 47735 | U15: 46091 | V15: 46091 | W15: NA | X15: NA | Y15: Steve | Z15: 46091 | AA15: None | AB15: NA | AC15: NA
A16: 15 | B16: FOH | C16: 46080 | D16: 46093 | E16: 26.5 - Sprint 1 Stretch | F16: Atchaiaih | G16: 52306 | H16: MFOH - Automation - Kaleida changes update to the Setup - Tools - Scheduler Task [General & Log Tab UI] | I16: Story Completed | J16: 2 | K16: 2 | L16: 8 | M16: 46092 | N16: 46093 | O16: NA | P16: NA | Q16: NA | R16: NA | S16: NA | T16: 47775 | U16: 46093 | V16: 46093 | W16: NA | X16: NA | Y16: Steve | Z16: 46093 | AA16: None | AB16: NA | AC16: NA
A17: 16 | B17: FOH | C17: 46080 | D17: 46093 | E17: 26.5 - Sprint 1 Stretch | F17: Alpha/Ashwin | G17: 51697 | H17: Mosaic FOH - Snyk Findings - Path Traversal - UtilitiesController.cs- Unsanitized input flows into global::System.IO.StreamWriter | I17: Story Being Developed | J17: 5 | K17: 4.5 | L17: 18 | M17: 46091 | N17: 46093 | O17: Alpha
A18: 17 | B18: FOH | C18: 46080 | D18: 46093 | E18: 26.5 - Sprint 1 Stretch | F18: Arvinth | G18: 51698 | H18: Mosaic FOH - Snyk Findings - Path Traversal - UtilitiesController.cs- Unsanitized input flows into global::System.IO.Directory.Exists | I18: Story Being Developed | J18: 5 | K18: 0.75 | L18: 3 | M18: 46093 | N18: 46093

Sheet 26.5 - Sprint 1-Defect
A1: S.No | B1: Sprint # | C1: Story/Defect ID | D1: Parent Story | E1: Developer | F1: Issue Type | G1: Issue Description | H1: Priority | I1: Defect Source | J1: Type | K1: Status | L1: Root Cause Category | M1: Comments

Sheet 26.1 - Sprint 4-Status
A1: S.No | B1: Application Name | C1: Sprint Start Date | D1: Sprint End Date | E1: Sprint | F1: Developer | G1: Story ID/Defect ID | H1: Description | I1: Status | J1: Estimated(hrs/sp) | K1: Actual(hrs/sp) | L1: Actual Worklog (Hours) | M1: Dev Start Date | N1: Dev End Date | O1: Unit testing | P1: Peer Tested By | Q1: Peer Tested Comments, if any | R1: Peer Reviewed By | S1: Peer Code Review Comments, if any | T1: PR Number/Link | U1: PR Created Date | V1: PR Approved Date | W1: Onsite Lead Code Review | X1: Code Review Comments, if any | Y1: Client Code Review | Z1: Approved Date | AA1: Code Review Comments, if any2 | AB1: Internal PO -POV Comments | AC1: Client PO -POV Comments | AD1: Comments | AE1: Does this story meet expectations?
A2: 1 | B2: FOH | C2: 46066 | D2: 46079 | E2: 26.1 - Sprint 4 | F2: Atchaiah | G2: 51806 | H2: MFOH - Automation (Regression) - Kaleida changes update to the close day report search screen & close day report maintenance screen | I2: Story Completed | J2: 1 | K2: 1 | L2: 4 | M2: 46066 | N2: 46069 | O2: NA | P2: NA | Q2: NA | R2: NA | S2: NA | T2: 47290 | U2: 46070 | V2: 46070 | W2: NA | X2: NA | Y2: Steve | Z2: 46070 | AA2: None | AB2: NA | AC2: NA
A3: 2 | B3: FOH | C3: 46066 | D3: 46079 | E3: 26.1 - Sprint 4 | F3: Alpha | G3: 26749 | H3: MFOH [WAVE] - Fix the console error that blocks the save and retrieval of the dashboard | I3: Story Completed | J3: 2 | K3: 3 | L3: 12 | M3: 46066 | N3: 46069 | O3: Alpha | P3: Subha | Q3: None | R3: NA | S3: NA | T3: 47406 | U3: 46073 | V3: 46073 | W3: Subha | X3: None | Y3: Steve | Z3: 46073 | AA3: None | AB3: NA | AC3: NA | AD3: Due to multiple console error in defect and it's only visible in deployed environment, it's getting late.
A4: 3 | B4: FOH | C4: 46066 | D4: 46079 | E4: 26.1 - Sprint 4 | F4: Alpha/Arvinth | G4: 51438 | H4: MFOH - Add an option to delete multiple export fields (Transaction Export Setup) | I4: Story Completed | J4: 2 | K4: 2.25 | L4: 9 | M4: 46070 | N4: 46072 | O4: Alpha | P4: Arvint | Q4: None | R4: Arvinth | S4: None | T4: 47407 | U4: 46073 | V4: 46073 | W4: Subha | X4: None | Y4: Steve | Z4: 46073 | AA4: None | AB4: NA | AC4: NA
A5: 4 | B5: FOH | C5: 46066 | D5: 46079 | E5: 26.1 - Sprint 4 | F5: Arvinth/Alpha | G5: 26798 | H5: MFOH - School selection is retained even after the school filter is set to Blank (Close Day Reports) | I5: Story Completed | J5: 2 | K5: 2 | L5: 8 | M5: 46069 | N5: 46070 | O5: Arvinth | P5: Ashwin | Q5: None | R5: Ashwin | S5: None | T5: 47347 | U5: 46071 | V5: 46071 | W5: Subha | X5: None | Y5: Steve | Z5: 46071 | AA5: None | AB5: None | AC5: None
A6: 5 | B6: FOH | C6: 46066 | D6: 46079 | E6: 26.1 - Sprint 4 | F6: Subhasri | G6: 51945 | H6: MFOH - Default Letter Sent Status to BLANK (Student Letters) | I6: Story Completed | J6: 3 | K6: 3 | L6: 11.75 | M6: 46066 | N6: 46069 | O6: Subhasri | P6: Alpha | Q6: None | R6: Alpha | S6: None | T6: 47390 | U6: 46072 | V6: 46072 | W6: NA | X6: NA | Y6: Steve | Z6: 46072 | AA6: None | AB6: None | AC6: None
A7: 6 | B7: FOH | C7: 46066 | D7: 46079 | E7: 26.1 - Sprint 4 | F7: Subhasri | G7: 23660 | H7: Mosaic - FOH - Issues with Reimbursement Due Report | I7: Story Being Tested | J7: 2 | K7: 2.5 | L7: 10 | M7: 46066 | N7: 46072 | O7: Subhasri | P7: Arvinth | Q7: None | R7: Arvinth | S7: None | T7: 47464 | U7: 46077 | V7: 46077 | W7: NA | X7: NA | Y7: Steve | Z7: 46077 | AA7: None | AB7: None | AC7: None | AD7: All development activities from our side have been completed on time and it is pending with the Onsite QA.
A8: 7 | B8: FOH | C8: 46066 | D8: 46079 | E8: 26.1 - Sprint 4 | F8: Arvinth/Atchaiah | G8: 51937 | H8: Mosaic - FOH 26.1(Regression) - Utilities | I8: Story Completed | J8: 8 | K8: 8 | L8: 32 | M8: 46072 | N8: 46079 | O8: NA | P8: NA | Q8: NA | R8: NA | S8: NA | T8: NA | U8: NA | V8: NA | W8: NA | X8: NA | Y8: NA | Z8: NA | AA8: NA | AB8: NA | AC8: NA | AD8: Regression Testing
A9: 8 | B9: FOH | C9: 46066 | D9: 46079 | E9: 26.1 - Sprint 4 Stretch | F9: Atchaiah | G9: 51805 | H9: MFOH - Automation (Regression) - Kaleida changes update to the close day Search screen & maintenance screen | I9: Story Being Developed | J9: 8 | K9: 6 | L9: 24 | M9: 46069 | N9: 46072 | AD9: Due to release is a priority, we kept on hold. -> Carry forward to current sprint
A10: 9 | B10: FOH | C10: 46066 | D10: 46079 | E10: 26.1 - Sprint 4 | F10: Alpha/Atchaiah | G10: 51929 | H10: Mosaic - FOH 26.1(Regression) - End of Day | I10: Story Completed | J10: 5 | K10: 5 | L10: 20 | M10: 46073 | N10: 46079 | O10: NA | P10: NA | Q10: NA | R10: NA | S10: NA | T10: NA | U10: NA | V10: NA | W10: NA | X10: NA | Y10: NA | Z10: NA | AA10: NA | AB10: NA | AC10: NA | AD10: Regression Testing
A11: 10 | B11: FOH | C11: 46066 | D11: 46079 | E11: 26.1 - Sprint 4 | F11: Subhasri/Atchaiah | G11: 51939 | H11: Mosaic - FOH 26.1 (Regression) - Eligibility (F&R) | I11: Story Completed | J11: 5 | K11: 5 | L11: 20 | M11: 46073 | N11: 46079 | O11: NA | P11: NA | Q11: NA | R11: NA | S11: NA | T11: NA | U11: NA | V11: NA | W11: NA | X11: NA | Y11: NA | Z11: NA | AA11: NA | AB11: NA | AC11: NA | AD11: Regression Testing
A12: 11 | B12: FOH | C12: 46066 | D12: 46079 | E12: 26.1 - Sprint 4 | F12: Alpha | G12: 26699 | H12: MFOH - Close Day (Today Grid) is showing the records from the Previous Days Grid | I12: Story Completed | J12: 1 | K12: 1 | L12: 4 | M12: 46076 | N12: 46076 | O12: NA | P12: NA | Q12: NA | R12: NA | S12: NA | T12: NA | U12: NA | V12: NA | W12: NA | X12: NA | Y12: NA | Z12: NA | AA12: NA | AB12: NA | AC12: NA | AD12: Manual Testing
A13: 12 | B13: FOH | C13: 46066 | D13: 46079 | E13: 26.1 - Sprint 4 | F13: Ashwin/Atchaiah | G13: 51928 | H13: Mosaic - FOH 26.1(Regression) - Students | I13: Story Completed | J13: 5 | K13: 5 | L13: 20 | M13: 46072 | N13: 46077 | O13: NA | P13: NA | Q13: NA | R13: NA | S13: NA | T13: NA | U13: NA | V13: NA | W13: NA | X13: NA | Y13: NA | Z13: NA | AA13: NA | AB13: NA | AC13: NA | AD13: Regression Testing
A14: 13 | B14: FOH | C14: 46066 | D14: 46079 | E14: 26.1 - Sprint 4 | F14: Ashwin/Atchaiah | G14: 51933 | H14: Mosaic - FOH 26.1 (Regression) - POS(Menu Option) | I14: Story Completed | J14: 2 | K14: 2.75 | L14: 11 | M14: 46077 | N14: 46079 | O14: NA | P14: NA | Q14: NA | R14: NA | S14: NA | T14: NA | U14: NA | V14: NA | W14: NA | X14: NA | Y14: NA | Z14: NA | AA14: NA | AB14: NA | AC14: NA | AD14: Regression Testing
A15: 13 | B15: FOH | C15: 46066 | D15: 46079 | E15: 26.1 - Sprint 4 | F15: Arvinth | G15: 26755 | H15: Mosaic FOH - SP Edit Check - Claimed Free Meals individual School and Grant Total Mismatch | I15: Story Completed | J15: 1 | K15: 1 | L15: 4 | M15: 46077 | N15: 46077 | O15: NA | P15: NA | Q15: NA | R15: NA | S15: NA | T15: NA | U15: NA | V15: NA | W15: NA | X15: NA | Y15: NA | Z15: NA | AA15: NA | AB15: NA | AC15: NA | AD15: Manual Testing
A16: 14 | B16: FOH | C16: 46066 | D16: 46079 | E16: 26.1 - Sprint 4 | F16: Arvinth | G16: 26746 | H16: MFOH - Fix the issue with MSB Spending Limits setting | I16: Story Completed | J16: 1 | K16: 1 | L16: 4 | M16: 46078 | N16: 46078 | O16: NA | P16: NA | Q16: NA | R16: NA | S16: NA | T16: NA | U16: NA | V16: NA | W16: NA | X16: NA | Y16: NA | Z16: NA | AA16: NA | AB16: NA | AC16: NA | AD16: Manual Testing
A17: 15 | B17: FOH | C17: 46066 | D17: 46079 | E17: 26.1 - Sprint 4 | F17: Alpha | G17: 26633 | H17: Mosaic FOH - Display Bug in DC Import when Merging Records | I17: Story Being Tested | J17: 2 | K17: 1 | L17: 4 | M17: 46079 | AD17: Manual Testing; The testing support story was not completed as the team prioritized regression testing. As a result, testing for this item only began toward the end of the sprint.
A18: 16 | B18: FOH | C18: 46066 | D18: 46079 | E18: 26.1 - Sprint 4 | F18: Subhasri | G18: 26841 | H18: MFOH - Transaction History Report CSV missing fields | I18: Story Completed | J18: 0 | K18: 0.5 | L18: 2 | M18: 46078 | N18: 46079 | O18: Subhasri | P18: Ashwin | Q18: None | R18: NA | S18: NA | T18: 47504 | U18: 46078 | V18: 46078 | W18: NA | X18: NA | Y18: Steve | Z18: None | AA18: None | AB18: NA | AC18: NA
A19: 17 | B19: FOH | C19: 46066 | D19: 46079 | E19: 26.1 - Sprint 4 | F19: Alpha/Bala | G19: 26849 | H19: MFOH (26.1 Regression) - Getting an error while Execute the Status Synchronization | I19: Defect Fixed | J19: 0 | K19: 0 | L19: 0 | M19: 46078 | N19: 46079 | O19: Bala | P19: Alpha | Q19: None | R19: Alpha | S19: None | T19: 47489 | U19: 46078 | V19: 46078 | W19: Subha | X19: None | Y19: Steve | Z19: None | AA19: None | AB19: NA | AC19: NA
A20: 18 | B20: FOH | C20: 46066 | D20: 46079 | E20: 26.1 - Sprint 4 | F20: Alpha/Ashwin | G20: 26851 | H20: MFOH (26.1 Regression) - Delete button is missing in Open Previous Day Maintenance screen | I20: Defect Fixed | J20: 0 | K20: 0 | L20: 0 | M20: 46078 | N20: 46078 | O20: Ashwin | P20: Alpha | Q20: None | R20: Alpha | S20: None | T20: 47490 | U20: 46078 | V20: 46078 | W20: Subha | X20: None | Y20: Steve | Z20: None | AA20: None | AB20: NA | AC20: NA
A21: 19 | B21: FOH | C21: 46066 | D21: 46079 | E21: 26.1 - Sprint 4 | F21: Alpha/Ashwin | G21: 26852 | H21: MFOH (26.1 Regression) - Console error when trying to change the attendance count in close day | I21: Defect Fixed | J21: 0 | K21: 0 | L21: 0 | M21: 46078 | N21: 46078 | O21: Ashwin | P21: Alpha | Q21: None | R21: Alpha | S21: None | T21: 47491 | U21: 46078 | V21: 46078 | W21: Subha | X21: None | Y21: Steve | Z21: None | AA21: None | AB21: NA | AC21: NA
A22: 20 | B22: FOH | C22: 46066 | D22: 46079 | E22: 26.1 - Sprint 4 | F22: Alpha/Bala | G22: 26848 | H22: MFOH (26.1 Regression) - "Failed to convert parameter value from a String to a Int32." when the terminal Number is blank in import file. | I22: Defect Fixed | J22: 0 | K22: 0 | L22: 0 | M22: 46078 | N22: 46079 | O22: Bala | P22: NA | Q22: NA | R22: NA | S22: NA | T22: 47503 | U22: 46078 | V22: 46078 | W22: Subha | X22: None | Y22: Steve | Z22: None | AA22: None | AB22: NA | AC22: NA
A23: 21 | B23: FOH | C23: 46066 | D23: 46079 | E23: 26.1 - Sprint 4 | F23: Subha/Bala | G23: 26850 | H23: MFOH (26.1 Regression) - Getting an error while trying to update the input devices name to give more than 50 characters | I23: Defect Fixed | J23: 0 | K23: 0 | L23: 0 | M23: 46078 | N23: 46079 | O23: Bala | P23: NA | Q23: NA | R23: NA | S23: NA | T23: 47502 | U23: 46078 | V23: 46078 | W23: Subha | X23: None | Y23: Steve | Z23: None | AA23: None | AB23: NA | AC23: NA
A24: 22 | B24: FOH | C24: 46066 | D24: 46079 | E24: 26.1 - Sprint 4 | F24: Alpha | G24: 26865 | H24: MFOH (26.1 Regression) - Error during Close year | I24: Defect Fixed | J24: 0 | K24: 0 | L24: 0 | M24: 46079 | N24: 46079 | O24: Alpha | P24: Ashwin | Q24: None | R24: NA | S24: NA | T24: 47515 | U24: 46079 | V24: 46079 | W24: Subha | X24: None | Y24: Steve | Z24: None | AA24: None | AB24: NA | AC24: NA

Sheet 26.1 - Sprint 4-Defect
A1: S.No | B1: Sprint # | C1: Story/Defect ID | D1: Parent Story | E1: Developer | F1: Issue Type | G1: Issue Description | H1: Priority | I1: Defect Source | J1: Type | K1: Status | L1: Root Cause Category | M1: Comments

Sheet 26.1 - Sprint 3-Status
A1: S.No | B1: Application Name | C1: Sprint Start Date | D1: Sprint End Date | E1: Sprint | F1: Developer | G1: Story ID/Defect ID | H1: Description | I1: Status | J1: Estimated(hrs/sp) | K1: Actual(hrs/sp) | L1: Actual Worklog (Hours) | M1: Dev Start Date | N1: Dev End Date | O1: Unit testing | P1: Peer Tested By | Q1: Peer Tested Comments, if any | R1: Peer Reviewed By | S1: Peer Code Review Comments, if any | T1: PR Number/Link | U1: PR Created Date | V1: PR Approved Date | W1: Onsite Lead Code Review | X1: Code Review Comments, if any | Y1: Client Code Review | Z1: Approved Date | AA1: Code Review Comments, if any2 | AB1: Internal PO -POV Comments | AC1: Client PO -POV Comments | AD1: Comments | AE1: Does this story meet expectations?
A2: 1 | B2: FOH | C2: 46052 | D2: 46065 | E2: 26.1 - Sprint 3 | F2: Alpha | G2: 26682 | H2: MFoH - Daily Sales Report with just 2 serving periods goes over 1 page | I2: Story Completed | J2: 2 | K2: 0.5 | L2: 2 | M2: 46052 | N2: 46055 | O2: NA | P2: NA | Q2: NA | R2: NA | S2: NA | T2: NA | U2: NA | V2: NA | W2: NA | X2: NA | Y2: NA | Z2: NA | AA2: NA | AB2: NA | AC2: NA | AD2: Defect rejected as we found this is not a defect. For states ND, OR, and NJ adding new labels for meal counts and amount, and that's why the report is extending to the second page.
A3: 2 | B3: FOH | C3: 46052 | D3: 46065 | E3: 26.1 - Sprint 3 | F3: Arvinth | G3: 50680 | H3: MFOH - Add 'Daily Sales Report CC' as a Close Day Report | I3: Story Completed | J3: 3 | K3: 2.5 | L3: 10 | M3: 46052 | N3: 46056 | O3: Arvinth | P3: Ashwin | Q3: None | R3: Alpha | S3: Version history in one page. | T3: 47073 | U3: 46057 | V3: 46057 | W3: Subha | X3: None | Y3: Steve | Z3: 46057 | AA3: None | AB3: None | AC3: NA
A4: 3 | B4: FOH | C4: 46052 | D4: 46065 | E4: 26.1 - Sprint 3 | F4: Alpha | G4: 51319 | H4: Mosaic FOH - Add student medical alert changes as Event type filter for Student History Report | I4: Story Completed | J4: 5 | K4: 7.75 | L4: 31 | M4: 46052 | N4: 46063 | O4: Alpha | P4: Arvinth | Q4: Initial one time insert record was showing in the report. | R4: Arvinth | S4: Insert to detail table is not required. | T4: 47185 | U4: 46063 | V4: 46063 | W4: Subha | X4: None | Y4: Steve | Z4: 46063 | AA4: None | AB4: None | AC4: NA | AD4: The story underwent a technical discussion and development commenced on 02/04/2026. Following the discussion, it was determined that the story requires additional story points/efforts to accurately reflect the scope of work.
A5: 4 | B5: FOH | C5: 46052 | D5: 46065 | E5: 26.1 - Sprint 3 | F5: Subhasri | G5: 26587 | H5: MFOH - Add New Eligibility Record UI is crashed | I5: Story Completed | J5: 2 | K5: 0.75 | L5: 3 | M5: 46052 | N5: 46052 | O5: Subhasri | P5: Arvinth | Q5: None | R5: Arvinth | S5: None | T5: 47051 | U5: 46056 | V5: 46056 | W5: NA | X5: NA | Y5: Steve | Z5: 46056 | AA5: None | AB5: None | AC5: NA
A6: 5 | B6: FOH | C6: 46052 | D6: 46065 | E6: 26.1 - Sprint 3 | F6: Subhasri | G6: 26617 | H6: MFOH - New Jersey Master Eligibility List Report - Missing Homerooms | I6: Story Completed | J6: 2 | K6: 1 | L6: 4 | M6: 46055 | N6: 46056 | O6: Subhasri | P6: NA | Q6: NA | R6: NA | S6: NA | T6: 47052 | U6: 46056 | V6: 46056 | W6: NA | X6: NA | Y6: Steve | Z6: 46056 | AA6: None | AB6: None | AC6: NA
A7: 6 | B7: FOH | C7: 46052 | D7: 46065 | E7: 26.1 - Sprint 3 | F7: Ashwin | G7: 50679 | H7: MFOH - Add a Grand Total Page to Extend Sales Report (Single School) | I7: Story Completed | J7: 3 | K7: 2.25 | L7: 9 | M7: 46052 | N7: 46055 | O7: Ashwin | P7: Arvinth | Q7: None | R7: Arvinth | S7: None | T7: 47074 | U7: 46057 | V7: 46057 | W7: Subha | X7: None | Y7: Steve | Z7: 46057 | AA7: None | AB7: None | AC7: NA
A8: 7 | B8: FOH | C8: 46052 | D8: 46065 | E8: 26.1 - Sprint 3 | F8: Alpha | G8: 51726 | H8: MFOH - Automated Low Funds Email is not sent for Free Students | I8: Story Completed | J8: 3 | K8: 2.5 | L8: 10 | M8: 46055 | N8: 46056 | O8: Alpha | P8: Arvinth | Q8: None | R8: Arvinth | S8: Suggestion to write the filter query in an another way. | T8: 47059 | U8: 46057 | V8: 46057 | W8: Subha | X8: None | Y8: Steve | Z8: 46057 | AA8: None | AB8: None | AC8: NA
A9: 8 | B9: FOH | C9: 46052 | D9: 46065 | E9: 26.1 - Sprint 3 | F9: Subhasri | G9: 51439 | H9: MFOH - Add a Serving Period wise Grand Total Page to Edit Check Worksheet Report | I9: Story Completed | J9: 5 | K9: 3.5 | L9: 14 | M9: 46056 | N9: 46059 | O9: Subhasri | P9: Ashwin | Q9: None | R9: Ashwin | S9: None | T9: 47157 | U9: 46062 | V9: 46062 | W9: NA | X9: None | Y9: Steve | Z9: 46062 | AA9: None | AB9: None | AC9: NA
A10: 9 | B10: FOH | C10: 46052 | D10: 46065 | E10: 26.1 - Sprint 3 | F10: Arvinth | G10: 26664 | H10: MFoH - Reproducible error when double-clicking the Sign-In button | I10: Story Completed | J10: 3 | K10: 3 | L10: 12 | M10: 46063 | N10: 46064 | O10: Arvinth | P10: Ashwin | Q10: None | R10: Alpha | S10: None | T10: 47195 | U10: 46064 | V10: 46064 | W10: Subha | X10: None | Y10: Steve | Z10: 46064 | AA10: None | AB10: None | AC10: NA
A11: 10 | B11: FOH | C11: 46052 | D11: 46065 | E11: 26.1 - Sprint 3 | F11: Ashwin/Subhasri | G11: 26706 | H11: MFoH - Setup - District Maintenance - Feature Flag field expands below frame | I11: Story Completed | J11: 1 | K11: 0.5 | L11: 2 | M11: 46058 | N11: 46058 | O11: Ashwin | P11: Arvinth | Q11: None | R11: Arvinth | S11: None | T11: 47155 | U11: 46062 | V11: 46062 | W11: Subha | X11: None | Y11: Steve | Z11: 46062 | AA11: None | AB11: None | AC11: NA
A12: 11 | B12: FOH | C12: 46052 | D12: 46065 | E12: 26.1 - Sprint 3 Stretch | F12: Atchaiah | G12: 51576 | H12: MFOH - MFOH [BAU] - Automation (46897) | I12: Story Completed | J12: 1 | K12: 1 | L12: 4 | M12: 46052 | N12: 46056 | O12: NA | P12: NA | Q12: NA | R12: NA | S12: NA | T12: 47047 | U12: 46056 | V12: 46056 | W12: NA | X12: NA | Y12: Steve | Z12: 46056 | AA12: None | AB12: NA | AC12: NA
A13: 12 | B13: FOH | C13: 46052 | D13: 46065 | E13: 26.1 - Sprint 3 Stretch | F13: Atchaiah | G13: 51581 | H13: MFOH - MFOH [BAU] - Automation (51305) | I13: Story Completed | J13: 2 | K13: 2 | L13: 8 | M13: 46056 | N13: 46058 | O13: NA | P13: NA | Q13: NA | R13: NA | S13: NA | T13: 47126 | U13: 46059 | V13: 46059 | W13: NA | X13: NA | Y13: Steve | Z13: 46059 | AA13: None | AB13: NA | AC13: NA
A14: 13 | B14: FOH | C14: 46052 | D14: 46065 | E14: 26.1 - Sprint 3 Stretch | F14: Atchaiah | G14: 51580 | H14: MFOH - MFOH [BAU] - Automation (51222) | I14: Story Completed | J14: 2 | K14: 2 | L14: 8 | M14: 46058 | N14: 46059 | O14: NA | P14: NA | Q14: NA | R14: NA | S14: NA | T14: 47144 | U14: 46062 | V14: 46062 | W14: NA | X14: NA | Y14: Steve | Z14: 46062 | AA14: None | AB14: NA | AC14: NA
A15: 14 | B15: FOH | C15: 46052 | D15: 46065 | E15: 26.1 - Sprint 3 Stretch | F15: Ashwin | G15: 26737 | H15: MFOH - Default the Homeroom filter to BLANK (POS Roster and Roster Extended) | I15: Story Completed | J15: 2 | K15: 1.5 | L15: 6 | M15: 46056 | N15: 46057 | O15: Arvinth | P15: Alpha | Q15: None | R15: Alpha | S15: None | T15: 47099 | U15: 46058 | V15: 46058 | W15: Subha | X15: None | Y15: Steve | Z15: 46058 | AA15: None | AB15: None | AC15: NA
A16: 15 | B16: FOH | C16: 46052 | D16: 46065 | E16: 26.1 - Sprint 3 Stretch | F16: Arvinth | G16: 26699 | H16: MFOH - Close Day (Today Grid) is showing the records from the Previous Days Grid | I16: Story Ready For Testing | J16: 3 | K16: 1.5 | L16: 6 | M16: 46062 | N16: 46063 | O16: Arvinth | P16: NA | Q16: NA | R16: NA | S16: NA | T16: 47181 | U16: 46063 | V16: 46063 | W16: Subha | X16: None | Y16: Steve | Z16: 46063 | AA16: None | AB16: None | AC16: NA
A17: 16 | B17: FOH | C17: 46052 | D17: 46065 | E17: 26.1 - Sprint 3 Stretch | F17: Atchaiah | G17: 51806 | H17: MFOH - Automation (Regression) - Kaleida changes update to the close day report search screen & close day report maintenance screen | I17: Story Being Developed | J17: 5 | K17: 5.25 | L17: 22 | M17: 46062 | N17: 46065 | O17: NA | AD17: Xpath is not working due to Vega UI changes updated, so we need to work with JavaScript.
A18: 17 | B18: FOH | C18: 46052 | D18: 46065 | E18: 26.1 - Sprint 3 Stretch | F18: Alpha | G18: 51438 | H18: MFOH - Add an option to delete multiple export fields (Transaction Export Setup) | I18: Story Being Developed | J18: 3 | K18: 2.5 | L18: 10.25 | M18: 46064 | N18: 46065 | O18: Alpha
A19: 18 | B19: FOH | C19: 46052 | D19: 46065 | E19: 26.1 - Sprint 3 Stretch | F19: Subhasri | G19: 26746 | H19: MFOH - Fix the issue with MSB Spending Limits setting | I19: Story Ready For Testing | J19: 1 | K19: 1 | L19: 4 | M19: 46058 | N19: 46059 | O19: Subhasri | P19: Ashwin | Q19: None | R19: NA | S19: NA | T19: 47156 | U19: 46062 | V19: 46062 | W19: NA | X19: NA | Y19: Steve | Z19: 46062 | AA19: None | AB19: None | AC19: NA

Sheet 26.1 - Sprint 3-Defect
A1: S.No | B1: Sprint # | C1: Story/Defect ID | D1: Parent Story | E1: Developer | F1: Issue Type | G1: Issue Description | H1: Priority | I1: Defect Source | J1: Type | K1: Status | L1: Root Cause Category | M1: Comments

Sheet 26.1 - Sprint 2-Status
A1: S.No | B1: Application Name | C1: Sprint Start Date | D1: Sprint End Date | E1: Sprint | F1: Developer | G1: Story ID/Defect ID | H1: Description | I1: Status | J1: Estimated(hrs/sp) | K1: Actual(hrs/sp) | L1: Actual Worklog (Hours) | M1: Dev Start Date | N1: Dev End Date | O1: Unit testing | P1: Peer Tested By | Q1: Peer Tested Comments, if any | R1: Peer Reviewed By | S1: Peer Code Review Comments, if any | T1: PR Number/Link | U1: PR Created Date | V1: PR Approved Date | W1: Onsite Lead Code Review | X1: Code Review Comments, if any | Y1: Client Code Review | Z1: Approved Date | AA1: Code Review Comments, if any2 | AB1: Internal PO -POV Comments | AC1: Client PO -POV Comments | AD1: Comments | AE1: Does this story meet expectations?
A2: 1 | B2: FOH | C2: 46038 | D2: 46051 | E2: 26.1 - Sprint 2 | F2: Subhasri | G2: 26573 | H2: MFOH - Extended Daily Sales Summary Report - Refunds subtracted from System CC Total | I2: Story Completed | J2: 2 | K2: 1 | L2: 4 | M2: 46038 | N2: 46042 | O2: Subhasri | P2: Ashwin | Q2: None | R2: Ashwin | S2: None | T2: 46805 | U2: 46044 | V2: 46044 | W2: NA | X2: NA | Y2: Steve | Z2: 46044 | AA2: None | AB2: None | AC2: NA | AE2: Meets Expectation
A3: 2 | B3: FOH | C3: 46038 | D3: 46051 | E3: 26.1 - Sprint 2 | F3: Arvinth | G3: 49981 | H3: MFOH - Add a 'School' filter to 'Menu Product Detail Report' | I3: Story Completed | J3: 3 | K3: 2.5 | L3: 10 | M3: 46038 | N3: 46041 | O3: Arvinth | P3: Alpha | Q3: None | R3: Alpha | S3: Drop the temptable if exist | T3: 46802 | U3: 46044 | V3: 46044 | W3: Subha | X3: None | Y3: Steve | Z3: 46044 | AA3: None | AB3: None | AC3: None | AE3: Meets Expectation
A4: 3 | B4: FOH | C4: 46038 | D4: 46051 | E4: 26.1 - Sprint 2 | F4: Alpha | G4: 51435 | H4: Mosaic FOH - Special Provision Edit Check Report - Display entire Free Claim % | I4: Story Completed | J4: 2 | K4: 1.5 | L4: 6 | M4: 46038 | N4: 46041 | O4: Alpha | P4: Arvinth | Q4: None | R4: Arvinth | S4: None | T4: 46799 | U4: 46044 | V4: 46044 | W4: Subha | X4: None | Y4: Steve | Z4: 46044 | AA4: None | AB4: None | AC4: None | AE4: Meets Expectation
A5: 4 | B5: FOH | C5: 46038 | D5: 46051 | E5: 26.1 - Sprint 2 | F5: Arvinth | G5: 46670 | H5: Mosaic - POS (Web) - Add Bank Deposit Report as a Close Day Report | I5: Story Completed | J5: 5 | K5: 4 | L5: 16 | M5: 46041 | N5: 46043 | O5: Arvinth | P5: Atchai | Q5: None | R5: Alpha | S5: None | T5: 46801 | U5: 46044 | V5: 46044 | W5: Subha | X5: None | Y5: Steve | Z5: 46044 | AA5: None | AB5: None | AC5: None | AE5: Meets Expectation
A6: 5 | B6: FOH | C6: 46038 | D6: 46051 | E6: 26.1 - Sprint 2 | F6: Subhasri | G6: 26574 | H6: MFOH - Daily Sales CC Report - Refunds subtracted from CC Income Totals | I6: Story Completed | J6: 2 | K6: 1.25 | L6: 5 | M6: 46038 | N6: 46042 | O6: subhasri | P6: Ashwin | Q6: None | R6: Ashwin | S6: None | T6: 46806 | U6: 46044 | V6: 46044 | W6: NA | X6: NA | Y6: Steve | Z6: 46044 | AA6: None | AB6: None | AC6: NA | AE6: Meets Expectation
A7: 6 | B7: FOH | C7: 46038 | D7: 46051 | E7: 26.1 - Sprint 2 | F7: Alpha | G7: 46682 | H7: Mosaic - POS (Web) - Add a new report type to Meal Report | I7: Story Completed | J7: 8 | K7: 6 | L7: 24 | M7: 46041 | N7: 46045 | O7: Alpha | P7: Ashwin | Q7: None | R7: Arvinth | S7: None | T7: 46886 | U7: 46049 | V7: 46049 | W7: Subha | X7: None | Y7: Steve | Z7: 46049 | AA7: None | AB7: None | AC7: NA | AD7: Had clarification from Gary, so kept hold for sometime. | AE7: Meets Expectation
A8: 7 | B8: FOH | C8: 46038 | D8: 46051 | E8: 26.1 - Sprint 2 | F8: Ashwin/Subhasri | G8: 51453 | H8: MFOH - SSN masking fails when (-) is used in between the digits | I8: Story Completed | J8: 2 | K8: 1 | L8: 4 | M8: 46041 | N8: 46042 | O8: Ashwin | P8: Arvinth | Q8: None | R8: Arvinth | S8: None | T8: 46887 | U8: 46049 | V8: 46049 | W8: Subha | X8: None | Y8: Steve | Z8: 46049 | AA8: None | AB8: Missed masking in Student contact SSN | AC8: None | AE8: Meets Expectation
A9: 8 | B9: FOH | C9: 46038 | D9: 46051 | E9: 26.1 - Sprint 2 | F9: Alpha/Subhasri | G9: 51454 | H9: MFOH - Mask SSN (except last 4 digits) in multiple mosaic screens (KDE) | I9: Story Completed | J9: 3 | K9: 2.5 | L9: 10 | M9: 46043 | N9: 46044 | O9: Alpha | P9: Atchai | Q9: None | R9: Arvinth | S9: None | T9: 46888 | U9: 46049 | V9: 46049 | W9: Subha | X9: None | Y9: Steve | Z9: 46049 | AA9: None | AB9: None | AC9: None | AE9: Meets Expectation
A10: 9 | B10: FOH | C10: 46038 | D10: 46051 | E10: 26.1 - Sprint 2 | F10: Subhasri | G10: 50547 | H10: Mosaic FOH - MSB Spending Limits - Add "Required for All Students" | I10: Story Completed | J10: 8 | K10: 5.5 | L10: 22 | M10: 46043 | N10: 46048 | O10: Subhasri | P10: Arvinth | Q10: Yes' Showing in the grid instead of original value | R10: Arvinth | S10: None | T10: 46892 | U10: 46049 | V10: 46049 | W10: NA | X10: NA | Y10: Steve | Z10: 46049 | AA10: None | AB10: None | AC10: NA | AE10: Meets Expectation
A11: 10 | B11: FOH | C11: 46038 | D11: 46051 | E11: 26.1 - Sprint 2 Stretch | F11: Atchaiah | G11: 51400 | H11: MFOH [BAU] - Automation (50446) | I11: Story Completed | J11: 1 | K11: 1 | L11: 4 | M11: 46036 | N11: 46043 | O11: NA | P11: NA | Q11: NA | R11: NA | S11: NA | T11: 46790 | U11: 46044 | V11: 46044 | W11: NA | X11: NA | Y11: Steve | Z11: 46044 | AA11: None | AB11: NA | AC11: NA
A12: 11 | B12: FOH | C12: 46038 | D12: 46051 | E12: 26.1 - Sprint 2 Stretch | F12: Atchaiah | G12: 51401 | H12: MFOH [BAU] - Automation (50471) | I12: Story Completed | J12: 1 | K12: 1 | L12: 4 | M12: 46041 | N12: 46042 | O12: NA | P12: NA | Q12: NA | R12: NA | S12: NA | T12: 46732 | U12: 46042 | V12: 46042 | W12: NA | X12: NA | Y12: Steve | Z12: 46042 | AA12: None | AB12: NA | AC12: NA
A13: 12 | B13: FOH | C13: 46038 | D13: 46051 | E13: 26.1 - Sprint 2 Stretch | F13: Atchaiah | G13: 51577 | H13: MFOH - MFOH [BAU] - Automation (50472) | I13: Story Completed | J13: 1 | K13: 1 | L13: 4 | M13: 46045 | N13: 46049 | O13: NA | P13: NA | Q13: NA | R13: NA | S13: NA | T13: 46878 | U13: 46049 | V13: 46049 | W13: NA | X13: NA | Y13: Steve | Z13: 46049 | AA13: None | AB13: NA | AC13: NA
A14: 13 | B14: FOH | C14: 46038 | D14: 46051 | E14: 26.1 - Sprint 2 Stretch | F14: Atchaiah | G14: 51578 | H14: MFOH - MFOH [BAU] - Automation (50473) | I14: Story Completed | J14: 1 | K14: 1 | L14: 4 | M14: 46049 | N14: 46049 | O14: NA | P14: NA | Q14: NA | R14: NA | S14: NA | T14: 46882 | U14: 46049 | V14: 46049 | W14: NA | X14: NA | Y14: Steve | Z14: 46049 | AA14: None | AB14: NA | AC14: NA
A15: 14 | B15: FOH | C15: 46038 | D15: 46051 | E15: 26.1 - Sprint 2 Stretch | F15: Atchaiah | G15: 51579 | H15: MFOH - MFOH [BAU] - Automation (51081) | I15: Story Completed | J15: 1 | K15: 1 | L15: 4 | M15: 46050 | N15: 46050 | O15: NA | P15: NA | Q15: NA | R15: NA | S15: NA | T15: 46907 | U15: 46050 | V15: 46050 | W15: NA | X15: NA | Y15: Steve | Z15: 46050 | AA15: None | AB15: NA | AC15: NA
A16: 15 | B16: FOH | C16: 46038 | D16: 46051 | E16: 26.1 - Sprint 2 Stretch | F16: Atchaiah | G16: 51582 | H16: MFOH - MFOH [BAU] - Automation (45804) | I16: Story Completed | J16: 1 | K16: 1 | L16: 4 | M16: 46051 | N16: 46051 | O16: NA | P16: NA | Q16: NA | R16: NA | S16: NA | T16: 46940 | U16: 46051 | V16: 46051 | W16: NA | X16: NA | Y16: Steve | Z16: 46051 | AA16: None | AB16: NA | AC16: NA
A17: 16 | B17: FOH | C17: 46038 | D17: 46051 | E17: 26.1 - Sprint 2 Stretch | F17: Subhasri | G17: 51588 | H17: Mosaic FOH - Script to update all districts to Tier 2 | I17: Story Ready For Testing | J17: 1 | K17: 0.25 | L17: 1 | M17: 46051 | N17: 46051 | O17: NA | P17: NA | Q17: NA | R17: NA | S17: NA | T17: 46951 | U17: 46051 | V17: 46051 | W17: NA | X17: NA | Y17: Steve | Z17: 46051 | AA17: None | AB17: NA | AC17: NA
A18: 17 | B18: FOH | C18: 46038 | D18: 46051 | E18: 26.1 - Sprint 2 Stretch | F18: Atchaiah | G18: 51576 | H18: MFOH - MFOH [BAU] - Automation (46897) | I18: Story Being Developed | J18: 2 | K18: 1 | L18: 4 | M18: 46044 | AD18: Close day report Vega UI changes have been updated.
A19: 18 | B19: FOH | C19: 46038 | D19: 46051 | E19: 26.1 - Sprint 2 Stretch | F19: Ashwin | G19: 26587 | H19: MFOH - Add New Eligibility Record UI is crashed | I19: Story Being Developed | J19: 3 | K19: 0.25 | L19: 1 | M19: 46038 | N19: 46038 | AD19: This is in stretch and its a low priority defect. May be carry forward in the next sprint for reviews and testing.
A20: 19 | B20: FOH | C20: 46038 | D20: 46051 | E20: 26.1 - Sprint 2 Stretch | F20: Arvinth | G20: 50680 | H20: MFOH - Add 'Daily Sales Report CC' as a Close Day Report | I20: Story Being Developed | J20: 5 | K20: 1.5 | L20: 6 | M20: 46044 | AD20: Kept hold of this story, due to priority items in the Sprint

Sheet 26.1 - Sprint 2-Defect
A1: S.No | B1: Sprint # | C1: Story/Defect ID | D1: Parent Story | E1: Developer | F1: Issue Type | G1: Issue Description | H1: Priority | I1: Defect Source | J1: Type | K1: Status | L1: Root Cause Category | M1: Comments
B2: 26.1 - Sprint 2 | C2: 46682 | D2: 46682 | E2: Alpha | F2: Bounceback/Sub-Defect | G2: Grand total was showing when running for Single school | H2: Minor | I2: Manual | J2: Internal | K2: Closed/Rejected | L2: Enhancements

Sheet 26.1 - Sprint 1-Status
A1: S.No | B1: Application Name | C1: Sprint Start Date | D1: Sprint End Date | E1: Sprint | F1: Developer | G1: Story ID/Defect ID | H1: Description | I1: Status | J1: Estimated(hrs/sp) | K1: Actual(hrs/sp) | L1: Actual Worklog (Hours) | M1: Dev Start Date | N1: Dev End Date | O1: Unit testing | P1: Peer Tested By | Q1: Peer Tested Comments, if any | R1: Peer Reviewed By | S1: Peer Code Review Comments, if any | T1: PR Number/Link | U1: PR Created Date | V1: PR Approved Date | W1: Onsite Lead Code Review | X1: Code Review Comments, if any | Y1: Client Code Review | Z1: Approved Date | AA1: Code Review Comments, if any2 | AB1: Internal PO -POV Comments | AC1: Client PO -POV Comments | AD1: Comments | AE1: Does this story meet expectations?
A2: 1 | B2: FOH | C2: 46010 | D2: 46037 | E2: 26.1 - Sprint 1 | F2: Alpha | G2: 51326 | H2: Mosaic POS- Capture Serving line Note Changes and Grades for Student History Report | I2: Story Completed | J2: 5 | K2: 4.5 | L2: 18 | M2: 46010 | N2: 46015 | O2: Alpha | P2: Ashwin | Q2: None | R2: Arvinth | S2: None | T2: 46516 | U2: 46030 | V2: 46030 | W2: Subha | X2: Remove blank space in the botom of the stored procedure | Y2: Steve | Z2: 46030 | AA2: None | AB2: None | AC2: NA | AE2: Meets Expectation
A3: 2 | B3: FOH | C3: 46010 | D3: 46037 | E3: 26.1 - Sprint 1 | F3: Arvinth/Alpha | G3: 50473 | H3: MFOH - Add 'Elig. Record Notes' as a Field to Custom Student Report | I3: Story Completed | J3: 2 | K3: 2 | L3: 8 | M3: 46010 | N3: 46010 | O3: Arvinth | P3: Ashwin | Q3: None | R3: Alpha | S3: None | T3: 46454 | U3: 46028 | V3: 46028 | W3: Subha | X3: None | Y3: Steve | Z3: 46028 | AA3: None | AB3: None | AC3: NA | AE3: Meets Expectation
A4: 3 | B4: FOH | C4: 46010 | D4: 46037 | E4: 26.1 - Sprint 1 | F4: Atchaiah | G4: 51057 | H4: MFOH [BAU] - Automation (49680) | I4: Story Completed | J4: 2 | K4: 2 | L4: 8 | M4: 46010 | N4: 46013 | O4: NA | P4: NA | Q4: NA | R4: NA | S4: NA | T4: 46458 | U4: 46028 | V4: 46028 | W4: NA | X4: NA | Y4: Steve | Z4: 46028 | AA4: None | AB4: NA | AC4: NA
A5: 4 | B5: FOH | C5: 46010 | D5: 46037 | E5: 26.1 - Sprint 1 | F5: Ashwin/Arvinth | G5: 51222 | H5: MFOH - Student Letter Setup (Alternate) - Add Label Formats | I5: Story Completed | J5: 5 | K5: 5 | L5: 20 | M5: 46010 | N5: 46014 | O5: Ashwin | P5: Arvinth | Q5: None | R5: Arvinth | S5: None | T5: 46453 | U5: 46028 | V5: 46028 | W5: Subha | X5: None | Y5: Steve | Z5: 46028 | AA5: None | AB5: None | AC5: NA | AE5: Meets Expectation
A6: 5 | B6: FOH | C6: 46010 | D6: 46037 | E6: 26.1 - Sprint 1 | F6: Subhasri/Arvinth | G6: 46897 | H6: MFOH - Add a report type filter to Student Meal Report | I6: Story Completed | J6: 5 | K6: 7 | L6: 28 | M6: 46010 | N6: 46030 | O6: Subhasri | P6: Alpha | Q6: 1. A few issues due to Vega changes. 2. When we are running the report with Purchased Meal: Yes (Has Non-Reimb. Meal), the report header is showing if there is no data exists | R6: Alpha | S6: None | T6: 46590 | U6: 46034 | V6: 46034 | W6: NA | X6: NA | Y6: Steve | Z6: 46034 | AA6: None | AB6: None | AC6: NA | AE6: Meets Expectation
A7: 6 | B7: FOH | C7: 46010 | D7: 46037 | E7: 26.1 - Sprint 1 | F7: Arvinth/Alpha | G7: 50472 | H7: MFOH - Add 'Student Notes' as a Field to Custom Student Report | I7: Story Completed | J7: 3 | K7: 3 | L7: 12 | M7: 46013 | N7: 46014 | O7: Arvinth | P7: Ashwin | Q7: None | R7: Alpha | S7: None | T7: 46453 | U7: 46028 | V7: 46028 | W7: Subha | X7: None | Y7: Steve | Z7: 46028 | AA7: None | AB7: None | AC7: NA | AE7: Meets Expectation
A8: 7 | B8: FOH | C8: 46010 | D8: 46037 | E8: 26.1 - Sprint 1 | F8: Atchaiah | G8: 51058 | H8: MFOH [BAU] - Automation (50183) | I8: Story Completed | J8: 1 | K8: 1 | L8: 4 | M8: 46014 | N8: 46014 | O8: NA | P8: NA | Q8: NA | R8: NA | S8: NA | T8: 46443 | U8: 46028 | V8: 46028 | W8: NA | X8: NA | Y8: Steve | Z8: 46028 | AA8: None | AB8: NA | AC8: NA
A9: 8 | B9: FOH | C9: 46010 | D9: 46037 | E9: 26.1 - Sprint 1 | F9: Atchaiah | G9: 51059 | H9: MFOH [BAU] - Automation (49970) | I9: Story Completed | J9: 1 | K9: 1 | L9: 4 | M9: 46015 | N9: 46015 | O9: NA | P9: NA | Q9: NA | R9: NA | S9: NA | T9: 46442 | U9: 46028 | V9: 46028 | W9: NA | X9: NA | Y9: Steve | Z9: 46028 | AA9: None | AB9: NA | AC9: NA
A10: 9 | B10: FOH | C10: 46010 | D10: 46037 | E10: 26.1 - Sprint 1 | F10: Atchaiah | G10: 51060 | H10: MFOH [BAU] - Automation (50325) | I10: Story Completed | J10: 1 | K10: 1 | L10: 4 | M10: 46021 | N10: 46022 | O10: NA | P10: NA | Q10: NA | R10: NA | S10: NA | T10: 46438 | U10: 46028 | V10: 46028 | W10: NA | X10: NA | Y10: Steve | Z10: 46028 | AA10: None | AB10: NA | AC10: NA
A11: 10 | B11: FOH | C11: 46010 | D11: 46037 | E11: 26.1 - Sprint 1 | F11: Alpha/Arvinth | G11: 51081 | H11: Mosaic POS- Serving line note & Grade feature in Event type filter for Student History Report | I11: Story Completed | J11: 3 | K11: 3 | L11: 12 | M11: 46022 | N11: 46028 | O11: Alpha | P11: Ashwin | Q11: None | R11: Arvinth | S11: None | T11: 46517 | U11: 46030 | V11: 46030 | W11: Subha | X11: None | Y11: Steve | Z11: 46030 | AA11: None | AB11: None | AC11: NA | AE11: Meets Expectation
A12: 11 | B12: FOH | C12: 46010 | D12: 46037 | E12: 26.1 - Sprint 1 | F12: Atchaiah | G12: 51061 | H12: MFOH [BAU] - Automation (50470) | I12: Story Completed | J12: 1 | K12: 1 | L12: 4 | M12: 46022 | N12: 46028 | O12: NA | P12: NA | Q12: NA | R12: NA | S12: NA | T12: 46459 | U12: 46028 | V12: 46028 | W12: NA | X12: NA | Y12: Steve | Z12: 46028 | AA12: None | AB12: NA | AC12: NA
A13: 12 | B13: FOH | C13: 46010 | D13: 46037 | E13: 26.1 - Sprint 1 | F13: Alpha/Arvinth | G13: 45804 | H13: Mosaic - POS (Web) - Add 'Include Barcode' filter to POS Roster Report | I13: Story Completed | J13: 3 | K13: 2 | L13: 8 | M13: 46028 | N13: 46030 | O13: Alpha | P13: Ashwin | Q13: None | R13: Arvinth | S13: None | T13: 46542 | U13: 46031 | V13: 46031 | W13: Subha | X13: None | Y13: Steve | Z13: 46031 | AA13: None | AB13: None | AC13: NA | AE13: Meets Expectation
A14: 13 | B14: FOH | C14: 46010 | D14: 46037 | E14: 26.1 - Sprint 1 | F14: Arvinth | G14: 26247 | H14: Mosaic FOH - Custom Student Lookup Defect | I14: Defect Fixed | J14: 1 | K14: 0.75 | L14: 3 | M14: NA | N14: NA | O14: NA | P14: NA | Q14: NA | R14: NA | S14: NA | T14: NA | U14: NA | V14: NA | W14: NA | X14: NA | Y14: NA | Z14: NA | AA14: NA | AB14: NA | AC14: NA
A15: 14 | B15: FOH | C15: 46010 | D15: 46037 | E15: 26.1 - Sprint 1 Stretch | F15: Arvinth/Alpha | G15: 51314 | H15: MFOH - Add a Student Active filter to Notification Letter (Elig. Record Maintenance) | I15: Story Completed | J15: 2 | K15: 2 | L15: 8 | M15: 46020 | N15: 46021 | O15: Arvinth | P15: Ashwin | Q15: None | R15: Alpha | S15: None | T15: 46527 | U15: 46030 | V15: 46030 | W15: Subha | X15: None | Y15: Steve | Z15: 46030 | AA15: None | AB15: None | AC15: NA | AE15: Meets Expectation
A16: 15 | B16: FOH | C16: 46010 | D16: 46037 | E16: 26.1 - Sprint 1 Stretch | F16: Arvinth/Alpha | G16: 50849 | H16: MFOH - Replace Blank with '0.00' for the columns in the report when the day is opened with 0 meal counts | I16: Story Completed | J16: 2 | K16: 2 | L16: 8 | M16: 46021 | N16: 46021 | O16: Arvinth | P16: Ashwin | Q16: None | R16: Alpha | S16: None | T16: 46528 | U16: 46030 | V16: 46030 | W16: Subha | X16: None | Y16: Steve | Z16: 46030 | AA16: None | AB16: None | AC16: NA | AE16: Meets Expectation
A17: 16 | B17: FOH | C17: 46010 | D17: 46037 | E17: 26.1 - Sprint 1 Stretch | F17: Ashwin/Arvinth | G17: 49449 | H17: MFOH - Add a new export field 'Custom Charge Limit' to Student Export | I17: Story Completed | J17: 3 | K17: 2.75 | L17: 11 | M17: 46014 | N17: 46015 | O17: Ashwin | P17: Arvinth | Q17: None | R17: Arvinth | S17: None | T17: 46518 | U17: 46030 | V17: 46030 | W17: Subha | X17: None | Y17: Steve | Z17: 46030 | AA17: None | AB17: None | AC17: NA | AE17: Meets Expectation
A18: 17 | B18: FOH | C18: 46010 | D18: 46037 | E18: 26.1 - Sprint 1 Stretch | F18: Atchaiah | G18: 51397 | H18: MFOH [BAU] - Automation (47864) | I18: Story Completed | J18: 2 | K18: 2 | L18: 8 | M18: 46028 | N18: 46030 | O18: NA | P18: NA | Q18: NA | R18: NA | S18: NA | T18: 46523 | U18: 46030 | V18: 46030 | W18: NA | X18: NA | Y18: Steve | Z18: 46030 | AA18: None | AB18: NA | AC18: NA | AE18: Meets Expectation
A19: 18 | B19: FOH | C19: 46010 | D19: 46037 | E19: 26.1 - Sprint 1 Stretch | F19: Subhasri | G19: 50847 | H19: MFOH - Hide the visibility of Balance/Status column based on the Report Type selection (POS Roster Report) | I19: Story Completed | J19: 2 | K19: 2 | L19: 8.25 | M19: 46027 | N19: 46027 | O19: Subhasri | P19: Alpha | Q19: NA | R19: Alpha | S19: NA | T19: 46491 | U19: 46029 | V19: 46029 | W19: NA | X19: NA | Y19: Steve | Z19: 46029 | AA19: None | AB19: NA | AC19: NA | AE19: Meets Expectation
A20: 19 | B20: FOH | C20: 46010 | D20: 46037 | E20: 26.1 - Sprint 1 Stretch | F20: Atchaiah | G20: 51398 | H20: MFOH [BAU] - Automation (48289) | I20: Story Completed | J20: 2 | K20: 2 | L20: 8 | M20: 46030 | N20: 46034 | O20: NA | P20: NA | Q20: NA | R20: NA | S20: NA | T20: 46579 | U20: 46034 | V20: 46034 | W20: NA | X20: NA | Y20: Steve | Z20: 46034 | AA20: None | AB20: NA | AC20: NA
A21: 20 | B21: FOH | C21: 46010 | D21: 46037 | E21: 26.1 - Sprint 1 Stretch | F21: Atchaiah | G21: 51399 | H21: MFOH [BAU] - Automation (48824) | I21: Story Completed | J21: 1 | K21: 1 | L21: 4 | M21: 46035 | N21: 46036 | O21: NA | P21: NA | Q21: NA | R21: NA | S21: NA | T21: 46644 | U21: 46036 | V21: 46036 | W21: NA | X21: NA | Y21: Steve | Z21: 46036 | AA21: None | AB21: NA | AC21: NA
A22: 21 | B22: FOH | C22: 46010 | D22: 46037 | E22: 26.1 - Sprint 1 Stretch | F22: Subhasri | G22: 51459 | H22: MFOH - MSA Client - Determine the matching logics (Analysis Story) | I22: Story Completed | J22: 2 | K22: 2 | L22: 9 | M22: 46031 | N22: 46036 | O22: NA | P22: NA | Q22: NA | R22: NA | S22: NA | T22: NA | U22: NA | V22: NA | W22: NA | X22: NA | Y22: NA | Z22: NA | AA22: NA | AB22: NA | AC22: NA | AE22: NA
A23: 22 | B23: FOH | C23: 46010 | D23: 46037 | E23: 26.1 - Sprint 1 Stretch | F23: Arvinth | G23: 51180 | H23: MFOH - Add 'Weekly with Only Status' report type option to 'POS Weekly Roster Report' | I23: Story Ready For Testing | J23: 5 | K23: 5 | L23: 20 | M23: 46022 | N23: 46036 | O23: Arvinth | P23: Alpha | Q23: None | R23: Alpha | S23: None | T23: 46652 | U23: 46036 | V23: 46036 | W23: Subha | X23: None | Y23: Steve | Z23: 46036 | AA23: None | AB23: None | AC23: NA | AE23: Meets Expectation
A24: 23 | B24: FOH | C24: 46010 | D24: 46037 | E24: 26.1 - Sprint 1 Stretch | F24: Subhasri | G24: 26521 | H24: Mosaic FOH - Fall Mountain Regional School District - Student Account Summary Defect- some adjustments not being counted | I24: Story Being Developed | J24: 1 | K24: 0.75 | L24: 3 | M24: 46029 | AD24: Changed to Story Needs more info in axosoft
A25: 24 | B25: FOH | C25: 46010 | D25: 46037 | E25: 26.1 - Sprint 1 Stretch | F25: Alpha | G25: 51435 | H25: Mosaic FOH - Special Provision Edit Check Report - Display entire Free Claim % | I25: Story Being Developed | J25: 3 | K25: 1.5 | L25: 6 | M25: 46031
A26: 25 | B26: FOH | C26: 46010 | D26: 46037 | E26: 26.1 - Sprint 1 Stretch | F26: Arvinth | G26: 49981 | H26: MFOH - Add a 'School' filter to 'Menu Product Detail Report' | I26: Story Being Developed | J26: 3 | K26: 1.5 | L26: 6 | M26: 46031
A27: 26 | B27: FOH | C27: 46010 | D27: 46037 | E27: 26.1 - Sprint 1 Stretch | F27: Atchaiah | G27: 51400 | H27: MFOH [BAU] - Automation (50446) | I27: Story Being Developed | J27: 1 | K27: 1 | L27: 4 | M27: 46036

Sheet 26.1 - Sprint 1-Defect
A1: S.No | B1: Sprint # | C1: Story/Defect ID | D1: Parent Story | E1: Developer | F1: Issue Type | G1: Issue Description | H1: Priority | I1: Defect Source | J1: Type | K1: Status | L1: Root Cause Category | M1: Comments

Sheet 4.25 - Sprint 5-Status
A1: S.No | B1: Application Name | C1: Sprint Start Date | D1: Sprint End Date | E1: Sprint | F1: Developer | G1: Story ID/Defect ID | H1: Description | I1: Status | J1: Estimated(hrs/sp) | K1: Actual(hrs/sp) | L1: Actual Worklog (Hours) | M1: Dev Start Date | N1: Dev End Date | O1: Unit testing | P1: Peer Tested By | Q1: Peer Tested Comments, if any | R1: Peer Reviewed By | S1: Peer Code Review Comments, if any | T1: PR Number/Link | U1: PR Created Date | V1: PR Approved Date | W1: Onsite Lead Code Review | X1: Code Review Comments, if any | Y1: Client Code Review | Z1: Approved Date | AA1: Code Review Comments, if any2 | AB1: Internal PO -POV Comments | AC1: Client PO -POV Comments | AD1: Comments | AE1: Does this story meet expectations?
A2: 1 | B2: FOH | C2: 45982 | D2: 46009 | E2: 4.25 - Sprint 5 | F2: Arvinth/Alpha | G2: 50817 | H2: Mosaic FOH - Snyk Findings - Path Traversal - UtilitiesController.cs - Part 2 | I2: Story Completed | J2: 3 | K2: =Table24568910212131411151819202122172324252627282930[[#This Row],[Actual Worklog (Hours)]] / 4 -> 3 | L2: 12 | M2: 45982 | N2: 45985 | O2: Arvinth | P2: Atchai | Q2: None | R2: Alpha | S2: None | T2: 45932 | U2: 45986 | V2: 45986 | W2: Subha | X2: None | Y2: Ying | Z2: 45986 | AA2: None | AB2: NA | AC2: NA
A3: 2 | B3: FOH | C3: 45982 | D3: 46009 | E3: 4.25 - Sprint 5 | F3: Subhasri/Arvinth | G3: 50813 | H3: Mosaic FOH - Snyk Findings - Path Traversal - UtilitiesController.cs | I3: Story Completed | J3: 5 | K3: 3 | L3: 15.75 | M3: 45982 | N3: 45985 | O3: Subhasri | P3: Arvinth | Q3: If there is export path textbox in UI, shall we change the else condition to else if (string.IsNullOrEmpty(model.ExportPath) | R3: Arvinth | S3: None | T3: 45950 | U3: 45986 | V3: 45986 | W3: NA | X3: NA | Y3: Ying | Z3: 45986 | AA3: None | AB3: NA | AC3: NA
A4: 3 | B4: FOH | C4: 45982 | D4: 46009 | E4: 4.25 - Sprint 5 | F4: Alpha | G4: 50785 | H4: Mosaic FOH - Snyk Findings - Cross-site Scripting - ‎EndOfDayController.cs | I4: Story Completed | J4: 3 | K4: =Table24568910212131411151819202122172324252627282930[[#This Row],[Actual Worklog (Hours)]] / 4 -> 2.25 | L4: 9 | M4: 45985 | N4: 45992 | O4: NA | P4: NA | Q4: NA | R4: NA | S4: NA | T4: NA | U4: NA | V4: NA | W4: NA | X4: NA | Y4: NA | Z4: NA | AA4: NA | AB4: NA | AC4: NA | AD4: Story Rejected; No code changes needed.
A5: 4 | B5: FOH | C5: 45982 | D5: 46009 | E5: 4.25 - Sprint 5 | F5: Atchaiah | G5: 50688 | H5: MFOH [BAU] - Automation (50224) | I5: Story Completed | J5: 1 | K5: =Table24568910212131411151819202122172324252627282930[[#This Row],[Actual Worklog (Hours)]] / 4 -> 1 | L5: 4 | M5: 45985 | N5: 45986 | O5: NA | P5: NA | Q5: NA | R5: NA | S5: NA | T5: 45934 | U5: 45986 | V5: 45986 | W5: NA | X5: NA | Y5: Ying | Z5: 45986 | AA5: None | AB5: NA | AC5: NA
A6: 5 | B6: FOH | C6: 45982 | D6: 46009 | E6: 4.25 - Sprint 5 | F6: Alpha/Arvinth | G6: 50818 | H6: Mosaic FOH - Snyk Findings - Path Traversal - FreeAndReducedReportsController.cs | I6: Story Completed | J6: 2 | K6: =Table24568910212131411151819202122172324252627282930[[#This Row],[Actual Worklog (Hours)]] / 4 -> 1.9375 | L6: 7.75 | M6: 45986 | N6: 45986 | O6: Alpha | P6: Arvinth | Q6: None | R6: Arvinth | S6: None | T6: 45923 | U6: 45986 | V6: 45986 | W6: Subha | X6: None | Y6: Ying | Z6: 45986 | AA6: None | AB6: NA | AC6: NA
A7: 6 | B7: FOH | C7: 45982 | D7: 46009 | E7: 4.25 - Sprint 5 | F7: Arvinth | G7: 50820 | H7: Mosaic FOH - Snyk Findings - Path Traversal - ReportController.cs | I7: Story Completed | J7: 2 | K7: =Table24568910212131411151819202122172324252627282930[[#This Row],[Actual Worklog (Hours)]] / 4 -> 2 | L7: 8 | M7: 45985 | N7: 45987 | O7: NA | P7: NA | Q7: NA | R7: NA | S7: NA | T7: NA | U7: NA | V7: NA | W7: NA | X7: NA | Y7: NA | Z7: NA | AA7: NA | AB7: NA | AC7: NA
A8: 7 | B8: FOH | C8: 45982 | D8: 46009 | E8: 4.25 - Sprint 5 | F8: Alpha | G8: 50819 | H8: Mosaic FOH - Snyk Findings - Path Traversal - OtherReportsController.cs | I8: Story Completed | J8: 2 | K8: =Table24568910212131411151819202122172324252627282930[[#This Row],[Actual Worklog (Hours)]] / 4 -> 1.75 | L8: 7 | M8: 45985 | N8: 45986 | O8: Alpha | P8: Arvinth | Q8: None | R8: Arvinth | S8: None | T8: 45980 | U8: 45992 | V8: 45992 | W8: Subha | X8: None | Y8: Ying | Z8: 45992 | AA8: None | AB8: NA | AC8: NA
A9: 8 | B9: FOH | C9: 45982 | D9: 46009 | E9: 4.25 - Sprint 5 | F9: Atchaiah | G9: 50690 | H9: MFOH [BAU] - Automation (50301) | I9: Story Completed | J9: 1 | K9: =Table24568910212131411151819202122172324252627282930[[#This Row],[Actual Worklog (Hours)]] / 4 -> 1 | L9: 4 | M9: 45982 | N9: 45985 | O9: NA | P9: NA | Q9: NA | R9: NA | S9: NA | T9: 45894 | U9: 45985 | V9: 45986 | W9: NA | X9: NA | Y9: Ying | Z9: 45986 | AA9: None | AB9: NA | AC9: NA
A10: 9 | B10: FOH | C10: 45982 | D10: 46009 | E10: 4.25 - Sprint 5 | F10: Atchaiah | G10: 50691 | H10: MFOH [BAU] - Automation (50405) | I10: Story Completed | J10: 1 | K10: 1 | L10: 4 | M10: 45989 | N10: 45992 | O10: NA | P10: NA | Q10: NA | R10: NA | S10: NA | T10: 45985 | U10: 45992 | V10: 45992 | W10: NA | X10: NA | Y10: Ying | Z10: 45992 | AA10: None | AB10: NA | AC10: NA
A11: 10 | B11: FOH | C11: 45982 | D11: 46009 | E11: 4.25 - Sprint 5 | F11: Subhasri | G11: 26304 | H11: MFOH - Offsite Meal Report - Do not exclude inactive students | I11: Story Completed | J11: 2 | K11: 1 | L11: 4 | M11: 45987 | N11: 45989
A12: 11 | B12: FOH | C12: 45982 | D12: 46009 | E12: 4.25 - Sprint 5 | F12: Arvinth/Alpha | G12: 50786 | H12: Mosaic FOH - Snyk Findings - Path Traversal - ‎EndOfDayController.cs | I12: Story Completed | J12: 2 | K12: 1.75 | L12: 7 | M12: 45985 | N12: 45986 | O12: Arvinth | P12: Alpha | Q12: None | R12: Alpha | S12: None | T12: 45931 | U12: 45986 | V12: 45986 | W12: Subha | X12: None | Y12: Ying | Z12: 45986 | AA12: None | AB12: NA | AC12: NA
A13: 12 | B13: FOH | C13: 45982 | D13: 46009 | E13: 4.25 - Sprint 5 | F13: Arvinth | G13: 50809 | H13: Mosaic FOH - Snyk Findings - Server-Side Request Forgery (SSRF) - ‎DF.WCF/BOHSyncWCF.cs | I13: Story Completed | J13: 1 | K13: 1 | L13: 4 | M13: NA | N13: NA | O13: NA | P13: NA | Q13: NA | R13: NA | S13: NA | T13: NA | U13: NA | V13: NA | W13: NA | X13: NA | Y13: NA | Z13: NA | AA13: NA | AB13: NA | AC13: NA | AD13: Manual Testing story.
A14: 13 | B14: FOH | C14: 45982 | D14: 46009 | E14: 4.25 - Sprint 5 | F14: Arvinth | G14: 50812 | H14: Mosaic FOH - Snyk Findings - Server-Side Request Forgery (SSRF) - LunchBoxScheduler/MySchoolBucks.cs | I14: Story Completed | J14: 1 | K14: 1 | L14: 4 | M14: NA | N14: NA | O14: NA | P14: NA | Q14: NA | R14: NA | S14: NA | T14: NA | U14: NA | V14: NA | W14: NA | X14: NA | Y14: NA | Z14: NA | AA14: NA | AB14: NA | AC14: NA | AD14: Manual Testing story.
A15: 14 | B15: FOH | C15: 45982 | D15: 46009 | E15: 4.25 - Sprint 5 | F15: Alpha | G15: 50844 | H15: Mosaic FOH - Snyk Findings - Path Traversal - CateringReportsController.cs | I15: Story Completed | J15: 1 | K15: 1 | L15: 4 | M15: NA | N15: NA | O15: NA | P15: NA | Q15: NA | R15: NA | S15: NA | T15: NA | U15: NA | V15: NA | W15: NA | X15: NA | Y15: NA | Z15: NA | AA15: NA | AB15: NA | AC15: NA | AD15: Manual Testing story.
A16: 15 | B16: FOH | C16: 45982 | D16: 46009 | E16: 4.25 - Sprint 5 | F16: Alpha/Atchaiah | G16: 50953 | H16: Mosaic - FOH 4.25 (Regression) - POS(Menu Option) | I16: Story Completed | J16: 2 | K16: 3 | L16: 12 | M16: 45994 | N16: 46008 | O16: NA | P16: NA | Q16: NA | R16: NA | S16: NA | T16: NA | U16: NA | V16: NA | W16: NA | X16: NA | Y16: NA | Z16: NA | AA16: NA | AB16: NA | AC16: NA | AD16: Regression Testing
A17: 16 | B17: FOH | C17: 45982 | D17: 46009 | E17: 4.25 - Sprint 5 | F17: Arvinth/Atchaiah | G17: 50948 | H17: Mosaic - FOH 4.25(Regression) - End of Day | I17: Story Completed | J17: 5 | K17: 7.25 | L17: 29 | M17: 45994 | N17: 46008 | O17: NA | P17: NA | Q17: NA | R17: NA | S17: NA | T17: NA | U17: NA | V17: NA | W17: NA | X17: NA | Y17: NA | Z17: NA | AA17: NA | AB17: NA | AC17: NA | AD17: Regression Testing
A18: 17 | B18: FOH | C18: 45982 | D18: 46009 | E18: 4.25 - Sprint 5 | F18: Alpha/Atchaiah | G18: 50958 | H18: Mosaic - FOH 4.25(Regression) - Setup | I18: Story Completed | J18: 5 | K18: 6.75 | L18: 27 | M18: 45995 | N18: 46008 | O18: NA | P18: NA | Q18: NA | R18: NA | S18: NA | T18: NA | U18: NA | V18: NA | W18: NA | X18: NA | Y18: NA | Z18: NA | AA18: NA | AB18: NA | AC18: NA | AD18: Regression Testing
A19: 18 | B19: FOH | C19: 45982 | D19: 46009 | E19: 4.25 - Sprint 5 | F19: Subhasri/Ashwin | G19: 50947 | H19: Mosaic - FOH 4.25(Regression) - Students | I19: Story Completed | J19: 5 | K19: 6.25 | L19: 25 | M19: 45994 | N19: 46008 | O19: NA | P19: NA | Q19: NA | R19: NA | S19: NA | T19: NA | U19: NA | V19: NA | W19: NA | X19: NA | Y19: NA | Z19: NA | AA19: NA | AB19: NA | AC19: NA | AD19: Regression Testing
A20: 19 | B20: FOH | C20: 45982 | D20: 46009 | E20: 4.25 - Sprint 5 | F20: Alpha/Atchaiah | G20: 50950 | H20: Mosaic - FOH 4.25 (Regression) - Reports - Eligibility (F&R) | I20: Story Completed | J20: 3 | K20: 3.75 | L20: 15 | M20: 45999 | N20: 46008 | O20: NA | P20: NA | Q20: NA | R20: NA | S20: NA | T20: NA | U20: NA | V20: NA | W20: NA | X20: NA | Y20: NA | Z20: NA | AA20: NA | AB20: NA | AC20: NA | AD20: Regression Testing
A21: 20 | B21: FOH | C21: 45982 | D21: 46009 | E21: 4.25 - Sprint 5 | F21: Arvinth/Atchaiah | G21: 50957 | H21: Mosaic - FOH 4.25(Regression) - Utilities | I21: Story Completed | J21: 5 | K21: 6.25 | L21: 25 | M21: 45996 | N21: 46008 | O21: NA | P21: NA | Q21: NA | R21: NA | S21: NA | T21: NA | U21: NA | V21: NA | W21: NA | X21: NA | Y21: NA | Z21: NA | AA21: NA | AB21: NA | AC21: NA | AD21: Regression Testing
A22: 21 | B22: FOH | C22: 45982 | D22: 46009 | E22: 4.25 - Sprint 5 | F22: Arvinth/Alpha | G22: 26450 | H22: MFOH (4.25 Regression) - Export Name is not fully showing in the Export Maintenance when there is a dot in the middle of the name | I22: Defect Fixed | J22: 0 | K22: 0 | L22: 0 | M22: 46003 | N22: 46003 | O22: Arvinth | P22: Alpha | Q22: None | R22: NA | S22: NA | T22: 46190 | U22: 46003 | V22: 46003 | W22: NA | X22: NA | Y22: Ying | Z22: 46003 | AA22: None | AB22: NA | AC22: NA
A23: 22 | B23: FOH | C23: 45982 | D23: 46009 | E23: 4.25 - Sprint 5 | F23: Arvinth/Alpha | G23: 26455 | H23: MFOH (4.25 Regression) - Up arrow and down arrow not visible in Bulk entry form settings | I23: Defect Fixed | J23: 0 | K23: 0 | L23: 0 | M23: 46003 | N23: 46003 | O23: Arvinth | P23: Alpha | Q23: None | R23: NA | S23: NA | T23: 46191 | U23: 46003 | V23: 46003 | W23: NA | X23: NA | Y23: Ying | Z23: 46003 | AA23: None | AB23: NA | AC23: NA
A24: 23 | B24: FOH | C24: 45982 | D24: 46009 | E24: 4.25 - Sprint 5 | F24: Arvinth/Alpha | G24: 26457 | H24: MFOH (4.25 Regression) - Student Grade dropdown style seems different | I24: Defect Fixed | J24: 0 | K24: 0 | L24: 0 | M24: 46003 | N24: 46003 | O24: Arvinth | P24: Alpha | Q24: None | R24: NA | S24: NA | T24: 46192 | U24: 46003 | V24: 46003 | W24: NA | X24: NA | Y24: Ying | Z24: 46003 | AA24: None | AB24: NA | AC24: NA
A25: 24 | B25: FOH | C25: 45982 | D25: 46009 | E25: 4.25 - Sprint 5 | F25: Arvinth/Alpha | G25: 26458 | H25: MFOH (4.25 Regression) - Edit button is disabled in Review transactions maintenance | I25: Defect Fixed | J25: 0 | K25: 0 | L25: 0 | M25: 46003 | N25: 46003 | O25: Arvinth | P25: Alpha | Q25: None | R25: NA | S25: NA | T25: 46193 | U25: 46003 | V25: 46003 | W25: Subha | X25: None | Y25: Ying | Z25: 46003 | AA25: None | AB25: NA | AC25: NA
A26: 25 | B26: FOH | C26: 45982 | D26: 46009 | E26: 4.25 - Sprint 5 | F26: Arvinth/Alpha | G26: 26459 | H26: MFOH (4.25 Regression) - when export directory textbox is empty in Alachu financial export, it's not throwing error | I26: Defect Fixed | J26: 0 | K26: 0 | L26: 0 | M26: 46003 | N26: 46003 | O26: Arvinth | P26: Alpha | Q26: None | R26: NA | S26: NA | T26: 46194 | U26: 46003 | V26: 46003 | W26: Subha | X26: None | Y26: Ying | Z26: 46003 | AA26: None | AB26: NA | AC26: NA
A27: 26 | B27: FOH | C27: 45982 | D27: 46009 | E27: 4.25 - Sprint 5 | F27: Alpha/Arvinth | G27: 26451 | H27: MFOH (4.25 Regression) - Serving in the Classroom Report does not return any value if the search has been done with POS Custom Lookup - PR #46197 | I27: Defect Fixed | J27: 0 | K27: 0 | L27: 0 | M27: 46003 | N27: 46003 | O27: Alpha | P27: Arvinth | Q27: None | R27: Arvinth | S27: None | T27: 46197 | U27: 46003 | V27: 46003 | W27: Subha | X27: None | Y27: Ying | Z27: 46003 | AA27: None | AB27: NA | AC27: NA
A28: 27 | B28: FOH | C28: 45982 | D28: 46009 | E28: 4.25 - Sprint 5 | F28: Alpha/Arvinth | G28: 26452 | H28: MFOH (4.25 Regression) - UI issue for button in Serving in the classroom page | I28: Defect Fixed | J28: 0 | K28: 0 | L28: 0 | M28: 46003 | N28: 46003 | O28: Alpha | P28: Arvinth | Q28: None | R28: Arvinth | S28: None | T28: 46196 | U28: 46003 | V28: 46003 | W28: Subha | X28: None | Y28: Ying | Z28: 46003 | AA28: None | AB28: NA | AC28: NA
A29: 28 | B29: FOH | C29: 45982 | D29: 46009 | E29: 4.25 - Sprint 5 | F29: Alpha/Arvinth/Ashwin | G29: 26453 | H29: MFOH (4.25 Regression) - UI issue for Grid in Feeding Site Meal Setup | I29: Defect Fixed | J29: 0 | K29: 0 | L29: 0 | M29: 46003 | N29: 46003 | O29: Alpha | P29: Arvinth | Q29: None | R29: Arvinth | S29: None | T29: 46195 | U29: 46003 | V29: 46003 | W29: Subha | X29: None | Y29: Ying | Z29: 46003 | AA29: None | AB29: NA | AC29: NA
A30: 29 | B30: FOH | C30: 45982 | D30: 46009 | E30: 4.25 - Sprint 5 | F30: Alpha/Arvinth/Ashwin | G30: 26449 | H30: MFOH (4.25 Regression) - Condition in Student Export Settings is saving the value without clicking Ok (Mappings) | I30: Defect Fixed | J30: 0 | K30: 0 | L30: 0 | M30: 46006 | N30: 46006 | O30: Alpha | P30: Arvinth | Q30: None | R30: Arvinth | S30: None | T30: 46223 | U30: 46006 | V30: 46006 | W30: Subha | X30: None | Y30: Ying | Z30: 46006 | AA30: None | AB30: NA | AC30: NA
A31: 30 | B31: FOH | C31: 45982 | D31: 46009 | E31: 4.25 - Sprint 5 | F31: Alpha/Arvinth/Ashwin | G31: 26456 | H31: MFOH (4.25 Regression) - Condition is saving the value without clicking Ok (Mappings and Exclusion) | I31: Defect Fixed | J31: 0 | K31: 0 | L31: 0 | M31: 46006 | N31: 46006 | O31: Alpha | P31: Arvinth | Q31: None | R31: Arvinth | S31: None | T31: 46225 | U31: 46006 | V31: 46006 | W31: Subha | X31: None | Y31: Ying | Z31: 46006 | AA31: None | AB31: NA | AC31: NA
A32: 31 | B32: FOH | C32: 45982 | D32: 46009 | E32: 4.25 - Sprint 5 | F32: Subhasri | G32: 50958 | H32: SQL 2008 Error in Dashboard Export Query | I32: Story Completed | J32: 0 | K32: 0 | L32: 0 | M32: 46009 | N32: 46009 | O32: Subhasri | P32: NA | Q32: NA | R32: NA | S32: NA | T32: 46282 | U32: 46009 | V32: 46009 | W32: NA | X32: NA | Y32: Ying | Z32: 46009 | AA32: None | AB32: None | AC32: NA | AD32: Regression Testing
A33: 32 | B33: FOH | C33: 45982 | D33: 46009 | E33: 4.25 - Sprint 5 | F33: Ashwin/Arvinth/Subha | G33: 26454 | H33: MFOH (4.25 Regression) - Bulk entry form setting allows duplicate name to save | I33: Defect Fixed | J33: 0 | K33: 0 | L33: 0 | M33: 46008 | N33: 46008 | O33: Arvinth | P33: Alpha | Q33: None | R33: Alpha | S33: None | T33: 46271 | U33: 46008 | V33: 46008 | W33: NA | X33: NA | Y33: Ying | Z33: 46008 | AA33: None | AB33: None | AC33: NA
A34: 33 | B34: FOH | C34: 45982 | D34: 46009 | E34: 4.25 - Sprint 5 Stretch | F34: Alpha/Atchaiah | G34: 50951 | H34: Mosaic - FOH 4.25 (Regression) - Eligibility (F&R) | I34: Story Completed | J34: 5 | K34: 6 | L34: 24 | M34: 46000 | N34: 46008 | O34: NA | P34: NA | Q34: NA | R34: NA | S34: NA | T34: NA | U34: NA | V34: NA | W34: NA | X34: NA | Y34: NA | Z34: NA | AA34: NA | AB34: NA | AC34: NA | AD34: Regression Testing
A35: 34 | B35: FOH | C35: 45982 | D35: 46009 | E35: 4.25 - Sprint 5 Stretch | F35: Atchaiah | G35: 51080 | H35: MFOH - Run Automation on FOH QA Site | I35: Story Completed | J35: 0 | K35: 8 | L35: 32 | M35: 45993 | N35: 46002 | O35: NA | P35: NA | Q35: NA | R35: NA | S35: NA | T35: NA | U35: NA | V35: NA | W35: NA | X35: NA | Y35: NA | Z35: NA | AA35: NA | AB35: NA | AC35: NA | AD35: Automation Testing
A36: 35 | B36: FOH | C36: 45982 | D36: 46009 | E36: 4.25 - Sprint 5 Stretch | F36: Atchaiah | G36: 51056 | H36: MFOH [BAU] - Automation (46270) | I36: Story Completed | J36: 2 | K36: 2 | L36: 8 | M36: 45989 | N36: 46009 | O36: NA | P36: NA | Q36: NA | R36: NA | S36: NA | T36: 46302 | U36: 46009 | V36: 46009 | W36: NA | X36: NA | Y36: Ying | Z36: 46009 | AA36: NA | AB36: NA | AC36: NA
A37: 36 | B37: FOH | C37: 45982 | D37: 46009 | E37: 4.25 - Sprint 5 Stretch | F37: Subhasri | G37: 26247 | H37: Mosaic FOH - Custom Student Lookup Defect | I37: Story Ready For Testing | J37: 0 | K37: 0 | L37: 0 | M37: 45992 | N37: 46002 | O37: Subhasri | P37: Arvinth | Q37: None | R37: Arvinth | S37: None | T37: 46202 | U37: 46003 | V37: 46003 | W37: NA | X37: NA | Y37: Ying | Z37: 46003 | AA37: None | AB37: None | AC37: NA
A38: 37 | B38: FOH | C38: 45982 | D38: 46009 | E38: 4.25 - Sprint 5 Stretch | F38: Arvinth | G38: 50473 | H38: MFOH - Add 'Elig. Record Notes' as a Field to Custom Student Report | I38: Story Being Developed | J38: 3 | K38: 1 | L38: 4 | M38: 46009
A39: 38 | B39: FOH | C39: 45982 | D39: 46009 | E39: 4.25 - Sprint 5 Stretch | F39: Alpha | G39: 45804 | H39: Mosaic - POS (Web) - Add 'Include Barcode' filter to POS Roster Report | I39: Story Being Developed | J39: 3 | K39: 3 | L39: 12 | M39: 46008

Sheet 4.25 - Sprint 5-Defect
A1: S.No | B1: Sprint # | C1: Story/Defect ID | D1: Parent Story | E1: Developer | F1: Issue Type | G1: Issue Description | H1: Priority | I1: Defect Source | J1: Type | K1: Status | L1: Root Cause Category | M1: Comments

Sheet 4.25 - Sprint 4-Status
A1: S.No | B1: Application Name | C1: Sprint Start Date | D1: Sprint End Date | E1: Sprint | F1: Developer | G1: Story ID/Defect ID | H1: Description | I1: Status | J1: Estimated(hrs/sp) | K1: Actual(hrs/sp) | L1: Actual Worklog (Hours) | M1: Dev Start Date | N1: Dev End Date | O1: Unit testing | P1: Peer Tested By | Q1: Peer Tested Comments, if any | R1: Peer Reviewed By | S1: Peer Code Review Comments, if any | T1: PR Number/Link | U1: PR Created Date | V1: PR Approved Date | W1: Onsite Lead Code Review | X1: Code Review Comments, if any | Y1: Client Code Review | Z1: Approved Date | AA1: Code Review Comments, if any2 | AB1: Internal PO -POV Comments | AC1: Client PO -POV Comments | AD1: Comments | AE1: Does this story meet expectations?
A2: 1 | B2: FOH | C2: 45968 | D2: 45981 | E2: 4.25 - Sprint 4 | F2: Arvinth | G2: 48289 | H2: MFOH - Allow to delete Inactive Student only with Zero Balances during EOY (KDE) | I2: Story Completed | J2: 5 | K2: 5.5 | L2: 22 | M2: 45968 | N2: 45973 | O2: Arvinth | P2: Alpha | Q2: None | R2: Alpha | S2: DEFAULT '0' in the script should be given as 0 | T2: 45702 | U2: 45974 | V2: 45974 | W2: Subha | X2: remove the console and remove version history in file that doesn't has changes | Y2: Steve | Z2: 45974 | AA2: None | AB2: None | AC2: None | AE2: Meets Expectation
A3: 2 | B3: FOH | C3: 45968 | D3: 45981 | E3: 4.25 - Sprint 4 | F3: Alpha | G3: 47864 | H3: MFOH - Add an option to the Advance Schools/Grades setting to select 12th graders (Close Year Screen) | I3: Story Completed | J3: 5 | K3: 4.5 | L3: 18 | M3: 45968 | N3: 45974 | O3: Alpha | P3: Arvinth | Q3: "No" option should be selected by default, change the width of the dropdown, Error when running the close year with "Yes - Everyone" | R3: Arvinth | S3: Remove unused line of code. | T3: 45762 | U3: 45978 | V3: 45978 | W3: Subha | X3: None | Y3: Steve | Z3: 45978 | AA3: None | AB3: None | AC3: NA | AE3: Meets Expectation
A4: 3 | B4: FOH | C4: 45968 | D4: 45981 | E4: 4.25 - Sprint 4 | F4: Alpha | G4: 26260 | H4: MFOH - Student Export - Add Export Fields and Quick Add - Not Applying Header Name | I4: Story Completed | J4: 1 | K4: 0.5 | L4: 2 | M4: 45972 | N4: 45972 | O4: Alpha | P4: Ashwin | Q4: None | R4: Arvinth | S4: None | T4: 45650 | U4: 45972 | V4: 45972 | W4: Subha | X4: None | Y4: Steve | Z4: 45972 | AA4: None | AB4: None | AC4: NA | AE4: Meets Expectation
A5: 4 | B5: FOH | C5: 45968 | D5: 45981 | E5: 4.25 - Sprint 4 | F5: Ashwin | G5: 48824 | H5: MFOH - Add 'Letter Sent Status' filter to Student Letters | I5: Story Completed | J5: 3 | K5: 2.75 | L5: 11 | M5: 45968 | N5: 45972 | O5: Ashwin | P5: Alpha | Q5: None | R5: Alpha | S5: None | T5: 45735 | U5: 45975 | V5: 45975 | W5: Subha | X5: None | Y5: Steve | Z5: 45975 | AA5: None | AB5: None | AC5: NA | AE5: Meets Expectation
A6: 5 | B6: FOH | C6: 45968 | D6: 45981 | E6: 4.25 - Sprint 4 | F6: Arvinth | G6: 26202 | H6: MFOH - MEC - Kaleida UI Issues | I6: Story Completed | J6: 1 | K6: 0.5 | L6: 2 | M6: 45972 | N6: 45972 | O6: Arvinth | P6: Alpha | Q6: None | R6: Alpha | S6: None | T6: 45646 | U6: 45972 | V6: 45972 | W6: Subha | X6: None | Y6: Steve | Z6: 45972 | AA6: None | AB6: None | AC6: NA | AE6: Meets Expectation
A7: 6 | B7: FOH | C7: 45968 | D7: 45981 | E7: 4.25 - Sprint 4 | F7: Subhasri | G7: 26255 | H7: MFOH - Fields not populating for Student Listing Data Source (Report Designer) | I7: Story Completed | J7: 2 | K7: 2 | L7: 8 | M7: 45974 | N7: 45975 | O7: Subhasri | P7: Arvinth | Q7: None | R7: Arvinth | S7: None | T7: 45772 | U7: 45978 | V7: 45978 | W7: NA | X7: NA | Y7: Steve | Z7: 45978 | AA7: None | AB7: None | AC7: None | AE7: Meets Expectation
A8: 7 | B8: FOH | C8: 45968 | D8: 45981 | E8: 4.25 - Sprint 4 | F8: Subhasri | G8: 50149 | H8: MFOH - MSA Client (Communication) | I8: Story Being Tested | J8: 5 | K8: 5 | L8: 20 | M8: 45971 | N8: 45973 | O8: Subhasri | P8: Arvinth | Q8: None | R8: Arvinth | S8: None | T8: 45713 | U8: 45974 | V8: 45974 | W8: NA | X8: NA | Y8: Steve | Z8: 45974 | AA8: None | AB8: None | AC8: None | AD8: This story was in onsite QA Bucket (Mike) | AE8: Meets Expectation
A9: 8 | B9: FOH | C9: 45968 | D9: 45981 | E9: 4.25 - Sprint 4 Stretch | F9: Atchaiah | G9: 50685 | H9: MFOH [BAU] - Automation (50100) | I9: Story Completed | J9: 2 | K9: 2 | L9: 8 | M9: 45971 | N9: 45968 | O9: NA | P9: NA | Q9: NA | R9: NA | S9: NA | T9: 45754 | U9: 45978 | V9: 45978 | W9: NA | X9: NA | Y9: Steve | Z9: 45978 | AA9: None | AB9: NA | AC9: NA
A10: 9 | B10: FOH | C10: 45968 | D10: 45981 | E10: 4.25 - Sprint 4 Stretch | F10: Atchaiah | G10: 50739 | H10: MFOH - CPS Automation | I10: Story Completed | J10: 5 | K10: 5 | L10: 20 | M10: 45967 | N10: 45974 | O10: NA | P10: NA | Q10: NA | R10: NA | S10: NA | T10: NA | U10: NA | V10: NA | W10: NA | X10: NA | Y10: NA | Z10: NA | AA10: NA | AB10: NA | AC10: NA
A11: 10 | B11: FOH | C11: 45968 | D11: 45981 | E11: 4.25 - Sprint 4 Stretch | F11: Atchaiah | G11: 50684 | H11: MFOH [BAU] - Automation (49975) | I11: Story Completed | J11: 1 | K11: 1 | L11: 4 | M11: 45978 | N11: 45979 | O11: NA | P11: NA | Q11: NA | R11: NA | S11: NA | T11: 45788 | U11: 45979 | V11: 45979 | W11: NA | X11: NA | Y11: Steve | Z11: 45979 | AA11: None | AB11: NA | AC11: NA
A12: 11 | B12: FOH | C12: 45968 | D12: 45981 | E12: 4.25 - Sprint 4 Stretch | F12: Atchaiah | G12: 50686 | H12: MFOH [BAU] - Automation (49233) | I12: Story Completed | J12: 1 | K12: 1 | L12: 4 | M12: 45979 | N12: 45980 | O12: NA | P12: NA | Q12: NA | R12: NA | S12: NA | T12: 45813 | U12: 45980 | V12: 45980 | W12: NA | X12: NA | Y12: Steve | Z12: 45980 | AA12: None | AB12: NA | AC12: NA
A13: 12 | B13: FOH | C13: 45968 | D13: 45981 | E13: 4.25 - Sprint 4 Stretch | F13: Atchaiah | G13: 50687 | H13: MFOH [BAU] - Automation (50108) | I13: Story Completed | J13: 1 | K13: 1 | L13: 4 | M13: 45980 | N13: 45980 | O13: NA | P13: NA | Q13: NA | R13: NA | S13: NA | T13: 45825 | U13: 45980 | V13: 45980 | W13: NA | X13: NA | Y13: Steve | Z13: 45980 | AA13: None | AB13: NA | AC13: NA
A14: 13 | B14: FOH | C14: 45968 | D14: 45981 | E14: 4.25 - Sprint 4 Stretch | F14: Atchaiah | G14: 50689 | H14: MFOH [BAU] - Automation (50140) | I14: Story Completed | J14: 1 | K14: 1 | L14: 4 | M14: 45981 | N14: 45981 | O14: NA | P14: NA | Q14: NA | R14: NA | S14: NA | T14: 45842 | U14: 45981 | V14: 45981 | W14: NA | X14: NA | Y14: Steve | Z14: 45981 | AA14: None | AB14: NA | AC14: NA
A15: 14 | B15: FOH | C15: 45968 | D15: 45981 | E15: 4.25 - Sprint 4 Stretch | F15: Alpha | G15: 50819 | H15: Mosaic FOH - Snyk Findings - Path Traversal - OtherReportsController.cs | I15: Story Being Developed | J15: 0 | K15: 1.25 | L15: 5 | M15: 45978 | N15: 45979 | O15: Alpha | P15: Ashwin | Q15: None | R15: Arvinth | S15: None | AD15: Waiting for PR conformation
A16: 15 | B16: FOH | C16: 45968 | D16: 45981 | E16: 4.25 - Sprint 4 Stretch | F16: Alpha | G16: 50818 | H16: Mosaic FOH - Snyk Findings - Path Traversal - FreeAndReducedReportsController.cs | I16: Story Being Developed | J16: 0 | K16: 1.25 | L16: 5 | M16: 45979 | N16: 45980 | O16: Alpha | P16: Ashwin | Q16: None | R16: Arvinth | S16: None | AD16: Waiting for PR conformation
A17: 16 | B17: FOH | C17: 45968 | D17: 45981 | E17: 4.25 - Sprint 4 Stretch | F17: Alpha | G17: 50785 | H17: Mosaic FOH - Snyk Findings - Cross-site Scripting - ‎EndOfDayController.cs | I17: Story Being Developed | J17: 0 | K17: 3 | L17: 12 | M17: 45980
A18: 17 | B18: FOH | C18: 45968 | D18: 45981 | E18: 4.25 - Sprint 4 Stretch | F18: Subhasri | G18: 50813 | H18: Mosaic FOH - Snyk Findings - Path Traversal - UtilitiesController.cs | I18: Story Being Developed | J18: 0 | K18: 2.5 | L18: 10 | M18: 45978
A19: 18 | B19: FOH | C19: 45968 | D19: 45981 | E19: 4.25 - Sprint 4 Stretch | F19: Arvinth | G19: 50786 | H19: Mosaic FOH - Snyk Findings - Path Traversal - ‎EndOfDayController.cs | I19: Story Being Developed | J19: 0 | K19: 3 | L19: 12 | M19: 45978 | N19: 45979 | O19: Arvinth | P19: Ashwin | Q19: None | R19: Alpha | S19: None | AD19: Waiting for PR conformation
A20: 19 | B20: FOH | C20: 45968 | D20: 45981 | E20: 4.25 - Sprint 4 Stretch | F20: Arvinth | G20: 50817 | H20: Mosaic FOH - Snyk Findings - Path Traversal - UtilitiesController.cs - Part 2 | I20: Story Being Developed | J20: 0 | K20: 2 | L20: 8 | M20: 45980

Sheet 4.25 - Sprint 3-Status
A1: S.No | B1: Application Name | C1: Sprint Start Date | D1: Sprint End Date | E1: Sprint | F1: Developer | G1: Story ID/Defect ID | H1: Description | I1: Status | J1: Estimated(hrs/sp) | K1: Actual(hrs/sp) | L1: Actual Worklog (Hours) | M1: Dev Start Date | N1: Dev End Date | O1: Unit testing | P1: Peer Tested By | Q1: Peer Tested Comments, if any | R1: Peer Reviewed By | S1: Peer Code Review Comments, if any | T1: PR Number/Link | U1: PR Created Date | V1: PR Approved Date | W1: Onsite Lead Code Review | X1: Code Review Comments, if any | Y1: Client Code Review | Z1: Approved Date | AA1: Code Review Comments, if any2 | AB1: Internal PO -POV Comments | AC1: Client PO -POV Comments | AD1: Comments | AE1: Does this story meet expectations?
A2: 1 | B2: FOH | C2: 45954 | D2: 45967 | E2: 4.25 - Sprint 3 | F2: Alpha | G2: 49541 | H2: MFOH[WAVE] - Student Debt by district/site chart (FOH dashboard) | I2: Story Completed | J2: 8 | K2: 6.25 | L2: 25 | M2: 45954 | N2: 45964 | O2: Alpha | P2: Arvinth | Q2: None | R2: Arvinth | S2: None | T2: 45459 | U2: 45965 | V2: 45965 | W2: Subha | X2: Update comment | Y2: Steve | Z2: 45965 | AA2: None | AB2: None | AC2: NA | AE2: Meets Expectation
A3: 2 | B3: FOH | C3: 45954 | D3: 45967 | E3: 4.25 - Sprint 3 | F3: Arvinth | G3: 50084 | H3: MFOH - Modify the Logout POS User Search screen to honor the central time zone setting (DBS) | I3: Story Completed | J3: 2 | K3: 1.5 | L3: 6 | M3: 45957 | N3: 45958 | O3: Arvinth | P3: Ashwin | Q3: None | R3: Alpha | S3: None | T3: 45369 | U3: 45959 | V3: 45959 | W3: Subha | X3: None | Y3: Steve | Z3: 45959 | AA3: None | AB3: None | AC3: NA | AE3: Meets Expectation
A4: 3 | B4: FOH | C4: 45954 | D4: 45967 | E4: 4.25 - Sprint 3 | F4: Subhasri | G4: 50111 | H4: Mosaic FOH - New Jersey Master Eligibility List Report Modifications | I4: Story Completed | J4: 8 | K4: 5 | L4: 20 | M4: 45954 | N4: 45959 | O4: Subhasri | P4: Arvinth | Q4: None | R4: Arvinth | S4: None | T4: 45442 | U4: 45964 | V4: 45964 | W4: NA | X4: None | Y4: Steve | Z4: 45964 | AA4: None | AB4: None | AC4: None | AE4: Meets Expectation
A5: 4 | B5: =Dashboard!$J$1 -> FOH | C5: 45954 | D5: 45967 | E5: 4.25 - Sprint 3 | F5: Ashwin | G5: 46270 | H5: Mosaic - POS (Web) (Fresno) - Add a tool tip to Categorical Eligibility Extension Maintenance | I5: Story Completed | J5: 2 | K5: 1.1 | L5: 4.25 | M5: 45957 | N5: 45958 | O5: Ashwin | P5: Arvinth | Q5: None | R5: Arvinth | S5: None | T5: 45389 | U5: 45960 | V5: 45960 | W5: Subha | X5: None | Y5: Steve | Z5: 45960 | AA5: None | AB5: None | AC5: NA | AE5: Meets Expectation
A6: 5 | B6: =Dashboard!$J$1 -> FOH | C6: 45954 | D6: 45967 | E6: 4.25 - Sprint 3 | F6: Ashwin | G6: 50183 | H6: MFOH - Add a 'Group By School' filter to Students Without an Eligibility Determination Report | I6: Story Completed | J6: 5 | K6: 4.5 | L6: 18 | M6: 45959 | N6: 45961 | O6: Ashwin | P6: Arvinth | Q6: None | R6: Arvinth | S6: None | T6: 45434 | U6: 45964 | V6: 45964 | W6: Subha | X6: None | Y6: Steve | Z6: 45964 | AA6: None | AB6: None | AC6: NA | AE6: Meets Expectation
A7: 6 | B7: FOH | C7: 45954 | D7: 45967 | E7: 4.25 - Sprint 3 | F7: Arvinth | G7: 49680 | H7: MFOH - DC Import Improvements | I7: Story Completed | J7: 5 | K7: 3.5 | L7: 14 | M7: 45958 | N7: 45960 | O7: Arvinth | P7: Ashwin | Q7: None | R7: Alpha | S7: None | T7: 45435 | U7: 45964 | V7: 45964 | W7: Subha | X7: None | Y7: Steve | Z7: 45964 | AA7: None | AB7: None | AC7: None | AE7: Meets Expectation
A8: 7 | B8: FOH | C8: 45954 | D8: 45967 | E8: 4.25 - Sprint 3 | F8: Subhasri | G8: 50546 | H8: Mosaic FOH - MSB Spending Limits - remove the Logic for the Meal Control radio | I8: Story Completed | J8: 3 | K8: 1.5 | L8: 8 | M8: 45964 | N8: 45965 | O8: Subhasri | P8: NA | Q8: NA | R8: NA | S8: NA | T8: 45485 | U8: 45965 | V8: 45965 | W8: NA | X8: NA | Y8: Steve | Z8: 45965 | AA8: None | AB8: NA | AC8: NA | AE8: Meets Expectation
A9: 8 | B9: FOH | C9: 45954 | D9: 45967 | E9: 4.25 - Sprint 3 Stretch | F9: Atchaiah | G9: 50551 | H9: MFOH [BAU] - Automation (46018) | I9: Story Completed | J9: 1 | K9: 1 | L9: 4 | M9: 45954 | N9: 45957 | O9: NA | P9: NA | Q9: NA | R9: NA | S9: NA | T9: 45322 | U9: 45957 | V9: 45957 | W9: NA | X9: NA | Y9: Steve | Z9: 45957 | AA9: None | AB9: NA | AC9: NA
A10: 9 | B10: FOH | C10: 45954 | D10: 45967 | E10: 4.25 - Sprint 3 Stretch | F10: Atchaiah | G10: 50552 | H10: MFOH [BAU] - Automation (48706) | I10: Story Completed | J10: 2 | K10: 2 | M10: 45958 | N10: 45960 | O10: NA | P10: NA | Q10: NA | R10: NA | S10: NA | T10: 45394 | U10: 45960 | V10: 45960 | W10: NA | X10: NA | Y10: Steve | Z10: 45960 | AA10: None | AB10: NA | AC10: NA
A11: 10 | B11: FOH | C11: 45954 | D11: 45967 | E11: 4.25 - Sprint 3 Stretch | F11: Atchaiah | G11: 50654 | H11: MFOH [BAU] - Automation (48917) | I11: Story Completed | J11: 1 | K11: 1 | L11: 4 | M11: 45960 | N11: 45961 | O11: NA | P11: NA | Q11: NA | R11: NA | S11: NA | T11: 45431 | U11: 45964 | V11: 45964 | W11: NA | X11: NA | Y11: Steve | Z11: 45964 | AA11: None | AB11: NA | AC11: NA
A12: 11 | B12: FOH | C12: 45954 | D12: 45967 | E12: 4.25 - Sprint 3 Stretch | F12: Atchaiah | G12: 50669 | H12: MFOH [BAU] - Automation (49969) | I12: Story Completed | J12: 1 | K12: 1 | L12: 4 | M12: 45964 | N12: 45965 | O12: NA | P12: NA | Q12: NA | R12: NA | S12: NA | T12: 45477 | U12: 45965 | V12: 45965 | W12: NA | X12: NA | Y12: Steve | Z12: 45965 | AA12: None | AB12: NA | AC12: NA
A13: 12 | B13: FOH | C13: 45954 | D13: 45967 | E13: 4.25 - Sprint 3 Stretch | F13: Atchaiah | G13: 50685 | H13: MFOH [BAU] - Automation (50100) | I13: Story Being Developed | J13: 2 | K13: 1 | L13: 4
A14: 13 | B14: FOH | C14: 45954 | D14: 45967 | E14: 4.25 - Sprint 3 Stretch | F14: Arvinth | G14: 26249 | H14: Student history - CSV format broken | I14: Story Ready For Testing | J14: 2 | K14: 1 | L14: 4 | M14: 45966 | N14: 45966 | O14: Arvinth | P14: Ashwin | Q14: None | R14: Ashwin | S14: None | T14: 45533 | U14: 45967 | V14: 45967 | W14: Subha | X14: None | Y14: Steve | Z14: 45967 | AA14: None | AB14: NA | AC14: NA | AE14: Meets Expectation
A15: 14 | B15: FOH | C15: 45954 | D15: 45967 | E15: 4.25 - Sprint 3 Stretch | F15: Arvinth | G15: 26202 | H15: MFOH - MEC - Kaleida UI Issues | I15: Story Being Developed | J15: 2 | K15: 1 | L15: 4 | M15: 45967
A16: 15 | B16: FOH | C16: 45954 | D16: 45967 | E16: 4.25 - Sprint 3 Stretch | F16: Alpha | G16: 26260 | H16: MFOH - Student Export - Add Export Fields and Quick Add - Not Applying Header Name | I16: Story Being Developed | J16: 2 | K16: 1.25 | L16: 5 | M16: 45966 | N16: 45967 | O16: Alpha
A17: 16 | B17: FOH | C17: 45954 | D17: 45967 | E17: 4.25 - Sprint 3 Stretch | F17: Subhasri | G17: 50149 | H17: MFOH - MSA Client (Communication) | I17: Story Being Developed | J17: 8 | K17: 2 | L17: 8 | M17: 45961

Sheet 4.25 - Sprint 4-Defect
A1: S.No | B1: Sprint # | C1: Story/Defect ID | D1: Parent Story | E1: Developer | F1: Issue Type | G1: Issue Description | H1: Priority | I1: Defect Source | J1: Type | K1: Status | L1: Root Cause Category | M1: Comments

Sheet 4.25 - Sprint 3-Defect
A1: S.No | B1: Sprint # | C1: Story/Defect ID | D1: Parent Story | E1: Developer | F1: Issue Type | G1: Issue Description | H1: Priority | I1: Defect Source | J1: Type | K1: Status | L1: Root Cause Category | M1: Comments
B2: 4.25 - Sprint 3 | C2: 49541 | D2: 49541 | E2: Alpha | F2: Bounceback/Sub-Defect | G2: UI and cosmetics issues | H2: Minor | I2: Manual | J2: Internal | K2: Defect Fixed | L2: Enhancements

Sheet 4.25 - Sprint 2-Status
A1: S.No | B1: Application Name | C1: Sprint Start Date | D1: Sprint End Date | E1: Sprint | F1: Developer | G1: Story ID/Defect ID | H1: Description | I1: Status | J1: Estimated(hrs/sp) | K1: Actual(hrs/sp) | L1: Actual Worklog (Hours) | M1: Dev Start Date | N1: Dev End Date | O1: Unit testing | P1: Peer Tested By | Q1: Peer Tested Comments, if any | R1: Peer Reviewed By | S1: Peer Code Review Comments, if any | T1: PR Number/Link | U1: PR Created Date | V1: PR Approved Date | W1: Onsite Lead Code Review | X1: Code Review Comments, if any | Y1: Client Code Review | Z1: Approved Date | AA1: Code Review Comments, if any2 | AB1: Internal PO -POV Comments | AC1: Client PO -POV Comments | AD1: Comments | AE1: Does this story meet expectations?
A2: 1 | B2: FOH | C2: 45940 | D2: 45953 | E2: 4.25 - Sprint 2 | F2: Alpha | G2: 50405 | H2: MFOH - Add 'Student Attendance Import' to the Scheduler Task | I2: Story Completed | J2: 3 | K2: =Table245689102121314111518192021221723242526[[#This Row],[Actual Worklog (Hours)]] / 4 -> 2.5 | L2: 10 | M2: 45940 | N2: 45944 | O2: Alpha | P2: Ashwin | Q2: None | R2: Arvinth | S2: Specify the column names on INSERT query, Change switch case to if condition, Security page name change is needed. | T2: 45137 | U2: 45945 | V2: 45945 | W2: Subha | X2: Correct the Security page update script, Consider the invalid Path/File scenario, Apply ApplicationRole change based on the Security page name change. | Y2: Steve | Z2: 45945 | AA2: None | AB2: None | AC2: NA | AE2: Meets Expectation
A3: 2 | B3: FOH | C3: 45940 | D3: 45953 | E3: 4.25 - Sprint 2 | F3: Subhasri | G3: 50224 | H3: MFOH - Move the Stats menu from the Top Navigation Menu to System Utilities (4.25) | I3: Story Completed | J3: 3 | K3: 1 | L3: 6 | M3: 45940 | N3: 45940 | O3: Subhasri | P3: Ashwin | Q3: None | R3: None | S3: None | T3: 45126 | U3: 45944 | V3: 45944 | W3: NA | X3: NA | Y3: Steve | Z3: 45944 | AA3: None | AB3: None | AC3: None | AE3: Meets Expectation
A4: 3 | B4: FOH | C4: 45940 | D4: 45953 | E4: 4.25 - Sprint 2 | F4: Ashwin | G4: 49233 | H4: MFOH - Improvements to Student Balance Import Results Report (DBS) | I4: Story Completed | J4: 3 | K4: 2.3 | L4: 9.25 | M4: 45940 | N4: 45944 | O4: Ashwin | P4: Subha | Q4: None | R4: Subha | S4: None | T4: 45197 | U4: 45947 | V4: 45947 | W4: Subha | X4: None | Y4: Steve | Z4: 45947 | AA4: None | AB4: None | AC4: NA | AE4: Meets Expectation
A5: 4 | B5: FOH | C5: 45940 | D5: 45953 | E5: 4.25 - Sprint 2 | F5: Arvinth | G5: 49781 | H5: MFOH [WAVE] - Add a new widget 'ADP%' to the Dashboard | I5: Story Completed | J5: 8 | K5: =Table245689102121314111518192021221723242526[[#This Row],[Actual Worklog (Hours)]] / 4 -> 12.5 | L5: 50 | M5: 45940 | N5: 45952 | O5: Arvinth | P5: Alpha | Q5: None | R5: Alpha | S5: None | T5: 45244 | U5: 45952 | V5: 45952 | W5: Subha | X5: None | Y5: Steve | Z5: 45952 | AA5: None | AB5: None | AC5: NA | AD5: Due to technical complexity work logs exceeds the actual SP | AE5: Meets Expectation
A6: 5 | B6: =Dashboard!$J$1 -> FOH | C6: 45940 | D6: 45953 | E6: 4.25 - Sprint 2 | F6: Subhasri | G6: 50301 | H6: Mosaic FOH - Add an Active flag to Student Export Setup | I6: Story Completed | J6: 5 | K6: 3 | L6: 12 | M6: 45946 | N6: 45950 | O6: Subhasri | P6: NA | Q6: NA | R6: NA | S6: None | T6: 45243 | U6: 45952 | V6: 45952 | X6: NA | Y6: Steve | Z6: 45952 | AA6: None | AB6: None | AC6: NA | AE6: Meets Expectation
A7: 6 | B7: =Dashboard!$J$1 -> FOH | C7: 45940 | D7: 45953 | E7: 4.25 - Sprint 2 | F7: Subhasri | G7: 50108 | H7: Mosaic FOH - Tyler-MUNIS Financial Export Modifications | I7: Story Completed | J7: 2 | K7: 1 | L7: 4 | M7: 45944 | N7: 45945 | O7: Subhasri | P7: Ashwin | Q7: None | R7: None | S7: None | T7: 45173 | U7: 45946 | V7: 45946 | W7: NA | X7: NA | Y7: Steve | Z7: 45946 | AA7: None | AB7: None | AC7: NA | AE7: Meets Expectation
A8: 7 | B8: =Dashboard!$J$1 -> FOH | C8: 45940 | D8: 45953 | E8: 4.25 - Sprint 2 | F8: Subhasri | G8: 49968 | H8: MFOH - Modify VA SNP-12 Report to show only actual serving days where meal count > 0 (DBS | I8: Story Completed | J8: 2 | K8: 1 | L8: 5 | M8: 45943 | N8: 45944 | O8: Subhasri | P8: Ashwin | Q8: None | R8: None | S8: None | T8: 45162 | U8: 45946 | V8: 45946 | W8: NA | X8: NA | Y8: Steve | Z8: 45946 | AA8: None | AB8: None | AC8: NA | AE8: Meets Expectation
A9: 8 | B9: FOH | C9: 45940 | D9: 45953 | E9: 4.25 - Sprint 2 Stretch | F9: Alpha | G9: 49541 | H9: MFOH[WAVE] - Student Debt by district/site chart (FOH dashboard) | I9: Story Being Developed | J9: 13 | K9: =Table245689102121314111518192021221723242526[[#This Row],[Actual Worklog (Hours)]] / 4 -> 7.5 | L9: 30
A10: 9 | B10: FOH | C10: 45940 | D10: 45953 | E10: 4.25 - Sprint 2 Stretch | F10: Atchaiah | G10: 50310 | H10: MFOH [BAU] - Automation (49419) | I10: Story Completed | J10: 1 | K10: =Table245689102121314111518192021221723242526[[#This Row],[Actual Worklog (Hours)]] / 4 -> 1 | L10: 4 | M10: 45940 | N10: 45943 | O10: NA | P10: NA | Q10: NA | R10: NA | S10: NA | T10: 45107 | U10: 45944 | V10: 45944 | W10: NA | X10: NA | Y10: Steve | Z10: 45944 | AA10: None | AB10: NA | AC10: NA | AE10: Meets Expectation
A11: 10 | B11: FOH | C11: 45940 | D11: 45953 | E11: 4.25 - Sprint 2 Stretch | F11: Atchaiah | G11: 50312 | H11: MFOH [BAU] - Automation (49835) | I11: Story Completed | J11: 2 | K11: 2 | L11: 8 | M11: 45944 | N11: 45947 | O11: NA | P11: NA | Q11: NA | R11: NA | S11: NA | T11: 45191 | U11: 45947 | V11: 45947 | W11: NA | X11: NA | Y11: Steve | Z11: 45947 | AA11: None | AB11: NA | AC11: NA
A12: 11 | B12: FOH | C12: 45940 | D12: 45953 | E12: 4.25 - Sprint 2 Stretch | F12: Atchaiah | G12: 50306 | H12: MFOH [BAU] - Automation (49335) | I12: Story Completed | J12: 2 | K12: 2 | L12: 8 | M12: 45951 | N12: 45952 | O12: NA | P12: NA | Q12: NA | R12: NA | S12: NA | T12: 45261 | U12: 45953 | V12: 45953 | W12: NA | X12: NA | Y12: Steve | Z12: 45953 | AA12: None | AB12: NA | AC12: NA

Sheet 4.25 - Sprint 2-Defect
A1: S.No | B1: Sprint # | C1: Story/Defect ID | D1: Parent Story | E1: Developer | F1: Issue Type | G1: Issue Description | H1: Priority | I1: Defect Source | J1: Type | K1: Status | L1: Root Cause Category | M1: Comments

Sheet 4.25 - Sprint 1-Status
A1: S.No | B1: Application Name | C1: Sprint Start Date | D1: Sprint End Date | E1: Sprint | F1: Developer | G1: Story ID/Defect ID | H1: Description | I1: Status | J1: Estimated(hrs/sp) | K1: Actual(hrs/sp) | L1: Actual Worklog (Hours) | M1: Dev Start Date | N1: Dev End Date | O1: Unit testing | P1: Peer Tested By | Q1: Peer Tested Comments, if any | R1: Peer Reviewed By | S1: Peer Code Review Comments, if any | T1: PR Number/Link | U1: PR Created Date | V1: PR Approved Date | W1: Onsite Lead Code Review | X1: Code Review Comments, if any | Y1: Client Code Review | Z1: Approved Date | AA1: Code Review Comments, if any2 | AB1: Internal PO -POV Comments | AC1: Client PO -POV Comments | AD1: Comments | AE1: Does this story meet expectations?
A2: 1 | B2: FOH | C2: 45926 | D2: 45939 | E2: 4.25 - Sprint 1 | F2: Arvinth | G2: 49969 | H2: MFOH - Add new fields to Students > Custom Report | I2: Story Completed | J2: 2 | K2: 1.15 | L2: 4.5 | M2: 45926 | N2: 45929 | O2: Arvinth | P2: Ashwin | Q2: None | R2: Alpha | S2: None | T2: 44867 | U2: 45929 | V2: 45929 | W2: Subha | X2: None | Y2: Steve | Z2: 45929 | AA2: None | AB2: None | AC2: NA | AE2: Meets Expectation
A3: 2 | B3: FOH | C3: 45926 | D3: 45939 | E3: 4.25 - Sprint 1 | F3: Ashwin | G3: 50211 | H3: MFOH - Modifications to CA CNIPS Export (Operating Days) | I3: Story Completed | J3: 2 | K3: 0.8 | L3: 3.25 | M3: 45926 | N3: 45926 | O3: Ashwin | P3: Arvinth | Q3: None | R3: Arvinth | S3: None | T3: 44913 | U3: 45930 | V3: 45930 | W3: Subha | X3: None | Y3: Steve | Z3: 45930 | AA3: None | AB3: None | AC3: None | AE3: Meets Expectation
A4: 3 | B4: FOH | C4: 45926 | D4: 45939 | E4: 4.25 - Sprint 1 | F4: Subhasri | G4: 48917 | H4: MFOH - Add an 'Age' filter to Elig. Record Student Listing Report | I4: Story Completed | J4: 3 | K4: 2 | L4: 12 | M4: 45926 | N4: 45930 | O4: Subhasri | P4: Ashwin | Q4: None | R4: Ashwin | S4: None | T4: 44912 | U4: 45930 | V4: 45930 | W4: NA | X4: NA | Y4: Steve | Z4: 45930 | AA4: None | AB4: None | AC4: None | AE4: Meets Expectation
A5: 4 | B5: FOH | C5: 45926 | D5: 45939 | E5: 4.25 - Sprint 1 | F5: Subhasri | G5: 48706 | H5: Mosaic FOH - Need an attendance import to modify the attendance maintenance | I5: Story Completed | J5: 3 | K5: 2 | L5: 7 | M5: 45929 | N5: 45930 | O5: Subhasri | P5: Arvinth | Q5: None | R5: Arvinth | S5: None | T5: 44928 | U5: 45931 | V5: 45931 | W5: NA | X5: NA | Y5: Steve | Z5: 45931 | AA5: None | AB5: None | AC5: None | AE5: Meets Expectation
A6: 5 | B6: FOH | C6: 45926 | D6: 45939 | E6: 4.25 - Sprint 1 | F6: Ashwin | G6: 25876 | H6: MFOH - When running the Student Balance Import Results Report, the Errors only filter is showing the no errors as well | I6: Story Completed | J6: 1 | K6: 0.35 | L6: 1.5 | M6: 45926 | N6: 45929 | O6: Ashwin | P6: Arvinth | Q6: None | R6: Arvinth | S6: None | T6: 44868 | U6: 45929 | V6: 45929 | W6: Subha | X6: None | Y6: Steve | Z6: 45929 | AA6: None | AB6: None | AC6: NA | AE6: Meets Expectation
A7: 6 | B7: =Dashboard!$J$1 -> FOH | C7: 45926 | D7: 45939 | E7: 4.25 - Sprint 1 | F7: Alpha | G7: 49762 | H7: MFOH [WAVE] - Add 'Participation By' filter to the Standard Claim Report | I7: Story Completed | J7: 2 | K7: =Table2456891021213141115181920212217232425[[#This Row],[Actual Worklog (Hours)]] / 4 -> 1.5 | L7: 6 | M7: 45926 | N7: 45926 | O7: Alpha | P7: NA | Q7: NA | R7: NA | S7: NA | T7: 44885 | U7: 45930 | V7: 45930 | W7: Subha | X7: None | Y7: Steve | Z7: 45930 | AA7: None | AB7: None | AC7: None | AE7: Meets Expectation
A8: 7 | B8: FOH | C8: 45926 | D8: 45939 | E8: 4.25 - Sprint 1 | F8: Arvinth | G8: 50083 | H8: MFOH - Modifications to NC Claim Export (Operating Days) | I8: Story Completed | J8: 2 | K8: 1.25 | L8: 5 | M8: 45929 | N8: 45930 | O8: Arvinth | P8: Ashwin | Q8: None | R8: Ashwin | S8: None | T8: 44908 | U8: 45930 | V8: 45930 | W8: Subha | X8: None | Y8: Steve | Z8: 45930 | AA8: None | AB8: None | AC8: None | AE8: Meets Expectation
A9: 8 | B9: FOH | C9: 45926 | D9: 45939 | E9: 4.25 - Sprint 1 | F9: Arvinth | G9: 50213 | H9: MFOH - Modifications to KY CNIPS Export (Operating Days) | I9: Story Completed | J9: 2 | K9: 1 | L9: 4 | M9: 45930 | N9: 45930 | O9: Arvinth | P9: Ashwin | Q9: None | R9: Ashwin | S9: None | T9: 44909 | U9: 45930 | V9: 45930 | W9: Subha | X9: None | Y9: Steve | Z9: 45930 | AA9: None | AB9: None | AC9: NA | AE9: Meets Expectation
A10: 9 | B10: FOH | C10: 45926 | D10: 45939 | E10: 4.25 - Sprint 1 | F10: Subhasri | G10: 49513 | H10: MFOH [WAVE]- Add a new widget 'MPLH' to the Dashboard | I10: Story Completed | J10: 5 | K10: 4 | L10: 20 | M10: 45930 | N10: 45938 | O10: Subhasri | P10: Alpha | Q10: None | R10: Alpha | S10: None | T10: 45035 | U10: 45938 | V10: 45938 | W10: NA | X10: NA | Y10: Steve | Z10: 45938 | AA10: None | AB10: None | AC10: None
A11: 10 | B11: FOH | C11: 45926 | D11: 45939 | E11: 4.25 - Sprint 1 Stretch | F11: Atchaiah | G11: 50060 | H11: MFOH [BAU] - Automation (49305) | I11: Story Completed | J11: 1 | K11: 1 | L11: 4 | M11: 45911 | N11: 45926 | O11: NA | P11: NA | Q11: NA | R11: NA | S11: NA | T11: 44817 | U11: 45926 | V11: 45926 | W11: NA | X11: NA | Y11: Ying | Z11: 45926 | AA11: None | AB11: NA | AC11: NA
A12: 11 | B12: FOH | C12: 45926 | D12: 45939 | E12: 4.25 - Sprint 1 Stretch | F12: Atchaiah | G12: 50308 | H12: MFOH [BAU] - Automation (48822) | I12: Story Completed | J12: 1 | K12: 1 | L12: 4 | M12: 45936 | N12: 45936 | O12: NA | P12: NA | Q12: NA | R12: NA | S12: NA | T12: 44971 | U12: 45936 | V12: 45936 | W12: NA | X12: NA | Y12: Steve | Z12: 45936 | AA12: None | AB12: NA | AC12: NA
A13: 12 | B13: FOH | C13: 45926 | D13: 45939 | E13: 4.25 - Sprint 1 Stretch | F13: Alpha | G13: 50100 | H13: MFOH - Improvements to the POS Roster Reports | I13: Story Completed | J13: 5 | K13: 4 | L13: 16 | M13: 45936 | N13: 45938 | O13: Alpha | P13: Ashwin | Q13: None | R13: Arvinth | S13: None | T13: 45029 | U13: 45938 | V13: 45938 | W13: Subha | X13: None | Y13: Steve | Z13: 45938 | AA13: None | AB13: None | AC13: NA | AE13: Meets Expectation
A14: 13 | B14: FOH | C14: 45926 | D14: 45939 | E14: 4.25 - Sprint 1 Stretch | F14: Atchaiah | G14: 50309 | H14: MFOH [BAU] - Automation (49242) | I14: Story Completed | J14: 1 | K14: 1 | L14: 4 | M14: 45937 | N14: 45938 | O14: NA | P14: NA | Q14: NA | R14: NA | S14: NA | T14: 45041 | U14: 45939 | V14: 45939 | W14: NA | X14: NA | Y14: Steve | Z14: 45939 | AA14: None | AB14: NA | AC14: NA
A15: 14 | B15: FOH | C15: 45926 | D15: 45939 | E15: 4.25 - Sprint 1 Stretch | F15: Atchaiah | G15: 50311 | H15: MFOH [BAU] - Automation (49814) | I15: Story Completed | J15: 1 | K15: 1 | L15: 4 | M15: 45939 | N15: 45939 | O15: NA | P15: NA | Q15: NA | R15: NA | S15: NA | T15: 45048 | U15: 45939 | V15: 45939 | W15: NA | X15: NA | Y15: Steve | Z15: 45939 | AA15: None | AB15: NA | AC15: NA
A16: 15 | B16: FOH | C16: 45926 | D16: 45939 | E16: 4.25 - Sprint 1 Stretch | F16: Atchaiah | G16: 50307 | H16: MFOH [BAU] - Automation (49503) | I16: Story Peer Review | J16: 1 | K16: 1 | L16: 4 | M16: 45937 | N16: 45937 | O16: NA | P16: NA | Q16: NA | R16: NA | S16: NA | T16: 45016 | U16: 45938 | W16: NA | X16: NA | Y16: Steve
A17: 16 | B17: FOH | C17: 45926 | D17: 45939 | E17: 4.25 - Sprint 1 Stretch | F17: Arvinth | G17: 49781 | H17: MFOH [WAVE] - Add a new widget 'ADP%' to the Dashboard | I17: Story Being Developed | J17: 13 | K17: 5.75 | L17: 23 | M17: 45933

Sheet 4.25 - Sprint 1-Defect
A1: S.No | B1: Sprint # | C1: Story/Defect ID | D1: Parent Story | E1: Developer | F1: Issue Type | G1: Issue Description | H1: Priority | I1: Defect Source | J1: Type | K1: Status | L1: Root Cause Category | M1: Comments
B2: 4.25 - Sprint 1 | C2: 49513 | D2: 49513 | E2: Subhasri | F2: Bounceback/Sub-Defect | G2: Issues in Copy and Export in MPLH Widget | H2: Minor | I2: Manual | J2: Internal | K2: Defect Fixed | L2: Existing_Issues | M2: The issue existing in the other widgets as well for the specific scenario.

Sheet 4.24 - Sprint 4-Status
A1: S.No | B1: Application Name | C1: Sprint Start Date | D1: Sprint End Date | E1: Sprint | F1: Developer | G1: Story ID/Defect ID | H1: Description | I1: Status | J1: Estimated(hrs/sp) | K1: Actual(hrs/sp) | L1: Actual Worklog (Hours) | M1: Dev Start Date | N1: Dev End Date | O1: Unit testing | P1: Peer Tested By | Q1: Peer Tested Comments, if any | R1: Peer Reviewed By | S1: Peer Code Review Comments, if any | T1: PR Number/Link | U1: PR Created Date | V1: PR Approved Date | W1: Onsite Lead Code Review | X1: Code Review Comments, if any | Y1: Client Code Review | Z1: Approved Date | AA1: Code Review Comments, if any2 | AB1: Internal PO -POV Comments | AC1: Client PO -POV Comments | AD1: Comments | AE1: Does this story meet expectations?
A2: 1 | B2: FOH | C2: 45912 | D2: 45925 | E2: 4.24 - Sprint 4 | F2: Alpha/Atchaiah | G2: 50026 | H2: Mosaic - FOH 4.24(Regression) - End of Day | I2: Story Completed | J2: 5 | K2: 6.25 | L2: 25 | M2: 45914 | N2: 45925 | O2: NA | P2: NA | Q2: NA | R2: NA | S2: NA | T2: NA | U2: NA | V2: NA | W2: NA | X2: NA | Y2: NA | Z2: NA | AA2: NA | AB2: NA | AC2: NA | AD2: Regression Testing, SP exceeded as we have more number of regression defects in this sprint
A3: 2 | B3: FOH | C3: 45912 | D3: 45925 | E3: 4.24 - Sprint 4 | F3: Atchaiah/Ashwin | G3: 50025 | H3: Mosaic - FOH 4.24(Regression) - Students | I3: Story Completed | J3: 5 | K3: 6 | L3: 24 | M3: 45914 | N3: 45925 | O3: NA | P3: NA | Q3: NA | R3: NA | S3: NA | T3: NA | U3: NA | V3: NA | W3: NA | X3: NA | Y3: NA | Z3: NA | AA3: NA | AB3: NA | AC3: NA | AD3: Regression Testing, SP exceeded as we have more number of regression defects in this sprint
A4: 3 | B4: FOH | C4: 45912 | D4: 45925 | E4: 4.24 - Sprint 4 | F4: Subhasri/Atchaiah | G4: 50036 | H4: Mosaic - FOH 4.24(Regression) - Setup | I4: Story Completed | J4: 5 | K4: 6.5 | L4: 26 | M4: 45914 | N4: 45925 | O4: NA | P4: NA | Q4: NA | R4: NA | S4: NA | T4: NA | U4: NA | V4: NA | W4: NA | X4: NA | Y4: NA | Z4: NA | AA4: NA | AB4: NA | AC4: NA | AD4: Regression Testing, SP exceeded as we have more number of regression defects in this sprint
A5: 4 | B5: =Dashboard!$J$1 -> FOH | C5: =Dashboard!$F$1 -> 46136 | D5: =Dashboard!#REF! -> #REF! | E5: 4.24 - Sprint 4 | F5: Ashwin/Atchaiah | G5: 50031 | H5: Mosaic - FOH 4.24 (Regression) - POS(Menu Option) | I5: Story Completed | J5: 2 | K5: 3.5 | L5: 14 | M5: 45914 | N5: 45925 | O5: NA | P5: NA | Q5: NA | R5: NA | S5: NA | T5: NA | U5: NA | V5: NA | W5: NA | X5: NA | Y5: NA | Z5: NA | AA5: NA | AB5: NA | AC5: NA | AD5: Regression Testing, SP exceeded as we have more number of regression defects in this sprint
A6: 5 | B6: FOH | C6: 45912 | D6: 45925 | E6: 4.24 - Sprint 4 | F6: Arvinth/Atchaiah | G6: 50035 | H6: Mosaic - FOH 4.24(Regression) - Utilities | I6: Story Completed | J6: 5 | K6: 6 | L6: 24 | M6: 45914 | N6: 45925 | O6: NA | P6: NA | Q6: NA | R6: NA | S6: NA | T6: NA | U6: NA | V6: NA | W6: NA | X6: NA | Y6: NA | Z6: NA | AA6: NA | AB6: NA | AC6: NA | AD6: Regression Testing, SP exceeded as we have more number of regression defects in this sprint
A7: 6 | B7: FOH | C7: 45912 | D7: 45925 | E7: 4.24 - Sprint 4 | F7: Arvinth/Atchaiah/Alpha | G7: 50029 | H7: Mosaic - FOH 4.24 (Regression) - Eligibility (F&R) | I7: Story Completed | J7: 5 | K7: 6.75 | L7: 27 | M7: 45914 | N7: 45925 | O7: NA | P7: NA | Q7: NA | R7: NA | S7: NA | T7: NA | U7: NA | V7: NA | W7: NA | X7: NA | Y7: NA | Z7: NA | AA7: NA | AB7: NA | AC7: NA | AD7: Regression Testing, SP exceeded as we have more number of regression defects in this sprint
A8: 7 | B8: FOH | C8: 45912 | D8: 45925 | E8: 4.24 - Sprint 4 | F8: Subhasri/Atchaiah/Alpha | G8: 50028 | H8: Mosaic - FOH 4.24 (Regression) - Reports - Eligibility (F&R) | I8: Story Completed | J8: 3 | K8: 4 | L8: 16 | M8: 45914 | N8: 45925 | O8: NA | P8: NA | Q8: NA | R8: NA | S8: NA | T8: NA | U8: NA | V8: NA | W8: NA | X8: NA | Y8: NA | Z8: NA | AA8: NA | AB8: NA | AC8: NA | AD8: Regression Testing, SP exceeded as we have more number of regression defects in this sprint
A9: 8 | B9: FOH | C9: 45912 | D9: 45925 | E9: 4.24 - Sprint 4 | F9: Subhasri | G9: 26007 | H9: MFOH (4.24 Regression) - Console error on Reconcile day page load | I9: Story Completed | J9: 0 | K9: 0 | L9: 0 | M9: 45924 | N9: 45925 | O9: NA | P9: NA | Q9: NA | R9: NA | S9: NA | T9: 44753 | U9: 45924 | V9: 45924 | W9: NA | X9: NA | Y9: Ying | Z9: 45924 | AA9: None | AB9: NA | AC9: NA | AD9: Regression defect
A10: 9 | B10: FOH | C10: 45912 | D10: 45925 | E10: 4.24 - Sprint 4 | F10: Subhasri | G10: 26008 | H10: MFOH (4.24 Regression) - Scrolling in application import setting copy popup | I10: Story Completed | J10: 0 | K10: 0 | L10: 0 | M10: 45924 | N10: 45925 | O10: NA | P10: NA | Q10: NA | R10: NA | S10: NA | T10: 44752 | U10: 45924 | V10: 45924 | W10: NA | X10: NA | Y10: Ying | Z10: 45924 | AA10: None | AB10: NA | AC10: NA | AD10: Regression defect
A11: 10 | B11: FOH | C11: 45912 | D11: 45925 | E11: 4.24 - Sprint 4 | F11: Ashwin | G11: 26009 | H11: MFOH (4.24 Regression) - UI Issue in the student Grade Range screen - Pop up scroll is displayed and button are hidden | I11: Story Completed | J11: 0 | K11: 0 | L11: 0 | M11: 45924 | N11: 45924 | O11: Ashwin | P11: Arvinth | Q11: None | R11: Arvinth | S11: None | T11: 44748 | U11: 45924 | V11: 45924 | W11: NA | X11: NA | Y11: Ying | Z11: 45924 | AA11: None | AB11: None | AC11: NA | AD11: Regression defect
A12: 11 | B12: FOH | C12: 45912 | D12: 45925 | E12: 4.24 - Sprint 4 | F12: Alpha | G12: 26013 | H12: MFOH (4.24 Regression) - Semi-colon symbol is showing in multiple screens | I12: Story Completed | J12: 0 | K12: 0 | L12: 0 | M12: 45922 | N12: 45922 | O12: Alpha | P12: NA | Q12: None | R12: Arvinth | S12: None | T12: 44754 | U12: 45924 | V12: 45924 | W12: NA | X12: NA | Y12: Ying | Z12: 45924 | AA12: None | AB12: NA | AC12: NA | AD12: Regression defect
A13: 12 | B13: FOH | C13: 45912 | D13: 45925 | E13: 4.24 - Sprint 4 | F13: Ashwin | G13: 26014 | H13: MFOH (4.24 Regression) - Issues found in Chartwells Export Setup | I13: Story Completed | J13: 0 | K13: 0 | L13: 0 | M13: 45919 | N13: 45919 | O13: Ashwin | P13: Arvinth | Q13: Fix not working for different scenarios | R13: Arvinth | S13: None | T13: 44746 | U13: 45924 | V13: 45924 | W13: NA | X13: NA | Y13: Ying | Z13: 45924 | AA13: None | AB13: None | AC13: NA | AD13: Regression defect
A14: 13 | B14: FOH | C14: 45912 | D14: 45925 | E14: 4.24 - Sprint 4 | F14: Alpha | G14: 26015 | H14: MFOH (4.24 Regression) - Console error while running the populate eligibility daily count table tool | I14: Story Completed | J14: 0 | K14: 0 | L14: 0 | M14: 45924 | N14: 45924 | O14: Alpha | P14: Subha | Q14: None | R14: Arvinth | S14: None | T14: 44757 | U14: 45924 | V14: 45924 | W14: NA | X14: NA | Y14: Ying | Z14: 45924 | AA14: None | AB14: NA | AC14: NA | AD14: Regression defect
A15: 14 | B15: FOH | C15: 45912 | D15: 45925 | E15: 4.24 - Sprint 4 | F15: Arvinth | G15: 26016 | H15: MFOH (4.24 Regression) - In Categorical Eligibility Extension clicking on checkbox and click extended doesn't add + icon | I15: Story Completed | J15: 0 | K15: 0 | L15: 0 | M15: 45924 | N15: 45925 | O15: Arvinth | P15: NA | Q15: NA | R15: NA | S15: NA | T15: 44747 | U15: 45924 | V15: 45924 | W15: NA | X15: NA | Y15: Ying | Z15: 45924 | AA15: None | AB15: NA | AC15: NA | AD15: Regression defect
A16: 15 | B16: FOH | C16: 45912 | D16: 45925 | E16: 4.24 - Sprint 4 Stretch | F16: Arvinth | G16: 49969 | H16: MFOH - Add new fields to Students > Custom Report | I16: Story Being Developed | J16: 3 | K16: 1.5 | L16: 6 | M16: 45912 | AD16: Kept on hold due to regression
A17: 16 | B17: FOH | C17: 45912 | D17: 45925 | E17: 4.24 - Sprint 4 Stretch | F17: Atchaiah | G17: 50060 | H17: MFOH [BAU] - Automation (49305) | I17: Story Being Developed | J17: 2 | K17: 2 | L17: 8 | M17: 45911 | N17: 45912 | AD17: Re-started work at the end of the sprint
A18: 17 | B18: FOH | C18: 45912 | D18: 45925 | E18: 4.24 - Sprint 4 Stretch | F18: Subhasri | G18: 48706 | H18: Mosaic FOH - Need an attendance import to modify the attendance maintenance | I18: Story Being Developed | J18: 5 | K18: 1.5 | L18: 6 | M18: 45912 | AD18: Kept on hold due to regression
A19: 18 | B19: FOH | C19: 45912 | D19: 45925 | E19: 4.24 - Sprint 4 Stretch | F19: Alpha/Ashwin | G19: 25875 | H19: MFOH - Clicking "Delete Multiple Assignments" second time, the value for School Groups in the popup is not showing | I19: Story Ready For Testing | J19: 2 | K19: 1.5 | L19: 6 | M19: 45925 | N19: 45925 | O19: Alpha | P19: Alpha | Q19: None | R19: Alpha | S19: None | T19: 44783 | U19: 45925 | V19: 45925 | W19: None | X19: None | Y19: Ying | Z19: 45925 | AA19: None | AB19: None | AC19: NA
A20: 19 | B20: FOH | C20: 45912 | D20: 45925 | E20: 4.24 - Sprint 4 Stretch | F20: Alpha | G20: 49771 | H20: MFOH - Add a new label to the Sales Overview Report - PR#44784 | I20: Story Ready For Testing | J20: 1 | K20: 1 | L20: 4 | M20: 45925 | N20: 45925 | O20: Alpha | P20: Arvinth | Q20: None | R20: Arvinth | S20: None | T20: 44784 | U20: 45925 | V20: 45925 | W20: None | X20: None | Y20: Ying | Z20: 45925 | AA20: None | AB20: None | AC20: NA

Sheet 4.24 - Sprint 4-Defect
A1: S.No | B1: Sprint # | C1: Story/Defect ID | D1: Parent Story | E1: Developer | F1: Issue Type | G1: Issue Description | H1: Priority | I1: Defect Source | J1: Type | K1: Status | L1: Root Cause Category | M1: Comments

Sheet 4.24 - Sprint 3-Status
A1: S.No | B1: Application Name | C1: Sprint Start Date | D1: Sprint End Date | E1: Sprint | F1: Developer | G1: Story ID/Defect ID | H1: Description | I1: Status | J1: Estimated(hrs/sp) | K1: Actual(hrs/sp) | L1: Actual Worklog (Hours) | M1: Dev Start Date | N1: Dev End Date | O1: Unit testing | P1: Peer Tested By | Q1: Peer Tested Comments, if any | R1: Peer Reviewed By | S1: Peer Code Review Comments, if any | T1: PR Number/Link | U1: PR Created Date | V1: PR Approved Date | W1: Onsite Lead Code Review | X1: Code Review Comments, if any | Y1: Client Code Review | Z1: Approved Date | AA1: Code Review Comments, if any2 | AB1: Internal PO -POV Comments | AC1: Client PO -POV Comments | AD1: Comments | AE1: Does this story meet expectations?
A2: 1 | B2: FOH | C2: 45898 | D2: 45911 | E2: 4.24 - Sprint 3 | F2: Arvinth | G2: 49758 | H2: Mosaic FOH - Reimbursement Due Report - Display entire Reimbursement Rate | I2: Story Completed | J2: 2 | K2: =Table245689102121314111518192021221723[[#This Row],[Actual Worklog (Hours)]] / 4 -> 1.5 | L2: 6 | M2: 45898 | N2: 45898 | O2: Arvinth | P2: Ashwin | Q2: None | R2: Ashwin | S2: None | T2: 44312 | U2: 45902 | V2: 45902 | W2: Subha | X2: None | Y2: Steve | Z2: 45902 | AA2: None | AB2: None | AC2: NA | AE2: Meets Expectation
A3: 3 | B3: FOH | C3: 45898 | D3: 45911 | E3: 4.24 - Sprint 3 | F3: Subhasri | G3: 25826 | H3: Mosaic FOH - Student Letter - Cannot Email Letter | I3: Story Completed | J3: 1 | K3: =Table245689102121314111518192021221723[[#This Row],[Actual Worklog (Hours)]] / 4 -> 0.5 | L3: 2 | M3: 45897 | N3: 45897 | O3: Subhasri | P3: Ashwin | Q3: 1.setInterval method can be used on page load | R3: Arvinth | S3: None | T3: 44260 | U3: 45897 | V3: 45897 | W3: NA | X3: NA | Y3: Ying | Z3: 45897 | AA3: None | AB3: None | AC3: None | AE3: Meets Expectation
A4: 4 | B4: FOH | C4: 45898 | D4: 45911 | E4: 4.24 - Sprint 3 | F4: Subhasri | G4: 48822 | H4: MFOH - Add 'Language' filter to Eligibility Record Listing Report | I4: Story Completed | J4: 1 | K4: =Table245689102121314111518192021221723[[#This Row],[Actual Worklog (Hours)]] / 4 -> 0.75 | L4: 3 | M4: 45897 | N4: 45898 | O4: Subhasri | P4: Ashwin | Q4: None | R4: Arvinth | S4: None | T4: 44313 | U4: 45902 | V4: 45902 | W4: NA | X4: NA | Y4: Steve | Z4: 45902 | AA4: None | AB4: None | AC4: NA | AE4: Meets Expectation
A5: 5 | B5: FOH | C5: 45898 | D5: 45911 | E5: 4.24 - Sprint 3 | F5: Subhasri | G5: 49818 | H5: [WAVE]Mosaic FOH - Update Serving Period Program ID's (script) | I5: Story Completed | J5: 2 | K5: 1 | L5: 4 | M5: 45898 | N5: 45898 | O5: Subhasri | P5: Arvinth | Q5: None | R5: Arvinth | S5: None | T5: 44321 | U5: 45902 | V5: 45902 | W5: NA | X5: NA | Y5: Steve | Z5: 45902 | AA5: None | AB5: None | AC5: NA | AE5: Meets Expectation
A6: 6 | B6: FOH | C6: 45898 | D6: 45911 | E6: 4.24 - Sprint 3 | F6: Alpha | G6: 49595 | H6: MFOH - Add email address for email sent event type (Student & Notification Letter) (DBS) | I6: Story Completed | J6: 5 | K6: =Table245689102121314111518192021221723[[#This Row],[Actual Worklog (Hours)]] / 4 -> 5 | L6: 20 | M6: 45901 | N6: 45903 | O6: Alpha | P6: Ashwin | Q6: None | R6: Arvinth | S6: None | T6: 44401 | U6: 45905 | V6: 45905 | W6: Subha | X6: One of the script was missing on commit. | Y6: Steve | Z6: 45905 | AA6: None | AB6: None | AC6: NA | AE6: Meets Expectation
A7: 8 | B7: FOH | C7: 45898 | D7: 45911 | E7: 4.24 - Sprint 3 | F7: Arvinth | G7: 49757 | H7: Mosaic FOH - NC Claim Export - Update G3 Number of Enrolled Children calculation | I7: Story Completed | J7: 1 | K7: 0.25 | L7: 1 | M7: 45901 | N7: 45901 | O7: Arvinth | P7: Alpha | Q7: None | R7: Alpha | S7: None | T7: 44311 | U7: 45902 | V7: 45902 | W7: Subha | X7: None | Y7: Steve | Z7: 45902 | AA7: None | AB7: None | AC7: NA | AE7: Meets Expectation
A8: 2 | B8: FOH | C8: 45898 | D8: 45911 | E8: 4.24 - Sprint 3 | F8: Atchaiah | G8: 49676 | H8: MFOH [BAU] - Automation (46340) | I8: Story Completed | J8: 1 | K8: =Table245689102121314111518192021221723[[#This Row],[Actual Worklog (Hours)]] / 4 -> 1 | L8: 4 | M8: 45898 | N8: 45898 | O8: NA | P8: NA | Q8: NA | R8: NA | S8: NA | T8: 44280 | U8: 45898 | V8: 45898 | W8: NA | X8: NA | Y8: Ying | Z8: 45898 | AA8: None | AB8: NA | AC8: NA
A9: 7 | B9: FOH | C9: 45898 | D9: 45911 | E9: 4.24 - Sprint 3 Stretch | F9: Atchaiah | G9: 49865 | H9: MFOH [BAU] - Automation (46474) | I9: Story Completed | J9: 1 | K9: 1 | L9: 4 | M9: 45902 | N9: 45903 | O9: NA | P9: NA | Q9: NA | R9: NA | S9: NA | T9: 44329 | U9: 45903 | V9: 45903 | W9: NA | X9: NA | Y9: Steve | Z9: 45903 | AA9: None | AB9: NA | AC9: NA
A10: 10 | B10: FOH | C10: 45898 | D10: 45911 | E10: 4.24 - Sprint 3 Stretch | F10: Atchaiah | G10: 49866 | H10: MFOH [BAU] - Automation (48837) | I10: Story Completed | J10: 1 | K10: 1 | L10: 4 | M10: 45902 | N10: 45903 | O10: NA | P10: NA | Q10: NA | R10: NA | S10: NA | T10: 44357 | U10: 45904 | V10: 45904 | W10: NA | X10: NA | Y10: Steve | Z10: 45904 | AA10: None | AB10: NA | AC10: NA
A11: 11 | B11: FOH | C11: 45898 | D11: 45911 | E11: 4.24 - Sprint 3 Stretch | F11: Atchaiah | G11: 49920 | H11: MFOH [BAU] - Automation (48916) | I11: Story Completed | J11: 2 | K11: 2 | L11: 8 | M11: 45904 | N11: 45905 | O11: NA | P11: NA | Q11: NA | R11: NA | S11: NA | T11: 44405 | U11: 45905 | V11: 45905 | W11: NA | X11: NA | Y11: Steve | Z11: 45905 | AA11: None | AB11: NA | AC11: NA
A12: 13 | B12: FOH | C12: 45898 | D12: 45911 | E12: 4.24 - Sprint 3 Stretch | F12: Atchaiah | G12: 49963 | H12: MFOH [BAU] - Automation (49232) | I12: Story Completed | J12: 1 | K12: 1 | L12: 4 | M12: 45908 | N12: 45909 | O12: NA | P12: NA | Q12: NA | R12: NA | S12: NA | T12: 44452 | U12: 45909 | V12: 45909 | W12: NA | X12: NA | Y12: Steve | Z12: 45909 | AA12: None | AB12: NA | AC12: NA
A13: 14 | B13: FOH | C13: 45898 | D13: 45911 | E13: 4.24 - Sprint 3 Stretch | F13: Atchaiah | G13: 49985 | H13: MFOH [BAU] - Automation (48918) | I13: Story Completed | J13: 1 | K13: 1 | L13: 4 | M13: 45909 | N13: 45910 | O13: NA | P13: NA | Q13: NA | R13: NA | S13: NA | T13: 44476 | U13: 45910 | V13: 45910 | W13: NA | X13: NA | Y13: Steve | Z13: 45910 | AA13: None | AB13: NA | AC13: NA
A14: 16 | B14: FOH | C14: 45898 | D14: 45911 | E14: 4.24 - Sprint 3 Stretch | F14: Atchaiah | G14: 50038 | H14: MFOH [BAU] - Automation (48919) | I14: Story Completed | J14: 1 | K14: 1 | L14: 4 | M14: 45910 | N14: 45911 | O14: NA | P14: NA | Q14: NA | R14: NA | S14: NA | T14: 44504 | U14: 45911 | V14: 45911 | W14: NA | X14: NA | Y14: Steve | Z14: 45911 | AA14: None | AB14: NA | AC14: NA
A15: 9 | B15: FOH | C15: 45898 | D15: 45911 | E15: 4.24 - Sprint 3 Stretch | F15: Arvinth | G15: 49568 | H15: MFOH - Report Timeout Settings | I15: Story Ready For Testing | J15: 5 | K15: 5.75 | L15: 23.5 | M15: 45901 | N15: 45905 | O15: Arvinth | P15: Alpha | Q15: None | R15: Alpha | S15: None | T15: 44520 | U15: 45911 | V15: 45911 | W15: Subha | X15: Datatype need to mentioned for parameters | Y15: Steve | Z15: 45911 | AA15: None | AB15: None | AC15: NA | AD15: Had a technical complexity on the menu visibility to support user and district elevated access | AE15: Meets Expectation
A16: 12 | B16: FOH | C16: 45898 | D16: 45911 | E16: 4.24 - Sprint 3 Stretch | F16: Alpha | G16: 49771 | H16: MFOH - Add a new label to the Sales Overview Report | I16: Story Being Developed | J16: 2 | K16: 1 | L16: 5 | M16: 45904 | N16: 45904 | O16: Alpha | W16: Subha | X16: None | AD16: Waiting for release branch cut, after that will raise PR
A17: 15 | B17: FOH | C17: 45898 | D17: 45911 | E17: 4.24 - Sprint 3 Stretch | F17: Subhasri | G17: 48706 | H17: Mosaic FOH - Need an attendance import to modify the attendance maintenance | I17: Story Being Developed | J17: 8 | K17: 3.25 | L17: 13 | M17: 45904 | AD17: Started workin at end of the sprint
A18: 17 | B18: FOH | C18: 45898 | D18: 45911 | E18: 4.24 - Sprint 3 Stretch | F18: Ashwin | G18: 25875 | H18: MFOH - Clicking "Delete Multiple Assignments" second time, the value for School Groups in the popup is not showing | I18: Story Being Developed | J18: 2 | K18: 2 | L18: 8 | M18: 45910 | N18: 45910 | O18: Ashwin | P18: Alpha | Q18: None | R18: Alpha | S18: None | AD18: Waiting for release branch cut, after that will raise PR
A19: 18 | B19: FOH | C19: 45898 | D19: 45911 | E19: 4.24 - Sprint 3 Stretch | F19: Ashwin | G19: 25874 | H19: MFOH - Error pop-up not aligned properly while clicking save from the General tab. | I19: Story Being Developed | J19: 2 | K19: 1.5 | L19: 6 | M19: 45910 | N19: 45910 | O19: Ashwin | P19: Alpha | Q19: Not fixed for General tab | R19: Alpha | S19: None | AD19: Waiting for release branch cut, after that will raise PR
A20: 19 | B20: FOH | C20: 45898 | D20: 45911 | E20: 4.24 - Sprint 3 Stretch | F20: Ashwin | G20: 25876 | H20: MFOH - When running the Student Balance Import Results Report, the Errors only filter is showing the no errors as well. | I20: Story Being Developed | J20: 2 | K20: 1.5 | L20: 6.5 | M20: 45908 | N20: 45909 | O20: Ashwin | P20: Alpha | Q20: None | R20: Alpha | S20: None | AD20: Waiting for release branch cut, after that will raise PR

Sheet 4.24 - Sprint 3-Defect
A1: S.No | B1: Sprint # | C1: Story/Defect ID | D1: Parent Story | E1: Developer | F1: Issue Type | G1: Issue Description | H1: Priority | I1: Defect Source | J1: Type | K1: Status | L1: Root Cause Category | M1: Comments

Sheet 4.24 - Sprint 2-Status
A1: S.No | B1: Application Name | C1: Sprint Start Date | D1: Sprint End Date | E1: Sprint | F1: Developer | G1: Story ID/Defect ID | H1: Description | I1: Status | J1: Estimated(hrs/sp) | K1: Actual(hrs/sp) | L1: Actual Worklog (Hours) | M1: Dev Start Date | N1: Dev End Date | O1: Unit testing | P1: Peer Tested By | Q1: Peer Tested Comments, if any | R1: Peer Reviewed By | S1: Peer Code Review Comments, if any | T1: PR Number/Link | U1: PR Created Date | V1: PR Approved Date | W1: Onsite Lead Code Review | X1: Code Review Comments, if any | Y1: Client Code Review | Z1: Approved Date | AA1: Code Review Comments, if any2 | AB1: Internal PO -POV Comments | AC1: Client PO -POV Comments | AD1: Comments | AE1: Does this story meet expectations?
A2: 1 | B2: FOH | C2: 45884 | D2: 45897 | E2: 4.24 - Sprint 2 | F2: Subhasri | G2: 49503 | H2: MFOH - Add a search textbox to the scheduled reports | I2: Story Completed | J2: 3 | K2: 3.75 | L2: 15 | M2: 45883 | N2: 45888 | O2: Subhasri | P2: Alpha | Q2: 1. When cloicking on reset in schedule and Admin tab data load was different | R2: Alpha | S2: None | T2: 44067 | U2: 45889 | V2: 45889 | W2: NA | X2: NA | Y2: Ying | Z2: 45889 | AA2: None | AB2: None | AC2: None | AE2: Meets Expectation
A3: 2 | B3: FOH | C3: 45884 | D3: 45897 | E3: 4.24 - Sprint 2 | F3: Arvinth | G3: 49305 | H3: MFOH - Georgia DE106 Export | I3: Story Completed | J3: 3 | K3: 4.5 | L3: 18 | M3: 45887 | N3: 45894 | O3: Arvinth | P3: Alpha | Q3: comments need to be updated | R3: Alpha | S3: None | T3: 44147 | U3: 45894 | V3: 45894 | W3: Subha | X3: None | Y3: Ying | Z3: 45894 | AA3: None | AB3: None | AC3: None | AD3: Unit testing takes lot of efforts | AE3: Meets Expectation
A4: 3 | B4: FOH | C4: 45884 | D4: 45897 | E4: 4.24 - Sprint 2 Stretch | F4: Ashwin | G4: 49335 | H4: MFOH - Add 'At Risk' field to School Maintenance | I4: Story Completed | J4: 3 | K4: 2.25 | L4: 9 | M4: 45887 | N4: 45888 | O4: Ashwin | P4: Arvinth | Q4: None | R4: Arvinth | S4: None | T4: 44031 | U4: 45888 | V4: 45888 | W4: Subha | X4: AtRisk Column should be not null | Y4: Ying | Z4: 45888 | AA4: None | AB4: None | AC4: None | AE4: Meets Expectation
A5: 4 | B5: FOH | C5: 45884 | D5: 45897 | E5: 4.24 - Sprint 2 Stretch | F5: Atchaiah | G5: 49481 | H5: MFOH - Automation (46992) | I5: Story Completed | J5: 1 | K5: 1 | L5: 4 | O5: NA | P5: NA | Q5: NA | R5: NA | S5: NA | T5: 43945 | U5: 45882 | V5: 45887 | W5: Subha | X5: None | Y5: Ying | Z5: 45887 | AA5: None | AB5: NA | AC5: NA
A6: 5 | B6: FOH | C6: 45884 | D6: 45897 | E6: 4.24 - Sprint 2 Stretch | F6: Alpha | G6: 49242 | H6: MFOH - Add CSV option to the Student Listing Report (DBS) | I6: Story Ready For Testing | J6: 3 | K6: 2.5 | L6: 10 | M6: 45887 | N6: 45888 | O6: Alpha | P6: Ashwin | Q6: None | R6: Arvinth | S6: None | T6: 44224 | U6: 45897 | V6: 45897 | W6: Subha | X6: None | Y6: Ying | Z6: 45897 | AA6: None | AB6: NA | AC6: NA | AE6: Meets Expectation
A7: 6 | B7: FOH | C7: 45884 | D7: 45897 | E7: 4.24 - Sprint 2 Stretch | F7: Atchaiah | G7: 49676 | H7: MFOH [BAU] - Automation (46340) | I7: Story Being Developed | J7: 2 | K7: 2 | L7: 8 | AD7: Getting application errors while running the tests on my machine and the same need to check with other machines.
A8: 7 | B8: FOH | C8: 45884 | D8: 45897 | E8: 4.24 - Sprint 2 Stretch | F8: Alpha | G8: 49595 | H8: MFOH - Add email address for email sent event type (Student & Notification Letter) | I8: Story Being Developed | J8: 5 | L8: 20 | M8: 45894 | AD8: Started development at end of the sprint
A9: 8 | B9: FOH | C9: 45884 | D9: 45897 | E9: 4.24 - Sprint 2 Stretch | F9: Subhasri | G9: 48822 | H9: MFOH - Add 'Language' filter to Eligibility Record Listing Report | I9: Story Being Developed | J9: 3 | M9: 45889
A10: 9 | B10: FOH | C10: 45884 | D10: 45897 | E10: 4.24 - Sprint 2 Stretch | F10: Arvinth | G10: 49757 | H10: Mosaic FOH - NC Claim Export - Update G3 Number of Enrolled Children calculation | I10: Story Being Developed | J10: 3 | M10: 45895 | N10: 45897 | AD10: Started development at end of the sprint
A11: 10 | B11: FOH | C11: 45884 | D11: 45897 | E11: 4.24 - Sprint 2 Stretch | F11: Atchaiah | G11: 49764 | H11: MFOH [BAU] - Automation (48169) | I11: Story Completed | J11: 1 | K11: 1 | L11: 4 | M11: 45894 | N11: 45895 | O11: NA | P11: NA | Q11: NA | R11: NA | S11: NA | T11: 44170 | U11: 45895 | V11: 45895 | W11: NA | X11: NA | Y11: Ying | Z11: 45895 | AB11: NA | AC11: NA
A12: 11 | B12: FOH | C12: 45884 | D12: 45897 | E12: 4.24 - Sprint 2 Stretch | F12: Atchaiah | G12: 49763 | H12: MFOH [BAU] - Automation (48271) | I12: Story Completed | J12: 1 | K12: 1 | L12: 4 | M12: 45897 | N12: 45897 | O12: NA | P12: NA | Q12: NA | R12: NA | S12: NA | T12: 44252 | U12: 45897 | V12: 45897 | W12: NA | X12: NA | Y12: Ying | Z12: 45897 | AB12: NA | AC12: NA

Sheet 4.24 - Sprint 2-Defect
A1: S.No | B1: Sprint # | C1: Story/Defect ID | D1: Parent Story | E1: Developer | F1: Issue Type | G1: Issue Description | H1: Priority | I1: Defect Source | J1: Type | K1: Status | L1: Root Cause Category | M1: Comments

Sheet 4.24 - Sprint 1-Status
A1: S.No | B1: Application Name | C1: Sprint Start Date | D1: Sprint End Date | E1: Sprint | F1: Developer | G1: Story ID/Defect ID | H1: Description | I1: Status | J1: Estimated(hrs/sp) | K1: Actual(hrs/sp) | L1: Actual Worklog (Hours) | M1: Dev Start Date | N1: Dev End Date | O1: Unit testing | P1: Peer Tested By | Q1: Peer Tested Comments, if any | R1: Peer Reviewed By | S1: Peer Code Review Comments, if any | T1: PR Number/Link | U1: PR Created Date | V1: PR Approved Date | W1: Onsite Lead Code Review | X1: Code Review Comments, if any | Y1: Client Code Review | Z1: Approved Date | AA1: Code Review Comments, if any2 | AB1: Internal PO -POV Comments | AC1: Client PO -POV Comments | AD1: Comments | AE1: Does this story meet expectations?
A2: 1 | B2: FOH | C2: 45870 | D2: 45883 | E2: 4.24 - Sprint 1 | F2: Alpha | G2: 48918 | H2: MFOH - Add 'Last Payment Date' as an export field (Student Export) | I2: Story Completed | J2: 1 | K2: 1.5 | L2: 2.5 | M2: 45870 | N2: 45870 | O2: Alpha | P2: Ashwin | Q2: Filter (=) is not working due to the format. | R2: Arvinth | S2: None | T2: 43752 | U2: 45873 | V2: 45874 | W2: Subha | X2: Revision history to 4.24 | Y2: Ying | Z2: 45874 | AA2: FORMAT is not working with sql server 2008 | AB2: None | AC2: NA | AE2: Meets Expectation
A3: 2 | B3: FOH | C3: 45870 | D3: 45883 | E3: 4.24 - Sprint 1 | F3: Arvinth | G3: 49232 | H3: MFOH - Improvements to NC SFS-4 Export | I3: Story Completed | J3: 3 | K3: 2.75 | L3: 11 | M3: 45870 | N3: 45873 | O3: Arvinth | P3: Ashwin | Q3: None | R3: Ashwin | S3: None | T3: 43918 | U3: 45881 | V3: 45881 | W3: Subha | X3: None | Y3: Ying | Z3: 45881 | AA3: None | AB3: None | AC3: None | AE3: Meets Expectation
A4: 3 | B4: FOH | C4: 45870 | D4: 45883 | E4: 4.24 - Sprint 1 | F4: Alpha | G4: 49424 | H4: MFOH [WAVE] - Add a 'Refresh' option inside the dashboard widget | I4: Story Rejected | J4: 5 | K4: 1 | L4: 4 | M4: 45870 | N4: NA | O4: NA | P4: NA | Q4: NA | R4: NA | S4: NA | T4: NA | U4: NA | V4: NA | W4: NA | X4: NA | Y4: NA | Z4: NA | AA4: NA | AB4: NA | AC4: NA | AD4: Story Rejected; The feature will not be beneficial for the users.
A5: 4 | B5: FOH | C5: 45870 | D5: 45883 | E5: 4.24 - Sprint 1 | F5: Alpha | G5: 49426 | H5: MFOH [WAVE] - Add an option to export the widget and its underlying data | I5: Story Completed | J5: 5 | K5: 7.5 | L5: 29 | M5: 45873 | N5: 45882 | O5: Alpha | P5: Subha | Q5: Reimbursable meal count export has duplicate rows, Last applied filter is affecting the export of other widget, Export to download location was not working. | R5: NA | S5: NA | T5: 43946 | U5: 45882 | V5: 45882 | W5: Subha | X5: Add the xml comments to new methods. Revision history name update. | Y5: Ying | Z5: 45882 | AA5: None | AB5: None | AC5: None | AD5: Story was under estimated and it is conveyed on time.
A6: 5 | B6: FOH | C6: 45870 | D6: 45883 | E6: 4.24 - Sprint 1 | F6: Subhasri | G6: 25693 | H6: MFOH - Serving period filter selection is not retained in the user dashboard | I6: Defect Fixed | J6: 3 | K6: 3 | L6: 15 | M6: 45873 | N6: 45876 | O6: Subhasri | P6: Alpha | Q6: 1.One of the scenario is missing selection serving period 2. ClearFilter is again making the serving period selection wrongly | R6: Alpha | S6: NA | T6: 43849 | U6: 45876 | V6: 45877 | W6: NA | X6: NA | Y6: Ying | Z6: 45877 | AA6: None | AB6: None | AC6: None
A7: 6 | B7: FOH | C7: 45870 | D7: 45883 | E7: 4.24 - Sprint 1 Stretch | F7: Atchaiah | G7: 49277 | H7: MFOH [BAU] - Automation (45931) | I7: Story Completed | J7: 1 | K7: 1 | L7: 4 | O7: NA | P7: NA | Q7: NA | R7: NA | S7: NA | T7: 43716 | U7: 45870 | V7: 45870 | W7: NA | X7: NA | Y7: Yiing | Z7: 45870 | AA7: None | AB7: NA | AC7: NA
A8: 7 | B8: FOH | C8: 45870 | D8: 45883 | E8: 4.24 - Sprint 1 Stretch | F8: Atchaiah | G8: 49454 | H8: MFOH [BAU] - Automation (46988) | I8: Story Completed | J8: 1 | K8: 1 | L8: 4 | M8: 45873 | N8: 45874 | O8: NA | P8: NA | Q8: NA | R8: NA | S8: NA | T8: 43778 | U8: 45874 | V8: 45874 | W8: NA | X8: NA | Y8: Yiing | Z8: 45874 | AA8: None | AB8: NA | AC8: NA
A9: 8 | B9: FOH | C9: 45870 | D9: 45883 | E9: 4.24 - Sprint 1 Stretch | F9: Atchaiah | G9: 49481 | H9: MFOH - Automation (46992) | I9: Story Peer Review | J9: 2 | K9: 2 | L9: 8 | M9: 45881 | N9: 45882 | O9: NA | P9: NA | Q9: NA | R9: NA | S9: NA | T9: 43945 | U9: 45882 | W9: NA | X9: NA | Y9: Ying | AB9: NA | AC9: NA | AD9: Story is in peer review
A10: 9 | B10: FOH | C10: 45870 | D10: 45883 | E10: 4.24 - Sprint 1 Stretch | F10: Atchaiah | G10: 49564 | H10: MFOH [BAU] - Automation (46472) | I10: Story Completed | J10: 1 | K10: 1 | L10: 4 | M10: 45880 | N10: 45880 | O10: NA | P10: NA | Q10: NA | R10: NA | S10: NA | T10: 43886 | U10: 45880 | V10: 45880 | W10: NA | X10: NA | Y10: Ying | Z10: 45880 | AA10: None | AB10: NA | AC10: NA
A11: 10 | B11: FOH | C11: 45870 | D11: 45883 | E11: 4.24 - Sprint 1 Stretch | F11: Arvinth | G11: 49517 | H11: MFOH - Revert the changes done in 48246 | I11: Story Ready For Testing | J11: 5 | K11: 3.5 | L11: 14 | M11: 45876 | N11: 45881 | O11: Arvinth | P11: Alpha | Q11: None | R11: Alpha | S11: None | T11: 43917 | U11: 45881 | V11: 45881 | W11: Subha | X11: Remove the reportrow file changes | Y11: Ying | Z11: 45881 | AA11: None | AB11: None | AC11: NA | AD11: Story is in onsite QA bucket | AE11: Meets Expectation
A12: 11 | B12: FOH | C12: 45870 | D12: 45883 | E12: 4.24 - Sprint 1 Stretch | F12: Arvinth | G12: 49305 | H12: MFOH - Georgia DE106 Export | I12: Story Being Developed | J12: 8 | K12: 3 | L12: 12 | AD12: Started this story at the end of the sprint
A13: 12 | B13: FOH | C13: 45870 | D13: 45883 | E13: 4.24 - Sprint 1 Stretch | F13: Subhasri | G13: 25669 | H13: MFOH - Student Import - Homeroom - Special characters in name causing issues | I13: Story Rejected | J13: 1 | K13: 0.5 | L13: 2 | M13: 45881 | N13: NA | O13: NA | P13: NA | Q13: NA | R13: NA | S13: NA | T13: NA | U13: NA | V13: NA | W13: NA | X13: NA | Y13: NA | Z13: NA | AA13: NA | AB13: NA | AC13: NA | AD13: Defect has been rejected because it is not able to reproduce it in any environment

Sheet 4.24 - Sprint 1-Defect
A1: S.No | B1: Sprint # | C1: Story/Defect ID | D1: Parent Story | E1: Developer | F1: Issue Type | G1: Issue Description | H1: Priority | I1: Defect Source | J1: Type | K1: Status | L1: Root Cause Category | M1: Comments

Sheet 4.23 - Sprint 4-Status
A1: S.No | B1: Application Name | C1: Sprint Start Date | D1: Sprint End Date | E1: Sprint | F1: Developer | G1: Story ID/Defect ID | H1: Description | I1: Status | J1: Estimated(hrs/sp) | K1: Actual(hrs/sp) | L1: Actual Worklog (Hours) | M1: Dev Start Date | N1: Dev End Date | O1: Unit testing | P1: Peer Tested By | Q1: Peer Tested Comments, if any | R1: Peer Reviewed By | S1: Peer Code Review Comments, if any | T1: PR Number/Link | U1: PR Created Date | V1: PR Approved Date | W1: Onsite Lead Code Review | X1: Code Review Comments, if any | Y1: Client Code Review | Z1: Approved Date | AA1: Code Review Comments, if any2 | AB1: Internal PO -POV Comments | AC1: Client PO -POV Comments | AD1: Comments | AE1: Does this story meet expectations?
A2: 1 | B2: FOH | C2: 45856 | D2: 45869 | E2: 4.23 - Sprint 4 | F2: Arvinth | G2: 48916 | H2: MFOH - Add 'Notes' Tab to POS Maintenance | I2: Story Completed | J2: 2 | K2: 1 | L2: 4 | M2: 45856 | N2: 45856 | O2: Arvinth | P2: Ashwin | Q2: None | R2: Alpha | S2: None | T2: 43557 | U2: 45861 | V2: 45861 | W2: Subha | X2: None | Y2: Ying | Z2: 45861 | AA2: None | AB2: None | AC2: NA | AE2: Meets Expectation
A3: 2 | B3: FOH | C3: 45856 | D3: 45869 | E3: 4.23 - Sprint 4 | F3: Alpha | G3: 48919 | H3: MFOH - Add an ability to select and add all the available student export fields | I3: Story Completed | J3: 1 | K3: 0.5 | L3: 2 | M3: 45856 | N3: 45856 | O3: Alpha | P3: Ashwin | Q3: None | R3: Arvinth | S3: None | T3: 43478 | U3: 45856 | V3: 45856 | W3: Subha | X3: None | Y3: Ying | Z3: 45856 | AA3: None | AB3: None | AC3: NA | AE3: Meets Expectation
A4: 3 | B4: FOH | C4: 45856 | D4: 45869 | E4: 4.23 - Sprint 4 | F4: Alpha/Atchaiah | G4: 49256 | H4: Mosaic - FOH 4.23(Regression) - End of Day | I4: Story Completed | J4: 5 | K4: 5.5 | L4: 22 | M4: 45860 | N4: 45869 | O4: NA | P4: NA | Q4: NA | R4: NA | S4: NA | T4: NA | U4: NA | V4: NA | W4: NA | X4: NA | Y4: NA | Z4: NA | AA4: NA | AB4: NA | AC4: NA | AD4: Regression Testing
A5: 4 | B5: FOH | C5: 45856 | D5: 45869 | E5: 4.23 - Sprint 4 | F5: Arvinth/Atchaiah | G5: 49261 | H5: Mosaic - FOH 4.23 (Regression) - POS(Menu Option) | I5: Story Completed | J5: 2 | K5: 3 | L5: 12 | M5: 45860 | N5: 45869 | O5: NA | P5: NA | Q5: NA | R5: NA | S5: NA | T5: NA | U5: NA | V5: NA | W5: NA | X5: NA | Y5: NA | Z5: NA | AA5: NA | AB5: NA | AC5: NA | AD5: Regression Testing
A6: 5 | B6: FOH | C6: 45856 | D6: 45869 | E6: 4.23 - Sprint 4 | F6: Subhasri/Atchaiah | G6: 49259 | H6: Mosaic - FOH 4.23 (Regression) - Eligibility (F&R) | I6: Story Completed | J6: 5 | K6: 6 | L6: 24 | M6: 45860 | N6: 45869 | O6: NA | P6: NA | Q6: NA | R6: NA | S6: NA | T6: NA | U6: NA | V6: NA | W6: NA | X6: NA | Y6: NA | Z6: NA | AA6: NA | AB6: NA | AC6: NA | AD6: Regression Testing
A7: 6 | B7: FOH | C7: 45856 | D7: 45869 | E7: 4.23 - Sprint 4 | F7: Ashwin/Atchaiah | G7: 49255 | H7: Mosaic - FOH 4.23 (Regression) - Students | I7: Story Completed | J7: 5 | K7: 5.5 | L7: 22.5 | M7: 45860 | N7: 45869 | O7: NA | P7: NA | Q7: NA | R7: NA | S7: NA | T7: NA | U7: NA | V7: NA | W7: NA | X7: NA | Y7: NA | Z7: NA | AA7: NA | AB7: NA | AC7: NA | AD7: Regression Testing
A8: 7 | B8: FOH | C8: 45856 | D8: 45869 | E8: 4.23 - Sprint 4 | F8: Arvinth/Atchaiah | G8: 49258 | H8: Mosaic - FOH 4.23 (Regression) - Reports - Eligibility (F&R) | I8: Story Completed | J8: 3 | K8: 3 | L8: 12 | M8: 45862 | N8: 45869 | O8: NA | P8: NA | Q8: NA | R8: NA | S8: NA | T8: NA | U8: NA | V8: NA | W8: NA | X8: NA | Y8: NA | Z8: NA | AA8: NA | AB8: NA | AC8: NA | AD8: Regression Testing
A9: 8 | B9: FOH | C9: 45856 | D9: 45869 | E9: 4.23 - Sprint 4 | F9: Arvinth | G9: 46474 | H9: Mosaic - POS (Web) - Add an Email Filter to Student Listing Report (DBS) | I9: Story Completed | J9: 1 | K9: 1 | L9: 4 | M9: 45869 | N9: 45869 | O9: NA | P9: NA | Q9: NA | R9: NA | S9: NA | T9: NA | U9: NA | V9: NA | W9: NA | X9: NA | Y9: NA | Z9: NA | AA9: NA | AB9: NA | AC9: NA | AD9: Manual Testing
A10: 9 | B10: FOH | C10: 45856 | D10: 45869 | E10: 4.23 - Sprint 4 | F10: Arvinth | G10: 48837 | H10: Mosaic - POS (Web) - Add 'Needs Letter' filter to Elig. Record Student Listing Report (DBS) | I10: Story Completed | J10: 1 | K10: 1 | L10: 4 | M10: 45869 | N10: 45869 | O10: NA | P10: NA | Q10: NA | R10: NA | S10: NA | T10: NA | U10: NA | V10: NA | W10: NA | X10: NA | Y10: NA | Z10: NA | AA10: NA | AB10: NA | AC10: NA | AD10: Manual Testing
A11: 10 | B11: FOH | C11: 45856 | D11: 45869 | E11: 4.23 - Sprint 4 | F11: Arvinth | G11: 25678 | H11: MFOH - (4.23 Regression) - Issues with Ohio CN Report Setup | I11: Story Completed | J11: 0 | K11: 0 | L11: 0 | M11: 45867 | N11: 45867 | O11: Arvinth | P11: Ashwin | Q11: None | R11: NA | S11: NA | T11: 43657 | U11: 45867 | V11: 45867 | W11: NA | X11: NA | Y11: Ying | Z11: 45867 | AA11: None | AB11: None | AC11: NA | AD11: Regression defect
A12: 11 | B12: FOH | C12: 45856 | D12: 45869 | E12: 4.23 - Sprint 4 | F12: Arvinth | G12: 25672 | H12: MFOH - (4.23 Regression) - Date Format Issue in multiple screens | I12: Story Completed | J12: 0 | K12: 0 | L12: 0 | M12: 45867 | N12: 45867 | O12: Arvinth | P12: Ashwin | Q12: None | R12: NA | S12: NA | T12: 43656 | U12: 45867 | V12: 45867 | W12: NA | X12: NA | Y12: Ying | Z12: 45867 | AA12: None | AB12: None | AC12: NA | AD12: Regression defect
A13: 12 | B13: FOH | C13: 45856 | D13: 45869 | E13: 4.23 - Sprint 4 Stretch | F13: Alpha/Atchaiah | G13: 49254 | H13: Mosaic - FOH 4.23(Regression) - Setup | I13: Story Completed | J13: 5 | K13: 5.75 | L13: 23.5 | M13: 45862 | N13: 45869 | O13: NA | P13: NA | Q13: NA | R13: NA | S13: NA | T13: NA | U13: NA | V13: NA | W13: NA | X13: NA | Y13: NA | Z13: NA | AA13: NA | AB13: NA | AC13: NA | AD13: Regression Testing
A14: 13 | B14: FOH | C14: 45856 | D14: 45869 | E14: 4.23 - Sprint 4 Stretch | F14: Alpha/Ashwin | G14: 49253 | H14: Mosaic - FOH 4.23(Regression) - Utilities | I14: Story Completed | J14: 5 | K14: 6.25 | L14: 25 | M14: 45863 | N14: 45869 | O14: NA | P14: NA | Q14: NA | R14: NA | S14: NA | T14: NA | U14: NA | V14: NA | W14: NA | X14: NA | Y14: NA | Z14: NA | AA14: NA | AB14: NA | AC14: NA | AD14: Regression Testing
A15: 14 | B15: FOH | C15: 45856 | D15: 45869 | E15: 4.23 - Sprint 4 Stretch | F15: Alpha | G15: 48918 | H15: MFOH - Add 'Last Payment Date' as an export field (Student Export) | I15: Story Being Developed | J15: 3 | K15: 3 | L15: 12 | M15: 45859 | N15: NA | O15: Alpha | AB15: None | AC15: NA | AD15: Development completed and kept on hold due to regression
A16: 15 | B16: FOH | C16: 45856 | D16: 45869 | E16: 4.23 - Sprint 4 Stretch | F16: Atchaiah | G16: 49277 | H16: MFOH [BAU] - Automation (45931) | I16: Story Being Developed | J16: 2 | K16: 1.5 | L16: 6 | AD16: Development completed and kept on hold due to regression

Sheet 4.23 - Sprint 4-Defect
A1: S.No | B1: Sprint # | C1: Story/Defect ID | D1: Parent Story | E1: Developer | F1: Issue Type | G1: Issue Description | H1: Priority | I1: Defect Source | J1: Type | K1: Status | L1: Root Cause Category | M1: Comments

Sheet 4.23 - Sprint 3-Status
A1: S.No | B1: Application Name | C1: Sprint Start Date | D1: Sprint End Date | E1: Sprint | F1: Developer | G1: Story ID/Defect ID | H1: Description | I1: Status | J1: Estimated(hrs/sp) | K1: Actual(hrs/sp) | L1: Actual Worklog (Hours) | M1: Unit testing | N1: Peer Tested By | O1: Peer Tested Comments, if any | P1: Peer Reviewed By | Q1: Peer Code Review Comments, if any | R1: PR Number/Link | S1: PR Created Date | T1: PR Approved Date | U1: Onsite Lead Code Review | V1: Code Review Comments, if any | W1: Client Code Review | X1: Approved Date | Y1: Code Review Comments, if any2 | Z1: Internal PO -POV Comments | AA1: Client PO -POV Comments | AB1: Comments | AC1: Does this story meet expectations?
A2: 1 | B2: FOH | C2: 45842 | D2: 45855 | E2: 4.23 - Sprint 3 | F2: Alpha | G2: 48246 | H2: Mosaic FoH - Sales Overview and Standard Claim Reports (ADA and ADP discrepancies) | I2: Story Completed | J2: 3 | K2: 2.5 | L2: 10 | M2: Alpha | N2: Arvinth | O2: None | P2: Arvinth | Q2: None | R2: 43301 | S2: 45848 | T2: 45848 | U2: Subha | V2: None | W2: Ying | X2: 45848 | Y2: None | Z2: None | AA2: None | AC2: Meets Expectation
A3: 2 | B3: FOH | C3: 45842 | D3: 45855 | E3: 4.23 - Sprint 3 | F3: Arvinth | G3: 48740 | H3: MFOH - Replace Serving Period with Serving Period Program GUID in Georgia DE0118 | I3: Story Completed | J3: 2 | K3: 1.25 | L3: 5 | M3: Arvinth | N3: Ashwin | O3: None | P3: Alpha | Q3: None | R3: 43232 | S3: 45846 | T3: 45846 | U3: Subha | V3: None | W3: Ying | X3: 45846 | Y3: None | Z3: None | AA3: None | AC3: Meets Expectation
A4: 3 | B4: FOH | C4: 45842 | D4: 45855 | E4: 4.23 - Sprint 3 | F4: Ashwin | G4: 48741 | H4: MFOH - Replace Serving Period with Serving Period Program GUID in Georgia DE0113 | I4: Story Completed | J4: 2 | K4: 1.25 | L4: 5 | M4: Ashwin | N4: Sabir | O4: Missing commands in stored procedure | P4: Sabir | Q4: None | R4: 43271 | S4: 45847 | T4: 45847 | U4: Subha | V4: None | W4: Ying | X4: 45847 | Y4: None | Z4: None | AA4: None | AC4: Meets Expectation
A5: 4 | B5: FOH | C5: 45842 | D5: 45855 | E5: 4.23 - Sprint 3 | F5: Alpha | G5: 49000 | H5: MFOH - Separate CC from Cash in Extended Daily Sales Summary Report (CC Sales Management) | I5: Story Completed | J5: 3 | K5: 3 | L5: 11 | M5: Alpha | N5: Ashwin | O5: None | P5: Arvinth | Q5: None | R5: 43302 | S5: 45848 | T5: 45848 | U5: Subha | V5: None | W5: Ying | X5: 45848 | Y5: None | Z5: None | AA5: None | AC5: Meets Expectation
A6: 5 | B6: FOH | C6: 45842 | D6: 45855 | E6: 4.23 - Sprint 3 | F6: Arvinth | G6: 48169 | H6: MFOH - Improvements to the Student Meal Report (Duane's List) | I6: Story Completed | J6: 5 | K6: 4.5 | L6: 18 | M6: Arvinth | N6: Ashwin | O6: None | P6: Alpha | Q6: condition need to be added for | R6: 43353 | S6: 45852 | T6: 45852 | U6: Subha | V6: use diplayname condition to filter | W6: Ying | X6: 45852 | Y6: None | Z6: None | AA6: NA | AC6: Meets Expectation
A7: 6 | B7: FOH | C7: 45842 | D7: 45855 | E7: 4.23 - Sprint 3 Stretch | F7: Atchaiah | G7: 49038 | H7: MFOH [BAU] - Automation (47184) | I7: Story Completed | J7: 2 | K7: 2 | L7: 10 | M7: NA | N7: NA | O7: NA | P7: NA | Q7: NA | R7: 43444 | S7: 45855 | T7: 45855 | U7: Subha | V7: None | W7: Ying | X7: 45855 | Y7: None | Z7: NA | AA7: NA | AC7: Meets Expectation
A8: 7 | B8: FOH | C8: 45842 | D8: 45855 | E8: 4.23 - Sprint 3 Stretch | F8: Alpha | G8: 48837 | H8: Mosaic - POS (Web) - Add 'Needs Letter' filter to Elig. Record Student Listing Report (DBS) | I8: Story Ready For Testing | J8: 3 | K8: 2.5 | L8: 10 | M8: Alpha | N8: Ashwin | O8: None | P8: Arvinth | Q8: None | R8: 43368 | S8: 45853 | T8: 45853 | U8: Subha | V8: None | W8: Ying | X8: 45853 | Y8: None | Z8: None | AA8: NA | AB8: Story is in onsite QA bucket | AC8: Meets Expectation
A9: 8 | B9: FOH | C9: 45842 | D9: 45855 | E9: 4.23 - Sprint 3 Stretch | F9: Arvinth | G9: 48916 | H9: MFOH - Add 'Notes' Tab to POS Maintenance | I9: Story Being Developed | J9: 5 | K9: 4.25 | L9: 17 | AB9: Started this story at the end of the sprint
A10: 9 | B10: FOH | C10: 45842 | D10: 45855 | E10: 4.23 - Sprint 3 Stretch | F10: Alpha | G10: 48919 | H10: MFOH - Add an ability to select and add all the available student export fields | I10: Story Being Developed | J10: 5 | K10: 5 | L10: 20 | M10: Alpha | N10: Ashwin | O10: None | AB10: Started this story at the end of the sprint
