Workbook

Sheet Dashboard
A1: Current Sprint | B1: {=INDEX($B$2:$B$101,MATCH(1,(($D$2:$D$101 >=TODAY())*($C$2:$C$101<=TODAY())),0))} -> 26.7 M Sprint 1 | C1: Current Sprint Sheet | D1: =CONCATENATE(B1,"-Status") -> 26.7 M Sprint 1-Status | E1: Sprint Start Date | F1: =VLOOKUP($B$1,$B$1:$C$101,2) -> 46157 | G1: Sprint End Date | H1: =VLOOKUP($B$1,$B$1:$D$101,3) -> 46170 | I1: Application NAme | J1: MSB Mobile | K1: Users | L1: sambath.selvam@relevantz.com;rupesh.kumar@relevantz.com;vaishnavi.shanmugavel@relevantz.com;ashwin.majella@relevantz.com;premkumar.rajendran@relevantz.com;bavithra.arasakumaran@relevantz.com;gursewak.jaspal@relevantz.com;amrit.harjit@relevantz.com;jagdeep.singh@relevantz.com | M1: Teams Name(GP-MSB.Mobile) | N1: 19:aa5856a8e6e3487ab79589431d926322@thread.v2
A2: Sprint Type | B2: Sprint # | C2: Sprint Start Date | D2: Sprint End Date | E2: Assigned | F2: Completed | G2: Story Points Story points introduced/removed | H2: Sprint Summary | I2: Accomplishments | J2: Remarks | K2: Retro Points (Internal & External) | L2: Unplanned Leaves | M2: Data sanity Audit Status | N2: AuditDate | O2: Completed Stretch | P2: Backlog Health
A3: =IF(AND($D$1>=C3,$D$1<=D3),"CurrentSprint","NA") -> NA | B3: 13.5 Spirnt 2 | C3: 45301 | D3: 45314 | E3: 26 | F3: 26 | J3: 7 Story point introduced in mid of the sprint NOTE: MAUI stories are also in progress, but paused due to high priority defects. | K3: Internal: External: | O3: 7
A4: =IF(AND($D$1>=C4,$D$1<=D4),"CurrentSprint","NA") -> NA | B4: 13.5 Sprint 3 | C4: 45315 | D4: 45328 | E4: 15 | F4: 17 | J4: Strech Stories are holded by client because of regression defects NOTE: MAUI stories are also in progress, but paused due to high priority regression defects. | K4: Internal: External: | O4: 8
A5: =IF(AND($D$1>=C5,$D$1<=D5),"CurrentSprint","NA") -> NA | B5: 13.6 Sprint 1 | C5: 45329 | D5: 45342 | E5: 17 | F5: 12 | J5: The development of the 43394 story is complete, but a new POV scope has been added. So this story is carried to the next sprint. NOTE: Comments added respective stories | K5: Internal: External: | O5: 3
A6: =IF(AND($D$1>=C6,$D$1<=D6),"CurrentSprint","NA") -> NA | B6: 13.6 Sprint 2 | C6: 45343 | D6: 45356 | E6: 24 | F6: 19 | J6: MAUI Stories Update 42130 story is carried due to the bounce backs. 42138 story is completed and its under the testing. MAUI Stretch Stories Update 42131 story is compled but gokul have the build issue in Mac Mini so he is fixing the issue. 42142 story is completed, Testing is under progress. | K6: Internal: External: | O6: 4
A7: =IF(AND($D$1>=C7,$D$1<=D7),"CurrentSprint","NA") -> NA | B7: 13.6 Sprint 3 | C7: 45357 | D7: 45370 | E7: 13 | F7: 13 | G7: 13 | J7: All MAUI Stories are moved to Stretch, Working with POV comments and bounebacks. 42130 - Maui Story is completed and now it's ready for testing | K7: Internal: External: | O7: 2
A8: =IF(AND($D$1>=C8,$D$1<=D8),"CurrentSprint","NA") -> NA | B8: 13.7 Sprint 1 | C8: 45371 | D8: 45384 | E8: 14 | F8: 14 | G8: 11 | J8: 42129 - Login Maui story bounce back issue fixed, and it is needed some foundation level fix so sean is looking into that issue. 42131,42138 - Gokul is fixing the internal testing issues, once done, wrap up all the committed MAUI stories, and close it as soon as possible. NOTE: Detailed comments added in respective stories. | K8: Internal: External:
A9: =IF(AND($D$1>=C9,$D$1<=D9),"CurrentSprint","NA") -> NA | B9: 13.7 Sprint 2 | C9: 45385 | D9: 45398 | E9: 21 | F9: 15 | G9: 16 | J9: 43928 is dev completed, New changes add at end of the sprint, and POV and Testing is Pending. Defect 19537 is fixed, but added peer review comments so this defect is carried to the next sprint MAUI Stories are still in External Testing. NOTE: Detailed comments added in respective stories. | K9: Internal: External:
A10: =IF(AND($D$1>=C10,$D$1<=D10),"CurrentSprint","NA") -> NA | B10: 13.7 Sprint 3 | C10: 45399 | D10: 45412 | E10: 12 | F10: 12 | G10: 17 | J10: The story 43928 has been completed but it hasn't been tested yet, thus we need help testing it. so the brain will support the tests Completing high priority tasks by fixing regression defects, and after those are finished, moving on to stretch stories. Pulled the new MAUI stretch stories and Working on it. Note: Not pulled new committed stoies to work because this is a regression sprint. | K10: Internal: External:
A11: =IF(AND($D$1>=C11,$D$1<=D11),"CurrentSprint","NA") -> NA | B11: 13.8 Sprint 1 | C11: 45413 | D11: 45426 | E11: 10 | F11: 10 | J11: Regression Sprint. We are working on stretch stories for MAUI. and for this sprint, no newly committed stories were pulled. | K11: Internal: External:
A12: =IF(AND($D$1>=C12,$D$1<=D12),"CurrentSprint","NA") -> NA | B12: 13.8 Sprint 2 | C12: 45427 | D12: 45440 | E12: 22 | F12: 17 | J12: Some stories cannot be tested since the iOS device and simulator are not operating, therefore they are carried over to the next sprint. | K12: Internal: External:
A13: =IF(AND($D$1>=C13,$D$1<=D13),"CurrentSprint","NA") -> NA | B13: 13.8 Sprint 3 | C13: 45441 | D13: 45454 | E13: 25 | F13: 21 | J13: This sprint, we are worked on regression issues, therefore some of the committed stories only partially worked. | K13: Internal: External:
A14: =IF(AND($D$1>=C14,$D$1<=D14),"CurrentSprint","NA") -> NA | B14: 14.0 Sprint 1 | C14: 45455 | D14: 45468 | E14: 14 | F14: 11 | G14: 2 | J14: Due to POV comments, the story 42133 is carried over to the next sprint. | K14: Internal: External:
A15: =IF(AND($D$1>=C15,$D$1<=D15),"CurrentSprint","NA") -> NA | B15: 14.0 Sprint 2 | C15: 45469 | D15: 45484 | E15: 11 | F15: 15.5 | G15: 6.5 | J15: Completed 1 stretch story. | K15: Internal: External:
A16: =IF(AND($D$1>=C16,$D$1<=D16),"CurrentSprint","NA") -> NA | B16: 14.0 Sprint 3 | C16: 45485 | D16: 45498 | E16: 13 | F16: 13 | G16: 26 | J16: Completed 1 stretch story, and currently working on MAUI stretch stories. | K16: Internal: External:
A17: =IF(AND($D$1>=C17,$D$1<=D17),"CurrentSprint","NA") -> NA | B17: 14.1 Sprint 1 | C17: 45499 | D17: 45512 | E17: 11 | F17: 11 | G17: 29 | J17: Completed 2 strech stories and 1 committed story, and we are worked on MAUI Strech stories. | K17: Internal: External:
A18: =IF(AND($D$1>=C18,$D$1<=D18),"CurrentSprint","NA") -> NA | B18: 14.1 Sprint 2 | C18: 45513 | D18: 45526 | E18: 7 | F18: 7 | G18: 25 | J18: we are cotinued to working on MAUI stretch stories | K18: Internal: External:
A19: =IF(AND($D$1>=C19,$D$1<=D19),"CurrentSprint","NA") -> NA | B19: 14.1 Sprint 3 | C19: 45527 | D19: 45540 | E19: 29 | F19: 27.5 | G19: 21 | J19: Cotinued to working on MAUI stretch stories | K19: Internal: External:
A20: =IF(AND($D$1>=C20,$D$1<=D20),"CurrentSprint","NA") -> NA | B20: 14.2 Sprint 1 | C20: 45541 | D20: 45554 | E20: 8.5 | F20: 13.5 | G20: 16 | J20: Cotinued to working on MAUI stretch stories. Regression defects are worked and the SP are burned down to the regression Stories | K20: Internal: External:
A21: =IF(AND($D$1>=C21,$D$1<=D21),"CurrentSprint","NA") -> NA | B21: 14.2 M Sprint 2 | C21: 45555 | D21: 45568 | E21: 4 | F21: 4 | G21: 14 | J21: CRC Peer - 0, Onsite - 0, Client - 0. Internal Defect - 0, External Defect - 0.
A22: =IF(AND($D$1>=C22,$D$1<=D22),"CurrentSprint","NA") -> NA | B22: 14.2 M Sprint 3 | C22: 45569 | D22: 45582 | E22: 13 | F22: 16 | G22: 21
A23: =IF(AND($D$1>=C23,$D$1<=D23),"CurrentSprint","NA") -> NA | B23: 14.3 M Sprint 1 | C23: 45583 | D23: 45596 | E23: 19 | F23: 14 | G23: 15
A24: =IF(AND($D$1>=C24,$D$1<=D24),"CurrentSprint","NA") -> NA | B24: 14.3 M Sprint 2 | C24: 45597 | D24: 45610 | E24: 17.5 | F24: 6.5 | G24: 8 | I24: Maui Stories-Development and testing completed. | J24: Testing was delayed due to a deployment issue in the build pipeline, GSOC scope change and DS dependency
A25: =IF(AND($D$1>=C25,$D$1<=D25),"CurrentSprint","NA") -> NA | B25: 14.3 M Sprint 3 | C25: 45611 | D25: 45628 | E25: 18 | F25: 5 | G25: 10 | I25: Development completed for most of the MAUI stories from stretch. | J25: MSBP regression could not be completed due to external dependency for greenLight testing(functionality).The workflow in GLs end was changed which was not intimated until Letashia tested it and found it. GL cannot be tested offshore due to region specific restriction. Dotnet 9 update caused the bottom sheet issues(Internal Component) so MAUI stories could not be tested. | K25: Most of the stories are blocked due the .Net 9 update
A26: =IF(AND($D$1>=C26,$D$1<=D26),"CurrentSprint","NA") -> NA | B26: 14.4 M Sprint 1 | C26: 45629 | D26: 45638 | E26: 11 | F26: 11.3 | G26: 25 | I26: Completed Regression testing before the release | J26: Dotnet 9 and Telerik updated caused the bottom sheet issues(Internal Component) and input modal crash issue respectively. So MAUI stories could not be tested. The Blockers were addressed by Client Dev. | K26: Most of the stories are blocked due to .Net 9 and Telerik updates. Client decided to go with MAUI controls instead of telerik for Datepicker and Input Modal entry control due to the long time blocker.
A27: =IF(AND($D$1>=C27,$D$1<=D27),"CurrentSprint","NA") -> NA | B27: 14.4 M Sprint 2 | C27: 45639 | D27: 45666 | E27: 10 | F27: 16 | G27: 5 | I27: Maui- commited stories completed within the sprint target date | J27: Fixing Dotnet9 issues.
A28: =IF(AND($D$1>=C28,$D$1<=D28),"CurrentSprint","NA") -> NA | B28: 14.4 M Sprint 3 | C28: 45667 | D28: 45680 | E28: 12 | F28: 13 | G28: 12 | I28: Maui- commited stories completed. MSBP regression testing completed. Major defects found | J28: Continue to working on MAUI Stretch Stories | O28: 1
A29: =IF(AND($D$1>=C29,$D$1<=D29),"CurrentSprint","NA") -> NA | B29: 14.5 M Sprint 1 | C29: 45681 | D29: 45694 | E29: 12 | F29: 12 | G29: 28 | I29: Maui- Completed all committed stories and started working on stretch stories. Issues found were fixed and tested withing the sprint timeline | K29: Moving the status and logging time sheet and adding comments to the story before sprint planning | O29: 8
A30: =IF(AND($D$1>=C30,$D$1<=D30),"CurrentSprint","NA") -> NA | B30: 14.5 M Sprint 2 | C30: 45695 | D30: 45708 | E30: 21 | F30: 35 | G30: 14 | I30: Most of the committed stories completed, and one of the story is get delayed to due to tesing and bounce backs | J30: we can't run the code in iOS simulator or iOS device. we have bloker on this. | O30: 8
A31: =IF(AND($D$1>=C31,$D$1<=D31),"CurrentSprint","NA") -> NA | B31: 14.5 M Sprint 3 | C31: 45709 | D31: 45722 | E31: 21 | F31: 33.5 | G31: 2.5 | I31: Completed Regression testing. Team picked the defects from stretch and completed fixing those. Retesting completed for those defects. | O31: 14
A32: =IF(AND($D$1>=C32,$D$1<=D32),"CurrentSprint","NA") -> NA | B32: 14.6 M Sprint 1 | C32: 45723 | D32: 45740 | E32: 26.5 | F32: 52.88 | G32: 0 | I32: Completed the development and testing for the defects found and started finding issues in Maui as part of Maui regression(Post migration testing) | J32: Client has approved to work in Defects, considering the Migration to MAUI is done for Major Stories. Telerik CollectionView control is having some issues some of which are still open issues tickets. Hence we are migrating to native collection view and it is missing some features of Telerik control. So working on it to manully replicate the features in native control. Please Note: All the Defects found were logged directly to Commit. These defects were found during Post migration Maui Regression testing. | O32: 0
A33: =IF(AND($D$1>=C33,$D$1<=D33),"CurrentSprint","NA") -> NA | B33: 14.6 M Sprint 2 | C33: 45741 | D33: 45750 | E33: 14.5 | F33: 10.5 | G33: 0 | I33: Completed fixing and testing the Maui-Staging regression defects. Added camera support for Tickets Box office in MSBA | O33: 5
A34: =IF(AND($D$1>=C34,$D$1<=D34),"CurrentSprint","NA") -> NA | B34: 14.6 M Sprint 3 | C34: 45751 | D34: 45764 | E34: 5 | F34: 4.5 | G34: 0 | I34: Completed MSBP Xamarin regression testing. Worked on few MSB Anywhere stories and defects from the stretch | O34: 29.25
A35: =IF(AND($D$1>=C35,$D$1<=D35),"CurrentSprint","NA") -> NA | B35: 14.7 M Sprint 1 | C35: 45765 | D35: 45778 | E35: 3 | F35: 1 | G35: 2 | I35: Completed MSBP CA regression testing. Development completed for stories/defects from the stretch. updated the test cases for the stories under development. | J35: Due to app crash in iOS and android, testing was delayed by 1 day. later we found an workaround to test that. Now that issue has been fixed. Build issues in main brach caused delay in development. | O35: 7
A36: =IF(AND($D$1>=C36,$D$1<=D36),"CurrentSprint","NA") -> NA | B36: 14.7 M Sprint 2 | C36: 45779 | D36: 45792 | E36: 18.5 | F36: 18.5 | G36: 0 | I36: New requirement 'Family Pass' and 'Events' has been developed and tested successfully - Cross sell popup - Hooray screen - FP Payment method | J36: NA CRC Peer - 0, Onsite - 0, Client - 0. Internal Defect - 0, External Defect - 0. | O36: 2
A37: =IF(AND($D$1>=C37,$D$1<=D37),"CurrentSprint","NA") -> NA | B37: 14.7 M Sprint 3 | C37: 45793 | D37: 45806 | E37: 12 | F37: 7 | G37: 0 | I37: 1. Completed testing and development for MSBA Maui defects found during Xamarin to Maui conversion. | J37: Due to an iOS app crash, testing and development activities were blocked. The issue was brought up during daily standup and Sean was working on it. CRC Peer - 0, Onsite - 0, Client - 0. Internal Defect - 0, External Defect - 0. | O37: 0
A38: =IF(AND($D$1>=C38,$D$1<=D38),"CurrentSprint","NA") -> NA | B38: 15.0 M Sprint 1 | C38: 45807 | D38: 45820 | E38: 42 | F38: 23 | G38: 0 | I38: 1. Completed MSBA MAUI Regression defects 2.Regression testing completed for MSBP 14.7 Xamarin version 3.Smoke testing against prod environment completed for Xamarin - MSB Parent app - MSB Anywhere app - MSBP CA app | J38: 1.Defects were tested and closed at the end of the sprint as we were unable to test in IOS devices due to build issues in iOS. 2.This was fixed by Client dev. Client is already aware of these issues. CRC Peer - 3, Onsite - 0, Client - 0. Internal Defect - 0, External Defect - 0. | O38: 8
A39: =IF(AND($D$1>=C39,$D$1<=D39),"CurrentSprint","NA") -> NA | B39: 15.0 M Sprint 2 | C39: 45821 | D39: 45833 | E39: 28.5 | F39: 22 | G39: 0 | I39: Completed the below items 1. MSBA Maui defects. 2. MSBP Maui defects 3. MSBP CA regression 4. MSBA Xamarin Regression 5. Appium set up in iOS and Android | J39: CRC Peer - 0, Onsite - 0, Client - 0. Internal Defect - 0, External Defect - 0. | O39: 4
A40: =IF(AND($D$1>=C40,$D$1<=D40),"CurrentSprint","NA") -> NA | B40: 15.0 M Sprint 3 | C40: 45834 | D40: 45848 | E40: 40 | F40: 10 | G40: 0 | I40: Completed the below items 1. MSBP Maui Regression 2. Appium setup in iOS and android 3. Few automation stories development completed, waiting for client review. 4. MSBA Stretch stories completed. | J40: CRC Peer - 0, Onsite - 0, Client - 0. Internal Defect - 1, External Defect - 0. 1. Due to Firewall update, all domain request failed, API and Logins were not working. 2. Bottom sheet issue and Acceptance criteria for automation stories modified at the end of the sprint timeline RCA: Due to issues with Owen's environment and there is no proper framework, automation fails in Owen's system. Some of the framework are not reusable due to that which is causing delay in automation work. Fix: Needs a discussion with Ashwin and Owen on this. | K40: Internal 1. Environment setup for Automation 2. MAUI MSBP Regression 3. Started working on Automation stories 4. Completed MSBP Events story Needs Improvement - 1. Last minute AC update leads to delay in completiong automation stories. 2.Delays due to Peer review from Owen(Client) 3.Bottom sheet issues in iOS caused delay 4. Delay in setting up the environment in local | O40: 14
A41: =IF(AND($D$1>=C41,$D$1<=D41),"CurrentSprint","NA") -> NA | B41: 15.1 M Sprint 1 | C41: 45849 | D41: 45862 | E41: 38 | F41: 14 | G41: 0 | I41: Completed below items 1. CA MSBP Smoke Testing against Prod version 2. Few automation stories completed. 3. MSBA Maui coversion stories completed 4. Development completed for automation stories, client review is pending | J41: CRC Peer - 2, Onsite - 6, Client - 6. Internal Defect - 0, External Defect - 0. | K41: Internal 1. Framework re-build for Automation 2. New functionalities included as part of automation 3. Needs Improvement - 1. Last minute AC update/modification on requirement. 2.Delays due to Peer review from Owen(Client) 3.Bottom sheet issues in iOS caused delay | O41: 0
A42: =IF(AND($D$1>=C42,$D$1<=D42),"CurrentSprint","NA") -> NA | B42: 15.1 M Sprint 2 | C42: 45863 | D42: 45876 | E42: 46 | F42: 32 | G42: 0 | I42: "Completed below items 1. Completed the automation stories from main sprint | J42: CRC Peer - , Onsite - , Client - . Internal Defect - 0, External Defect - 0. Commited Stories: 15 Completed - 12 Being Developed - 1 Being Peer review - 2 (AC update and reviewed delayed) | O42: 0
A43: =IF(AND($D$1>=C43,$D$1<=D43),"CurrentSprint","NA") -> NA | B43: 15.1 M Sprint 3 | C43: 45877 | D43: 45890 | E43: 25 | F43: 14 | G43: 0 | H43: 1. In this sprint, we were focused on completing the pending automation stories. 2. No new automation stoires were picked as we were having many MSBA Maui Regression defects which needs to be fixed and tested. 3. Due to automation story 49019 which was not closed, we were unable to complete 2 automation stories which has the dependency with story 49019. 4. Development and testing completed for 10 MSBA MAUI defects. | I43: Completed below items 1. Automation stories stuffs going well. Able to completed most of the automation stories. 2. MSBA MAUI Regression defects were fixed and tested. | J43: CRC Peer - 2, Onsite - 1, Client - 1 Internal Defect - 0, External Defect - 3. Commited Stories/Defects: 10 Completed - 6 Being Developed - 1 Being Peer review - 3 (Due to dependency of story 49019, 2 automaiton stories were unable to complete) Completed Stretch Defects - 10 | K43: External (Needs Improvement) - 1. After completing the commited stories from main sprint then only we can pick the stretch stories/defects. 2. Focus on main commit defects/stories | O43: 21
A44: =IF(AND($D$1>=C44,$D$1<=D44),"CurrentSprint","NA") -> NA | B44: 15.2 M Sprint 1 | C44: 45891 | D44: 45904 | E44: 23 | F44: 20 | G44: 0 | H44: 1. In this sprint we focused on completing all the committed stories. Completed all the committed stories. 2. Pending automation stories were completed and approved by Client except 1 story which client review is pending 3. Completed all the MSBA/MSBP defect and stories 4. Worked on the defects and stories from the stretch | I44: 1. Completed all completed MSBA/MSBP defects 2. Automation stories completed 3. Picked defects from backlog and completed | J44: CRC Peer - , Onsite - 2, Client - 1 Internal Defect - 0, External Defect - . Total Commited Stories/Defects: 18 Completed - 17 Being Developed - 0 Being Peer review - 1 (Due to merging issue, Client is unable to run the automation script. Fixed the merging issue and sent for review) Completed Stretch Defects - 13 Completed Stretch Stories - 2 | K44: (External) 1. Axosoft hours needs to be done on daily basis. | O44: 18
A45: =IF(AND($D$1>=C45,$D$1<=D45),"CurrentSprint","NA") -> NA | B45: 15.2 M Sprint 2 | C45: 45905 | D45: 45918 | E45: 18.5 | F45: 18 | G45: 0 | H45: 1. In this sprint we focused on completing all the committed stories. Completed all the committed stories/defects 2. Completed all the MSBA/MSBP defect and stories 3. Worked on the defects and stories from the stretch | I45: 1. Completed all completed MSBA/MSBP defects 2. Automation stories from main commit completed 3. Picked defects from stretch/backlog and completed | J45: CRC Peer - , Onsite - , Client - Internal Defect - 0, External Defect - . Total Commited Stories/Defects: 16 Completed - 14 Rejected - 1 Being Tested - 1 (Defect was fixed by onsite developer and moved to testing at the end date of the sprint. Issue was not reproducible by Relevantz QA and Client QA. Only Jason from client was able to reproduce) Total Stretch Stories/Defects - 10 Completed Stretch Defects - 9 Blocked Stretch Defects - 1 | K45: (External) 1. Got appreciation from client for completing the committed stories/defects from last 2 sprints. 2. If Test MSB is down, use Dev MSB | O45: 21
A46: =IF(AND($D$1>=C46,$D$1<=D46),"CurrentSprint","NA") -> NA | B46: 15.2 M Sprint 3 | C46: 45919 | D46: 45932 | E46: 50.5 | F46: 50.5 | G46: 0 | H46: 1. In this sprint we focused on completing all the committed stories/regression defects. Completed all the committed stories/defects 2. Production defects were fixed by the offshore developers on time. | I46: 1. Testing and Development Completed for all the committed stories 2. Regression Testing completed. 3. Developers fixed the Production defect | J46: CRC Peer - , Onsite - 0, Client - 1 Internal Defect - 0, External Defect - 0, Regression Defects - 6 Total Commited Stories/Defects: 31 Completed - 28 Rejected - 1 Need more info - 1 Ready for testing - 1 Total Stretch Stories/Defects - 5 Under Development/Peer review - 5 | K46: (External) 1. Got appreciation from PM for Offshore on amazing progress and Sprint forecast & goal was basically SPOT ON. | O46: 0
A47: =IF(AND($D$1>=C47,$D$1<=D47),"CurrentSprint","NA") -> NA | B47: 15.3 M Sprint 1 | C47: 45933 | D47: 45946 | E47: 22.5 | F47: 18.5 | G47: 0 | H47: 1. In this sprint we focused on all the committed stories and defects. 2. Kickstarted the planning for MSBA Automation. created userstories for the automation. . 3. Stories/defects were developed and tested within the sprint 4. Team worked on the MSBP automation story from stretch | I47: 1. Testing and Development Completed for most of the committed stories 2. Planning completed for MSBA automation. 3. Defects fixed and tested | J47: CRC Peer - , Onsite - 2, Client - 2 Internal Defect - 2, External Defect - 0 Total Commited Stories/Defects: 13 Completed - 10 Need more info - 1 Peer Review - 2 Total Stretch Stories/Defects - 10 Under Development/Peer review - Completed - 5 Under Development - 4 Rejected - 1 . | K47: External - Needs Improvement 1. Needs to double check the bouncebacks before approving PR & sending to testing 2. Ashwin appreciated Sambath for helping work with offshore team on getting unblocked | O47: 6
A48: =IF(AND($D$1>=C48,$D$1<=D48),"CurrentSprint","NA") -> NA | B48: 15.3 M Sprint 2 | C48: 45947 | D48: 45960 | E48: 23.5 | F48: 20.5 | G48: 0 | H48: 1. In this sprint we focused on all the committed stories and defects. 2. Automation fixes for iOS completed. 3. Stories/defects were developed and tested within the sprint 4. Stretch defects/stories has been completed | I48: 1. Testing and Development Completed for most of the committed stories 2. Automation fixes for most of the workflow completed in MSBP Maui. 3. Defects fixed and tested | J48: CRC Peer - , Onsite -2 , Client - 2 Internal Defect - 0 , External Defect - 0 Total Commited Stories/Defects: 16 Completed - 12 Rejected: 2 Ready For testing: 1 Under development - 1 . Total Stretch Stories/Defects - 14 Under Development/Peer review - 2 Completed - 7 Under Development - 3 Need more info - 1 Ready for testing: 1 | K48: External 1. Jason appreciated Bavithra for co-ordinating the team on the automation story.. 2. Comments from Letashia"we have automation looking like its doing a good job covering with our recent fixes-" Internal: Automation failing randomly when run end to end in BS - Team is working on the fix for that issue. | O48: 12
A49: =IF(AND($D$1>=C49,$D$1<=D49),"CurrentSprint","NA") -> NA | B49: 15.3 M Sprint 3 | C49: 45961 | D49: 0 | E49: 28.5 | F49: 28.5 | G49: 0 | H49: 1. In this sprint we focused on completing the regression testing and fixing/testing the regression defects. 2. MSBAautomation stories were completed and approved by Client. Also merged to Main branch. 3. All regression defects were tested and closed within the sprint. 4. Worked on the defects and stories from the stretch. 5.Completed all the commited stories in this sprint | I49: 1. MSBAautomation stories were completed and approved by Client. Also merged to Main branch. 2. All regression defects were tested and closed within the sprint. 3.Completed all the commited stories in this sprint | J49: CRC Peer - , Onsite - , Client - Internal Defect - 0 , External Defect - 0 Total Commited Stories/Defects: 26 Completed - 25 Rejected: 1 Total Stretch Stories/Defects - 12 Under Development/Peer review - 1 Completed - 3 Under Development - 4 Need more info - 1 Rejected: 3 | K49: External Jason - So much work completed. Great team collab. Internal: Ashwin - Regression, Automation and MSBP App improvements | O49: 11.5
A50: =IF(AND($D$1>=C50,$D$1<=D50),"CurrentSprint","NA") -> NA | B50: 26.1 M Sprint 1 | C50: 45975 | D50: 45987 | E50: 16.5 | F50: 5.5 | G50: 0 | H50: 1. In this sprint we focused on completing the committed stories/defects. 2. Worked on MSBA Automation stories. 3. MSBP CA Regression testing completed 4. Worked on the defects and stories from the stretch. | I50: 1. Development completed for MSBAautomation stories 2. MSBP CA Regression testing completed 3. New enhancement stories were completed. 5. Defects from Main and stretch were completed. | J50: CRC Peer -1 , Onsite - 0, Client - 0 Internal Defect - 0 , External Defect - 0 Total Commited Stories/Defects: 11 Completed - 6 Under Development - 3 Under Peer reveiw - 1 Need more infor - 1 Total Stretch Stories/Defects - 11 Under Development/Peer review - 2 Completed - 5 Under Development - 4 | K50: External: Team Goal - Pair coding / Swarm coding (maintain focus + help others = finish faster & better quality) | O50: 5
A51: =IF(AND($D$1>=C51,$D$1<=D51),"CurrentSprint","NA") -> NA | B51: 26.1 M Sprint 2 | C51: 45988 | D51: 46002 | E51: 24.5 | F51: 21.5 | G51: 0 | H51: 1. In this sprint we focused on completing the committed stories/defects. 2. Worked on MSBA Automation story 3. New enhancembent stories were completed 4. Completed defects and stories from the stretch. | I51: 1. Development completed for MSBAautomation story 2. New enhancement stories were completed. 3. Defects /stories from Main and stretch were completed. | J51: CRC Peer -17 , Onsite - 1, Client - 37 Internal Defect - 0 , External Defect - 0 Total Commited Stories/Defects: 10 Completed - 8 Under Development - 1(due to bb this story was carried) Rejected - 1 Total Stretch Stories/Defects - 6 Under Development/Peer review - 1 Completed - 4 Under Development - 1 | K51: External: . 1.QA should not be going to dev management for clarification on testing criteria 2. Communication related to stories with client needs to be documented in the axosoft stories/defects 3.Team Goal: Pair coding / Swarm coding (maintain focus + help others = finish faster & better quality). 4.Double checking on bouncebacks before approving PR & sending to testing. | O51: 5.5
A52: =IF(AND($D$1>=C52,$D$1<=D52),"CurrentSprint","NA") -> NA | B52: 26.1 M Sprint 3 | C52: 46003 | D52: 46030 | E52: 41 | F52: 38 | G52: 0 | H52: 1. This is a one month sprint.We focused on completing all the committed stories/defects. 2. Worked on MSBA Automation story 3. MSBP .net10 package upgrade stories were completed. 4. MSBP Maui regression testing completed. . 5. MSBP CA Smoke testing completed. 6. MSBA Smoke testing completed. 7. Completed the new enhancement Tickets stories. | I52: 1. Completed MSBA Automation story 2. Completed MSBP .net10 package upgrade stories 3. Completed MSBP Maui regression testing . . 4. Completed MSBP CA Smoke testing . 5. Completed MSBA Smoke testing . 6. Completed the new enhancement Tickets stories. | J52: CRC Peer - 4, Onsite - 4, Client - 5 Internal Defect - 0 , External Defect - 0 Total Commited Stories/Defects: 16 Completed - 15 Under Development - 1 Total Stretch Stories/Defects: 1 Under Development - 1 (Defect picked for developement at the end day of the sprint, so it got carry forwarded) | K52: . (External) 1. Jason: Thank you to Bavithra for reviewing over 200 enhancement requests and assigning personas.. 2. Jason: We are making great progress on our big goals. Congrats to the team for getting MSBP Tickets in the state that it is, ready for 26.1 release. | O52: 0
A53: =IF(AND($D$1>=C53,$D$1<=D53),"CurrentSprint","NA") -> NA | B53: 26.3 M Sprint 1 | C53: 46031 | D53: 46044 | E53: 23.5 | F53: 21.5 | G53: 0 | H53: 1. MSBA .NET 10 package update completed successfully 2. Defects from main sprint has been fixed and tested 3. Started testing the the MSBP Kaleida stories 4. Defects and stories from stretch were completed 5. Smoke test of MSBA application after .net 10 package update completed | I53: 1. Completed MSBA .NET 10 package update 2. Completed development and testing of MSBA/MSBP Defects/stories from main sprint and stretch 3. Completed Smoke test of MSBA application after .net 10 package update 4. Started to work on Kaleida stories for parent ap | J53: CRC Peer - 1, Onsite -0 , Client - 1 Internal Defect - 0 , External Defect - 0 Total Commited Stories/Defects: 13 Completed - 10 Under Development - 2 ( Bounceback created and onsite developer is working on the fix). Blocked - 1 (testing blocked due to an another issue for which new defect will be created) Total Stretch Stories/Defects: 22 Completed - 10 .Under Development - 5 Ready For Testing - 2 Peer review - 2 Verified - 1 Rejected - 1 . Blocked - 1 | K53: (External) 1. Jason: Incredible amount of work completed. Improvement-Keep backlog refined & consistent storage location for all new things we’ll pull for Next Work and early notification of needed work to help keep in front of it and be able to refine if needed. | O53: 14.5
A54: =IF(AND($D$1>=C54,$D$1<=D54),"CurrentSprint","NA") -> NA | B54: 26.3 M Sprint 2 | C54: 46045 | D54: 46058 | E54: 21.5 | F54: 19.5 | G54: 0 | H54: 1. MSBP Kaleida stories were completed. 2. .net10 Defects from main sprint has been fixed and tested 3. New enhancement stories were completed. 4. Defects and stories from stretch were completed 5. Started development for MSBA Kaleida stories | I54: 1. Completed the Kaleida stories for MSBP. 2. Testing and development completed for .net10 Defects from main sprint 3. Completed the development and teting for the New enhancement stories 4. Completed Defects and stories from stretch | J54: CRC Peer - 1, Onsite -1 , Client - 4 Internal Defect - 0 , External Defect - 0 Total Commited Stories/Defects: 16 Completed - 15 Under Development - 1(51191 - This story was picked up on the end day of the sprint and moved to development phase due to an open bounceback. This is being worked by the Onsite developer) Total Stretch Stories/Defects: 17 Completed - 11 Under Development - 4 Peer review - 2 | K54: External: . 1. Ashwin – Good progress on MSBA Kaleida and defect fixes | O54: 19.5
A55: =IF(AND($D$1>=C55,$D$1<=D55),"CurrentSprint","NA") -> NA | B55: 26.3 M Sprint 3 | C55: 46059 | D55: 46072 | E55: 38 | F55: 22 | G55: 0 | H55: 1. MSBP - Full regression testing completed 2. MSBA - Smoke testing completed 3. MSBP CA - regression testing completed. 4. MSBA Kaleida enhancement stories completed. 5. Regression defects completed. 6. Team worked on the MSBA new enhancement Kaleida stories. | I55: 1. Completed MSBP - Full regression testing 2. CompletedMSBA - Smoke testing completed 3. CompletedMSBP CA - regression testing completed. 4. CompletedMSBA Kaleida enhancement stories completed. 5. Completed Regression defects completed. | J55: CRC Peer - 1, Onsite -1 , Client - 7 Internal Defect - 0 , External Defect - 0 Total Commited Stories/Defects: 18 Completed - 13 Need more info - 1 Rejected - 1 Being Tested - 1 (Deployment to prod was not happned due to which testing blocked). Peer review - 2 Total Stretch Stories/Defects: 5 Under Development - 1 Ready for Testing: 4 ( Moved to testing at the EOD of the sprint end date) | O55: 0
A56: =IF(AND($D$1>=C56,$D$1<=D56),"CurrentSprint","NA") -> NA | B56: 26.4 M Sprint 1 | C56: 46073 | D56: 46086 | E56: 39.5 | F56: 26.5 | H56: 1. MSBA - Regression defects fixed and tested. 2. MSBA Kaleida enhancement stories completed. 3. Stretch stories completed 4. Team worked on MSBA new enhancement Kaleida stories.. 5. Team worked on MSBP new enhancements stories as well. | I56: 1. Completed MSBA - Regression defects. 2. Completed MSBP defects. 3.MSBA Kaleida and MSBP enhancement stories completed. 4. Stretch stories completed | J56: CRC Peer - 0, Onsite -2 , Client - 7 Internal Defect - 0 , External Defect - 0 Total Commited Stories/Defects: 27 Completed - 23 Under Development - 4 Total Stretch Stories/Defects: 6 Completed - 3. Under Development - 1 Need more info: 2 | K56: AM: MSBA Kaleida is making good progress. Transaction history story passed without a BB! Which proves the additional dev test on multiple devices is helping. Also lots of defects fixed. AM – Figma occasionally still getting followed by dev more than AC. Has reminded Relevantz offshore team to follow AC more than Figma. Improvements - Has asked Relevantz offshore team to get on call/discuss with BA,QA,Dev to fully understand the AC for each of our work items. | O56: 10
A57: =IF(AND($D$1>=C57,$D$1<=D57),"CurrentSprint","NA") -> NA | B57: 26.4 M Sprint 2 | C57: 46087 | D57: 46100 | E57: 32 | F57: 24 | H57: 1.Team worked on MSBA Kaleida enhancement stories 2.MSBP CA 26.3 release smoke test in prod completed 3. MSBP US 26.3 release smoke test in prod completed 4. Worked on MSBA/MSBP regression defect 5.Smoke test of MSBP Kaleida merge into Main completed. | I57: 1.Completed MSBP CA 26.3 release smoke test in prod 2.Completed MSBP US 26.3 release smoke test in prod. 3.Completed the MSBA/MSBP regression defects 4.Smoke test of MSBP Kaleida merge into Main completed. 5.Team worked on the MSBA Kaleida enhancement stories. | J57: CRC Peer - 4, Onsite -3 , Client - 7 Internal Defect - 0 , External Defect - 0 Total Commited Stories/Defects: 19 Completed - 12 Under Development - 3 Peer review - 1 Rejected -3 Total Stretch Stories/Defects: 14 Completed - 6 Under Development - 1 Need more info -1 Approved - 3 (hours entered for test case update) Peer review - 3 . . | K57: What went well:​ (External)​ SJ – Offshore / Ashwin on task and implementing components & getting it to look good​ JM: Ashwin/Bavithra - keeping the lights on at night, keeping the team moving.​ JM: Bavithra – completed analysis for multiple WCAG things, got started early on VPAT too. ​ ​ ​ What Didn't go well: ​ - Settings story blowing out of proportion due to the kaleida common control changes​ Now not blocked on moving forward with controls. | O57: 8.5
A58: =IF(AND($D$1>=C58,$D$1<=D58),"CurrentSprint","NA") -> NA | B58: 26.04 M Sprint 3 | C58: 46101 | D58: 46114 | E58: 32 | F58: 29 | H58: 1.Team worked on MSBA Kaleida enhancement stories 2.MSBP Kaleida components stories completed 3. MSBP and MSBA Regression defects completed. | I58: 1.Team worked on MSBA Kaleida enhancement stories 2.Completed MSBP Kaleida components stories 3. Developmnet and testing completed for MSBP and MSBA Regression defects . 4. New enhancement MSBP Tickets season pass story completed. | J58: CRC Peer - 9, Onsite -1 , Client - 18 Internal Defect - 0 , External Defect - 0 Total Commited Stories/Defects: 33 Completed - 22 Under Development - 3 Peer review - 3 Rejected - 1 Being Tested - 1 Need more info - 2. Ready for testing - 1 Total Stretch Stories/Defects: 8 Completed - 3 Under Development - 3 Approved -1 Being Tested - 1 | K58: Retro not conducted due to absence of Product Manager | O58: 0
A59: =IF(AND($D$1>=C59,$D$1<=D59),"CurrentSprint","NA") -> NA | B59: 26.5 M Sprint 1 | C59: 46115 | D59: 46128 | E59: 33.5 | F59: 17.5 | G59: 0 | H59: 1.Team worked on MSBA Kaleida enhancement stories 2.MSBP CA 26.4 release smoke test completed 3. MSBP US 26.4 release smoke test in prod completed 4. MSBA - Smoke Test Against 26.4 Web RC 5.Completed the high priority regression defects for MSBA and MSBP | I59: 1.Completed MSBP CA 26.4 release smoke test in prod 2.Completed MSBP US 26.4 release smoke test in prod. 3.Completed the MSBA/MSBP regression defects 4.Team worked on the MSBA Kaleida enhancement stories. | J59: CRC Peer - 4, Onsite - 1, Client - 24 Internal Defect - 0 , External Defect - 0 Total Commited Stories/Defects: 24 Completed - 15 Under Development - 5 Peer review - 1 Being Tested - 2 Need more info - 1 Total Stretch Stories/Defects: 1 Under Development - 1 | K59: What went well:​ Ashwin - Good amount of regression defects fixed. Owen - QA channel for QA team to stay on top of things and Owen can answer when needed. Letashia - Got Beta out! What Didn't go well: ​ Letashia - we had a ton of carryover due to things not moving until the end of the sprint. This included stories that were estimated as “mostly testing” that had 0sp left by the time it reached testing.This adversely impacted the velocity tracking sheet. Additionally there were things marked for tomorrows release that seemed to be deprioritized behind Kaleida and Maui stories. Still struggling with missing AC things at times- there have been a lot of back and forth about what we are supposed to have in a story despite the increased details we have tried to put into each one Owen QA still has to log each of the things they find. Need to follow it and dive in for each (if it’s released to work). Improvements- - If we have development in flight which we have to put on hold in order to fix a high priority defect/story/escalation, we should move the Workflow Step to “Approved”, keep developer name assigned, and update the Status to “On Hold” with a comment in the story such as “I paused this in order to fix the high priority defect 1234”. - Try Live Pov video as a preference | L59: 3
A60: =IF(AND($D$1>=C60,$D$1<=D60),"CurrentSprint","NA") -> NA | B60: 26.5 M Sprint 2 | C60: 46129 | D60: 46142 | E60: 19 | F60: 26 | G60: 0 | H60: 1.Team worked on MSBA Kaleida enhancement stories 2. Worked on MSBA and MSBP defects 3. Completed few stories/defects from stretch | I60: 1.Completed the MSBA/MSBP defects 2.Development completed for MSBA Kaleida enhancement stories. . 3. | J60: CRC Peer -4 , Onsite - 1, Client - 3 Internal Defect - 6 , External Defect - 3 Total Commited Stories/Defects: 13 Completed - 12 Under development - 1 (this story being worked by Sean Onsite developer) Total Stretch Stories/Defects: 13 Under Development - 5 Completed - 5 Peer review - 2 PO Verify - 1 | K60: What went well:​ LJ- got through a lot of work (beta defects, release defects, Kaleida work) SJ – MSBA beta seems to be going well AM- Strong sprint. The coordination within the team was great. What Didn't go well: ​ NA Improvements- LJ- less release defects, either less changes after regression testing has been completed or more thorough view after so many extra changes are made to prevent catching it at the last minute LJ – Dev communicate with QA on if there are possibly other areas which might be affected on changes. Kudos - BS training went really well, great questions and participation Brags - JM: Bavithra learned Pendo – is currently tagging the MSBA App JM: MSBA Beta – going swell JM: VPAT is complete and we are further along now understanding Accessibility needs than before, and QA is trained on Browserstack as well.
A61: =IF(AND($D$1>=C61,$D$1<=D61),"CurrentSprint","NA") -> NA | B61: 26.5 M Sprint 3 | C61: 46143 | D61: 46156 | E61: 13 | F61: 22 | G61: 0 | H61: 1.Team worked on MSBA Kaleida enhancement stories 2. Worked on MSBA and MSBP defects 3. Completed high priority stories/defects from stretch. 4. Worked on MSBP Regression testing | I61: 1.Completed the MSBA/MSBP defects 2.Team worked on the MSBA Kaleida enhancement stories. | J61: CRC Peer -5 , Onsite - 0, Client - 5 Internal Defect - 0 , External Defect - 0 Total Commited Stories/Defects: 9 Completed - 7 Under development - 2 (One defect worked by Onsite developer) Total Stretch Stories/Defects: 14 Blocked - 1 Completed - 1 Peer review - 3 Ready for testing- 7. Being tested - 2 | K61: What went well:​ JM: So much – appreciate the flexibility with the Beta/test flight. AM: Communication between offshore and Avery has been good to resolve the Kaleida control issues and updates What Didn't go well: ​ NA Improvements- LJ- Dev/QA balance (this sprint is looking much better) Kudos - CR – Letashia & QA team for hanging in there Brags - MSBA GA – let's not count our chickens yet but I mean...the plan seems solid! Customers are reporting that things are working well. No major issues or reasons to NOT GA. | P61: 10
A62: =IF(AND($D$1>=C62,$D$1<=D62),"CurrentSprint","NA") -> NA | B62: 26.7 M Sprint 1 | C62: 46157 | D62: 46170

Sheet Defect-template
A1: S.No | B1: Sprint # | C1: Story/Defect ID | D1: Parent Story | E1: Developer | F1: Issue Type | G1: Issue Description | H1: Priority | I1: Defect Source | J1: Type | K1: Status | L1: Root Cause Category | M1: Comments

Sheet Unplanned Leaves
A1: Total Leaves | B1: =SUM(B21:J21) -> 12
B2: Resource Name
A3: Sprint | B3: Amrit Pal Harjit Singh | C3: Ashwin Majella | D3: Bavithra Arasakumaran | E3: Gursewak Singh Jaspal Singh | F3: Jagdeep Singh | G3: Premkumar Rajendran | H3: Rupesh Kumar | I3: Sambath Selvam | J3: Vaishnavi Shanmugavel | K3: Remarks
A4: 26.3 M Sprint 2 (23-Jan-2026 to 5-Feb-2026) | B4: 1 | C4: 0 | D4: 0 | E4: 0 | F4: 0 | G4: 0 | H4: 0 | I4: 0 | J4: 1 | K4: 27-Jan-26 Vaishnavi - well its planned but updated at the last minute so it is unplanned leave in Leave tracker, 29-Jan-26 Amrit took sick leave
A5: 26.4 M Sprint 1 (20-Feb-2026 to 05-Mar-2026) | B5: 0 | C5: 0 | D5: 0 | E5: 1 | F5: 0 | G5: 0 | H5: 0 | I5: 0 | J5: 0 | K5: 9-Feb-26 Gursewak took the leave for family emergency.
A6: 26.3 M Sprint 3 (06-Feb-2026 to 19-Feb-2026) | B6: 0 | C6: 1 | D6: 0 | E6: 0 | F6: 0 | G6: 0 | H6: 0 | I6: 0 | J6: 0 | K6: 14 Feb - Ashwin Sick leave
A7: 26.4 M Sprint 1 (20-Feb-2026 to 05-Mar-2026) | B7: 0 | C7: 1 | D7: 1 | E7: 0 | F7: 0 | G7: 1 | H7: 0 | I7: 0 | J7: 0 | K7: 27 Feb - Ashwin Sick Leave, 3 Mar - Bavithra emergency leave met with small accident, Prem Sick leave.
A8: 26.4 M Sprint 3 (20-Mar-2026 to 02-Apr-2026) | B8: 0 | C8: 0 | D8: 1 | E8: 0 | F8: 0 | G8: 0 | H8: 0 | I8: 1 | J8: 0 | K8: 30 Mar - Bavithra Sick leave and Sambath network issue.
A9: 26.5 M Sprint 1 (03-Apr-2026 to 16-Apr-2026) | B9: 1 | C9: 0 | D9: 0 | E9: 0 | F9: 0 | G9: 1 | H9: 0 | I9: 0 | J9: 1 | K9: 6th Apr - Vaishnavi sick leave, 10th Apr - Prem Sick Leave 9th Apr- Amrit Unplanned sick leave
A21: Total | B21: =SUM(B4:B20) -> 2 | C21: =SUM(C4:C20) -> 2 | D21: =SUM(D4:D20) -> 2 | E21: =SUM(E4:E20) -> 1 | F21: =SUM(F4:F20) -> 0 | G21: =SUM(G4:G20) -> 2 | H21: =SUM(H4:H20) -> 0 | I21: =SUM(I4:I20) -> 1 | J21: =SUM(J4:J20) -> 2 | K21: =SUM(K5:K20) -> 0

Sheet 26.7 M Sprint 1-Status
A1: S.No | B1: Application Name | C1: Sprint Start Date | D1: Sprint End Date | E1: Sprint | F1: Developer | G1: Story ID/Defect ID | H1: Description | I1: Status | J1: Estimated(sp) | K1: Actual(sp) | L1: Actual Hours Worklog | M1: Dev Start Date | N1: Dev End Date | O1: Unit testing | P1: Peer Tested By | Q1: Peer Tested Defects, if any | R1: Peer Reviewed By | S1: Peer Code Review Comments, if any | T1: PR Number/Link | U1: PR Created Date | V1: PR Approved Date | W1: Reviewer 1 | X1: Code Review Comments, if any | Y1: Reviewer 2 | Z1: Approved Date | AA1: Code Review Comments, if any2 | AB1: Internal PO -POV Comments | AC1: Client PO -POV Comments | AD1: Comments | AE1: Does this story meet the expectations? | AF1: Comments | AG1: Sprint Tag
A2: 1 | B2: MSB Mobile | C2: 46143 | D2: 46156 | E2: 26.7 M Sprint 1 | F2: chandler/vaishnavi/ | G2: 27320 | H2: 27320 MSBP - Android - All text and sizes are inflated on pixel pro devices, sometimes pushing items off viewable area (26.5) | I2: Defect Being Tested | M2: NA | N2: NA | O2: NA | P2: NA | Q2: NA | R2: NA | S2: NA | T2: NA | U2: NA | V2: NA | W2: NA | X2: NA | Y2: NA | Z2: NA | AA2: NA | AB2: NA | AC2: NA | AD2: 15-May - chandler working on the fix.
A3: 2 | B3: MSB Mobile Kaleida | C3: 46157 | D3: 46170 | E3: 26.7 M Sprint 1 | F3: Jagdeep/vaishnavi | G3: 52343 | H3: [WAVE] MSBA - Kaleida - Update Offset Language - Difference(Over/Short) | I3: Story Being Tested | M3: 46147 | N3: 46148 | O3: NA | P3: Amrit/Vashnavi | Q3: NA | R3: Rupesh/Sambath | S3: NA | T3: https://dev.azure.com/heartlandschools/Mobile/_git/MSBA.MAUI/pullrequest/48842 | U3: 46147 | V3: 46149 | W3: Ashwin | X3: NA | Y3: Avery | Z3: 46149 | AA3: NA | AB3: POV done with Bavithra No Comment | AC3: POV done with Jason No Comment | AD3: 15-May- will work on the testing
A4: 3 | B4: MSB Mobile | C4: 46157 | D4: 46170 | E4: 26.7 M Sprint 1 | F4: Amrit/Gursewak | G4: 27283 | H4: MSBA - MAUI - iOS- meal payments screen changing formatting when cart preview is on with items in it | I4: Defect Ready For Testing | M4: 46150 | N4: 46153 | O4: NA | P4: Gursewak | Q4: Yes | R4: Rupesh/Sambath | S4: NA | T4: https://dev.azure.com/heartlandschools/Mobile/_git/MSBA.MAUI/pullrequest/48972 | U4: 46153 | V4: NA | W4: NA | X4: NA | Y4: NA | Z4: Na | AA4: NA | AB4: POV done with Bavithra No Comment | AC4: NA | AD4: 14 May - PR Pending from Ashwin and Client Side 15 May - Defect ready for testing
A5: 4 | B5: MSB Mobile Kaleida | C5: 46157 | D5: 46170 | E5: 26.7 M Sprint 1 | F5: Jagdeep | G5: 27276 | H5: MSBP - Android - Can double click and open multiple stacks of menus | I5: Defect Ready For Testing | M5: 46148 | N5: 46150 | O5: NA | P5: Gursewak | Q5: NA | R5: Rupesh/Sambath | S5: NA | T5: https://dev.azure.com/heartlandschools/Mobile/_git/MSBP.MAUI/pullrequest/48903 | U5: 46149 | V5: 46155 | W5: Ashwin | X5: NA | Y5: Avery | Z5: 46155 | AA5: NA | AB5: POV done with Bavithra No Comment | AC5: NA | AD5: Will pick this after completing the MSBA, MSBP CA, MSBP smoke tests
A6: 5 | B6: MSB Mobile Kaleida | C6: 46157 | D6: 46170 | E6: 26.7 M Sprint 1 | F6: Gursewak/Prem | G6: 27015 | H6: MSBA - MAUI - iphone - invoice add to cart button not formatted correctly (regression) | I6: Defect Fixed | M6: 46150 | N6: 46150 | O6: NA | P6: Yes | Q6: NA | R6: Rupesh/Sambath | S6: NA | T6: https://dev.azure.com/heartlandschools/Mobile/_git/MSBA.MAUI/pullrequest/48924 | U6: 46150 | V6: 46150 | W6: NA | X6: NA | Y6: NA | Z6: NA | AA6: NA | AB6: POV done with Bavithra No Comment | AC6: NA | AD6: Will pick this after completing the MSBA, MSBP CA, MSBP smoke tests 15 May - Testing completed
A7: 6 | B7: MSB Mobile | C7: 46157 | D7: 46170 | E7: 26.7 M Sprint 1 | F7: Amrit | G7: 27006 | H7: MSBA - MAUI - iOS - Cart has extra space underneath buttons (regression) | I7: Defect Ready For Testing | M7: 46150 | N7: 46153 | O7: NA | P7: Gursewak | Q7: Yes | R7: Rupesh/Sambath | S7: NA | T7: https://dev.azure.com/heartlandschools/Mobile/_git/MSBA.MAUI/pullrequest/48926 | U7: 46153 | V7: NA | W7: NA | X7: NA | Y7: NA | Z7: NA | AA7: NA | AB7: POV done with Ashwin No Comment | AC7: NA | AD7: 14 May - PR Pending from Ashwin and Client Side 15 May - Defect ready for testing
A8: 7 | B8: MSB Mobile Kaleida | C8: 46157 | D8: 46170 | E8: 26.7 M Sprint 1 | F8: Jagdeep | G8: 27255 | H8: MSBP - missing phone number page and profile phone pages do not match | I8: Defect Peer Review | M8: 46150 | N8: 46153 | O8: NA | P8: Amrit | Q8: NA | R8: Rupesh | S8: NA | T8: https://dev.azure.com/heartlandschools/Mobile/_git/MSBP.MAUI/pullrequest/49015 | U8: 46153 | V8: NA | W8: NA | X8: NA | Y8: NA | Z8: NA | AA8: NA | AB8: POV done with Bavithra No Comment | AC8: NA | AD8: 15 May - Waiting for aproval from Ashwin and Client side.
A9: 8 | B9: MSB Mobile Kaleida | C9: 46157 | D9: 46170 | E9: 26.7 M Sprint 1 | F9: Gursewak | G9: 26881 | H9: MSBA - Cart icon/badge is larger than expected (regression) | I9: Defect Ready For Testing | M9: 46150 | N9: 46153 | O9: NA | P9: Yes | Q9: NA | R9: Rupesh/Sambath | S9: NA | T9: https://dev.azure.com/heartlandschools/Mobile/_git/MSBA.MAUI/pullrequest/48932 | U9: 46153 | V9: 46153 | W9: NA | X9: NA | Y9: NA | Z9: NA | AA9: NA | AB9: POV done with Bavithra No Comment | AC9: NA | AD9: 15 May- Merged, ready for testing.
A10: 9 | B10: MSB Mobile | C10: 46157 | D10: 46170 | E10: 26.7 M Sprint 1 | F10: Vaishnavi/Prem | G10: 53092 | H10: REG - MSBP - Regression 26.5 | I10: Story Being Tested | M10: NA | N10: NA | O10: NA | P10: NA | Q10: NA | R10: NA | S10: NA | T10: NA | U10: NA | V10: NA | W10: NA | X10: NA | Y10: NA | Z10: NA | AA10: NA | AB10: NA | AC10: NA | AD10: Work on the invoice push notificaiton test cases
A11: 10 | B11: MSB Mobile | C11: 46157 | D11: 46170 | E11: 26.7 M Sprint 1 | F11: Rupesh/Vaishnavi | G11: 27394 | H11: MSBA - stock option formatting issues (regression) | I11: Defect Being Tested | M11: 46155 | AD11: WIll start the testing.
A12: 12 | B12: MSB Mobile Kaleida | C12: 46157 | D12: 46170 | E12: 26.7 M Sprint 1 | F12: Prem | G12: 53090 | H12: MSBP CA - Regression/Smoke Test Against Staging 26.5 RC | I12: Story Being Tested | J12: 1 | M12: NA | N12: NA | O12: NA | P12: NA` | Q12: NA | R12: NA | S12: NA | T12: NA | U12: NA | V12: NA | W12: NA | X12: NA | Y12: NA | Z12: NA | AA12: NA | AB12: NA | AC12: NA | AD12: 15 May - Testing is in Progress
A13: 13 | B13: MSB Mobile | C13: 46157 | D13: 46170 | E13: 26.7 M Sprint 1 Stretch | F13: Amrit/Prem | G13: 52344 | H13: [WAVE] MSBA - Update Components/Fonts to Kaleida - Hamburger Menu | I13: Story Ready For Testing | M13: 46132 | N13: 46134 | O13: NA | P13: Jagdeep | Q13: NA | R13: Jagdeep | S13: NA | T13: https://dev.azure.com/heartlandschools/Mobile/_git/MSBA.MAUI/pullrequest/48532 | U13: 46138 | V13: 46140 | W13: Sambath | X13: NA | Y13: Avery | Z13: 46140 | AA13: NA | AB13: POV done with Bavithra No Comment | AC13: NA | AD13: After completing the main commit stories/defects will work on these stories
A14: 14 | B14: MSB Mobile Kaleida | C14: 46157 | D14: 46170 | E14: 26.7 M Sprint 1 Stretch | F14: Gursewak | G14: 52346 | H14: [WAVE] MSBA - Update Components/Fonts to Kaleida - Header | I14: Story Ready For Testing | M14: 46133 | N14: 46142 | O14: NA | P14: Yes | Q14: NA | R14: Rupesh/Sambath | S14: Total Comments: 3 Rupesh Kumar (1 Comment) Please use static resource color from Kaleida. Sambath Selvam (2 Comments) Remove default value properties. Remove RowSpacing="0". | T14: https://dev.azure.com/heartlandschools/Mobile/_git/MSBA.MAUI/pullrequest/48736 | U14: 46142 | V14: 46142 | W14: Ashwin | X14: NA | Y14: Avery | Z14: 46148 | AA14: Total Comments: 5 Avery Wold (5 Comments) Remove this since Demo Mode is not used. Use "K" colors – KAppHeaderBackgroundColor. Fix KCircleButton property mismatch and incorrect styling. Use correct "K" color – KChipBackgroundColor. Remove unnecessary CornerRadius (handled by KCircleButton). Do not hardcode Black; use KPrimaryTextColor. | AB14: POV done with Bavithra No Comment | AC14: POV done with Jason No Comment | AD14: After completing the main commit stories/defects will work on these stories
A15: 15 | B15: MSB Mobile | C15: 46157 | D15: 46170 | E15: 26.7 M Sprint 1 Stretch | F15: Sambath | G15: 52347 | H15: 52347 [WAVE] MSBA - Update Components/Fonts to Kaleida - Transaction History | I15: Story Ready For Testing | M15: 46133 | N15: 46146 | O15: NA | P15: Rupesh | Q15: NA | R15: Rupesh | S15: remove the default value properties | T15: https://dev.azure.com/heartlandschools/Mobile/_git/MSBA.MAUI/pullrequest/48726 | U15: 46146 | V15: 46146 | W15: NA | X15: NA | Y15: Avery | Z15: 46153 | AA15: Count (10) Exiting Code:Shell.Current.DisplayAlertAsync changed to DialogService.ShowDialogAsync(), this is new change has added by avery (16). Exiting Code:Naming convension changed to ShowHideAdminLoginModalCommand instead of ShowHideBarcodeModalCommand (2) New change : Loading Inidicator changes, that is new changes (4) Kcolor missed in two places (2). Exiting Code:Font size removed from all Kcontrol, it take default font size from K library (21) KButton has been repalced with KIconButton (1) New change :Custom ItemTemplate was removed, instead used New KListTile control (1). Exiting Code:Image control has been replaced with Klable to show the icon only option (1) Exiting Code: For consistency with other buttons change this to HeightRequest="44" (2) Exiting Code:exiting EmailRefundPopup Code has been refacored based on avery suggesion (10). | AB15: POV Done | AD15: After completing the main commit stories/defects will work on these stories
A16: 16 | B16: MSB Mobile | C16: 46157 | D16: 46170 | E16: 26.7 M Sprint 1 Stretch | F16: Rupesh/Prem | G16: 52348 | H16: [WAVE] MSBA - Update Components/Fonts to Kaleida - Forgot Login Workflow | I16: Story Ready For Testing | M16: 46134 | N16: NA | O16: NA | P16: Jagdeep | Q16: NA | R16: Jagdeep/Sambath | S16: NA | T16: https://dev.azure.com/heartlandschools/Mobile/_git/MSBA.MAUI/pullrequest/48656 | U16: 46139 | V16: 46146 | W16: Ashwin | X16: NA | Y16: Avery | Z16: 46148 | AA16: Comments - 14 This should be using the Kaleida component(For BG image). - 5 Get rid of this since we do not have Demo mode - 5 KHeader is already defaulted to use KPrimaryColor, no need to add this." - 1 KHeader is already Bold, no need to add this - 1 This should probably be a KHeader(KLabel was used):- 1 Get rid of this old style and consider using the KHeader (Old style was used as it was before)- 6 This should probably be a KCircleButton(This was a Klabel ) - 3 This is the default, adding this is redundant - 9 Consider using the KLabelFootnote style for consistency.(Label was used) - 1 This is overcomplicated, can be simplified - 4 if this needs to be a Header based on the old style still attached consider using a KHeader, otherwise this could be simplified : - 1 This is not a phonenumber field and the name here should be updated to reflect that(This was existing one)- 1 KPasswordField has a build in error message, simplify it- 4 | AB16: POV done with Ashwin No Comment | AC16: NA | AD16: After completing the main commit stories/defects will work on these stories
A17: 17 | B17: MSB Mobile | C17: 46157 | D17: 46170 | E17: 26.7 M Sprint 1 | F17: Rupesh | G17: 27406 | H17: MSBA - Shift Mode - Unable to Start Shift - Errors with Starting Shifts | I17: Defect Found | J17: 3 | M17: 46157
A18: 18 | B18: MSB Mobile Kaleida | C18: 46157 | D18: 46170 | E18: 26.7 M Sprint 1 | F18: Gursewak | G18: 53208 | H18: MSBA - TECH DEBT - Unit Tests - Update to .NET10 | I18: Story Being Developed | J18: 3 | M18: 46157 | AD18: 15 May - start working on it.
A19: 19 | B19: MSB Mobile Kaleida | C19: 46157 | D19: 46170 | E19: 26.7 M Sprint 1 | F19: Jagdeep | G19: 53209 | H19: MSBP - TECH DEBT - Unit Tests - Update to .NET10 | I19: Story Being Developed | J19: 3 | M19: 46157 | N19: NA | O19: NA | P19: NA` | Q19: NA | R19: NA | S19: NA | T19: NA | U19: NA | V19: NA | W19: NA | X19: NA | Y19: NA | Z19: NA | AA19: NA | AB19: NA | AC19: NA | AD19: 15 May - start working on it. | AG19: Main

Sheet 26.5 M Sprint 3-Status
A1: S.No | B1: Application Name | C1: Sprint Start Date | D1: Sprint End Date | E1: Sprint | F1: Developer | G1: Story ID/Defect ID | H1: Description | I1: Status | J1: Estimated(sp) | K1: Actual(sp) | L1: Actual Hours Worklog | M1: Dev Start Date | N1: Dev End Date | O1: Unit testing | P1: Peer Tested By | Q1: Peer Tested Defects, if any | R1: Peer Reviewed By | S1: Peer Code Review Comments, if any | T1: PR Number/Link | U1: PR Created Date | V1: PR Approved Date | W1: Reviewer 1 | X1: Code Review Comments, if any | Y1: Reviewer 2 | Z1: Approved Date | AA1: Code Review Comments, if any2 | AB1: Internal PO -POV Comments | AC1: Client PO -POV Comments | AD1: Comments | AE1: Does this story meet the expectations? | AF1: Comments | AG1: Sprint Tag
A2: 2 | B2: MSB Mobile | C2: 46143 | D2: 46156 | E2: 26.5 M Sprint 3 Stretch | F2: Amrit/Prem | G2: 52344 | H2: [WAVE] MSBA - Update Components/Fonts to Kaleida - Hamburger Menu | I2: Story Ready For Testing | J2: 3 | L2: 8.5 | M2: 46132 | N2: 46134 | O2: NA | P2: Jagdeep | Q2: NA | R2: Jagdeep | S2: NA | T2: https://dev.azure.com/heartlandschools/Mobile/_git/MSBA.MAUI/pullrequest/48532 | U2: 46138 | V2: 46140 | W2: Sambath | X2: NA | Y2: Avery | Z2: 46140 | AA2: NA | AB2: POV done with Bavithra No Comment | AC2: NA | AD2: 04,05-may- Amrit PTO 6 May - Space issue InProgress for small devices android, Transaction history crash is being fixed by sambath in different PR 7 May - Transaction History Sambath PR is in Review, Space Issue we are not doing as discussed with client. 8 May - Waiting for Sambath PR to be merged for transaction history PR. 11 May - Story Moved to Need more info its pending until 52347 is merged 12 May - Story ready for testing 52347 is merged | AE2: Exceeds Expectation | AF2: Due to regression testing and other high priority defects/stories, this story was not picked up by the tester | AG2: Stretch
A3: 4 | B3: MSB Mobile Kaleida | C3: 46143 | D3: 46156 | E3: 26.5 M Sprint 3 Stretch | F3: Gursewak | G3: 52346 | H3: [WAVE] MSBA - Update Components/Fonts to Kaleida - Header | I3: Story Ready For Testing | J3: 2 | L3: 4 | M3: 46133 | N3: 46142 | O3: NA | P3: Yes | Q3: NA | R3: Rupesh/Sambath | S3: Total Comments: 3 Rupesh Kumar (1 Comment) Please use static resource color from Kaleida. Sambath Selvam (2 Comments) Remove default value properties. Remove RowSpacing="0". | T3: https://dev.azure.com/heartlandschools/Mobile/_git/MSBA.MAUI/pullrequest/48736 | U3: 46142 | V3: 46142 | W3: Ashwin | X3: NA | Y3: Avery | Z3: 46148 | AA3: Total Comments: 5 Avery Wold (5 Comments) Remove this since Demo Mode is not used. Use "K" colors – KAppHeaderBackgroundColor. Fix KCircleButton property mismatch and incorrect styling. Use correct "K" color – KChipBackgroundColor. Remove unnecessary CornerRadius (handled by KCircleButton). Do not hardcode Black; use KPrimaryTextColor. | AB3: POV done with Bavithra No Comment | AC3: POV done with Jason No Comment | AD3: 04 May - PR review pending from Sambath, Ashwin,client side. 05 May - Client review pending. 06 May - Avery added some comments, start working on it, will test and update the PR. 06 May - EOD - Ready for test.. 08-May- QA team working on the main commit defects/stories follwed by regression testing. | AE3: Exceeds Expectation | AF3: Due to regression testing and other high priority defects/stories, this story was not picked up by the tester | AG3: Stretch
A4: 5 | B4: MSB Mobile | C4: 46143 | D4: 46156 | E4: 26.5 M Sprint 3 Stretch | F4: Sambath | G4: 52347 | H4: 52347 [WAVE] MSBA - Update Components/Fonts to Kaleida - Transaction History | I4: Story Ready For Testing | J4: 8 | L4: 35 | M4: 46133 | N4: 46146 | O4: NA | P4: Rupesh | Q4: NA | R4: Rupesh | S4: remove the default value properties | T4: https://dev.azure.com/heartlandschools/Mobile/_git/MSBA.MAUI/pullrequest/48726 | U4: 46146 | V4: 46146 | W4: NA | X4: NA | Y4: Avery | Z4: 46153 | AA4: Count (10) Exiting Code:Shell.Current.DisplayAlertAsync changed to DialogService.ShowDialogAsync(), this is new change has added by avery (16). Exiting Code:Naming convension changed to ShowHideAdminLoginModalCommand instead of ShowHideBarcodeModalCommand (2) New change : Loading Inidicator changes, that is new changes (4) Kcolor missed in two places (2). Exiting Code:Font size removed from all Kcontrol, it take default font size from K library (21) KButton has been repalced with KIconButton (1) New change :Custom ItemTemplate was removed, instead used New KListTile control (1). Exiting Code:Image control has been replaced with Klable to show the icon only option (1) Exiting Code: For consistency with other buttons change this to HeightRequest="44" (2) Exiting Code:exiting EmailRefundPopup Code has been refacored based on avery suggesion (10). | AB4: POV Done | AD4: i have to run the POV with client, 07-May - Resolving merge conflicts, testing the app 08-May - Found some issue in KPopup and checked with avery, he modifed in library and i need to work updating the new Kpopup feature into app. 11- May - Working with code review changes 12- it is moved to ready for testing | AE4: Meets Expectation | AF4: Due to regression testing and other high priority defects/stories, this story was not picked up by the tester 14-May -26 - This story only covers Kcontrol and font and kcolor changes, but I also worked on other code refactor changes based on Avery’s suggestions. We need to plan what changes are included in this story, because if we spend time on items outside the AC, it will take longer and lead to more review comments | AG4: Stretch
A5: 6 | B5: MSB Mobile | C5: 46143 | D5: 46156 | E5: 26.5 M Sprint 3 Stretch | F5: Rupesh/Prem | G5: 52348 | H5: [WAVE] MSBA - Update Components/Fonts to Kaleida - Forgot Login Workflow | I5: Story Ready For Testing | J5: 3 | L5: 6 | M5: 46134 | N5: NA | O5: NA | P5: Jagdeep | Q5: NA | R5: Jagdeep/Sambath | S5: NA | T5: https://dev.azure.com/heartlandschools/Mobile/_git/MSBA.MAUI/pullrequest/48656 | U5: 46139 | V5: 46146 | W5: Ashwin | X5: NA | Y5: Avery | Z5: 46148 | AA5: Comments - 14 This should be using the Kaleida component(For BG image). - 5 Get rid of this since we do not have Demo mode - 5 KHeader is already defaulted to use KPrimaryColor, no need to add this." - 1 KHeader is already Bold, no need to add this - 1 This should probably be a KHeader(KLabel was used):- 1 Get rid of this old style and consider using the KHeader (Old style was used as it was before)- 6 This should probably be a KCircleButton(This was a Klabel ) - 3 This is the default, adding this is redundant - 9 Consider using the KLabelFootnote style for consistency.(Label was used) - 1 This is overcomplicated, can be simplified - 4 if this needs to be a Header based on the old style still attached consider using a KHeader, otherwise this could be simplified : - 1 This is not a phonenumber field and the name here should be updated to reflect that(This was existing one)- 1 KPasswordField has a build in error message, simplify it- 4 | AB5: POV done with Ashwin No Comment | AC5: NA | AD5: 04 May : POV’d by Jason, I have published the PR for review. 05 May : Client approval is pending. Received pr comments , resolved and sent them back for review. 08 - QA team working on the main commit defects/stories follwed by regression testing. 08 May - Testing is in Progress 11 May - Tested and Raised a BB.And assigned back to dev to fix the same 12 May - Received some BB’s related to Primary button, I connected with Avery and he made some changes, need to pull Kaleida and test it and if everything looks okay, will raise the PR. | AE5: Exceeds Expectation | AF5: Due to regression testing and other high priority defects/stories, this story was not picked up by the tester | AG5: Stretch
A6: 9 | B6: MSB Mobile Kaleida | C6: 46143 | D6: 46156 | E6: 26.5 M Sprint 3 | F6: Amrit/Vaishnavi | G6: 52633 | H6: MSBP - Store Catalog - General header changed to Products | I6: Story Completed | J6: 1 | L6: 4 | M6: 46139 | N6: 46139 | O6: NA | P6: Jagdeep | Q6: NA | R6: Rupesh/Sambath | S6: NA | T6: https://dev.azure.com/heartlandschools/Mobile/_git/MSBP.MAUI/pullrequest/48662 | U6: 46139 | V6: 46139 | W6: Ashwin | X6: NA | Y6: Avery | Z6: 46142 | AA6: NA | AB6: POV done with Bavithra No Comment | AC6: NA | AD6: 4-May-Will be starting the testing. | AE6: Exceeds Expectation | AG6: Main
A7: 12 | B7: MSB Mobile Kaleida | C7: 46143 | D7: 46156 | E7: 26.5 M Sprint 3 | F7: Amrit/Vaishnavi | G7: 26882 | H7: MSBA - Cart Icon does not have the correct MSBA blue background | I7: Defect Fixed | J7: 1 | L7: 4 | M7: 46141 | N7: 46141 | O7: NA | P7: Rupesh | Q7: NA | R7: Rupesh/Sambath | S7: NA | T7: https://dev.azure.com/heartlandschools/Mobile/_git/MSBA.MAUI/pullrequest/48721 | U7: 46142 | V7: 46142 | W7: Ashwin | X7: NA | Y7: NA | Z7: 46142 | AA7: NA | AB7: POV done with Bavithra No Comment | AC7: NA | AD7: 4-May-Will be starting the testing. | AE7: Exceeds Expectation | AG7: Main
A8: 13 | B8: MSB Mobile | C8: 46143 | D8: 46156 | E8: 26.5 M Sprint 3 | F8: Rupesh/Vaishnavi | G8: 52964 | H8: MSBA - Admin Settings - BETA build - Require Elevated Privileges | I8: Story Completed | J8: 3 | L8: 18 | M8: 46141 | N8: 46153 | O8: NA | P8: Jagdeep | Q8: NA | R8: Jagdeep/Sambath | S8: Can we use StaticResource colors instead of hardcoded value. | T8: https://dev.azure.com/heartlandschools/Mobile/_git/MSBA.MAUI/pullrequest/48865 | U8: 46148 | V8: 46148 | W8: Ashwin | X8: NA | Y8: Avery | Z8: 46150 | AA8: Comments - 3 -This array is duplicated from ViewModelBase.cs Add a protected helper method to ViewModelBase for consistency -This is missing an await -The ApplyPendingChange() and RevertPendingChange() methods add ~200 lines - Instead consider simpler approach. | AB8: POV done with Bavithra No Comment | AC8: NA | AD8: 04 May : Other day, I had a plan to do the POV, however during UT, i found some issue, so will be working on that issue and then will run the POV. 05 May : Found some issue during peer testing, will be fixing those. 06 May : did the POV both internal and external and raised the PR.. 07-Vaishnavi- Will be updating the test cases for this story 08 - Received few comment from Avery, will resolve it today. 11 May - Receive one BB, will be working on that. | AE8: Exceeds Expectation | AG8: Main
A9: 15 | B9: MSB Mobile Kaleida | C9: 46143 | D9: 46156 | E9: 26.5 M Sprint 3 | F9: Jagdeep/Prem | G9: 48498 | H9: [WAVE] MSBA - Receipt Screen - Show Confirmation/Green Check once SMS/Email Sent | I9: Story Completed | J9: 1 | L9: 11 | M9: 46142 | N9: 46146 | O9: NA | P9: Rupesh | Q9: NA | R9: Rupesh/Sambath | S9: NA | T9: https://dev.azure.com/heartlandschools/Mobile/_git/MSBA.MAUI/pullrequest/48815 | U9: 46146 | V9: 46147 | W9: Ashwin | X9: NA | Y9: Avery | Z9: 46147 | AA9: Count :- 2 1. WasSent should be reset to false in OnError handler, failed sends should show 'Send' not 'Resend' 2. Change OriginalButtonText from field to property. | AB9: POV done with Bavithra No Comment | AC9: POV done with Jason No Comment | AD9: 04 May - Will continue work on this defect and will do POV today. 05 May - Will work for to resolve PR comment.(Comment Resolved Story under peer a review) 06 May - Story ready for testing. 07 May - Test Case updation and testing completed | AE9: Exceeds Expectation | AG9: Main
A10: 16 | B10: MSB Mobile Kaleida | C10: 46143 | D10: 46156 | E10: 26.5 M Sprint 3 Stretch | F10: Gursewak/Sambath/Prem | G10: 27318 | H10: MSBA - Kaleida - I/A - Unable to navigate back from Admin Settings when shift is already active | I10: Defect Fixed | J10: 3 | L10: 14 | M10: 46146 | N10: 46149 | O10: NA | P10: Yes | Q10: NA | R10: NA | S10: NA | T10: https://dev.azure.com/heartlandschools/Mobile/_git/MSBA.MAUI/pullrequest/48817?base=2&iteration=3 | U10: 46149 | V10: 46149 | W10: Ashwin | X10: NA | Y10: Avery | Z10: 46149 | AA10: NA | AB10: POV done with Bavithra No Comment | AC10: NA | AD10: 04 May - Will start working on this defect. 04 May-EOD-Worked on analyzing and reproducing the issue, then started working on a fix. After that, the issue was resolved and tested on iPhone and iPad. Reviewed the code with Ashwin, and he suggested finding an alternative approach to resolve the problem. I will work with Sambath on this. 05 May - As ashwin suggested need to work with Sambath on this defect. 06 May - Ashwin sent message on slack for more clarification from Jason, waiting for reply. 07 May - As Sambath discussed with Ashwin, need to check on Meal Money page and Transaction Page, if it is not effect on these pages we will inform to client., Sambath also support me on the same today. 07 May - EOD - Merged, ready for test. QA team working on the main commit defects/stories follwed by regression testing. 08 Apr - Testing Completed | AE10: Exceeds Expectation | AF10: NA | AG10: Stretch
A11: 17 | B11: MSB Mobile | C11: 46143 | D11: 46156 | E11: 26.5 M Sprint 3 | F11: chandler/vaishnavi/ | G11: 27320 | H11: 27320 MSBP - Android - All text and sizes are inflated on pixel pro devices, sometimes pushing items off viewable area (26.5) | I11: Defect Being Tested | J11: 2 | M11: NA | N11: NA | O11: NA | P11: NA | Q11: NA | R11: NA | S11: NA | T11: NA | U11: NA | V11: NA | W11: NA | X11: NA | Y11: NA | Z11: NA | AA11: NA | AB11: NA | AC11: NA | AD11: This is issue is not reproduced in emaulator, need to test with device, so once received new device, i will continue to work. Waiting for new device to fix this issue. 7- May - will relate the new user stories to solve the correct way with responsive design. will relate the new epic which we'll refine. Added by RJ may be it could move to rejected status.. . 08-Apr - Prem/Vaishnavi - As per disucssion with Letashia, we will work on the testing with different devices.. 11-May - testing in progress. . 12-May- chandler working on the fix. 14-May- testing in progress. still facing few issues with pixel devices. will be sending those to letashia's review. | AG11: Main
A12: 18 | B12: MSB Mobile Kaleida | C12: 46143 | D12: 46156 | E12: 26.5 M Sprint 3 | F12: Prem | G12: 52989 | H12: MSB - Web - Parent Portal - Re-attach orphaned Invoices to students that were deleted and returned - MOBILE TESTING STORY | I12: Story Completed | J12: 2 | L12: 8 | M12: NA | N12: NA | O12: NA | P12: NA | Q12: NA | R12: NA | S12: NA | T12: NA | U12: NA | V12: NA | W12: NA | X12: NA | Y12: NA | Z12: NA | AA12: NA | AB12: NA | AC12: NA | AD12: 05 May - will start working on test case updation and will continue once the test case updation gets done 06 May - Test case updation and testing is completed | AE12: Exceeds Expectation | AG12: Main
A13: 19 | B13: MSB Mobile Kaleida | C13: 46143 | D13: 46156 | E13: 26.5 M Sprint 3 Stretch | F13: Jagdeep/vaishnavi | G13: 52343 | H13: [WAVE] MSBA - Kaleida - Update Offset Language - Difference(Over/Short) | I13: Story Being Tested | J13: 2 | L13: 5 | M13: 46147 | N13: 46148 | O13: NA | P13: Amrit/Vashnavi | Q13: NA | R13: Rupesh/Sambath | S13: NA | T13: https://dev.azure.com/heartlandschools/Mobile/_git/MSBA.MAUI/pullrequest/48842 | U13: 46147 | V13: 46149 | W13: Ashwin | X13: NA | Y13: Avery | Z13: 46149 | AA13: NA | AB13: POV done with Bavithra No Comment | AC13: POV done with Jason No Comment | AD13: 05 May - Starting work on this story. 06 May - Will create apk file and will share to Vashnavi for internal testing with printer.(POV done , Story under peer review , waiting Approval from Ashwin and client side). 08 May - Story ready for testing.QA team working on the main commit defects/stories follwed by regression testing.. 12-May - Due to regression testing, testing is on hold for this story. | AF13: Due to regression testing and other high priority defects/stories, this story was not worked by the tester | AG13: Stretch
A14: 20 | B14: MSB Mobile | C14: 46143 | D14: 46156 | E14: 26.5 M Sprint 3 Stretch | F14: Rupesh | G14: 27234 | H14: MSBA - Cart consolidated after promocode addition causing issue when allow user to set qty = no (26.7) | I14: Defect Blocked | J14: 2 | L14: 4 | M14: 46147 | N14: NA | O14: NA | P14: NA | Q14: NA | R14: NA | S14: NA | T14: NA | U14: NA | V14: NA | W14: NA | X14: NA | Y14: NA | Z14: NA | AA14: NA | AB14: NA | AC14: NA | AD14: 06 May - Development is in progress. 07 May - looks like api issue, I will get all the api response and see where it is breaking. 08 May - Ashwin asked me to try one approach(Same product with different stock option) and then see how orders are getting created. 11 May - Created a doc with all the possible scenarios, Ashwin reviewed and asked to make some changes. | AE14: Exceeds Expectation | AF14: When allow user to set qty = no (26.7) the issue is that the API result when applying promocode is combining the products into a single order. The fix for this should be that for products with allow user to set qty set to no should create separate orders for each product and not combine it under one order. Request: curl --location --request PUT 'https://test.www.myschoolbucks.com/mobilepay/3.0/checkout/process/' \ --header 'apiKey: EX87L7NSH3WM5X5FB25LMM1PBY5ELW' \ --header 'token: 94VWV2BY31EJYP5' \ --header 'mfaSessionKey: KH4AYWBNTIIKQR6' \ --header 'Content-Type: application/json' \ --header 'Cookie: JSESSIONID=YpWUueQMj9D00UJCi41sOKYJF07oXEwEi_gXVTnU.schoolbucks-cluster-5965cd768c-ktlbx; TS01dc4fc6=010e7b7cc2cf32352e80dfb1c4ca91a26abc4b34a2d73c7d46c0a91c1342c1bb6dcbd91c913ca9c8f24714f13e25787edf3de8a672' \ --data '{ "fundingDetailsInvoices": {}, "fundingDetailsMeals": {}, "storeItems": [ { "productRef": "KytlcCcpfSR1I3krJXdy", "quantity": 1, "unitPrice": 100.00, "stockOptionID": "opt1607", "studentKey": null, "formFields": null, "ignoreAddOn": false, "ignoreInventory": false, "ignoreSalesTax": false }, { "productRef": "KytlcCcpfSR1I3krJXdy", "quantity": 1, "unitPrice": 100.00, "stockOptionID": "opt1607", "studentKey": null, "formFields": null, "ignoreAddOn": false, "ignoreInventory": false, "ignoreSalesTax": false } ], "paymentMethodDetails": { "paymentMethodType": "Cash", "signatureImageFormat": "JPG" }, "promoCodeId": "regressiontest1", "appVersion": "15", "deviceDesc": "417591003b5efa57" }' Response: { "result": 1, "message": "", "basketKey": "", "programFee": 0.00, "salesTax": 0.00, "subtotal": 190.00, "subTotalBeforePromoCodes": 200.00, "promoCodeTotal": -10.00, "appliedPromoCodes": [ { "amount": 10.00, "quantity": -1, "amountIsPercentage": false, "minimumOrderTotal": 10.00, "name": "regressiontest1", "id": "regressiontest1", "desc": "", "error": "" } ], "failedPromoCodes": [], "orders": [ { "clientKey": "ZZJ22K7JR50ZCV3", "fees": 0.00, "salesTax": 0.00, "orderSubtotal": 190.00, "cardEntryType": [], "storeItems": [ { "studentKey": "", "imageLink": "", "name": "TestRupesh2", "unitPrice": 90.00, "unitPriceBeforePromoCode": 100.00, "amount": 90.00, "amountBeforePromoCode": 100.00, "quantity": 1, "availableQuantity": 1, "clientKey": "ZZJ22K7JR50ZCV3", "productRef": "KytlcCcpfSR1I3krJXdy", "productID": "prod448", "storeID": "10OQG", "clientID": "", "stockOptionID": "opt1607", "propertyValues": [] }, { "studentKey": "", "imageLink": "", "name": "TestRupesh2", "unitPrice": 100.00, "unitPriceBeforePromoCode": 100.00, "amount": 100.00, "amountBeforePromoCode": 100.00, "quantity": 1, "availableQuantity": 1, "clientKey": "ZZJ22K7JR50ZCV3", "productRef": "KytlcCcpfSR1I3krJXdy", "productID": "prod448", "storeID": "10OQG", "clientID": "", "stockOptionID": "opt1607", "propertyValues": [] } ], "invoiceItems": [], "mealPayments": [], "gatewayDetails": [ { "paymentMethodType": "cash", "userName": null, "password": null, "siteID": null, "licenseID": null, "deviceID": null, "developerID": null, "versionNumber": null, "url": null, "message": "Order not for (Chip/Contactless) credit card txn" } ] } ], "redirectUrl": "", "returnToSiteUrl": "" } After this when we try to checkout since the qty is changed the below API is throwing an error. curl --location 'https://test.www.myschoolbucks.com/mobilepay/3.0/checkout/paymentMethods' \ --header 'apiKey: EX87L7NSH3WM5X5FB25LMM1PBY5ELW' \ --header 'token: 94VWV2BY31EJYP5' \ --header 'mfaSessionKey: KH4AYWBNTIIKQR6' \ --header 'Content-Type: application/json' \ --header 'Cookie: JSESSIONID=3bTmR4zbXdLD6PJOXcyyd4m0kEZWnDxzbbmatjWD.schoolbucks-cluster-7d6d5594b-7nrrl; TS01dc4fc6=010e7b7cc2d0b63ca816bf6e93c45505976c7223911e6c4b234f37a1bd14afa6ff3a6e811f963dde0197c017fec585426131190645' \ --data '{ "storeItems": [ { "productRef": "KytlcCcpfSR1I3krJXdy", "quantity": 2, "unitPrice": 100.00, "stockOptionID": "opt1607", "studentKey": null } ] } Response: { "result": 2, "message": "Unable to create basket items from checkout request. Ex: KytlcCcpfSR1I3krJXdy:You are not allowed to set the quantity." } | AG14: Stretch
A15: 21 | B15: MSB Mobile | C15: 46143 | D15: 46156 | E15: 26.5 M Sprint 3 | F15: Vaishnavi | G15: 52988 | H15: MSB - Web - Parent Portal - Allow Payment on Invoices for Deleted Students - MOBILE TESTING STORY | I15: Story Completed | J15: 3 | L15: 5 | M15: NA | N15: NA | O15: NA | P15: NA | Q15: NA | R15: NA | S15: NA | T15: NA | U15: NA | V15: NA | W15: NA | X15: NA | Y15: NA | Z15: NA | AA15: NA | AB15: NA | AC15: NA | AD15: 05 May - will start working on test case updation and will continue once the test case updation gets done. 06-May- will work on the testing. Had the doubts clarified from letashia yesterday. 07-As per Jason and troy discussion, this story can be closed as it needs a future enhancement. Will be confirming with Letashia and closing this story today. . 08-Apr - Prem/Vaishnavi - As per disucssion with Letashia, we will work on the testing with different devices. | AG15: Main
A16: 22 | B16: MSB Mobile | C16: 46143 | D16: 46156 | E16: 26.5 M Sprint 3 Stretch | F16: Amrit/Gursewak | G16: 27283 | H16: MSBA - MAUI - iOS- meal payments screen changing formatting when cart preview is on with items in it | I16: Defect Peer Review | J16: 1 | L16: 6 | M16: 46150 | N16: 46153 | O16: NA | P16: Gursewak | Q16: NA | R16: Rupesh/Sambath | S16: NA | T16: https://dev.azure.com/heartlandschools/Mobile/_git/MSBA.MAUI/pullrequest/48972 | U16: 46153 | V16: NA | W16: NA | X16: NA | Y16: NA | Z16: Na | AA16: NA | AB16: POV done with Bavithra No Comment | AC16: NA | AD16: 6 May - Reproducing and analyzing defect 7 May - Issue is in particular iPad 9 26.3.1 real device we will have to test internally in this device 8 May - TODO PEER Testing today 08 May -Gursewak - Support to Amrit for Peer testing. 11 May - Defect PR Created POV Pending 12 May - PR Approved by Rupesh pending from Samath 13 May - PR Approved by Rupesh pending from Samath 14 May - PR Pending from Client Side | AE16: Exceeds Expectation | AF16: Peer review | AG16: Stretch
A17: 23 | B17: MSB Mobile Kaleida | C17: 46143 | D17: 46156 | E17: 26.5 M Sprint 3 Stretch | F17: Jagdeep | G17: 27276 | H17: MSBP - Android - Can double click and open multiple stacks of menus | I17: Defect Ready For Testing | J17: 3 | L17: 9 | M17: 46148 | N17: 46150 | O17: NA | P17: Gursewak | Q17: NA | R17: Rupesh/Sambath | S17: NA | T17: https://dev.azure.com/heartlandschools/Mobile/_git/MSBP.MAUI/pullrequest/48903 | U17: 46149 | V17: 46155 | W17: Ashwin | X17: NA | Y17: Avery | Z17: 46155 | AA17: NA | AB17: POV done with Bavithra No Comment | AC17: NA | AD17: 6 May- Starting work on this defect. 7 May - will continue work on this defect. 8 May - Defect under Peer review . 14 May - Defect ready for testing. | AF17: Due to regression testing and other high priority defects/stories, this story was not worked by the tester | AG17: Stretch
A18: 25 | B18: MSB Mobile Kaleida | C18: 46143 | D18: 46156 | E18: 26.5 M Sprint 3 Stretch | F18: Gursewak | G18: 27015 | H18: MSBA - MAUI - iphone - invoice add to cart button not formatted correctly (regression) | I18: Defect Ready For Testing | J18: 1 | L18: 2.5 | M18: 46150 | N18: 46150 | O18: NA | P18: Yes | Q18: NA | R18: Rupesh/Sambath | S18: NA | T18: https://dev.azure.com/heartlandschools/Mobile/_git/MSBA.MAUI/pullrequest/48924 | U18: 46150 | V18: 46150 | W18: NA | X18: NA | Y18: NA | Z18: NA | AA18: NA | AB18: POV done with Bavithra No Comment | AC18: NA | AD18: 08 May, Start working on it, issue fixed, POV done, ready for review. 09 May - Ashwin marked the pull request as a draft 14 May - New release branch 26.5 is created, now change the branch, and ready for review. internal team review the PR. Ashwin and client side pending. 14 May - EOD - Merged, ready for test now. | AE18: Exceeds Expectation | AF18: NA | AG18: Stretch
A19: 26 | B19: MSB Mobile | C19: 46143 | D19: 46156 | E19: 26.5 M Sprint 3 Stretch | F19: Amrit | G19: 27006 | H19: MSBA - MAUI - iOS - Cart has extra space underneath buttons (regression) | I19: Defect Peer Review | J19: 1 | L19: 6 | M19: 46150 | N19: 46153 | O19: NA | P19: Gursewak | Q19: NA | R19: Rupesh/Sambath | S19: NA | T19: https://dev.azure.com/heartlandschools/Mobile/_git/MSBA.MAUI/pullrequest/48926 | U19: 46153 | V19: NA | W19: NA | X19: NA | Y19: NA | Z19: NA | AA19: NA | AB19: POV done with Ashwin No Comment | AC19: NA | AD19: 8 May - Analyzing and reproducing defect 11 May - Defect ready for PEER Review 12 May - PR In Review 13 May - PR Pending Internal review 14 May - PR Pending from Ashwin and Client Side | AE19: Exceeds Expectation | AF19: Peer review | AG19: Stretch
A20: 27 | B20: MSB Mobile Kaleida | C20: 46143 | D20: 46156 | E20: 26.5 M Sprint 3 Stretch | F20: Jagdeep | G20: 27255 | H20: MSBP - missing phone number page and profile phone pages do not match | I20: Defect Peer Review | J20: 1 | L20: 3 | M20: 46150 | N20: 46153 | O20: NA | P20: Amrit | Q20: NA | R20: Rupesh | S20: NA | T20: https://dev.azure.com/heartlandschools/Mobile/_git/MSBP.MAUI/pullrequest/49015 | U20: 46153 | V20: NA | W20: NA | X20: NA | Y20: NA | Z20: NA | AA20: NA | AB20: POV done with Bavithra No Comment | AC20: NA | AD20: 11 May - requirement cleared today will work and complete it. 12 May - Defect under peer review.(Sambath , ashwin, and client side pending). 14 May - Waiting for aproval from Ashwin and Client side. | AF20: Defect fixed still PR in Review, Ashwin and client side review pending | AG20: Stretch
A21: 28 | B21: MSB Mobile Kaleida | C21: 46143 | D21: 46156 | E21: 26.5 M Sprint 3 Stretch | F21: Gursewak | G21: 26881 | H21: MSBA - Cart icon/badge is larger than expected (regression) | I21: Defect Ready For Testing | J21: 1 | L21: 4.5 | M21: 46150 | N21: 46153 | O21: NA | P21: Yes | Q21: NA | R21: Rupesh/Sambath | S21: NA | T21: https://dev.azure.com/heartlandschools/Mobile/_git/MSBA.MAUI/pullrequest/48932 | U21: 46153 | V21: 46153 | W21: NA | X21: NA | Y21: NA | Z21: NA | AA21: NA | AB21: POV done with Bavithra No Comment | AC21: NA | AD21: 08 May- Working on it. 11 May - Will fix this issue, do the POV, and create the PR. 12 May - Ashwin and client side review pending. 14 May - New release branch 26.5 is created, now change the branch, and ready for review. internal team review the PR. Ashwin and client side pending. 14 May - EOD - Merged, ready for test now. | AE21: Exceeds Expectation | AF21: NA | AG21: Stretch
A22: 29 | B22: MSB Mobile | C22: 46143 | D22: 46156 | E22: 26.5 M Sprint 3 Stretch | F22: Vaishnavi/Prem | G22: 53092 | H22: REG - MSBP - Regression 26.5 | I22: Story Being Tested | J22: 8 | M22: NA | N22: NA | O22: NA | P22: NA | Q22: NA | R22: NA | S22: NA | T22: NA | U22: NA | V22: NA | W22: NA | X22: NA | Y22: NA | Z22: NA | AA22: NA | AB22: NA | AC22: NA | AD22: 12-May - Will work on the testing today. 14-May - Testing in progress. Vaishnavi - As per letashia, defect 27320 needs to be completed first, will be working on that. later will work on the pending regression test cases. | AG22: Stretch
A23: 30 | B23: MSB Mobile Kaleida | C23: 46143 | D23: 46156 | E23: 26.5 M Sprint 3 | F23: Jagdeep | G23: 27389 | H23: MSBP - MAUI - Android - Cart icon showing the badge count when no items available in the shopping cart (regression) | I23: Defect Fixed | J23: 0 | L23: 4 | M23: 46155 | N23: 46155 | O23: NA | P23: Gursewak | Q23: NA | R23: Rupesh/Sambath | S23: NA | T23: https://dev.azure.com/heartlandschools/Mobile/_git/MSBP.MAUI/pullrequest/49020 | U23: 46155 | V23: 46155 | W23: Ashwin | X23: NA | Y23: Avery | Z23: 46155 | AA23: NA | AB23: POV done with Ashwin No Comment | AC23: NA | AD23: 13 May - Start work on this defect. 14 May - Defect ready for testing. | AG23: Main
A24: 31 | B24: MSB Mobile | C24: 46143 | D24: 46156 | E24: 26.5 M Sprint 3 | F24: Rupesh | G24: 27394 | H24: MSBA - stock option formatting issues (regression) | I24: Defect Peer Review | J24: 0 | L24: 8 | M24: 46155 | AD24: 13 May - will analyse and then start the development. 14 May - will try to fix it and run the POV today. | AF24: Picked up on 13th May as this regression defect was created at the last moment. | AG24: Main
B25: MSB Mobile | C25: 46143 | D25: 46156 | E25: 26.5 M Sprint 3 | F25: Dev Team | G25: 87660 | H25: MSB Mobile - Exploratory Testing | I25: Story Completed | J25: 8 | L25: 62

Sheet 26.5 M Sprint 3-Defect
A1: S.No | B1: Sprint # | C1: Story/Defect ID | D1: Parent Story | E1: Developer | F1: Issue Type | G1: Issue Description | H1: Priority | I1: Defect Source | J1: Type | K1: Status | L1: Root Cause Category | M1: Who Reported It? | N1: Comments
B2: 26.5 M Sprint 3 | C2: 26882 MSBA - Cart Icon does not have the correct MSBA blue background | D2: 26882 MSBA - Cart Icon does not have the correct MSBA blue background | E2: Amrit/ | F2: Defect | H2: Minor | I2: Manual | J2: Internal | K2: Closed | L2: Development | M2: Relevantz QA | N2: Xamarin to Maui conversion defects
B3: 26.5 M Sprint 3 Stretch | C3: 27318 MSBA - Kaleida - I/A - Unable to navigate back from Admin Settings when shift is already active | D3: 27318 MSBA - Kaleida - I/A - Unable to navigate back from Admin Settings when shift is already active | E3: Gursewak/Sambath | F3: Defect | H3: Minor | I3: Manual | J3: Internal | K3: Closed | L3: Development | M3: Relevantz QA | N3: Maui to Kaleida conversion defects
B4: 26.5 M Sprint 3 | C4: 27320 MSBP - Android - All text and sizes are inflated on pixel pro devices, sometimes pushing items off viewable area (26.5)" | D4: 27320 MSBP - Android - All text and sizes are inflated on pixel pro devices, sometimes pushing items off viewable area (26.5)" | E4: chandler | F4: Defect | H4: Minor | I4: Manual | J4: External | K4: Inprogress | L4: Development | M4: Client QA | N4: Xamarin to Maui conversion defects
B5: 26.5 M Sprint 3 Stretch | C5: 27234 MSBA - Cart consolidated after promocode addition causing issue when allow user to set qty = no (26.7) | D5: 27234 MSBA - Cart consolidated after promocode addition causing issue when allow user to set qty = no (26.7) | E5: Rupesh | F5: Defect | H5: Minor | I5: Manual | J5: External | K5: Closed | L5: Development | M5: Client QA | N5: Enhancement
B6: 26.5 M Sprint 3 Stretch | C6: 27283 MSBA - MAUI - iOS- meal payments screen changing formatting when cart preview is on with items in it | D6: 27283 MSBA - MAUI - iOS- meal payments screen changing formatting when cart preview is on with items in it | E6: Amrit/Gursewak | F6: Defect | H6: Minor | I6: Manual | J6: External | K6: Inprogress | L6: Development | M6: Client QA | N6: Xamarin to Maui conversion defects
B7: 26.5 M Sprint 3 Stretch | C7: 27276 MSBP - Android - Can double click and open multiple stacks of menus | D7: 27276 MSBP - Android - Can double click and open multiple stacks of menus | E7: Jagdeep | F7: Defect | H7: Minor | I7: Manual | J7: External | K7: Inprogress | L7: Development | M7: Client QA | N7: Xamarin to Maui conversion defects
B8: 26.5 M Sprint 3 Stretch | C8: 27015 MSBA - MAUI - iphone - invoice add to cart button not formatted correctly (regression) | D8: 27015 MSBA - MAUI - iphone - invoice add to cart button not formatted correctly (regression) | E8: Gursewak | F8: Defect | H8: Minor | I8: Manual | J8: External | K8: Closed | L8: Development | M8: Client QA | N8: Regression defects
B9: 26.5 M Sprint 3 Stretch | C9: 27006 MSBA - MAUI - iOS - Cart has extra space underneath buttons (regression) | D9: 27006 MSBA - MAUI - iOS - Cart has extra space underneath buttons (regression) | E9: Amrit | F9: Defect | H9: Minor | I9: Manual | J9: Internal | K9: Inprogress | L9: Development | M9: Relevantz QA | N9: Regression defects
B10: 26.5 M Sprint 3 Stretch | C10: 27255 MSBP - missing phone number page and profile phone pages do not match | D10: 27255 MSBP - missing phone number page and profile phone pages do not match | E10: Jagdeep | F10: Defect | H10: Minor | I10: Manual | J10: External | K10: Inprogress | L10: Development | M10: Client QA | N10: Xamarin to Maui conversion defects
B11: 26.5 M Sprint 3 Stretch | C11: 26881 MSBA - Cart icon/badge is larger than expected (regression) | D11: 26881 MSBA - Cart icon/badge is larger than expected (regression) | E11: Gursewak | F11: Defect | H11: Minor | I11: Manual | J11: External | K11: Inprogress | L11: Development | M11: Client QA | N11: Regression defects
B12: 26.5 M Sprint 3 | C12: 27389 MSBP - MAUI - Android - Cart icon showing the badge count when no items available in the shopping cart (regression) | D12: 27389 MSBP - MAUI - Android - Cart icon showing the badge count when no items available in the shopping cart (regression) | E12: Jagdeep | F12: Defect | H12: Minor | I12: Manual | J12: Internal | K12: Closed | L12: Development | M12: Relevantz QA | N12: Regression defects
B13: 26.5 M Sprint 3 | C13: 27394 MSBA - stock option formatting issues (regression) | D13: 27394 MSBA - stock option formatting issues (regression) | E13: Rupesh | F13: Defect | H13: Minor | I13: Manual | J13: External | K13: Inprogress | L13: Development | M13: Client QA | N13: Regression defects

Sheet 26.5 M Sprint 2-Status
A1: S.No | B1: Application Name | C1: Sprint Start Date | D1: Sprint End Date | E1: Sprint | F1: Developer | G1: Story ID/Defect ID | H1: Description | I1: Status | J1: Estimated(sp) | K1: Actual(sp) | L1: Actual Hours Worklog | M1: Dev Start Date | N1: Dev End Date | O1: Unit testing | P1: Peer Tested By | Q1: Peer Tested Defects, if any | R1: Peer Reviewed By | S1: Peer Code Review Comments, if any | T1: PR Number/Link | U1: PR Created Date | V1: PR Approved Date | W1: Reviewer 1 | X1: Code Review Comments, if any | Y1: Reviewer 2 | Z1: Approved Date | AA1: Code Review Comments, if any2 | AB1: Internal PO -POV Comments | AC1: Client PO -POV Comments | AD1: Comments | AE1: Does this story meet the expectations? | AF1: Comments | AG1: Sprint Tag
A2: 1 | B2: MSB Mobile | C2: 46129 | D2: 46142 | E2: 26.5 M Sprint 2 | F2: Sean/ Vaishnavi | G2: 51966 | H2: [WAVE] MSBA - Kaleida - Settings - Apps & Stores | I2: Story Being Developed | J2: 5 | M2: 46071 | N2: NA | O2: NA | P2: NA | Q2: NA | R2: NA | S2: NA | T2: https://dev.azure.com/heartlandschools/Mobile/_git/MSBA.MAUI/pullrequest/47478 | U2: 25/2/2026 | V2: 46094 | W2: Ashwin | X2: NA | Y2: Avery | Z2: 46101 | AA2: NA | AB2: POV done with Bavithra | AD2: 20- Apr - Rupesh - Ashwin assigned this defect to Rupesh, will be continuing on that. This story will be on hold until defect 27072 is completed. 24 Apr - BB testing is in progress. 27 - Apr - will do a round of testing except the BB which was work by Sean. 28 -Apr - Still the BB fix by the onsite developer is in progress. Waiting for the fix. | AG2: Main
A3: 2 | B3: MSB Mobile | C3: 46129 | D3: 46142 | E3: 26.5 M Sprint 2 | F3: Rupesh/Prem | G3: 52056 | H3: MSBA - Close Out - Offer Portrait and Landscape Orientation | I3: Story Completed | J3: 3 | L3: 20 | M3: 46097 | N3: 46135 | O3: NA | P3: NA | Q3: NA | R3: Sambath | S3: NA | T3: https://dev.azure.com/heartlandschools/Mobile/_git/MSBA.MAUI/pullrequest/48454 | U3: 46128 | V3: 46135 | W3: Ashwin | X3: Use common color | Y3: Avery | Z3: 46135 | AA3: NA | AB3: POV done with Bavithra | AC3: NA | AD3: 17 Apr - Few BB’s are fixed, will be working on remaking ones Today. Raised the PR, pending from Ashwin. 21: Resolved Ashwin PR comments and implemented copilot PR suggestions. Ashwin approved it , pending from client side. 23 Apr - testing completed | AE3: Exceeds Expectation | AG3: Main
A4: 3 | B4: MSB Mobile Kaleida | C4: 46129 | D4: 46142 | E4: 26.5 M Sprint 2 | F4: Jagdeep/Vaishnavi | G4: 51972 | H4: [WAVE] MSBA - Kaleida - Settings - Admin Settings | I4: Story Completed | J4: 2 | L4: 12 | M4: 46105 | N4: 46125 | O4: NA | P4: NA | Q4: NA | R4: Rupesh/Sambath | S4: Count - 2 * don't hard code the sales tag method DiscardIncompleteFields instead of pass from cancelButtonAction paramsdon't hard code the sales tag method DiscardIncompleteFields instead of pass from cancelButtonAction params * move to AdminSettings validation rule | T4: https://dev.azure.com/heartlandschools/Mobile/_git/MSBA.MAUI/pullrequest/48410 | U4: 46119 | V4: 46127 | W4: Ashwin | X4: NA | Y4: Avery | Z4: 46125 | AA4: NA | AB4: Count - 3 POV done with Bavithra with solved comments:- 1. “School Number and Custom Label value should show if we already selected and come back on the screen. 2. Text not matching in Record sales tag section. 3. Search bar width and custom label entry width looking different | AC4: POV Done with JASON No Comments | AD4: 17 April - Will fix and done POV and will create PR. 20Apr- will work on this story after completing testing defect 27078.. 21-Apr - Completed testing in all devices. will close it shortly. | AE4: Exceeds Expectation | AG4: Main
A5: 4 | B5: MSB Mobile Kaleida | C5: 46129 | D5: 46142 | E5: 26.5 M Sprint 2 | F5: Amrit/Vaishnavi | G5: 51967 | H5: [WAVE] MSBA - Kaleida - Settings - Item Visibility | I5: Story Completed | J5: 2 | L5: 2 | M5: 46105 | N5: 46118 | O5: Na | P5: NA | Q5: NA | R5: Rupesh/Sambath | S5: Ashwin - The assignment is redundant since DisplayFeaturedItems already has that value. (3) | T5: https://dev.azure.com/heartlandschools/Mobile/_git/MSBA.MAUI/pullrequest/48175 | U5: 46026 | V5: 15/4/2026 | W5: Ashwin | X5: NA | Y5: Avery | Z5: 46126 | AA5: NA | AB5: POV Done with JASON No Comments | AC5: Na | AD5: 17-Apr- Testing in progress. EOD - Testing completed. | AE5: Exceeds Expectation | AG5: Main
A6: 5 | B6: MSB Mobile Kaleida | C6: 46129 | D6: 46142 | E6: 26.5 M Sprint 2 | F6: Gursewak/Vaishnavi | G6: 51968 | H6: [WAVE] MSBA - Kaleida - Settings - Cart and Transactions | I6: Story Completed | J6: 3 | L6: 17.5 | M6: 46105 | N6: 46126 | O6: NA | P6: Yes | Q6: NA | R6: Rupesh/Sambath | S6: NA | T6: https://dev.azure.com/heartlandschools/Mobile/_git/MSBA.MAUI/pullrequest/48183 https://dev.azure.com/heartlandschools/Mobile/_git/MSBA.MAUI/pullrequest/48183 | U6: 46126 | V6: 46126 | W6: Ashwin | X6: NA | Y6: Avery | Z6: 46127 | AA6: Avery Comments (2) Save/Load key mismatch (missing CurrentUserId suffix) • Count: 3 Missing blank line before next property definition • Count: 3 | AB6: POV done with Bavithra No Comment | AC6: NA | AD6: 17-April- Working on the same BB. 17 Apil - BB fixed, POV done, created PR, PR merged & ready for test.. 21-Apr-Will work on the testing today 27 April - Gursewak - As discussed with Ashwin, start working on BB on this story - Required signature field value is not clearing after enabling/disabling the toggle when user has entered some amount and save previously. 27-Apr - Testing in progress. 27-Apr-EOD- Below two BB has been fixed. - Required signature field value is not clearing after enabling/disabling the toggle when user has entered some amount and save previously - Discard and Stay & complete button loaded after showing some incorrect button name at first Both are merged, and ready for test.. 28-Apr - BB testing in progress. | AE6: Exceeds Expectation | AF6: This story took more time than estimated because additional bugs were identified during testing, requiring further fixes, POV validation, PR creation/merge, and multiple testing cycles. Extra effort was also needed to resolve newly reported issues related to toggle behavior, field value clearing, and incorrect button labels before final validation. | AG6: Main
A7: 6 | B7: MSB Mobile Kaleida | C7: 46129 | D7: 46142 | E7: 26.5 M Sprint 2 | F7: Jagdeep/vaishnavi | G7: 27078 | H7: 27078 MSBA - MAUI - android phone - app crash when trying to apply filters (regression) | I7: Defect Fixed | J7: 2 | L7: 2 | M7: 46113 | N7: 46127 | O7: NA | P7: NA | Q7: NA | R7: Rupesh/Sambath | S7: Count: 1 why ExecuteGroupsStores was removed, Group filter is required after changing the stores | T7: https://dev.azure.com/heartlandschools/Mobile/_git/MSBA.MAUI/pullrequest/48418 | U7: 46127 | V7: 46129 | W7: Ashwin | X7: NA | Y7: Avery | Z7: 46129 | AA7: NA | AB7: "POV done with Ashwin No Comment" | AC7: POV Done with Bavithra No Comments | AD7: 17 April - Will fix and done POV and will create PR. 20Apr- will work on this story after completing testing defect 27078. 06 - April - not yet started to work 14 - April - Today will investigate and try to find root cause and then will work for fix it. 15 - April - First will work for BB coming on story 51972 then will start continue work on it. 15 - April - Work with Jagdeep on the defect. 16- April - As Ashwin suggestion , reverted all performance based changes only kept bug fixes related changes.(defect now Peer a review ) 20 April - Defect ready for testing. | AE7: Exceeds Expectation | AG7: Main
A8: 8 | B8: MSB Mobile Kaleida | C8: 46129 | D8: 46142 | E8: 26.5 M Sprint 2 | F8: Prem/Gursewak | G8: 52194 | H8: [WAVE] MSBA - Kaleida - Update Shift Mode Status Icons on Top Header Bar | I8: Story Completed | J8: 2 | L8: 23.5 | M8: 46097 | N8: 46136 | O8: NA | P8: Yes | Q8: NA | R8: NA | S8: NA | T8: https://dev.azure.com/heartlandschools/Mobile/_git/MSBA.MAUI/pullrequest/48615 | U8: 46136 | V8: 46136 | W8: Ashwin | X8: NA | Y8: Avery | Z8: 46136 | AA8: NA | AB8: POV done with Ashwin No Comment | AC8: NA | AD8: 17 Apr - tested and raised a BB. and assigned top dev fix the same 22 Apr - Tested and still the BB exists. Reassigning back to dev to fix the same 23 Apr - Fixed BB - Android - Mobile - Buttons (Shift On/Off), Cart, Search) shows bigger which is overlapping with the header text. Added screenshot for reference, Created PR, and it is merged. 24 Apr - Start work on BB - Clock icon being cut off in shift mode status icon on Top header bar in Android tablet 24 Apr - BB testing is in progress 24 Apr-EOD-Clock icon being cut off in shift mode status icon on Top header bar in Android tablet issue has been already fixed. tested On BS today i checked on all Samsung tabs like:- Galaxy Tab S7 11, Galaxy Tab S8 12, Galaxy Tab S9 13, Galaxy Tab S9+ 14, Galaxy Tab S10+ 15, Galaxy Tab S11 16 27 Apr - Testing Completed | AE8: Exceeds Expectation | AF8: Story #52194 took more time than estimated because multiple UI issues were identified during testing, requiring additional fixes, re-testing, and validation across different Android devices and Samsung tablets to ensure the top header status icons worked correctly on all supported devices. | AG8: Main
A9: 9 | B9: MSB Mobile | C9: 46129 | D9: 46142 | E9: 26.5 M Sprint 2 | F9: Amrit | G9: 27019 | H9: MSBA - MAUI - phones - cannot drag to sort products | I9: Defect Fixed | J9: 3 | L9: 14 | M9: 46127 | N9: 46128 | O9: NA | P9: NA | Q9: NA | R9: Rupesh/Sambath | S9: NA | T9: https://dev.azure.com/heartlandschools/Mobile/_git/MSBA.MAUI/pullrequest/48491 | U9: 46129 | V9: 46132 | W9: Ashwin | X9: NA | Y9: Avery | Z9: 46132 | AA9: Avery 1 targetItem should be verified as ProductSummary type before passing to ReorderProductAsync. Should be reverted to: if (_draggedItem is ProductSummary sourceProduct && targetItem is ProductSummary targetProduct) | AB9: NA | AC9: POV Done with Bavithra No Comments | AD9: 17 Apr - Testing done, POV Done , PR Created 20 Apr - Working on PR Comments, PR Merged | AE9: Exceeds Expectation | AG9: Main
A10: 11 | B10: MSB Mobile | C10: 46129 | D10: 46142 | E10: 26.5 M Sprint 2 Stretch | F10: Amrit/Prem | G10: 52344 | H10: [WAVE] MSBA - Update Components/Fonts to Kaleida - Hamburger Menu | I10: Story Being Developed | J10: 3 | L10: 8.5 | M10: 46132 | N10: 46134 | O10: NA | P10: NA | Q10: NA | R10: Jagdeep | S10: NA | T10: https://dev.azure.com/heartlandschools/Mobile/_git/MSBA.MAUI/pullrequest/48532 | U10: 46138 | V10: NA | W10: Sambath | X10: NA | Y10: Avery | Z10: NA | AA10: Avery Comments (17) Remove unnecessary Grid wrappers • Count: 7 Redundant Command / CommandParameter on CustomMenuItem • Count: 6 Use proper Kaleida styles (KLabelFootnote / KLabelSectionHeader) • Count: 2 Use proper component (KCircleButton for close button) • Count: 1 Component consistency / standard Kaleida pattern • Count: 1 | AB10: POV done with Bavithra No Comment | AC10: NA | AD10: 20 Apr - Will start after compleing 27019 21 Apr - Working on Component Changes 22 Apr - Status is Product Owner Verifying . Amrit is fixing few spaces issue for android and update PR 23 Apr - Need to do PEER testing by Jagdeep and Peer Review, POV with Bavithra 24 Apr - PR Level 1 Approved , Pending from Level 2 and 3 25 Apr - PR Pending from Level 3 28 Apr - Working on PR Comments 29 Apr - Tested and raised a BB. And assigned the same to dev 30 Apr - Will Test and fix scrolling issue in Pixel device | AE10: Exceeds Expectation | AF10: Space Issue in only android small devices, which can take some time to fix, 90% done | AG10: Stretch
A11: 12 | B11: MSB Mobile Kaleida | C11: 46129 | D11: 46142 | E11: 26.5 M Sprint 2 | F11: Jagdeep | G11: 27204 | H11: MSBA - MAUI- iOS - Transparency issue in iOS on clicking shift mode icon. (26.5) | I11: Defect Fixed | J11: 2 | L11: 6 | M11: 46132 | N11: 46132 | O11: NA | P11: Yes | Q11: Rupesh | R11: Rupesh | S11: NA | T11: https://dev.azure.com/heartlandschools/Mobile/_git/MSBA.MAUI/pullrequest/48519 | U11: 46132 | V11: 46132 | W11: Ashwin | X11: NA | Y11: Avery | Z11: 46132 | AA11: NA | AB11: "POV done with Ashwin No Comment" | AC11: NA | AD11: 20 April - Will reproduce the issue and start work to fix this defect. 21 April - Defect ready for testing. | AE11: Exceeds Expectation | AG11: Main
A12: 13 | B12: MSB Mobile Kaleida | C12: 46129 | D12: 46142 | E12: 26.5 M Sprint 2 Stretch | F12: Gursewak | G12: 26762 | H12: MSBP - allows identical Routing # and Account # for eCheck Autopay, causing silent payment failure and missing notifications. | I12: Defect Fixed | J12: 2 | L12: 5.5 | M12: 46132 | N12: 46132 | O12: NA | P12: Yes | Q12: NA | R12: Rupesh | S12: NA | T12: https://dev.azure.com/heartlandschools/Mobile/_git/MSBP.MAUI/pullrequest/48514 | U12: 46132 | V12: 46132 | W12: Ashwin | X12: NA | Y12: Avery | Z12: 46132 | AA12: NA | AB12: POV done with Bavithra No Comment | AC12: NA | AD12: 20 April - I will analyze the issue, reproduce it, and start working to fix this defect. 20 april - EOD - Development completed, did POV, Created PR, PR merged, Ready for test. | AE12: Exceeds Expectation | AG12: Stretch
A13: 14 | B13: MSB Mobile Kaleida | C13: 46129 | D13: 46142 | E13: 26.5 M Sprint 2 Stretch | F13: Gursewak | G13: 52346 | H13: [WAVE] MSBA - Update Components/Fonts to Kaleida - Header | I13: Story Being Developed | J13: 2 | M13: 46133 | N13: NA | O13: NA | P13: NA | Q13: NA | R13: NA | S13: NA | T13: https://dev.azure.com/heartlandschools/Mobile/_git/MSBA.MAUI/pullrequest/48736 | U13: 46141 | V13: NA | W13: NA | X13: NA | Y13: NA | Z13: NA | AA13: NA | AB13: NA | AC13: NA | AD13: 21 April - Start working on it. 21 April - EOD - Worked on this story, development is completed, did the POV with Vaishnavi. During the POV we found issue on tablet, large District name is cut off. working on it. 22 April - District name cut off in tablet, need to fix the issue in KStatusChip, working on it. after that will do the POV and will create PR. 24 Apr - Not work on this story today, becuase 52194 story BB need to fix on first prority. 27 Apr - Not working on this story due to BB on the story 51968, working on BB on story 51968 28 Apr - Start working on the pending work on this story, will merge the Kaleida branch, and try to complete and did the POV. 29 Apr - Will start work on BB on this story 30-Apr-Doing testing, did the POV, after that create PR. 30 Apr-EOD- Development is complete, including fixes for the Android header white space issue, while another reported issue could not be reproduced and was verified with QA. Testing has been completed across all devices (Android/iOS, phone and tablet), along with peer testing and POV | AE13: Exceeds Expectation | AF13: NA | AG13: Stretch
A14: 16 | B14: MSB Mobile | C14: 46129 | D14: 46142 | E14: 26.5 M Sprint 2 Stretch | F14: Sambath | G14: 52347 | H14: 52347 [WAVE] MSBA - Update Components/Fonts to Kaleida - Transaction History | I14: Story Being Developed | J14: 8 | M14: 46133 | AD14: 21 - Apr - Startred to working on this story 22 - Apr - Working with tablet UI changes 23- Apr - Working with tablet design changes, 24- Apr - Tested desing for tablet, and started wokring on phone design 27 - Apr - Contiue to working with Phone design changes 28 - Apr - Worked Phone design and testing is in-progress 29 - Apr - Dev Testing is in-progress. 30 - Apr - Fixing the POV changes, testing issues
A15: 17 | B15: MSB Mobile | C15: 46129 | D15: 46142 | E15: 26.5 M Sprint 2 Stretch | F15: Rupesh | G15: 52348 | H15: [WAVE] MSBA - Update Components/Fonts to Kaleida - Forgot Login Workflow | I15: Product Owner - Verify | J15: 3 | L15: 14 | M15: 46134 | N15: NA | O15: NA | P15: NA | Q15: NA | R15: NA | S15: NA | T15: NA | U15: NA | V15: NA | W15: NA | X15: NA | Y15: NA | Z15: NA | AA15: NA | AB15: POV done with Ashwin No Comment | AC15: NA | AD15: 22 Apr - Will start development today. 27 Apr - Will try to finish remaining steps as first 2 steps has been done. 28 Apr - Will request for peer testing and then will have POV. 29 Apr - Will share the POV with client today and then raise the PR today, shared the screen recording with Ashwin and he confirmed it looks okay. 29 Apr : POV pending from Jason side. | AE15: Exceeds Expectation | AG15: Stretch
A16: 15 | B16: MSB Mobile Kaleida | C16: 46129 | D16: 46142 | E16: 26.5 M Sprint 2 | F16: Jagdeep | G16: 27257 | H16: MSBP - Android - App navigation hidden under phone navigation (release defect) | I16: Defect Fixed | J16: 0 | L16: 6 | M16: 46133 | N16: 46133 | O16: NA | P16: Yes | Q16: Rupesh | R16: Rupesh/Sambath | S16: NA | T16: https://dev.azure.com/heartlandschools/Mobile/_git/MSBP.MAUI/pullrequest/48539 | U16: 46133 | V16: 46134 | W16: Ashwin | X16: NA | Y16: Avery | Z16: 46134 | AA16: NA | AB16: "POV done with Vashnavi No Comment" | AC16: NA | AD16: 21 April - First will try to reproduce and will start work on it. 22-Apr- Letashia will be testing this. need to check this with Ashwin | AE16: Exceeds Expectation | AG16: Main
A17: 18 | B17: MSB Mobile Kaleida | C17: 46129 | D17: 46142 | E17: 26.5 M Sprint 2 | F17: Jagdeep | G17: 27088 | H17: MSBP - A - Button does not turn blue even after meeting the entry requirements (regression) | I17: Defect Fixed | J17: 0 | L17: 6 | M17: 46135 | N17: 46136 | O17: NA | P17: Yes | Q17: Rupesh | R17: Sambath | S17: NA | T17: https://dev.azure.com/heartlandschools/Mobile/_git/MSBP.MAUI/pullrequest/48632 | U17: 46136 | V17: 46136 | W17: Ashwin | X17: NA | Y17: Avery | Z17: 46136 | AA17: NA | AB17: POV done with Bavithra No Comment | AC17: NA | AD17: 23 April - First will reproduce then will start work on it.(Tested but not reproduced issue informed to QA so hold it and working with Gursawek on stroy 52346. 24 April- Now able to reproduce with different repro steps after discussion with Latisha and Ashwin , today will work on it and will fix it.. 27 - Assigned to Letashia | AE17: Exceeds Expectation | AG17: Main
A18: 19 | B18: MSB Mobile Kaleida | C18: 46129 | D18: 46142 | E18: 26.5 M Sprint 2 | F18: Gursewak | G18: 27275 | H18: MSBP - Android - Add to cart button in invoices under nav bar after adding invoice (release defect) | I18: Defect Fixed | J18: 0 | L18: 3.5 | M18: 46135 | N18: 46135 | O18: NA | P18: Yes | Q18: NA | R18: NA | S18: NA | T18: https://dev.azure.com/heartlandschools/Mobile/_git/MSBP.MAUI/pullrequest/48619 | U18: 46135 | V18: 46135 | W18: Ashwin | X18: NA | Y18: Avery | Z18: 46135 | AA18: NA | AB18: POV done with Ashwin No Comment | AC18: NA | AD18: 23 April - Start working on it. 23 April - EOD - Development completed, PR merged, ready for test. | AE18: Exceeds Expectation | AF18: NA | AG18: Main
A19: 20 | B19: MSB Mobile Kaleida | C19: 46129 | D19: 46142 | E19: 26.5 M Sprint 2 Stretch | F19: Amrit/Vaishnavi | G19: 52516 | H19: MSBP - Wrap Product Name Text on Store Page to the 3rd line | I19: Story Completed | J19: 1 | L19: 3.5 | M19: 46136 | N19: 46136 | O19: NA | P19: Yes | Q19: NA | R19: Ashwin | S19: NA | T19: https://dev.azure.com/heartlandschools/Mobile/_git/MSBP.MAUI/pullrequest/48629 | U19: 46136 | V19: 46136 | W19: Ashwin | X19: NA | Y19: Avery | Z19: 46137 | AA19: NA | AB19: POV done with Bavithra No Comment | AC19: NA | AD19: 23 April - Start working on it. After 52334 24 Apr - Will be testing in all devices then will do POV and Create PR. 28 - Apr - Testing in progress. | AE19: Exceeds Expectation | AG19: Stretch
A20: 21 | B20: MSB Mobile Kaleida | C20: 46129 | D20: 46142 | E20: 26.5 M Sprint 2 Stretch | F20: Amrit/Vaishnavi | G20: 52726 | H20: MSBA - Settings - Update Optimal Settings Message | I20: Story Completed | J20: 1 | L20: 1.5 | M20: 46139 | N20: 46139 | O20: NA | P20: Yes | Q20: NA | R20: Rupesh/Sambath | S20: NA | T20: https://dev.azure.com/heartlandschools/Mobile/_git/MSBA.MAUI/pullrequest/48655 | U20: 46139 | V20: 46139 | W20: Ashwin | X20: NA | Y20: Avery | Z20: 46140 | AA20: NA | AB20: POV done with Bavithra No Comment | AC20: NA | AD20: 27 Apr - Working on story, PEER Testing DONE by Rupesh. 29-Apr- Will be starting the testing. | AE20: Exceeds Expectation | AG20: Stretch
A21: 22 | B21: MSB Mobile Kaleida | C21: 46129 | D21: 46142 | E21: 26.5 M Sprint 2 Stretch | F21: Amrit | G21: 52633 | H21: MSBP - Store Catalog - General header changed to Products | I21: Story Peer Review | J21: 1 | L21: 1.5 | M21: 46139 | N21: 46139 | O21: NA | P21: NA | Q21: NA | R21: Rupesh/Sambath | S21: NA | T21: https://dev.azure.com/heartlandschools/Mobile/_git/MSBP.MAUI/pullrequest/48662 | U21: 46139 | V21: 46139 | W21: Ashwin | X21: NA | Y21: NA | Z21: NA | AA21: NA | AB21: POV done with Bavithra No Comment | AC21: NA | AD21: 27 Apr - Working on story - PEER Testing Pending 28 Apr - PEER Testing will be done with Jagdeep 29 Apr - Working on changes told by Ashwin for check value 30 Apr - PR Pending from Ashwin and Client | AE21: Exceeds Expectation | AG21: Stretch
A22: 23 | B22: MSB Mobile | C22: 46129 | D22: 46142 | E22: 26.5 M Sprint 2 Stretch | F22: Avery/Prem | G22: 52345 | H22: [WAVE] MSBA - Update Components/Fonts to Kaleida - Bottom Nav | I22: Story Completed | J22: 1 | L22: 19.25 | M22: NA | N22: NA | O22: NA | P22: NA | Q22: NA | R22: NA | S22: NA | T22: NA | U22: NA | V22: NA | W22: NA | X22: NA | Y22: NA | Z22: NA | AA22: NA | AB22: NA | AC22: NA | AD22: 28 Apr - Testcase updation is in progress. And will start testing once test case updation gets done. Raised a BB and assigned back to dev 30 Apr - Testing is in progress | AE22: Exceeds Expectation
A23: 24 | B23: MSB Mobile Kaleida | C23: 46129 | D23: 46142 | E23: 26.5 M Sprint 2 Stretch | F23: Jagdeep/Vaishnavi | G23: 27033 | H23: MSBA - MAUI - error presented after logo | I23: Defect Fixed | J23: 2 | L23: 6 | M23: 46140 | N23: 46141 | O23: NA | P23: Yes | Q23: Rupesh | R23: Rupesh/Sambath | S23: NA | T23: https://dev.azure.com/heartlandschools/Mobile/_git/MSBA.MAUI/pullrequest/48698 | U23: 46140 | V23: 46141 | W23: Ashwin | X23: NA | Y23: Avery | Z23: 46141 | AA23: NA | AB23: POV done with Bavithra(By Shared Video) No Comment | AC23: NA | AD23: 28 April - Will reroduce first then will start work on it. 29 April - will do peer a testing with Rupesh ,if found any issue then will work.. 30-Apr-WIll work on the testing. | AG23: Stretch
A24: 25 | B24: MSB Mobile Kaleida | C24: 46129 | D24: 46142 | E24: 26.5 M Sprint 2 Stretch | F24: Amrit | G24: 26882 | H24: MSBA - Cart Icon does not have the correct MSBA blue background | I24: Defect Peer Review | J24: 1 | L24: 0 | M24: 46141 | N24: NA | O24: NA | P24: NA | Q24: NA | R24: Rupesh/Sambath | S24: NA | T24: https://dev.azure.com/heartlandschools/Mobile/_git/MSBA.MAUI/pullrequest/48721 | U24: Na | V24: NA | W24: NA | X24: NA | Y24: NA | Z24: NA | AA24: NA | AB24: NA | AC24: NA | AD24: 29 Apr- Defect Fixed, Sent for peer testing 30 Apr - PR Ready for Review for internal | AG24: Stretch
A25: 26 | B25: MSB Mobile | C25: 46129 | D25: 46142 | E25: 26.5 M Sprint 2 Stretch | F25: Rupesh | G25: 52964 | H25: MSBA - Admin Settings - BETA build - Require Elevated Privileges | I25: Story Being Developed | J25: 5 | L25: 12 | M25: 46141 | N25: NA | O25: NA | P25: NA | Q25: NA | R25: NA | S25: NA | T25: NA | U25: NA | V25: NA | W25: NA | X25: NA | Y25: NA | Z25: NA | AA25: NA | AB25: NA | AC25: NA | AD25: 29 Apr - started analysing and then willd o the development. 30 Apr - Will continue the development and try to run the internal POV by EOD today. | AE25: Exceeds Expectation | AG25: Stretch
A26: 27 | B26: MSB Mobile Kaleida | C26: 46129 | D26: 46142 | E26: 26.5 M Sprint 2 Stretch | F26: Jagdeep | G26: 48498 | H26: [WAVE] MSBA - Receipt Screen - Show Confirmation/Green Check once SMS/Email Sent | I26: Story Being Developed | J26: 1 | L26: 2 | M26: 46142 | N26: NA | O26: NA | P26: NA | Q26: NA | R26: NA | S26: NA | T26: NA | U26: NA | V26: NA | W26: NA | X26: NA | Y26: NA | Z26: NA | AA26: NA | AB26: NA | AC26: NA | AD26: 30 April - Started work on it in sprint last day, Still working on it. | AF26: This Story took last day of sprint, so still continue working on it . Testing , POV , peer testing pending so it will goes into next sprint. | AG26: Stretch

Sheet 26.5 M Sprint 2-Defect
A1: S.No | B1: Sprint # | C1: Story/Defect ID | D1: Parent Story | E1: Developer | F1: Issue Type | G1: Issue Description | H1: Priority | I1: Defect Source | J1: Type | K1: Status | L1: Root Cause Category | M1: Who Reported It? | N1: Comments
B2: 26.5 M Sprint 2 | C2: 27078 MSBA - MAUI - android phone - app crash when trying to apply filters (regression) | D2: 27019 MSBA - MAUI - phones - cannot drag to sort products | E2: Jagdeep/vaishnavi | F2: Defect | H2: Minor | I2: Manual | J2: Internal | K2: Closed | L2: Development | M2: Client QA | N2: Xamarin to Maui conversion defects
B3: 26.5 M Sprint 2 | C3: 27019 MSBA - MAUI - phones - cannot drag to sort products | D3: 27204 MSBA - MAUI- iOS - Transparency issue in iOS on clicking shift mode icon. (26.5) | E3: Amrit | F3: Defect | H3: Minor | I3: Manual | J3: Internal | K3: Closed | L3: Development | M3: Client QA | N3: Xamarin to Maui conversion defects
B4: 26.5 M Sprint 2 Stretch | C4: 27204 MSBA - MAUI- iOS - Transparency issue in iOS on clicking shift mode icon. (26.5) | D4: 26762 MSBP - allows identical Routing # and Account # for eCheck Autopay, causing silent payment failure and missing notifications. | E4: Jagdeep | F4: Defect | H4: Minor | I4: Manual | J4: Internal | K4: Closed | L4: Development | M4: Client QA | N4: Xamarin to Maui conversion defects
B5: 26.5 M Sprint 2 | C5: 26762 MSBP - allows identical Routing # and Account # for eCheck Autopay, causing silent payment failure and missing notifications. | D5: 27257 MSBP - Android - App navigation hidden under phone navigation (release defect) | E5: Gursewak | F5: Defect | H5: Minor | I5: Manual | J5: External | K5: Closed | L5: Development | M5: Client QA | N5: Enhancement
B6: 26.5 M Sprint 2 | C6: 27257 MSBP - Android - App navigation hidden under phone navigation (release defect) | D6: 27088 MSBP - A - Button does not turn blue even after meeting the entry requirements (regression) | E6: Jagdeep | F6: Defect | H6: Minor | I6: Manual | J6: External | K6: Closed | L6: Development | M6: Client QA | N6: Production defects
B7: 26.5 M Sprint 2 | C7: 27088 MSBP - A - Button does not turn blue even after meeting the entry requirements (regression) | D7: 27275 MSBP - Android - Add to cart button in invoices under nav bar after adding invoice (release defect) | E7: Jagdeep | F7: Defect | H7: Minor | I7: Manual | J7: Internal | K7: Closed | L7: Development | M7: Client QA | N7: Xamarin to Maui conversion defects
B8: 26.5 M Sprint 2 | C8: 27275 MSBP - Android - Add to cart button in invoices under nav bar after adding invoice (release defect) | D8: 27033 MSBA - MAUI - error presented after logo | E8: Gursewak | F8: Defect | H8: Minor | I8: Manual | J8: External | K8: Closed | L8: Development | M8: Client QA | N8: Production defects
B9: 26.5 M Sprint 2 Stretch | C9: 27033 MSBA - MAUI - error presented after logo | D9: 26882 MSBA - Cart Icon does not have the correct MSBA blue background | E9: Jagdeep/Vaishnavi | F9: Defect | H9: Minor | I9: Manual | J9: Internal | K9: Closed | L9: Development | M9: Client QA | N9: Xamarin to Maui conversion defects
B10: 26.5 M Sprint 2 Stretch | C10: 26882 MSBA - Cart Icon does not have the correct MSBA blue background | D10: 26882 MSBA - Cart Icon does not have the correct MSBA blue background | E10: Amrit | F10: Defect | H10: Minor | I10: Manual | J10: Internal | K10: Inprogress | L10: Development | M10: Client QA | N10: Xamarin to Maui conversion defects

Sheet 26.5 M Sprint 1-Status
A1: S.No | B1: Application Name | C1: Sprint Start Date | D1: Sprint End Date | E1: Sprint | F1: Developer | G1: Story ID/Defect ID | H1: Description | I1: Status | J1: Estimated(sp) | K1: Actual(sp) | L1: Actual Hours Worklog | M1: Dev Start Date | N1: Dev End Date | O1: Unit testing | P1: Peer Tested By | Q1: Peer Tested Defects, if any | R1: Peer Reviewed By | S1: Peer Code Review Comments, if any | T1: PR Number/Link | U1: PR Created Date | V1: PR Approved Date | W1: Reviewer 1 | X1: Code Review Comments, if any | Y1: Reviewer 2 | Z1: Approved Date | AA1: Code Review Comments, if any2 | AB1: Internal PO -POV Comments | AC1: Client PO -POV Comments | AD1: Comments | AE1: Does this story meet the expectations? | AF1: Comments | AG1: Sprint Tag
A2: 1 | B2: MSB Mobile | C2: 46115 | D2: 46128 | E2: 26.5 M Sprint 1 | F2: Sambath/ Vaishnavi/Rupesh | G2: 51966 | H2: [WAVE] MSBA - Kaleida - Settings - Apps & Stores | I2: Story Being Developed | J2: 2 | L2: 25.5 | M2: 46071 | N2: NA | O2: NA | P2: NA | Q2: NA | R2: NA | S2: NA | T2: https://dev.azure.com/heartlandschools/Mobile/_git/MSBA.MAUI/pullrequest/47478 | U2: 25/2/2026 | V2: 46094 | W2: Ashwin | X2: NA | Y2: Avery | Z2: 46101 | AA2: NA | AB2: POV done with Bavithra | AD2: 3-Apr - Testing in progress. . 7-Apr - BB testing in progress. 7 Apr - (Amrit)- Worked as supportive for Redirection issue 08 - April - Gursewak - Will work on BB Android/iphone - when scrolling through the settings screen, able to see some white spaces at top and bottom 08-April-EOD-Gursewak-Development completed, tested, did POV with Bavithra, Created PR. (Ashwin marked PR draft -09 April) 09-Apr Sambath - Working with bounce backs, 10 - one BB fixed, that has been approved. . 13 - Apr - Will be testing the 1 bb which was fixed. 15 - Apr - Sambath - Working with New BB 16- Apr - Sambath - Continue to working with BB This story will be on hold until defect 27072 is completed. | AF2: Wait for the Kaleida merge from the develop branch before starting the test. and This story will be on hold until defect 27072 is completed. New Bounce back has been added by letaisa. The testing and fixing the bounce backs took longer than originally estimated | AG2: Main
A3: 2 | B3: MSB Mobile | C3: 46115 | D3: 46128 | E3: 26.5 M Sprint 1 | F3: Rupesh/Amrit/Prem | G3: 52056 | H3: MSBA - Close Out - Offer Portrait and Landscape Orientation | I3: Story Being Developed | J3: 3 | L3: 32.75 | M3: 46097 | N3: NA | O3: NA | P3: NA | Q3: NA | R3: Sambath | S3: NA | T3: https://dev.azure.com/heartlandschools/Mobile/_git/MSBA.MAUI/pullrequest/47877 | U3: 46099 | V3: 46125 | W3: Ashwin | X3: NA | Y3: Avery | Z3: 46126 | AA3: NA | AB3: POV done with Bavithra | AC3: NA | AD3: Yet to check with Ashwin to check the priority. 08 Apr : I will be starting once done with the POV of 27120. 09 Apr : I will be working on the UI issues, found during unit testing. 10 Apr : Will run a POV with Bavithra. 13 Apr : Got some suggestion on my PR from Ashwin, looks like PR has been reviewed on complete file not for my changes only. I will fix the applicable ones. 15 Apr - Tested and raised a BB. And informed to dev to fix the same 16 Apr - Testing and raised a new BB's and assigned back to dev to fix the same | AE3: Exceeds Expectation | AF3: Bounce backs received, will be carriying forward to next sprint because of BB's. | AG3: Main
A4: 3 | B4: MSB Mobile Kaleida | C4: 46115 | D4: 46128 | E4: 26.5 M Sprint 1 | F4: Jagdeep/Vaishnavi | G4: 51972 | H4: [WAVE] MSBA - Kaleida - Settings - Admin Settings | I4: Story Being Developed | J4: 3 | L4: 13 | M4: 46105 | N4: 46125 | O4: NA | P4: NA | Q4: NA | R4: Rupesh/Sambath | S4: Count - 2 * don't hard code the sales tag method DiscardIncompleteFields instead of pass from cancelButtonAction paramsdon't hard code the sales tag method DiscardIncompleteFields instead of pass from cancelButtonAction params * move to AdminSettings validation rule | T4: https://dev.azure.com/heartlandschools/Mobile/_git/MSBA.MAUI/pullrequest/48410 | U4: 46119 | V4: 46127 | W4: Ashwin | X4: NA | Y4: Avery | Z4: 46125 | AA4: Count - 6 1. This PR implements a custom popup using Telerik RadBorder instead of the Kaleida Components KModal * This is only cleared in OnAppearing() but is never used anywhere in the codebase. Remove it and it's usage on line 1031 * Under what scenario would AppSession.UserSettings be null anywhere in SettingsViewModel? If it's never null, remove all the defensive checks. If it can be null, add a guard at OnAppearing instead of scattered checks. * One line - Please format this line properly * This is handled above, no need for the duplicate, could cause race conditions. Delete these lines. * This command is overcomplicated for toggling a radio button. The validation, school lookups, and error handling should live in the property setters and existing validation commands, not in a 70+ line selection handler. Can this be simplified? * These three admin toggle commands (ShiftModeToggledCommand, AllowOversellToggledCommand, CloseDayBlindCountToggledCommand) are architecturally redundant: | AB4: Count - 3 POV done with Bavithra with solved comments:- 1. “School Number and Custom Label value should show if we already selected and come back on the screen. 2. Text not matching in Record sales tag section. 3. Search bar width and custom label entry width looking different | AC4: POV Done with JASON No Comments | AD4: 08 April - Starting work on this defect. 09 April - development completed , Internal PR approved , waiting for client approval. 03 April- First will close my opened regression defect. 06 April - This story still on hold today first will completed the defect 27087 then will start work on it. 07 April - Will continue work on this story and will do internal and external POV today. 08 April - Story under Peer a Review. 09 April - Will work for resolve PR comments regarding Required field popup and remove background image for phone device . 10 April - Story PR approved by Rupesh and Sambath , pending from Ashwin and client side. 14 April - Story ready for testing. will work on the testing. 15 Apr - Testing in progress. 15 April - Will work on BB If found during testing. 16-Apr - Will test this after completing the defects testing. 16 April - Will work on BB issues. | AF4: Major functionality is complete, but QA testing revealed bounce-backs related to sales tag format. These fixes, along with the required POV validation, will extend beyond the current sprint and will go next sprint. | AG4: Main
A5: 4 | B5: MSB Mobile Kaleida | C5: 46115 | D5: 46128 | E5: 26.5 M Sprint 1 | F5: Amrit/Vaishnavi | G5: 51967 | H5: [WAVE] MSBA - Kaleida - Settings - Item Visibility | I5: Story Being Tested | J5: 2 | L5: 20 | M5: 46105 | N5: 46118 | O5: Na | P5: NA | Q5: NA | R5: Rupesh/Sambath | S5: Ashwin - The assignment is redundant since DisplayFeaturedItems already has that value. (3) | T5: https://dev.azure.com/heartlandschools/Mobile/_git/MSBA.MAUI/pullrequest/48175 | U5: 46026 | V5: 15/4/2026 | W5: Ashwin | X5: NA | Y5: Avery | Z5: NA | AA5: Avery Comments(7) Use CurrentUserId instead of AppSession.UserSettings.UserId • Count: 3 Missing AutomationId in toggle switches • Count: 3 Load/Save mismatch for ShowAllStudentsInInvoice • Count: 1 (Critical) XAML structure not following standard pattern • Count: 1 | AB5: POV Done with JASON No Comments | AC5: Na | AD5: 3 Apr - Continue working on Story 6 Apr- Continue working on story 7 Apr - Story Peer Review (Doing some testings with multiple users) 8 Apr - Working on PR comment given by Ashwin 9 Apr- PR Pending from Ashwin and Client 10 Apr - Will solve merge conflicts 13 Apr - Working on save command changes as suggested by Avery 14 Apr - Working on PR Comments and testing 15 Apr - PR Merged story ready for testing 15 Apr - Will work once the 52056 gets done. 16-Apr - Testing in progress. Completed testing in Android and iOS tablet. Execution pending in Mobile devices and iOS18 devices | AE5: Exceeds Expectation | AF5: Testing in progress. Completed testing in Android and iOS tablet. Execution pending in Mobile devices and iOS18 devices. Will not be able to close it today as I need the obsevation clarified from letashia inbetween. | AG5: Main
A6: 5 | B6: MSB Mobile Kaleida | C6: 46115 | D6: 46128 | E6: 26.5 M Sprint 1 | F6: Gursewak | G6: 51968 | H6: [WAVE] MSBA - Kaleida - Settings - Cart and Transactions | I6: Story Being Developed | J6: 3 | L6: 25 | M6: 46105 | N6: 46126 | O6: NA | P6: NA | Q6: NA | R6: Rupesh/Sambath | S6: NA | T6: https://dev.azure.com/heartlandschools/Mobile/_git/MSBA.MAUI/pullrequest/48183 | U6: 46126 | V6: 46126 | W6: Ashwin | X6: NA | Y6: Avery | Z6: 46127 | AA6: Avery Comments (6) Save/Load key mismatch (missing CurrentUserId suffix) • Count: 3 Missing blank line before next property definition • Count: 3 | AB6: POV done with Bavithra No Comment | AC6: NA | AD6: 06 April - Start working on it today, will try to completed and do the POV. 07 April - Some functionality is pending while entering amount on the same page, will work on it, and complete and do the POV and create PR. 08 April - POV done with Bavithra, Also sent the POV video in slack group for client review, but not recieve any feedback yet. Will do code cleaning and create the PR. after that will work on BB scrolling issue on the settings screen 09-April-Jason added comment under POV video for update the new design (POV - Update the Portrait/landscape phone view to be borderless, working on it. https://www.figma.com/design/r24M7rgybpJJgMyntCNhwJ/MSB-Anywhere?node-id=1926-14689&t=QUAXe1OLdPmd88kg-0) 10-April - Ashwin sent comment on slack (Avery has checked in into the MSBA Kaleida branch which is causing conflicts in your PRs. So merge the latest and update the PR.) work on it. also complete the validation process on popup. 13 April - Waiting for merge "51972" story. 14 April - This story "51972" has been merged. Today, I will pull the latest code, merge it into my branch, resolve any merge conflicts, make the necessary code changes, test them, and then create the POV and publish the PR for review. 15 April - Client review pending. 15 April-EOD-Merged, ready for testing.. 16-Apr- Testers will pick this after competing the pending defects and stories. 16 April - Working on BB - App crash when user Deleting the value from required signature field after entering the amount | AE6: Exceeds Expectation | AF6: The story took additional time due to design changes after POV, delayed client feedback, merge conflicts, and dependency on story 51972 (Admin Settings). Final implementation and testing could only be completed after that story was merged. | AG6: Main
A7: 6 | B7: MSB Mobile Kaleida | C7: 46115 | D7: 46128 | E7: 26.5 M Sprint 1 | F7: Gursewak/Amrit/Prem | G7: 27052 | H7: MSBA - MAUI - Android - unable to read entire product description (regression) | I7: Defect Fixed | J7: 0 | L7: 11.5 | M7: 46108 | N7: 46114 | O7: NA | P7: NA | Q7: NA | R7: Rupesh/Sambath | S7: NA | T7: https://dev.azure.com/heartlandschools/Mobile/_git/MSBA.MAUI/pullrequest/48200 | U7: 46115 | V7: 46115 | W7: Ashwin | X7: NA | Y7: Avery | Z7: 46115 | AA7: NA | AB7: POV done with Bavithra No Comment | AC7: NA | AD7: 27 March - Will work, test, do the POV and create the PR 27 March-EOD - Completed defect 27063, start workin on the it, issue has been fixed, facing scrolling issue in iOS trying to resolve it. 30 March - Today will try on fix the scroll issue in iOS, test the defect, do the POV and will create the PR. after that will start work on 51968 31 March - This issue been fixed, Testing and POV pending, will complete today. 01 april - internal and external review pending. 02 April - As discussed with Ashwin on call, Amrit will work on today on same task. Defect Fixed POV DONE, PR Created 06 Apr - Testing Completed | AE7: Exceeds Expectation | AF7: NA | AG7: Main
A8: 7 | B8: MSB Mobile Kaleida | C8: 46115 | D8: 46128 | E8: 26.5 M Sprint 1 | F8: Sambath/Avery | G8: 27072 | H8: MSBA - MAUI - Android - Bottom navigation icons are showing the icons which were not enabled from the Settings menu(regression) | I8: Defect Being Fixed | J8: 0 | L8: 20 | M8: 46111 | N8: NA | O8: NA | P8: NA | Q8: NA | R8: NA | S8: NA | T8: NA | U8: NA | V8: NA | W8: NA | X8: NA | Y8: NA | Z8: NA | AA8: NA | AB8: NA | AC8: NA | AD8: 6 April- Started working with this defect as discussed with ashiwn 7 - April - found the root cause of the defect, and started fixing. 8- Apr - Fixed the issue and testing is pending 13 - Apr - Fixed the issue, waitng for PR resoution 13 Apr - Amrit - First will finish 51967 changes for save commands then will try to check this defect 14-Apr - Sambath - going to work with Avery comments | AF8: This defect has been fixed, but avery took this defect for further investication so it will not be included in the current release. It is planned for the next release due to major changes in the login flow, so for now it is looking by avery | AG8: Main
A9: 8 | B9: MSB Mobile Kaleida | C9: 46115 | D9: 46128 | E9: 26.5 M Sprint 1 | F9: Gursewak/vaishnavi | G9: 27001 | H9: MSBA - MAUI - phones - now only displaying 3 products in landscape (regresssion) | I9: Defect Fixed | J9: 0 | L9: 6 | M9: 46113 | N9: 46113 | O9: NA | P9: NA | Q9: NA | R9: Rupesh/Sambath | S9: NA | T9: https://dev.azure.com/heartlandschools/Mobile/_git/MSBA.MAUI/pullrequest/48166 | U9: 46113 | V9: 46113 | W9: Ashwin | X9: Avery Comments (3) Event handler not unsubscribed in OnDisappearing() • Count: 1 Duplicate property (already exists in ViewModelBase) • Count: 1 XAML margin formatting should be Margin="5, 10" • Count: 1 | Y9: Avery | Z9: 46114 | AA9: This needs to be unsubscribed. Add in OnDisappearing(): This property is identical to CurrentDeviceOrientation already defined in ViewModelBase (which this class inherits from). Remove these lines and use the inherited property instead. | AB9: POV done with Bavithra No Comments. | AC9: NA | AD9: 3-Apr - Testing in progress. | AE9: Exceeds Expectation | AF9: NA | AG9: Main
A10: 9 | B10: MSB Mobile Kaleida | C10: 46115 | D10: 46128 | E10: 26.5 M Sprint 1 | F10: Jagdeep/Prem | G10: 27087 | H10: MSBP - Total value shows incorrect once removing the promotion code(regression) | I10: Defect Fixed | J10: 1 | L10: 4 | M10: 46113 | N10: 46118 | O10: NA | P10: NA | Q10: NA | R10: Rupesh/Sambath | S10: NA | T10: https://dev.azure.com/heartlandschools/Mobile/_git/MSBP.MAUI/pullrequest/48237 | U10: 46118 | V10: 46118 | W10: Ashwin | X10: NA | Y10: Avery | Z10: 46118 | AA10: NA | AB10: "POV done with Ashwin No Comment" | AC10: NA | AD10: 03 April - Will start work on it after discussion with sambath and vashnavi. 06 April - Today will start work on it and will complete it, as discussion with Ashwin. 07 April - Defect ready for testing. 07 Apr - Testing is in progress | AE10: Exceeds Expectation | AG10: Main
A11: 10 | B11: MSB Mobile | C11: 46115 | D11: 46128 | E11: 26.5 M Sprint 1 | F11: Amrit/Prem | G11: 27098 | H11: MSBP - I/A - Search text is not clearing even after adding a product to the cart or switching to a different school (regression) | I11: Defect Fixed | J11: 0.5 | L11: 6 | M11: 46113 | N11: 46113 | O11: NA | P11: NA | Q11: NA | R11: Rupesh/Sambath | S11: NA | T11: https://dev.azure.com/heartlandschools/Mobile/_git/MSBP.MAUI/pullrequest/48172 | U11: 46113 | V11: 46085 | W11: Ashwin | X11: NA | Y11: Avery | Z11: 46085 | AA11: NA | AB11: POV done with Bavithra No Comment | AC11: NA | AD11: 3 Apr - PR Pending from Client Side (Approved by Ashwin,rupesh,sambath) 06 Apr - Testing Completed | AE11: Exceeds Expectation | AG11: Main
A12: 11 | B12: MSB Mobile | C12: 46115 | D12: 46128 | E12: 26.5 M Sprint 1 | F12: Jagdeep/Gursewak | G12: 27078 | H12: 27078 MSBA - MAUI - android phone - app crash when trying to apply filters (regression) | I12: Defect Peer Review | J12: 0 | L12: 9.5 | M12: 46113 | N12: 46127 | O12: NA | P12: NA | Q12: NA | R12: Rupesh/Sambath | S12: Count: 1 why ExecuteGroupsStores was removed, Group filter is required after changing the stores | T12: https://dev.azure.com/heartlandschools/Mobile/_git/MSBA.MAUI/pullrequest/48418 | U12: 46127 | V12: NA | W12: NA | X12: NA | Y12: NA | Z12: NA | AA12: NA | AB12: "POV done with Ashwin No Comment" | AC12: NA | AD12: 06 - April - not yet started to work 14 - April - Today will investigate and try to find root cause and then will work for fix it. 15 - April - First will work for BB coming on story 51972 then will start continue work on it. 15 - April - Work with Jagdeep on the defect. | AE12: Exceeds Expectation | AF12: This defect assigned to Jadeep on (14 April) by Ashwin. On 15 April defect fixed and done POV and Created the PR , review pending from Ashwin and client side. Because review and testing pending so it will go in next sprint. | AG12: Main
A13: 12 | B13: MSB Mobile Kaleida | C13: 46115 | D13: 46128 | E13: 26.5 M Sprint 1 | F13: Jagdeep/Prem | G13: 27104 | H13: MSBP - I/A - Missing Profile Information screen, Answer Field appears disabled and only becomes enabled on switching to navigation icons(regression) | I13: Defect Fixed | J13: 1 | L13: 4 | M13: 46114 | N13: 46115 | O13: NA | P13: NA | Q13: NA | R13: Rupesh | S13: NA | T13: https://dev.azure.com/heartlandschools/Mobile/_git/MSBP.MAUI/pullrequest/48222 | U13: 46115 | V13: 46116 | W13: Ashwin | X13: NA | Y13: Avery | Z13: 46116 | AA13: NA | AB13: "POV done with Bavithra No Comment" | AC13: NA | AD13: 03 April - will continue work on these defect. 03 April - defect fixed done POV and created the PR. 06 April - defect ready for testing. 06 Apr - Testing Completed | AE13: Exceeds Expectation | AG13: Main
A14: 13 | B14: MSB Mobile | C14: 46115 | D14: 46128 | E14: 26.5 M Sprint 1 | F14: Rupesh/Prem | G14: 27105 | H14: MSBP - A - Missing Profile Information screen, Text (We need to update your profile) is shows in cut off mode(regression) | I14: Defect Fixed | J14: 0.5 | L14: 1 | M14: 46114 | N14: 46118 | O14: NA | P14: NA | Q14: NA | R14: Jagdeep | S14: NA | T14: https://dev.azure.com/heartlandschools/Mobile/_git/MSBP.MAUI/pullrequest/48201 | U14: 46114 | V14: 46115 | W14: Ashwin | X14: NA | Y14: Avery | Z14: 46115 | AA14: NA | AB14: POV done with Bavithra. | AC14: NA | AD14: 02 April - Will reproduce it first and then fix. PR is pending from internal team. 06 Apr - Testing Completed | AE14: Exceeds Expectation | AG14: Main
A15: 14 | B15: MSB Mobile | C15: 46115 | D15: 46128 | E15: 26.5 M Sprint 1 | F15: Rupesh/Prem | G15: 27106 | H15: MSBP - I/A - Bottom navigation icons should not present in Missing Profile Information screen(regression) | I15: Defect Fixed | J15: 0.5 | L15: 1 | M15: 46114 | N15: 46118 | O15: NA | P15: NA | Q15: NA | R15: Jagdeep | S15: NA | T15: https://dev.azure.com/heartlandschools/Mobile/_git/MSBP.MAUI/pullrequest/48201 | U15: 46114 | V15: 46115 | W15: Ashwin | X15: NA | Y15: Avery | Z15: 46115 | AA15: NA | AB15: POV done with Bavithra. | AC15: NA | AD15: 02 April - Will reproduce it first and then fix. PR is pending from internal team. 06 Apr - Testing Completed | AE15: Exceeds Expectation | AG15: Main
A16: 15 | B16: MSB Mobile | C16: 46115 | D16: 46128 | E16: 26.5 M Sprint 1 | F16: Prem | G16: 52440 | H16: MSBP CA - Regression/Smoke Test Against Staging 26.4 RC | I16: Story Completed | J16: 1 | L16: 6 | M16: NA | N16: NA | O16: NA | P16: NA | Q16: NA | R16: NA | S16: NA | T16: NA | U16: NA | V16: NA | W16: NA | X16: NA | Y16: NA | Z16: NA | AA16: NA | AB16: NA | AC16: NA | AD16: 03 April - Testing is in Progress 06 Apr - will contiue once the regression defects testing gets done 07 Apr - Testing Completed | AE16: Exceeds Expectation | AG16: Main
A17: 16 | B17: MSB Mobile | C17: 46115 | D17: 46128 | E17: 26.5 M Sprint 1 | F17: Rupesh | G17: 27120 | H17: MSBP - Upon return of sign up from Greenlight, home page is not refreshing to show assign card tray (regression) | I17: Defect Needs More Info | J17: 3 | L17: 12 | M17: 46115 | N17: NA | O17: NA | P17: NA | Q17: NA | R17: NA | S17: NA | Z17: NA | AA17: NA | AD17: 03 April - Will reproduce the issue and then will be fixing it. 06 April - looks like it’s not happening in test environment and happening in staging. Will continue to fix this issue. 07 April : Fixed with another approach(Max attempts). 08 April : Will run the POV with Bavithra and then will be moving on 52056. After POV, raised the PR. 09 April : Comment is resolved given by Sambath, Pending from Ashwin Side. 10 April : Need to implement another approach as the current one may have performance issue. 13 April : Looks like API Issue, Ashwin will discuss with backend team . 14 Apr : As Ashwin suggested, will implement cache approach and see if it fixes the issue. 15 Apr : This has dependency on backend team, so moved to defect needs more info state. | AF17: This has dependency on backend team, so moved to defect needs more info state. | AG17: Main
A18: 17 | B18: MSB Mobile Kaleida | C18: 46115 | D18: 46128 | E18: 26.5 M Sprint 1 | F18: Vaishnavi | G18: 52439 | H18: MSBA - Smoke Test Against 26.4 Web RC | I18: Story Completed | J18: 2 | L18: 4 | M18: NA | N18: NA | O18: NA | P18: NA | Q18: NA | R18: NA | S18: NA | T18: NA | U18: NA | V18: NA | W18: NA | X18: NA | Y18: NA | Z18: NA | AA18: NA | AB18: NA | AC18: NA | AD18: 08 - Apr - Testing in progress 09 Apr - Will continue working on testing | AE18: Exceeds Expectation | AG18: Main
A19: 18 | B19: MSB Mobile | C19: 46115 | D19: 46128 | E19: 26.5 M Sprint 1 | F19: Prem | G19: 52442 | H19: MSBP - Prod Smoke Test Against RC | I19: Story Completed | J19: 1 | L19: 6 | M19: NA | N19: NA | O19: NA | P19: NA | Q19: NA | R19: NA | S19: NA | T19: NA | U19: NA | V19: NA | W19: NA | X19: NA | Y19: NA | Z19: NA | AA19: NA | AB19: NA | AC19: NA | AD19: 08 - Apr - Testing in progress 09 Apr - Testing Completed | AE19: Exceeds Expectation | AG19: Main
A20: 19 | B20: MSB Mobile Kaleida | C20: 46115 | D20: 46128 | E20: 26.5 M Sprint 1 | F20: Jagdeep/Prem | G20: 27142 | H20: MSBP CA - iOS - Value is not showing after the decimal point for Sub Total in the Checkout Page(regression) | I20: Defect Fixed | J20: 0 | L20: 5 | M20: 46120 | N20: 46120 | O20: NA | P20: NA | Q20: NA | R20: Rupesh/Sambath | S20: NA | T20: https://dev.azure.com/heartlandschools/Mobile/_git/MSBP.MAUI/pullrequest/48288 | U20: 46120 | V20: 46121 | W20: Ashwin | X20: NA | Y20: Avery | Z20: 46121 | AA20: NA | AB20: "POV done with Bavithra No Comment" | AC20: NA | AD20: 08 April - Starting work on this defect. 09 April - development completed , Internal PR approved , waiting for client approval. 10 April - defect ready for testing. Testing was blocked due to login issues in Test environment. 13 April - Testing completed | AE20: Exceeds Expectation | AG20: Main
A21: 20 | B21: MSB Mobile | C21: 46115 | D21: 46128 | E21: 26.5 M Sprint 1 | F21: Sambath/vaishnavi | G21: 27162 | H21: MSBP - Home Screen is blank when logged in with the user credential created in Web MSB (26.4) | I21: Defect Fixed | J21: 0 | L21: 17.5 | M21: 46122 | N21: 46126 | O21: NA | P21: NA | Q21: NA | R21: Rupesh | S21: NA | T21: https://dev.azure.com/heartlandschools/Mobile/_git/MSBP.MAUI/pullrequest/48409 | U21: 46126 | V21: 46126 | W21: Ashwin | X21: NA | Y21: Avery | Z21: 46126 | AA21: NA | AB21: "POV done with Bavithra No Comment" | AC21: NA | AD21: 10-Apr - Merged . ready for testing. 16-Aprl- testing in progress. | AE21: Exceeds Expectation | AG21: Main
A22: 21 | B22: MSB Mobile | C22: 46115 | D22: 46128 | E22: 26.5 M Sprint 1 | F22: Rupesh/vaishnavi | G22: 27119 | H22: MSBP - Showing Portal Cards from Other Districts In Household | I22: Defect Fixed | J22: 5 | L22: 14 | M22: 46125 | O22: NA | P22: NA | Q22: NA | R22: Sambath | S22: NA | T22: https://dev.azure.com/heartlandschools/Mobile/_git/MSBP.MAUI/pullrequest/48422 | U22: 46127 | V22: 04/152026 | W22: Ashwin | X22: NA | Y22: Avery | Z22: 46127 | AA22: Code has been reverted due to UI change but that is not part of this defect, so avery added comments to revert it back Please revert the StudentProfileSheet.xaml changes and keep only the HomeViewModel.cs changes. The layout changes here require additional QA effort and are out of scope for this defect. | AB22: POV done with Ashwin | AC22: NA | AD22: 113 Apr : Will anyalyze first and the will start the development. 14 Apr : After 27120, I will move on this. 15 Apr : Will try to do the POV and raise the PR.. 16-Apr - Testing completed. checking with Letashia for confirmation on the scenarios which needs to covered as this is a prod issue. Testing completed. got confirmation from letashia | AE22: Exceeds Expectation | AG22: Main
A23: 22 | B23: MSB Mobile Kaleida | C23: 46115 | D23: 46128 | E23: 26.5 M Sprint 1 | F23: Jagdeep/Prem | G23: 52193 | H23: [WAVE] MSBA - Kaleida - Side Menu - Update Shift Mode Start/End and Open Cash Drawer Buttons | I23: Story Completed | J23: 2 | L23: 7 | M23: 46097 | N23: 46122 | O23: NA | P23: NA | Q23: NA | R23: Rupesh | S23: NA | T23: https://dev.azure.com/heartlandschools/Mobile/_git/MSBA.MAUI/pullrequest/47973 | U23: 3.24/2026 | V23: 3.24/2026 | W23: Ashwin | X23: NA | Y23: Avery | Z23: 46106 | AA23: Comment count:- 2 1. This should be using PrimaryGhost buttonType. Can be simplified to: 2. Replace these with: Padding="24,8" | AB23: "POV done with Bavithra No Comment" | AC23: POV done with Jason, No Comment. | AD23: 10-Apr - Merged . ready for testing. 14-Aprl- testing in progress. | AE23: Exceeds Expectation | AG23: Main
A24: 23 | B24: MSB Mobile Kaleida | C24: 46115 | D24: 46128 | E24: 26.5 M Sprint 1 Stretch | F24: Amrit | G24: 27019 | H24: MSBA - MAUI - phones - cannot drag to sort products | I24: Defect Being Fixed | J24: 3 | L24: 5 | M24: 46127 | N24: NA | O24: NA | P24: NA | Q24: NA | R24: NA | S24: NA | T24: Na | U24: NA | V24: NA | W24: NA | X24: NA | Y24: NA | Z24: NA | AA24: NA | AB24: NA | AC24: NA | AD24: 15 Apr - Analyzing and trying to reproduce 15 Apr - Defect reproduced now fixing. 16 Apr - if no BB on main task then will complete testing and POV | AF24: Currently on hold supporting team members for their main stories | AG24: Stretch
A25: 24 | B25: MSB Mobile Kaleida | C25: 46115 | D25: 46128 | E25: 26.5 M Sprint 1 | F25: Prem | G25: 52194 | H25: [WAVE] MSBA - Kaleida - Update Shift Mode Status Icons on Top Header Bar | I25: Story Being Tested | J25: 2 | M25: NA | N25: NA | O25: NA | P25: NA | Q25: NA | R25: NA | S25: NA | T25: NA | U25: NA | V25: NA | W25: NA | X25: NA | Y25: NA | Z25: NA | AA25: NA | AB25: NA | AC25: NA | AD25: 16 Apr - Will start once the testing for 52056 gets completed.Started testing. Yet to do the executions | AE25: Exceeds Expectation | AG25: Main
A26: 25 | B26: MSB Mobile | C26: 46115 | D26: 46128 | E26: 26.5 M Sprint 1 | F26: Letashia/Offshore team | G26: 52655 | H26: MSBA - End to End Testing of Maui [Time Box] Pt 4 | I26: Story Completed | J26: 3 | L26: 29 | M26: NA | N26: NA | O26: NA | P26: NA | Q26: NA | R26: NA | S26: NA | T26: NA | U26: NA | V26: NA | W26: NA | X26: NA | Y26: NA | Z26: NA | AA26: NA | AB26: NA | AC26: NA | AD26: Testers and developers will be logging the worklogs for the regression defects. | AE26: Exceeds Expectation | AG26: Main

Sheet 26.5 M Sprint 1-Defect
A1: S.No | B1: Sprint # | C1: Story/Defect ID | D1: Parent Story | E1: Developer | F1: Issue Type | G1: Issue Description | H1: Priority | I1: Defect Source | J1: Type | K1: Status | L1: Root Cause Category | M1: Who Reported It? | N1: Comments
B2: 26.5 M Sprint 1 | C2: 27052 MSBA - MAUI - Android - unable to read entire product description (regression) | D2: 27052 MSBA - MAUI - Android - unable to read entire product description (regression) | E2: Gursewak | F2: Defect | H2: Minor | I2: Manual | J2: External | K2: Closed | L2: Development | M2: Client QA | N2: Xamarin to Maui conversion defects
B3: 26.5 M Sprint 1 | C3: 27001 MSBA - MAUI - phones - now only displaying 3 products in landscape (regresssion) | D3: 27001 MSBA - MAUI - phones - now only displaying 3 products in landscape (regresssion) | E3: Gursewak | F3: Defect | H3: Minor | I3: Manual | J3: External | K3: Closed | L3: Development | M3: Client QA | N3: Xamarin to Maui conversion defects
B4: 26.5 M Sprint 1 | C4: 27087 MSBP - Total value shows incorrect once removing the promotion code(regression) | D4: 27087 MSBP - Total value shows incorrect once removing the promotion code(regression) | E4: Jagdeep | F4: Defect | H4: Minor | I4: Manual | J4: External | K4: Closed | L4: Development | M4: Relevantz QA | N4: Xamarin to Maui conversion defects
B5: 26.5 M Sprint 1 | C5: 27098 MSBP - I/A - Search text is not clearing even after adding a product to the cart or switching to a different school (regression) | D5: 27098 MSBP - I/A - Search text is not clearing even after adding a product to the cart or switching to a different school (regression) | E5: Amrit | F5: Defect | H5: Minor | I5: Manual | J5: External | K5: Closed | L5: Development | M5: Relevantz QA | N5: Xamarin to Maui conversion defects
B6: 26.5 M Sprint 1 | C6: 27078 MSBA - MAUI - android phone - app crash when trying to apply filters (regression)" | D6: 27078 MSBA - MAUI - android phone - app crash when trying to apply filters (regression)" | E6: Sambath | F6: Defect | H6: Minor | I6: Manual | J6: External | K6: Inprogress | L6: Development | M6: Client QA | N6: Xamarin to Maui conversion defects
B7: 26.5 M Sprint 1 | C7: 27104 MSBP - I/A - Missing Profile Information screen, Answer Field appears disabled and only becomes enabled on switching to navigation icons(regression) | D7: 27104 MSBP - I/A - Missing Profile Information screen, Answer Field appears disabled and only becomes enabled on switching to navigation icons(regression) | E7: Jagdeep | F7: Defect | H7: Minor | I7: Manual | J7: External | K7: Closed | L7: Development | M7: Relevantz QA | N7: Xamarin to Maui conversion defects
B8: 26.5 M Sprint 1 | C8: 27105 MSBP - A - Missing Profile Information screen, Text (We need to update your profile) is shows in cut off mode(regression) | D8: 27105 MSBP - A - Missing Profile Information screen, Text (We need to update your profile) is shows in cut off mode(regression) | E8: Rupesh | F8: Defect | H8: Minor | I8: Manual | J8: External | K8: Closed | L8: Development | M8: Relevantz QA | N8: Xamarin to Maui conversion defects
B9: 26.5 M Sprint 1 | C9: 27106 MSBP - I/A - Bottom navigation icons should not present in Missing Profile Information screen(regression) | D9: 27106 MSBP - I/A - Bottom navigation icons should not present in Missing Profile Information screen(regression) | E9: Rupesh | F9: Defect | H9: Minor | I9: Manual | J9: External | K9: Closed | L9: Development | M9: Relevantz QA | N9: Xamarin to Maui conversion defects
B10: 26.5 M Sprint 1 | C10: 27120 MSBP - Upon return of sign up from Greenlight, home page is not refreshing to show assign card tray (regression) | D10: 27120 MSBP - Upon return of sign up from Greenlight, home page is not refreshing to show assign card tray (regression) | E10: Rupesh | F10: Defect | H10: Minor | I10: Manual | J10: External | K10: Inprogress | L10: Development | M10: Client QA | N10: Xamarin to Maui conversion defects
B11: 26.5 M Sprint 1 | C11: 27142 MSBP CA - iOS - Value is not showing after the decimal point for Sub Total in the Checkout Page(regression) | D11: 27142 MSBP CA - iOS - Value is not showing after the decimal point for Sub Total in the Checkout Page(regression) | E11: Jagdeep | F11: Defect | H11: Minor | I11: Manual | J11: External | K11: Closed | L11: Development | M11: Relevantz QA | N11: Xamarin to Maui conversion defects
B12: 26.5 M Sprint 1 | C12: 27162-MSBP - Home Screen is blank when logged in with the user credential created in Web MSB (26.4) | D12: 27162-MSBP - Home Screen is blank when logged in with the user credential created in Web MSB (26.4) | E12: Sambath | F12: Defect | H12: Minor | I12: Manual | J12: External | K12: Closed | L12: Development | M12: Relevantz QA | N12: Xamarin to Maui conversion defects
B13: 26.5 M Sprint 1 | C13: 27119-MSBP - Showing Portal Cards from Other Districts In Household | D13: 27119-MSBP - Showing Portal Cards from Other Districts In Household | E13: Rupesh | F13: Defect | H13: Minor | I13: Manual | J13: External | K13: Closed | L13: Development | M13: Relevantz QA | N13: Xamarin to Maui conversion defects

Sheet 26.4 M Sprint 3-Status 
A1: S.No | B1: Application Name | C1: Sprint Start Date | D1: Sprint End Date | E1: Sprint | F1: Developer | G1: Story ID/Defect ID | H1: Description | I1: Status | J1: Estimated(sp) | K1: Actual(sp) | L1: Actual Hours Worklog | M1: Dev Start Date | N1: Dev End Date | O1: Unit testing | P1: Peer Tested By | Q1: Peer Tested Defects, if any | R1: Peer Reviewed By | S1: Peer Code Review Comments, if any | T1: PR Number/Link | U1: PR Created Date | V1: PR Approved Date | W1: Reviewer 1 | X1: Code Review Comments, if any | Y1: Reviewer 2 | Z1: Approved Date | AA1: Code Review Comments, if any2 | AB1: Internal PO -POV Comments | AC1: Client PO -POV Comments | AD1: Comments | AE1: Does this story meet the expectations? | AF1: Comments | AG1: Sprint Tag
A2: 1 | B2: MSB Mobile | C2: 46101 | D2: 46114 | E2: 26.4 M Sprint 3 | F2: Sambath/ Vaishnavi/Rupesh | G2: 51966 | H2: [WAVE] MSBA - Kaleida - Settings - Apps & Stores | I2: Story Being Tested | J2: 3 | L2: 35 | M2: 46071 | N2: NA | O2: NA | P2: NA | Q2: NA | R2: Sambath | S2: Used KDivider unnecessary places, model clsass refference not propery used. | T2: https://dev.azure.com/heartlandschools/Mobile/_git/MSBA.MAUI/pullrequest/47478 | U2: 25/2/2026 | V2: 46094 | W2: Ashwin | X2: NA | Y2: Avery | Z2: 46101 | AA2: Move to color resource file(4) , Changed all maui native controls into Kaleida controls, code refactoring changes. | AB2: POV done with Bavithra | AD2: 20-Mar - Deployment failed. sambath will be checking that and resolve the issue. 23 - Vaishnavi - will be starting the testing today. 24 - Testing in progress. created BB for the issue identified. 25- Rupesh- will be working on BB issue. 25- Sambath i working with BB issues 26-Sambath working with app crash bb issue. 31-mar - Regression defects are priority. will be working on the MSBA regression defects later will work on this. . 2-Apr - Will test the bb once completing the greenlight regression. This story includes testing in 4 different device and 4 different orientations. Will not be able to complete the testing by today. | AE2: Needs Improvement | AF2: This story has been delayed due to new Kaleida control changes. At the same time, the client is working with Kaleida control libraries, which has caused multiple issues while integrating the control into the MSBA project. In addition, Some new AC has been updated, which has further delayed the move to testing.. 2 - Apr - This story will be challenging to complete it today as we have to run the test cases in 4 different physical devices(mobile/tablet), each device with portrait and landscape mode and also with ios26 OS versions. This story was taken to testing on 1st April EOD only. | AG2: Main
A3: 2 | B3: MSB Mobile Kaleida | C3: 46101 | D3: 46114 | E3: 26.4 M Sprint 3 | F3: Amrit/Vaishnavi/Prem | G3: 46158 | H3: MSBP - Tickets - Season Passes | I3: Story Completed | J3: 2 | L3: 54.75 | M3: 46080 | N3: 46145 | O3: NA | P3: NA | Q3: NA | R3: Rupesh/Sambath | S3: Selvam Sambath Count: 14 • Remove StrokeThickness • Remove Margin • Move logic from code-behind to XAML • Use DataTriggers for expand/collapse icons • Use Core.FontAwesome instead of hardcoded glyphs • Move strings to resources • Replace hardcoded values • Remove unnecessary code Majella Ashwin Count: 6 • Remove unnecessary curly braces • Simplify if/else statements • Improve alignment and readability • Remove unnecessary layouts • Use localization Kumar Rupesh Count: 6 • Move else to new line • Simplify conditions into single line • Remove unnecessary brackets • Use static colors • Improve layout structure | T3: https://dev.azure.com/heartlandschools/Mobile/_git/MSBP.MAUI/pullrequest/47624 | U3: 46176 | V3: 46268 | W3: Rupesh,Ashwin | X3: NA | Y3: Avery | Z3: 46298 | AA3: Wold Avery Count: 8 Replace hardcoded colors with static resources Remove unused methods Replace AsyncCommand with Command Remove redundant API calls Merge duplicate methods Cache computed lists Remove duplicate UI elements Delete unused templates | AB3: Internal POV done with Vaishnavi, Bavithra - 1 comment regarding bottomsheet size and fixed | AC3: POV done with Jason, No Comment. | AD3: 20 Mar - PR is in internal Review (Approved by rupesh and ashwin) 23 Mar - PR Review pending from Sambath 24 - story ready for testing 24 Mar - Tested and Blocked due to transactions getting failed 25 Mar - Testing Completed | AE3: Exceeds Expectation | AG3: Main
A4: 3 | B4: MSB Mobile | C4: 46101 | D4: 46114 | E4: 26.4 M Sprint 3 | F4: Sambath/ Gursewak/Prem | G4: 26897 | H4: MSBA - MAUI -Android - recent students search cut off (regression) | I4: Defect Fixed | J4: 3 | L4: 5.5 | M4: 46099 | N4: 46100 | O4: NA | P4: NA | Q4: NA | R4: Rupesh | S4: NA | T4: https://dev.azure.com/heartlandschools/Mobile/_git/MSBA.MAUI/pullrequest/47844?_a=files | U4: 46098 | V4: 46101 | W4: Ashwin | X4: remobed the RecentHeaderRowHeight property from viewmodel | Y4: Avery | Z4: 20/3/2026 | AA4: NA | AB4: Done the POV with Bavithra | AC4: NA | AD4: 20 Mar - Testing Completed | AE4: Exceeds Expectation | AG4: Main
A5: 4 | B5: MSB Mobile Kaleida | C5: 46101 | D5: 46114 | E5: 26.4 M Sprint 3 | F5: Gursewak/Prem | G5: 52194 | H5: [WAVE] MSBA - Kaleida - Update Shift Mode Status Icons on Top Header Bar | I5: Story Needs More Info | J5: 3 | L5: 12.25 | M5: 46097 | N5: 46100 | O5: NA | P5: NA | Q5: NA | R5: Rupesh | S5: 1. Can we give some other name fo Text. | T5: https://dev.azure.com/heartlandschools/Mobile/_git/MSBA.MAUI/pullrequest/47852?_a=files | U5: 46099 | V5: 46100 | W5: Ashwin | X5: NA | Y5: Avery | Z5: 46101 | AA5: Double command execution: parent HorizontalStackLayout has a TapGestureRecognizer and KStatusChip has its own Command binding. Since KStatusChip internally wraps a TapGestureRecognizer that executes Command, tapping fires GoToAsync("CloseDaySession") twice. Remove the outer TapGestureRecognizer from the HorizontalStackLayout for the shift chip, or remove the Command binding from KStatusChip. Rather than adding a new StopWatchOn = "\uf2f2" constant, just update the existing Stopwatch = "\u23f1" to "\uf2f2". \u23f1 is the correct FA glyph. Stopwatch has no usages anywhere in the codebase so there's no risk of breakage, and it keeps the file clean with a single stopwatch constant. | AB5: POV done with Bavithra No Comments. | AC5: POV done with Jason, No Comment. | AD5: 20 March - Client review pending. 20 Mar - Will work on udpating test cases 20 March - Merged, ready for test. 23 mar - Completed test case review comments From RJ - in order to be able to test, we have added 51972 and 51968 as a related items which will need to be completed before QA is able to test this user story. | AF5: Story still on hold , 51972 will have to be completed first in order to be able to test. | AG5: Main
A6: 5 | B6: MSB Mobile Kaleida | C6: 46101 | D6: 46114 | E6: 26.4 M Sprint 3 | F6: Jagdeep/Prem | G6: 52193 | H6: WAVE] MSBA - Kaleida - Side Menu - Update Shift Mode Start/End and Open Cash Drawer Buttons | I6: Story Needs More Info | J6: 2 | L6: 0 | M6: 46097 | N6: 46098 | O6: NA | P6: NA | Q6: NA | R6: Rupesh/Sambath | S6: NA | T6: https://dev.azure.com/heartlandschools/Mobile/_git/MSBA.MAUI/pullrequest/47973 | U6: 46097 | V6: NA | W6: Ashwin | X6: NA | Y6: Avery | Z6: NA | AA6: Comment count:- 2 1. This should be using PrimaryGhost buttonType. Can be simplified to: 2. Replace these with: Padding="24,8" | AB6: POV done with Bavithra No Comments. | AC6: POV done with Jason, No Comment. | AD6: 23 Mar- 52193 depends on 51972, will have to have 51968 completed first.(So 51972 will have to be completed first in order to be able to test.) | AF6: Story still on hold , 51972 will have to be completed first in order to be able to test. | AG6: Main
A7: 6 | B7: MSB Mobile | C7: 46101 | D7: 46114 | E7: 26.4 M Sprint 3 | F7: Ashwin/vaishnavi | G7: 26886 | H7: MSBA - MAUI - Close day is missing EMV transactions from Expected payment summary and Sales summary and credit total (regression) | I7: Defect Fixed | J7: 0 | K7: 0 | L7: 2 | M7: NA | N7: NA | O7: NA | P7: NA | Q7: NA | R7: NA | S7: NA | T7: https://dev.azure.com/heartlandschools/Mobile/_git/MSBA.MAUI/pullrequest/47979 | U7: 46105 | V7: 46105 | W7: NA | X7: NA | Y7: Avery | Z7: 46105 | AA7: NA | AB7: NA | AC7: NA | AD7: will work on the testing part after completing the pending testing stories/defects/ . 26-Mar - will work on this after updating the test cases for regression suite. | AE7: Exceeds Expectation | AG7: Main
A8: 7 | B8: MSB Mobile Kaleida | C8: 46101 | D8: 46114 | E8: 26.4 M Sprint 3 | F8: Jagdeep/Prem | G8: 26977 | H8: MSBA - MAUI - iOS - Error message behind other popup in shift mode (regression) | I8: Defect Fixed | J8: 0 | L8: 4 | M8: 46099 | N8: 46099 | O8: NA | P8: NA | Q8: NA | R8: Rupesh/Sambath | S8: NA | T8: https://dev.azure.com/heartlandschools/Mobile/_git/MSBA.MAUI/pullrequest/47882 | U8: 46099 | V8: 46099 | W8: Ashwin | X8: NA | Y8: Avery | Z8: 46101 | AA8: Comment count:- 1 1. Please restore these TODOs and the corresponding commented out ShowCustomDialogAsync because we have not yet implemented the Kaleida custom dialog. Removing them here is inconsistent and may cause these to be missed when the Kaleida migration is completed. | AB8: POV done with Bavithra No Comments. | AC8: NA | AD8: 20 March- PR approved internally and Ashwin side , waiting for client approval. 23 March - PR approved internally and client side , and Merged now it’s ready for testing. Will start the testing today. 24 Mar - Testing Completed | AE8: Exceeds Expectation | AG8: Main
A9: 8 | B9: MSB Mobile Kaleida | C9: 46101 | D9: 46114 | E9: 26.4 M Sprint 3 | F9: Gursewak/vaishnavi | G9: 52433 | H9: MSBP - Kaleida - Use Kaleida Components: Bottom Nav | I9: Story Completed | J9: 2 | L9: 8 | M9: 46101 | N9: 46105 | O9: NA | P9: NA | Q9: NA | R9: Rupesh/Sambath | S9: NA | T9: https://dev.azure.com/heartlandschools/Mobile/_git/MSBP.MAUI/pullrequest/47936 | U9: 46105 | V9: 46105 | W9: Ashwin | X9: NA | Y9: Avery | Z9: 46105 | AA9: NA | AB9: POV done with Bavithra No Comments. | AC9: POV done with Jason, No Comment. | AD9: 20 March - Start analyzing, reviewing, and working on this story 20 Mar - Vaishnavi- Test case updated 23 March - Working on it, implement K control or colors etc and test. 24 March - Development completed, will test more and will do the POV. Draft PR is already created. after that will start work on "51968" 24-March- merged, ready for test. 25 Mar - Will pick this once testing of 46158 &52435 gets done 26 March - Gursewak - Start work on BB, after fix it Will start work pending changes on 51968. 27 March - As Ashwin sent message on slack "No need to work on the BBs on the MSBP kaleida stories as it will be created as defects as per my discussion. So work on the assigned defects." start working on 27052 and 27063 | AE9: Exceeds Expectation | AG9: Main
A10: 9 | B10: MSB Mobile Kaleida | C10: 46101 | D10: 46114 | E10: 26.4 M Sprint 3 | F10: Amrit/Prem | G10: 27024 | H10: MSBA - MAUI - shift mode error message incorrect (regression) | I10: Defect Fixed | J10: 0 | K10: 0 | L10: 2 | M10: 46101 | N10: 46102 | O10: NA | P10: NA | Q10: NA | R10: Rupesh/Sambath | S10: NA | T10: https://dev.azure.com/heartlandschools/Mobile/_git/MSBA.MAUI/pullrequest/47928 | U10: 46102 | V10: 46101 | W10: Ashwin | X10: NA | Y10: Avery | Z10: 46101 | AA10: NA | AB10: POV Done with Bavithra No Comments. | AC10: NA | AD10: 20 Mar - Analyzing ,Reproducing and fixing 23 Mar - Testing completed | AE10: Exceeds Expectation | AG10: Main
A11: 10 | B11: MSB Mobile | C11: 46101 | D11: 46114 | E11: 26.4 M Sprint 3 | F11: Sambath/Vaishnavi | G11: 27009 | H11: 27009 MSBA - MAUI - iphone - buzzing on barcode scan/not closing camera in background after scan (regression) | I11: Defect Fixed | J11: 0 | K11: 0 | L11: 5 | M11: 46101 | N11: 46101 | O11: NA | P11: NA | Q11: NA | R11: Rupesh | S11: NA | T11: https://dev.azure.com/heartlandschools/Mobile/_git/MSBA.MAUI/pullrequest/47941?_a=files https://dev.azure.com/heartlandschools/Mobile/_git/MSBA.MAUI/pullrequest/48074 | U11: 46108 | V11: 46108 | W11: NA | X11: NA | Y11: Avery | Z11: 46108 | AA11: NA | AB11: NA | AC11: NA | AD11: Fixed the defect, moved to testing 24 Mar - Tested and reopened because app crash. 25 -Mar - Sambath - Working with App crash issue 27-Mar - Sambath fixed the app crash issue for bar code scan. 31-mar - Will start the testing. | AE11: Exceeds Expectation | AG11: Main
A12: 11 | B12: MSB Mobile | C12: 46101 | D12: 46114 | E12: 26.4 M Sprint 3 | F12: Rupesh/Prem | G12: 52434 | H12: MSBP - Kaleida - Use Kaleida Components: Header Bar | I12: Story Completed | J12: 2 | L12: 12.75 | M12: 46101 | N12: 46107 | O12: NA | P12: NA | Q12: NA | R12: Sambath | S12: NA | T12: https://dev.azure.com/heartlandschools/Mobile/_git/MSBP.MAUI/pullrequest/47998 | U12: 46106 | V12: 46106 | W12: Ashwin | X12: NA | Y12: Sean | Z12: 46106 | AA12: NA | AB12: POV done with Bavithra. | AC12: NA | AD12: 20 March -Rupesh - Start analyzing, reviewing, and working on this story. 20 Mar - Vaishnavi- Test case updated 23 March - Rupesh - Will try to finis it today and will run the POV. 24 March - Rupesh - 52434 and 52435 have some common code changes, PR has been raised for 52435 and once it it merged to main, I will merge main to my 52434 and then will be raising the PR. PR has been raised.Internal review is pending from Internal Team/Sambath. 26 Mar - Tested and Raised BB and assigned back to Rupesh to fix the same 27 Mar - Testing is in Completed. Since the new build did not fix the BB. As per discussion in scrum, Informed to Raise this as Defect and close this story if there is no other BB. | AE12: Exceeds Expectation | AG12: Main
A13: 12 | B13: MSB Mobile | C13: 46101 | D13: 46114 | E13: 26.4 M Sprint 3 | F13: Jagdeep/Prem | G13: 52435 | H13: MSBP - Kaleida - Use Kaleida Components: Hamburger Menu | I13: Story Completed | J13: 2 | L13: 11.25 | M13: 46101 | N13: 46104 | O13: NA | P13: NA | Q13: NA | R13: Rupesh/Sambath | S13: Comment count:- 1 1. please remove unused reference | T13: https://dev.azure.com/heartlandschools/Mobile/_git/MSBP.MAUI/pullrequest/47930 | U13: 46104 | V13: 46105 | W13: Ashwin | X13: NA | Y13: Avery | Z13: 46105 | AA13: Comment count:- 3 1. This should be using a KCircleButton. It will also provide the correct pressed state. 2. There's a style for these Section Navigation Items consistent with the figma design: 3.You can remove HorizontalOptions="Start" since it's already provided by the KLink implicit style. | AB13: POV done with Bavithra No Comments. | AC13: POV done with Jason, No Comment. | AD13: 20 March - Start work on this story. 23 March - Development completed , POV has been done and created the PR 24 March - Story in a peer a review. 25 Mar - Tested and Raised a BB and assigned back to Jagdeep to fix the same 26 Mar - BB fix is not available in the latest build. Assigning back to Jagdeep to confirm the same 26 March - BB fixed in development side, need to merge Kalieda.Maui control branch into main branch and then need to create latest build.(Found changes not merged into latest build yet. ) 27 Mar - testing completed | AE13: Exceeds Expectation | AG13: Main
A14: 13 | B14: MSB Mobile | C14: 46101 | D14: 46114 | E14: 26.4 M Sprint 3 | F14: Amrit/Prem | G14: 27036 | H14: MSBA - MAUI - iOS - when in shift mode adding/deleting shift user, can swipe to get to a different box (regression) | I14: Defect Fixed | J14: 0 | K14: 0 | L14: 4 | M14: 46104 | N14: 46104 | O14: NA | P14: Na | Q14: NA | R14: Rupesh/Sambath | S14: NA | T14: https://dev.azure.com/heartlandschools/Mobile/_git/MSBA.MAUI/pullrequest/47961 | U14: 24/3/2026 | V14: 24/3/2026 | W14: Ashwin | X14: NA | Y14: Avery | Z14: 46105 | AA14: NA | AB14: POV done with Bavithra No Comments. | AC14: NA | AD14: 23 - Reproducing and analyzing 24 mar - Testing Completed | AE14: Exceeds Expectation | AG14: Main
A15: 14 | B15: MSB Mobile | C15: 46101 | D15: 46114 | E15: 26.4 M Sprint 3 | F15: Sambath/vaishnavi | G15: 27032 | H15: MSBA - MAUI - phone - app crash on session ending (regression) | I15: Defect Fixed | J15: 0 | K15: 0 | L15: 3 | M15: 46104 | N15: 46105 | O15: NA | P15: NA | Q15: NA | R15: Rupesh | S15: NA | T15: https://dev.azure.com/heartlandschools/Mobile/_git/MSBA.MAUI/pullrequest/47984 | U15: 24/3/2026 | V15: 24/3/2026 | W15: Ashwin | X15: NA | Y15: Avery | Z15: 46106 | AA15: NA | AB15: POV done with Bavithra | AC15: NA | AD15: will work on the testing part after completing the pending testing stories/defects/ 24-Mar - Sambath - fixing the app crash issue. 25 -Mar - After completing the priority task, will work on this. . 27 - Mar - Testing in progress. . | AE15: Exceeds Expectation | AG15: Main
A16: 15 | B16: MSB Mobile | C16: 46101 | D16: 46114 | E16: 26.4 M Sprint 3 | F16: Amrit/Vaishnavi | G16: 27058 | H16: MSBP - Unable to scroll in the payment method drawer under meal money autopay and invoice autopay(regression) | I16: Defect Fixed | J16: 0 | K16: 0 | L16: 5 | M16: 46107 | N16: 46107 | O16: NA | P16: NA | Q16: NA | R16: Rupesh/Sambath | S16: NA | T16: https://dev.azure.com/heartlandschools/Mobile/_git/MSBP.MAUI/pullrequest/48048 | U16: 26/3/2026 | V16: 27/3/2026 | W16: Ashwin | X16: NA | Y16: Avery | Z16: 27/3/2026 | AA16: NA | AB16: POV done with Bavithra No Comments. | AC16: NA | AD16: 26 Mar - Defect Being Fixed (PR Created Sent for Review) 27 Mar - Defect Ready For Testing. 31-mar - Will start the testing. | AE16: Exceeds Expectation | AG16: Main
A17: 16 | B17: MSB Mobile | C17: 46101 | D17: 46114 | E17: 26.4 M Sprint 3 | F17: Prem | G17: 52438 | H17: MSBP - Full Regression 26.4 | I17: Story Completed | J17: 8 | L17: 35.5 | M17: NA | N17: NA | O17: NA | P17: NA | Q17: NA | R17: NA | S17: NA | T17: NA | U17: NA | V17: NA | W17: NA | X17: NA | Y17: NA | Z17: NA | AA17: NA | AB17: NA | AC17: NA | AD17: 26 -Mar - Will be updating the regression suite as per discussion with Letashia. After completing will work on defect 26886 30 Mar - Testing is in Progress 31 Mar - Will continue the testing 01 Apr - Will continue the regression testing 02 Apr - Testing is in Progress. Greenlight test cases validation pending. Waiting response from Letashia. | AG17: Main
A18: 17 | B18: MSB Mobile | C18: 46101 | D18: 46114 | E18: 26.4 M Sprint 3 Stretch | F18: Rupesh/Amrit | G18: 52056 | H18: MSBA - Close Out - Offer Portrait and Landscape Orientation | I18: Story Being Developed | L18: 13 | M18: 46097 | N18: NA | O18: NA | P18: NA | Q18: NA | R18: NA | S18: NA | T18: NA | U18: NA | V18: NA | W18: NA | X18: NA | Y18: NA | Z18: NA | AA18: NA | AB18: NA | AC18: NA | AD18: RJ - Due to main commit stories , it is kept on Hold. | AF18: First working for regression defects, After complete regression defects will start work on it . untill it is on Hold. | AG18: Main
A19: 18 | B19: MSB Mobile Kaleida | C19: 46101 | D19: 46114 | E19: 26.4 M Sprint 3 Stretch | F19: Jagdeep | G19: 51972 | H19: [WAVE] MSBA - Kaleida - Settings - Admin Settings | I19: Story Being Developed | J19: 5 | L19: 6 | M19: 46105 | N19: NA | O19: NA | P19: NA | Q19: NA | R19: NA | S19: NA | T19: NA | U19: NA | V19: NA | W19: NA | X19: NA | Y19: NA | Z19: NA | AA19: NA | AB19: POV done with Bavithra with solved comments:- 1. “School Number and Custom Label value should show if we already selected and come back on the screen. 2Text not matching in Record sales tag section. 3Search bar width and custom label entry width looking different | AC19: NA | AD19: 24 March - Started work on this story. 25 March - Continue work on this story , will complete Blind count settings and Enable Shift mode settings functionality. 26 March - Continue work on this story Blind count and Enabled Shift Mode has been done , will complete OverSell and Sales tag functionality. 27 March - Continue work on this story , will complete it and will POV for this story 30 March - First will work on 27072(regression), After complete it will start work on it . 31 March - first will clean up code and will create PR . 01 April - Hold it due to regression defects need to fix fiest . | AF19: Will be moved to next sprint because priority is regression defect and this is in stretch | AG19: Stretch
A20: 19 | B20: MSB Mobile Kaleida | C20: 46101 | D20: 46114 | E20: 26.4 M Sprint 3 Stretch | F20: Amrit | G20: 51967 | H20: [WAVE] MSBA - Kaleida - Settings - Item Visibility | I20: Story Being Developed | J20: 3 | L20: 3 | M20: 46105 | N20: NA | O20: Na | P20: NA | Q20: NA | R20: NA | S20: NA | T20: NA | U20: NA | V20: NA | W20: NA | X20: NA | Y20: Na | Z20: NA | AA20: NA | AB20: NA | AC20: Na | AD20: 24 Mar - Amrit - Continuing Development 24 Mar - Tablet UI and functionality DONE 25 Mar - Phone UI and functionality in Progress (Facing issue in phone for navigation) 26 Mar - Provided branch to Ashwin for testing Product search cases & Ashwin will cherry pick gursewak fix for featured item then POV will be possible 31 Mar - Will try to connect with vaishnavi for testing and accounts information otherwise blocked 1 Apr - Giving one round of testing then it will ready for POV but keeping it on hold because of regression defects are high priority | AF20: Working on regression defect (main commit) that is on prority. This story is from stretch that's the reason stop work on it right now. when we complete all defect will start work on. | AG20: Stretch
A21: 20 | B21: MSB Mobile Kaleida | C21: 46101 | D21: 46114 | E21: 26.4 M Sprint 3 Stretch | F21: Gursewak | G21: 51968 | H21: [WAVE] MSBA - Kaleida - Settings - Cart and Transactions | I21: Story Approved | J21: 5 | L21: 15 | M21: 46105 | N21: NA | O21: NA | P21: NA | Q21: NA | R21: NA | S21: NA | T21: NA | U21: NA | V21: NA | W21: NA | X21: NA | Y21: NA | Z21: NA | AA21: NA | AB21: NA | AC21: NA | AD21: 24 Mar - will start work on it. first will do the POV for story 52433 24 March-EOD-completed tablet view design. 25 March- Start working on phone design view and data binding after that will do the testing. 26 March - First will start work on 52433 BB, after that will work on the same story for fix the phone changes as discussed with Ashwin on standup call. 27 March - if i will get time then i will work on this, because already assigned two regression defect and story is need to fix the BB. 30 March - will complete the defect 27052, after that will start work on this story. 31 March, Will complete assigned regression defects due to on high prority. | AE21: Exceeds Expectation | AG21: Stretch
A22: 21 | B22: MSB Mobile | C22: 46101 | D22: 46114 | E22: 26.4 M Sprint 3 | F22: Rupesh/vaishnavi | G22: 27034 | H22: MSBA - MAUI - iphone - edges of the printers and readers menus cut off (regression) | I22: Defect Fixed | J22: 0 | L22: 9 | M22: 46107 | N22: 46108 | O22: NA | P22: NA | Q22: NA | R22: Sambath | S22: NA | T22: https://dev.azure.com/heartlandschools/Mobile/_git/MSBA.MAUI/pullrequest/48075 | U22: 46108 | V22: 46108 | W22: Ashwin | X22: NA | Y22: Avery | Z22: 46108 | AA22: 5 times The text alignment should remain HorizontalTextAlignment="Start" | AB22: POV done with Bavithra | AC22: NA | AD22: Will reproduce and then fix the defect. As per the discussion with Ashwin will add some margin/padding then will take it from there.. 31-mar - Will start the testing. | AE22: Exceeds Expectation | AF22: Internal and external review pending. | AG22: Main
A23: 22 | B23: MSB Mobile Kaleida | C23: 46101 | D23: 46114 | E23: 26.4 M Sprint 3 | F23: Gursewak/Amrit | G23: 27052 | H23: MSBA - MAUI - Android - unable to read entire product description (regression) | I23: Defect Ready For Testing | J23: 0 | L23: 11.5 | M23: 46108 | N23: 46114 | O23: NA | P23: NA | Q23: NA | R23: Rupesh/Sambath | S23: NA | T23: https://dev.azure.com/heartlandschools/Mobile/_git/MSBA.MAUI/pullrequest/48200 | U23: 46115 | V23: 46115 | W23: Ashwin | X23: NA | Y23: Avery | Z23: 46115 | AA23: NA | AB23: POV done with Bavithra No Comment | AC23: NA | AD23: 27 March - Will work, test, do the POV and create the PR 27 March-EOD - Completed defect 27063, start workin on the it, issue has been fixed, facing scrolling issue in iOS trying to resolve it. 30 March - Today will try on fix the scroll issue in iOS, test the defect, do the POV and will create the PR. after that will start work on 51968 31 March - This issue been fixed, Testing and POV pending, will complete today. 01 april - internal and external review pending. 02 April - As discussed with Ashwin on call, Amrit will work on today on same task. Defect Fixed POV DONE, PR Created | AE23: Exceeds Expectation | AF23: Moved to ready for testing at the end day of the sprint. | AG23: Main
A24: 23 | B24: MSB Mobile Kaleida | C24: 46101 | D24: 46114 | E24: 26.4 M Sprint 3 | F24: Gursewak/Prem | G24: 27063 | H24: MSBA - MAUI - Save & Close button not centered (regression) | I24: Defect Fixed | J24: 0 | L24: 3 | M24: 46108 | N24: 46108 | O24: NA | P24: NA | Q24: NA | R24: Rupesh/Sambath | S24: NA | T24: https://dev.azure.com/heartlandschools/Mobile/_git/MSBA.MAUI/pullrequest/48135 | U24: 46108 | V24: 46108 | W24: Ashwin | X24: NA | Y24: Avery | Z24: 46108 | AA24: NA | AB24: POV Done with Bavithra No Comment. | AC24: NA | AD24: 27 March - Will work, test, do the POV and create the PR 27 March - EOD - completed this defect, did the POV, tested, PR created, PR merged, now ready for test. 31 - Testing in progress. 31 March - reopen for button bottom space fixes, development and POV done, ready for code review. 01 April - client review pending 01 April - EOD - merged, ready for test. 02 Apr - Testing Completed | AE24: Exceeds Expectation | AF24: We spent some time exploring possible workarounds for the RadSlideView issue, but none of them worked, so we are currently blocked on this because it is offical maui issue as already informed to CLIENT | AG24: Main
A25: 24 | B25: MSB Mobile Kaleida | C25: 46101 | D25: 46114 | E25: 26.4 M Sprint 3 | F25: Amrit/Prem | G25: 27065 | H25: MSBA - MAUI -Android phone - on returning to step 1 from a later step, cannot scroll to pick a shift in close out (regression) | I25: Defect Fixed | J25: 0 | L25: 0 | M25: 46115 | N25: 46026 | O25: NA | P25: NA | Q25: NA | R25: Chandler | S25: NA | T25: https://dev.azure.com/heartlandschools/Mobile/_git/MSBA.MAUI/pullrequest/48191 | U25: 46026 | V25: 46026 | W25: Avery | X25: NA | Y25: Avery | Z25: 46026 | AA25: NA | AB25: POV Done client side by chandler | AC25: NA | AD25: 27 Mar - Reproducing 31 Mar - This is official issue of MAUI no workaround is working till now so totally blocked for now 1 Apr - Will give workaround to radslideview as suggested by Ashwin for 1 hour max 1 Apr - As discussed with client defect is blocked and put down in backlog ( Defect fixed by Chandler and merged) 02 Apr - Testing Completed | AE25: Exceeds Expectation | AG25: Main
A26: 25 | B26: MSB Mobile | C26: 46101 | D26: 46114 | E26: 26.4 M Sprint 3 | F26: Rupesh/Prem | G26: 27047 | H26: MSBA - MAUI - Android tablet - Nav icons small (regression) | I26: Defect Fixed | J26: 0 | L26: 9 | M26: 46108 | N26: 46113 | O26: NA | P26: NA | Q26: NA | R26: Sambath | S26: NA | T26: https://dev.azure.com/heartlandschools/Mobile/_git/MSBA.MAUI/pullrequest/48163 | U26: 46113 | V26: 46113 | W26: Ashwin | X26: NA | Y26: Avery | Z26: 46113 | AA26: NA | AB26: POV done with Bavithra | AC26: NA | AD26: 30 Mar - development is in progress. 31 Mar - Yesterday tried custom handler and other approaches like made the changes in MainActivity and tried fixing setting Shell style. Looks like Android has limitation with BottomNavigationView. Today I will try tabbar approach and see how it goes. 1 Apr - Issue has been fixed, will run the POV today. 02 Apr - Testing Completed | AE26: Exceeds Expectation | AG26: Main
A27: 27 | B27: MSB Mobile Kaleida | C27: 46101 | D27: 46114 | E27: 26.4 M Sprint 3 Stretch | F27: Jagdeep/Prem | G27: 26986 | H27: MSBA - MAUI - iphone - when rotated in landscape mode there are white bars on edges of screen (regression) | I27: Defect Fixed | J27: 0 | L27: 4 | M27: 46111 | N27: NA | O27: NA | P27: NA | Q27: NA | R27: Rupesh | S27: NA | T27: https://dev.azure.com/heartlandschools/Mobile/_git/MSBA.MAUI/pullrequest/48104 | U27: 46111 | V27: 46113 | W27: Ashwin | X27: NA | Y27: Sean | Z27: 46113 | AA27: Comment count:- 1 1. Change this to the following. You don't need the Android switch anymore | AB27: POV done with Bavithra and Ashwin No Comments. | AC27: NA | AD27: 31 March - will do POV and will create PR. 01- April - defect in peer a review , (Internal review done by Rupesh and Ashwin) 02 Apr - Testing Completed | AE27: Exceeds Expectation | AG27: Stretch
A28: 28 | B28: MSB Mobile Kaleida | C28: 46101 | D28: 46114 | E28: 26.4 M Sprint 3 Stretch | F28: Gursewak/vaishnavi | G28: 27000 | H28: MSBA - MAUI - tablet - Barcode on store page now transparent (regression) | I28: Defect Fixed | J28: 0 | L28: 2.5 | M28: 46111 | N28: 46111 | O28: NA | P28: NA | Q28: NA | R28: Rupesh | S28: NA | T28: https://dev.azure.com/heartlandschools/Mobile/_git/MSBA.MAUI/pullrequest/48105 | U28: 46111 | V28: 46111 | W28: Ashwin | X28: NA | Y28: Avery | Z28: 46111 | AA28: NA | AB28: POV done with Ashwin No Comment | AC28: NA | AD28: 30 March - Start working on it. 30 March-EOD-This issue has been fixed, did the POV with Ashwin, create PR, PR merged, now ready for test.. 31-mar - After completing the main | AE28: Exceeds Expectation | AG28: Main
A29: 29 | B29: MSB Mobile Kaleida | C29: 46101 | D29: 46114 | E29: 26.4 M Sprint 3 Stretch | F29: Gursewak/vaishnavi | G29: 27001 | H29: MSBA - MAUI - phones - now only displaying 3 products in landscape (regresssion) | I29: Defect Being Tested | J29: 0 | L29: 6 | M29: 46113 | N29: 46113 | O29: NA | P29: NA | Q29: NA | R29: Rupesh/Sambath | S29: NA | T29: https://dev.azure.com/heartlandschools/Mobile/_git/MSBA.MAUI/pullrequest/48166 | U29: 46113 | V29: 46113 | W29: Ashwin | X29: Change to Margin="5, 10" Change to Margin="3, 5" | Y29: Avery | Z29: NA | AA29: This needs to be unsubscribed. Add in OnDisappearing(): This property is identical to CurrentDeviceOrientation already defined in ViewModelBase (which this class inherits from). Remove these lines and use the inherited property instead. | AB29: POV done with Bavithra No Comments. | AC29: NA | AD29: 01 April, start working on it. 01 April, development completed, POV done, created PR, resolved PR comments added by Ashwin. 02 April - Resolved two comments added by Avery, again client review pending. | AE29: Exceeds Expectation | AG29: Main
A30: 30 | B30: MSB Mobile Kaleida | C30: 46101 | D30: 46114 | E30: 26.4 M Sprint 3 | F30: Jagdeep/Prem | G30: 27086 | H30: MSBP - Value is not showing after the decimal point for Total in the Checkout Page(regression) | I30: Defect Fixed | J30: 0 | L30: 4 | M30: 46112 | N30: 46112 | O30: NA | P30: NA | Q30: NA | R30: Rupesh/Sambath | S30: NA | T30: https://dev.azure.com/heartlandschools/Mobile/_git/MSBP.MAUI/pullrequest/48141 | U30: 46112 | V30: 46113 | W30: Ashwin | X30: NA | Y30: Avery | Z30: 46113 | AA30: NA | AB30: POV done with Bavithra No Comments. | AC30: NA | AD30: 31 -March - Started work on it. 01 -April - Defect ready for peer a review. 02 Apr - Testing Completed | AE30: Exceeds Expectation | AG30: Main
A31: 31 | B31: MSB Mobile Kaleida | C31: 46101 | D31: 46114 | E31: 26.4 M Sprint 3 Stretch | F31: Jagdeep/vaishnavi | G31: 27002 | H31: MSBA - MAUI - product name when no image no longer wrapping in portrait (regression) | I31: Defect Fixed | J31: 0 | L31: 0 | M31: 46112 | N31: 46112 | O31: NA | P31: NA | Q31: NA | R31: Rupesh | S31: NA | T31: https://dev.azure.com/heartlandschools/Mobile/_git/MSBA.MAUI/pullrequest/48110 | U31: 46111 | V31: 46111 | W31: Ashwin | X31: NA | Y31: Avery | Z31: 46111 | AA31: NA | AB31: POV done with Ashwin No Comments. | AC31: NA | AD31: 30- March - started work and fixed. 01-April - defect ready for testing. Will work on the priority defects from main commit and later work on the stretch items. | AE31: Exceeds Expectation | AG31: Stretch
A32: 32 | B32: MSB Mobile Kaleida | C32: 46101 | D32: 46114 | E32: 26.4 M Sprint 3 | F32: Jagdeep | G32: 27087 | H32: MSBP - Total value shows incorrect once removing the promotion code(regression) | I32: Defect Being Fixed | J32: 0 | L32: 2 | M32: 46113 | N32: NA | O32: NA | P32: NA | Q32: NA | R32: NA | S32: NA | T32: NA | U32: NA | V32: NA | W32: NA | X32: NA | Y32: NA | Z32: NA | AA32: NA | AB32: NA | AC32: NA | AD32: 01- April - Will reproduce then will start work on it.(,defect reason found but Need to dissus with Ashwin ) 02 April - As discussion with Ashiwn today will check it vashnavi by create new account and student and will try to reproduce it again. | AF32: The same behavior is also observed in the Xamarin app. Need to disscussion. | AG32: Main
A33: 33 | B33: MSB Mobile | C33: 46101 | D33: 46114 | E33: 26.4 M Sprint 3 | F33: Vaishnavi | G33: 27077 | H33: MSBA - MAUI - if select print on close day more than once before button goes in disabled state, it doubles the deposit slip only (regression) | I33: Defect Fixed | J33: 0 | L33: 1 | M33: NA | N33: NA | O33: NA | P33: NA | Q33: NA | R33: NA | S33: NA | T33: NA | U33: NA | V33: NA | W33: NA | X33: NA | Y33: NA | Z33: NA | AA33: NA | AB33: NA | AC33: NA | AD33: Testing completed | AE33: Exceeds Expectation | AF33: 02 April- Created the new account with help of Vashnavi and checked it’s happened first time with new account in current year, and same behavior in Xamarin App. (Will inform to client , this is existing behavior.) | AG33: Main
A34: 34 | B34: MSB Mobile | C34: 46101 | D34: 46114 | E34: 26.4 M Sprint 3 | F34: Vaishnavi | G34: 27076 | H34: MSBA - MAUI - Android phone - Close Day print button does not go back into ready (regression) | I34: Defect Fixed | J34: 0 | L34: 1 | M34: NA | N34: NA | O34: NA | P34: NA | Q34: NA | R34: NA | S34: NA | T34: NA | U34: NA | V34: NA | W34: NA | X34: NA | Y34: NA | Z34: NA | AA34: NA | AB34: NA | AC34: NA | AD34: Testing completed | AE34: Exceeds Expectation | AG34: Main
A35: 35 | B35: MSB Mobile | C35: 46101 | D35: 46114 | E35: 26.4 M Sprint 3 | F35: Amrit | G35: 27098 | H35: MSBP - I/A - Search text is not clearing even after adding a product to the cart or switching to a different school (regression) | I35: Defect Peer Review | J35: 0 | L35: 5 | M35: 46113 | N35: 46113 | O35: NA | P35: NA | Q35: NA | R35: Rupesh/Sambath | S35: NA | T35: https://dev.azure.com/heartlandschools/Mobile/_git/MSBP.MAUI/pullrequest/48172 | U35: 46113 | V35: NA | W35: NA | X35: NA | Y35: NA | Z35: NA | AA35: NA | AB35: POV done with Bavithra No Comment | AC35: NA | AD35: 1 Apr - Reporoducing Defect - Working on Fix - POV DONE(PR Created) 2 Apr - PR Approved by Sambath and Rupesh | AE35: Exceeds Expectation | AF35: Client review pending. | AG35: Main
A36: 36 | B36: MSB Mobile Kaleida | C36: 46101 | D36: 46114 | E36: 26.4 M Sprint 3 | F36: Jagdeep/Prem | G36: 27099 | H36: MSBP - I/A - Save button remains enabled even after clearing the value in 'Other Amount', and field value still updates when clicking Save(regression) | I36: Defect Fixed | J36: 0 | L36: 4 | M36: 46113 | N36: 46113 | O36: NA | P36: NA | Q36: NA | R36: Rupesh/Sambath | S36: NA | T36: https://dev.azure.com/heartlandschools/Mobile/_git/MSBP.MAUI/pullrequest/48164 | U36: 46113 | V36: 46113 | W36: Ashwin | X36: NA | Y36: Avery | Z36: 46113 | AA36: NA | AB36: POV done with Bavithra No Comments. | AC36: NA | AD36: 1 April - start working on it. 02 Apr - Testing Completed | AE36: Exceeds Expectation | AG36: Main
A37: 37 | B37: MSB Mobile | C37: 46101 | D37: 46114 | E37: 26.4 M Sprint 3 | F37: Rupesh | G37: 27088 | H37: MSBP - A - Button does not turn blue even after meeting the entry requirements (regression) | I37: Defect Rejected | J37: 0 | L37: 3 | M37: 46113 | N37: NA | O37: NA | P37: NA | Q37: NA | R37: NA | S37: NA | T37: NA | U37: NA | V37: NA | W37: NA | X37: NA | Y37: NA | Z37: NA | AA37: NA | AB37: NA | AC37: NA | AD37: Jason rejected it as it is happening on old devices like, Pixel 4a. | AG37: Main
A38: 38 | B38: MSB Mobile | C38: 46101 | D38: 46114 | E38: 26.4 M Sprint 3 | F38: Sambath | G38: 27078 | H38: 27078 MSBA - MAUI - android phone - app crash when trying to apply filters (regression) | I38: Defect Being Fixed | J38: 0 | M38: 46113 | AD38: 1 Apr - Started anysing this defect 2 Apr - Still finding the root cause of crash and freeze issue | AF38: it seems to be telerick control issue so still finding the root cause of crash and freeze issue
A39: 39 | B39: MSB Mobile | C39: 46101 | D39: 46114 | E39: 26.4 M Sprint 3 | F39: Letashia and offshore team | G39: 52225 | H39: MSBA - End to End Testing of Maui [Time Box] Pt 3 | I39: Story Completed | J39: 5 | M39: NA | N39: NA | O39: NA | P39: NA | Q39: NA | R39: NA | S39: NA | T39: NA | U39: NA | V39: NA | W39: NA | X39: NA | Y39: NA | Z39: NA | AA39: NA | AB39: NA | AC39: NA | AD39: Testers and Developers will be adding the worklogs in this story as part of MSBA regression defects
A40: 40 | B40: MSB Mobile Kaleida | C40: 46101 | D40: 46114 | E40: 26.4 M Sprint 3 | F40: Jagdeep | G40: 27104 | H40: MSBP - I/A - Missing Profile Information screen, Answer Field appears disabled and only becomes enabled on switching to navigation icons(regression) | I40: Defect Being Fixed | J40: 0 | L40: 0 | M40: 46114 | N40: NA | O40: NA | P40: NA | Q40: NA | R40: NA | S40: NA | T40: NA | U40: NA | V40: NA | W40: NA | X40: NA | Y40: NA | Z40: NA | AA40: NA | AB40: NA | AC40: NA | AD40: 02 April - starting work on this defect. | AF40: picked up this defect midway through the day, so I still need more time to work on it. As a result, it will carry over into the next sprint. | AG40: Main
A41: 41 | B41: MSB Mobile | C41: 46101 | D41: 46114 | E41: 26.4 M Sprint 3 | F41: Rupesh | G41: 27105 | H41: MSBP - A - Missing Profile Information screen, Text (We need to update your profile) is shows in cut off mode(regression) | I41: Defect Peer Review | J41: 0 | L41: 0 | M41: 46114 | N41: NA | O41: NA | P41: NA | Q41: NA | R41: NA | S41: NA | T41: https://dev.azure.com/heartlandschools/Mobile/_git/MSBP.MAUI/pullrequest/48201 | U41: 46114 | V41: NA | W41: NA | X41: NA | Y41: NA | Z41: NA | AA41: NA | AB41: POV done with Bavithra. | AC41: NA | AD41: 02 April - Will reproduce it first and then fix. PR is pending from internal team. | AE41: Exceeds Expectation | AF41: Client review pending. | AG41: Main
A42: 42 | B42: MSB Mobile | C42: 46101 | D42: 46114 | E42: 26.4 M Sprint 3 | F42: Rupesh | G42: 27106 | H42: MSBP - I/A - Bottom navigation icons should not present in Missing Profile Information screen(regression) | I42: Defect Peer Review | J42: 0 | L42: 0 | M42: 46114 | N42: NA | O42: NA | P42: NA | Q42: NA | R42: NA | S42: NA | T42: https://dev.azure.com/heartlandschools/Mobile/_git/MSBP.MAUI/pullrequest/48201 | U42: 46114 | V42: NA | W42: NA | X42: NA | Y42: NA | Z42: NA | AA42: NA | AB42: POV done with Bavithra. | AC42: NA | AD42: 02 April - Will reproduce it first and then fix. PR is pending from internal team. | AE42: Exceeds Expectation | AF42: Client review pending. | AG42: Main

Sheet 26.4 M Sprint 3-Defect
A1: S.No | B1: Sprint # | C1: Story/Defect ID | D1: Parent Story | E1: Developer | F1: Issue Type | G1: Issue Description | H1: Priority | I1: Defect Source | J1: Type | K1: Status | L1: Root Cause Category | M1: Who Reported It? | N1: Comments
B2: 26.4 M Sprint 3 | C2: 26897 MSBA - MAUI -Android - recent students search cut off (regression) | D2: 26897 MSBA - MAUI -Android - recent students search cut off (regression) | E2: Sambath/ Gursewak/Prem | F2: Defect | H2: Minor | I2: Manual | J2: External | K2: Closed | L2: Development | M2: Others | N2: Xamarin to Maui conversion defects
B3: 26.4 M Sprint 3 | C3: 26886 MSBA - MAUI - Close day is missing EMV transactions from Expected payment summary and Sales summary and credit total (regression) | D3: 26886 MSBA - MAUI - Close day is missing EMV transactions from Expected payment summary and Sales summary and credit total (regression) | E3: Ashwin | F3: Defect | H3: Minor | I3: Manual | J3: External | K3: Closed | L3: Development | M3: Relevantz QA | N3: Xamarin to Maui conversion defects
B4: 26.4 M Sprint 3 | C4: 26977 MSBA - MAUI - iOS - Error message behind other popup in shift mode (regression) | D4: 26977 MSBA - MAUI - iOS - Error message behind other popup in shift mode (regression) | E4: Jagdeep | F4: Defect | H4: Minor | I4: Manual | J4: External | K4: Closed | L4: Development | M4: Client QA | N4: Xamarin to Maui conversion defects
B5: 26.4 M Sprint 3 | C5: 27024 MSBA - MAUI - shift mode error message incorrect (regression) | D5: 27024 MSBA - MAUI - shift mode error message incorrect (regression) | E5: Amrit/ | F5: Defect | H5: Minor | I5: Manual | J5: External | K5: Closed | L5: Development | M5: Client QA | N5: Xamarin to Maui conversion defects
B6: 26.4 M Sprint 3 | C6: 27009 MSBA - MAUI - iphone - buzzing on barcode scan/not closing camera in background after scan (regression)" | D6: 27009 MSBA - MAUI - iphone - buzzing on barcode scan/not closing camera in background after scan (regression)" | E6: Sambath | F6: Defect | H6: Minor | I6: Manual | J6: External | K6: Closed | L6: Development | M6: Client QA | N6: Xamarin to Maui conversion defects
B7: 26.4 M Sprint 3 | C7: 27036 MSBA - MAUI - iOS - when in shift mode adding/deleting shift user, can swipe to get to a different box (regression) | D7: 27036 MSBA - MAUI - iOS - when in shift mode adding/deleting shift user, can swipe to get to a different box (regression) | E7: Amrit/ | F7: Defect | H7: Minor | I7: Manual | J7: External | K7: Closed | L7: Development | M7: Relevantz QA | N7: Xamarin to Maui conversion defects
B8: 26.4 M Sprint 3 | C8: 27032 MSBA - MAUI - phone - app crash on session ending (regression) | D8: 27032 MSBA - MAUI - phone - app crash on session ending (regression) | E8: Sambath | F8: Defect | H8: Minor | I8: Manual | J8: External | K8: Closed | L8: Development | M8: Relevantz QA | N8: Xamarin to Maui conversion defects
B9: 26.4 M Sprint 3 | C9: 27058 MSBP - Unable to scroll in the payment method drawer under meal money autopay and invoice autopay(regression) | D9: 27058 MSBP - Unable to scroll in the payment method drawer under meal money autopay and invoice autopay(regression) | E9: Amrit | F9: Defect | H9: Minor | I9: Manual | J9: External | K9: Closed | L9: Development | M9: Relevantz QA | N9: Xamarin to Maui conversion defects
B10: 26.4 M Sprint 3 | C10: 27034 MSBA - MAUI - iphone - edges of the printers and readers menus cut off (regression) | D10: 27034 MSBA - MAUI - iphone - edges of the printers and readers menus cut off (regression) | E10: Rupesh | F10: Defect | H10: Minor | I10: Manual | J10: External | K10: Inprogress | L10: Development | M10: Client QA | N10: Xamarin to Maui conversion defects
B11: 26.4 M Sprint 3 | C11: 27052 MSBA - MAUI - Android - unable to read entire product description (regression) | D11: 27052 MSBA - MAUI - Android - unable to read entire product description (regression) | E11: Gursewak/Amrit | F11: Defect | H11: Minor | I11: Manual | J11: External | K11: Closed | L11: Development | M11: Client QA | N11: Xamarin to Maui conversion defects
B12: 26.4 M Sprint 3 | C12: 27063 MSBA - MAUI - Save & Close button not centered (regression) | D12: 27063 MSBA - MAUI - Save & Close button not centered (regression) | E12: Gursewak/Prem | F12: Defect | H12: Minor | I12: Manual | J12: External | K12: Closed | L12: Development | M12: Client QA | N12: Xamarin to Maui conversion defects
B13: 26.4 M Sprint 3 | C13: 27065 MSBA - MAUI -Android phone - on returning to step 1 from a later step, cannot scroll to pick a shift in close out (regression) | D13: 27065 MSBA - MAUI -Android phone - on returning to step 1 from a later step, cannot scroll to pick a shift in close out (regression) | E13: Amrit/Prem | F13: Defect | H13: Minor | I13: Manual | J13: External | K13: Closed | L13: Development | M13: Client QA | N13: Xamarin to Maui conversion defects
... B26: 26.4 M Sprint 3 | C26: 27106 MSBP - I/A - Bottom navigation icons should not present in Missing Profile Information screen(regression) | D26: 27106 MSBP - I/A - Bottom navigation icons should not present in Missing Profile Information screen(regression) | E26: Rupesh | F26: Defect | H26: Minor | I26: Manual | J26: External | K26: Inprogress | L26: Development | M26: Client QA | N26: Xamarin to Maui conversion defects

Sheet 26.4 M Sprint 2-Status
A1: S.No | B1: Application Name | C1: Sprint Start Date | D1: Sprint End Date | E1: Sprint | F1: Developer | G1: Story ID/Defect ID | H1: Description | I1: Status | J1: Estimated(sp) | K1: Actual(sp) | L1: Actual Hours Worklog | M1: Dev Start Date | N1: Dev End Date | O1: Unit testing | P1: Peer Tested By | Q1: Peer Tested Defects, if any | R1: Peer Reviewed By | S1: Peer Code Review Comments, if any | T1: PR Number/Link | U1: PR Created Date | V1: PR Approved Date | W1: Reviewer 1 | X1: Code Review Comments, if any | Y1: Reviewer 2 | Z1: Approved Date | AA1: Code Review Comments, if any2 | AB1: Internal PO -POV Comments | AC1: Client PO -POV Comments | AD1: Comments | AE1: Does this story meet the expectations? | AF1: Comments | AG1: Sprint Tag
A2: 1 | B2: MSB Mobile Kaleida | C2: 46087 | D2: 46100 | E2: 26.4 M Sprint 2 | F2: Sambath/Prem | G2: 51966 | H2: [WAVE] MSBA - Kaleida - Settings - Apps & Stores | I2: Story Being Developed | J2: 5 | M2: 46071 | N2: NA | O2: NA | P2: NA | Q2: NA | R2: NA | S2: NA | T2: https://dev.azure.com/heartlandschools/Mobile/_git/MSBA.MAUI/pullrequest/47478 | U2: 25/2/2026 | V2: NA | W2: Na | X2: NA | Y2: NA | Z2: NA | AA2: Move to color resource file(4) | AD2: Dev completed, testing this story, new ac has been updated at end of sprint so i am working with that. 8 Mar - Sambath - Working on testing fixes. 09 Mar - Test Case Comments Updations is Completed 9 Mar -Amrit - Working on PR Comments and Code Cleanup and fixed dropdown issue 9 March - Jagdeep - will test app accordingly AC point (Found some crash issues and fixed and for dropdown refresh issue informed to Sambath) 10 - Mar - Sambath working on the Merge the latest code from maui and fixed build issue, and testing the story. 11- Mar - Sambath - Woking on POV Changes and Testing in Android device. 12-March-Gursewak - Will work on color code fixes need to move in common place. 13-Mar - Sambath worked the testing fixes and review comments. 17 Mar - Rupesh - worked on POV findings. 18 Mar - Rupesh - will run the POV again. Fixed the crash that we found out during crash and added missing code form existing SettingsViewModel. 19 Mar - Will have to run POV again. | AE2: Needs Improvement | AF2: 21 Feb - AC Changed by Client, Few changes was discussed along with development with client. (27 Feb) Requirement changed by client discussion in progress 27-Feb - Sambath - going to work with new AC changes in settings screen. This story is carried from previous sprint, so for this sprint initally added 5 SP then alter added 8 SP for New AC Update. Time logged for this sprint 59.5 Hrs, and Previouse sprint logged 23.5 Hrs 9-Mar - Sambath - Work with review comments and testing with iOS 13-Mar - Sambath - i am working with Avery changes for Kcontrol and fixng the iOS issue. | AG2: Main
A3: 2 | B3: MSB Mobile Kaleida | C3: 46087 | D3: 46100 | E3: 26.4 M Sprint 2 | F3: Gursewak/Prem | G3: 26879 | H3: MSBA - when using the "display featured items" toggle, other products don't display (regression) | I3: Defect Fixed | J3: 0 | L3: 18.5 | M3: 46083 | N3: 46091 | O3: NA | P3: NA | Q3: NA | R3: Rupesh | S3: Remove the curly braces and make it in one line as this block is having one statement to execute. Please do it for all the places wherever it's aplicable. | T3: https://dev.azure.com/heartlandschools/Mobile/_git/MSBA.MAUI/pullrequest/47712 | U3: 46091 | V3: 46091 | W3: Ashwin | X3: Use common color Add this Automation ID back | Y3: Avery | Z3: 46097 | AA3: NA | AB3: POV done with Bavithra No Comments. | AC3: NA | AD3: 06-March - The original issue has been fixed. During testing, a spacing issue was identified in both Featured and Products, which has now been resolved. Currently, when clicking collapse and expand, the data is not displaying under Featured and Products. I am working on fixing this issue. Once it is resolved, I will complete the POV and create the PR. 09-March- Trying to implement telerik:RadCollectionView as discussed in Friday standup call. 09-March-EOD-Implemented and completed the functionality with RadCollectionView, also did the POV with "Bavithra", during the code review with Rupesh we found one crash issue on his system, The RadCollectionView working fine in debug mode but app crash in release mode. same thing discussed in standup also with ashwin. 10-March-Gursewak-Will work on RadCollectionView crash issue in release mode will try to fix the issue. 10 -March - Jagdeep will work with Gurusewak and support on this story. 10 March - EOD - Telerik RadCollectionView is not working as expected according to the reported defect. Additionally, if we add a simple Telerik RadCollectionView to a blank XAML page and test it in Release mode, the application crashes. Today, we tried implementing a bindable VerticalStackLayout and FlexLayout instead. This approach fixed the issue according to our requirements. We tested it on iOS and Android (both phone and tablet). We also completed a POV with Bavithra and Ashwin, and it is working fine. 11-March-Gursewak- As ashwin send message on slack for all dev team, Will work on copilot prompt to review my code that created a PR, and test it again and update the PR. after that will start work on "52142" 11-March-EOD-Rupesh approved the PR. 12-March- PR review pending from Sambath,Ashwin and client side. 13 March - As Ashwin comment on slack, "The app is crashing when I run it in release mode in simulator and both in debug and release mode on a physical device from your branch when landing on the stores page. If I keep the default as meals or invoice it lands on it but when I switch to store it crashes. Check and fix this", working on it today. 13 March - EOD - The issue has been fixed. I have done the POV testing on both the simulator and a real device, and the app is no longer crashing when landing on the Stores page. 16-March-Client side PR review pending. 16-March-EOD- Merged, ready for test. 17 Mar - Testing Completed | AE3: Exceeds Expectation | AF3: The delay was due to unexpected issues with Telerik RadCollectionView, where the app was crashing in release mode despite working in debug. This required investigation and a shift to an alternative approach using VerticalStackLayout and FlexLayout, along with additional testing and POV validations. There were also a few review comments and crash fixes during PR validation, which added to the timeline. After resolving all issues, the changes were merged and tested successfully. | AG3: Stretch
