Workbook

Sheet Dashboard
A1: Current Sprint | B1: {=INDEX($B$2:$B$99,MATCH(1,(($D$2:$D$99 >=TODAY())*($C$2:$C$99<=TODAY())),0))} -> GGO 8.4.0 Sprint 4 | C1: Current Sprint Sheet | D1: =CONCATENATE(B1,"-Status") -> GGO 8.4.0 Sprint 4-Status | E1: Sprint Start Date | F1: =VLOOKUP($B$1,$B$1:$C$99,2) -> 46156 | G1: Sprint End Date | H1: =VLOOKUP($B$1,$B$1:$D$99,3) -> 46170 | I1: Application Name | J1: GGO Web | K1: Users | L1: jennifer.anthony@relevantz.com;saranya.namachivayam@relevantz.com;sathiyabharathi.paramasivam@relevantz.com;priyadharshini.ravichandran@relevantz.com;rajeshkannan.subramanian@relevantz.com;satarupa.mohanty@relevantz.com | M1: Teams Name(GP-GGO.Web) | N1: 19:ac26c2f1541e4a10bdec732dd7eb2936@thread.v2
A2: Sprint Type | B2: Sprint # | C2: Sprint Start Date | D2: Sprint End Date | E2: Assigned | F2: Completed | G2: Story points introduced/removed | H2: Sprint Summary | I2: Accomplishments | J2: Remarks | K2: Retro Points (Internal & External) | L2: Data sanity Audit Status | M2: AuditDate | N2: Planned Leaves | O2: Availed Leaves | P2: Backlog Health
A3: =IF(AND($D$1>=C3,$D$1<=D3),"CurrentSprint","NA") -> NA | B3: GGO 7.15.0 Sprint 4 | C3: 45303 | D3: 45316 | E3: 17 | F3: 15 | G3: 7 | J3: Completed all the introduced story in the mid of the sprint | K3: Internal: External:
A4: =IF(AND($D$1>=C4,$D$1<=D4),"CurrentSprint","NA") -> NA | B4: GGO 7.16.0 Sprint 1 | C4: 45317 | D4: 45330 | E4: 17 | F4: 14 | G4: 3 | J4: Actual estimated stories (17pts) got completed from our end with Development and Testing, From Onsite QA (Nate) took time for testing 3 point story because of PRD release and he took half day leave and he got only 4 hrs of time. So from this I would like to say, we should plan to complete the estimated stories 2 days prior, else Nate won't close on the last day of sprint. Introduced Story - 3 point is Development completed, only Testing pending. | K4: Internal: External:
A5: =IF(AND($D$1>=C5,$D$1<=D5),"CurrentSprint","NA") -> NA | B5: GGO 7.16.0 Sprint 2 | C5: 45331 | D5: 45344 | E5: 23 | F5: 22 | G5: 2 | J5: Completed all the stories on time, but we noticed one minor issue in GGO-13703 Bid-18 report on xls and xlsx formats. the column header occupying some aditional column . It require an report engine code changes.verified some other reports also having the same issue and it's an existing issue.completed introduced story as well | K5: Internal: External:
A6: =IF(AND($D$1>=C6,$D$1<=D6),"CurrentSprint","NA") -> NA | B6: GGO 7.16.0 Sprint 3 | C6: 45345 | D6: 45358 | E6: 27 | F6: 23 | G6: 7 | J6: GGO-13801-onsite QA(Nathan) raised one bug , we tried to reproduce the issue on rounding but we are not able to do that. We have asked for the steps to reproduce the issue. GGO-13738 -Development has been completed on this story, it require's IT team support to complete the testing. Introduced Story - 7 points (Except GGO-13738 testing) all completed | K6: Internal: External:
A7: =IF(AND($D$1>=C7,$D$1<=D7),"CurrentSprint","NA") -> NA | B7: GGO 7.16.0 Sprint 4 | C7: 45359 | D7: 45372 | E7: 20 | F7: 16 | G7: 5 | J7: GGO-13796 and GGO-13773 development has been completed.testing requires IT team support to complete,currently salesforce team doing some changes at their side we can't test salesforce api's .Introduced Story - 5 points Develpment has been completed for that. | K7: Internal: External:
A8: =IF(AND($D$1>=C8,$D$1<=D8),"CurrentSprint","NA") -> NA | B8: GGO 7.17.0 Sprint 1 | C8: 45373 | D8: 45386 | E8: 14 | F8: 11 | G8: 3 | J8: Since we need support from sales force team for testing GGO -13773 ,PAPI-702 saranya supported Mike wall for testing We got info from Doug about the 4 PROD issues in planning meeting 1. Convenience Fee Issue - Not able to reproduce by our team and Onsite QA in DEV, TST & CRT, it is occurring only in PRD, finding a way to check the values, settings in PROD to replicate in lower envrionment 2. Package Tax Issue - Round off to whole number instead of 2 decimal, this is our mistake that has got in to PRD 3 months before, when fixing old code to replace SQL CLR to C# method. 3. Item tax added to Package - This was old issue, but many clients started to raise concern about this issue now, because of our new implementation for Convenience Fee. 4. Payment show error when Actually it is success in PAPI for Few Clients in PRD - Still don't know the reason, analysing the root cause of this issue. | K8: Internal: External:
A9: =IF(AND($D$1>=C9,$D$1<=D9),"CurrentSprint","NA") -> NA | B9: GGO 7.17.0 Sprint 2 | C9: 45387 | D9: 45400 | E9: 19 | F9: 17 | G9: 0 | J9: This sprint we fixed production issues and macroscope security issues . PAPI-702 carried because card details need to verified with PAPI database, we don't have required permission for that, only onsite QA need to be verified. | K9: Internal: External:
A10: =IF(AND($D$1>=C10,$D$1<=D10),"CurrentSprint","NA") -> NA | B10: GGO 7.17.0 Sprint 3 | C10: 45401 | D10: 45414 | E10: 18 | F10: 11 | G10: 0 | J10: 2 stories got carried. 1. Due to salesforce team confirmed they can't do any changes. 2. Onshore Testing is pending | K10: Internal: External:
A11: =IF(AND($D$1>=C11,$D$1<=D11),"CurrentSprint","NA") -> NA | B11: GGO 7.17.0 Sprint 4 | C11: 45415 | D11: 45428 | E11: 14 | F11: 4 | G11: 0 | J11: CRT Regression Testing is still in Progress. 3 stores are blocked and carried because of IT dependencey (Certificate Issue and Permission issue for Report Instance folder in DEV & TST Environments), all the development and testing works are done from our end. | K11: Internal: External:
A12: =IF(AND($D$1>=C12,$D$1<=D12),"CurrentSprint","NA") -> NA | B12: GGO 7.18.0 Sprint 1 | C12: 45429 | D12: 45442 | E12: 15 | F12: 14 | G12: 0 | J12: Testing blocked due to certificate issue | K12: Internal: External:
A13: =IF(AND($D$1>=C13,$D$1<=D13),"CurrentSprint","NA") -> NA | B13: GGO 7.18.0 Sprint 2 | C13: 45443 | D13: 45456 | E13: 20 | F13: 16 | G13: 0 | K13: Internal: External:
A14: =IF(AND($D$1>=C14,$D$1<=D14),"CurrentSprint","NA") -> NA | B14: GGO 7.18.0 Sprint 3 | C14: 45457 | D14: 45470 | E14: 17 | F14: 15 | G14: 2 | K14: Internal: External:
A15: =IF(AND($D$1>=C15,$D$1<=D15),"CurrentSprint","NA") -> NA | B15: GGO 7.18.0 Sprint 4 | C15: 45471 | D15: 45484 | E15: 20 | F15: 20 | G15: 0 | K15: Internal: External:
A16: =IF(AND($D$1>=C16,$D$1<=D16),"CurrentSprint","NA") -> NA | B16: GGO 7.19.0 Sprint 1 | C16: 45485 | D16: 45498 | E16: 15 | F16: 15 | G16: 5 | J16: Two stretch stories got carried to next sprint. | K16: Internal: External:
A17: =IF(AND($D$1>=C17,$D$1<=D17),"CurrentSprint","NA") -> NA | B17: GGO 7.19.0 Sprint 2 | C17: 45499 | D17: 45511 | E17: 6 | F17: 6 | G17: 7 | J17: Two stretch stories got carried to next sprint. | K17: Internal: External:
A18: =IF(AND($D$1>=C18,$D$1<=D18),"CurrentSprint","NA") -> NA | B18: GGO 7.19.0 Sprint 3 | C18: 45512 | D18: 45526 | E18: 16 | F18: 16 | G18: 2 | K18: Internal: External:
A19: =IF(AND($D$1>=C19,$D$1<=D19),"CurrentSprint","NA") -> NA | B19: GGO 7.19.0 Sprint 4 | C19: 45527 | D19: 45540 | E19: 17 | F19: 14 | G19: 2 | J19: Automation Regression story got carried over as it was new for Offshore QA and there was some learning curve involved. | K19: Internal: External:
A20: =IF(AND($D$1>=C20,$D$1<=D20),"CurrentSprint","NA") -> NA | B20: GGO 7.20.0 Sprint 1 | C20: 45540 | D20: 45554 | E20: 15 | F20: 13 | G20: 2 | J20: 2 point carry forwarded to next sprint, development and testing completed from our end, but onsite QA didn't complete it. | K20: Internal: External:
A21: =IF(AND($D$1>=C21,$D$1<=D21),"CurrentSprint","NA") -> NA | B21: GGO 7.20.0 Sprint 2 | C21: 45555 | D21: 45568 | E21: 19 | F21: 14 | G21: 2 | J21: GGO-14067 got carried, We are migrating Bid-03 report to new RDLC framework, there is lot of existing logic present in RPT file. we need to exactly replicate same logic in SQL stored procedure for new RDLC format.understanding .rpt file logic is complication involved Peer CRC:0 Onsite CRC: 0 Client CRC: 0 Internal Defects: 0 External Defects: 0 | K21: Internal: External:
A22: =IF(AND($D$1>=C22,$D$1<=D22),"CurrentSprint","NA") -> NA | B22: GGO 7.20.0 Sprint 3 | C22: 45569 | D22: 45582 | E22: 17 | F22: 12 | J22: GGO-14067 got carried, Getting Timeout issue for large records,Suporterwise page breakup and some functionlity in spreadsheetlayout is pending Onsite CRC: 0 Onsite CRC: 0 Client CRC: 0 Internal Defects: 1 External Defects: 0 | K22: Internal: External:
A23: =IF(AND($D$1>=C23,$D$1<=D23),"CurrentSprint","NA") -> NA | B23: GGO 7.20.0 Sprint 4 | C23: 45583 | D23: 45596 | E23: 16 | F23: 13 | I23: 1. Login Page Privacy policy update in MFA login page of GGO application 2. Paymen Receipt in new RDLC replacing form display helps users to download receipt as PDF and send email with attachment. | J23: GGO-14067 got carried, Getting Timeout issue for large records Onsite CRC: 0 Client CRC: 0 Internal Defects: 1 External Defects: 0 | K23: Internal: External:
A24: =IF(AND($D$1>=C24,$D$1<=D24),"CurrentSprint","NA") -> NA | B24: GGO 7.21.0 Sprint 1 | C24: 45597 | D24: 45610 | E24: 18 | F24: 17 | G24: 3/0 | I24: 1.Fixed Timeout issue on Bid-03 RDLC report generation. 2.Completed two tickets introduced in the mid of the sprint | J24: Completed all story points on time Onsite CRC: 0 Client CRC: 0 Internal Defects: 2 External Defects: 0 | K24: Internal: External:
A25: =IF(AND($D$1>=C25,$D$1<=D25),"CurrentSprint","NA") -> NA | B25: GGO 7.21.0 Sprint 2 | C25: 45611 | D25: 45621 | E25: 14 | F25: 11 | I25: 1. Fixed Grid selection issue on Bid-03 RDLC report generation. 2. Fixed Azure Images issue replacing content server url with azure url 3. Investigated GGO to OB Queue flow to replace it with Quartz Job. 4. Allow GGO to validate and support different card card types (JCB, Diners club & Discover Debit) | J25: GGO-13319 story got rolled over due to Azure image access issue and a ticket with Microsoft has been opened​ by IT Onsite CRC: 0 Client CRC: 1 Internal Defects: 0 External Defects: 0 | K25: Internal: External:Rajesh and offshore for continued work on reports Priya, Nathan and Conor for testing a lot of stories and completing them
A26: =IF(AND($D$1>=C26,$D$1<=D26),"CurrentSprint","NA") -> NA | B26: GGO 7.21.0 Sprint 3 | C26: 45622 | D26: 45638 | E26: 14 | F26: 14 | G26: 7/0 | I26: 1. Application images moved in Azure , previously we stored the images in DB as bytes 2. 7.20.1 Successfully deployed to PRD 3. EMV Implementation -completed most of the cardreader functionality | J26: GGO-14325 - BID-06 story is a huge effort and cannot be completed in one sprint, hence it was taken as a strech goal Peer CRC:0 Onsite CRC: 0 Client CRC: 0 Internal Defects: 0 External Defects: 0 | K26: Internal: External:
A27: =IF(AND($D$1>=C27,$D$1<=D27),"CurrentSprint","NA") -> NA | B27: GGO 7.21.0 Sprint 4 | C27: 45639 | D27: 45666 | E27: 24 | F27: 19 | G27: 3/0 | I27: 1. Fixed Duplicate Event X Code issue that was a PROD bug for more than 5 years. 2. Good progress on Bid-06 RDLC update and feel confident in completing it next sprint 3. Popup warning for Convenience fee validation implemented 4. Quartz Job implemented for Bid-06 email flow with our own effort and stored the PDF in Azure. | J27: GGO-14427 - BID-06 - Part-3 story is a huge effort, this has got more than 100 scenario's, so it took more time for testing left out with 2 bugs at the end of sprint (development done for the bugs) only testing pending. Peer CRC:0 Onsite CRC: 0 Client CRC: 0 Internal Defects: 8 External Defects: 0 | K27: Internal: External: Offshore team made great progress on Bid-06 report
A28: =IF(AND($D$1>=C28,$D$1<=D28),"CurrentSprint","NA") -> NA | B28: GGO 7.22.0 Sprint 1 | C28: 45667 | D28: 45680 | E28: 21 | F28: 17 | G28: 4/0 | I28: 1.GGO-14484 Jan 21 Prod Release 2. Successfully completed Bid-06 with new report tool set 3. CRT regression testing completed | J28: GGO-14427 - BID-06 - Part-3 during the CRT testing noticed package item enabled scenario taking too long to complete the report - immediately addressed this Issue. GGO-14483 Completed CRT Release & Regression Testing Peer CRC:0 Onsite CRC: 0 Client CRC: 0 Internal Defects: 6 External Defects: 0 Reason for pending: GGO-14422, PAPI-789 - Development and Testing completed from our end, Pending testing from Nate (Onsite QA) because he was focusing more in CRT regression. GGO-14447 - Automation story completed from our end, pending review from Nate GGO-14450 - A.C change one day prior to Sprint end date, so it got carry forward to next sprint
A29: =IF(AND($D$1>=C29,$D$1<=D29),"CurrentSprint","NA") -> NA | B29: GGO 7.22.0 Sprint 2 | C29: 45681 | D29: 45694 | E29: 18 | F29: 11 | G29: 2/0 | I29: 1.Enhance RSVP Functionality with key features to enable better data gathering and management of attendee info. 2.Azure Thumbnail image creation issue fix - Add this project as part of GGO Solution and build it via Build pipeline and add it to GGO Artifact | J29: Peer CRC:0 Onsite CRC: 0 Client CRC: 0 Internal Defects: 0 External Defects: 1 Testing is pending by Onsite QA and we completed the stories (GGO-14503, GGO-14450) and deployed to TST 2 days prior Sprint end, that's the reason these stories got rolled over to next sprint.
A30: =IF(AND($D$1>=C30,$D$1<=D30),"CurrentSprint","NA") -> NA | B30: GGO 7.22.0 Sprint 3 | C30: 45695 | D30: 45708 | E30: 18 | F30: 8 | I30: 1.Adjust Admission Functionality and Infrastructure(Graph) update 2.Bid-19 and Bid-15 Report Updates | J30: Peer CRC:0 Onsite CRC: 0 Client CRC: 4 Internal Defects: 4 External Defects: 1 Reason for pending: GGO-14504 - The story was given Onisite QA for testing 3 days before the end of Sprint but Onsite QA logged bug on the last day of Thesprint. It was fixed and deployed before sprint prep, QA didn't get time to complete it. GGO-14070 - Development took a lot of time and got completed only on 1 day before Sprint end, the offshore QA logged a minor bug on the last day of sprint, fixed the bug and PR created for review. (Saranya worked on the RDLC report for the first time and there was a learning curve involved which took time)
A31: =IF(AND($D$1>=C31,$D$1<=D31),"CurrentSprint","NA") -> NA | B31: GGO 7.22.0 Sprint 4 | C31: 45709 | D31: 45722 | E31: 20 | F31: 15 | G31: 2/0 | I31: CRT Release & Regression testing for GGO 7.22.0 and PAPI 7.17.0 | J31: Peer CRC:0 Onsite CRC: 0 Client CRC: 0 Internal Defects: 4 External Defects: 0 Reason for pending: GGO-14510 - Bootstrap update - Development and Testing from Offshore got completed, the automation flow broken with this bootstrap update, so Nate created a automation change ticket under this story and this got carry forwarded to next sprint.
A32: NA | B32: GGO 7.23.0 Sprint 1 | C32: 45723 | D32: 45736 | E32: 19 | F32: 19 | G32: 7/0 | I32: Continued EMV Implementation and Infrastructure updates Allowed 19 digit card entry in GGAM, GGO and PAPI Cleared some Macroscope issues in PAPI Fixed cache issue in GGO Accomplishments: Addiitionally completed Developemnt for stretch goal stories | J32: Peer CRC:0 Onsite CRC: 0 Client CRC: 0 Internal Defects: 0 External Defects: 0 | K32: Internal Retro 1. Sathiya/ Rajesh and Saranya for providing help to Priya testing the stories 2. Team for completing all the story points
A33: NA | B33: GGO 7.23.0 Sprint 2 | C33: 45736 | D33: 45750 | E33: 13 | F33: 19 | G33: 10/0 | I33: Completed Duplicate even code story and Invoice import and Invoice Payment Pages story Fixed Quartz Job access issues and Email Queue Issues. Accomplishments: Completing the development and testing for lot of stretch goal stories on the current sprint | J33: Peer CRC:0 Onsite CRC: 0 Client CRC: 0 Internal Defects: 2 External Defects: 0 Pending Story: 2 Stories has been carried forward 1.GGO-14573 -Hard to reproduce in the lower environements. The offshore developers made several attempts to reproduce the issue, but because it’s related to performance, it took a considerable amount of time to replicate. That’s why it got carried over. 2.PAPI-839(Stretch Goal) -Dependency on Onsite QA to complete it(Offshore QA has already completed testing for this story) | K33: Retro: 1.Rajesh for supporting multiple escalation issues 2.Sathiya/ Rajesh and Saranya for covering such a wide spread of stories 3.Priya for completing the testing for the planned as well as lot of stretch jiras
A34: NA | B34: GGO 7.23.0 Sprint 3 | C34: 45751 | D34: 45764 | E34: 22 | F34: 24 | G34: 6/0 | I34: Completed Multiple RSVP Imports Accomplishments: Did some Redis changes which was very challenging and OP to GGO import timeouts(which is a esclation ticket) Completing the development for the stretch goal stories on the current sprint | J34: Peer CRC:0 Onsite CRC: 0 Client CRC: 0 Internal Defects: 1 External Defects: 0 Pending Story: 2 stories has been carried forward which includes 1 stretch PAPI-840(8spt)and GGO-14644[Stretch] -Development for this story was completed three days ahead of the sprint deadline. However, a last-minute AC request from the client required code modifications, which were implemented the timeline.The story was left in Peer Review upon completion, per the client's request to hold it and maintain this branch separately from the CERT branch.Offshore QA has completed verification in the lower environment. The story is now pending validation from Onsite QA. | K34: Rajesh and offshore for taking the redis changes which was very challenging
A35: NA | B35: GGO 7.23.0 Sprint 4 | C35: 45765 | D35: 45778 | E35: 23 | F35: 27 | G35: 5/0 | I35: Accomplishments: Completed CRT testing Completed all planned stories and more Okta 1 Proof of concept Completed more macroscopic stories | J35: Peer CRC:0 Onsite CRC: 0 Client CRC: 0 Internal Defects: 1 External Defects: 0 Pending Story: 2 stories has been carried forward GGO-13722 ->we documented the alternative encryption change, client wanted to add new feature flag based on that need to follow the old and new encryption flow GGO-13723 ->we documented the alternative encryption change, client wanted to add new feature flag based on that need to follow the old and new encryption flow | K35: To the whole team for helping remove all the blockers for testing Rajesh and offshore for helping with the fallback cases Rajesh for assisting with integrating the Okta proof-of-concept
A36: NA | B36: GGO 7.24.0 Sprint 1 | C36: 45779 | D36: 45792 | E36: 19 | F36: 16 | G36: 2/0 | I36: Accomplishments: Old Amex certification testing Nav Bar Updation Fixed Dashboard generation Issue and Enabled Online Bidding for the same Fixed Export Sales issue Completed more macroscopic stories | J36: Peer CRC:0 Onsite CRC: 0 Client CRC: 0 Internal Defects: 0 External Defects: 0 Pending Story: 2 stories has been carried forward GGO-14628->Hard to reproduce in the lower environements. The offshore developers and QA's made several attempts to reproduce the issue, However, on the last day of the sprint,we found one way to reproduce it. But team need to ensure this after providing the solutions and to check whether this the cause of this issue. Team is still working on it.That’s why it got carried over. GGO-14656->Reskin-V2 is a complete overhaul of the existing Master Page. The new layout seamlessly integrates Telerik controls, Bootstrap, and Kendo UI CSS, ensuring an optimized, modern, and adaptive user experience across all devices. As part of this redesign, we need to explore which Telerik control is best suited for the requested layout to achieve the desired functionality and responsiveness. Its taking more time to complete this story | K36: Rajesh and Sathiyabharathi for working on the Nav bar update. Rajesh for helping with the Escalation issue
A37: NA | B37: GGO 7.24.0 Sprint 2 | C37: 45793 | D37: 45806 | E37: 26 | F37: 23 | I37: Accomplishments: Completed Pendo Implementation Completed Nav Bar Implementation Fixed Amex card disable for select organizations Fixed Sale Grid Export issue | J37: Peer CRC:0 Onsite CRC: 0 Client CRC: 0 Internal Defects: 0 External Defects: 0 Pending Story: 1 story has been carried forward GGO-14628->Hard to reproduce in the lower environements. The offshore developers and QA's made several attempts to reproduce the issue. Team is still working on it.That’s why it was put on hold as it is of low priority | K37: Rajesh and Sathiyabharathi for the Nav bar update. Rajesh and offshore team on the quick implementation of pendo. Mike Horihan gave Kudos for the quick Pendo implementation
A38: NA | B38: GGO 7.24.0 Sprint 3 | C38: 45806 | D38: 45820 | E38: 14 | F38: 6 | G38: 5-removed | I38: Accomplishments: Completed Reskin User Profile Development | J38: Peer CRC:0 Onsite CRC: 0 Client CRC: 0 Internal Defects: 3 External Defects: 0 Pending Story: 2 stories has been carried forward GGO-14682 and GGO-14683 - Reskin-V2 is a complete overhaul of the existing Master Page. The new layout seamlessly integrates Telerik controls, Bootstrap, and Kendo UI CSS, ensuring an optimized, modern, and adaptive user experience across all devices. As part of this redesign, we need to explore which Telerik control is best suited for the requested layout to achieve the desired functionality and responsiveness. Its taking more time to complete this since UI design work is new to the development team and it is bit challenging too.Also for GGO-14682 ->Development took a lot of time and got completed only on 1 day before Sprint end, the offshore QA logged a bug on the last day of sprint | K38: 1.Sathiyabharathi and Saranya for implementing most the design changes and making sure the existing workflow is in in place +2 2.Priya for testing all the changes before sending to the PR to onsite and identifying the bugs early. 3.Rajesh for helping multiple offshore teams and get them all set up and going
A39: NA | B39: GGO 7.24.0 Sprint 4 | C39: 45820 | D39: 45834 | E39: 22 | F39: 22 | I39: Accomplishments: completed Reskin User Profile and Profject home. CRT Regression Completed for the release | J39: Peer CRC:0 Onsite CRC: 0 Client CRC: 0 Internal Defects: 0 External Defects: 0 Completed all the assigned stories | K39: Great job Team on completing all planned stories and more! It was well appreciated by everyone here at onsite. Sathiyabharathi and Saranya for focussing on project reskin Priya for completing CRT Regression and the sprint story testing Rajesh for managing all the different projects at the same time
A40: NA | B40: GGO 7.25.0 Sprint 1 | C40: 45834 | D40: 45848 | E40: 20 | F40: 10 | I40: Accomplishments:Project home page and great progress in Supporter reskin design | J40: Peer CRC:0 Onsite CRC: 0 Client CRC: 0 Internal Defects: 0 External Defects: 0 Pending :GGO-14687 and GGO-14802: 2 stories has been carried forward as we are currently working on the reskinning of the grid component. Once this is completed, the remaining stories for the upcoming sprints are expected to progress quickly. Informed to client as well | K40: GGO Dev offshore team for reskin progress Rajesh for figuring out the SalesForce production issue Priya for doing a thorough testing before sending to Dev and TST
A41: NA | B41: GGO 7.25.0 Sprint 2 | C41: 45848 | D41: 45862 | E41: 22 | F41: 9 | I41: Accompolishment : Supporter Grid Page and great progress in Common controls and Filters | J41: Peer CRC:0 Onsite CRC: 0 Client CRC: 0 Internal Defects: 3 External Defects: 0 Pending: 3 stories carried forward GGO-14688 - Can't able to complete the task as planned due to changes in the new layout design, which introduced additional controls and complexity. Also, another story GGO-14687 required more time than anticipated, which impacted the overall timeline." GGO-14802 - Development is completed. During testing,tester found 3 defects. 2 defects and this story also got carried forward. GGO-14724: Client requested to add few more things in the same story at the end of the sprint end. | K41: What went well? Progress on OneTrust Closed several MacroScope Issues Kudos QA for testing so many stories Offsore developers for the supporter grid Development
A42: NA | B42: GGO 7.25.0 Sprint 3 | C42: 45862 | D42: 45876 | E42: 24 | F42: 14 | J42: Peer CRC:0 Onsite CRC: 0 Client CRC: 0 Internal Defects: 1 External Defects: 0 Pending: 2 stories carried forward GGO-14712 and GGO-14851- The design challenges in this story prevent us from reusing existing user controls in every controls
A43: NA | B43: GGO 7.25.0 Sprint 4 | C43: 45876 | D43: 45890 | E43: 14 | F43: 14 | G43: Stretch - 6 | I43: Accomplishments: Completed Advanced filter search(Sales & Payments) for View Supporters page | J43: Peer CRC:0 Onsite CRC: 0 Client CRC: 0 Internal Defects: 3 External Defects: 0 Pending: 2 stretch stories carried forward GGO-14858 - Development part is completed. Testing is in progress. GGO-14863 - Onetrust cookies are not deleting properly to reopen the onetrsut consent popup again when clicking Privacy option under User Profile | K43: What went well? Finished all the BTT tests Kudos Offshore team for the reskin stuff is very complicated Prabhu for filling in for Rajesh
A44: NA | B44: GGO 8.0.0 Sprint 1 | C44: 45890 | D44: 45904 | E44: 15 | F44: 14 | G44: Stretch - 5 Stretch Completed - 4 | I44: Accomplishments: Completed the existing design layout issues with reskin enabled. Completed Advanced filter search(Bidders and Attendees, Staffs, Contributors and Fundaraisers) for View Supporters Page | J44: Peer CRC:0 Onsite CRC: 0 Client CRC: 0 Internal Defects: 1 External Defects: 0 Pending: 1 assigned story and 1 stretch story carried forward GGO-14875 - Onsite Dev-Mike Wall picked this story earlier did some basic changes due to design difficulties hand overed the story to offshore on 1-sep-25 and also So far, we’ve worked on implementing grid controls across all modules. The team is currently focused on the Create Pages as part of the redesign effort, which is taking additional time due to the complexity of the UI work. GGO - 14854 - Stretch stories - Development and Dev env testing completed from our QA. Pending for Review. | K44: What went well? Completed more than planned Good progress on Filter and Item page Kudos Rajesh to cover the Demo today Offshore for progress on the create item ticket Offshore Donor team for completing all planned and more stories Praveen and Sathiyabharati for fixing the existing design layout issues with reskin enabled
A45: NA | B45: GGO 8.0.0 Sprint 2 | C45: 45904 | D45: 45918 | E45: 12 | F45: 11 | G45: Stretch - 2 | I45: Accomplishment: Completed the Item Page with the new UI design, conditional on reskin being enabled. | J45: Peer CRC:0 Onsite CRC: 0 Client CRC: 0 Internal Defects: 1 External Defects: 0 Pending: 1 assigned story carried forward Due to complications involving multiple user controls on the filter page, some functions within the new user control are not triggering as expected. Additionally, new controls were added which require further integration and testing to ensure smooth functionality. | K45: What went well? Donor Api work went well Items page got done Pendo and one trust deployed to prod Kudos Praveen and Sathiyabharthi for finishing the Item story +1 Rajesh and Donor offshore team for the Donor API progress+1
A46: NA | B46: GGO 8.0.0 Sprint 3 | C46: 45918 | D46: 45932 | E46: 15 | F46: 15 | G46: Stretch -2 | I46: Accomplishment: Completed Saved Search and more than planned story points | J46: Peer CRC:0 Onsite CRC: 0 Client CRC: 0 Internal Defects: 0 External Defects: 0 Completed all the assigned stories | K46: What went well? Completed more than planned story points Kudos Rajesh e for picking up the slack and working on the credit card stuff Conor for doing all the testing related to Carlos changing storage account settings in all Environments Offshore team booth GGO and GDONOr for completing all the planned stories and more Saranya and Sathiyabharti for completing the save search
A47: NA | B47: GGO 8.0.0 Sprint 4 | C47: 45932 | D47: 45946 | E47: 13 | F47: 13 | G47: Stretch - 1 | I47: Accomplishment: Completed Rich Text editor and Image Control (Multi Image chooser) | J47: Peer CRC:0 Onsite CRC: 0 Client CRC: 0 Internal Defects: 0 External Defects: 0 Completed all the assigned stories | K47: What went well? Met the Sprint goal Kudos Rajesh for finding the needle in the hay stack, finding the root cause for Go time error GGO team for meeting the goal +1 Jennifer for keeping up with all the UI changes +1
A48: NA | B48: GGO 8.1.0 Sprint 1 | C48: 45946 | D48: 45960 | E48: 17 | F48: 12 | I48: Accomplishment: Completed Group by Household functionality and fixed variuos issue in View Supporters Filter | J48: Peer CRC:0 Onsite CRC: 0 Client CRC: 0 Internal Defects: 0 External Defects: 0 Pending: 1 assigned story carried forward GGO-14901 - Since the design is more complex for the manage images popup and focused on group items by household functionality in the view supporters filter | K48: What went well? The team was able to respond to the Azure outage very fast Kudos Mike H: Rajesh for figuring out the Pendo One trust thing and RDLC receipt problem Rajesh: Offshore for implementing the household in the supporter grid +1 Conor for keeping up with everything on 2 teams +1 Priya for doing multiple round of testing household and CRT +1
A49: NA | B49: GGO 8.1.0 Sprint 2 | C49: 45960 | D49: 45974 | E49: 23 | F49: 23 | G49: Stretch -1 | I49: Accomplishment: Completed Manage pop up design changes and completed all planned and more | J49: Peer CRC:0 Onsite CRC: 0 Client CRC: 0 Internal Defects: 0 External Defects: 0 Completed all the assigned stories | K49: What went well? Completed all planned and more Good feedback from CS, customers and Kisa during the Sprint review Kudos Conor Kudos to Rajesh for getting the hotfixes out quickly Mike H: The team for going over and beyond and the extra late nights Rajesh: Kudos to Conor and Priya for testing the hotfixes in all the environments Sathiya and Saranaya for the Manage pop up design changes.
A50: NA | B50: GGO 8.1.0 Sprint 3 | C50: 45974 | D50: 45988 | E50: 19 | F50: 24 | G50: Stretch -3 2 stretch stories are completed. Development is completed for 1 story | I50: Accomplishment: Completed all planned stories and more | J50: Peer CRC:0 Onsite CRC: 0 Client CRC: 0 Internal Defects: 0 External Defects: 0 Completed all the assigned stories | K50: What went well? Completed all planned stories and more Kudos Conor Mike H: The whole team for another impressive Sprint especially Dev Rajesh: Offshore for completing the overall Sprint goal Priya and Conor for testing all kind of scenarios for current sprint stories Doug Thank you for the super quick turn around on the RSVP escalation Great work team!
A51: NA | B51: GGO 8.1.0 Sprint 4 | C51: 45988 | D51: 46002 | E51: 21 | F51: 21 | G51: Stretch -2 GGO-15068 - Development completed. Testing is in progress GGO-15086 Development is in progress | I51: Accomplishment: Completed more than planned and Create/Edit Package Page | J51: Peer CRC:0 Onsite CRC: 0 Client CRC: 0 Internal Defects: 0 External Defects: 0 Completed all the assigned stories | K51: What went well? Completed more than planned Kudos Conor Priya for helping out with current sprint story testing Mike H: Rajesh for keeping up with everything and making sure the team is successful Conor and Priya for CRT regression and current sprint stories Keep up the good work!
A52: NA | B52: GGO 8.2.0 Sprint 1 | C52: 46002 | D52: 46030 | E52: 30 | F52: 39 | G52: Stretch -5 4 Stretch stories completed 1 story is pending GGO-15123 - Development is completed | I52: Accomplishment: Completed more than planned story points Completed Online Bidding Settings View/Edit Design Updated Supporter API for NextGen Completed no negative search for Sales and Payments | J52: Peer CRC:0 Onsite CRC: 0 Client CRC: 0 Internal Defects: 0 External Defects: 0 Completed all the assigned stories | K52: What went well? Completed all planned and more stories even through the holidays Kudos Conor Mike H: Offshore is on autopilot Rajesh: Sathiyabharathi for the Online bidding settings Priya for general testing of all stories through the holidays(+1 Conor) Charles and Vishnu for completing the GGAM online activity story
A53: NA | B53: GGO 8.2.0 Sprint 3 | C53: 46030 | D53: 46044 | E53: 22 | F53: 19 | I53: Accomplishment: Completed Duplicate EventXCode Completed Jscramber Implementation | J53: Peer CRC:0 Onsite CRC: 0 Client CRC: 0 Internal Defects: 0 External Defects: 0 Pending: 2 assigned stories carried forward GGO-14628 Hard to reproduce the the Print invoice/receipt page issue in lower environment GGO-15135 Development and testing is completed by our end. Settings to be updated by Jscramber IT team | K53: What went well? Sizable commit Completed Kudos Mike H: Team for getting sizable commit done Rajesh and Conor for managing 2 teams Rajesh: Kudos to GGO and GDON team for completing all the committed work
A54: NA | B54: GGO 8.2.0 Sprint 4 | C54: 46044 | D54: 46058 | E54: 19 | F54: 23 | G54: 5 | I54: Accomplishment: Refined Supporter Query | J54: Peer CRC:0 Onsite CRC: 0 Client CRC: 0 Internal Defects: 0 External Defects: 0 Pending: 2 assigned stories carried forward GGO-14628 - For this issue, a temporary fix has been provided by the offshore development team. However, the client has requested a permanent fix with a different approach, so the story has been carried forward GGO-15140 - CRT regression testing has been completed by the offshore QA team. The onsite QA requested that this story be put on hold, as WAF testing is still pending on his side. Therefore, the story has been carried forward | K54: What went well? Sizable commit completed Kudos Mike H: Rajesh for the refining the supporter query Rajesh: Offshore GGO and GDOn team for completing all the stories | N54: 1 | O54: 0.5
A55: NA | B55: GGO 8.3.0 Sprint 1 | C55: 46058 | D55: 46072 | E55: 23 | F55: 28 | G55: 7 | I55: Accomplishment: 1. Achieved a 20% usability improvement with the Reskin project, enhancing user experience and efficiency. 2. Successfully met the planned commit targets and seamlessly integrated additional patch work mid-sprint. 3. Thoroughly tested all report scenarios, ensuring quality and reliability. 4. Completed most of the report changes, driving progress forward. | J55: Peer CRC:0 Onsite CRC: 0 Client CRC: 0 Internal Defects: 0 External Defects: 0 Pending: 1 story carried forward GGO-14628 - Development has been completed. Since we planned to provide a permanent fix, instead of calculating the mostRecentDate at the time of generating invoices or receipts, we decided to pre-calculate and update the relevant tables when associating sales with the corresponding payments. Initially, this logic was implemented in code, but later we moved it to triggers. As this is a major change, the testing effort required is significant, so the work has been carried forward. | K55: What went well? Met the planned commit commit along with the patch work which was added mid sprint Kudos Mike H: The whole team for meeting the allocated story points Rajesh: Sathiyabharathi for fixing all the report bugs(+1 Jennifer) Conor and Priya for testing all the scenarios for the Report Saranya for the working on the Print email timeout issue GDON team for completing the planned stories Doug Finished most of the Report changes 20% improvement in usability with the Reskin project | N55: 1 | O55: 1
A56: NA | B56: GGO 8.3.0 Sprint 2 | C56: 46072 | D56: 46086 | E56: 22 | F56: 29 | G56: 7 | I56: Accomplishment: 1. Successfully met the planned commit targets 2. Successfully completed Print/Email invoice or receipts issue | J56: Peer CRC:0 Onsite CRC: 0 Client CRC: 0 Internal Defects: 0 External Defects: 0 Completed all the assigned stories | K56: What went well? Met the planned commit Kudos Mike H: Rajesh for handling multiple teams here, handling the super difficult stories Rajesh: Offshore team for achieving the sprint goal | N56: 1 | O56: 1
A57: NA | B57: GGO 8.3.0 Sprint 3 | C57: 46086 | D57: 46100 | E57: 23 | F57: 26 | G57: 4 | I57: Accomplishment: 1. Successfully met the planned commit targets 2. Successfully completed RSVP Dashboard | J57: Peer CRC:0 Onsite CRC: 0 Client CRC: 0 Internal Defects: 0 External Defects: 0 Completed all the assigned stories | K57: What went well? Completed all planned stories and more Kudos Mike H: Rajesh for getting the receipt print and duplicate bidder key tickets completed Conor for doing double duty and keep the operation afloat (+1 Rajesh) Rajesh for triple duty Rajesh: Whole GGo offshore team for achieving the goal(+1Mike H) Sathiyabharathi Paramasivam [C] for working on the RSVP functionality Jennifer Anthony Bosco [C] for always supporting the team and clarifying any question that the team has | N57: 1 | O57: 2
A58: NA | B58: GGO 8.3.0 Sprint 4 | C58: 46100 | D58: 46114 | E58: 20 | F58: 21 | G58: 4 | I58: Accomplishment: 1. Most of the planned sprint stories were successfully delivered. 2. Rajesh ensured smooth handling of LLBGen setup challenges, addressing edge cases and performance issues 3. Team members supported each other, with kudos highlighting individual and collective efforts. | J58: Peer CRC:0 Onsite CRC: 0 Client CRC: 0 Internal Defects: 0 External Defects: 0 Pending: 1 stretch story carried forward GGO-12244 - Development was delayed because we received the setup file only on the last day of the sprint. | K58: What went well? Completed most of the stories Kudos Mike H: Rajesh for keep it all coordinated specially the LLBGen files tones of edge cases fixed, performance Rajesh: Offshore team for completing the stories in the sprint | N58: 4 | O58: 4
A59: NA | B59: GGO 8.4.0 Sprint 1 | C59: 46114 | D59: 46128 | E59: 20 | F59: 28 | G59: 10 | H59: Successfully implemented Reskin design for Sales Page. Successfully implemented the Text Template and SMS request once the checkout is done , and implemented a new Donor API - CheckBidderHouseHold for both Individual and Household supported and Implemented the GetCreditCards API which was always returning as 2 - while updating the AddressTypeId | I59: Accomplishment: 1. The team achieved timely completion of the majority of planned sprint stories, ensuring consistent progress toward project goals. 2. Fixed some synk vulnerability issues 3. API Support for mobile team | J59: Peer CRC:0 Onsite CRC: 0 Client CRC: 0 Internal Defects: 0 External Defects: 0 Completed all the assigned stories | K59: What went well? Completed all the stories and some stretch Kudos Mike H: Rajesh and Conor for pulling double duty on teams Rajesh: Whole GGO and GDON offshore team for completing all the tickets Conor, Priya and Charles for completing the testing for all the stories | N59: 4 | O59: 4 | P59: 1357
A60: NA | B60: GGO 8.4.0 Sprint 2 | C60: 46128 | D60: 46142 | E60: 21 | F60: 22 | G60: 3 | H60: This sprint's focus is to further develop the GGO Reskin for the Sales and Payments pages, which includes the Create/Edit Sales & Payments, Common Controls, and Advanced search functionalities. It also covers the page functionalities for Non-Admin users. Moreover, there are plans to work on the APIs for Donor Check-out and Check-in. Furthermore, the Username will be updated for receipt generation when requests are received from NextGen for the Mobile team. | I60: Accomplishment: 1. Finished all the designated stories 2. Effectively executed the Reskin design for the Sales and Payments Page 3. Provided API support for the Mobile and Donor Team | J60: Peer CRC:0 Onsite CRC: 1 1. Is there a common JavaScript file with this function in it to include instead of the inline javascript? Client CRC: 0 Internal Defects: 0 External Defects: 0 Completed all the assigned stories. | K60: What went well? Rajesh and Conor did double duty as always and still managed to complete more than forecast Completed all the stories and some stretch Kudos Rajesh: Offshore GGO and GDon for completing all the stories Sathiyabharathi for completing the sales stories, as it was complex Priya for testing all the sales stories | N60: 4 | O60: 4 | P60: 1330
A61: NA | B61: GGO 8.4.0 Sprint 3 | C61: 46142 | D61: 46156 | E61: 20 | F61: 21 | G61: 3 | H61: In this Sprint, we are continuing our efforts on the GGO Reskin for the Sales and Payments pages, which includes addressing some outstanding items concerning Manage Charge Batches. Additionally, we are implementing fixes for Priority defects, improving Infrastructure, and offering support for APIs associated with Donor Check-out. | I61: Accomplishment: 1. Successfully achieved the Sprint objective 2. Completed the development of the Create Refund page - Edit Payments 3. Executed the implementation of the Manage Charge Batch pages within Sales & Payments 4. Certain Donor Check-in and API functionalities have been developed 5. A number of priority bugs have been fixed 6. Lastly, worked on some of the Synk findings | J61: Peer CRC:0 Onsite CRC: 0 Client CRC: 0 Internal Defects: 0 External Defects: 0 Completed all the assigned stories. | K61: Well Done team in maintaining consistent Delivery! What went well? Completed all planned stories and more Kudos Mike H: Rajesh for supporting 3 teams and Conor for supporting 2 teams Rajesh: GGO and GDON offshore team for achieving the sprint goal (+1 Mike) | P61: 1334
A62: NA | B62: GGO 8.4.0 Sprint 4 | C62: 46156 | D62: 46170 | E62: 23

Sheet Unplanned Leaves
B1: Resource Name
A2: Sprint Name | B2: Priyadharshini Ravichandran | C2: Saranya Namachivayam | D2: Jennifer | E2: Sathiyabharathi | F2: Rajesh | G2: Total Planned Leaves | H2: Remarks
A3: GGO 8.3.0 Sprint 1 (05-Feb-26 to 19-Feb-26) | B3: 1 | C3: 0 | D3: 0 | E3: 0 | F3: 0 | G3: =SUM(B3:F3) -> 1
A4: GGO 8.3.0 Sprint 2 (19-Feb-26 to 05-Mar-26) | B4: 0 | C4: 0 | D4: 0 | E4: 0 | F4: 0 | G4: =SUM(B4:F4) -> 0
A5: GGO 8.3.0 Sprint 3 (05-Mar-26 to 19-Mar-26) | B5: 0 | C5: 1 | D5: 0.5 | E5: 0 | F5: 0 | G5: =SUM(B5:F5) -> 1.5
A6: GGO 8.3.0 Sprint 4 (19-Mar-26 to 02-Apr-26) | B6: 1 | C6: 2 | D6: 0 | E6: 1 | F6: 1 | G6: =SUM(B6:F6) -> 5
A7: GGO 8.4.0 Sprint 1 (02-Apr-26 to 16-Apr-26) | B7: 1 | C7: 0 | D7: 1 | E7: 1 | F7: 0 | G7: =SUM(B7:F7) -> 3
A8: GGO 8.4.0 Sprint 2 (16-Apr-26 to 30-Apr-26) | B8: 0 | C8: 0 | D8: 0 | E8: 0 | F8: 0 | G8: 0
A9: GGO 8.4.0 Sprint 3 (30-Apr-26 to 14-May-26) | B9: 0 | C9: 0 | D9: 0.5 | E9: 1 | F9: 3 | G9: 4.5
E35: ]

Sheet GGO 8.4.0 Sprint 4-Status
A1: S.No | B1: Application Name | C1: Sprint Start Date | D1: Sprint End Date | E1: Sprint | F1: Developer | G1: Story ID/Defect ID | H1: Description | I1: Status | J1: Estimated(sp) | K1: Actual(sp) | L1: Actual Hours Worklog | M1: Dev Start Date | N1: Dev End Date | O1: Unit testing | P1: Peer Tested By | Q1: Peer Tested Defects, if any | R1: Peer Reviewed By | S1: Peer Code Review Comments, if any | T1: PR Number/Link | U1: PR Created Date | V1: PR Approved Date | W1: Reviewer 1 | X1: Code Review Comments, if any | Y1: Reviewer 2 | Z1: Approved Date | AA1: Code Review Comments, if any2 | AB1: Internal PO -POV Comments | AC1: Client PO -POV Comments | AD1: Comments
A2: 1 | B2: GGO Web | C2: 46156 | D2: 46170 | E2: GGO 8.4.0 Sprint 4 | F2: Saranya | G2: GGO-15245 | H2: Snyk Finding - Microsoft.AspNetCore.Server.Kestrel@2.2.0 update to 2.3.6 | I2: Being Developed | J2: 2 | M2: 46157
A3: 2 | B3: GGO Web | C3: 46156 | D3: 46170 | E3: GGO 8.4.0 Sprint 4 | G3: GGO-15170 | H3: Employee Controls for Reports | I3: Refinement | J3: 5
A4: 3 | B4: GGO Web | C4: 46156 | D4: 46170 | E4: GGO 8.4.0 Sprint 4 | F4: Saranya | G4: GGO-14513 | H4: Log Quartz Job errors in Elmah log | I4: Being Developed | J4: 2 | M4: 46157
A5: 4 | B5: GGO Web | C5: 46156 | D5: 46170 | E5: GGO 8.4.0 Sprint 4 | F5: Rajesh | G5: PAPI-291 | H5: PAPI is using an old version of LLBGEN i.e. 2.5. We need to upgrade to the latest LLBGen i.e. 5.8 | I5: Being Developed | J5: 3 | M5: 46157
A6: 5 | B6: GGO Web | C6: 46156 | D6: 46170 | E6: GGO 8.4.0 Sprint 4 | G6: GGO-15251 | H6: Project Builder - Feature Flag to turn off/on the changes | I6: Refinement | J6: 2
A7: 6 | B7: GGO Web | C7: 46156 | D7: 46170 | E7: GGO 8.4.0 Sprint 4 | F7: Sathiya | G7: GGO-15219 | H7: Project Builder - Create Project - Getting Started section | I7: Being Developed | J7: 5 | M7: 46157
A8: 7 | B8: GGO Web | C8: 46156 | D8: 46170 | E8: GGO 8.4.0 Sprint 4 | F8: Priya-QA | G8: GGO-15242 | H8: 19 May GGO 8.4.0 CRT Release & Regression testing | I8: Refinement | J8: 3
A9: 8 | B9: GGO Web | C9: 46156 | D9: 46170 | E9: GGO 8.4.0 Sprint 4 | F9: Priya-QA | G9: PAPI-898 | H9: 19 May PAPI 8.2.0 CRT Release & Regression testing | I9: Refinement | J9: 1

Sheet GGO 8.4.0 Sprint 4-Defect
A1: S.No | B1: Sprint # | C1: Story/Defect ID | D1: Parent Story | E1: Developer | F1: Issue Type | G1: Issue Description | H1: Priority | I1: Defect Source | J1: Type | K1: Status | L1: Root Cause Category | M1: Found By | N1: Comment | O1: RCA Comment
G2: NO Defects

Sheet GGO 8.4.0 Sprint 3-Status
A1: S.No | B1: Application Name | C1: Sprint Start Date | D1: Sprint End Date | E1: Sprint | F1: Developer | G1: Story ID/Defect ID | H1: Description | I1: Status | J1: Estimated(sp) | K1: Actual(sp) | L1: Actual Hours Worklog | M1: Dev Start Date | N1: Dev End Date | O1: Unit testing | P1: Peer Tested By | Q1: Peer Tested Defects, if any | R1: Peer Reviewed By | S1: Peer Code Review Comments, if any | T1: PR Number/Link | U1: PR Created Date | V1: PR Approved Date | W1: Reviewer 1 | X1: Code Review Comments, if any | Y1: Reviewer 2 | Z1: Approved Date | AA1: Code Review Comments, if any2 | AB1: Internal PO -POV Comments | AC1: Client PO -POV Comments | AD1: Comments
A2: 1 | B2: GGO Web | C2: 46142 | D2: 46156 | E2: GGO 8.4.0 Sprint 3 | F2: Saranya | G2: GGO-15229 | H2: Edit Payments - Create Refund page | I2: Completed | J2: 2 | K2: 2 | L2: 14 | M2: 46116 | N2: 46147 | O2: Done | P2: Priya | R2: Sathiya | T2: https://greatergiving.visualstudio.com/Greater%20Giving/_git/GGO/pullrequest/9520 | U2: 46141 | V2: 46147 | W2: Rajesh | Y2: Mike Horihan | Z2: 46148 | AD2: Created a enhanced refund page on 04/29/2026 Unit testing done and Created a PR on 04/30/2026. Testing Completed in the TST env
A3: 2 | B3: GGO Web | C3: 46142 | D3: 46156 | E3: GGO 8.4.0 Sprint 3 | F3: Rajesh | G3: GGO-15230 | H3: Validate Sales Force Invoice Posted Items API flow with real data | I3: Completed | J3: 2 | K3: 2 | L3: 12 | M3: 46143 | N3: 46155 | O3: Done | P3: Priya | R3: Saranya | T3: https://greatergiving.visualstudio.com/Greater%20Giving/_git/GGO/pullrequest/9562 | U3: 46155 | V3: NA | W3: NA | Y3: Mike Horihan | Z3: 46155 | AD3: Testing Completed in the TST env
A4: 3 | B4: GGO Web | C4: 46142 | D4: 46156 | E4: GGO 8.4.0 Sprint 3 | F4: Rajesh | G4: GGO-15216 | H4: Online Bidding setup opens Old UI instead of New Online Bidding UI | I4: Completed | J4: 1 | K4: 1 | L4: 11 | M4: 46143 | N4: 46143 | O4: Done | P4: Priya | R4: Saranya | T4: https://greatergiving.visualstudio.com/Greater%20Giving/_git/GGO/pullrequest/9532 | U4: 46147 | V4: NA | W4: NA | Y4: Mike Horihan | Z4: 46147 | AD4: Testing Completed in the TST env
A5: 4 | B5: GGO Web | C5: 46142 | D5: 46156 | E5: GGO 8.4.0 Sprint 3 | F5: Rajesh | G5: GGO-15218 | H5: New GGO Clients are not setup with bluetooth | I5: Completed | J5: 2 | K5: 2 | L5: 5 | M5: 46143 | N5: 46147 | O5: Done | P5: Priya | R5: Saranya | T5: https://greatergiving.visualstudio.com/Greater%20Giving/_git/GGO/pullrequest/9533 | U5: 46147 | V5: NA | W5: NA | Y5: Mike Horihan | Z5: 46147 | AD5: Testing Completed in the TST env
A6: 5 | B6: GGO Web | C6: 46142 | D6: 46156 | E6: GGO 8.4.0 Sprint 3 | F6: Sathiya | G6: GGO-14911 | H6: Sales & Payments - Manage Charge Batches | I6: Completed | J6: 5 | K6: 5 | L6: 44.5 | M6: 46146 | N6: 46148 | O6: Done | P6: Priya | R6: Rajesh | T6: https://dev.azure.com/greatergiving/Greater%20Giving/_git/GGO/pullrequest/9535 | U6: 46148 | V6: 46148 | W6: NA | Y6: Mike Horihan | Z6: 46148 | AD6: Copied all the necessary files from oldl ayout 05/04/2026 Created an enhanced charge batch page 05/05/2026 Unit testing done and Created a PR on 05/06/2026. Testing Completed in the TST env
A7: 6 | B7: GGO Web | C7: 46142 | D7: 46156 | E7: GGO 8.4.0 Sprint 3 | F7: Saranya | G7: GGO-14912 | H7: Sales & Payments - View Charge Batch Page | I7: Completed | J7: 5 | K7: 5 | L7: 54.5 | M7: 46146 | N7: 46150 | O7: Done | P7: Priya | R7: Sathiya | T7: https://greatergiving.visualstudio.com/Greater%20Giving/_git/GGO/pullrequest/9550 | U7: 46150 | V7: NA | W7: NA | Y7: Mike Horihan | Z7: 46153 | AD7: Copied all the necessary files from old ayout 05/04/2026 Created an enhanced charge batch page 05/05/2026 Created an enhanced declined page on 05/06/2026 Incorporated UI changes suggested by Jennifer on 05/07/2026 Unit testing done and Created a PR on 05/08/2026. Testing Completed in the TST env
A8: 7 | B8: GGO Web | C8: 46142 | D8: 46156 | E8: GGO 8.4.0 Sprint 3 | F8: Rajesh | G8: GGO-15150 | H8: BID-10 report not showing image | I8: Completed | J8: 2 | K8: 2 | L8: 5 | M8: 46146 | N8: 46148 | O8: Done | P8: Priya | R8: Sathiya | T8: https://greatergiving.visualstudio.com/Greater%20Giving/_git/GGO/pullrequest/9537 | U8: 46148 | V8: NA | W8: NA | Y8: Mike Horihan | Z8: 46148 | AD8: Testing Completed in the TST env
A9: 8 | B9: GGO Web | C9: 46142 | D9: 46156 | E9: GGO 8.4.0 Sprint 3 | F9: Saranya | G9: GGO-15157 | H9: Lack of ConvenienceFeeRate in sectionGridSettings causes error | I9: Completed | J9: 1 | K9: 1 | L9: 9 | M9: 46153 | N9: 46153 | O9: Done | P9: Priya | R9: Rajesh | T9: https://greatergiving.visualstudio.com/Greater%20Giving/_git/GGO/pullrequest/9556 | U9: 46153 | W9: Rajesh | Y9: Mike Horihan | AD9: Fixed ConvenienceFeeRate issue in SectionGrid Settings, Unit testing done and Created a PR on 05/11/2026. Testing Completed in the TST env
A10: 9 | B10: GGO Web | C10: 46142 | D10: 46156 | E10: GGO 8.4.0 Sprint 3 [STRETCH] | F10: Sathiya | G10: GGO-15247 | H10: Snyk Finding - System.Security.Cryptography.Xml@8.0.2 update to 8.0.3 | I10: Completed | J10: 1 | K10: 1 | L10: 28 | M10: 46154 | N10: 46154 | O10: Done | P10: Priya | R10: Rajesh | T10: https://dev.azure.com/greatergiving/Greater%20Giving/_git/GGO/pullrequest/9560 | U10: 46154 | V10: 46154 | W10: Rajesh | Y10: Mike Horihan | Z10: 46154 | AA10: Also seeing the reference in GreaterGiving.Online.Website.Reskin | AD10: Updated package version did dev testing PR created 05/12/2026 Addressed code review comments . Updated package across all the solution did dev testing PR updated 05/13/2026. Testing Completed in the TST env
A11: 10 | B11: GGO Web | C11: 46142 | D11: 46156 | E11: GGO 8.4.0 Sprint 3 [STRETCH] | F11: Saranya | G11: GGO-15245 | H11: Snyk Finding - Microsoft.AspNetCore.Server.Kestrel@2.2.0 update to 2.3.6 | I11: Being Developed | J11: 2 | K11: 0 | L11: 12 | M11: 46155

Sheet GGO 8.4.0 Sprint 3-Defect
A1: S.No | B1: Sprint # | C1: Story/Defect ID | D1: Parent Story | E1: Developer | F1: Issue Type | G1: Issue Description | H1: Priority | I1: Defect Source | J1: Type | K1: Status | L1: Root Cause Category | M1: Found By | N1: Comment | O1: RCA Comment
G2: NO Defects

Sheet GGO 8.4.0 Sprint 2-Status
A1: S.No | B1: Application Name | C1: Sprint Start Date | D1: Sprint End Date | E1: Sprint | F1: Developer | G1: Story ID/Defect ID | H1: Description | I1: Status | J1: Estimated(sp) | K1: Actual(sp) | L1: Actual Hours Worklog | M1: Dev Start Date | N1: Dev End Date | O1: Unit testing | P1: Peer Tested By | Q1: Peer Tested Defects, if any | R1: Peer Reviewed By | S1: Peer Code Review Comments, if any | T1: PR Number/Link | U1: PR Created Date | V1: PR Approved Date | W1: Reviewer 1 | X1: Code Review Comments, if any | Y1: Reviewer 2 | Z1: Approved Date | AA1: Code Review Comments, if any2 | AB1: Internal PO -POV Comments | AC1: Client PO -POV Comments | AD1: Comments
A2: 1 | B2: GGO Web | C2: 46128 | D2: 46142 | E2: GGO 8.4.0 Sprint 2 | F2: Saranya | G2: GGO-14792 | H2: View Payments Page | I2: Completed | J2: 1 | K2: 1 | L2: 13 | M2: NA | N2: NA | O2: Done | P2: Priya | R2: Sathiya | T2: https://greatergiving.visualstudio .com/Greater%20Giving/_git/GGO/ pullrequest/9464 | U2: 46125 | V2: 46129 | W2: Rajesh | Y2: Mike Horihan | Z2: 46130 | AA2: No concerns have been noted up to this point; it will be rolled over. | AD2: Payments Grid new reskin design implementation started on 04/10/2026 Developement and testing completed. Created a PR on 04/13/2026
A3: 2 | B3: GGO Web | C3: 46128 | D3: 46142 | E3: GGO 8.4.0 Sprint 2 | F3: Saranya | G3: GGO-14818 | H3: View Payments Common controls | I3: Completed | J3: 1 | K3: 1 | L3: 12 | M3: NA | N3: NA | O3: Done | P3: Priya | R3: Sathiya | T3: https://greatergiving.visualstudio .com/Greater%20Giving/_git/GGO/ pullrequest/9464 | U3: 46125 | V3: 46129 | W3: Rajesh | Y3: Mike Horihan | Z3: 46130 | AA3: No concerns have been noted up to this point; | AD3: Implemented Payments Grid common controls and testing completed. Created a PR on 04/13/2026
A4: 3 | B4: GGO Web | C4: 46128 | D4: 46142 | E4: GGO 8.4.0 Sprint 2 | F4: Saranya | G4: GGO-14820 | H4: View Payments Advanced search | I4: Completed | J4: 2 | K4: 2 | L4: 29 | M4: 46129 | N4: 46134 | O4: Done | P4: Priya | R4: Rajesh | T4: https://greatergiving.visualstudio.com/Greater%20Giving/_git/GGO/pullrequest/9485 | U4: 46129 | V4: 46134 | W4: Rajesh | Y4: Mike Horihan | Z4: 46134 | AA4: Is there a common JavaScript file with this function in it to include instead of the inline javascript? | AD4: Implemented Payment Advanced search filters and Unit Testing done on 04/17/2026 Moved Payment Reference # serach into Advanced Search Filter and tested on 04/21/2026 Incorporated code review comments given by MikeH and tested on 04/22/2026
A5: 4 | B5: GGO Web | C5: 46128 | D5: 46142 | E5: GGO 8.4.0 Sprint 2 | F5: Sathiya | G5: GGO-14791 | H5: Create/Edit Sales page | I5: Completed | J5: 5 | K5: 5 | L5: 52 | M5: 46129 | N5: 46135 | O5: Done | P5: Priya | R5: Rajesh | T5: https://greatergiving.visualstudio.com/Greater%20Giving/_git/GGO/pullrequest/9501 | U5: 46135 | V5: 46140 | W5: Rajesh | Y5: Mike Horihan | Z5: 46140 | AD5: Started implementing Create/Edit Sales Page on 04/17/2026 Started to implement details tab on 04/20/2026. Started to implement purchaser tab on 04/21/2026. Started to implement admission tab on 04/22/2026 Admisson tab grid design update on 04/23/2026 Details tab rsvp url design update on 04/24/2026 Completed Testing
A6: 5 | B6: GGO Web | C6: 46128 | D6: 46142 | E6: GGO 8.4.0 Sprint 2 | F6: Sathiya | G6: GGO-15209 | H6: View Sales page for Non-Admin users | I6: Completed | J6: 3 | K6: 3 | L6: 21 | M6: 46139 | N6: 46140 | O6: Done | P6: Priya | R6: Saranya | T6: https://greatergiving.visualstudio.com/Greater%20Giving/_git/GGO/pullrequest/9516 | U6: 46140 | V6: 46141 | W6: Rajesh | Y6: Mike Horihan | Z6: 46141 | AD6: Design update for non-admin users on 04/28/2026 Jennifer gave some inputs changing the control design applied the design on 04/28/2026
A7: 6 | B7: GGO Web | C7: 46128 | D7: 46142 | E7: GGO 8.4.0 Sprint 2 | F7: Saranya | G7: GGO-14793 | H7: Create/Edit Payment page | I7: Completed | J7: 5 | K7: 5 | L7: 33 | M7: 46132 | N7: 46139 | O7: Done | P7: Priya | R7: Rajesh | T7: https://greatergiving.visualstudio.com/Greater%20Giving/_git/GGO/pullrequest/9512 | U7: 46139 | V7: 46140 | W7: Rajesh | Y7: Mike Horihan | Z7: 46141 | AD7: Started implementing Create/Edit Payment Page on 04/20/2026. Worked on Grid changes on 04/23/2026 Worked on alignment issues and new Datepicker on 04/24/2026 Implemented indeterminate checkbox on 04/27/2026 Verified in the Dev env. 4/28/2026 3:54 PM
A8: 7 | B8: GGO Web | C8: 46128 | D8: 46142 | E8: GGO 8.4.0 Sprint 2 | F8: Saranya | G8: GGO-15210 | H8: View Payments page for Non-Admin users | I8: Completed | J8: 3 | K8: 3 | L8: 12 | M8: 46139 | N8: 46140 | O8: Done | P8: Priya | R8: Sathiya | T8: https://greatergiving.visualstudio.com/Greater%20Giving/_git/GGO/pullrequest/9512 | U8: 46139 | V8: 46140 | W8: Rajesh | Y8: Mike Horihan | Z8: 46141 | AD8: Started implementing view payments for non-admin user on 04/27/2026 Unit testing done and created a PR on 04/28/2026
A9: 8 | B9: GGO Web | C9: 46128 | D9: 46142 | E9: GGO 8.4.0 Sprint 2 | F9: Rajesh | G9: GGO-15215 | H9: Update Username for receipt generation when receiving the request from NextGen | I9: Completed | J9: 1 | K9: 1 | L9: 10 | M9: 46132 | N9: 46135 | O9: Done | P9: Priya | R9: Saranya | T9: https://greatergiving.visualstudio.com/Greater%20Giving/_git/GGO/pullrequest/9503 | U9: 46135 | V9: NA | W9: NA | Y9: Patterson, Scott | Z9: 46136 | AD9: Implemented passing username as a parameter in cookie header from nextgen API instead of using AesopSession username on 04/20/2026 Fixed invoice generation error on 04/21/2026 Unit testing done and Created a PR on 04/23/06
A10: 9 | B10: GGO Web | C10: 46128 | D10: 46142 | E10: GGO 8.4.0 Sprint 2 [STRETCH] | F10: Saranya | G10: GGO-15229 | H10: Edit Payments - Create Refund page | I10: Being Developed | J10: 3 | K10: 1 | L10: 12 | M10: 46141 | N10: 46142 | T10: https://greatergiving.visualstudio.com/Greater%20Giving/_git/GGO/pullrequest/9520 | U10: 46141 | W10: Rajesh | Y10: Mike Horihan | AD10: Created a enhanced refund page on 04/29/2026 Unit testing done and Created a PR on 04/30/2026

Sheet GGO 8.4.0 Sprint 2-Defect
A1: S.No | B1: Sprint # | C1: Story/Defect ID | D1: Parent Story | E1: Developer | F1: Issue Type | G1: Issue Description | H1: Priority | I1: Defect Source | J1: Type | K1: Status | L1: Root Cause Category | M1: Found By | N1: Comment | O1: RCA Comment
G2: NO Defects

Sheet GGO 8.4.0 Sprint 1-Status
A1: S.No | B1: Application Name | C1: Sprint Start Date | D1: Sprint End Date | E1: Sprint | F1: Developer | G1: Story ID/Defect ID | H1: Description | I1: Status | J1: Estimated(sp) | K1: Actual(sp) | L1: Actual Hours Worklog | M1: Dev Start Date | N1: Dev End Date | O1: Unit testing | P1: Peer Tested By | Q1: Peer Tested Defects, if any | R1: Peer Reviewed By | S1: Peer Code Review Comments, if any | T1: PR Number/Link | U1: PR Created Date | V1: PR Approved Date | W1: Reviewer 1 | X1: Code Review Comments, if any | Y1: Reviewer 2 | Z1: Approved Date | AA1: Code Review Comments, if any2 | AB1: Internal PO -POV Comments | AC1: Client PO -POV Comments | AD1: Comments
A2: 1 | B2: GGO Web | C2: 46114 | D2: 46128 | E2: GGO 8.4.0 Sprint 1 | F2: Rajesh | G2: GGO-12244 | H2: LLBGen Upgrade to the latest version | I2: Completed | J2: 2 | K2: 2 | L2: 18 | M2: 46101 | N2: 46113 | O2: Done | P2: Priya | R2: Saranya | T2: https://greatergiving.visualstudio.com/Greater%20Giving/_git/GGO/pullrequest/9424 | U2: 46113 | V2: 46113 | W2: Rajesh | Y2: Mike Horihan | Z2: 46114 | AD2: Got LLBLGen 5.10.1 setup file and started to work on it on 03/30/2026 Completed development, PR created and sent it to Approval on 04/01/2026 Testing completed in the TST env.
A3: 2 | B3: GGO Web | C3: 46114 | D3: 46128 | E3: GGO 8.4.0 Sprint 1 | F3: Saranya | G3: GGO-15169 | H3: API update to provide card expiration date to next gen | I3: Completed | J3: 1 | K3: 1 | L3: 6 | M3: 46113 | N3: 46113 | O3: Done | P3: Priya | R3: Rajesh | T3: https://greatergiving.visualstudio.com/Greater%20Giving/_git/GGO/pullrequest/9426 | U3: 46114 | V3: 46116 | W3: Rajesh | Y3: Mike Horihan | Z3: 46118 | AD3: Development is completed in previous sprint itself. Testing completed in the TST env.
A4: 3 | B4: GGO Web | C4: 46114 | D4: 46128 | E4: GGO 8.4.0 Sprint 1 | F4: Rajesh | G4: GGO-15174 | H4: Remove Deleted Package from ap_OnlineBiddingSettings featuredPackageIDs Column | I4: Completed | J4: 2 | K4: 2 | L4: 4 | M4: 46115 | N4: 46115 | O4: Done | P4: Priya | R4: Rajesh | T4: https://greatergiving.visualstudio.com/Greater%20Giving/_git/GGO/pullrequest/9431 | U4: 46115 | V4: NA | W4: Na | Y4: Mike Horihan | Z4: 46115 | AD4: Development is completed. Unit testing is done and Created a PR on 04/03/2026. Testing completed in the TST env.
A5: 4 | B5: GGO Web | C5: 46114 | D5: 46128 | E5: GGO 8.4.0 Sprint 1 | F5: Saranya | G5: GGO-15186 | H5: Snyk Findings - form-data@4.0.0 | I5: Completed | J5: 2 | K5: 2 | L5: 12 | M5: 46115 | N5: 46118 | O5: Done | P5: Priya | R5: Rajesh | T5: https://greatergiving.visualstudio.com/Greater%20Giving/_git/GGO/pullrequest/9440 | U5: 46118 | W5: Rajesh | Y5: Mike Horihan | Z5: 46119 | AD5: Started upgrading form-data package from 4.0.0 to 4.0.4 for angular project and facing some issues on 04/03/2026 Fixed issue. Testing is done and Created PR on 04/06/2026. Testing completed in the TST env.
A6: 5 | B6: GGO Web | C6: 46114 | D6: 46128 | E6: GGO 8.4.0 Sprint 1 | F6: Saranya | G6: GGO-15187 | H6: Snyk Finding - ajv@8.12.0 | I6: Completed | J6: 2 | K6: 2 | L6: 7 | M6: 46115 | N6: 46115 | O6: Done | P6: Priya | R6: Rajesh | T6: https://greatergiving.visualstudio.com/Greater%20Giving/_git/GGO/pullrequest/9436 | U6: 46115 | V6: NA | W6: NA | Y6: Mike Horihan | Z6: 46118 | AD6: Upgraded ajv package from 8.8.0 to 8.18.0 for angular project. Testing is done and Created PR on 04/03/2026. Testing completed in the TST env.
A7: 6 | B7: GGO Web | C7: 46114 | D7: 46128 | E7: GGO 8.4.0 Sprint 1 | F7: Sathiya | G7: GGO-14790 | H7: View Sales page | I7: Completed | J7: 3 | K7: 3 | L7: 38.5 | M7: 46115 | N7: 46118 | O7: Done | P7: Priya | R7: Saranya | T7: https://dev.azure.com/greatergiving/Greater%20Giving/_git/GGO/pullrequest/9433 | U7: 46118 | V7: 46122 | W7: Rajesh | Y7: Mike Horihan | Z7: 46122 | AA7: There was an issue with the text alignment that has been addressed and completed. | AD7: Need to verify in local and dev since implementation is completed on 04/03/2026 Verified in DEV environment. Published the PR on 04/06/2026. Testing completed in the TST env.
A8: 7 | B8: GGO Web | C8: 46114 | D8: 46128 | E8: GGO 8.4.0 Sprint 1 | F8: Sathiya | G8: GGO-14819 | H8: View Sales Advanced search | I8: Completed | J8: 5 | K8: 5 | L8: 29 | M8: 46118 | N8: 46120 | O8: Done | P8: Priya | R8: Saranya | T8: https://greatergiving.visualstudio.com/Greater%20Giving/_git/GGO/pullrequest/9450 | U8: 46120 | V8: 46126 | W8: Rajesh | Y8: Mike Horihan | Z8: 46126 | AA8: Detected a few problems and rectified some; the remaining issues will be addressed in the forthcoming story. | AD8: Started View sales advanced search on 04/06/2026 Fixed issues in Frozen column on 04/09/2026 PackageNumber and BidderNumber search make confusion on grid result Asked PO for the clarification on 04/10/2026 Moved package search to advanced search section on 04/14/2026 Testing completed in the TST env.
A9: 8 | B9: GGO Web | C9: 46114 | D9: 46128 | E9: GGO 8.4.0 Sprint 1 | F9: Sathiya | G9: GGO-14817 | H9: View Sales common controls | I9: Completed | J9: 3 | K9: 3 | L9: 28 | M9: 46115 | N9: 46118 | O9: Done | P9: Priya | R9: Saranya | T9: https://dev.azure.com/greatergiving/Greater%20Giving/_git/GGO/pullrequest/9433 | U9: 46118 | V9: 46122 | W9: Rajesh | Y9: Mike Horihan | Z9: 46122 | AA9: Implemented successfully | AD9: Need to verify in local and dev since implementation is completed on 04/03/2026 Verified in DEV environment. Published the PR on 04/06/2026. Testing completed in the TST env.
A10: 9 | B10: GGO Web | C10: 46114 | D10: 46128 | E10: GGO 8.4.0 Sprint 1 [STRETCH] | F10: Sathiya | G10: GGO-15201 | H10: Investigate Snyk Finding - @angular/compiler-cli@16.2.8 | I10: Completed | J10: 2 | K10: 2 | L10: 7.5 | M10: 46125 | N10: NA | O10: NA | P10: NA | Q10: NA | R10: NA | S10: NA | T10: NA | U10: NA | V10: NA | W10: NA | X10: NA | Y10: NA | Z10: NA | AA10: NA | AB10: NA | AC10: NA | AD10: Snyk fix require to update angular version from 8 to 19+ and Updated comments in Jira on 04/14/2026
A11: 10 | B11: GGO Web | C11: 46114 | D11: 46128 | E11: GGO 8.4.0 Sprint 1 [STRETCH] | F11: Saranya | G11: GGO-15145 | H11: Error on Merge with proccessedInvoice | I11: Completed | J11: 2 | K11: 2 | L11: 14 | M11: 46120 | N11: 46122 | O11: Done | P11: Priya | R11: Rajesh | T11: https://greatergiving.visualstudio.com /Greater%20Giving/_git/GGO/ pullrequest/9455 | U11: 46121 | V11: 46123 | W11: Rajesh | Y11: Mike Horihan | Z11: 46123 | AD11: Started analyzing the issue and tried to reprduce the issue in TST ENV on 04/09/2026 Fixed the issue wih replacing target SupporterId with Source SupporterId while megring two supporters on 04/10/2026 Unit Testing is done on 04/11/2026
A12: 11 | B12: GGO Web | C12: 46114 | D12: 46128 | E12: GGO 8.4.0 Sprint 1 [STRETCH] | F12: Saranya | G12: GGO-14792 | H12: View Payments Page | I12: Being Developed | J12: 3 | K12: 2 | L12: 26 | M12: 46122 | N12: 46125 | O12: Done | P12: Priya | R12: Sathiya | T12: https://greatergiving.visualstudio .com/Greater%20Giving/_git/GGO/ pullrequest/9464 | U12: 46125 | W12: Rajesh | Y12: Mike Horihan | AA12: No concerns have been noted up to this point; it will be rolled over. | AD12: Payments Grid new reskin design implementation started on 04/10/2026 Developement and testing completed. Created a PR on 04/13/2026
A13: 12 | B13: GGO Web | C13: 46114 | D13: 46128 | E13: GGO 8.4.0 Sprint 1 [STRETCH] | F13: Saranya | G13: GGO-14818 | H13: View Payments Common controls | I13: Being Developed | J13: 1 | K13: 0 | L13: 15 | M13: 46125 | N13: 46125 | O13: Done | P13: Priya | R13: Sathiya | T13: https://greatergiving.visualstudio .com/Greater%20Giving/_git/GGO/ pullrequest/9464 | U13: 46125 | W13: Rajesh | Y13: Mike Horihan | AA13: No concerns have been noted up to this point; | AD13: Implemented Payments Grid common controls and testing completed. Created a PR on 04/13/2026
A14: 13 | B14: GGO Web | C14: 46114 | D14: 46128 | E14: GGO 8.4.0 Sprint 1 [STRETCH] | F14: Rajesh | G14: GGO-15204 | H14: Fundraising Signup Issue - Could not load file or assembly 'System.ValueTuple, Version=4.0.0.0, Culture=neutral, PublicKeyToken=cc7b13ffcd2ddd51' or one of its dependencies. The system cannot find the file specified. | I14: Completed | J14: 1 | K14: 1 | L14: 7 | M14: 46127 | N14: 46127 | O14: Done | P14: Priya | R14: Saranya | T14: https://greatergiving.visualstudio.com/Greater%20Giving/_git/GGO/pullrequest/9471 | U14: 46127 | V14: NA | W14: Rajesh | Y14: Mike Horihan | Z14: 46127
A15: 14 | B15: GGO Web | C15: 46114 | D15: 46128 | E15: GGO 8.4.0 Sprint 1 [STRETCH] | F15: Rajesh | G15: GGO-15206 | H15: Add Index to OnlineBidderKey for ap_OnlineBidder table | I15: Completed | J15: 1 | K15: 1 | L15: 1 | M15: 46127 | N15: 46127 | O15: Done | P15: Priya | R15: Sathiya | T15: https://greatergiving.visualstudio.com/Greater%20Giving/_git/GGO/pullrequest/9478 | U15: 46128 | V15: NA | W15: NA | Y15: Mike Horihan | Z15: 46128 | AD15: Migration script added for creating index for ap_OnlineBidder table for this issue and Unit testing done on 04/15/2026

Sheet GGO 8.4.0 Sprint 1-Defect
A1: S.No | B1: Sprint # | C1: Story/Defect ID | D1: Parent Story | E1: Developer | F1: Issue Type | G1: Issue Description | H1: Priority | I1: Defect Source | J1: Type | K1: Status | L1: Root Cause Category | M1: Found By | N1: Comment | O1: RCA Comment
G2: NO Defects

Sheet GGO 8.3.0 Sprint 4-Status
A1: S.No | B1: Application Name | C1: Sprint Start Date | D1: Sprint End Date | E1: Sprint | F1: Developer | G1: Story ID/Defect ID | H1: Description | I1: Status | J1: Estimated(sp) | K1: Actual(sp) | L1: Actual Hours Worklog | M1: Dev Start Date | N1: Dev End Date | O1: Unit testing | P1: Peer Tested By | Q1: Peer Tested Defects, if any | R1: Peer Reviewed By | S1: Peer Code Review Comments, if any | T1: PR Number/Link | U1: PR Created Date | V1: PR Approved Date | W1: Reviewer 1 | X1: Code Review Comments, if any | Y1: Reviewer 2 | Z1: Approved Date | AA1: Code Review Comments, if any2 | AB1: Internal PO -POV Comments | AC1: Client PO -POV Comments | AD1: Tester Comments | AE1: Developer Comments
A2: 1 | B2: GGO Web | C2: 46100 | D2: 46114 | E2: GGO 8.3.0 Sprint 4 | F2: Saranya | G2: GGO-15048 | H2: API Update for Next Gen - Invoicing Email | I2: Completed | J2: 1 | K2: 1 | L2: 22.5 | M2: NA | N2: NA | O2: Done | P2: Priya | R2: Sathiya | T2: https://greatergiving.visualstudio.com/Greater%20Giving/_git/GGO/pullrequest/9387 | U2: 46099 | V2: 46101 | W2: Rajesh | Y2: Mike Horihan | Z2: 46102 | AD2: Testing completed in the TST env
A3: 2 | B3: GGO Web | C3: 46100 | D3: 46114 | E3: GGO 8.3.0 Sprint 4 | F3: Sathiya | G3: GGO-15185 | H3: OB Edit Image Upload issue | I3: Completed | J3: 1 | K3: 1 | L3: 8 | M3: NA | N3: NA | O3: Done | P3: Priya | R3: Rajesh | S3: NA | T3: https://dev.azure.com/greatergiving/Greater%20Giving/_git/GGO/pullrequest/9393 | U3: 46101 | V3: 46101 | W3: Rajesh | X3: NA | Y3: NA | Z3: NA | AA3: NA | AB3: NA | AC3: NA+ | AD3: Testing completed in the TST env | AE3: Fixed the issue and created the PR on 03/20/26
A4: 3 | B4: GGO Web | C4: 46100 | D4: 46114 | E4: GGO 8.3.0 Sprint 4 | F4: Rajesh | G4: GGO-12244 | H4: LLBGen Upgrade to the latest version | I4: Ready for Testing | J4: 5 | K4: 3 | L4: 28 | M4: 46101 | N4: 46113 | T4: https://greatergiving.visualstudio.com/Greater%20Giving/_git/GGO/pullrequest/9424 | U4: 46113 | V4: 46113 | W4: Rajesh | Y4: Mike Horihan | Z4: 46114 | AE4: Got LLBLGen 5.10.1 setup file and started to work on it on 03/30/26 Completed development, PR created and sent it to Approval on 04/01/2026
A5: 4 | B5: GGO Web | C5: 46100 | D5: 46114 | E5: GGO 8.3.0 Sprint 4 | F5: Sathiya | G5: GGO-15167 | H5: OB Settings - Donation Bar | I5: Completed | J5: 3 | K5: 3 | L5: 25.5 | M5: 46104 | N5: 46106 | O5: Done | P5: Priya | R5: Rajesh | T5: https://dev.azure.com/greatergiving/Greater%20Giving/_git/GGO/pullrequest/9402 | U5: 46105 | V5: 46106 | W5: Rajesh | Y5: Mike Horihan | Z5: 46107 | AE5: Verified in dev flag value pushed to the OB queue correctly and created PR on 03/25/26
A6: 5 | B6: GGO Web | C6: 46100 | D6: 46114 | E6: GGO 8.3.0 Sprint 4 | F6: Saranya | G6: GGO-12200 | H6: Consolidate Nuget Packages | I6: Completed | J6: 3 | K6: 3 | L6: 52.5 | M6: 46101 | N6: 46111 | O6: Done | P6: Priya | T6: https://greatergiving.visualstudio.com/Greater%20Giving/_git/GGO/pullrequest/9413 | U6: 46111 | V6: 46112 | W6: Rajesh | Y6: Mike Horihan | Z6: 46112
A7: 6 | B7: GGO Web | C7: 46100 | D7: 46114 | E7: GGO 8.3.0 Sprint 4 | F7: Rajesh | G7: GGO-13962 | H7: Update NuGet Authenticate in Azure Pipeline | I7: Completed | J7: 2 | K7: 2 | L7: 6 | M7: 46101 | N7: 46105 | O7: Done | P7: Priya | R7: Rajesh | T7: https://greatergiving.visualstudio.com/Greater%20Giving/_git/GGO/pullrequest/9400 | U7: 46105 | V7: NA | W7: NA | Y7: Mike Horihan | Z7: 46106 | AE7: Started development on 03/20/26 Completed development and created PR on 03/24/26
A8: 7 | B8: GGO Web | C8: 46100 | D8: 46114 | E8: GGO 8.3.0 Sprint 4 | F8: Sathiya | G8: GGO-12282 | H8: Replace DLL direct references with NuGet packages | I8: Completed | J8: 2 | K8: 2 | L8: 15.5 | M8: 46106 | N8: 46106 | O8: Done | P8: Priya | R8: Rajesh | T8: https://greatergiving.visualstudio.com/Greater%20Giving/_git/GGO/pullrequest/9412 | U8: 46111 | V8: 46111 | W8: Rajesh | Y8: Mike Horihan | Z8: 46112 | AE8: [26-Mar-26] Except Nevron.dll we can't remove other dll's for above reason. all are third party dll's can't find in NuGet
A9: 8 | B9: GGO Web | C9: 46100 | D9: 46114 | E9: GGO 8.3.0 Sprint 4 | F9: Priya-QAa | G9: GGO-15182 | H9: 24 Mar GGO 8.3.0 CRT Release & Regression testing | I9: Completed | J9: 3 | K9: 3 | L9: 36 | M9: NA | N9: NA | O9: NA | P9: NA | Q9: NA | R9: NA | S9: NA | T9: NA | U9: NA | V9: NA | W9: NA | X9: NA | Y9: NA | Z9: NA | AA9: NA | AB9: NA | AD9: Testing completed in the CRT env
A10: 9 | B10: GGO Web | C10: 46100 | D10: 46114 | E10: GGO 8.3.0 Sprint 4 [STRETCH] | F10: Saranya | G10: GGO-15173 | H10: API Update for Card Entry Permissions in Go Time | I10: Completed | J10: 2 | K10: 2 | L10: 8 | M10: 46112 | N10: 46112 | O10: Done | P10: Priya | R10: Rajesh | T10: https://greatergiving.visualstudio.com/Greater%20Giving/_git/GGO/pullrequest/9422 | U10: 46112 | V10: 46112 | W10: Rajesh | Y10: Mike Horihan | Z10: 46113 | AE10: Analyzing existing GetCards API and added additional property(EditCreditCards) for NextGen and Testing completed in Local and Dev Env on 03/31/2026
A11: 10 | B11: GGO Web | C11: 46100 | D11: 46114 | E11: GGO 8.3.0 Sprint 4 [STRETCH] | F11: Saranya | G11: GGO-15169 | H11: API update to provide card expiration date to next gen | I11: Being Developed | J11: 2 | K11: 1 | L11: 8 | M11: 46113 | N11: 46113 | T11: https://greatergiving.visualstudio.com/Greater%20Giving/_git/GGO/pullrequest/9426 | U11: 46114 | W11: Rajesh | Y11: Mike Horihan | AE11: Analyzing existing GetCards API and added additional property(CardExpirationDate) for NextGen and Testing completed in Local and Dev Env on 04/01/2026

Sheet GGO 8.3.0 Sprint 4-Defect
A1: S.No | B1: Sprint # | C1: Story/Defect ID | D1: Parent Story | E1: Developer | F1: Issue Type | G1: Issue Description | H1: Priority | I1: Defect Source | J1: Type | K1: Status | L1: Root Cause Category | M1: Found By | N1: Comment | O1: RCA Comment
G2: NO Defects

Sheet GGO 8.3.0 Sprint 3-Status
A1: S.No | B1: Application Name | C1: Sprint Start Date | D1: Sprint End Date | E1: Sprint | F1: Developer | G1: Story ID/Defect ID | H1: Description | I1: Status | J1: Estimated(sp) | K1: Actual(sp) | L1: Actual Hours Worklog | M1: Dev Start Date | N1: Dev End Date | O1: Unit testing | P1: Peer Tested By | Q1: Peer Tested Defects, if any | R1: Peer Reviewed By | S1: Peer Code Review Comments, if any | T1: PR Number/Link | U1: PR Created Date | V1: PR Approved Date | W1: Reviewer 1 | X1: Code Review Comments, if any | Y1: Reviewer 2 | Z1: Approved Date | AA1: Code Review Comments, if any2 | AB1: Internal PO -POV Comments | AC1: Client PO -POV Comments | AD1: Tester Comments | AE1: Developer Comments
A2: 1 | B2: GGO Web | C2: 46086 | D2: 46100 | E2: GGO 8.3.0 Sprint 3 | F2: Rajesh | G2: GGO-15147 | H2: RSVP - Special Characters During Import for Apostrophe and Ampersand | I2: Completed | J2: 1 | K2: 1 | L2: 11 | M2: 46090 | N2: 46091 | O2: Done | P2: Priya | R2: Saranya | T2: https://greatergiving.visualstudio.com/Greater%20Giving/_git/GGO/pullrequest/9360 | U2: 46092 | V2: NA | W2: NA | Y2: Mike Horihan | Z2: 46092 | AE2: Fixed RSVP Special charcters issue during import on 03/09/2026 Tested and Created a PR on 03/10/2026
A3: 2 | B3: GGO Web | C3: 46086 | D3: 46100 | E3: GGO 8.3.0 Sprint 3 | F3: Rajesh | G3: GGO-15165 | H3: Unicode Characters in Item Descriptions | I3: Completed | J3: 2 | K3: 2 | L3: 6 | M3: 46087 | N3: 46087 | O3: Done | P3: Priya | R3: Saranya | T3: https://greatergiving.visualstudio.com/Greater%20Giving/_git/GGO/pullrequest/9348 | U3: 46087 | V3: NA | W3: NA | Y3: Mike Horihan | Z3: 46088 | AE3: Reproduced issue in TST environment, development completed by handling the Unicode char for the item and package description. 100% development completed and shared PR to client on 03/06/2026
A4: 3 | B4: GGO Web | C4: 46086 | D4: 46100 | E4: GGO 8.3.0 Sprint 3 | F4: Rajesh | G4: GGO-15047 | H4: API Update for Next Gen - Invoicing Available | I4: Completed | J4: 2 | K4: 2 | L4: 11 | M4: 46087 | N4: 46087 | O4: Done | P4: Priya | R4: Saranya | T4: https://greatergiving.visualstudio.com/Greater%20Giving/_git/GGO/pullrequest/9351 | U4: 46090 | V4: NA | W4: NA | Y4: Mike Horihan | Z4: 46090 | AE4: Created new GoTime API to check the invoicing status and return response to Mobile Team. 100% development completed and shared PR to client on 03/06/2026
A5: 4 | B5: GGO Web | C5: 46086 | D5: 46100 | E5: GGO 8.3.0 Sprint 3 | F5: Sathiya | G5: GGO-14809 | H5: Manage Project - RSVP Dashboard - Admission, Admission by Package and Meal Types grids | I5: Completed | J5: 3 | K5: 3 | L5: 25 | M5: 46087 | N5: 46091 | O5: Done | P5: Priya | R5: Rajesh | T5: https://greatergiving.visualstudio.com/Greater%20Giving/_git/GGO/pullrequest/9359 | U5: 46091 | V5: 46092 | W5: Rajesh | Y5: Mike Horihan | Z5: 46092 | AE5: Development started on 03/10/2026 Did local and dev testing and created PR on 03/10/2026
A6: 5 | B6: GGO Web | C6: 46086 | D6: 46100 | E6: GGO 8.3.0 Sprint 3 | F6: Sathiya | G6: GGO-14812 | H6: Manage Project - RSVP Dashboard | I6: Completed | J6: 5 | K6: 5 | L6: 47.25 | M6: 46091 | N6: 46097 | O6: Done | P6: Priya | R6: Saranya/Rajesh | T6: https://greatergiving.visualstudio.com/Greater%20Giving/_git/GGO/pullrequest/9380 | U6: 46097 | V6: 46098 | W6: Rajesh | Y6: Mike Horihan | Z6: 46098 | AE6: Implemented rsvp grid on 03/13/2026 Develoment completed fixing minor UI issues on 03/16/2026
A7: 6 | B7: GGO Web | C7: 46086 | D7: 46100 | E7: GGO 8.3.0 Sprint 3 | F7: Rajesh | G7: GGO-15162 | H7: Scroll bar issue in PRD - View Packages | I7: Completed | J7: 2 | K7: 2 | L7: 6 | M7: 46093 | N7: 46094 | O7: Done | P7: Priya | R7: Sathiya | T7: https://greatergiving.visualstudio.com/Greater%20Giving/_git/GGO/pullrequest/9371 | U7: 46094 | V7: NA | W7: Rajesh | Y7: Mike Horihan | Z7: 46094 | AE7: Reproduced issue in TST environment with help of customer service team took some time to fix this issue. 100 % development completed and shared PR to client on 03/13/2026
A8: 7 | B8: GGO Web | C8: 46086 | D8: 46100 | E8: GGO 8.3.0 Sprint 3 | F8: Saranya | G8: GGO-15038 | H8: Data not importing in from OP RSVP | I8: Completed | J8: 2 | K8: 2 | L8: 23 | M8: 46087 | N8: 46093 | O8: Done | P8: Priya | R8: Rajesh | T8: https://greatergiving.visualstudio.com/Greater%20Giving/_git/GGO/pullrequest/9368 | U8: 46093 | V8: 46093 | W8: Rajesh | Y8: Mike Horihan | Z8: 46094 | AE8: Trying to reproduce this issue. But unable to reproduce in Local, Dev, TST and CRT on 03/06//2026
A9: 8 | B9: GGO Web | C9: 46086 | D9: 46100 | E9: GGO 8.3.0 Sprint 3 | F9: Saranya | G9: GGO-15160 | H9: Streamline Support Redirect from Equipment Express | I9: Completed | J9: 3 | K9: 3 | L9: 23 | M9: 46091 | N9: 46093 | O9: Done | P9: Priya | R9: Rajesh | T9: https://greatergiving.visualstudio.com/Greater%20Giving/_git/GGO/pullrequest/9358 | U9: 46091 | V9: 46093 | W9: Rajesh | Y9: Mike Horihan | Z9: 46093 | AE9: Development 90% Completed. Created Banner and Popup to redirect Streamline support from Equipment Express. Testing is inprogress on 03/10/2026
A10: 9 | B10: GGO Web | C10: 46086 | D10: 46100 | E10: GGO 8.3.0 Sprint 3 | F10: Sathiya | G10: GGO-14810 | H10: Manage Project - RSVP Dashboard - Search field and Send Letters & Emails button | I10: Completed | J10: 3 | K10: 3 | L10: 16.5 | M10: 46091 | N10: 46097 | O10: Done | P10: Priya | R10: Saranya/Rajesh | T10: https://greatergiving.visualstudio.com/Greater%20Giving/_git/GGO/pullrequest/9380 | U10: 46097 | V10: 46098 | W10: Rajesh | Y10: Mike Horihan | Z10: 46098 | AE10: Implemented search functionality on 03/13/2026 Develoment completed fixing minor UI issues on 03/16/2026
A11: 10 | B11: GGO Web | C11: 46086 | D11: 46100 | E11: GGO 8.3.0 Sprint 3 [STRETCH] | F11: Rajesh | G11: GGO-15178 | H11: Un-hide PKG-06en | I11: Completed | J11: 1 | K11: 1 | L11: 3 | M11: 46099 | N11: 46099 | O11: Done | P11: Priya | R11: Sathiya | T11: https://greatergiving.visualstudio.com/Greater%20Giving/_git/GGO/pullrequest/9384 | U11: 46099 | V11: NA | W11: NA | Y11: Mike Horihan | Z11: 46099 | AE11: Fixed unhide PGK report and testing completed and Created PR on 03/18/2026
A12: 11 | B12: GGO Web | C12: 46086 | D12: 46100 | E12: GGO 8.3.0 Sprint 3 [STRETCH] | F12: Saranya/Sathiya | G12: GGO-15048 | H12: API Update for Next Gen - Invoicing Email | I12: Being Developed | J12: 3 | K12: 2 | L12: 47.5 | M12: 46097 | N12: 46100 | O12: Done | AE12: Analyzing existig Email functionality to create new API for NextGen on 03/16/2026 Created a new API to Send Email Invoice for nextgen on 03/18/2026 Testing in Local and Dev Env on 03/19/2026

Sheet GGO 8.3.0 Sprint 3-Defect
A1: S.No | B1: Sprint # | C1: Story/Defect ID | D1: Parent Story | E1: Developer | F1: Issue Type | G1: Issue Description | H1: Priority | I1: Defect Source | J1: Type | K1: Status | L1: Root Cause Category | M1: Found By | N1: Comment | O1: RCA Comment
G2: NO Defects

Sheet GGO 8.3.0 Sprint 2-Status
A1: S.No | B1: Application Name | C1: Sprint Start Date | D1: Sprint End Date | E1: Sprint | F1: Developer | G1: Story ID/Defect ID | H1: Description | I1: Status | J1: Estimated(sp) | K1: Actual(sp) | L1: Actual Hours Worklog | M1: Dev Start Date | N1: Dev End Date | O1: Unit testing | P1: Peer Tested By | Q1: Peer Tested Defects, if any | R1: Peer Reviewed By | S1: Peer Code Review Comments, if any | T1: PR Number/Link | U1: PR Created Date | V1: PR Approved Date | W1: Reviewer 1 | X1: Code Review Comments, if any | Y1: Reviewer 2 | Z1: Approved Date | AA1: Code Review Comments, if any2 | AB1: Internal PO -POV Comments | AC1: Client PO -POV Comments | AD1: Tester Comments | AE1: Developer Comments
A2: 1 | B2: GGO Web | C2: 46072 | D2: 46086 | E2: GGO 8.3.0 Sprint 2 | F2: Rajesh/Saranya | G2: GGO-14628 | H2: Print Invoice/Receipts page - Timeout when Omit Sales and payment option selected with both Before and After date options | I2: Completed | J2: 2 | K2: 2 | L2: 41 | M2: 46059 | N2: 46071 | O2: Done | P2: Priya | Q2: No Defects | R2: Rajesh | S2: NA | T2: https://greatergiving.visualstudio.com/Greater%20Giving/_git/GGO/pullrequest/9303 | U2: 46072 | V2: 46073 | W2: Rajesh | Y2: Mike Horihan | Z2: 46073 | AA2: Is this change related to the Timeout Issue? | AB2: NA | AC2: NA | AD2: Testing Completed in the TST env | AE2: 23/2/2026 - Testing is inprogress in TST. Found one issue 24/2/2026 - Fixed the issue and deployed in DEV env and Testing is inprogress
A3: 2 | B3: GGO Web | C3: 46072 | D3: 46086 | E3: GGO 8.3.0 Sprint 2 | F3: Sathiya/Praveen | G3: GGO-14874 | H3: Reports and Exports - View Report Page | I3: Completed | J3: 3 | K3: 3 | L3: 31.5 | M3: 46073 | N3: 46076 | O3: Done | P3: Priya | Q3: GGO-15163 | R3: Rajesh | S3: NA | T3: https://dev.azure.com/greatergiving/Greater%20Giving/_git/GGO/pullrequest/9312 | U3: 46076 | V3: 46077 | W3: Rajesh | Y3: Mike Horihan | Z3: 46078 | AB3: NA | AC3: NA | AD3: Testing Completed in the TST env | AE3: 20/2/2026 - Sorting order changed on search 23/2/2026 - Loaded all the reports section and created PR
A4: 3 | B4: GGO Web | C4: 46072 | D4: 46086 | E4: GGO 8.3.0 Sprint 2 | F4: Saranya | G4: GGO-15076 | H4: API Update for Next Gen - Checkout | I4: Completed | J4: 5 | K4: 5 | L4: 38 | M4: 46073 | N4: 46079 | O4: Done | P4: Priya | R4: Rajesh | S4: NA | T4: https://dev.azure.com/greatergiving/Greater%20Giving/_git/GGO/pullrequest/9334 | U4: 46081 | V4: 46081 | W4: Rajesh | Y4: Mike Horihan | Z4: 46081 | AB4: NA | AC4: NA | AD4: Raised bug 9:00 PM 3/3/2026 | AE4: 20/2/2026 - Analysing checkout recorded against the admission- similar to check-in 23/2/2026 - Analysing the existing functionality of checkin and checkout API's 24/2/2026 - Implemented code 20% 25/2/2026 - Added new API to update attendee's chekout info and fetch the same info in GetCheckinDetails API 26/2/2026 - Dev testing is completed and Created a PR
A5: 4 | B5: GGO Web | C5: 46072 | D5: 46086 | E5: GGO 8.3.0 Sprint 2 | F5: Rajesh | G5: GGO-15105 | H5: Update to GGO GPPostedInvoiceItems Data | I5: Completed | J5: 5 | K5: 5 | L5: 19 | T5: https://dev.azure.com/greatergiving/Greater%20Giving/_git/GGO/pullrequest/9325 | U5: 46080 | V5: 46080 | W5: Rajesh | Y5: Mike Horihan | Z5: 46081 | AD5: Testing Completed in the TST env
A6: 5 | B6: GGO Web | C6: 46072 | D6: 46086 | E6: GGO 8.3.0 Sprint 2 | F6: Saranya | G6: PAPI-893 | H6: Investigation into PAPI Client & Settlement Data | I6: Completed | J6: 2 | K6: 2 | L6: 22 | M6: 46079 | O6: NA | P6: NA | Q6: NA | R6: NA | S6: NA | T6: NA | U6: NA | V6: NA | W6: NA | X6: NA | Y6: NA | Z6: NA | AA6: NA | AB6: NA | AC6: NA | AD6: NA | AE6: 26/2/2026 - Started analysing PAPIClients from OPSStaging Database 27/2/2026 - Documentaion preparation
A7: 6 | B7: GGO Web | C7: 46072 | D7: 46086 | E7: GGO 8.3.0 Sprint 2 | F7: Sathiya | G7: GGO-11918 | H7: Sponsor imgs not updating for non ob projects on displays | I7: Completed | J7: 3 | K7: 3 | L7: 14.5 | M7: 46078 | N7: 46078 | O7: Done | P7: Priya | T7: https://dev.azure.com/greatergiving/Greater%20Giving/_git/GGO/pullrequest/9320 | U7: 46078 | V7: 46079 | W7: Rajesh | Y7: Mike Horihan | Z7: 46079 | AB7: NA | AC7: NA | AD7: Testing Completed in the TST env | AE7: 25/2/2026 did SP changes verified in dev environment
A8: 7 | B8: GGO Web | C8: 46072 | D8: 46086 | E8: GGO 8.3.0 Sprint 2 | F8: Sathiya/Rajesh | G8: GGO-15152 | H8: Telerik Shared Library Issue | I8: Completed | J8: 1 | K8: 1 | L8: 6.5 | M8: 46079 | N8: 46079 | O8: Done | T8: https://greatergiving.visualstudio.com/Greater%20Giving/_git/GGO/pullrequest/9326 | U8: 46080 | V8: 46080 | W8: Rajesh | Y8: Mike Horihan | Z8: 46080 | AB8: NA | AC8: NA | AD8: Testing Completed in the TST env | AE8: 26/02/2026 Fixed mentioned CSP issue by adding data: in the iframe src now facing new CORS issue on Jscrambler 27/02/2026 Created PR
A9: 8 | B9: GGO Web | C9: 46072 | D9: 46086 | E9: GGO 8.3.0 Sprint 2 | F9: Rajesh | G9: GGO-15149 | H9: Update SkiSharp to version 2.88.6 in GGOImageTransferApp | I9: Completed | J9: 1 | K9: 1 | O9: Done | T9: https://greatergiving.visualstudio.com/Greater%20Giving/_git/GGO/pullrequest/9314 | U9: 46076 | V9: 46080 | W9: Rajesh | Y9: Mike Horihan | Z9: 46080 | AB9: NA | AC9: NA | AD9: Testing Completed in the TST env
A10: 9 | B10: GGO Web | C10: 46072 | D10: 46086 | E10: GGO 8.3.0 Sprint 2 [STRETCH] | F10: Sathiya | G10: GGO-14561 | H10: Bidder was assigned reused URL that led to another org | I10: Completed | J10: 5 | K10: 5 | L10: 55 | M10: 46080 | N10: 46086 | O10: Done | P10: NA | Q10: NA | R10: NA | T10: https://greatergiving.visualstudio.com/Greater%20Giving/_git/GGO/pullrequest/9339 | U10: 46084 | V10: 46085 | W10: Rajesh | Y10: Mike Horihan | Z10: 46085 | AB10: NA | AC10: NA | AD10: Testing Completed in the Dev env. 9:00 PM 3/3/2026 | AE10: 27/02/2026 - created the new function and calling old function in it 02/03/2026 - WITH EXECUTE AS CALLER and UNIQUE KEY constraint is necessary to add 03/03/2026 - Provided the script to checking the duplicates and updated verified locally 04/03/2026 - Rajesh maodified the script and updated OnlineBidding Script 05/03/2026 - Change log created and updated script verified in local
A11: 10 | B11: GGO Web | C11: 46072 | D11: 46086 | E11: GGO 8.3.0 Sprint 2 [STRETCH] | F11: Saranya | G11: GGO-11722 | H11: Discount code not able to update when set to fixed type | I11: Completed | J11: 2 | K11: 2 | L11: 8 | M11: 46084 | N11: 46085 | O11: Done | P11: Priya | R11: Rajesh | T11: https://greatergiving.visualstudio.com/Greater%20Giving/_git/GGO/pullrequest/9343 | U11: 46085 | V11: 46085 | W11: Rajesh | Y11: Mike Horihan | Z11: 46085 | AB11: NA | AC11: NA | AD11: Testing Completed in the TST env | AE11: 3/3/2026 - Started analyzing about Dicount Codes 4/3/2026 - Fixed this issue and Unit testing is done. Created PR

Sheet GGO 8.3.0 Sprint 2-Defect
A1: S.No | B1: Sprint # | C1: Story/Defect ID | D1: Parent Story | E1: Developer | F1: Issue Type | G1: Issue Description | H1: Priority | I1: Defect Source | J1: Type | K1: Status | L1: Root Cause Category | M1: Found By | N1: Comment | O1: RCA Comment
B2: GGO 8.3.0 Sprint 2 | C2: GGO-15163 | D2: GGO-14874 | E2: Sathiya | F2: Bounceback/Sub-Defect | G2: View Report- Text Does Not Highlight in Blue After Generating Report | H2: Minor | I2: Manual | J2: Internal | K2: Closed | L2: Design | M2: Priya | N2: Minor UI issues
B3: GGO 8.3.0 Sprint 2 | C3: GGO-15166 | D3: GGO-15076 | E3: Saranya | F3: Bounceback/Sub-Defect | G3: isCheckedOut flag is required for household members in API response | H3: Significant | I3: Manual | J3: Internal | K3: Closed | L3: Design | M3: Priya | N3: Requested by the Mobile team to add a flag

Sheet GGO 8.3.0 Sprint 1-Status
A1: S.No | B1: Application Name | C1: Sprint Start Date | D1: Sprint End Date | E1: Sprint | F1: Developer | G1: Story ID/Defect ID | H1: Description | I1: Status | J1: Estimated(sp) | K1: Actual(sp) | L1: Actual Hours Worklog | M1: Dev Start Date | N1: Dev End Date | O1: Unit testing | P1: Peer Tested By | Q1: Peer Tested Defects, if any | R1: Peer Reviewed By | S1: Peer Code Review Comments, if any | T1: PR Number/Link | U1: PR Created Date | V1: PR Approved Date | W1: Reviewer 1 | X1: Code Review Comments, if any | Y1: Reviewer 2 | Z1: Approved Date | AA1: Code Review Comments, if any2 | AB1: Internal PO -POV Comments | AC1: Client PO -POV Comments | AD1: Tester Comments | AE1: Developer Comments
A2: 1 | B2: GGO Web | C2: 46058 | D2: 46072 | E2: GGO 8.3.0 Sprint 1 | F2: Sathiya | G2: GGO-15103 | H2: Optout.aspx.cs Exception | I2: Completed | J2: 1 | K2: 1 | L2: 6.5 | M2: 46058 | N2: 46058 | O2: Done | P2: Priya | Q2: No Defects | T2: https://dev.azure.com/greatergiving/Greater%20Giving/_git/GGO/pullrequest/9260 | U2: 46058 | AD2: Testing completed in the TST env | AE2: 2/5/2026 - Fixed decryption issue and verified in DEV. Created PR
A3: 2 | B3: GGO Web | C3: 46058 | D3: 46072 | E3: GGO 8.3.0 Sprint 1 | F3: Priya-QA | G3: GGO-15140 | H3: 27 Jan GGO 8.2.0 CRT Release & Regression Testing | I3: Completed | J3: 1 | K3: 1 | L3: 16 | M3: NA | N3: NA | O3: Done | P3: Priya | Q3: No Defects | R3: NA | S3: NA | T3: NA | U3: NA | V3: NA | W3: NA | X3: NA | Y3: NA | Z3: NA | AA3: NA | AB3: NA | AC3: NA | AD3: Testing completed in CRT env. | AE3: CRT regression testing has been completed by the offshore QA team. The onsite QA requested that this story be put on hold, as WAF testing is still pending on his side. Therefore, the story has been carried forward
A4: 3 | B4: GGO Web | C4: 46058 | D4: 46072 | E4: GGO 8.3.0 Sprint 1 | F4: Saranya | G4: GGO-13847 | H4: Disable/Hide the Reports | I4: Completed | J4: 5 | K4: 5 | L4: 10 | M4: 46059 | N4: 46059 | O4: Done | P4: Priya | Q4: The migration script missed one report name in the delete statement. | R4: Rajesh | S4: NA | T4: https://greatergiving.visualstudio.com/Greater%20Giving/_git/GGO/pullrequest/9263 | U4: 46060 | V4: 46060 | W4: Rajesh | X4: NA | Y4: Mike Horihan | Z4: 46060 | AA4: NA | AB4: NA | AC4: NA | AD4: Testing completed in the TST env | AE4: 2/6/2026 - Created migration script to delete the reports which was mentioned in the story. Unit testing is done and Created PR
A5: 4 | B5: GGO Web | C5: 46058 | D5: 46072 | E5: GGO 8.3.0 Sprint 1 | F5: Sathiya/Praveen | G5: GGO-14865 | H5: Reports and Exports page - Left nav and Header section | I5: Completed | J5: 3 | K5: 3 | L5: 18.5 | M5: 46059 | N5: 46063 | O5: Done | P5: Priya | Q5: No Defects | R5: Rajesh | S5: NA | T5: https://greatergiving.visualstudio.com/Greater%20Giving/_git/GGO/pullrequest/9269 | U5: 46063 | V5: 46065 | W5: Rajesh | X5: NA | Y5: Mike Horihan | Z5: 46065 | AA5: NA | AB5: NA | AC5: NA | AD5: Testing completed in the TST env | AE5: 06/02/2026 - Applied Praveen changes to to current branch Implemented new card design for the reports 10/02/2026 - Unit testing , PO verfication and fixed UI Issues 11/02/2026 - Deployed in dev and fixed minor UI issues
A6: 5 | B6: GGO Web | C6: 46058 | D6: 46072 | E6: GGO 8.3.0 Sprint 1 | F6: Sathiya/Praveen | G6: GGO-14866 | H6: Reports and Exports - Search bar | I6: Completed | J6: 3 | K6: 3 | L6: 9.5 | M6: 46059 | N6: 46063 | O6: Done | P6: Priya | Q6: No Defects | R6: Rajesh | S6: NA | T6: https://greatergiving.visualstudio.com/Greater%20Giving/_git/GGO/pullrequest/9269 | U6: 46063 | V6: 46065 | W6: Rajesh | X6: NA | Y6: Mike Horihan | Z6: 46065 | AA6: NA | AB6: NA | AC6: NA | AD6: Testing completed in the TST env | AE6: 09/02/2026 - Implemented search functionality on the reports 10/02/2026 - Unit testing , PO verfication and fixed UI Issues 11/02/2026 - Deployed in dev and fixed minor UI issues
A7: 6 | B7: GGO Web | C7: 46058 | D7: 46072 | E7: GGO 8.3.0 Sprint 1 | F7: Sathiya/Praveen | G7: GGO-14867 | H7: Reports and Exports - Favorite Reports section | I7: Completed | J7: 5 | K7: 5 | L7: 13.5 | M7: 46059 | N7: 46063 | O7: Done | P7: Priya | Q7: No Defects | R7: Rajesh | S7: NA | T7: https://greatergiving.visualstudio.com/Greater%20Giving/_git/GGO/pullrequest/9269 | U7: 46063 | V7: 46065 | W7: Rajesh | X7: NA | Y7: Mike Horihan | Z7: 46065 | AA7: NA | AB7: NA | AC7: NA | AD7: Testing completed in the TST env | AE7: 10/02/2026 - Unit testing , PO verfication and fixed UI Issues 11/02/2026 - Deployed in dev and fixed minor UI issues
A8: 7 | B8: GGO Web | C8: 46058 | D8: 46072 | E8: GGO 8.3.0 Sprint 1 | F8: Rajesh/Saranya | G8: GGO-14628 | H8: Print Invoice/Receipts page - Timeout when Omit Sales and payment option selected with both Before and After date options | I8: Peer review | J8: 5 | K8: 3 | L8: 94.5 | M8: 46059 | N8: 46071 | O8: Done | P8: Priya | Q8: No Defects | R8: Rajesh | S8: NA | T8: https://greatergiving.visualstudio.com/Greater%20Giving/_git/GGO/pullrequest/9303 | U8: 46072 | V8: 46073 | W8: Rajesh | AB8: NA | AC8: NA | AD8: Testing completed in the Dev env | AE8: Development has been completed. Since we planned to provide a permanent fix, instead of calculating the mostRecentDate at the time of generating invoices or receipts, we decided to pre-calculate and update the relevant tables when associating sales with the corresponding payments. Initially, this logic was implemented in code, but later we moved it to triggers. As this is a major change, the testing effort required is significant, so the work has been carried forward.
A9: 8 | B9: GGO Web | C9: 46058 | D9: 46072 | E9: GGO 8.3.0 Sprint 1 [STRETCH] | F9: Sathiya/Praveen | G9: GGO-14868 | H9: Reports and Exports - Recommended Reports section | I9: Completed | J9: 1 | K9: 1 | L9: 11.5 | M9: 46065 | N9: 46065 | O9: Done | P9: Priya | Q9: No Defects | R9: Rajesh | S9: NA | T9: https://dev.azure.com/greatergiving/Greater%20Giving/_git/GGO/pullrequest/9281 | U9: 46065 | V9: 46066 | W9: Rajesh | X9: NA | Y9: Mike Horihan | Z9: 46066 | AB9: NA | AC9: NA | AD9: Testing completed in the TST env | AE9: [02/12/2026]-did design changes for recommended reportes and created PR
A10: 9 | B10: GGO Web | C10: 46058 | D10: 46072 | E10: GGO 8.3.0 Sprint 1 [STRETCH] | F10: Sathiya/Praveen | G10: GGO-14869 | H10: Reports and Exports - All Reports Section | I10: Completed | J10: 3 | K10: 3 | M10: 46065 | N10: 46066 | O10: Done | P10: Priya | Q10: No Defects | R10: Rajesh | S10: NA | T10: https://dev.azure.com/greatergiving/Greater%20Giving/_git/GGO/pullrequest/9284 | U10: 46066 | V10: 46067 | W10: Rajesh | X10: NA | Y10: Mike Horihan | Z10: 46067 | AB10: NA | AC10: NA | AD10: Testing completed in the TST env | AE10: 02/13/2026]-did design changes for all reports and exports and created PR
A11: 10 | B11: GGO Web | C11: 46058 | D11: 46072 | E11: GGO 8.3.0 Sprint 1 [STRETCH] | F11: Sathiya/Praveen | G11: GGO-14872 | H11: Reports and Exports - Standard and Advanced Settings Page | I11: Completed | J11: 3 | K11: 3 | L11: 18 | M11: 46069 | N11: 46071 | O11: Done | P11: Priya | Q11: No Defects | R11: Rajesh | S11: NA | T11: https://greatergiving.visualstudio.com/Greater%20Giving/_git/GGO/pullrequest/9302 | U11: 46071 | V11: 46071 | W11: Rajesh | X11: Na | Y11: Mike Horihan | Z11: 46071 | AB11: NA | AC11: NA | AD11: Testing completed in the TST env | AE11: 02/13/2026]-did design changes for all reports and exports and created PR

Sheet GGO 8.3.0 Sprint 1-Defect
A1: S.No | B1: Sprint # | C1: Story/Defect ID | D1: Parent Story | E1: Developer | F1: Issue Type | G1: Issue Description | H1: Priority | I1: Defect Source | J1: Type | K1: Status | L1: Root Cause Category | M1: Found By | N1: Comment | O1: RCA Comment
G2: NO Defects

Sheet GGO 8.2.0 Sprint 4-Status
A1: S.No | B1: Application Name | C1: Sprint Start Date | D1: Sprint End Date | E1: Sprint | F1: Developer | G1: Story ID/Defect ID | H1: Description | I1: Status | J1: Estimated(sp) | K1: Actual(sp) | L1: Actual Hours Worklog | M1: Dev Start Date | N1: Dev End Date | O1: Unit testing | P1: Peer Tested By | Q1: Peer Tested Defects, if any | R1: Peer Reviewed By | S1: Peer Code Review Comments, if any | T1: PR Number/Link | U1: PR Created Date | V1: PR Approved Date | W1: Reviewer 1 | X1: Code Review Comments, if any | Y1: Reviewer 2 | Z1: Approved Date | AA1: Code Review Comments, if any2 | AB1: Internal PO -POV Comments | AC1: Client PO -POV Comments | AD1: Tester Comments | AE1: Developer Comments
A2: 1 | B2: GGO Web | C2: 46044 | D2: 46058 | E2: GGO 8.2.0 Sprint 4 | F2: Sathiya/Saranya/Rajesh | G2: GGO-15135 | H2: Jscrambler for GGO & GGAM & GO Time | I2: Completed | J2: 3 | K2: 3 | L2: 16 | M2: 46044 | N2: 46044 | O2: Done | P2: Priya | Q2: No Defects | T2: https://greatergiving.visualstudio.com/Greater%20Giving/_git/GGO/pullrequest/9201 | U2: 46043 | V2: 46044 | W2: Rajesh | Y2: Mike Horihan | Z2: 46045 | AD2: Dev Testing Completed. Testing completed in TST env. | AE2: Development is completed in last sprint itself
A3: 2 | B3: GGO Web | C3: 46044 | D3: 46058 | E3: GGO 8.2.0 Sprint 4 | F3: Rajesh | G3: GGO-15138 | H3: Online Bidding Settings Embed Video Settings | I3: Completed | J3: 1 | K3: 1 | L3: 2 | M3: 46045 | N3: 46045 | O3: Done | P3: Priya | Q3: No Defects | T3: https://greatergiving.visualstudio.com/Greater%20Giving/_git/GGO/pullrequest/9209 | U3: 46045 | V3: 46045 | Y3: Mike Horihan | Z3: 46045 | AD3: Dev Testing Completed. Testing completed in TST env. | AE3: 01/23/2026 - Development 100% completed. Dev testing completed and Created PR
A4: 3 | B4: GGO Web | C4: 46044 | D4: 46058 | E4: GGO 8.2.0 Sprint 4 | F4: Sathiya | G4: GGO-15137 | H4: Implement ReCaptcha in Supporter | I4: Completed | J4: 2 | K4: 2 | L4: 35.5 | M4: 46045 | N4: 46050 | O4: Done | P4: Priya | Q4: No Defects | T4: https://dev.azure.com/greatergiving/Greater%20Giving/_git/GGO/pullrequest/9211 | U4: 46050 | V4: 46050 | W4: Rajesh | Y4: Mike Horihan | Z4: 46050 | AD4: Dev Testing Completed. Testing completed in TST env. | AE4: 01/27/2026 - Implemented Recaptcha for Fundraising Activity page 01/27/2026 - Development 50% completed 01/28/2026 - Fixed recaptcha error message clearing issue Removed unused reference of CSP from the controllers Local Unit testing and Created PR
A5: 4 | B5: GGO Web | C5: 46044 | D5: 46058 | E5: GGO 8.2.0 Sprint 4 | F5: Saranya/Rajesh | G5: GGO-15108 | H5: Equipment Express Update | I5: Completed | J5: 1 | K5: 1 | L5: 15 | M5: 46045 | N5: 46045 | O5: Done | P5: Priya | Q5: No Defects | R5: Rajesh | S5: Method repeated multiple times. Move to common service and call it. | T5: https://dev.azure.com/greatergiving/Greater%20Giving/_git/GGO/pullrequest/9213 | U5: 46045 | V5: 46046 | W5: Rajesh | Y5: Mccarty Joseph | Z5: 46046 | AD5: Dev Testing Completed. Testing completed in TST env. | AE5: 01/23/2026 - Remove the bullet point about Android Compatibility when the bluetooth option is enabled for a client. Development 100% completed Dev testing completed and Created PR
A6: 5 | B6: GGO Web | C6: 46044 | D6: 46058 | E6: GGO 8.2.0 Sprint 4 | F6: Rajesh | G6: GGO-13585 | H6: Update to fix LLBLgen generated code | I6: Completed | J6: 1 | K6: 1 | L6: 12 | M6: 46045 | N6: 46051 | O6: Done | P6: Priya | Q6: No Defects | T6: https://greatergiving.visualstudio.com/Greater%20Giving/_git/GGO/pullrequest/9229 | U6: 46050 | V6: 46051 | W6: Rajesh | Y6: Mike Horihan | Z6: 46051 | AD6: Dev Testing Completed. Testing completed in TST env. | AE6: 01/23/2026 - Some LLBLGen Work is completed by Rajesh 01/28/2026 - Fixed code issue. Dev testing is completed
A7: 6 | B7: GGO Web | C7: 46044 | D7: 46058 | E7: GGO 8.2.0 Sprint 4 | F7: Saranya/Rajesh | G7: GGO-15109 | H7: Upgrade the Telerik to its latest version | I7: Completed | J7: 5 | K7: 5 | L7: 17 | M7: 46051 | O7: Done | P7: Priya | Q7: No Defects | AD7: Dev Testing Completed. Testing completed in TST env. | AE7: 01/29/2026 - Upgraded Latest Telerik.Licensig Package 01/30/2026 - Analyzing how to implement licensing environmental wise for Telerik.Licensing package
A8: 7 | B8: GGO Web | C8: 46044 | D8: 46058 | E8: GGO 8.2.0 Sprint 4 | F8: Saranya | G8: GGO-15142 | H8: API Update for Next Gen - Checkout part 1 | I8: Completed | J8: 1 | K8: 1 | L8: 10 | M8: 46050 | N8: 46050 | O8: Done | P8: Priya | Q8: No Defects | T8: https://greatergiving.visualstudio.com/Greater%20Giving/_git/GGO/pullrequest/9235 | U8: 46051 | V8: 46051 | W8: Rajesh | Y8: Mike Horihan | Z8: 46052 | AD8: Dev Testing Completed. Testing completed in TST env. | AE8: 01/28/2026 - GetCheckinDetails API Updated with some additional info for NextGen. Development 100% completed 01/29/2026 - Dev testing completed. Created PR
A9: 8 | B9: GGO Web | C9: 46044 | D9: 46058 | E9: GGO 8.2.0 Sprint 4 | F9: Rajesh | G9: PAPI-883 | H9: Upgrade the Polly NuGet Package | I9: Completed | J9: 2 | K9: 2 | L9: 2 | M9: 46052 | N9: 46053 | O9: Done | P9: Priya | Q9: No Defects | T9: https://dev.azure.com/greatergiving/Greater%20Giving/_git/PAPI/pullrequest/9242 | U9: 46053 | V9: 46053 | W9: Rajesh | Y9: Mike Horihan | Z9: 46053 | AD9: Dev Testing Completed. Testing completed in TST env.
A10: 9 | B10: GGO Web | C10: 46044 | D10: 46058 | E10: GGO 8.2.0 Sprint 4 [Stretch] | F10: Saranya | G10: GGO-15084 | H10: Report Timestamps in UTC | I10: Completed | J10: 2 | K10: 2 | L10: 10 | M10: 46057 | N10: 46058 | O10: Done | P10: Priya | Q10: No Defects | AD10: Dev Testing Completed. Testing completed in TST env. Pending with Onsite QA | AE10: 02/04/2026 - Implemented report run time based on Project timezone for rpf reports
A11: 10 | B11: GGO Web | C11: 46044 | D11: 46058 | E11: GGO 8.2.0 Sprint 4 [Stretch] | F11: Rajesh | G11: GGO-15143 | H11: Update the Apigee domain for Azure B2C OIDC endpoints. | I11: Completed | J11: 1 | K11: 1 | L11: 1 | M11: 46057 | N11: 46058 | O11: Done | P11: Priya | Q11: No Defects | AD11: Dev Testing Completed. Testing completed in TST env. Pending with Onsite QA
A12: 11 | B12: GGO Web | C12: 46044 | D12: 46058 | E12: GGO 8.2.0 Sprint 4 [Stretch] | F12: Sathiya | G12: GGO-15103 | H12: Optout.aspx.cs Exception | I12: Verfiy | J12: 2 | K12: 1 | L12: 10.5 | M12: 46058 | N12: 46058 | O12: Done | T12: https://dev.azure.com/greatergiving/Greater%20Giving/_git/GGO/pullrequest/9260 | U12: 46058 | AE12: 2/5/2026 -Fixed decryption issue verified in dev. PR created
A13: 12 | B13: GGO Web | C13: 46044 | D13: 46058 | E13: GGO 8.2.0 Sprint 4 | F13: Sathiya/Rajesh | G13: GGO-14628 | H13: Print Invoice/Receipts page - Timeout when Omit Sales and payment option selected with both Before and After date options | I13: Being Developed | J13: 3 | L13: 64.5 | M13: 46045 | T13: https://greatergiving.visualstudio.com/Greater%20Giving/_git/GGO/pullrequest/9220 | U13: 46049 | V13: NA | W13: NA | Y13: Mike Horihan | AD13: 0 | AE13: 01/28/2026 - Identified query part which taking more time 01/29/2026 - Writing new sp for calculating most recent association date Added migration script for the new SPCreated LLBLGen for the SP call definition
A14: 13 | B14: GGO Web | C14: 46044 | D14: 46058 | E14: GGO 8.2.0 Sprint 4 | F14: Priya-QA | G14: GGO-15140 | H14: 27 Jan GGO 8.2.0 CRT Release & Regression Testing | I14: Being Tested | J14: 3 | K14: 3 | L14: 22 | M14: 46057 | N14: 46058 | O14: Done | P14: Priya | Q14: No Defects | R14: NA | S14: NA | T14: NA | U14: NA | V14: NA | W14: NA | X14: NA | Y14: NA | Z14: NA | AA14: NA | AB14: NA | AC14: NA | AD14: Testing completed in CRT env. Pending with Onsite QA

Sheet GGO 8.2.0 Sprint 4-Defect
A1: S.No | B1: Sprint # | C1: Story/Defect ID | D1: Parent Story | E1: Developer | F1: Issue Type | G1: Issue Description | H1: Priority | I1: Defect Source | J1: Type | K1: Status | L1: Root Cause Category | M1: Found By | N1: Comment | O1: RCA Comment
G2: NO Defects

Sheet GGO 8.2.0 Sprint3-Defect
A1: S.No | B1: Sprint # | C1: Story/Defect ID | D1: Parent Story | E1: Developer | F1: Issue Type | G1: Issue Description | H1: Priority | I1: Defect Source | J1: Type | K1: Status | L1: Root Cause Category | M1: Found By | N1: Comment | O1: RCA Comment
G2: NO Defects

Sheet GGO 8.2.0 Sprint 3-Status
A1: S.No | B1: Application Name | C1: Sprint Start Date | D1: Sprint End Date | E1: Sprint | F1: Developer | G1: Story ID/Defect ID | H1: Description | I1: Status | J1: Estimated(sp) | K1: Actual(sp) | L1: Actual Hours Worklog | M1: Dev Start Date | N1: Dev End Date | O1: Unit testing | P1: Peer Tested By | Q1: Peer Tested Defects, if any | R1: Peer Reviewed By | S1: Peer Code Review Comments, if any | T1: PR Number/Link | U1: PR Created Date | V1: PR Approved Date | W1: Reviewer 1 | X1: Code Review Comments, if any | Y1: Reviewer 2 | Z1: Approved Date | AA1: Code Review Comments, if any2 | AB1: Internal PO -POV Comments | AC1: Client PO -POV Comments | AD1: Tester Comments | AE1: Developer Comments
A2: 1 | B2: GGO Web | C2: 46030 | D2: 46044 | E2: GGO 8.2.0 Sprint 3 | F2: Saranya | G2: GGO-15123 | H2: package item search | I2: Completed | J2: 1 | K2: 1 | L2: 14 | M2: 46035 | N2: 46031 | O2: Done | P2: Priya | T2: https://greatergiving.visualstudio.com/Greater%20Giving/_git/GGO/pullrequest/9159 | U2: 46031 | V2: 46031 | W2: Rajesh | Y2: Mike Horihan | Z2: 46032 | AD2: Dev Testing Completed. Testing completed in TST env. | AE2: 8/1/2026 - Item name search functionality implemented in View Packages search 9/1/2026 - Unit and Dev testing is completed. Created PR
A3: 2 | B3: GGO Web | C3: 46030 | D3: 46044 | E3: GGO 8.2.0 Sprint 3 | F3: Rajesh | G3: GGO-14843 | H3: GGO is Creating Duplicate Event Codes | I3: Completed | J3: 5 | K3: 5 | L3: 28 | M3: 46035 | N3: 46041 | O3: Done | P3: Priya | T3: https://greatergiving.visualstudio.com/Greater%20Giving/_git/GGO/pullrequest/9183 | U3: 46039 | V3: NA | W3: NA | Y3: Mike Horihan | Z3: 46043 | AD3: Dev Testing Completed. Testing completed in TST env. Pending with Onsite QA
A4: 3 | B4: GGO Web | C4: 46030 | D4: 46044 | E4: GGO 8.2.0 Sprint 3 | F4: Sathiya | G4: GGO-15125 | H4: View Items - Reposition the buttons | I4: Completed | J4: 1 | K4: 1 | L4: 16.5 | M4: 46031 | N4: 46031 | O4: Done | P4: Priya | T4: https://greatergiving.visualstudio.com/Greater%20Giving/_git/GGO/pullrequest/9158 | U4: 46031 | V4: 46032 | W4: Rajesh | Y4: Mike Horihan | Z4: 46032 | AD4: Dev Testing Completed. Testing completed in TST env. | AE4: 1/9/2026 - Development 100% completed. Dev testing is completed and Created a PR
A5: 4 | B5: GGO Web | C5: 46030 | D5: 46044 | E5: GGO 8.2.0 Sprint 3 | F5: Saranya | G5: GGO-15126 | H5: Create/Edit Item - Update the options within Image Description, Restriction and Images | I5: Completed | J5: 1 | K5: 1 | L5: 9 | M5: 46031 | N5: 46031 | O5: Done | P5: Priya | T5: https://greatergiving.visualstudio.com/Greater%20Giving/_git/GGO/pullrequest/9167 | U5: 46034 | V5: 46035 | W5: Rajesh | Y5: Mike Horihan | Z5: 46035 | AD5: Dev Testing Completed. Testing completed in TST env. | AE5: 1/9/2026 - Development 100% completed. Dev testing is completed and Created a PR
A6: 5 | B6: GGO Web | C6: 46030 | D6: 46044 | E6: GGO 8.2.0 Sprint 3 | F6: Saranya | G6: GGO-15127 | H6: View Items/Packages - Remove Merge option | I6: Completed | J6: 1 | K6: 1 | L6: 13 | M6: 46031 | N6: 46031 | O6: Done | P6: Priya | T6: https://greatergiving.visualstudio.com/Greater%20Giving/_git/GGO/pullrequest/9167 | U6: 46034 | V6: 46035 | W6: Rajesh | Y6: Mike Horihan | Z6: 46035 | AA6: the exclamation point is not necessary | AD6: Dev Testing Completed. Testing completed in TST env. | AE6: 1/9/2026 - Development 100% completed. Merge option removed from Actons dropdown in View Item and View Packages pages. Dev testing is completed and Created a PR
A7: 6 | B7: GGO Web | C7: 46030 | D7: 46044 | E7: GGO 8.2.0 Sprint 3 | F7: Rajesh | G7: GGO-15079 | H7: Do not allow OB Donation package as a featured package | I7: Completed | J7: 3 | K7: 3 | L7: 25 | M7: 46038 | N7: 46041 | O7: Done | P7: Priya | T7: https://greatergiving.visualstudio.com/Greater%20Giving/_git/GGO/pullrequest/9191 | U7: 46043 | V7: 46043 | W7: Rajesh | Y7: Mike Horihan | Z7: 46043 | AD7: Dev Testing Completed. Testing completed in TST env. Pending with Onsite QA | AE7: 1/16/2026 - Analysis completed 1/17/2026 - Development is 80% completed 1/18/2026 - Development is 100% completed 1/19/2026 - Unit and Dev testing is completed and created a PR
A8: 7 | B8: GGO Web | C8: 46030 | D8: 46044 | E8: GGO 8.2.0 Sprint 3 | F8: Saranya | G8: GGO-15128 | H8: Image File Size not getting set | I8: Completed | J8: 2 | K8: 2 | L8: 16 | M8: 46034 | N8: 46035 | O8: Done | P8: Priya | T8: https://greatergiving.visualstudio.com/Greater%20Giving/_git/GGO/pullrequest/9172 | U8: 46035 | V8: 46036 | W8: Rajesh | Y8: Mike Horihan | Z8: 46036 | AD8: Dev Testing Completed. Testing completed in TST env. | AE8: 1/12/2026 - Development 80% completed 1/13/2026 - LLBLGen created for stored procedure and Dev testing is completed and created a PR
A9: 8 | B9: GGO Web | C9: 46030 | D9: 46044 | E9: GGO 8.2.0 Sprint 3 | F9: Rajesh | G9: GGO-15104 | H9: Guides & Analytics toggle won't save | I9: Completed | J9: 2 | K9: 2 | L9: 2 | M9: 46031 | N9: 46031 | P9: NA | T9: NA | U9: NA | V9: NA | W9: NA | Y9: NA | Z9: NA | AE9: Development is completed by our end. Pending from Pendo side
A10: 9 | B10: GGO Web | C10: 46030 | D10: 46044 | E10: GGO 8.2.0 Sprint 3 | F10: Sathiya/Saranya/Rajesh | G10: GGO-15135 | H10: Jscrambler for GGO & GGAM & GO Time | I10: Peer review | J10: 3 | K10: 3 | L10: 30.5 | M10: 46041 | N10: 46043 | O10: Done | P10: Priya | T10: https://greatergiving.visualstudio.com/Greater%20Giving/_git/GGO/pullrequest/9201 | U10: 46043 | V10: 46044 | W10: Rajesh | Y10: Mike Horihan | AE10: 1/19/2026 - Completed analysis & Implemented Jscramber in ManageSalesAndPayements and GoTime 1/20/2026 - Implemented Jscramber in GGAM Page 1/21/2026 - Refactored code. Unit testing and peer review done. Created Pull request for review. Development and unit testing is done by our end. Settings to be updated by Jcramber Side
A11: 10 | B11: GGO Web | C11: 46030 | D11: 46044 | E11: GGO 8.2.0 Sprint 3 | F11: Sathiya | G11: GGO-14628 | H11: Print Invoice/Receipts page - Timeout when Omit Sales and payment option selected with both Before and After date options | I11: Being Developed | J11: 3 | L11: 56 | M11: 46031 | AE11: Unable to reproduce in TST env. Mike will confirm with backend team whether we need to close this ticket or provide the steps to reproduce

Sheet GGO 8.2.0 Sprint 1-Status
A1: S.No | B1: Application Name | C1: Sprint Start Date | D1: Sprint End Date | E1: Sprint | F1: Developer | G1: Story ID/Defect ID | H1: Description | I1: Status | J1: Estimated(sp) | K1: Actual(sp) | L1: Actual Hours Worklog | M1: Dev Start Date | N1: Dev End Date | O1: Unit testing | P1: Peer Tested By | Q1: Peer Tested Defects, if any | R1: Peer Reviewed By | S1: Peer Code Review Comments, if any | T1: PR Number/Link | U1: PR Created Date | V1: PR Approved Date | W1: Reviewer 1 | X1: Code Review Comments, if any | Y1: Reviewer 2 | Z1: Approved Date | AA1: Code Review Comments, if any2 | AB1: Internal PO -POV Comments | AC1: Client PO -POV Comments | AD1: Comments
A2: 1 | B2: GGO Web | C2: 46002 | D2: 46030 | E2: GGO 8.2.0 Sprint 1 | F2: Saranya | G2: GGO-15068 | H2: Print or Email Invoices/Receipts - Add a loading Pop-up | I2: Completed | J2: 1 | L2: 4 | M2: 46000 | N2: 46000 | O2: Saranya | P2: Priya | R2: Rajesh | T2: https://greatergiving.visualstudio.com/Greater%20Giving/_git/GGO/pullrequest/9094 | U2: 46001 | V2: 46001 | W2: Rajesh | Y2: Mike Horihan | Z2: 46001 | AD2: Completed Testing in the TST env
A3: 2 | B3: GGO Web | C3: 46002 | D3: 46030 | E3: GGO 8.2.0 Sprint 1 | F3: Saranya | G3: GGO-15124 | H3: Item Name field allows more than 127 characters, causing error on save in the Create Item Page | I3: Completed | J3: 2 | L3: 1 | M3: 46007 | N3: 46007 | O3: Saranya | P3: Priya | R3: Rajesh | T3: https://greatergiving.visualstudio.com/Greater%20Giving/_git/GGO/pullrequest/9109 | U3: 46007 | V3: 46007 | W3: Rajesh | Y3: Mike Horihan | Z3: 46007 | AD3: Completed Testing in the TST env
A4: 3 | B4: GGO Web | C4: 46002 | D4: 46030 | E4: GGO 8.2.0 Sprint 1 | F4: Rajesh | G4: GGO-15052 | H4: API Update for Next Gen - Supporter Search | I4: Completed | J4: 3 | L4: 31 | M4: 46003 | N4: 46041 | O4: Rajesh | P4: Priya | R4: Saranya | T4: https://greatergiving.visualstudio.com/Greater%20Giving/_git/GGO/pullrequest/9105 | U4: 46006 | V4: 46007 | W4: Rajesh | Y4: Mike Horihan | Z4: 46007 | AD4: Completed Testing in the TST env
A5: 4 | B5: GGO Web | C5: 46002 | D5: 46030 | E5: GGO 8.2.0 Sprint 1 | F5: Saranya | G5: GGO-15086 | H5: no negative search for sales and payments | I5: Completed | J5: 5 | L5: 53 | M5: 46003 | N5: 46041 | O5: Saranya | P5: Priya | R5: Rajesh | T5: https://greatergiving.visualstudio.com/Greater%20Giving/_git/GGO/pullrequest/9126 | U5: 46011 | V5: 46011 | W5: Rajesh | Y5: Mike Horihan | Z5: 46011 | AD5: Completed Testing in the TST env
A6: 5 | B6: GGO Web | C6: 46002 | D6: 46030 | E6: GGO 8.2.0 Sprint 1 | F6: Sathiya | G6: GGO-14956 | H6: Online Bidding settings page - Section 1 | I6: Completed | J6: 5 | L6: 82 | M6: 46006 | N6: 46022 | O6: Sathiya | P6: Priya | R6: Rajesh | T6: https://greatergiving.visualstudio.com/Greater%20Giving/_git/GGO/pullrequest/9136 | U6: 46017 | V6: 46023 | W6: Rajesh | Y6: Mccarty, Joseph | Z6: 46023 | AD6: Completed Testing in the TST env
A7: 5 | B7: GGO Web | C7: 46002 | D7: 46030 | E7: GGO 8.2.0 Sprint 1 | F7: Sathiya | G7: GGO-14919 | H7: Online Bidding settings page - Section 2 | I7: Completed | J7: 5 | L7: 44 | M7: 46007 | N7: 46022 | O7: Sathiya | P7: Priya | R7: Rajesh | T7: https://greatergiving.visualstudio.com/Greater%20Giving/_git/GGO/pullrequest/9136 | U7: 46017 | V7: 46023 | W7: Rajesh | Y7: Mccarty, Joseph | Z7: 46023 | AD7: Completed Testing in the TST env
A8: 6 | B8: GGO Web | C8: 46002 | D8: 46030 | E8: GGO 8.2.0 Sprint 1 | F8: Sathiya | G8: GGO-14957 | H8: Online Bidding settings page - Section 3 | I8: Completed | J8: 5 | L8: 37 | M8: 46008 | N8: 46022 | O8: Sathiya | P8: Priya | R8: Rajesh | T8: https://greatergiving.visualstudio.com/Greater%20Giving/_git/GGO/pullrequest/9136 | U8: 46017 | V8: 46023 | W8: Rajesh | Y8: Mccarty, Joseph | Z8: 46023 | AD8: Completed Testing in the TST env
A9: 7 | B9: GGO Web | C9: 46003 | D9: 46030 | E9: GGO 8.2.0 Sprint 1 | F9: Rajesh | G9: GGO-15094 | H9: Fallback plan for OB changes | I9: Completed | J9: 1 | L9: 6 | M9: NA | N9: NA | O9: NA | P9: Priya | R9: NA | T9: NA | U9: NA | V9: NA | W9: NA | Y9: NA | Z9: NA | AD9: Completed Testing in the TST env
A10: 8 | B10: GGO Web | C10: 46003 | D10: 46030 | E10: GGO 8.2.0 Sprint 1 | F10: Rajesh/Saranya | G10: GGO-15080 | H10: API update for Next Gen - supporter badges | I10: Completed | J10: 3 | L10: 7 | M10: 46013 | N10: 46014 | O10: Saranya | P10: Priya | R10: Rajesh | T10: https://greatergiving.visualstudio.com/Greater%20Giving/_git/GGO/pullrequest/9140 | U10: 46021 | V10: 46022 | W10: Rajesh | Y10: Mccarty, Joseph | Z10: 46022 | AD10: Completed Testing in the TST env
A11: 9 | B11: GGO Web | C11: 46002 | D11: 46030 | E11: GGO 8.2.0 Sprint 1 | F11: Saranya | G11: GGO-15117 | H11: View Package for for Non-Admin User* | I11: Completed | J11: 2 | L11: 18 | M11: 45993 | N11: 46027 | O11: Saranya | P11: Priya | R11: Rajesh | T11: https://greatergiving.visualstudio.com/Greater%20Giving/_git/GGO/pullrequest/9149 | U11: 46027 | V11: 46028 | W11: Rajesh | Y11: Mike Horihan | Z11: 46028 | AD11: Completed Testing in the TST env
A12: 10 | B12: GGO Web | C12: 46003 | D12: 46030 | E12: GGO 8.2.0 Sprint 1 | F12: Sathiya | G12: GGO-15132 | H12: Online Bidding Settings - Edit or Change Phase* | I12: Completed | J12: 2 | L12: 12.5 | M12: 46022 | N12: 46024 | O12: Sathiya | P12: Priya | R12: Saranya | T12: https://greatergiving.visualstudio.com/Greater%20Giving/_git/GGO/pullrequest/9146 | U12: 46024 | V12: 46025 | W12: Rajesh | Y12: Mike Horihan | Z12: 46027 | AD12: Completed Testing in the TST env
A13: 11 | B13: GGO Web | C13: 46003 | D13: 46030 | E13: GGO 8.2.0 Sprint 1 | F13: Sathiya | G13: GGO-15111 | H13: Revise Create/Edit Package design* | I13: Completed | J13: 3 | L13: 22 | M13: 46029 | N13: 46029 | O13: Sathiya | P13: Priya | R13: Saranya | T13: https://greatergiving.visualstudio.com/Greater%20Giving/_git/GGO/pullrequest/9150 | U13: 46029 | V13: 46029 | W13: Rajesh | Y13: Mike Horihan | Z13: 46029
A14: 12 | B14: GGO Web | C14: 46003 | D14: 46030 | E14: GGO 8.2.0 Sprint 1 | F14: Sathiya/Saranya | G14: GGO-15112 | H14: Update the grids - Supporter, Items and Packages pages* | I14: Completed | J14: 2 | L14: 29 | M14: 46028 | N14: 46029 | O14: Saranya | P14: Priya | R14: Sathiya | T14: https://greatergiving.visualstudio.com/Greater%20Giving/_git/GGO/pullrequest/9151 | U14: 46029 | V14: 46030 | W14: Rajesh | Y14: Mike Horihan | Z14: 46030
A15: 13 | B15: GGO Web | C15: 46003 | D15: 46030 | E15: GGO 8.2.0 Sprint 1 | F15: Saranya | G15: GGO-15123 | H15: package item search* | I15: Being Developed | J15: 2 | L15: 9 | M15: 45999

Sheet GGO 8.2.0 Sprint 1-Defect
A1: S.No | B1: Sprint # | C1: Story/Defect ID | D1: Parent Story | E1: Developer | F1: Issue Type | G1: Issue Description | H1: Priority | I1: Defect Source | J1: Type | K1: Status | L1: Root Cause Category | M1: Found By | N1: Comment | O1: RCA Comment
G2: NO Defects

Sheet GGO 8.1.0 Sprint 4-Status
A1: S.No | B1: Application Name | C1: Sprint Start Date | D1: Sprint End Date | E1: Sprint | F1: Developer | G1: Story ID/Defect ID | H1: Description | I1: Status | J1: Estimated(sp) | K1: Actual(sp) | L1: Actual Hours Worklog | M1: Dev Start Date | N1: Dev End Date | O1: Unit testing | P1: Peer Tested By | Q1: Peer Tested Defects, if any | R1: Peer Reviewed By | S1: Peer Code Review Comments, if any | T1: PR Number/Link | U1: PR Created Date | V1: PR Approved Date | W1: Reviewer 1 | X1: Code Review Comments, if any | Y1: Reviewer 2 | Z1: Approved Date | AA1: Code Review Comments, if any2 | AB1: Internal PO -POV Comments | AC1: Client PO -POV Comments | AD1: Comments
A2: 1 | B2: GGO Web | C2: 45988 | D2: 46002 | E2: GGO 8.1.0 Sprint 4 | F2: Rajesh | G2: GGO-14932 | H2: Pop-up Dialogs in View Packages page | I2: Completed | J2: 1 | L2: 12 | M2: 45987 | N2: 45987 | O2: Saranya | P2: Priya | R2: Rajesh | T2: https://greatergiving.visualstudio.com/Greater%20Giving/_git/GGO/pullrequest/9053 | U2: 45987 | V2: 45987 | W2: Rajesh | Y2: Mike Horihan | Z2: 45987
A3: 2 | B3: GGO Web | C3: 45988 | D3: 46002 | E3: GGO 8.1.0 Sprint 4 | F3: Sathiya | G3: GGO-15091 | H3: Image Manager Missing in New UI for Edit Package Image while creating New Items | I3: Completed | J3: 1 | L3: 18 | M3: 45988 | N3: 45988 | O3: Sathiya | P3: Priya | R3: Saranya | T3: https://greatergiving.visualstudio.com/Greater%20Giving/_git/GGO/pullrequest/9052 | U3: 45987 | V3: 45988 | W3: Rajesh | Y3: Mike Horihan | Z3: 45988
A4: 3 | B4: GGO Web | C4: 45988 | D4: 46002 | E4: GGO 8.1.0 Sprint 4 | F4: Saranya | G4: GGO-15085 | H4: package search update | I4: Completed | J4: 3 | L4: 28 | M4: 45988 | N4: 45993 | O4: Saranya | P4: Priya | R4: Rajesh | T4: https://greatergiving.visualstudio.com/Greater%20Giving/_git/GGO/pullrequest/9068 | U4: 45994 | V4: 45994 | W4: Rajesh | Y4: Mike Horihan | Z4: 45994
A5: 4 | B5: GGO Web | C5: 45988 | D5: 46002 | E5: GGO 8.1.0 Sprint 4 | F5: Rajesh | G5: GGO-15095 | H5: Nuget Package updates | I5: Completed | J5: 3 | L5: 10 | M5: 45988 | O5: Rajesh | P5: Priya | R5: Priya | T5: https://greatergiving.visualstudio.com/Greater%20Giving/_git/GGO/pullrequest/9087 | U5: 45997 | V5: 45997 | W5: Rajesh | Y5: Mike Horihan | Z5: 45997
A6: 5 | B6: GGO Web | C6: 45988 | D6: 46002 | E6: GGO 8.1.0 Sprint 4 | F6: Sathiya | G6: GGO-14876 | H6: Create/Edit Package Page | I6: Completed | J6: 8 | L6: 85.25 | M6: 45989 | N6: 46000 | O6: Sathya | P6: Priya | R6: Saranya/Rajesh | T6: https://greatergiving.visualstudio.com/Greater%20Giving/_git/GGO/pullrequest/9084 | U6: 45996 | V6: 46000 | W6: Rajesh | Y6: Mike Horihan | Z6: 46000
A7: 6 | B7: GGO Web | C7: 45988 | D7: 46002 | E7: GGO 8.1.0 Sprint 4 | F7: Saranya | G7: GGO-15071 | H7: Image Manager - Folder Rename Issue | I7: Completed | J7: 3 | L7: 40 | M7: 45992 | O7: Saranya | P7: Priya | R7: Rajesh | T7: https://greatergiving.visualstudio.com/Greater%20Giving/_git/GGO/pullrequest/9086 | U7: 45996 | V7: 45996 | W7: Rajesh | Y7: Mccarty, Joseph | Z7: 45997
A8: 7 | B8: GGO Web | C8: 45988 | D8: 46002 | E8: GGO 8.1.0 Sprint 4 | F8: Rajesh | G8: GGO-15072 | H8: Project Home Update - Non OB Clients | I8: Completed | J8: 2 | L8: 8 | M8: 45988 | O8: Rajesh | P8: Priya | R8: Sathiya | T8: https://greatergiving.visualstudio.com/Greater%20Giving/_git/GGO/pullrequest/9063 | U8: 45993 | V8: 45993 | W8: Rajesh | Y8: Mike Horihan | Z8: 45993
A9: 8 | B9: GGO Web | C9: 45988 | D9: 46002 | E9: GGO 8.1.0 Sprint 4 | F9: Saranya | G9: GGO-15106 | H9: All radio buttons appear selected by default on the Edit Invoice and GoTime Settings page | I9: Completed | J9: NA | L9: 2 | M9: 45995 | N9: 45995 | O9: Saranya | P9: Priya | R9: Sathiya | T9: https://greatergiving.visualstudio.com/Greater%20Giving/_git/GGO/pullrequest/9078 | U9: 45995 | V9: 45995 | W9: Rajesh | Y9: Mike Horihan | Z9: 45995
A10: 9 | B10: GGO Web | C10: 45988 | D10: 46002 | E10: GGO 8.1.0 Sprint 4 | F10: Rajesh/Saranya | G10: GGO-15110 | H10: Edit Package - Change Type and UI issue | I10: Completed | J10: NA | L10: 15.5 | M10: 46000 | N10: 46000 | O10: Saranya | P10: Priya | R10: Rajesh | T10: https://greatergiving.visualstudio.com/Greater%20Giving/_git/GGO/pullrequest/9095 | U10: 46001 | V10: 46001 | W10: Rajesh | Y10: Mike Horihan | Z10: 46001
A11: 10 | B11: GGO Web | C11: 45988 | D11: 46002 | E11: GGO 8.1.0 Sprint 4 | F11: Saranya | G11: GGO-15068 | H11: Print or Email Invoices/Receipts - Add a loading Pop-up* | I11: Being Tested | J11: 1 | L11: 4 | M11: 46000 | N11: 46000 | O11: Saranya | P11: Priya | R11: Rajesh | T11: https://greatergiving.visualstudio.com/Greater%20Giving/_git/GGO/pullrequest/9094 | U11: 46001 | V11: 46001 | W11: Rajesh | Y11: Mike Horihan | Z11: 46001
A12: 11 | B12: GGO Web | C12: 45988 | D12: 46002 | E12: GGO 8.1.0 Sprint 4 | F12: Saranya | G12: GGO-15086 | H12: no negative search for sales and payments* | I12: Being Developed | J12: 5 | L12: 8 | M12: 46002

Sheet GGO 8.1.0 Sprint 4-Defect
A1: S.No | B1: Sprint # | C1: Story/Defect ID | D1: Parent Story | E1: Developer | F1: Issue Type | G1: Issue Description | H1: Priority | I1: Defect Source | J1: Type | K1: Status | L1: Root Cause Category | M1: Found By | N1: Comment | O1: RCA Comment
B2: GGO 8.1.0 Sprint 4 | C2: GGO-15106 | D2: GGO-15014 | E2: Saranya | F2: Defect | G2: All radio buttons appear selected by default on the Edit Invoice and GoTime Settings page | H2: Significant | I2: Manual | J2: Internal | K2: Closed | L2: Design | M2: Priya
B3: GGO 8.1.0 Sprint 4 | C3: GGO-15110 | D3: GGO-14876 | E3: Saranya | F3: Defect | G3: Edit Package - Change Type and UI issue | H3: Significant | I3: Manual | J3: Internal | K3: Closed | L3: Design | M3: Priya

Sheet GGO 8.1.0 Sprint 3-Status
A1: S.No | B1: Application Name | C1: Sprint Start Date | D1: Sprint End Date | E1: Sprint | F1: Developer | G1: Story ID/Defect ID | H1: Description | I1: Status | J1: Estimated(sp) | K1: Actual(sp) | L1: Actual Hours Worklog | M1: Dev Start Date | N1: Dev End Date | O1: Unit testing | P1: Peer Tested By | Q1: Peer Tested Defects, if any | R1: Peer Reviewed By | S1: Peer Code Review Comments, if any | T1: PR Number/Link | U1: PR Created Date | V1: PR Approved Date | W1: Reviewer 1 | X1: Code Review Comments, if any | Y1: Reviewer 2 | Z1: Approved Date | AA1: Code Review Comments, if any2 | AB1: Internal PO -POV Comments | AC1: Client PO -POV Comments | AD1: Comments
A2: 1 | B2: GGO Web | C2: 45974 | D2: 45988 | E2: GGO 8.1.0 Sprint 3 | F2: Rajesh | G2: GGO-14931 | H2: View Items Advanced Search | I2: Completed | J2: 2 | L2: 14 | M2: 45967 | N2: 45974 | O2: Saranya | P2: Priya | R2: Sathya | T2: https://greatergiving.visualstudio.com/Greater%20Giving/_git/GGO/pullrequest/9004 | U2: 45973 | V2: 45974 | W2: Rajesh | Y2: Mike Horihan | Z2: 45974 | AD2: Completed Testing in the TST env
A3: 2 | B3: GGO Web | C3: 45974 | D3: 45988 | E3: GGO 8.1.0 Sprint 3 | F3: Rajesh | G3: GGO-15075 | H3: Supporter and Item Search advanced syntax | I3: Completed | J3: 1 | L3: 24 | M3: 45974 | N3: 45974 | O3: Saranya | P3: Priya | R3: Rajesh | T3: https://greatergiving.visualstudio.com/Greater%20Giving/_git/GGO/pullrequest/9008 | U3: 45974 | V3: 45975 | W3: Rajesh | Y3: Mike Horihan | Z3: 45975 | AD3: Completed Testing in the TST env
A4: 3 | B4: GGO Web | C4: 45974 | D4: 45988 | E4: GGO 8.1.0 Sprint 3 | F4: Sathya | G4: GGO-15065 | H4: Cancel Button Hidden in Popups on Package Page Across All Environments - UI Issues | I4: Completed | J4: 2 | L4: 42.5 | M4: 45975 | N4: 45979 | O4: Sathya | P4: Priya | R4: Rajesh | T4: https://greatergiving.visualstudio.com/Greater%20Giving/_git/GGO/pullrequest/9017 | U4: 45979 | V4: 45979 | W4: Rajesh | Y4: Mike Horihan | Z4: 45979 | AD4: Completed Testing in the TST env
A5: 4 | B5: GGO Web | C5: 45974 | D5: 45988 | E5: GGO 8.1.0 Sprint 3 | F5: Sathya | G5: GGO-15058 | H5: Login Page Update - Expiring Privacy Policy Message v2 | I5: Completed | J5: 3 | L5: 23 | M5: 45979 | N5: 45981 | O5: Sathya | P5: Priya | R5: Rajesh | T5: https://greatergiving.visualstudio.com/Greater%20Giving/_git/GGO/pullrequest/9031 | U5: 45980 | V5: 45982 | W5: Rajesh | Y5: Mike Horihan | Z5: 45982 | AA5: the whole div should be removed, right? Are we also hiding the B2C Batch Migration setting? this div is the end div that was surrounding the B2C Batch Migration, right? | AD5: Completed Testing in the TST env
A6: 5 | B6: GGO Web | C6: 45974 | D6: 45988 | E6: GGO 8.1.0 Sprint 3 | F6: Rajesh | G6: GGO-15067 | H6: Nav Bar - Maintain consistent behavior throughout the application | I6: Completed | J6: 3 | L6: 13 | M6: 45975 | N6: 45978 | O6: Rajesh | P6: Priya | R6: Saranya | T6: https://greatergiving.visualstudio.com/Greater%20Giving/_git/GGO/pullrequest/9019 | U6: 45978 | V6: 45979 | W6: Rajesh | Y6: Mike Horihan | Z6: 45979 | AD6: Completed Testing in the TST env
A7: 6 | B7: GGO Web | C7: 45974 | D7: 45988 | E7: GGO 8.1.0 Sprint 3 | F7: Saranya | G7: GGO-14933 | H7: View Packages Advanced Search | I7: Completed | J7: 5 | L7: 26 | M7: 45978 | N7: 45980 | O7: Saranya | P7: Priya | R7: Rajesh | T7: https://greatergiving.visualstudio.com/Greater%20Giving/_git/GGO/pullrequest/9028 | U7: 45979 | V7: 45979 | W7: Rajesh | Y7: Mike Horihan | Z7: 45980 | AD7: Completed Testing in the TST env
A8: 7 | B8: GGO Web | C8: 45974 | D8: 45988 | E8: GGO 8.1.0 Sprint 3 | F8: Saranya / Rajesh | G8: PAPI-891 | H8: GoTime Check-in with EMV is missing PAPI Payment record for CardVerify | I8: Completed | J8: 3 | L8: 6 | M8: 45978 | N8: 45979 | O8: Saranya | P8: Priya | R8: Rajesh | T8: https://greatergiving.visualstudio.com/Greater%20Giving/_git/PAPI/pullrequest/9029 | U8: 45980 | V8: 45980 | W8: Rajesh | Y8: Mike Horihan | Z8: 45980 | AD8: Completed Testing in the TST env
A9: 8 | B9: GGO Web | C9: 45974 | D9: 45988 | E9: GGO 8.1.0 Sprint 3 | F9: Saranya | G9: GGO-15081 | H9: Create Items - Update Hyperlink Manager pop-up* | I9: Completed | J9: 2 | L9: 34 | M9: 45981 | N9: 45987 | O9: Saranya | P9: Priya | R9: Sathya | T9: https://greatergiving.visualstudio.com/Greater%20Giving/_git/GGO/pullrequest/9040 | U9: 45986 | V9: 45986 | W9: Rajesh | Y9: Mike Horihan | Z9: 45986 | AD9: Completed Testing in the Dev env
A10: 9 | B10: GGO Web | C10: 45974 | D10: 45988 | E10: GGO 8.1.0 Sprint 3 | F10: Saranya | G10: GGO-15082 | H10: Rename popup UI shrinks and require multiple clicks in Global Search to apply changes | I10: Completed | J10: NA | L10: 6 | M10: 45981 | N10: 45981 | O10: Saranya | P10: Priya | R10: Rajesh | T10: https://greatergiving.visualstudio.com/Greater%20Giving/_git/GGO/pullrequest/9038 | U10: 45981 | V10: 45981 | W10: Rajesh | Y10: Mike Horihan | Z10: 45982 | AD10: Completed Testing in the TST env
A11: 10 | B11: GGO Web | C11: 45974 | D11: 45988 | E11: GGO 8.1.0 Sprint 3 | F11: Rajesh | G11: GGO-15089 | H11: RSVP Import Delays / Slowness* | I11: Completed | J11: 2 | L11: 6 | O11: Rajesh | P11: Priya | R11: =-Dashboard!E5026 -> 0 | T11: https://greatergiving.visualstudio.com/Greater%20Giving/_git/GGO/pullrequest/9050 | U11: 45987 | V11: 45987 | W11: Rajesh | Y11: Mike Horihan | Z11: 45987
A12: 11 | B12: GGO Web | C12: 45974 | D12: 45988 | E12: GGO 8.1.0 Sprint 3 | F12: Saranya / Rajesh | G12: GGO-14932 | H12: Pop-up Dialogs in View Packages page | I12: Verify | J12: 2 | L12: 3 | M12: 45987 | N12: 45987 | O12: Saranya | P12: Priya | R12: Rajesh | T12: https://greatergiving.visualstudio.com/Greater%20Giving/_git/GGO/pullrequest/9053 | U12: 45987 | V12: 45987 | W12: Rajesh | Y12: Mike Horihan | Z12: 45987

Sheet GGO 8.1.0 Sprint 3-Defect
A1: S.No | B1: Sprint # | C1: Story/Defect ID | D1: Parent Story | E1: Developer | F1: Issue Type | G1: Issue Description | H1: Priority | I1: Defect Source | J1: Type | K1: Status | L1: Root Cause Category | M1: Found By | N1: Comment | O1: RCA Comment
B2: GGO 8.1.0 Sprint 3 | C2: GGO-14933 | D2: GGO-15802 | E2: Saranya | F2: Defect | G2: Rename popup UI shrinks and require multiple clicks in Global Search to apply changes | H2: Significant | I2: Manual | J2: Internal | K2: Closed | L2: Design | M2: Priya

Sheet GGO 8.1.0 Sprint 2-Status
A1: S.No | B1: Application Name | C1: Sprint Start Date | D1: Sprint End Date | E1: Sprint | F1: Developer | G1: Story ID/Defect ID | H1: Description | I1: Status | J1: Estimated(sp) | K1: Actual(sp) | L1: Actual Hours Worklog | M1: Dev Start Date | N1: Dev End Date | O1: Unit testing | P1: Peer Tested By | Q1: Peer Tested Defects, if any | R1: Peer Reviewed By | S1: Peer Code Review Comments, if any | T1: PR Number/Link | U1: PR Created Date | V1: PR Approved Date | W1: Reviewer 1 | X1: Code Review Comments, if any | Y1: Reviewer 2 | Z1: Approved Date | AA1: Code Review Comments, if any2 | AB1: Internal PO -POV Comments | AC1: Client PO -POV Comments | AD1: Comments
A2: 1 | B2: GGO Web | C2: 45960 | D2: 45974 | E2: GGO 8.1.0 Sprint 2 | F2: Sathiya/Saranya | G2: GGO-14901 | H2: Manage Images - Popup | I2: Completed | J2: 5 | L2: 52 | M2: 45961 | N2: 45971 | O2: Sathiya | P2: Priya | R2: Saranya | T2: https://dev.azure.com/greatergiving/Greater%20Giving/_git/GGO/pullrequest/8963 | U2: 45958 | V2: 45968 | W2: Rajesh | Y2: Mike Horihan | Z2: 45968 | AD2: Completed Testing in the TST env
A3: 2 | B3: GGO Web | C3: 45960 | D3: 45974 | E3: GGO 8.1.0 Sprint 2 | F3: Rajesh | G3: GGO-10698 | H3: Item solicitor doesn't import when added during Import Online Item Donation process | I3: Completed | J3: 3 | L3: 22 | M3: 45961 | N3: 45965 | O3: Rajesh | P3: Priya | R3: Sathya | T3: https://dev.azure.com/greatergiving/Greater%20Giving/_git/GGO/pullrequest/8980 | U3: 45965 | V3: 45965 | W3: Saranya | Y3: Mike Horihan | Z3: 45965 | AD3: Completed Testing in the TST env
A4: 3 | B4: GGO Web | C4: 45960 | D4: 45974 | E4: GGO 8.1.0 Sprint 2 | F4: Rajesh | G4: GGO-15054 | H4: Supporters - Filters - Retain Radio buttons value in Saved Search | I4: Completed | J4: 3 | L4: 19 | M4: 45961 | N4: 45961 | O4: Rajesh | P4: Priya | R4: Sathya | T4: https://dev.azure.com/greatergiving/Greater%20Giving/_git/GGO/pullrequest/8971 | U4: 45961 | V4: 45961 | W4: Sathya | Y4: Mike Horihan | Z4: 45961 | AD4: Completed Testing in the TST env
A5: 4 | B5: GGO Web | C5: 45960 | D5: 45974 | E5: GGO 8.1.0 Sprint 2 | F5: Sathya | G5: GGO-15060 | H5: View Items page for Non-Admin User | I5: Completed | J5: 3 | L5: 16 | M5: 45967 | N5: 45971 | O5: Sathya | P5: Priya | R5: Rajesh | T5: https://greatergiving.visualstudio.com/Greater%20Giving/_git/GGO/pullrequest/8990 | U5: 45968 | V5: 45968 | W5: Rajesh | Y5: Mike Horihan | Z5: 45969 | AD5: Completed Testing in the TST env
A6: 5 | B6: GGO Web | C6: 45960 | D6: 45974 | E6: GGO 8.1.0 Sprint 2 | F6: Saranya | G6: GGO-15055 | H6: View Items - Actions - Copy Items from other Projects | I6: Completed | J6: 3 | L6: 29 | M6: 45964 | N6: 45967 | O6: Saranya | P6: Priya | R6: Sathya | T6: https://dev.azure.com/greatergiving/Greater%20Giving/_git/GGO/pullrequest/8987 | U6: 45967 | V6: 45967 | W6: Rajesh | Y6: Mike Horihan | Z6: 45968 | AD6: Completed Testing in the TST env
A7: 6 | B7: GGO Web | C7: 45960 | D7: 45974 | E7: GGO 8.1.0 Sprint 2 | F7: Rajesh/Saranya/Sathya | G7: GGO-14931 | H7: View Items Advanced Search* | I7: Being Tested | J7: 5 | L7: 40 | M7: 45967 | N7: 45974 | O7: Saranya | P7: Priya | R7: Sathya | T7: https://greatergiving.visualstudio.com/Greater%20Giving/_git/GGO/pullrequest/9004 | U7: 45973 | V7: 45974 | W7: Rajesh | Y7: Mike Horihan | Z7: 45974
A8: 7 | B8: GGO Web | C8: 45960 | D8: 45974 | E8: GGO 8.1.0 Sprint 2 | F8: Rajesh/Saranya/Sathya | G8: GGO-15066 | H8: Equipment Needed banner is missing after the GGO UI refresh released to Production | I8: Completed | J8: 2 | L8: 4 | M8: 45972 | N8: 45974 | O8: Rajesh | P8: Priya | R8: Saranya | T8: https://greatergiving.visualstudio.com/Greater%20Giving/_git/GGO/pullrequest/8998 | U8: 45972 | V8: 45972 | W8: Rajesh | Y8: Mike Horihan | Z8: 45972 | AD8: Completed Testing in the TST env
A9: 8 | B9: GGO Web | C9: 45960 | D9: 45974 | E9: GGO 8.1.0 Sprint 2 | F9: Rajesh/Saranya/Sathya | G9: GGO-15070 | H9: View Supporters no cards on file search filter is not working | I9: Completed | J9: 2 | L9: 10 | M9: 45972 | N9: 45974 | O9: Saranya | P9: Priya | R9: Sathya | T9: https://greatergiving.visualstudio.com/Greater%20Giving/_git/GGO/pullrequest/9002 | U9: 45972 | V9: 45972 | W9: Rajesh | Y9: Mike Horihan | Z9: 45972 | AD9: Completed Testing in the TST env
A10: 9 | B10: GGO Web | C10: 45960 | D10: 45974 | E10: GGO 8.1.0 Sprint 2 | F10: Rajesh/Saranya/Sathya | G10: GGO-15073 | H10: Activate OB Link isn't on the New GGO Home Page | I10: Completed | J10: 2 | L10: 13.5 | M10: 45972 | N10: 45974 | O10: Sathya | P10: Priya | R10: Rajesh | T10: https://greatergiving.visualstudio.com/Greater%20Giving/_git/GGO/pullrequest/9000 | U10: 45972 | V10: 45973 | W10: Rajesh | Y10: Mike Horihan | Z10: 45973 | AD10: Completed Testing in the TST env
A11: 10 | B11: GGO Web | C11: 45960 | D11: 45974 | E11: GGO 8.1.0 Sprint 2 | F11: Sathiya/Saranya | G11: GGO-15069 | H11: UI Issues | I11: Completed | L11: 6.5 | M11: 45968 | N11: 45968 | O11: Sathya | P11: Priya | R11: Rajesh | T11: https://greatergiving.visualstudio.com/Greater%20Giving/_git/GGO/pullrequest/8994 | U11: 45969 | V11: 45969 | W11: Rajesh | Y11: Mike Horihan | Z11: 45969 | AD11: Completed Testing in the TST env
A12: 11 | B12: GGO Web | C12: 45960 | D12: 45974 | E12: GGO 8.1.0 Sprint 2 | F12: Saranya | G12: GGO-15075 | H12: Supporter and Item Search advanced syntax | I12: Verify | L12: 14 | M12: 45974 | N12: 45974 | O12: Saranya | P12: Priya | R12: Rajesh | T12: https://greatergiving.visualstudio.com/Greater%20Giving/_git/GGO/pullrequest/9008 | U12: 45974 | V12: 45975 | W12: Rajesh | Y12: Mike Horihan | Z12: 45975 | AD12: Completed Testing in the TST env

Sheet GGO 8.1.0 Sprint 1-Status
A1: S.No | B1: Application Name | C1: Sprint Start Date | D1: Sprint End Date | E1: Sprint | F1: Developer | G1: Story ID/Defect ID | H1: Description | I1: Status | J1: Estimated(sp) | K1: Actual(sp) | L1: Actual Hours Worklog | M1: Dev Start Date | N1: Dev End Date | O1: Unit testing | P1: Peer Tested By | Q1: Peer Tested Defects, if any | R1: Peer Reviewed By | S1: Peer Code Review Comments, if any | T1: PR Number/Link | U1: PR Created Date | V1: PR Approved Date | W1: Reviewer 1 | X1: Code Review Comments, if any | Y1: Reviewer 2 | Z1: Approved Date | AA1: Code Review Comments, if any2 | AB1: Internal PO -POV Comments | AC1: Client PO -POV Comments | AD1: Comments
A2: 1 | B2: GGO Web | C2: 45946 | D2: 45960 | E2: GGO 8.1.0 Sprint 1 | F2: Saranya | G2: GGO-15042 | H2: Re-introduce Group by Household to Supporter Grid* | I2: Completed | J2: 3 | M2: 45947 | O2: Saranya | P2: Priya | R2: Sathiya | T2: https://greatergiving.visualstudio.com/Greater%20Giving/_git/GGO/pullrequest/8944 | U2: 45953 | V2: 45953 | W2: Rajesh | Y2: Mike Horihan | Z2: 45953 | AD2: Testing completed in the TST env.
A3: 2 | B3: GGO Web | C3: 45946 | D3: 45960 | E3: GGO 8.1.0 Sprint 1 | F3: Rajesh | G3: GG0-15041 | H3: Household Investigation | I3: Completed | J3: 3 | L3: 9 | M3: 45947 | T3: NA | U3: NA | V3: NA | W3: NA | Y3: NA | Z3: NA | AD3: NA
A4: 3 | B4: GGO Web | C4: 45946 | D4: 45960 | E4: GGO 8.1.0 Sprint 1 | F4: Rajesh | G4: GGO-15020 | H4: OneTrust implementation issue | I4: Completed | J4: 3 | M4: 45947 | O4: Rajesh | P4: Priya | T4: https://greatergiving.visualstudio.com/Greater%20Giving/_git/GGO/pullrequest/8954 | U4: 45955 | V4: 45955 | W4: Rajesh | Y4: Mike Horihan | Z4: 45957 | AD4: Testing completed in the TST env.
A5: 4 | B5: GGO Web | C5: 45946 | D5: 45960 | E5: GGO 8.1.0 Sprint 1 | F5: Sathiya | G5: GGO-14901 | H5: Manage Images - Popup | I5: Completed | J5: 5 | M5: 45947 | AD5: Since the design is more complex and focused on group items by household functionality in the view supporters filter
A6: 5 | B6: GGO Web | C6: 45946 | D6: 45960 | E6: GGO 8.1.0 Sprint 1 | F6: Saranya/Sathya | G6: GGO-14930 | H6: Pop-up Dialogs in View Items page | I6: Completed | J6: 3 | M6: 45947 | O6: Saranya | P6: Priya | R6: Sathiya | T6: https://greatergiving.visualstudio.com/Greater%20Giving/_git/GGO/pullrequest/8960 | U6: 45958 | V6: 45958 | W6: Rajesh | Y6: Mike Horihan | Z6: 45958 | AA6: Selecting 2 items, click Package from Actions, Click cancel causes the page to refresh and items selected become unselected. | AD6: Testing completed in the TST env.

Sheet GGO 8.1.0 Sprint 2-Defect
A1: S.No | B1: Sprint # | C1: Story/Defect ID | D1: Parent Story | E1: Developer | F1: Issue Type | G1: Issue Description | H1: Priority | I1: Defect Source | J1: Type | K1: Status | L1: Root Cause Category | M1: Found By | N1: Comment | O1: RCA Comment
B2: GGO 8.1.0 Sprint 1 | C2: GGO-15069 | D2: GGO-14901 | E2: Sathiya/Rajesh/Saranya | F2: Defect | G2: UI Issues | H2: Significant | I2: Manual | J2: Internal | K2: Closed | L2: Design | M2: Priya

Sheet GGO 8.1.0 Sprint 1-Defect
A1: S.No | B1: Sprint # | C1: Story/Defect ID | D1: Parent Story | E1: Developer | F1: Issue Type | G1: Issue Description | H1: Priority | I1: Defect Source | J1: Type | K1: Status | L1: Root Cause Category | M1: Found By | N1: Comment | O1: RCA Comment
B2: GGO 8.1.0 Sprint 1 | C2: GGO-15042 | D2: GGO-15050 | E2: Sathiya/Rajesh/Saranya | F2: Defect | G2: Search filter and design issues | H2: Significant | I2: Manual | J2: Internal | K2: Closed | L2: Design | M2: Priya

Sheet GGO 8.0.0 Sprint 4-Status
A1: S.No | B1: Application Name | C1: Sprint Start Date | D1: Sprint End Date | E1: Sprint | F1: Developer | G1: Story ID/Defect ID | H1: Description | I1: Status | J1: Estimated(sp) | K1: Actual(sp) | L1: Actual Hours Worklog | M1: Dev Start Date | N1: Dev End Date | O1: Unit testing | P1: Peer Tested By | Q1: Peer Tested Defects, if any | R1: Peer Reviewed By | S1: Peer Code Review Comments, if any | T1: PR Number/Link | U1: PR Created Date | V1: PR Approved Date | W1: Reviewer 1 | X1: Code Review Comments, if any | Y1: Reviewer 2 | Z1: Approved Date | AA1: Code Review Comments, if any2 | AB1: Internal PO -POV Comments | AC1: Client PO -POV Comments | AD1: Comments
A2: 1 | B2: GGO Web | C2: 45933 | D2: 45946 | E2: GGO 8.0.0 Sprint 4 | F2: Praveen/Sathiya | G2: GGO-15015 | H2: Create Item - Update the Rich Text editor | I2: Completed | J2: 2 | L2: 32 | M2: 45933 | O2: Sathiya | P2: Priya | R2: Praveen | T2: https://greatergiving.visualstudio.com/Greater%20Giving/_git/GGO/pullrequest/8918 | U2: 45941 | V2: 45941 | W2: Rajesh | Y2: Mike Horihon | Z2: 45943 | AD2: Verified in the TST env. Working well
A3: 2 | B3: GGO Web | C3: 45933 | D3: 45946 | E3: GGO 8.0.0 Sprint 4 | F3: Saranya | G3: GGO-14966 | H3: item package updates | I3: Completed | J3: 2 | L3: 13 | M3: 45933 | O3: Saranya | P3: Priya | R3: Sathiya | T3: https://greatergiving.visualstudio.com/Greater%20Giving/_git/GGO/pullrequest/8902 | U3: 45936 | V3: 45937 | W3: Rajesh | Y3: Mike Horihon | Z3: 45937 | AD3: Verified in the TST env. Working well
A4: 3 | B4: GGO Web | C4: 45933 | D4: 45946 | E4: GGO 8.0.0 Sprint 4 | F4: Praveen/Sathiya | G4: GGO-14877 | H4: Create Item - Image Control (Multi-image chooser) | I4: Completed | J4: 5 | L4: 36 | M4: 45933 | O4: Sathiya | P4: Priya | R4: Praveen | T4: https://greatergiving.visualstudio.com/Greater%20Giving/_git/GGO/pullrequest/8922 | U4: 45944 | V4: 45945 | W4: Rajesh | Y4: Mike Horihon | Z4: 45945 | AD4: Verified in the TST env. Working well
A5: 4 | B5: GGO Web | C5: 45933 | D5: 45946 | E5: GGO 8.0.0 Sprint 4 | F5: Rajesh | G5: GGO-15037 | H5: Error clicking cancel in Email Verify and Password Reset | I5: Completed | J5: 1 | L5: 3 | M5: 45933 | O5: Rajesh | P5: Priya | R5: Saranya | T5: https://greatergiving.visualstudio.com/Greater%20Giving/_git/GGO/pullrequest/8893 | U5: 45933 | V5: 45933 | W5: NA | Y5: Mike Horihon | Z5: 45933 | AD5: Verified in the TST env. Working well
A6: 5 | B6: GGO Web | C6: 45933 | D6: 45946 | E6: GGO 8.0.0 Sprint 4 | F6: Sathiya/Rajesh | G6: GGO-15029 | H6: Gotime-Error | I6: Completed | J6: 3 | L6: 43.5 | M6: 45933 | O6: NA | P6: NA | R6: NA | T6: NA | U6: NA | V6: NA | W6: NA | Y6: NA | Z6: NA | AD6: Verified from client side.
A7: 6 | B7: GGO Web | C7: 45933 | D7: 45946 | E7: GGO 8.0.0 Sprint 4 | F7: Saranya | G7: GGO-15042 | H7: Re-introduce Group by Household to Supporter Grid* | I7: Being Developed | J7: 5 | L7: 47 | M7: 45943 | AD7: Testing in Dev env.

Sheet GGO 8.0.0 Sprint 3-Status
A1: S.No | B1: Application Name | C1: Sprint Start Date | D1: Sprint End Date | E1: Sprint | F1: Developer | G1: Story ID/Defect ID | H1: Description | I1: Status | J1: Estimated(sp) | K1: Actual(sp) | L1: Actual Hours Worklog | M1: Dev Start Date | N1: Dev End Date | O1: Unit testing | P1: Peer Tested By | Q1: Peer Tested Defects, if any | R1: Peer Reviewed By | S1: Peer Code Review Comments, if any | T1: PR Number/Link | U1: PR Created Date | V1: PR Approved Date | W1: Reviewer 1 | X1: Code Review Comments, if any | Y1: Reviewer 2 | Z1: Approved Date | AA1: Code Review Comments, if any2 | AB1: Internal PO -POV Comments | AC1: Client PO -POV Comments | AD1: Comments
A2: 1 | B2: GGO Web | C2: 45918 | D2: 45932 | E2: GGO 8.0.0 Sprint 3 | F2: Sathiya/Rajesh/Saranya | G2: GGO-14980 | H2: View Supporter Page Filter - Save Search | I2: Completed | J2: 3 | L2: 106 | M2: 45905 | N2: 45929 | O2: Sathiya | P2: Priya | R2: Saranya | T2: https://greatergiving.visualstudio.com/Greater%20Giving/_git/GGO/pullrequest/8872 | U2: 45925 | V2: 45927 | W2: Rajesh | Y2: Mike Horihan | Z2: 45927 | AD2: Due to complications involving multiple user controls on the filter page, some functions within the new user control are not triggering as expected. Additionally, new controls were added which require further integration and testing to ensure smooth functionality.
A3: 2 | B3: GGO Web | C3: 45918 | D3: 45932 | E3: GGO 8.0.0 Sprint 3 | F3: Saranya | G3: GGO-14822 | H3: Update Email validation on Project Builder | I3: Completed | J3: 2 | L3: 18 | M3: 45922 | N3: 45924 | O3: Saranya | P3: Priya | R3: Sathiya | T3: https://greatergiving.visualstudio.com/Greater%20Giving/_git/GGO/pullrequest/8860 | U3: 45923 | V3: 45924 | W3: Rajesh | Y3: Mccarty, Joseph | Z3: 45924 | AD3: Testing Completed in the TST env
A4: 3 | B4: GGO Web | C4: 45918 | D4: 45932 | E4: GGO 8.0.0 Sprint 3 | F4: Praveen | G4: GGO-15013 | H4: Remove G logo from side nav | I4: Completed | J4: 2 | L4: 8 | M4: 45919 | O4: Praveen | P4: Priya | R4: Sathiya | T4: https://greatergiving.visualstudio.com/Greater%20Giving/_git/GGO/pullrequest/8853 | U4: 45922 | V4: 45922 | W4: Rajesh | Y4: Michael Wall | Z4: 45922 | AD4: Testing Completed in the TST env
A5: 4 | B5: GGO Web | C5: 45918 | D5: 45932 | E5: GGO 8.0.0 Sprint 3 | F5: Rajesh | G5: GGO-14661 | H5: Reskin Feature flag for new clients | I5: Completed | J5: 3 | L5: 9 | M5: 45919 | O5: Rajesh | P5: Priya | R5: Sathiya | T5: https://greatergiving.visualstudio.com/Greater%20Giving/_git/GGO/pullrequest/8850 | U5: 45922 | V5: 45923 | W5: Rajesh | Y5: Michael Wall | Z5: 45923 | AD5: Testing Completed in the TST env
A6: 5 | B6: GGO Web | C6: 45918 | D6: 45932 | E6: GGO 8.0.0 Sprint 3 | F6: Saranya/Praveen | G6: GGO-15010 | H6: Reskin Project Home Update Issue | I6: Completed | J6: 2 | L6: 13 | M6: 45923 | N6: 45926 | O6: Saranya | P6: Priya | R6: Sathiya | T6: https://greatergiving.visualstudio.com/Greater%20Giving/_git/GGO/pullrequest/8873 | U6: 45925 | V6: 45925 | W6: Rajesh | Y6: Michael Wall | Z6: 45926 | AD6: Testing Completed in the TST env
A7: 6 | B7: GGO Web | C7: 45918 | D7: 45932 | E7: GGO 8.0.0 Sprint 3 | F7: Rajesh/Sathiya | G7: GGO-14960 | H7: Macroscope - High - Prevent URL Redirector Abuse on Logout | I7: Completed | J7: 2 | L7: 17.5 | M7: 45923 | O7: Sathiya | P7: Priya | R7: Rajesh | T7: https://greatergiving.visualstudio.com/Greater%20Giving/_git/GGO/pullrequest/8876 | U7: 45926 | V7: 45926 | W7: Rajesh | Y7: Mike Horihan | Z7: 45926 | AD7: Testing Completed in the TST env
A8: 7 | B8: GGO Web | C8: 45918 | D8: 45932 | E8: GGO 8.0.0 Sprint 3 | F8: Saranya/Rajesh | G8: PAPI-882 | H8: Ensure All Card Types can be added as CoF when amount = $0.01 is set by Mobile Team | I8: Completed | J8: 1 | L8: 11 | M8: 45929 | O8: Saranya | P8: Rajesh | R8: Rajesh | T8: NA | U8: NA | V8: NA | W8: NA | Y8: NA | Z8: NA | AD8: Testing Completed in the TST env
A9: 8 | B9: GGO Web | C9: 45918 | D9: 45932 | E9: GGO 8.0.0 Sprint 3 | F9: Praveen/Sathiya | G9: GGO-15015 | H9: Create Item - Update the Rich Text editor* | I9: Being Developed | J9: 2 | L9: 5 | M9: 45929
A10: 9 | B10: GGO Web | C10: 45918 | D10: 45932 | E10: GGO 8.0.0 Sprint 3 | F10: Saranya | G10: GGO-14966 | H10: item package updates* | I10: Being Developed | J10: 3 | L10: 8 | M10: 45930 | W10: Rajesh | Y10: Mike Horihan

Sheet GGO 8.0.0 Sprint 3-Defect
A1: S.No | B1: Sprint # | C1: Story/Defect ID | D1: Parent Story | E1: Developer | F1: Issue Type | G1: Issue Description | H1: Priority | I1: Defect Source | J1: Type | K1: Status | L1: Root Cause Category | M1: Found By | N1: Comment | O1: RCA Comment
B2: GGO 8.0.0 Sprint 3 | C2: GGO-15030 | D2: GGO-14980 | E2: Sathiya/Rajesh/Saranya | F2: Defect | G2: Create sales page UI impact | H2: Significant | I2: Manual | J2: Internal | K2: Closed | L2: Design | M2: Sathiya

Sheet GGO 8.0.0 Sprint 2-Status
A1: S.No | B1: Application Name | C1: Sprint Start Date | D1: Sprint End Date | E1: Sprint | F1: Developer | G1: Story ID/Defect ID | H1: Description | I1: Status | J1: Estimated(sp) | K1: Actual(sp) | L1: Actual Hours Worklog | M1: Dev Start Date | N1: Dev End Date | O1: Unit testing | P1: Peer Tested By | Q1: Peer Tested Defects, if any | R1: Peer Reviewed By | S1: Peer Code Review Comments, if any | T1: PR Number/Link | U1: PR Created Date | V1: PR Approved Date | W1: Reviewer 1 | X1: Code Review Comments, if any | Y1: Reviewer 2 | Z1: Approved Date | AA1: Code Review Comments, if any2 | AB1: Internal PO -POV Comments | AC1: Client PO -POV Comments | AD1: Comments
A2: 1 | B2: GGO Web | C2: 45904 | D2: 45918 | E2: GGO 8.0.0 Sprint 2 | F2: Saranya | G2: GGO-14854 | H2: View Supporter Page Filter - Staff and Fundraisers* | I2: Completed | J2: 1 | K2: 2 | M2: 45905 | O2: Saranya | P2: Priya | R2: Sathya | T2: https://greatergiving.visualstudio.com/Greater%20Giving/_git/GGO/pullrequest/8810 | U2: 45905 | V2: 45905 | W2: Rajesh | Y2: Mike Horihan | Z2: 45906 | AD2: Testing completed in the Dev env. 4:30 PM 9/4/2025
A3: 2 | B3: GGO Web | C3: 45904 | D3: 45918 | E3: GGO 8.0.0 Sprint 2 | F3: Sathya / Praveen | G3: GGO-14875 | H3: Create Item Page | I3: Completed | J3: 5 | K3: 5 | M3: 45905 | O3: Sathiya | P3: Priya | R3: Saranya | T3: https://dev.azure.com/greatergiving/Greater%20Giving/_git/GGO/pullrequest/8744 | U3: 45916 | V3: 45916 | W3: Rajesh | Y3: Mike Wall | Z3: 45916 | AD3: Testing completed in the TST env.
A4: 3 | B4: GGO Web | C4: 45904 | D4: 45918 | E4: GGO 8.0.0 Sprint 2 | F4: Saranya | G4: GGO-14979 | H4: View Supporter Page Filter - Supporters | I4: Completed | J4: 3 | K4: 3 | M4: 45905 | O4: Saranya | P4: Priya | R4: Sathya | T4: https://greatergiving.visualstudio.com/Greater%20Giving/_git/GGO/pullrequest/8822 | U4: 45910 | V4: 45910 | W4: Rajesh | Y4: Mike Horihan | Z4: 45911 | AD4: Testing completed in the TST env.
A5: 4 | B5: GGO Web | C5: 45904 | D5: 45918 | E5: GGO 8.0.0 Sprint 2 | F5: Rajesh/Saranya | G5: GGO-14980 | H5: View Supporter Page Filter - Save Search | I5: Being Developed | J5: 3 | M5: 45905 | AD5: Due to complications involving multiple user controls on the filter page, some functions within the new user control are not triggering as expected. Additionally, new controls were added which require further integration and testing to ensure smooth functionality.
A6: 5 | B6: GGO Web | C6: 45904 | D6: 45918 | E6: GGO 8.0.0 Sprint 2 | F6: Rajesh | G6: GGO-14984 | H6: Content Security Policy Update for Pendo * | I6: Completed | J6: 2 | K6: 2 | M6: 45905 | O6: Rajesh | P6: Priya | T6: https://greatergiving.visualstudio.com/Greater%20Giving/_git/GGO/pullrequest/8820 | U6: 45909 | V6: 45909 | Y6: Mike Horihan | Z6: 45909 | AD6: Testing completed in the TST env.
A7: 6 | B7: GGO Web | C7: 45904 | D7: 45918 | E7: GGO 8.0.0 Sprint 2 | F7: Priya-QA | G7: GGO-15009 | H7: sub field creation links to classic page | I7: Completed | J7: NA | K7: NA | L7: NA | M7: NA | N7: NA | O7: NA | P7: NA | Q7: NA | R7: NA | S7: NA | T7: NA | U7: NA | V7: NA | W7: NA | X7: NA | Y7: NA | Z7: NA | AA7: NA | AB7: NA | AC7: NA

Sheet GGO 8.0.0 Sprint 2-Defect
A1: S.No | B1: Sprint # | C1: Story/Defect ID | D1: Parent Story | E1: Developer | F1: Issue Type | G1: Issue Description | H1: Priority | I1: Defect Source | J1: Type | K1: Status | L1: Root Cause Category | M1: Found By | N1: Comment | O1: RCA Comment
B2: GGO 8.0.0 Sprint 2 | C2: GGO-15009 | D2: GGO-14875 | E2: Sathiya | F2: Defect | G2: sub field creation links to classic page | H2: Significant | I2: Manual | J2: Internal | K2: Closed | L2: Enhancements | M2: Conor | N2: We found the same kind of issue in the dev env while testing the create item page. Onsite QA found the same issue while editing the items in the TST env

Sheet GGO 8.0.0 Sprint 1-Status
A1: S.No | B1: Application Name | C1: Sprint Start Date | D1: Sprint End Date | E1: Sprint | F1: Developer | G1: Story ID/Defect ID | H1: Description | I1: Status | J1: Estimated(sp) | K1: Actual(sp) | L1: Actual Hours Worklog | M1: Dev Start Date | N1: Dev End Date | O1: Unit testing | P1: Peer Tested By | Q1: Peer Tested Defects, if any | R1: Peer Reviewed By | S1: Peer Code Review Comments, if any | T1: PR Number/Link | U1: PR Created Date | V1: PR Approved Date | W1: Reviewer 1 | X1: Code Review Comments, if any | Y1: Reviewer 2 | Z1: Approved Date | AA1: Code Review Comments, if any2 | AB1: Internal PO -POV Comments | AC1: Client PO -POV Comments | AD1: Comments
A2: 1 | B2: GGO Web | C2: 45890 | D2: 45904 | E2: GGO 8.0.0 Sprint 1 | F2: Praveen / Sathiya | G2: GGO-14858 | H2: Retain the overall design of the application | I2: Completed | J2: 2 | K2: 2 | M2: 45888 | N2: 45889 | O2: Praveen/Sathiya | P2: Priya | R2: Saranya | T2: https://dev.azure.com/greatergiving/Greater%20Giving/_git/GGO/pullrequest/8756 | U2: 45889 | V2: 45889 | W2: Prabhu | Y2: Michael Wall | Z2: 45889 | AD2: It is stretched story development and testing completed by offshore , onsite QA testing not yet completed.[22-Aug-25]. Testing completed
A3: 2 | B3: GGO Web | C3: 45890 | D3: 45904 | E3: GGO 8.0.0 Sprint 1 | F3: Rajesh/Saranya/Sathya | G3: GGO-14863 | H3: OneTrust Privacy Center in profile | I3: Completed | J3: 2 | K3: 2 | O3: Rajesh | P3: Priya | R3: Saranya | T3: https://greatergiving.visualstudio.com/Greater%20Giving/_git/GGO/pullrequest/8779 | U3: 45896 | V3: 45896 | W3: Sathiya | Y3: Michael Wall | Z3: 45896 | AD3: Testing completed in the TST env,
A4: 3 | B4: GGO Web | C4: 45890 | D4: 45904 | E4: GGO 8.0.0 Sprint 1 | F4: Sathya / Praveen | G4: GGO-14852 | H4: View Supporter Page Filter - Bidders & Attendees | I4: Completed | J4: 3 | K4: 3 | O4: Sathya/Praveen | P4: Priya | R4: Saranya | T4: https://greatergiving.visualstudio.com/Greater%20Giving/_git/GGO/pullrequest/8786 | U4: 45897 | V4: 45899 | W4: Rajesh | Y4: Mccarty, Joseph | Z4: 45899 | AD4: Testing completed in the TST env,
A5: 4 | B5: GGO Web | C5: 45890 | D5: 45904 | E5: GGO 8.0.0 Sprint 1 | F5: Rajesh / Saranya / Sathya | G5: GGO-14853 | H5: View Supporter Page Filter - Sponsors and Donors | I5: Completed | J5: 3 | K5: 3 | O5: Sathya/Praveen | P5: Priya | R5: Saranya | T5: https://greatergiving.visualstudio.com/Greater%20Giving/_git/GGO/pullrequest/8786 | U5: 45897 | V5: 45899 | W5: Rajesh | Y5: Mccarty, Joseph | Z5: 45899 | AD5: Testing completed in the TST env,
A6: 5 | B6: GGO Web | C6: 45890 | D6: 45904 | E6: GGO 8.0.0 Sprint 1 - [Stretch] | F6: Saranya | G6: GGO-14854 | H6: View Supporter Page Filter - Staff and Fundraisers* | I6: Being Developed | J6: 3 | K6: 2 | O6: Saranya | P6: Priya | R6: Sathya | AD6: Testing completed in the Dev env. 4:30 PM 9/4/2025
A7: 6 | B7: GGO Web | C7: 45890 | D7: 45904 | E7: GGO 8.0.0 Sprint 1 - [Stretch] | F7: Rajesh | G7: GGO-14971 | H7: Pendo Content Security Policy * | I7: Completed | J7: 2 | K7: 2 | O7: Rajesh | P7: Priya | R7: Saranya | T7: https://greatergiving.visualstudio.com/Greater%20Giving/_git/GGO/pullrequest/8799 | U7: 45903 | V7: NA | W7: NA | Y7: Michael Wall | Z7: 45903 | AD7: Testing completed by Client. Offshore QA doesnt have access to do the testing for this
A8: 7 | B8: GGO Web | C8: 45890 | D8: 45904 | E8: GGO 8.0.0 Sprint 1 | F8: Rajesh | G8: GGO-14972 | H8: org mail templates error | I8: Completed | J8: NA | K8: NA | T8: https://greatergiving.visualstudio.com/Greater%20Giving/_git/GGO/pullrequest/8773 | U8: NA | V8: NA | W8: NA | Y8: Michael Wall | Z8: 45896 | AD8: Carry forward CRT bug
A9: 8 | B9: GGO Web | C9: 45890 | D9: 45904 | E9: GGO 8.0.0 Sprint 1 | F9: Rajesh | G9: GGO-14970 | H9: jquery update issues | I9: Completed | J9: NA | K9: NA | M9: 45902 | N9: 45902 | Y9: Michael Wall | Z9: 45895 | AD9: Carry forward CRT bug
A10: 9 | B10: GGO Web | C10: 45890 | D10: 45904 | E10: GGO 8.0.0 Sprint 1 | F10: Sathya / Praveen | G10: GGO-14875 | H10: Create Item Page | I10: Being Developed | J10: 5 | AD10: Onsite Dev-Mike Wall picked this story earlier did some basic changes due to design difficulties handovered the story to offshore on 1-sep-25
A11: 10 | B11: GGO Web | C11: 45890 | D11: 45904 | E11: GGO 8.0.0 Sprint 1 | F11: Priya-QA | G11: GGO-14981 | H11: Date Picker Positioning Breaks After Scrolling the Page | I11: Completed | J11: NA | K11: NA | T11: https://greatergiving.visualstudio.com/Greater%20Giving/_git/GGO/pullrequest/8791 | U11: 45902 | V11: 45903 | W11: Rajesh | Y11: Michael Wall | Z11: 45903 | AD11: Carry forward CRT bug

Sheet GGO 8.0.0 Sprint 1-Defect
A1: S.No | B1: Sprint # | C1: Story/Defect ID | D1: Parent Story | E1: Developer | F1: Issue Type | G1: Issue Description | H1: Priority | I1: Defect Source | J1: Type | K1: Status | L1: Root Cause Category | M1: Found By | N1: Comment | O1: RCA Comment
B2: GGO 8.0.0 Sprint 1 | C2: GGO-14981 | D2: GGO-14852 | E2: Sathiya | F2: Defect | G2: Date Picker Positioning Breaks After Scrolling the Page | H2: Significant | I2: Manual | J2: Internal | K2: Closed | L2: Enhancements | M2: Priya

Sheet GGO 7.25.0 Sprint 4-Status
A1: S.No | B1: Application Name | C1: Sprint Start Date | D1: Sprint End Date | E1: Sprint | F1: Developer | G1: Story ID/Defect ID | H1: Description | I1: Status | J1: Estimated(sp) | K1: Actual(sp) | L1: Actual Hours Worklog | M1: Dev Start Date | N1: Dev End Date | O1: Unit testing | P1: Peer Tested By | Q1: Peer Tested Defects, if any | R1: Peer Reviewed By | S1: Peer Code Review Comments, if any | T1: PR Number/Link | U1: PR Created Date | V1: PR Approved Date | W1: Reviewer 1 | X1: Code Review Comments, if any | Y1: Reviewer 2 | Z1: Approved Date | AA1: Code Review Comments, if any2 | AB1: Internal PO -POV Comments | AC1: Client PO -POV Comments | AD1: Comments
A2: 1 | B2: GGO Web | C2: 45876 | D2: 45890 | E2: GGO 7.25.0 Sprint 4 | F2: Rajesh/Sathya/Saranya | G2: GGO-14851 | H2: Filter pages - Sales & Payments (with Payments on) and Supporters | I2: Completed | J2: 5 | K2: 5 | L2: 52.25 | M2: 45881 | N2: 45884 | O2: Sathiya | P2: Priya | R2: Saranya | T2: https://greatergiving.visualstudio.com/Greater%20Giving/_git/GGO/pullrequest/8742 | U2: 45884 | V2: 45884 | W2: Rajesh | Y2: Michael Wall | Z2: 45884 | AD2: Testing completed in the TST env.
A3: 2 | B3: GGO Web | C3: 45876 | D3: 45890 | E3: GGO 7.25.0 Sprint 4 | F3: Rajesh/Sathya/Saranya | G3: GGO-14712 | H3: View Supporter Filter and Sales & Payments (with Sales on) page | I3: Completed | J3: 5 | K3: 5 | L3: 54.75 | M3: 45876 | N3: 45880 | O3: Sathiya | P3: Priya | R3: Saranya | T3: https://greatergiving.visualstudio.com/Greater%20Giving/_git/GGO/pullrequest/8725 | U3: 45880 | V3: 45882 | W3: Rajesh | Y3: Michael Wall | Z3: 45882 | AD3: Testing completed in the TST env.
A4: 3 | B4: GGO Web | C4: 45876 | D4: 45890 | E4: GGO 7.25.0 Sprint 4 | F4: Rajesh/Saranya | G4: GGO-14863 | H4: OneTrust Privacy Center in profile* | I4: Being Developed | J4: 3 | L4: 37.75 | M4: 45887
A5: 4 | B5: GGO Web | C5: 45876 | D5: 45890 | E5: GGO 7.25.0 Sprint 4 | F5: Praveen/Sathiya | G5: GGO-14858 | H5: Retain the overall design of the application* | I5: Ready for testing | J5: 3 | L5: 21 | M5: 45888 | N5: 45889 | O5: Praveen/Sathiya | P5: Priya | R5: Saranya | T5: https://dev.azure.com/greatergiving/Greater%20Giving/_git/GGO/pullrequest/8756 | U5: 45889 | V5: 45889 | W5: Prabhu | Y5: Michael Wall | Z5: 45889 | AD5: It is stretched story development and testing completed by offshore , onsite QA testing not yet completed.[22-Aug-25]
A6: 5 | B6: GGO Web | C6: 45876 | D6: 45890 | E6: GGO 7.25.0 Sprint 4 | F6: Priya-QA | G6: GGO-14954 | H6: Filter Not Reset When Sales Is Disabled | I6: Completed | J6: NA | K6: NA | L6: 9.5 | M6: 45882 | N6: 45882 | T6: https://greatergiving.visualstudio.com/Greater%20Giving/_git/GGO/pullrequest/8738 | U6: 45882 | V6: 45883 | W6: Rajesh | Y6: Michael Wall | Z6: 45883 | AD6: Testing completed in the TST env.
A7: 6 | B7: GGO Web | C7: 45876 | D7: 45890 | E7: GGO 7.25.0 Sprint 4 | F7: Priya-QA | G7: GGO-14961 | H7: Supporter Records Not Filtering Correctly When "Has Payment" is Toggled On | I7: Completed | J7: NA | K7: NA | L7: 1 | M7: 45882 | N7: 45882 | T7: https://greatergiving.visualstudio.com/Greater%20Giving/_git/GGO/pullrequest/8738 | U7: 45882 | V7: 45883 | W7: Rajesh | Y7: Michael Wall | Z7: 45883 | AD7: Testing completed in the TST env.
A8: 7 | B8: GGO Web | C8: 45876 | D8: 45890 | E8: GGO 7.25.0 Sprint 4 | F8: Priya-QA | G8: GGO-14691 | H8: View Packages page | I8: Completed | J8: 1 | K8: 1 | L8: 2.25 | M8: NA | N8: NA | AD8: Testing completed in the TST env.
A9: 8 | B9: GGO Web | C9: 45876 | D9: 45890 | E9: GGO 7.25.0 Sprint 4 | F9: Priya-QA | G9: GGO-14689 | H9: View Items page | I9: Completed | J9: 1 | K9: 1 | L9: 10 | M9: NA | N9: NA | T9: NA | U9: NA | V9: NA | W9: NA | Y9: NA | Z9: NA | AD9: Testing completed in the TST env.
A10: 9 | B10: GGO Web | C10: 45876 | D10: 45890 | E10: GGO 7.25.0 Sprint 4 | F10: Priya-QA | G10: GGO-14962 | H10: Old Icon Displayed for "Type" in View Packages Page | I10: Completed | J10: NA | K10: NA | L10: 1 | M10: NA | N10: NA | T10: NA | U10: NA | V10: NA | W10: NA | Y10: NA | Z10: NA | AD10: Testing completed in the TST env.
A11: 10 | B11: GGO Web | C11: 45876 | D11: 45890 | E11: GGO 7.25.0 Sprint 4 | F11: Priya-QA | G11: GGO-14927 | H11: Macroscope - High - Microsoft.VSSDK.BuildTools:15.8.3252 | I11: Completed | J11: 1 | K11: 1 | L11: 2 | N11: NA | T11: NA | U11: NA | V11: NA | W11: NA | Y11: NA | Z11: NA | AD11: Testing completed in the TST env.
A12: 11 | B12: GGO Web | C12: 45876 | D12: 45890 | E12: GGO 7.25.0 Sprint 4 | F12: Priya-QA | G12: GGO-14955 | H12: MacroScope - Medium - BDSA-2022-2259 - System.Security.Cryptography.Xml/4.5.0 | I12: Completed | J12: 1 | K12: 1 | L12: 2 | M12: NA | N12: NA | T12: NA | U12: NA | V12: NA | W12: NA | Y12: NA | Z12: NA | AD12: Testing completed in the TST env.

Sheet GGO 7.25.0 Sprint 4-Defect
A1: S.No | B1: Sprint # | C1: Story/Defect ID | D1: Parent Story | E1: Developer | F1: Issue Type | G1: Issue Description | H1: Priority | I1: Defect Source | J1: Type | K1: Status | L1: Root Cause Category | M1: Found By | N1: Comment | O1: RCA Comment
B2: GGO 7.25.0 Sprint 4 | C2: GGO-14954 | D2: GGO-14712 | E2: Sathiya/Rajesh/Saranya | F2: Defect | G2: Filter Not Reset When Sales Is Disabled | H2: Significant | I2: Manual | J2: Internal | K2: Closed | L2: Enhancements | M2: Priya
B3: GGO 7.25.0 Sprint 4 | C3: GGO-14961 | D3: GGO-14851 | E3: Sathiya/Rajesh/Saranya | F3: Defect | G3: Supporter Records Not Filtering Correctly When "Has Payment" is Toggled On | H3: Significant | I3: Manual | J3: Internal | K3: Closed | L3: Enhancements | M3: Priya
B4: GGO 7.25.0 Sprint 4 | C4: GGO-14962 | D4: GGO-14691 | E4: Mike Wall | F4: Defect | G4: Old Icon Displayed for "Type" in View Packages Page | H4: Significant | I4: Manual | J4: Internal | K4: Closed | L4: Enhancements | M4: Priya

Sheet GGO 7.25.0 Sprint 3-Status
A1: S.No | B1: Application Name | C1: Sprint Start Date | D1: Sprint End Date | E1: Sprint | F1: Developer | G1: Story ID/Defect ID | H1: Description | I1: Status | J1: Estimated(sp) | K1: Actual(sp) | L1: Actual Hours Worklog | M1: Dev Start Date | N1: Dev End Date | O1: Unit testing | P1: Peer Tested By | Q1: Peer Tested Defects, if any | R1: Peer Reviewed By | S1: Peer Code Review Comments, if any | T1: PR Number/Link | U1: PR Created Date | V1: PR Approved Date | W1: Reviewer 1 | X1: Code Review Comments, if any | Y1: Reviewer 2 | Z1: Approved Date | AA1: Code Review Comments, if any2 | AB1: Internal PO -POV Comments | AC1: Client PO -POV Comments | AD1: Comments
A2: 1 | B2: GGO Web | C2: 45862 | D2: 45876 | E2: GGO 7.25.0 Sprint 3 | F2: Rajesh/Sathya/Saranya | G2: GGO-14802 | H2: GGO Reskin - Implement the View Supporter common controls | I2: Completed | J2: 3 | K2: 3 | M2: 45852 | N2: 45866 | P2: Priya | R2: Sathya | T2: https://greatergiving.visualstudio.com/Greater%20Giving/_git/GGO/pullrequest/8677 | U2: 45861 | V2: 45861 | W2: Rajesh | Y2: Michael Wall | Z2: 45861 | AD2: 28 July 2025 at 09:13 Verified in the TST env.
A3: 2 | B3: GGO Web | C3: 45862 | D3: 45876 | E3: GGO 7.25.0 Sprint 3 | F3: Rajesh | G3: GGO-14724 | H3: Implement OneTrust | I3: Completed | J3: 2 | K3: 2 | M3: 45852 | N3: 45866 | T3: https://greatergiving.visualstudio.com/Greater%20Giving/_git/GGO/pullrequest/8667 | U3: 45859 | V3: 45859 | W3: Rajesh | Y3: Michael Wall | Z3: 45860 | AD3: Verified in the TST env. Working well
A4: 3 | B4: GGO Web | C4: 45862 | D4: 45876 | E4: GGO 7.25.0 Sprint 3 | F4: Rajesh/Sathya/Saranya | G4: GGO-14840 | H4: Pop-up Dialogs in Supporters page | I4: Completed | J4: 5 | K4: 5 | M4: 45863 | T4: https://greatergiving.visualstudio.com/Greater%20Giving/_git/GGO/pullrequest/8706 | U4: 45874 | V4: 45874 | W4: Rajesh | Y4: Michael Wall | Z4: 45874
A5: 4 | B5: GGO Web | C5: 45862 | D5: 45876 | E5: GGO 7.25.0 Sprint 3 | F5: Rajesh/Sathya/Saranya | G5: GGO-14855 | H5: when saved search is selected no new search can be done | I5: Completed | M5: 45862 | N5: 45866 | T5: https://greatergiving.visualstudio.com/Greater%20Giving/_git/GGO/pullrequest/8691 | U5: 45863 | V5: 45863 | W5: Rajesh | Y5: Michael Wall | Z5: 45863 | AD5: 28 July 2025 at 09:13 Except for the 1st scenario, Everything is working as expected. As discussed with Jennifer, greying out the other action dropdowns except import will be fixed in the Popup story. Hence, closing the defect.
A6: 5 | B6: GGO Web | C6: 45862 | D6: 45876 | E6: GGO 7.25.0 Sprint 3 | F6: Rajesh/Sathya/Saranya | G6: GGO-14851 | H6: Filter pages - Sales & Payments (with Payments on) and Supporters | I6: Being Developed | J6: 5 | AD6: The design challenges in this story prevent us from reusing existing user controls in every context.
A7: 6 | B7: GGO Web | C7: 45862 | D7: 45876 | E7: GGO 7.25.0 Sprint 3 | F7: Rajesh/Sathya/Saranya | G7: GGO-14712 | H7: View Supporter Filter and Sales & Payments (with Sales on) page | I7: Being Developed | J7: 5 | AD7: We didn’t work on this story due to story GGO-14840 taking more time than anticipated due to its complexity
A8: 7 | B8: GGO Web | C8: 45862 | D8: 45876 | E8: GGO 7.25.0 Sprint 3 | F8: Rajesh | G8: GGO-14794 | H8: GGO Reskin - Implement the View Catalog page | I8: Completed | J8: 3 | K8: 3 | T8: https://greatergiving.visualstudio.com/Greater%20Giving/_git/GGO/pullrequest/8687 | U8: 45863 | V8: 45870 | Y8: Rajesh | Z8: 45870 | AD8: 4 August 2025 at 09:14 Verified in the TST env. Working well
A9: 8 | B9: GGO Web | C9: 45862 | D9: 45876 | E9: GGO 7.25.0 Sprint 3 | F9: Priya-QA | G9: GGO-14900 | H9: Update Manage Columns in Catalog Grid | I9: Completed | J9: 1 | K9: 1 | O9: NA | P9: NA | Q9: NA | R9: NA | S9: NA | T9: NA | U9: NA | V9: NA | W9: NA | X9: NA | Y9: NA | Z9: NA | AA9: NA | AB9: NA | AC9: NA | AD9: Verified in the TST env. Working well
A10: 9 | B10: GGO Web | C10: 45862 | D10: 45876 | E10: GGO 7.25.0 Sprint 3 | F10: Priya-QA | G10: GGO-14906 | H10: checkbox Alignment Issues and Missed to implement Bottom Border Opacity and Title panel Aligns | I10: Completed | O10: NA | P10: NA | Q10: NA | R10: NA | S10: NA | T10: NA | U10: NA | V10: NA | W10: NA | X10: NA | Y10: NA | Z10: NA | AA10: NA | AB10: NA | AC10: NA | AD10: Verified in the TST env. Working well

Sheet GGO 7.25.0 Sprint 2-Status
A1: S.No | B1: Application Name | C1: Sprint Start Date | D1: Sprint End Date | E1: Sprint | F1: Developer | G1: Story ID/Defect ID | H1: Description | I1: Status | J1: Estimated(sp) | K1: Actual(sp) | L1: Actual Hours Worklog | M1: Dev Start Date | N1: Dev End Date | O1: Unit testing | P1: Peer Tested By | Q1: Peer Tested Defects, if any | R1: Peer Reviewed By | S1: Peer Code Review Comments, if any | T1: PR Number/Link | U1: PR Created Date | V1: PR Approved Date | W1: Reviewer 1 | X1: Code Review Comments, if any | Y1: Reviewer 2 | Z1: Approved Date | AA1: Code Review Comments, if any2 | AB1: Internal PO -POV Comments | AC1: Client PO -POV Comments | AD1: Comments
A2: 1 | B2: GGO Web | C2: 45848 | D2: 45862 | E2: GGO 7.25.0 Sprint 2 | F2: Rajesh/Sathya/Saranya | G2: GGO-14687 | H2: GGO Reskin - Implement the View Supporter page | I2: Completed | J2: 3 | K2: 3 | M2: 45849 | N2: 45852 | P2: Priya | T2: https://greatergiving.visualstudio.com/Greater%20Giving/_git/GGO/pullrequest/8649 | U2: 45854 | V2: 45854 | W2: Rajesh | Y2: Michael Wall | Z2: 45854 | AD2: Testing is still in progress in the TST env 8:52 PM 7/16/2025. Testing completed in the TST env. 7/21/2025
A3: 2 | B3: GGO Web | C3: 45848 | D3: 45862 | E3: GGO 7.25.0 Sprint 2 | F3: Rajesh/Sathya/Saranya | G3: GGO-14802 | H3: GGO Reskin - Implement the View Supporter common controls | I3: Being Developed | J3: 5 | M3: 45852 | N3: 45861 | P3: Priya | R3: Sathya | T3: https://greatergiving.visualstudio.com/Greater%20Giving/_git/GGO/pullrequest/8677 | U3: 45861 | V3: 45861 | W3: Rajesh | Y3: Michael Wall | Z3: 45861 | AD3: Did Testing in TST Env. Found a bug.Created a defect under this story
A4: 3 | B4: GGO Web | C4: 45848 | D4: 45862 | E4: GGO 7.25.0 Sprint 2 | F4: Rajesh | G4: GGO-14724 | H4: Implement OneTrust | I4: Being Developed | J4: 5 | M4: 45852 | N4: 45862 | T4: https://greatergiving.visualstudio.com/Greater%20Giving/_git/GGO/pullrequest/8667 | U4: 45859 | V4: 45859 | W4: Rajesh | Y4: Michael Wall | Z4: 45860 | AD4: Development part is completed. OneTrust website is not yet available in the TST environment
A5: 4 | B5: GGO Web | C5: 45848 | D5: 45862 | E5: GGO 7.25.0 Sprint 2 | F5: Rajesh/Sathya/Saranya | G5: GGO-14688 | H5: GGO Reskin - Implement the Edit Supporter details page - Top Section | I5: Being Developed | J5: 3 | AD5: Can't able to complete the task as planned due to changes in the new layout design, which introduced additional controls and complexity. Also, another story GGO-14687 required more time than anticipated, which impacted the overall timeline."
A6: 5 | B6: GGO Web | C6: 45848 | D6: 45862 | E6: GGO 7.25.0 Sprint 2 | F6: Priya-QA | G6: GGO-14831 | H6: MacroScope - High - Microsoft.Owin.Security.OpenIdConnect:4.2.2 | I6: Completed | J6: 1 | K6: 1 | O6: NA | P6: NA | Q6: NA | R6: NA | S6: NA | T6: NA | U6: NA | V6: NA | W6: NA | X6: NA | Y6: NA | Z6: NA | AA6: NA | AB6: NA | AC6: NA | AD6: Did one round of Regression Testing in the TST env.
A7: 6 | B7: GGO Web | C7: 45848 | D7: 45862 | E7: GGO 7.25.0 Sprint 2 | F7: Priya-QA | G7: GGO-14835 | H7: MacroScope - High - BDSA-2024-7402 - jQuery.UI.Combined/1.12.1 | I7: Completed | J7: 1 | K7: 1 | O7: NA | P7: NA | Q7: NA | R7: NA | S7: NA | T7: NA | U7: NA | V7: NA | W7: NA | X7: NA | Y7: NA | Z7: NA | AA7: NA | AB7: NA | AC7: NA | AD7: Did one round of Regression Testing in the TST env.
A8: 7 | B8: GGO Web | C8: 45848 | D8: 45862 | E8: GGO 7.25.0 Sprint 2 | F8: Priya-QA | G8: GGO-14832 | H8: MacroScope - High - CVE-2021-24112 - System.Drawing.Common | I8: Completed | J8: 1 | K8: 1 | O8: NA | P8: NA | Q8: NA | R8: NA | S8: NA | T8: NA | U8: NA | V8: NA | W8: NA | X8: NA | Y8: NA | Z8: NA | AA8: NA | AB8: NA | AC8: NA | AD8: Did one round of Regression Testing in the TST env.
A9: 8 | B9: GGO Web | C9: 45848 | D9: 45862 | E9: GGO 7.25.0 Sprint 2 | F9: Priya-QA | G9: GGO-14829 | H9: MacroScope - High - Manual HTML Sanitization | I9: Completed | J9: 1 | K9: 1 | O9: NA | P9: NA | Q9: NA | R9: NA | S9: NA | T9: NA | U9: NA | V9: NA | W9: NA | X9: NA | Y9: NA | Z9: NA | AA9: NA | AB9: NA | AC9: NA | AD9: Did one round of Regression Testing in the TST env.
A10: 9 | B10: GGO Web | C10: 45848 | D10: 45862 | E10: GGO 7.25.0 Sprint 2 | F10: Priya-QA | G10: GGO-14837 | H10: MacroScope - High - DomPurify.js Unsanitized HTML | I10: Completed | J10: 1 | K10: 1 | O10: NA | P10: NA | Q10: NA | R10: NA | S10: NA | T10: NA | U10: NA | V10: NA | W10: NA | X10: NA | Y10: NA | Z10: NA | AA10: NA | AB10: NA | AC10: NA | AD10: Did one round of Regression Testing in the TST env.
A11: 9 | B11: GGO Web | C11: 45848 | D11: 45862 | E11: GGO 7.25.0 Sprint 2 | F11: Priya-QA | G11: GGO-14829 | H11: MacroScope - High - Manual HTML Sanitization | I11: Completed | J11: 1 | K11: 1 | O11: NA | P11: NA | Q11: NA | R11: NA | S11: NA | T11: NA | U11: NA | V11: NA | W11: NA | X11: NA | Y11: NA | Z11: NA | AA11: NA | AB11: NA | AC11: NA | AD11: Did one round of Regression Testing in the TST env.

Sheet GGO 7.25.0 Sprint 3-Defect
A1: S.No | B1: Sprint # | C1: Story/Defect ID | D1: Parent Story | E1: Developer | F1: Issue Type | G1: Issue Description | H1: Priority | I1: Defect Source | J1: Type | K1: Status | L1: Root Cause Category | M1: Found By | N1: Comment | O1: RCA Comment
B2: GGO 7.25.0 Sprint 3 | C2: GGO-14906 | D2: GGO-14840 | E2: Sathiya | F2: Defect | G2: checkbox Alignment Issues and Missed to implement Bottom Border Opacity and Title panel Aligns | H2: Significant | I2: Manual | J2: Internal | K2: Closed | L2: Enhancements | M2: Priya

Sheet GGO 7.25.0 Sprint 2-Defect
A1: S.No | B1: Sprint # | C1: Story/Defect ID | D1: Parent Story | E1: Developer | F1: Issue Type | G1: Issue Description | H1: Priority | I1: Defect Source | J1: Type | K1: Status | L1: Root Cause Category | M1: Found By | N1: Comment | O1: RCA Comment
B2: GGO 7.25.0 Sprint 2 | C2: GGO-14850 | D2: GGO-14802 | E2: Rajesh/Saranya/Sathiya | F2: Defect | G2: Display warning popup when only one supporter is selected for household creation | H2: Minor | I2: Manual | J2: Internal | K2: Closed | L2: Development | M2: Saranya | N2: Developer missed handling this negative scenario. | O2: Moving forward, Developers will also do proper Unit testing before pushing this to TST env
B3: GGO 7.25.0 Sprint 2 | C3: GGO-14855 | D3: GGO-14802 | E3: Rajesh/Saranya/Sathiya | F3: Defect | G3: Dropdown under Actions is disabled when searching for supporters and no records are found, and also few UI Alignment issues | H3: Significant | I3: Manual | J3: Internal | K3: Inprogress | L3: Development | M3: Priya | N3: Developer missed handling this negative scenario. | O3: Moving forward, Developers will also do proper Unit testing before pushing this to TST env
B4: GGO 7.25.0 Sprint 2 | C4: GGO-14856 | D4: GGO-14802 | E4: Rajesh/Saranya/Sathiya | F4: Defect | G4: when saved search is selected no new search can be done | H4: Significant | I4: Manual | J4: Internal | K4: Rejected | L4: Development | M4: Conor | N4: Developer missed handling this negative scenario. | O4: Moving forward, Developers will also do proper Unit testing before pushing this to TST env

Sheet GGO 7.25.0 Sprint 1-Status
A1: S.No | B1: Application Name | C1: Sprint Start Date | D1: Sprint End Date | E1: Sprint | F1: Developer | G1: Story ID/Defect ID | H1: Description | I1: Status | J1: Estimated(sp) | K1: Actual(sp) | L1: Actual Hours Worklog | M1: Unit testing | N1: Peer Tested By | O1: Peer Tested Defects, if any | P1: Peer Reviewed By | Q1: Peer Code Review Comments, if any | R1: PR Number/Link | S1: PR Created Date | T1: PR Approved Date | U1: Reviewer 1 | V1: Code Review Comments, if any | W1: Reviewer 2 | X1: Approved Date | Y1: Code Review Comments, if any2 | Z1: Internal PO -POV Comments | AA1: Client PO -POV Comments | AB1: Comments
A2: 1 | B2: GGO Web | C2: 45834 | D2: 45848 | E2: GGO 7.25.0 Sprint 1 | F2: Saranya | G2: GGO-14799 | H2: API update for next gen section times | I2: Completed | J2: 2 | K2: 2 | M2: Saranya | N2: Priya | P2: Rajesh | R2: https://greatergiving.visualstudio.com/Greater%20Giving/_git/GGO/pullrequest/8619 | S2: 45841 | T2: 45841 | U2: Rajesh | W2: Michael Wall | X2: 45841 | AB2: 3 July 2025 at 09:11 Verified in the TST env.Working fine
A3: 2 | B3: GGO Web | C3: 45834 | D3: 45848 | E3: GGO 7.25.0 Sprint 1 | F3: Sathiya | G3: GGO-14699 | H3: GGO Reskin - Update for the Project Home for Total sales grid | I3: Completed | J3: 3 | K3: 3 | M3: Sathiya | N3: Saranya | P3: Saranya | R3: https://dev.azure.com/greatergiving/Greater%20Giving/_git/GGO/pullrequest/8606 | S3: 45838 | T3: 45839 | U3: Rajesh | W3: Michael Wall | X3: 45839 | AB3: 3 July 2025 at 08:03 Verified in the TST env.
A4: 3 | B4: GGO Web | C4: 45834 | D4: 45848 | E4: GGO 7.25.0 Sprint 1 | F4: Saranya | G4: GGO-14700 | H4: GGO Reskin - Update for the Project Home for the Total Payments grid | I4: Completed | J4: 3 | K4: 3 | M4: Saranya | N4: Sathya | P4: Sathiya | R4: https://dev.azure.com/greatergiving/Greater%20Giving/_git/GGO/pullrequest/8612 | S4: 45839 | T4: 45840 | U4: Rajesh | W4: Michael Wall | X4: 45840 | AB4: 3 July 2025 at 08:06 Verified in the TST env.
A5: 4 | B5: GGO Web | C5: 45834 | D5: 45848 | E5: GGO 7.25.0 Sprint 1 | F5: Rajesh/Sathya/Saranya | G5: GGO-14687 | H5: GGO Reskin - Implement the View Supporter page | I5: Being Developed | J5: 5
A6: 5 | B6: GGO Web | C6: 45834 | D6: 45848 | E6: GGO 7.25.0 Sprint 1 | F6: Rajesh | G6: https://greatergiving.atlassian.net/browse/GGO-14798 | H6: Go Time Script Update | I6: Completed | J6: 2 | K6: 2
A7: 6 | B7: GGO Web | C7: 45834 | D7: 45848 | E7: GGO 7.25.0 Sprint 1 | F7: Rajesh/Sathya/Saranya | G7: GGO-14802 | H7: GGO Reskin - Implement the View Supporter common controls | I7: Being Developed | J7: 5

Sheet GGO 7.24.0 Sprint 4-Status
A1: S.No | B1: Application Name | C1: Sprint Start Date | D1: Sprint End Date | E1: Sprint | F1: Developer | G1: Story ID/Defect ID | H1: Description | I1: Status | J1: Estimated(sp) | K1: Actual(sp) | L1: Actual Hours Worklog | M1: Unit testing | N1: Peer Tested By | O1: Peer Tested Defects, if any | P1: Peer Reviewed By | Q1: Peer Code Review Comments, if any | R1: PR Number/Link | S1: PR Created Date | T1: PR Approved Date | U1: Reviewer 1 | V1: Code Review Comments, if any | W1: Reviewer 2 | X1: Approved Date | Y1: Code Review Comments, if any2 | Z1: Internal PO -POV Comments | AA1: Client PO -POV Comments | AB1: Comments
A2: 1 | B2: GGO Web | C2: 45820 | D2: 45834 | E2: GGO 7.24.0 Sprint 4 | F2: Saranya | G2: GGO-14682 | H2: Reskin update for the User profile | I2: Completed | J2: 5 | K2: 5 | M2: Priya | N2: Priya | O2: NA | R2: NA | AB2: Tested in the Dev and TST env. Few issues found. Testing completed in the TST env.
A3: 2 | B3: GGO Web | C3: 45820 | D3: 45834 | E3: GGO 7.24.0 Sprint 4 | F3: Rajesh/Sathiya/Saranya | G3: GGO-14683 | H3: Reskin update for the Project Home | I3: Completed | J3: 8 | K3: 8 | M3: Saranya/Sathiya/Rajesh | N3: Priya | O3: NA | P3: Rajesh | R3: http://greatergiving.visualstudio.com/Greater%20Giving/_git/GGO/pullrequest/8598 | S3: 45832 | T3: 45833 | U3: Rajesh | W3: Michael Wall | X3: 45833 | AB3: Testing completed in the TST env
A4: 3 | B4: GGO Web | C4: 45820 | D4: 45834 | E4: GGO 7.24.0 Sprint 4 | F4: Saranya/Sathiya | G4: GGO-14763 | H4: UI Issues | I4: Completed | M4: Saranya/Priya | N4: Sathiya/Priya | O4: NA | P4: Rajesh | R4: https://greatergiving.visualstudio.com/Greater%20Giving/_git/GGO/pullrequest/8581 | S4: 45822 | T4: 45822 | U4: Rajesh | W4: Mike Horihan | X4: 45822 | AB4: Tested in the TST env directly.Still one issues exists 5:25 PM 6/16/2025 Testing completed in the TST env
A5: 4 | B5: GGO Web | C5: 45820 | D5: 45834 | E5: GGO 7.24.0 Sprint 4 | F5: Priya-QA | G5: GGO-14765 | H5: GGO 7.24.0 CRT Release & Regression Testing | I5: Completed | J5: 3 | K5: 3 | M5: NA | N5: NA | O5: NA | P5: NA | Q5: NA | R5: NA | S5: NA | T5: NA | U5: NA | V5: NA | W5: NA | X5: NA | Y5: NA | Z5: NA | AA5: NA | AB5: Testing completed in the CRT env
A6: 5 | B6: GGO Web | C6: 45820 | D6: 45834 | E6: GGO 7.24.0 Sprint 4 | F6: Priya-QA | G6: PAPI-866 | H6: PAPI 7.19.0 CRT Release & Regression Testing | I6: Completed | J6: 3 | K6: 3 | M6: NA | N6: NA | O6: NA | P6: NA | Q6: NA | R6: NA | S6: NA | T6: NA | U6: NA | V6: NA | W6: NA | X6: NA | Y6: NA | Z6: NA | AA6: NA | AB6: Testing completed in the CRT env
A7: 6 | B7: GGO Web | C7: 45820 | D7: 45834 | E7: GGO 7.24.0 Sprint 4 | F7: Priya-QA | G7: https://greatergiving.atlassian.net/browse/GGO-14732 | H7: Update MFA physical address & other old addresses | I7: Completed | J7: 1 | K7: 1 | M7: NA | N7: NA | O7: NA | R7: NA | S7: NA | T7: NA | U7: NA | V7: NA | W7: NA | X7: NA | Y7: NA | Z7: NA | AA7: NA | AB7: Testing completed in the TST env
A8: 7 | B8: GGO Web | C8: 45820 | D8: 45834 | E8: GGO 7.24.0 Sprint 4 | F8: Saranya | G8: https://greatergiving.atlassian.net/browse/GGO-14766 | H8: Update Pendo Implementation | I8: Completed | J8: 2 | K8: 2 | N8: Priya | O8: NA | AB8: Testing completed in the TST env

Sheet GGO 7.24.0 Sprint 3-Status
A1: S.No | B1: Application Name | C1: Sprint Start Date | D1: Sprint End Date | E1: Sprint | F1: Developer | G1: Story ID/Defect ID | H1: Description | I1: Status | J1: Estimated(sp) | K1: Actual(sp) | L1: Actual Hours Worklog | M1: Unit testing | N1: Peer Tested By | O1: Peer Tested Defects, if any | P1: Peer Reviewed By | Q1: Peer Code Review Comments, if any | R1: PR Number/Link | S1: PR Created Date | T1: PR Approved Date | U1: Reviewer 1 | V1: Code Review Comments, if any | W1: Reviewer 2 | X1: Approved Date | Y1: Code Review Comments, if any2 | Z1: Internal PO -POV Comments | AA1: Client PO -POV Comments | AB1: Comments
A2: 1 | B2: GGO Web | C2: 45806 | D2: 45820 | E2: GGO 7.24.0 Sprint 3 | F2: Rajesh | G2: GGO-14721 | H2: GoTime - NextGen API Update - Changing to a new project doesn't persist on next login if user changed their home organization | I2: Completed | J2: 1 | K2: 1 | R2: https://greatergiving.visualstudio.com/Greater%20Giving/_git/GGO/pullrequest/8562 | S2: 45818 | T2: 45819 | W2: Mike Horihan | X2: 45819 | AB2: Completed
A3: 2 | B3: GGO Web | C3: 45806 | D3: 45820 | E3: GGO 7.24.0 Sprint 3 | F3: Saranya | G3: GGO-14682 | H3: Reskin update for the User profile | I3: Being Developed | J3: 5 | K3: 86 | M3: Saranya | N3: Priya | P3: Sathya | R3: https://greatergiving.visualstudio.com/Greater%20Giving/_git/GGO/pullrequest/8576 | S3: 45820 | T3: 45820 | U3: Rajesh | W3: Michael Wall | X3: 45820 | AB3: Raised bug under this story in the TST env.
A4: 3 | B4: GGO Web | C4: 45806 | D4: 45820 | E4: GGO 7.24.0 Sprint 3 | F4: SathiyaBharathi | G4: GGO-14657 | H4: Reskin for the TopBar | I4: Completed | J4: 3 | K4: 3 | L4: 74 | M4: Sathiya | N4: Priya | O4: UI issues | P4: Rajesh | R4: https://greatergiving.visualstudio.com/Greater%20Giving/_git/GGO/pullrequest/8531 | S4: 45807 | T4: 45818 | U4: Rajesh | W4: Michael Wall | X4: 45818 | AB4: Testing completed in the TST env.
A5: 4 | B5: GGO Web | C5: 45806 | D5: 45820 | E5: GGO 7.24.0 Sprint 3 | F5: Saranya | G5: GGO-14724 | H5: Implement OneTrust | I5: Being Developed | J5: 5 | AB5: We do not have access to OneTrust Privay Policy Center and discussions are still ongoing on the client side. So Client has been moved this stroy to the backlog
A6: 5 | B6: GGO Web | C6: 45806 | D6: 45820 | E6: GGO 7.24.0 Sprint 3 | F6: Rajesh | G6: GGO-14683 | H6: Reskin update for the Project Home | I6: Being Developed | J6: 5 | K6: 18.5 | AB6: Reskin-V2 is a complete overhaul of the existing Master Page. The new layout seamlessly integrates Telerik controls, Bootstrap, and Kendo UI CSS, ensuring an optimized, modern, and adaptive user experience across all devices. As part of this redesign, we need to explore which Telerik control is best suited for the requested layout to achieve the desired functionality and responsiveness. Its taking more time to complete this since UI design work is new to the development team and it is bit challenging too
A7: 6 | B7: GGO Web | C7: 45806 | D7: 45820 | E7: GGO 7.24.0 Sprint 3 | F7: Priya-QA | G7: GGO-14722 | H7: Stop checking expiration dates | I7: Completed | J7: 1 | K7: 1 | L7: 3 | AB7: Did one round of Payment Regression Testing in the TST env
A8: 7 | B8: GGO Web | C8: 45806 | D8: 45820 | E8: GGO 7.24.0 Sprint 3 | F8: Priya-QA | G8: https://greatergiving.atlassian.net/browse/PAPI-864 | H8: Stop checking expiration dates | I8: Completed | J8: 1 | K8: 1 | AB8: Did one round of Payment Regression Testing in the TST env
A9: 8 | B9: GGO Web | C9: 45806 | D9: 45820 | E9: GGO 7.24.0 Sprint 3 | F9: SathiyaBharathi | G9: GGO-14744 | H9: UI Issues | I9: Completed | R9: https://greatergiving.visualstudio.com/Greater%20Giving/_git/GGO/pullrequest/8564 | S9: 45818 | T9: 45818 | U9: Rajesh | W9: Michael Wall | X9: 45818 | AB9: Testing completed in the TST env.
A10: 9 | B10: GGO Web | C10: 45806 | D10: 45820 | E10: GGO 7.24.0 Sprint 3 | F10: Rajesh | G10: GGO-14748 | H10: Update Hamburger Menu matching figma only with 3 lines, remove border | I10: Completed | R10: https://greatergiving.visualstudio.com/Greater%20Giving/_git/GGO/pullrequest/8569 | S10: 45819 | T10: 45819 | U10: Rajesh | W10: Mike Horihan | X10: 45819 | AB10: Testing completed in the TST env.
A11: 10 | B11: GGO Web | C11: 45806 | D11: 45820 | E11: GGO 7.24.0 Sprint 3 | F11: Saranya / Sathiya | G11: GGO-14763 | H11: UI Issues | I11: Being Developed

Sheet GGO 7.24.0 Sprint 3-Defect
A1: S.No | B1: Sprint # | C1: Story/Defect ID | D1: Parent Story | E1: Developer | F1: Issue Type | G1: Issue Description | H1: Priority | I1: Defect Source | J1: Type | K1: Status | L1: Root Cause Category | M1: Found By | N1: Comment | O1: RCA Comment
B2: GGO 7.24.0 Sprint 3 | C2: GGO-14744 | D2: GGO-14657 | E2: Sathiya | F2: Defect | G2: UI Issues | H2: Significant | I2: Manual | J2: Internal | K2: Closed | L2: Enhancements | M2: Priya
B3: GGO 7.24.0 Sprint 3 | C3: GGO-14748 | D3: GGO-14657 | E3: Rajesh | F3: Defect | G3: Update Hamburger Menu matching figma only with 3 lines, remove border | H3: Significant | I3: Manual | J3: Internal | K3: Closed | L3: Enhancements | M3: Rajesh
B4: GGO 7.24.0 Sprint 3 | C4: GGO-14763 | D4: GGO-14682 | E4: Saranya/Sathiya | F4: Defect | G4: UI Issues | H4: Significant | I4: Manual | J4: Internal | K4: Inprogress | L4: Enhancements | M4: Priya

Sheet GGO 7.24.0 Sprint 2-Status
A1: S.No | B1: Application Name | C1: Sprint Start Date | D1: Sprint End Date | E1: Sprint | F1: Developer | G1: Story ID/Defect ID | H1: Description | I1: Status | J1: Estimated(sp) | K1: Actual(sp) | L1: Actual Hours Worklog | M1: Unit testing | N1: Peer Tested By | O1: Peer Tested Defects, if any | P1: Peer Reviewed By | Q1: Peer Code Review Comments, if any | R1: PR Number/Link | S1: PR Created Date | T1: PR Approved Date | U1: Reviewer 1 | V1: Code Review Comments, if any | W1: Reviewer 2 | X1: Approved Date | Y1: Code Review Comments, if any2 | Z1: Internal PO -POV Comments | AA1: Client PO -POV Comments | AB1: Comments
A2: 1 | B2: GGO Web | C2: 45793 | D2: 45806 | E2: GGO 7.24.0 Sprint 2 | F2: Rajesh | G2: GGO-14628 | H2: Print Invoice/Receipts page - Timeout when Omit Sales and payment option selected with both Before and After date options | I2: Being Developed | J2: 3 | L2: 27.5 | AB2: Issue not reproduceable in Dev and TST.Need to check query execution CRT The work around has been provided and ticket has been put on hold for now as it only impacts only one client/org and is of low priority
A3: 2 | B3: GGO Web | C3: 45793 | D3: 45806 | E3: GGO 7.24.0 Sprint 2 | F3: Rajesh/ Sathiya | G3: GGO-14656 | H3: Nav Bar Update | I3: Completed | J3: 5 | K3: 5 | L3: 107 | M3: Sathiya | N3: Priya | P3: Rajesh | R3: https://greatergiving.visualstudio.com/Greater%20Giving/_git/GGO/pullrequest/8525 | S3: 45805 | T3: 45805 | U3: Rajesh | W3: Michael Wall | X3: 45805 | AB3: Testing this in the Dev. In Progress 4:32 PM 5/27/2025
A4: 3 | B4: GGO Web | C4: 45793 | D4: 45806 | E4: GGO 7.24.0 Sprint 2 | F4: Saranya | G4: GGO-14679 | H4: Sales Grid and Details Update for old Convenience Fee assets | I4: Completed | J4: 3 | K4: 3 | L4: 19 | M4: Saranya | N4: Rajesh | P4: Sathya | R4: https://greatergiving.visualstudio.com/Greater%20Giving/_git/GGO/pullrequest/8496 | S4: 45793 | T4: 45797 | U4: Rajesh | W4: Michael Wall | X4: 45797 | AB4: Verified in the TST env successfully. 20 May 2025 at 05:52
A5: 4 | B5: GGO Web | C5: 45793 | D5: 45806 | E5: GGO 7.24.0 Sprint 2 | F5: Saranya | G5: GGO-9991 | H5: "Purchaser Company Name" column causes error when the "Export" link is selected | I5: Completed | J5: 2 | K5: 2 | L5: 11.5 | M5: Saranya | N5: Priya | P5: Rajesh | R5: https://greatergiving.visualstudio.com/Greater%20Giving/_git/GGO/pullrequest/8502 | S5: 45796 | T5: 45797 | U5: Rajesh | W5: Michael Wall | X5: 45796 | AB5: Verified this in the TST env. 21 May 2025 at 09:23
A6: 5 | B6: GGO Web | C6: 45793 | D6: 45806 | E6: GGO 7.24.0 Sprint 2 | F6: Rajesh | G6: GGO-14708 | H6: Remove Pivotal WebApi Project from GGO Repo - Unused project and it is using .Net Core 6 (deprecated version)* | I6: Completed | J6: 2 | K6: 2 | L6: 33 | M6: Rajesh | N6: Priya | P6: Saranya | R6: https://greatergiving.visualstudio.com/Greater%20Giving/_git/GGO/pullrequest/8498 | S6: 45794 | T6: 45796 | U6: Saranya | W6: Michael Wall | X6: 45797 | AB6: Offshore QA Verified this in the TST env. 21 May 2025 at 09:23
A7: 6 | B7: GGO Web | C7: 45793 | D7: 45806 | E7: GGO 7.24.0 Sprint 2 | F7: Mike Wall/Rajesh/Saranya | G7: GGO-14701 | H7: Update Implementation of Flag to Disable Card Types in select Organizations | I7: Completed | J7: 2 | K7: 2 | L7: 23.75 | M7: Saranya | N7: Priya | P7: Rajesh | R7: https://greatergiving.visualstudio.com/Greater%20Giving/_git/GGO/pullrequest/8508 | S7: 45798 | T7: 45798 | U7: Rajesh | W7: Michael Wall | X7: 45798 | AB7: Verified in the TST env. 22 May 2025 at 08:01
A8: 7 | B8: GGO Web | C8: 45793 | D8: 45806 | E8: GGO 7.24.0 Sprint 2 | F8: Mike Wall/Rajesh/Saranya | G8: PAPI-858 | H8: Update Flag to Disable Amex in select Organizations With Pre-Token Check* | I8: Completed | J8: 2 | K8: 2 | L8: 38 | M8: Saranya | N8: Priya | P8: Rajesh | R8: https://greatergiving.visualstudio.com/Greater%20Giving/_git/PAPI/pullrequest/8518 | S8: 45799 | T8: 45800 | U8: Rajesh | W8: Mike H | X8: 45800 | AB8: Verified in the TST env. 22 May 2025 at 08:01
A9: 8 | B9: GGO Web | C9: 45793 | D9: 45806 | E9: GGO 7.24.0 Sprint 2 | F9: Rajesh/Saranya | G9: GGO-14684 | H9: Implement Pendo for GGO | I9: Completed | J9: 5 | K9: 5 | L9: 41.75 | M9: Rajesh | N9: Priya | P9: Saranyas | R9: https://greatergiving.visualstudio.com/Greater%20Giving/_git/GGO/pullrequest/8523 | S9: 45804 | T9: 45806 | U9: Rajesh | V9: 1. Let's add the following to the account metadata Environment: pendoEnvironment, 2. PendoUserID should be prefixed with PendoEnvironment so that UserID is unique across all environments 3. Dev and local should not fall under the same environment label | W9: Mike H | X9: 45806 | AB9: Testing this in the Dev. In Progress 4:32 PM 5/27/2025
A10: 9 | B10: GGO Web | C10: 45793 | D10: 45806 | E10: GGO 7.24.0 Sprint 2 | F10: Saranya | G10: GGO-14313 | H10: HIGH- Usage of Manual HTML Sanitization (XSS) | I10: Completed | J10: 2 | K10: 2 | L10: 20.5 | M10: Saranya | N10: Rajesh | P10: Rajesh | R10: https://greatergiving.visualstudio.com/Greater%20Giving/_git/GGO/pullrequest/8524 | S10: 45804 | T10: 45805 | U10: Rajesh | W10: Michael Wall | X10: 45805

Sheet GGO 7.24.0 Sprint 2-Defect
A1: S.No | B1: Sprint # | C1: Story/Defect ID | D1: Parent Story | E1: Developer | F1: Issue Type | G1: Issue Description | H1: Priority | I1: Defect Source | J1: Type | K1: Status | L1: Root Cause Category | M1: Found By | N1: Comment | O1: RCA Comment

Sheet GGO 7.24.0 Sprint 1-Status
A1: S.No | B1: Application Name | C1: Sprint Start Date | D1: Sprint End Date | E1: Sprint | F1: Developer | G1: Story ID/Defect ID | H1: Description | I1: Status | J1: Estimated(sp) | K1: Actual(sp) | L1: Actual Hours Worklog | M1: Unit testing | N1: Peer Tested By | O1: Peer Tested Defects, if any | P1: Peer Reviewed By | Q1: Peer Code Review Comments, if any | R1: PR Number/Link | S1: PR Created Date | T1: PR Approved Date | U1: Reviewer 1 | V1: Code Review Comments, if any | W1: Reviewer 2 | X1: Approved Date | Y1: Code Review Comments, if any2 | Z1: Internal PO -POV Comments | AA1: Client PO -POV Comments | AB1: Comments
A2: 1 | B2: GGO Web | C2: 45779 | D2: 45792 | E2: GGO 7.24.0 Sprint 1 | F2: Sathiya | G2: GGO-13722 | H2: High - Weak Encryption: Insecure Mode of Operation - Cryptography.cs: 56 | I2: Completed | J2: 1 | K2: 1 | L2: 15 | M2: Sathiya | N2: Priya | R2: https://greatergiving.visualstudio.com/Greater%20Giving/_git/GGO/pullrequest/8458 | S2: 45779 | T2: 45779 | U2: Rajesh | W2: Michael Wall | X2: 45780 | AB2: Verified in the TST env.5 May 2025 at 08:36
A3: 2 | B3: GGO Web | C3: 45779 | D3: 45792 | E3: GGO 7.24.0 Sprint 1 | F3: Sathiya | G3: GGO-13723 | H3: High - Weak Encryption: Insecure Mode of Operation - SymmetricAlgorithmProvider.cs: 35 | I3: Completed | J3: 1 | K3: 1 | L3: 34.5 | M3: Sathiya | N3: Priya | R3: https://greatergiving.visualstudio.com/Greater%20Giving/_git/GGO/pullrequest/8457 | S3: 45779 | T3: 45783 | U3: Rajesh | W3: Michael Wall, Loan Troung | X3: 45784 | AB3: Tested in the TST env 7 May 2025 at 09:20
A4: 3 | B4: GGO Web | C4: 45779 | D4: 45792 | E4: GGO 7.24.0 Sprint 1 | F4: Sathiya | G4: GGO-14618 | H4: MEDIUM - BDSA-2024-4605 - System.IdentityModel.Tokens.Jwt/5.5.0 | I4: Completed | J4: 2 | K4: 2 | L4: 10.25 | M4: Sathiya | N4: Rajesh | R4: https://dev.azure.com/greatergiving/Greater%20Giving/_git/GGO/pullrequest/8474 | S4: 45784 | T4: 45785 | U4: Rajesh | W4: Michael Wall | X4: 45785 | AB4: Tested in the Dev env 8:09 PM 5/7/2025
A5: 4 | B5: GGO Web | C5: 45779 | D5: 45792 | E5: GGO 7.24.0 Sprint 1 | F5: Rajesh/Saranya | G5: PAPI-841 | H5: Fix ValidateAndGetPorticoToken calls to handle when Token or CardBrandTransactionId exists | I5: Completed | J5: 2 | K5: 2 | L5: 18 | M5: Saranya | N5: Rajesh | R5: https://greatergiving.visualstudio.com/Greater%20Giving/_git/PAPI/pullrequest/8477 | S5: 45785 | T5: 45786 | U5: Rajesh | W5: Michael Wall | X5: 45786 | AB5: Did one round of Payment Regression Testing for this story in the TST env.9 May 2025 at 09:19
A6: 5 | B6: GGO Web | C6: 45779 | D6: 45792 | E6: GGO 7.24.0 Sprint 1 | F6: Saranya | G6: GGO-14601 | H6: Project UI accepting Invalid Email address results in error on GGO to SF sync | I6: Completed | J6: 2 | K6: 2 | L6: 35 | M6: Saranya | N6: Priya | R6: https://greatergiving.visualstudio.com/Greater%20Giving/_git/GGO/pullrequest/8463 | S6: 45782 | T6: 45783 | U6: Rajesh | W6: Michael Wall | X6: 45783 | AB6: Test Cycle executed Successfully in the TST env.7 May 2025 at 07:30
A7: 6 | B7: GGO Web | C7: 45779 | D7: 45792 | E7: GGO 7.24.0 Sprint 1 | F7: Saranya | G7: GGO-14652 | H7: Enable Online Bidding - Blocked when users mistakenly generate Display Board | I7: Completed | J7: 5 | K7: 5 | L7: 49.5 | M7: Saranya | N7: Rajesh | R7: https://greatergiving.visualstudio.com/Greater%20Giving/_git/GGO/pullrequest/8476 | S7: 45785 | T7: 45787 | U7: Rajesh | W7: Michael Wall | X7: 45789 | AB7: Tested in the TST env 13 May 2025 at 09:16
A8: 7 | B8: GGO Web | C8: 45779 | D8: 45792 | E8: GGO 7.24.0 Sprint 1[Stretch] | F8: Rajesh | G8: GGO-14678 | H8: Unable to Export Sales* | I8: Completed | J8: 2 | K8: 2 | L8: 19 | M8: Rajesh | N8: Sathiya,Priya | R8: NA | S8: NA | T8: NA | U8: NA | W8: NA | X8: NA
A9: 8 | B9: GGO Web | C9: 45779 | D9: 45792 | E9: GGO 7.24.0 Sprint 1 | F9: Rajesh | G9: GGO-14628 | H9: Print Invoice/Receipts page - Timeout when Omit Sales and payment option selected with both Before and After date options | I9: Being Developed | J9: 3 | K9: 0 | L9: 50.5 | AB9: Issue not reproduceable in Dev and TST.Need to check query execution CRT
A10: 9 | B10: GGO Web | C10: 45779 | D10: 45792 | E10: GGO 7.24.0 Sprint 1 | F10: Rajesh/ Sathiya | G10: GGO-14656 | H10: Nav Bar Update | I10: Being Developed | J10: 3 | K10: 0 | L10: 64.5 | AB10: Reskin-V2 is a complete overhaul of the existing Master Page, focusing on delivering a fully responsive design. The new layout seamlessly integrates Telerik controls, Bootstrap, and Kendo UI CSS, ensuring an optimized, modern, and adaptive user experience across all devices. As part of this redesign, we need to explore which Telerik control is best suited for the requested layout to achieve the desired functionality and responsiveness.
A11: 10 | B11: GGO Web | C11: 45779 | D11: 45792 | E11: GGO 7.24.0 Sprint 1 | F11: Priya-QA | G11: GGO-14619 | H11: MEDIUM - CVE-2024-43485 - System.Text.Json/8.0.4 | I11: Completed | J11: 1 | K11: 1 | L11: 29 | M11: NA | N11: NA | O11: NA | P11: NA | Q11: NA | R11: NA | S11: NA | T11: NA | U11: NA | V11: NA | W11: NA | X11: NA | Y11: NA | Z11: NA | AA11: NA | AB11: Completed Testing in the TST env.

Sheet GGO 7.24.0 Sprint 1-Defect
A1: S.No | B1: Sprint # | C1: Story/Defect ID | D1: Parent Story | E1: Developer | F1: Issue Type | G1: Issue Description | H1: Priority | I1: Defect Source | J1: Type | K1: Status | L1: Root Cause Category | M1: Found By | N1: Comment | O1: RCA Comment
B2: GGO 7.24.0 Sprint 1 | C2: GGO-14678 | D2: GGO-13890 | E2: Rajesh | F2: Defect | G2: Unable to Export Sales* | H2: Major | I2: Manual | J2: External | K2: Closed | L2: Enhancements | M2: End User | N2: This is a production issue. The export sale grid functionality broke due to changes in the SLS report | O2: For every small change implemented, a complete regression testing cycle must be performed to ensure system stability. This includes updating both automation and manual test cases to reflect any new or impacted scenarios. Additionally, thorough verification of all buttons across all application pages must be included, and corresponding scenarios should be documented and maintained in the manual test cases to ensure comprehensive coverage.

Sheet GGO 7.23.0 Sprint 4-Status
A1: S.No | B1: Application Name | C1: Sprint Start Date | D1: Sprint End Date | E1: Sprint | F1: Developer | G1: Story ID/Defect ID | H1: Description | I1: Status | J1: Estimated(sp) | K1: Actual(sp) | L1: Actual Hours Worklog | M1: Unit testing | N1: Peer Tested By | O1: Peer Tested Defects, if any | P1: Peer Reviewed By | Q1: Peer Code Review Comments, if any | R1: PR Number/Link | S1: PR Created Date | T1: PR Approved Date | U1: Reviewer 1 | V1: Code Review Comments, if any | W1: Reviewer 2 | X1: Approved Date | Y1: Code Review Comments, if any2 | Z1: Internal PO -POV Comments | AA1: Client PO -POV Comments | AB1: Comments
A2: 1 | B2: GGO Web | C2: 45764 | D2: 45778 | E2: GGO 7.23.0 Sprint 4 | F2: Saranya | G2: PAPI-840 | H2: Remove the use of StringHashTable | I2: Completed | J2: 3 | K2: 3 | L2: 23.5
A3: 2 | B3: GGO Web | C3: 45764 | D3: 45778 | E3: GGO 7.23.0 Sprint 4 | F3: Rajesh, Saranya | G3: GGO-14644 | H3: Remove Hash table in PAPI - GGO need to pass Bluetooth Swipe data on StoreFront scenario* | I3: Completed | J3: 1 | K3: 1 | L3: 14.5 | AB3: Completed One round of Payment Regression
A4: 3 | B4: GGO Web | C4: 45764 | D4: 45778 | E4: GGO 7.23.0 Sprint 4 | F4: Rajesh | G4: GGO-14614 | H4: HIGH - Microsoft.AspNetCore.Http.Connections.Client:1.0.0 | I4: Completed | J4: 2 | K4: 2 | L4: 19.5 | M4: Rajesh | N4: Sathish,Priya | R4: https://greatergiving.visualstudio.com/Greater%20Giving/_git/GGO/pullrequest/8431 | S4: 45770 | T4: 45770 | U4: Rajesh | W4: Loan Troung | X4: 45770 | AB4: Completed One round of Standard Regression
A5: 4 | B5: GGO Web | C5: 45764 | D5: 45778 | E5: GGO 7.23.0 Sprint 4 | F5: Sathya | G5: GGO-14613 | H5: HIGH - Cross-Site Scripting: DOM - MaintenanceNotification.js: 22 & 25 | I5: Completed | J5: 2 | K5: 2 | L5: 34.5 | M5: Sathiya | N5: Rajesh,Priya | R5: https://greatergiving.visualstudio.com/Greater%20Giving/_git/GGO/pullrequest/8434 | S5: 45771 | T5: 45775 | U5: Rajesh | W5: Michael Wall, Loan Troung | X5: 45775
A6: 5 | B6: GGO Web | C6: 45764 | D6: 45778 | E6: GGO 7.23.0 Sprint 4[Stretch] | F6: Sathya | G6: GGO-14658 | H6: CRITICAL - CVE-2021-43569 - starkbank-ecdsa/1.3.1* | I6: Completed | J6: 1 | K6: 1 | L6: 14 | M6: Sathiya | N6: Rajesh,Priya | R6: https://dev.azure.com/greatergiving/Greater%20Giving/_git/GGO/pullrequest/8436 | S6: 45772 | T6: 45775 | U6: Rajesh | W6: Michael Wall | X6: 45775 | AB6: Development has been completed and tested in local and Dev enviroment[28-April-2025] Completed One round of Standard Regression
A7: 6 | B7: GGO Web | C7: 45764 | D7: 45778 | E7: GGO 7.23.0 Sprint 4 | F7: Sathiya, Rajesh | G7: GGO-13722 | H7: High - Weak Encryption: Insecure Mode of Operation - Cryptography.cs: 56 | I7: Peer review | J7: 1 | K7: 0.5 | L7: 12.5 | M7: Sathiya | N7: Rajesh | R7: NA
A8: 7 | B8: GGO Web | C8: 45764 | D8: 45778 | E8: GGO 7.23.0 Sprint 4 | F8: Saranya | G8: GGO-14615 | H8: HIGH - Microsoft.Bcl.Async:1.0.168 | I8: Completed | J8: 2 | K8: 2 | L8: 10.5 | M8: Saranya | N8: Rajesh | R8: https://greatergiving.visualstudio.com/Greater%20Giving/_git/GGO/pullrequest/8427 | S8: 45769 | T8: 45769 | U8: Rajesh | W8: Loan Troung | X8: 45769 | AB8: Completed One round of Standard Regression
A9: 8 | B9: GGO Web | C9: 45764 | D9: 45778 | E9: GGO 7.23.0 Sprint 4 | F9: Saranya | G9: GGO-13723 | H9: High - Weak Encryption: Insecure Mode of Operation - SymmetricAlgorithmProvider.cs: 35 | I9: Peer review | J9: 1 | K9: 0.5 | L9: 22 | R9: NA
A10: 9 | B10: GGO Web | C10: 45764 | D10: 45778 | E10: GGO 7.23.0 Sprint 4[Stretch] | F10: MikeW, Rajesh, Saranya | G10: GGO-14651 | H10: Pass New IsFallback Swipe Flag from GoTime to PAPI | I10: Completed | J10: 2 | K10: 2 | L10: 36 | R10: https://greatergiving.visualstudio.com/Greater%20Giving/_git/GGO/pullrequest/8440 | S10: 45775 | T10: 45775 | U10: Rajesh | W10: Michael Wall | X10: 45775
A11: 10 | B11: GGO Web | C11: 45764 | D11: 45778 | E11: GGO 7.23.0 Sprint 4 | F11: MikeW, Rajesh, Saranya | G11: PAPI-846 | H11: EMV Fallback Requires <EMVChipCondition> Tag along with Swipe Data* | I11: Completed | J11: 3 | K11: 3 | L11: 48 | R11: https://greatergiving.visualstudio.com/Greater%20Giving/_git/PAPI/pullrequest/8441 | S11: 45775 | T11: 45775 | U11: Rajesh | W11: Michael Wall | X11: 45775
A12: 11 | B12: GGO Web | C12: 45764 | D12: 45778 | E12: GGO 7.23.0 Sprint 4 | F12: Priya-QA | G12: GGO-14649 | H12: 22 APR GGO 7.23.0 CRT Release & Regression Testing | I12: Completed | J12: 5 | K12: 5 | L12: 35.5 | AB12: CRT Regression Testing in Progress
