Workbook

Sheet Dashboard
A1: Current Sprint | B1: {=INDEX($B$2:$B$100,MATCH(1,(($D$2:$D$100 >=TODAY())*($C$2:$C$100<=TODAY())),0))} -> OB-OP 8.6.0 Sprint 4 | C1: Current Sprint Sheet | D1: =CONCATENATE(B1,"-Status") -> OB-OP 8.6.0 Sprint 4-Status | E1: Sprint Start Date | F1: =VLOOKUP($B$1,$B$1:$C$100,2) -> 46149 | G1: Sprint End Date | H1: =VLOOKUP($B$1,$B$1:$D$100,3) -> 46163 | I1: Application Name | J1: Donor Wave | K1: Users | L1: kannan.muthiah@relevantz.com;Ubaithullah.shahjahan@relevantz.com;irsath.kisar@relevantz.com;arivalagan.ramasamy@relevantz.com;saranya.palani@relevantz.com;murugesan.manthiramoorthy@relevantz.com | M1: Teams Name(GP-GGO.Donor Wave) | N1: 19:1e26e53c861e4b028fd5faa4b55c0a68@thread.v2
A2: Sprint Type | B2: Sprint # | C2: Sprint Start Date | D2: Sprint End Date | E2: Assigned | F2: Completed | G2: Story points introduced/removed | H2: Sprint Summary | I2: Accomplishments | J2: Remarks | K2: Retro Points (Internal & External) | L2: Data sanity Audit Status | M2: AuditDate | N2: Planned Leaves | O2: Availed Leaves | P2: Backlog Health
A3: =IF(AND($D$1>=C3,$D$1<=D3),"CurrentSprint","NA") -> NA | B3: OBOP 7.10.0 Sprint 4 | C3: 45296 | D3: 45309 | E3: 12 | F3: 9 | G3: 5/0 | J3: Offshore team faced some challenges while implementing the Rich textbox. | K3: Internal: External:
A4: =IF(AND($D$1>=C4,$D$1<=D4),"CurrentSprint","NA") -> NA | B4: OBOP 7.11.0 Sprint 1,2 | C4: 45310 | D4: 45337 | E4: 25 | F4: 23 | G4: 0/0 | J4: Offshore team got appreciations for more than expected story points completed. Prabhu and Rajesh for helping with the hotfix as well. | K4: Internal: External:
A5: =IF(AND($D$1>=C5,$D$1<=D5),"CurrentSprint","NA") -> NA | B5: OBOP 7.11.0 Sprint 3 | C5: 45338 | D5: 45351 | E5: 13 | F5: 13 | G5: 0 | J5: Overall good sprint, Prabhu and offshore team got appreciated for DNN libraries documentation. | K5: Internal: External:
A6: =IF(AND($D$1>=C6,$D$1<=D6),"CurrentSprint","NA") -> NA | B6: OBOP 7.11.0 Sprint 4 | C6: 45352 | D6: 45365 | E6: 9 | F6: 9 | G6: 0/0 | J6: Offshore team got appreciations for investigating the AHA templates-DNN7(OP) and group filter story(OB). | K6: Internal: External:
A7: =IF(AND($D$1>=C7,$D$1<=D7),"CurrentSprint","NA") -> NA | B7: OBOP 7.12.0 Sprint 1 | C7: 45366 | D7: 45379 | E7: 11 | F7: 11 | G7: 2/0 | J7: Appreciated for completing all the work with good production release. | K7: Internal: External:
A8: =IF(AND($D$1>=C8,$D$1<=D8),"CurrentSprint","NA") -> NA | B8: OBOP 7.12.0 Sprint 2 | C8: 45380 | D8: 45393 | E8: 13 | F8: 10 | G8: 5/0 | J8: 2 DNN-7 story getting carried. Prabhu and Offshore team got appreciated for doing great job in learning and updating AHA templates. | K8: Internal: External:
A9: =IF(AND($D$1>=C9,$D$1<=D9),"CurrentSprint","NA") -> NA | B9: OBOP 7.12.0 Sprint 3 | C9: 45394 | D9: 45407 | E9: 7 | F9: 7 | G9: 0/0 | J9: Client appreciated for completing Recaptcha DNN9 conversion. Addition to this development completed for one stretch story. | K9: Internal: External:
A10: =IF(AND($D$1>=C10,$D$1<=D10),"CurrentSprint","NA") -> NA | B10: OBOP 7.12.0 Sprint 4 | C10: 45408 | D10: 45421 | E10: 15 | F10: 15 | G10: 6/0 | J10: Overall good sprint, Team completed more than expected story points. | K10: Internal: External:
A11: =IF(AND($D$1>=C11,$D$1<=D11),"CurrentSprint","NA") -> NA | B11: OBOP 7.13.1 Sprint 1 | C11: 45422 | D11: 45435 | E11: 17 | F11: 17 | G11: 0/0 | J11: Prabhu got appriciated for getting all AHA fixes completed and Mercy got appriciated for finding lot of issues. | K11: Internal: External:
A12: =IF(AND($D$1>=C12,$D$1<=D12),"CurrentSprint","NA") -> NA | B12: OBOP 7.13.1 Sprint 2 | C12: 45436 | D12: 45449 | E12: 28 | F12: 23 | G12: 8/0 | J12: Completed most of assigned stories/defects | K12: Internal: External:
A13: =IF(AND($D$1>=C13,$D$1<=D13),"CurrentSprint","NA") -> NA | B13: OBOP 7.13.1 Sprint 3 | C13: 45450 | D13: 45463 | E13: 17 | F13: 16 | G13: 5/0 | J13: Appreciated for completing all the work | K13: Internal: External:
A14: =IF(AND($D$1>=C14,$D$1<=D14),"CurrentSprint","NA") -> NA | B14: OBOP 7.13.1 Sprint 4 | C14: 45464 | D14: 45476 | E14: 8 | F14: 8 | G14: 1/0 | J14: Appreciated dev team for Investigation stories and Mercy for finding defect. | K14: Internal: External:
A15: =IF(AND($D$1>=C15,$D$1<=D15),"CurrentSprint","NA") -> NA | B15: OBOP 7.14.0 Sprint 1 | C15: 45477 | D15: 45491 | E15: 13 | F15: 13 | G15: 3/0 | J15: Appreciated Mercy for good testing | K15: Internal: External:
A16: =IF(AND($D$1>=C16,$D$1<=D16),"CurrentSprint","NA") -> NA | B16: OBOP 7.14.0 Sprint 2 | C16: 45492 | D16: 45505 | E16: 12 | F16: 12 | G16: 0/0 | J16: Completing another sprint successfully, Appriciated Prabhu and offshore for completing the work on messaging | K16: Internal: External:
A17: =IF(AND($D$1>=C17,$D$1<=D17),"CurrentSprint","NA") -> NA | B17: OBOP 7.14.0 Sprint 3 | C17: 45506 | D17: 45519 | E17: 11 | F17: 8 | G17: 0/0 | J17: Couldn't complete testing because of release pipeline certificate issue. | K17: Internal: External:
... A19: =IF(AND($D$1>=C19,$D$1<=D19),"CurrentSprint","NA") -> NA | B19: OBOP 8.2.0 Sprint 1 | C19: 45534 | D19: 45547 | E19: 12 | F19: 12 | G19: 0/0 | J19: Appreciated Prabhu for providing KT to quick invoice team | K19: Internal: External:
A20: =IF(AND($D$1>=C20,$D$1<=D20),"CurrentSprint","NA") -> NA | B20: OBOP 8.2.0 Sprint 2 | C20: 45548 | D20: 45561 | E20: 20 | F20: 15 | G20: 5/0 | K20: Internal: External:
A21: =IF(AND($D$1>=C21,$D$1<=D21),"CurrentSprint","NA") -> NA | B21: OBOP 8.2.0 Sprint 3 | C21: 45562 | D21: 45575 | E21: 20 | F21: 17 | G21: 3/3 | J21: TST was down which lead to rolling over one story Peer CRC: 0 Onsite CRC: 2 Client CRC: 0 Internal Defects :2 External Defects:0 Appreciated i)Prabhu for helping Alice on providing info on some stories ii)Mercy for helping out while Alice was unavailable iii) Rajesh and Prabhu for helping Joe set up GGO locally. iv) Lot of challenges while developing the OP page module and offshore continued working through it v) Rajesh for helping Prabhu and team with testing of OP stories. vi) Rajkumar and Prabhu for good coordination for getting the entire flow end to end on Quick invoicing | K21: Internal: External:
A22: =IF(AND($D$1>=C22,$D$1<=D22),"CurrentSprint","NA") -> NA | B22: OBOP 8.2.0 Sprint 4 | C22: 45576 | D22: 45589 | E22: 17 | F22: 17 | G22: 0/0 | I22: 1.Import quick invoice payment page designed, created in GGO and placed in between Registrations & RSVPs 2. Added new convenience fee sale and made reconcile with sale payment association 3.Pending quick invoice imports count included in existing left nav notification counter | J22: i) Appreciated the team for completing all the quick invoice stories. ii) Kudos to Farhath and Mercy for helping with the test planning and testing which made it easier for Alice. iii) Kudos to Prabhu and Rajkumar for coordinating with offshore teams and completing all the planned stories for the sprint iv) Appreciated Offshore for finishing the planned stories and meeting the deadline v) Rajesh and Prabhu helped Rajkumar & offshore with the OP and GGO integration. Peer CRC: 2 Onsite CRC: 0 Client CRC: 0 Internal Defects :0 External Defects:0
A23: =IF(AND($D$1>=C23,$D$1<=D23),"CurrentSprint","NA") -> NA | B23: OBOP 8.3.0 Sprint 1 | C23: 45590 | D23: 45603 | E23: 11 | F23: 8 | G23: 0/0 | I23: 1.Quick Invoice feature release into CRT 2.Added Privacy Police notice on both OB & OP 3.Default application text css changes & Text updates | J23: Nice job with the privacy policy implementation. One story has been moved to next sprint for testing alone Kudos to Offshore QA - has been very helpful , making sure all gaps are covered Peer CRC: 0 Onsite CRC: 0 Client CRC: 0 Internal Defects:2 External Defects: 0
A24: =IF(AND($D$1>=C24,$D$1<=D24),"CurrentSprint","NA") -> NA | B24: OBOP 8.3.0 Sprint 2 | C24: 45604 | D24: 45617 | E24: 14 | F24: 14 | G24: 3/0 | I24: 1.OP 8.2.0 release to CRT & PRD 2.App help url updates 3.Invoicing feature updates - Collected from pilot user's feedback 4.Escalation support | J24: Kudos shared to Mercy for the support in making a lot of test plans and doing thorough testing that really helped out with all the small areas we have to verify, especially with all of the stories we added during the quick invoice effort. Rajkumar and team for the merge field completion. Rajesh for helping with the merge strategies and Prabhu was very helpful for a couple of tickets Joe had. Peer CRC:0 Onsite CRC:0 Client CRC: 6 Internal Defects:2 External Defects: 0 A 3 point story was added towards the end of the Sprint as part of the strech goal and was rolled over to the next sprint
A25: =IF(AND($D$1>=C25,$D$1<=D25),"CurrentSprint","NA") -> NA | B25: OB-OP 8.3.0 Sprint 3 | C25: 45618 | D25: 45631 | E25: 21 | F25: 21 | G25: Ten/0 | I25: 1. We had 8.2.2 OP CRT release 2. completed final set of pending invoicing tasks 3.Macroscope fixes | J25: Kudos to Rajkumar and team for taking invoicing project to finish line, Offshore QA - Mercy and Farhath for putting some good notes for Alice which was helpful when she got back and Preethi and Karthi for managing all the dev work during the US thanksgiving holidays when everyone was away Kalai and Rajiv are very dynamic and all the deliveries were on time Prabhu and Rajesh for the KT and support to the invoicing team Peer CRC:0 Onsite CRC:2 Client CRC: 2 Internal Defects:1 External Defects: 0 A 2 point story was added towards the end of the Sprint as part of the strech goal and was rolled over to the next sprint
A26: =IF(AND($D$1>=C26,$D$1<=D26),"CurrentSprint","NA") -> NA | B26: OB-OP 8.3.0 Sprint 4 | C26: 45632 | D26: 45659 | E26: 11 | F26: 13 | G26: 15/0 | I26: 1.OB 7.12.1 release to CRT& PRD 2. OP 8.2.2 PRD Release 3.Complete Invoicing 4.Macroscope fix | J26: Kudos Offshore in general and offshore QA for keeping up with things when Onsite was away for holidays +2 Mercy for keeping up with test plans when Alice was out Raj kumar and team for a great impact on past few sprints +1 Peer CRC:0 Onsite CRC:1 Client CRC: 0 Internal Defects:0 External Defects: 0 Some of the stories are stretch and got carry forwarded because of client resources unavailability due to holidays
A27: =IF(AND($D$1>=C27,$D$1<=D27),"CurrentSprint","NA") -> NA | B27: OB-OP 8.4.0 Sprint 1 | C27: 45660 | D27: 45673 | E27: 16 | F27: 13 | G27: 0/0 | I27: 1. Release 8.3.0 to CRT and PRD 2. Macroscope fix in OP and OB | J27: Kudos to Given the release, towards the end of the sprint we were seeing a bunch of issues in OP and OB and Mercy was very helpful in testing those Given the product overlap across both teams and the staggered release for both teams, it was confusing but the team did a great job overall staying on top of everything Rajesh for helping Joe set up for the portals To the team on a great job on the overall Invoice project and release Peer CRC:0 Onsite CRC:2 Client CRC: 0 Internal Defects:0 External Defects: 0 3 point story carry forwarded to next sprint. Part of the performance improvement done.Restrictions on DNN9 core functionality prevents us from finding performance improvements. But there is more room left for improvements. So Story was carry forwarded
A28: =IF(AND($D$1>=C28,$D$1<=D28),"CurrentSprint","NA") -> NA | B28: OB-OP 8.4.0 Sprint 2 | C28: 45674 | D28: 45687 | E28: 16 | F28: 10 | G28: 5/0 | I28: RSVP enhancements, continuing with Macroscope work,OP MFA login production hotfix | J28: Peer CRC:0 Onsite CRC:0 Client CRC: 0 Internal Defects:1 External Defects: 0 2 RSVP stories got carried over to the next sprint, RSVP Multiple attendee dynamic control creation has been challenging. Completed major functionalities, local testing and dev testing is in progress and a 3 point story is dependent on that 8 point story so we couldn't proceed that without completing the main story
A29: =IF(AND($D$1>=C29,$D$1<=D29),"CurrentSprint","NA") -> NA | B29: OB-OP 8.4.0 Sprint 3 | C29: 45688 | D29: 45701 | E29: 14 | F29: 12 | G29: 1/0 | I29: Continue RSVP enhancements, Supported OP 8.3.2 Hotfix testing support for delay in OP site creation, RSVP index table update and Apigee threading exception | J29: Kudos to i) Rajesh to take the big feature and manage it +1 ii) Joe,Mike , Rajesh, Derek was handling all the rapid change in the sprint goal iii) Rajesh for handling all on both teams GGO and OB/OP iv) Offshore dev and QA for working hard on multiple attendees and getting all the scenarios covered Peer CRC:2 Onsite CRC:2 Client CRC: 0 Internal Defects:0 External Defects: 2 3 pt bug has been carry forwarded to next sprint as we couldn't able to reproduce the bug in our environment and trying to find the root cause for it
A30: =IF(AND($D$1>=C30,$D$1<=D30),"CurrentSprint","NA") -> NA | B30: OB-OP 8.4.0 Sprint 4 | C30: 45702 | D30: 45715 | E30: 9 | F30: 9 | G30: 6/3 | I30: New card type added with existing ones, OP 8.3.3 and 8.4.0 release to CRT | J30: Kudos to i) Everyone in the team for all the hard work this sprint ii) Joe , Rajesh, Mike and Carlos for all of the release stuff iii) Offshore for taking care of all the sprint stories Peer CRC:0 Onsite CRC:0 Client CRC: 0 Internal Defects:1 External Defects: 3 3 pt bug has been flagged in JIRA as blocker and removed from sprint during sprint end and another 3 pt bug which is in stretch has been carry forwarded to next sprint, in which we have completed the fix for 1 report, need to check for remaining 3 reports
A31: =IF(AND($D$1>=C31,$D$1<=D31),"CurrentSprint","NA") -> NA | B31: OB-OP 8.5.0 Sprint 1 | C31: 45716 | D31: 45729 | E31: 14 | F31: 11 | G31: 0/0 | I31: Release OP 8.4 to PRD, begin investigating OB UX and QoL fixes | J31: Kudos i) Prabhu and Rajesh on assisting Joe on a ticket related to convenience fee ii) Offshore QA Mercy for the test plan put together for catalog verification, very good testing and makes it more secure iii) Karthi and Preethi for great documentation on the investigation stories Peer CRC:0 Onsite CRC:0 Client CRC: 0 Internal Defects:0 External Defects: 2 One of the story got completed at the last minute because the fix wasn't working so the team had to coninue trying out different aproaches till it worked. It was sent for peer review on the last day and hence got carry forwarded to the next sprint for testing
A32: =IF(AND($D$1>=C32,$D$1<=D32),"CurrentSprint","NA") -> NA | B32: OB-OP 8.5.0 Sprint 2 | C32: 45729 | D32: 45743 | E32: 14 | F32: 19 | G32: 7/0 | I32: Begin work on OB UX settings and layouts | J32: Kudos i) We did a stretch AC on the layout and Prabhu assisted Joe on that ii) Prabhu for helping Alice with testing iii) Rajesh for helping Alice on the email issue +1 iv) Offshore for completing all the planned stories and adding some stretch stories Peer CRC:0 Onsite CRC:0 Client CRC: 1 Internal Defects:0 External Defects: 0 OB UX settings and layout implementation Escalation support for investigating the max bid label update Fixed Max Bid label OP negative payment fix
A33: =IF(AND($D$1>=C33,$D$1<=D33),"CurrentSprint","NA") -> NA | B33: OB-OP 8.5.0 Sprint 3 | C33: 45743 | D33: 45757 | E33: 14 | F33: 11 | G33: 0/0 | I33: Continue OB UX and high value OP items Accompolishments: Added new settings in Online bidding settings page Feature flag implementation for OB - sending data from GGO to OB | J33: Peer CRC:0 Onsite CRC:0 Client CRC: 0 Internal Defects:1 External Defects: 2 Pending reason One 3-point story was carried over to the next sprint. While development, local testing, and DEV testing were completed from our side, the peer review and testing for OB-3731 were delayed. This was primarily due to the extended time required for development and testing of OB-3708 (an 8-point story). As a result, OB-3731 has been moved to the next sprint. | K33: What went well? Offshore doing testing in Dev before going to TST helps mitigate issues later in the Sprint What didn’t go well? The development for OB settings page was a little challenging Kudos 1. Nice job team on OB settings page, the mockups really look good 2. Great QA team for being a sport , working last minute to test the stories +1 3. Offshore QA Mercy for finding the issues before it hit TST and helped in not sending it back to Dev later 4. Prabhu and Rajesh for their support to Alice 5. Prabhu, Offshore dev Preethi and Karthi for completing the OB settings page for spending extended hours in completing it +2
A34: =IF(AND($D$1>=C34,$D$1<=D34),"CurrentSprint","NA") -> NA | B34: OB-OP 8.5.0 Sprint 4 | C34: 45757 | D34: 45771 | E34: 11 | F34: 14 | G34: 5/0 | I34: Release and test OP 8.5 and OB 7.13 to CRT. Donor Project continuing work Accomplishment 1. Tested OP 8.5 and OB 7.13 in CRT 2. Upgraded Angular 12 to 13, version got upgraded but facing few routing issues | J34: Peer CRC:0 Onsite CRC:0 Client CRC: 0 Internal Defects:0 External Defects: 0 Pending reason 1 Bug has been carry forwarded to next sprint since it is taking more time than expected. Also PM cannot remember what this report looked like working in Prod, so we may need to do some discovery and explanation in order to come up with a good solution | K34: What went well? 1. CRT testing completed on time 2. Great progress on Angular update 3. Good initial progress on Donor project 4. Completed more stories than planned What didn’t go well? 1. The package dependency made the Angular update challenging 2. Fixing the section report issue has been more complex than planned Kudos Prabhu and Rajesh for supporting the CRT issue fix, Carlos as well Rajesh for leading the way on Donor Project +2 Offshore for the Angular update , that was a big jump +2
A35: =IF(AND($D$1>=C35,$D$1<=D35),"CurrentSprint","NA") -> NA | B35: OB-OP a7.14.0 Sprint 1 | C35: 45771 | D35: 45785 | E35: 15 | F35: 11 | G35: 0/0 | I35: OB & OP PRD release, continue with OB UX and Donor project Accomplishment 1. Passed the new settings value from GGO to OB and mapped the header values in OB side UI 2. Upgraded Angular 12 to 13, Updated node version from 14 to 16, fixing the errors | J35: Peer CRC:0 Onsite CRC:0 Client CRC: 3 Internal Defects:0 External Defects: 0 Pending reason OP-2747-It has been carry forwarded to next sprint since it is taking more time than expected. Also PM cannot remember what this report looked like working in Prod, so we may need to do some discovery and explanation in order to come up with a good solution OB-3680 - Story has been carry forwarded to next sprint - Dependent on OB-3755. Development and peer review is completed, Since PR was shared in the last day testing will be done in next sprint | K35: What went well? The new Donor platform setup went well On pace with OB UX What didn’t go well? Last minute unplanned PTO for team member led to delay in closing a few tickets New OB page and design turned out to be a little challenging Kudos Preethi for updating the node and Angular version as it requires a lot of tracking and patience. Thanks for doing it
A36: =IF(AND($D$1>=C36,$D$1<=D36),"CurrentSprint","NA") -> NA | B36: OB-OP 8.0 Sprint 2 | C36: 45785 | D36: 45799 | E36: 15 | F36: 15 | G36: 0/0 | I36: OB & OP PRD release, continue with OB UX and Donor project Accomplishment 1. The team completed all they planned for and more (initially firebase was spike later converted to story) 2. Fixed the warnings while compiling angular 13, ended up with 1 console error while running application | J36: Peer CRC:0 Onsite CRC:1 Client CRC: 0 Internal Defects:1 External Defects: 0 Escaped defect RCA - Should do proper code review and local testing,DEV testing covering all scenarios Review Comment - Add try catch block here when you connecting with DB to make operations | K36: What went well? The team completed all they planned for and more PRD releases were long and it went well What didn’t go well? Firebase notification was a little tricky to configure Handling Aesgcn decryption for existing URLs cost a little extra time to complete Docker desktop is not authorized so it forced the team to find a different way to communicate with the database Kudos Offshore and Dev Prabhu for completing the investigation and implementation of Firebase notification +2
A37: =IF(AND($D$1>=C37,$D$1<=D37),"CurrentSprint","NA") -> NA | B37: OB-OP 8.0 Sprint 3 | C37: 45800 | D37: 45814 | E37: 16 | F37: 14 | G37: 6/0 | I37: Continue OB UX work, setup for donor platform Accomplishment 1. Updated Node js to version 16 and then to 18, trying to fix the errors 2. Firebase notification is coming correctly to the bidders who are outbidden 3. New team members setup is completed and started the design story | J37: Peer CRC:0 Onsite CRC:0 Client CRC: 2 Internal Defects:0 External Defects: 0 Review comment - 1. Macroscope will ding us for putting apikeys or secrets in the repo. We need to add these as variables, even for local testing the same way we do for the SMS test keys 2. Let's add a general exception catch as well. Pending reason 1. OB-3675 -During the sprint, a few high-priority security issues were introduced that required quick attention. Addressing them took some time away from our originally planned work. Development work has been completed successfully, and dev environment testing was verified by the Relevantz offshore QA team. However, during deployment to the TST environment, we encountered issues related to pipeline variables. As a result, only testing is pending for this story. 2. DON-20 - Stretch story - Development completed, local testing is in progress, Once done will raise the PR in next sprint | K37: What went well? Onboarding went well What didn’t go well? 2 Security issues took about a week of 2 of the team members time New developers onboarding For multiple bidders, Firebase notification is not getting sent randomly Angular upgrade has been challenging Escalation support for OP Login issue Kudos Prabhu nice job get everybody onboarded +3 Takeaways 6/5/2025 Angular Update timebox effort should be significantly lowered - 10 hrs a Sprint Escalation Support should be filtered by Derek Anderson and Mike Horihan so that team can focus on OB UX overhaul and Donor project
A38: =IF(AND($D$1>=C38,$D$1<=D38),"CurrentSprint","NA") -> NA | B38: OB-OP 8.0 Sprint 4 | C38: 45814 | D38: 45826 | E38: 7 | F38: 2 | G38: 2/0 | I38: CRT Release and testing for OB and OP, continue with OB UX and Donor project Accomplishment Completed the design for login and registration page | J38: Peer CRC:0 Onsite CRC:0 Client CRC: 0 Internal Defects:0 External Defects: 0 Pending reason 1. DON-20, DON-21 - Local testing completed from offshore QA end and updated the comments in JIRA but since onsite QA was occupied with CRT testing, couldn't give signoff to this ticket. Gave the PR for DON-21 on tuesday (17/06) | K38: A special shout out to the new Donor team for coming up to speed very fast and taking control right away. Well done! Overall it was a good sprint even though we didn't meet the Sprint forecast this time. The onsite QA needs to signoff on those tickets before closing and given this was a regression sprint, the onsite QA had her hands full with CRT testing. Kudos New Donor team for completing a lot of the design work +1
A39: =IF(AND($D$1>=C39,$D$1<=D39),"CurrentSprint","NA") -> NA | B39: OB-OP 8.1 Sprint 1 | C39: 45827 | D39: 45841 | E39: 12 | F39: 7 | G39: 3/0 | I39: Release OB/OP to PRD, continue OB UX and Donor Platform Completed the design for registration page and password reset pages | J39: Peer CRC:0 Onsite CRC:0 Client CRC: 3 Internal Defects:0 External Defects: 0 Pending reason DON-16 - 5 point story - Development completed, local testing is completed,need to do some more common functionality in API Once done will raise the PR in next sprint, Initially this was a 3 point story, later due to more work on that the story point has been increased from 3 to 5 Review comment 1.Rename the varialbe 2.These 5 radio buttons should not be inputs. They will be checked off during client side input validation. 3.Remove hard-coded email. | K39: What went well? All planned stories got completed and more Quick turn around on the Hot Fix What didn’t go well? A number of security issues came through which was unplanned and high priority for some old modules The arc review is preventing us from implementing B2C Kudos Offshore team did a great job on OB and Donor work, completed everything +1 Appreciate Rajesh stepping in and covering for Prabhu Joe and Prabhu giving assistance on couple of stories for testing to Alice( specially on Donor project) Quick turn around on the Hot Fix Alice and Offshore QA team has done a great job on automation testing which made both the prod release testing quick +1
A40: =IF(AND($D$1>=C40,$D$1<=D40),"CurrentSprint","NA") -> NA | B40: OB-OP 8.1 Sprint 2 | C40: 45841 | D40: 45855 | E40: 14 | F40: 7 | G40: 0/0 | I40: More OB UX, Donor Platform infrastructure, and OP security remediation. Accomplishement Completed API Structure and serilog setup | J40: Peer CRC:0 Onsite CRC:0 Client CRC: 0 Internal Defects:0 External Defects: 0 Pending reason Don-39 - Incorporating Vega components into the input validation effort was more completex than initially thought Don-45 - B2C team not yet create Tenant & Singin and Singup page in Azure Portal | K40: What went well? API Setup from scratch and user creation and Serilog implementation What didn’t go well? Faced some of the validation issues from Vega controls Kudos Prabhu did a great job on api setup and user creation code review and suggession Offshore team did a great job on OB and Donor work Murugesan for detailed testing
A41: =IF(AND($D$1>=C41,$D$1<=D41),"CurrentSprint","NA") -> NA | B41: OB-OP 8.1 Sprint 3 | C41: 45855 | D41: 45869 | E41: 11 | F41: 8 | G41: 0/0 | I41: Continue OB UX (Package Cards, Donation Modal), Platform work, Security remediation Accomplishement Created Home page design | J41: Peer CRC:0 Onsite CRC:0 Client CRC: 0 Internal Defects:0 External Defects: 0 Pending reason Don-45 - B2C implementation requirement little bit changed integrate according to angular 19 | K41: What went well? Donor app progress was good A lot of positive comments from CS on the Donor Platform progress - well done team! “The login page looks great and it will be one of the most visited page” What didn’t go well? OB certificate issue blocked testing in Dev, TST and CRT OB build Pipeline issue The fixes for WhiteHat security findings was challenging Kudos Joe for taking care of all the scrum processes seamlessly in Rupa’s absence Prabhu for supporting Alice with Donor platform testing Mercy for cross site scripting testing and bringing up some issues Prabhu, Rajesh, Mike H and Joe for getting the Certificate issue resolved, it is very close to getting done Joe for fixing the Build pipeline and the whitehat security scanning +1 Arivalagan - the code he delivered for Don 39 and Don 40 is of high quality
A42: =IF(AND($D$1>=C42,$D$1<=D42),"CurrentSprint","NA") -> NA | B42: OB-OP 8.1 Sprint 4 | C42: 45869 | D42: 45883 | E42: 10 | F42: 7 | G42: 2/0 | I42: Continue OB UX, Platform work, Security remediation Accomplishement Completed Azure B2C Implementation and Google api for address search | J42: Peer CRC:0 Onsite CRC:0 Client CRC: 0 Internal Defects:0 External Defects: 0 Pending reason Don-45 - B2C implementation done waiting for client`s review | K42: What went well? Most of the planned stories got completed + some stretch stories Upper Management support for getting us out of OP bug bounty What didn’t go well? Implementing the WAF caused us to do additional testing in CRT affecting both OB and OP B2C implementation using MSAL was challenging without having designated MFA policy Kudos Alice for getting through a bunch of WAF testing and a bunch of app testing as well( it was tedious) +2 Offshore team and Prabhu for the implementation of B2C token, It was difficult and needed a lot of coordination +1 Well Done on the OB Cert issue Sarah was extremely helpful during WAF testing Carlos for the release support Prabhu and Joe for the support with all the testing Owen for rounds of regression testing Offshore QA for for helping Alice with all the testing Moose for all the help with pipeline Joe for all the macroscope work Rajesh for clearing the CRT issue Offshore ( OB/OP and Donor) for completing the planned stories+1
A43: =IF(AND($D$1>=C43,$D$1<=D43),"CurrentSprint","NA") -> NA | B43: OB-OP 8.2 Sprint 1 | C43: 45883 | D43: 45897 | E43: 14 | F43: 3 | G43: 0/0 | I43: Release OB 8.1 to PRD, OB UX, Donor Platform Accomplishement Completed organization and events details | J43: Peer CRC:0 Onsite CRC:0 Client CRC: 0 Internal Defects:0 External Defects: 0 Pending reason Don-45 - B2C implementation done waiting for client`s review Don-51 - Events development done waiting for client`s review they did more changes in figma 2 days back too they updated the figma | K43: What went well? Both OB and Donor feature implementation went well Automation updates for the new OB Smoke test progress is awesome OB Prod release was long but very smooth What didn’t go well? Dependency on B2C token Given multiple stories were for the same Home page there was time spent on fixing merge conflict Kudos OB search functionality was a great win- Prabhu Sankar [C]+1 Prabhu for sticking in there on the Donor app with Joe- coordinating all the updates with offshore +1 Prabhu for supporting Alice on the local setup for Donor testing
A44: =IF(AND($D$1>=C44,$D$1<=D44),"CurrentSprint","NA") -> NA | B44: OB-OP 8.2 Sprint 2 | C44: 45897 | D44: 45911 | E44: 12 | F44: 12 | G44: 3/0 | I44: OP PRD release, continue Ob UX work, continue Donor Platform Accomplishement Completed header nameplate and B2C PR Suggestions | J44: Peer CRC:0 Onsite CRC:0 Client CRC: 0 Internal Defects:0 External Defects: 0 | K44: Keep up the good work team, kudos on hustling to complete the planned stories given the build issue this Sprint! What went well? Completed way more than planned 2 Prod releases this sprint Over the hump on the security issues (DevOps side) Macroscope report is up to date Macroscope report is up to date What didn’t go well? Implemented security measures that caused pipeline issues The team is putting renewed emphasis to be compliant with FIGMA design Kudos Great job team on completing more than planned given all the challenges Prabhu and Joe for helping setup Dionor platform and general testing support, including the hotfix testing Offshore for fixing the bugs under OB stories really fast To Prabhu for getting offshore to be compliant with Bootstrap +2 Offshore team for being resilient and delivering on the designs meeting all the AC +2
... A53: =IF(AND($D$1>=C53,$D$1<=D53),"CurrentSprint","NA") -> NA | B53: OB-OP 8.4 Sprint 4 | C53: 46037 | D53: 46051 | E53: 14 | F53: 15 | G53: 7/0 | I53: Release OB 8.4.0 to CRT. Test it thoroughly. Continue Donor Platform build for b2c Accomplishment Completed current sprint stories and started to work from the backlog | J53: Peer CRC:0 Onsite CRC:0 Client CRC: 0 Internal Defects:0 External Defects: 0 Pending Reason DON-183 - Development completed from offshore end and PR also got approved, currently its in VERIFY status, testing will be done in next sprint | K53: Great effort, Keep up the good work! What went well? CRT release went and CS team tested and shared their feedback What didn’t go well? Trouble shooting and setting up the new Dev environment has been difficult Kudos Joe: Prabhu really pushes the pace of the team and that's why we were able to bring in those bugs(+1 Rajesh) Consistent high quality work by the team(+1 Prabhu) B2C pages looks great +1 Prabhu Derek for queuing in all those bugs from CS and internal Stakeholders (+1 Alice, +1 Rajesh, +1 Prabhu) Client Services for great testing (+1 Alice) Great testing by CS, Alice and offshore in the past Sprint Alice: Offshore Dev for fixing all the bugs Offshore Qa Mercy for finding few of the bugs Online Bidding sales issue support from Rajesh and Joe Prabhu: Offshore team for taking ownership of the bugs which came and they quickly fixed it. Kudos to Preethi, Karthi and Mercy(+1 Joe, +1 Mike , +1 Alice , +1 Rajesh) All the bugs got discussed and completed because of Joe ‘s support given he already had a lot on his plate
A54: =IF(AND($D$1>=C54,$D$1<=D54),"CurrentSprint","NA") -> NA | B54: OB-OP 8.5 Sprint 1 | C54: 46051 | D54: 46065 | E54: 15 | F54: 13 | G54: 5/0 | I54: Release OB 8.4.0 to CRT. Test it thoroughly. Continue Donor Platform build for b2c Accomplishment Completed current sprint planned development stories Took a stretch story and made good progress on that | J54: Peer CRC:0 Onsite CRC:0 Client CRC: 0 Internal Defects:0 External Defects: 0 Pending Reason DON-189 - Development is completed as per the requirement given at the beginning and draft PR was created but now requirement is going to change and yet to update that in AC by PO, so this was kept hold and will be carry forwarded to next sprint. | K54: Well Done Team! What went well? Completed more than planned What didn’t go well? Working with Donor B2C team has been challenging because of the time difference OP escalations taking up time Kudos Joe: All of the offshore team, their quality of work has been really high right now and that has led to more stories as the code quality is high and gets completed after the 1st pull request.No sending back (+1 Alice, +1 Mike H, +1 Prabhu, +1 Rajesh) Derek for keeping tickets up to date, getting all the stories AC up to date as per request (+1 Alice, +1 Prabhu) Alice for getting all the testing done at the end of the sprint and CRT testing as well Alice: Offshore QA for getting all the bases covered and an extra eye on CRT environment Joe and Prabhu for the extra support with testing the stories and completing them Prabhu: The team was able to complete all the stories only because Joe took up the complex tasks Mike: Rajesh for helping me with the Op escalations Joe for helping me with GCP and B2C teams Anything that needs to be highlighted from the past Sprint Donor Dev environment is up and running Takeaways Going forward for the next releases, as a team we need to remind ourselves that given a deadline we need to release the MVP for the release and tackle the rest in the next release instead of stretching ourselves | N54: 1 | O54: 1
A55: =IF(AND($D$1>=C55,$D$1<=D55),"CurrentSprint","NA") -> NA | B55: OB-OP 8.5 Sprint 2 | C55: 46065 | D55: 46079 | E55: 12 | F55: 10 | G55: 0/0 | I55: Release OB 8.4.0 to CRT. Test it thoroughly. Continue Donor Platform build for b2c Accomplishment Completed stepper 2 component though it was complex Development for all the planned sprint stories are completed | J55: Peer CRC:0 Onsite CRC:0 Client CRC: 0 Internal Defects:0 External Defects: 0 Pending reason DON-185 - Checkout Steeper 2 was complex and Stepper 3 was dependent on Stepper 2 which kind of delayed completing Stepper 3, development completed and shared the PR | K55: A very challenging Sprint, everyone in retro acknowledged it. What went well? A lot got completed given how complex some of the stories turned out to be What didn’t go well? Checkout Steeper 2 was complex and Stepper 3 was dependent on Stepper 2 which kind of delayed completing Stepper 3 The scenarios for back button were a lot more than the effort originally planned by the team Delay in response from B2C team given the different time zones Kudos Joe: Team did a great job on(+1 Mike H, +1 Rajesh , +1 Alice) OB price sorting as we knew it has potential to cause issues. The team did a great job Donor side - great job on Stepper Kudos to Prabhu for keeping everyone on schedule and peer reviews with the OB release coming up. He has done a lot in leading the team (+1 Mike H, +1 Rajesh , +1 Alice) Alice found some issues which we missed, thanks for the thorough testing( +1 Prabhu) Thanks Mike on taking lead on the OP Apigee URL switch Alice: Joe and Prabhu for support on testing efforts Shout out to Derek for all the last minute information close to release(+1 Joe, +1 Prabhu) Great testing and test plans from Mercy and Murugasen Prabhu: Joe for leading the way for MFA and lot of insights on the work in the Sprint Offshore got a lot done this sprint even though we couldn’t mark those complete | N55: 3 | O55: 2
A56: =IF(AND($D$1>=C56,$D$1<=D56),"CurrentSprint","NA") -> NA | B56: OB-OP 8.5 Sprint 3 | C56: 46079 | D56: 46093 | E56: 14 | F56: 14 | G56: 5/0 | I56: Release OB 8.4.0 to PRD. OP Security Items. Continue Donor Platform work Accomplishment Completed the current sprint assigned stories Made very good progress on the 2 stretch stories - Development completed and PR raised | J56: Peer CRC:0 Onsite CRC:0 Client CRC: 2 Internal Defects:2 External Defects: 0 Client CRC 1. Implement timeout and response size handling 2. This response status needs to get checked & errors handled according to their type. Internal Defect DON-312, DON-313 - Both features were working during the development and local testing phases. However, after making a few code changes based on Prabu’s and Joe’s suggestions, this part of the logic was missed somehow. | K56: Well Done team for completed a good Sprint. A lot positive feedback for the foort which went in for the OB release. What went well? Prod release went well Completed all the planned stories What didn’t go well? Working with B2C team took more time than planned given their availability Reproducing OP errors was challenging Kudos Joe: Some really good work on Checkout Irsath and arivalagan and Prabhu backed me on this, don 128 Release went well (+1 Derek) Thanks for offshore for the great work and Prabhu Sankar [C], a lot of time was spent on OB for the last few months. I really appreciate all the work A ton of automation works which goes in with UX changes, thanks to Alice for taking care of all the automation work Derek for dealing with all the client interaction Alice: Entire team for a great release OB 8.4.0 (+1 Prabhu, +1 Rajesh, +1 Mike) Derek for managing all our stories and progression for the OB UX release(+1 Joe) Offshore QA Mercy for good testing leading to a smooth release CS also helped in identifying a lot of issues which the team was able to fix before the release Prabhu: Don 128 and Don 129 Irsath, arivalagan, kanna and Ubai for the progress on it Rajesh for helping in identifying the root cause of the OP issue Mike: Joe for making great strides on the B2c stories (+1 Prabhu) Anything that needs to be highlighted from the past Sprint Ob UX release went well and that will increase the performance going forward Takeaways If we have mock data and put it in a local file and not into the repository Point the stories better to be able to complete the stories without getting stretched Going forward for the next releases, as a team we need to remind ourselves that given a deadline we need to release the MVP for the release and tackle the rest in the next release instead of stretching ourselves | N56: 1 | O56: 2
A57: =IF(AND($D$1>=C57,$D$1<=D57),"CurrentSprint","NA") -> NA | B57: OB-OP 8.5 Sprint 4 | C57: 46093 | D57: 46107 | E57: 10 | F57: 10 | G57: 6/0 | I57: OB 8.5.0 CRT release and continue with Donor work Accomplishment 1. Completed current sprint stories and made good progress on stretch stories as well, development completed and gave for peer review 2. Did good work on checkout pages | J57: Peer CRC:0 Onsite CRC:1 Client CRC: 2 Internal Defects:0 External Defects: 0 Client CRC 1. withCredentials: true is applied to all requests unconditionally here. The issue is a lack of domain check. 2. Any authorized user could pass a cardReferenceId. We need to extract claims. Onsite CRC If we are passing firstname to this method as a first parameter, should we receive it as a firstname right? Creating confusions b/w firstname and username . Name it as relevant | K57: Well Done on another great sprint! What went well? Completed the planned stories and a few stretch What didn’t go well? Dependency on B2C and GCP team was a blocker It was challenging for the team to reproduce the OP splash page error Kudos Joe: Nice job on Checkout : Prabhu has been working on that feature for 2 weeks now Rajesh, Karthi and Preethi were able to find where to make the change for OP splash page issue (+1 Mike Horihan) Thanks for all quick quick work on OB for the Crt release- Alice and offshore Alice: Offshore and Murugasen for good test plans and good testing documentation Dev team for all the work on the release Prabhu: Ob/OP offshore team for completing the bugs for the release fast Donor team did a great job on the checkout step Mike: Joe for continuing to work on B2C (+1 Rajesh, +1 Prabhu) | N57: 9 | O57: 8
A58: =IF(AND($D$1>=C58,$D$1<=D58),"CurrentSprint","NA") -> NA | B58: OB-OP 8.6.0 Sprint 1 | C58: 46107 | D58: 46121 | E58: 16 | F58: 20 | G58: 9/0 | H58: Worked on the checkout and household functionality Updated the payment component and cancellation token | I58: OB 8.5.0 Prod release, continue Donor Platform Checkout work, some of OB and OP stories Accomplishment Completed current sprint stories Took 3 stories from backlog and completed 2 Client mentioned in standup that most of the PRs were ready for review in first week of the sprint itself | J58: Peer CRC:0 Onsite CRC:0 Client CRC: 2 Internal Defects:0 External Defects: 0 Client CRC 1. Log the exception with account Id. Do not bubble the accountId in the exception revealing it 2. Let's correct this string interpolation for Angular's binding system while we're in here. We miss this sometimes. | K58: Well Done Team for keeping up the momentum and completing more than planned! What went well? Completed more than planned stories What didn’t go well? Connecting with B2C team has been challenging Configuration stuff for Donor environment took a lot of time The audit process for Donor initial release is time taking Kudos Lot of great work on Donor tickets this sprint The payment component and cancellation token work from offshore donor and Rajesh is appreciated Appreciate Rajesh's stepping up getting the PRs through and made it seamless Donor - Murugasen has put together a lot of good test plans and good testing The release went well, a lot of good testing over all so kudos to the team on it Nivetha has already started creating test plans running, thanks to the entire teams support in it Joe for supporting for all the PRs and local testing Offshore Donor and OB team for completing all tickets. Whole team, has always been self managing | N58: 4 | O58: 7
A59: =IF(AND($D$1>=C59,$D$1<=D59),"CurrentSprint","NA") -> NA | B59: OB-OP 8.6.0 Sprint 2 | C59: 46121 | D59: 46135 | E59: 13 | F59: 18 | G59: 13/0 | H59: 1. Integrating login flow with Checkout 2. SNYK Remediation and manually address edit | I59: Continue Donor Platform Checkout work, some of OB and OP stories Accomplishments 1. Completed current sprint stories 2. Completed SYNK remediated stories 3. Took 7 stories from backlog and completed 4, made good progress on others | J59: Peer CRC:0 Onsite CRC:0 Client CRC: 0 Internal Defects:0 External Defects: 0 | K59: Well Done Team for all the good work! What went well? Met the Sprint commit given we have new team member What didn’t go well? B2C continues to be challenging Kudos Team did a great job , kept their foot on the gas pedal all sprint(+1 Mike ) Rajesh a lot gone done this sprint coordinating with offshore(+1 Mike ) Offshore for delivering high quality work(+1 Mike ) Rajesh supported with setup in Donor platform(+1 Mike ) Murugasen for all the testing and putting really good information on the testing report(+1 Mike ) Nivetha for taking care of testing and creating good reports (+1 Mike ) Ob and Donor offshore team for completing all the stories(+1 Mike ) Alice , Murgasen and Nivetha for all the good testing(+1 Mike ) | N59: 3 | O59: 3
A60: =IF(AND($D$1>=C60,$D$1<=D60),"CurrentSprint","NA") -> NA | B60: OB-OP 8.6.0 Sprint 3 | C60: 46135 | D60: 46149 | E60: 13 | F60: 13 | G60: 0/0 | H60: 1. Full flow needs to be the checkout (with project key as well as bidder key) 2. All service health checkup and fixing all identified issues | I60: Continue Donor Platform, some of OB and OP stories Accomplishments 1. Completed the current sprint stories 2. Great job on maintenance notification and health check work 3. Worked on B2c styling updates | J60: Peer CRC:0 Onsite CRC:0 Client CRC: 0 Internal Defects:0 External Defects: 0 | K60: Well Done Team for all the good work! What went well? ○ B2C CERT/PROD release credentials created and in progress towards implementation. ○ Exceeded expectations of story completion as well as great testing effort in Donor. What didn’t go well? ○ Reliance on 3rd party teams for routine updates in Donor environments delays our potential. Kudos ■ Thank you for the last minute testing of the OB slide out menu so we didn’t have to carry it forward. ■ Thanks for a great pre-PTO hand-off. ■ Thank you for the OP queries ■ Offshore team did a great job working within a looser-than-typical arrangement with DON-360 (catch-all), but was able to catch several bugs, resolve, retest and reiterate on some great improvements. (+1Alice) ■ Preethi was a huge help in Rajeshs’ absence. ■ Great job on B2C styling updates ■ Great job on maintenance notification and health check work ■ Great testing and fixes for OB (filter clearing and featured package appearance) done by offshore team along with some very good testing documentation from Murugesan and Nivetha. (+1 Joe) Takeaways ○ Loosen the rate limiter for DEV/TST | N60: 0 | O60: 0
A61: =IF(AND($D$1>=C61,$D$1<=D61),"CurrentSprint","NA") -> NA | B61: OB-OP 8.6.0 Sprint 4 | C61: 46149 | D61: 46163 | E61: 9 | F61: 0 | G61: 6/0 | I61: Release OP, OB & Donor | J61: Peer CRC:0 Onsite CRC:0 Client CRC: 0 Internal Defects:0 External Defects: 0 | N61: 3 | O61: 0

Sheet Unplanned Leaves
A1: Total Planned Leaves
A2: Total Unplanned Leaves | B2: 0
B3: Resource Name
A4: Sprint Name | B4: Saranya Palani | C4: Ubaithulla | D4: Arivalagan | E4: Irsath | F4: Kannan | G4: Murugesan | H4: Remarks
A5: OB-OP 8.5 Sprint 1 (29-Jan-26 to 12-Feb-2026) | B5: 0 | C5: 0 | D5: 0 | E5: 0 | F5: 0 | G5: 0 | H5: No unplanned leaves
A6: OB-OP 8.5 Sprint 2 (12-Jan-26 to 26-Feb-2026) | B6: 0 | C6: 0 | D6: 0 | E6: 0 | F6: 0 | G6: 0 | H6: No unplanned leaves
A7: OB-OP 8.5 Sprint 3 (26-Feb-26 to 12-Feb-2026)0 | B7: 0 | C7: 0 | D7: 3/11/2026 - 1 | E7: 0 | F7: 0 | G7: 0 | H7: Wife admitted in hospital
A8: OB-OP 8.5 Sprint 4 (12-Mar-26 to 26-Mar-2026) | B8: 0 | C8: 0 | D8: 0 | E8: 0 | F8: 0 | G8: 0 | H8: No unplanned leaves
A9: OB-OP 8.6.0 Sprint 1 (26-Mar-26 to 09-Apr-2026) | B9: 0 | C9: 0 | D9: 0 | E9: 4 | F9: 0 | G9: 0 | H9: Paternity Leave - 6,7,8,9 Ubai didnt take the planned leave
A10: OB-OP 8.6.0 Sprint 2 (09-Apr-26 to 23-Apr-2026) | B10: 0 | C10: 0 | D10: 0 | E10: 0 | F10: 0 | G10: 0 | H10: No unplanned leaves
A11: OB-OP 8.6.0 Sprint 3 (24-Apr-26 to 07-May-2026) | B11: 0 | C11: 0 | D11: 0 | E11: 0 | F11: 0 | G11: 0 | H11: No unplanned leaves
A18: Total | B18: 0 | C18: 0 | D18: 1 | E18: 0 | F18: 0

Sheet OB-OP 8.6.0 Sprint 4-Status
A1: S.No | B1: Application Name | C1: Sprint Start Date | D1: Sprint End Date | E1: Sprint | F1: Developer | G1: Story ID/Defect ID | H1: Description | I1: Status | J1: Estimated(hrs/sp) | K1: Actual(hrs/sp) | L1: Actual Hours Worklog | M1: Dev Start Date | N1: Dev End Date | O1: Unit testing | P1: Peer Tested By | Q1: Peer Tested Defects, if any | R1: Peer Reviewed By | S1: Peer Code Review Comments, if any | T1: PR Number/Link | U1: PR Created Date | V1: PR Approved Date | W1: Onsite Lead Code Review | X1: Code Review Comments, if any | Y1: Client Code Review | Z1: Approved Date | AA1: Code Review Comments, if any2 | AB1: Internal PO -POV Comments | AC1: Client PO -POV Comments | AD1: Comments | AE1: QA Comments
A2: 1 | B2: Donor Wave | C2: 46149 | D2: 46163 | E2: OB-OP 8.6.0 Sprint 4 | F2: Irsath | G2: DON-331 | H2: Design and implement self check-in page for Supporters - Payment Methods | I2: Being Developed | K2: 3 | M2: 46150 | AD2: 5/8/2026 - Analysis completed started development. 5/11/2026 -Started the designing 5/12/2026 - Functionality has been completed
A3: 2 | B3: Donor Wave | C3: 46149 | D3: 46163 | E3: OB-OP 8.6.0 Sprint 4 | F3: Arivalagan/Saranya | G3: DON-137 | H3: Design and implement self check-in page for Supporters - Event details | I3: Peer Review | K3: 3 | M3: 46150 | P3: Murugesan .M | Q3: 1]location and events font size should match with figma 2] Event Details should be displayed on navigate option - 3] figma shows 434 width for complete check in btn , app shows 534 width and looks bit lengthy 4 ]event details should be static like back btn in check out page - 5] hyphen should not be displayed in the header in page tile as per figma - retested 6] the check in text is not required in the appln header as we have already respective page header in the check in page -this looks double entry - 7]profile initial and edit profile option is not displayed in the right top of the page - 8] Check in page should be displayed as in the figma like ticket [ top and bottom curve should come] - 9]Org icon size should be displayed as it is in the figma | AD3: 5/8/2026 - Analysis completed started development 5/11/2026-Started the design and functionality 5/12/2026-Design and functionality completed
A4: 3 | B4: Donor Wave | C4: 46149 | D4: 46163 | E4: OB-OP 8.6.0 Sprint 4 | F4: Kannan/Ubai | G4: DON-330 | H4: Design and implement self check-in page for Supporters - Tickets | I4: Being Developed | K4: 3 | M4: 46150 | P4: Murugesan .M | Q4: 1] user name and address should be displayed in the ticket , currently events name is displayed wrongly 2] ticket box should be displayed as in the figma 3] not checked in and checked in btn color code should be displayed as in the figma 4] Edit btn should be displayed as in the figma [bold and curve] - 5]Ticket icon should be displayed as in the figma besides your ticket text - 6]Your ticket text and purchased line should be matched with figma - Retested 7]Donor user name text and size style should be displayed as in the figma - 8]edit button functionality need to be fixed and address should be updated - 9]Ticket name font size looks 18 px in figma ,but the same looks 16 px in the application UI now 10]Complete check in button width looks 436 px in figma and current ui shows 528 px width 11]ticket Image size should rounded off as 13x13 as in the figma 12] Edit Address should be displayed instead of below edit profile address label text . | AD4: 5/8/2026 - Analysis completed (UX and API) 5/11/2026-Started the design 5/12/2026-DON-137 code merged and develop completed
A5: 4 | B5: Donor Wave | C5: 46149 | D5: 46163 | E5: OB-OP 8.6.0 Sprint 4 - [STRETCH] | F5: Saranya | G5: DON-325 | H5: Donor Check-in (Event details API) - Backend | I5: Being Developed | K5: 2 | M5: 46154 | AD5: 5/12/2026 - Analysis completed start the api intergration 5/13/2026 - API development completed
A6: 5 | B6: Donor Wave | C6: 46149 | D6: 46163 | E6: OB-OP 8.6.0 Sprint 4 - [STRETCH] | F6: Ubaithullah | G6: DON-328 | H6: Donor Check-in (Tickets API) - Backend | I6: Peer Review | K6: 2 | M6: 46154 | AD6: 5/12/2026 - Analysis and development completed
A7: 6 | B7: Donor Wave | C7: 46149 | D7: 46163 | E7: OB-OP 8.6.0 Sprint 4 - [STRETCH] | F7: Irsath/Ubaithullah | G7: DON-329 | H7: Donor check-in (Create GET/SET call) - Backend | I7: Being Developed | K7: 2 | M7: 46155 | AD7: 5/13/2026 - Analysis completed started development. 5/14/2026 - 30% API has been created 5/15/2026 - 60% API has been created

Sheet OB-OP 8.6.0 Sprint 4-Defect
A1: S.No | B1: Sprint | C1: Story/Defect ID | D1: Parent Story | E1: Developer | F1: Issue Type | G1: Issue Description | H1: Priority | I1: Defect Source | J1: Type | K1: Status | L1: Root Cause Category | M1: Comments | N1: Found By | O1: RCA Comment

Sheet OB-OP 8.6.0 Sprint 3-Status
A1: S.No | B1: Application Name | C1: Sprint Start Date | D1: Sprint End Date | E1: Sprint | F1: Developer | G1: Story ID/Defect ID | H1: Description | I1: Status | J1: Estimated(hrs/sp) | K1: Actual(hrs/sp) | L1: Actual Hours Worklog | M1: Dev Start Date | N1: Dev End Date | O1: Unit testing | P1: Peer Tested By | Q1: Peer Tested Defects, if any | R1: Peer Reviewed By | S1: Peer Code Review Comments, if any | T1: PR Number/Link | U1: PR Created Date | V1: PR Approved Date | W1: Onsite Lead Code Review | X1: Code Review Comments, if any | Y1: Client Code Review | Z1: Approved Date | AA1: Code Review Comments, if any2 | AB1: Internal PO -POV Comments | AC1: Client PO -POV Comments | AD1: Comments | AE1: QA Comments
A2: 1 | B2: Donor Wave | C2: 46135 | D2: 46149 | E2: OB-OP 8.6.0 Sprint 3 | F2: Irsath | G2: DON-348 | H2: Donor b2c Styling Update | I2: Completed | J2: 1 | K2: 1 | M2: 46136 | N2: 46139 | O2: Done | P2: Murugesan.M | Q2: Nil | R2: Ubaithullah | S2: Nil | T2: https://dev.azure.com/greatergiving/Greater%20Giving/_git/Donor/pullrequest/9479 | U2: 46139 | V2: 46143 | W2: Rajesh | X2: Nil | Y2: Joe | Z2: 46143 | AA2: Nil | AB2: Nil | AC2: Nil | AD2: 4/24/2026 - Deveopment has been completed. Waiting for B2C Team Change the setting of allow external javascript access. 4/28/2026 -Unit Testing has been completed | AE2: 4/27/2026-Completed testing on style .css file 5/6/2026-Tested config scema in dev env
A3: 2 | B3: Donor Wave | C3: 46135 | D3: 46149 | E3: OB-OP 8.6.0 Sprint 3 | F3: Saranya | G3: DON-351 | H3: Donor Maintenance Notifications | I3: Completed | J3: 2 | K3: 2 | M3: 46136 | N3: 46139 | O3: Done | P3: Murugesan.M | Q3: Nil | R3: Kannan | S3: Nil | T3: https://dev.azure.com/greatergiving/Greater%20Giving/_git/Donor/pullrequest/9509 | U3: 46140 | V3: 46142 | W3: Rajesh | X3: Nil | Y3: Joe | Z3: 46143 | AA3: Nil | AB3: Nil | AC3: Nil | AD3: 4/24/2026 - implemented the maintanance notification functionality 4/27/2026 -code refactoring 4/30/2026 - migration script based code changed | AE3: 4/24/2026-Completed first round of testing 4/29/2026- Completed testing and Prepared validation doc 5/4/2026 -Regression testing 5/7/2026 - Tested in develop branch
A4: 3 | B4: Donor Wave | C4: 46135 | D4: 46149 | E4: OB-OP 8.6.0 Sprint 3 | F4: Arivalagan | G4: DON-356 | H4: Expan-health-check | I4: Completed | J4: 2 | K4: 2 | M4: 46136 | N4: 46148 | O4: Done | P4: Murugesan.M | Q4: Nil | R4: Kannan | S4: Nil | T4: https://dev.azure.com/greatergiving/Greater%20Giving/_git/Donor/pullrequest/9536 | U4: 46146 | V4: 46149 | W4: Rajesh | X4: Nil | Y4: Joe | Z4: 46149 | AA4: Nil | AB4: Nil | AC4: Nil | AD4: 4/14/2026-Analysis and stated teh implementation 4/27/2026-Implemented Profile service in repository 4/28/2026-Code refactoring issue are fixed 4/29/2026-Review code fixed | AE4: 4/24/2026- Analysis and Test Scenarios preprations 4/29/2026- Completed first round of testing 4/30/2026- regression testing 5/7/2026 - Tested in dev env
A5: 4 | B5: Donor Wave | C5: 46135 | D5: 46149 | E5: OB-OP 8.6.0 Sprint 3 | F5: Ubaitullah | G5: DON-362 | H5: Profile update email | I5: Completed | J5: 1 | K5: 1 | M5: 46136 | N5: 46136 | O5: Done | P5: Murugesan.M | Q5: Nil | R5: Kannan | S5: Nil | T5: https://dev.azure.com/greatergiving/Greater%20Giving/_git/Donor/pullrequest/9505 | U5: 46136 | V5: 46141 | W5: Rajesh | X5: Nil | Y5: Joe | Z5: 46141 | AA5: Nil | AB5: Nil | AC5: Nil | AD5: 4/24/2026 - Developement completed, Provided to QA for testing | AE5: 4/24/2026-Completed first round of testing 4/28/2026- Completed testing and Prepared validation doc
A6: 5 | B6: Donor Wave | C6: 46135 | D6: 46149 | E6: OB-OP 8.6.0 Sprint 3 | F6: Ubaitullah/ Irsath/ Kannan/Arivalagan/Saranya | G6: DON-360 | H6: Donor Catch all | I6: Completed | J6: 5 | K6: 5 | M6: 46136 | N6: 46148 | O6: Done | P6: Murugesan.M | Q6: 1.Getting internal error 500 and unser unable to login to the appication and throwing an error in console as well | R6: Irsath/Ubai | S6: Nil | T6: https://greatergiving.visualstudio.com/Greater%20Giving/_git/Donor/pullrequest/9530 https://greatergiving.visualstudio.com/Greater%20Giving/_git/Donor/pullrequest/9514 https://greatergiving.visualstudio.com/Greater%20Giving/_git/Donor/pullrequest/9536 | U6: 5/28/2026 5/4/2026 5/5/2026 | V6: 5/5/2026 5/5/2026 5/6/2026 | W6: Rajesh | X6: Nil | Y6: Joe | Z6: 5/5/2026 5/5/2026 5/6/2026 | AA6: NIl | AB6: Nil | AC6: Nil | AD6: 4/27/2026 - Bug fixing 15% has been completed 4/28/2026 - Bug fixing 20% has been completed 4/29/2026 - Bug fixing 40% has been completed 4/30/2026 - Bug fixing 70% has been completed 5/4/2026 - - Bug fixing 90% has been completed 5/5/2026 - - Bug fixing 95% has been completed 5/6/2026 - - Bug fixes has been completed and given for PR | AE6: 4/27/2026 -Retested the fixed defects 4/28/2026-Retested the fixed two defects sna reopened one issue 4/29/2026-Retested the fixed defects 4/30/2026- regression testing 5/5/2026-Retested the fixes 5/6/2026- tested in Dev env 5/7/2026 - Tested in develop branch
A7: 6 | B7: Donor Wave | C7: 46135 | D7: 46149 | E7: OB-OP 8.6.0 Sprint 3 | F7: Kannan | G7: DON-353 | H7: Correlate Project Key to Signin/ Signup | I7: Completed | J7: 2 | K7: 2 | M7: 46136 | N7: 46140 | O7: Done | P7: Murugesan.M | Q7: Nil | R7: Ubaithullah | S7: Nil | T7: Pull Request 9491: DON-353 Correlate Project Key to Signin/ Signup | U7: 46146 | V7: 46147 | W7: Rajesh | X7: Nil | Y7: Joe | Z7: 46147 | AA7: Nil | AB7: Nil | AC7: Nil | AD7: 4/24/2026 - merged the DON-130 code and testing | AE7: 4/24/2026- Analysis and Test Scenarios preprations 4/28/2026- Completed first round of testing 4/29/2026- Completed testing and Prepared validation doc 5/5/2026-Regresstion testing 5/7/2026 - Tested in develop branch

Sheet OB-OP 8.6.0 Sprint 3-Defect
A1: S.No | B1: Sprint | C1: Story/Defect ID | D1: Parent Story | E1: Developer | F1: Issue Type | G1: Issue Description | H1: Priority | I1: Defect Source | J1: Type | K1: Status | L1: Root Cause Category | M1: Comments | N1: Found By | O1: RCA Comment

Sheet OB-OP 8.6.0 Sprint 2-Status
A1: S.No | B1: Application Name | C1: Sprint Start Date | D1: Sprint End Date | E1: Sprint | F1: Developer | G1: Story ID/Defect ID | H1: Description | I1: Status | J1: Estimated(hrs/sp) | K1: Actual(hrs/sp) | L1: Actual Hours Worklog | M1: Dev Start Date | N1: Dev End Date | O1: Unit testing | P1: Peer Tested By | Q1: Peer Tested Defects, if any | R1: Peer Reviewed By | S1: Peer Code Review Comments, if any | T1: PR Number/Link | U1: PR Created Date | V1: PR Approved Date | W1: Onsite Lead Code Review | X1: Code Review Comments, if any | Y1: Client Code Review | Z1: Approved Date | AA1: Code Review Comments, if any2 | AB1: Internal PO -POV Comments | AC1: Client PO -POV Comments | AD1: Comments | AE1: QA Comments
A2: 1 | B2: Donor Wave | C2: 46121 | D2: 46135 | E2: OB-OP 8.6 Sprint 2 | F2: Saranya | G2: DON-344 | H2: Manual Address Entry Fix | I2: Completed | J2: 3 | K2: 3 | M2: 46122 | N2: 46129 | O2: Done | P2: Murugesan .M | Q2: 1]Add address text and font size and color code should match with Figma 2]City input fields should accept only 50 chrs | R2: Arivu | S2: Nil | T2: https://dev.azure.com/greatergiving/Greater%20Giving/_git/Donor/pullrequest/9474 | U2: 46127 | V2: 46129 | W2: Rajesh | X2: Nil | Y2: Joe | Z2: 46129 | AA2: Nil | AB2: Nil | AC2: Nil | AD2: 4/10/2026 -Anaylyzing story 4/13/2026 - Start the development 4/14/2026 - implemented the add address manually functionality 4/15/2026 - code refactoring and unit testing 4/16/2026 -working on review comments | AE2: 4/10/2026 -Completed analysis 4/13/2026-Test Scenario Preparations 4/16/2026- Did first round of testing 4/17/2026 - Completed testing and prepared Validation document
A3: 2 | B3: Donor Wave | C3: 46121 | D3: 46135 | E3: OB-OP 8.6 Sprint 2 | F3: Kannan/ Ubhai | G3: DON-341 | H3: Donor - SNYK Remediation | I3: Completed | J3: 3 | K3: 3 | M3: 46122 | N3: 46125 | O3: Done | P3: Murugesan .M | Q3: Nil | R3: Irsath | S3: Nil | T3: Pull Request 9461: [DON-341] Donor - SNYK Remediation | U3: 46125 | V3: 46125 | W3: Rajesh | X3: Nil | Y3: Joe | Z3: 46125 | AA3: Nil | AB3: Nil | AC3: Nil | AD3: 4/10/2026 -Anaylyzing story 4/13/2026 - Start the development and created PR | AE3: 4/10/2026 -Completed analysis 4/13/2026 -Completed Regression Testing in local branch 4/14/2026 -Completed Regression Testing in Develop branch
A4: 3 | B4: Donor Wave | C4: 46121 | D4: 46135 | E4: OB-OP 8.6 Sprint 2 | F4: Arivalagan | G4: DON-130 | H4: Integrate login flow to Checkout | I4: Completed | J4: 5 | K4: 5 | M4: 46122 | N4: 46135 | O4: Done | P4: Murugesan .M | Q4: 1]Credit card payment is not working and gets failed in checkout flow | R4: Kannan | S4: Nil | T4: https://dev.azure.com/greatergiving/Greater%20Giving/_git/Donor/pullrequest/9470 | U4: 46127 | V4: 46135 | W4: Rajesh | X4: Nil | Y4: Joe | Z4: 46135 | AA4: Nil | AB4: Nil | AC4: Nil | AD4: 4/10/2026 -Integrate the API and started the development 4/13/2026-Authentication on checkout api 4/14/2026-implement the front end code functionality 4/15/2026-Unit testing 4/16/2026- Added project key functionaltiy 4/17/2026-Fixed design changes 4/20/2026-Added Project key functionaltiy 4/21/2026-Code refactoring 4/22/2026-Code refactoring and Bidder key implementation 4/23/2026-Unit testing | AE4: 4/10/2026 -Completed analysis 4/13/2026-Test Scenario Preparations 4/16/2026- Completed first round of testing 4/17/2026 - retested after changes and raised an observation 4/21/2026-Retested the changes 4/22/2026-Retested the changes
A5: 4 | B5: Donor Wave | C5: 46121 | D5: 46135 | E5: OB-OP 8.6 Sprint 2 - [Stretch] | F5: Irsath | G5: DON-348 | H5: Donor b2c Styling Update | I5: Being Developed | J5: 2 | M5: 46125 | N5: 46128 | O5: Done | P5: Murugesan .M | Q5: Nil | R5: Ubaithullah | S5: Nil | T5: https://dev.azure.com/greatergiving/Greater%20Giving/_git/Donor/pullrequest/9479 | U5: 46128 | W5: Rajesh | X5: Nil | Y5: Joe | AB5: Nil | AC5: Nil | AD5: 4/13/2026 - Analysis done started development 4/14/2026 - Development completed 4/15/2026 - New Requirement has been added working on that 4/16/2026 - Development and unit testing has been completed 4/21/2026 - New Requirement has been added and completed. | AE5: 4/13/2026-Completed analysis and Test Scenario Preparations 4/15/2026- Completed testing and prepared Validation document 4/21/2026- Did tetsting the flows in Dev Env
A6: 5 | B6: Donor Wave | C6: 46121 | D6: 46135 | E6: OB-OP 8.6 Sprint 2 - [Stretch] | F6: Kannan | G6: DON-191 | H6: Cookie Based Session Management Migration | I6: Completed | J6: 1 | K6: 1 | M6: 46126 | N6: 46127 | O6: Done | P6: Murugesan .M | Q6: 1] Showing 401 unauthorized error msg after clicking in B2c sign in button from login page | R6: Ubaithullah | S6: Nil | T6: Pull Request 9476: [DON-191] Cookie Based Session Management Migration | U6: 46127 | V6: 46129 | W6: Rajesh | X6: Nil | Y6: Joe | Z6: 46129 | AA6: Nil | AB6: Nil | AC6: Nil | AD6: 4/14/2026 - Analysis done started development 4/15/2026 - Development done and PR created | AE6: 4/14/2026 -did Regression Testing in local branch 4/15/2026- Completed Retesting after package updates
A7: 6 | B7: Donor Wave | C7: 46121 | D7: 46135 | E7: OB-OP 8.6 Sprint 2 - [Stretch] | F7: Ubaithullah | G7: DON-349 | H7: Remove b2c Dev Backdoor | I7: Completed | J7: 2 | K7: 2 | M7: 46126 | N7: 46127 | O7: Done | P7: Murugesan .M | Q7: Nil | R7: Kannan | S7: Nil | T7: https://dev.azure.com/greatergiving/Greater%20Giving/_git/Donor/pullrequest/9420 | U7: 46127 | V7: 46127 | W7: Rajesh | X7: Nil | Y7: Joe | Z7: 46127 | AA7: Nil | AB7: Nil | AC7: Nil | AD7: 4/14/2026 - Analysis and development completed 4/15/2026 - Testing Completed PR created | AE7: 4/14/2026 -did Regression Testing in local branch
A8: 7 | B8: Donor Wave | C8: 46121 | D8: 46135 | E8: OB-OP 8.6 Sprint 2 - [Stretch] | F8: Ubaithullah | G8: DON-352 | H8: Fix User Logout | I8: Completed | J8: 1 | K8: 1 | M8: 46128 | N8: 46130 | O8: Done | P8: Murugesan .M | Q8: Nil | R8: Kannan | S8: Nil | T8: https://dev.azure.com/greatergiving/Greater%20Giving/_git/Donor/pullrequest/9483 | U8: 46129 | V8: 46132 | W8: Rajesh | X8: Nil | Y8: Joe | Z8: 46132 | AA8: Nil | AB8: Nil | AC8: Nil | AD8: 4/16/2026 - Anlaysis completed and development started 4/18/2026 - Raised PR | AE8: 4/17/2026 - Analyzed the story and prepared Test Preparation 4/20/2026 - Performed Testing and prepared Validation doc
A9: 8 | B9: Donor Wave | C9: 46121 | D9: 46135 | E9: OB-OP 8.6 Sprint 2 | F9: Kannan/Irsath | G9: DON-347 | H9: Donor Environment Configuration | I9: Completed | J9: 2 | K9: 2 | M9: 46127 | N9: 46128 | O9: Done | P9: Murugesan .M | Q9: Nil | R9: Ubaithullah | S9: Nil | T9: Pull Request 9477: [DON-347] Angular version (21.2.0) update | U9: 46127 | V9: 46128 | W9: Rajesh | X9: Nil | Y9: Joe | Z9: 46128 | AA9: Nil | AB9: Nil | AC9: Nil | AD9: 4/15/2026 - Updated packages and PR created 4/16/2026 - Requested one more package update and its updated today 4/17/2026 - Worked on Database timeout issue
A10: 9 | B10: Donor Wave | C10: 46121 | D10: 46135 | E10: OB-OP 8.6 Sprint 2 - [Stretch] | F10: Kannan | G10: DON-353 | H10: Correlate Project Key to Signin/ Signup | I10: Being Developed | J10: 3 | M10: 46129 | AD10: 4/17/2026 Started analysis [Note]: Waiting for story point | AE10: 4/21/2026- did first round of testing
A11: 10 | B11: Donor Wave | C11: 46121 | D11: 46135 | E11: OB-OP 8.6 Sprint 2 - [Stretch] | F11: Irsath | G11: DON-354 | H11: Remove Password Requirement for Legacy Login | I11: Completed | J11: 1 | K11: 1 | M11: 46132 | N11: 46132 | O11: Done | P11: Murugesan .M | Q11: Nil | R11: Ubaithullah | S11: Nil | T11: https://dev.azure.com/greatergiving/Greater%20Giving/_git/Donor/pullrequest/9488 | U11: 46132 | V11: 46132 | W11: Rajesh | X11: Nil | Y11: Joe | Z11: 46134 | AA11: Nil | AB11: Nil | AC11: Nil | AD11: 4/20/2026 - Development has been completed and PR has been created
A12: 11 | B12: Donor Wave | C12: 46121 | D12: 46135 | E12: OB-OP 8.6 Sprint 2 - [Stretch] | F12: Saranya | G12: DON-351 | H12: Donor Maintenance Notifications | I12: Being Developed | J12: 3 | M12: 46134 | AD12: 4/22/2026 - Analysis completed 4/22/2026 - start the development 4/23/2026 - implemented the functionality

Sheet OB-OP 8.6.0 Sprint 2-Defect
A1: S.No | B1: Sprint | C1: Story/Defect ID | D1: Parent Story | E1: Developer | F1: Issue Type | G1: Issue Description | H1: Priority | I1: Defect Source | J1: Type | K1: Status | L1: Root Cause Category | M1: Comments | N1: Found By | O1: RCA Comment

Sheet OB-OP 8.6.0 Sprint 1-Status
A1: S.No | B1: Application Name | C1: Sprint Start Date | D1: Sprint End Date | E1: Sprint | F1: Developer | G1: Story ID/Defect ID | H1: Description | I1: Status | J1: Estimated(hrs/sp) | K1: Actual(hrs/sp) | L1: Actual Hours Worklog | M1: Dev Start Date | N1: Dev End Date | O1: Unit testing | P1: Peer Tested By | Q1: Peer Tested Defects, if any | R1: Peer Reviewed By | S1: Peer Code Review Comments, if any | T1: PR Number/Link | U1: PR Created Date | V1: PR Approved Date | W1: Onsite Lead Code Review | X1: Code Review Comments, if any | Y1: Client Code Review | Z1: Approved Date | AA1: Code Review Comments, if any2 | AB1: Internal PO -POV Comments | AC1: Client PO -POV Comments | AD1: Comments | AE1: QA Comments
A2: 1 | B2: Donor Wave | C2: 46107 | D2: 46121 | E2: OB-OP 8.6 Sprint 1 | F2: Irsath | G2: Don-333 | H2: Fix Payment Component | I2: Completed | J2: 2 | K2: 2 | L2: 48.75 | M2: 46108 | N2: 46112 | O2: Done | P2: Murugesan .M | Q2: 1.Amex card is not adding into donor platform , showing 'Failed to add credit card accountId : 757' 2.Visa card is not adding into donor platform , showing 'Failed to add credit card accountId : 757' | R2: Arivalagan | S2: Nil | T2: https://dev.azure.com/greatergiving/Greater%20Giving/_git/Donor/pullrequest/9415 | U2: 46118 | V2: 46120 | W2: Rajesh | X2: Nil | Y2: Joe | Z2: 46120 | AA2: Nil | AB2: Nil | AC2: Nil | AD2: 3/27/2026 - Analysis done started development 3/30/2026 - I have found few GDon API side issue during save credit card 3/31/2026 - Postal code issue has been fixed 4/6/2026 - Need to verify with different cards today, once murugesan confirms, will share the PR to Rajesh today 4/7/2026 - secret key needs to be changed in joe's machine - after that only he can test in his local, so pending for that | AE2: 03/27/2026 - Completed analysis and started test scenraios 4/1/2026 -Testing is in progress 4/3/2026 -Retested the fixes and completed testing 4/9/2026 -Regression testing on Develop branch
A3: 2 | B3: Donor Wave | C3: 46107 | D3: 46121 | E3: OB-OP 8.6 Sprint 1 | F3: Kannan | G3: DON-336 | H3: Household - Front End | I3: Completed | J3: 2 | K3: 2 | L3: 28.75 | M3: 46108 | N3: 46112 | O3: Done | P3: Murugesan .M | Q3: 1.Email should be displayed in the household section 2.Dot should be displayed as it is in the attached ref ticket 3.House hold inside data icon should be aligned with section round icon - pls ref below screenshot . [ currently it shows bit right side ] 4.Title should be Partner/Spouse . currently the title shows only spouse in the UI | R3: Ubai | S3: Nil | T3: Pull Request 9416: DON-336 Household - Front End | U3: 46112 | V3: 46120 | W3: Rajesh | X3: Nil | Y3: Joe | Z3: 46120 | AA3: Log the exception with account Id. Do not bubble the accountId in the exception revealing it | AB3: Nil | AC3: Nil | AD3: 3/27/2026 - Analysis started still waiting for the full flow requirement 3/30/2026 - Development completed based on API. Expecting minor when GDON API team implementing this feature 03/31/2026 - PR Created 4/6/2026 - Pending with Prabu approval, rajesh might review today and share to Joe 4/7/2026 - need to take latest develop and resolve conflicts and test once since many PRs went yesterday | AE3: 03/27/2026 - Completed analysis and started test scenraios 4/1/2026 -Completed one round of testing and shared the observations 4/6/2026 - Completed testing and Prepared validation doc 4/8/2026 -Regression testing on Develop branch
A4: 3 | B4: Donor Wave | C4: 46107 | D4: 46121 | E4: OB-OP 8.6 Sprint 1 | F4: saranya | G4: DON-316 | H4: Checkout - Implement Error banners | I4: Completed | J4: 2 | K4: 2 | L4: 67.35 | M4: 46108 | N4: 46108 | O4: Done | P4: Murugesan .M | Q4: Nil | R4: Kannan | S4: Nil | T4: https://dev.azure.com/greatergiving/Greater%20Giving/_git/Donor/pullrequest/9408 | U4: 46108 | V4: 46120 | W4: Rajesh | X4: Nil | Y4: Joe | Z4: 46120 | AA4: Nil | AB4: Nil | AC4: Nil | AD4: 3/27/2026 -Code refactoring and unit testing 4/2/2026 - code refactoring merge with DON-321 branch 4/3/2026 -merge with develop branch 4/6/2026 - Prabu approved the PR on friday, waiting for Joe's approval 4/7/2026 - Having conflict because of recent PR completion, mock data suggestion given by joe, need to implement that | AE4: 4/1/2026 -Completed one round of testing 4/3/2026 - Completed testing and Prepared validation doc 4/7/2026 -Regression testing in Local 4/8/2026 -Regression testing on Develop branch
A5: 4 | B5: Donor Wave | C5: 46107 | D5: 46121 | E5: OB-OP 8.6 Sprint 1 | F5: Ubaithullah | G5: DON-337 | H5: Household - Backend | I5: Completed | J5: 3 | K5: 3 | L5: 39.75 | M5: 46108 | N5: 46118 | O5: Done | P5: Murugesan .M | Q5: Nil | R5: Kannan | S5: Nil | T5: https://dev.azure.com/greatergiving/Greater%20Giving/_git/Donor/pullrequest/9417 | U5: 46112 | V5: 46119 | W5: Rajesh | X5: Nil | Y5: Joe | Z5: 46119 | AA5: Nil | AB5: Nil | AC5: Nil | AD5: 3/27/2026 - Checked with GDON team need to discuss with prabhu 3/30/2026 - Development and unit testing completed 3/31/2026 - Code Refactored and PR created 4/6/2026 - Pending with Prabu approval, rajesh might review today and share to Joe | AE5: 03/27/2026 - Completed analysis and started test scenraios 4/1/2026 -Completed testing and Prepared validation doc
A6: 5 | B6: Donor Wave | C6: 46107 | D6: 46121 | E6: OB-OP 8.6 Sprint 1 | F6: Arivalagan | G6: DON-317 | H6: Checkout-Header | I6: Completed | J6: 3 | K6: 3 | L6: 83.3 | M6: 46108 | N6: 46112 | O6: Done | P6: Murugesan .M | Q6: 1]Home text should be displayed instead of checkout while clicking back option in edit profile page 2]User should not be redirected to check out page after updating the edit profile , should go to home page after updating the profile. 3]G icon should display instead of greater giving text in the left header page for mobile landscape 4]Adding profile image is not updating in the user profile initials while editing profile | R6: Saranya | S6: Nil | T6: https://dev.azure.com/greatergiving/Greater%20Giving/_git/Donor/pullrequest/9420 | U6: 46112 | V6: 46120 | W6: Rajesh | X6: Nil | Y6: Joe | Z6: 46120 | AA6: Let's correct this string interpolation for Angular's binding system while we're in here. We miss this sometimes. | AB6: Nil | AC6: Nil | AD6: 3/27/2026-Analysis and started the development 3/30/2026-Completed logout and edit profile functionaltiy 3/31/2026 - Code refactored and Project key functionatliy is implemented 4/1/2026 - Code refactored and functionality testing 4/2/2026 -Code merged with DON-316 and fixed some functionality 4/7/2026 - many code changes related to other branches are in the PR, need to take latest develop and resolve conflict and test again 4/8/2026-Review comments fixed | AE6: 03/27/2026 - Completed analysis and started test scenraios 4/1/2026 -Testing is in progress 4/02/2026 - Completed testing and Prepared validation doc 4/7/2026 -Regression testing in Local 4/8/2026 -Regression testing on Develop branch
A7: 6 | B7: Donor Wave | C7: 46107 | D7: 46121 | E7: OB-OP 8.6 Sprint 1 | F7: saranya | G7: DON-335 | H7: Update Payment Receipt Call | I7: Completed | J7: 1 | K7: 1 | L7: 21.3 | M7: 46108 | N7: 46115 | O7: Done | P7: Murugesan .M | Q7: 1.Json reader exception is thrown while clicking on download receipt in the checkout page. - Report GUIID shows undefined when debugging it. | R7: Arivalagan | S7: Nil | T7: https://dev.azure.com/greatergiving/Greater%20Giving/_git/Donor/pullrequest/9434 | U7: 46115 | V7: 46118 | W7: Prabu | X7: Nil | Y7: Joe | Z7: 46118 | AA7: Nil | AB7: Nil | AC7: Nil | AD7: 3/27/2026 -Disscuss with GDON team 4/2/2026 - changed receipt generate values 4/3/2026 -unit testing and merge with develop branch 4/6/2026 - Prabu approved the PR on friday, waiting for Joe's approval | AE7: 03/27/2026 - Completed analysis and started test scenraios 4/3/2026 -Retested the fixes and Completed testing and Prepared validation doc
A8: 7 | B8: Donor Wave | C8: 46107 | D8: 46121 | E8: OB-OP 8.6 Sprint 1 | F8: Kannan/ Ubhai | G8: DON-321 | H8: Add Cancellation Token and Size Constraints to Download Feature | I8: Completed | J8: 2 | K8: 2 | L8: 31 | M8: 46119 | N8: 46119 | O8: Done | P8: Murugesan .M | Q8: Nil | R8: Ubai/Kannan | S8: Nil | T8: Pull Request 9396: DON-321 Add Cancellation Token and Size Constraints to Download Feature | U8: 46108 | V8: 46120 | W8: Prabu | X8: Nil | Y8: Joe | Z8: 46120 | AA8: Nil | AB8: Nil | AC8: Nil | AD8: PR Created last sprint itself waiting for Prabhu and Joe review. If any obervation from them, will work on it. Prabu approved, waiting for Joe's approval - 4/6/2026 PR suggestion branch came from joe - need to check that and update whichever is necessary - 4/7/2026 | AE8: 4/7/2026 -Regression testing in Local 4/8/2026 -Regression testing on Develop branch
A9: 8 | B9: Donor Wave | C9: 46107 | D9: 46121 | E9: OB-OP 8.6 Sprint 1 - [Stretch] | F9: Irsath | G9: DON-338 | H9: Update automapper | I9: Completed | J9: 1 | K9: 1 | L9: 11.5 | M9: 46114 | N9: 46114 | O9: Done | P9: Murugesan .M | Q9: Nil | R9: Kannan | S9: Nil | T9: https://dev.azure.com/greatergiving/Greater%20Giving/_git/Donor/pullrequest/9432 | U9: 46115 | V9: 46119 | W9: Prabu | X9: Nil | Y9: Joe | Z9: 46118 | AA9: Nil | AB9: Nil | AC9: Nil | AD9: 4/2/2026 - Development completed 4/3/2026 - Given for PR 4/6/2026 - Prabu approved the PR on friday, waiting for Joe's approval | AE9: 4/6/2026- regression testing in Local
A10: 9 | B10: Donor Wave | C10: 46107 | D10: 46121 | E10: OB-OP 8.6 Sprint 1 | F10: Ubaithullah | G10: DON-334 | H10: Migration script for CC types | I10: Completed | J10: 1 | K10: 1 | L10: 7 | M10: 46114 | N10: 46114 | O10: Done | P10: Murugesan .M | Q10: Nil | R10: Kannan | S10: Nil | T10: https://dev.azure.com/greatergiving/Greater%20Giving/_git/Donor/pullrequest/9427 | U10: 46114 | V10: 46119 | W10: Rajesh | X10: Nil | Y10: Joe | Z10: 46119 | AA10: Nil | AB10: Nil | AC10: Nil | AD10: 4/2/2026 - Development and unit testing completed, PR raised 4/7/2026 - Implemented the suggestions given by Rajesh, took latest develop and resolved conflicts, will be sharing the PR tonight | AE10: 4/02/2026 - Completed testing and Prepared validation doc
A11: 10 | B11: Donor Wave | C11: 46107 | D11: 46121 | E11: OB-OP 8.6 Sprint 1 - [Stretch] | F11: Kannan/ Ubhai /Irsath | G11: DON-340 | H11: Dev, TST, CRT environmental setup | I11: Completed | J11: 3 | K11: 3 | L11: 67.25 | M11: 46115 | N11: 46120 | O11: Done | P11: Murugesan .M | Q11: 1.Application is not loading due to HouseholdRepository service is missed in the service | R11: Saranya/Arivu | S11: Nil | T11: Pull Request 9448: [DON-340] Dev, TST, CRT environmental setup | U11: 46120 | V11: 46120 | W11: Rajesh | X11: Nil | Y11: Joe | Z11: 46120 | AA11: Nil | AB11: Nil | AC11: Nil | AD11: 4/3/2026 - Analysis done started development 4/6/2026 - Code comments and removed logs which are not needed (API end) 4/8/2026 - Code comments and created PR | AE11: 4/8/2026 -Regresstion testing on Develop branch
A12: 11 | B12: Donor Wave | C12: 46107 | D12: 46121 | E12: OB-OP 8.6 Sprint 1 - [Stretch] | F12: Arivalagan/Saranya | G12: DON-130 | H12: Integrate login flow to Checkout | I12: Being Developed | J12: 5 | L12: 22 | M12: 46118 | AD12: 4/6/2026-Analysis and started the development 4/9/2026-Code impelementation

Sheet OB-OP 8.6.0 Sprint 1-Defect
A1: S.No | B1: Sprint | C1: Story/Defect ID | D1: Parent Story | E1: Developer | F1: Issue Type | G1: Issue Description | H1: Priority | I1: Defect Source | J1: Type | K1: Status | L1: Root Cause Category | M1: Comments | N1: Found By | O1: RCA Comment

Sheet OB-OP 8.5 Sprint 4-Status
A1: S.No | B1: Application Name | C1: Sprint Start Date | D1: Sprint End Date | E1: Sprint | F1: Developer | G1: Story ID/Defect ID | H1: Description | I1: Status | J1: Estimated(hrs/sp) | K1: Actual(hrs/sp) | L1: Actual Hours Worklog | M1: Dev Start Date | N1: Dev End Date | O1: Unit testing | P1: Peer Tested By | Q1: Peer Tested Defects, if any | R1: Peer Reviewed By | S1: Peer Code Review Comments, if any | T1: PR Number/Link | U1: PR Created Date | V1: PR Approved Date | W1: Onsite Lead Code Review | X1: Code Review Comments, if any | Y1: Client Code Review | Z1: Approved Date | AA1: Code Review Comments, if any2 | AB1: Internal PO -POV Comments | AC1: Client PO -POV Comments | AD1: Comments | AE1: QA Comments
A2: 1 | B2: Donor Wave | C2: 46093 | D2: 46107 | E2: OB-OP 8.5 Sprint 4 | F2: Saranya | G2: DON-324 | H2: Checkout - Manage Card Payment Selection/Storage | I2: Completed | J2: 3 | K2: 3 | L2: 82 | M2: 46094 | N2: 46106 | O2: Done | P2: Murugesan .M | Q2: 1.WHen existing card is disabled , then respective billing address should not be displayed in the billing address section 2.Instaed of user name string text is displayed in the downloaded checkout receipt pdf file | R2: Kannan | S2: Nil | T2: https://dev.azure.com/greatergiving/Greater%20Giving/_git/Donor/pullrequest/9390 | U2: 46100 | V2: 46107 | W2: Prabu | X2: Nil | Y2: Joe | Z2: 46107 | AA2: Nil | AB2: Nil | AC2: Nil | AD2: 3/13/2026-analysis completed 3/16/2026-unit tesing and code refactoring 3/17/2026 - Added new paramater check with GDON team 3/19/2026 - code refactoring and unit testing 3/24/2026 - Fixed space issue for added CC 3/25/2026 - Merged with develop and tested in the local, updated PR | AE2: 3/13/2026- Completed Analysis and Test Scenarios Preparations are in progress 3/16/2026 - Worked on Test case updates 3/17/2026 - Completed the testing 3/24/2026 -Regression Testing
A3: 2 | B3: Donor Wave | C3: 46093 | D3: 46107 | E3: OB-OP 8.5 Sprint 4 | F3: Irsath | G3: DON-319 | H3: Fix reCAPTCHA Validation in Checkout Payment Flow | I3: Completed | J3: 2 | K3: 2 | L3: 45 | M3: 46094 | N3: 46099 | O3: Done | P3: Murugesan .M | Q3: Nil | R3: Arivalagan | S3: Nil | T3: https://dev.azure.com/greatergiving/Greater%20Giving/_git/Donor/pullrequest/9401 | U3: 46105 | V3: 46106 | W3: Prabu | X3: Nil | Y3: Joe | Z3: 46106 | AA3: Nil | AB3: Nil | AC3: Nil | AD3: 3/13/2026 - Analysis done started development 3/16/2026 - Found out 2 time api call during exception 3/17/2026 - reCaptcha testing done it works as expected 3/24/2026 - PR has been created 3/25/2026 - PR approved | AE3: 3/13/2026- Completed Analysis and Test Scenarios Preparations are in progress 3/16/2026 - Worked on Test case updates 3/17/2026 - Completed testing 3/24/2026-3/20/2026 -Completed analysis and prepared the test scenarios and did first round of tesing 3/25/2026 - Completed testing and prepared the validation doc and updated in JIRA 3/26/2026 - Verified this in Dev Branch
A4: 3 | B4: Donor Wave | C4: 46093 | D4: 46107 | E4: OB-OP 8.5 Sprint 4 | F4: Kannan, Ubhaithulla | G4: DON-320 | H4: Implement Authorization Attributes and Token Claims Across Controllers | I4: Completed | J4: 3 | K4: 3 | L4: 83.75 | M4: 46094 | N4: 46098 | O4: Done | P4: Murugesan .M | Q4: Nil | R4: Irsath | S4: Nil | T4: https://dev.azure.com/greatergiving/Greater%20Giving/_git/Donor/pullrequest/9382 | U4: 46098 | V4: 46107 | W4: Prabu | X4: If we are passing firstname to this method as a first parameter, should we receive it as a firstname right? Creating confusions b/w firstname and username . Name it as relevant | Y4: Joe | Z4: 46107 | AA4: 1. withCredentials: true is applied to all requests unconditionally here. The issue is a lack of domain check. 2. Any authorized user could pass a cardReferenceId. We need to extract claims. | AD4: 3/13/2026 - Analysis done started development 3/16/2026 - Implemented JWT based cookie authentication and code clean up 3/17/2026 - Code refactoring and completed the testing , PR has been created 3/23/2026 - Prabu reviewed and approved the PR, waiting for Joe's approval 3/25/2026 - Joe gave review comment, updating that | AE4: 3/13/2026- Completed Analysis and Test Scenarios Preparations are in progress 3/16/2026 -did one round of testing on donor application 3/18/2026- Completed the testing 3/19/2026: -Prepared the validation document and updated in the JIRA
A5: 4 | B5: Donor Wave | C5: 46093 | D5: 46107 | E5: OB-OP 8.5 Sprint 4 | F5: saranya | G5: DON-314 | H5: Checkout-Donation | I5: Completed | J5: 1 | K5: 1 | L5: 8.5 | M5: 46099 | N5: 46099 | O5: Done | P5: Murugesan .M | Q5: Nil | R5: irsath | S5: Nil | T5: https://dev.azure.com/greatergiving/Greater%20Giving/_git/Donor/pullrequest/9366 | U5: 46093 | W5: Prabu | X5: Nil | Y5: Joe | Z5: 46107 | AA5: Nil | AB5: Nil | AC5: Nil | AD5: 3/18/2026 - Added add donation value sum in subtotal stepper 1 3/19/2026 - Prabhu approved the PR,waiting for joe approval - Since OB CRT release is priority this is still under Joe's review 3/25/2026 - Since Joe was working on another MFA story , he didn't approve this PR yet
A6: 5 | B6: Donor Wave | C6: 46093 | D6: 46107 | E6: OB-OP 8.5 Sprint 4 | F6: Irsath | G6: DON-315 | H6: Checkout - Remove Donation | I6: Completed | J6: 1 | K6: 1 | L6: 8.5 | M6: 46099 | N6: 46099 | O6: Done | P6: Murugesan .M | Q6: Nil | R6: saranya | S6: Nil | T6: https://dev.azure.com/greatergiving/Greater%20Giving/_git/Donor/pullrequest/9366 | U6: 46093 | V6: 46107 | W6: Prabu | X6: Nil | Y6: Joe | Z6: 46107 | AA6: Nil | AB6: Nil | AC6: Nil | AD6: 3/19/2026 - Prabhu approved the PR,waiting for joe approval - Since OB CRT release is priority this is still under Joe's review 3/25/2026 - Since Joe was working on another MFA story , he didn't approve this PR yet -
A7: 6 | B7: Donor Wave | C7: 46093 | D7: 46107 | E7: OB-OP 8.5 Sprint 4 - [STRETCH] | F7: Kannan, Irsath | G7: DON-321 | H7: Add Cancellation Token and Size Constraints to Download Feature | I7: Being Developed | J7: 3 | L7: 79 | M7: 46100 | N7: 46105 | O7: Done | P7: Murugesan .M | Q7: 1.The error message is not coming up when file size exceeds the limit 2.Donwload progress % should not be displayed when file size exceeds the limit | R7: Ubai | S7: Nil | T7: https://greatergiving.visualstudio.com/Greater%20Giving/_git/Donor/pullrequest/9396 | U7: 46105 | W7: Prabu | Y7: Joe | AB7: Nil | AC7: Nil | AD7: 3/19/2026 - Analysis done started development 3/20/2026 - Development completed and handover to testing 3/25/2026 - Will be sharing the PR to Joe tonight | AE7: 3/20/2026 -Completed analysis and prepared the test scenarios and did first round of tesing 3/23/2026 - Completed testing and prepared the validation doc and updated in JIRA
A8: 7 | B8: Donor Wave | C8: 46093 | D8: 46107 | E8: OB-OP 8.5 Sprint 4 - [STRETCH] | F8: Saranya,Arivu | G8: DON-316 | H8: Checkout - Implement Error banners | I8: Being Developed | J8: 3 | L8: 71.85 | M8: 46104 | AD8: 3/23/2026 -Analysis done start the development 3/24/2026 - Added design for banner 3/25/2026 - Implemented banner functionality | AE8: 3/23/2026 - Completed analysis 3/24/2026 - Prepared Test Scenarios 3/26/2026 - Did first round testing for the implemented messages

Sheet OB-OP 8.5 Sprint 3-Status
A1: S.No | B1: Application Name | C1: Sprint Start Date | D1: Sprint End Date | E1: Sprint | F1: Column1 | G1: Developer | H1: Story ID/Defect ID | I1: Description | J1: Status | K1: Estimated(hrs/sp) | L1: Actual(hrs/sp) | M1: Actual Hours Worklog | N1: Dev Start Date | O1: Dev End Date | P1: Unit testing | Q1: Peer Tested By | R1: Peer Tested Defects, if any | S1: Peer Reviewed By | T1: Peer Code Review Comments, if any | U1: PR Number/Link | V1: PR Created Date | W1: PR Approved Date | X1: Onsite Lead Code Review | Y1: Code Review Comments, if any | Z1: Client Code Review | AA1: Approved Date | AB1: Code Review Comments, if any2 | AC1: Internal PO -POV Comments | AD1: Client PO -POV Comments | AE1: Comments | AF1: QA Comments
A2: 1 | B2: Donor Wave | C2: 46079 | D2: 46093 | E2: OB-OP 8.5 Sprint 3 | G2: Irsath/Arivalagan | H2: Don-128 | I2: Call GGO Receipt and display | J2: Completed | K2: 5 | L2: 5 | M2: 106 | N2: 46080 | O2: 46087 | P2: Done | Q2: Murugesan M | R2: 1.company name is not coming up in the receipt when user added company name in the business address type 2.billing address is not displayed in PDF file when adding CC with forced billing address in checkout page | S2: Ubaithullah | T2: Nil | U2: https://dev.azure.com/greatergiving/Greater%20Giving/_git/Donor/pullrequest/9355 | V2: 46086 | W2: 46092 | X2: Prabu | Y2: Nil | Z2: Joe | AA2: 46092 | AB2: 1. Implement timeout and response size handling 2. This response status needs to get checked & errors handled according to their type. | AC2: Nil | AD2: Nil | AE2: 2/27/2026 - Analysis completed , Developement started 3/2/2026 - API has been created 3/3/2026 - Generate PDF viewer implemented 3/4/2026 - Development has been completed and given for testing 3/5/2026 - Testing completed.PR has been created | AF2: 2/27/2026- Analysis 3/2/22026 -Test Scenarios Preparations 3/4/22026 -Test Case Updates 3/10/2026 -Tested the download file functionality 3/11/2026 -completed testing and Prepared validation doc
A3: 2 | B3: Donor Wave | C3: 46079 | D3: 46093 | E3: OB-OP 8.5 Sprint 3 | G3: Saranya | H3: DON-185 | I3: Checkout componnet stepper 3 | J3: Completed | K3: 2 | L3: 2 | M3: 47.5 | N3: 46080 | O3: 46086 | P3: Done | Q3: Murugesan M | R3: Nil | S3: Kannan | T3: Nil | U3: https://dev.azure.com/greatergiving/Greater%20Giving/_git/Donor/pullrequest/9307 | V3: 46087 | W3: 46091 | X3: Prabu | Y3: Nil | Z3: Joe | AA3: 46091 | AB3: Nil | AC3: Nil | AD3: Nil | AE3: 3/2/2026 - working on design issue 3/4/2026 - code review 3/6/2026 - prabu made few updates and shared to Joe for review | AF3: 2/27/2026-Retested the fixes and 3/3/2026 -Regressioin testing
A4: 3 | B4: Donor Wave | C4: 46079 | D4: 46093 | E4: OB-OP 8.5 Sprint 3 | G4: Ubaithullah/ Kannan | H4: DON-129 | I4: Update GGO with Payment information on Completion | J4: Completed | K4: 5 | L4: 5 | M4: 149.25 | N4: 46080 | O4: 46091 | P4: Done | Q4: Murugesan M | R4: 1.Confirm and pay checkout button is not working and showing error as payment not completed , not found in console when processing for the existing credit card which was created from home page | S4: Irsath | T4: Nil | U4: https://greatergiving.visualstudio.com/Greater%20Giving/_git/Donor/pullrequest/9356 | V4: 46091 | W4: 46093 | X4: Prabu | Y4: Nil | Z4: Joe | AA4: 46093 | AB4: Nil | AC4: Nil | AD4: Nil | AE4: 02/27/2026 - Analysis completed share the observations to Prabhu 03/02/2026 - Backend API and UI changes implementation started 03/03/2026 - UX implemention completed 03/04/2026 - Constructed the JSON data and backend code refactor 04/04/2026 - Integrated UX and Backend and unit testing in progress | AF4: 2/27/2026- Analysis 3/2/22026 -Test Scenarios Preparations 3/6/22026 -Tested the backend flows 3/9/22026 -Tested the UI checkout functionality 3/10/2026 -Regression testing 3/11/2026 -Completed testing and Prepared validation doc 3/12/2026- -Regression testing after code review comments fix
A5: 4 | B5: Donor Wave | C5: 46079 | D5: 46093 | E5: OB-OP 8.5 Sprint 3 | G5: saranya | H5: DON-312 | I5: Getting Error contact support banner message in the stepper 2 checkout page | J5: Completed | K5: 1 | L5: 1 | M5: 10.3 | N5: 46080 | O5: 46080 | P5: Done | Q5: Murugesan M | R5: Nil | S5: Arivalagan | T5: Nil | U5: https://dev.azure.com/greatergiving/Greater%20Giving/_git/Donor/pullrequest/9331 | V5: 46080 | W5: 46086 | X5: Prabu | Y5: Nil | Z5: Joe | AA5: 46086 | AB5: Nil | AC5: Nil | AD5: Nil | AE5: 2/27/2026- fixed banner error message 3/5/2026 - SInce OB is going for production, waiting for Joe's approval | AF5: 2/27/2026-Retested the fixes and Regressioin testing
A6: 5 | B6: Donor Wave | C6: 46079 | D6: 46093 | E6: OB-OP 8.5 Sprint 3 | G6: saranya | H6: DON-313 | I6: Edit Billing address is not updating the address value while modifying any of the fields in the address section | J6: Completed | K6: 1 | L6: 1 | M6: 11.3 | N6: 46080 | O6: 46080 | P6: Done | Q6: Murugesan M | R6: Nil | S6: Arivalagan | T6: Nil | U6: https://dev.azure.com/greatergiving/Greater%20Giving/_git/Donor/pullrequest/9331 | V6: 46080 | W6: 46086 | X6: Prabu | Y6: Nil | Z6: Joe | AA6: 46086 | AB6: Nil | AC6: Nil | AD6: Nil | AE6: 2/27/2026 - add address and edit address has been fixed 3/5/2026 - SInce OB is going for production, waiting for Joe's approval | AF6: 2/27/2026-Retested the fixes and Regressioin testing
A7: 6 | B7: Donor Wave | C7: 46079 | D7: 46093 | E7: OB-OP 8.5 Sprint 3 - [STRETCH] | G7: Irsath/Arivalagan | H7: Don-315 | I7: Checkout - Remove Donation | J7: Peer Review | K7: 3 | M7: 60.5 | N7: 46087 | O7: 46092 | P7: Done | Q7: Murugesan M | R7: 1.Added donation should be displayed in the stepper summary page | S7: Kannan | T7: Nil | U7: https://dev.azure.com/greatergiving/Greater%20Giving/_git/Donor/pullrequest/9366 | V7: 46092 | X7: Prabu | Y7: Nil | Z7: Joe | AB7: Nil | AC7: Nil | AD7: Nil | AE7: 3/6/2026 - Analysis completed , Developement started 3/9/2026 - Trash icon implemented 3/10/2026 - Values passed to salesinfo object and given for testing 3/11/2026 - Unit testnig done PR has been created 3/12/2026 - Code has been merged with 314 | AF7: 3/6/2026 - Analysis 3/10/2026-Prepared test scenarios 3/11/2026-Completed testing and Prepared validation doc 3/12/2026- -Regression testing after code review comments fix
A8: 7 | B8: Donor Wave | C8: 46079 | D8: 46093 | E8: OB-OP 8.5 Sprint 3 - [STRETCH] | G8: Saranya | H8: DON-314 | I8: Checkout - Donation | J8: Peer Review | K8: 2 | M8: 45.8 | N8: 46087 | O8: 46093 | P8: Done | Q8: Murugesan M | R8: Nil | S8: Ubai | T8: Nil | U8: https://dev.azure.com/greatergiving/Greater%20Giving/_git/Donor/pullrequest/9366 | V8: 46092 | X8: Prabu | Z8: Joe | AE8: 3/6/2026 -Analysis completed ,started development 3/9/2026 - completed the functionality and unit testing 3/11/2026 -unit testing and code refactoring. | AF8: 3/6/2026 : Analysis 3/10/2026-Prepared test scenarios 3/11/2026-completed testing and Prepared validation doc

Sheet OB-OP 8.5 Sprint 4-Defect
A1: S.No | B1: Sprint | C1: Story/Defect ID | D1: Parent Story | E1: Developer | F1: Issue Type | G1: Issue Description | H1: Priority | I1: Defect Source | J1: Type | K1: Status | L1: Root Cause Category | M1: Comments | N1: Found By | O1: RCA Comment

Sheet OB-OP 8.5 Sprint 3-Defect
A1: S.No | B1: Sprint | C1: Story/Defect ID | D1: Parent Story | E1: Developer | F1: Issue Type | G1: Issue Description | H1: Priority | I1: Defect Source | J1: Type | K1: Status | L1: Root Cause Category | M1: Comments | N1: Found By | O1: RCA Comment
B2: 1 | C2: DON-313 | D2: Previous sprint | E2: saranya | F2: Defect | G2: Edit Billing address is not updating the address value while modifying any of the fields in the address section | H2: Major | I2: Manual | J2: Internal | K2: Closed | L2: Existing_Issues | M2: Fixed add and edit address while adding credit card | N2: Murugesan
B3: 2 | C3: DON-312 | D3: Previous sprint | E3: saranya | F3: Defect | G3: Getting Error contact support banner message in the stepper 2 checkout page | H3: Significant | I3: Manual | J3: Internal | K3: Closed | L3: Existing_Issues | M3: fixed banner error message | N3: Murugesan

Sheet OB-OP 8.5 Sprint 2-Status
A1: S.No | B1: Application Name | C1: Sprint Start Date | D1: Sprint End Date | E1: Sprint | F1: Developer | G1: Story ID/Defect ID | H1: Description | I1: Status | J1: Estimated(hrs/sp) | K1: Actual(hrs/sp) | L1: Actual Hours Worklog | M1: Dev Start Date | N1: Dev End Date | O1: Unit testing | P1: Peer Tested By | Q1: Peer Tested Defects, if any | R1: Peer Reviewed By | S1: Peer Code Review Comments, if any | T1: PR Number/Link | U1: PR Created Date | V1: PR Approved Date | W1: Onsite Lead Code Review | X1: Code Review Comments, if any | Y1: Client Code Review | Z1: Approved Date | AA1: Code Review Comments, if any2 | AB1: Internal PO -POV Comments | AC1: Client PO -POV Comments | AD1: Comments | AE1: QA Comments
A2: 1 | B2: Donor Wave | C2: 46065 | D2: 46079 | E2: OB-OP 8.5 Sprint 2 | F2: Ubaithullah / Kannan | G2: DON-185 | H2: Checkout Body Components - Stepper 3 | I2: Peer Review | J2: 3 | K2: 1 | L2: 127.25 | M2: 46066 | P2: Murugesan M | Q2: 1.Confirmation text should be displayed when stepper 3 is selected in the page 2.Confirmation page should be displayed properly when scroll up the content in the page, currently it goes up beyond stepper progress 3.Payment label and below text all transaction are secure and encrypted text should be displayed in the payment section 4.Confirmation layout should be 600 px and each section should be 552 px width, currently it shows extra width as 750. 5.Billing address should be color code #04041CF2 and size should be 16 px as per figma 6.Colon should be displayed after Total text in the section and total and value should be color code #212529 as per figma 7.View detils button should not be displayed in the blue color background by default , only the text color should be in #262AFF 8.Need space between card name and expiry text in the payment section for 430 responsive view 9.circle with tick icon of confirmation looks bit small while comparing to Figma, fix this if possible | T2: https://dev.azure.com/greatergiving/Greater%20Giving/_git/Donor/pullrequest/9307 | U2: 46073 | W2: Prabu | AD2: 13/02/2026 - Analysis completed , Developement started 16/02/2026 - Design completed and merging with stepper-2 in progress 17/02/2026 - Functionality implementation in progress 18/02/2026 - Created checkout- confirmation component and design 19/02/2026 - Code refactor and code merge with DON-184 20/02/2026 - PR Created and code refactored 23/02/2026 - Code merge from DON-184 and code changes 24/02/2026 - QA findings fixed 25/02/2026 - Merged with DON-184 26/02/2026 - Meged with DON-184 | AE2: 2/13/2026:Analysis and Test Scenarios Prep 2/16/2026 : Test Scenarios Updates 2/23/2026: Completed first round of testing and raised issues 2/24/2026: Completed testing and retested the fixes as well - working fine and Prepared the validation doc and updated in JIRA
A3: 2 | B3: Donor Wave | C3: 46065 | D3: 46079 | E3: OB-OP 8.5 Sprint 2 | F3: Irsath | G3: DON-195 | H3: Add Check Out button to Donor Events | I3: Completed | J3: 2 | K3: 2 | L3: 36.25 | M3: 46066 | N3: 46069 | O3: Done | P3: Murugesan M | Q3: 1.Stepper should be displayed as per figma 2.Scroll bar should not come in the page | R3: Arivalagan | S3: Nil | T3: https://dev.azure.com/greatergiving/Greater%20Giving/_git/Donor/pullrequest/9297 | U3: 46070 | V3: 46079 | W3: Prabu | X3: Nil | Y3: Joe | Z3: 46079 | AA3: Nil | AB3: Nil | AC3: Nil | AD3: 13/02/2026 - Analysis completed , Developement started 2/16/2026 - Development has been completed and given for testing | AE3: 2/13/2026:Analysis and Test Scenarios Prep 2/16/2026 : Test Scenarios Updates 2/17/2026:Testing completed in local env 2/24/2026: Completed testing in Dev branch - working fine
A4: 3 | B4: Donor Wave | C4: 46065 | D4: 46079 | E4: OB-OP 8.5 Sprint 2 | F4: Saranya/Arivalagan | G4: DON-184 | H4: Checkout Body Components - Stepper 2 | I4: Completed | J4: 5 | K4: 5 | L4: 260.6 | M4: 46066 | N4: 46073 | O4: YES | P4: Murugesan M | Q4: 1.Clicking on Add donation button should not redirect to stepper 2 page 2.Below to estimated total section is not displayed fully in the stepper 2 page 3.Edit link should be displayed as 27 px as it is in the figma 4.Modifying address type should allow the user to save in the billing information section 5.Add New Payment Method fint size should be displayed as it is in the figma 6.Total and extimated tax calculation value does not matched and should be shown even in the mock data 7.Billing address is not shown in the billing section on stepper 2 but the card has saved billing address and able to see the show address option in the payment section 8.Edit option is not coming up in the billing information section when there is an issue in the billing informaion section 9.primary text should be displayed fully in the responsive view 10.Quanity is displayed as zero for the package type , but package price value is displayed 11.Confirm and pay button should not be enabled when there is no payment CC in the page 12.Cover transaction checkbox width size should be 12x12 , not 24x24 13.colon should be displayed after Estimated Total text as per figma 14.Stepper progress number should not be clickable in the check out page 15.Cover transaction checkbox width size should be 12x12 , not 24x24 16.colon should be displayed after Estimated Total text as per figma 17.Stepper progress number should not be clickable in the check out page 18.Add new address button is displayed instead of billing address of CC when the card is there with billing address 19after editing the address and select save for future events and clicking on confirm and pay button, user not redirecting to stepper 3 page 20.primary tag should not come when there is one card in the payment section 21.Primary tag should come for the added credit card when opting Set as Default payment method and save the card details 22.Getting error contact support banner msg in the top of the page wheen adding CC in the page 23.Billing address is not saved when editing one field amoung five and click save option 24.Next payment method button should not be enabled after loading the page n stepper 1 page and clicking disable button should not user to redirect to another page | R4: Kannan | S4: NIl | T4: https://dev.azure.com/greatergiving/Greater%20Giving/_git/Donor/pullrequest/9311 | U4: 46074 | V4: 46079 | W4: Prabu | X4: Nil | Y4: Joe | Z4: 46079 | AA4: Nill | AB4: Nil | AC4: Nil | AD4: 2/13/2026 - Address and payment functionality implementation 2/16/2026 - card based address loaded functionality implemented 2/17/2026-Unit testing and removed unwanted code 2/18/2026-fixed mobile design issues 2/19/2026- code cleanup fixed design issue 2/20/2026-Add flag based condion for future use API implementation 2/23/2026-Modified Checkbox based added implementeation in address section. 2/24/2026-Reported issue fxing and code refactoring. 2/25/2026-code refactoring | AE4: 2/16/2026 : Test Scenarios Updates 2/17/2026:Testing is in progress and raised defects 2/18/2026:Testing is in progress and raised defects 2/19/2026:Testing is in progress and raised defects 2/20/2026:Retested the fixed issues 2/23/2026: Retested the fixed issues 2/24/2026: Completed testing and retested the fixes as well - working fine 2/25/2026: After fixing code review comments , tested the story again and raised few issues and did resting it and Prepared the validation doc and updated in JIRA
A5: 4 | B5: Donor Wave | C5: 46065 | D5: 46079 | E5: OB-OP 8.5 Sprint 2 | F5: Ubaithullah | G5: DON-189 | H5: Fix IDOR vulnerabilities | I5: Completed | J5: 2 | K5: 2 | L5: 15.25 | M5: 46078 | N5: 46078 | O5: Done | P5: Murugesan M | Q5: NIl | R5: Kannan | S5: Nil | T5: https://dev.azure.com/greatergiving/Greater%20Giving/_git/Donor/pullrequest/9274 | U5: 46078 | V5: 46078 | W5: Prabu | X5: Nil | Y5: Joe | Z5: 46078 | AA5: Nill | AB5: Nil | AC5: Nil | AD5: 26/02/2026 - Account Id validation for Claims, Code refactoring unit testing.

Sheet OB-OP 8.5 Sprint 2-Defect
A1: S.No | B1: Sprint | C1: Story/Defect ID | D1: Parent Story | E1: Developer | F1: Issue Type | G1: Issue Description | H1: Priority | I1: Defect Source | J1: Type | K1: Status | L1: Root Cause Category | M1: Comments | N1: Found By | O1: RCA Comment
B2: OB-OP 8.5 Sprint 2 | C2: DON-312 | D2: DON-184 | E2: arivalagan ramasamy | F2: Defect | G2: Getting Error contact support banner message in the stepper 2 checkout page | H2: Major | I2: Manual | J2: Internal | K2: Inprogress | L2: QA
B3: OB-OP 8.5 Sprint 3 | C3: DON-313 | D3: DON-184 | E3: arivalagan ramasamy | F3: Defect | G3: Edit Billing address is not updating the address value while modifying any of the fields in the address section | H3: Major | I3: Manual | J3: Internal | K3: Inprogress | L3: QA

Sheet OB-OP 8.5 Sprint 1-Status
A1: S.No | B1: Application Name | C1: Sprint Start Date | D1: Sprint End Date | E1: Sprint | F1: Developer | G1: Story ID/Defect ID | H1: Description | I1: Status | J1: Estimated(hrs/sp) | K1: Actual(hrs/sp) | L1: Actual Hours Worklog | M1: Dev Start Date | N1: Dev End Date | O1: Unit testing | P1: Peer Tested By | Q1: Peer Tested Defects, if any | R1: Peer Reviewed By | S1: Peer Code Review Comments, if any | T1: PR Number/Link | U1: PR Created Date | V1: PR Approved Date | W1: Onsite Lead Code Review | X1: Code Review Comments, if any | Y1: Client Code Review | Z1: Approved Date | AA1: Code Review Comments, if any2 | AB1: Internal PO -POV Comments | AC1: Client PO -POV Comments | AD1: Comments | AE1: QA Comments
A2: 1 | B2: Donor Wave | C2: 46051 | D2: 46065 | E2: OB-OP 8.5 Sprint 1 | F2: Irsath | G2: Don-163 | H2: Checkout Body Components - Stepper 1 | I2: Completed | J2: 5 | K2: 5 | L2: 76 | M2: 46052 | N2: 46062 | O2: Done | P2: Murugesan M | Q2: 1.Round up input field should accept only numeric values 2.Total text should have color code #04041c code as per figma 3.Decimal value .00 should be displayed for the package as per figma 4.package and total value should have a color code #04041c code as per figma - not fixed 5.Next: payment method button should have 600 X 56 width as per figma 6.Mobile responsive view 767 [Mob Landscape] recurring come below to amount input filed . 7.$ should be displayed before the value in the amont input field on round up section 8.Need space in the bottom of next payment method button 9.Recurring drop down should be displayed parallell to amount input field for 767 mobile landscape view | R2: Kannan | S2: Nil | T2: https://dev.azure.com/greatergiving/Greater%20Giving/_git/Donor/pullrequest/9254 | U2: 46062 | V2: 46065 | W2: Prabhu | X2: Nil | Y2: Joe | Z2: 46065 | AA2: Nil | AB2: Nil | AC2: Nil | AD2: 1/30/2026 - Analysis done started development 2/2/2026 - Development 20% has been completed 2/3/2026 - Development 60% has been completed 2/4/2026 - Development 100% has been completed and given for testing Kept hold since requirement is going to slightly change - from 5th feb 2/9/2026 - Worked on sales section and given for testing | AE2: 11/2/2026 -Testing has been completed
A3: 2 | B3: Donor Wave | C3: 46051 | D3: 46065 | E3: OB-OP 8.5 Sprint 1 | F3: Ubaithullah | G3: DON-189 | H3: Fix IDOR vulnerabilities | I3: Being Developed | J3: 3 | K3: 1 | L3: 40.25 | M3: 46052 | O3: Done | P3: Murugesan M | T3: https://dev.azure.com/greatergiving/Greater%20Giving/_git/Donor/pullrequest/9274 | U3: 46064 | W3: Prabu | X3: Nil | AA3: Nil | AD3: 1/30/2026 - Analysis Completed 2/2/2026 - Development 50% has been completed 2/3/2026 - Development has been completed and unit completed 2/4/2026 - Code refactoring and given for testing Kept hold for further clarification from 4th Feb 02/11/2026 - Draft PR created and this story will be hold , as yet to update the requirement by PO. | AE3: 11/2/2026 -Testing has been completed for Backend
A4: 3 | B4: Donor Wave | C4: 46051 | D4: 46065 | E4: OB-OP 8.5 Sprint 1 | F4: Saranya | G4: DON-126 | H4: Create Checkout Page | I4: Completed | J4: 3 | K4: 3 | L4: 34 | M4: 46052 | N4: 46056 | O4: Done | P4: Murugesan M | Q4: 1.Right corner Profile initials square size looks as 28x28 in figma , so needs to be changed from current 36 px to figma ref 2.Checkout text should be displayed in the center of the page | R4: Kannan | S4: Nil | T4: https://dev.azure.com/greatergiving/Greater%20Giving/_git/Donor/pullrequest/9254 | U4: 46064 | V4: 46065 | W4: Prabu | X4: Nil | Y4: Joe | Z4: 46065 | AA4: Nil | AB4: Nil | AC4: Nil | AD4: 1/30/2026-Analysis done started design implementation 2/2/2026-Implemented the stepper 1 container design 2/3/2026-Design implementation for footer 2/11/2026-unit testing for stepper 1 component | AE4: 11/2/2026 -Testing has been completed
A5: 4 | B5: Donor Wave | C5: 46051 | D5: 46065 | E5: OB-OP 8.5 Sprint 1 | F5: Arivalagan | G5: DON-190 | H5: Add Rate limiter | I5: Completed | J5: 2 | K5: 2 | L5: 49.25 | M5: 46052 | N5: 46055 | O5: Done | P5: Murugesan M | Q5: Nil | R5: Saranya | S5: Nil | T5: https://dev.azure.com/greatergiving/Greater%20Giving/_git/Donor/pullrequest/9249 | U5: 46055 | V5: 46064 | W5: Prabu | X5: Nil | Y5: Joe | Z5: 46064 | AA5: Nil | AB5: Nil | AC5: Nil | AD5: 1/30/2026-Stated the implementation for rate limiter 2/2/2026-Added rate limiter for specfic action Completed from developer end and waiting for prabu's review - 2/9/2026 2/11/2026-Testing Rate limiter functionaltiy | AE5: 11/2/2026 -Testing has been completed
A6: 5 | B6: Donor Wave | C6: 46051 | D6: 46065 | E6: OB-OP 8.5 Sprint 1 | F6: Kannan | G6: DON-127 | H6: Read API from GGO for Checkout | I6: Completed | J6: 2 | K6: 2 | L6: 28 | M6: 46052 | N6: 46055 | O6: Done | P6: Murugesan M | Q6: Nil | R6: Ubaithullah | S6: Nil | T6: https://greatergiving.visualstudio.com/Greater%20Giving/_git/Donor/pullrequest/9248 | U6: 46055 | V6: 46064 | W6: Prabu | X6: Nil | Y6: Joe | Z6: 46064 | AA6: Nil | AB6: Nil | AC6: Nil | AD6: 1/30/2026 development started 2/2/2026 Development completed and PR created 2/3/2026 - Hold this PR and Story due to some changes required from GDON 2/10/2026 required changes collected from GDON and pushed code and its completed on 2/11/2026 | AE6: 11/2/2026 -Testing has been completed
A7: 6 | B7: Donor Wave | C7: 46051 | D7: 46065 | E7: OB-OP 8.5 Sprint 1 - [Stretch] | F7: Kannan/Ubaithullah/Irsath/Arivalagan/Saranya | G7: Don-184 | H7: Checkout Body Components - Stepper 2 | I7: Being Developed | J7: 5 | L7: 180.75 | M7: 46058 | AD7: 2/5/2026 - Analysis done started development 2/6/2026 - Development 50% has been completed 2/5/2026 - Development started from summary section (Kannan) 2/6/2026 - Worked summary section and pushed the code (Kannan) 2/9/2026 - Development 60% has been completed 2/10/2026 - Development 70% has been completed 2/11/2026 - Development 80% has been completed

Sheet OB-OP 8.5 Sprint 1-Defect
A1: S.No | B1: Sprint | C1: Story/Defect ID | D1: Parent Story | E1: Developer | F1: Issue Type | G1: Issue Description | H1: Priority | I1: Defect Source | J1: Type | K1: Status | L1: Root Cause Category | M1: Comments | N1: Found By | O1: RCA Comment

Sheet OB-OP 8.4 Sprint 4-Status
A1: S.No | B1: Application Name | C1: Sprint Start Date | D1: Sprint End Date | E1: Sprint | F1: Developer | G1: Story ID/Defect ID | H1: Description | I1: Status | J1: Estimated(hrs/sp) | K1: Actual(hrs/sp) | L1: Actual Hours Worklog | M1: Dev Start Date | N1: Dev End Date | O1: Unit testing | P1: Peer Tested By | Q1: Peer Tested Defects, if any | R1: Peer Reviewed By | S1: Peer Code Review Comments, if any | T1: PR Number/Link | U1: PR Created Date | V1: PR Approved Date | W1: Onsite Lead Code Review | X1: Code Review Comments, if any | Y1: Client Code Review | Z1: Approved Date | AA1: Code Review Comments, if any2 | AB1: Internal PO -POV Comments | AC1: Client PO -POV Comments | AD1: Comments
A2: 1 | B2: Donor Wave | C2: 46038 | D2: 46051 | E2: OB-OP 8.4 Sprint 4 | F2: Irsath | G2: DON-177 | H2: Login page Creation for b2c | I2: Completed | J2: 3 | L2: 41.33 | M2: 46038 | N2: 46044 | O2: Done | P2: Murugesan M | Q2: 1]Footer text should be displayed in the middle of login button 2]Login text should display bit down and should have space in btw in greater giving icon and login text 3] Mandatory required error message is not displayed when entering space alone in the password field and password field accepts space as valid one there 4]Mouseover on create account button shows the wrong URL in the left bottom of the page- it should not display when there is no navigations. 5]Give space in between login button and forgot password , currently need few spaces there. | R2: Ubaithullah | S2: Nil | T2: https://dev.azure.com/greatergiving/Greater%20Giving/_git/Donor/pullrequest/9215 | U2: 46045 | V2: 46050 | W2: Prabhu | X2: Nil | Y2: Joe | Z2: 46050 | AA2: Nil | AB2: Nil | AC2: Nil | AD2: 1/16/2026 - Development 50% completed 1/19/2026 - Development 100% completed 1/20/2026 - Converted HTML to vegacontrols 1/21/2026 - Unit testing done and provide to QA testing and Internal Peer Review. 1/22/2026 - Observation fixed and provide to QA for retesting. Once QA confirm will create the PR. 1/22/2026 -QA Testing Completed Created PR - 1/23/2026 Prabu approved the PR - 1/27/2026 (Since OB release stories are priority, this will be reviewed by Joe tomorrow)
A3: 2 | B3: Donor Wave | C3: 46038 | D3: 46051 | E3: OB-OP 8.4 Sprint 4 | F3: Kannan | G3: DON-181 | H3: Password Creation page Creation for b2c | I3: Completed | J3: 3 | L3: 57.33 | M3: 46038 | N3: 46045 | O3: Done | P3: Murugesan M | Q3: 1]There is no space from top of the page on Greater giving icon, icon should display bit down as per figma 2]Green progress status should not be appeared when the values are matched in the pwd -refer below 3]eye icon should not be displayed in the pwd fields as per figma 4]Strong and Too weak text should display bit down as in the figma 5]The bullet point should be displayed as it in the figma , currently it shows bit extra size 6] Progress bar below new password input field should match with light color as it in the figma 7]Repeat pwd value should be hidden , should not display the entered value to the user 8] Footer text does not display when having browser 100 % zoom size , hidden scroll can be implemented in the page 9] Repeat password does not match error message should be displayed when new and repeat password are not matched 10]430 px view - Footer text is not coming up 11]The last two options are not selected in Password page when the conditions are met there for Murugesh12#45 12]The following color code #E5EFFF should be displayed by default in the create password page . currently some gray color is displayed 13]Appropriate error message should be displayed when both password are not matched 14]Please remove the extra Password quality indication text and display only too weak and strong 15]Last two options of password conditions should be checked by default as it is in the Dev 16]Need space between create password button and footer text not -fixed 17]Remove the dot after to secure your account text 18]The font size of repeat password text should be 14px as there in the new password error message 19]Text should be altered in the button as Create password instead of Create your password in the page 20] Choose a strong password to secure your account text should not displayed bold in the page | R3: Ubaithullah/Irsath | S3: Nil | T3: https://dev.azure.com/greatergiving/Greater%20Giving/_git/Donor/pullrequest/9215 | U3: 46045 | V3: 46050 | W3: Prabu | X3: Nil | Y3: Joe | Z3: 46050 | AA3: Nil | AB3: Nil | AC3: Nil | AD3: 1/16/2026- Analysis, html page created for password create along with validations 1/19/2026 - Development 50% completed 1/20/2026 - Development 100% completed. 1/21/2026 - Unit testing done and provide to QA testing and Internal Peer Review. 1/22/2026 - Observation fixed and provide to QA for retesting. Once QA confirm will create the PR. 1/23/2026 -QA Testing Completed Created PR - 1/23/2026 Prabu approved the PR - 1/27/2026 (Since OB release stories are priority, this will be reviewed by Joe tomorrow)
A4: 3 | B4: Donor Wave | C4: 46038 | D4: 46051 | E4: OB-OP 8.4 Sprint 4 | F4: Ubaithullah | G4: DON-179 | H4: Verification page Creation for b2c | I4: Completed | J4: 3 | L4: 43.33 | M4: 46038 | N4: 46044 | O4: Done | P4: Murugesan M | Q4: 1] Greater giving icon should display bit low , so that can have some space in the top of the page in 430 view 2] Display the Input box in the middle of the text and resend code button .[currently it has less space above resend code button] | R4: Irsath | S4: Nil | T4: https://dev.azure.com/greatergiving/Greater%20Giving/_git/Donor/pullrequest/9215 | U4: 46045 | V4: 46050 | W4: Prabu | X4: Nil | Y4: Joe | Z4: 46050 | AA4: Nil | AB4: Nil | AC4: Nil | AD4: 1/16/2026 - Analysis for B2C functionality with custom html form fields 1/19/2026 - Development 50% completed 1/20/2026 - Development 100% completed. 1/21/2026 - Unit testing done and provide to QA testing and Internal Peer Review. 1/22/2026 - Observation fixed and provide to QA for retesting. Once QA confirm will create the PR. 1/22/2026 -QA Testing Completed Created PR - 1/23/2026 Prabu approved the PR - 1/27/2026 (Since OB release stories are priority, this will be reviewed by Joe tomorrow)
A5: 4 | B5: Donor Wave | C5: 46038 | D5: 46051 | E5: OB-OP 8.4 Sprint 4 | F5: Arivalagan/Saranya | G5: DON-180 | H5: Signup page creation for b2c | I5: Completed | J5: 3 | L5: 82.83 | M5: 46038 | N5: 46049 | O5: Done | P5: Murugesan M | Q5: 1] Need one space between greater icon and Create your text 2]Footer text should display in the middle , move bit right side as in the Dev branch 3]Arrow should display after the text in the buttons , not before the text in the button 4]Change Sign in link color code to #262AFF 5]Change the Create your account color code to #04041CF2 6]Footer text not displayed fully in the default browser zoom size 7]Page should be aligned in the center and avoid extra space in the left side page | R5: Saranya | S5: Nil | T5: https://dev.azure.com/greatergiving/Greater%20Giving/_git/Donor/pullrequest/9215 | U5: 46045 | V5: 46050 | W5: Prabu | X5: Nil | Y5: Joe | Z5: 46050 | AA5: Nil | AB5: Nil | AC5: Nil | AD5: 1/16/2026 -Analysis for B2C functionality with custom fileds creation for signup 1/19/2026-Started Signup page implementattion 1/20/2026-Worked on Validation part 1/21/2026-Design and validation functionality is working 1/22/2026-Unit testing and code refactoring (QA local testing pending) 1/23/2026 - Observation fixed and provide to QA for retesting. 1/23/2026 -QA Testing Completed Created PR - 1/23/2026 Prabu approved the PR - 1/27/2026 (Since OB release stories are priority, this will be reviewed by Joe tomorrow)
A6: 5 | B6: Donor Wave | C6: 46038 | D6: 46051 | E6: OB-OP 8.4 Sprint 4 | F6: Saranya | G6: DON-183 | H6: Donar-Cleanup | I6: Verify | J6: 2 | L6: 15.25 | M6: 46041 | N6: 46042 | O6: Done | P6: Murugesan M | R6: Arivalagan | S6: Nil | T6: https://dev.azure.com/greatergiving/Greater%20Giving/_git/Donor/pullrequest/9176 | U6: 46036 | AD6: 1/19/2026-payment page banner message issue 1/20/2026-unit testing Have analysed this story and discussed one point with Prabhu. He said to hold that point for for now as other stories are priority 1/21/2026 Kept hold as per the discussion we had with prabu - 1/28/2026
A7: 6 | B7: Donor Wave | C7: 46038 | D7: 46051 | E7: OB-OP 8.4 Sprint 4 - [STRETCH] | F7: Irsath/Ubaithullah | G7: DON-182 | H7: Forgot password page creation for b2c | I7: Completed | J7: 3 | L7: 27.75 | M7: 46045 | N7: 46049 | O7: Done | R7: Prabhu | S7: Nil | T7: https://dev.azure.com/greatergiving/Greater%20Giving/_git/Donor/pullrequest/9215 | U7: 46045 | V7: 46050 | W7: Prabu | X7: Nil | Y7: Joe | Z7: 46050 | AA7: Nil | AB7: Nil | AC7: Nil | AD7: 1/23/2026 - Development Completed provided to QA 1/23/2026 -QA Testing Completed 1/27/2026 - Testing bugs has been fixed
A8: 7 | B8: Donor Wave | C8: 46038 | D8: 46051 | E8: OB-OP 8.4 Sprint 4 - [STRETCH] | F8: Irsath/Ubaithullah | G8: Don-189 | H8: Insecure Direct Object Reference (IDOR) vulnerabilities Issue fixes | I8: Being Developed | J8: 2 | L8: 25 | M8: 46050 | AB8: Nil | AC8: Nil | AD8: 1/28/2026 - Analysis done and development started 1/29/2026 - Document has been created
A9: 8 | B9: Donor Wave | C9: 46038 | D9: 46051 | E9: OB-OP 8.4 Sprint 4 - [STRETCH] | F9: Arivalagan/Saranya | G9: DON-190 | H9: Rate limiter prevents brute force and DDOS attacks. | I9: Being Developed | J9: 2 | L9: 26.5 | M9: 46050 | AD9: 1/28/2026 - Analysis done and development started 1/29/2026 - Implemented on API side

Sheet OB-OP 8.4 Sprint 4-Defect
A1: S.No | B1: Sprint | C1: Story/Defect ID | D1: Parent Story | E1: Developer | F1: Issue Type | G1: Issue Description | H1: Priority | I1: Defect Source | J1: Type | K1: Status | L1: Root Cause Category | M1: Comments | N1: Found By | O1: RCA Comment

Sheet OB-OP 8.4 Sprint 2-Status
A1: S.No | B1: Application Name | C1: Sprint Start Date | D1: Sprint End Date | E1: Sprint | F1: Developer | G1: Story ID/Defect ID | H1: Description | I1: Status | J1: Estimated(hrs/sp) | K1: Actual(hrs/sp) | L1: Actual Hours Worklog | M1: Dev Start Date | N1: Dev End Date | O1: Unit testing | P1: Peer Tested By | Q1: Peer Tested Defects, if any | R1: Peer Reviewed By | S1: Peer Code Review Comments, if any | T1: PR Number/Link | U1: PR Created Date | V1: PR Approved Date | W1: Onsite Lead Code Review | X1: Code Review Comments, if any | Y1: Client Code Review | Z1: Approved Date | AA1: Code Review Comments, if any2 | AB1: Internal PO -POV Comments | AC1: Client PO -POV Comments | AD1: Comments
A2: 1 | B2: Donor Wave | C2: 46009 | D2: 46037 | E2: OB-OP 8.4 Sprint 2 | F2: Irsath | G2: DON-168 | H2: Donor Clean Up - Address Area | I2: Completed | J2: 1 | L2: 6.75 | M2: 46013 | N2: 46013 | O2: Done | P2: Murugesh | Q2: Nil | R2: Ubaithullah | S2: Nil | V2: 46027 | W2: Prabhu | X2: Nil | Y2: Leo | Z2: 46027 | AA2: Nil | AB2: Nil | AC2: Nil | AD2: 12/22/2025 - Task completed Remove Button works fine due to fix of GGO donor API i did not change any Donor side code that is why it does not have PR Link
A3: 2 | B3: Donor Wave | C3: 46009 | D3: 46037 | E3: OB-OP 8.4 Sprint 2 | F3: Ubaithullah | G3: DON-169 | H3: Donor Clean Up - DB users table | I3: Completed | J3: 1 | L3: 13.75 | M3: 46013 | N3: 46013 | O3: Done | P3: Murugesh | Q3: Nil | R3: Irsath | T3: https://dev.azure.com/greatergiving/Greater%20Giving/_git/Donor/pullrequest/9128 | U3: 46013 | V3: 46015 | W3: Prabu | AD3: 12/22/2025 - Task completed
A4: 3 | B4: Donor Wave | C4: 46009 | D4: 46037 | E4: OB-OP 8.4 Sprint 2 | F4: Saranya | G4: DON-167 | H4: Donor Clean Up - Create account page | I4: Completed | J4: 1 | L4: 14.75 | M4: 46013 | N4: 46014 | O4: Done | P4: Murugesh | R4: Arivalagan | T4: https://dev.azure.com/greatergiving/Greater%20Giving/_git/Donor/pullrequest/9129 | U4: 46013 | V4: 46015 | W4: Prabu | AD4: 12/22/2025-Fixed alignment issue
A5: 4 | B5: Donor Wave | C5: 46009 | D5: 46037 | E5: OB-OP 8.4 Sprint 2 | F5: Kannan Muthiah | G5: DON-170 | H5: Donor Clean Up - Reset your pwd page | I5: Completed | J5: 1 | L5: 3.75 | M5: 46013 | N5: 46014 | O5: Done | P5: Murugesh | R5: Ubaithullah | T5: https://dev.azure.com/greatergiving/Greater%20Giving/_git/Donor/pullrequest/9129 | U5: 46013 | V5: 46015 | W5: Prabu
A6: 5 | B6: Donor Wave | C6: 46009 | D6: 46037 | E6: OB-OP 8.4 Sprint 2 | F6: Arivalagan Ramasamy | G6: DON-171 | H6: Donor Clean Up - Create your pwd page | I6: Completed | J6: 1 | L6: 1 | M6: 46013 | N6: 46014 | O6: Done | P6: Murugesh | R6: Irsath | T6: https://dev.azure.com/greatergiving/Greater%20Giving/_git/Donor/pullrequest/9129 | U6: 46013 | V6: 46015 | W6: Prabu | AD6: 12/22/2025-did some code tuning
A7: 6 | B7: Donor Wave | C7: 46009 | D7: 46037 | E7: OB-OP 8.4 Sprint 2 | F7: Irsath | G7: DON-46 | H7: Handle user authentication into OB from Donor Platform | I7: Completed | J7: 1 | L7: 9.25 | M7: 46014 | N7: 46015 | O7: Done | P7: Murugesh | Q7: Nil | R7: Arivalagan | S7: Nil | W7: Prabhu | X7: Nil | Y7: Nil | AA7: Nil | AB7: Nil | AC7: Nil | AD7: The organization and Events features are implemted for profile in donor platform
A8: 7 | B8: Donor Wave | C8: 46009 | D8: 46037 | E8: OB-OP 8.4 Sprint 2 | F8: Kannan , Ubaithullah | G8: DON-165 | H8: Donor - Back End Code Review | I8: Completed | J8: 3 | L8: 120 | M8: 46014 | N8: 46036 | O8: Done | P8: Murugesh | Q8: 1]Email address does not get updated in the UI , but updated in the Users table correctly. 2] Payment card is not added in payment area second time , but getting success banner message in the home page 3] Warning message for duplicate card entry [ Card already exists ] is coming up inconsistently | R8: Arivalagan | T8: https://greatergiving.visualstudio.com/Greater%20Giving/_git/Donor/pullrequest/9135 https://greatergiving.visualstudio.com/Greater%20Giving/_git/Donor/pullrequest/9144 https://greatergiving.visualstudio.com/Greater%20Giving/_git/Donor/pullrequest/9145 | U8: 46017 | V8: 46037 | W8: Prabu | X8: Nil | Y8: Nil | Z8: 46036
A9: 8 | B9: Donor Wave | C9: 46009 | D9: 46037 | E9: OB-OP 8.4 Sprint 2 | F9: Saranya\Arivalagan Ramasamy/Irsath | G9: DON-166 | H9: Donor - Front End Code Review | I9: Completed | J9: 3 | L9: 249.75 | M9: 46014 | N9: 46036 | O9: Done | P9: Murugesh | Q9: 1] when clicking on edit profile icon , below 500 error is coming in the home page 2] org and events area still loading - data is not loading for 372 account ID 3] Input box looks broken in forgot Pwd flow verify code page for 430 px 4] Create account page looks bit short in right side space while comparing to left side for 430 px 5] Input box looks broken in sign up flow verify code page for 430 px 6] Resend code button left side is not rounded off on left side on verify code page for 430 px 7] personal information page should have equal space on right and left side for 430 px view and 598 [mobile view] 8] Add payment method page should have equal space on right and left side for 430 px and 598 [mobile view] 9] profile initials circle is not displayed in the middle on name space area 10] x-close icon is not working in image upload modal 11] Login button and footer text are not coming up 12] loader is displaying in the top of the page instead of middle of the page in the add payment method page 13] Add payment method page - Continue button gets disabled just check and uncheck the use different billing address option after entering all the mandatory fields above toggle set as default payment method 14]The custom error message was displayed on security code input field when entering invalid value there. | R9: Prabu | S9: Nil | T9: https://dev.azure.com/greatergiving/Greater%20Giving/_git/Donor/pullrequest/9137 https://dev.azure.com/greatergiving/Greater%20Giving/_git/Donor/pullrequest/9148 https://dev.azure.com/greatergiving/Greater%20Giving/_git/Donor/pullrequest/9154 | U9: 12/29/2025 01/05/2026 01/08/2026 | V9: 46037 | W9: Prabhu | X9: Nil | Y9: Joe | Z9: 46036 | AA9: Nil | AD9: 12/23/2025-Change div to vega box , vega flex 12/22/2025-Added Common Data transfer for non depantable component 12/19/2025-Stepper functionality simpifiy 12/24/2025 - 20% completed 12/26/2025 - 30% completed 12/29/2025 - 40% completed 12/30/2025 - 50% completed 12/31/2025 - 70% completed 1/2/2026 - 80% completed 1/5/2026 - 100% completed Giveing for testing 1/6/2026 - Issue has been fixed 1/7/2026 - Removed unwanted Css 1/8/2026 - Created common navigator service 1/9/2026 - Progress tracker functionality simplify 1/12/2026 - Shadow root Remove for color code 1/13/2026 - Inline css remove 1/14/2026 - Code formatting and Removed unwanted spaces in the html and TS and comments added
A10: 9 | B10: Donor Wave | C10: 46009 | D10: 46037 | E10: OB-OP 8.4 Sprint 2 | F10: saranya | G10: DON-161 | H10: Create Account page | I10: Completed | J10: 1 | L10: 33 | M10: 46013 | N10: 46013 | P10: Murugesh | R10: murugesan | T10: https://dev.azure.com/greatergiving/Greater%20Giving/_git/Donor/pullrequest/9108 | U10: 46007 | V10: 46015 | W10: Prabu | X10: Nil | Y10: Joe | Z10: 46015 | AA10: Nil | AB10: Nil | AC10: Nil | AD10: 12/22/2025-Fixed design alignment issue.
A11: 10 | B11: Donor Wave | C11: 46009 | D11: 46037 | E11: OB-OP 8.4 Sprint 2 - [STRETCH] | F11: Irsath/Kannan | G11: Don-178 | H11: Investigation into B2C page creation using HTML/JS | I11: Completed | J11: 1 | L11: 32 | M11: 46030 | N11: 46036 | O11: Done | P11: Murugesh | Q11: Nil | R11: Ubaithullah | S11: Nil | W11: Prabhu | X11: Nil | Y11: Nil | AA11: Nil | AB11: Nil | AC11: Nil | AD11: 1/8/2026 - Analysis completed 50% 1/9/2026 - Analysis completed 80% 1/12/2026 - Analysis completed 90% 1/13/2026 - Analysis completed 95% 1/14/2026 - Analysis completed 100% and suggestion shared This is R&D task that is why it does not have PR Link
A12: 11 | B12: Donor Wave | C12: 46009 | D12: 46037 | E12: OB-OP 8.4 Sprint 2 | F12: Irsath | G12: DON-28 | H12: Implement OneTrust on Donor Platform | I12: Completed | J12: 2 | L12: 13.5 | M12: 46029 | N12: 46029 | O12: Done | P12: Murugesh | Q12: Nil | R12: Ubaithullah | S12: Nil | T12: https://dev.azure.com/greatergiving/Greater%20Giving/_git/Donor/pullrequest/9107 | U12: 46030 | V12: 46031 | W12: Prabhu | X12: Nil | Y12: Joe | Z12: 46031 | AA12: Nil | AB12: Nil | AC12: Nil | AD12: 1/7/2026 - Development completed
A13: 12 | B13: Donor Wave | C13: 46009 | D13: 46037 | E13: OB-OP 8.4 Sprint 2 - [STRETCH] | F13: Arivalagan/Ubaithullah | G13: DON-183 | H13: Donor-Cleanup-Continuation | I13: Being Developed | J13: 3 | L13: 29.25 | M13: 46030 | N13: 46030 | P13: Murugesh | R13: Ubaithullah | T13: https://dev.azure.com/greatergiving/Greater%20Giving/_git/Donor/pullrequest/9176 | U13: 46036 | W13: Prabhu | X13: Nil | Y13: Joe | AA13: Nil | AB13: Nil | AC13: Nil | AD13: 1/8/2026-fixed user initialis functionality

Sheet OB-OP 8.4 Sprint 2-Defect
A1: S.No | B1: Sprint | C1: Story/Defect ID | D1: Parent Story | E1: Developer | F1: Issue Type | G1: Issue Description | H1: Priority | I1: Defect Source | J1: Type | K1: Status | L1: Root Cause Category | M1: Comments | N1: Found By | O1: RCA Comment

Sheet OB-OP 8.4 Sprint 1-Status
A1: S.No | B1: Application Name | C1: Sprint Start Date | D1: Sprint End Date | E1: Sprint | F1: Developer | G1: Story ID/Defect ID | H1: Description | I1: Status | J1: Estimated(hrs/sp) | K1: Actual(hrs/sp) | L1: Actual Hours Worklog | M1: Dev Start Date | N1: Dev End Date | O1: Unit testing | P1: Peer Tested By | Q1: Peer Tested Defects, if any | R1: Peer Reviewed By | S1: Peer Code Review Comments, if any | T1: PR Number/Link | U1: PR Created Date | V1: PR Approved Date | W1: Onsite Lead Code Review | X1: Code Review Comments, if any | Y1: Client Code Review | Z1: Approved Date | AA1: Code Review Comments, if any2 | AB1: Internal PO -POV Comments | AC1: Client PO -POV Comments | AD1: Comments
A2: 1 | B2: Donor Wave | C2: 45995 | D2: 46009 | E2: OB-OP 8.4 Sprint 1 | F2: Saranya | G2: DON-157 | H2: Secure Code Page | I2: Completed | J2: 1 | L2: 23.5 | M2: 45996 | N2: =DATEVALUE(MID(LEFT(Table145678109312131114151719182120162223242625272829[[#This Row],[Comments]], FIND("{token}", SUBSTITUTE(Table145678109312131114151719182120162223242625272829[[#This Row],[Comments]], "-", "{token}", LEN(Table145678109312131114151719182120162223242625272829[[#This Row],[Comments]]) - LEN(SUBSTITUTE(Table145678109312131114151719182120162223242625272829[[#This Row],[Comments]], "-", "")))) - 1), FIND("{token}", SUBSTITUTE(Table145678109312131114151719182120162223242625272829[[#This Row],[Comments]], "/", "{token}", LEN(Table145678109312131114151719182120162223242625272829[[#This Row],[Comments]]) - LEN(SUBSTITUTE(Table145678109312131114151719182120162223242625272829[[#This Row],[Comments]], "/", "")) - 1)) - 2, LEN(Table145678109312131114151719182120162223242625272829[[#This Row],[Comments]]))) + TIMEVALUE(MID(LEFT(Table145678109312131114151719182120162223242625272829[[#This Row],[Comments]], FIND("{token}", SUBSTITUTE(Table145678109312131114151719182120162223242625272829[[#This Row],[Comments]], "-", "{token}", LEN(Table145678109312131114151719182120162223242625272829[[#This Row],[Comments]]) - LEN(SUBSTITUTE(Table145678109312131114151719182120162223242625272829[[#This Row],[Comments]], "-", "")))) - 1), FIND("{token}", SUBSTITUTE(Table145678109312131114151719182120162223242625272829[[#This Row],[Comments]], "/", "{token}", LEN(Table145678109312131114151719182120162223242625272829[[#This Row],[Comments]]) - LEN(SUBSTITUTE(Table145678109312131114151719182120162223242625272829[[#This Row],[Comments]], "/", "")) - 1)) - 2, LEN(Table145678109312131114151719182120162223242625272829[[#This Row],[Comments]]))) -> 45999 | O2: Done | P2: Murugesan M | Q2: 1] First and Last input box looks incomplete in tablet landscape view -1024 px 2] First and Last input box looks incomplete in Mobile Portrait view -430 px | R2: Kannan | S2: Nill | T2: https://dev.azure.com/greatergiving/Greater%20Giving/_git/Donor/pullrequest/9085 | U2: 45999 | V2: 46006 | W2: Prabhu | X2: Nil | Y2: Joe | Z2: 46006 | AA2: Nil | AB2: Nil | AC2: Nil | AD2: 12/05/2025-working on design issue 12/08/2025-working on design issue for tablet view
A3: 2 | B3: Donor Wave | C3: 45995 | D3: 46009 | E3: OB-OP 8.4 Sprint 1 | F3: Irsath | G3: Don-155 | H3: Add View Billing address | I3: Completed | J3: 3 | L3: 48 | M3: 45996 | N3: 46001 | O3: Done | P3: Murugesan M | Q3: Nil | R3: Arivalagan | S3: Nil | T3: https://dev.azure.com/greatergiving/Greater%20Giving/_git/Donor/pullrequest/9093 | U3: 46001 | V3: 46007 | W3: Prabhu | X3: Nil | Y3: Joe | Z3: 46007 | AA3: Nil | AB3: Nil | AC3: Nil | AD3: 12/5/2025 - Analysis done,start development 12/8/2025 - Model has been created 12/9/2025 - Show hide implemented for show billing address button 12/10/2025 - Unit testing done and given for testing 12/11/2025 - Update vega library version and test all pages
A4: 3 | B4: Donor Wave | C4: 45995 | D4: 46009 | E4: OB-OP 8.4 Sprint 1 | F4: Kannan | G4: DON-153 | H4: Determine method for storing Billing address | I4: Completed | J4: 3 | L4: 90 | M4: 45996 | N4: 46002 | O4: Done | P4: Murugesan M | Q4: 1.Billing address label should not be displayed when selecting use Different billing address option 2.Save Payment method button should not be enabled when the mandatory field company name is empty 3. Save payment method button is not working after selecting the Add address manually option 4.Company name is returning as null on GGO API response for the saved CC card. 5. Address type is returning as null only to all the address types on GGO API response for the saved CC card. 6. Some deley there on use different billing address check box to disabled 7.Has Billing address column shown as false in card_reference table after adding Billing address for payment card | R4: Irasath | S4: Nil | T4: https://greatergiving.visualstudio.com/Greater%20Giving/_git/Donor/pullrequest/9099 | U4: 46002 | V4: 46008 | W4: Prabu | X4: Nil | Y4: Joe | Z4: 46009 | AA4: Nil | AB4: Nil | AC4: Nil | AD4: 12/05/2025 - Started development (Code behind started but not yet confirmed the UX side to use the existing address component) 12/09/2025 confirmation received for to use the existing address component 12/11/2025 - PR Created 12/15/2025 Asked to update the user address in donor db 12/17/2020 Asked to update the UX changes in Credit card page, Billing Address is mandatory if profile address is empty
A5: 4 | B5: Donor Wave | C5: 45995 | D5: 46009 | E5: OB-OP 8.4 Sprint 1 | F5: Arivalagan / Ubaithullah | G5: Don-149 | H5: Implement Progress Bar in Donor Home | I5: Completed | J5: 5 | L5: 155.25 | M5: 45996 | N5: =DATEVALUE(MID(LEFT(Table145678109312131114151719182120162223242625272829[[#This Row],[Comments]], FIND("{token}", SUBSTITUTE(Table145678109312131114151719182120162223242625272829[[#This Row],[Comments]], "-", "{token}", LEN(Table145678109312131114151719182120162223242625272829[[#This Row],[Comments]]) - LEN(SUBSTITUTE(Table145678109312131114151719182120162223242625272829[[#This Row],[Comments]], "-", "")))) - 1), FIND("{token}", SUBSTITUTE(Table145678109312131114151719182120162223242625272829[[#This Row],[Comments]], "/", "{token}", LEN(Table145678109312131114151719182120162223242625272829[[#This Row],[Comments]]) - LEN(SUBSTITUTE(Table145678109312131114151719182120162223242625272829[[#This Row],[Comments]], "/", "")) - 1)) - 2, LEN(Table145678109312131114151719182120162223242625272829[[#This Row],[Comments]]))) + TIMEVALUE(MID(LEFT(Table145678109312131114151719182120162223242625272829[[#This Row],[Comments]], FIND("{token}", SUBSTITUTE(Table145678109312131114151719182120162223242625272829[[#This Row],[Comments]], "-", "{token}", LEN(Table145678109312131114151719182120162223242625272829[[#This Row],[Comments]]) - LEN(SUBSTITUTE(Table145678109312131114151719182120162223242625272829[[#This Row],[Comments]], "-", "")))) - 1), FIND("{token}", SUBSTITUTE(Table145678109312131114151719182120162223242625272829[[#This Row],[Comments]], "/", "{token}", LEN(Table145678109312131114151719182120162223242625272829[[#This Row],[Comments]]) - LEN(SUBSTITUTE(Table145678109312131114151719182120162223242625272829[[#This Row],[Comments]], "/", "")) - 1)) - 2, LEN(Table145678109312131114151719182120162223242625272829[[#This Row],[Comments]]))) -> 46009 | O5: Done | P5: Murugesan M | Q5: 1.Stepper popup is coming as flicker once it is completed 2.Appropriate text should be displayed in the stepper 3. Appropriate URL should be displayed in the browser while profile focus on edit profile mobile field 4.dismiss btn is not working in progress stepper 5.Adding payment from signup flow . shows one cc in payment area of home page , but stepper shows 4th step as incomplete | R5: Irasath | S5: Nill | T5: https://dev.azure.com/greatergiving/Greater%20Giving/_git/Donor/pullrequest/9103 | U5: 46003 | V5: 46009 | W5: Prabhu | X5: Create a common method and pass the respective parameter and use it | Y5: Joe | Z5: 46009 | AA5: Nil | AB5: Nil | AC5: Nil | AD5: 12/5/2025- Started Analysis and development 12/8/2025 -Started implementation progress bar 12/9/2025-Design implementation and functionality development 12/10/2025-Code refactoring and fine tune changes 12/11/2025- Mobile redirection and check completed steps 12/12/2025-code refactroing 12/15/2025-Clicking an unfinished step should take the user to the appropriate accordion/screen to enter information 12/16/2025-code refactroing 12/17/2025-code refactroing 12/18/2025-code refactroing
A6: 5 | B6: Donor Wave | C6: 45995 | D6: 46009 | E6: OB-OP 8.4 Sprint 1 | F6: Saranya | G6: DON-158 | H6: Personal Information Page | I6: Completed | J6: 1 | L6: 15 | M6: 45996 | N6: =DATEVALUE(MID(LEFT(Table145678109312131114151719182120162223242625272829[[#This Row],[Comments]], FIND("{token}", SUBSTITUTE(Table145678109312131114151719182120162223242625272829[[#This Row],[Comments]], "-", "{token}", LEN(Table145678109312131114151719182120162223242625272829[[#This Row],[Comments]]) - LEN(SUBSTITUTE(Table145678109312131114151719182120162223242625272829[[#This Row],[Comments]], "-", "")))) - 1), FIND("{token}", SUBSTITUTE(Table145678109312131114151719182120162223242625272829[[#This Row],[Comments]], "/", "{token}", LEN(Table145678109312131114151719182120162223242625272829[[#This Row],[Comments]]) - LEN(SUBSTITUTE(Table145678109312131114151719182120162223242625272829[[#This Row],[Comments]], "/", "")) - 1)) - 2, LEN(Table145678109312131114151719182120162223242625272829[[#This Row],[Comments]]))) + TIMEVALUE(MID(LEFT(Table145678109312131114151719182120162223242625272829[[#This Row],[Comments]], FIND("{token}", SUBSTITUTE(Table145678109312131114151719182120162223242625272829[[#This Row],[Comments]], "-", "{token}", LEN(Table145678109312131114151719182120162223242625272829[[#This Row],[Comments]]) - LEN(SUBSTITUTE(Table145678109312131114151719182120162223242625272829[[#This Row],[Comments]], "-", "")))) - 1), FIND("{token}", SUBSTITUTE(Table145678109312131114151719182120162223242625272829[[#This Row],[Comments]], "/", "{token}", LEN(Table145678109312131114151719182120162223242625272829[[#This Row],[Comments]]) - LEN(SUBSTITUTE(Table145678109312131114151719182120162223242625272829[[#This Row],[Comments]], "/", "")) - 1)) - 2, LEN(Table145678109312131114151719182120162223242625272829[[#This Row],[Comments]]))) -> 45996 | O6: Done | P6: Murugesan M | Q6: Nil | R6: Kannan | S6: Nill | T6: https://dev.azure.com/greatergiving/Greater%20Giving/_git/Donor/pullrequest/9085 | U6: 45996 | V6: 46006 | W6: Prabhu | X6: Nil | Y6: Joe | Z6: 46006 | AA6: Nil | AB6: Nil | AC6: Nil | AD6: 12/05/2025-Fixing the dropdown list
A7: 6 | B7: Donor Wave | C7: 45995 | D7: 46009 | E7: OB-OP 8.4 Sprint 1 | F7: Saranya | G7: DON-162 | H7: Adjust Login Page width | I7: Completed | J7: 1 | L7: 30.75 | M7: 46000 | N7: =DATEVALUE(MID(LEFT(Table145678109312131114151719182120162223242625272829[[#This Row],[Comments]], FIND("{token}", SUBSTITUTE(Table145678109312131114151719182120162223242625272829[[#This Row],[Comments]], "-", "{token}", LEN(Table145678109312131114151719182120162223242625272829[[#This Row],[Comments]]) - LEN(SUBSTITUTE(Table145678109312131114151719182120162223242625272829[[#This Row],[Comments]], "-", "")))) - 1), FIND("{token}", SUBSTITUTE(Table145678109312131114151719182120162223242625272829[[#This Row],[Comments]], "/", "{token}", LEN(Table145678109312131114151719182120162223242625272829[[#This Row],[Comments]]) - LEN(SUBSTITUTE(Table145678109312131114151719182120162223242625272829[[#This Row],[Comments]], "/", "")) - 1)) - 2, LEN(Table145678109312131114151719182120162223242625272829[[#This Row],[Comments]]))) + TIMEVALUE(MID(LEFT(Table145678109312131114151719182120162223242625272829[[#This Row],[Comments]], FIND("{token}", SUBSTITUTE(Table145678109312131114151719182120162223242625272829[[#This Row],[Comments]], "-", "{token}", LEN(Table145678109312131114151719182120162223242625272829[[#This Row],[Comments]]) - LEN(SUBSTITUTE(Table145678109312131114151719182120162223242625272829[[#This Row],[Comments]], "-", "")))) - 1), FIND("{token}", SUBSTITUTE(Table145678109312131114151719182120162223242625272829[[#This Row],[Comments]], "/", "{token}", LEN(Table145678109312131114151719182120162223242625272829[[#This Row],[Comments]]) - LEN(SUBSTITUTE(Table145678109312131114151719182120162223242625272829[[#This Row],[Comments]], "/", "")) - 1)) - 2, LEN(Table145678109312131114151719182120162223242625272829[[#This Row],[Comments]]))) -> 46006 | O7: Done | P7: Murugesan M | Q7: 1]There should be some space before privacy text in the footer 2]Scrolling down the page is not working in reset password page 3]Footer text is not coming up in 1024,768 and 598 px width for Reset your password page 4]Footer text is not coming up in 1024,768 and 598 px width for Create your password page 5.Ltext in the Login should display bit left. 6.Forgot password page has bit space in right side | R7: Arivalagan | S7: Nill | T7: https://dev.azure.com/greatergiving/Greater%20Giving/_git/Donor/pullrequest/9096 | U7: 46001 | V7: 46006 | W7: Prabhu | X7: Nil | Y7: Joe | Z7: 46006 | AA7: Nil | AB7: Nil | AC7: Nil | AD7: 12/09/2025-working on footer text alignment issue 12/10/2025-working on dropdown alignment issue 12/11/2025-Unit testing for application. 12/15/2025-unit testing for Login Page
A8: 7 | B8: Donor Wave | C8: 45995 | D8: 46009 | E8: OB-OP 8.4 Sprint 1 - [STRETCH] | F8: Irsath | G8: DON-28 | H8: Implement OneTrust on Donor Platform | I8: Peer Review | J8: 3 | L8: 30 | M8: 46003 | N8: 46007 | R8: Ubaithullah | S8: Nil | T8: https://dev.azure.com/greatergiving/Greater%20Giving/_git/Donor/pullrequest/9107 | U8: 46007 | W8: Prabhu | X8: Nil | Y8: Joe | AC8: Nil | AD8: 12/12/2025-Analysis done start development 12/15/2025- Development 60% completed 12/16/2025- Development 90% completed 12/17/2025-Completed. 12/18/2025-Completed Given for Peer review
A9: 8 | B9: Donor Wave | C9: 45995 | D9: 46009 | E9: OB-OP 8.4 Sprint 1 - [STRETCH] | F9: Saranya | G9: DON-161 | H9: Create Account page | I9: Being Developed | J9: 1 | L9: 28 | M9: 46003 | N9: 46008 | P9: Murugesan M | Q9: 1.some extra space on create account page right side for 598 view only | R9: Ubaithullah | S9: Nill | T9: https://dev.azure.com/greatergiving/Greater%20Giving/_git/Donor/pullrequest/9108 | U9: 46007 | W9: Prabhu | X9: Nil | Y9: Joe | AD9: 12/12/2025-Alignmnet issue fixing in create account page 12/16/2025-unit testing for create workflow

Sheet OB-OP 8.4 Sprint 1-Defect
A1: S.No | B1: Sprint | C1: Story/Defect ID | D1: Parent Story | E1: Developer | F1: Issue Type | G1: Issue Description | H1: Priority | I1: Defect Source | J1: Type | K1: Status | L1: Root Cause Category | M1: Comments | N1: Found By | O1: RCA Comment
B2: OB-OP 8.4 sprint -1 | C2: DON-164 | D2: DON-153 | E2: Kannan Muthiah | F2: Defect | G2: Has Billing address column shown as false in card_reference table after adding Billing address for payment card | H2: Major | I2: Manual | J2: Internal | K2: Closed | L2: Development | M2: During the peer review, column name has been renamed in domain model but not updated in ux interface. | N2: Murugesan | O2: Need to revisit and test all the features again after review is done

Sheet OB-OP 8.3 Sprint 4-Status
A1: S.No | B1: Application Name | C1: Sprint Start Date | D1: Sprint End Date | E1: Sprint | F1: Developer | G1: Story ID/Defect ID | H1: Description | I1: Status | J1: Estimated(hrs/sp) | K1: Actual(hrs/sp) | L1: Actual Hours Worklog | M1: Dev Start Date | N1: Dev End Date | O1: Unit testing | P1: Peer Tested By | Q1: Peer Tested Defects, if any | R1: Peer Reviewed By | S1: Peer Code Review Comments, if any | T1: PR Number/Link | U1: PR Created Date | V1: PR Approved Date | W1: Onsite Lead Code Review | X1: Code Review Comments, if any | Y1: Client Code Review | Z1: Approved Date | AA1: Code Review Comments, if any2 | AB1: Internal PO -POV Comments | AC1: Client PO -POV Comments | AD1: Comments
A2: 1 | B2: Donor Wave | C2: 45981 | D2: 45995 | E2: OB-OP 8.3 Sprint 4 | F2: Ubaithullah/Kannan | G2: Don-146 | H2: Complete Profile Initials Functionality | I2: Completed | J2: 5 | L2: 73.75 | M2: 45982 | N2: 45987 | O2: Done | P2: Murugesan M | Q2: 1]Updating value not reflecting in home page , gets reflected only in edit profile page after clicked on save profile button 2]Default color[yellow] is not displayed in the modal now 3]Alpha chars only should allow in profile initials input box 4]X icon is not working in the modal | R2: Kannan | S2: Nil | T2: https://dev.azure.com/greatergiving/Greater%20Giving/_git/Donor/pullrequest/9047 | U2: 45986 | V2: 45993 | W2: Prabu | X2: Nil | Y2: Joe | Z2: 45993 | AA2: Nil | AB2: Nil | AC2: Nil | AD2: 11/21/2025 - Analysis 11/24/2025 - Completed Save and update backend funcitonality 11/25/2025 - Back end Get funcationality completed and UX completed. 11/26/2025 - Code optimization and testing
A3: 2 | B3: Donor Wave | C3: 45981 | D3: 45995 | E3: OB-OP 8.3 Sprint 4 | F3: Irsath | G3: Don-148 | H3: Implement OB Activity | I3: Completed | J3: 3 | L3: 38 | M3: 45982 | N3: 45987 | O3: Done | P3: Murugesan M | Q3: Nil | R3: Ubaithullah | S3: Nil | T3: https://dev.azure.com/greatergiving/Greater%20Giving/_git/Donor/pullrequest/9043 | U3: 45987 | V3: 45993 | W3: Prabhu | X3: Nil | Y3: Joe | Z3: 45993 | AA3: Nil | AB3: Nil | AC3: Nil | AD3: 11/21/2025 - Analysis done 11/24/2025 - Create OnlineBidding Activity API has been created 11/25/2025 - Tested and PR has been created
A4: 3 | B4: Donor Wave | C4: 45981 | D4: 45995 | E4: OB-OP 8.3 Sprint 4 | F4: Arivalagan/saranya | G4: Don-144 | H4: Notification Display Area | I4: Completed | J4: 3 | L4: 58.5 | M4: 45982 | N4: 45986 | O4: Done | P4: Murugesan M | R4: saranya | S4: Nil | T4: https://dev.azure.com/greatergiving/Greater%20Giving/_git/Donor/pullrequest/9044 | U4: 45987 | V4: 45993 | W4: Prabhu | X4: Nil | Y4: Joe | Z4: 45993 | AA4: Nil | AB4: Nil | AC4: Nil | AD4: 11/21/2025- Analysis 11/24/2025-design implementation 11/25/2025-working vega-banner
A5: 4 | B5: Donor Wave | C5: 45981 | D5: 45995 | E5: OB-OP 8.3 Sprint 4 | F5: Irsath | G5: Don-147 | H5: Session storage | I5: Completed | J5: 3 | L5: 45 | M5: 45987 | N5: 45994 | O5: Done | P5: Murugesan M | Q5: Nil | R5: Arivalagan | S5: Nil | T5: https://dev.azure.com/greatergiving/Greater%20Giving/_git/Donor/pullrequest/9060 | U5: 45994 | V5: 45995 | W5: Prabhu | X5: Nil | Y5: Joe | Z5: 45995 | AA5: Nil | AB5: Nil | AC5: Nil | AD5: 11/26/2025 - Analysis 11/27/2025 - Analysis 11/28/2025 - Session Storage Implement secure and encrypted 12/1/2025 - Unit testing 12/2/2025 - Code Optimization 12/3/2025 - A fallback to alternative storage (in-memory storage) for cases when session storage is unavailable 12/4/2025 - A fallback to alternative storage (in-memory storage) for cases when session storage is unavailable
A6: 5 | B6: Donor Wave | C6: 45981 | D6: 45995 | E6: OB-OP 8.3 Sprint 4 - [STRETCH] | F6: Saranya/Arivalagan | G6: Don-154 | H6: Clarify Progress Bar in Create account | I6: Completed | J6: 3 | L6: 114.5 | M6: 45987 | N6: 45995 | O6: Done | P6: Murugesan M | Q6: 1]Continue button should be worked in single click in create your password page 2]Aria label are missing to represent the progress stepper functionality 3]Scroll bar should not be displayed in payment method page 4]Scroll bar should not be displayed in personal information page 5]progress bar color code should match with Donor's standard one #262AFF | R6: Arivu/Saranya/Kannan | S6: Nil | T6: https://dev.azure.com/greatergiving/Greater%20Giving/_git/Donor/pullrequest/9070 | U6: 45995 | V6: 45995 | W6: Prabu | X6: Nil | Y6: Joe | Z6: 45995 | AA6: This needs to be disconnected/destroyed. | AB6: Nil | AC6: Nil | AD6: 11/26/2025 -Analysis 11/27/2025-design implementation 11/28/2025-working progress bar step functionality 12/01/2025-Fixing design issue and unit testing 12/02/2025-fixing finding issue 12/03/2025-code cleanup 12/04/2025-code refactoring
A7: 6 | B7: Donor Wave | C7: 45981 | D7: 45995 | E7: OB-OP 8.3 Sprint 4 | F7: Ubaithullah/Kannan | G7: DON-151 | H7: Continue Error page Work in Donor Platform | I7: Completed | J7: 3 | L7: 87 | M7: 45988 | N7: 45995 | O7: Done | P7: Murugesan M | R7: Kannan/Ubai | S7: Nil | T7: https://dev.azure.com/greatergiving/Greater%20Giving/_git/Donor/pullrequest/9073 | U7: 45995 | V7: 45995 | W7: Prabu | X7: Nil | Y7: Joe | Z7: 45995 | AA7: We should use the error code array rather than magic numbers here. | AB7: Nil | AC7: Nil

Sheet OB-OP 8.3 Sprint 4-Defect
A1: S.No | B1: Sprint | C1: Story/Defect ID | D1: Parent Story | E1: Developer | F1: Issue Type | G1: Issue Description | H1: Priority | I1: Defect Source | J1: Type | K1: Status | L1: Root Cause Category | M1: Comments | N1: Found By | O1: RCA Comment

Sheet OB-OP 8.3 Sprint 3-Status
A1: S.No | B1: Application Name | C1: Sprint Start Date | D1: Sprint End Date | E1: Sprint | F1: Developer | G1: Story ID/Defect ID | H1: Description | I1: Status | J1: Estimated(hrs/sp) | K1: Actual(hrs/sp) | L1: Actual Hours Worklog | M1: Dev Start Date | N1: Dev End Date | O1: Unit testing | P1: Peer Tested By | Q1: Peer Tested Defects, if any | R1: Peer Reviewed By | S1: Peer Code Review Comments, if any | T1: PR Number/Link | U1: PR Created Date | V1: PR Approved Date | W1: Onsite Lead Code Review | X1: Code Review Comments, if any | Y1: Client Code Review | Z1: Approved Date | AA1: Code Review Comments, if any2 | AB1: Internal PO -POV Comments | AC1: Client PO -POV Comments | AD1: Comments
A2: 1 | B2: Donor Wave | C2: 45967 | D2: 45981 | E2: OB-OP 8.3 Sprint 3 | F2: Irsath | G2: Don-99 | H2: Convert Address page from bootstrap to Vega control | I2: Completed | J2: 2 | L2: 47.75 | M2: 45968 | N2: 45972 | O2: Done | P2: Murugesan M | Q2: 1] Pin code should accept only numbers 2] loaders should display in the center of the page , currently shows in the top of page 3] error msg is not coming up for address field if you remove address value using x icon in add address page 4] state value should not accept numeric value 5] Remove button should not be displayed in add address window 6] Entering space allows as valid value in address field , Error message should display when there is no value 7] City value accepts all special characters, can restrict to letters 8] save button is not enabled while clicking on edit address button of partial address text update from home page | R2: Ubauithullah | S2: Nil | T2: https://dev.azure.com/greatergiving/Greater%20Giving/_git/Donor/pullrequest/8995 | U2: 45971 | V2: 45975 | W2: Prabhu | X2: Nil | Y2: Joe | Z2: 45975 | AA2: Nil | AB2: Nil | AC2: Nil | AD2: 11/7/2025 - Worked for Google address api auto complete 11/10/2025 - Converted address API`s into URI Builder
A3: 2 | B3: Donor Wave | C3: 45967 | D3: 45981 | E3: OB-OP 8.3 Sprint 3 | F3: Ubaithullah/Kannan | G3: Don-109 | H3: Profile Data Management | I3: Completed | J3: 5 | L3: 138.75 | M3: 45968 | N3: 45980 | O3: Done | P3: Murugesan M | R3: Kannan | S3: Nil | T3: https://dev.azure.com/greatergiving/Greater%20Giving/_git/Donor/pullrequest/9003 | U3: 45973 | V3: 45980 | W3: Prabhu | X3: Nil | Y3: Joe | Z3: 45980 | AA3: Nil | AB3: Nil | AC3: Nil
A4: 3 | B4: Donor Wave | C4: 45967 | D4: 45967 | E4: OB-OP 8.3 Sprint 3 | F4: Arivalagan | G4: DON-117 | H4: Profile Cleanup | I4: Completed | J4: 2 | L4: 82.5 | M4: 45968 | N4: 45979 | O4: Done | P4: Murugesan M | Q4: 1] When updating name with space in btw letters , it is saving with space in the profile | R4: Saranya | S4: Nil | T4: https://dev.azure.com/greatergiving/Greater%20Giving/_git/Donor/pullrequest/9023 | U4: 45978 | V4: 45979 | W4: Prabhu | X4: Nil | Y4: Joe | Z4: 45979 | AA4: Nil | AB4: Nil | AC4: Nil | AD4: 11/7/2025- Started Analysis and development 11/10/2025-Removed unwanted code, and working on Validation 11/11/2025- Design issue is fixed 11/12/2025-worked 320 px design changes 11/13/2025-design implmentation 11/14/2025-Worked on update and api functionaltiy 11/18/2025-Review comments worked
A5: 4 | B5: Donor Wave | C5: 45967 | D5: 45981 | E5: OB-OP 8.3 Sprint 3 | F5: Saranya | G5: DON-110 | H5: Terms of Use URL | I5: Completed | J5: 1 | L5: 9.25 | M5: 45968 | N5: 45968 | O5: Done | P5: Murugesan M | Q5: Nil | R5: Arivalagan | S5: Nil | T5: https://dev.azure.com/greatergiving/Greater%20Giving/_git/Donor/pullrequest/8989 | U5: 45968 | V5: 45969 | W5: Prabhu | X5: Nil | Y5: Joe | Z5: 45969 | AA5: Nil | AB5: Nil | AC5: Nil | AD5: 11/7/2025-Terms of Use URL replaced url
A6: 5 | B6: Donor Wave | C6: 45967 | D6: 45981 | E6: OB-OP 8.3 Sprint 3 | F6: Saranya/Irsath | G6: DON-100 | H6: Error pages design implementation | I6: Completed | J6: 5 | L6: 123.25 | M6: 45968 | N6: 45981 | O6: Done | P6: Murugesan M | Q6: 1.HTTP Error code ZERO along with text "Server not connected" is not valid when failed to load resource from API service 2.Wrong text message is displayed for 503 error code 3.Wrong text is displayed on the home page redirection button for 404 error code | R6: irsath | S6: Nil | T6: https://dev.azure.com/greatergiving/Greater%20Giving/_git/Donor/pullrequest/9007 | U6: 45980 | V6: 45981 | W6: Prabhu | X6: nil | Y6: joe | Z6: 45981 | AA6: Nil | AB6: Nil | AC6: Nil | AD6: 11/7/2025-Error pages design implementation 11/10/2025-working error code functionality 11/11/2025-fixing design issues. 11/12/2025-Unit testing 11/17/2025-page redirect issue fixing 11/18/2025-network issue finding 11/19/2025-code tuning 11/20/2025-working on cros issue code
A7: 7 | B7: Donor Wave | C7: 45967 | D7: 45981 | E7: OB-OP 8.3 Sprint 3 - [STRETCH] | F7: Saranya | G7: DON-122 | H7: Clicking -Cards on File | I7: Completed | J7: 1 | L7: 11 | M7: 45975 | N7: 45975 | O7: Done | P7: Murugesan M | Q7: Nil | R7: Arivalagan | S7: Nil | T7: https://dev.azure.com/greatergiving/Greater%20Giving/_git/Donor/pullrequest/9010 | U7: 45975 | V7: 45978 | W7: Prabhu | X7: Nil | Y7: Joe | Z7: 45978 | AA7: Nil | AB7: Nil | AC7: Nil | AD7: 11/14/2025- implementation for Cards on File
A8: 8 | B8: Donor Wave | C8: 45967 | D8: 45981 | E8: OB-OP 8.3 Sprint 3 - [STRETCH] | F8: Ubaithullah | G8: DON-120 | H8: Add AccountId to Donor card_references Table | I8: Completed | J8: 1 | L8: 19 | M8: 45975 | N8: 45979 | O8: Done | P8: Murugesan M | Q8: Nil | R8: Prabu | S8: Nil | T8: https://dev.azure.com/greatergiving/Greater%20Giving/_git/Donor/pullrequest/9016 | U8: 45978 | V8: 45979 | W8: Prabhu | X8: Nil | Y8: Joe | Z8: 45979 | AA8: Nil | AB8: Nil | AC8: Nil

Sheet OB-OP 8.3 Sprint 3-Defect
A1: S.No | B1: Sprint | C1: Story/Defect ID | D1: Parent Story | E1: Developer | F1: Issue Type | G1: Issue Description | H1: Priority | I1: Defect Source | J1: Type | K1: Status | L1: Root Cause Category | M1: Comments | N1: Found By | O1: RCA Comment

Sheet OB-OP 8.3 Sprint 2-Status
A1: S.No | B1: Application Name | C1: Sprint Start Date | D1: Sprint End Date | E1: Sprint | F1: Developer | G1: Story ID/Defect ID | H1: Description | I1: Status | J1: Estimated(hrs/sp) | K1: Actual(hrs/sp) | L1: Actual Hours Worklog | M1: Dev Start Date | N1: Dev End Date | O1: Unit testing | P1: Peer Tested By | Q1: Peer Tested Defects, if any | R1: Peer Reviewed By | S1: Peer Code Review Comments, if any | T1: PR Number/Link | U1: PR Created Date | V1: PR Approved Date | W1: Onsite Lead Code Review | X1: Code Review Comments, if any | Y1: Client Code Review | Z1: Approved Date | AA1: Code Review Comments, if any2 | AB1: Internal PO -POV Comments | AC1: Client PO -POV Comments | AD1: Comments
A2: 1 | B2: Donor Wave | C2: 45953 | D2: 45967 | E2: OB-OP 8.3 Sprint 2 | F2: Irsath | G2: Don-108 | H2: Establish b2c flow via login | I2: Completed | J2: 3 | M2: 45954 | N2: 45957 | O2: Done | Q2: Nil | R2: Kannan | S2: Nil | T2: https://dev.azure.com/greatergiving/Greater%20Giving/_git/Donor/pullrequest/8961 | U2: 45957 | V2: 45967 | W2: Prabhu | X2: Nil | Y2: Joe | Z2: 45967 | AA2: Nil | AB2: Nil | AC2: Nil | AD2: 10/24/2025 - Unwanted code has been reviewed and documented for non PKCE 10/27/2025 - Implemeneted Custom PKCE
A3: 2 | B3: Donor Wave | C3: 45953 | D3: 45967 | E3: OB-OP 8.3 Sprint 2 | F3: Kannan | G3: DON-103 | H3: Profile edit icon is not centered on Profile Image | I3: Completed | J3: 1 | M3: 45954 | N3: 45954 | O3: Done | P3: Murugesan M | Q3: Nil | R3: Prabhu | S3: Nil | T3: https://greatergiving.visualstudio.com/Greater%20Giving/_git/Donor/pullrequest/8951 | U3: 45954 | V3: 45954 | W3: Prabu | X3: Nil | Y3: Joe | Z3: 45954 | AA3: Nil | AB3: Nil | AC3: Nil
A4: 3 | B4: Donor Wave | C4: 45953 | D4: 45967 | E4: OB-OP 8.3 Sprint 2 | F4: Kannan | G4: DON-104 | H4: Adjust address Icon on Mobile | I4: Completed | J4: 1 | M4: 45954 | N4: 45954 | O4: Done | P4: Murugesan M | Q4: Nil | R4: Prabhu | S4: Nil | T4: https://greatergiving.visualstudio.com/Greater%20Giving/_git/Donor/pullrequest/8950 | U4: 45954 | V4: 45954 | W4: Prabu | X4: Nil | Y4: Joe | Z4: 45954 | AA4: Nil | AB4: Nil | AC4: Nil
A5: 4 | B5: Donor Wave | C5: 45953 | D5: 45967 | E5: OB-OP 8.3 Sprint 2 | F5: Ubaithullah/Kannan | G5: DON-97 | H5: Update to Credit Card area | I5: Completed | J5: 3 | M5: 45954 | N5: 45964 | O5: Done | P5: Murugesan M | Q5: 1]*should display before the last four digits of card name - VISA*4111 2]Amex card's Exp11/26 should move bit left to match other cards Exp dates-alignment issue 3]Primary should not be displayed when the card is already set as primary 4]Add payment button should display as per Figma for all the views 5]Border line should be displayed in between each credit cards 6]Add payment method button color code should match with Figma Ref -#262AFF 7]All the master card name and number should display in the same row for Mobile Landscape 8]Delete text should be in Red color -#910818 9]Y was displayed in next row in primary text in Mobile Portrait responsive 10]One space was displayed in Exp date when i created same credit card second time in my system | R5: Irsath | S5: Nil | T5: https://dev.azure.com/greatergiving/Greater%20Giving/_git/Donor/pullrequest/8968 | U5: 45960 | V5: 45964 | W5: Prabhu | X5: Nil | Y5: Joe | Z5: 45964 | AA5: NIl | AB5: NIl | AC5: Nil
A6: 5 | B6: Donor Wave | C6: 45953 | D6: 45967 | E6: OB-OP 8.3 Sprint 2 | F6: Arivalagan/Saranya | G6: DON-92 | H6: Login page styling | I6: Completed | J6: 5 | M6: 45954 | N6: 45965 | O6: Done | P6: Murugesan M | Q6: 1.Footer text should be displayed as Cookie policy , not alone privacy policy and agree text should be displayed in the first row after you as per Figma 2.Error message should be displayed as Enter a valid email address as per figma 3.Lock icon should 16x16 width height as per figma- not fixed 4.That text should display in first row security code as per figma[ This helps us keep your account secure by verifying that it’s really you.] 5.Footer text should not be displayed in security page as per Figma 6.Login security code page text box gap looks 12 px and each button width size looks 490 in Figma 7.Rest your password text alignment should match with Figma 8.letter spacing needs to adjusted as per figma in Reset your password page 9.Forgot email hyperlink should show fully in the bottom of login page when mouse hover it 10.to and policy should be displayed to next link in the footer text as per figma in reset your password page 11.Spelling mistake in Repeate [Repeat]Password is required text in Reset your password page 12]Password text should be masked while typing in reset password | T6: https://greatergiving.visualstudio.com/Greater%20Giving/_git/Donor/pullrequest/8975 | U6: 45964 | V6: 45965 | W6: Prabhu | X6: nil | Y6: Joe | Z6: 45965 | AA6: Nil | AB6: Nil | AC6: Nil | AD6: 10/24/2025-Analysis and start implementaion 10/27/2025-Login page design implementation 10/28/2025-Reset password page design implementation 10/29/2025- Security Code Screen implementaion 10/30/2025-login page hide and show working 10/31/2025-finding issue fixed 11/03/2025-code cleanup 11/04/2025-autofocus implementation 11/5/2025-autofoucs implementation 11/6/2025-vega textbox image findings
A7: 6 | B7: Donor Wave | C7: 45953 | D7: 45967 | E7: OB-OP 8.3 Sprint 2 | F7: Kannan | G7: DON-101 | H7: Remove CVV from DB | I7: Completed | J7: 2 | M7: 45957 | N7: 45958 | AD7: PR was not created for this
A8: 7 | B8: Donor Wave | C8: 45953 | D8: 45967 | E8: OB-OP 8.3 Sprint 2 - [STRETCH] | F8: Irsath | G8: Don-87 | H8: Review Loading screens | I8: Completed | J8: 2 | M8: 45958 | N8: 45961 | O8: Done | P8: Murugesan M | Q8: Nil | R8: Ubaithullah | S8: Nil | T8: https://dev.azure.com/greatergiving/Greater%20Giving/_git/Donor/pullrequest/8966 | U8: 45959 | V8: 45964 | W8: Prabhu | X8: Nil | Y8: Joe | Z8: 45964 | AA8: Nil | AB8: Nil | AC8: Nil | AD8: 10/28/2025 - Loader implemented in address and edit page 10/29/2025 - Task has been completed and created PR 10/30/2025 - Banner hight issues has been resolved
A9: 8 | B9: Donor Wave | C9: 45953 | D9: 45967 | E9: OB-OP 8.3 Sprint 2 - [STRETCH] | F9: Irsath | G9: DON-102 | H9: Adjust Body Height | I9: Completed | J9: 1 | M9: 45961 | N9: 45961 | O9: Done | P9: Murugesan M | Q9: Nil | R9: Arivalagan | S9: Nil | T9: https://dev.azure.com/greatergiving/Greater%20Giving/_git/Donor/pullrequest/8972 | U9: 45961 | V9: 45964 | W9: Prabhu | X9: Nil | Y9: Joe | Z9: 45964 | AA9: Nil | AB9: Nil | AC9: Nil | AD9: 10/31/2025 - Design issue has been fixed
A10: 9 | B10: Donor Wave | C10: 45953 | D10: 45967 | E10: OB-OP 8.3 Sprint 2 - [STRETCH] | F10: Irsath | G10: Don-99 | H10: Convert Address page from bootstrap to Vega control | I10: Being Developed | J10: 3 | M10: 45964 | AD10: 11/3/2025 - Few textboxs convert from bootstap to vega control 11/4/2025 - 30% controls converted into vega 11/5/2025 - 80% controls converted into vega 11/5/2025 - 100% controls converted into vega
A11: 10 | B11: Donor Wave | C11: 45953 | D11: 45967 | E11: OB-OP 8.3 Sprint 2 - [STRETCH] | F11: Ubaithullah/Kannan | G11: Don-109 | H11: Profile Data Management | I11: Being Developed | J11: 5 | M11: 45964 | AD11: 11/4/2025 - Analysis

Sheet OB-OP 8.3 Sprint 2-Defect
A1: S.No | B1: Sprint | C1: Story/Defect ID | D1: Parent Story | E1: Developer | F1: Issue Type | G1: Issue Description | H1: Priority | I1: Defect Source | J1: Type | K1: Status | L1: Root Cause Category | M1: Comments | N1: Found By | O1: RCA Comment

Sheet OB-OP 8.3 Sprint 1-Status
A1: S.No | B1: Application Name | C1: Sprint Start Date | D1: Sprint End Date | E1: Sprint | F1: Developer | G1: Story ID/Defect ID | H1: Description | I1: Status | J1: Estimated(hrs/sp) | K1: Actual(hrs/sp) | L1: Actual Hours Worklog | M1: Dev Start Date | N1: Dev End Date | O1: Unit testing | P1: Peer Tested By | Q1: Peer Tested Defects, if any | R1: Peer Reviewed By | S1: Peer Code Review Comments, if any | T1: PR Number/Link | U1: PR Created Date | V1: PR Approved Date | W1: Onsite Lead Code Review | X1: Code Review Comments, if any | Y1: Client Code Review | Z1: Approved Date | AA1: Code Review Comments, if any2 | AB1: Internal PO -POV Comments | AC1: Client PO -POV Comments | AD1: Comments
A2: 1 | B2: Donor Wave | C2: 45939 | D2: 45953 | E2: OB-OP 8.3 Sprint 1 | F2: Arivalagan, Ubhaithulla | G2: DON-71 | H2: Donor Platform - When clicking Edit Icon for Nameplate, go to Edit Profile | I2: Completed | J2: 5 | L2: 214.25 | M2: 45940 | N2: 45952 | O2: Done | P2: Murugesan M | Q2: 1.File type not supported text is displayed by default even after clicking cancel button on upload model -fixed 2.Image should not be displayed again in upload modal once it is deleted 3.Remove here text from upload your image icon modal 4.File size exceeds!text is displayed by default even after clicking cancel button on upload model 5.Allowing space in name fields does not allow save button enabled ,need some restrictions there 6.Default name text should not be displayed in image preview view , can show profile image text there generally. 7.update btn is still enabled when come next time after selecting image and close the modal without updating it 8.Error message should not be displayed while uploading the image second time in the add profile modal after clikcing cancel button | T2: https://dev.azure.com/greatergiving/Greater%20Giving/_git/Donor/pullrequest/8911 | U2: 45947 | V2: 45953 | W2: Prabu | Y2: Joe | Z2: 45953 | AA2: 1. Make sure you clean up the interval in the ngOnDestroy, or even remove this entirely because it's handled in [disabled]="profileForm.invalid". 2. Direct DOM manipulation is unsafe. Let's get the file through the event parameter rather than DOM manipulation. Use Angular's built-in change detection. 3. Magic number here. Let's make it a constant/configurable. 4. Remove unused property 5. Sanitize the result before binding (xss risk) 6. This form needs labels rather than placeholders. See the FIgma document. Use the "label" Vega attribute. 7. Name fields (first, middle, last) should have the input validation | AB2: Nil | AC2: Nil | AD2: 10/10/2025-Implement the vega components 10/13/2025-implement the vega button and upload components 10/14/2025-vega desing issue and button component 10/15/2025 -vega desing issue and button component 10/16/2025-vega input design implementation 10/17/2025-finding issue fixed 10/21/2025 -worked on refactoring the code 10/22/2025-working on client reivew code 10/23/2025-working on review and code walkthrough
A3: 2 | B3: Donor Wave | C3: 45939 | D3: 45953 | E3: OB-OP 8.3 Sprint 1 | F3: Saranya | G3: DON-92 | H3: Donor-Login Page Styling | I3: Being Developed | J3: 3 | L3: 70.5 | M3: 45940 | O3: Done | P3: Murugesan M | Q3: 1.Email address label should be displayed as per Figma_ Create account page 2.div content max width should be 500 px and so that text box width should be matched with Figma_ Create account page 3.text box label bg color does not match with Figma #04041C94 _ Create account page 4.Continue button color code should match with Figma #262AFF _ Create account page 5.Button width should be matched with Figma 500px,currently bit short_Check your inbox page 6.Continue and resend code button should match with Figma color code #262AFF _Verify your Account page 7.new password and Repeat password label text color should match with Figma _Create your password page 8.Continue button bg color should match with Figma in #B0B4B5 [grey]and #262AFF[Blue]_Create your password page 9.Input text box color should be ##04041C94_Add a Member to your account page 10.Continue and Skip text should be #262AFF_Add a Member to your account page 11.Console error "address-form.component.ts:612 ERROR TypeError: Cannot set properties of null (setting 'disabled') at address-form.component.ts:619:23 is displayed in create password page 12]Consol;e error "Error NG0150: form control name must be used with a parent form group directive is displayed | R3: Arivalagan | T3: https://dev.azure.com/greatergiving/Greater%20Giving/_git/Donor/pullrequest/8931 | U3: 45947 | AD3: 10/10/2025-sign-up page design implementation 10/13/2025-personal information page 10/14/2025-signup page unit testing 10/15/2025-login page design implementation 10/16/2025-fixing design issues 10/17/2025-fixing design issue
A4: 3 | B4: Donor Wave | C4: 45939 | D4: 45953 | E4: OB-OP 8.3 Sprint 1 | F4: Irsath/Kannan | G4: DON-23 | H4: Create the backend login flow | I4: Completed | J4: 3 | L4: 112.25 | M4: 45940 | N4: 45953 | O4: Done | R4: Prabhu | S4: Nil | AD4: 10/10/2025 - Analyzed done 10/13/2025 - Working on B2C 10/14/2025 - Working on B2C 10/15/2025 - Working on B2C 10/16/2025 - Working on B2C 10/17/2025 - Working on B2C 10/21/2025 - Working on B2C 10/22/2025 - Working on B2C 10/23/2025 - Working on B2C
A5: 4 | B5: Donor Wave | C5: 45939 | D5: 45953 | E5: OB-OP 8.3 Sprint 1 | F5: Kannan | G5: DON-89 | H5: Donor - Add missing info banners | I5: Completed | J5: 2 | L5: 12 | M5: 45940 | N5: 45940 | O5: Done | P5: Murugesan M | Q5: 1] Show the warning message text same as it is in Address accordian area | R5: Prabhu | S5: Nil | T5: Pull Request 8916: DON-89 Donor - Add missing info banners | U5: 45940 | V5: 45945 | W5: Prabhu | X5: Nil | Y5: Joe | Z5: 45945 | AA5: Development done on 10/10/2025 and tested by Murugesan and created PR the same day | AB5: Nil | AC5: Nil | AD5: 10/10/2025 - Development done and created PR
A6: 5 | B6: Donor Wave | C6: 45939 | D6: 45953 | E6: OB-OP 8.3 Sprint 1 - [STRETCH] | F6: Prabu | G6: DON-96 | H6: Update Profile API handling | I6: Completed | J6: 2 | L6: 7.5 | M6: 45951 | N6: 45952 | O6: Done | P6: Prabu | Q6: Nil | R6: Joe | S6: Nil | T6: https://greatergiving.visualstudio.com/Greater%20Giving/_git/Donor/pullrequest/8943 | U6: 45953 | V6: 45953 | W6: Prabu | X6: Nil | Y6: Joe | Z6: 45953 | AA6: Nil | AB6: Nil | AC6: Nil
A7: 6 | B7: Donor Wave | C7: 45939 | D7: 45953 | E7: OB-OP 8.3 Sprint 1 - [SPIKE] | F7: Prabu | G7: DON-95 | H7: Use GGO policy instead of OP Policy for MFA login | I7: Completed | J7: 1 | L7: 0.75 | M7: 45951 | N7: 45953 | AD7: It is a investigation story, and it will get completed by tonight 10/23/2025

Sheet OB-OP 8.3 Sprint-1-Defect
A1: S.No | B1: Sprint | C1: Story/Defect ID | D1: Parent Story | E1: Developer | F1: Issue Type | G1: Issue Description | H1: Priority | I1: Defect Source | J1: Type | K1: Status | L1: Root Cause Category | M1: Comments | N1: Found By | O1: RCA Comment

Sheet OB-OP 8.2 Sprint 4-Status
A1: S.No | B1: Application Name | C1: Sprint Start Date | D1: Sprint End Date | E1: Sprint | F1: Developer | G1: Story ID/Defect ID | H1: Description | I1: Status | J1: Estimated(hrs/sp) | K1: Actual(hrs/sp) | L1: Actual Hours Worklog | M1: Dev Start Date | N1: Dev End Date | O1: Unit testing | P1: Peer Tested By | Q1: Peer Tested Defects, if any | R1: Peer Reviewed By | S1: Peer Code Review Comments, if any | T1: PR Number/Link | U1: PR Created Date | V1: PR Approved Date | W1: Onsite Lead Code Review | X1: Code Review Comments, if any | Y1: Client Code Review | Z1: Approved Date | AA1: Code Review Comments, if any2 | AB1: Internal PO -POV Comments | AC1: Client PO -POV Comments | AD1: Comments
A2: 1 | B2: Donor Wave | C2: 45925 | D2: 45939 | E2: OB-OP 8.2 Sprint 4 | F2: Kannan, Ubhaithulla | G2: DON-71 | H2: Donor Platform - When clicking Edit Icon for Nameplate, go to Edit Profile | I2: Being Developed | J2: 5 | L2: 157.75 | M2: 45926 | N2: 45938 | O2: Done | P2: Murugesan M | Q2: 1]profile gets updated with invalid values 2]Profile gets updated without values input fields- should show error msg for empty fields 3]Image upload accepts doc file and no error msg displayed 4]need space btw profile photo label and add profile button as per figma 5]Color code of update btn , select or drop text should match with figma - #262AFF 6]Home page Input fields label text color should match with Figma#04041C94 58% 7]Removal image option is not displayed if image exists 8]padding should be 32px in upload modal and color code of cancel btn should match with figma - #262AFF 9]Add profile photo text should be #04041CF2 as per figma 10]Add profile modal should have 550 x 332 px from Desktop to Mob L and for Mob P only should have 390 x 330 px width and height 11]Upload area div should match width and height with figma from Desktop to Mobile Portrait 12]Cancel and update button color code ,width and padding should match with Figma 13]Upload note content text color code should match with Figma 14]Upload modal close icon color code and width should match with Figma 15]Upload modal bg color should be #F0F3F7 as per Figma 16]Add profile photo and Edit initials buttons color code should match with Figma 17]Save profile and cancel button color code should match with Figma -#262AFF 18]Edit profile and profile Photo text color should match with Figma -#04041CF2 19]Uploading new image should not updated in edit profile page when clicking on cancel btn 20]Add delete icon in edit profile page if image exists 21]Modal cancel and update button figma size match 22]In the Mob portrait view , profile photo text should come bit right and bit space btw image and add profile edit intials btn as in figma 23]Mobile number is required error message should be displayed when there is no value present in mobile field 24]Error message should be displayed for incomplete value in email field 25]Red bg color should be displayed behind the input field when there is any error to highlight user though error message is displayed in the page | T2: https://greatergiving.visualstudio.com/Greater%20Giving/_git/Donor/pullrequest/8911 | AD2: 10/09/2025-task completed
A3: 2 | B3: Donor Wave | C3: 45925 | D3: 45939 | E3: OB-OP 8.2 Sprint 4 | F3: Irsath | G3: Don-64 | H3: Donor Platform - Add Address button | I3: Completed | J3: 3 | K3: 3 | L3: 56.75 | M3: 45926 | N3: 45936 | O3: Done | P3: Murugesan M | Q3: 1]Add address manually option is not coming when address is not available in google API 2]Black background color is displayed in the search result panel 3] there is some Difference on edit address remove confirmation window with Figma 4]Should be a camel case in country name input field error msg | R3: Arivalagan | S3: Nil | T3: https://dev.azure.com/greatergiving/Greater%20Giving/_git/Donor/pullrequest/8862 | U3: 45938 | V3: 45939 | W3: Prabu | X3: Nill | Y3: Joe | Z3: 45939 | AA3: Nil | AB3: Nil | AC3: Nil | AD3: 9/26/2025 - Add Address Manully design issue has been fixed 9/29/2025 - Code has been optimized 9/30/2025- Code has been optimized 10/7/2025- Fixed Review comments issues 10/8/2025- Fixed Review comments issues 10/9/2025- Fixed Review comments issues
A4: 3 | B4: Donor Wave | C4: 45925 | D4: 45939 | E4: OB-OP 8.2 Sprint 4 | F4: saranya | G4: DON-78 | H4: Donor Platform - Clean Up | I4: Completed | J4: 2 | L4: 26 | M4: 45926 | N4: 45930 | O4: Done | P4: Murugesan M | Q4: Nil | R4: Arivalagan | S4: Nil | T4: https://dev.azure.com/greatergiving/Greater%20Giving/_git/Donor/pullrequest/8885 | U4: 45930 | V4: 45934 | W4: Prabu | X4: Nil | Y4: Joe | Z4: 45934 | AA4: Nil | AB4: Nil | AC4: Nil | AD4: 9/26/2025 - Banner Persists working 9/29/2025-Add Address Area 9/30/2025-Payment Method
A5: 4 | B5: Donor Wave | C5: 45925 | D5: 45939 | E5: OB-OP 8.2 Sprint 4 | F5: arivalagan | G5: DON-70 | H5: Past Events - Show Previous Events button/Functionality | I5: Completed | J5: 5 | K5: 5 | L5: 45.5 | M5: 45926 | N5: 45934 | O5: Done | P5: Murugesan M | Q5: 1]previous events attended label width was mismatched with Figma ref 2]help and previous was displayed as button instead of link | R5: saranya | T5: https://dev.azure.com/greatergiving/Greater%20Giving/_git/Donor/pullrequest/8889 | U5: 45931 | V5: 45934 | W5: Prabu | X5: Nil | Y5: joe | Z5: 45934 | AA5: Nil | AB5: Nil | AC5: Nil | AD5: 9/26/2025 - Analysis and stated implementation 9/29/2025-Design implementation 9/30/2025-findings issue fixed 10/03/2025-Finding and issue fixing
A6: 5 | B6: Donor Wave | C6: 45925 | D6: 45939 | E6: OB-OP 8.2 Sprint 4 - [Stretch] | F6: saranya | G6: DON-83 | H6: Donor-Help-accordion | I6: Completed | J6: 1 | L6: 9 | M6: 45933 | N6: 45933 | O6: Done | P6: Murugesan M | Q6: 1]help link icon's arrow was mismatched with figma ref | R6: Arivalagan | S6: Nil | T6: https://dev.azure.com/greatergiving/Greater%20Giving/_git/Donor/pullrequest/8898 | U6: 45936 | V6: 45937 | W6: Prabu | X6: Nil | Y6: Joe | Z6: 45937 | AA6: Nil | AB6: Nil | AC6: Nil | AD6: 10/03/2025- added help link
A7: 6 | B7: Donor Wave | C7: 45925 | D7: 45939 | E7: OB-OP 8.2 Sprint 4 - [Stretch] | F7: saranya | G7: DON-85 | H7: Donor-Updatered-pill-to-match-Remove-text | I7: Completed | J7: 1 | L7: 6 | M7: 45933 | N7: 45933 | O7: Done | P7: Murugesan M | Q7: Nil | R7: Arivalagan | S7: Nil | T7: https://dev.azure.com/greatergiving/Greater%20Giving/_git/Donor/pullrequest/8899 | U7: 45936 | V7: 45937 | W7: Prabu | X7: Nil | Y7: Joe | Z7: 45937 | AA7: Nil | AB7: Nil | AC7: Nil | AD7: 10/03/2025-pill color code has been changed
A8: 7 | B8: Donor Wave | C8: 45925 | D8: 45939 | E8: OB-OP 8.2 Sprint 4 - [Stretch] | F8: Irsath | G8: Don-86 | H8: Donor-Update backend to pick up Org and Events in single call | I8: Completed | J8: 5 | L8: 32.25 | M8: 45933 | N8: 45938 | O8: Done | P8: Murugesan M | Q8: Nil | R8: Arivalagan | S8: Nil | T8: https://dev.azure.com/greatergiving/Greater%20Giving/_git/Donor/pullrequest/8900 | U8: 45936 | V8: 45938 | W8: Prabu | X8: Nil | Y8: Joe | Z8: 45938 | AA8: Nil | AB8: Nil | AC8: Nil | AD8: 10/03/2025 - Created API 10/06/2025 - Integrated API for org and events
A9: 8 | B9: Donor Wave | C9: 45925 | D9: 45939 | E9: OB-OP 8.2 Sprint 4 - [Stretch] | F9: saranya/arivalagan | G9: DON-92 | H9: Donor-Login Page Styling | I9: Being Developed | J9: 3 | L9: 31.75 | M9: 45936 | O9: Done | AD9: 10/06/2025 -Donor-Login Page Styling-analyzing and design implementation 10/07/2025-Login page design implementation 10/08/2025-signup page design 10/09/2025-signup page design
A10: 9 | B10: Donor Wave | C10: 45925 | D10: 45939 | E10: OB-OP 8.2 Sprint 4 | F10: Prabu | G10: DON-81 | H10: Donor - Update "Events Purchased" to "Upcoming Events" | I10: Completed | J10: 1 | L10: 8.5 | M10: 45927 | N10: 45927 | O10: Done | P10: Prabu | Q10: Nil | R10: Joe | S10: Nil | T10: https://greatergiving.visualstudio.com/Greater%20Giving/_git/Donor/pullrequest/8880 | U10: 45927 | V10: 45927 | W10: Rajesh | X10: Nill | Y10: Joe | Z10: 45927 | AA10: Nil | AB10: Nil | AC10: Nil | AD10: 10/09/2025-task completed

Sheet OB-OP 8.2 Sprint 3-Status
A1: S.No | B1: Application Name | C1: Sprint Start Date | D1: Sprint End Date | E1: Sprint | F1: Developer | G1: Story ID/Defect ID | H1: Description | I1: Status | J1: Estimated(hrs/sp) | K1: Actual(hrs/sp) | L1: Actual Hours Worklog | M1: Dev Start Date | N1: Dev End Date | O1: Unit testing | P1: Peer Tested By | Q1: Peer Tested Defects, if any | R1: Peer Reviewed By | S1: Peer Code Review Comments, if any | T1: PR Number/Link | U1: PR Created Date | V1: PR Approved Date | W1: Onsite Lead Code Review | X1: Code Review Comments, if any | Y1: Client Code Review | Z1: Approved Date | AA1: Code Review Comments, if any2 | AB1: Internal PO -POV Comments | AC1: Client PO -POV Comments | AD1: Comments
A2: 1 | B2: Donor Wave | C2: 45911 | D2: 45925 | E2: OB-OP 8.2 Sprint 3 | F2: Irsath/Arivalagan | G2: DON-64 | H2: Donor Platform - Add Address button | I2: Being Developed | J2: 5 | L2: 129.5 | M2: 45911 | N2: 45925 | O2: Nill | P2: Murugesan M | Q2: 1.Blank white pop-up is displayed in Add address window if user does not close address deleted successfully pop-up in home page and clicked Add address button 2.Remove button should not be displayed in Add address window 3.User address should not be saved and update without value in the input field 4.Add result component UI issues –it is not rounded off in the corner and background button blue color should not display in the right bottom and Location icon should not be displayed. 5.Postal code input field should accept only numeric values, it accepts letters as well now 6.Mobile and Tablet UI issue: drop down values comes out of screen and background blue should also be #262AFF 7.City value should not accept numeric values in add and Edit address window 8.Dot should not display at the end of warning message in Add address area 9.There should space between country / Region label 10.Remove window – Dot should be displayed at the end of confirm text 11.Cancel button color should be #262AFF as per Figma 12.Remove text Bg color code should be as per Figma #910818 13.From home page to remove address , entire confirmation text shows as bold , but from edit remove it shows as in figma 14.Black background color is displayed in the search result panel 15.Add Address manually option is not working on first click, taking time. [ some delay there] 16.Add address manually option is still coming up even user is chosen manually enter option from first screen 17.Add address manually option is not coming when address is not available in google API 18.In mobile portrait view, address update successfully confirmation text coming not coming in one line in edit address window | R2: Arivalagan | S2: Nil | T2: https://dev.azure.com/greatergiving/Greater%20Giving/_git/Donor/pullrequest/8862 | U2: 45923 | V2: Nil | W2: Nil | X2: Nil | Y2: Nil | Z2: Nil | AA2: Nil | AB2: Nil | AC2: Nil | AD2: 9/12/2025 - Analysis completed started development 9/16/2025 - Created address component and add home address design done 9/17/2025 -Completed Save & Delete Address API ,Created separate component for address. 9/18/2025 - Implemeting Google address api 9/19/2025 - Address API New changes done,align issues has been fixed 9/22/2025 - Integrated Save,Edit & Remove Api with component 9/23/2025 - Adderss page`s Response UI 9/24/2025 - Hide/Show Address Autocomplete based on condition 9/25/2025 - Alignment Issue fixed
A3: 2 | B3: Donor Wave | C3: 45911 | D3: 45925 | E3: OB-OP 8.2 Sprint 3 | F3: Arivalagan | G3: Don-63 | H3: Donor Platform - Payment Method MVP | I3: Completed | J3: 2 | L3: 62 | M3: 45912 | N3: 45919 | P3: Murugesan M | Q3: 1.Add payment button font size differs to Figma Reference in Mobile view | T3: https://dev.azure.com/greatergiving/Greater%20Giving/_git/Donor/pullrequest/8841 | U3: 45916 | V3: 45925 | W3: Prabu | X3: Nil | Y3: Joe | Z3: 45925 | AA3: Nil | AB3: Nil | AC3: Nil | AD3: 9/12/2025-Working mobile desing with desktop as well 9/16/2025-findings fixed 9/17/2025-Desing issue fixing and Added svg icon 9/19/2025-removed SVG icon, and adjust the remove button
A4: 3 | B4: Donor Wave | C4: 45911 | D4: 45925 | E4: OB-OP 8.2 Sprint 3 | F4: Saranya | G4: Don-73 | H4: Past Events - Completed Tag and Leave Story in list | I4: Completed | J4: 2 | L4: 47.5 | M4: 45912 | N4: 45923 | O4: Done | P4: Murugesan M | Q4: 1.There is difference in Color code and Font on Event complete Text While comparing to Figma [Color should be #04041CF2] and Font should be Inter only. 2.Hyphen is missing before the city in the event data. please ref the Attachment in the Jira ticket or Figma event area. | R4: Arivalagan | S4: Nil | T4: https://greatergiving.visualstudio.com/Greater%20Giving/_git/Donor/pullrequest/8855 | U4: 45923 | V4: 45924 | W4: Prabu | X4: Nil | Y4: Joe | Z4: 45924 | AA4: Nil | AB4: Nil | AC4: Nil | AD4: 9/12/2025-Analysing the story 9/15/2025-start the development 9/16/2025-working on functionality and design issue 9/17/2025-working on vega -chip design issue 9/18/2025-working on vega -chip color code issue
A5: 4 | B5: Donor Wave | C5: 45911 | D5: 45925 | E5: OB-OP 8.2 Sprint 3 | F5: Saranya | G5: Don-72 | H5: DON-72 Donor Clean Up | I5: Completed | J5: 1 | L5: 38.75 | M5: 45919 | N5: 45924 | O5: Done | P5: Murugesan M | Q5: 1.Footer Links color code does not match with Figma reference 2. There is more white space between footer text and help area | R5: Arivalagan | S5: Nil | T5: https://greatergiving.visualstudio.com/Greater%20Giving/_git/Donor/pullrequest/8857 | U5: 45924 | V5: 45924 | W5: Prabu | X5: Nil | Y5: Joe | Z5: 45924 | AA5: Nil | AB5: Nil | AC5: Nil | AD5: 9/19/2025- Analysing the story -started Resize Icons design changes 9/22/2025-Responsive Accordion border bottoms 9/23/2025-Logging Review

Sheet OB-OP 8.2 Sprint-4-Defect
A1: S.No | B1: Sprint | C1: Story/Defect ID | D1: Parent Story | E1: Developer | F1: Issue Type | G1: Issue Description | H1: Priority | I1: Defect Source | J1: Type | K1: Status | L1: Root Cause Category | M1: Comments | N1: Found By | O1: RCA Comment

Sheet OB-OP 8.2 Sprint-3-Defect
A1: S.No | B1: Sprint | C1: Story/Defect ID | D1: Parent Story | E1: Developer | F1: Issue Type | G1: Issue Description | H1: Priority | I1: Defect Source | J1: Type | K1: Status | L1: Root Cause Category | M1: Comments | N1: Found By | O1: RCA Comment

Sheet OB-OP 8.2 Sprint 2-Status
A1: S.No | B1: Application Name | C1: Sprint Start Date | D1: Sprint End Date | E1: Sprint | F1: Developer | G1: Story ID/Defect ID | H1: Description | I1: Status | J1: Estimated(hrs/sp) | K1: Actual(hrs/sp) | L1: Actual Hours Worklog | M1: Dev Start Date | N1: Dev End Date | O1: Unit testing | P1: Peer Tested By | Q1: Peer Tested Defects, if any | R1: Peer Reviewed By | S1: Peer Code Review Comments, if any | T1: PR Number/Link | U1: PR Created Date | V1: PR Approved Date | W1: Onsite Lead Code Review | X1: Code Review Comments, if any | Y1: Client Code Review | Z1: Approved Date | AA1: Code Review Comments, if any2 | AB1: Internal PO -POV Comments | AC1: Client PO -POV Comments | AD1: Comments
A2: 1 | B2: Donor Wave | C2: 45897 | D2: 45911 | E2: OB-OP 8.2 Sprint 2 | F2: Irsath | G2: DON-41 | H2: Donor Platform Home - Nameplate | I2: Completed | J2: 5 | L2: 70.5 | M2: 45897 | N2: 45909 | O2: Nil | P2: Murugesan M | Q2: 1Error message is not displayed when uploading iamge more than 2 mb second time in the profile section | R2: Arivalagan | S2: Nil | T2: https://dev.azure.com/greatergiving/Greater%20Giving/_git/Donor/pullrequest/8800 | U2: 45903 | V2: 45909 | W2: Prabhu | X2: Nil | Y2: Joe | Z2: 45909 | AA2: Nil | AB2: Nil | AC2: Nil | AD2: 8/29/2025 - Analysis are completed 9/1/2025 - First/last initials of the user , max image size -2mb completed 9/2/2025 - Update Profile Picture`s API completed 9/3/2025 - Removed Background Image,Tested Profile Pictures 9/4/2025 - Get Uploaded profile picture API done 9/5/2025 - Toaster message font issue has been fixed 9/8/2025 - Merge code with don-51
A3: 2 | B3: Donor Wave | C3: 45897 | D3: 45911 | E3: OB-OP 8.2 Sprint 2 | F3: Arivu | G3: DON-51 | H3: Donor Platform - Events MVP | I3: Completed | J3: 3 | L3: 102.17 | M3: 45898 | N3: 45905 | O3: Nil | P3: Murugesan M | R3: Irsath | S3: 1.Need to develop simplifiy the code | T3: https://dev.azure.com/greatergiving/Greater%20Giving/_git/Donor/pullrequest/8765 | U3: 45894 | V3: 45909 | W3: Prabhu | X3: Nil | Y3: Joe | Z3: 45909 | AA3: Nil | AB3: Nil | AC3: Nil | AD3: 8/29/2025-Finding issue fixing 9/1/2025-Finding and reported issue is fixed 9/2/2025-Findings and design issue fixing 9/3/2025-Event screen issue fixng 9/5/2025-Code merge and issue is fxing
A4: 3 | B4: Donor Wave | C4: 45897 | D4: 45911 | E4: OB-OP 8.2 Sprint 2 | F4: Saranya | G4: Don-66 | H4: Donor Platform Home - header | I4: Completed | J4: 2 | L4: 48.75 | M4: 45898 | N4: 45904 | O4: Nil | P4: Murugesan M | R4: Arivalagan | S4: Nil | T4: https://dev.azure.com/greatergiving/Greater%20Giving/_git/Donor/pullrequest/8789 | U4: 45901 | V4: 45905 | W4: Prabhu | X4: Nil | Y4: Joe | Z4: 45905 | AA4: Nil | AB4: Nil | AC4: Nil | AD4: 8/29/2025 - DON-66 Analysis and implement design part 9/1/2025 -DON-66 Fixing the design issue 9/2/2025- Exploring Azure defender storage 9/3/2025- Exploring Azure defender storage and preparing document 9/4/2025 -DON-66 logo design and media breakpoint issue fixing
A5: 4 | B5: Donor Wave | C5: 45883 | D5: 45897 | E5: OB-OP 8.2 Sprint 2 | F5: Irsath | G5: DON-45 | H5: Donor Platform - Handle Token from B2C | I5: Completed | J5: 2 | L5: 37 | M5: 45909 | N5: 45910 | O5: Nil | R5: Arivalagan | S5: Nil | T5: https://dev.azure.com/greatergiving/Greater%20Giving/_git/Donor/pullrequest/8652 | U5: 45882 | V5: 45911 | W5: Prabhu | X5: Nil | Y5: Joe | Z5: 45911 | AA5: Nil | AB5: Nil | AC5: Nil | AD5: 9/8/2025- Document Preparation 9/9/2025 - Resolve merge conflicts with dev branch 9/10/2025 - B2C Issue fixed 9/11/2025 - B2C Issue fixed
A6: 5 | B6: Donor Wave | C6: 45897 | D6: 45911 | E6: OB-OP 8.2 Sprint 2 - [Stretch] | F6: Saranya | G6: Don-63 | H6: Donor Platform - Payment Method MVP | I6: Being Developed | J6: 3 | L6: 73.75 | M6: 45905 | O6: Nil | P6: Murugesan M | Q6: 1.Card type has some variations in font size while comparing to Figma [Font size should be Inter- 18 px] 2.There is some difference in Expiration type’s width and font while comparing to Figma 3.There is some difference in Payment methods row size width while comparing to Figma 4.Primary text is missing in the payment method area when there is multiple cards are present 5.Remove link should be displayed at right last column as it is in the Figma 6.Clicking on remove link goes to login window now. There should not be edit functionality at this time. 7.Add payment method button should start and display under exactly card image, currently it is bit moved left side it seem while comparing to Figma. 8.Payment methods is not displayed properly in Mobile portrait view while comparing to Figma | AD6: 9/5/2025-Don-63 analyzing and start the design implemntation 9/08/2025 -Don-63 -design implementation 9/09/2025-Don-63-working on card functionality 9/10/2025-Don-63-working on design issue 9/11/2025-Don-63-working on mobile design

Sheet OB-OP 8.2 Sprint-2-Defect
A1: S.No | B1: Sprint | C1: Story/Defect ID | D1: Parent Story | E1: Developer | F1: Issue Type | G1: Issue Description | H1: Priority | I1: Defect Source | J1: Type | K1: Status | L1: Root Cause Category | M1: Comments | N1: Found By | O1: RCA Comment

Sheet OB-OP 8.2 Sprint 1-Status
A1: S.No | B1: Application Name | C1: Sprint Start Date | D1: Sprint End Date | E1: Sprint | F1: Developer | G1: Story ID/Defect ID | H1: Description | I1: Status | J1: Estimated(hrs/sp) | K1: Actual(hrs/sp) | L1: Actual Hours Worklog | M1: Dev Start Date | N1: Dev End Date | O1: Unit testing | P1: Peer Tested By | Q1: Peer Tested Defects, if any | R1: Peer Reviewed By | S1: Peer Code Review Comments, if any | T1: PR Number/Link | U1: PR Created Date | V1: PR Approved Date | W1: Onsite Lead Code Review | X1: Code Review Comments, if any | Y1: Client Code Review | Z1: Approved Date | AA1: Code Review Comments, if any2 | AB1: Internal PO -POV Comments | AC1: Client PO -POV Comments | AD1: Comments
A2: 1 | B2: Donor Wave | C2: 45883 | D2: 45897 | E2: OB-OP 8.2 Sprint 1 | F2: Irsath | G2: DON-61 | H2: Organizations - Update to MVP | I2: Completed | J2: 3 | K2: 3 | L2: 89.75 | M2: 45883 | N2: 45895 | O2: Nil | P2: Murugesan M | Q2: 1.Organization area/section seems very lengthy,which should be center aligned as in the Figma 2.Organization area/section Arrow function is not working to get collapsed, it looks always expanded by default 3.Organization icon background color should be grey from blue when it is collapsed, as it is in Figma 4.Organization area/section light border color code should be displayed as it is in Figma 5.Organization name's Text color code should be displayed as it is in Figma 6.The background of the organization title box color should be displayed as it is in Figma 7. Comma should not be displayed when there is no city , state in the organization 8.When org area is collapsed it should be #FCFCFC color Bg code, but we have #FFFFFF in UI now 9. Your organization text should be #04041C Bg code, but we have #0525C65 now 10.There are difference in Mobile view portrait height for organization area | R2: Arivu | S2: Nil | T2: https://dev.azure.com/greatergiving/Greater%20Giving/_git/Donor/pullrequest/8758 | U2: 45894 | V2: 45896 | W2: Prabhu | X2: Nil | Y2: Joe | Z2: 45896 | AA2: Nil | AB2: Nil | AC2: Nil | AD2: 8/18/2025 -Created components and design the organization page 8/19/2025 -Created Web API and Angular service and blinded with UI 8/20/2025 - Design issue has been fixed 8/21/2025 -Testing issues has been fixed 8/22/2025 -Testing issues has been fixed 8/25/2025 -Merged Don-60 with Don-61 8/26/2025 -Develop branch merged with Don-61
A3: 2 | B3: Donor Wave | C3: 45883 | D3: 45897 | E3: OB-OP 8.2 Sprint 1 | F3: Arivu / Saranya | G3: DON-51 | H3: Donor Platform - Events MVP | I3: Peer Review | J3: 8 | L3: 149.67 | M3: 45883 | N3: 45896 | O3: Nil | P3: Murugesan M | Q3: 1.Year should be displayed fully , no hard code over there 2.Icon od event button should be displayed as it is in Figma 3.Event website and donate now button shows blank page in new tab. we can make it as no action there , since the functionality is not available now 4.Event website button icon should be displayed as it is in Figma 5.Irrelevant pop up is displayed while clicking on share button. We can make it as no action there , since the functionality is not yet confirmed 6. There are difference in Event area's width and hight pixels when comparing to Figma especially in Landscape mode for Mobile and Tablet view. 7. City should be displayed below to Event date and year , but currently it displays next to date and year in Mobile - Portrait view. 8.There are slight difference in Event and Organization text's width and hight pixels when comparing to Figma especially in Landscape mode for Mobile and Tablet view 9.When clicking on share button , Share to copied pop up is displaying right top side for desktop and tablet mode 10.When clicking on share button , Share to copied pop up is displaying right top side for Mobile mode | R3: irsath | S3: Nil | T3: https://dev.azure.com/greatergiving/Greater%20Giving/_git/Donor/pullrequest/8765 | U3: 45897 | W3: Prabhu | X3: Nil | AD3: 8/18/2025 - Analysis and implement design part 8/19/2025 - Desing and API implementation 8/20/2025 -Design completed and checking responsive UI 8/21/2025-Design part implementation also reponsive UI integration 8/21/2025-Design issue fixing. 8/22/2025-Reported issue fixing 8/25/2025-DON-51-code Intergration with DON-60 8/26/2025-DON -51 latest chages working from figma design 8/28/2025-[DON-51]- Code conflict and design changes working.
A4: 3 | B4: Donor Wave | C4: 45883 | D4: 45897 | E4: OB-OP 8.2 Sprint 1 | F4: Irsath/Prabu | G4: DON-45 | H4: Donor Platform - Handle Token from B2C | I4: Being Developed | J4: 3 | L4: 29.25 | M4: 45897 | N4: 45897 | O4: Nil | P4: Nil | Q4: Nil | R4: Nil | S4: Nil | T4: https://dev.azure.com/greatergiving/Greater%20Giving/_git/Donor/pullrequest/8652 | U4: 45882 | V4: 45882 | W4: Prabhu | X4: Nil | Y4: Joe | Z4: 45897 | AA4: Nil | AB4: Nil | AC4: Nil | AD4: 8/28/2025 - Applied Review comments code and changes

Sheet OB-OP 8.2 Sprint-1-Defect
A1: S.No | B1: Sprint | C1: Story/Defect ID | D1: Parent Story | E1: Developer | F1: Issue Type | G1: Issue Description | H1: Priority | I1: Defect Source | J1: Type | K1: Status | L1: Root Cause Category | M1: Comments | N1: Found By | O1: RCA Comment

Sheet OB-OP 8.1 Sprint 4-Status
A1: S.No | B1: Application Name | C1: Sprint Start Date | D1: Sprint End Date | E1: Sprint | F1: Developer | G1: Story ID/Defect ID | H1: Description | I1: Status | J1: Estimated(hrs/sp) | K1: Actual(hrs/sp) | L1: Actual Hours Worklog | M1: Dev Start Date | N1: Dev End Date | O1: Unit testing | P1: Peer Tested By | Q1: Peer Tested Defects, if any | R1: Peer Reviewed By | S1: Peer Code Review Comments, if any | T1: PR Number/Link | U1: PR Created Date | V1: PR Approved Date | W1: Onsite Lead Code Review | X1: Code Review Comments, if any | Y1: Client Code Review | Z1: Approved Date | AA1: Code Review Comments, if any2 | AB1: Internal PO -POV Comments | AC1: Client PO -POV Comments | AD1: Comments
A2: 1 | B2: Donor Wave | C2: 45869 | D2: 45883 | E2: OB-OP 8.1 Sprint 4 | F2: Irsath | G2: DON-45 | H2: Donor Platform - Handle Token from B2C | I2: Peer Review | J2: 5 | L2: 111.75 | M2: 45869 | N2: 45882 | O2: Done | P2: Murugesan M | Q2: Nil | R2: Niranjan /Arivu | S2: Nil | T2: https://dev.azure.com/greatergiving/Greater%20Giving/_git/Donor/pullrequest/8652 | U2: 45882 | V2: 45882 | W2: Prabhu | X2: Nil | Y2: Joe | Z2: 45882 | AA2: Nil | AB2: Nil | AC2: Nil | AD2: 8/1/2025 -MSAL integration with angular 8/4/2025 - MSAL integation with angular -30% completed 8/5/2025 - MSAL integation with angular -60% completed 8/6/2025 - MSAL integation with angular -70% completed 8/7/2025 - MSAL integation with angular -75% completed 8/8/2025 - MSAL integation with angular -80% completed 8/11/2025 - MSAL integation with angular -90% completed 8/12/2025 - MSAL integation with angular -95% completed 8/13/2025 - MSAL integation with angular -100% completed
A3: 2 | B3: Donor Wave | C3: 45869 | D3: 45883 | E3: OB-OP 8.1 Sprint 4 | F3: Arivu | G3: DON-48 | H3: Investigate GCP pipeline and Build | I3: Completed | J3: 2 | K3: 2 | L3: 58.75 | M3: 45870 | N3: 45877 | O3: Done | P3: Murugesan M | Q3: Nill | R3: Niranjan | S3: Nil | T3: https://docs.google.com/document/d/1emYAKq7LFpFkX2vNgUscjEsB2ZTcFKVFAx1a2NOpF0E/edit?tab=t.0 | U3: 45876 | V3: 45881 | W3: Prabhu | X3: Nil | Y3: Joe | Z3: 45881 | AA3: Nil | AB3: Nil | AC3: Nil | AD3: 8/1/2025-Preparing the document for Build pipline 8/4/2025-Preparing the document for Build pipline 8/5/2025-document pipline creating and YAMAL Creating 8/6/2025-analysis some build and pipeline creating 8/7/2025- completed document prepation and moved to review 8/8/2025-create sample build and pipline creating 11/8/2025-check pipeline build and deployment
A4: 3 | B4: Donor Wave | C4: 45869 | D4: 45883 | E4: OB-OP 8.1 Sprint 4 | F4: Niranjan | G4: DON-57 | H4: Connect google api to address search | I4: Completed | J4: 3 | K4: 3 | L4: 78.25 | M4: 45870 | N4: 45881 | O4: Done | P4: Murugesan M | Q4: 1.Some google API warning message is displayed in console page | R4: Arivu | S4: Nil | T4: https://dev.azure.com/greatergiving/Greater%20Giving/_git/Donor/pullrequest/8730 | U4: 45881 | V4: 45882 | W4: Prabu | X4: Nil | Y4: Joe | Z4: 45882 | AA4: Nil | AB4: Nil | AC4: Nil | AD4: \
A5: 4 | B5: Donor Wave | C5: 45869 | D5: 45883 | E5: OB-OP 8.1 Sprint 4 - [Stretch] | F5: Niranjan | G5: DON-58 | H5: Name field does not accept Space in the input field | I5: Completed | J5: 2 | L5: 35.75 | M5: 45873 | N5: 45874 | O5: Done | P5: Murugesan M | Q5: Nil | R5: Arivu | S5: Nil | T5: https://dev.azure.com/greatergiving/Greater%20Giving/_git/Donor/pullrequest/8707 | U5: 45874 | V5: 45877 | W5: Prabu | X5: Nil | Y5: Joe | Z5: 45877 | AA5: Nil | AB5: Nil | AC5: Nil | AD5: 8/4/2025 3:27 PM - To working on Issue fixing. 8/4/2025- Retested the fix , working as expected 8/5/2025 12:06 PM- I’ve resolved the DON-58 issue and it has been moved to testing. I have changes done the following components: - SignupComponent - PaymentComponent - FamilyMemberComponent I have created the Draft PR . 8/7/2025 2:06 PM - To start working on name field validations 8/8/2025 11:40 AM - DON-58 – NameFieldSpaceValidation. I have committed the changes. As per the DON-39 Acceptance Criteria attached Image reference. We have additionally added the Spaces and Accented characters. These two paterns need to include or update into Acceptance Criteria or Jira. - DON-58 - PR has approved by Prabhu and Mccarty, Joseph

Sheet OB-OP 8.1 Sprint-4-Defect
A1: S.No | B1: Sprint | C1: Story/Defect ID | D1: Parent Story | E1: Developer | F1: Issue Type | G1: Issue Description | H1: Priority | I1: Defect Source | J1: Type | K1: Status | L1: Root Cause Category | M1: Comments | N1: Found By | O1: RCA Comment
B2: OB-OP 8.1 sprint 4 | C2: DON-58 | D2: DON-39 | E2: Niranjan | F2: Defect | G2: Name field does not accept Space in the name input field on Card | H2: Medium | I2: Manual | J2: Internal | K2: Closed | L2: Missed the logic | N2: Murugesan M

Sheet OB-OP 8.1 Sprint 3-Status
A1: S.No | B1: Application Name | C1: Sprint Start Date | D1: Sprint End Date | E1: Sprint | F1: Developer | G1: Story ID/Defect ID | H1: Description | I1: Status | J1: Estimated(hrs/sp) | K1: Actual(hrs/sp) | L1: Actual Hours Worklog | M1: Dev Start Date | N1: Dev End Date | O1: Unit testing | P1: Peer Tested By | Q1: Peer Tested Defects, if any | R1: Peer Reviewed By | S1: Peer Code Review Comments, if any | T1: PR Number/Link | U1: PR Created Date | V1: PR Approved Date | W1: Onsite Lead Code Review | X1: Code Review Comments, if any | Y1: Client Code Review | Z1: Approved Date | AA1: Code Review Comments, if any2 | AB1: Internal PO -POV Comments | AC1: Client PO -POV Comments | AD1: Comments
