Workbook

Sheet Dashboard
A1: Current Sprint | B1: {=INDEX($B$2:$B$101,MATCH(1,(($D$2:$D$101 >=TODAY())*($C$2:$C$101<=TODAY())),0))} -> 26.06 Sprint 2 | C1: Current Sprint Sheet | D1: =CONCATENATE(B1,"-Status") -> 26.06 Sprint 2-Status | E1: Sprint Start Date | F1: =VLOOKUP($B$1,$B$3:$C$101,2,FALSE) -> 46148 | G1: Sprint End Date | H1: =VLOOKUP($B$1,$B$3:$D$101,3,FALSE) -> 46161 | I1: Application Name | J1: MSB Accounting | K1: Users | L1: karthikeyan.ganesan@relevantz.com;abdulqadir.varawala@relevantz.com;pramod.korikkar@relevantz.com;rijo.ponthekkan@relevantz.com;sowjanya.krishnamoorthy@relevantz.com | M1: Teams Name(GP-MSB.Accounting) | N1: 19:8a9b6ea893c94a118cce0008488fa0fd@thread.v2
A2: Current Sprint | B2: Sprint # | C2: Sprint Start Date | D2: Sprint End Date | E2: Assigned | F2: Completed | G2: Story points introduced/removed | H2: Sprint Summary | I2: Accomplishments | J2: Remarks | K2: Retro Points (Internal & External) | L2: Planned Leaves | M2: Total Leaves | N2: Data sanity Audit Status | O2: AuditDate | P2: Backlog Health
A3: =IF(AND($D$1>=C3,$D$1<=D3),"CurrentSprint","NA") -> NA | B3: 13.5 Sprint 2 | C3: 45294 | D3: 45307 | E3: 22 | F3: 19 | G3: 0 | J3: Risks / Challenges 3 Escalations introduced. | K3: Internal: External:
A4: =IF(AND($D$1>=C4,$D$1<=D4),"CurrentSprint","NA") -> NA | B4: 13.5 Sprint 3 | C4: 45308 | D4: 45321 | E4: 21.5 | F4: 18.5 | G4: 3 - OnHold | J4: Escalations - 5 (29.75hrs) Defect 22651 (Misc Bank Charge Debit…) - Needed further PO research Regression Sprint. | K4: Internal: External:
A5: =IF(AND($D$1>=C5,$D$1<=D5),"CurrentSprint","NA") -> NA | B5: 13.6 Sprint 1 | C5: 45322 | D5: 45335 | E5: 22 | F5: 17 | G5: 0 | J5: 34016 - Bounceback reported , Last day of sprint was when BB identified. QA identified, this was not introduced new , but an existing prod defect still a blocker for the story completion.Retro Comments : | K5: Internal: External:
A6: =IF(AND($D$1>=C6,$D$1<=D6),"CurrentSprint","NA") -> NA | B6: 13.6 Sprint 2 | C6: 45336 | D6: 45349 | E6: 31 | F6: 19 | G6: 8 - On hold 6 - Testing 2- Introduced and completed. | J6: 5 Stories assigned during Start of the sprint. Risks / Challenges - 2 Escalations introduced and closed. Found additional issues with the Year End Process affecting 2 defects. Defects put on hold until analysis is completed. | K6: Internal: External:
A7: =IF(AND($D$1>=C7,$D$1<=D7),"CurrentSprint","NA") -> NA | B7: 13.6. Sprint 3 | C7: 45350 | D7: 45363 | E7: 27 | F7: 27 | G7: 0 | J7: Risks and Challenges: 4 escalations, 2 Defects found during regression. Completed all items assigned including the defects found from regression. | K7: Internal: External:
A8: =IF(AND($D$1>=C8,$D$1<=D8),"CurrentSprint","NA") -> NA | B8: 13.7. Sprint 1 | C8: 45364 | D8: 45377 | E8: 33 | F8: 31 | G8: 0 | J8: Risks and Challenges: 4 Escalations - 3 Bluebear, 1 Accounting. Lost DB access for 2 days - Affected closing stories earlier. Dev Testing Setup - Linking new schools with MSB. | K8: Internal: External:
A9: =IF(AND($D$1>=C9,$D$1<=D9),"CurrentSprint","NA") -> NA | B9: 13.7. Sprint 2 | C9: 45378 | D9: 45391 | E9: 30 | F9: 20 | G9: 0 | J9: 3 Stories got carried. (1 - Deployment delay from Client side, 2 - Development Inprogress) Client side Developer left in the beginning of the sprint. | K9: Internal: External:
A10: =IF(AND($D$1>=C10,$D$1<=D10),"CurrentSprint","NA") -> NA | B10: 13.7 Sprint 3 | C10: 45392 | D10: 45405 | E10: 19 | F10: 19 | G10: 0 | J10: Carried Stories completed. 4 sp were being worked by Michael, blocked because of need to coordinate more with platOps. Capturing only Relevantz SP's from this sprint onwards. | K10: Internal: External:
A11: =IF(AND($D$1>=C11,$D$1<=D11),"CurrentSprint","NA") -> NA | B11: 13.8. Sprint 1 | C11: 45406 | D11: 45419 | E11: 16 | F11: 11 | G11: 5sp-Testing , 5sp- In Development 3- Escalations Closed. 2 - Escalations in Progress 1- Defect Fixed. 1- Defect Identified for backlog. | J11: Found Defects during Smoke Testing 5 Escalations related to Accounting. Deployed Application to Production with ABP Upgrades (3.0 to 9.0) | K11: Internal: External:
A12: =IF(AND($D$1>=C12,$D$1<=D12),"CurrentSprint","NA") -> NA | B12: 13.8. Sprint 2 | C12: 45420 | D12: 45433 | E12: 20 | F12: 17 | G12: 3 new stories introduced and completed. | J12: 3 Sp in dev. | K12: Internal: External:
A13: =IF(AND($D$1>=C13,$D$1<=D13),"CurrentSprint","NA") -> NA | B13: 13.8. Sprint 3 | C13: 45434 | D13: 45447 | E13: 21 | F13: 17 | J13: 4 sp missed because of a story in testing was dependant on stretch item to be completed. | K13: Internal: External:
A14: =IF(AND($D$1>=C14,$D$1<=D14),"CurrentSprint","NA") -> NA | B14: 13.8. Sprint 4 | C14: 45448 | D14: 45461 | E14: 19 | F14: 12 | J14: 5sp was in progress. 3 sp dependant on the 5 sp story. Reforecast was sent out mid sprint changing priorities from a Regression to a development sprint. | K14: Internal: External:
A15: =IF(AND($D$1>=C15,$D$1<=D15),"CurrentSprint","NA") -> NA | B15: 13.8. Sprint 5 | C15: 45462 | D15: 45475 | E15: 16 | F15: 3 | J15: 13 sp Story got carried - Identified more difference in source data during Data fix. | K15: Internal: External:
A16: =IF(AND($D$1>=C16,$D$1<=D16),"CurrentSprint","NA") -> NA | B16: 13.8. Sprint 6 | C16: 45476 | D16: 45489 | E16: 18 | F16: 13 | J16: Major focus on the update Scripts for the Beginning Balance. 5 sp wasnt worked on at all as we had depdendencies on other stories 2 sp is a defect which is also a dependency. 10 sp was marked completed and pivoted into a new story. | K16: Internal: External:
A17: =IF(AND($D$1>=C17,$D$1<=D17),"CurrentSprint","NA") -> NA | B17: 13.8 Sprint 7 | C17: 45490 | D17: 45503 | E17: 32 | F17: 3 | K17: Internal: External:
A18: =IF(AND($D$1>=C18,$D$1<=D18),"CurrentSprint","NA") -> NA | B18: 13.8 Sprint 8 | C18: 45504 | D18: 45517 | E18: 17 | F18: 17 | K18: Internal: External:
A19: =IF(AND($D$1>=C19,$D$1<=D19),"CurrentSprint","NA") -> NA | B19: 14.1 Sprint 1 | C19: 45518 | D19: 45531 | E19: 10 | F19: 10 | J19: Started Working on Stretch items as part of the sprint. Pulled in a epic. | K19: Internal: External:
A20: =IF(AND($D$1>=C20,$D$1<=D20),"CurrentSprint","NA") -> NA | B20: 14.1 Sprint 2 | C20: 45532 | D20: 45545 | E20: 23 | F20: 10 | J20: Missed 13 sp because we couldnt completed regression in time because we had blocking items to complete | K20: Internal: External:
A21: =IF(AND($D$1>=C21,$D$1<=D21),"CurrentSprint","NA") -> NA | B21: 14.1 Sprint 3 | C21: 45546 | D21: 45559 | E21: 24 | F21: 21 | J21: 3 SP was in POV, dev completed but can't test now since we have a dependancy on other item. 26-Sep-24: CRC Peer - 0, Onsite - 0, Client - 0. Internal Defect - 3, External Defect - 0. | K21: Internal: External: | N21: Completed
A22: =IF(AND($D$1>=C22,$D$1<=D22),"CurrentSprint","NA") -> NA | B22: 14.2 Sprint 1 | C22: 45560 | D22: 45573 | E22: 15 | F22: 10 | G22: Introduced - 8 sp | K22: Internal: External:
A23: =IF(AND($D$1>=C23,$D$1<=D23),"CurrentSprint","NA") -> NA | B23: 14.2 Sprint 2 | C23: 45574 | D23: 45587 | E23: 28 | F23: 20 | J23: 8 sp - Detailed Accounting Analysis required | K23: Internal: External:
A24: =IF(AND($D$1>=C24,$D$1<=D24),"CurrentSprint","NA") -> NA | B24: 14.2 Sprint 3 | C24: 45588 | D24: 45601 | E24: 24 | F24: 13 | J24: 5sp - Accounting Data investigation. 8sp - Changes to the story late in the sprint. | K24: Internal: External:
A25: =IF(AND($D$1>=C25,$D$1<=D25),"CurrentSprint","NA") -> NA | B25: 14.3 Sprint 1 | C25: 45602 | D25: 45615 | E25: 14 | F25: 14 | I25: Completed new implementation approach for MSB batch import changes, added UI for associating schools to MSB Gateways, added automation tests | J25: 8 sp worked on by OnSite Dev (which is in Testing) CRC Peer - 0, Onsite - 0, Client - 0. Internal Defect - 1, External Defect - 4. | K25: Internal: Great job done by Rijo and Karthik in getting the MSB batch Import new design changes External: Appreciation recieved from Michael Rose for Sushmitha on her automation activities, from Sarah to Qadir for closing escalation with fix, from Michael Rose to Rijo and Karthik for MSB Batch Import new changes
A26: =IF(AND($D$1>=C26,$D$1<=D26),"CurrentSprint","NA") -> NA | B26: 14.3 Sprint 2 | C26: 45616 | D26: 45629 | E26: 16 | F26: 11 | I26: Import from MSB defects fixes​ Macroscope remediation​ Import from MSB redesign data scripts and UI story​ Identified the Root cause of missing installment payments In import From MSB | J26: 5 sp missed because the fix for the escalation defect is dependant on changes made in 46200 whcih is a stretch item still in progress. CRC Peer - , Onsite - , Client - . Internal Defect - , External Defect - . | K26: Internal: External:
A27: =IF(AND($D$1>=C27,$D$1<=D27),"CurrentSprint","NA") -> NA | B27: 14.3 Sprint 3 | C27: 45630 | D27: 45643 | E27: 17 | F27: 9 (Completed -17.7) | G27: Introduced Stretch - 8.7 (Completed) | I27: Macroscope remediation​ Import from MSB redesign completed, BrowserStack Integration for automated Tests Issues with Installment Payments / Refunds fixed. | J27: Commit Story - 8 is in progress 8 sp in Client POV before we create the PR, and Test. We found some additional work to be done for this story to manage existing data, so when we deploy , this scenario works seamlessly. CRC Peer - 0 , Onsite - 0, Client - 0 . Internal Defect - 1, External Defect - 1. | K27: Internal:Sushmita - Testing and Working On Automation Test Cases - Qadir External: 1) Sushmitha doing so well with both manual & Automation testing efforts - Michael Rose 2) Pramod - thanks for always being willing to roll with new processes and for all the great discussions on our upcoming work! - Sarah
A28: =IF(AND($D$1>=C28,$D$1<=D28),"CurrentSprint","NA") -> NA | B28: 14.4 Sprint 1 | C28: 45644 | D28: 45671 | E28: 22 | F28: 24 | I28: Shared gateway functional changes on Import from MSB. - This brings the end to the changes to ImportFromMSB. Import MSB batches - Background query changes to create batches from existing data 14.3 Regression Completed | J28: 2 sp story has been rolled over to the new sprint as a 8 sp story. We're still unsure of the reason the send email job isnt running. We've allocated more time to investigate the issue. Along the way we've found more issues on Production, which were Important to investigate to determine whether we need immediate fixes or not. CRC Peer - 0 , Onsite - 1, Client - 0. Internal Defect - 2, External Defect - 1 . What Went Well 1) Regression went relatively smoothly, with only 1 main issue. 2) We've got Import Batches now ! No more ImportFromMSB What didnt Go Well 1) Found issues in prod while researching Email Error Logs 2) Test MSB was down during holidays. 3) Possible configuration issue with gateway / not getting batch IDs. | K28: Internal : Rijo / Karthik - Great Coordination in handling the Import MSB batches. Pramod - Reminding team of using new MIDs during Regression. Sushmitha - identifying the edge cases External : Team - keeping focused on sprint goals - Michael Qadir - for taking a majority of the escalation work - Michael Qadir -Good job incorporating the new review points in the demo - Sarah
A29: =IF(AND($D$1>=C29,$D$1<=D29),"CurrentSprint","NA") -> NA | B29: 14.4 Sprint 2 | C29: 45672 | D29: 45685 | E29: 19 | F29: 23 | G29: 3 sp introduced. | I29: PROD deployment Completed. Team was quick to pivot to work on the story to hide batches as it could affect users in PROD. | J29: 3 sp from the Alpine DatePicker has been rolled over to the new sprint. We started it late in the sprint, and it was more complicated than we anticipated. We had to bring in a new story about hiding the batches once Journalled, because as part of the data fix, we had hidden them. Newly journalled batches were still being displayed. We needed to fix the inconsistency. CRC Peer - 0 , Onsite - 1, Client - 0. Internal Defect - 2, External Defect - 0 What Went Well 1) PROD deployment went well. 2) UI for the Job Queue - Will be helpful for the future. 3) Closed all items except Alpine component, completed 19 out of 19 SP including the 3 SP added later to sprint 4)Got client appreciation for Sushmitha for making progress with Automation test suite What didnt Go Well 1) Alpine Js datepicker story couldnt be completed as it was more complex than we anticipated.-3sp 2) Escalation fix got sidetracked. Defect create on it now. | K29: Internal : Sushmitha continuing the progress on the Automation
A30: =IF(AND($D$1>=C30,$D$1<=D30),"CurrentSprint","NA") -> NA | B30: 14.4 Sprint 3 | C30: 45686 | D30: 45699 | E30: 17 | F30: 22 | G30: 3 sp introduced. | I30: Regression was completed. Completed 1 story from the stretch and another from the stretch ready for POV. | J30: Missed 3 sp for the Alpine TextBoxes, Links because we had to focus on the edge case regression defects that were found with Importing batches. We completed 3 sp from the stretch as well, bringing in a new feature for Bank Deposit Summary Type setting in the School Settings . This was a story requested by Accounting Customers. CRC Peer - 0 , Onsite - 0, Client - 0. Internal Defect - 2, External Defect - 0 What Went Well 1) Regression was completed. 2) We added an additional story to the release - 23903, which was not planned. 3) Figured out the cause of the Jobs not running as per schedule in Cert and prod. 4) Karthik and Pramod got client appreciation for completing some stretch items and taking care of standups in the absense of scrum master and PO respectively. What didnt Go Well 1) Couldnt Close out Alpine Story. We were very close. 2) CERT deployment was delayed, and we missed completing one regression defect. | K30: Internal : Same as External External : Pramod for standing in For Sarah and RJ - RJ Karthik for closing out an item from stretch - James Qadir - For figuring out the issue with the job Queue.
A31: =IF(AND($D$1>=C31,$D$1<=D31),"CurrentSprint","NA") -> NA | B31: 14.5 Sprint 1 | C31: 45700 | D31: 45713 | E31: 17 | F31: 37 | I31: Deployment Completed to PROD. We pulled in 2 stories as escalations to be released as it was urgent | J31: CRC Peer - 0 , Onsite - 0, Client - 2. Bounceback -1 Internal Defect - 1, External Defect - 2 What Went Well Overall, a very good sprint. What didnt Go Well Highlighted an observeation with the client that server patch upgrade was also done during deployment causing server downtime while post deployment verification | K31: Internal : Same as External External : Team was hihgly appreciated for achieving more than the sprint commit
A32: =IF(AND($D$1>=C32,$D$1<=D32),"CurrentSprint","NA") -> NA | B32: 14.5 Sprint 2 | C32: 45714 | D32: 45727 | E32: 23 | F32: 32.5 | G32: Sprint Reforecast done - Pulled in additional 5 sp for relevantz. Pulled out 3 sp because it was blocked. Completed additional 3 Stories - 10 sp from stretch | J32: CRC Peer - 0 , Onsite - 0, Client - 1. Bounceback -0 Internal Defect - 0, External Defect - 4 What Went Well 1. Completed almost the committed SP by picking up items from stretch 2. Rijo and Karthik got client (Sarah and Qadir) appreciation for great demo and completing lots of work even with time off respectively. What didnt Go Well 2 Stories were blocked due to scrubbed prod db restoration issue on Dev server. Missed 8 SP there. | K32: Internal : Same as External External : Rijo - For explaining the context of the 3rd party fees mapping epic - great demo!
A33: =IF(AND($D$1>=C33,$D$1<=D33),"CurrentSprint","NA") -> NA | B33: 14.5 Sprint 3 | C33: 45728 | D33: 45741 | E33: 27 | F33: 34.5 | G33: We pulled in 5sp as defects we found during the sprint which should be a part of the release. | I33: Per Item Fees are now captured by MSB and now Accounting and we can see the proper total fo Tickets Products in MSB Accounting. Completed verifications for 2 districts for year end changes . | J33: CRC Peer - 1, Onsite - 0, Client - 0. Bounceback -0 Internal Defect - 1, External Defect - 3 What Went Well 1. Per item fees changes look good. 2. Nice Error Page What didnt Go Well 1 We need to break regression into smaller chunks 2 Jobs were not running on last day of sprint | K33: Internal : Same as External External : Appreciation to Sushmitha - from Wes Perkins (Client QA) for covering the QA activities while he was unable to help on testing due to issues with his laptop to the entire team - from accounting customers for good feature updates - from the MSB Accounting customer feedbacks as captured by Sarah and RJ from their "Connect Conference" with the customers to Pramod - from Michael Rose, Sarah and RJ for covering the activities for Sarah and RJ while they were absent for the team
A34: =IF(AND($D$1>=C34,$D$1<=D34),"CurrentSprint","NA") -> NA | B34: 14.6 Sprint 1 | C34: 45742 | D34: 45755 | E34: 22 | F34: 17.3 | G34: 2.25 (Defect 24968 ) | I34: Deployment Completed to PROD. 14.5 Release | J34: CRC Peer - 0, Onsite - 0, Client - 0. Bounceback -0 Internal Defect - 2, External Defect - 2 What Went Well 1) Deployment went Well 2) Identifying the underlying cases for the bank rec notification message. What didnt Go Well 1 We should have reforecast the story Rijo Was working after finding issues that we had not considered. (47244,47262,47263) | K34: Internal : Same as External External : Appreciation to Rijo - from James Varney (Client Dev) and Michael Rose for successfully leading the deployment in Qadir's absence Sushmitha and Karthik - from James Varney and Sarah for good Demo during Sprint review Karthik - from Sarah for identifying all underlying cases of bank rec completion notifications and not ending up just with a fix for the surface level defect that was reported
A35: =IF(AND($D$1>=C35,$D$1<=D35),"CurrentSprint","NA") -> NA | B35: 14.6 Sprint 2 | C35: 45756 | D35: 45769 | E35: 19 | F35: 19 | G35: None | I35: Completed the epic related to third party GL s from Msb and its mapping to Accounting, which is the major item for this release cycle. Getting started on the entire page migrations to Alpine js by the relevantz team. | J35: CRC Peer - 0, Onsite - 1, Client - 0. Bounceback -3 (2 from Client Dev) Internal Defect - 1, External Defect - 0 What Went Well 1. Completed the Epic story - 3rd party fee integration support 2. Completed all commited items. What didnt Go Well: Nil | K35: Internal : Appreciation to Sushmitha - For catching few edge cases in her QA activities Karthik - For quickly understanding the additional observation around AC points with me while my POVs and working on it Rijo - For his continuous focus and getting the first set of mapping stories done in this sprint Qadir - For syncing up with Sarah and closing the discussions for Dev team (All by Pramod) External : Sushmitha for covering all items in the absence of client QA by - Wes(Client QA) and the entire team Rijo for great demo with explanations for the Epic story - By entire team
A36: =IF(AND($D$1>=C36,$D$1<=D36),"CurrentSprint","NA") -> NA | B36: 14.6 Sprint 3 | C36: 45770 | D36: 45783 | E36: 21 | F36: 23 | G36: 2(Story 47936 re-estimated from 3 to 5 SP) | I36: Completed the fix for the GUIDs for the 3rd party fees. Regression Completed successfully. | J36: CRC Peer - 0, Onsite - 0, Client - 0. Bounceback -2 Internal Defect - 0, External Defect - 0 What Went Well 1. Completed Regression on time. 2. Completed all commited items. 3. Reforecasting our stories. What didnt Go Well: Nil | K36: Internal : Sushmitha - For her work on testing and automated Tests - Qadir/ Pramod External : Qadir - Good Review Demo - Wes / James Sushmitha - For her work on Automation - Owen Sieber Sushmitha - For testing scenarios where we found a big issue with the payment confirmation logic. - Michael Rose/ Sarah Rijo - Good Work on the GUID to String Changes and 3rd party Fees - James
A37: =IF(AND($D$1>=C37,$D$1<=D37),"CurrentSprint","NA") -> NA | B37: 14.7 Sprint 1 | C37: 45784 | D37: 45797 | E37: 22 | F37: 22 | G37: None | I37: Successful Production Deployment. Hitting our sprint targets despite some disruption with the new Synergy integration conflict and escalations | J37: CRC Peer - 0, Onsite - 0, Client - 0. Bounceback -1 Internal Defect - 2, External Defect - 1 | K37: Internal : External : Sushmitha - for catching sneaky issues in the overdraw warning - James/ Sarah / Qadir Rijo and Sushmitha -coordinating the issues on the Shared batches on Import Batches Feature - Wes /Qadir (Client QA)
A38: =IF(AND($D$1>=C38,$D$1<=D38),"CurrentSprint","NA") -> NA | B38: 14.7 Sprint 2 | C38: 45798 | D38: 45811 | E38: 24 | F38: 18 | G38: 2 (In stretch) | I38: Resolved all 3 escalations. Completed the automation test story. Completed 18 of 24 SP in spite of the issue with Dev database slowness which affected testing from this sprint. | J38: CRC Peer - 0, Onsite - 2, Client - 0. Bounceback -1 Internal Defect - 2, External Defect - 3 What went well: Completed 18 of 24 SP in spite of the issue with Dev database slowness which affected testing from this sprint. What didnt Go Well: 1) 3 Escalations 2) DEV Database slowness affected testing.on our stories. | K38: Internal : Qadir, Rijo and Karthik were focussed on getting the items completed, good progress by Sushmitha on automation - Pramod External : Sushmitha & Rijo - Good demos - James Entire team - Escalation was resolved when I got back from PTO - Sarah Pramod - covered POVs to keep things moving - Sarah
A39: =IF(AND($D$1>=C39,$D$1<=D39),"CurrentSprint","NA") -> NA | B39: 14.7 Sprint 3 | C39: 45812 | D39: 45825 | E39: 21 | F39: 31 | G39: 10 (In stretch) | I39: Got Regression Completed. HotFix Deployment went well. Get to start sprint completely fresh. | J39: CRC Peer - 0, Onsite - 0, Client - 0. Bounceback -2 Internal Defect - 3, External Defect - 2 What went well: Successful hotfix deployment and completed regression with minimal findings. What didnt Go Well: Scrubbed PROD DB Backup took some time to setup locally due to space. | K39: Internal : External : Michael Rose - Well executed sprint. I love the flexible sprint commit.
A40: =IF(AND($D$1>=C40,$D$1<=D40),"CurrentSprint","NA") -> NA | B40: 15.0 Sprint 1 | C40: 45826 | D40: 45839 | E40: 16 | F40: 8 | G40: 3 SP missed because Owen was on vacation and couldnt review. 5 SP missed because we planned 2 stories with 5 sp each which eventually needed to be completed together to release. We could have planned this better. 2 SP from stretch was blocked because we need customer confirmation | I40: Completed Production Deployment. Good Progress on Alpine Reports using Co Pilot. | J40: CRC Peer - 0, Onsite - 0, Client - 1. Bounceback -0 Internal Defect - 0 External Defect - 0 What went well: Successful Production deployment Co-Pilot Work on Alpine Reports. Continuous Progress on Automation Test Cases. What didnt Go Well: DEV and QA Sites were down for half the sprint. Work on the batches - As always we keep finding these edge case scenarios. | K40: Internal : Qadir - Sushmitha's Continous work on Automation. Pramod - Thinking ‘outside the box’ on our work & discussing scenarios / AC Pramod - Communication in the team. External : Michael Rose - Team resilience, even with PO transition. Michael Rose - Good demo on the use of Copilot by Qadir for Alpine Reports. Wes Perkins - Qadir on defect I had to test, Sushmitha for picking up while I was on vacation
A41: =IF(AND($D$1>=C41,$D$1<=D41),"CurrentSprint","NA") -> NA | B41: 15.0 Sprint 2 | C41: 45840 | D41: 45853 | E41: 23.5 | F41: 15.5 | G41: 6 sp blocked because of issues on MSB Side with Portico. We couldnt test. 6 sp missed with the work on Alpinejs. Stretch completed 4 sp completed from stretch | I41: Beginning Balance changes - Completed 5 Districts this sprint () Automation Progress. | J41: Comments : CRC Peer - 2, Onsite - 0, Client - 1. Defects: Bounceback -0 Internal Defect - 1 External Defect - 0 What went well: MSB team responded quickly to the issue on the batchid’s Pramod PO stepping in Beginning balance story progress - Completed 5 stories. Automation progress What didnt Go Well: Overcommitted - Alpine Reports Blocker with batchids timeout issues on Portico side (issue on Portico side) | K41: Internal : Qadir/ Pramod : Karthik plowing through the Beginning Balance changes / data analysis and narrowing down potential trouble areas as pattern Qadir/ Pramod : Sushmitha towards her automation work Pramod : Rijo assist with Sushmitha on batches / troubleshooting Karthik : Pramod & Qadir on BatchID issue resolution / collaboration Karthik : Pramod beginning balance collab External : Wes (Client QA) : Karthikeyan - the POV video on story 47285 was a great help when it came to testing. James : Demos as usual went really well.
A42: =IF(AND($D$1>=C42,$D$1<=D42),"CurrentSprint","NA") -> NA | B42: 15.0 Sprint 3 | C42: 45854 | D42: 45867 | E42: 27 | F42: 29 | G42: 2 SPs from regression couldn't be completed because of delayed deployment to CERT. Completed 4 SPs from stretch. | I42: Completed 90% regression in a short duration Added functionality for the support team to lock beginning balances and Fix batches imported from MSB. | J42: Comments : CRC Peer - 1, Onsite - 0, Client - 1. Defects: Bounceback -3 Internal Defect - 2 External Defect - 0 What went well: Completed Regression in a short period of time. Closed 2 escalations. What didnt Go Well: CERT Deployment took a day longer than we were ready. Missed a day to test. | K42: Internal : Qadir - Entire Team - Great coordination on getting this far into the regression Qadir - Pramod - Taking on a lot more! Pramod - Rijo for the work on Lock/Unlock beg balance and Fix MSB Batches page Sushmitha - Kudos to Pramod for managing all the PO activities in Sarah's absence. Great job stepping Sushmitha - Appreciate Qadir's coordination with the Platform Ops teams to modify the database queries for testing the GETMSBBatches functionality. Karthik - Rijo gave a great demo . Karthik- Sushmitha - for her continuous high-quality testing effort. External : James Varney / RJ - Super Demo by Rijo James Varney - The team - The regression went really well with the short time period.
A43: =IF(AND($D$1>=C43,$D$1<=D43),"CurrentSprint","NA") -> NA | B43: 15.1 Sprint 1 | C43: 45868 | D43: 45881 | E43: 27 | F43: 26 | G43: (16 sp commit, 10 stretch) 8 SPs missed with the stories worked by client dev. 3 SPs missed because we got few escalations in the middle of sprint. So couldn't make progress on this. Completed 10 SPs from stretch. | I43: 15.0 Deployment went well. Completed new requirement that came as an escalation from customer. (Thatcher) | J43: Comments : CRC Peer - 0, Onsite - 0, Client - 0. Defects: Bounceback -1 Internal Defect - 0 External Defect - 3 What went well: Completed 15.0 deployment successfully. Closed 1 escalations. Completed new requirement that came as an escalation from customer. What didnt Go Well: Dev DB restore took extra time. Clarifications needed from customers on work. 4 Escalations. Issues with WAF. | K43: Internal : Sushmitha - Rijo on stepping in for Thatcher escalation understanding their needs Karthik - Rijo’s great work on Thatcher’s requirement from escalation. Qadir - Karthik quietly working on the beginning balance changes. Qadir - Pramod taking on the additional work after Sarah's departure. External : James Varney - Qadir demo’s
A44: =IF(AND($D$1>=C44,$D$1<=D44),"CurrentSprint","NA") -> NA | B44: 15.1 Sprint 2 | C44: 45882 | D44: 45895 | E44: 25 | F44: 14 | G44: Missed 11 sp due to time spent on escalations that came in during the sprint. | H44: We had a good sprint where we completed a Hotfix and resolved 1 escalation and found an additianal defect on another escalations. We had quite a few roadblocks this sprint, due to time spent in resolving escalations and going back forth with customers who dont respond timely. We also had infrastructure related issue where our DEV/QA Servers were down on both mondays after auto park didnt work. Apart from the auto park, the infrastructre team implemented a WAF on DEV/QA which blocked our reports, and hence our testing on a few stories. The WAF implementation is also an escalation since we saw a lot of Bad URL requests coming in through the logs. | I44: 15.0 Hotfix completed Made progress on most of the escalations. | J44: Comments : CRC Peer - 0, Onsite - 0, Client - 0. Defects: Bounceback -2 Internal Defect - 2 External Defect - 5 (including escalations) What went well: Very good progress on Escalations, and we are ready for hot fix deployment. Some good progress on Alpine Parmod 5 Stars for Planning and Review.. What didnt Go Well: WAF on DEV/QA blocked testing for a while We had DEV/QA servers unavailable on monday. 6 Escalations. | K44: Sushmitha Thirumurugan [C] - for coordinating with MSB Web team and using her own implementation to create over 200 transactions on test MSB. Pramod - for handling review and planning in the absence of RJ and Tino. Rijo - - Kudos to Rijo for identifying the root cause of the import issue and fixing it
A45: =IF(AND($D$1>=C45,$D$1<=D45),"CurrentSprint","NA") -> NA | B45: 15.1 Sprint 3 | C45: 45896 | D45: 45909 | E45: 28 | F45: 31 | G45: Completed 26 from main commit and 5 from stretch. Missed 2 SP from main commit since we were waiting for confirmation from the customer for a week. | H45: We had a good sprint. Completed a hotfix deployment and the escalation got resolved, both customer and support team was happy about it. Completed regression and haven't found much issues. Closed all 5 escalations that were open in the sprint. | I45: Successfull hotfix deployment. Completed target SPs amid 5 escalations that we worked in this sprint. Closed all 5 escalations from this sprint. | J45: Comments : CRC Peer - 0, Onsite - 0, Client - 0. Defects: Bounceback -0 Internal Defect - 2 External Defect - 4 (including escalations) What went well: Closed all 5 escalations. Successfull hotfix deployment, escalation got resolved and the prod district started getting transactions from MSB. Completed regression and haven't found much issues. What didnt Go Well: 5 Escalations(3 carried from last sprint) | K45: Internal: Qadir - To Rijo for Handling the Deployment after I had to drop off. Pramod - To Rijo for RCA and fix for getting the Thacher MSB Batches fetch working and handling the hotfix deployment Sushmitha - Kudos to Rijo and Pramod for handling the hotfix deployment! Sushmitha - Kudos to Pramod and Qadir for consistently following up on escalations and keeping the status updated in the comments Pramod - To Sushmitha for handling QA activities Pramod - To Karthik for getting the beginning balance fixies going External: James: Rijo\Pramod fielded questions like a boss from Nadia during sprint demo.
A46: =IF(AND($D$1>=C46,$D$1<=D46),"CurrentSprint","NA") -> NA | B46: 15.2 Sprint 1 | C46: 45910 | D46: 45923 | E46: 24 | F46: 14 | G46: Completed 11 SP from main commit and 3 from stretch. | H46: It was an average sprint, we couldn't meet the SP commited. The alpine stories took more time than expected, and also few AC points were added later to the story. We had some escalations and spent time looking for the rooot cause. On the positive note, we have closed all the escalations, had a successfull production deployment and made good progress with automation test suite. | I46: Closed all 4 escalations. Successfull 15.1 deployment. Made good progress with automation test suite. | J46: Comments : CRC Peer - 0, Onsite - 0, Client - 0. Defects: Bounceback -0 Internal Defect - 3 External Defect - 4 (including escalations) What went well: Closed all 4 escalations. Successfull 15.1 production deployment What didnt Go Well: Couldn't complete the commited SP s. | K46: Rijo - Taking over the close of deployment. Sushmitha - Making progress on the Automation Test Cases. Karthik - Good progress with the school Groups UI. Rijo - To Sushmitha for making good progress with automation stories. Pramod - To Qadir and Rijo for helping on the deployment, To Sushmitha for keeping the QA activities while focussing alongside with the automation test creation tasks Pramod - To Tino for being around and helping me around on the product discussions areas Rijo - Handling the demo and ensuring a smooth walkthrough Pramod - Juggling a lot of things right now. Kudos !
A47: =IF(AND($D$1>=C47,$D$1<=D47),"CurrentSprint","NA") -> NA | B47: 15.2 Sprint 2 | C47: 45924 | D47: 45937 | E47: 15 | F47: 15 | G47: Completed 10 from main commit and 5 from stretch. Missed 2 due to escalations and couldn't work on the item and 3 - waiting for confirmation from customer to proceed. | H47: It was a good sprint overall. We completed 15 SP s out of 15, but including 5 from stretch. Couldn't complete 2 items from commit. 1- Need confirmation from customer to execute, analysis and fix completed from our end. 2- Couldn't work much on this item since we were concentrating on escalations. On the positive note, we have completed the epic of school groups, made good progress with escalations and automation test suite. | I47: Met the SPs commited. Made good progress with escalations. Completed the epic story of school groups. | J47: Comments : CRC Peer - 0, Onsite - 0, Client - 0. Defects: Bounceback -0 Internal Defect - 2 External Defect - 4 (including escalations) What went well: Met the SPs commited. Made good progress with escalations. What didnt Go Well: Couldn't complete 2 stories from the main commit and could not close out any escalations. | K47: KUDOS… Karthik - Fantastic work/ progress on School groups. Pramod - to Karthik for getting the School Groups done, to Sushmitha for progress on automation, to James for taking care of Check Form changes Sushmitha - Kudos to Karthik for Completing the School Groups epic and to Rijo for quickly fixing the reported bouncebacks and ensuring they were immediately available for testing. Sushmitha - Kudos to Qadir for his consistent follow-ups on escalations Karthik - Kudos to Sushmitha for great progress on automation and good job in testing as well.
A48: =IF(AND($D$1>=C48,$D$1<=D48),"CurrentSprint","NA") -> NA | B48: 15.2 Sprint 3 | C48: 45938 | D48: 45951 | E48: 10 | F48: 7 | H48: This was initially forecast as a Regression sprint, however, due to escalations from the customer on a number of stories from the backlog, we had to work on those instead. The team completed all the work on escalaltion that caused a deviation in our planning, and also released a hotfix to an issue which arised from duplicate FeeIds for different products on the batches, as well as the ability to update the dates on reversal entries. | I48: Hotfix completed. 3 / 7 escalations closed in the sprint. | J48: Comments : CRC Peer - 0, Onsite - 0, Client - 0. Defects: 9 Bounceback -0 Internal Defect - 2 External Defect - 7 What went well: What didnt Go Well: | K48: Pramod - to Abdulqadir Varawala [C] for continuos followup and fix help on the escalations Pramod - to Karthikeyan Ganesan [C] for getting the Elk Grove 6 schools beg bal fixes done Pramod - to Rijo P R [C] for the analysis and fix on the GL Account mapping escalation Pramod - to Sushmitha Thirumurugan [C] for faster QA closures on beg balance fixes and other items Pramod - to Nadia Boudeffa for followups with customer getting us the customer feedback Pramod - to Jeanette Elliot for helping around while Nadia was busy Rijo - To Karthik for closing out beg bal stories quickly. Sushmitha - Abdulqadir Varawala [C] and Pramod Rai on continuous follow up and getting clarification from customer on escalations Sushmitha - Kudos to Karthikeyan Ganesan [C] for prioritizing and successfully completing the Elk Grove stories Sushmitha - Kudos to Wes Perkins for testing and completing the elk grove stories while i was in PTO Jeanette - to Qadir, Karthik, Rijo, Sushmitha, James, Wes, Pramod, RJ, Nadia for all the great rallying and pushing through with all the escalations that came our way
A49: =IF(AND($D$1>=C49,$D$1<=D49),"CurrentSprint","NA") -> NA | B49: 15.3 Sprint 1 | C49: 45952 | D49: 45965 | E49: 24 | F49: 24 | G49: Completed 22 SP from main commit and 2 SP from the stretch. 2 items of 1SP each missed from main commit.(Alpine SSO due to focus on other high priority issues at hand and Beginning bal defect verification due to prod db backup delay.) | H49: This was a Regression sprint. We got few other escalations as well during the sprint. We have completed the regression and closed 6 escalations. Made good progress on the stretch items as well. 2 items from stretch related to PY report feature flag is dev completed and ready for testing. | I49: Completed regression items. Closed 6/8 escalations in the sprint. Made good progress with stretch items. | J49: Comments : CRC Peer - 0, Onsite - 0, Client - 0. Defects: 10 Bounceback -0 Internal Defect - 2 External Defect - 8(including escalations) What went well: Completed regression items. Closed 6/8 escalations in the sprint. Made good progress with stretch items. Met the SPs commited. What didnt Go Well: Getting new escalations during sprint. WAF issues blocking testing. Performance issues found with large MSB batch imports. | K49: Rijo - To Karthik for making good progress on stretch items. To Pramod for making good progress with Negative Invoice,Checks Thatcher escalation. Qadir To Owen - Removing MSB recaptcha blocker to run Automation scripts on CERT for testing. Karthik - To Pramod and Qadir for their excellent coordination on the escalation fixes and clarifications. Sushmitha - To Owen Sieber for clearing out MSB recaptcha blocks Jeanette - Team, great job on completing regression and closing out most of our escalations. Pramod - to RJ for the new planning,review, retro call timings Pramod - to Nadia and Jeanette for shielding (me) from Thatcher to help me focus on my analysis for negative credit invoices Pramod - to Rijo and Karthik for greatly focussing on escalations and Sushmitha on QA items Pramod - to Qadir for clearing the WAF blockers Qadir - Team doing a great job !
A50: =IF(AND($D$1>=C50,$D$1<=D50),"CurrentSprint","NA") -> NA | B50: 15.3 Sprint 2 | C50: 45966 | D50: 45979 | E50: 23 | F50: 27 | G50: Completed 22 SP from main commit and 5 SP from stretch. Couldn't complete 1 story with 1 SP because SSO login blocked due to WAF issue on MSB. | H50: The main goal in the sprint was to improve the performance on import process with large batches, completed both stories related to it. Other major item was clearing PY transactions on entry screens with feature flag - completed all 3 stories related to that. And as usual closing the escalations was the first priority, closed most of it except the one that came on 2nd last day of sprint and 1 which is still waiting for the data from customer. Overall it was a very productive and successfull sprint. | I50: Completed more SP than committed in total. Made good progress on stretch items. Made code fix and the item is ready for testing for the major performance issue story, even though the scope was to identify a fix to make it faster. | J50: Comments : CRC Peer - 0, Onsite - 0, Client - 0. Defects: 10 Bounceback -0 Internal Defect - 4 External Defect - 6(including escalations) What went well: Completed more SP than committed in total. Closedmost of the escalations in the sprint. Made good progress with stretch items. Made good progress with performance issue story for large batch import. What didnt Go Well: Getting new escalations during sprint. WAF issues blocking SSO login in alpine. | K50: Qadir : Rijo and karthik steadily taking the team forward, since I was in and out this sprint. Qadir - Karthik for taking up some of the new escalations that came in. Sushmitha - Kudos to Rijo for his excellent work in fixing the performance issue with a huge set of batches Jeanette - Huge kudos to the team for figuring out a path forward to improve performance issues!
A51: =IF(AND($D$1>=C51,$D$1<=D51),"CurrentSprint","NA") -> NA | B51: 15.3 Sprint 3 | C51: 45980 | D51: 45993 | E51: 29.5 | F51: 19.5 | G51: 10 SP missed from the Main commit. 2 regression stories were blocked due to migration issue on Cert. 1 defect is waiting for customer feed back. 1 story is in testing, bounce back fixed, testing in progress. | H51: It was a regression sprint. We had few items to complete as pre requiste for starting regression. Started regression very late, but completed everything from regression except 2 items which got blocked due to a migration issue while deploying. This was an average sprint in terms of completion, but we have dev completed 1 item from stretch, will be moving to testing in the next sprint. | I51: Successful Production Deployment. Completed most of regression stories except 2 despite starting very late. Closed all escalations. Currently we got 0 active escalations. | J51: Comments : CRC Peer - 0, Onsite - 0, Client - 0. Defects: 5 Bounceback -0 Internal Defect - 1 External Defect - 4(including escalations) What went well: Successful Production Deployment. Completed most of regression stories except 2 despite starting very late. Closed all escalations. What didnt Go Well: Couldn't meet SP committed. WAF issues blocking SSO login in alpine. | K51: Internal: Rijo - To Sowjanya for handling the handoff from Sushmitha and getting through the first Regression. Qadir - to Rijo for continuing to focus on import & resolve issues Qadir - to Karthik on the progress on the smaller stories & getting those done Qadir - to Pramod for helping with our regression Qadir - to Sowjanya / welcome to team External: Jeanette (Client PM): Great job done by the team in closing all the escalations and getting most of the regression completed
A52: =IF(AND($D$1>=C52,$D$1<=D52),"CurrentSprint","NA") -> NA | B52: 20.1 Sprint 1 | C52: 45994 | D52: 46007 | E52: 26 | F52: 20 | G52: 10 SP missed from the Main commit. 4 SP completed from stretch. Missed 2 items of 5 SPs each. Both were in testing and testing was also close to completion. But unfortunately it took a while longer and couldn't close it in time. | H52: It was a good sprint overall, but SP completed don't show that unfortunately. Disappointed as we were on the last step of testing 2 items but couldn’t really cross the line. Everyone made all the effort but it was unfortunate. Otherwise we made good progress with all items, it was a very productive sprint. We have completed the beginning balance update for all district - has been going on for more than a year now. | I52: We made movement on Thatcher and hopefully will be able to close out during the next sprint. Good progress with performance issues and beg bal verification stories. Finally we have completed the beginning balance update for all district - has been going on for more than a year now. Wrapped up the Alpine SSO story. | J52: Comments : CRC Peer - 0, Onsite - 1, Client - 0. Defects: 6 Bounceback -0 Internal Defect - 3 External Defect - 3(including escalations) What went well: Made good progress with performance issues. Finally we have completed the beginning balance update for all district - has been going on for more than a year now. What didnt Go Well: Couldn't meet SP committed. Postponed production release | K52: Internal: Sowjanya-Karthik, Rijo, Qadir Thank you all for supporting me by clarifying my doubts at work. Qadir, Rijo, Pramod - Sowjanya ramped up well on the testing. External: Jeanette - Pramod, thank you for all your guidance and direction on the best ways we can design our updated version of Onboarding that will allow us to easily grow and evolve the process as our company and product evolves. Jeanette - Karthik and Rijo, I appreciate you being more vocal the past 2 weeks, your knowledge and understanding is valuable and I am thankful for your insights as well. Thank you so much for that both during refinement and planning. Jeanette - Qadir, thank you so much for jumping on last night and trying to help figure out a way to solve Thatcher asap even when it was so late. Jeanette - Sowjanya, catching issues in cert before release. Jeanette - Team thank you for rallying together today with RJ out. Wes - Ditto! Sowjanya ramped up well. Wes - Rijo for thorough POV videos which helped me in testing. Wes - Qadir for connecting with me on a zoom call and helping me with testing.
A53: =IF(AND($D$1>=C53,$D$1<=D53),"CurrentSprint","NA") -> NA | B53: 26.01 Sprint 2 | C53: 46008 | D53: 46035 | E53: 35 | F53: 25 | G53: 10 SP missed from the main commit. 1 story to deploy the alpine nine branch to QA took more time than we planned earlier. 2 alpine stories was delayed since Rijo was completely blocked from work for 3 days due to e-hps login blocker because of authenticator issue. | H53: It was a 4 weeks sprint. We could not complete the story points committed due to some blockers. And there were few escalations towards the end of the sprint, which took some considerable amount of time as well. But still we managed to complete the dev work for 2 out of 3 open items as well. Considering everything, it was a productive sprint. | I53: Successful Production Deployment. Good progress with escalations reported, closed 2 and 1 is in blocked state. | J53: Comments : CRC Peer - 0, Onsite - 0, Client - 0. Defects: 6 Bounceback -0 Internal Defect - 2 External Defect - 4(including escalations) What went well: Successful Production Deployment. Good progress with escalations reported, closed 2 and 1 is in blocked state. What didnt Go Well: Couldn't meet SP committed. Faced few blockers due to e-hps login issue and WAF issues which halted the progress. | K53: Qadir, Rijo - Big kudos to Karthik. He completed a big portion of the sprint. Sowjanya-Sincere Kudos to Qadir and Pramod for their assistance in resolving the MSB integration Issue. Any doubts or clarifications regarding the story were clarified by Karthik and Rijo,Sincere thanks to them for their support . Karthik - Had good coordination with Qadir and Pramod during the escalations handling.
A54: =IF(AND($D$1>=C54,$D$1<=D54),"CurrentSprint","NA") -> NA | B54: 26.2 Sprint 3 | C54: 46036 | D54: 46049 | E54: 26 | F54: 26 | G54: Completed all commited items from main sprint except 1 defect which was pulled into the sprint on the last day with 0 SP. | H54: It was a good sprint. We have completed all the items committed. It was mainly a regression sprint, we completed regression and fixed all regression defect as well. | I54: Completed committed SP. Cpmpleted regression successfully along with regression defects. Made good progress with escalations - closed 4 out of 5. | J54: Comments : CRC Peer - 0, Onsite - 0, Client - 0. Defects: 10 Bounceback -0 Internal Defect - 5 External Defect - 5(including escalations) What went well: Completed committed SP. Completed regression successfully along with regression defects. Made good progress with escalations - closed 4 out of 5. What didnt Go Well: Getting new escalations during sprint. | K54: Qadir - Completed all regression items in the main commit. (Import MSB Batches was in the stretch) Jeanette - Were able to close out most of our escalations within the sprint Sowjanya – Regression went well. Trying to speed up with the team. Pramod – Good Sprint - Completed regression, committed items, good discussions on escalations and closure, good team coordination, product discussions with Jeanette, Sowjanya catching-up with the speed, great UI upgrade design ideas from James V Pramod – to Qadir, Rijo, Karthik for overall support
A55: =IF(AND($D$1>=C55,$D$1<=D55),"CurrentSprint","NA") -> NA | B55: 26.3 Sprint 1 | C55: 46050 | D55: 46063 | E55: 23 | F55: 26 | G55: Completed 18 from main commit and 8 from stretch. Missed a 5SP story from the main commit. But completed 8 SP from stretch | H55: It was a good sprint overall. We have completed all committed items from main sprint except 1 - which is ready for POV at the end of sprint. And we have completed 2 stories from stretch and made good progress with other items from stretch as well. And we did a successfull and smooth production deployment. | I55: Completed 3 extra SP compared to the commited including 2 items from stretch. Successfull and smooth production deployment. Made good progress with escalations - closed 2 out of 3. | J55: Comments : CRC Peer - 0, Onsite - 0, Client - 0. Defects: 10 Bounceback -0 Internal Defect - 5 External Defect - 5(including escalations) What went well: Completed committed SP. Successfull production deployment. Made good progress with escalations - closed 2 out of 3. What didnt Go Well: Could not close 1 item, which was dev completed and waiting for POV. | K55: Jeanette - Rijo, Qadir, Thanks so much for each pushing to get another defect resolved and pushed out to our Feb release! Jeanette - Rijo, wonderful job for putting together a thorough document on our MSB Batches that is going to pay dividends for our team and product in the future! Rijo – To Karthik for fixing and closing a lot of defects. Sowjanya – Thanks to Rijo and Qadir for the last-minute fix on the import MSB batch and for helping me throughout the work. And Rijo on import MSB document will help us create automation easily and get more clear on each scenarios. Karthik – Rijo for his import MSB batches documentation, it will be very helpful in the future. Jeanette - Team - All the great work last sprint that set us up for the solid 26.2 release! Pramod – to James UI upgrade changes while my continuous feedback, to Karthik for multiple defect fixes, to Sowjanya for getting more confident with QA activities and staging data for deployment, to Rijo for MSB Batch Import documentation, to Jeanette for good product discussions, to Wes for covering us while post deployment verifications, Qadir for holding up on everything to keep pushing forward! Qadir – James for working on the UI for MSB Accounting – Refreshing to see a new look. | L55: 2 | M55: 4
A56: =IF(AND($D$1>=C56,$D$1<=D56),"CurrentSprint","NA") -> NA | B56: 26.3 Sprint 2 | C56: 46064 | D56: 46077 | E56: 15 | F56: 19 | G56: Completed 13 SPs from main commit and 6 from stretch. Missed a 2SP story from the main commit. The missed item was wating for PR approval for the last 2 days. | H56: It was a good sprint overall. We have completed all committed items from main sprint except 1 - which was waiting for PR approval for the last 2 days. And we have completed 2 stories from stretch and made good progress with other items from stretch as well. And completed all escalations reported during the sprint. | I56: Completed 4 extra SPs compared to the commited including 2 items from stretch. Closed all escalations Started on On-boarding items. | J56: Comments : CRC Peer - 0, Onsite - 0, Client - 0 Defects: 8 Bounceback -0 Internal Defect - 6 External Defect - 2(including escalations) What went well: Completed committed SP. Closed all escalations reported. What didnt Go Well: Could not close 1 item, which was dev completed and waiting for POV. | K56: Jeanette , Qadir, Rijo : Accounting defects that was knock out Jeanette : Onboarding items are going well. Jeanette , Qadir, Rijo: Less Accounting escalations in this sprint. Closed them all. Pramod: Good Sprint, good discussions within the team on the fix approaches, good product Qadir, Rijo : Dynamic IP issue took some time to sort out. Delay with starting with the onboarding work Qadir : Could not get a copy of the DB restored locally. Still using the DEV DB for dev for Onboarding. Qadir : James for working on the accounting UI. Qadir : Jeanette making good progress on fixing thatcher’s bad entries. | L56: 1 | M56: 2
A57: =IF(AND($D$1>=C57,$D$1<=D57),"CurrentSprint","NA") -> NA | B57: 26.3 Sprint 3 | C57: 46078 | D57: 46091 | E57: 19 | F57: 14 | G57: Completed 13 SPs from main commit and 1 from stretch. Missed two 3SP items from the main commit. 1 item was in testing by client QA and close to completion, other was waiting for POV approval from client PO for over a week. | H57: We have missed two 3SP items from the main commit due to dependencies on the client end. 1 item was in testing by client QA and close to completion, other was waiting for POV approval from client PO for over a week. Even though the team made good progress on the stretch items as well, could not close those out since those were low priority. | I57: The escalations reported reduced drastically (Only 1 from accounting), closed 2 escalations which was reported as well. Great continued work on defects and stories that will prevent future escalations (year end/date locking) | J57: Comments : CRC Peer - 1 (suggestion), Onsite - 0, Client - 0 Defects: 5 Bounceback -4 Internal Defect - 4 External Defect - 1(escalation) What went well: Closed all escalations reported. Escalation count reduced to 1. What didnt Go Well: We could not meet the SP commited. | K57: James – Jeanette / Qadir on the Thatcher issue James – Figma training this week James – Onboarding stories for the team being knocked out!!!! Qadir – Jeanette for the work on figuring out Thatcher Qadir – Sowjanya's discussions/questions brought up in discussions with dev Jeanette – Sowjanya’s strong support on testing and Figma design review Qadir – Sowjanya for thorough testing. Sowjanya – Jeanette, James, Qadir, Rijo on help this sprint James - Chris and Qdir both helping on the 403 issue with QA/DEV (Past dinner time lol) Jeanette – Great continued work on defects and stories that will prevent future escalations (year end/date locking) | L57: 7 | M57: 9
A58: =IF(AND($D$1>=C58,$D$1<=D58),"CurrentSprint","NA") -> NA | B58: 26.04 Sprint 1 | C58: 46092 | D58: 46105 | E58: 16 | F58: 19 | G58: Completed 14 from main commit and 5 from stretch. Missed a 2 SP story from the main commit. But completed 5 SP from stretch | H58: Overall, it was a good sprint. We completed all committed items from the main sprint except one, which is pending PR creation due to an unexpected team member’s sick leave. Additionally, we completed two stretch items and made good progress on the remaining stretch goals. A total of five escalations were reported during the sprint. Fixes have been completed for four, while the remaining one is awaiting client approval | I58: Completed 4 additional story points beyond the committed scope, including 2 items from the stretch goals. Addressed 4 out of 5 escalations; one additional escalation has been fixed in production and is awaiting customer confirmation, while the remaining one is pending client confirmation. Made good progress on the remaining stretch items. | J58: Comments : CRC Peer - 0 (suggestion), Onsite - 0, Client - 0 Defects: 0 Bounceback -2 Internal Defect - 1 External Defect - 6 (5 escalation) What went well: Effectively handled escalation fixes, with most of the issues related to data corrections. Completed several stretch items successfully. What didnt Go Well: We could not meet the SP commited. | K58: External: Allan Browder: Great effort by the team in getting all 5 escalations completed along with other items James: Karthik for completing the escalation work Chris: QA team for catching bouncebacks & thorough testing + all the feedback and documentation helping with where things are now Internal: Pramod: Rijo, Karthik balancing and completing the workloads this sprint while Qadir's week-long absence Qadir: Team for Escalation work while out Qadir: Karthik for work the Accounting work and escalations | L58: 7 | M58: 10.5
A59: =IF(AND($D$1>=C59,$D$1<=D59),"CurrentSprint","NA") -> NA | B59: 26.04 Sprint 2 | C59: 46106 | D59: 46119 | E59: 11 | F59: 24 | G59: Completed 11 SPs assigned from main commit and 13 SPs from the stretch. | H59: Overall, it was a very good sprint. We completed all committed items from the main sprint. Additionally, we completed four stretch items and made good progress on the remaining stretch goals. A total of five escalations were reported during the sprint for accounting. All 5 were completed and closed around the mid sprint. | I59: Completed all committed items from the main sprint and we completed four stretch items and made good progress on the remaining stretch items, 2 other items was in product owner verify state. We have completed and closed all 5 escalations reported in this sprint. | J59: Comments : CRC Peer - 0 (suggestion), Onsite - 0, Client - 0 Defects: 6 Bounceback -0 Internal Defect - 3 External Defect - 3 (2 escalations) | K59: External: James: Really good feedback from Pramod and Sowjanya Wes – We completed a number of onboarding tasks and I Improved my knowledge. James: Really good demos from everyone. (Rijo always so calm) James: Qadir is always there when you need him Internal: Qadir , Rijo : Really good sprint. Covered a lot of ground , even if SP doesn’t show it. Qadir : @Rijo P R [C] and @Karthikeyan Ganesan [C] - Great job closing out a lot of defects in stretch Pramod– Good sprint, good team discussions to maintain focus on the dev works Karthik – Completed almost all the planned items, we also finished some additional stretch items. Qadir : Client POV approvals were slightly delayed, affecting testing. Pramod: Jeanette could handoff or inform me to be a proxy for POV approvals while she is away to keep things moving and she can review later Sowjanya- Thanks to Pramod and Rijo on clarification while testing Sowjanya- Thanks to James for the very Quick fix Rijo – Sowjanya and Wes for covering good ground with testing on both Accounting and onboarding items Rijo – Karthik and Qadir for fixing all the accounting escalations quickly Pramod: to JV for all the great changes he made on my additional requests after my POV Pramod: Rijo and Karthik for focus on accounting items Pramod: Qadir for helping on everything needed for the team Pramod: Chris on the perfect changes on onboarding items What went well: Effectively handled escalation fixes, with most of the issues related to data corrections. Completed all committed items from the main sprint Completed several stretch items successfully. What didnt Go Well: Nothing | L59: 4 | M59: 5
A60: =IF(AND($D$1>=C60,$D$1<=D60),"CurrentSprint","NA") -> NA | B60: 26.04 Sprint 3 | C60: 46120 | D60: 46133 | E60: 44 | F60: 33 | G60: Completed 33 SPs from main commit. Missed 11 since few regression items was blocked due to UI issues from Kaleida changes. And few defects which is being worked by client dev got bouncebacks. | H60: It was a good sprint overall. We have almost completed regression. But since we found so UI issues with the new Kaleida and layout changes which were fixed by client developer. | I60: Completed most of the regression items. And almost all defects found are fixed and tested by QA. We have closed 3 out of 5 escalations and made good progress with other 2. | J60: Comments : CRC Peer - 0 (suggestion), Onsite - 0, Client - 0 Defects: 5 Bounceback -0 Internal Defect - 2 External Defect - 2 (2 escalations) Appreciations - James: Sowjanya for finding every issue under every nook and cranny. Meetings to go over fixes at 4:00am, James: Pramod for all the actions on reviewing all the changes for the report's dialog and status popups and others. Pramod: James for all those quick turarounds on UI changes Pramod: Sowjanya for testing and coordination on defect items Sowjanya- Pramod, Rijo and Qadir For clarifying me on few thing while testing Sowjanya- James was superfast fix on defects and bounce back Jeanette – James amazing work on the UI, Sowjanya great testing findings to ensure a great product gets released to our customers, Rijo’s continued Batch King knowledge to help with the batch escalation Qadir - James for fixing the defects findings immediately. Qadir – Sowjanya – Amazing job on testing defects. There were a lot of defects and she had great cooridnation with Pramod to make sure the defects were in Axosoft Qadir - Pramod – For keeping Axosoft up to date with the defects found. | K60: What went well: Good sprint, faster UI upgrade changes, team discussions, lots of items tested switching the focus between Cert and QA due to UI changes for this sprint Nothing What didnt Go Well: No user Kaleida UI stories for visibility, transparency, & tracking. | L60: 3 | M60: 3 | P60: 111
A61: =IF(AND($D$1>=C61,$D$1<=D61),"CurrentSprint","NA") -> NA | B61: 26.06 Sprint 1 | C61: 46134 | D61: 46147 | E61: 22 | F61: 25 | G61: Completed all 22 SPs from the main commit and additional 3 Sps from the stretch. | H61: It was a very good sprint. We have completed all commited items and 2 additional items from stretch. And made good progress on other stretch items as well. | I61: Regression completed and release candidate is ready for production deployment this week. We have completed all commited items and 2 additional items from stretch. And made good progress on other stretch items as well. | J61: Comments : CRC Peer - 0 (suggestion), Onsite - 0, Client - 0 Defects: 6 Bounceback -0 Internal Defect - 4 External Defect - 2 (2 escalations) Appreciations - James: Seems like more stories was completed Jeanette - Regression completed Karthik – Completed all committed items and few from stretch. Qadir - Regression completed. Pramod– Good sprint, completed all regression defects+regression, few additional stretch items as well, excited to present the new upgraded UI for the customers in the next release Sowjanya- Regression Completed Karthik ,James– Sowjanya and Wes for excellent job in the testing. Sowjanya- Thanks to Pramod was clearing all queries while testing even he was busy with his work | K61: What went well: Good sprint, faster UI upgrade changes, team discussions, lots of items tested switching the focus between Cert and QA due to UI changes for this sprint What didnt Go Well: No deployment yet, but soon... No POV for header/nav/footer from January. No user Kaleida UI stories for visibility, transparency, & tracking. | L61: 4 | M61: 4 | P61: 103.25
A62: =IF(AND($D$1>=C62,$D$1<=D62),"CurrentSprint","NA") -> NA | B62: 26.06 Sprint 2 | C62: 46148 | D62: 46161 | E62: 25 | L62: 2

Sheet Defect-template
A1: S.No | B1: Sprint # | C1: Story/Defect ID | D1: Parent Story | E1: Developer | F1: Issue Type | G1: Issue Description | H1: Priority | I1: Defect Source | J1: Type | K1: Status | L1: Root Cause Category | M1: Comments

Sheet 26.06 Sprint 2-Status
A1: S.No | B1: Application Name | C1: Sprint Start Date | D1: Sprint End Date | E1: Sprint | F1: Developer | G1: Story ID/Defect ID | H1: Description | I1: Status | J1: Estimated(sp) | K1: Actual(sp) | L1: Actual Hours Worklog | M1: Dev Start Date | N1: Dev End Date | O1: Unit testing | P1: Peer Tested By | Q1: Peer Tested Comments, if any | R1: Peer Reviewed By | S1: Peer Code Review Comments, if any | T1: PR Number/Link | U1: PR Created Date | V1: PR Approved Date | W1: Onsite Lead Code Review | X1: Onsite Lead Code Review Comments, if any | Y1: Client Code Review | Z1: PR Approved Date2 | AA1: Client Code Review Comments, if any | AB1: Internal PO -POV Comments | AC1: Client PO -POV Comments | AD1: Comments | AE1: Story met clarity expectations? | AF1: 46148 | AG1: 46149 | AH1: 46150 | AI1: 46153 | AJ1: 46154 | AK1: 46155 | AL1: 46156 | AM1: 46157 | AN1: 46160 | AO1: 46161
A2: 1 | B2: MSB Accounting | C2: 46148 | D2: 46161 | E2: MSB Accounting 26.06 Sprint 2 | F2: Client Dev | G2: 52474 | H2: MSB Onboarding - Complete User Experience with New Flow | I2: Story Completed | J2: 2 | AF2: Have created a bounce back for Sign & Exit | AG2: Waiting for the bounceback fix. | AH2: Waiting for the bounceback fix. | AI2: Waiting for the bounceback fix. | AJ2: Waiting for bounceback fix. | AK2: Have one doubt regarding save and exit. | AL2: Completed testing regarding save and exit. Have one more doubut, will discuss. | AM2: Completed testing and closed
A3: 2 | B3: MSB Accounting | C3: 46148 | D3: 46161 | E3: MSB Accounting 26.06 Sprint 2 | F3: Karthik | G3: 45225 | H3: MSB ACCT - BKK - Add Warnings and Blockers for Unclosed Years (26.5) | I3: Story Completed | J3: 2 | K3: 4 | L3: 16 | M3: 46150 | N3: 46150 | O3: Completed | P3: Rijo | Q3: Pass | R3: Qadir | S3: Pass | T3: https://dev.azure.com/heartlandschools/Accounting/_git/MSBAccounting-NewSchoolBooks/pullrequest/48944 | U3: 46150 | V3: 46150 | W3: Done | X3: Pass | Y3: Done | Z3: NA | AA3: Pass | AB3: Pass | AC3: Pass | AF3: Sowjanya started testing after completing test cases. 1 AC point covered. | AG3: Completed AC points. But need to validate few more things before closing. | AH3: Biunce back created - If the FY Close Warning Type is selected as “Warn Only” or “Warn and Stop Entries,” the system does not allow selecting the “Warning Date” and “New Entry Stop Date” as “0 days after fiscal year ends.” | AI3: PR for the bounce back completed. Waiting for the deployment for bb testing. | AJ3: Testing completed and Sowjanya will close this. | AK3: _
A4: 3 | B4: MSB Accounting | C4: 46148 | D4: 46161 | E4: MSB Accounting 26.06 Sprint 2 | F4: Rijo | G4: 22751 | H4: MSB ACCT - Integration - Renumber Merge deletes a mapped GL account in ImportFromMSB transaction causing error | I4: Defect Ready For Testing | J4: 5 | M4: 46148 | N4: 46150 | AF4: Completed warning part. Working on Account change. Need to do deep analysis for downstream impacts as well. | AG4: Dev and unit testing completed. Ready for POV. | AH4: POV completed with Pramod. Shared recording in the channel. And shared branch details for review. | AI4: Code review and peer testing completed by Qadir. Will be creating a PR once I get the approval from Jeanette. | AJ4: Waiting on Jeanette's approval. | AK4: Waiting on Jeanette's approval. | AL4: Waiting on Jeanette's approval. | AM4: Completed PR. Ready for testing.
A5: 4 | B5: MSB Accounting | C5: 46148 | D5: 46161 | E5: MSB Accounting 26.06 Sprint 2 Stretch | F5: Karthik | G5: 51720 | H5: MSB ACCT - BKK - Implement iTextSharpTool alternative opensource tool for report-to-PDF conversion | I5: Story Peer Review | J5: 8 | K5: 6 | L5: 24 | M5: 46148 | N5: 46154 | O5: Completed | R5: Qadir | S5: Reported a padding issue in the new version receipting PDF. | AB5: Pass | AC5: Pass | AF5: PDF changes in progress. Getting some UI alignment issues in reports. | AG5: Validating new reports with existing ones. Found 1 overlapping issue. Will be recording issues in an excel sheet. | AH5: Found 1 more UI issue and made fix. Continuing with custom template, there are 250+ templates. | AI5: Karthik PTO. | AJ5: Completed textoveralpping issue fix and POV with Pramod. | AK5: Waiting on Jeanette's approval. | AL5: Waiting on Jeanette's approval. | AM5: Jeanette added one more AC point and got 1 peer review comment from Qadir to work on.
A6: 5 | B6: MSB Accounting | C6: 46148 | D6: 46161 | E6: MSB Accounting 26.06 Sprint 2 | F6: Qadir | G6: SRX28874 | H6: MSB ACCT - Variance for second Bank Rec (Thatcher-July-BankB) | I6: Defect Being Fixed | J6: 0 | AF6: Waiting for Jeanette's approval about the fix we proposed. Made some progress with the analysis as well. | AG6: No progress. | AH6: Prod db copy restored on Dev. Will try to replicate the issue. | AI6: Not much updates. Was working on backround jobs escalations. | AJ6: Dev environment setup in progress. | AK6: No updates. Working on delayed batches escalation. | AL6: No updates. Working on delayed batches escalation. | AM6: No updates. Working on delayed batches escalation.
A7: 6 | B7: MSB Accounting | C7: 46148 | D7: 46161 | E7: MSB Accounting 26.06 Sprint 2 | F7: Qadir | G7: SRX28876 | H7: DUR - MSB ACCT - BKK - Kingsport City Schools (129907) - Dobyns-Bennett High School (DOB) | I7: Defect Being Fixed | J7: 0 | AF7: Still waiting for dev db to be restored with prod copy. Trying to use the db locally in the mean while. | AG7: No progress. Still waiting for dev db to be restored with prod copy. | AH7: Prod db copy restored on Dev. Will try to replicate the issue. | AI7: Not much updates. Was working on backround jobs escalations. | AJ7: Waiting on DBA setup. | AK7: No updates. Working on delayed batches escalation. | AL7: No updates. Working on delayed batches escalation. | AM7: Able to replicate the issue on Dev. Increasing the timeout should be the only option since it's an in-built feature.
A8: 7 | B8: MSB Accounting | C8: 46148 | D8: 46161 | E8: MSB Accounting 26.06 Sprint 2 | F8: Rijo | G8: 47478 | H8: MSB ACCT - BKK - Update Bank Deposit History Report to Reflect Changes to Import MSB Batches (26.5) | I8: Story Completed | J8: 1 | AG8: Created PR. | AH8: Deployed and ready for testing. | AI8: Being tested by client QA. | AJ8: Closed by Client QA
A9: 8 | B9: MSB Accounting | C9: 46148 | D9: 46161 | E9: MSB Accounting 26.06 Sprint 2 Stretch | F9: Rijo | G9: 47848 | H9: MSB ACCT - BKK - Rename "New Data" Feature Flag (26.5) | I9: Story Ready For Testing | J9: 3 | AG9: Will be creating PR after Qadir's review. POV already approved earlier. | AH9: Waiting for deployment. | AI9: Waiting for deployment. | AJ9: Will start testing once committed items completed. | AK9: Will start testing once committed items completed. | AL9: Will start testing once committed items completed. | AM9: Will start testing once committed items completed.
A10: 9 | B10: MSB Accounting | C10: 46148 | D10: 46161 | E10: MSB Accounting 26.06 Sprint 2 | F10: Rijo | G10: 27200 | H10: MSB ACCT - BKK - Cash Transfer does not save the "Notes" after editing | I10: Defect Fixed | J10: 1 | AG10: Will be creating PR after Qadir's review. POV already approved earlier. | AH10: Started testing. Notes text area size is larger than other pages. Rijo will be fixing it. | AI10: Notes resize done and PR completed. Can be verified after deployment. | AJ10: Completed testing and closed
A11: 10 | B11: MSB Accounting | C11: 46148 | D11: 46161 | E11: MSB Accounting 26.06 Sprint 2 Stretch | F11: Rijo | G11: 25390 | H11: MSB ACCT - BKK - Warning icon not displaying for overdrawn line items in a manual check while editing an existing record | I11: Product Owner - Verify | J11: 1 | AH11: Ready for POV. | AI11: Found some issue with overdraw amount calculation and fixed. Waiting for Pramod for the POV. | AJ11: POV completed with Pramod. Shared recording in the channel. | AL11: Waiting on Jeanette's approval. | AM11: Got POV approval and peer review done. Will be creating a PR soon.
A12: 11 | B12: MSB Accounting | C12: 46148 | D12: 46161 | E12: MSB Accounting 26.06 Sprint 2 | F12: Client Dev | G12: 52708 | H12: MSB Onboarding - Updated Program Selector Page | I12: Story Completed | J12: 3 | AI12: Test cases covered. Need to discuss few UI changes and clarify 1 scenario with client Dev before closing. | AJ12: Sowjanya need clarification about findings. | AK12: Need 1 more clarification from client dev. | AL12: Qadir will get this clarified. | AM12: Completed and closed
A13: 12 | B13: MSB Accounting | C13: 46148 | D13: 46161 | E13: MSB Accounting 26.06 Sprint 2 | F13: Qadir/Rijo | G13: SRX28912 | H13: MSB ACCT - BKK - Batches are not available for importing from 5/7 | I13: Defect Being Fixed | J13: 0 | AI13: Made scheduler jobs on A01 to keep the server active and running. It would resolve the issue with shutting down the server due to inactivity. But we are looking for a long term solution, but not as part of this escalation. | AJ13: Closed. | AM13: Will discuss with RJ to close batch missing related escalations since we got all batches.
A14: 13 | B14: MSB Accounting | C14: 46148 | D14: 46161 | E14: MSB Accounting 26.06 Sprint 2 Stretch | F14: Rijo | G14: 49563 | H14: MSB ACCT - BKK - New Feature: Credit Note and Debit Note-DB Changes | I14: Story Being Developed | J14: 5 | AJ14: Picked up and started analysis. | AK14: Not much progress. Analysis still in progress. | AL14: Created table structure, need some clarifications from Pramod. | AM14: Wil discuss with Pramod before the actual POV.
A15: 14 | B15: MSB Accounting | C15: 46148 | D15: 46161 | E15: MSB Accounting 26.06 Sprint 2 | F15: Rijo | G15: SRX28916 | H15: MSB ACCT - BKK - MSB batches are not available for importing from 5/12 | I15: Defect Being Fixed | AJ15: Started analysis. | AK15: Still server getting shutdown and jobs not getting completed in time. | AL15: Fix completed on PROD. Will get a confirmation and close. | AM15: Will discuss with RJ to close batch missing related escalations since we got all batches.
A16: 15 | B16: MSB Accounting | C16: 46148 | D16: 46161 | E16: MSB Accounting 26.06 Sprint 2 | F16: Client Dev | G16: 53136 | H16: MSB Onboarding - Update the Maintenance Form View | I16: Story Completed | J16: 3 | AK16: Started testing today. Started with maintanance page. Cleared doubt with James. Testing going on. | AL16: Testing in progress. | AM16: Completed and closed
A17: 16 | B17: MSB Accounting | C17: 46148 | D17: 46161 | E17: MSB Accounting 26.06 Sprint 2 Stretch | F17: Karthik | G17: 52626 | H17: MSB Accounting - Printing Reports Default | I17: Story Being Developed | J17: 5 | K17: 3 | L17: 12 | M17: 46155 | N17: 46156 | O17: Completed | P17: Rijo | Q17: Pass | R17: Qadir | S17: Pass | AB17: Pass | AK17: Completed dev changes. Updated 52 rdlc files. Dev testing in progress. | AL17: Dev testing completed, waiting for Pramod to run POV. | AM17: POV completed. Will be sharing the recording in the channel. Peer review also completed.
A18: 17 | B18: MSB Accounting | C18: 46148 | D18: 46161 | E18: MSB Accounting 26.06 Sprint 2 | F18: Qadir/ Clent Dev | G18: SRX28920 | H18: MSB ACCT - BKK - School Site Users Unable to Print Checks (CCSD) | I18: Defect Being Fixed | J18: 0 | AM18: Checked out the issue. Permission issue with forms. No need of any fix from our issue, just need to assign the permission to the user role.

Sheet 26.06 Sprint 2-Defect
A1: S.No | B1: Sprint # | C1: Story/Defect ID | D1: Parent Story | E1: Developer | F1: Issue Type | G1: Issue Description | H1: Priority | I1: Defect Source | J1: Type | K1: Status | L1: Root Cause Category | M1: Comments

Sheet 26.06 Sprint 1-Status
A1: S.No | B1: Application Name | C1: Sprint Start Date | D1: Sprint End Date | E1: Sprint | F1: Developer | G1: Story ID/Defect ID | H1: Description | I1: Status | J1: Estimated(sp) | K1: Actual(sp) | L1: Actual Hours Worklog | M1: Dev Start Date | N1: Dev End Date | O1: Unit testing | P1: Peer Tested By | Q1: Peer Tested Comments, if any | R1: Peer Reviewed By | S1: Peer Code Review Comments, if any | T1: PR Number/Link | U1: PR Created Date | V1: PR Approved Date | W1: Onsite Lead Code Review | X1: Onsite Lead Code Review Comments, if any | Y1: Client Code Review | Z1: PR Approved Date2 | AA1: Client Code Review Comments, if any | AB1: Internal PO -POV Comments | AC1: Client PO -POV Comments | AD1: Comments | AE1: Story met clarity expectations? | AF1: 46134 | AG1: 46135 | AH1: 46136 | AI1: 46139 | AJ1: 46140 | AK1: 46141 | AL1: 46142 | AM1: 46143 | AN1: 46146 | AO1: 46147
A2: 1 | B2: MSB Accounting | C2: 46134 | D2: 46147 | E2: MSB Accounting 26.06 Sprint 1 Stretch | F2: Client Dev | G2: 52277 | H2: MSB Onboarding - Sign & Submit | I2: Story Completed | J2: 1 | K2: 1 | L2: 4 | M2: NA | N2: NA | O2: NA | P2: NA | Q2: NA | R2: NA | S2: NA | T2: NA | U2: NA | V2: NA | W2: NA | X2: NA | Y2: NA | Z2: NA | AA2: NA | AB2: NA | AC2: NA | AD2: Worked by client dev. Only testing effort for us. | AE2: Meets Expectation | AF2: Created a bounceback on theprimary and secondary contact when i enter a phone number and its picking up another number | AG2: Waiting on Bounceback Fix | AH2: Waiting on the bounceback | AI2: Waiting on the bounceback | AJ2: When i add the phone number in contacts and save then click edit to check the number the number seems to be different-Again assigned to james | AK2: Bounceback reported to James. Sowjanya - PTO | AL2: Moved to testing and Wes pick up. | AM2: Wes completed
A3: 2 | B3: MSB Accounting | C3: 46134 | D3: 46147 | E3: MSB Accounting 26.06 Sprint 1 Stretch | F3: Qadir | G3: 52629 | H3: MSB Onboarding - Remove all old onboarding pages | I3: Story Completed | J3: 2 | K3: 1.75 | L3: 7 | M3: NA | N3: NA | O3: NA | P3: NA | Q3: NA | R3: NA | S3: NA | T3: NA | U3: NA | V3: NA | W3: NA | X3: NA | Y3: NA | Z3: NA | AA3: NA | AB3: NA | AC3: NA | AD3: Needed to remove the old pages from the new workflow. Dev was completed last sprint. Only testing in this sprint. | AE3: Meets Expectation | AF3: Started and check on the pages | AG3: - | AH3: need to verify create account page. | AI3: Completed | AJ3: - | AK3: - | AL3: -
A4: 3 | B4: MSB Accounting | C4: 46134 | D4: 46147 | E4: MSB Accounting 26.6 Sprint 1 | F4: Qadir/ Karthik | G4: SRX28874 | H4: MSB ACCT - Variance for second Bank Rec (Thatcher-July-BankB) | I4: Defect Being Fixed | J4: 0 | K4: 4.93 | L4: 19.75 | M4: 46134 | N4: NA | O4: NA | P4: NA | Q4: NA | R4: NA | S4: NA | T4: NA | U4: NA | V4: NA | W4: NA | X4: NA | Y4: NA | Z4: NA | AA4: NA | AB4: NA | AC4: NA | AD4: Qadir - Waiting for prod db copy to be restored on dev. Still Waiting for Jeanette verification. Request to restore db on Dev has been created on Apr 29th, still waiting for completion. | AE4: Meets Expectation | AF4: Still working on this. Looked at the prod data. Trying identify if the abnk rec lines are not being updated. | AG4: - | AH4: Found the root cause. Previous ending balance not calculated correctly. Checked with prev ending balance. | AI4: shared details with jeanette. Waiting on feedback. new Dev Database to be setup. | AJ4: jeanette needs DB Restored on DEV Request Made | AK4: Qadir will check about the DEV environment setup. | AL4: Waiting for Jeanette verification. | AN4: Qadir - Waiting for prod db copy to be restored on dev. Still Waiting for Jeanette verification. | AO4: Qadir - Waiting for prod db copy to be restored on dev. Still Waiting for Jeanette verification.
A5: 4 | B5: MSB Accounting | C5: 46134 | D5: 46147 | E5: MSB Accounting 26.6 Sprint 1 | F5: Qadir | G5: SRX28876 | H5: DUR - MSB ACCT - BKK - Kingsport City Schools (129907) - Dobyns-Bennett High School (DOB) | I5: Defect Being Fixed | J5: 0 | K5: 2.12 | L5: 8.5 | M5: 46134 | N5: NA | O5: NA | P5: NA | Q5: NA | R5: NA | S5: NA | T5: NA | U5: NA | V5: NA | W5: NA | X5: NA | Y5: NA | Z5: NA | AA5: NA | AB5: NA | AC5: NA | AD5: Waiting for prod db copy to be restored on dev. Request to restore db on Dev has been created on Apr 29th, still waiting for completion. | AE5: Meets Expectation | AF5: No Progress. | AG5: - | AH5: Code Fix. i have rewritten Acount SnapShot Report. Also, Looking at the beginning balances. | AI5: Dev Testing completed. need to make a PR for this today. | AJ5: PR made right now. | AK5: Will try to replicate this in DEV with latest DB, and will test the fix in the same environment if it replicated. | AL5: Will try to replicate in DEV. Also Qadil will check the DB update. | AN5: Waiting for prod db copy to be restored on dev. | AO5: Waiting for prod db copy to be restored on dev.
A6: 5 | B6: MSB Accounting | C6: 46134 | D6: 46147 | E6: MSB Accounting 26.6 Sprint 1 | F6: Rijo | G6: 52715 | H6: MSB ACCT - BKK - Regression - Entry Menu (Not Import MSB Batches) (26.4) | I6: Story Completed | J6: 2 | K6: 2.75 | L6: 11 | M6: NA | N6: NA | O6: NA | P6: NA | Q6: NA | R6: NA | S6: NA | T6: NA | U6: NA | V6: NA | W6: NA | X6: NA | Y6: NA | Z6: NA | AA6: NA | AB6: NA | AC6: NA | AD6: Regression testing. No code changes and PR. | AE6: Meets Expectation | AF6: Start Testing today | AG6: Completed 7 screens. All working as expected. | AH6: Completed | AI6: - | AJ6: - | AK6: - | AL6: -
A7: 6 | B7: MSB Accounting | C7: 46134 | D7: 46147 | E7: MSB Accounting 26.6 Sprint 1 | F7: Karthik | G7: 52714 | H7: MSB ACCT - BKK - Regression - Maintenance Menu (26.4) | I7: Story Completed | J7: 1 | K7: 1 | L7: 4 | M7: NA | N7: NA | O7: NA | P7: NA | Q7: NA | R7: NA | S7: NA | T7: NA | U7: NA | V7: NA | W7: NA | X7: NA | Y7: NA | Z7: NA | AA7: NA | AB7: NA | AC7: NA | AD7: Regression testing. No code changes and PR. | AE7: Meets Expectation | AG7: Completed. | AH7: - | AI7: - | AJ7: - | AK7: - | AL7: -
A8: 7 | B8: MSB Accounting | C8: 46134 | D8: 46147 | E8: MSB Accounting 26.6 Sprint 1 | F8: Client Dev | G8: 27265 | H8: MSB ACCT - BKK - [Regression] Upgrade 1099 Print Forms to the new UI look and feel | I8: Defect Fixed | J8: 2 | K8: 0.75 | L8: 3 | M8: NA | N8: NA | O8: NA | P8: NA | Q8: NA | R8: NA | S8: NA | T8: NA | U8: NA | V8: NA | W8: NA | X8: NA | Y8: NA | Z8: NA | AA8: NA | AB8: NA | AC8: NA | AD8: Worked by client dev. Only testing effort for us. | AE8: Meets Expectation | AG8: While testing found the popup size was too big | AH8: Waiting on the client dev to completed work | AI8: Found the pdf blank so retesting the scenario. Filling in the right data for the PO's / Invoices to fetch 1099 data | AJ8: Completed | AK8: - | AL8: -
A9: 8 | B9: MSB Accounting | C9: 46134 | D9: 46147 | E9: MSB Accounting 26.6 Sprint 1 | F9: Sowjanya | G9: 52724 | H9: MSB ACCT - BKK - Regression - 26.3 & 26.4 Stories and Defects | I9: Story Completed | J9: 8 | K9: 2.75 | L9: 11 | M9: NA | N9: NA | O9: NA | P9: NA | Q9: NA | R9: NA | S9: NA | T9: NA | U9: NA | V9: NA | W9: NA | X9: NA | Y9: NA | Z9: NA | AA9: NA | AB9: NA | AC9: NA | AD9: Regression testing. No code changes and PR. | AE9: Meets Expectation | AG9: Have completed 3 defects and 1 story | AH9: Completed 10 defects. 1 defect and 1 story pending. | AI9: Everything completed except 1 defect pending on receipting so pushed to wes for testing | AJ9: Completed | AK9: - | AL9: -
A10: 9 | B10: MSB Accounting | C10: 46134 | D10: 46147 | E10: MSB Accounting 26.6 Sprint 1 | F10: Rijo | G10: 52719 | H10: MSB ACCT - BKK - Regression - Administration Menu (26.4) | I10: Story Completed | J10: 2 | K10: 2 | L10: 8 | M10: NA | N10: NA | O10: NA | P10: NA | Q10: NA | R10: NA | S10: NA | T10: NA | U10: NA | V10: NA | W10: NA | X10: NA | Y10: NA | Z10: NA | AA10: NA | AB10: NA | AC10: NA | AD10: Regression testing. No code changes and PR. | AE10: Meets Expectation | AH10: Completed Role managment. | AI10: - | AJ10: - | AK10: - | AL10: -
A11: 10 | B11: MSB Accounting | C11: 46134 | D11: 46147 | E11: MSB Accounting 26.6 Sprint 1 | F11: Client Dev | G11: 27265 | H11: MSB ACCT - BKK - [Regression] Bank rec. id is displayed instead of date in Bank Rec. History Report (26.4) | I11: Defect Fixed | J11: 0 | K11: 0.75 | L11: 4 | M11: NA | N11: NA | O11: NA | P11: NA | Q11: NA | R11: NA | S11: NA | T11: NA | U11: NA | V11: NA | W11: NA | X11: NA | Y11: NA | Z11: NA | AA11: NA | AB11: NA | AC11: NA | AD11: Worked by client dev. Only testing effort for us. | AE11: Meets Expectation | AI11: Could not reproduce in CERT> | AJ11: - | AK11: - | AL11: -
A12: 11 | B12: MSB Accounting | C12: 46134 | D12: 46147 | E12: MSB Accounting 26.6 Sprint 1 | F12: Karthik | G12: 52936 | H12: MSB ACCT - BKK - Regression - Period End Menu (26.4) | I12: Story Completed | J12: 3 | K12: 3 | L12: 12 | M12: NA | N12: NA | O12: NA | P12: NA | Q12: NA | R12: NA | S12: NA | T12: NA | U12: NA | V12: NA | W12: NA | X12: NA | Y12: NA | Z12: NA | AA12: NA | AB12: NA | AC12: NA | AD12: Regression testing. No code changes and PR. | AE12: Meets Expectation | AI12: Completed bank Rec Month End year end . Working on 1099 reports. | AJ12: Completed 1099 Reporting Menu. Completed post Year End Observations. Existing Issue shared | AK12: Completed | AL12: -
A13: 12 | B13: MSB Accounting | C13: 46134 | D13: 46147 | E13: MSB Accounting 26.6 Sprint 1 | F13: Rijo | G13: 52718 | H13: MSB ACCT - BKK - Regression - Management Menu (26.4) | I13: Story Completed | J13: 2 | K13: 2.25 | L13: 9 | M13: NA | N13: NA | O13: NA | P13: NA | Q13: NA | R13: NA | S13: NA | T13: NA | U13: NA | V13: NA | W13: NA | X13: NA | Y13: NA | Z13: NA | AA13: NA | AB13: NA | AC13: NA | AD13: Regression testing. No code changes and PR. | AE13: Meets Expectation | AI13: Started today. Conmpleted 4 screens. Failed School Settings. 52912. | AJ13: Closed the issue with School Settings. Almost Completed special functions questions on hardware settings. | AK13: Completed | AL13: -
A14: 13 | B14: MSB Accounting | C14: 46134 | D14: 46147 | E14: MSB Accounting 26.6 Sprint 1 | F14: Qadir | G14: SRX28888 | H14: MSB ACCT - BKK - Duplicate Adjustment Entry on Bank Rec/Report (Pleasanton) | I14: Defect Fixed | J14: 0 | K14: 2.5 | L14: 10 | M14: 46136 | N14: 46141 | O14: Completed | P14: Rijo | Q14: Pass | R14: Karthik | S14: Pass | T14: NA | U14: NA | V14: NA | W14: NA | X14: NA | Y14: NA | Z14: NA | AA14: NA | AB14: NA | AC14: NA | AD14: Prod data fix, update query ran on prod db. No code changes and PR. | AE14: Meets Expectation | AI14: Had a discussion with the team on the root cause. Make the data fix. Make a request for Audit Logs. | AK14: Data fix done for this and verification is pending. Audit log analsis in progress. | AL14: Completed verification and new defect will be created to find the root cause.
A15: 14 | B15: MSB Accounting | C15: 46134 | D15: 46147 | E15: MSB Accounting 26.6 Sprint 1 | F15: Rijo | G15: 52912 | H15: MSB ACCT - BKK - Upgrade Purchase Order Entry Page and School Settings page with Shipping address validations | I15: Story Completed | J15: 2 | K15: 0.12 | L15: 0.5 | M15: NA | N15: NA | O15: Completed | P15: Karthik | Q15: Pass | R15: Qadir | S15: Pass | T15: https://dev.azure.com/heartlandschools/Accounting/_git/MSBAccounting-NewSchoolBooks/pullrequest/48608 | U15: 46135 | V15: 46135 | W15: Done | X15: Pass | Y15: Done | Z15: NA | AA15: Pass | AB15: Pass | AC15: Pass | AD15: Development was completed last sprint. | AE15: Meets Expectation | AJ15: Testing in progress. Almost completed. | AK15: Completed | AL15: -
A16: 15 | B16: MSB Accounting | C16: 46134 | D16: 46147 | E16: MSB Accounting 26.06 Sprint 1 Stretch | F16: Rijo | G16: 27200 | H16: MSB ACCT - BKK - Cash Transfer does not save the "Notes" after editing | I16: Product Owner - Verify | J16: 2 | K16: 1.5 | L16: 6 | M16: 46141 | N16: 46146 | O16: Completed | P16: NA | Q16: NA | R16: NA | S16: NA | T16: NA | U16: NA | V16: NA | W16: NA | X16: NA | Y16: NA | Z16: NA | AA16: NA | AB16: Pass | AC16: NA | AD16: Waiting for the client PO approval for the POV for the last 2 days. The review and PR is pending. | AE16: Meets Expectation | AK16: Made the fix, testing it out. Will be doing the POV by next day. | AL16: Rijo PTO | AM16: Holiday | AN16: Did the POV with Pramod and posted for Jeanette's approval. | AO16: Still waiting for Jeanette's approval.
A17: 16 | B17: MSB Accounting | C17: 46134 | D17: 46147 | E17: MSB Accounting 26.06 Sprint 1 Stretch | F17: Karthik | G17: 45225 | H17: MSB ACCT - BKK - Add Warnings and Blockers for Unclosed Years (26.5) | I17: Story Peer Review | J17: 3 | K17: 1.5 | L17: 6 | M17: 46141 | N17: 46141 | O17: Completed | P17: Rijo | Q17: Pass | R17: Qadir | S17: Pass | T17: https://dev.azure.com/heartlandschools/Accounting/_git/MSBAccounting-NewSchoolBooks/pullrequest/48844 | U17: 46147 | V17: 46147 | W17: Done | X17: Pass | Y17: Done | Z17: NA | AA17: Pass | AB17: Pass | AC17: Pass | AD17: Dev completed, and testing will be completed on next sprint. | AE17: Meets Expectation | AK17: Completed pending changes, and will create a PR once release branch created. | AL17: Found duplicate css and js with bank deposit entry screen. Made fix and Qadir will do peer review. | AM17: Holiday | AN17: Waiting for Qadir's review. | AO17: Needs to deploy
A18: 17 | B18: MSB Accounting | C18: 46134 | D18: 46147 | E18: MSB Accounting 26.06 Sprint 1 Stretch | F18: Client Dev | G18: 52474 | H18: MSB Onboarding - Complete User Experience with New Flow | I18: Story Being Tested | J18: 3 | K18: 3.33 | L18: 10 | M18: NA | N18: NA | O18: NA | P18: NA | Q18: NA | R18: NA | S18: NA | T18: NA | U18: NA | V18: NA | W18: NA | X18: NA | Y18: NA | Z18: NA | AA18: NA | AB18: NA | AC18: NA | AD18: Worked by client dev. Only testing effort for us. | AE18: Meets Expectation | AM18: Holiday | AN18: Found a possible issue, need to clarify with client dev. | AO18: Got clarified and need to create a bounceback
A19: 18 | B19: MSB Accounting | C19: 46134 | D19: 46147 | E19: MSB Accounting 26.6 Sprint 1 | F19: Karthik/Rijo | G19: 27326 | H19: MSB ACCT - BKK - [Regression] MSB Import Batch does not show the payment items (26.4) | I19: Defect Rejected | J19: 0 | K19: 2.25 | L19: 9 | M19: 46142 | N19: 46146 | O19: NA | P19: NA | Q19: NA | R19: NA | S19: NA | T19: NA | U19: NA | V19: NA | W19: NA | X19: NA | Y19: NA | Z19: NA | AA19: NA | AB19: NA | AC19: NA | AD19: Defect rejected. It was a set up issue with gateway assignment. User is not supposed to remove assigned schools for a shared batch. | AE19: Meets Expectation | AN19: Defect rejected. It was a set up issue with gateway assignment. User is not supposed to remove assigned schools for a shared batch.
A20: 19 | B20: MSB Accounting | C20: 46134 | D20: 46147 | E20: MSB Accounting 26.06 Sprint 1 Stretch | F20: Rijo | G20: 22751 | H20: MSB ACCT - Integration - Renumber Merge deletes a mapped GL account in ImportFromMSB transaction causing error | I20: Defect Being Fixed | J20: 5 | K20: 1.25 | L20: 5 | M20: 46147 | N20: NA | O20: NA | P20: NA | Q20: NA | R20: NA | S20: NA | T20: NA | U20: NA | V20: NA | W20: NA | X20: NA | Y20: NA | Z20: NA | AA20: NA | AB20: NA | AC20: NA | AD20: Defect fix still in progress. Added to stretch and started on the last day of the sprint. | AE20: Meets Expectation | AO20: Completed analysis and started dev changes. Working on user warning if a mapping existing for the GL account.
A21: 20 | B21: MSB Accounting | C21: 46134 | D21: 46147 | E21: MSB Accounting 26.06 Sprint 1 Stretch | F21: Karthik | G21: 26753 | H21: MSB ACCT - BKK - "Cancel" button is not enabled while viewing a Transfer and Receipt Entry | I21: Defect Peer Review | J21: 2 | K21: 0.5 | L21: 2 | M21: 46147 | N21: 46147 | O21: Completed | P21: NA | Q21: NA | R21: NA | S21: NA | T21: NA | U21: NA | V21: NA | W21: NA | X21: NA | Y21: NA | Z21: NA | AA21: NA | AB21: Pass | AC21: Pass | AD21: Dev completed, and testing will be completed on next sprint. | AE21: Meets Expectation | AO21: Have completed dev changes and POV

Sheet 26.06 Sprint 1-Defect
A1: S.No | B1: Sprint # | C1: Story/Defect ID | D1: Parent Story | E1: Developer | F1: Issue Type | G1: Issue Description | H1: Priority | I1: Defect Source | J1: Type | K1: Status | L1: Root Cause Category | M1: Comments
A2: 1 | B2: MSB Accounting | C2: SRX28874 | E2: Qadir/ Karthik | F2: Task | G2: MSB ACCT - Variance for second Bank Rec (Thatcher-July-BankB) | H2: Significant | I2: Manual | J2: External | K2: Defect Being Fixed | L2: Project_Management | M2: The customer completed reconciliation with an incorrect ending balance, which is causing a variance in the next month's reconciliation. We have suggested deleting the previous reconciliation and recreate with the correct ending balance. Currently we are waiting for Jeanette's verification on this fix.
A3: 2 | B3: MSB Accounting | C3: SRX28876 | E3: Qadir | F3: Defect | G3: DUR - MSB ACCT - BKK - Kingsport City Schools (129907) - Dobyns-Bennett High School (DOB) | H3: Significant | I3: Manual | J3: External | K3: Defect Being Fixed | L3: Project_Management | M3: Existing issue, Facing a timout issue during large Excel export in the report. Query performance improved. Issue not reproducible locally, so planning to validate in dev. Waiting for PlatOps to restore the latest DB.
A4: 3 | B4: MSB Accounting | C4: 27265 | E4: Client Dev | F4: Defect | G4: MSB ACCT - BKK - [Regression] Upgrade 1099 Print Forms to the new UI look and feel | H4: Minor | I4: Manual | J4: Internal | K4: Defect Fixed | L4: Development | M4: Issue with the new Kaleida UI changes. All changes are worked by client dev. Defect also handleb by same client dev.
A5: 4 | B5: MSB Accounting | C5: 27265 | E5: Client Dev | F5: Defect | G5: MSB ACCT - BKK - [Regression] Bank rec. id is displayed instead of date in Bank Rec. History Report (26.4) | H5: Minor | I5: Manual | J5: Internal | K5: Defect Fixed | L5: Development | M5: Issue with the new Kaleida UI changes. All changes are worked by client dev. Defect also handleb by same client dev.
A6: 5 | B6: MSB Accounting | C6: SRX28888 | E6: Qadir | F6: Defect | G6: MSB ACCT - BKK - Duplicate Adjustment Entry on Bank Rec/Report (Pleasanton) | H6: Significant | I6: Manual | J6: External | K6: Defect Fixed | L6: Project_Management | M6: The customer had a duplicate adjustment entry in bank reconciliation. We were unable to replicate the issue, so we created a new defect to investigate the root cause. We also performed a data fix to resolve the customer's blocker.
A7: 6 | B7: MSB Accounting | C7: 27200 | E7: Rijo | F7: Defect | G7: MSB ACCT - BKK - Cash Transfer does not save the "Notes" after editing | H7: Significant | I7: Manual | J7: External | K7: Defect Fixed | L7: Existing_Issues | M7: Existing issue. We had this in backlog for a long time since it is a low priority issue. The issue was "Submit" button getting disabled while opening popup.
A8: 7 | B8: MSB Accounting | C8: 27326 | E8: Karthik/Rijo | F8: Defect | G8: MSB ACCT - BKK - [Regression] MSB Import Batch does not show the payment items (26.4) | H8: Major | I8: Manual | J8: Internal | K8: Defect Rejected | L8: Enhancements | M8: Defect rejected. It was a set up issue with gateway assignment. User is not supposed to remove assigned schools for a shared batch.
A9: 8 | B9: MSB Accounting | C9: 22751 | E9: Rijo | F9: Defect | G9: MSB ACCT - Integration - Renumber Merge deletes a mapped GL account in ImportFromMSB transaction causing error | H9: Significant | I9: Manual | J9: Internal | K9: Defect Being Fixed | L9: Existing_Issues | M9: Existing issue. When the user change the account number using re-number merge, the mapped gl account in import msb becomes invalid. This is a scenario we haven't considered while designing the mapping.
A10: 9 | B10: MSB Accounting | C10: 26753 | E10: Karthik | F10: Defect | G10: MSB ACCT - BKK - "Cancel" button is not enabled while viewing a Transfer and Receipt Entry | H10: Significant | I10: Manual | J10: Internal | K10: Defect Fixed | L10: Existing_Issues | M10: Existing issue. The cancel button is in disabled state while viewing the transfer and receipt entry.

Sheet 26.04 Sprint 3-Status
A1: S.No | B1: Application Name | C1: Sprint Start Date | D1: Sprint End Date | E1: Sprint | F1: Developer | G1: Story ID/Defect ID | H1: Description | I1: Status | J1: Estimated(sp) | K1: Actual(sp) | L1: Actual Hours Worklog | M1: Dev Start Date | N1: Dev End Date | O1: Unit testing | P1: Peer Tested By | Q1: Peer Tested Comments, if any | R1: Peer Reviewed By | S1: Peer Code Review Comments, if any | T1: PR Number/Link | U1: PR Created Date | V1: PR Approved Date | W1: Onsite Lead Code Review | X1: Onsite Lead Code Review Comments, if any | Y1: Client Code Review | Z1: PR Approved Date2 | AA1: Client Code Review Comments, if any | AB1: Internal PO -POV Comments | AC1: Client PO -POV Comments | AD1: Comments | AE1: Story met clarity expectations? | AF1: 46120 | AG1: 46121 | AH1: 46122 | AI1: 46125 | AJ1: 46126 | AK1: 46127 | AL1: 46128 | AM1: 46129 | AN1: 46132 | AO1: 46133
A2: 1 | B2: MSB Accounting | C2: 46120 | D2: 46133 | E2: MSB Accounting 26.04 Sprint 3 Stretch | F2: Client Dev | G2: 52277 | H2: MSB Onboarding - Sign & Submit | I2: Story Ready For Testing | J2: 2 | K2: 4 | L2: 16 | M2: NA | N2: NA | O2: NA | P2: NA | Q2: NA | R2: NA | S2: NA | T2: NA | U2: NA | V2: NA | W2: NA | X2: NA | Y2: NA | Z2: NA | AA2: NA | AB2: NA | AC2: NA | AD2: Worked by client dev. Only testing effort for our team | AE2: Meets Expectation | AF2: Tested - Intermittent Issues while testing. | AG2: Observed an issue in Authorized Signers : when two contacts (primary and secondary) are configured, the secondary contact is not able to sign the documents getting an popup as "The agreement can no longer be modified" | AH2: James fixed the issue. Testing is in progress. | AI2: 1 scenario pending. Blocker with 2 people signing. | AJ2: Bounceback found. Wiating on client Dev. | AK2: No update on this. | AL2: On hold for Regression | AM2: On hold for Regression | AN2: On hold for Regression | AO2: On hold for Regression
A3: 2 | B3: MSB Accounting | C3: 46120 | D3: 46133 | E3: MSB Accounting 26.04 Sprint 3 Stretch | F3: Rijo | G3: 47478 | H3: MSB ACCT - BKK - Update Bank Deposit History Report to Reflect Changes to Import MSB Batches (26.5) | I3: Story Peer Review | J3: 2 | K3: 1.25 | L3: 5 | M3: 46120 | N3: 46120 | O3: Completed | P3: Karthik | Q3: Pass | R3: Qadir | S3: Pass | T3: NA | U3: NA | V3: NA | W3: NA | X3: NA | Y3: NA | Z3: NA | AA3: NA | AB3: NA | AC3: NA | AD3: Story on Hold. This will be for the next release | AE3: Meets Expectation | AF3: POV With Pramod completed. Posted on channel | AG3: Code Review in Progress. | AI3: Peer review complete. Waiting on CERT Develop status. | AJ3: Story on Hold for Release | AK3: Story on Hold for Release | AL3: Story on Hold for Release | AM3: Story on Hold for Release | AN3: Story on Hold for Release
A4: 3 | B4: MSB Accounting | C4: 46120 | D4: 46133 | E4: MSB Accounting 26.04 Sprint 3 Stretch | F4: Karthik | G4: 24926 | H4: MSB ACCT - BKK - GL Account Maintenance current balances do not display the most recent balances (26.5) | I4: Story Peer Review | J4: 2 | K4: 1 | L4: 4 | M4: 46120 | N4: 46121 | O4: NA | P4: NA | Q4: NA | R4: NA | S4: NA | T4: NA | U4: NA | V4: NA | W4: NA | X4: NA | Y4: NA | Z4: NA | AA4: NA | AB4: NA | AC4: NA | AD4: Story on Hold. This will be for the next release | AE4: Meets Expectation | AF4: Still doing dev testing in DEV environment. | AG4: Qadir To Review. | AI4: Qadir to still review whether the client's timezone should be valid for calculation of account balances since all entry times were earlier made with the server time. Question: How would this change impact 2 users using the application from different timezones when they make different but entries at the same time ? | AJ4: Story on Hold for Release | AK4: Story on Hold for Release | AL4: Story on Hold for Release | AM4: Story on Hold for Release | AN4: Story on Hold for Release
A5: 4 | B5: MSB Accounting | C5: 46120 | D5: 46133 | E5: MSB Accounting 26.04 Sprint 3 Stretch | F5: Karthik | G5: 45225 | H5: MSB ACCT - BKK - Add Warnings and Blockers for Unclosed Years (26.5) | I5: Story Approved | J5: 3 | K5: 1.5 | L5: 6 | M5: 46120 | O5: NA | P5: NA | Q5: NA | R5: NA | S5: NA | T5: NA | U5: NA | V5: NA | W5: NA | X5: NA | Y5: NA | Z5: NA | AA5: NA | AB5: NA | AC5: NA | AD5: Story on Hold. This will be for the next release | AE5: Meets Expectation | AF5: Waiting on jeanette | AG5: POV Comments - Working on fixing conflicts locally | AI5: need to completed a few POV changes. Putting story on hold for regression | AJ5: Story on Hold for Release | AK5: Story on Hold for Release | AL5: Story on Hold for Release | AM5: Story on Hold for Release | AN5: Story on Hold for Release
A6: 5 | B6: MSB Accounting | C6: 46120 | D6: 46133 | E6: MSB Accounting 26.04 Sprint 3 | F6: Qadir | G6: 87509 | H6: MSB Accounting: Merge Develop & UI Changes 26.4 SP 3 | I6: Story Completed | J6: 0 | K6: 1.25 | L6: 5 | M6: 46120 | N6: 46120 | O6: NA | P6: NA | Q6: NA | R6: NA | S6: NA | T6: https://dev.azure.com/heartlandschools/Accounting/_git/MSBAccounting-NewSchoolBooks/pullrequest/48313 | U6: 46121 | V6: 46121 | W6: Done | X6: Pass | Y6: Done | Z6: NA | AA6: Pass | AB6: Pass | AC6: Pass | AD6: This was a task to merge a very big feature branch | AE6: Meets Expectation | AF6: Branch being merged. Lots of files to review. | AG6: Completed. | AH6: - | AI6: - | AJ6: - | AK6: - | AL6: - | AM6: - | AN6: -
A7: 6 | B7: MSB Accounting | C7: 46120 | D7: 46133 | E7: MSB Accounting 26.04 Sprint 3 Stretch | F7: Qadir | G7: 52629 | H7: MSB Onboarding - Remove all old onboarding pages | I7: Story Ready For Testing | J7: 2 | K7: 0.25 | L7: 1 | M7: 46125 | N7: 46125 | O7: NA | P7: NA | Q7: NA | R7: NA | S7: NA | T7: NA | U7: NA | V7: NA | W7: NA | X7: NA | Y7: NA | Z7: NA | AA7: NA | AB7: NA | AC7: NA | AD7: Story on Hold. This will be for the next release | AE7: Meets Expectation | AG7: Ready for POV. | AI7: Qadir to post POV to the channel. | AJ7: Waiting on Client POV | AK7: Approved . PR to be made. | AL7: Will test after priorities | AM7: Will test after priorities | AN7: review whether it can be completed | AO7: On hold for regression
A8: 7 | B8: MSB Accounting | C8: 46120 | D8: 46133 | E8: MSB Accounting 26.04 Sprint 3 | F8: Karthik | G8: SRX28861 | H8: DUR - MSB ACCT - BKK - Clark County School District (CCSD) - 27 Pilot Schools | I8: Defect Fixed | J8: 0 | K8: 1.5 | L8: 6 | M8: 46121 | N8: 46122 | O8: NA | P8: NA | Q8: NA | R8: NA | S8: NA | T8: NA | U8: NA | V8: NA | W8: NA | X8: NA | Y8: NA | Z8: NA | AA8: NA | AB8: NA | AC8: NA | AD8: This was a data fix for wrong entry by users. | AE8: Meets Expectation | AG8: Data request made. Still waiting on Data. | AH8: Completed data fix query and shared for Qadir's review on the channel. | AI8: Data fix completed on PROD. Waiting on Confirmation from support. | AJ8: Closed | AK8: - | AL8: - | AM8: - | AN8: -
A9: 8 | B9: MSB Accounting | C9: 46120 | D9: 46133 | E9: MSB Accounting 26.04 Sprint 3 Stretch | F9: Rijo | G9: 25390 | H9: MSB ACCT - BKK - Warning icon not displaying for overdrawn line items in a manual check while editing an existing record (26.5) | I9: Defect Verified | J9: 2 | K9: 1.5 | L9: 6 | M9: 46121 | N9: NA | O9: NA | P9: NA | Q9: NA | R9: NA | S9: NA | T9: NA | U9: NA | V9: NA | W9: NA | X9: NA | Y9: NA | Z9: NA | AA9: NA | AB9: NA | AC9: NA | AD9: Story on Hold. This will be for the next release | AE9: Meets Expectation | AG9: Made the fix. Dev testing in progress. | AI9: No progress. On hold for regression | AJ9: Story on Hold for Release | AK9: Story on Hold for Release | AL9: Story on Hold for Release | AM9: Story on Hold for Release | AN9: Story on Hold for Release
A10: 9 | B10: MSB Accounting | C10: 46120 | D10: 46133 | E10: MSB Accounting 26.04 Sprint 3 | F10: Rijo | G10: 52715 | H10: MSB ACCT - BKK - Regression - Entry Menu (Not Import MSB Batches) | I10: Story Being Tested | J10: 2 | K10: 2 | L10: 8 | M10: NA | N10: NA | O10: NA | P10: NA | Q10: NA | R10: NA | S10: NA | T10: NA | U10: NA | V10: NA | W10: NA | X10: NA | Y10: NA | Z10: NA | AA10: NA | AB10: NA | AC10: NA | AE10: Meets Expectation | AH10: Completed 6 entry menu. Working on 7th. All 6 are failed. Will discuss with Pramod. | AI10: 6 entry screens failed. | AJ10: Holding off until blockers | AK10: Holding off until blockers | AL10: Holding off until blockers | AM10: Holding off until blockers | AN10: Holding off until blockers | AO10: Holding off until blockers
A11: 10 | B11: MSB Accounting | C11: 46120 | D11: 46133 | E11: MSB Accounting 26.04 Sprint 3 | F11: Karthik | G11: 52714 | H11: MSB ACCT - BKK - Regression - Maintenance Menu | I11: Story Completed | J11: 1 | K11: 1 | L11: 4 | M11: NA | N11: NA | O11: NA | P11: NA | Q11: NA | R11: NA | S11: NA | T11: NA | U11: NA | V11: NA | W11: NA | X11: NA | Y11: NA | Z11: NA | AA11: NA | AB11: NA | AC11: NA | AE11: Meets Expectation | AH11: Found few issues. Got 1 blocker, discussed with Pramod. Item failed. | AI11: issue fixed on DEV | AJ11: Holding off until blockers | AK11: Holding off until blockers | AL11: Holding off until blockers | AM11: Holding off until blockers | AN11: Holding off until blockers | AO11: Holding off until blockers
A12: 11 | B12: MSB Accounting | C12: 46120 | D12: 46133 | E12: MSB Accounting 26.04 Sprint 3 | F12: Sowjanya | G12: 52724 | H12: MSB ACCT - BKK - Regression - 26.3 & 26.4 Stories and Defects | I12: Story Being Tested | J12: 8 | K12: 2.25 | L12: 9 | M12: NA | N12: NA | O12: NA | P12: NA | Q12: NA | R12: NA | S12: NA | T12: NA | U12: NA | V12: NA | W12: NA | X12: NA | Y12: NA | Z12: NA | AA12: NA | AB12: NA | AC12: NA | AE12: Meets Expectation | AH12: Found issue with Manual check entry. 2 items related to reports are passed. | AI12: 3 Stories/ defects closed. 2 are blocked because of UI issues. and 4 more to go. | AJ12: Holding off until blockers | AK12: Holding off until blockers | AL12: Holding off until blockers | AM12: Started to work on the pending defects | AN12: Just started | AO12: Holding off until blockers
A13: 12 | B13: MSB Accounting | C13: 46120 | D13: 46133 | E13: MSB Accounting 26.04 Sprint 3 | F13: Karthik / Rijo | G13: 52716 | H13: MSB ACCT - BKK - Regression - Reports Menu | I13: Story Completed | J13: 5 | K13: 4.5 | L13: 18 | M13: NA | N13: NA | O13: NA | P13: NA | Q13: NA | R13: NA | S13: NA | T13: NA | U13: NA | V13: NA | W13: NA | X13: NA | Y13: NA | Z13: NA | AA13: NA | AB13: NA | AC13: NA | AE13: Meets Expectation | AI13: Karthik - Completed GL / Vendor/ Banking reports Rijo - Completed Financial / PO and PY in progress. | AJ13: Rijo - PY reports - 3 pending . Currently blocked because of MSB Login | AK13: No progress | AL13: Closed. RIjo - PY Reports Completed. | AM13: - | AN13: - | AO13: -
A14: 13 | B14: MSB Accounting | C14: 46120 | D14: 46133 | E14: MSB Accounting 26.04 Sprint 3 | F14: Qadir | G14: 52817 | H14: MSB ACCT - BKK - Rename Menu Items | I14: Story Completed | J14: 2 | K14: 5.62 | L14: 22.5 | M14: 46121 | N14: 46127 | O14: Completed | P14: Karthik | Q14: Pass | R14: Karthik | S14: Pass | T14: https://dev.azure.com/heartlandschools/Accounting/_git/MSBAccounting-NewSchoolBooks/pullrequest/48449 | U14: 46128 | V14: 46128 | W14: Done | X14: Pass | Y14: Done | Z14: NA | AA14: Pass | AB14: Pass | AC14: Pass | AE14: Meets Expectation | AI14: Fixing hard Coded Page headers in the code | AJ14: 70% of headers. | AK14: Dev Testing in Progress | AL14: Waiting on Peer Review | AM14: Ready for Testing | AO14: Almost completed.
A15: 14 | B15: MSB Accounting | C15: 46120 | D15: 46133 | E15: MSB Accounting 26.04 Sprint 3 | F15: Client Dev | G15: 27165 | H15: MSB ACCT - BKK - [Regression] Fix the "Add Item" pop-up window positioning behind the parent window issue | I15: Defect Fixed | J15: 0 | K15: 0.25 | L15: 1 | M15: NA | N15: NA | O15: NA | P15: NA | Q15: NA | R15: NA | S15: NA | T15: NA | U15: NA | V15: NA | W15: NA | X15: NA | Y15: NA | Z15: NA | AA15: NA | AB15: NA | AC15: NA | AE15: Meets Expectation | AJ15: Bounceback. - Cash Transfer | AK15: Waiting on Bounceback | AM15: fixed
A16: 15 | B16: MSB Accounting | C16: 46120 | D16: 46133 | E16: MSB Accounting 26.04 Sprint 3 | F16: Client Dev | G16: 27187 | H16: MSB ACCT - BKK - [Regression] Fix the error popup while searching with "ALL" criteria in GL Account Maintenance | I16: Defect Fixed | J16: 0 | K16: 0.375 | L16: 1.5 | M16: NA | N16: NA | O16: NA | P16: NA | Q16: NA | R16: NA | S16: NA | T16: NA | U16: NA | V16: NA | W16: NA | X16: NA | Y16: NA | Z16: NA | AA16: NA | AB16: NA | AC16: NA | AE16: Meets Expectation | AJ16: Checked in DEV. Fixed in DEV | AK16: Fixed
A17: 16 | B17: MSB Accounting | C17: 46120 | D17: 46133 | E17: MSB Accounting 26.04 Sprint 3 | F17: Client Dev | G17: 27168 | H17: MSB ACCT - BKK - [Regression] Fix the scroll issues for multiple UI pop-up windows | I17: Defect Fixed | J17: 3 | K17: 0.43 | L17: 1.75 | M17: NA | N17: NA | O17: NA | P17: NA | Q17: NA | R17: NA | S17: NA | T17: NA | U17: NA | V17: NA | W17: NA | X17: NA | Y17: NA | Z17: NA | AA17: NA | AB17: NA | AC17: NA | AE17: Meets Expectation | AJ17: In progress. | AK17: Fixed
A18: 17 | B18: MSB Accounting | C18: 46120 | D18: 46133 | E18: MSB Accounting 26.04 Sprint 3 | F18: Client Dev | G18: 27179 | H18: MSB ACCT - BKK - [Regression] Fix "Edit" action item icon orange background color on hover for all UI pages | I18: Defect Fixed | J18: 0 | K18: 0.81 | L18: 3.25 | M18: NA | N18: NA | O18: NA | P18: NA | Q18: NA | R18: NA | S18: NA | T18: NA | U18: NA | V18: NA | W18: NA | X18: NA | Y18: NA | Z18: NA | AA18: NA | AB18: NA | AC18: NA | AE18: Meets Expectation | AJ18: Bounceback - Receipt Page and Void Entry | AK18: Waiting on Bounceback | AL18: Waiting on bounceBack. Still with James | AM18: Fixed
A19: 18 | B19: MSB Accounting | C19: 46120 | D19: 46133 | E19: MSB Accounting 26.04 Sprint 3 | F19: Client Dev | G19: 27169 | H19: MSB ACCT - BKK - [Regression] Fix action item icon margins in the table cells | I19: Defect Fixed | J19: 3 | K19: 0.81 | L19: 3.25 | M19: NA | N19: NA | O19: NA | P19: NA | Q19: NA | R19: NA | S19: NA | T19: NA | U19: NA | V19: NA | W19: NA | X19: NA | Y19: NA | Z19: NA | AA19: NA | AB19: NA | AC19: NA | AE19: Meets Expectation | AJ19: Bounceback For Purchase Orders. | AL19: Fixed
A20: 19 | B20: MSB Accounting | C20: 46120 | D20: 46133 | E20: MSB Accounting 26.04 Sprint 3 | F20: Client Dev | G20: 27184 | H20: MSB ACCT - BKK - [Regression] Fix the white background on action Item while mouse hover in Import MSB Batches UI | I20: Defect Fixed | J20: 0 | K20: 0.31 | L20: 1.25 | M20: NA | N20: NA | O20: NA | P20: NA | Q20: NA | R20: NA | S20: NA | T20: NA | U20: NA | V20: NA | W20: NA | X20: NA | Y20: NA | Z20: NA | AA20: NA | AB20: NA | AC20: NA | AE20: Meets Expectation | AJ20: Verirfied in DEV. Fixed in DEV | AK20: Fixed
A21: 20 | B21: MSB Accounting | C21: 46120 | D21: 46133 | E21: MSB Accounting 26.04 Sprint 3 | F21: Rijo | G21: 52719 | H21: MSB ACCT - BKK - Regression - Administration Menu | I21: Story Completed | J21: 2 | K21: 1.5 | L21: 6 | M21: NA | N21: NA | O21: NA | P21: NA | Q21: NA | R21: NA | S21: NA | T21: NA | U21: NA | V21: NA | W21: NA | X21: NA | Y21: NA | Z21: NA | AA21: NA | AB21: NA | AC21: NA | AE21: Meets Expectation | AK21: No progress today | AL21: Almost Completed Testing. Found issues with all 4 pages. School Groups Page isnt completed with the updated design Password Validation | AM21: Issues with Admin Menu Blocked. | AN21: On Hold for defect Blockers | AO21: On Hold for defect Blockers
A22: 21 | B22: MSB Accounting | C22: 46120 | D22: 46133 | E22: MSB Accounting 26.04 Sprint 3 | F22: Client Dev | G22: 27178 | H22: MSB ACCT - BKK - [Regression] Fix Transfer History Report multiple issues | I22: Defect Fixed | J22: 3 | K22: 0.31 | L22: 1.25 | M22: NA | N22: NA | O22: NA | P22: NA | Q22: NA | R22: NA | S22: NA | T22: NA | U22: NA | V22: NA | W22: NA | X22: NA | Y22: NA | Z22: NA | AA22: NA | AB22: NA | AC22: NA | AE22: Meets Expectation | AK22: Bounceback created | AL22: Not working on this issue right now. | AM22: Fixed
A23: 22 | B23: MSB Accounting | C23: 46120 | D23: 46133 | E23: MSB Accounting 26.04 Sprint 3 | F23: Client Dev | G23: 27185 | H23: MSB ACCT - BKK - [Regression] Fix the Print option dialog positioning | I23: Defect Fixed | J23: 0 | K23: 0.31 | L23: 1.25 | M23: NA | N23: NA | O23: NA | P23: NA | Q23: NA | R23: NA | S23: NA | T23: NA | U23: NA | V23: NA | W23: NA | X23: NA | Y23: NA | Z23: NA | AA23: NA | AB23: NA | AC23: NA | AE23: Meets Expectation | AK23: Bounceback created | AL23: Waiting on dev changes | AM23: Fixed
A24: 23 | B24: MSB Accounting | C24: 46120 | D24: 46133 | E24: MSB Accounting 26.04 Sprint 3 | F24: Client Dev | G24: 27173 | H24: MSB ACCT - BKK - [Regression] Fix the session timeout even after "Stay Connected" is clicked issue | I24: Defect Fixed | J24: 3 | K24: 0.31 | L24: 1.25 | M24: NA | N24: NA | O24: NA | P24: NA | Q24: NA | R24: NA | S24: NA | T24: NA | U24: NA | V24: NA | W24: NA | X24: NA | Y24: NA | Z24: NA | AA24: NA | AB24: NA | AC24: NA | AE24: Meets Expectation | AK24: Need to verify | AM24: Fixed
A25: 24 | B25: MSB Accounting | C25: 46120 | D25: 46133 | E25: MSB Accounting 26.04 Sprint 3 | F25: Client Dev | G25: 27198 | H25: MSB ACCT - BKK - [Regression] Fix all reports search filter section - floating checkboxes on page header | I25: Defect Fixed | J25: 0 | K25: 0.37 | L25: 1.5 | M25: NA | N25: NA | O25: NA | P25: NA | Q25: NA | R25: NA | S25: NA | T25: NA | U25: NA | V25: NA | W25: NA | X25: NA | Y25: NA | Z25: NA | AA25: NA | AB25: NA | AC25: NA | AE25: Meets Expectation | AK25: Fixed. | AM25: Fixed
A26: 25 | B26: MSB Accounting | C26: 46120 | D26: 46133 | E26: MSB Accounting 26.04 Sprint 3 | F26: Client Dev | G26: 27196 | H26: MSB ACCT - BKK - [Regression] Fix School Settings page - floating checkboxes on page header | I26: Defect Fixed | J26: 1 | K26: 0.25 | L26: 1 | M26: NA | N26: NA | O26: NA | P26: NA | Q26: NA | R26: NA | S26: NA | T26: NA | U26: NA | V26: NA | W26: NA | X26: NA | Y26: NA | Z26: NA | AA26: NA | AB26: NA | AC26: NA | AE26: Meets Expectation | AM26: Fixed
A27: 26 | B27: MSB Accounting | C27: 46120 | D27: 46133 | E27: MSB Accounting 26.04 Sprint 3 | F27: Client Dev | G27: 27186 | H27: MSB ACCT - BKK - [Regression] Fix the issue with form position while cancel and reopen in Vendor maintenance UI | I27: Defect Fixed | J27: 0 | K27: 0.31 | L27: 1.25 | M27: NA | N27: NA | O27: NA | P27: NA | Q27: NA | R27: NA | S27: NA | T27: NA | U27: NA | V27: NA | W27: NA | X27: NA | Y27: NA | Z27: NA | AA27: NA | AB27: NA | AC27: NA | AE27: Meets Expectation | AM27: Fixed
A28: 27 | B28: MSB Accounting | C28: 46120 | D28: 46133 | E28: MSB Accounting 26.04 Sprint 3 | F28: Qadir / Rijo | G28: SRX28868 | H28: MSB ACCT - BKK - PO Backorder not saving (Glendale) | I28: Defect Fixed | J28: 0 | K28: 1.12 | L28: 4.5 | M28: NA | N28: NA | O28: NA | P28: NA | Q28: NA | R28: NA | S28: NA | T28: NA | U28: NA | V28: NA | W28: NA | X28: NA | Y28: NA | Z28: NA | AA28: NA | AB28: NA | AC28: NA | AE28: Meets Expectation | AL28: investigated and asked Pramod to speak to Nadia. | AM28: Created a Defect | AN28: Story created on internal defect found. Waiting on customer feedback on the backorder. | AO28: Story created out of this Escalation. Customer not blocked.
A29: 28 | B29: MSB Accounting | C29: 46120 | D29: 46133 | E29: MSB Accounting 26.04 Sprint 3 | F29: Qadir | G29: SRX28874 | H29: MSB ACCT - Variance for second Bank Rec (Thatcher-July-BankB) | I29: Defect Being Fixed | J29: 0 | K29: 2.25 | L29: 9 | M29: NA | N29: NA | O29: NA | P29: NA | Q29: NA | R29: NA | S29: NA | T29: NA | U29: NA | V29: NA | W29: NA | X29: NA | Y29: NA | Z29: NA | AA29: NA | AB29: NA | AC29: NA | AE29: Meets Expectation | AL29: Gotten the data working on the analysis to see why the accounts are out of balance. | AM29: Analysis in progress. | AN29: Waiting on PROD DB. | AO29: Will investigate afer getting DB
A30: 29 | B30: MSB Accounting | C30: 46120 | D30: 46133 | E30: MSB Accounting 26.04 Sprint 3 | F30: Karthik | G30: 27183 | H30: MSB ACCT - BKK - [Regression] Fix CSV export data mismatch in Transfer History Report | I30: Defect Fixed | J30: 0 | K30: 3 | L30: 12 | M30: 46128 | N30: 46132 | O30: Completed | P30: Rijo | Q30: Pass | R30: Qadir | S30: Pass | T30: https://dev.azure.com/heartlandschools/Accounting/_git/MSBAccounting-NewSchoolBooks/pullrequest/48518 | U30: 46132 | V30: 46132 | W30: Done | X30: Pass | Y30: Done | Z30: NA | AA30: Pass | AB30: Pass | AC30: Pass | AE30: Meets Expectation | AL30: Started working on it. Unable to replicate locally. | AM30: Fix made. Able to replicate issue. | AN30: Completed POV with Pramod. Peer review pending | AO30: Fixed
A31: 30 | B31: MSB Accounting | C31: 46120 | D31: 46133 | E31: MSB Accounting 26.04 Sprint 3 | F31: Client Dev | G31: 27164 | H31: MSB ACCT - BKK - [Regression] Fix the action menu remains visible in the Entry UIs issue | I31: Defect Fixed | J31: 3 | K31: 0.43 | L31: 1.75 | M31: NA | N31: NA | O31: NA | P31: NA | Q31: NA | R31: NA | S31: NA | T31: NA | U31: NA | V31: NA | W31: NA | X31: NA | Y31: NA | Z31: NA | AA31: NA | AB31: NA | AC31: NA | AE31: Meets Expectation | AM31: Fixed
A32: 31 | B32: MSB Accounting | C32: 46120 | D32: 46133 | E32: MSB Accounting 26.04 Sprint 3 | F32: Client Dev | G32: 27175 | H32: MSB ACCT - BKK - [Regression] Fix the district selector list box in Manage Providers page | I32: Defect Fixed | J32: 1 | K32: 0.31 | L32: 1.25 | M32: NA | N32: NA | O32: NA | P32: NA | Q32: NA | R32: NA | S32: NA | T32: NA | U32: NA | V32: NA | W32: NA | X32: NA | Y32: NA | Z32: NA | AA32: NA | AB32: NA | AC32: NA | AE32: Meets Expectation | AM32: Fixed
A33: 32 | B33: MSB Accounting | C33: 46120 | D33: 46133 | E33: MSB Accounting 26.04 Sprint 3 | F33: Client Dev | G33: 27210 | H33: MSB ACCT - BKK - [Regression] Fix the PO "Add Item" not showing Back Order, Cancel Save & Continue, Save & Exit buttons | I33: Defect Fixed | J33: 3 | K33: 0.37 | L33: 1.5 | M33: NA | N33: NA | O33: NA | P33: NA | Q33: NA | R33: NA | S33: NA | T33: NA | U33: NA | V33: NA | W33: NA | X33: NA | Y33: NA | Z33: NA | AA33: NA | AB33: NA | AC33: NA | AE33: Meets Expectation | AM33: Fixed
A34: 33 | B34: MSB Accounting | C34: 46120 | D34: 46133 | E34: MSB Accounting 26.04 Sprint 3 | F34: Rijo | G34: 52912 | H34: MSB ACCT - BKK - Upgrade Purchase Order Entry Page and School Settings page with Shipping address validations | I34: Story Peer Review | J34: 0 | K34: 1.37 | L34: 5.5 | M34: 46129 | N34: 46133 | O34: NA | P34: NA | Q34: NA | R34: NA | S34: NA | T34: NA | U34: NA | V34: NA | W34: NA | X34: NA | Y34: NA | Z34: NA | AA34: NA | AB34: NA | AC34: NA | AD34: Added to the sprint on 2nd last day. Dev completed and waiting for peer review. | AE34: Meets Expectation | AM34: Started working on the validations. UI Changes pending | AN34: Not made much progress. | AO34: Internal POV completed. Waiting on jeanette
A35: 34 | B35: MSB Accounting | C35: 46120 | D35: 46133 | E35: MSB Accounting 26.04 Sprint 3 | F35: Rijo | G35: 52718 | H35: MSB ACCT - BKK - Regression - Management Menu | I35: Story Completed | J35: 2 | K35: 1 | L35: 4 | M35: NA | N35: NA | O35: NA | P35: NA | Q35: NA | R35: NA | S35: NA | T35: NA | U35: NA | V35: NA | W35: NA | X35: NA | Y35: NA | Z35: NA | AA35: NA | AB35: NA | AC35: NA | AE35: Meets Expectation | AM35: Completed 1 item and failed 2. | AO35: Blockers
A36: 35 | B36: MSB Accounting | C36: 46120 | D36: 46133 | E36: MSB Accounting 26.04 Sprint 3 | F36: Qadir | G36: SRX28876 | H36: DUR - MSB ACCT - BKK - Kingsport City Schools (129907) - Dobyns-Bennett High School (DOB) | I36: Story being tested | J36: 0 | K36: 1.5 | L36: 6 | M36: NA | N36: NA | O36: NA | P36: NA | Q36: NA | R36: NA | S36: NA | T36: NA | U36: NA | V36: NA | W36: NA | X36: NA | Y36: NA | Z36: NA | AA36: NA | AB36: NA | AC36: NA | AE36: Meets Expectation | AN36: Worked on performance fixes for the Report. Still need to try locally to replicate the timeout. | AO36: Still testing this out.
A37: 36 | B37: MSB Accounting | C37: 46120 | D37: 46133 | E37: MSB Accounting 26.04 Sprint 3 | F37: Client Dev | G37: 27165 | H37: MSB ACCT - BKK - [Regression] Normalize the Page heading color to match the new color code | I37: Defect Fixed | J37: 0 | K37: 0.31 | L37: 1.25 | M37: NA | N37: NA | O37: NA | P37: NA | Q37: NA | R37: NA | S37: NA | T37: NA | U37: NA | V37: NA | W37: NA | X37: NA | Y37: NA | Z37: NA | AA37: NA | AB37: NA | AC37: NA | AE37: Meets Expectation | AN37: Fixed
A38: 37 | B38: MSB Accounting | C38: 46120 | D38: 46133 | E38: MSB Accounting 26.04 Sprint 3 | F38: Client Dev | G38: 27230 | H38: MSB ACCT - BKK - [Regression] Fix the Table header color and irregular cell height | I38: Defect Fixed | J38: 0 | K38: 0.31 | L38: 1.25 | M38: NA | N38: NA | O38: NA | P38: NA | Q38: NA | R38: NA | S38: NA | T38: NA | U38: NA | V38: NA | W38: NA | X38: NA | Y38: NA | Z38: NA | AA38: NA | AB38: NA | AC38: NA | AE38: Meets Expectation | AN38: Fixed
A39: 38 | B39: MSB Accounting | C39: 46120 | D39: 46133 | E39: MSB Accounting 26.04 Sprint 3 | F39: Client Dev | G39: 27233 | H39: MSB ACCT - BKK - [Regression] Fix the PO-Type column - not scrolling horizontally | I39: Defect Fixed | J39: 0 | K39: 0.5 | L39: 2 | M39: NA | N39: NA | O39: NA | P39: NA | Q39: NA | R39: NA | S39: NA | T39: NA | U39: NA | V39: NA | W39: NA | X39: NA | Y39: NA | Z39: NA | AA39: NA | AB39: NA | AC39: NA | AE39: Meets Expectation | AN39: Fixed
A40: 39 | B40: MSB Accounting | C40: 46120 | D40: 46133 | E40: MSB Accounting 26.04 Sprint 3 | F40: Client Dev | G40: 27232 | H40: MSB ACCT - BKK - [Regression] Fix the text field alignments in Get MSB Batch Payments page when different display scaling | I40: Defect Being Fixed | J40: 1 | K40: 0.37 | L40: 1.5 | M40: NA | N40: NA | O40: NA | P40: NA | Q40: NA | R40: NA | S40: NA | T40: NA | U40: NA | V40: NA | W40: NA | X40: NA | Y40: NA | Z40: NA | AA40: NA | AB40: NA | AC40: NA | AE40: Meets Expectation | AN40: Created a bounce on Get Msb batch Gateway box misalignment | AO40: Waiting on bounceback changes.
A41: 40 | B41: MSB Accounting | C41: 46120 | D41: 46133 | E41: MSB Accounting 26.04 Sprint 3 | F41: Rijo | G41: SRX28879 | H41: MSB ACCT - Missing Batches in the UI | I41: Defect Fixed | J41: 0 | K41: 2.25 | L41: 9 | M41: NA | N41: NA | O41: NA | P41: NA | Q41: NA | R41: NA | S41: NA | T41: NA | U41: NA | V41: NA | W41: NA | X41: NA | Y41: NA | Z41: NA | AA41: NA | AB41: NA | AC41: NA | AD41: The escalation was to figure out root cause for missing batches. No code changes and PR. | AE41: Meets Expectation | AN41: Invesitgating this. Waiting on PROD DB.
A42: 41 | B42: MSB Accounting | C42: 46120 | D42: 46133 | E42: MSB Accounting 26.04 Sprint 3 | F42: Client Dev | G42: 27253 | H42: MSB ACCT - BKK - [Regression] Fix the flyout message in 1099 Reporting - Import Data | I42: Defect Fixed | J42: 1 | K42: 0.5 | L42: 2 | M42: NA | N42: NA | O42: NA | P42: NA | Q42: NA | R42: NA | S42: NA | T42: NA | U42: NA | V42: NA | W42: NA | X42: NA | Y42: NA | Z42: NA | AA42: NA | AB42: NA | AC42: NA | AE42: Meets Expectation | AO42: Fixed

Sheet 26.04 Sprint 3-Defect
A1: S.No | B1: Sprint # | C1: Story/Defect ID | D1: Parent Story | E1: Developer | F1: Issue Type | G1: Issue Description | H1: Priority | I1: Defect Source | J1: Type | K1: Status | L1: Root Cause Category | M1: Comments
A2: 1 | B2: MSB Accounting | C2: 24926 | E2: Karthik | F2: Defect | G2: MSB ACCT - BKK - GL Account Maintenance current balances do not display the most recent balances (26.5) | H2: Significant | I2: Manual | J2: Internal | K2: Defect Being Fixed | L2: Existing_Issues | M2: Existing issue, This issue occured in time zones other than the central time zone because the GL account maintenance current balance was calculated using the server's current date and time. As a result, entries from other time zones after that time were not included. The issue has been fixed by using the client's time zone for balance calculation. Dev testing in progress.
A3: 2 | B3: MSB Accounting | C3: SRX28861 | E3: Karthik | F3: Task | G3: DUR - MSB ACCT - BKK - Clark County School District (CCSD) - 27 Pilot Schools | H3: Significant | I3: Manual | J3: External | K3: Defect Fixed | L3: Project_Management | M3: This was a data fix for wrong entry by users.
A4: 3 | B4: MSB Accounting | C4: 25390 | E4: Rijo | F4: Defect | G4: MSB ACCT - BKK - Warning icon not displaying for overdrawn line items in a manual check while editing an existing record (26.5) | H4: Significant | I4: Manual | J4: Internal | K4: Defect Verified | L4: Project_Management | M4: Existing issue. We had this in backlog for a long time since it is a low priority issue.
A5: 4 | B5: MSB Accounting | C5: 27165 | E5: Client Dev | F5: Defect | G5: MSB ACCT - BKK - [Regression] Fix the "Add Item" pop-up window positioning behind the parent window issue | H5: Major | I5: Manual | J5: Internal | K5: Defect Fixed | L5: Development | M5: Issue with the new Kaleida UI changes. All changes are worked by client dev. Defect also handleb by same client dev.
A6: 5 | B6: MSB Accounting | C6: 27187 | E6: Client Dev | F6: Defect | G6: MSB ACCT - BKK - [Regression] Fix the error popup while searching with "ALL" criteria in GL Account Maintenance | H6: Minor | I6: Manual | J6: Internal | K6: Defect Fixed | L6: Development | M6: Issue with the new Kaleida UI changes. All changes are worked by client dev. Defect also handleb by same client dev.
A7: 6 | B7: MSB Accounting | C7: 27168 | E7: Client Dev | F7: Defect | G7: MSB ACCT - BKK - [Regression] Fix the scroll issues for multiple UI pop-up windows | H7: Minor | I7: Manual | J7: Internal | K7: Defect Fixed | L7: Development | M7: Issue with the new Kaleida UI changes. All changes are worked by client dev. Defect also handleb by same client dev.
A8: 7 | B8: MSB Accounting | C8: 27179 | E8: Client Dev | F8: Defect | G8: MSB ACCT - BKK - [Regression] Fix "Edit" action item icon orange background color on hover for all UI pages | H8: Minor | I8: Manual | J8: Internal | K8: Defect Fixed | L8: Development | M8: Issue with the new Kaleida UI changes. All changes are worked by client dev. Defect also handleb by same client dev.
A9: 8 | B9: MSB Accounting | C9: 27169 | E9: Client Dev | F9: Defect | G9: MSB ACCT - BKK - [Regression] Fix action item icon margins in the table cells | H9: Minor | I9: Manual | J9: Internal | K9: Defect Fixed | L9: Development | M9: Issue with the new Kaleida UI changes. All changes are worked by client dev. Defect also handleb by same client dev.
A10: 9 | B10: MSB Accounting | C10: 27184 | E10: Client Dev | F10: Defect | G10: MSB ACCT - BKK - [Regression] Fix the white background on action Item while mouse hover in Import MSB Batches UI | H10: Minor | I10: Manual | J10: Internal | K10: Defect Fixed | L10: Development | M10: Issue with the new Kaleida UI changes. All changes are worked by client dev. Defect also handleb by same client dev.
A11: 10 | B11: MSB Accounting | C11: 27178 | E11: Client Dev | F11: Defect | G11: MSB ACCT - BKK - [Regression] Fix Transfer History Report multiple issues | H11: Major | I11: Manual | J11: Internal | K11: Defect Fixed | L11: Development | M11: Issue with the new Kaleida UI changes. All changes are worked by client dev. Defect also handleb by same client dev.
A12: 11 | B12: MSB Accounting | C12: 27185 | E12: Client Dev | F12: Defect | G12: MSB ACCT - BKK - [Regression] Fix the Print option dialog positioning | H12: Minor | I12: Manual | J12: Internal | K12: Defect Fixed | L12: Development | M12: Issue with the new Kaleida UI changes. All changes are worked by client dev. Defect also handleb by same client dev.
A13: 12 | B13: MSB Accounting | C13: 27173 | E13: Client Dev | F13: Defect | G13: MSB ACCT - BKK - [Regression] Fix the session timeout even after "Stay Connected" is clicked issue | H13: Significant | I13: Manual | J13: Internal | K13: Defect Fixed | L13: Development | M13: Issue with the new Kaleida UI changes. All changes are worked by client dev. Defect also handleb by same client dev.
A14: 13 | B14: MSB Accounting | C14: 27198 | E14: Client Dev | F14: Defect | G14: MSB ACCT - BKK - [Regression] Fix all reports search filter section - floating checkboxes on page header | H14: Minor | I14: Manual | J14: Internal | K14: Defect Fixed | L14: Development | M14: Issue with the new Kaleida UI changes. All changes are worked by client dev. Defect also handleb by same client dev.
A15: 14 | B15: MSB Accounting | C15: 27196 | E15: Client Dev | F15: Defect | G15: MSB ACCT - BKK - [Regression] Fix School Settings page - floating checkboxes on page header | H15: Minor | I15: Manual | J15: Internal | K15: Defect Fixed | L15: Development | M15: Issue with the new Kaleida UI changes. All changes are worked by client dev. Defect also handleb by same client dev.
B16: MSB Accounting | C16: 27186 | E16: Client Dev | F16: Defect | G16: MSB ACCT - BKK - [Regression] Fix the issue with form position while cancel and reopen in Vendor maintenance UI | H16: Minor | I16: Manual | J16: Internal | K16: Defect Fixed | L16: Development | M16: Issue with the new Kaleida UI changes. All changes are worked by client dev. Defect also handleb by same client dev.
A17: 15 | B17: MSB Accounting | C17: SRX28868 | E17: Qadir / Rijo | F17: Defect | G17: MSB ACCT - BKK - PO Backorder not saving (Glendale) | H17: Significant | I17: Manual | J17: External | K17: Defect Being Fixed | L17: Project_Management | M17: Back order had no issues. User was not aware the functionality. And other issue with PO zip code validation was an existing issue, created a seperate story to handle it.
A18: 16 | B18: MSB Accounting | C18: SRX28874 | E18: Qadir | F18: Defect | G18: MSB ACCT - Variance for second Bank Rec (Thatcher-July-BankB) | H18: Significant | I18: Manual | J18: External | K18: Defect Being Fixed | L18: Project_Management | M18: Root cause for this issue is still being identified. Client has made a substantial amount of mistakes follwoing the flow of the application.
A19: 17 | B19: MSB Accounting | C19: 27183 | E19: Karthik | F19: Defect | G19: MSB ACCT - BKK - [Regression] Fix CSV export data mismatch in Transfer History Report | H19: Significant | I19: Manual | J19: Internal | K19: Defect Fixed | L19: Development | M19: Existing issue, the header row of the first entry in a standard transfer was not printed in the CSV when the last entry of a cash transfer and the first entry of a standard transfer had the same reference number. The fix has been implemented in the export CSV function by updating the entry header visibility logic.
A20: 18 | B20: MSB Accounting | C20: 27164 | E20: Client Dev | F20: Defect | G20: MSB ACCT - BKK - [Regression] Fix the action menu remains visible in the Entry UIs issue | H20: Minor | I20: Manual | J20: Internal | K20: Defect Fixed | L20: Development | M20: Issue with the new Kaleida UI changes. All changes are worked by client dev. Defect also handleb by same client dev.
A21: 19 | B21: MSB Accounting | C21: 27175 | E21: Client Dev | F21: Defect | G21: MSB ACCT - BKK - [Regression] Fix the district selector list box in Manage Providers page | H21: Significant | I21: Manual | J21: Internal | K21: Defect Fixed | L21: Development | M21: Issue with the new Kaleida UI changes. All changes are worked by client dev. Defect also handleb by same client dev.
A22: 20 | B22: MSB Accounting | C22: 27210 | E22: Client Dev | F22: Defect | G22: MSB ACCT - BKK - [Regression] Fix the PO "Add Item" not showing Back Order, Cancel Save & Continue, Save & Exit buttons | H22: Major | I22: Manual | J22: Internal | K22: Defect Fixed | L22: Development | M22: Issue with the new Kaleida UI changes. All changes are worked by client dev. Defect also handleb by same client dev.
A23: 21 | B23: MSB Accounting | C23: 27165 | E23: Client Dev | F23: Defect | G23: MSB ACCT - BKK - [Regression] Normalize the Page heading color to match the new color code | H23: Minor | I23: Manual | J23: Internal | K23: Defect Fixed | L23: Development | M23: Issue with the new Kaleida UI changes. All changes are worked by client dev. Defect also handleb by same client dev.
A24: 22 | B24: MSB Accounting | C24: 27230 | E24: Client Dev | F24: Defect | G24: MSB ACCT - BKK - [Regression] Fix the Table header color and irregular cell height | H24: Minor | I24: Manual | J24: Internal | K24: Defect Fixed | L24: Development | M24: Issue with the new Kaleida UI changes. All changes are worked by client dev. Defect also handleb by same client dev.
A25: 23 | B25: MSB Accounting | C25: 27233 | E25: Client Dev | F25: Defect | G25: MSB ACCT - BKK - [Regression] Fix the PO-Type column - not scrolling horizontally | H25: Significant | I25: Manual | J25: Internal | K25: Defect Fixed | L25: Development | M25: Issue with the new Kaleida UI changes. All changes are worked by client dev. Defect also handleb by same client dev.
A26: 24 | B26: MSB Accounting | C26: 27232 | E26: Client Dev | F26: Defect | G26: MSB ACCT - BKK - [Regression] Fix the text field alignments in Get MSB Batch Payments page when different display scaling | H26: Minor | I26: Manual | J26: Internal | K26: Defect Being Fixed | L26: Development | M26: Issue with the new Kaleida UI changes. All changes are worked by client dev. Defect also handleb by same client dev.
A27: 25 | B27: MSB Accounting | C27: SRX28879 | E27: Rijo | F27: Task | G27: MSB ACCT - Missing Batches in the UI | H27: Significant | I27: Manual | J27: External | K27: Defect Being Fixed | L27: Project_Management | M27: Not a defect. The escalation was created to analyse why the batches are getting missed. It was a set issue on MSB side.
A28: 26 | B28: MSB Accounting | C28: 27253 | E28: Client Dev | F28: Defect | G28: MSB ACCT - BKK - [Regression] Fix the flyout message in 1099 Reporting - Import Data | H28: Significant | I28: Manual | J28: Internal | K28: Defect Fixed | L28: Development | M28: Issue with the new Kaleida UI changes. All changes are worked by client dev. Defect also handleb by same client dev.

Sheet 26.04 Sprint 2-Status
A1: S.No | B1: Application Name | C1: Sprint Start Date | D1: Sprint End Date | E1: Sprint | F1: Developer | G1: Story ID/Defect ID | H1: Description | I1: Status | J1: Estimated(sp) | K1: Actual(sp) | L1: Actual Hours Worklog | M1: Dev Start Date | N1: Dev End Date | O1: Unit testing | P1: Peer Tested By | Q1: Peer Tested Comments, if any | R1: Peer Reviewed By | S1: Peer Code Review Comments, if any | T1: PR Number/Link | U1: PR Created Date | V1: PR Approved Date | W1: Onsite Lead Code Review | X1: Onsite Lead Code Review Comments, if any | Y1: Client Code Review | Z1: PR Approved Date2 | AA1: Client Code Review Comments, if any | AB1: Internal PO -POV Comments | AC1: Client PO -POV Comments | AD1: Comments | AE1: Story met clarity expectations? | AF1: 46106 | AG1: 46107 | AH1: 46108 | AI1: 46111 | AJ1: 46112 | AK1: 46113 | AL1: 46114 | AM1: 46115 | AN1: 46118 | AO1: 46119
A2: 1 | B2: MSB Accounting | C2: 46106 | D2: 46119 | E2: MSB Accounting 26.04 Sprint 2 | F2: Karthik | G2: SRX28830 | H2: DUR - MSB ACCT - REC - Carpinteria High School (CPHS) - Cannot import some batches from Receipting | I2: Defect Fixed | J2: 0 | K2: 0 | L2: 0 | M2: 46101 | N2: 46104 | O2: NA | P2: NA | Q2: NA | R2: NA | S2: NA | T2: NA | U2: NA | V2: NA | W2: NA | X2: NA | Y2: NA | Z2: NA | AA2: NA | AB2: NA | AC2: NA | AD2: Closed as defect since code changes require for this. | AE2: Meets Expectation | AF2: Closed | AG2: - | AH2: - | AI2: - | AJ2: - | AK2: - | AL2: -
A3: 2 | B3: MSB Accounting | C3: 46106 | D3: 46119 | E3: MSB Accounting 26.04 Sprint 2 | F3: Karthik | G3: SRX28834 | H3: DUR - MSB ACCT - BKK - Carpinteria High School (CPHS) - Hide Batch Seq # 423 and 424 | I3: Defect Fixed | J3: 0 | K3: 0 | L3: 0 | M3: 46104 | N3: 46104 | O3: NA | P3: NA | Q3: NA | R3: NA | S3: NA | T3: NA | U3: NA | V3: NA | W3: NA | X3: NA | Y3: NA | Z3: NA | AA3: NA | AB3: NA | AC3: NA | AD3: Data Fix Completed on PROD | AE3: Meets Expectation | AF3: Data Fix Made. Verified. waiting on Customer approval | AG3: Karthik on PTO. Needs to be verified. by customer | AH3: Closed | AI3: - | AJ3: - | AK3: - | AL3: -
A4: 3 | B4: MSB Accounting | C4: 46106 | D4: 46119 | E4: MSB Accounting 26.04 Sprint 2 | F4: Karthik | G4: SRX28841 | H4: DUR - MSB ACCT - BKK - Kingsport City Schools (Sevier, Robinson & Roosevelt) - Update GL Code | I4: Defect Fixed | J4: 0 | K4: 1 | L4: 4.25 | M4: 46106 | N4: 46106 | O4: NA | P4: NA | Q4: NA | R4: NA | S4: NA | T4: NA | U4: NA | V4: NA | W4: NA | X4: NA | Y4: NA | Z4: NA | AA4: NA | AB4: NA | AC4: NA | AD4: Data Fix Completed on PROD | AE4: Meets Expectation | AF4: Query is ready - Waiting on review. | AG4: Karthik on PTO | AH4: Queries run on Prod. Waiting on Pramod's Confirmation about fix. | AI4: - | AJ4: - | AK4: - | AL4: -
A5: 4 | B5: MSB Accounting | C5: 46106 | D5: 46119 | E5: MSB Accounting 26.04 Sprint 2 | F5: Qadir | G5: SRX28828 | H5: MSB ACCT - BKK - Remove Duplicate Adjustments from Bank Rec Report Preview (Kingsport) | I5: Defect Fixed | J5: 0 | K5: 0.75 | L5: 3 | M5: 46106 | N5: 46107 | O5: NA | P5: NA | Q5: NA | R5: NA | S5: NA | T5: NA | U5: NA | V5: NA | W5: NA | X5: NA | Y5: NA | Z5: NA | AA5: NA | AB5: NA | AC5: NA | AD5: Permanent Fix made to exclude deleted banks. SP changes made in PROD as well. | AE5: Meets Expectation | AF5: found the issue on the report. Push changes to run as a migration. Also, can push this as a fix directly on the DB , so we dont face this issue again. | AG5: PROD fix made. Waiting on confirmation | AH5: Got confirmation the fix is in | AI5: - | AJ5: - | AK5: - | AL5: -
A6: 5 | B6: MSB Accounting | C6: 46106 | D6: 46119 | E6: MSB Accounting 26.04 Sprint 2 | F6: Qadir | G6: SRX28840 | H6: MSB ACCT - BKK - Error 'User name already taken' When Adding District Admin | I6: Defect Fixed | J6: 0 | K6: 0.37 | L6: 1.5 | M6: 46105 | N6: 46107 | O6: NA | P6: NA | Q6: NA | R6: NA | S6: NA | T6: NA | U6: NA | V6: NA | W6: NA | X6: NA | Y6: NA | Z6: NA | AA6: NA | AB6: NA | AC6: NA | AD6: This was a non issue. The user had been added in another district. After figuring out the other district, user was deleted from there and added to desired district. | AE6: Meets Expectation | AF6: Data request Made to PROD. | AG6: Closed. Confirmed Support was able to delete user from another test district | AH6: - | AI6: - | AJ6: - | AK6: - | AL6: -
A7: 6 | B7: MSB Accounting | C7: 46106 | D7: 46119 | E7: MSB Accounting 26.04 Sprint 2 | F7: Qadir | G7: 52283 | H7: MSB Onboarding - Identifying Payment Accounts that are for Fees Only | I7: Story Completed | J7: 5 | K7: 7.87 | L7: 31.5 | M7: 46105 | N7: 46112 | O7: Completed | P7: Rijo | Q7: Pass | R7: Karthik | S7: Pass | T7: https://dev.azure.com/heartlandschools/Merchant/_git/Boarding/pullrequest/48151 | U7: 46112 | V7: 46112 | W7: Done | X7: Pass | Y7: Done | Z7: NA | AA7: Pass | AB7: Pass | AC7: Pass | AE7: Meets Expectation | AF7: Reviewed the story. Will start working on this today. | AG7: In Progress | AH7: Dev Complete. Dev Testing in progress. | AI7: Bugs need to be fixed. POV with pramod after standup | AJ7: Bugs are fixed. POV pending with pramod. | AK7: PR made. Completed testing. | AL7: -
A8: 7 | B8: MSB Accounting | C8: 46106 | D8: 46119 | E8: MSB Accounting 26.04 Sprint 2 | F8: Rijo | G8: 51861 | H8: MSB Onboarding - Capturing Tax and Federal Eligibility | I8: Story Completed | J8: 1 | K8: 2.62 | L8: 10.5 | M8: 46107 | N8: 46108 | O8: Completed | P8: Karthik | Q8: Pass | R8: Qadir | S8: Pass | T8: https://dev.azure.com/heartlandschools/Merchant/_git/Boarding/pullrequest/48103 | U8: 46111 | V8: 46111 | W8: Done | X8: Pass | Y8: Done | Z8: NA | AA8: Pass | AB8: Pass | AC8: Pass | AE8: Meets Expectation | AF8: Rijo on PTO | AG8: Pushed changes for the code review. | AH8: Qadir to Review | AI8: ready for Testing | AJ8: Sowjanya - Created a bounceback inbetween the Financial Status options and Federal Tax ID (EIN) Rijo - Fixed and Deployed. Ready For Testing again. | AK8: - | AL8: -
A9: 8 | B9: MSB Accounting | C9: 46106 | D9: 46119 | E9: MSB Accounting 26.04 Sprint 2 | F9: Rijo | G9: 52282 | H9: MSB Onboarding - Adjustments to Onboarding Main Page | I9: Story Completed | J9: 2 | K9: 1.75 | L9: 7 | M9: 46108 | N9: 46108 | O9: Completed | P9: Karthik | Q9: Pass | R9: Qadir | S9: Pass | T9: https://dev.azure.com/heartlandschools/Merchant/_git/Boarding/pullrequest/48127 | U9: 46112 | V9: 46112 | W9: Done | X9: Pass | Y9: Done | Z9: NA | AA9: Pass | AB9: Pass | AC9: Pass | AE9: Meets Expectation | AJ9: Testing almost complete. Ready to close. | AL9: -
A10: 9 | B10: MSB Accounting | C10: 46106 | D10: 46119 | E10: MSB Accounting 26.04 Sprint 2 | F10: Rijo | G10: 27010 | H10: MSB ACCT - Importing GLs with leading 0's | I10: Defect Fixed | J10: 3 | K10: 2.5 | L10: 10 | M10: 46107 | N10: 46111 | O10: Completed | P10: Karthik | Q10: Pass | R10: Qadir | S10: Pass | T10: https://dev.azure.com/heartlandschools/Accounting/_git/MSBAccounting-NewSchoolBooks/pullrequest/48128 | U10: 46112 | V10: 46112 | W10: Done | X10: Pass | Y10: Done | Z10: NA | AA10: Pass | AB10: Pass | AC10: Pass | AE10: Meets Expectation | AG10: Started analysis. | AH10: ready for POV. Waiting on Pramod. | AI10: POV with pramod. Posted jeanette | AJ10: ready for Testing. | AK10: Completed Testing | AL10: -
A11: 10 | B11: MSB Accounting | C11: 46106 | D11: 46119 | E11: MSB Accounting 26.04 Sprint 2 Stretch | F11: Rijo | G11: 51841 | H11: MSB ACCT - BKK - Improvize "Get MSB Batch Payments tool" to avoid adding the missing payments more than once | I11: Story Completed | J11: 3 | K11: 1.5 | L11: 6 | M11: NA | N11: NA | O11: NA | P11: NA | Q11: NA | R11: NA | S11: NA | T11: NA | U11: NA | V11: NA | W11: NA | X11: NA | Y11: NA | Z11: NA | AA11: NA | AB11: NA | AC11: NA | AD11: Dev changes was completed last sprint, only testing effort in this sprint. | AE11: Meets Expectation | AG11: While testing found an error for one batch ID but sould not replicate so requested rijo to raise a few more batches | AH11: Request made to modify batches to test support tool. | AI11: Have Verified in Cert Environment | AJ11: Completed | AK11: - | AL11: -
A12: 11 | B12: MSB Accounting | C12: 46106 | D12: 46119 | E12: MSB Accounting 26.04 Sprint 2 Stretch | F12: Karthik | G12: 25100 | H12: MSB ACCT - BKK - GL Account number search for '190000000' does not find masked number '1900-000-00' in the search field | I12: Defect Fixed | J12: 2 | K12: 3 | L12: 12 | M12: 46112 | N12: 46112 | O12: Completed | P12: Rijo | Q12: Pass | R12: Qadir | S12: Pass | T12: https://dev.azure.com/heartlandschools/Accounting/_git/MSBAccounting-NewSchoolBooks/pullrequest/48167 | U12: 46113 | V12: 46113 | W12: Done | X12: Pass | Y12: Done | Z12: NA | AA12: Pass | AB12: Pass | AC12: Pass | AE12: Meets Expectation | AJ12: completed Dev Changes and POV. Will post recording to the channel. | AK12: PR Created. | AL12: Completed Testing in Dev Environment
A13: 12 | B13: MSB Accounting | C13: 46106 | D13: 46119 | E13: MSB Accounting 26.04 Sprint 2 Stretch | F13: Rijo | G13: 52469 | H13: MSB ACCT - Analysis for the Impact on the year process when Deleting Imported Batches in Bank Deposit Entry | I13: Story Completed | J13: 5 | K13: 4 | L13: 16 | M13: 46111 | N13: 46113 | O13: NA | P13: NA | Q13: NA | R13: NA | S13: NA | T13: NA | U13: NA | V13: NA | W13: NA | X13: NA | Y13: NA | Z13: NA | AA13: NA | AB13: Pass | AC13: Pass | AD13: No code changes and PR. This is a story to analyse downstream impacts. | AE13: Meets Expectation | AJ13: Still going on. checking whether we can hard delete a batch ? | AK13: Did POV with pramod. No Approval / PR. | AL13: Waiting on Client POV | AM13: Completed
A14: 13 | B14: MSB Accounting | C14: 46106 | D14: 46119 | E14: MSB Accounting 26.04 Sprint 2 Stretch | F14: Karthik | G14: 27057 | H14: DUR - MSB ACCT - BKK - Carpinteria High School (CPHS) - Cannot import some batches from Receipting | I14: Defect Fixed | J14: 0 | K14: 0.5 | L14: 2.25 | M14: 46106 | N14: 46106 | O14: Completed | P14: Rijo | Q14: Pass | R14: Qadir | S14: Pass | T14: https://dev.azure.com/heartlandschools/Accounting/_git/MSBAccounting-NewSchoolBooks/pullrequest/48108 | U14: 46111 | V14: 46111 | W14: Done | X14: Pass | Y14: Done | Z14: NA | AA14: Pass | AB14: Pass | AC14: Pass | AE14: Meets Expectation | AF14: Completed Fix. Waiting on POV. | AG14: POV completed. | AH14: Completed POV with pramod | AI14: waiting on POV from jeanette | AJ14: Ready for Testing | AK14: Ready for Testing. | AL14: Issues with Testing on Dev environment because of an old integration with receipting. | AM14: Tsting by Client QA.
A15: 14 | B15: MSB Accounting | C15: 46106 | D15: 46119 | E15: MSB Accounting 26.04 Sprint 2 Stretch | F15: Karthik | G15: 45225 | H15: MSB ACCT - BKK - Add Warnings and Blockers for Unclosed Years | I15: Product Owner - Verify | J15: 5 | K15: 6 | L15: 24 | M15: 46108 | N15: 46113 | O15: Completed | P15: NA | Q15: NA | R15: NA | S15: NA | T15: NA | U15: NA | V15: NA | W15: NA | X15: NA | Y15: NA | Z15: NA | AA15: NA | AB15: NA | AC15: NA | AD15: 3 more additional points included in the AC during internal POV and completed all the changes. Waiting on POV approval. | AE15: Meets Expectation | AH15: Dev Changes completed. Dev Testing in Progress. | AI15: Completed cleanup and dev testing. | AJ15: POV with pramod. need 3 more additional changes about Message Updates. | AK15: Completed POV changes. | AL15: Still waiting on Client POV. Peer Review pending | AM15: Sowjanya - Have Completed writing testcase Karthik - Completed Feedback Changes. Qadir - To complete Review. | AN15: Working on Code review comments from Qadir. Completed 3 points, working on last point which was given later. | AO15: Clarifications cleared for POV. Waiting on jeanette
A16: 15 | B16: MSB Accounting | C16: 46106 | D16: 46119 | E16: MSB Accounting 26.04 Sprint 2 Stretch | F16: Rijo | G16: 47848 | H16: MSB ACCT - BKK - Rename "New Data" Feature Flag | I16: Product Owner - Verify | J16: 3 | K16: 3.37 | L16: 13.5 | M16: 46114 | N16: 46115 | O16: NA | P16: NA | Q16: NA | R16: NA | S16: NA | T16: NA | U16: NA | V16: NA | W16: NA | X16: NA | Y16: NA | Z16: NA | AA16: NA | AB16: NA | AC16: NA | AD16: Still waiting for client PO's approval. | AE16: Meets Expectation | AJ16: Ananlysis in progress. | AL16: need a migration for all the stored Proc. | AM16: Dev completed. POV pending with Pramod. | AN16: POv completed. | AO16: Waiting on client POV to be released.
A17: 16 | B17: MSB Accounting | C17: 46106 | D17: 46119 | E17: MSB Accounting 26.04 Sprint 2 Stretch | F17: Karthik | G17: 24926 | H17: MSB ACCT - BKK - GL Account Maintenance current balances do not display the most recent balances | I17: Defect Being Fixed | J17: 3 | K17: 2 | L17: 8 | M17: 46114 | N17: 46115 | O17: NA | P17: NA | Q17: NA | R17: NA | S17: NA | T17: NA | U17: NA | V17: NA | W17: NA | X17: NA | Y17: NA | Z17: NA | AA17: NA | AB17: NA | AC17: NA | AD17: Dev completed and it has been moved to the next sprint for further work. | AE17: Meets Expectation | AL17: Analysis in Progress. | AM17: Unable to replicate in local. but able to replicate in local. | AN17: Need Update on DEV. | AO17: Dev Testing in progress.
A18: 17 | B18: MSB Accounting | C18: 46106 | D18: 46119 | E18: MSB Accounting 26.04 Sprint 2 Stretch | F18: Qadir | G18: 52629 | H18: MSB Onboarding - Remove all old onboarding pages | I18: Story Being Developed | J18: 3 | K18: 4.75 | L18: 19 | M18: 46112 | N18: NA | O18: NA | P18: NA | Q18: NA | R18: NA | S18: NA | T18: NA | U18: NA | V18: NA | W18: NA | X18: NA | Y18: NA | Z18: NA | AA18: NA | AB18: NA | AC18: NA | AD18: Development still in progress. | AE18: Meets Expectation | AM18: Started working on this. Still in progress. | AN18: Ready for POV. Need to get latest from James' work and review. | AO18: Got the code from james. and compared. need to connect with pramod for POV.
A19: 18 | B19: MSB Accounting | C19: 46106 | D19: 46119 | E19: MSB Accounting 26.04 Sprint 2 Stretch | F19: Rijo | G19: 47478 | H19: MSB ACCT - BKK - Update Bank Deposit History Report to Reflect Changes to Import MSB Batches | I19: Story Being Developed | J19: 3 | K19: 2.25 | L19: 9 | M19: 46118 | N19: NA | O19: NA | P19: NA | Q19: NA | R19: NA | S19: NA | T19: NA | U19: NA | V19: NA | W19: NA | X19: NA | Y19: NA | Z19: NA | AA19: NA | AB19: NA | AC19: NA | AD19: Development still in progress. Started on the 2nd last day of sprint. | AE19: Meets Expectation | AN19: Made changes in bank Deposit history report. PY Report changes pending. | AO19: Ready for POV.
A20: 19 | B20: MSB Accounting | C20: 46106 | D20: 46119 | E20: MSB Accounting 26.04 Sprint 2 Stretch | F20: Client Dev | G20: 52572 | H20: MSB Onboarding - HomePage Adjustments for Kaleida Alignment | I20: Story Completed | J20: 3 | K20: 1.25 | L20: 5 | M20: NA | N20: NA | O20: NA | P20: NA | Q20: NA | R20: NA | S20: NA | T20: NA | U20: NA | V20: NA | W20: NA | X20: NA | Y20: NA | Z20: NA | AA20: NA | AB20: NA | AC20: NA | AD20: Worked by client dev. Only testing effort for our team | AE20: Meets Expectation | AO20: Story Completed and closed -Created a bounce Back -1.The Gap in-between the content and image seems to slight odd . 2.And the background color seems to be bright when we look at the figma..
A21: 20 | B21: MSB Accounting | C21: 46106 | D21: 46119 | E21: MSB Accounting 26.04 Sprint 2 Stretch | F21: Client Dev | G21: 52277 | H21: MSB Onboarding - Sign & Submit | I21: Story Being Tested | J21: 3 | K21: 1.5 | L21: 6 | M21: NA | N21: NA | O21: NA | P21: NA | Q21: NA | R21: NA | S21: NA | T21: NA | U21: NA | V21: NA | W21: NA | X21: NA | Y21: NA | Z21: NA | AA21: NA | AB21: NA | AC21: NA | AD21: Worked by client dev. Only testing effort for our team. Started today Few scenarios need to be tested | AE21: Meets Expectation | AO21: Few Scenarios are pending in testing
A22: 21 | B22: MSB Accounting | C22: 46106 | D22: 46119 | E22: MSB Accounting 26.04 Sprint 2 Stretch | F22: Qadir | G22: 25660 | H22: MSB ACCT - BKK - [Regression] Updated notes not shown in CSV report for cash transfer entries | I22: Story Being Developed | J22: 3 | K22: 0.75 | L22: 3 | M22: 46119 | N22: NA | O22: NA | P22: NA | Q22: NA | R22: NA | S22: NA | T22: NA | U22: NA | V22: NA | W22: NA | X22: NA | Y22: NA | Z22: NA | AA22: NA | AB22: NA | AC22: NA | AD22: Development still in progress. Started on the last day of sprint. | AE22: Meets Expectation | AO22: Started today. Dev Completed. Dev testing in progress.

Sheet 26.04 Sprint 2-Defect
A1: S.No | B1: Sprint # | C1: Story/Defect ID | D1: Parent Story | E1: Developer | F1: Issue Type | G1: Issue Description | H1: Priority | I1: Defect Source | J1: Type | K1: Status | L1: Root Cause Category | M1: Comments
A2: 1 | B2: MSB Accounting | C2: SRX28830 | E2: Karthik | F2: Defect | G2: DUR - MSB ACCT - REC - Carpinteria High School (CPHS) - Cannot import some batches from Receipting | H2: Significant | I2: Manual | J2: External | K2: Defect Fixed | L2: Existing_Issues | M2: Existing issue with vendor object mapping for refund check types. A code fix is required, so we may need to provide a hotfix based on the customer's requirement. Details have been shared with Jeanette, and she will confirm the next steps.
A3: 2 | B3: MSB Accounting | C3: SRX28834 | E3: Karthik | F3: Task | G3: DUR - MSB ACCT - BKK - Carpinteria High School (CPHS) - Hide Batch Seq # 423 and 424 | H3: Significant | I3: Manual | J3: External | K3: Defect Fixed | L3: Existing_Issues | M3: This issue related to previous escalation SRX28830. Since it needs code fix, customer has entered data manually for the issue caused batch. So we made data fix to hide those batches on import from receipting screen. Waiting for customers confirmation.
A4: 3 | B4: MSB Accounting | C4: SRX28841 | E4: Karthik | F4: Task | G4: DUR - MSB ACCT - BKK - Kingsport City Schools (Sevier, Robinson & Roosevelt) - Update GL Code | H4: Significant | I4: Manual | J4: External | K4: Defect Fixed | L4: Project_Management | M4: This is not an issue, It is a customer data fix request. Customer wanted to update the account code for few accounts, so we have applied a data fix for this.
A5: 4 | B5: MSB Accounting | C5: SRX28828 | E5: Qadir | F5: Defect | G5: MSB ACCT - BKK - Remove Duplicate Adjustments from Bank Rec Report Preview (Kingsport) | H5: Significant | I5: Manual | J5: External | K5: Defect Fixed | L5: Existing_Issues | M5: Scenario involved Accounts from Deleted banks being joined and showing as duplicates on the reports.
A6: 5 | B6: MSB Accounting | C6: SRX28840 | E6: Qadir | F6: Task | G6: MSB ACCT - BKK - Error 'User name already taken' When Adding District Admin | H6: Significant | I6: Manual | J6: External | K6: Defect Fixed | L6: Project_Management | M6: User had been assigned to a test school instead of the actual school. Support could not add the user again. Not an issue with the code, it was a mistake from the user.
A7: 6 | B7: MSB Accounting | C7: 27010 | E7: Rijo | F7: Defect | G7: MSB ACCT - Importing GLs with leading 0's | H7: Minor | I7: Manual | J7: Internal | K7: Defect Fixed | L7: Existing_Issues | M7: Existing issue, but recently found. The initial 0s before a digit was getting truncated.
A8: 7 | B8: MSB Accounting | C8: 25100 | E8: Karthik | F8: Defect | G8: MSB ACCT - BKK - GL Account number search for '190000000' does not find masked number '1900-000-00' in the search field | H8: Minor | I8: Manual | J8: Internal | K8: Defect Fixed | L8: Existing_Issues | M8: Existing issue, account number search doesn't find masked number if search with unmasked numbers. This has been fixed by validating the search input and apply the masking if needed.
A9: 8 | B9: MSB Accounting | C9: 27057 | E9: Karthik | F9: Defect | G9: DUR - MSB ACCT - BKK - Carpinteria High School (CPHS) - Cannot import some batches from Receipting | H9: Major | I9: Manual | J9: External | K9: Defect Fixed | L9: Existing_Issues | M9: Existing issue with vendor object mapping for refund check types. This has been fixed by registering the vendor object mapping in the automaping configuration.
A10: 9 | B10: MSB Accounting | C10: 24926 | E10: Karthik | F10: Defect | G10: MSB ACCT - BKK - GL Account Maintenance current balances do not display the most recent balances | H10: Minor | I10: Manual | J10: Internal | K10: Defect Being Fixed | L10: Existing_Issues | M10: Existing issue, This issue occured in time zones other than the central time zone because the GL account maintenance current balance was calculated using the server's current date and time. As a result, entries from other time zones after that time were not included. The issue has been fixed by using the client's time zone for balance calculation. Dev testing in progress.

Sheet 26.04 Sprint 1-Status
A1: S.No | B1: Application Name | C1: Sprint Start Date | D1: Sprint End Date | E1: Sprint | F1: Developer | G1: Story ID/Defect ID | H1: Description | I1: Status | J1: Estimated(sp) | K1: Actual(sp) | L1: Actual Hours Worklog | M1: Dev Start Date | N1: Dev End Date | O1: Unit testing | P1: Peer Tested By | Q1: Peer Tested Comments, if any | R1: Peer Reviewed By | S1: Peer Code Review Comments, if any | T1: PR Number/Link | U1: PR Created Date | V1: PR Approved Date | W1: Onsite Lead Code Review | X1: Onsite Lead Code Review Comments, if any | Y1: Client Code Review | Z1: PR Approved Date2 | AA1: Client Code Review Comments, if any | AB1: Internal PO -POV Comments | AC1: Client PO -POV Comments | AD1: Comments | AE1: Story met clarity expectations? | AF1: 46092 | AG1: 46093 | AH1: 46094 | AI1: 46097 | AJ1: 46098 | AK1: 46099 | AL1: 46100 | AM1: 46101 | AN1: 46104 | AO1: 46105
A2: 1 | B2: MSB Accounting | C2: 3/11/1016 | D2: 46105 | E2: MSB Accounting 26.04 Sprint 1 | F2: Client Dev | G2: 51860 | H2: MSB Onboarding - Managing a Variety of User Journeys Using the Left Nav within Application | I2: Story Completed | J2: 2 | K2: 1 | L2: 4 | M2: NA | N2: NA | O2: NA | P2: NA | Q2: NA | R2: NA | S2: NA | T2: NA | U2: NA | V2: NA | W2: NA | X2: NA | Y2: NA | Z2: NA | AA2: NA | AB2: NA | AC2: NA | AE2: Meets Expectation | AF2: Created a bounce back on points missing -1. The untitle Application # xxxx is missing for few pages 2. On each page we need save & exit, cancel and Next button is missing 3. The Checkbox button is not matching the figma | AG2: Moved to chris. Bounceback . | AH2: Still a bounceback | AL2: Completed
A3: 2 | B3: MSB Accounting | C3: 3/11/1016 | D3: 46105 | E3: MSB Accounting 26.04 Sprint 1 | F3: Karthik | G3: 26211 | H3: MSB ACCT - BKK - [Regression] Reversal for a Receipt Entry does not display Sales Tax amount in Receipt Report - Sales Tax line | I3: Defect Fixed | J3: 1 | K3: 1 | L3: 4 | M3: NA | N3: NA | O3: NA | P3: NA | Q3: NA | R3: NA | S3: NA | T3: NA | U3: NA | V3: NA | W3: NA | X3: NA | Y3: NA | Z3: NA | AA3: NA | AB3: NA | AC3: NA | AD3: Unable to replicate this issue. This might have already been fixed earlier as part of the reversal form related changes. So, moving this directly to QA to verify and close. | AE3: Meets Expectation | AF3: .Have Verified in dev Environment i can see the sale tax for reversal Entry- Closed | AG3: Completed | AH3: - | AJ3: -
A4: 3 | B4: MSB Accounting | C4: 3/11/1016 | D4: 46105 | E4: MSB Accounting 26.04 Sprint 1 | F4: Rijo | G4: 51861 | H4: MSB Onboarding - Capturing Tax and Federal Eligibility | I4: Defect Peer Review | J4: 2 | K4: 2.5 | L4: 10 | M4: 3/11/1016 | AD4: Dev and POV is completed, PR creation was pending due to unexpected sick leave. The item will be moved to QA in the next sprint. | AF4: CSS changes still in progress. Will be completed tomorrow. | AG4: Unplanned PTO. | AH4: Rijo to share details with jeanette for details. | AI4: Completed UI changes given by Jeanette and shared the screenshots again. | AJ4: Rijo PTO | AK4: Completed UI changes given by Jeanette and shared the screenshots again. | AL4: Waiting for Jeanette's approval. | AM4: Waiting on PR.
A5: 4 | B5: MSB Accounting | C5: 3/11/1016 | D5: 46105 | E5: MSB Accounting 26.04 Sprint 1 Stretch | F5: Karthik | G5: 26889 | H5: MSB ACCT - BKK - Cannot Add Print Groups to GL Account (Kingsport) | I5: Defect Fixed | J5: 2 | K5: 1 | L5: 4 | M5: 46087 | N5: 46090 | O5: Completed | P5: Rijo | Q5: Pass | R5: Qadir | S5: Pass | T5: https://dev.azure.com/heartlandschools/Accounting/_git/MSBAccounting-NewSchoolBooks/pullrequest/47717 | U5: 46091 | V5: 46091 | W5: Done | X5: Pass | Y5: Done | Z5: NA | AA5: Pass | AB5: Pass | AC5: Pass | AE5: Meets Expectation | AF5: Final round of testing. Fixed on DEV. Tested on CERT and was able to see the issue. | AG5: Verified on DEV. | AH5: Completed. | AJ5: -
A6: 5 | B6: MSB Accounting | C6: 3/11/1016 | D6: 46105 | E6: MSB Accounting 26.04 Sprint 1 | F6: Karthik | G6: SRX28802 | H6: DUR - MSB ACCT - BKK - Blackstone Valley Tech High School (13496) - Update October Deposit Dates | I6: Defect Fixed | K6: 1.25 | L6: 5 | M6: 46092 | N6: 46093 | O6: NA | P6: NA | Q6: NA | R6: NA | S6: NA | T6: NA | U6: NA | V6: NA | W6: NA | X6: NA | Y6: NA | Z6: NA | AA6: NA | AB6: NA | AC6: NA | AD6: Production data fix. No code changes and PR. | AE6: Meets Expectation | AF6: Completed Data Fix query. Verifying changes with the report. | AG6: Data Fix query is updated after comments. Ready to make a request to run on PROD. | AH6: Data Fix queries run in PROD. waiting on Customer verification | AJ6: -
A7: 6 | B7: MSB Accounting | C7: 3/11/1016 | D7: 46105 | E7: MSB Accounting 26.04 Sprint 1 Stretch | F7: Karthik | G7: 45225 | H7: MSB ACCT - BKK - Add Warnings and Blockers for Unclosed Years | I7: Story Being Developed | J7: 8 | K7: 5 | L7: 20 | M7: 46094 | N7: NA | O7: NA | P7: NA | Q7: NA | R7: NA | S7: NA | T7: NA | U7: NA | V7: NA | W7: NA | X7: NA | Y7: NA | Z7: NA | AA7: NA | AB7: NA | AC7: NA | AD7: There was not much progress on this story due to escalations work. It will be carried over to the next sprint. | AF7: Started analysis. | AG7: Limited progress. | AH7: Worked on this. Clarifications on AC. Started working on School Settings. | AI7: Completed school settings section. Cleared doubts with Pramod, currently working with alert popup UI related changes. | AJ7: Completed warning message related changes and working on for blocking the entries changes. | AK7: Completed entry blocking changes and working on for validation and migration related changes. | AL7: Completed dev changes. Pramod asked for some additional changes. | AM7: No progress. Escalations to be worked on
A8: 7 | B8: MSB Accounting | C8: 3/11/1016 | D8: 46105 | E8: MSB Accounting 26.04 Sprint 1 | F8: Karthik | G8: SRX28805 | H8: MSB ACCT - BKK - Add Print Groups to GL Accounts (Kingsport) | I8: Defect Fixed | K8: 0.5 | L8: 2 | M8: 46093 | N8: 46093 | O8: NA | P8: NA | Q8: NA | R8: NA | S8: NA | T8: NA | U8: NA | V8: NA | W8: NA | X8: NA | Y8: NA | Z8: NA | AA8: NA | AB8: NA | AC8: NA | AD8: Production data fix. No code changes and PR. | AE8: Meets Expectation | AG8: Created data fix query. Made a request for PROD update. | AH8: Completed in PROD. Wiaiting on Pramod's Confirmation. | AJ8: -
A9: 8 | B9: MSB Accounting | C9: 3/11/1016 | D9: 46105 | E9: MSB Accounting 26.04 Sprint 1 Stretch | F9: Rijo | G9: 51841 | H9: MSB ACCT - BKK - Improvize "Get MSB Batch Payments tool" to avoid adding the missing payments more than once | I9: Story Being Tested | J9: 3 | K9: 2.5 | L9: 10.5 | M9: NA | N9: NA | O9: Completed | P9: Karthik | Q9: Pass | R9: Qadir | S9: Pass | T9: https://dev.azure.com/heartlandschools/Accounting/_git/MSBAccounting-NewSchoolBooks/pullrequest/47795 | U9: 46094 | V9: 46094 | W9: Done | X9: Pass | Y9: Done | Z9: NA | AA9: Pass | AB9: Pass | AC9: Pass | AD9: Testing in progress | AH9: Made a PR. Needs to be deployed to CER. | AI9: Made request to revert cert db to old one. Need to deploy to cert after that. | AJ9: Rijo PTO | AK9: Started writing testcase | AL9: Created a service now ticket with queries to update the batch totals and remove payments. | AM9: Deployed to CERT. Testing in progress. Clarifications reqd. | AO9: Gateway alignment is not proper i have added a screenshot in the story and need to test few more scenarios
A10: 9 | B10: MSB Accounting | C10: 3/11/1016 | D10: 46105 | E10: MSB Accounting 26.04 Sprint 1 | F10: Client Dev | G10: 51857 | H10: MSB Onboarding - Home Page to Start, Manage, and View Applications | I10: Story Completed | J10: 2 | K10: 2.25 | L10: 9 | M10: NA | N10: NA | O10: NA | P10: NA | Q10: NA | R10: NA | S10: NA | T10: NA | U10: NA | V10: NA | W10: NA | X10: NA | Y10: NA | Z10: NA | AA10: NA | AB10: NA | AC10: NA | AE10: Meets Expectation | AH10: Got Clarified and created a bounceback | AI10: Found 1 more alignment issue, reported to Pramod and James. James made the fix and waiting for deployment to verify again. | AK10: Story completed | AL10: _
A11: 10 | B11: MSB Accounting | C11: 3/11/1016 | D11: 46105 | E11: MSB Accounting 26.04 Sprint 1 Stretch | F11: Client Dev | G11: 51858 | H11: MSB Onboarding - Header + Footer Design to Align with Kaleida | I11: Story Completed | J11: 3 | K11: 1.25 | L11: 5 | M11: NA | N11: NA | O11: NA | P11: NA | Q11: NA | R11: NA | S11: NA | T11: NA | U11: NA | V11: NA | W11: NA | X11: NA | Y11: NA | Z11: NA | AA11: NA | AB11: NA | AC11: NA | AE11: Meets Expectation | AH11: Got Clarified and created a bounceback | AJ11: Got clarifed and tested -closed | AK11: Story completed | AL11: _
A12: 11 | B12: MSB Accounting | C12: 3/11/1016 | D12: 46105 | E12: MSB Accounting 26.04 Sprint 1 Stretch | F12: Rijo | G12: 52282 | H12: MSB Onboarding - Adjustments to Onboarding Main Page | I12: Product Owner - Verify | J12: 3 | K12: 5 | L12: 20 | AD12: Waiting for client PO's approval. | AI12: Haven't made much progress. UI changes still in progress. | AJ12: Completed and closed | AL12: Ready for POV. | AM12: pending with Jeanette pOV
A13: 12 | B13: MSB Accounting | C13: 3/11/1016 | D13: 46105 | E13: MSB Accounting 26.04 Sprint 1 | F13: Client Dev | G13: 51864 | H13: MSB Onboarding - Capturing Payment Account Details | I13: Story Completed | J13: 3 | K13: 2.25 | L13: 9 | M13: NA | N13: NA | O13: NA | P13: NA | Q13: NA | R13: NA | S13: NA | T13: NA | U13: NA | V13: NA | W13: NA | X13: NA | Y13: NA | Z13: NA | AA13: NA | AB13: NA | AC13: NA | AE13: Meets Expectation | AI13: Completed Testcase | AJ13: On payment Account page account type -that one combo should not be disabled on add or edit. Should only be disabled on view mode-but now its disable on the add or edit- created a bounce back | AL13: Created a bounce on bankletter is not adding only when we edit its adding | AM13: Story Completed
A14: 13 | B14: MSB Accounting | C14: 3/11/1016 | D14: 46105 | E14: MSB Accounting 26.04 Sprint 1 | F14: Karthik | G14: SRX28823 | H14: DUR - MSB ACCT - BKK - Diamond Bar High School (DBH) - Hide October & November MSB Import Batches | I14: Defect Fixed | K14: 1.5 | L14: 6 | M14: 46098 | N14: 46098 | O14: NA | P14: NA | Q14: NA | R14: NA | S14: NA | T14: NA | U14: NA | V14: NA | W14: NA | X14: NA | Y14: NA | Z14: NA | AA14: NA | AB14: NA | AC14: NA | AD14: Production data fix. No code changes and PR. | AE14: Meets Expectation | AJ14: Created data fix queries and verifying the fixes in local environment. Also need to check with Rijo before run it on PROD. | AK14: Created service ticket to execute data fix on PROD. Waiting for DBA response. | AL14: Update query executed on prod db. Waiting for confirmation
A15: 14 | B15: MSB Accounting | C15: 3/11/1016 | D15: 46105 | E15: MSB Accounting 26.04 Sprint 1 | F15: Client Dev | G15: 51865 | H15: MSB Onboarding - Capturing Pricing Options | I15: Story Completed | J15: 3 | K15: 2 | L15: 8 | M15: NA | N15: NA | O15: NA | P15: NA | Q15: NA | R15: NA | S15: NA | T15: NA | U15: NA | V15: NA | W15: NA | X15: NA | Y15: NA | Z15: NA | AA15: NA | AB15: NA | AC15: NA | AE15: Meets Expectation | AK15: Have completed Testcase | AL15: Have created a bounce back on -When i start a new application and navigating to Pricing options and without clicking anything im just clicking next button and then im coming back to pricing options but the box is selected | AM15: The bounceback is not fixed .i could see the issue again | AN15: Waiting on Dev Completion | AO15: Tested in Dev and closed the story
A16: 15 | B16: MSB Accounting | C16: 3/11/1016 | D16: 46105 | E16: MSB Accounting 26.04 Sprint 1 | F16: Client Dev | G16: 51863 | H16: MSB Onboarding - Capturing Organizational and Billing Details | I16: Story Completed | J16: 3 | K16: 0.5 | L16: 2 | M16: NA | N16: NA | O16: NA | P16: NA | Q16: NA | R16: NA | S16: NA | T16: NA | U16: NA | V16: NA | W16: NA | X16: NA | Y16: NA | Z16: NA | AA16: NA | AB16: NA | AC16: NA | AE16: Meets Expectation | AK16: Have completed Testcase | AM16: Client QA Completed | AN16: -
A17: 16 | B17: MSB Accounting | C17: 3/11/1016 | D17: 46105 | E17: MSB Accounting 26.04 Sprint 1 | F17: Karthik | G17: SRX28830 | H17: DUR - MSB ACCT - REC - Carpinteria High School (CPHS) - Cannot import some batches from Receipting | I17: Defect Being Fixed | K17: 2.5 | L17: 10 | M17: 46101 | N17: 46104 | O17: NA | P17: NA | Q17: NA | R17: NA | S17: NA | T17: NA | U17: NA | V17: NA | W17: NA | X17: NA | Y17: NA | Z17: NA | AA17: NA | AB17: NA | AC17: NA | AD17: Completed the analysis and identified the root cause. A code fix is required, so we may need to provide a hotfix based on the customer's requirement. Details have been shared with Jeanette, and she will confirm the next steps. | AM17: Done analysis and found the root cause. The issue occured when there are any check entries in the import data line items. The issue is related to vendor mapping in the code. So code changes required for this to fix. Need to check with client stadup.
A18: 17 | B18: MSB Accounting | C18: 3/11/1016 | D18: 46105 | E18: MSB Accounting 26.04 Sprint 1 | F18: Karthik | G18: SRX28834 | H18: DUR - MSB ACCT - BKK - Carpinteria High School (CPHS) - Hide Batch Seq # 423 and 424 | I18: Defect Ready For Testing | K18: 0.5 | L18: 2 | M18: 46104 | N18: 46104 | O18: NA | P18: NA | Q18: NA | R18: NA | S18: NA | T18: NA | U18: NA | V18: NA | W18: NA | X18: NA | Y18: NA | Z18: NA | AA18: NA | AB18: NA | AC18: NA | AD18: Completed datafix on PROD and waiting for customer's confirmation.

Sheet 26.04 Sprint 1-Defect
A1: S.No | B1: Sprint # | C1: Story/Defect ID | D1: Parent Story | E1: Developer | F1: Issue Type | G1: Issue Description | H1: Priority | I1: Defect Source | J1: Type | K1: Status | L1: Root Cause Category | M1: Comments
A2: 1 | B2: MSB Accounting | C2: 26211 | E2: Karthik | F2: Defect | G2: MSB ACCT - BKK - [Regression] Reversal for a Receipt Entry does not display Sales Tax amount in Receipt Report - Sales Tax line | H2: Significant | I2: Manual | J2: Internal | K2: Defect Fixed | L2: Existing_Issues | M2: Unable to replicate this issue. This might have already been fixed earlier as part of the reversal form related changes. So, moving this directly to QA to verify and close.
A3: 2 | B3: MSB Accounting | C3: SRX28802 | E3: Karthik | F3: Defect | G3: DUR - MSB ACCT - BKK - Blackstone Valley Tech High School (13496) - Update October Deposit Dates | H3: Significant | I3: Manual | J3: External | K3: Defect Fixed | L3: Existing_Issues | M3: This was caused by a defect we had previously, which was fixed later. For this issue, we have applied a data fix.
A4: 3 | B4: MSB Accounting | C4: 26889 | E4: Karthik | F4: Defect | G4: MSB ACCT - BKK - Cannot Add Print Groups to GL Account (Kingsport) | H4: Significant | I4: Manual | J4: External | K4: Defect Fixed | L4: Existing_Issues | M4: Existing issue, Some of the account's banks were deleted after mapping, which caused a null reference error. For now, this has been fixed by adding a null check. We will create a new story to prevent deletion of mapped banks.
A5: 4 | B5: MSB Accounting | C5: SRX28805 | E5: Karthik | F5: Defect | G5: MSB ACCT - BKK - Add Print Groups to GL Accounts (Kingsport) | H5: Significant | I5: Manual | J5: External | K5: Defect Fixed | L5: Existing_Issues | M5: Some of the account's banks were deleted after mapping, which caused a null reference error while updating the print groups for those accounts. This issue was already fixed as part of the earliest defect, However, we applied a data fix by updating the print groups to resolve the existing blocker for the customer.
A6: 5 | B6: MSB Accounting | C6: SRX28823 | E6: Karthik | F6: Defect | G6: DUR - MSB ACCT - BKK - Diamond Bar High School (DBH) - Hide October & November MSB Import Batches | H6: Significant | I6: Manual | J6: External | K6: Defect Fixed | L6: Existing_Issues | M6: This is not an issue, It is a customer data fix request. Since the MSB imported batches were manually manually entered in the bank deposit, the customer wanted to hide them on the import MSB screen We have applied a data fix for this.
A7: 6 | B7: MSB Accounting | C7: SRX28830 | E7: Karthik | F7: Defect | G7: DUR - MSB ACCT - REC - Carpinteria High School (CPHS) - Cannot import some batches from Receipting | H7: Significant | I7: Manual | J7: External | K7: Defect Being Fixed | L7: Existing_Issues | M7: Existing issue with vendor object mapping for refund check types. A code fix is required, so we may need to provide a hotfix based on the customer's requirement. Details have been shared with Jeanette, and she will confirm the next steps.
A8: 7 | B8: MSB Accounting | C8: SRX28834 | E8: Karthik | F8: Defect | G8: DUR - MSB ACCT - BKK - Carpinteria High School (CPHS) - Hide Batch Seq # 423 and 424 | H8: Significant | I8: Manual | J8: External | K8: Defect Ready For Testing | L8: Existing_Issues | M8: This issue related to previous escalation SRX28830. Since it needs code fix, customer has entered data manually for the issue caused batch. So we made data fix to hide those batches on import from receipting screen. Waiting for customers confirmation.

Sheet 26.3 Sprint 2-Status
A1: S.No | B1: Application Name | C1: Sprint Start Date | D1: Sprint End Date | E1: Sprint | F1: Developer | G1: Story ID/Defect ID | H1: Description | I1: Status | J1: Estimated(sp) | K1: Actual(sp) | L1: Actual Hours Worklog | M1: Dev Start Date | N1: Dev End Date | O1: Unit testing | P1: Peer Tested By | Q1: Peer Tested Comments, if any | R1: Peer Reviewed By | S1: Peer Code Review Comments, if any | T1: PR Number/Link | U1: PR Created Date | V1: PR Approved Date | W1: Onsite Lead Code Review | X1: Onsite Lead Code Review Comments, if any | Y1: Client Code Review | Z1: PR Approved Date2 | AA1: Client Code Review Comments, if any | AB1: Internal PO -POV Comments | AC1: Client PO -POV Comments | AD1: Comments | AE1: Story met clarity expectations? | AF1: 46064 | AG1: 46065 | AH1: 46066 | AI1: 46069 | AJ1: 46070 | AK1: 46071 | AL1: 46072 | AM1: 46073 | AN1: 46076 | AO1: 46077
A2: 1 | B2: MSB Accounting | C2: 2/11//2026 | D2: 46077 | E2: MSB Accounting 26.3 Sprint 2 | F2: Sowjanya | G2: 51706 | H2: 51706 MSB ACCT - BKK - Automation Smoke Tests - School Settings UI in Management | I2: Story Peer Review | J2: 2 | K2: 2.5 | L2: 10 | M2: 46064 | N2: 46073 | O2: NA | P2: Pass | Q2: Pass | R2: Pass | S2: Pass | T2: https://dev.azure.com/heartlandschools/Accounting/_git/AccountingAutomation/pullrequest/47192?_a=files | U2: 46328 | V2: NA | W2: Done | X2: Why is this being used and not LandingPage. LoginAccounting? And told to remove the unused files | Y2: Done | Z2: 46073 | AA2: Pass | AB2: Pass | AC2: For demo have created a seperate file told me to remove the file He told to create The API will allow us to upload the CSV file to browser stack, It will return a URL to the file. What we do is point to that URL and it will upload it. | AD2: Have created PR on Monday and still waiting for Client approval | AE2: Meets Expectation | AF2: Have completed the management menu and created the PR- | AG2: He made a comment on the code | AH2: Had replied to his comment and started writing testcase for the defect and then analysing the onboarding stories | AI2: Sowjanya on PTO | AJ2: Review comment by Owen - "should be using the Login that is in the landingpage and not the common one.." | AK2: Have completed the changes beacuse of the intergration it got delayed need to run the code see Debv Completed. Challenges with integration of MSB District. Final round of testing pending | AL2: While testing found error in Support tools fixed .Have pushes the changes and informed Owen to approve | AM2: He instructed me to modify the code format in the same way he had guided Sushmitha. He also advised uploading the CSV file using the App Automate API , retrieving the generated URL, and using that URL for testing purposes | AN2: Updated client POV comments. Need to discuss about Automate API. | AO2: Updated Code based on Owen's code changes. Waiting for approval
A3: 2 | B3: MSB Accounting | C3: 2/11//2026 | D3: 46077 | E3: MSB Accounting 26.3 Sprint 2 | F3: Rijo | G3: 26212 | H3: MSB ACCT - BKK - [Regression] Bank Deposit Entry not fetching the Notes to UI saved earlier into the field upon editing | I3: Defect Rejected | J3: 3 | K3: 0.5 | L3: 2 | M3: 46064 | N3: 46064 | O3: NA | P3: NA | Q3: NA | R3: NA | S3: NA | T3: NA | U3: NA | V3: NA | W3: NA | X3: NA | Y3: NA | Z3: NA | AA3: NA | AB3: NA | AC3: NA | AD3: Issue is not replicating now on any environments including in local. This was a defect from earlier regression. Rejecting the defect since it's not happening now. | AE3: Meets Expectation | AF3: not able to replicate | AG3: not able to replicate | AH3: not able to replicate. Waiting for Pramod to reject the defect. | AI3: not able to replicate. Waiting for Pramod to reject the defect. | AJ3: - | AK3: - | AL3: - | AM3: - | AN3: - | AO3: -
A4: 3 | B4: MSB Accounting | C4: 2/11//2026 | D4: 46077 | E4: MSB Accounting 26.3 Sprint 2 | F4: Karthik | G4: 25287 | H4: MSB ACCT - BKK - Vendor Category Does Not Pre-Populate on PO's, Invoices, or Manual Checks | I4: Defect Fixed | J4: 2 | K4: 3.93 | L4: 15.75 | M4: 46064 | N4: 46064 | O4: Completed | P4: Rijo | Q4: Pass | R4: Qadir | S4: Pass | T4: https://dev.azure.com/heartlandschools/Accounting/_git/MSBAccounting-NewSchoolBooks/pullrequest/47235 | U4: 46065 | V4: 46065 | W4: Pass | X4: Done | Y4: Done | Z4: NA | AA4: Pass | AB4: Pass | AC4: Pass | AE4: Meets Expectation | AF4: Completed Dev Testing. 4 more issues. - All related to dropdown selection change. Waiting on POV. | AG4: Waiting on Jeanette's approval. peer testing in progress | AH4: PR completed. Waiting for dev deployment. | AI4: Deployed to Dev. Ready for testing. | AJ4: Doing final round of testing Found an issue with the adding an item | AK4: Completed Testing in Dev Environment | AL4: - | AM4: - | AN4: - | AO4: -
A5: 4 | B5: MSB Accounting | C5: 2/11//2026 | D5: 46077 | E5: MSB Accounting 26.3 Sprint 2 | F5: Rijo | G5: 25160 | H5: MSB ACCT - BKK - Trial Balance Header Line Only Shows on First Page | I5: Defect Fixed | J5: 2 | K5: 2.5 | L5: 10 | M5: 46064 | N5: 46064 | O5: Completed | P5: Karthik | Q5: Pass | R5: Qadir | S5: Pass | T5: https://dev.azure.com/heartlandschools/Accounting/_git/MSBAccounting-NewSchoolBooks/pullrequest/47298 | U5: 46070 | V5: 46070 | W5: Pass | X5: Done | Y5: Done | Z5: NA | AA5: Pass | AB5: Pass | AC5: Pass | AD5: Defect closed. | AE5: Meets Expectation | AF5: Fix completed. Waiting on POV. | AG5: Waiting on POV with Pramod | AH5: Waiting on POV with Pramod | AI5: Waiting on POV with Pramod | AJ5: Waiting on jeanette to approve. Waiting on Qaditr to review | AK5: Waiting on Deployment to DEV. Automated Dev deployment failed. | AL5: Have Completed testing in dev and closed the defect | AM5: - | AN5: - | AO5: -
A6: 5 | B6: MSB Accounting | C6: 2/11//2026 | D6: 46077 | E6: MSB Accounting 26.3 Sprint 2 | F6: Qadir | G6: 51683 | H6: MSB ACCT - Improve DB Performance - Create / Drop Indexes | I6: Story Completed | J6: 3 | K6: 6.75 | L6: 27 | M6: 46064 | N6: 46073 | O6: Completed | P6: Karthik | Q6: Pass | R6: Karthik | S6: Pass | T6: https://dev.azure.com/heartlandschools/Accounting/_git/MSBAccounting-NewSchoolBooks/pullrequest/47403 | U6: 46073 | V6: 46073 | W6: Pass | X6: Done | Y6: Done | Z6: NA | AA6: Pass | AB6: Need justification for removing the indexes. | AC6: Pass | AE6: Meets Expectation | AF6: Code Cleanup Completed. Still Dev testing. POV with Pramod. | AG6: Had a POV with pramod. Need justification for removing the indexes. | AH6: ___ | AI6: Qadir on PTO | AJ6: Shared the POV with jeanette. | AK6: Karthik Reviewed and tested. | AL6: - | AM6: Deployed to DEV | AN6: Testing in Progress | AO6: Testing completed
A7: 6 | B7: MSB Accounting | C7: 2/11//2026 | D7: 46077 | E7: MSB Accounting 26.3 Sprint 2 Stretch | F7: Rijo | G7: 25868 | H7: MSB ACCT - BKK - Payments disappear for the other schools in a shared gateway batch if one school claims their payments | I7: Defect Rejected | J7: 3 | K7: 3.75 | L7: 15 | M7: 46065 | N7: 46069 | O7: NA | P7: NA | Q7: NA | R7: NA | S7: NA | T7: NA | U7: NA | V7: NA | W7: NA | X7: NA | Y7: NA | Z7: NA | AA7: NA | AB7: NA | AC7: NA | AD7: This defect was reported 1 year back. We recently changed all background process for Import MSB batches as part of Performance improvement. The issue is not happening now, and we are rejecting this defect. | AE7: Meets Expectation | AG7: Unable to replicate. complex scenario. Will try to replicate . PotentiallyDefect Rejected? | AH7: Still not able to replicate. Will check with Pramod to potentially reject this defect. | AI7: not able to replicate. Waiting for Pramod to reject the defect. | AJ7: - | AK7: - | AL7: - | AM7: - | AN7: -
A8: 7 | B8: MSB Accounting | C8: 2/11//2026 | D8: 46077 | E8: MSB Accounting 26.3 Sprint 2 Stretch | F8: Karthik | G8: 25674 | H8: MSB ACCT - BKK - [Regression] Trial Balance Report data not matching with CSV file while "Use GL Print Groups" is checked | I8: Defect Fixed | J8: 3 | K8: 3.5 | L8: 14 | M8: 46065 | N8: 46066 | O8: Completed | P8: Rijo | Q8: Pass | R8: Qadir | S8: Pass | T8: https://dev.azure.com/heartlandschools/Accounting/_git/MSBAccounting-NewSchoolBooks/pullrequest/47266 | U8: 46069 | V8: 46069 | W8: Pass | X8: Done | Y8: Done | Z8: NA | AA8: Pass | AB8: Pass | AC8: Pass | AE8: Meets Expectation | AG8: Completed Dev changes. Will connect with pramod for POV. | AH8: Completed POV and shared details for review. | AI8: PR completed, waiting for deployment. | AJ8: Ready for Testing | AK8: Testing completed | AL8: - | AM8: - | AN8: -
A9: 8 | B9: MSB Accounting | C9: 2/11//2026 | D9: 46077 | E9: MSB Accounting 26.3 Sprint 2 | F9: Rijo | G9: SRX28739 | H9: MSB BKK - Martinez USD - Alhambra HS - Wrong Total on Batch Import | I9: Defect Fixed | J9: 0 | K9: 0.37 | L9: 1.5 | M9: 46064 | N9: 46064 | O9: Completed | P9: Karthik | Q9: Pass | R9: Qadir | S9: Pass | T9: NA | U9: NA | V9: NA | W9: NA | X9: NA | Y9: NA | Z9: NA | AA9: NA | AB9: NA | AC9: NA | AD9: No code changes and PR. Update query ran on production db, verified the fix and closed escalation. | AE9: Meets Expectation | AF9: Worked on this | AG9: - | AH9: - | AI9: - | AJ9: - | AK9: - | AL9: - | AM9: - | AN9: -
A10: 9 | B10: MSB Accounting | C10: 2/11//2026 | D10: 46077 | E10: MSB Accounting 26.3 Sprint 2 | F10: Karthik | G10: 51859 | H10: MSB Onboarding - Navigating in and out of Merchant Applications | I10: Story Completed | J10: 3 | K10: 4.37 | L10: 17.5 | M10: 46066 | N10: 46069 | O10: Completed | P10: Qadir | Q10: Pass | R10: Qadir | S10: Pass | T10: https://dev.azure.com/heartlandschools/Merchant/_git/Boarding/pullrequest/47375 | U10: NA | V10: NA | W10: NA | X10: NA | Y10: NA | Z10: NA | AA10: NA | AB10: NA | AC10: NA | AE10: Meets Expectation | AH10: Started analysing, Need some clarifications about AC. Will discuss in the catchup. | AI10: Completed dev changes. Will connect with Pramod for POV. | AJ10: Completed POV . Waiting on jeanette's approval. Qadir to do peer testing/ peer review | AK10: Qadir facing issues with Onboarding DB to test | AL10: Qadir Approved | AM10: Have completed writing tescase and started testing | AN10: Completed testing in Dev amd QA environment
A11: 10 | B11: MSB Accounting | C11: 2/11//2026 | D11: 46077 | E11: MSB Accounting 26.3 Sprint 2 Stretch | F11: Rijo | G11: 25659 | H11: MSB ACCT - BKK - [Regression] Error while saving the note while reversal for cash transfer entry | I11: Defect Ready For Testing | J11: 5 | K11: 3 | L11: 12 | M11: 46070 | N11: 46071 | O11: Completed | P11: Karthik | Q11: Pass | R11: Qadir | S11: Pass | T11: https://dev.azure.com/heartlandschools/Accounting/_git/MSBAccounting-NewSchoolBooks/pullrequest/47379 | U11: 46072 | V11: 46072 | W11: Pass | X11: Done | Y11: Done | Z11: NA | AA11: Pass | AB11: Pass | AC11: Pass | AD11: Defect Ready For Testing | AE11: Meets Expectation | AJ11: Waiting on Pramod for POV. | AK11: Waiting on POV with Pramod | AL11: Completed Testcase. | AM11: Ready for Testing | AN11: Ready for Testing
A12: 11 | B12: MSB Accounting | C12: 2/11//2026 | D12: 46077 | E12: MSB Accounting 26.3 Sprint 2 Stretch | F12: Karthik | G12: 44176 | H12: MSB Onboarding - Encrypt Routing, Account Numbers, and SSN | I12: Product Owner - Verify | J12: 5 | K12: 6.31 | L12: 25.25 | M12: 46070 | N12: 46077 | O12: Completed | P12: NA | Q12: NA | R12: NA | S12: NA | T12: NA | U12: NA | V12: NA | W12: NA | X12: NA | Y12: NA | Z12: NA | AA12: NA | AB12: NA | AC12: NA | AE12: Meets Expectation | AJ12: Started working on this.need some clarity on some parts of this story. | AK12: not much progress today. Escalation was in focus | AL12: Applying to add/edit functionality. We need a migration for the code to encrypt and decrypt. | AM12: Completed Encryption changes Added changes in the DB context. Migration changes need to be added. | AN12: Working on migration, Changes made in global.asax
A13: 12 | B13: MSB Accounting | C13: 2/11//2026 | D13: 46077 | E13: MSB Accounting 26.3 Sprint 2 | F13: Karthik | G13: SRX28768 | H13: MSB ACCT - BKK - Bank Rec Report Preview Shows Duplicate Line Items (Kingsport) | I13: Defect Fixed | J13: 0 | K13: 1 | L13: 4 | M13: 46071 | N13: 46071 | O13: NA | P13: NA | Q13: NA | R13: NA | S13: NA | T13: NA | U13: NA | V13: NA | W13: NA | X13: NA | Y13: NA | Z13: NA | AA13: NA | AB13: NA | AC13: NA | AD13: Production data fix. No code changes and PR. | AE13: Meets Expectation | AK13: Issue with a deleted bank in the database. We need to hard delete. | AL13: Waiting on Confirmation from PROD. | AM13: Waiting on Confirmation from PROD. | AN13: Still waiting on Customer confirmation
A14: 13 | B14: MSB Accounting | C14: 2/11//2026 | D14: 46077 | E14: MSB Accounting 26.3 Sprint 2 Stretch | F14: Rijo | G14: 49951 | H14: MSB ACCT - BKK - Lock the School Year "Start Date" and "End Date" from changing after first Bank reconciliation | I14: Story Peer Review | J14: 3 | K14: 4.12 | L14: 16.5 | M14: 46071 | N14: 46073 | O14: Completed | P14: Karthik | Q14: Pass | R14: NA | S14: NA | T14: NA | U14: NA | V14: NA | W14: NA | X14: NA | Y14: NA | Z14: NA | AA14: NA | AB14: NA | AC14: NA | AD14: Code changes and POV completed. Waiting for peer review to create PR. | AE14: Meets Expectation | AK14: Lockign part completed. Working on the alert on bank rec. | AL14: ready for POV. Waiting for Pramod. | AN14: Waiting on Client POV.
A15: 14 | B15: MSB Accounting | C15: 2/11//2026 | D15: 46077 | E15: MSB Accounting 26.3 Sprint 2 Stretch | F15: Rijo | G15: 51861 | H15: MSB Onboarding - Capturing Tax and Federal Eligibility | I15: Story Being Developed | J15: 3 | K15: 2.25 | L15: 9 | M15: 46073 | N15: NA | O15: NA | P15: NA | Q15: NA | R15: NA | S15: NA | T15: NA | U15: NA | V15: NA | W15: NA | X15: NA | Y15: NA | Z15: NA | AA15: NA | AB15: NA | AC15: NA | AD15: Development is in progress | AE15: Meets Expectation | AL15: Just picked it up. running the application locally. | AN15: Discussion with pramod. Clarification with James. Need to redesign the page.
A16: 15 | B16: MSB Accounting | C16: 2/11//2026 | D16: 46077 | E16: MSB Accounting 26.3 Sprint 2 Stretch | F16: Qadir | G16: 26818 | H16: MSB ACCT - Account Report Detail Not Consistently Ordering Transactions Under GLs | I16: Story Being Developed | J16: 5 | K16: 2.37 | L16: 9.5 | M16: 46072 | N16: NA | O16: NA | P16: NA | Q16: NA | R16: NA | S16: NA | T16: NA | U16: NA | V16: NA | W16: NA | X16: NA | Y16: NA | Z16: NA | AA16: NA | AB16: NA | AC16: NA | AE16: Meets Expectation | AL16: Account Detail Report. | AN16: Dev Completed

Sheet 26.3 Sprint 3-Status
A1: S.No | B1: Application Name | C1: Sprint Start Date | D1: Sprint End Date | E1: Sprint | F1: Developer | G1: Story ID/Defect ID | H1: Description | I1: Status | J1: Estimated(sp) | K1: Actual(sp) | L1: Actual Hours Worklog | M1: Dev Start Date | N1: Dev End Date | O1: Unit testing | P1: Peer Tested By | Q1: Peer Tested Comments, if any | R1: Peer Reviewed By | S1: Peer Code Review Comments, if any | T1: PR Number/Link | U1: PR Created Date | V1: PR Approved Date | W1: Onsite Lead Code Review | X1: Onsite Lead Code Review Comments, if any | Y1: Client Code Review | Z1: PR Approved Date2 | AA1: Client Code Review Comments, if any | AB1: Internal PO -POV Comments | AC1: Client PO -POV Comments | AD1: Comments | AE1: Story met clarity expectations? | AF1: 46078 | AG1: 46079 | AH1: 46080 | AI1: 46083 | AJ1: 46084 | AK1: 46085 | AL1: 46086 | AM1: 46087 | AN1: 46090 | AO1: 46091
A2: 1 | B2: MSB Accounting | C2: 46078 | D2: 46091 | E2: MSB Accounting 26.3 Sprint 3 | F2: Rijo | G2: 25659 | H2: MSB ACCT - BKK - [Regression] Error while saving the note while reversal for cash transfer entry | I2: Defect Fixed | J2: 2 | K2: 1.5 | L2: 6 | M2: NA | N2: NA | O2: NA | P2: NA | Q2: NA | R2: NA | S2: NA | T2: NA | U2: NA | V2: NA | W2: NA | X2: NA | Y2: NA | Z2: NA | AA2: NA | AB2: NA | AC2: NA | AD2: Only testing scope in this sprint. Testing completed and closed story. | AE2: Meets Expectation | AF2: Completed testing and story closed. | AG2: - | AH2: - | AI2: - | AJ2: - | AK2: - | AL2: - | AM2: - | AN2: -
A3: 2 | B3: MSB Accounting | C3: 46078 | D3: 46091 | E3: MSB Accounting 26.3 Sprint 3 | F3: Rijo | G3: 51861 | H3: MSB Onboarding - Capturing Tax and Federal Eligibility | I3: Product Owner - Verify | J3: 3 | K3: 5 | L3: 20 | M3: 46078 | N3: 46080 | O3: Completed | P3: NA | Q3: NA | R3: NA | S3: NA | T3: NA | U3: NA | V3: NA | W3: NA | X3: NA | Y3: NA | Z3: NA | AA3: NA | AB3: NA | AC3: NA | AD3: Dev work and internal POV completed on 3/3. Waiting for POV approval from client PO. | AE3: Meets Expectation | AF3: Made some UI changes. Will continue with dev work. | AG3: Dev Completed. | AH3: Ready for POV . Will do POV with Pramod on monday | AI3: Waiting for Pramod for the POV. | AJ3: Started Writing testcase | AK3: Waiting for jeanette's approval Waiting on a few clarifications on the POV. | AL3: Still waiting for jeanette's approval | AM3: Still waiting for jeanette's approval | AN3: Still waiting for jeanette's approval Got comments on this verbally about the image and the file upload.
A4: 3 | B4: MSB Accounting | C4: 46078 | D4: 46091 | E4: MSB Accounting 26.3 Sprint 3 | F4: Client Dev | G4: 51856 | H4: MSB Onboarding - Log In Page Display and Button Updates | I4: Story Completed | J4: 1 | K4: 2.25 | L4: 9 | M4: NA | N4: NA | O4: NA | P4: NA | Q4: NA | R4: NA | S4: NA | T4: NA | U4: NA | V4: NA | W4: NA | X4: NA | Y4: NA | Z4: NA | AA4: NA | AB4: NA | AC4: NA | AD4: Worked by client dev. Only testing effort. | AE4: Meets Expectation | AF4: Completed Testcase | AH4: Waiting on Client POV approval | AI4: While tesing found few thing as mismatching with figma .need to be clarified | AJ4: When I reached out a while ago on this one, I was told this page isn't designed by the UX team. so jeanette told to push this story to her name | AK4: Waiting on PO for image. | AL4: As discussed in call checked the functioality and closed the story | AM4: - | AN4: -
A5: 4 | B5: MSB Accounting | C5: 46078 | D5: 46091 | E5: MSB Accounting 26.3 Sprint 3 | F5: Rijo | G5: 49951 | H5: MSB ACCT - BKK - Lock the School Year "Start Date" and "End Date" from changing after first Bank reconciliation | I5: Story Completed | J5: 2 | K5: 1.31 | L5: 5.25 | M5: NA | N5: NA | O5: NA | P5: NA | Q5: NA | R5: NA | S5: NA | T5: NA | U5: NA | V5: NA | W5: NA | X5: NA | Y5: NA | Z5: NA | AA5: NA | AB5: NA | AC5: NA | AD5: PR was completed last sprint. Testing effort only. | AE5: Meets Expectation | AG5: Completed Testcase andTesting is in progress | AH5: Completed | AI5: - | AJ5: - | AK5: - | AL5: - | AM5: - | AN5: -
A6: 5 | B6: MSB Accounting | C6: 46078 | D6: 46091 | E6: MSB Accounting 26.3 Sprint 3 | F6: Sowjanya | G6: 51706 | H6: 51706 MSB ACCT - BKK - Automation Smoke Tests - School Settings UI in Management | I6: Story Completed | J6: 1 | K6: 0.25 | L6: 1 | M6: NA | N6: NA | O6: NA | P6: NA | Q6: NA | R6: NA | S6: NA | T6: NA | U6: NA | V6: NA | W6: NA | X6: NA | Y6: NA | Z6: NA | AA6: NA | AB6: NA | AC6: NA | AD6: DEV work and PR creation was completed last sprint. PR got approved and story closed. | AE6: Meets Expectation | AG6: Checked whether each and every testcases are running without any error-Need to check one thing with owen after that will change the status to Peer review | AH6: Waiting on Client POV. | AI6: Completed | AJ6: - | AK6: - | AL6: - | AM6: - | AN6: -
A7: 6 | B7: MSB Accounting | C7: 46078 | D7: 46091 | E7: MSB Accounting 26.3 Sprint 3 | F7: Qadir | G7: 49703 | H7: 49703 MSB ACCT - BKK - Add a button for starting the Year End Process | I7: Story Completed | J7: 2 | K7: 8.31 | L7: 33.25 | M7: 46078 | N7: 46080 | O7: Completed | P7: Rijo | Q7: Warning icon is missing in popup. The symbols are flashing on the screen at page load time. | R7: Rijo | S7: Move the repeating message from js to xml file. | T7: https://dev.azure.com/heartlandschools/Accounting/_git/MSBAccounting-NewSchoolBooks/pullrequest/47608 | U7: 46085 | V7: 46085 | W7: Done | X7: Pass | Y7: Done | Z7: NA | AA7: Pass | AB7: Pass | AC7: Pass | AE7: Meets Expectation | AG7: dev Complete. POV pending. | AH7: POV completed. Dev changes based on POV completed. new POV video to be created. | AK7: peer review comments fixes made. | AL7: The first round of functionality testing is completed, and I am currently working on the test cases. | AM7: Unable to verify error message. - When we have multiple due to Student Body Account, is active a warning popup is displayed. After clicking ‘OK’, the popup closes; however, the Year-End Processing continues to load and the status remains ‘In Progress.
A8: 7 | B8: MSB Accounting | C8: 46078 | D8: 46091 | E8: MSB Accounting 26.3 Sprint 3 | F8: Qadir | G8: 26818 | H8: MSB ACCT - Account Report Detail Not Consistently Ordering Transactions Under GLs | I8: Defect Fixed | J8: 3 | K8: 1.75 | L8: 7 | M8: 46078 | N8: 46079 | O8: Completed | P8: Rijo | Q8: Pass | R8: Rijo | S8: Pass | T8: https://dev.azure.com/heartlandschools/Accounting/_git/MSBAccounting-NewSchoolBooks/pullrequest/47525 | U8: 46079 | V8: 46079 | W8: Done | X8: Pass | Y8: Done | Z8: NA | AA8: Pass | AB8: Pass | AC8: Pass | AE8: Meets Expectation | AG8: Shared POV with Jeanette for approval | AH8: Completed Testing and closed | AI8: - | AJ8: - | AK8: - | AL8: - | AM8: - | AN8: -
A9: 8 | B9: MSB Accounting | C9: 46078 | D9: 46091 | E9: MSB Accounting 26.3 Sprint 3 | F9: Client Dev | G9: 51860 | H9: MSB Onboarding - Managing a Variety of User Journeys Using the Left Nav within Application | I9: Story Being Tested | J9: 2 | K9: 1.12 | L9: 4.5 | M9: NA | N9: NA | O9: NA | P9: NA | Q9: NA | R9: NA | S9: NA | T9: NA | U9: NA | V9: NA | W9: NA | X9: NA | Y9: NA | Z9: NA | AA9: NA | AB9: NA | AC9: NA | AD9: Worked by client dev. Only testing effort. | AE9: Meets Expectation | AH9: Testing in Progress. Getting error when we navigate to district informations.Created a bounce back | AI9: District Information page navigation is missing. Assigned back to developer | AJ9: Waiting on client dev changes | AK9: Waiting on client dev changes | AL9: - | AM9: - | AN9: waiting on client Dev changes. | AO9: When we click on District information the details like Eligiblity is missing
A10: 9 | B10: MSB Accounting | C10: 46078 | D10: 46091 | E10: MSB Accounting 26.3 Sprint 3 | F10: Rijo | G10: 26207 | H10: MSB ACCT - BKK - [Regression] Invoice Item details does not fetch "Account" and "Authorized By" from referenced PO | I10: Defect Fixed | J10: 3 | K10: 4.5 | L10: 18 | M10: 46083 | N10: 46084 | O10: Completed | P10: Qadir | Q10: Pass | R10: Qadir | S10: Pass | T10: https://dev.azure.com/heartlandschools/Accounting/_git/MSBAccounting-NewSchoolBooks/pullrequest/47609 | U10: 46085 | V10: 46085 | W10: Done | X10: Pass | Y10: Done | Z10: NA | AA10: Pass | AB10: Pass | AC10: Pass | AE10: Meets Expectation | AI10: Dev changes completed, will be doing POV with Pramod soon. | AJ10: Have completed writing Testcase | AK10: Waiting for Review | AL10: Have completed testing | AM10: Testing completed | AN10: -
A11: 10 | B11: MSB Accounting | C11: 46078 | D11: 46091 | E11: MSB Accounting 26.3 Sprint 3 | F11: Client Dev | G11: 51857 | H11: MSB Onboarding - Home Page to Start, Manage, and View Applications | I11: Story Being Developed | J11: 2 | K11: 1 | L11: 4 | M11: NA | N11: NA | O11: NA | P11: NA | Q11: NA | R11: NA | S11: NA | T11: NA | U11: NA | V11: NA | W11: NA | X11: NA | Y11: NA | Z11: NA | AA11: NA | AB11: NA | AC11: NA | AD11: Worked by client dev. Only testing effort. | AE11: Meets Expectation | AJ11: Have completed writing Testcase- Received the color scheme and image for completed applications that was originally missed and added it to the description above. so push bach to jeanette | AK11: Waiting on POV commnent changes | AL11: Waiting on Client Dev for changes | AM11: Waiting on Client Dev for changes
A12: 11 | B12: MSB Accounting | C12: 46078 | D12: 46091 | E12: MSB Accounting 26.3 Sprint 3 Stretch | F12: Rijo | G12: 51841 | H12: MSB ACCT - BKK - Improvize "Get MSB Batch Payments tool" to avoid adding the missing payments more than once | I12: Product Owner - Verify | J12: 5 | K12: 5 | L12: 20 | M12: 46084 | N12: 46090 | O12: Completed | P12: NA | Q12: NA | R12: NA | S12: NA | T12: NA | U12: NA | V12: NA | W12: NA | X12: NA | Y12: NA | Z12: NA | AA12: NA | AB12: NA | AC12: NA | AD12: POV completed with Pramod. Waiting for approval from Client PO. | AE12: Meets Expectation | AK12: Still trying to replicate the duplicate batches give user option to replace batch if amounts dont match up. | AM12: Able to replicate issue. Made fix. POV pending | AN12: Ready for POV - Waiting on Pramod.
A13: 12 | B13: MSB Accounting | C13: 46078 | D13: 46091 | E13: MSB Accounting 26.3 Sprint 3 | F13: Karthik | G13: SRX28794 | H13: MSB ACCT - BKK - Remove Duplicate Adjustment Entries from Bank Rec Report Preview (Kingsport) | I13: Defect Fixed | J13: 0 | K13: 1.75 | L13: 6.5 | M13: 46086 | N13: 46086 | O13: NA | P13: NA | Q13: NA | R13: NA | S13: NA | T13: NA | U13: NA | V13: NA | W13: NA | X13: NA | Y13: NA | Z13: NA | AA13: NA | AB13: NA | AC13: NA | AD13: Production data fix. No code changes and PR. | AE13: Meets Expectation | AL13: Completed data fix script and shared with team for review. Also requested latest DB backup to verify the fix in local. | AM13: Got Prod copy data. need to verify there, | AN13: PQuery Executed in PROD.
A14: 13 | B14: MSB Accounting | C14: 46078 | D14: 46091 | E14: MSB Accounting 26.3 Sprint 3 | F14: Qadir | G14: 44176 | H14: MSB Onboarding - Encrypt Routing, Account Numbers, and SSN | I14: Story Being Tested | J14: 3 | K14: 4.12 | L14: 16.5 | M14: 46080 | N14: 46085 | O14: NA | P14: NA | Q14: NA | R14: NA | S14: NA | T14: NA | U14: NA | V14: NA | W14: NA | X14: NA | Y14: NA | Z14: NA | AA14: NA | AB14: NA | AC14: NA | AE14: Meets Expectation | AM14: Issue with deploymnet, missing web.config changes. | AN14: web.config changes added.
A15: 14 | B15: MSB Accounting | C15: 46078 | D15: 46091 | E15: MSB Accounting 26.3 Sprint 3 Stretch | F15: Karthik | G15: 26889 | H15: MSB ACCT - BKK - Cannot Add Print Groups to GL Account (Kingsport) | I15: Defect Ready For Testing | J15: 2 | K15: 1.56 | L15: 6.25 | M15: 46087 | N15: 46090 | O15: Completed | P15: Rijo | Q15: Pass | R15: Qadir | S15: Pass | T15: https://dev.azure.com/heartlandschools/Accounting/_git/MSBAccounting-NewSchoolBooks/pullrequest/47717 | U15: 46091 | V15: 46091 | W15: Done | X15: Pass | Y15: Done | Z15: NA | AA15: Pass | AB15: Pass | AC15: Pass | AE15: Meets Expectation | AM15: Dev Completed. POV pending | AN15: POV completed. Print Group lisitng order. Waiting on jeanette's approval.
A16: 15 | B16: MSB Accounting | C16: 46078 | D16: 46091 | E16: MSB Accounting 26.3 Sprint 3 Stretch | F16: Karthik | G16: 52245 | H16: MSB Onboarding - Updating Fav Icon | I16: Story Completed | J16: 1 | K16: 0.5 | L16: 2.25 | M16: 46090 | N16: 46090 | O16: Completed | P16: Rijo | Q16: Pass | R16: Qadir | S16: Pass | T16: https://dev.azure.com/heartlandschools/Merchant/_git/Boarding/pullrequest/47689 | U16: 46090 | V16: 46090 | W16: Done | X16: Pass | Y16: Done | Z16: NA | AA16: Pass | AB16: Pass | AC16: Pass | AE16: Meets Expectation | AN16: POV completed with Pramod.
A17: 16 | B17: MSB Accounting | C17: 46078 | D17: 46091 | E17: MSB Accounting 26.3 Sprint 3 Stretch | F17: Karthik | G17: 26211 | H17: MSB ACCT - BKK - [Regression] Reversal for a Receipt Entry does not display Sales Tax amount in Receipt Report - Sales Tax line | I17: Defect Being Tested | J17: 3 | K17: 1 | L17: 4 | M17: NA | N17: NA | O17: NA | P17: NA | Q17: NA | R17: NA | S17: NA | T17: NA | U17: NA | V17: NA | W17: NA | X17: NA | Y17: NA | Z17: NA | AA17: NA | AB17: NA | AC17: NA | AD17: Unable to replicate this issue. This might have already been fixed earlier as part of the reversal form related changes. So, moving this directly to QA to verify and close. | AE17: Meets Expectation | AN17: Analysis in progress.

Sheet 26.3 Sprint 3-Defect
A1: S.No | B1: Sprint # | C1: Story/Defect ID | D1: Parent Story | E1: Developer | F1: Issue Type | G1: Issue Description | H1: Priority | I1: Defect Source | J1: Type | K1: Status | L1: Root Cause Category | M1: Comments
A2: 1 | B2: MSB Accounting | C2: 25659 | E2: Rijo | F2: Defect | G2: MSB ACCT - BKK - [Regression] Error while saving the note while reversal for cash transfer entry | H2: Significant | I2: Manual | J2: Internal | K2: Defect Fixed | L2: Existing_Issues | M2: Existing issue from the beginning when we got the project. It was reported and added in the back log long time back. Now we are clearing defects from backlog.
A3: 2 | B3: MSB Accounting | C3: 26818 | E3: Qadir | F3: Defect | G3: MSB ACCT - Account Report Detail Not Consistently Ordering Transactions Under GLs | H3: Significant | I3: Manual | J3: Internal | K3: Defect Fixed | L3: Existing_Issues | M3: Existing Issue. This was an edge case issue observed on PROD with the ordering of the report. Unable to replicate locally, however we've added code to make sure it sorts as expected.
A4: 3 | B4: MSB Accounting | C4: 26207 | E4: Rijo | F4: Defect | G4: MSB ACCT - BKK - [Regression] Invoice Item details does not fetch "Account" and "Authorized By" from referenced PO | H4: Significant | I4: Manual | J4: Internal | K4: Defect Fixed | L4: Existing_Issues | M4: Existing issue. The 2 fields were not mapped correctly when creating an invoice by selecting a PO.
A5: 4 | B5: MSB Accounting | C5: SRX28794 | E5: Karthik | F5: Defect | G5: MSB ACCT - BKK - Remove Duplicate Adjustment Entries from Bank Rec Report Preview (Kingsport) | H5: Significant | I5: Manual | J5: External | K5: Defect Fixed | L5: Existing_Issues | M5: Existing issue. Soft deleted bank accounts are causing duplicate entries in the report. We already have a defect for this in the backlog. For now, this issue has been fixed by hard deleting the soft deleted bank accounts in the database.
