Workbook

Sheet Dashboard
A1: Current Sprint | B1: {=INDEX($B$2:$B$97,MATCH(1,(($D$2:$D$97 >=TODAY())*($C$2:$C$97<=TODAY())),0))} -> GGO 8.4.0 Sprint 4 | C1: Current Sprint Sheet | D1: =CONCATENATE(B1,"-Status") -> GGO 8.4.0 Sprint 4-Status | E1: Sprint Start Date | F1: =VLOOKUP($B$1,$B$1:$C$97,2) -> 46156 | G1: Sprint End Date | H1: =VLOOKUP($B$1,$B$1:$D$97,3) -> 46170 | I1: Application Name | J1: GGO Donor Wave | K1: Users | L1: vishnuram.balaji@relevantz.com;charles.rapheal@relevantz.com | M1: Teams Name(GGO Donor_Web_API) | N1: 19:4ae543cca7444593b1d022935b8fb11d@thread.v2
A2: Sprint Type | B2: Sprint # | C2: Sprint Start Date | D2: Sprint End Date | E2: Assigned | F2: Completed | G2: Story points introduced/removed | H2: Sprint Summary | I2: Accomplishments | J2: Remarks | K2: Retro Points (Internal & External) | L2: Data sanity Audit Status | M2: AuditDate | N2: Planned Leaves | O2: Availed Leaves | P2: Backlog Health
A3: =IF(AND($D$1>=C3,$D$1<=D3),"CurrentSprint","NA") -> NA | B3: GGO 7.15.0 Sprint 4 | C3: 45303 | D3: 45316 | E3: 17 | F3: 15 | G3: 7 | J3: Completed all the introduced story in the mid of the sprint | K3: Internal: External:
A4: =IF(AND($D$1>=C4,$D$1<=D4),"CurrentSprint","NA") -> NA | B4: GGO 7.16.0 Sprint 1 | C4: 45317 | D4: 45330 | E4: 17 | F4: 14 | G4: 3 | J4: Actual estimated stories (17pts) got completed from our end with Development and Testing, From Onsite QA (Nate) took time for testing 3 point story because of PRD release and he took half day leave and he got only 4 hrs of time. So from this I would like to say, we should plan to complete the estimated stories 2 days prior, else Nate won't close on the last day of sprint. Introduced Story - 3 point is Development completed, only Testing pending. | K4: Internal: External:
A5: =IF(AND($D$1>=C5,$D$1<=D5),"CurrentSprint","NA") -> NA | B5: GGO 7.16.0 Sprint 2 | C5: 45331 | D5: 45344 | E5: 23 | F5: 22 | G5: 2 | J5: Completed all the stories on time, but we noticed one minor issue in GGO-13703 Bid-18 report on xls and xlsx formats. the column header occupying some aditional column . It require an report engine code changes.verified some other reports also having the same issue and it's an existing issue.completed introduced story as well | K5: Internal: External:
A6: =IF(AND($D$1>=C6,$D$1<=D6),"CurrentSprint","NA") -> NA | B6: GGO 7.16.0 Sprint 3 | C6: 45345 | D6: 45358 | E6: 27 | F6: 23 | G6: 7 | J6: GGO-13801-onsite QA(Nathan) raised one bug , we tried to reproduce the issue on rounding but we are not able to do that. We have asked for the steps to reproduce the issue. GGO-13738 -Development has been completed on this story, it require's IT team support to complete the testing. Introduced Story - 7 points (Except GGO-13738 testing) all completed | K6: Internal: External:
A7: =IF(AND($D$1>=C7,$D$1<=D7),"CurrentSprint","NA") -> NA | B7: GGO 7.16.0 Sprint 4 | C7: 45359 | D7: 45372 | E7: 20 | F7: 16 | G7: 5 | J7: GGO-13796 and GGO-13773 development has been completed.testing requires IT team support to complete,currently salesforce team doing some changes at their side we can't test salesforce api's .Introduced Story - 5 points Develpment has been completed for that. | K7: Internal: External:
A8: =IF(AND($D$1>=C8,$D$1<=D8),"CurrentSprint","NA") -> NA | B8: GGO 7.17.0 Sprint 1 | C8: 45373 | D8: 45386 | E8: 14 | F8: 11 | G8: 3 | J8: Since we need support from sales force team for testing GGO -13773 ,PAPI-702 saranya supported Mike wall for testing We got info from Doug about the 4 PROD issues in planning meeting 1. Convenience Fee Issue - Not able to reproduce by our team and Onsite QA in DEV, TST & CRT, it is occurring only in PRD, finding a way to check the values, settings in PROD to replicate in lower envrionment 2. Package Tax Issue - Round off to whole number instead of 2 decimal, this is our mistake that has got in to PRD 3 months before, when fixing old code to replace SQL CLR to C# method. 3. Item tax added to Package - This was old issue, but many clients started to raise concern about this issue now, because of our new implementation for Convenience Fee. 4. Payment show error when Actually it is success in PAPI for Few Clients in PRD - Still don't know the reason, analysing the root cause of this issue. | K8: Internal: External:
A9: =IF(AND($D$1>=C9,$D$1<=D9),"CurrentSprint","NA") -> NA | B9: GGO 7.17.0 Sprint 2 | C9: 45387 | D9: 45400 | E9: 19 | F9: 17 | G9: 0 | J9: This sprint we fixed production issues and macroscope security issues . PAPI-702 carried because card details need to verified with PAPI database, we don't have required permission for that, only onsite QA need to be verified. | K9: Internal: External:
A10: =IF(AND($D$1>=C10,$D$1<=D10),"CurrentSprint","NA") -> NA | B10: GGO 7.17.0 Sprint 3 | C10: 45401 | D10: 45414 | E10: 18 | F10: 11 | G10: 0 | J10: 2 stories got carried. 1. Due to salesforce team confirmed they can't do any changes. 2. Onshore Testing is pending | K10: Internal: External:
A11: =IF(AND($D$1>=C11,$D$1<=D11),"CurrentSprint","NA") -> NA | B11: GGO 7.17.0 Sprint 4 | C11: 45415 | D11: 45428 | E11: 14 | F11: 4 | G11: 0 | J11: CRT Regression Testing is still in Progress. 3 stores are blocked and carried because of IT dependencey (Certificate Issue and Permission issue for Report Instance folder in DEV & TST Environments), all the development and testing works are done from our end. | K11: Internal: External:
A12: =IF(AND($D$1>=C12,$D$1<=D12),"CurrentSprint","NA") -> NA | B12: GGO 7.18.0 Sprint 1 | C12: 45429 | D12: 45442 | E12: 15 | F12: 14 | G12: 0 | J12: Testing blocked due to certificate issue | K12: Internal: External:
A13: =IF(AND($D$1>=C13,$D$1<=D13),"CurrentSprint","NA") -> NA | B13: GGO 7.18.0 Sprint 2 | C13: 45443 | D13: 45456 | E13: 20 | F13: 16 | G13: 0 | K13: Internal: External:
A14: =IF(AND($D$1>=C14,$D$1<=D14),"CurrentSprint","NA") -> NA | B14: GGO 7.18.0 Sprint 3 | C14: 45457 | D14: 45470 | E14: 17 | F14: 15 | G14: 2 | K14: Internal: External:
A15: =IF(AND($D$1>=C15,$D$1<=D15),"CurrentSprint","NA") -> NA | B15: GGO 7.18.0 Sprint 4 | C15: 45471 | D15: 45484 | E15: 20 | F15: 20 | G15: 0 | K15: Internal: External:
A16: =IF(AND($D$1>=C16,$D$1<=D16),"CurrentSprint","NA") -> NA | B16: GGO 7.19.0 Sprint 1 | C16: 45485 | D16: 45498 | E16: 15 | F16: 15 | G16: 5 | J16: Two stretch stories got carried to next sprint. | K16: Internal: External:
A17: =IF(AND($D$1>=C17,$D$1<=D17),"CurrentSprint","NA") -> NA | B17: GGO 7.19.0 Sprint 2 | C17: 45499 | D17: 45511 | E17: 6 | F17: 6 | G17: 7 | J17: Two stretch stories got carried to next sprint. | K17: Internal: External:
A18: =IF(AND($D$1>=C18,$D$1<=D18),"CurrentSprint","NA") -> NA | B18: GGO 7.19.0 Sprint 3 | C18: 45512 | D18: 45526 | E18: 16 | F18: 16 | G18: 2 | K18: Internal: External:
A19: =IF(AND($D$1>=C19,$D$1<=D19),"CurrentSprint","NA") -> NA | B19: GGO 7.19.0 Sprint 4 | C19: 45527 | D19: 45540 | E19: 17 | F19: 14 | G19: 2 | J19: Automation Regression story got carried over as it was new for Offshore QA and there was some learning curve involved. | K19: Internal: External:
A20: =IF(AND($D$1>=C20,$D$1<=D20),"CurrentSprint","NA") -> NA | B20: GGO 7.20.0 Sprint 1 | C20: 45540 | D20: 45554 | E20: 15 | F20: 13 | G20: 2 | J20: 2 point carry forwarded to next sprint, development and testing completed from our end, but onsite QA didn't complete it. | K20: Internal: External:
A21: =IF(AND($D$1>=C21,$D$1<=D21),"CurrentSprint","NA") -> NA | B21: GGO 7.20.0 Sprint 2 | C21: 45555 | D21: 45568 | E21: 19 | F21: 14 | G21: 2 | J21: GGO-14067 got carried, We are migrating Bid-03 report to new RDLC framework, there is lot of existing logic present in RPT file. we need to exactly replicate same logic in SQL stored procedure for new RDLC format.understanding .rpt file logic is complication involved Peer CRC:0 Onsite CRC: 0 Client CRC: 0 Internal Defects: 0 External Defects: 0 | K21: Internal: External:
A22: =IF(AND($D$1>=C22,$D$1<=D22),"CurrentSprint","NA") -> NA | B22: GGO 7.20.0 Sprint 3 | C22: 45569 | D22: 45582 | E22: 17 | F22: 12 | J22: GGO-14067 got carried, Getting Timeout issue for large records,Suporterwise page breakup and some functionlity in spreadsheetlayout is pending Onsite CRC: 0 Onsite CRC: 0 Client CRC: 0 Internal Defects: 1 External Defects: 0 | K22: Internal: External:
A23: =IF(AND($D$1>=C23,$D$1<=D23),"CurrentSprint","NA") -> NA | B23: GGO 7.20.0 Sprint 4 | C23: 45583 | D23: 45596 | E23: 16 | F23: 13 | I23: 1. Login Page Privacy policy update in MFA login page of GGO application 2. Paymen Receipt in new RDLC replacing form display helps users to download receipt as PDF and send email with attachment. | J23: GGO-14067 got carried, Getting Timeout issue for large records Onsite CRC: 0 Client CRC: 0 Internal Defects: 1 External Defects: 0 | K23: Internal: External:
A24: =IF(AND($D$1>=C24,$D$1<=D24),"CurrentSprint","NA") -> NA | B24: GGO 7.21.0 Sprint 1 | C24: 45597 | D24: 45610 | E24: 18 | F24: 17 | G24: 3/0 | I24: 1.Fixed Timeout issue on Bid-03 RDLC report generation. 2.Completed two tickets introduced in the mid of the sprint | J24: Completed all story points on time Onsite CRC: 0 Client CRC: 0 Internal Defects: 2 External Defects: 0 | K24: Internal: External:
A25: =IF(AND($D$1>=C25,$D$1<=D25),"CurrentSprint","NA") -> NA | B25: GGO 7.21.0 Sprint 2 | C25: 45611 | D25: 45621 | E25: 14 | F25: 11 | I25: 1. Fixed Grid selection issue on Bid-03 RDLC report generation. 2. Fixed Azure Images issue replacing content server url with azure url 3. Investigated GGO to OB Queue flow to replace it with Quartz Job. 4. Allow GGO to validate and support different card card types (JCB, Diners club & Discover Debit) | J25: GGO-13319 story got rolled over due to Azure image access issue and a ticket with Microsoft has been opened​ by IT Onsite CRC: 0 Client CRC: 1 Internal Defects: 0 External Defects: 0 | K25: Internal: External:Rajesh and offshore for continued work on reports Priya, Nathan and Conor for testing a lot of stories and completing them
A26: =IF(AND($D$1>=C26,$D$1<=D26),"CurrentSprint","NA") -> NA | B26: GGO 7.21.0 Sprint 3 | C26: 45622 | D26: 45638 | E26: 14 | F26: 14 | G26: 7/0 | I26: 1. Application images moved in Azure , previously we stored the images in DB as bytes 2. 7.20.1 Successfully deployed to PRD 3. EMV Implementation -completed most of the cardreader functionality | J26: GGO-14325 - BID-06 story is a huge effort and cannot be completed in one sprint, hence it was taken as a strech goal Peer CRC:0 Onsite CRC: 0 Client CRC: 0 Internal Defects: 0 External Defects: 0 | K26: Internal: External:
A27: =IF(AND($D$1>=C27,$D$1<=D27),"CurrentSprint","NA") -> NA | B27: GGO 7.21.0 Sprint 4 | C27: 45639 | D27: 45666 | E27: 24 | F27: 19 | G27: 3/0 | I27: 1. Fixed Duplicate Event X Code issue that was a PROD bug for more than 5 years. 2. Good progress on Bid-06 RDLC update and feel confident in completing it next sprint 3. Popup warning for Convenience fee validation implemented 4. Quartz Job implemented for Bid-06 email flow with our own effort and stored the PDF in Azure. | J27: GGO-14427 - BID-06 - Part-3 story is a huge effort, this has got more than 100 scenario's, so it took more time for testing left out with 2 bugs at the end of sprint (development done for the bugs) only testing pending. Peer CRC:0 Onsite CRC: 0 Client CRC: 0 Internal Defects: 8 External Defects: 0 | K27: Internal: External: Offshore team made great progress on Bid-06 report
A28: =IF(AND($D$1>=C28,$D$1<=D28),"CurrentSprint","NA") -> NA | B28: GGO 7.22.0 Sprint 1 | C28: 45667 | D28: 45680 | E28: 21 | F28: 17 | G28: 4/0 | I28: 1.GGO-14484 Jan 21 Prod Release 2. Successfully completed Bid-06 with new report tool set 3. CRT regression testing completed | J28: GGO-14427 - BID-06 - Part-3 during the CRT testing noticed package item enabled scenario taking too long to complete the report - immediately addressed this Issue. GGO-14483 Completed CRT Release & Regression Testing Peer CRC:0 Onsite CRC: 0 Client CRC: 0 Internal Defects: 6 External Defects: 0 Reason for pending: GGO-14422, PAPI-789 - Development and Testing completed from our end, Pending testing from Nate (Onsite QA) because he was focusing more in CRT regression. GGO-14447 - Automation story completed from our end, pending review from Nate GGO-14450 - A.C change one day prior to Sprint end date, so it got carry forward to next sprint
A29: =IF(AND($D$1>=C29,$D$1<=D29),"CurrentSprint","NA") -> NA | B29: GGO 7.22.0 Sprint 2 | C29: 45681 | D29: 45694 | E29: 18 | F29: 11 | G29: 2/0 | I29: 1.Enhance RSVP Functionality with key features to enable better data gathering and management of attendee info. 2.Azure Thumbnail image creation issue fix - Add this project as part of GGO Solution and build it via Build pipeline and add it to GGO Artifact | J29: Peer CRC:0 Onsite CRC: 0 Client CRC: 0 Internal Defects: 0 External Defects: 1 Testing is pending by Onsite QA and we completed the stories (GGO-14503, GGO-14450) and deployed to TST 2 days prior Sprint end, that's the reason these stories got rolled over to next sprint.
A30: =IF(AND($D$1>=C30,$D$1<=D30),"CurrentSprint","NA") -> NA | B30: GGO 7.22.0 Sprint 3 | C30: 45695 | D30: 45708 | E30: 18 | F30: 8 | I30: 1.Adjust Admission Functionality and Infrastructure(Graph) update 2.Bid-19 and Bid-15 Report Updates | J30: Peer CRC:0 Onsite CRC: 0 Client CRC: 4 Internal Defects: 4 External Defects: 1 Reason for pending: GGO-14504 - The story was given Onisite QA for testing 3 days before the end of Sprint but Onsite QA logged bug on the last day of Thesprint. It was fixed and deployed before sprint prep, QA didn't get time to complete it. GGO-14070 - Development took a lot of time and got completed only on 1 day before Sprint end, the offshore QA logged a minor bug on the last day of sprint, fixed the bug and PR created for review. (Saranya worked on the RDLC report for the first time and there was a learning curve involved which took time)
A31: =IF(AND($D$1>=C31,$D$1<=D31),"CurrentSprint","NA") -> NA | B31: GGO 7.22.0 Sprint 4 | C31: 45709 | D31: 45722 | E31: 20 | F31: 15 | G31: 2/0 | I31: CRT Release & Regression testing for GGO 7.22.0 and PAPI 7.17.0 | J31: Peer CRC:0 Onsite CRC: 0 Client CRC: 0 Internal Defects: 4 External Defects: 0 Reason for pending: GGO-14510 - Bootstrap update - Development and Testing from Offshore got completed, the automation flow broken with this bootstrap update, so Nate created a automation change ticket under this story and this got carry forwarded to next sprint.
A32: NA | B32: GGO 7.23.0 Sprint 1 | C32: 45723 | D32: 45736 | E32: 19 | F32: 19 | G32: 7/0 | I32: Continued EMV Implementation and Infrastructure updates Allowed 19 digit card entry in GGAM, GGO and PAPI Cleared some Macroscope issues in PAPI Fixed cache issue in GGO Accomplishments: Addiitionally completed Developemnt for stretch goal stories | J32: Peer CRC:0 Onsite CRC: 0 Client CRC: 0 Internal Defects: 0 External Defects: 0 | K32: Internal Retro 1. Sathiya/ Rajesh and Saranya for providing help to Priya testing the stories 2. Team for completing all the story points
A33: NA | B33: GGO 7.23.0 Sprint 2 | C33: 45736 | D33: 45750 | E33: 13 | F33: 19 | G33: 10/0 | I33: Completed Duplicate even code story and Invoice import and Invoice Payment Pages story Fixed Quartz Job access issues and Email Queue Issues. Accomplishments: Completing the development and testing for lot of stretch goal stories on the current sprint | J33: Peer CRC:0 Onsite CRC: 0 Client CRC: 0 Internal Defects: 2 External Defects: 0 Pending Story: 2 Stories has been carried forward 1.GGO-14573 -Hard to reproduce in the lower environements. The offshore developers made several attempts to reproduce the issue, but because it’s related to performance, it took a considerable amount of time to replicate. That’s why it got carried over. 2.PAPI-839(Stretch Goal) -Dependency on Onsite QA to complete it(Offshore QA has already completed testing for this story) | K33: Retro: 1.Rajesh for supporting multiple escalation issues 2.Sathiya/ Rajesh and Saranya for covering such a wide spread of stories 3.Priya for completing the testing for the planned as well as lot of stretch jiras
A34: NA | B34: GGO 7.23.0 Sprint 3 | C34: 45751 | D34: 45764 | E34: 22 | F34: 24 | G34: 6/0 | I34: Completed Multiple RSVP Imports Accomplishments: Did some Redis changes which was very challenging and OP to GGO import timeouts(which is a esclation ticket) Completing the development for the stretch goal stories on the current sprint | J34: Peer CRC:0 Onsite CRC: 0 Client CRC: 0 Internal Defects: 1 External Defects: 0 Pending Story: 2 stories has been carried forward which includes 1 stretch PAPI-840(8spt)and GGO-14644[Stretch] -Development for this story was completed three days ahead of the sprint deadline. However, a last-minute AC request from the client required code modifications, which were implemented the timeline.The story was left in Peer Review upon completion, per the client's request to hold it and maintain this branch separately from the CERT branch.Offshore QA has completed verification in the lower environment. The story is now pending validation from Onsite QA. | K34: Rajesh and offshore for taking the redis changes which was very challenging
A35: NA | B35: GGO 7.23.0 Sprint 4 | C35: 45765 | D35: 45778 | E35: 23 | F35: 27 | G35: 5/0 | I35: Accomplishments: Completed CRT testing Completed all planned stories and more Okta 1 Proof of concept Completed more macroscopic stories | J35: Peer CRC:0 Onsite CRC: 0 Client CRC: 0 Internal Defects: 1 External Defects: 0 Pending Story: 2 stories has been carried forward GGO-13722 ->we documented the alternative encryption change, client wanted to add new feature flag based on that need to follow the old and new encryption flow GGO-13723 ->we documented the alternative encryption change, client wanted to add new feature flag based on that need to follow the old and new encryption flow | K35: To the whole team for helping remove all the blockers for testing Rajesh and offshore for helping with the fallback cases Rajesh for assisting with integrating the Okta proof-of-concept
A36: NA | B36: GGO 7.24.0 Sprint 1 | C36: 45779 | D36: 45792 | E36: 19 | F36: 16 | G36: 2/0 | I36: Accomplishments: Old Amex certification testing Nav Bar Updation Fixed Dashboard generation Issue and Enabled Online Bidding for the same Fixed Export Sales issue Completed more macroscopic stories | J36: Peer CRC:0 Onsite CRC: 0 Client CRC: 0 Internal Defects: 0 External Defects: 0 Pending Story: 2 stories has been carried forward GGO-14628->Hard to reproduce in the lower environements. The offshore developers and QA's made several attempts to reproduce the issue, However, on the last day of the sprint,we found one way to reproduce it. But team need to ensure this after providing the solutions and to check whether this the cause of this issue. Team is still working on it.That’s why it got carried over. GGO-14656->Reskin-V2 is a complete overhaul of the existing Master Page. The new layout seamlessly integrates Telerik controls, Bootstrap, and Kendo UI CSS, ensuring an optimized, modern, and adaptive user experience across all devices. As part of this redesign, we need to explore which Telerik control is best suited for the requested layout to achieve the desired functionality and responsiveness. Its taking more time to complete this story | K36: Rajesh and Sathiyabharathi for working on the Nav bar update. Rajesh for helping with the Escalation issue
A37: NA | B37: GGO 7.24.0 Sprint 2 | C37: 45793 | D37: 45806 | E37: 26 | F37: 23 | I37: Accomplishments: Completed Pendo Implementation Completed Nav Bar Implementation Fixed Amex card disable for select organizations Fixed Sale Grid Export issue | J37: Peer CRC:0 Onsite CRC: 0 Client CRC: 0 Internal Defects: 0 External Defects: 0 Pending Story: 1 story has been carried forward GGO-14628->Hard to reproduce in the lower environements. The offshore developers and QA's made several attempts to reproduce the issue. Team is still working on it.That’s why it was put on hold as it is of low priority | K37: Rajesh and Sathiyabharathi for the Nav bar update. Rajesh and offshore team on the quick implementation of pendo. Mike Horihan gave Kudos for the quick Pendo implementation
A38: NA | B38: GGO 7.24.0 Sprint 3 | C38: 45806 | D38: 45820 | E38: 9 | F38: 9 | G38: 3 | I38: Accomplishments: Completed Donor Web APIproject setup Completed Integration test Project setup Completed API Authentication for Donor Web API | J38: Peer CRC:0 Onsite CRC: 0 Client CRC: 0 Internal Defects: 0 External Defects: 0 Pending story: 1 Story has been carried forward GDON-7 -> Stretch | K38: New Donor team for completing the project setup, build issue and the publish fix. They are quick in implementing the changes Rajesh for helping multiple offshore teams and get them all set up and going
A39: NA | B39: GGO 7.24.0 Sprint 4 | C39: 45820 | D39: 45834 | E39: 10 | F39: 10 | G39: 5 | I39: Accomplishments: Completed Account Information for Donor Web API Completed Profile Information for Donor Web API Completed project release and pipeline set up | J39: Peer CRC:0 Onsite CRC: 0 Client CRC: 0 Internal Defects: 0 External Defects: 0 Pending story: 1 Story has been carried forward GDON-11 -> Stretch | K39: Good progress on the Donor API. Donor team dev and QA for completing all the donor team stories
A40: NA | B40: GGO 7.25.0 Sprint 1 | C40: 45834 | D40: 45848 | E40: 8 | F40: 8 | G40: donor | J40: Peer CRC:0 Onsite CRC: 0 Client CRC: 0 Internal Defects: 0 External Defects: 0 Pending story: 2 Story has been carried forward GDON-12 -> Stretch GDON-13 -> Stretch
A41: NA | B41: GGO 7.25.0 Sprint 2 | C41: 45848 | D41: 45862 | E41: 16 | F41: 16 | G41: 2 - Removed 5- Strech (2 Completed , 3 Carried forward) | J41: Peer CRC:0 Onsite CRC: 0 Client CRC: 0 Internal Defects: 0 External Defects: 0 Suggestion: 0 Pending story: 1 Story has been carried forward GDON-28 -> Stretch
A42: NA | B42: GGO 7.25.0 Sprint 3 | C42: 45862 | D42: 45876 | E42: 13 | F42: 13 | G42: 7 - Strech (2 - Completed, 5- Carried forward | J42: Peer CRC:0 Onsite CRC: 0 Client CRC: 0 Internal Defects: 0 External Defects: 0 Suggestion: 0 Pending story: 2 Story has been carried forward GDON- 32-> Stretch GDON- 33-> Stretch | K42: Offshore Donor team for completing all the planned Donor stories
A43: NA | B43: GGO 7.25.0 Sprint 4 | C43: 45876 | D43: 45890 | E43: 15 | F43: 14 | G43: 11 - Strech (11 Carried Forward) | I43: Accomplishments : Completed fundraising team member API Completed Edit offline Donation API Completed Get offline Donation API | J43: Peer CRC:0 Onsite CRC: 6 Client CRC: 1 Internal Defects: 1 (Bug Story GDON-38 Supporter image Id not updated while updating the profile image ) External Defects: 0 Suggestion: 0 Pending story: GDON18 - 1 story got carried forward - Devlopment and Testing completed from our end. Pending with Onsite QA GDON- 36-> Stretch got carried forward - Bug raised on last day of the sprint so unable to fix in the same sprint - CRC - 4 2 Stretch Story has been carried forward GDON- 37-> Stretch GDON- 34-> Stretch | K43: Donor Team for Api and Offshore team for the reskin stuff both are very complicated
A44: NA | B44: GGO 8.0.0 Sprint 1 | C44: 45890 | D44: 45904 | E44: 15 | F44: 17 (11 Stretch) | G44: 2-Strech (Completed - 2) | I44: Accomplishments : Completed Profile Image Upload API Completed Logging mechinsm in Azure Completed Contacts Upload API Completed FundraisngTeamCoordinator API Completed Get Fundraising Info Completed Organization and events API | J44: Peer CRC:0 Onsite CRC: 0 Client CRC: 1 (Suggestion) Internal Defects: 0 External Defects: 0 Suggestion: 0 Pending story: | K44: Offshore Donor team for completing all planned and more stories
A45: NA | B45: GGO 8.0.0 Sprint 2 | C45: 45904 | D45: 45918 | E45: 15 | F45: 15 | G45: 0 | I45: Accomplishments: Completed save , get and update credit card API Completed the exception handling and logging in App Insights Completed the send email after update the profile API | J45: Peer CRC:0 Onsite CRC: Client CRC: 0 Internal Defects: 0 External Defects: 0 Suggestion: 0 | K45: Rajesh and Donor offshore team for the Donor API progress+1
A46: NA | B46: GGO 8.0.0 Sprint 3 | C46: 45918 | D46: 45932 | E46: 7 | F46: 9 | G46: 2 Story points Introduced - (Completed - 2) | I46: Accomplishments: Completed Update ApAdmin settings Completed Get ApAdmin settings Completed Update GetOrganizationEvents | J46: Peer CRC:0 Onsite CRC: Client CRC: 0 Internal Defects: 0 External Defects: 0 Suggestion: 0 | K46: Offshore team booth GGO and GDONOR for completing all the planned stories and more
A47: NA | B47: GGO 8.0.0 Sprint 4 | C47: 45932 | D47: 45946 | E47: 7 | F47: 9 | G47: 2 Story points Introduced | I47: Accomplishments: Completed GetOrCreateAccountProfileInfo Completed Update the Profile APIs to use Account ID instead of Profile ID Completed GetAddressInfo / UpdateAddressInfo Completed Donor API - Add Address Type for profile Completed Handle Image in Update Profile | J47: Peer CRC:0 Onsite CRC: Client CRC: 0 Internal Defects: 0 External Defects: 0 Suggestion: 0 | K47: GGO and GDON team for meeting the goal +1 | L47: GGO 8.1.0 Sprint 1
A48: NA | B48: GGO 8.1.0 Sprint 1 | C48: 45946 | D48: 45960 | E48: 7 | F48: 9 | G48: 2 Story points Introduced | I48: Accomplishments: Completed Add Company Name for the Business address type Completed Create OnlineBiddingActivity to accept multiple Credit Card and transfer default ClientXid to respective Org clientxid Completed Validate User Profile - Check Bidder/Supporter has got GGAM User Profile or not using "BidderKey" | J48: Peer CRC:0 Onsite CRC: Client CRC: 0 Internal Defects: 0 External Defects: 0 Suggestion: 0 | K48: GGO and GDON team for meeting the goal +1
A49: NA | B49: GGO 8.1.0 Sprint 2 | C49: 45960 | D49: 45974 | E49: 7 | F49: 7 | G49: 2 Story points Introduced | I49: Accomplishments: 1. Completed Update Account Creation to include Online Bidding Activity creation if user login via OB 2. Completed Donor API - Update GGO Card reference in SaveCreditCard 3. Completed Donor API - Update ggo with multiple credit cards from Joinme card reference | J49: Peer CRC:0 Onsite CRC: Client CRC: 0 Internal Defects: 0 External Defects: 0 Suggestion: 0
A50: NA | B50: GGO 8.1.0 Sprint 3 | C50: 45974 | D50: 45988 | E50: 8 | F50: 8 | G50: 2 Story points Introduced | I50: Accomplishments: 1. Completed Donor API - Update the Response code for all the donor API based 2. Completed Donor API - Delete Credit Card in donor app should also delete from GGO if no charge is made 3. Completed Donor API - Validate Card data when creating Online Bidding Activity (either card data or CardXid's) | J50: Peer CRC:0 Onsite CRC: Client CRC: 0 Internal Defects: 0 External Defects: 0 Suggestion: 0 Completed all the planned stories | K50: Offshore for completing the overall Sprint goal
A51: NA | B51: GGO 8.1.0 Sprint 4 | C51: 45988 | D51: 46002 | E51: 7 | F51: 7 | G51: 2 Story points Introduced | I51: Accomplishments: 1. Completed - Create Donor Admin Page 2. Completed - Donor API - Validate Online Bidding activity and Card address before creating OB activity 3. Developement started - Donor API - Create Online Bidding Activity without Credit Card Info* | J51: Peer CRC:0 Onsite CRC: Client CRC: 0 Internal Defects: 0 External Defects: 0 Suggestion: 0 Completed all the planned stories | K51: Rajesh for keeping up with everything and making sure the team is successful
A52: NA | B52: GGO 8.2.0 Sprint 1 | C52: 46002 | D52: 46030 | E52: 10 | F52: 10 | G52: 2 Story points Introduced | I52: Accomplishments: 1. Completed - Donor API - Create Online Bidding Activity without Credit Card Info* 2. Completed - Disabled the Online Bidding activity creation process and hide the display of OB activities in GGAM based on flag 3. Dev Completed - Donor API - Include AddressTypeId and CompanyName in the GetProfileCreditCards API * | J52: Peer CRC:0 Onsite CRC: Client CRC: 0 Internal Defects: 0 External Defects: 0 Suggestion: 0 Completed all the planned stories | K52: Charles and Vishnu for completing the GGAM online activity story
A53: NA | B53: GGO 8.2.0 Sprint 3 | C53: 46030 | D53: 46044 | E53: 9 | F53: 11 | G53: 2 Story points Introduced | I53: Accomplishments: 1. Testing Completed - Donor API - Include AddressTypeId and CompanyName in the GetProfileCreditCards API * 2. Completed - Create GG API to send Checkout information to Donor Platform 3. Completed - Donor API - Add Donation Sale for Donor 4. Completed - GetOrCreateAccount API throws error when sending resettokenutc as null* | J53: Peer CRC:0 Onsite CRC: Client CRC: 0 Internal Defects: 0 External Defects: 0 Suggestion: 0 Completed more than the planned stories | K53: Kudos to GGO and GDON team for completing all the committed work
A54: NA | B54: GGO 8.2.0 Sprint 4 | C54: 46044 | D54: 46058 | E54: 10 | F54: 10 | G54: 2 Story points Introduced | I54: Accomplishments: 1. Testing completed for all the assigned stories Completed - GDON - 71 - Create GGO Org Settings Completed - GDON - 82 - Donor Checkout - Charge CC, create Payment record/association 2. Have taken one story and started Development GDON - 72 - Create GGO Donor Project Settings | J54: Peer CRC:0 Onsite CRC: Client CRC: 0 Internal Defects: 0 External Defects: 0 Suggestion: 0 Completed all the planned stories | K54: Offshore GGO and GDON team for completing all the stories | N54: 0 | O54: 2
A55: NA | B55: GGO 8.3.0 Sprint 1 | C55: 46058 | D55: 46072 | E55: 11 | F55: 11 | G55: 1 Story point introduced (Found an Issue) | I55: Accomplisments: 1. Completed DEV & Testing - GDON - 72 - Create GGO Donor Project Settings 2. Completed DEV & Testing - GDON - 83 - Donor API - Update GetCheckout API to include Convenience Fee and Sale Payment Association flag 3. Completed DEV & Testing in Dev env., - GDON - 80 - Donor Checkout - Generate Receipt | J55: Peer CRC:0 Onsite CRC: Client CRC: 0 Internal Defects: 0 External Defects: 0 Suggestion: 0 Completed all the planned stories Found an issue and fixed that in the current sprint itself Testing in TST env., alone is pending for the ticket GDON-80 | K55: GDON team for completing the planned stories | N55: 0 | O55: 0
A56: NA | B56: GGO 8.3.0 Sprint 2 | C56: 46072 | D56: 46086 | E56: 10 | F56: 9 | G56: 3 | I56: Accomplisments: 1. Completed DEV & Testing in DEV env., - GDON - 84 - Donor Settings - Project Name to cascade to Ob Settings 2. Completed DEV & Testing in Dev & TST env.,- GDON - 86 - Display self checkout badge in GGO Manage Sales & Payments 3. Completed DEV & Testing in Dev & TST env., - GDON - 87 - Donor API - Update Charge Card using selected card in Donor App | J56: Peer CRC:0 Onsite CRC:0 Client CRC: 0 Internal Defects: 0 External Defects: 0 Suggestion: 0 1 Story carried forward for Testing in TST env.,. Development is completed | K56: Offshore team for achieving the sprint goal | N56: 1 | O56: 1.5
A57: NA | B57: GGO 8.3.0 Sprint 3 | C57: 46086 | D57: 46100 | E57: 12 | F57: 12 | G57: 3 | I57: Accomplishments: 1. Completed DEV & TST Testing - GDON-84 - Donor Settings - Project Name to cascade to Ob Settings 2. Completed DEV & TST Testing - GDON - 81 - Donor Checkout - Generate email and send receipt 3. Completed DEV & TST Testing - GDON - 88 - Donor API - Common credit card model for both OnlineBidding and CreditCard APIs 4. Completed DEV & TST Testing - GDON - 89 - Donor API - Add payment source "DonorEngage" to differentiate the payment from Donor App 5. Started development on GDON - 90 - Donor API - Cleanup donor API's | J57: Peer CRC:0 Onsite CRC:1 1.Is this file needed? It looks like config values come from the appsettings.json file Client CRC: 0 Internal Defects: 0 External Defects: 0 Suggestion: 0 | K57: Whole GGo offshore team for achieving the goal | N57: 0 | O57: 1.5
A58: NA | B58: GGO 8.3.0 Sprint 4 | C58: 46100 | D58: 46114 | E58: 12 | F58: 12 | G58: 2 | I58: Accomplishments: 1. Successfully implemented the Email Template and its subject of the mail once the check out is done 2. Implemented the Donor API's - Cleanup process 3. In Generate Payment Receipt API - successfully implemented the ReportGuId in the Params for generating the token 4. Implemented Email Address update in Update Profile API | J58: Peer CRC:0 Onsite CRC: Client CRC: 0 Internal Defects: 0 External Defects: 0 Suggestion: 0 Completed all the planned stories and taken one bug ticket and started development | K58: Offshore team for completing all the planned taken stories in the sprint | N58: 1 | O58: 1
A59: NA | B59: GGO 8.4.0 Sprint 1 | C59: 46114 | D59: 46128 | E59: 11 | F59: 11 | G59: 3 | I59: Accomplishments: 1. Successfully implemented the Text Template and SMS request once the check out is done 2. Implemented a new Donor API's - CheckBidderHouseHold for both Individual and Household supporters 3. Successfully implemented the GenerateCheckOut API with the below mentioned formats i. with AccountId, ProjectKey & BidderKey ii. with AccountId & ProjectKey iii. with AccountId & BidderKey 4. Implemented the GetCreditCards API which was always returning as 2 - while updating the AddressTypeId | J59: Peer CRC:0 Onsite CRC: Client CRC: 0 Internal Defects: 0 External Defects: 0 Suggestion: 0 Completed all the planned stories and taken one ticket from the backlog and it is being developed | K59: 1. Whole GGO and GDON offshore team for completing all the tickets 2. Conor, Priya and Charles for completing the testing for all the stories | N59: 0 | O59: 1
A60: NA | B60: GGO 8.4.0 Sprint 2 | C60: 46128 | D60: 46142 | E60: 11 | F60: 11 | G60: - | I60: Accomplishments: 1. Successfully implemented three new API's - Event details API, Tickets API and GetHouseHoldMembers 2. Successfully implemented the ProjectKey in the GetCheckout Result 3. Implemented the CreateAccount API without giving password in the JSON | J60: Peer CRC:0 Onsite CRC: Client CRC: 0 Internal Defects: 0 External Defects: 0 Suggestion: 0 Completed all the planned stories | K60: Offshore GGO and GDON for completing all the stories | N60: 0 | O60: 1
A61: NA | B61: GGO 8.4.0 Sprint 3 | C61: 46142 | D61: 46156 | E61: 9 | F61: 9 | G61: - | I61: Accomplishments: 1. Successfully implemented a new API - GetBidderHouseHoldAndTableInfo 2. Successfully implemented Self Checkin Settings under Donor Project settings and another new API GetCheckinInfo 3. Implemented the Online Bidding sceanrio without creating duplicate supporter in the list 4. Successfully implemented another new API - UpdateCheckinStatus | J61: Peer CRC:0 Onsite CRC: Client CRC: 0 Internal Defects: 0 External Defects: 0 Suggestion: 0 Completed all the planned stories | K61: GGO & GDON offshore team for achieving the sprint goal | N61: 1 | O61: 1.5
A62: NA | B62: GGO 8.4.0 Sprint 4 | C62: 46156 | D62: 46170 | E62: 11 | N62: 0 | O62: 0

Sheet Unplanned Leaves
A2: Total Unplanned Leaves | B2: 0
B3: Resource Name
A4: Sprint Name | B4: Charles Infant Rabi | C4: Vishnu | D4: Remarks
A5: GGO 8.3.0 Sprint 1 (05-Feb-26 to 19-Feb-26) | B5: 0 | C5: 0
A6: GGO 8.3.0 Sprint 2 (19-Feb-26 to 05-Mar-26) | B6: 0.5 1 | C6: 0 | D6: Charles: Due to Fever (26/02) 2nd half Planned leave (05/03)
A7: GGO 8.3.0 Sprint 3 (05-Mar-26 to 19-Mar-26) | B7: 0.5 | C7: 1 | D7: Charles: Personal work (10/03) - 2nd half Vishnu: Personal reasons
A8: GGO 8.3.0 Sprint 4 (19-Mar-26 to 02-Apr-26) | B8: 1 | C8: 0 | D8: Charles: Planned leave (30/03)
A9: GGO 8.4.0 Sprint 1 (02-Apr-26 to 16-Apr-26) | B9: 0 | C9: 1 | D9: Vishnu: Personal work (16/04/2026)
A10: GGO 8.4.0 Sprint 2 (16-Apr-26 to 30-Apr-26) | B10: 0 | C10: 0
A11: GGO 8.4.0 Sprint 3 (30-Apr-26 to 14-May-26) | B11: 1 | C11: 0.5 | D11: Charles: Family Function (04/05/2026) Vishnu: Personal work (13/05/2026)
A18: Total | B18: 4 | C18: 2.5

Sheet  GGO 8.4.0 Sprint 4-Status
A1: S.No | B1: Application Name | C1: Sprint Start Date | D1: Sprint End Date | E1: Sprint | F1: Developer | G1: Story ID / Defect ID | H1: Description | I1: Status | J1: Estimated (sp) | K1: Actual (sp) | L1: Actual Hours Worklog | M1: Dev Start Date | N1: Dev End Date | O1: Unit testing | P1: Peer Tested By | Q1: Peer Tested Defects, if any | R1: Peer Reviewed By | S1: Peer Code Review Comments, if any | T1: PR Number/Link | U1: PR Created Date | V1: PR Approved Date | W1: Reviewer 1 | X1: Code Review Comments, if any | Y1: Reviewer 2 | Z1: Approved Date | AA1: Code Review Comments, if any2 | AB1: Internal PO - POV Comments | AC1: Client PO - POV Comments | AD1: Comments
A2: 1 | B2: GGO Donor Wave | C2: 46156 | D2: 46170 | E2: GGO 8.4.0 Sprint 4 | F2: Vishnu | G2: GDON-104 | H2: Donor API - Update GetBidderHouseHoldAndTableInfo to include the Member details for OB | I2: Being Developed | J2: 3 | M2: 46157
A3: 2 | B3: GGO Donor Wave | C3: 46156 | D3: 46170 | E3: GGO 8.4.0 Sprint 4 | F3: Vishnu | G3: GDON-105 | H3: Donor API - Include Image Url in the GetCheckIn Details API | I3: Refinement | J3: 2
A4: 3 | B4: GGO Donor Wave | C4: 46156 | D4: 46170 | E4: GGO 8.4.0 Sprint 4 | F4: Vishnu | G4: GDON-106 | H4: GGO - Indicate when a Supporter has a donor profile | I4: Refinement | J4: 3
A5: 4 | B5: GGO Donor Wave | C5: 46156 | D5: 46170 | E5: GGO 8.4.0 Sprint 4 | F5: Vishnu | G5: GDON-107 | H5: GGO - Indicate when a Donor Self Checks In | I5: Refinement | J5: 3

Sheet GGO 8.4.0 Sprint 3-Status
A1: S.No | B1: Application Name | C1: Sprint Start Date | D1: Sprint End Date | E1: Sprint | F1: Developer | G1: Story ID / Defect ID | H1: Description | I1: Status | J1: Estimated (sp) | K1: Actual (sp) | L1: Actual Hours Worklog | M1: Dev Start Date | N1: Dev End Date | O1: Unit testing | P1: Peer Tested By | Q1: Peer Tested Defects, if any | R1: Peer Reviewed By | S1: Peer Code Review Comments, if any | T1: PR Number/Link | U1: PR Created Date | V1: PR Approved Date | W1: Reviewer 1 | X1: Code Review Comments, if any | Y1: Reviewer 2 | Z1: Approved Date | AA1: Code Review Comments, if any2 | AB1: Internal PO - POV Comments | AC1: Client PO - POV Comments | AD1: Comments
A2: 1 | B2: GGO Donor Wave | C2: 46142 | D2: 46156 | E2: GGO 8.4.0 Sprint 3 | F2: Vishnu | G2: GDON-100 | H2: Donor API - Update table info in GetHousehold API call | I2: Completed | J2: 2 | K2: 2 | L2: 16.5 | M2: 46146 | N2: 46146 | O2: Done | P2: Charles | R2: Rajesh | T2: https://dev.azure.com/greatergiving/Greater%20Giving/_git/GGO/pullrequest/9529 | U2: 46146 | V2: 46146 | W2: Rajesh | Y2: Mccarty, Joseph | Z2: 46146 | AD2: Testing in TST env., completed on 05/05/2026 at 19:00 pm Working fine as expected / Updated the QA notes and comments in JIRA
A3: 2 | B3: GGO Donor Wave | C3: 46142 | D3: 46156 | E3: GGO 8.4.0 Sprint 3 | F3: Vishnu | G3: GDON-101 | H3: Donor Check In Settings | I3: Completed | J3: 3 | K3: 3 | L3: 34.5 | M3: 46147 | N3: 46149 | O3: Done | P3: Charles | R3: Rajesh | T3: https://dev.azure.com/greatergiving/Greater%20Giving/_git/GGO/pullrequest/9546 | U3: 46149 | V3: 46153 | W3: Rajesh | Y3: Mccarty, Joseph | Z3: 46153 | AD3: Dev completed on 07/05/2026 Testing in TST env., completed on 12/05/2026 at 16:30 pm Working fine as expected / Updated the QA notes and comments in JIRA
A4: 3 | B4: GGO Donor Wave | C4: 46142 | D4: 46156 | E4: GGO 8.4.0 Sprint 3 | F4: Vishnu | G4: GDON-102 | H4: Donor API - Update Online Bidding Activity API and cleanup | I4: Completed | J4: 2 | K4: 2 | L4: 30 | M4: 46150 | N4: 46153 | O4: Done | P4: Charles | R4: Rajesh | T4: https://dev.azure.com/greatergiving/Greater%20Giving/_git/GGO/pullrequest/9553 | U4: 46153 | V4: 46154 | W4: Rajesh | Y4: Mccarty, Joseph | Z4: 46154 | AD4: Testing in DEV env., - Completed on 12/05/2026 and 13/05/2026 It is working fine as expected. Updated the QA notes and comments in JIRA Unable to test in TST env., as the TST DONOR URL is not accessible
A5: 4 | B5: GGO Donor Wave | C5: 46142 | D5: 46156 | E5: GGO 8.4.0 Sprint 3 | F5: Vishnu | G5: GDON-103 | H5: Donor API - Checkin Supporter API | I5: Completed | J5: 2 | K5: 2 | L5: 34 | M5: 46154 | N5: 46155 | O5: Done | P5: Charles | R5: Rajesh | T5: https://dev.azure.com/greatergiving/Greater%20Giving/_git/GGO/pullrequest/9559 | U5: 46155 | V5: 46155 | W5: Rajesh | Y5: Mccarty, Joseph | Z5: 46155 | AD5: Testing in TST env., completed on 14/05/2026 at 14:00 pm Working fine as expected Will update the QA notes and comments shortly

Sheet GGO 8.4.0 Sprint 2-Status
A1: S.No | B1: Application Name | C1: Sprint Start Date | D1: Sprint End Date | E1: Sprint | F1: Developer | G1: Story ID / Defect ID | H1: Description | I1: Status | J1: Estimated (sp) | K1: Actual (sp) | L1: Actual Hours Worklog | M1: Dev Start Date | N1: Dev End Date | O1: Unit testing | P1: Peer Tested By | Q1: Peer Tested Defects, if any | R1: Peer Reviewed By | S1: Peer Code Review Comments, if any | T1: PR Number/Link | U1: PR Created Date | V1: PR Approved Date | W1: Reviewer 1 | X1: Code Review Comments, if any | Y1: Reviewer 2 | Z1: Approved Date | AA1: Code Review Comments, if any2 | AB1: Internal PO - POV Comments | AC1: Client PO - POV Comments | AD1: Comments
A2: 1 | B2: GGO Donor Wave | C2: 46128 | D2: 46142 | E2: GGO 8.4.0 Sprint 2 | F2: Vishnu | G2: GDON-94 | H2: Create an Event Details API | I2: Completed | J2: 3 | K2: 3 | L2: 46.5 | M2: 46133 | N2: 46136 | O2: Done | P2: Charles | R2: Rajesh | T2: https://dev.azure.com/greatergiving/Greater%20Giving/_git/GGO/pullrequest/9507 | U2: 46136 | V2: 46139 | W2: Rajesh | Y2: Mccarty, Joseph | Z2: 46139 | AD2: Working fine as expected in DEV env., Testing completed on 27/04/2026 20:30PM Testing in TST env., completed on 28/04/2026 17:00PM and it is working fine as expected
A3: 2 | B3: GGO Donor Wave | C3: 46128 | D3: 46142 | E3: GGO 8.4.0 Sprint 2 | F3: Vishnu | G3: GDON-95 | H3: Create a Tickets API | I3: Being Developed | J3: 5 | L3: 45.5 | M3: 46139 | N3: 46141 | O3: Done | P3: Charles | R3: Rajesh | T3: https://dev.azure.com/greatergiving/Greater%20Giving/_git/GGO/pullrequest/9515 | U3: 46141 | V3: 46141 | W3: Rajesh | Y3: Mccarty, Joseph | Z3: 46141 | AD3: Testing in TST env., Inprogress
A4: 3 | B4: GGO Donor Wave | C4: 46128 | D4: 46142 | E4: GGO 8.4.0 Sprint 2 | F4: Vishnu | G4: GDON-98 | H4: Donor API - Get Household members | I4: Completed | J4: 2 | K4: 2 | L4: 39.5 | M4: 46127 | N4: 46133 | O4: Done | P4: Charles | R4: Rajesh | T4: https://dev.azure.com/greatergiving/Greater%20Giving/_git/GGO/pullrequest/9490 | U4: 46133 | V4: 46134 | W4: Rajesh | Y4: Mccarty, Joseph | Z4: 46134 | AD4: Working fine as expected in DEV env., Testing completed on 22/04/2026 17:00PM Testing completed in TST env., 23/04/2026 18:30 PM and it is working fine as expected.
A5: 4 | B5: GGO Donor Wave | C5: 46128 | D5: 46142 | E5: GGO 8.4.0 Sprint 2 | F5: Rajesh | G5: GDON-99 | H5: Donor API - Update create account password to a random string instead of getting from Donor App | I5: Completed | J5: 1 | K5: 1 | L5: 9.5 | M5: 46128 | N5: 46129 | O5: Done | P5: Charles | R5: Rajesh | T5: https://dev.azure.com/greatergiving/Greater%20Giving/_git/GGO/pullrequest/9486 | U5: 46129 | V5: 46129 | W5: Rajesh | Y5: Mccarty, Joseph | Z5: 46129 | AD5: Working fine as expected in TST env., - Testing completed on 20/04/2026 17:30 PM

Sheet GGO 8.4.0 Sprint 1-Status
A1: S.No | B1: Application Name | C1: Sprint Start Date | D1: Sprint End Date | E1: Sprint | F1: Developer | G1: Story ID / Defect ID | H1: Description | I1: Status | J1: Estimated (sp) | K1: Actual (sp) | L1: Actual Hours Worklog | M1: Dev Start Date | N1: Dev End Date | O1: Unit testing | P1: Peer Tested By | Q1: Peer Tested Defects, if any | R1: Peer Reviewed By | S1: Peer Code Review Comments, if any | T1: PR Number/Link | U1: PR Created Date | V1: PR Approved Date | W1: Reviewer 1 | X1: Code Review Comments, if any | Y1: Reviewer 2 | Z1: Approved Date | AA1: Code Review Comments, if any2 | AB1: Internal PO - POV Comments | AC1: Client PO - POV Comments | AD1: Comments
A2: 1 | B2: GGO Donor Wave | C2: 46114 | D2: 46128 | E2: GGO 8.4.0 Sprint 1 | F2: Rajesh | G2: GDON-78 | H2: Create Text Template | I2: Completed | J2: 3 | K2: 3 | L2: 26.5 | M2: 46122 | N2: 46126 | O2: Done | P2: Charles | R2: Vishnu | T2: https://dev.azure.com/greatergiving/Greater%20Giving/_git/GGO/pullrequest/9466 | U2: 46126 | V2: 46126 | W2: Rajesh | Y2: Horihan, Mike | Z2: 46126 | AD2: Working fine as expected in both DEV & TST env.,
A3: 2 | B3: GGO Donor Wave | C3: 46114 | D3: 46128 | E3: GGO 8.4.0 Sprint 1 | F3: Vishnu | G3: GDON-93 | H3: Update Online Bidding to Recognize HH vs Individual Bidder keys | I3: Completed | J3: 3 | K3: 3 | L3: 32.5 | M3: 46121 | N3: 46125 | O3: Done | P3: Charles | R3: Rajesh | T3: https://dev.azure.com/greatergiving/Greater%20Giving/_git/GGO/pullrequest/9462 | U3: 46125 | V3: 46125 | W3: Rajesh | Y3: Mccarty, Joseph | Z3: 46125 | AD3: In DEV Testing Result is coming as True for both the Bidderkeys - Individual and Household 1. True should be come only for Household Bidderkey 2. And It should be False for Individual Bidderkey Fixed the above issue and completed testing in TST env., it is working fine as expected now
A4: 3 | B4: GGO Donor Wave | C4: 46114 | D4: 46128 | E4: GGO 8.4.0 Sprint 1 | F4: Vishnu | G4: GDON-96 | H4: Donor API - Get Account and Project Info By BidderKey | I4: Completed | J4: 3 | K4: 3 | L4: 26 | M4: 46118 | N4: 46120 | O4: Done | P4: Charles | R4: Rajesh | T4: https://dev.azure.com/greatergiving/Greater%20Giving/_git/GGO/pullrequest/9449 | U4: 46120 | V4: 46121 | W4: Rajesh | Y4: Horihan, Mike | Z4: 46122 | AD4: Working fine as expected in both DEV & TST env.,
A5: 4 | B5: GGO Donor Wave | C5: 46114 | D5: 46128 | E5: GGO 8.4.0 Sprint 1 | F5: VIshnu | G5: GDON-97 | H5: Donor API - AddressTypeId is always returning as Type 2 in GetCreditCards API | I5: Completed | J5: 2 | K5: 2 | L5: 35.5 | M5: 46113 | N5: 46118 | O5: Done | P5: Charles | R5: Rajesh | T5: https://dev.azure.com/greatergiving/Greater%20Giving/_git/GGO/pullrequest/9438 | U5: 46118 | V5: 46121 | W5: Rajesh | Y5: Horihan, Mike | Z5: 46121 | AA5: Is this the way normally determine first name and last name? | AD5: Working fine as expected in both DEV & TST env.,
A6: 5 | B6: GGO Donor Wave | C6: 46114 | D6: 46128 | E6: GGO 8.4.0 Sprint 1 [Stretch] | F6: VIshnu | G6: GDON-98 | H6: Donor API - Get Household members | I6: Being Developed | J6: 3 | L6: 9 | M6: 46127 | AD6: Being Developed

Sheet GGO 8.3.0 Sprint 4-Status
A1: S.No | B1: Application Name | C1: Sprint Start Date | D1: Sprint End Date | E1: Sprint | F1: Developer | G1: Story ID / Defect ID | H1: Description | I1: Status | J1: Estimated (sp) | K1: Actual (sp) | L1: Actual Hours Worklog | M1: Dev Start Date | N1: Dev End Date | O1: Unit testing | P1: Peer Tested By | Q1: Peer Tested Defects, if any | R1: Peer Reviewed By | S1: Peer Code Review Comments, if any | T1: PR Number/Link | U1: PR Created Date | V1: PR Approved Date | W1: Reviewer 1 | X1: Code Review Comments, if any | Y1: Reviewer 2 | Z1: Approved Date | AA1: Code Review Comments, if any2 | AB1: Internal PO - POV Comments | AC1: Client PO - POV Comments | AD1: Tester Comments | AE1: Developer comments | AF1: Remarks
A2: 1 | B2: GGO Donor Wave | C2: 46100 | D2: 46114 | E2: GGO 8.3.0 Sprint 4 | F2: Vishnu | G2: GDON-90 | H2: Donor API - Cleanup donor API's | I2: Completed | J2: 3 | K2: 3 | L2: 36 | M2: 46101 | N2: 46104 | O2: Done | P2: Charles | R2: Rajesh | T2: https://dev.azure.com/greatergiving/Greater%20Giving/_git/GGO/pullrequest/9397 | U2: 46104 | V2: 46104 | W2: Rajesh | Y2: Mccarty, Joseph | Z2: 46104 | AD2: Testing activity in TST env., - Completed on 24/03/2026 20:00PM | AE2: Dev started on 17/03/2026 Dev Completed on 23/03/2026 | AF2: Collection of APIs - Based on different scenarios - TST env.,
A3: 2 | B3: GGO Donor Wave | C3: 46100 | D3: 46114 | E3: GGO 8.3.0 Sprint 4 | F3: Vishnu | G3: GDON-91 | H3: Validate Generate receipt requester identity | I3: Completed | J3: 2 | K3: 2 | L3: 38.5 | M3: 46108 | N3: 46112 | O3: Done | P3: Charles | R3: Rajesh | T3: https://dev.azure.com/greatergiving/Greater%20Giving/_git/GGO/pullrequest/9418 | U3: 46112 | V3: 46113 | W3: Rajesh | Y3: Mccarty, Joseph | Z3: 46113 | AD3: Testing activity in DEV env., - Completed on 01/04/2026 13:00PM Testing activity in TSTenv., completed on 02/04/2026 - 16:00PM | AE3: Dev started on 27/03/2026 Dev Completed on 31/03/2026
A4: 3 | B4: GGO Donor Wave | C4: 46100 | D4: 46114 | E4: GGO 8.3.0 Sprint 4 | F4: Vishnu | G4: GDON-92 | H4: Donor API - Update profile and supporter email address based on change email request from donor app | I4: Completed | J4: 2 | K4: 2 | L4: 43 | M4: 46105 | N4: 46107 | O4: Done | P4: Charles | R4: Rajesh | T4: https://dev.azure.com/greatergiving/Greater%20Giving/_git/GGO/pullrequest/9407 | U4: 46107 | V4: 46107 | W4: Rajesh | Y4: Mccarty, Joseph | Z4: 46107 | AD4: Testing activity in DEV env., completed on 26/03/2026 - 20:00PM Testing activity in TSTenv., completed on 27/03/2026 - 21:00PM | AE4: Dev started on 24/03/2026 Dev Completed on 26/03/2026
A5: 4 | B5: GGO Donor Wave | C5: 46100 | D5: 46114 | E5: GGO 8.3.0 Sprint 4 | F5: Rajesh | G5: GDON-74 | H5: Create Email Template | I5: Completed | J5: 5 | K5: 5 | L5: 22.5 | M5: 46101 | N5: 46108 | O5: Done | P5: Charles | R5: Vishnu | T5: https://dev.azure.com/greatergiving/Greater%20Giving/_git/GGO/pullrequest/9418 | U5: 46112 | V5: 46112 | W5: Rajesh | Y5: Mccarty, Joseph | Z5: 46112 | AD5: Testing activity in DEV env., completed on 30/03/2026 - 20:00PM Testing activity in TSTenv., completed on 01/04/2026 - 16:00PM | AE5: Dev started on 20/03/2026 Dev Completed on 27/03/2026
A6: 4 | B6: GGO Donor Wave | C6: 46100 | D6: 46114 | E6: GGO 8.3.0 Sprint 4 [Stretch] | F6: Vishnu | G6: GDON-97 | H6: Donor API - AddressTypeId is always returning as Type 2 in GetCreditCards API | I6: Being Developed | J6: 2 | K6: 1 | L6: 10.5 | M6: 46113

Sheet GGO 8.3.0 Sprint 4-Defect
A1: S.No | B1: Sprint | C1: Story/Defect ID | D1: Parent Story | E1: Developer | F1: Issue Type | G1: Issue Description | H1: Priority | I1: Defect Source | J1: Type | K1: Status | L1: Root Cause Category | M1: Comments | N1: Found By | O1: RCA Comment | AD1: Tester Comments | AE1: Developer comments | AF1: Remarks
G2: NO Defects | AE2: Dev Started on 05-Feb-2026

Sheet GGO 8.3.0 Sprint 3-Status
A1: S.No | B1: Application Name | C1: Sprint Start Date | D1: Sprint End Date | E1: Sprint | F1: Developer | G1: Story ID / Defect ID | H1: Description | I1: Status | J1: Estimated (sp) | K1: Actual (sp) | L1: Actual Hours Worklog | M1: Dev Start Date | N1: Dev End Date | O1: Unit testing | P1: Peer Tested By | Q1: Peer Tested Defects, if any | R1: Peer Reviewed By | S1: Peer Code Review Comments, if any | T1: PR Number/Link | U1: PR Created Date | V1: PR Approved Date | W1: Reviewer 1 | X1: Code Review Comments, if any | Y1: Reviewer 2 | Z1: Approved Date | AA1: Code Review Comments, if any2 | AB1: Internal PO - POV Comments | AC1: Client PO - POV Comments | AD1: Tester Comments | AE1: Developer comments | AF1: Remarks
A2: 1 | B2: GGO Donor Wave | C2: 46086 | D2: 46100 | E2: GGO 8.3.0 Sprint 3 | F2: Vishnu | G2: GDON-84 | H2: Donor Settings - Project Name to cascade to Ob Settings | I2: Completed | J2: 1 | K2: 1 | L2: 6 | O2: Done | P2: Charles | R2: Rajesh | T2: https://dev.azure.com/greatergiving/Greater%20Giving/_git/GGO/pullrequest/9341 | U2: 46085 | W2: Rajesh | AD2: Testing activity in DEV env., completed on 27/02/2026 / 18:30PM Testing activity in TST env., completed on 06/03/2026 - 15:00PM | AE2: Dev completed on 04/03/2026
A3: 2 | B3: GGO Donor Wave | C3: 46086 | D3: 46100 | E3: GGO 8.3.0 Sprint 3 | F3: Rajesh/Vishnu | G3: GDON-81 | H3: Donor Checkout - Generate email and send receipt | I3: Completed | J3: 5 | K3: 5 | L3: 17.5 | M3: 46087 | N3: 46094 | O3: Done | P3: Charles | R3: Vishnu | T3: https://dev.azure.com/greatergiving/Greater%20Giving/_git/GGO/pullrequest/9377 | U3: 46097 | V3: 46097 | W3: Vishnu | Y3: Mccarty, Joseph | Z3: 46097 | AD3: Testing activity in DEV env., completed on 16/03/2026 - 12:00PM Testing activity in TSTenv., completed on 17/03/2026 - 17:00PM | AE3: Dev started on 06/03/2026 Dev completed on 16/03/2026
A4: 3 | B4: GGO Donor Wave | C4: 46086 | D4: 46100 | E4: GGO 8.3.0 Sprint 3 | F4: Vishnu | G4: GDON-88 | H4: Donor API - Common credit card model for both OnlineBidding and CreditCard APIs | I4: Completed | J4: 3 | K4: 3 | L4: 40.5 | M4: 46087 | N4: 46091 | O4: Done | P4: Charles | R4: Rajesh | T4: https://dev.azure.com/greatergiving/Greater%20Giving/_git/GGO/pullrequest/9353 | U4: 46091 | V4: 46092 | W4: Rajesh | Y4: Mccarty, Joseph | Z4: 46092 | AD4: Testing activity in DEV env., completed on 10/03/2026 - 21:00PM Testing activity in TST env.,Completed on 11/03/2026 - 20:00PM | AE4: Dev Started on 06/03/2026 Dev Completed on 10/03/2026
A5: 4 | B5: GGO Donor Wave | C5: 46086 | D5: 46100 | E5: GGO 8.3.0 Sprint 3 | F5: Vishnu | G5: GDON-89 | H5: Donor API - Add payment source "DonorEngage" to differentiate the payment from Donor App | I5: Completed | J5: 3 | K5: 3 | L5: 32 | M5: 46092 | N5: 46093 | O5: Done | P5: Charles | R5: Rajesh | T5: https://dev.azure.com/greatergiving/Greater%20Giving/_git/GGO/pullrequest/9370 | U5: 46093 | V5: 46094 | W5: Rajesh | Y5: Horihan, Mike | Z5: 46094 | AD5: Testing activity in DEV env., completed on 13/03/2026 - 15:00PM Testing activity in TST env.,Completed on 16/03/2026 - 16:00PM | AE5: Dev started on 11/03/2026 Dev Completed on 12/03/2026
A6: 4 | B6: GGO Donor Wave | C6: 46086 | D6: 46100 | E6: GGO 8.3.0 Sprint 3 [Stretch] | F6: Vishnu | G6: GDON-90 | H6: Donor API - Cleanup donor API's | I6: Being Developed | J6: 3 | L6: 44.5 | M6: 46098 | AE6: Dev started on 17/03/2026 Dev Completed on | AF6: Collection of APIs - Scenarios based - TST env.,

Sheet GGO 8.3.0 Sprint 3-Defect
A1: S.No | B1: Sprint | C1: Story/Defect ID | D1: Parent Story | E1: Developer | F1: Issue Type | G1: Issue Description | H1: Priority | I1: Defect Source | J1: Type | K1: Status | L1: Root Cause Category | M1: Comments | N1: Found By | O1: RCA Comment | AD1: Tester Comments | AE1: Developer comments | AF1: Remarks
G2: NO Defects | AE2: Dev Started on 05-Feb-2026

Sheet GGO 8.3.0 Sprint 2-Status
A1: S.No | B1: Application Name | C1: Sprint Start Date | D1: Sprint End Date | E1: Sprint | F1: Developer | G1: Story ID / Defect ID | H1: Description | I1: Status | J1: Estimated (sp) | K1: Actual (sp) | L1: Actual Hours Worklog | M1: Dev Start Date | N1: Dev End Date | O1: Unit testing | P1: Peer Tested By | Q1: Peer Tested Defects, if any | R1: Peer Reviewed By | S1: Peer Code Review Comments, if any | T1: PR Number/Link | U1: PR Created Date | V1: PR Approved Date | W1: Reviewer 1 | X1: Code Review Comments, if any | Y1: Reviewer 2 | Z1: Approved Date | AA1: Code Review Comments, if any2 | AB1: Internal PO - POV Comments | AC1: Client PO - POV Comments | AD1: Tester Comments | AE1: Developer comments | AF1: Remarks
A2: 1 | B2: GGO Donor Wave | C2: 46072 | D2: 46086 | E2: GGO 8.3.0 Sprint 2 | F2: Rajesh | G2: GDON-80 | H2: Donor Checkout - Generate Receipt | I2: Completed | J2: 1 | K2: 1 | L2: 19.5 | M2: 46065 | N2: 46072 | O2: Done | P2: Charles | R2: Vishnu | T2: https://dev.azure.com/greatergiving/Greater%20Giving/_git/GGO/pullrequest/9304 | U2: 46072 | W2: Vishnu | Y2: Horihan, Mike | Z2: 46072 | AA2: Question: Is this file needed? It looks like config values come from the appsettings.json file. | AD2: Testing activity completed in DEV env., on 19/02/2026 / 12:30PM Testing activity completed in TST env., on 20/02/2026 / 15:00PM | AE2: Dev completed on 19/02/2026
A3: 2 | B3: GGO Donor Wave | C3: 46072 | D3: 46086 | E3: GGO 8.3.0 Sprint 2 | F3: Vishnu | G3: GDON-84 | H3: Donor Settings - Project Name to cascade to Ob Settings | I3: Verify | J3: 3 | K3: 2 | L3: 31.5 | M3: 46083 | N3: 46085 | O3: Done | P3: Charles | R3: Rajesh | T3: https://dev.azure.com/greatergiving/Greater%20Giving/_git/GGO/pullrequest/9341 | U3: 46085 | W3: Rajesh | AD3: Testing activity completed in DEV env., on 27/02/2026 / 18:30PM Testing activity in TST env., completed on 06/03/2026 - 15:00PM | AE3: Dev completed on 04/03/2026
A4: 3 | B4: GGO Donor Wave | C4: 46072 | D4: 46086 | E4: GGO 8.3.0 Sprint 2 | F4: Vishnu | G4: GDON-86 | H4: Display self checkout badge in GGO Manage Sales & Payments | I4: Completed | J4: 3 | K4: 3 | L4: 4.5 | M4: 46078 | N4: 46080 | O4: Done | P4: Charles | R4: Rajesh | T4: https://dev.azure.com/greatergiving/Greater%20Giving/_git/GGO/pullrequest/9324 | U4: 46079 | W4: Rajesh | Y4: Horihan, Mike | Z4: 46083 | AD4: Testing activity completed in DEV env., on 27/02/2026 / 18:30PM Testing activity completed in TST env., on 03/03/2026 / 14:30PM | AE4: Dev completed on 02/03/2026
A5: 4 | B5: GGO Donor Wave | C5: 46072 | D5: 46086 | E5: GGO 8.3.0 Sprint 2 | F5: Vishnu | G5: GDON-87 | H5: Donor API - Update Charge Card using selected card in Donor App | I5: Completed | J5: 3 | K5: 3 | L5: 35.5 | M5: 46073 | N5: 46077 | O5: Done | P5: Charles | R5: Rajesh | T5: https://dev.azure.com/greatergiving/Greater%20Giving/_git/GGO/pullrequest/9316 | U5: 46077 | W5: Rajesh | Y5: Mccarty, Joseph | Z5: 46077 | AD5: Testing activity in TST env., completed on 25/02/2026 / 14:30 PM | AE5: Dev completed on 24/02/2026 | AF5: Found one issue while CreateCardPayment API - (Payment is not getting paid - Error type-1 - (Not found))
A6: 5 | B6: GGO Donor Wave | C6: 46072 | D6: 46086 | E6: GGO 8.3.0 Sprint 2 [Stretch] | F6: Vishnu | G6: GDON-88 | H6: Donor API - Common credit card model for both OnlineBidding and CreditCard APIs* | I6: Being Developed | J6: 3 | L6: 6.5 | M6: 46086

Sheet GGO 8.3.0 Sprint 1-Status
A1: S.No | B1: Application Name | C1: Sprint Start Date | D1: Sprint End Date | E1: Sprint | F1: Developer | G1: Story ID / Defect ID | H1: Description | I1: Status | J1: Estimated (sp) | K1: Actual (sp) | L1: Actual Hours Worklog | M1: Dev Start Date | N1: Dev End Date | O1: Unit testing | P1: Peer Tested By | Q1: Peer Tested Defects, if any | R1: Peer Reviewed By | S1: Peer Code Review Comments, if any | T1: PR Number/Link | U1: PR Created Date | V1: PR Approved Date | W1: Reviewer 1 | X1: Code Review Comments, if any | Y1: Reviewer 2 | Z1: Approved Date | AA1: Code Review Comments, if any2 | AB1: Internal PO - POV Comments | AC1: Client PO - POV Comments | AD1: Tester Comments | AE1: Developer comments | AF1: Remarks
A2: 1 | B2: GGO Donor Wave | C2: 46058 | D2: 46072 | E2: GGO 8.3.0 Sprint 1 | F2: Vishnu | G2: GDON-72 | H2: Create GGO Donor Project Settings | I2: Completed | J2: 5 | K2: 5 | L2: x | M2: 46058 | N2: 46065 | O2: Done | P2: Charles | Q2: View Donor Project Settings is enabled for all the Projects | R2: Rajesh | T2: https://dev.azure.com/greatergiving/Greater%20Giving/_git/GGO/pullrequest/9273 | U2: 46065 | V2: 46065 | W2: Rajesh | Y2: Mccarty, Joseph | Z2: 46065 | AD2: Testing activity in TST env., Completed on 16/02/2026 / 17:00 | AE2: Dev completed on 12-Feb-2026 | AF2: Issue found is fixed and verified again in TST env., - (View Donor Project Settings is enabled for all the Projects)
A3: 2 | B3: GGO Donor Wave | C3: 46058 | D3: 46072 | E3: GGO 8.3.0 Sprint 1 | F3: Rajesh | G3: GDON-80 | H3: Donor Checkout - Generate Receipt | I3: Peer Review | J3: 3 | L3: 36.5 | M3: 46065 | N3: 46071 | O3: Done | P3: Charles | R3: Rajesh | U3: 46072 | W3: Rajesh | Y3: Mccarty, Joseph | AD3: Testing activity in DEV env., Completed on 19/02/2026 / 12:30 | AE3: Dev completed on 18-Feb-2026
A4: 3 | B4: GGO Donor Wave | C4: 46058 | D4: 46072 | E4: GGO 8.3.0 Sprint 1 | F4: Vishnu | G4: GDON-83 | H4: Donor API - Update GetCheckout API to include Convenience Fee and Sale Payment Association flag | I4: Completed | J4: 3 | K4: 3 | L4: 32.5 | M4: 46066 | N4: 46070 | O4: Done | P4: Charles | R4: Rajesh | T4: https://dev.azure.com/greatergiving/Greater%20Giving/_git/GGO/pullrequest/9296 | U4: 46070 | V4: 46070 | W4: Rajesh | Y4: Mccarty, Joseph | Z4: 46070 | AD4: Testing activity in TST env., Completed on 18/02/2026 / 15:00 | AE4: Dev completed on 17-Feb-2026
A5: 4 | B5: GGO Donor Wave | C5: 46058 | D5: 46072 | E5: GGO 8.3.0 Sprint 1 | F5: Vishnu | G5: GDON-85 | H5: View Donor Project Settings is enabled for all the Projects | I5: Completed | J5: 1 | K5: 1 | M5: 46066 | N5: 46066 | O5: Done | P5: Charles | R5: Rajesh | T5: https://dev.azure.com/greatergiving/Greater%20Giving/_git/GGO/pullrequest/9285 | U5: 46066 | V5: 46066 | W5: Rajesh | Y5: Mccarty, Joseph | Z5: 46066 | AD5: Testing activity in TST env., Completed on 16/02/2026 / 17:00 | AE5: Dev completed on 13-Feb-2026

Sheet GGO 8.3.0 Sprint 1-Defect
A1: S.No | B1: Sprint | C1: Story/Defect ID | D1: Parent Story | E1: Developer | F1: Issue Type | G1: Issue Description | H1: Priority | I1: Defect Source | J1: Type | K1: Status | L1: Root Cause Category | M1: Comments | N1: Found By | O1: RCA Comment | AD1: Tester Comments | AE1: Developer comments | AF1: Remarks
G2: No Defects | AE2: Dev Started on 05-Feb-2026

Sheet GGO 8.2.0 Sprint 4-Status
A1: S.No | B1: Application Name | C1: Sprint Start Date | D1: Sprint End Date | E1: Sprint | F1: Developer | G1: Story ID / Defect ID | H1: Description | I1: Status | J1: Estimated (sp) | K1: Actual (sp) | L1: Actual Hours Worklog | M1: Dev Start Date | N1: Dev End Date | O1: Unit testing | P1: Peer Tested By | Q1: Peer Tested Defects, if any | R1: Peer Reviewed By | S1: Peer Code Review Comments, if any | T1: PR Number/Link | U1: PR Created Date | V1: PR Approved Date | W1: Reviewer 1 | X1: Code Review Comments, if any | Y1: Reviewer 2 | Z1: Approved Date | AA1: Code Review Comments, if any2 | AB1: Internal PO - POV Comments | AC1: Client PO - POV Comments | AD1: Tester Comments | AE1: Developer comments | AF1: Remarks
A2: 1 | B2: GGO Donor Wave | C2: 46044 | D2: 46058 | E2: GGO 8.2.0 Sprint 4 | F2: Vishnu | G2: GDON-71 | H2: Create GGO Org Settings | I2: Completed | J2: 5 | K2: 5 | L2: 53.5 | M2: 46045 | N2: 46051 | O2: Done | P2: Charles | R2: Rajesh | T2: https://dev.azure.com/greatergiving/Greater%20Giving/_git/GGO/pullrequest/9227 | U2: 46050 | V2: 46052 | W2: Rajesh | Y2: Mccarty, Joseph | Z2: 46052 | AD2: Testing activity has been completed in the DEV env., Done on 01/30/2026 - 17:30PM Testing activity has been completed in the TST env., Done on 02/02/2026 - 16:00PM | AE2: Dev completed on 29-Jan-2026 | AF2: Found few existing issues - when we go back from organization level
A3: 2 | B3: GGO Donor Wave | C3: 46044 | D3: 46058 | E3: GGO 8.2.0 Sprint 4 | F3: Vishnu | G3: GDON-82 | H3: Donor Checkout - Charge CC, create Payment record/association | I3: Completed | J3: 5 | K3: 5 | M3: 46052 | N3: 46056 | O3: Done | P3: Charles | R3: Rajesh | T3: https://dev.azure.com/greatergiving/Greater%20Giving/_git/GGO/pullrequest/9253 | U3: 46056 | V3: 46056 | W3: Rajesh | Y3: Mccarty, Joseph | Z3: 46056 | AD3: Testing activity has been completed in the TST env., Done on 02/05/2026 - 17:00PM | AE3: Dev completed on 03-Feb-2026
A4: 3 | B4: GGO Donor Wave | C4: 46044 | D4: 46058 | E4: GGO 8.2.0 Sprint 4 [Stretch] | F4: Vishnu | G4: GDON-72 | H4: Create GGO Donor Project Settings | I4: Being Developed | J4: 5 | L4: 12.5 | M4: 46058 | AE4: Dev Started on 05-Feb-2026

Sheet GGO 8.2.0 Sprint 4-Defect
A1: S.No | B1: Sprint | C1: Story/Defect ID | D1: Parent Story | E1: Developer | F1: Issue Type | G1: Issue Description | H1: Priority | I1: Defect Source | J1: Type | K1: Status | L1: Root Cause Category | M1: Comments | N1: Found By | O1: RCA Comment | AD1: Tester Comments | AE1: Developer comments | AF1: Remarks
G2: No Defects | AE2: Dev Started on 05-Feb-2026

Sheet GGO 8.2.0 Sprint 3-Status
A1: S.No | B1: Application Name | C1: Sprint Start Date | D1: Sprint End Date | E1: Sprint | F1: Developer | G1: Story ID / Defect ID | H1: Description | I1: Status | J1: Estimated (sp) | K1: Actual (sp) | L1: Actual Hours Worklog | M1: Dev Start Date | N1: Dev End Date | O1: Unit testing | P1: Peer Tested By | Q1: Peer Tested Defects, if any | R1: Peer Reviewed By | S1: Peer Code Review Comments, if any | T1: PR Number/Link | U1: PR Created Date | V1: PR Approved Date | W1: Reviewer 1 | X1: Code Review Comments, if any | Y1: Reviewer 2 | Z1: Approved Date | AA1: Code Review Comments, if any2 | AB1: Internal PO - POV Comments | AC1: Client PO - POV Comments | AD1: Tester Comments | AE1: Developer comments | AF1: Remarks
A2: 1 | B2: GGO Donor Wave | C2: 46030 | D2: 46044 | E2: GGO 8.2.0 Sprint 3 | F2: Vishnu | G2: GDON-68 | H2: Donor API - Include AddressTypeId and CompanyName in the GetProfileCreditCards API * | I2: Completed | J2: 1 | K2: 1 | L2: 12.5 | M2: 46027 | N2: 46030 | O2: Done | P2: Charles | R2: Rajesh | T2: https://dev.azure.com/greatergiving/Greater%20Giving/_git/GGO/pullrequest/9155 | U2: 46030 | V2: 46030 | W2: Rajesh | Y2: Mccarty, Joseph | Z2: 46030 | AD2: Testing activity has been completed in the TST env., Done on 01/09/2026 - 19:00PM
A3: 2 | B3: GGO Donor Wave | C3: 46030 | D3: 46044 | E3: GGO 8.2.0 Sprint 3 | F3: Vishnu | G3: GDON-73 | H3: Create GG API to send Checkout information to Donor Platform | I3: Completed | J3: 5 | K3: 5 | L3: 53.5 | M3: 46031 | N3: 46038 | O3: Done | P3: Charles | R3: Rajesh | T3: https://dev.azure.com/greatergiving/Greater%20Giving/_git/GGO/pullrequest/9178 | U3: 46038 | V3: 46041 | W3: Rajesh | Y3: Mccarty, Joseph | Z3: 46041 | AD3: Testing activity has been completed in the TST env., Done on 01/19/2026 - 21:00PM
A4: 3 | B4: GGO Donor Wave | C4: 46030 | D4: 46044 | E4: GGO 8.2.0 Sprint 3 | F4: Vishnu | G4: GDON-75 | H4: Donor API - Add Donation Sale for Donor | I4: Completed | J4: 3 | K4: 3 | L4: 33.5 | M4: 46038 | N4: 46042 | O4: Done | P4: Charles | R4: Rajesh | T4: https://dev.azure.com/greatergiving/Greater%20Giving/_git/GGO/pullrequest/9188 | U4: 46042 | V4: 46042 | W4: Rajesh | Y4: Mccarty, Joseph | Z4: 46042 | AD4: Testing activity has been completed in the DEV env., Done on 01/20/2026 - 19:20PM Testing activity has been completed in the TST env., Done on 01/21/2026 - 15:00PM
A5: 4 | B5: GGO Donor Wave | C5: 46030 | D5: 46044 | E5: GGO 8.2.0 Sprint 3 | F5: Vishnu | G5: GDON-79 | H5: GetOrCreateAccount API throws error when sending resettokenutc as null* | I5: Completed | J5: 2 | K5: 2 | L5: 19 | M5: 46043 | N5: 46044 | O5: Done | P5: Charles | R5: Rajesh | T5: https://dev.azure.com/greatergiving/Greater%20Giving/_git/GGO/pullrequest/9200 | U5: 46042 | V5: 46043 | W5: Rajesh | Y5: Mccarty, Joseph | Z5: 46043 | AD5: Testing activity has been completed in the TST env., Done on 01/22/2026 - 18:00PM

Sheet GGO 8.2.0 Sprint 3-Defect
A1: S.No | B1: Sprint | C1: Story/Defect ID | D1: Parent Story | E1: Developer | F1: Issue Type | G1: Issue Description | H1: Priority | I1: Defect Source | J1: Type | K1: Status | L1: Root Cause Category | M1: Comments | N1: Found By | O1: RCA Comment | AD1: Tester Comments | AE1: Developer comments | AF1: Remarks
G2: No Defects | AE2: Dev Started on 05-Feb-2026

Sheet GGO 8.2.0 Sprint 1-Status
A1: S.No | B1: Application Name | C1: Sprint Start Date | D1: Sprint End Date | E1: Sprint | F1: Developer | G1: Story ID / Defect ID | H1: Description | I1: Status | J1: Estimated (sp) | K1: Actual (sp) | L1: Actual Hours Worklog | M1: Dev Start Date | N1: Dev End Date | O1: Unit testing | P1: Peer Tested By | Q1: Peer Tested Defects, if any | R1: Peer Reviewed By | S1: Peer Code Review Comments, if any | T1: PR Number/Link | U1: PR Created Date | V1: PR Approved Date | W1: Reviewer 1 | X1: Code Review Comments, if any | Y1: Reviewer 2 | Z1: Approved Date | AA1: Code Review Comments, if any2 | AB1: Internal PO - POV Comments | AC1: Client PO - POV Comments | AD1: Comments | AE1: Remarks
A2: 1 | B2: GGO Donor Wave | C2: 46002 | D2: 46030 | E2: GGO 8.2.0 Sprint 1 | F2: Vishnu | G2: GDON-66 | H2: Donor API - Create Online Bidding Activity without Credit Card Info* | I2: Completed | J2: 5 | K2: 5 | L2: 66.5 | M2: 45996 | N2: 46009 | P2: Charles | R2: Rajesh | T2: https://dev.azure.com/greatergiving/Greater%20Giving/_git/GGO/pullrequest/9104 | U2: 46006 | V2: 46014 | W2: Rajesh | Y2: Mccarty, Joseph | Z2: 46014 | AD2: Testing activity has been completed in the DEV env., Done on 12/18/2025 - 17:00PM Testing activity has been completed in the TST env., Done on 12/24/2025 - 16:00PM | AE2: Coordinated with UI team and verified the following scenarios oba add profile update profile create account organization mapping process save credit card get credit card
A3: 2 | B3: GGO Donor Wave | C3: 46002 | D3: 46030 | E3: GGO 8.2.0 Sprint 1 | F3: Vishnu | G3: GDON-67 | H3: Disabled the Online Bidding activity creation process and hide the display of OB activities in GGAM based on flag | I3: Completed | J3: 5 | K3: 5 | L3: 105 | M3: 46010 | N3: 46024 | P3: Charles | R3: Rajesh | T3: https://dev.azure.com/greatergiving/Greater%20Giving/_git/GGO/pullrequest/9133 | U3: 46015 | V3: 46029 | W3: Rajesh | Y3: Mccarty, Joseph | Z3: 46029 | AD3: Testing activity has been completed in the DEV env., Done on 01/05/2026 - 18:00PM Testing activity has been completed in the TST env., Done on 01/07/2026 - 20:00PM
A4: 3 | B4: GGO Donor Wave | C4: 46002 | D4: 46030 | E4: GGO 8.2.0 Sprint 1 | F4: Vishnu | G4: GDON-68 | H4: Donor API - Include AddressTypeId and CompanyName in the GetProfileCreditCards API * | I4: Verify | J4: 2 | K4: 2 | L4: 19.5 | M4: 46027 | N4: 46030 | P4: Charles | R4: Rajesh

Sheet GGO 8.2.0 Sprint 1-Defect
A1: S.No | B1: Sprint | C1: Story/Defect ID | D1: Parent Story | E1: Developer | F1: Issue Type | G1: Issue Description | H1: Priority | I1: Defect Source | J1: Type | K1: Status | L1: Root Cause Category | M1: Comments | N1: Found By | O1: RCA Comment | AD1: Tester Comments | AE1: Developer comments | AF1: Remarks
G2: No Defects | AE2: Dev Started on 05-Feb-2026

Sheet GGO 8.1.0 Sprint 4-Status
A1: S.No | B1: Application Name | C1: Sprint Start Date | D1: Sprint End Date | E1: Sprint | F1: Developer | G1: Story ID / Defect ID | H1: Description | I1: Status | J1: Estimated (sp) | K1: Actual (sp) | L1: Actual Hours Worklog | M1: Dev Start Date | N1: Dev End Date | O1: Unit testing | P1: Peer Tested By | Q1: Peer Tested Defects, if any | R1: Peer Reviewed By | S1: Peer Code Review Comments, if any | T1: PR Number/Link | U1: PR Created Date | V1: PR Approved Date | W1: Reviewer 1 | X1: Code Review Comments, if any | Y1: Reviewer 2 | Z1: Approved Date | AA1: Code Review Comments, if any2 | AB1: Internal PO -POV Comments | AC1: Client PO -POV Comments | AD1: Comments | AE1: Remarks
A2: 1 | B2: GGO Donor Wave | C2: 45988 | D2: 46002 | E2: GGO 8.1.0 Sprint 4 | F2: Vishnu | G2: GDON-63 | H2: Create Donor Admin Page | I2: Completed | J2: 5 | K2: 5 | M2: 45988 | N2: 45994 | P2: Charles | R2: Rajesh | T2: https://dev.azure.com/greatergiving/Greater%20Giving/_git/GGO/pullrequest/9066 | U2: 45994 | V2: 45994 | W2: Rajesh | Y2: Mccarty, Joseph | Z2: 45994 | AD2: Testing activity has been completed in the TST env., Done on 12/04/2025 - 12:30PM
A3: 2 | B3: GGO Donor Wave | C3: 45988 | D3: 46002 | E3: GGO 8.1.0 Sprint 4 | F3: Vishnu | G3: GDON-65 | H3: Donor API - Validate Online Bidding activity and Card address before creating OB activity | I3: Completed | J3: 2 | K3: 2 | M3: 45994 | N3: 45995 | P3: Charles | R3: Rajesh | T3: https://dev.azure.com/greatergiving/Greater%20Giving/_git/GGO/pullrequest/9076 | U3: 45995 | V3: 45996 | W3: Rajesh | Y3: Mccarty, Joseph | Z3: 45996 | AD3: Testing activity has been completed in the TST env., Done on 12/09/2025 - 13:00PM
A4: 3 | B4: GGO Donor Wave | C4: 45988 | D4: 46002 | E4: GGO 8.1.0 Sprint 4 | F4: Vishnu | G4: GDON-66 | H4: Donor API - Create Online Bidding Activity without Credit Card Info* | I4: Being Developed | J4: 3 | M4: 45996 | P4: Charles | R4: Rajesh

Sheet GGO 8.1.0 Sprint 3-Status
A1: S.No | B1: Application Name | C1: Sprint Start Date | D1: Sprint End Date | E1: Sprint | F1: Developer | G1: Story ID / Defect ID | H1: Description | I1: Status | J1: Estimated (sp) | K1: Actual (sp) | L1: Actual Hours Worklog | M1: Dev Start Date | N1: Dev End Date | O1: Unit testing | P1: Peer Tested By | Q1: Peer Tested Defects, if any | R1: Peer Reviewed By | S1: Peer Code Review Comments, if any | T1: PR Number/Link | U1: PR Created Date | V1: PR Approved Date | W1: Reviewer 1 | X1: Code Review Comments, if any | Y1: Reviewer 2 | Z1: Approved Date | AA1: Code Review Comments, if any2 | AB1: Internal PO -POV Comments | AC1: Client PO -POV Comments | AD1: Comments | AE1: Remarks
A2: 1 | B2: GGO Donor Wave | C2: 45974 | D2: 45988 | E2: GGO 8.1.0 Sprint 3 | F2: Vishnu | G2: GDON-59 | H2: Donor API - Update the Response code for all the donor API based | I2: Completed | J2: 3 | M2: 45982 | N2: 45986 | P2: Charles | R2: Rajesh | T2: https://dev.azure.com/greatergiving/Greater%20Giving/_git/GGO/pullrequest/9048 | U2: 45986 | V2: 45986 | W2: Rajesh | Y2: Mccarty, Joseph | Z2: 45986 | AD2: Testing activity has been completed in the TST env., Done on 11/26/2025 - 17:30PM
A3: 2 | B3: GGO Donor Wave | C3: 45974 | D3: 45988 | E3: GGO 8.1.0 Sprint 3 | F3: Vishnu | G3: GDON-61 | H3: Donor API - Delete Credit Card in donor app should also delete from GGO if no charge is made | I3: Completed | J3: 3 | M3: 45974 | N3: 45979 | P3: Charles | R3: Rajesh | T3: https://dev.azure.com/greatergiving/Greater%20Giving/_git/GGO/pullrequest/9018 | U3: 45978 | V3: 45978 | W3: Rajesh | Y3: Mccarty, Joseph | Z3: 45978 | AD3: Testing activity has been completed in the TST env., Done on 11/18/2025 - 14:00PM
A4: 3 | B4: GGO Donor Wave | C4: 45974 | D4: 45988 | E4: GGO 8.1.0 Sprint 3 | F4: Vishnu | G4: GDON-62 | H4: Donor API - Validate Card data when creating Online Bidding Activity (either card data or CardXid's) | I4: Completed | J4: 2 | M4: 45980 | N4: 45982 | P4: Charles | R4: Rajesh | T4: https://dev.azure.com/greatergiving/Greater%20Giving/_git/GGO/pullrequest/9037 | U4: 45981 | V4: 45982 | W4: Rajesh | Y4: Mccarty, Joseph | Z4: 45982 | AD4: Testing activity has been completed in the TST env., Done on 11/25/2025 - 13:30PM

Sheet GGO 8.1.0 Sprint 2-Status
A1: S.No | B1: Application Name | C1: Sprint Start Date | D1: Sprint End Date | E1: Sprint | F1: Developer | G1: Story ID / Defect ID | H1: Description | I1: Status | J1: Estimated (sp) | K1: Actual (sp) | L1: Actual Hours Worklog | M1: Dev Start Date | N1: Dev End Date | O1: Unit testing | P1: Peer Tested By | Q1: Peer Tested Defects, if any | R1: Peer Reviewed By | S1: Peer Code Review Comments, if any | T1: PR Number/Link | U1: PR Created Date | V1: PR Approved Date | W1: Reviewer 1 | X1: Code Review Comments, if any | Y1: Reviewer 2 | Z1: Approved Date | AA1: Code Review Comments, if any2 | AB1: Internal PO -POV Comments | AC1: Client PO -POV Comments | AD1: Comments | AE1: Remarks
A2: 1 | B2: GGO Donor Wave | C2: 45960 | D2: 45974 | E2: GGO 8.1.0 Sprint 2 [Strech] | F2: Vishnu | G2: GDON-56 | H2: Update Account Creation to include Online Bidding Activity creation if user login via OB | I2: Completed | J2: 2 | M2: 45959 | N2: 45964 | P2: Charles | R2: Rajesh | T2: https://dev.azure.com/greatergiving/Greater%20Giving/_git/GGO/pullrequest/8976 | U2: 45964 | V2: 45965 | W2: Rajesh | Y2: Mccarty, Joseph | Z2: 45965 | AD2: Testing activity done in the DEV env., Completed on 11/04/2025 - 20:00PM Testing activity done in the TST env., Completed on 11/05/2025 - 13:00PM
A3: 2 | B3: GGO Donor Wave | C3: 45960 | D3: 45974 | E3: GGO 8.1.0 Sprint 2 | F3: Vishnu | G3: GDON-57 | H3: Donor API - Update GGO Card reference in SaveCreditCard | I3: Ready for Testing | J3: 2 | M3: 45971 | N3: 45973 | P3: Charles | R3: Rajesh | U3: 45972 | V3: 45973 | W3: Rajesh | Y3: Mccarty, Joseph | Z3: 45973 | AD3: Testing activity done in the DEV env., Completed on 11/12/2025 - 23:00PM Testing activity done in the TST env., Completed on 11/13/2025 - 12:00PM
A4: 3 | B4: GGO Donor Wave | C4: 45960 | D4: 45974 | E4: GGO 8.1.0 Sprint 2 | F4: Vishnu | G4: GDON-58 | H4: Donor API - Update ggo with multiple credit cards from Joinme card reference | I4: Completed | J4: 3 | M4: 45965 | N4: 45971 | P4: Charles | R4: Rajesh | T4: https://dev.azure.com/greatergiving/Greater%20Giving/_git/GGO/pullrequest/8993 | U4: 45968 | V4: 45971 | W4: Rajesh | Y4: Mccarty, Joseph | Z4: 45971 | AD4: Testing activity done in the DEV env., Completed on 11/10/2025 - 19:00PM Testing activity done in the TST env., Completed on 11/11/2025 - 14:00PM

Sheet GGO 8.1.0 Sprint 1-Status
A1: S.No | B1: Application Name | C1: Sprint Start Date | D1: Sprint End Date | E1: Sprint | F1: Developer | G1: Story ID / Defect ID | H1: Description | I1: Status | J1: Estimated (sp) | K1: Actual (sp) | L1: Actual Hours Worklog | M1: Dev Start Date | N1: Dev End Date | O1: Unit testing | P1: Peer Tested By | Q1: Peer Tested Defects, if any | R1: Peer Reviewed By | S1: Peer Code Review Comments, if any | T1: PR Number/Link | U1: PR Created Date | V1: PR Approved Date | W1: Reviewer 1 | X1: Code Review Comments, if any | Y1: Reviewer 2 | Z1: Approved Date | AA1: Code Review Comments, if any2 | AB1: Internal PO -POV Comments | AC1: Client PO -POV Comments | AD1: Comments | AE1: Remarks
A2: 1 | B2: GGO Donor Wave | C2: 45947 | D2: 45960 | E2: GGO 8.1.0 Sprint 1 | F2: Vishnu | G2: GDON-53 | H2: Donor API - Add Company Name for the Business address type | I2: Completed | J2: 2 | M2: 45947 | N2: 45951 | P2: Charles | R2: Rajesh | T2: https://dev.azure.com/greatergiving/Greater%20Giving/_git/GGO/pullrequest/8936 | U2: 45951 | V2: 45951 | W2: Rajesh | Y2: Mccarty, Joseph | Z2: 45951 | AD2: Testing activity done in the TST env., Completed on 10/22/2025 - 17:00PM
A3: 2 | B3: GGO Donor Wave | C3: 45947 | D3: 45960 | E3: GGO 8.1.0 Sprint 1 | F3: Vishnu | G3: GDON-54 | H3: Validate User Profile - Check Bidder/Supporter has got GGAM User Profile or not using "BidderKey" | I3: Completed | J3: 2 | M3: 45952 | N3: 45953 | P3: Charles | R3: Rajesh | T3: https://dev.azure.com/greatergiving/Greater%20Giving/_git/GGO/pullrequest/8948 | U3: 45953 | V3: 45954 | W3: Rajesh | Y3: Mccarty, Joseph | Z3: 45954 | AD3: Testing activity done in the DEV env., Completed on 10/24/2025 - 15:00PM Testing activity done in the TST env., Completed on 10/27/2025 - 12:00PM
A4: 3 | B4: GGO Donor Wave | C4: 45947 | D4: 45960 | E4: GGO 8.1.0 Sprint 1 | F4: Vishnu | G4: GDON-55 | H4: Create OnlineBiddingActivity to accept multiple Credit Card and transfer default ClientXid to respective Org clientxid | I4: Completed | J4: 3 | M4: 45954 | N4: 45958 | P4: Charles | R4: Rajesh | T4: https://dev.azure.com/greatergiving/Greater%20Giving/_git/GGO/pullrequest/8964 | U4: 45958 | V4: 45958 | W4: Rajesh | Y4: Mccarty, Joseph | Z4: 45954 | AD4: Testing activity done in the DEV env., Completed on 10/29/2025 - 13:00PM Testing activity done in the TST env., Completed on 10/29/2025 - 21:00PM | AE4: Before CreateOnlineBiddingActivity >>>UPDATE JOINME.CardReference SET ClientXid ='Z10022' where CardXid ='PY179090'<<< “This is because, apart from the clientXId "S99999" no id's are working for credit card verification, so we are going with this approach”
A5: 4 | B5: GGO Donor Wave | C5: 45947 | D5: 45960 | E5: GGO 8.1.0 Sprint 1 [Strech] | F5: Vishnu | G5: GDON-56 | H5: Update Account Creation to include Online Bidding Activity creation if user login via OB | I5: Being Developed | J5: 3 | M5: 45959

Sheet GGO 8.0.0 Sprint 4-Status
A1: S.No | B1: Application Name | C1: Sprint Start Date | D1: Sprint End Date | E1: Sprint | F1: Developer | G1: Story ID/Defect ID | H1: Description | I1: Status | J1: Estimated(sp) | K1: Actual(sp) | L1: Actual Hours Worklog | M1: Dev Start Date | N1: Dev End Date | O1: Unit testing | P1: Peer Tested By | Q1: Peer Tested Defects, if any | R1: Peer Reviewed By | S1: Peer Code Review Comments, if any | T1: PR Number/Link | U1: PR Created Date | V1: PR Approved Date | W1: Reviewer 1 | X1: Code Review Comments, if any | Y1: Reviewer 2 | Z1: Approved Date | AA1: Code Review Comments, if any2 | AB1: Internal PO -POV Comments | AC1: Client PO -POV Comments | AD1: Comments | AE1: Remarks
A2: 1 | B2: GGO Donor Wave | C2: 45933 | D2: 45946 | E2: GGO 8.0.0 Sprint 4 | F2: Vishnu | G2: GDON-50 | H2: Donor API - Add Address Type for profile | I2: Completed | J2: 2 | M2: 45933 | N2: 45936 | P2: Charles | R2: Rajesh | T2: https://dev.azure.com/greatergiving/Greater%20Giving/_git/GGO/pullrequest/8901 | U2: 45936 | V2: 45936 | W2: Rajesh | Y2: Horihan, Mike | Z2: 45936 | AD2: Testing activity done in the DEV. & TST env., Completed on 10/07/2025 - 13:00PM
A3: 2 | B3: GGO Donor Wave | C3: 45933 | D3: 45946 | E3: GGO 8.0.0 Sprint 4 | F3: Vishnu | G3: GDON-51 | H3: Donor API - Modify Create Account API to validate email and return profile Info | I3: Completed | J3: 5 | M3: 45938 | N3: 45943 | P3: Charles | R3: Rajesh | T3: https://dev.azure.com/greatergiving/Greater%20Giving/_git/GGO/pullrequest/8914 | U3: 45939 | V3: 45943 | W3: Rajesh | Y3: Mccarty, Joseph | Z3: 45943 | AD3: Testing activity done on both DEV & TST env., Completed on 10/13/2025 - 18:30pm - DEV env., Completed on 10/14/2025 - 12:30pm - TST env.,
A4: 3 | B4: GGO Donor Wave | C4: 45933 | D4: 45946 | E4: GGO 8.0.0 Sprint 4 [Strech] | F4: Vishnu | G4: GDON-52 | H4: Handle Image in Update Profile | I4: Completed | J4: 2 | M4: 45944 | N4: 45945 | P4: Charles | R4: Rajesh | T4: https://dev.azure.com/greatergiving/Greater%20Giving/_git/GGO/pullrequest/8921 | U4: 45945 | V4: 45945 | W4: Rajesh | Y4: Mccarty, Joseph | Z4: 45945 | AD4: Testing activity done on both DEV & TST env., Completed on 10/16/2025 - 11:30am - DEV env., Completed on 10/16/2025 - 14:30pm - TST env.,

Sheet GGO 8.0.0 Sprint 3-Status
A1: S.No | B1: Application Name | C1: Sprint Start Date | D1: Sprint End Date | E1: Sprint | F1: Developer | G1: Story ID/Defect ID | H1: Description | I1: Status | J1: Estimated(sp) | K1: Actual(sp) | L1: Actual Hours Worklog | M1: Dev Start Date | N1: Dev End Date | O1: Unit testing | P1: Peer Tested By | Q1: Peer Tested Defects, if any | R1: Peer Reviewed By | S1: Peer Code Review Comments, if any | T1: PR Number/Link | U1: PR Created Date | V1: PR Approved Date | W1: Reviewer 1 | X1: Code Review Comments, if any | Y1: Reviewer 2 | Z1: Approved Date | AA1: Code Review Comments, if any2 | AB1: Internal PO -POV Comments | AC1: Client PO -POV Comments | AD1: Comments | AE1: Remarks
A2: 1 | B2: GGO Donor Wave | C2: 45919 | D2: 45932 | E2: GGO 8.0.0 Sprint 3 | F2: Vishnu | G2: GDON-46 | H2: Donor API - Update ApAdmin settings for Donor App | I2: Completed | J2: 5 | M2: 45922 | N2: 45926 | P2: Charles | R2: Rajesh | T2: https://dev.azure.com/greatergiving/Greater%20Giving/_git/GGO/pullrequest/8866 | U2: 45925 | V2: 45926 | W2: Rajesh | Y2: Mccarty, Joseph | Z2: 45926 | AD2: Testing activity done in the DEV. env., Completed on 09/26/2025 - 14:00PM
A3: 2 | B3: GGO Donor Wave | C3: 45919 | D3: 45932 | E3: GGO 8.0.0 Sprint 3 | F3: Vishnu | G3: GDON-47 | H3: Donor API - Get ApAdmin settings for Donor App | I3: Completed | J3: 2 | M3: 45919 | N3: 45924 | P3: Charles | R3: Rajesh | T3: https://dev.azure.com/greatergiving/Greater%20Giving/_git/GGO/pullrequest/8866 | U3: 45923 | V3: 45926 | W3: Rajesh | Y3: Mccarty, Joseph | Z3: 45926 | AD3: Testing activity done in the DEV. env., Completed on 09/24/2025 - 17:30PM
A4: 3 | B4: GGO Donor Wave | C4: 45919 | D4: 45932 | E4: GGO 8.0.0 Sprint 3 [Strech] | F4: Vishnu | G4: GDON-48 | H4: Donor API - Update GetOrganizationEvents API | I4: Completed | J4: 2 | M4: 45929 | N4: 45930 | P4: Charles | R4: Rajesh | T4: https://dev.azure.com/greatergiving/Greater%20Giving/_git/GGO/pullrequest/8887 | U4: 45930 | V4: 45931 | W4: Rajesh | Y4: Mccarty, Joseph | Z4: 45931 | AD4: Testing activity done in the DEV. env., Completed on 10/03/2025 - 10:30AM

Sheet GGO 8.0.0 Sprint 2-Status
A1: S.No | B1: Application Name | C1: Sprint Start Date | D1: Sprint End Date | E1: Sprint | F1: Developer | G1: Story ID/Defect ID | H1: Description | I1: Status | J1: Estimated(sp) | K1: Actual(sp) | L1: Actual Hours Worklog | M1: Dev Start Date | N1: Dev End Date | O1: Unit testing | P1: Peer Tested By | Q1: Peer Tested Defects, if any | R1: Peer Reviewed By | S1: Peer Code Review Comments, if any | T1: PR Number/Link | U1: PR Created Date | V1: PR Approved Date | W1: Reviewer 1 | X1: Code Review Comments, if any | Y1: Reviewer 2 | Z1: Approved Date | AA1: Code Review Comments, if any2 | AB1: Internal PO -POV Comments | AC1: Client PO -POV Comments | AD1: Comments | AE1: Remarks
A2: 1 | B2: GGO Donor Wave | C2: 45904 | D2: 45918 | E2: GGO 8.0.0 Sprint 2 | F2: Kannan | G2: GDON-31 | H2: Donor API - GetCreditCards for Account/Profile | I2: Completed | J2: 3 | M2: 45910 | N2: 45915 | P2: Charles | R2: Rajesh | T2: https://greatergiving.visualstudio.com/Greater%20Giving/_git/GGO/pullrequest/8840 | U2: 45915 | V2: 45916 | W2: Rajesh | Y2: Wall-Iannarelli, Michael | Z2: 45916 | AD2: Testing activity done in the DEV. env., Completed on 09/16/2025 - 14:00PM
A3: 2 | B3: GGO Donor Wave | C3: 45904 | D3: 45918 | E3: GGO 8.0.0 Sprint 2 | F3: Kannan | G3: GDON-43 | H3: Donor API - Save Credit Card for Account/Profile | I3: Completed | J3: 3 | M3: 45905 | N3: 45910 | P3: Charles | R3: Rajesh | T3: Pull Request 8836: [GDON-43] Save Credit Card for Profile | U3: 45911 | V3: 45911 | W3: Rajesh | Y3: Wall-Iannarelli, Michael | Z3: 45911 | AD3: Testing activity done in the DEV & TST env., Completed on 09/11/2025 - 15:00PM - DEV env., Completed on 09/15/2025 - 12:00PM - TST env.,
A4: 3 | B4: GGO Donor Wave | C4: 45904 | D4: 45918 | E4: GGO 8.0.0 Sprint 2 | F4: Vishnu | G4: GDON-44 | H4: Donor API - UpdateCreditCard for Account/Profile (Update only Primary and Billing address) | I4: Completed | J4: 3 | M4: 45912 | N4: 45917 | P4: Charles | R4: Rajesh | T4: https://dev.azure.com/greatergiving/Greater%20Giving/_git/GGO/pullrequest/8842 | U4: 45917 | V4: 45917 | W4: Rajesh | Y4: Wall-Iannarelli, Michael | Z4: 45917 | AD4: Testing activity done in the DEV & TST env., Completed on 09/17/2025 - 17:00PM - DEV env., Completed on 09/18/2025 - 10:30PM - TST env.,
A5: 4 | B5: GGO Donor Wave | C5: 45904 | D5: 45918 | E5: GGO 8.0.0 Sprint 2 | F5: Ubaithullah | G5: GDON-40 | H5: Donor API - Exception Handling | I5: Completed | J5: 3 | M5: 45905 | N5: 45912 | P5: Charles | R5: Rajesh | T5: https://dev.azure.com/greatergiving/Greater%20Giving/_git/GGO/pullrequest/8819 | U5: 45912 | V5: 45912 | W5: Rajesh | Y5: Wall-Iannarelli, Michael | Z5: 45912 | AD5: Testing activity done in the DEV. env., Completed on 09/13/2025 - 18:20PM
B6: GGO Donor Wave | C6: 45904 | D6: 45918 | E6: GGO 8.0.0 Sprint 2 | F6: Vishnu | G6: GDON-41 | H6: Donor API - Create Profile - Send Email to user after creating profile | I6: Completed | J6: 3 | M6: 45904 | N6: 45917 | P6: Charles | R6: Rajesh | T6: https://dev.azure.com/greatergiving/Greater%20Giving/_git/GGO/pullrequest/8824 (edited) | U6: 45910 | V6: 45917 | W6: Rajesh | Y6: Wall-Iannarelli, Michael | Z6: 45917 | AD6: Testing activity done on both DEV & TST env., Completed on 09/17/2025 - 18:30pm - DEV env., Completed on 09/18/2025 - 11:30am - TST env.,

Sheet GGO 8.0.0 Sprint 1-Status
A1: S.No | B1: Application Name | C1: Sprint Start Date | D1: Sprint End Date | E1: Sprint | F1: Developer | G1: Story ID/Defect ID | H1: Description | I1: Status | J1: Estimated(sp) | K1: Actual(sp) | L1: Actual Hours Worklog | M1: Dev Start Date | N1: Dev End Date | O1: Unit testing | P1: Peer Tested By | Q1: Peer Tested Defects, if any | R1: Peer Reviewed By | S1: Peer Code Review Comments, if any | T1: PR Number/Link | U1: PR Created Date | V1: PR Approved Date | W1: Reviewer 1 | X1: Code Review Comments, if any | Y1: Reviewer 2 | Z1: Approved Date | AA1: Code Review Comments, if any2 | AB1: Internal PO -POV Comments | AC1: Client PO -POV Comments | AD1: Comments | AE1: Remarks
A2: 1 | B2: GGO Donor Wave | C2: 45890 | D2: 45904 | E2: GGO 8.0.0 Sprint 1 | F2: Ubaithullah, Kannan | G2: GDON-36 | H2: Donor API - Update Profile Image | I2: Completed | J2: 2 | M2: 45882 | N2: 45888 | P2: Charles | R2: Prabhu | S2: Provided some internal comments, which has been fixed mentioned in previous Sprint GGO 7.25.0 Sprint 4 | T2: https://greatergiving.visualstudio.com/Greater%20Giving/_git/GGO/pullrequest/8753 | U2: 45888 | V2: 45889 | W2: Prabhu | Y2: Wall-Iannarelli, Michael | Z2: 45889 | AD2: Testing activity done in the TST. env., Completed on 012:00 PM 09/04/2025 | AE2: Found a defect and reported to the respective developer, also created a defect in JIRA - GDON-38. Also verified the updated comments mentioned on this ticket. Ascending and Descending scenarios for uploading a image. Also verified the image upload before OnlineBiddingActivity is created
A3: 2 | B3: GGO Donor Wave | C3: 45890 | D3: 45904 | E3: GGO 8.0.0 Sprint 1 | F3: Ubaithullah, Kannan | G3: GDON-37 | H3: API Request - Pull Organization and Events at the same time | I3: Completed | J3: 2 | M3: 45889 | N3: 45895 | P3: Charles | R3: Rajesh | T3: https://dev.azure.com/greatergiving/Greater%20Giving/_git/GGO/pullrequest/8757 | U3: 45895 | V3: 45876 | W3: Rajesh | Y3: Wall-Iannarelli, Michael | Z3: 45896 | AD3: Testing activity done in the Dev. env., Completed on 09:00 PM 08/28/2025
A4: 3 | B4: GGO Donor Wave | C4: 45890 | D4: 45904 | E4: GGO 8.0.0 Sprint 1 | F4: Vishnu , Ubaithullah | G4: GDON-34 | H4: Donor API - GetCoordinatorProgress | I4: Completed | J4: 2 | M4: 45889 | P4: Rajesh | R4: Rajesh | S4: I did analysis on the Team Coordinator display in GGAM and PROD data, noticed that functionality is disabled for all projects by default and also I verified the PROD data, that the last allowed Team Coordinator data is 2018. So I don’t want to spent much time on this Team Coordinator logic if it is not used in PROD. We will work on implementing new API’s once Donor team decide to add a new UI for this Teams Coordinator functionality in future. I would suggest to reduce the points to 2 and close this ticket.
A5: 4 | B5: GGO Donor Wave | C5: 45890 | D5: 45904 | E5: GGO 8.0.0 Sprint 1 | F5: Kannan | G5: GDON-35 | H5: Donor API - ContactsUpload | I5: Completed | J5: 3 | M5: 45889 | N5: 45895 | P5: Charles | R5: Rajesh | S5: Client Suggestion 1: Do we have this regEx in a common place so that we aren't duplicating code? | T5: https://greatergiving.visualstudio.com/Greater%20Giving/_git/GGO/pullrequest/8771 | U5: 45895 | V5: 45899 | W5: Rajesh | Y5: Wall-Iannarelli, Michael | Z5: 45899 | AD5: Testing activity done in the Dev. env., Completed on 03:00 PM 08/28/2025
A6: 5 | B6: GGO Donor Wave | C6: 45890 | D6: 45904 | E6: GGO 8.0.0 Sprint 1 | F6: Vishnu | G6: GDON-18 | H6: Donor API - Get/Create/Update/Delete FundraisingTeamCoordinator | I6: Completed | J6: 1 | M6: 45880 | N6: 45888 | P6: Charles | R6: Prabhu | S6: Provided some internal comments, which has been fixed mentioned in previous Sprint GGO 7.25.0 Sprint 4 | T6: https://dev.azure.com/greatergiving/Greater%20Giving/_git/GGO/pullrequest/8754 | U6: 45888 | V6: 45889 | W6: Prabhu | Y6: Wall-Iannarelli, Michael | Z6: 45889 | AD6: Tested in the Dev. env., Completed on 18:30 PM 08/20/2025. Onsite QA completed on 2:05AM 25/08/2025
A7: 6 | B7: GGO Donor Wave | C7: 45890 | D7: 45904 | E7: GGO 8.0.0 Sprint 1 [Strech] | F7: Vishnu | G7: GDON-42 | H7: Donor API - GetFundraisingInfo | I7: Completed | J7: 2 | M7: 45897 | N7: 45903 | P7: Charles | R7: Rajesh | T7: https://dev.azure.com/greatergiving/Greater%20Giving/_git/GGO/pullrequest/8801 | U7: 45903 | V7: 45903 | W7: Rajesh | Y7: Wall-Iannarelli, Michael | Z7: 45903 | AD7: Testing activity done in the TST. env., Completed on 08:00 PM 09/04/2025
A8: 7 | B8: GGO Donor Wave | C8: 45890 | D8: 45904 | E8: GGO 8.0.0 Sprint 1 | F8: Ubaithullah, Kannan | G8: GDON-39 | H8: Donor API - Logging | I8: Completed | J8: 5 | M8: 45901 | N8: 45903 | P8: Charles | R8: Rajesh | T8: https://dev.azure.com/greatergiving/Greater%20Giving/_git/GGO/pullrequest/8793 | U8: 45903 | V8: 45903 | W8: Rajesh | Y8: Wall-Iannarelli, Michael | Z8: 45903 | AD8: Testing activity done in the TST. env., Completed on 01:00 PM 09/04/2025

Sheet GGO 7.25.0 Sprint 4-Status
A1: S.No | B1: Application Name | C1: Sprint Start Date | D1: Sprint End Date | E1: Sprint | F1: Developer | G1: Story ID/Defect ID | H1: Description | I1: Status | J1: Estimated(sp) | K1: Actual(sp) | L1: Actual Hours Worklog | M1: Dev Start Date | N1: Dev End Date | O1: Unit testing | P1: Peer Tested By | Q1: Peer Tested Defects, if any | R1: Peer Reviewed By | S1: Peer Code Review Comments, if any | T1: PR Number/Link | U1: PR Created Date | V1: PR Approved Date | W1: Reviewer 1 | X1: Code Review Comments, if any | Y1: Reviewer 2 | Z1: Approved Date | AA1: Code Review Comments, if any2 | AB1: Internal PO -POV Comments | AC1: Client PO -POV Comments | AD1: Comments | AE1: Remarks
A2: 1 | B2: GGO Donor Wave | C2: 45876 | D2: 45890 | E2: GGO 7.25.0 Sprint 4 | F2: Kannan,Ubaithullah | G2: GDON-17 | H2: Donor API - Get/Create/Update/Delete FundraisingTeamMember | I2: Completed | J2: 5 | K2: 5 | M2: 45877 | N2: 45882 | P2: Charles | R2: Rajesh | T2: https://dev.azure.com/greatergiving/Greater%20Giving/_git/GGO/pullrequest/8736 | U2: 45882 | V2: 45883 | W2: Rajesh | Y2: Wall-Iannarelli, Michael | Z2: 45883 | AA2: Remove Semicolon | AD2: Tested in the Dev. env., Completed on 12:30 PM 08/14/2025
A3: 2 | B3: GGO Donor Wave | C3: 45876 | D3: 45890 | E3: GGO 7.25.0 Sprint 4 | F3: Vishnu | G3: GDON-18 | H3: Donor API - Get/Create/Update/Delete FundraisingTeamCoordinator | I3: Completed | J3: 5 | K3: 4 | L3: 85.25 | M3: 45880 | N3: 45888 | P3: Charles | R3: Prabhu | T3: https://dev.azure.com/greatergiving/Greater%20Giving/_git/GGO/pullrequest/8754 | U3: 45888 | V3: 45889 | W3: Prabhu | X3: 1. Correct the params here 2. Correct the param here 3. Don't we have to check teamCoordinator is not null here before accessing its property 4. correct the param name here 5. Why are we keeping empty class here? remove it if not needed Suggestion 1. rather than generic description like 'response' , why don't we use actual description 2. rather than generic description like 'response' , why don't we use actual description (i.e FundraisingTeamCoordinator) 3. You could use else or else if here Does there any edge case of equals 0 here 4. Consider renaming this variable here? to be more descriptive | Y3: Wall-Iannarelli, Michael | Z3: 45889 | AD3: Tested in the Dev. env., Completed on 18:30 PM 08/20/2025
A4: 3 | B4: GGO Donor Wave | C4: 45876 | D4: 45890 | E4: GGO 7.25.0 Sprint 4 | F4: Vishnu | G4: GDON-32 | H4: Donor API - GetOfflineDonation | I4: Completed | J4: 2 | K4: 2 | L4: 22.75 | M4: 45874 | N4: 45877 | P4: Charles | R4: Rajesh | T4: https://greatergiving.visualstudio.com/Greater%20Giving/_git/GGO/pullrequest/8724 | U4: 45878 | V4: 45878 | W4: Rajesh | Y4: Wall-Iannarelli, Michael | Z4: 45878 | AD4: Tested in the Dev. env., Completed on 12:30 PM 08/11/2025
A5: 4 | B5: GGO Donor Wave | C5: 45876 | D5: 45890 | E5: GGO 7.25.0 Sprint 4 | F5: Ubaithullah, Kannan | G5: GDON-33 | H5: Donor API - EditOfflineDonation | I5: Completed | J5: 3 | K5: 3 | L5: 26 | M5: 45875 | N5: 45877 | P5: Charles | R5: Rajesh | T5: https://greatergiving.visualstudio.com/Greater%20Giving/_git/GGO/pullrequest/8724 | U5: 45878 | V5: 45878 | W5: Rajesh | Y5: Wall-Iannarelli, Michael | Z5: 45878 | AD5: Tested in the Dev. env., Completed on 1:30 PM 08/11/2025
A6: 5 | B6: GGO Donor Wave | C6: 45876 | D6: 45890 | E6: GGO 7.25.0 Sprint 4 [Strech] | F6: Ubaithullah, Kannan | G6: GDON-36 | H6: Donor API - Update Profile Image | I6: Verify | J6: 3 | L6: 33.75 | M6: 45882 | N6: 45888 | P6: Charles | R6: Prabhu | S6: Comment/ Suggestions: 1. does the method name is descriptive enough to explain the functionality? 2. Why are we duplicating the if check here? 3. Avoid the Naming rule violation here by start with uppercase | T6: https://greatergiving.visualstudio.com/Greater%20Giving/_git/GGO/pullrequest/8753 | U6: 45888 | V6: 45889 | W6: Prabhu | X6: 1. does the method name is descriptive enough to explain the functionality? 2. Why are we duplicating the if check here? 3. Avoid the Naming rule violation here by start with uppercase 4. Does there any references also needs to be updated? | Y6: Wall-Iannarelli, Michael | Z6: 45889 | AD6: Tested in the Dev. env., Completed on 9:30 PM 08/29/2025 | AE6: Found a defect and reported to the respective developer, also created a defect in JIRA - GDON-38.
A7: 6 | B7: GGO Donor Wave | C7: 45876 | D7: 45890 | E7: GGO 7.25.0 Sprint 4 [Strech] | F7: Ubaithullah, Kannan | G7: GDON-37 | H7: API Request - Pull Organization and Events at the same time | I7: Completed | J7: 3 | L7: 18 | M7: 45889
A8: 7 | B8: GGO Donor Wave | C8: 45876 | D8: 45890 | E8: GGO 7.25.0 Sprint 4 [Strech] | F8: Vishnu | G8: GDON-34 | H8: Donor API - GetCoordinatorProgress | I8: Completed | J8: 5 | L8: 17.5 | M8: 45889

Sheet GGO 7.25.0 Sprint 4-Defect
A1: S.No | B1: Sprint # | C1: Story/Defect ID | D1: Parent Story | E1: Developer | F1: Issue Type | G1: Issue Description | H1: Priority | I1: Defect Source | J1: Type | K1: Status | L1: Root Cause Category | M1: Found By | N1: Comment | O1: RCA Comment
A2: 1 | B2: GGO 7.25.0 Sprint 4 | C2: GDON-38 | D2: GDON-36 | E2: Kannan | F2: Defect | G2: Supporter image Id not updated while updating the profile image | H2: Major | I2: Manual | J2: External | K2: Inprogress | L2: Enhancements | M2: End User | N2: Image URL is showing as null and not getting updated | O2: Incorrect parameter passed during the internal test and also logic has changed

Sheet GGO 7.25.0 Sprint 3-Status
A1: S.No | B1: Application Name | C1: Sprint Start Date | D1: Sprint End Date | E1: Sprint | F1: Developer | G1: Story ID/Defect ID | H1: Description | I1: Status | J1: Estimated(sp) | K1: Actual(sp) | L1: Actual Hours Worklog | M1: Dev Start Date | N1: Dev End Date | O1: Unit testing | P1: Peer Tested By | Q1: Peer Tested Defects, if any | R1: Peer Reviewed By | S1: Peer Code Review Comments, if any | T1: PR Number/Link | U1: PR Created Date | V1: PR Approved Date | W1: Reviewer 1 | X1: Code Review Comments, if any | Y1: Reviewer 2 | Z1: Approved Date | AA1: Code Review Comments, if any2 | AB1: Internal PO -POV Comments | AC1: Client PO -POV Comments | AD1: Comments
A2: 1 | B2: GGO Donor Wave | C2: 45862 | D2: 45876 | E2: GGO 7.25.0 Sprint 3 | F2: Kannan | G2: GDON-29 | H2: Create API to send info from GGO to Donor Platform - Organizations | I2: Completed | J2: 3 | M2: 45863 | N2: 45866 | P2: Charles | R2: Rajesh | T2: Pull Request 8692: GDON-29 Create API to send info from GGO to Donor Platform - Organizations | U2: 45866 | V2: 45868 | W2: Rajesh | Y2: Wall-Iannarelli, Michael | Z2: 45868 | AD2: Tested in the Dev. env., Completed on 6:00 PM 07/31/2025
A3: 2 | B3: GGO Donor Wave | C3: 45862 | D3: 45876 | E3: GGO 7.25.0 Sprint 3 | F3: Ubaithullah, Kannan | G3: GDON-28 | H3: Upload Image for Fundraising pages * | I3: Completed | J3: 2 | M3: 45861 | N3: 45866 | P3: Charles | R3: Rajesh | T3: https://greatergiving.visualstudio.com/Greater%20Giving/_git/GGO/pullrequest/8696 | U3: 45866 | V3: 45867 | W3: Rajesh | Y3: Wall-Iannarelli, Michael | Z3: 45867 | AD3: Tested in the Dev. env., Completed on 2:00 PM 07/29/2025
A4: 3 | B4: GGO Donor Wave | C4: 45862 | D4: 45876 | E4: GGO 7.25.0 Sprint 3 | F4: Ubaithullah, Kannan | G4: GDON-19 | H4: Donor API - Get/Send Email | I4: Completed | J4: 5 | M4: 45867 | N4: 45874 | P4: Charles | R4: Rajesh | T4: https://greatergiving.visualstudio.com/Greater%20Giving/_git/GGO/pullrequest/8713 | U4: 45874 | V4: 45874 | W4: Rajesh | Y4: Wall-Iannarelli, Michael | Z4: 45874 | AD4: Tested in the Dev. env., Completed on 3:00 PM 08/06/2025
A5: 4 | B5: GGO Donor Wave | C5: 45862 | D5: 45876 | E5: GGO 7.25.0 Sprint 3 | F5: Vishnu | G5: GDON-30 | H5: Create GGO API for Donor Platform - Events | I5: Completed | J5: 3 | M5: 45863 | N5: 45874 | P5: Charles | R5: Rajesh | T5: https://dev.azure.com/greatergiving/Greater%20Giving/_git/GGO/pullrequest/8704 | U5: 45873 | V5: 45874 | W5: Rajesh | Y5: Wall-Iannarelli, Michael | Z5: 45874 | AD5: Tested in the Dev. env., Completed on 8:40 PM 08/05/2025
A6: 5 | B6: GGO Donor Wave | C6: 45862 | D6: 45876 | E6: GGO 7.25.0 Sprint 3[Strech] | F6: Kannan | G6: GDON-21 | H6: Donor API - Delete FundraisingActivity | I6: Completed | J6: 2 | M6: 45874 | N6: 45874 | P6: Charles | R6: Rajesh | T6: Pull Request 8708: [GDON-21] Donor API - Delete Fundraising Activity | U6: 45874 | V6: 45874 | W6: Rajesh | Y6: Wall-Iannarelli, Michael | Z6: 45874 | AD6: Tested in the Dev. env., Completed on 4:30 PM 08/06/2025
A7: 6 | B7: GGO Donor Wave | C7: 45862 | D7: 45876 | E7: GGO 7.25.0 Sprint 3[Strech] | F7: Vishnu | G7: GDON-32 | H7: Donor API - GetOfflineDonation | I7: Being Developed | J7: 2 | M7: 45874 | AD7: Tested in the Dev. env., Completed on 12:30 PM 08/11/2025
A8: 7 | B8: GGO Donor Wave | C8: 45862 | D8: 45876 | E8: GGO 7.25.0 Sprint 3[Strech] | F8: Ubaithullah, Kannan | G8: GDON-33 | H8: Donor API - EditOfflineDonation | I8: Being Developed | J8: 3 | M8: 45875 | AD8: Tested in the Dev. env., Completed on 1:30 PM 08/11/2025

Sheet GGO 7.25.0 Sprint 2-Status
A1: S.No | B1: Application Name | C1: Sprint Start Date | D1: Sprint End Date | E1: Sprint | F1: Developer | G1: Story ID/Defect ID | H1: Description | I1: Status | J1: Estimated(sp) | K1: Actual(sp) | L1: Actual Hours Worklog | M1: Dev Start Date | N1: Dev End Date | O1: Unit testing | P1: Peer Tested By | Q1: Peer Tested Defects, if any | R1: Peer Reviewed By | S1: Peer Code Review Comments, if any | T1: PR Number/Link | U1: PR Created Date | V1: PR Approved Date | W1: Reviewer 1 | X1: Code Review Comments, if any | Y1: Reviewer 2 | Z1: Approved Date | AA1: Code Review Comments, if any2 | AB1: Internal PO -POV Comments | AC1: Client PO -POV Comments | AD1: Comments
A2: 1 | B2: GGO Donor Wave | C2: 45848 | D2: 45862 | E2: GGO 7.25.0 Sprint 2 | F2: Kannan, Ubaithullah | G2: GDON-25 | H2: Donor APi - Create/Update Fundraising Page | I2: Completed | J2: 5 | M2: 45848 | N2: 45858 | P2: Charles | R2: Rajesh, Vishnu | T2: Pull Request 8665: [GDON-25] Donor API - Create/Update Fundraising_Page | U2: 45859 | V2: 45859 | W2: Rajesh | Y2: Wall-Iannarelli, Michael | Z2: 45859 | AD2: Tested in the Dev. Completed 6:30 PM 07/22/2025
A3: 2 | B3: GGO Donor Wave | C3: 45848 | D3: 45862 | E3: GGO 7.25.0 Sprint 2 | F3: Ubaithullah | G3: GDON-26 | H3: Donor API - Delete Fundraising Page | I3: Rejected | J3: 2 | AD3: This stoy has been rejected due to fund raising details will be deleted while delete the fund raising activity. So Rajesh provided the justification to reject this story
A4: 3 | B4: GGO Donor Wave | C4: 45848 | D4: 45862 | E4: GGO 7.25.0 Sprint 2 | F4: Ubaithullah | G4: GDON-16 | H4: Donor API - Get FundraisingPage | I4: Completed | J4: 5 | M4: 45853 | N4: 45860 | P4: Charles | R4: Rajesh | T4: https://greatergiving.visualstudio.com/Greater%20Giving/_git/GGO/pullrequest/8673 | U4: 45860 | V4: 45860 | W4: Rajesh | Y4: Wall-Iannarelli, Michael | Z4: 45860 | AD4: Tested in the Dev. Completed 11:30 PM 07/23/2025
A5: 4 | B5: GGO Donor Wave | C5: 45848 | D5: 45862 | E5: GGO 7.25.0 Sprint 2 | F5: Charles | G5: GDON-12 | H5: Donor API - Get/Create/Update/Delete ElectronicContactInfo | I5: Completed | J5: 2 | P5: Charles | R5: Rajesh | T5: https://greatergiving.visualstudio.com/Greater%20Giving/_git/GGO/pullrequest/8632 | AD5: Tested in the Dev. Completed 12:30 PM 07/15/2025
A6: 5 | B6: GGO Donor Wave | C6: 45848 | D6: 45862 | E6: GGO 7.25.0 Sprint 2 | F6: Vishnu | G6: GDON-13 | H6: Donor API - Get/Create/Update/Delete AddressInfo | I6: Completed | J6: 2 | M6: 45848 | N6: 45849 | P6: Charles | R6: Rajesh | T6: https://dev.azure.com/greatergiving/Greater%20Giving/_git/GGO/pullrequest/8645 | U6: 45852 | V6: 45852 | W6: Rajesh | Y6: Wall-Iannarelli, Michael | Z6: 45852 | AD6: Tested in the Dev. Completed 2:00 PM 07/15/2025
A7: 6 | B7: GGO Donor Wave | C7: 45848 | D7: 45862 | E7: GGO 7.25.0 Sprint 2 | F7: Vishnu | G7: GDON-20 | H7: Donor API - GetImage for Fundraising Page | I7: Completed | J7: 2 | M7: 45852 | N7: 45856 | P7: Charles | R7: Rajesh | T7: https://dev.azure.com/greatergiving/Greater%20Giving/_git/GGO/pullrequest/8666 | U7: 45859 | V7: 45859 | W7: Rajesh | Y7: Wall-Iannarelli, Michael | Z7: 45859 | AD7: Tested in the Dev. Completed 8:30 PM 07/22/2025
A8: 7 | B8: GGO Donor Wave | C8: 45848 | D8: 45862 | E8: GGO 7.25.0 Sprint 2 [Strech] | F8: Kannan, Ubaithullah | G8: GDON-28 | H8: Upload image for Fundraising Page | I8: Being Developed | J8: 3 | M8: 45861
A9: 8 | B9: GGO Donor Wave | C9: 45848 | D9: 45862 | E9: GGO 7.25.0 Sprint 2 [Strech] | F9: Vishnu | G9: GDON-23 | H9: Donor API - Get Promote* | I9: Completed | J9: 2 | M9: 45859 | N9: 45861 | P9: Charles | R9: Rajesh | T9: https://dev.azure.com/greatergiving/Greater%20Giving/_git/GGO/pullrequest/8679 | U9: 45861 | V9: 45861 | W9: Rajesh | Y9: Wall-Iannarelli, Michael | Z9: 45861 | AD9: Tested in the Dev. Completed 6:30 PM 07/24/2025

Sheet GGO 7.25.0 Sprint 1-Status
A1: S.No | B1: Application Name | C1: Sprint Start Date | D1: Sprint End Date | E1: Sprint | F1: Developer | G1: Story ID/Defect ID | H1: Description | I1: Status | J1: Estimated(sp) | K1: Actual(sp) | L1: Actual Hours Worklog | M1: Unit testing | N1: Peer Tested By | O1: Peer Tested Defects, if any | P1: Peer Reviewed By | Q1: Peer Code Review Comments, if any | R1: PR Number/Link | S1: PR Created Date | T1: PR Approved Date | U1: Reviewer 1 | V1: Code Review Comments, if any | W1: Reviewer 2 | X1: Approved Date | Y1: Code Review Comments, if any2 | Z1: Internal PO -POV Comments | AA1: Client PO -POV Comments | AB1: Comments
A2: 1 | B2: GGO Donor Wave | C2: 45835 | D2: 45848 | E2: GGO 7.25.0 Sprint 1 | F2: Kannan, Ubaithullah | G2: GDON-11 | H2: Donor API - Get/Create/Update/Delete OnlineBiddingActivity | I2: Completed | J2: 5 | N2: Charles | P2: Rajesh | R2: https://greatergiving.visualstudio.com/Greater%20Giving/_git/GGO/pullrequest/8621 | S2: 45845 | T2: 45846 | U2: Rajesh | W2: Wall-Iannarelli, Michael | X2: 45846 | AB2: Tested in the Dev. Completed 5:30 PM 07/08/2025
A3: 2 | B3: GGO Donor Wave | C3: 45835 | D3: 45848 | E3: GGO 7.25.0 Sprint 1 | F3: Vishnu | G3: GDON-15 | H3: Donor API - Get/Create/Update/Delete AddressBookEntry | I3: Completed | J3: 3 | N3: Charles | P3: Rajesh | R3: https://dev.azure.com/greatergiving/Greater%20Giving/_git/GGO/pullrequest/8615 | S3: 45840 | T3: 45846 | U3: Rajesh | W3: Wall-Iannarelli, Michael | X3: 45846 | AA3: do we need to make sure error type matches operation type for all these methods ? | AB3: Tested in the Dev. Completed 12:30 PM 07/10/2025
A4: 3 | B4: GGO Donor Wave | C4: 45835 | D4: 45848 | E4: GGO 7.25.0 Sprint 1 [Stretch] | F4: Kannan, Ubaithullah | G4: GDON-14 | H4: Donor API - Get/Create/Update/Delete CreditCardInfo | I4: Completed | J4: 3 | N4: Charles | P4: Rajesh | R4: https://greatergiving.visualstudio.com/Greater%20Giving/_git/GGO/pullrequest/8627 | S4: 45846 | T4: 45846 | U4: Rajesh | W4: Wall-Iannarelli, Michael | X4: 45846 | AB4: Tested in the Dev. Completed 3:30 PM 07/09/2025
A5: 4 | B5: GGO Donor Wave | C5: 45835 | D5: 45848 | E5: GGO 7.25.0 Sprint 1 [Stretch] | F5: Ubaithullah | G5: GDON-12 | H5: Donor API - Get/Create/Update/Delete ElectronicContactInfo | I5: Verify | J5: 2 | N5: Charles | P5: Rajesh | R5: https://greatergiving.visualstudio.com/Greater%20Giving/_git/GGO/pullrequest/8632 | S5: 45847 | T5: 45848 | U5: Rajesh | W5: Wall-Iannarelli, Michael | X5: 45848 | AB5: Tested in the Dev. Completed 12:30 PM 07/15/2025
A6: 5 | B6: GGO Donor Wave | C6: 45835 | D6: 45848 | E6: GGO 7.25.0 Sprint 1 [Stretch] | F6: Vishnu | G6: GDON-13 | H6: Donor API - Get/Create/Update/Delete AddressInfo | I6: Being Developed | J6: 2 | N6: Charles | P6: Rajesh | R6: https://dev.azure.com/greatergiving/Greater%20Giving/_git/GGO/pullrequest/8645 | S6: 45852 | T6: 45852 | U6: Rajesh | W6: Wall-Iannarelli, Michael | X6: 45852 | AB6: Tested in the Dev. Completed 2:00 PM 07/15/2025
A7: 6

Sheet GGO 7.24.0 Sprint 4-Status
A1: S.No | B1: Application Name | C1: Sprint Start Date | D1: Sprint End Date | E1: Sprint | F1: Developer | G1: Story ID/Defect ID | H1: Description | I1: Status | J1: Estimated(sp) | K1: Actual(sp) | L1: Actual Hours Worklog | M1: Unit testing | N1: Peer Tested By | O1: Peer Tested Defects, if any | P1: Peer Reviewed By | Q1: Peer Code Review Comments, if any | R1: PR Number/Link | S1: PR Created Date | T1: PR Approved Date | U1: Reviewer 1 | V1: Code Review Comments, if any | W1: Reviewer 2 | X1: Approved Date | Y1: Code Review Comments, if any2 | Z1: Internal PO -POV Comments | AA1: Client PO -POV Comments | AB1: Comments
A2: 1 | B2: GGO Donor Wave | C2: 45820 | D2: 45834 | E2: GGO 7.24.0 Sprint 4 | F2: Kannan, Ubaithullah | G2: GDON-9 | H2: Donor API - Get/Create/Update/Delete Account Information | I2: Completed | J2: 5 | M2: Kannan | N2: Charles | P2: Rajesh | R2: Pull Request 8592: [GDON-9] Donor API - Get/Create/Update/Delete Account Information | S2: 45828 | T2: 45832 | U2: Rajesh | W2: Wall-Iannarelli, Michael | X2: 45828 | AB2: Tested in the Dev. Completed 4:45 PM 06/25/2025
A3: 2 | B3: GGO Donor Wave | C3: 45820 | D3: 45834 | E3: GGO 7.24.0 Sprint 3[Stretch] | F3: Vishnu | G3: GDON-7 | H3: GGO Donor Api Project Pipeline and Release setup | I3: Completed | J3: 2 | L3: 8 | M3: Vishnu | N3: Rajesh | P3: Rajesh | R3: https://dev.azure.com/greatergiving/Greater%20Giving/_git/GGO/pullrequest/8573 | S3: 45819 | T3: 45825 | U3: Rajesh | W3: Horihan, Mike | X3: 45825
A4: 3 | B4: GGO Donor Wave | C4: 45820 | D4: 45834 | E4: GGO 7.24.0 Sprint 4 | F4: Vishnu | G4: GDON-10 | H4: Donor API - Get/Create/Update/Delete Profile Information | I4: Completed | J4: 5 | L4: 36 | M4: Vishnu | N4: Charles | P4: Rajesh | R4: https://dev.azure.com/greatergiving/Greater%20Giving/_git/GGO/pullrequest/8593 | S4: 45828 | T4: 45829 | U4: Rajesh | W4: Wall-Iannarelli, Michael | X4: 45829 | Y4: Suggestion can we rename Phones to PhoneNumbers ? "Phones" by itself implies the hardware | AB4: Tested in the Dev. Completed 5:30 PM 06/24/2025
A5: 4 | B5: GGO Donor Wave | C5: 45820 | D5: 45834 | E5: GGO 7.24.0 Sprint [Stretch] | F5: Kannan, Ubaithullah | G5: GDON-11 | H5: Donor API - Get/Create/Update/Delete OnlineBiddingActivity | I5: Analysis Completed | J5: 5

Sheet GGO 7.24.0 Sprint 3-Status
A1: S.No | B1: Application Name | C1: Sprint Start Date | D1: Sprint End Date | E1: Sprint | F1: Developer | G1: Story ID/Defect ID | H1: Description | I1: Status | J1: Estimated(sp) | K1: Actual(sp) | L1: Actual Hours Worklog | M1: Unit testing | N1: Peer Tested By | O1: Peer Tested Defects, if any | P1: Peer Reviewed By | Q1: Peer Code Review Comments, if any | R1: PR Number/Link | S1: PR Created Date | T1: PR Approved Date | U1: Reviewer 1 | V1: Code Review Comments, if any | W1: Reviewer 2 | X1: Approved Date | Y1: Code Review Comments, if any2 | Z1: Internal PO -POV Comments | AA1: Client PO -POV Comments | AB1: Comments
A2: 1 | B2: GGO Donor Wave | C2: 45806 | D2: 45820 | E2: GGO 7.24.0 Sprint 3 | F2: Kannan | G2: GDON-4 | H2: GGO Donor Api Project Setup (WebApi Project in GGO Repo) | I2: Completed | J2: 3 | K2: 3 | L2: 25 | M2: Vishnu | N2: Rajesh | P2: Rajesh | R2: https://greatergiving.visualstudio.com/Greater%20Giving/_git/GGO/pullrequest/8547 | S2: 45813 | T2: 45817 | U2: Rajesh | W2: Mccarty, Mike | X2: 45817
A3: 2 | B3: GGO Donor Wave | C3: 45806 | D3: 45820 | E3: GGO 7.24.0 Sprint 3 | F3: Vishnu | G3: GDON-5 | H3: Create a Integration Test Project to unit test WebApi calls | I3: Completed | J3: 3 | K3: 3 | L3: 39 | M3: Vishnu | N3: Kannan | P3: Kannan | R3: https://dev.azure.com/greatergiving/Greater%20Giving/_git/GGO/pullrequest/8553 | S3: 45814 | T3: 45818 | U3: Rajesh | W3: Mccarty,Mike Wall | X3: 45818
A4: 3 | B4: GGO Donor Wave | C4: 45806 | D4: 45820 | E4: GGO 7.24.0 Sprint 3 | F4: Ubaithullah | G4: GDON-6 | H4: GGO Donor Api Authentication | I4: Completed | J4: 3 | K4: 3 | L4: 60 | M4: Ubaithullah | N4: Rajesh | P4: Kannan | R4: https://dev.azure.com/greatergiving/Greater%20Giving/_git/GGO/pullrequest/8566 | S4: 45818 | T4: 45819 | U4: Rajesh | W4: Mccarty | X4: 45936 | Y4: If we hardcode password, even temporarily as a placeholder, macroscope will flag it as a critical issue
A5: 4 | B5: GGO Donor Wave | C5: 45806 | D5: 45820 | E5: GGO 7.24.0 Sprint 3[Stretch] | F5: Kannan | G5: GDON-7 | H5: GGO Donor Api Project Pipeline and Release setup | I5: Being Developed | J5: 3 | L5: 43.5 | M5: Vishnu | N5: Rajesh | P5: Rajesh | R5: https://greatergiving.visualstudio.com/Greater%20Giving/_git/GGO/pullrequest/8573 | S5: 45819

Sheet GGO 7.24.0 Sprint 2-Status
A1: S.No | B1: Application Name | C1: Sprint Start Date | D1: Sprint End Date | E1: Sprint | F1: Developer | G1: Story ID/Defect ID | H1: Description | I1: Status | J1: Estimated(sp) | K1: Actual(sp) | L1: Actual Hours Worklog | M1: Unit testing | N1: Peer Tested By | O1: Peer Tested Defects, if any | P1: Peer Reviewed By | Q1: Peer Code Review Comments, if any | R1: PR Number/Link | S1: PR Created Date | T1: PR Approved Date | U1: Reviewer 1 | V1: Code Review Comments, if any | W1: Reviewer 2 | X1: Approved Date | Y1: Code Review Comments, if any2 | Z1: Internal PO -POV Comments | AA1: Client PO -POV Comments | AB1: Comments
A2: 1 | B2: GGO Web | C2: 45793 | D2: 45806 | E2: GGO 7.24.0 Sprint 2 | F2: Rajesh | G2: GGO-14628 | H2: Print Invoice/Receipts page - Timeout when Omit Sales and payment option selected with both Before and After date options | I2: Being Developed | J2: 3 | L2: 27.5 | AB2: Issue not reproduceable in Dev and TST.Need to check query execution CRT The work around has been provided and ticket has been put on hold for now as it only impacts only one client/org and is of low priority
A3: 2 | B3: GGO Web | C3: 45793 | D3: 45806 | E3: GGO 7.24.0 Sprint 2 | F3: Rajesh/ Sathiya | G3: GGO-14656 | H3: Nav Bar Update | I3: Completed | J3: 5 | K3: 5 | L3: 107 | M3: Sathiya | N3: Priya | P3: Rajesh | R3: https://greatergiving.visualstudio.com/Greater%20Giving/_git/GGO/pullrequest/8525 | S3: 45805 | T3: 45805 | U3: Rajesh | W3: Michael Wall | X3: 45805 | AB3: Testing this in the Dev. In Progress 4:32 PM 5/27/2025
A4: 3 | B4: GGO Web | C4: 45793 | D4: 45806 | E4: GGO 7.24.0 Sprint 2 | F4: Saranya | G4: GGO-14679 | H4: Sales Grid and Details Update for old Convenience Fee assets | I4: Completed | J4: 3 | K4: 3 | L4: 19 | M4: Saranya | N4: Rajesh | P4: Sathya | R4: https://greatergiving.visualstudio.com/Greater%20Giving/_git/GGO/pullrequest/8496 | S4: 45793 | T4: 45797 | U4: Rajesh | W4: Michael Wall | X4: 45797 | AB4: Verified in the TST env successfully. 20 May 2025 at 05:52
A5: 4 | B5: GGO Web | C5: 45793 | D5: 45806 | E5: GGO 7.24.0 Sprint 2 | F5: Saranya | G5: GGO-9991 | H5: "Purchaser Company Name" column causes error when the "Export" link is selected | I5: Completed | J5: 2 | K5: 2 | L5: 11.5 | M5: Saranya | N5: Priya | P5: Rajesh | R5: https://greatergiving.visualstudio.com/Greater%20Giving/_git/GGO/pullrequest/8502 | S5: 45796 | T5: 45797 | U5: Rajesh | W5: Michael Wall | X5: 45796 | AB5: Verified this in the TST env. 21 May 2025 at 09:23
A6: 5 | B6: GGO Web | C6: 45793 | D6: 45806 | E6: GGO 7.24.0 Sprint 2 | F6: Rajesh | G6: GGO-14708 | H6: Remove Pivotal WebApi Project from GGO Repo - Unused project and it is using .Net Core 6 (deprecated version)* | I6: Completed | J6: 2 | K6: 2 | L6: 33 | M6: Rajesh | N6: Priya | P6: Saranya | R6: https://greatergiving.visualstudio.com/Greater%20Giving/_git/GGO/pullrequest/8498 | S6: 45794 | T6: 45796 | U6: Saranya | W6: Michael Wall | X6: 45797 | AB6: Offshore QA Verified this in the TST env. 21 May 2025 at 09:23
A7: 6 | B7: GGO Web | C7: 45793 | D7: 45806 | E7: GGO 7.24.0 Sprint 2 | F7: Mike Wall/Rajesh/Saranya | G7: GGO-14701 | H7: Update Implementation of Flag to Disable Card Types in select Organizations | I7: Completed | J7: 2 | K7: 2 | L7: 23.75 | M7: Saranya | N7: Priya | P7: Rajesh | R7: https://greatergiving.visualstudio.com/Greater%20Giving/_git/GGO/pullrequest/8508 | S7: 45798 | T7: 45798 | U7: Rajesh | W7: Michael Wall | X7: 45798 | AB7: Verified in the TST env. 22 May 2025 at 08:01
A8: 7 | B8: GGO Web | C8: 45793 | D8: 45806 | E8: GGO 7.24.0 Sprint 2 | F8: Mike Wall/Rajesh/Saranya | G8: PAPI-858 | H8: Update Flag to Disable Amex in select Organizations With Pre-Token Check* | I8: Completed | J8: 2 | K8: 2 | L8: 38 | M8: Saranya | N8: Priya | P8: Rajesh | R8: https://greatergiving.visualstudio.com/Greater%20Giving/_git/PAPI/pullrequest/8518 | S8: 45799 | T8: 45800 | U8: Rajesh | W8: Mike H | X8: 45800 | AB8: Verified in the TST env. 22 May 2025 at 08:01
A9: 8 | B9: GGO Web | C9: 45793 | D9: 45806 | E9: GGO 7.24.0 Sprint 2 | F9: Rajesh/Saranya | G9: GGO-14684 | H9: Implement Pendo for GGO | I9: Completed | J9: 5 | K9: 5 | L9: 41.75 | M9: Rajesh | N9: Priya | P9: Saranyas | R9: https://greatergiving.visualstudio.com/Greater%20Giving/_git/GGO/pullrequest/8523 | S9: 45804 | T9: 45806 | U9: Rajesh | V9: 1. Let's add the following to the account metadata Environment: pendoEnvironment, 2. PendoUserID should be prefixed with PendoEnvironment so that UserID is unique across all environments 3. Dev and local should not fall under the same environment label | W9: Mike H | X9: 45806 | AB9: Testing this in the Dev. In Progress 4:32 PM 5/27/2025
A10: 9 | B10: GGO Web | C10: 45793 | D10: 45806 | E10: GGO 7.24.0 Sprint 2 | F10: Saranya | G10: GGO-14313 | H10: HIGH- Usage of Manual HTML Sanitization (XSS) | I10: Completed | J10: 2 | K10: 2 | L10: 20.5 | M10: Saranya | N10: Rajesh | P10: Rajesh | R10: https://greatergiving.visualstudio.com/Greater%20Giving/_git/GGO/pullrequest/8524 | S10: 45804 | T10: 45805 | U10: Rajesh | W10: Michael Wall | X10: 45805

Sheet GGO 7.24.0 Sprint 2-Defect
A1: S.No | B1: Sprint # | C1: Story/Defect ID | D1: Parent Story | E1: Developer | F1: Issue Type | G1: Issue Description | H1: Priority | I1: Defect Source | J1: Type | K1: Status | L1: Root Cause Category | M1: Found By | N1: Comment | O1: RCA Comment

Sheet GGO 7.24.0 Sprint 1-Status
A1: S.No | B1: Application Name | C1: Sprint Start Date | D1: Sprint End Date | E1: Sprint | F1: Developer | G1: Story ID/Defect ID | H1: Description | I1: Status | J1: Estimated(sp) | K1: Actual(sp) | L1: Actual Hours Worklog | M1: Unit testing | N1: Peer Tested By | O1: Peer Tested Defects, if any | P1: Peer Reviewed By | Q1: Peer Code Review Comments, if any | R1: PR Number/Link | S1: PR Created Date | T1: PR Approved Date | U1: Reviewer 1 | V1: Code Review Comments, if any | W1: Reviewer 2 | X1: Approved Date | Y1: Code Review Comments, if any2 | Z1: Internal PO -POV Comments | AA1: Client PO -POV Comments | AB1: Comments
A2: 1 | B2: GGO Web | C2: 45779 | D2: 45792 | E2: GGO 7.24.0 Sprint 1 | F2: Sathiya | G2: GGO-13722 | H2: High - Weak Encryption: Insecure Mode of Operation - Cryptography.cs: 56 | I2: Completed | J2: 1 | K2: 1 | L2: 15 | M2: Sathiya | N2: Priya | R2: https://greatergiving.visualstudio.com/Greater%20Giving/_git/GGO/pullrequest/8458 | S2: 45779 | T2: 45779 | U2: Rajesh | W2: Michael Wall | X2: 45780 | AB2: Verified in the TST env.5 May 2025 at 08:36
A3: 2 | B3: GGO Web | C3: 45779 | D3: 45792 | E3: GGO 7.24.0 Sprint 1 | F3: Sathiya | G3: GGO-13723 | H3: High - Weak Encryption: Insecure Mode of Operation - SymmetricAlgorithmProvider.cs: 35 | I3: Completed | J3: 1 | K3: 1 | L3: 34.5 | M3: Sathiya | N3: Priya | R3: https://greatergiving.visualstudio.com/Greater%20Giving/_git/GGO/pullrequest/8457 | S3: 45779 | T3: 45783 | U3: Rajesh | W3: Michael Wall, Loan Troung | X3: 45784 | AB3: Tested in the TST env 7 May 2025 at 09:20
A4: 3 | B4: GGO Web | C4: 45779 | D4: 45792 | E4: GGO 7.24.0 Sprint 1 | F4: Sathiya | G4: GGO-14618 | H4: MEDIUM - BDSA-2024-4605 - System.IdentityModel.Tokens.Jwt/5.5.0 | I4: Completed | J4: 2 | K4: 2 | L4: 10.25 | M4: Sathiya | N4: Rajesh | R4: https://dev.azure.com/greatergiving/Greater%20Giving/_git/GGO/pullrequest/8474 | S4: 45784 | T4: 45785 | U4: Rajesh | W4: Michael Wall | X4: 45785 | AB4: Tested in the Dev env 8:09 PM 5/7/2025
A5: 4 | B5: GGO Web | C5: 45779 | D5: 45792 | E5: GGO 7.24.0 Sprint 1 | F5: Rajesh/Saranya | G5: PAPI-841 | H5: Fix ValidateAndGetPorticoToken calls to handle when Token or CardBrandTransactionId exists | I5: Completed | J5: 2 | K5: 2 | L5: 18 | M5: Saranya | N5: Rajesh | R5: https://greatergiving.visualstudio.com/Greater%20Giving/_git/PAPI/pullrequest/8477 | S5: 45785 | T5: 45786 | U5: Rajesh | W5: Michael Wall | X5: 45786 | AB5: Did one round of Payment Regression Testing for this story in the TST env.9 May 2025 at 09:19
A6: 5 | B6: GGO Web | C6: 45779 | D6: 45792 | E6: GGO 7.24.0 Sprint 1 | F6: Saranya | G6: GGO-14601 | H6: Project UI accepting Invalid Email address results in error on GGO to SF sync | I6: Completed | J6: 2 | K6: 2 | L6: 35 | M6: Saranya | N6: Priya | R6: https://greatergiving.visualstudio.com/Greater%20Giving/_git/GGO/pullrequest/8463 | S6: 45782 | T6: 45783 | U6: Rajesh | W6: Michael Wall | X6: 45783 | AB6: Test Cycle executed Successfully in the TST env.7 May 2025 at 07:30
A7: 6 | B7: GGO Web | C7: 45779 | D7: 45792 | E7: GGO 7.24.0 Sprint 1 | F7: Saranya | G7: GGO-14652 | H7: Enable Online Bidding - Blocked when users mistakenly generate Display Board | I7: Completed | J7: 5 | K7: 5 | L7: 49.5 | M7: Saranya | N7: Rajesh | R7: https://greatergiving.visualstudio.com/Greater%20Giving/_git/GGO/pullrequest/8476 | S7: 45785 | T7: 45787 | U7: Rajesh | W7: Michael Wall | X7: 45789 | AB7: Tested in the TST env 13 May 2025 at 09:16
A8: 7 | B8: GGO Web | C8: 45779 | D8: 45792 | E8: GGO 7.24.0 Sprint 1[Stretch] | F8: Rajesh | G8: GGO-14678 | H8: Unable to Export Sales* | I8: Completed | J8: 2 | K8: 2 | L8: 19 | M8: Rajesh | N8: Sathiya,Priya | R8: NA | S8: NA | T8: NA | U8: NA | W8: NA | X8: NA
A9: 8 | B9: GGO Web | C9: 45779 | D9: 45792 | E9: GGO 7.24.0 Sprint 1 | F9: Rajesh | G9: GGO-14628 | H9: Print Invoice/Receipts page - Timeout when Omit Sales and payment option selected with both Before and After date options | I9: Being Developed | J9: 3 | K9: 0 | L9: 50.5 | AB9: Issue not reproduceable in Dev and TST.Need to check query execution CRT
A10: 9 | B10: GGO Web | C10: 45779 | D10: 45792 | E10: GGO 7.24.0 Sprint 1 | F10: Rajesh/ Sathiya | G10: GGO-14656 | H10: Nav Bar Update | I10: Being Developed | J10: 3 | K10: 0 | L10: 64.5 | AB10: Reskin-V2 is a complete overhaul of the existing Master Page, focusing on delivering a fully responsive design. The new layout seamlessly integrates Telerik controls, Bootstrap, and Kendo UI CSS, ensuring an optimized, modern, and adaptive user experience across all devices. As part of this redesign, we need to explore which Telerik control is best suited for the requested layout to achieve the desired functionality and responsiveness.
A11: 10 | B11: GGO Web | C11: 45779 | D11: 45792 | E11: GGO 7.24.0 Sprint 1 | F11: Priya-QA | G11: GGO-14619 | H11: MEDIUM - CVE-2024-43485 - System.Text.Json/8.0.4 | I11: Completed | J11: 1 | K11: 1 | L11: 29 | M11: NA | N11: NA | O11: NA | P11: NA | Q11: NA | R11: NA | S11: NA | T11: NA | U11: NA | V11: NA | W11: NA | X11: NA | Y11: NA | Z11: NA | AA11: NA | AB11: Completed Testing in the TST env.

Sheet GGO 7.24.0 Sprint 1-Defect
A1: S.No | B1: Sprint # | C1: Story/Defect ID | D1: Parent Story | E1: Developer | F1: Issue Type | G1: Issue Description | H1: Priority | I1: Defect Source | J1: Type | K1: Status | L1: Root Cause Category | M1: Found By | N1: Comment | O1: RCA Comment
B2: GGO 7.24.0 Sprint 1 | C2: GGO-14678 | D2: GGO-13890 | E2: Rajesh | F2: Defect | G2: Unable to Export Sales* | H2: Major | I2: Manual | J2: External | K2: Closed | L2: Enhancements | M2: End User | N2: This is a production issue. The export sale grid functionality broke due to changes in the SLS report | O2: For every small change implemented, a complete regression testing cycle must be performed to ensure system stability. This includes updating both automation and manual test cases to reflect any new or impacted scenarios. Additionally, thorough verification of all buttons across all application pages must be included, and corresponding scenarios should be documented and maintained in the manual test cases to ensure comprehensive coverage.

Sheet GGO 7.23.0 Sprint 4-Status
A1: S.No | B1: Application Name | C1: Sprint Start Date | D1: Sprint End Date | E1: Sprint | F1: Developer | G1: Story ID/Defect ID | H1: Description | I1: Status | J1: Estimated(sp) | K1: Actual(sp) | L1: Actual Hours Worklog | M1: Unit testing | N1: Peer Tested By | O1: Peer Tested Defects, if any | P1: Peer Reviewed By | Q1: Peer Code Review Comments, if any | R1: PR Number/Link | S1: PR Created Date | T1: PR Approved Date | U1: Reviewer 1 | V1: Code Review Comments, if any | W1: Reviewer 2 | X1: Approved Date | Y1: Code Review Comments, if any2 | Z1: Internal PO -POV Comments | AA1: Client PO -POV Comments | AB1: Comments
A2: 1 | B2: GGO Web | C2: 45764 | D2: 45778 | E2: GGO 7.23.0 Sprint 4 | F2: Saranya | G2: PAPI-840 | H2: Remove the use of StringHashTable | I2: Completed | J2: 3 | K2: 3 | L2: 23.5
A3: 2 | B3: GGO Web | C3: 45764 | D3: 45778 | E3: GGO 7.23.0 Sprint 4 | F3: Rajesh, Saranya | G3: GGO-14644 | H3: Remove Hash table in PAPI - GGO need to pass Bluetooth Swipe data on StoreFront scenario* | I3: Completed | J3: 1 | K3: 1 | L3: 14.5 | AB3: Completed One round of Payment Regression
A4: 3 | B4: GGO Web | C4: 45764 | D4: 45778 | E4: GGO 7.23.0 Sprint 4 | F4: Rajesh | G4: GGO-14614 | H4: HIGH - Microsoft.AspNetCore.Http.Connections.Client:1.0.0 | I4: Completed | J4: 2 | K4: 2 | L4: 19.5 | M4: Rajesh | N4: Sathish,Priya | R4: https://greatergiving.visualstudio.com/Greater%20Giving/_git/GGO/pullrequest/8431 | S4: 45770 | T4: 45770 | U4: Rajesh | W4: Loan Troung | X4: 45770 | AB4: Completed One round of Standard Regression
A5: 4 | B5: GGO Web | C5: 45764 | D5: 45778 | E5: GGO 7.23.0 Sprint 4 | F5: Sathya | G5: GGO-14613 | H5: HIGH - Cross-Site Scripting: DOM - MaintenanceNotification.js: 22 & 25 | I5: Completed | J5: 2 | K5: 2 | L5: 34.5 | M5: Sathiya | N5: Rajesh,Priya | R5: https://greatergiving.visualstudio.com/Greater%20Giving/_git/GGO/pullrequest/8434 | S5: 45771 | T5: 45775 | U5: Rajesh | W5: Michael Wall, Loan Troung | X5: 45775
A6: 5 | B6: GGO Web | C6: 45764 | D6: 45778 | E6: GGO 7.23.0 Sprint 4[Stretch] | F6: Sathya | G6: GGO-14658 | H6: CRITICAL - CVE-2021-43569 - starkbank-ecdsa/1.3.1* | I6: Completed | J6: 1 | K6: 1 | L6: 14 | M6: Sathiya | N6: Rajesh,Priya | R6: https://dev.azure.com/greatergiving/Greater%20Giving/_git/GGO/pullrequest/8436 | S6: 45772 | T6: 45775 | U6: Rajesh | W6: Michael Wall | X6: 45775 | AB6: Development has been completed and tested in local and Dev enviroment[28-April-2025] Completed One round of Standard Regression
A7: 6 | B7: GGO Web | C7: 45764 | D7: 45778 | E7: GGO 7.23.0 Sprint 4 | F7: Sathiya, Rajesh | G7: GGO-13722 | H7: High - Weak Encryption: Insecure Mode of Operation - Cryptography.cs: 56 | I7: Peer review | J7: 1 | K7: 0.5 | L7: 12.5 | M7: Sathiya | N7: Rajesh | R7: NA
A8: 7 | B8: GGO Web | C8: 45764 | D8: 45778 | E8: GGO 7.23.0 Sprint 4 | F8: Saranya | G8: GGO-14615 | H8: HIGH - Microsoft.Bcl.Async:1.0.168 | I8: Completed | J8: 2 | K8: 2 | L8: 10.5 | M8: Saranya | N8: Rajesh | R8: https://greatergiving.visualstudio.com/Greater%20Giving/_git/GGO/pullrequest/8427 | S8: 45769 | T8: 45769 | U8: Rajesh | W8: Loan Troung | X8: 45769 | AB8: Completed One round of Standard Regression
A9: 8 | B9: GGO Web | C9: 45764 | D9: 45778 | E9: GGO 7.23.0 Sprint 4 | F9: Saranya | G9: GGO-13723 | H9: High - Weak Encryption: Insecure Mode of Operation - SymmetricAlgorithmProvider.cs: 35 | I9: Peer review | J9: 1 | K9: 0.5 | L9: 22 | R9: NA
A10: 9 | B10: GGO Web | C10: 45764 | D10: 45778 | E10: GGO 7.23.0 Sprint 4[Stretch] | F10: MikeW, Rajesh, Saranya | G10: GGO-14651 | H10: Pass New IsFallback Swipe Flag from GoTime to PAPI | I10: Completed | J10: 2 | K10: 2 | L10: 36 | R10: https://greatergiving.visualstudio.com/Greater%20Giving/_git/GGO/pullrequest/8440 | S10: 45775 | T10: 45775 | U10: Rajesh | W10: Michael Wall | X10: 45775
A11: 10 | B11: GGO Web | C11: 45764 | D11: 45778 | E11: GGO 7.23.0 Sprint 4 | F11: MikeW, Rajesh, Saranya | G11: PAPI-846 | H11: EMV Fallback Requires <EMVChipCondition> Tag along with Swipe Data* | I11: Completed | J11: 3 | K11: 3 | L11: 48 | R11: https://greatergiving.visualstudio.com/Greater%20Giving/_git/PAPI/pullrequest/8441 | S11: 45775 | T11: 45775 | U11: Rajesh | W11: Michael Wall | X11: 45775
A12: 11 | B12: GGO Web | C12: 45764 | D12: 45778 | E12: GGO 7.23.0 Sprint 4 | F12: Priya-QA | G12: GGO-14649 | H12: 22 APR GGO 7.23.0 CRT Release & Regression Testing | I12: Completed | J12: 5 | K12: 5 | L12: 35.5 | AB12: CRT Regression Testing in Progress
A13: 12 | B13: GGO Web | C13: 45764 | D13: 45778 | E13: GGO 7.23.0 Sprint 4 | F13: Priya-QA | G13: PAPI-851 | H13: 22 APR PAPI 7.18.0 CRT Release & Regression Testing | I13: Completed | J13: 3 | K13: 3 | L13: 22 | AB13: CRT Regression Testing in Progress
A14: 13 | B14: GGO Web | C14: 45764 | D14: 45778 | E14: GGO 7.23.0 Sprint 4[Stretch] | F14: Sathiya | G14: GGO-14616 | H14: HIGH & MEDIUM - Microsoft.Owin.Security.OpenIdConnect:4.2.2 | I14: Completed | J14: 2 | K14: 2 | L14: 5.5 | M14: N/A | N14: N/A | O14: N/A | P14: Rajesh | R14: N/A | AB14: Since we can't move Reskin Project from .net framework to .netcore update the comments in the story [04/30/2025]

Sheet GGO 7.23.0 Sprint 4-Defect
A1: S.No | B1: Sprint # | C1: Story/Defect ID | D1: Parent Story | E1: Developer | F1: Issue Type | G1: Issue Description | H1: Priority | I1: Defect Source | J1: Type | K1: Status | L1: Root Cause Category | M1: Found By | N1: Comment | O1: RCA Comment
B2: GGO Web | C2: GGO-14614 | D2: GGO-14662 | E2: Sathiya | F2: Defect | G2: Section Times Page Fails to Load After Launch – 500 Internal Server Error in Console | H2: Significant | I2: Manual | J2: Internal | K2: Closed | L2: Development | M2: Priya/Rajesh | O2: As we updated Microsoft.AspNetCore.Http.Connections.Client:1.0.0 package to latest version 6.0.0.0 but it's dependent package Microsoft.Azure.SignalR.Asp.Net not updated by default Visual Studio and Pipeline doesn't show any exception

Sheet GGO 7.23.0 Sprint 3-Status
A1: S.No | B1: Application Name | C1: Sprint Start Date | D1: Sprint End Date | E1: Sprint | F1: Developer | G1: Story ID/Defect ID | H1: Description | I1: Status | J1: Estimated(sp) | K1: Actual(sp) | L1: Actual Hours Worklog | M1: Unit testing | N1: Peer Tested By | O1: Peer Tested Defects, if any | P1: Peer Reviewed By | Q1: Peer Code Review Comments, if any | R1: PR Number/Link | S1: PR Created Date | T1: PR Approved Date | U1: Reviewer 1 | V1: Code Review Comments, if any | W1: Reviewer 2 | X1: Approved Date | Y1: Code Review Comments, if any2 | Z1: Internal PO -POV Comments | AA1: Client PO -POV Comments | AB1: Comments
A2: 1 | B2: GGO Web | C2: 45750 | D2: 45764 | E2: GGO 7.23.0 Sprint 3 | F2: Sathiya | G2: GGO-14573 | H2: OP to GGO import timeouts | I2: Completed | J2: 3 | K2: 3 | L2: 42 | M2: Sathiya | N2: Priya | O2: Nill | R2: https://dev.azure.com/greatergiving/Greater%20Giving/_git/GGO/pullrequest/8370 | S2: 45754 | T2: 45755 | U2: Rajesh | W2: Mike Wall and Loan | X2: 45755
A3: 2 | B3: GGO Web | C3: 45750 | D3: 45764 | E3: GGO 7.23.0 Sprint 3 | F3: Rajesh | G3: GGO-14633 | H3: Allow Household Share on RSVP Imported Cards | I3: Completed | J3: 3 | K3: 3 | L3: 53 | M3: Rajesh | N3: Priya | O3: Nill
A4: 3 | B4: GGO Web | C4: 45750 | D4: 45764 | E4: GGO 7.23.0 Sprint 3 | F4: Sathiya | G4: GGO-14457 | H4: Allow Multiple RSVP Import from OP | I4: Completed | J4: 5 | K4: 5 | L4: 83 | M4: sathiya | N4: Priya | O4: Nill | R4: https://dev.azure.com/greatergiving/Greater%20Giving/_git/GGO/pullrequest/8380 | S4: 45761 | T4: 45762 | U4: Rajesh | W4: Mike Wall and Loan | X4: 45762
A5: 4 | B5: GGO Web | C5: 45750 | D5: 45764 | E5: GGO 7.23.0 Sprint 3-[Stretch] | F5: Saranya/Sathiya | G5: GGO-14620 | H5: BID-19 Admissions Count issue* | I5: Completed | J5: 3 | K5: 3 | L5: 13.5 | M5: Sathiya | N5: Priya | O5: Nill | R5: https://dev.azure.com/greatergiving/Greater%20Giving/_git/GGO/pullrequest/8407 | S5: 45763 | T5: 45763 | U5: Rajesh | W5: Mike Wall | X5: 45763
A6: 5 | B6: GGO Web | C6: 45750 | D6: 45764 | E6: GGO 7.23.0 Sprint 3-[Stretch] | F6: Priya-QA,Rajesh | G6: PAPI-839 | H6: Ensure all Portico calls use the client's API Key* | I6: Completed | J6: 1 | K6: 1 | L6: 13.25 | M6: NA | N6: NA | O6: NA | P6: NA | Q6: NA | R6: NA | S6: NA | T6: NA | U6: NA | V6: NA | W6: NA | X6: NA | Y6: NA | Z6: NA | AA6: NA | AB6: We dont have access to test EMV transactions. Offshore QA did payment Regression Testing only.
A7: 6 | B7: GGO Web | C7: 45750 | D7: 45764 | E7: GGO 7.23.0 Sprint 3 | F7: Priya-QA | G7: GGO-14617 | H7: HIGH & MEDIUM-Serilog.Sinks.File:4.0.0 | I7: Completed | J7: 1 | K7: 1 | L7: 3 | M7: NA | N7: NA | O7: NA | P7: NA | Q7: NA | R7: NA | S7: NA | T7: NA | U7: NA | V7: NA | W7: NA | X7: NA | Y7: NA | Z7: NA | AA7: NA | AB7: Completed 'testing in the TST env. 11:19 PM 4/7/2025
A8: 7 | B8: GGO Web | C8: 45750 | D8: 45764 | E8: GGO 7.23.0 Sprint 3 | F8: Priya-QA,Rajesh | G8: PAPI-842 | H8: Fix issue where Payer Records CreditCardStatus are being set to Invalid | I8: Completed | J8: 2 | K8: 2 | L8: 17.25 | M8: NA | N8: NA | O8: NA | P8: NA | Q8: NA | R8: NA | S8: NA | T8: NA | U8: NA | V8: NA | W8: NA | X8: NA | Y8: NA | Z8: NA | AA8: NA | AB8: Rajesh - Supported to analyze the root cause. Priya- Did Payment Regression Testing along with the void transaction from OP and Refund scenario
A9: 8 | B9: GGO Web | C9: 45750 | D9: 45764 | E9: GGO 7.23.0 Sprint 3 | F9: Saranya | G9: PAPI-840 | H9: Remove the use of StringHashTable | I9: Peer Review | J9: 8 | K9: 5 | L9: 90.5 | M9: Sathiya | N9: Priya | O9: Nill | AB9: Priya- Did Payment Regression Testing along with the void transaction from OP and Refund scenario. The story was left in Peer Review upon completion, per the client's request to hold it and maintain this branch separately from the CERT branch. Dependency on Onsite QA now
A10: 9 | B10: GGO Web | C10: 45750 | D10: 45764 | E10: GGO 7.23.0 Sprint 3-[Stretch] | F10: Saranya,Rajesh | G10: GGO-14644 | H10: Remove Hash table in PAPI - GGO need to pass Bluetooth Swipe data on StoreFront scenario* | I10: Peer Review | J10: 2 | K10: 1 | L10: 19.5 | M10: Sathiya | N10: Priya | O10: Nill | AB10: Priya- Did Payment Regression Testing along with the void transaction from OP and Refund scenario. The story was left in Peer Review upon completion, per the client's request to hold it and maintain this branch separately from the CERT branch. Dependency on Onsite QA now

Sheet GGO 7.23.0 Sprint 3-Defect
A1: S.No | B1: Sprint # | C1: Story/Defect ID | D1: Parent Story | E1: Developer | F1: Issue Type | G1: Issue Description | H1: Priority | I1: Defect Source | J1: Type | K1: Status | L1: Root Cause Category | M1: Found By | N1: Comment | O1: RCA Comment
B2: GGO Web | C2: GGO-14646 | D2: GGO-14457 | E2: Rajesh | F2: Defect | G2: Code mistakenly overwritten for GGO-14457 | H2: Significant | I2: Manual | J2: Internal | K2: Closed | L2: Development | M2: Rajesh | N2: GGO-14633 Code mistakenly overwritten for GGO-14457. TThe team addressed the issue promptly, and the defect was resolved and closed on the same day. | O2: Going forward team will make sure these kinds of overwrites will not be repeated and will do the review process accordingly

Sheet GGO 7.23.0 Sprint 2-Status
A1: S.No | B1: Application Name | C1: Sprint Start Date | D1: Sprint End Date | E1: Sprint | F1: Developer | G1: Story ID/Defect ID | H1: Description | I1: Status | J1: Estimated(sp) | K1: Actual(sp) | L1: Actual Hours Worklog | M1: Unit testing | N1: Peer Tested By | O1: Peer Tested Defects, if any | P1: Peer Reviewed By | Q1: Peer Code Review Comments, if any | R1: PR Number/Link | S1: PR Created Date | T1: PR Approved Date | U1: Reviewer 1 | V1: Code Review Comments, if any | W1: Reviewer 2 | X1: Approved Date | Y1: Code Review Comments, if any2 | Z1: Internal PO -POV Comments | AA1: Client PO -POV Comments | AB1: Comments
A2: 1 | B2: GGO Web | C2: 45736 | D2: 45750 | E2: GGO 7.23.0 Sprint 2 | F2: Rajesh | G2: GGO-14594 | H2: Invoice Payment Pages are calculating unapplied convenience fees | I2: Completed | J2: 2 | K2: 2 | L2: 22.5 | M2: Rajesh | N2: Saranya/Priya | O2: NA | R2: https://greatergiving.visualstudio.com/Greater%20Giving/_git/GGO/pullrequest/8336 | S2: 45740 | T2: 45740 | U2: Rajesh | W2: Loan Troung | X2: 45740 | AB2: Email Queues and Quartz job issue blocked us to test this. Verified this story in the TST env. 3/28/2025. But still Quartz job issue exists.
A3: 2 | B3: GGO Web | C3: 45736 | D3: 45750 | E3: GGO 7.23.0 Sprint 2-[Stretch] | F3: Rajesh | G3: GGO-14621 | H3: Email queues in TST repeatedly disabling* | I3: Completed | J3: 1 | K3: 1 | L3: 9 | O3: NIL | AB3: Email Queues issue got fixed. But still Quartz job issue exists in the TST env.
A4: 3 | B4: GGO Web | C4: 45736 | D4: 45750 | E4: GGO 7.23.0 Sprint 2-[Stretch] | F4: Rajesh | G4: GGO-14626 | H4: Quartz Job not sending email in TST environment* | I4: Completed | J4: 1 | K4: 1 | L4: 2 | O4: NIL | AB4: Quartz job issue exists in the TST env.
A5: 4 | B5: GGO Web | C5: 45736 | D5: 45750 | E5: GGO 7.23.0 Sprint 2 | F5: Sathiya | G5: GGO-14589 | H5: New clients don't have Invoicing capabilities | I5: Completed | J5: 2 | K5: 2 | L5: 13 | M5: Sathya | N5: Rajesh | R5: https://greatergiving.visualstudio.com/Greater%20Giving/_git/GGO/pullrequest/8330 | S5: 45737 | T5: 45737 | U5: Rajesh | W5: Mike Horihan | X5: 45738 | AB5: Completed Testing in the TST env. 3/25/2025
A6: 5 | B6: GGO Web | C6: 45736 | D6: 45750 | E6: GGO 7.23.0 Sprint 2 | F6: Sathiya | G6: GGO-14606 | H6: Duplicate EventXCode's are Being Created | I6: Completed | J6: 3 | K6: 3 | L6: 71 | M6: Sathya | N6: Rajesh,Priya | O6: NIL | R6: https://greatergiving.visualstudio.com/Greater%20Giving/_git/GGO/pullrequest/8355 | S6: 45743 | T6: 45744 | U6: Rajesh | W6: Loan Troung,Michael Wall | X6: 45744 | AB6: Testing in progres 7:17 PM 3/28/2025
A7: 6 | B7: GGO Web | C7: 45736 | D7: 45750 | E7: GGO 7.23.0 Sprint 2 | F7: Saranya | G7: GGO-14587 | H7: Invoice is not importing or clearing from import area | I7: Completed | J7: 2 | K7: 2 | L7: 32 | M7: Saranya | N7: Sathya | R7: https://greatergiving.visualstudio.com/Greater%20Giving/_git/GGO/pullrequest/8338 | S7: 45740 | T7: 45741 | U7: Rajesh | W7: Loan Troung | X7: 45741 | AB7: Completed Testing in the TST env. 3/28/2025
A8: 7 | B8: GGO Web | C8: 45736 | D8: 45750 | E8: GGO 7.23.0 Sprint 2 | F8: Saranya | G8: GGO-14573 | H8: OP to GGO import timeouts | I8: Being Developed | J8: 3 | K8: 5 | L8: 97 | AB8: We have reproduced this issue in DEV and TST environments but are still unable to reproduce it locally. Based on our analysis, GetClosedMatches method seems to be causing the issue. This method is used to find the closest matched names for the given input names and utilizes the Jaro-Winkler algorithm
A9: 8 | B9: GGO Web | C9: 45736 | D9: 45750 | E9: GGO 7.23.0 Sprint 2 | F9: Priya-QA | G9: GGO-14161 | H9: Rewrite AGG-13 to a new report toolset | I9: Completed | J9: 1 | K9: 1 | L9: 8 | M9: NA | N9: NA | O9: NA | P9: NA | Q9: NA | R9: NA | S9: NA | T9: NA | U9: NA | V9: NA | W9: NA | X9: NA | Y9: NA | Z9: NA | AA9: NA | AB9: Completed Testing in the TST env. 3/25/2025
A10: 9 | B10: GGO Web | C10: 45736 | D10: 45750 | E10: GGO 7.23.0 Sprint 2-[Stretch] | F10: Priya-QA | G10: GGO-14597 | H10: Deprecated "DOMNodeInserted" & "DOMSubtreeModified" event throwing error in multiple places * | I10: Completed | J10: 1 | K10: 1 | L10: 1 | M10: NA | N10: NA | O10: NA | P10: NA | Q10: NA | R10: NA | S10: NA | T10: NA | U10: NA | V10: NA | W10: NA | X10: NA | Y10: NA | Z10: NA | AA10: NA | AB10: Completed Testing in the TST env. 3/28/2025
A11: 10 | B11: GGO Web | C11: 45736 | D11: 45750 | E11: GGO 7.23.0 Sprint 2-[Stretch] | F11: Priya-QA | G11: PAPI-807 | H11: Not all Credit Card Last 4 being added to payments table after hotfix PAPI-795* | I11: Completed | J11: 1 | K11: 1 | L11: 2 | M11: NA | N11: NA | O11: NA | P11: NA | Q11: NA | R11: NA | S11: NA | T11: NA | U11: NA | V11: NA | W11: NA | X11: NA | Y11: NA | Z11: NA | AA11: NA | AB11: We dont have access to test EMV transactions. Offshore QA did payment Regression Testing only.
A12: 11 | B12: GGO Web | C12: 45736 | D12: 45750 | E12: GGO 7.23.0 Sprint 2-[Stretch] | F12: Priya-QA | G12: GGO-14592 | H12: Not all Credit Card Last 4 being added to payments table after hotfix PAPI-795* | I12: Completed | J12: 1 | K12: 1 | L12: 2 | M12: NA | N12: NA | O12: NA | P12: NA | Q12: NA | R12: NA | S12: NA | T12: NA | U12: NA | V12: NA | W12: NA | X12: NA | Y12: NA | Z12: NA | AA12: NA | AB12: We dont have access to test EMV transactions. Offshore QA did payment Regression Testing only.
A13: 12 | B13: GGO Web | C13: 45736 | D13: 45750 | E13: GGO 7.23.0 Sprint 2-[Stretch] | F13: Priya-QA | G13: GGO-14473 | H13: Remove equipment banner* | I13: Completed | J13: 1 | K13: 1 | L13: 1 | M13: NA | N13: NA | O13: NA | P13: NA | Q13: NA | R13: NA | S13: NA | T13: NA | U13: NA | V13: NA | W13: NA | X13: NA | Y13: NA | Z13: NA | AA13: NA | AB13: Completed Testing in the TST env. 3/25/2025
A14: 13 | B14: GGO Web | C14: 45736 | D14: 45750 | E14: GGO 7.23.0 Sprint 2-[Stretch] | F14: Priya-QA | G14: PAPI-839 | H14: Ensure all Portico calls use the client's API Key* | I14: Being Tested | J14: 1 | K14: 1 | L14: 7 | M14: NA | N14: NA | O14: NA | P14: NA | Q14: NA | R14: NA | S14: NA | T14: NA | U14: NA | V14: NA | W14: NA | X14: NA | Y14: NA | Z14: NA | AA14: NA | AB14: We dont have access to test Client API Key's. Offshore QA did payment Regression Testing only.
A15: 14 | B15: GGO Web | C15: 45736 | D15: 45750 | E15: GGO 7.23.0 Sprint 2-[Stretch] | F15: Rajesh,Sathiya | G15: GGO-14602 | H15: Handle message for 3X Reader Wi-Fi connection failed - StoreFront* | I15: Completed | J15: 2 | K15: 2 | L15: 1 | R15: https://greatergiving.visualstudio.com/Greater%20Giving/_git/GGO/pullrequest/8362 | S15: 45748 | T15: 45748 | U15: Rajesh | V15: NA | W15: Loan
A16: 14 | B16: GGO Web | C16: 45736 | D16: 45750 | E16: GGO 7.23.0 Sprint 2-[Stretch] | F16: Rajesh | G16: GGO-14624 | H16: Previous/Next Month buttons not displaying in apAdmin* | I16: Completed | J16: 1 | K16: 1 | L16: 1 | R16: https://greatergiving.visualstudio.com/Greater%20Giving/_git/GGO/pullrequest/8363 | S16: 45748 | T16: 45748 | U16: Rajesh | V16: NA | W16: MikeWall | AB16: Supported Loan for this story

Sheet GGO 7.23.0 Sprint 2-Defect
A1: S.No | B1: Sprint # | C1: Story/Defect ID | D1: Parent Story | E1: Developer | F1: Issue Type | G1: Issue Description | H1: Priority | I1: Defect Source | J1: Type | K1: Status | L1: Root Cause Category | M1: Found By | N1: RCA Comment
B2: GGO 7.23.0 Sprint 2 | C2: GGO-14626 | D2: NA | E2: Rajesh | F2: Defect | G2: Quartz Job not sending email in TST environment* | H2: Significant | I2: Manual | J2: Internal | K2: Closed | L2: Environment_Related | M2: Priya | N2: Deops team did setup new access rule for Azure Image Storage, missed to include Quartz Job server that results in failure of Quartz Job, finally fixed it by giving access for Quartz job server.
B3: GGO 7.23.0 Sprint 2 | C3: GGO-14621 | D3: NA | E3: Rajesh | F3: Defect | G3: Email queues in TST repeatedly disabling* | H3: Significant | I3: Manual | J3: Internal | K3: Closed | L3: Environment_Related | M3: Priya,Nathan | N3: This was issue related to Aesop Service bounce email not validated in Send Grid, removing the bounce email from Queue fixed this issue.

Sheet GGO 7.23.0 Sprint 1-Status
A1: S.No | B1: Application Name | C1: Sprint Start Date | D1: Sprint End Date | E1: Sprint | F1: Developer | G1: Story ID/Defect ID | H1: Description | I1: Status | J1: Estimated(sp) | K1: Actual(sp) | L1: Actual Hours Worklog | M1: Unit testing | N1: Peer Tested By | O1: Peer Tested Defects, if any | P1: Peer Reviewed By | Q1: Peer Code Review Comments, if any | R1: PR Number/Link | S1: PR Created Date | T1: PR Approved Date | U1: Reviewer 1 | V1: Code Review Comments, if any | W1: Reviewer 2 | X1: Approved Date | Y1: Code Review Comments, if any2 | Z1: Internal PO -POV Comments | AA1: Client PO -POV Comments | AB1: Comments
A2: 1 | B2: GGO Web | C2: 45723 | D2: 45736 | E2: GGO 7.23.0 Sprint 1 | F2: Rajesh | G2: GGO-14535 | H2: OPStats.GetRsvpCount not being cached correctly | I2: Completed | J2: 2 | K2: 2 | L2: 22 | M2: Rajesh | N2: Priya | O2: NIL | R2: https://greatergiving.visualstudio.com/Greater%20Giving/_git/GGO/pullrequest/8288 | S2: 45722 | T2: 45723 | U2: Rajesh | W2: Michael Wall | X2: 45723 | AB2: Completed Testing 3/11/2025 7:40 PM
A3: 2 | B3: GGO Web | C3: 45723 | D3: 45736 | E3: GGO 7.23.0 Sprint 1 | F3: Rajesh | G3: PAPI-822 | H3: Handle SystemError Response From Portico SOAP Call | I3: Completed | J3: 2 | K3: 2 | L3: 2.25 | M3: Rajesh | R3: https://dev.azure.com/greatergiving/Greater%20Giving/_git/PAPI/pullrequest/8291 | S3: 45723 | T3: 45724 | U3: Rajesh | W3: Michael Wall, Loan Troung | X3: 45724
A4: 3 | B4: GGO Web | C4: 45723 | D4: 45736 | E4: GGO 7.23.0 Sprint 1 | F4: SathiyaBharathi | G4: GGO-13890 | H4: Rewrite and Update SLS-10 | I4: Completed | J4: 3 | K4: 3 | L4: 45.5 | M4: Sathiya/Rajesh | N4: Priya | O4: NIL | P4: Rajesh | R4: https://dev.azure.com/greatergiving/Greater%20Giving/_git/GGO/pullrequest/8300 | S4: 45727 | T4: 45727 | U4: Rajesh | W4: Michael Wall | X4: 45727 | AB4: Completed Testing in the TST env 8:00 PM 3/12/2025
A5: 4 | B5: GGO Web | C5: 45723 | D5: 45736 | E5: GGO 7.23.0 Sprint 1 | F5: Saranya | G5: PAPI-816 | H5: Investigate Check-In not storing Card or Payer record for Go-Time Enter Card on EMV TAP when flag Portico_TestingNeverSendToProcessor=true | I5: Completed | J5: 2 | K5: 2 | L5: 14.25 | M5: Saranya | N5: Sathiya | P5: Rajesh | R5: https://dev.azure.com/greatergiving/Greater%20Giving/_git/PAPI/pullrequest/8293 | S5: 45723 | T5: 45726 | U5: Rajesh | W5: Michael Wall | X5: 45727 | AB5: Completed Testing in the TST env. 3/11/2025 7:40 PM
A6: 5 | B6: GGO Web | C6: 45723 | D6: 45736 | E6: GGO 7.23.0 Sprint 1 | F6: Rajesh | G6: GGO-14576 | H6: Investigate Card Verify Failure Message | I6: Completed | J6: 2 | K6: 2 | L6: 2.25 | R6: https://greatergiving.visualstudio.com/Greater%20Giving/_git/GGO/pullrequest/8292 | S6: 45723 | T6: 45724 | U6: Rajesh | W6: Michael Wall, Loan Troung | X6: 45724
A7: 6 | B7: GGO Web | C7: 45723 | D7: 45736 | E7: GGO 7.23.0 Sprint 1 | F7: Saranya | G7: PAPI-809 | H7: HIGH - jQuery/2.0.0 in PapiAdmin | I7: Completed | J7: 2 | K7: 2 | L7: 33.75 | M7: Saranya | N7: Rajesh | P7: Sathiya | R7: https://greatergiving.visualstudio.com/Greater%20Giving/_git/PAPI/pullrequest/8314 | S7: 45730 | T7: 45730 | U7: Rajesh | W7: Michael Wall, Loan Troung | X7: 45730 | AB7: Did one round of Payment Regression Testing in the TST env
A8: 7 | B8: GGO Web | C8: 45723 | D8: 45736 | E8: GGO 7.23.0 Sprint 1 | F8: Rajesh | G8: PAPI-808 | H8: HIGH - CVE-2024-43485 System.Text.Json 8.0.4 | I8: Completed | J8: 2 | K8: 2 | L8: 11.75 | M8: Rajesh | N8: Saranya | P8: Saranya | R8: https://greatergiving.visualstudio.com/Greater%20Giving/_git/PAPI/pullrequest/8312 | S8: 45729 | T8: 45730 | U8: Rajesh | W8: Michael Wall, Loan Troung | X8: 45730 | AB8: Did one round of Payment Regression Testing in the TST env
A9: 8 | B9: GGO Web | C9: 45723 | D9: 45736 | E9: GGO 7.23.0 Sprint 1-[Stretch] | F9: SathiyaBharathi/ Saranya/Rajesh | G9: GGO-14586 | H9: At Least 3 Card Brands Can Have Up to 19 Digit PAN* | I9: Ready For Testing | J9: 5 | K9: 5 | L9: 72 | M9: Saranya/Rajesh | N9: Priya | O9: NIL | P9: Saranya | R9: https://dev.azure.com/greatergiving/Greater%20Giving/_git/GGO/pullrequest/8320 | S9: 45734 | T9: 45735 | U9: Rajesh | W9: Michael Wall | X9: 45735 | AB9: Development has been completed and partially completed testing in dev environment[03/19/2025]. Did one round of payment Regression for this story in the TST env.
A10: 9 | B10: GGO Web | C10: 45723 | D10: 45736 | E10: GGO 7.23.0 Sprint 1-[Stretch] | F10: SathiyaBharathi/Rajesh | G10: PAPI-829 | H10: At Least 3 Card Brands Can Have Up to 19 Digit PAN* | I10: Ready For Testing | J10: 2 | K10: 2 | L10: 11.5 | M10: Sathiya/Rajesh | N10: Priya | P10: Saranya | R10: https://dev.azure.com/greatergiving/Greater%20Giving/_git/PAPI/pullrequest/8318 | S10: 45734 | T10: 45735 | U10: Rajesh | W10: Michael Wall | X10: 45735 | AB10: Development has been completed and partially completed testing in dev environment. [03/19/2025]
A11: 10 | B11: GGO Web | C11: 45723 | D11: 45736 | E11: GGO 7.23.0 Sprint 1-[Stretch] | F11: Rajesh | G11: GGO-14587 | H11: Invoice is not importing or clearing from import area* | I11: Being Developed | J11: 3 | L11: 14.5
A12: 11 | B12: GGO Web | C12: 45723 | D12: 45736 | E12: GGO 7.23.0 Sprint 1 | F12: Priya-QA | G12: GGO-14584 | H12: Resolve new issues introduced to automation | I12: Completed | J12: 1 | K12: 1 | L12: 22 | AB12: Dev completed. Testing in Progress. Facing Mailinator Issues in the TST env. Completed Coding and Execution and Raised PR
A13: 12 | B13: GGO Web | C13: 45723 | D13: 45736 | E13: GGO 7.23.0 Sprint 1 | F13: Priya-QA/ Sathiyabharathi/ Rajesh | G13: PAPI-820 | H13: Update the Portico Batch delayed interval | I13: Completed | J13: 1 | K13: 1 | L13: 18 | AB13: We dont have access to test EMV transactions. Offshore QA did payment Regression Testing only.
A14: 13 | B14: GGO Web | C14: 45723 | D14: 45736 | E14: GGO 7.23.0 Sprint 1 | F14: Priya-QA/ Rajesh | G14: GGO-14596 | H14: Add 3X SWIPE card payment method type* | I14: Completed | J14: 1 | K14: 1 | L14: 2 | AB14: We dont have access to test EMV transactions. Offshore QA did payment Regression Testing only.
A15: 14 | B15: GGO Web | C15: 45723 | D15: 45736 | E15: GGO 7.23.0 Sprint 1 | F15: Priya-QA | G15: PAPI-819 | H15: Fix 3X Swipe not Storing CCN Last4 GoTime | Checkin | Enter Card, & StoreFront | I15: Completed | J15: 1 | K15: 1 | L15: 1 | AB15: We dont have access to test EMV transactions. Offshore QA did payment Regression Testing only.

Sheet GGO 7.23.0 Sprint 1-Defect 
A1: S.No | B1: Sprint # | C1: Story/Defect ID | D1: Parent Story | E1: Developer | F1: Issue Type | G1: Issue Description | H1: Priority | I1: Defect Source | J1: Type | K1: Status | L1: Root Cause Category | M1: Found By | N1: RCA Comment

Sheet GGO 7.22.0 Sprint 4-Status
A1: S.No | B1: Application Name | C1: Sprint Start Date | D1: Sprint End Date | E1: Sprint | F1: Developer | G1: Story ID/Defect ID | H1: Description | I1: Status | J1: Estimated(sp) | K1: Actual(sp) | L1: Actual Hours Worklog | M1: Unit testing | N1: Peer Tested By | O1: Peer Tested Defects, if any | P1: Peer Reviewed By | Q1: Peer Code Review Comments, if any | R1: PR Number/Link | S1: PR Created Date | T1: PR Approved Date | U1: Reviewer 1 | V1: Code Review Comments, if any | W1: Reviewer 2 | X1: Approved Date | Y1: Code Review Comments, if any2 | Z1: Internal PO -POV Comments | AA1: Client PO -POV Comments | AB1: Comments
A2: 1 | B2: =Dashboard!$J$1 -> GGO Donor Wave | C2: 45709 | D2: 45722 | E2: GGO 7.22.0 Sprint 4 | F2: Saranya | G2: GGO-14070 | H2: Rewrite BID-15 to a new report toolset | I2: Completed | J2: 2 | K2: 2 | L2: 15.5 | M2: Saranya | N2: Priya | O2: Alignment Issues/ Design Issues | AB2: Test Case Prepartion is done 5:48 PM 2/7/2025. Tested in dev env. 7:30 PM 2/19/2025 Carry forwarded to next sprint : Saranya worked on the RDLC report and own the full task took some time for her to learn and implement. Bug GGO-14564 was created on 20/02/2025. Pull request created on 20/02/2025 and Closed on 21 February 2025 at 03:41
A3: 3 | B3: =Dashboard!$J$1 -> GGO Donor Wave | C3: 45709 | D3: 45722 | E3: GGO 7.22.0 Sprint 4 | F3: Sathiyabharathi | G3: GGO-14547 | H3: Edit Package Image Display Issue | I3: Completed | J3: 2 | K3: 1 | L3: 9 | M3: Sathiya | N3: Priya | O3: NA | R3: https://dev.azure.com/greatergiving/Greater%20Giving/_git/GGO/pullrequest/8265 | S3: 45709 | U3: Rajesh | AB3: Peer testing N/A for this bug it's required DB update. Priya: Verified in TST env.8:56 PM 2/24/2025
A4: 4 | B4: GGO Web | C4: 45709 | D4: 45722 | E4: GGO 7.22.0 Sprint 4 | F4: Sathiyabharathi | G4: GGO-14545 | H4: Move the Azure Storage Settings in to Redis/IIS cache to avoid multiple DB calls | I4: Completed | J4: 2 | K4: 3 | L4: 40.25 | M4: Sathiya | N4: Priya | O4: NA | R4: http://dev.azure.com/greatergiving/Greater%20Giving/_git/GGO/pullrequest/8272 | S4: 45714 | T4: 45714 | U4: Rajesh | AB4: [02/25/2025]-Created draft PR. Dev Testing in Progress. Tested in the TST env. Working well 7:47 PM2/27/2025
A5: 5 | B5: GGO Web | C5: 45709 | D5: 45722 | E5: GGO 7.22.0 Sprint 4 | F5: Loan/Sathiyabharathi | G5: GGO-14510 | H5: High - BDSA-2024-4305 - bootstrap/4.6.2 | I5: Being Tested | J5: 5 | K5: 3 | L5: 75.25 | M5: Sathiya | O5: NA | W5: Loan Troung | X5: 45714 | AB5: This story is developed by an onsite developer (Loan). After a Bootstrap version update, we’re facing some UI issues. Offshore developer (Sathiya) is assisting with that. Tested this in the TST env. Raised a bug under this. 5:51 PM 3/5/2025. Nathan Comments: Got some Errors in Automation. So It require automation code updates or app code fix.
A6: 6 | B6: GGO Web | C6: 45709 | D6: 45722 | E6: GGO 7.22.0 Sprint 4 | F6: Saranya | G6: GGO-14567 | H6: Bypass Verify on 3X Storefront swipe | I6: Completed | J6: 2 | K6: 2 | L6: 34.5 | M6: Saranya | N6: Priya | R6: https://greatergiving.visualstudio.com/Greater%20Giving/_git/GGO/pullrequest/8281 | S6: 45716 | T6: 45720 | U6: Rajesh | W6: Loan Troung | X6: 45721 | AB6: We dont have access to test EMV transactions. Did Payment Regression Testing using manual cards. Since Portico is down, we were not able to verify swipe transactions. Portico is UP on last day of sprint, Verified and Completed.
A7: 7 | B7: GGO Web | C7: 45709 | D7: 45722 | E7: GGO 7.22.0 Sprint 4 | F7: Saranya | G7: PAPI-811 | H7: Bypass Verify on 3X Storefront swipe | I7: Completed | J7: 2 | K7: 2 | L7: 35.75 | M7: Saranya | N7: Priya | R7: https://greatergiving.visualstudio.com/Greater%20Giving/_git/PAPI/pullrequest/8282 | S7: 45716 | T7: 45720 | U7: Rajesh | W7: Loan Troung | X7: 45721 | AB7: We dont have access to test EMV transactions. Did Payment Regression Testing using manual cards. Since Portico is down, we were not able to verify swipe transactions. Portico is UP on last day of sprint, Verified and Completed.
A8: 8 | B8: GGO Web | C8: 45709 | D8: 45722 | E8: GGO 7.22.0 Sprint 4-[Stretch] | F8: Saranya | G8: GGO-14535 | H8: OPStats.GetRsvpCount not being cached correctly | I8: Being Developed | J8: 2 | K8: 2 | L8: 31 | AB8: Stretch story taken 1 day before sprint end, so got carry forwarded to next sprint.
A9: 8 | B9: =Dashboard!$J$1 -> GGO Donor Wave | C9: 45709 | D9: 45722 | E9: GGO 7.22.0 Sprint 4 | F9: Priya-QA | G9: GGO-14546 | H9: Automation Maintenance | I9: Completed | J9: 1 | K9: 1 | L9: 10 | AB9: Coding is still in progress 8:55 PM 2/24/2025. Completed almost all the files. Execution is in Progress 8:33 PM 3/3/2025 Execution Completed on 3/5/2025.
A10: 9 | B10: =Dashboard!$J$1 -> GGO Donor Wave | C10: 45709 | D10: 45722 | E10: GGO 7.22.0 Sprint 4 | F10: Priya-QA | G10: PAPI-797 | H10: Ensure Credit Card Last 4 is stored in Payers and Payments tables for 3X tap/dip | I10: Completed | J10: 1 | K10: 1 | L10: 3 | M10: NA | N10: NA | O10: NA | P10: NA | Q10: NA | R10: NA | S10: NA | T10: NA | U10: NA | V10: NA | W10: NA | X10: NA | Y10: NA | Z10: NA | AA10: NA | AB10: We dont have access to test EMV transactions. Offshore QA did payment Regression Testing only. Testing blocked (since yesterday) by partial Portico outage – cannot generate successful EMV transactions.
A11: 10 | B11: =Dashboard!$J$1 -> GGO Donor Wave | C11: 45709 | D11: 45722 | E11: GGO 7.22.0 Sprint 4 | F11: Priya-QA | G11: GGO-14566 | H11: 25 Feb GGO 7.22.0 CRT Release & Regression Testing | I11: Completed | J11: 1 | K11: 1 | M11: NA | N11: NA | O11: NA | P11: NA | Q11: NA | R11: NA | S11: NA | T11: NA | U11: NA | V11: NA | W11: NA | X11: NA | Y11: NA | Z11: NA | AA11: NA | AB11: CRT Regression Testing is in Progress. 8:31 PM 3/3/2025.Partially blocked by Portico transaction failures in CRT.Completed Remaining scenario from our end
A12: 11 | B12: GGO Web | C12: 45709 | D12: 45722 | E12: GGO 7.22.0 Sprint 4 | F12: Priya-QA | G12: GGO-14509 | H12: Critical - Privacy Violation | I12: Completed | J12: 1 | K12: 1 | L12: 6 | M12: NA | N12: NA | O12: NA | P12: NA | Q12: NA | R12: NA | S12: NA | T12: NA | U12: NA | V12: NA | W12: NA | X12: NA | Y12: NA | Z12: NA | AA12: NA | AB12: Testing completed in TST env. 8:31 PM 3/3/2025
A13: 12 | B13: GGO Web | C13: 45709 | D13: 45722 | E13: GGO 7.22.0 Sprint 4 | F13: Priya-QA | G13: PAPI-812 | H13: 25 Feb PAPI 7.17.0 CRT Release & Regression Testing | I13: Completed | J13: 1 | K13: 1 | M13: NA | N13: NA | O13: NA | P13: NA | Q13: NA | R13: NA | S13: NA | T13: NA | U13: NA | V13: NA | W13: NA | X13: NA | Y13: NA | Z13: NA | AA13: NA | AB13: CRT Regression Testing is in Progress. 8:31 PM 3/3/2025.Partially blocked by Portico transaction failures in CRT. Completed Remaining scenario from our end

Sheet GGO 7.22.0 Sprint 4-Defect
A1: S.No | B1: Sprint # | C1: Story/Defect ID | D1: Parent Story | E1: Developer | F1: Issue Type | G1: Issue Description | H1: Priority | I1: Defect Source | J1: Type | K1: Status | L1: Root Cause Category | M1: Found By | N1: RCA Comment
B2: GGO 7.22.0 Sprint 4 | C2: GGO-14563 | D2: GGO-14504 | E2: Sathiyabharathi | F2: Defect | G2: If Adjusted Admissions purchased by one supporter 'even out,' Supporter Form -> Sales Summary does not show asterisk | H2: Significant | I2: Manual | J2: Internal | K2: Closed | L2: Development | M2: Nathan
B3: GGO 7.22.0 Sprint 4 | C3: GGO-14564 | D3: GGO-14070 | E3: Saranya | F3: Defect | G3: Negative Price Amounts Not Displaying Correctly | H3: Significant | I3: Manual | J3: Internal | K3: Closed | L3: Development | M3: Priya
B4: GGO 7.22.0 Sprint 4 | C4: GGO-14571 | D4: GGO-14070 | E4: Rajesh | F4: Defect | G4: Extra line appears after the Package Name in few scenario's | H4: Significant | I4: Manual | J4: Internal | K4: Closed | L4: Development | M4: Priya
B5: GGO 7.22.0 Sprint 4 | C5: GGO-14510 | D5: GGO-14579 | E5: Loan/Sathiyabharathi | F5: Defect | G5: Alignment Issues in GGO-apAdmin Page | H5: Significant | I5: Manual | J5: Internal | K5: Closed | L5: Development | M5: Priya

Sheet GGO 7.22.0 Sprint 3-Status
A1: S.No | B1: Application Name | C1: Sprint Start Date | D1: Sprint End Date | E1: Sprint | F1: Developer | G1: Story ID/Defect ID | H1: Description | I1: Status | J1: Estimated(sp) | K1: Actual(sp) | L1: Actual Hours Worklog | M1: Unit testing | N1: Peer Tested By | O1: Peer Tested Defects, if any | P1: Peer Reviewed By | Q1: Peer Code Review Comments, if any | R1: PR Number/Link | S1: PR Created Date | T1: PR Approved Date | U1: Reviewer 1 | V1: Code Review Comments, if any | W1: Reviewer 2 | X1: Approved Date | Y1: Code Review Comments, if any2 | Z1: Internal PO -POV Comments | AA1: Client PO -POV Comments | AB1: Comments
A2: 1 | B2: =Dashboard!$J$1 -> GGO Donor Wave | C2: =Dashboard!$F$1 -> 46156 | D2: =Dashboard!$H$1 -> 46170 | E2: GGO 7.22.0 Sprint 3 | F2: Sathiyabharathi | G2: GGO-14503 | H2: Adjust Admission Functionality - add/remove | I2: Completed | J2: 2 | K2: 2 | L2: 23 | M2: Sathiya | N2: Priya | P2: Rajesh | R2: https://dev.azure.com/greatergiving/Greater%20Giving/_git/GGO/pullrequest/8189 | S2: 45691 | T2: 45692 | U2: Rajesh | W2: Loan Troung | X2: 45692 | AB2: Story Analysis and Test Case preparation is on progress 5:07 PM 1/24/2025 Deletion of attendee row if supporter chosen showed the popup confirmation, working on Adjusted amount calculation [1/29/2025] Did developer testing in dev environment no issues found [02/05/2025] Automation is pending[02/19/2025]. Nathan Closed the Automation Ticket
A3: 2 | B3: =Dashboard!$J$1 -> GGO Donor Wave | C3: =Dashboard!$F$1 -> 46156 | D3: =Dashboard!$H$1 -> 46170 | E3: GGO 7.22.0 Sprint 3 | F3: RajeshKannan | G3: GGO-14450 | H3: GGO Image Thumbnail Creation error | I3: Completed | J3: 2 | K3: 2 | L3: 2 | M3: Rajesh | N3: Saranya | P3: Saranya | R3: https://dev.azure.com/greatergiving/Greater%20Giving/_git/GGO/pullrequest/8197 | S3: 45692 | T3: 45693 | U3: Rajesh | W3: Loan Troung | X3: 45693
A4: 3 | B4: =Dashboard!$J$1 -> GGO Donor Wave | C4: =Dashboard!$F$1 -> 46156 | D4: =Dashboard!$H$1 -> 46170 | E4: GGO 7.22.0 Sprint 3 | F4: Rajesh/Saranya | G4: GGO-14529 | H4: Invoice Timeout Fix | I4: Completed | J4: 1 | K4: 1 | L4: 7.5 | N4: Priya | R4: https://dev.azure.com/greatergiving/Greater%20Giving/_git/GGO/pullrequest/8204
A5: 4 | B5: =Dashboard!$J$1 -> GGO Donor Wave | C5: =Dashboard!$F$1 -> 46156 | D5: =Dashboard!$H$1 -> 46170 | E5: GGO 7.22.0 Sprint 3 | F5: Saranya | G5: GGO-14070 | H5: Rewrite BID-15 to a new report toolset | I5: Peer Review | J5: 5 | K5: 5 | L5: 84.5 | N5: Priya | AB5: Test Case Prepartion is done 5:48 PM 2/7/2025. Tested in dev env. 7:30 PM 2/19/2025 Carry forwarded to next sprint : Saranya worked on the RDLC report and own the full task took some time for her to learn and implement
A6: 6 | B6: =Dashboard!$J$1 -> GGO Donor Wave | C6: =Dashboard!$F$1 -> 46156 | D6: =Dashboard!$H$1 -> 46170 | E6: GGO 7.22.0 Sprint 3 | F6: Sathiyabharathi | G6: GGO-14530 | H6: Image Manager Fix | I6: Completed | J6: 1 | K6: 1 | L6: 25.5 | M6: Rajesh | N6: Priya | P6: Priya | R6: https://greatergiving.visualstudio.com/Greater%20Giving/_git/GGO/pullrequest/8218 | S6: 45695 | T6: 45695 | U6: Rajesh | W6: Loan Troung | X6: 45695 | AB6: 02/08/2025: This issue was Identitfied by CS and this is not a development or QA miss, this happens because the Javascript [DOM] component was deprecated and the code need to be updated accordingly.
A7: 7 | B7: =Dashboard!$J$1 -> GGO Donor Wave | C7: =Dashboard!$F$1 -> 46156 | D7: =Dashboard!$H$1 -> 46170 | E7: GGO 7.22.0 Sprint 3 | F7: Sathiyabharathi | G7: GGO-14504 | H7: Adjust Admission Functionality - graph updates | I7: Ready for Testing | J7: 5 | K7: 5 | L7: 60 | N7: Priya | R7: https://greatergiving.visualstudio.com/Greater%20Giving/_git/GGO/pullrequest/8228 | S7: 45700 | T7: 45706 | U7: Rajesh | W7: Loan Troung | X7: 45706 | Y7: GO PRINT N'Drop Procedure [dbo].[sp_GetAdjustedAdmissionCount]' GO IF OBJECT_ID('[dbo].[sp_GetAdjustedAdmissionCount]') IS NOT NULL DROP PROCEDURE [dbo].[sp_GetAdjustedAdmissionCount]; GO It is not necessary, but we do usually add PRINT statement. | AB7: Tested in the Dev env. 5:09 PM 2/17/2025. Completed testing the TST env. 8:27 PM 2/18/2025 Onsite QA Logged bug on last day of sprint, we fixed it deployed before sprint prep, QA didn't get time to complete it.
A8: 8 | B8: =Dashboard!$J$1 -> GGO Donor Wave | C8: =Dashboard!$F$1 -> 46156 | D8: =Dashboard!$H$1 -> 46170 | E8: GGO 7.22.0 Sprint 3 | F8: Priya-QA | G8: GGO-14071 | H8: Rewrite BID-19 to a new report toolset | I8: Completed | J8: 1 | K8: 1 | L8: 22 | M8: NA | N8: NA | O8: NA | P8: NA | Q8: NA | R8: NA | S8: NA | T8: NA | U8: NA | V8: NA | W8: NA | X8: NA | Y8: NA | Z8: NA | AA8: NA | AB8: Test Case Prepartion is done 5:48 PM 2/7/2025. Testing in dev env. 8:41 PM 2/13/2025. Completed Testing in the TST env.
A9: 9 | B9: =Dashboard!$J$1 -> GGO Donor Wave | C9: =Dashboard!$F$1 -> 46156 | D9: =Dashboard!$H$1 -> 46170 | E9: GGO 7.22.0 Sprint 3 | F9: Priya-QA | G9: PAPI-758 | H9: Add support for additional Card Types | I9: Completed | J9: 1 | K9: 1 | L9: 1 | M9: NA | N9: NA | O9: NA | P9: NA | Q9: NA | R9: NA | S9: NA | T9: NA | U9: NA | V9: NA | W9: NA | X9: NA | Y9: NA | Z9: NA | AA9: NA | AB9: Completed Testing in the TST env. Verified all the cards 8:26 PM2/18/2025

Sheet GGO 7.22.0 Sprint 3-Defect
A1: S.No | B1: Sprint # | C1: Story/Defect ID | D1: Parent Story | E1: Developer | F1: Issue Type | G1: Issue Description | H1: Priority | I1: Defect Source | J1: Type | K1: Status | L1: Root Cause Category | M1: Comments
B2: GGO 7.22.0 Sprint 3 | C2: GGO-14542 | D2: GGO-14503 | E2: Sathiyabharathi | F2: Bounceback/Sub-Defect | G2: Admission UI should display even after saving sale with admissions adjusted to 0 | H2: Significant | I2: Manual | J2: Internal | K2: Closed/Rejected | L2: Development
B3: GGO 7.22.0 Sprint 3 | C3: GGO-14544 | D3: GGO-14503 | E3: Sathiyabharathi | F3: Bounceback/Sub-Defect | G3: Fix for GGO-1077 no longer working (allocation deleted via supporter) | H3: Significant | I3: Manual | J3: Internal | K3: Closed/Rejected | L3: Development
B4: GGO 7.22.0 Sprint 3 | C4: GGO-14563 | D4: GGO-14504 | E4: Sathiyabharathi | F4: Bounceback/Sub-Defect | G4: If Adjusted Admissions purchased by one supporter 'even out,' Supporter Form -> Sales Summary does not show asterisk | H4: Significant | I4: Manual | J4: Internal | K4: Inprogress | L4: Development
B5: GGO 7.22.0 Sprint 3 | C5: GGO-14564 | D5: GGO-14070 | E5: Sathiyabharathi | F5: Bounceback/Sub-Defect | G5: Negative Price Amounts Not Displaying Correctly | H5: Significant | I5: Manual | J5: Internal | K5: Inprogress | L5: Development
B6: GGO 7.22.0 Sprint 3 | C6: GGO-14530 | F6: Defect | G6: Image Manager Fix - the Scroll was not working so the CS was only able to see the 1st set of records and nothing beyond that | H6: Significant | I6: Manual | J6: External | K6: Closed/Rejected | L6: Enhancements | M6: This issue was Identitfied by CS and this is not a development or QA miss, this happens because the Javascript [DOM] component was deprecated and the code need to be updated accordingly.

Sheet GGO 7.22.0 Sprint 2-Status
A1: S.No | B1: Application Name | C1: Sprint Start Date | D1: Sprint End Date | E1: Sprint | F1: Developer | G1: Story ID/Defect ID | H1: Description | I1: Status | J1: Estimated(sp) | K1: Actual(sp) | L1: Actual Hours Worklog | M1: Unit testing | N1: Peer Tested By | O1: Peer Tested Defects, if any | P1: Peer Reviewed By | Q1: Peer Code Review Comments, if any | R1: PR Number/Link | S1: PR Created Date | T1: PR Approved Date | U1: Reviewer 1 | V1: Code Review Comments, if any | W1: Reviewer 2 | X1: Approved Date | Y1: Code Review Comments, if any2 | Z1: Internal PO -POV Comments | AA1: Client PO -POV Comments | AB1: Comments
A2: 1 | B2: =Dashboard!$J$1 -> GGO Donor Wave | C2: =Dashboard!$F$1 -> 46156 | D2: =Dashboard!$H$1 -> 46170 | E2: GGO 7.22.0 Sprint 2 | F2: Saranya | G2: GGO-12487 | H2: Adjust Admission Functionality - sale details | I2: Completed | J2: 5 | K2: 5 | L2: 23 | M2: Saranya | N2: Priya | P2: Sathya | R2: https://greatergiving.visualstudio.com/Greater%20Giving/_git/GGO/pullrequest/8184 | S2: 45687 | T2: 45687 | U2: Rajesh | W2: Loan Troung | X2: 45687 | AB2: Story Analysis and Test Case preparation is on progress 5:07 PM 1/24/2025. Priya - Testing in dev env is in progress 4:48 PM 1/30/2025
A3: 2 | B3: =Dashboard!$J$1 -> GGO Donor Wave | C3: =Dashboard!$F$1 -> 46156 | D3: =Dashboard!$H$1 -> 46170 | E3: GGO 7.22.0 Sprint 2 | F3: Sathiyabharathi | G3: GGO-14503 | H3: Adjust Admission Functionality - add/remove | I3: Ready for Testing | J3: 5 | K3: 5 | M3: Sathiya | P3: Rajesh | R3: https://dev.azure.com/greatergiving/Greater%20Giving/_git/GGO/pullrequest/8189 | S3: 45691 | T3: 45692 | U3: Rajesh | W3: Loan Troung | X3: 45692 | AB3: Story Analysis and Test Case preparation is on progress 5:07 PM 1/24/2025 Deletion of attendee row if supporter chosen showed the popup confirmation, working on Adjusted amount calculation [1/29/2025] Did developer testing in TST environment no issues found [02/04/2025] Onsite QA testing pending since [02/04/2025]
A4: 3 | B4: =Dashboard!$J$1 -> GGO Donor Wave | C4: =Dashboard!$F$1 -> 46156 | D4: =Dashboard!$H$1 -> 46170 | E4: GGO 7.22.0 Sprint 2 | F4: RajeshKannan | G4: GGO-14514 | H4: Update remaining admission allocated attendee count in GGO webserivce to OP | I4: Completed | J4: 1 | K4: 1 | M4: Rajesh | N4: Priya | P4: Sathya | R4: https://greatergiving.visualstudio.com/Greater%20Giving/_git/GGO/pullrequest/8174 | S4: 45681 | T4: 45681 | U4: Rajesh | W4: Loan Troung | X4: 45681 | AB4: Completed Testing in the TST env. 8:31 PM 1/29/2025
A5: 4 | B5: =Dashboard!$J$1 -> GGO Donor Wave | C5: =Dashboard!$F$1 -> 46156 | D5: =Dashboard!$H$1 -> 46170 | E5: GGO 7.22.0 Sprint 2 | F5: Sathiyabharathi | G5: GGO-14477 | H5: BID-06 Header Settings Update | I5: Completed | J5: 2 | K5: 2 | M5: Sathiya | N5: Priya | P5: Rajesh | R5: https://greatergiving.visualstudio.com/Greater%20Giving/_git/GGO/pullrequest/8170 | S5: 45680 | T5: 45681 | U5: Rajesh | W5: Michael Wall | X5: 45681 | Z5: This is QA automation which comes under Infrastructure improvement | AB5: Picked on 01/22/2025.Development in progress 23/01/2025 Deployed in dev and completed developer testing. Priya - Completed Testing in Dev. Working well 5:07 PM 1/24/2025. Completed Testing in TST 5:02 PM 1/27/2025
A6: 5 | B6: =Dashboard!$J$1 -> GGO Donor Wave | C6: =Dashboard!$F$1 -> 46156 | D6: =Dashboard!$H$1 -> 46170 | E6: GGO 7.22.0 Sprint 2 | F6: RajeshKannan | G6: GGO-14450 | H6: GGO Image Thumbnail Creation error | I6: Ready for Testing | J6: 2 | K6: 2 | M6: Rajesh | N6: Saranya | P6: Saranya | R6: https://dev.azure.com/greatergiving/Greater%20Giving/_git/GGO/pullrequest/8197 | S6: 45692 | T6: 45693 | U6: Rajesh | W6: Loan Troung | X6: 45693 | AB6: It is completed and given for testing 3 days prior to Sprint end, Offshore QA doesn't got any access to test in TST, only MikeH and Nate got access to test it.
A7: 6 | B7: =Dashboard!$J$1 -> GGO Donor Wave | C7: =Dashboard!$F$1 -> 46156 | D7: =Dashboard!$H$1 -> 46170 | E7: GGO 7.22.0 Sprint 2 | F7: Priya-QA | G7: GGO-14511 | H7: GoTime SF Tap card generate Null Ref Error | I7: Completed | J7: 2 | K7: 2 | M7: NA | N7: NA | O7: NA | P7: NA | Q7: NA | R7: NA | S7: NA | T7: NA | U7: NA | V7: NA | W7: NA | X7: NA | Y7: NA | Z7: NA | AA7: NA | AB7: Priya- Did one round of Payment Regression Testing since we dont have access to Tap cards. 5:01 PM 1/27/2025
A8: 7 | B8: =Dashboard!$J$1 -> GGO Donor Wave | C8: =Dashboard!$F$1 -> 46156 | D8: =Dashboard!$H$1 -> 46170 | E8: GGO 7.22.0 Sprint 2 | F8: Priya-QA | G8: PAPI-794 | H8: Add Tag 9F6E to List of Acceptable Tags in ParseC3XJsonDataToTLV* | I8: Completed | J8: 1` | K8: 1 | M8: NA | N8: NA | O8: NA | P8: NA | Q8: NA | R8: NA | S8: NA | T8: NA | U8: NA | V8: NA | W8: NA | X8: NA | Y8: NA | Z8: NA | AA8: NA | AB8: Priya- Did one round of Payment Regression Testing since we dont have access to Tap cards. 8:00 PM1/28/2025
A9: 8 | B9: =Dashboard!$J$1 -> GGO Donor Wave | C9: =Dashboard!$F$1 -> 46156 | D9: =Dashboard!$H$1 -> 46170 | E9: GGO 7.22.0 Sprint 2 | F9: Saranya | G9: GGO-14529 | H9: Stretch --Invoice Timeout Fix* | I9: Peer Review | J9: 2 | K9: 2 | L9: 12 | R9: https://dev.azure.com/greatergiving/Greater%20Giving/_git/GGO/pullrequest/8204

Sheet GGO 7.22.0 Sprint 2-Defect
A1: S.No | B1: Sprint # | C1: Story/Defect ID | D1: Parent Story | E1: Developer | F1: Issue Type | G1: Issue Description | H1: Priority | I1: Defect Source | J1: Type | K1: Status | L1: Root Cause Category | M1: Comments
B2: GGO 7.22.0 Sprint 2 | C2: GGO-14529 | D2: Production bug | F2: Defect | G2: Invoice timeout fix | H2: Major | I2: Manual | J2: External | K2: Open | L2: Development | M2: A miss from both Onsite and Offshore QA and Onsite and offshore developemnt because the old report generation handled it but the new report didn't so a miss on both testing and developement end. Extended testing needs to be done with a lot more combination of data which could be infinite combination.Moving forward this type of complex reports must be tested by all the team members including onsite lead before pushing to TST environment.

Sheet GGO 7.22.0 Sprint 1-Status
A1: S.No | B1: Application Name | C1: Sprint Start Date | D1: Sprint End Date | E1: Sprint | F1: Developer | G1: Story ID/Defect ID | H1: Description | I1: Status | J1: Estimated(hrs/sp) | K1: Actual(hrs/sp) | L1: Actual Hours Worklog | M1: Unit testing | N1: Peer Tested By | O1: Peer Tested Defects, if any | P1: Peer Reviewed By | Q1: Peer Code Review Comments, if any | R1: PR Number/Link | S1: PR Created Date | T1: PR Approved Date | U1: Reviewer 1 | V1: Code Review Comments, if any | W1: Reviewer 2 | X1: Approved Date | Y1: Code Review Comments, if any2 | Z1: Internal PO -POV Comments | AA1: Client PO -POV Comments | AB1: Comments
A3: 1 | B3: =Dashboard!$J$1 -> GGO Donor Wave | C3: =Dashboard!$F$1 -> 46156 | D3: =Dashboard!$H$1 -> 46170 | E3: GGO 7.22.0 Sprint 1 | F3: Sathiyabharathi/Rajesh Kannan | G3: GGO-14427 | H3: Rewrite and Update BID-06 (Invoice) using RDLC - Part 3 (Sales & Payments) | I3: Completed | J3: 2 | K3: 2 | N3: Priya | P3: Rajesh Kannan | R3: https://dev.azure.com/greatergiving/Greater%20Giving/_git/GGO/pullrequest/8097 | S3: 45657 | T3: 37621 | U3: Rajesh | W3: Michael Wall | X3: 45657 | AB3: Tested in the TST env. And it is In Progress 1/3/2025 8:13 PM. Tested in the Dev as well as in TST Env- 8:28 PM 1/6/2025. Testing is still in progress. 1/8/2025 8:10 PM
A4: 2 | B4: =Dashboard!$J$1 -> GGO Donor Wave | C4: =Dashboard!$F$1 -> 46156 | D4: =Dashboard!$H$1 -> 46170 | E4: GGO 7.22.0 Sprint 1 | F4: Sathiyabharathi | G4: GGO-14474 | H4: Mismatch between the net invoice count and the report being generated. | I4: Completed | J4: 3 | K4: 3 | N4: Priya | P4: Rajesh Kannan | R4: https://dev.azure.com/greatergiving/Greater%20Giving/_git/GGO/pullrequest/8112 | S4: 45664 | T4: 45665 | U4: Rajesh | W4: Loan Troung | X4: 45665 | AB4: Tested in the Dev env. Looks good. 5:01 PM 1/21/2025.Tested in the TST env. Working well. 6:18 PM 1/22/2025
A5: 3 | B5: =Dashboard!$J$1 -> GGO Donor Wave | C5: =Dashboard!$F$1 -> 46156 | D5: =Dashboard!$H$1 -> 46170 | E5: GGO 7.22.0 Sprint 1 | F5: Saranya | G5: PAPI-790 | H5: Insecure Transport: Database - App.config: 5 | I5: Completed | J5: 1 | K5: 1 | N5: Priya | P5: Rajesh Kannan | R5: https://greatergiving.visualstudio.com/Greater%20Giving/_git/PAPI/pullrequest/8136 | S5: 45668 | T5: 45668 | U5: Rajesh | W5: Loan Troung | X5: 45668 | AB5: Did one round of payment related regression Testing in the TST env. Looks good. 7:13 PM 1/16/2025
A6: 4 | B6: =Dashboard!$J$1 -> GGO Donor Wave | C6: =Dashboard!$F$1 -> 46156 | D6: =Dashboard!$H$1 -> 46170 | E6: GGO 7.22.0 Sprint 1 | F6: Saranya/Rajesh Kannan | G6: GGO-14450 | H6: GGO Image Thumbnail Creation error | I6: Being Developed | J6: 3 | K6: 3 | N6: Priya | P6: Rajesh Kannan | R6: https://greatergiving.visualstudio.com/Greater%20Giving/_git/GGO/pullrequest/8158 | S6: 45674 | T6: 45678 | U6: Rajesh | W6: Loan Troung | X6: 45678
A7: 5 | B7: =Dashboard!$J$1 -> GGO Donor Wave | C7: =Dashboard!$F$1 -> 46156 | D7: =Dashboard!$H$1 -> 46170 | E7: GGO 7.22.0 Sprint 1 | F7: Priya-QA | G7: GGO-14422 | H7: Storefront Implement Signature Workflow in legacy go time code | I7: Ready for Testing | J7: 1 | K7: 1 | N7: NA | O7: NA | P7: NA | Q7: NA | R7: NA | S7: NA | T7: NA | U7: NA | V7: NA | W7: NA | X7: NA | Y7: NA | Z7: NA | AA7: NA | AB7: Did one round of payment Regression Testing in the TST env and checked cash and Check flow only(since I dont have EMV acces) Working well. 1/16/2025. 7:13 PM.
A8: 6 | B8: =Dashboard!$J$1 -> GGO Donor Wave | C8: =Dashboard!$F$1 -> 46156 | D8: =Dashboard!$H$1 -> 46170 | E8: GGO 7.22.0 Sprint 1 | F8: Priya-QA/Rajesh Kannan | G8: GGO-14483 | H8: 9 Jan CRT Release & Regression Testing | I8: Completed | J8: 5 | K8: 5 | N8: NA | O8: NA | P8: NA | Q8: NA | R8: NA | S8: NA | T8: NA | U8: NA | V8: NA | W8: NA | X8: NA | Y8: NA | Z8: NA | AA8: NA | AB8: Testing in the progress CRT env.1/17/2025 4:37 PM. Testing is still in progress in CRT env. 1/20/2025 8:12 PM
A9: 7 | B9: =Dashboard!$J$1 -> GGO Donor Wave | C9: =Dashboard!$F$1 -> 46156 | D9: =Dashboard!$H$1 -> 46170 | E9: GGO 7.22.0 Sprint 1 | F9: Saranya | G9: PAPI-791 | H9: Privacy Violation - PorticoSoapXmlBuilder.cs: 290 | I9: Completed | J9: 2 | K9: 2 | R9: NA | S9: NA | T9: NA | U9: NA | V9: NA | W9: NA | X9: NA | Y9: NA | Z9: NA | AA9: NA | AB9: attempted to encrypt the entire XML section, but this failed during XML loading and saving. I observed this same privacy policy violation in two files: PorticoSoapXMLBuilder.cs and PorticoAdminBase.cs We chose PorticoAdminBase.cs for debugging and testing, this file SOAP envelope contains a username and password for Portico access. I encrypted only the username and password. However, I received a 'remote server returned 500 error' upon execution. Since the necessary data is encrypted, marking this as a false positive.
A10: 8 | B10: =Dashboard!$J$1 -> GGO Donor Wave | C10: =Dashboard!$F$1 -> 46156 | D10: =Dashboard!$H$1 -> 46170 | E10: GGO 7.22.0 Sprint 1 | F10: Priya-QA | G10: GGO-14469 | H10: EMV Storefront - Implement Success Message for Card Entry flow | I10: Completed | J10: 1 | K10: 1 | N10: NA | O10: NA | P10: NA | Q10: NA | R10: NA | S10: NA | T10: NA | U10: NA | V10: NA | W10: NA | X10: NA | Y10: NA | Z10: NA | AA10: NA | AB10: Did one round of payment Regression Testing in the TST env. Working well. 1/17/2025 4:36 PM
A11: 9 | B11: =Dashboard!$J$1 -> GGO Donor Wave | C11: =Dashboard!$F$1 -> 46156 | D11: =Dashboard!$H$1 -> 46170 | E11: GGO 7.22.0 Sprint 1 | F11: Priya-QA | G11: GGO-14468 | H11: EMV Checkin - Implement Success Message for Card Entry flow | I11: Completed | J11: 1 | K11: 1 | N11: NA | O11: NA | P11: NA | Q11: NA | R11: NA | S11: NA | T11: NA | U11: NA | V11: NA | W11: NA | X11: NA | Y11: NA | Z11: NA | AA11: NA | AB11: Did one round of payment Regression Testing in the TST env. Working well. 1/17/2025 4:36 PM
A12: 10 | B12: =Dashboard!$J$1 -> GGO Donor Wave | C12: =Dashboard!$F$1 -> 46156 | D12: =Dashboard!$H$1 -> 46170 | E12: GGO 7.22.0 Sprint 1 | F12: Priya-QA | G12: GGO-14447 | H12: QA Automation - update EquipmentExpressVerification to account for date changes | I12: Being Developed | J12: 1 | K12: 1 | O12: NA | R12: https://dev.azure.com/greatergiving/Greater%20Giving/_git/GGAutomation/pullrequest/8157 | S12: 45674
A13: 11 | B13: =Dashboard!$J$1 -> GGO Donor Wave | C13: =Dashboard!$F$1 -> 46156 | D13: =Dashboard!$H$1 -> 46170 | E13: GGO 7.22.0 Sprint 1 | F13: Priya-QA | G13: PAPI-789 | H13: refactor apConstants.EMV_SUCCESS_CODE and apConstants.EMV_FAILURE_CODE usage | I13: Ready for Testing | J13: 1 | K13: 1 | N13: NA | O13: NA | P13: NA | Q13: NA | R13: NA | S13: NA | T13: NA | U13: NA | V13: NA | W13: NA | X13: NA | Y13: NA | Z13: NA | AA13: NA | AB13: Did one round of payment Regression Testing in the TST env. Working well. 4:35 PM 1/18/2025
A14: 12 | B14: =Dashboard!$J$1 -> GGO Donor Wave | C14: =Dashboard!$F$1 -> 46156 | D14: =Dashboard!$H$1 -> 46170 | E14: GGO 7.22.0 Sprint 1 | F14: Saranya | G14: GGO-14471 | H14: Stretch --Update UI for Receipt Dialogue* | I14: Completed | J14: 2 | K14: 2 | N14: Priya | P14: Rajesh Kannan | R14: https://greatergiving.visualstudio.com/Greater%20Giving/_git/GGO/pullrequest/8166 | S14: 45678 | T14: 45679 | U14: Rajesh | W14: Loan Troung | X14: 45679 | AB14: Tested in the TST env. Looks good. 6:17 PM 1/22/2025
A15: 13 | B15: =Dashboard!$J$1 -> GGO Donor Wave | C15: =Dashboard!$F$1 -> 46156 | D15: =Dashboard!$H$1 -> 46170 | E15: GGO 7.22.0 Sprint 1 | F15: Sathiyabharathi | G15: GGO-14477 | H15: Stretch -- BID-06 Header Settings Update.* | I15: Being Developed | J15: 2 | K15: 2 | AB15: Picked on 01/22/2025.Development in progress 23/01/2025 Deployed in dev and completed developer testing

Sheet GGO 7.22.0 Sprint 1-Defect
A1: S.No | B1: Sprint # | C1: Story/Defect ID | D1: Parent Story | E1: Developer | F1: Issue Type | G1: Issue Description | H1: Priority | I1: Defect Source | J1: Type | K1: Status | L1: Root Cause Category | M1: Comments
B2: GGO 7.22.0 Sprint 1 | C2: GGO-14489 | D2: GGO-14427 | E2: Sathiya | F2: Defect | G2: When the package number is entered under "omit sales and payments," it applies to all supporters, preventing the individual package values from being displayed for each supporter | H2: Significant | I2: Manual | J2: Internal | K2: Closed | L2: Development
B3: GGO 7.22.0 Sprint 1 | C3: GGO-14490 | D3: GGO-14427 | E3: Rajesh | F3: Defect | G3: Invoice link in email appearing twice when triggered from "Print/Email batch" | H3: Significant | I3: Manual | J3: Internal | K3: Closed | L3: Development
B4: GGO 7.22.0 Sprint 1 | C4: GGO-14500 | D4: GGO-14483 | E4: Rajesh | F4: Defect | G4: Print or Email Invoices - Over ride setting for "Show Invoice Page Link" & "Invoice Page Link Label" is not reflecting for a new email batch | H4: Significant | I4: Manual | J4: Internal | K4: Closed | L4: Development | M4: Verified in TST.Working well. 7:15 PM 1/16/2025
B5: GGO 7.22.0 Sprint 1 | C5: GGO-14499 | D5: GGO-14483 | E5: Rajesh | F5: Defect | G5: implement quartz retry logic for invoice emails | H5: Significant | I5: Manual | J5: Internal | K5: Closed | L5: Development | M5: Unable to reproduce this issue in TST. Email sent successfully within few secs without getting any failures 7:18 PM 1/16/2025
B6: GGO 7.22.0 Sprint 1 | C6: GGO-14512 | D6: GGO-14483 | E6: Rajesh | F6: Defect | G6: Report Bid-06 taking more time when selecting "View Items" in "Edit Invoice & Receipts settings" | H6: Significant | I6: Manual | J6: Internal | K6: Closed | L6: Development | M6: Tested in TST env. Working well. 8:11 PM 1/20/2025.

Sheet GGO 7.21.0 Sprint 4-Status
A1: S.No | B1: Application Name | C1: Sprint Start Date | D1: Sprint End Date | E1: Sprint | F1: Developer | G1: Story ID/Defect ID | H1: Description | I1: Status | J1: Estimated(hrs/sp) | K1: Actual(hrs/sp) | L1: Actual Hours Worklog | M1: Unit testing | N1: Peer Tested By | O1: Peer Tested Defects, if any | P1: Peer Reviewed By | Q1: Peer Code Review Comments, if any | R1: PR Number/Link | S1: PR Created Date | T1: PR Approved Date | U1: Reviewer 1 | V1: Code Review Comments, if any | W1: Reviewer 2 | X1: Approved Date | Y1: Code Review Comments, if any2 | Z1: Internal PO -POV Comments | AA1: Client PO -POV Comments | AB1: Comments
A2: 1 | B2: =Dashboard!$J$1 -> GGO Donor Wave | C2: =Dashboard!$F$1 -> 46156 | D2: =Dashboard!$H$1 -> 46170 | E2: GGO 7.21.0 Sprint 4 | F2: SathyaBharathi/Rajesh Kannan | G2: GGO-14325 | H2: Rewrite and Update BID-06 (Invoice) using RDLC Part 1 | I2: Completed | J2: 3 | K2: 3 | N2: Priya | P2: Rajesh Kannan/Saranya | R2: https://dev.azure.com/greatergiving/Greater%20Giving/_git/GGO/pullrequest/8075 | S2: 45643 | T2: 45643 | U2: Rajesh | W2: Michael Wall | X2: 45643 | AB2: Tested in the Dev environment - Informed few issues to the Team.12/17/202410:48 PM. Tested in the TST Env- 12/18/2024 7:20 PM.
A3: 2 | B3: =Dashboard!$J$1 -> GGO Donor Wave | C3: =Dashboard!$F$1 -> 46156 | D3: =Dashboard!$H$1 -> 46170 | E3: GGO 7.21.0 Sprint 4 | F3: SathyaBharathi/Rajesh Kannan | G3: GGO-14426 | H3: Rewrite and Update BID-06 (Invoice) using RDLC - Part 2 (Sales Only) | I3: Completed | J3: 5 | K3: 5 | N3: Priya | P3: Rajesh Kannan | AB3: Rolling over remaining testing to this story - GGO-14427
A4: 3 | B4: =Dashboard!$J$1 -> GGO Donor Wave | C4: =Dashboard!$F$1 -> 46156 | D4: =Dashboard!$H$1 -> 46170 | E4: GGO 7.21.0 Sprint 4 | F4: Saranya | G4: GGO-14418 | H4: Modify GGO SFDC Webservice | I4: Completed | J4: 3 | K4: 3 | N4: Priya | P4: Rajesh Kannan | R4: https://greatergiving.visualstudio.com/Greater%20Giving/_git/GGO/pullrequest/8079 | S4: 45639 | T4: 45643 | U4: Rajesh | W4: Michael Wall | X4: 45643 | AB4: Coordinated with saranya and Tested in Local -12/16/2024 8:56 PM.
A5: 4 | B5: =Dashboard!$J$1 -> GGO Donor Wave | C5: =Dashboard!$F$1 -> 46156 | D5: =Dashboard!$H$1 -> 46170 | E5: GGO 7.21.0 Sprint 4 | F5: Saranya | G5: GGO-14445 | H5: Project Website - Remove Deprecated Share Functionality | I5: Completed | J5: 2 | K5: 2 | N5: Priya | P5: Rajesh Kannan | R5: https://greatergiving.visualstudio.com/Greater%20Giving/_git/GGO/pullrequest/8080 | S5: 45639 | T5: 45642 | U5: Rajesh | W5: Loan Troung | X5: 45642 | AB5: Tested in the Dev environment - 12/16/2024 8:57 PM. Tested in the TST env. Working well. 12/17/2024 10:47 PM
A6: 5 | B6: =Dashboard!$J$1 -> GGO Donor Wave | C6: =Dashboard!$F$1 -> 46156 | D6: =Dashboard!$H$1 -> 46170 | E6: GGO 7.21.0 Sprint 4 | F6: Rajesh Kannan | G6: GGO-14419 | H6: Duplicate EventXcode updated when GGO sync with SF | I6: Completed | J6: 3 | K6: 3 | N6: Priya | P6: Saranya | R6: https://greatergiving.visualstudio.com/Greater%20Giving/_git/GGO/pullrequest/8092 | S6: 45653 | T6: 45656 | U6: Rajesh | W6: Michael Wall | X6: 45656
A7: 6 | B7: =Dashboard!$J$1 -> GGO Donor Wave | C7: =Dashboard!$F$1 -> 46156 | D7: =Dashboard!$H$1 -> 46170 | E7: GGO 7.21.0 Sprint 4 | F7: Saranya/Rajesh Kannan | G7: GGO-14375 | H7: Pop-up warning on batch process with unapplied convenience fees | I7: Completed | J7: 3 | K7: 3 | N7: Priya | P7: Rajesh Kannan | R7: https://greatergiving.visualstudio.com/Greater%20Giving/_git/GGO/pullrequest/8096 | S7: 45657 | T7: 45657 | U7: Rajesh | W7: Michael Wall | X7: 45657 | AB7: Tested in the TST env. Working well 1/3/2025 8:13 PM
A8: 7 | B8: =Dashboard!$J$1 -> GGO Donor Wave | C8: =Dashboard!$F$1 -> 46156 | D8: =Dashboard!$H$1 -> 46170 | E8: GGO 7.21.0 Sprint 4 | F8: Sathiyabharathi/Rajesh Kannan | G8: GGO-14427 | H8: Rewrite and Update BID-06 (Invoice) using RDLC - Part 3 (Sales & Payments) | I8: Being Tested | J8: 5 | K8: 5 | N8: Priya | P8: Rajesh Kannan | R8: https://dev.azure.com/greatergiving/Greater%20Giving/_git/GGO/pullrequest/8097 | S8: 45657 | T8: 37621 | U8: Rajesh | W8: Michael Wall | X8: 45657 | AB8: Tested in the TST env. And it is In Progress 1/3/2025 8:13 PM. Tested in the Dev as well as in TST Env- 8:28 PM 1/6/2025. Testing is still in progress. 1/8/2025 8:10 PM
A9: 8 | B9: =Dashboard!$J$1 -> GGO Donor Wave | C9: =Dashboard!$F$1 -> 46156 | D9: =Dashboard!$H$1 -> 46170 | E9: GGO 7.21.0 Sprint 4 | F9: Sathiyabharathi | G9: GGO-14474 | H9: Stretch -- Mismatch between the net invoice count and the report being generated.* | I9: Ready For Testing | J9: 3 | K9: 3 | N9: Priya | P9: Rajesh Kannan | R9: https://dev.azure.com/greatergiving/Greater%20Giving/_git/GGO/pullrequest/8112 | S9: 45664 | T9: 45665 | U9: Rajesh | W9: Loan | X9: 45665

Sheet GGO 7.21.0 Sprint 4-Defect
A1: S.No | B1: Sprint # | C1: Story/Defect ID | D1: Developer | E1: Issue Type | F1: Issue Description | G1: Priority | H1: Type | I1: Status | J1: Root Cause Category | K1: Comments
B2: GGO 7.21.0 Sprint 4 | C2: GGO-14479 | D2: Sathiya | E2: Defect | F2: Design issues | G2: Minor | H2: Internal | I2: Closed | J2: Design
B3: GGO 7.21.0 Sprint 4 | C3: GGO-14480 | D3: Rajesh | E3: Defect | F3: Express indicator displaying on Top right in compact scenario even the Supporter is not marked as "Express Checkout" | G3: Significant | H3: Internal | I3: Closed | J3: Development
B4: GGO 7.21.0 Sprint 4 | C4: GGO-14481 | D4: Sathiya | E4: Defect | F4: When the "Only Show Sales That Are Paid" option is enabled in the invoice settings, the "Total Due" field should not be displayed in the Bid 06 report but it is still visible | G4: Significant | H4: Internal | I4: Closed | J4: Development
B5: GGO 7.21.0 Sprint 4 | C5: GGO-14486 | D5: Rajesh | E5: Defect | F5: Font not changing in Bid-06 RDLC report based on "General Accounts & Settings" | G5: Significant | H5: Internal | I5: Closed | J5: Development
B6: GGO 7.21.0 Sprint 4 | C6: GGO-14488 | D6: Rajesh | E6: Defect | F6: Receipt Settings Override while sending Invoice email is not working | G6: Significant | H6: Internal | I6: Closed | J6: Development
B7: GGO 7.21.0 Sprint 4 | C7: GGO-14476 | D7: Saranya | E7: Defect | F7: When the convenience fee is disabled, clicking on "Start New Batch" does not navigate to the next page. | G7: Significant | H7: Internal | I7: Closed | J7: Development
B8: GGO 7.21.0 Sprint 4 | C8: GGO-14489 | D8: Sathiya | E8: Defect | F8: When the package number is entered under "omit sales and payments," it applies to all supporters, preventing the individual package values from being displayed for each supporter | G8: Significant | H8: Internal | I8: Inprogress | J8: Development
B9: GGO 7.21.0 Sprint 4 | C9: GGO-14490 | D9: Rajesh | E9: Defect | F9: Invoice link in email appearing twice when triggered from "Print/Email batch" | G9: Significant | H9: Internal | I9: Closed | J9: Development

Sheet GGO 7.21.0 Sprint 3-Status
A1: S.No | B1: Sprint | C1: Developer | D1: Story ID/Defect ID | E1: Description | F1: Status | G1: Estimated(hrs/sp) | H1: Actual(hrs/sp) | I1: Unit testing | J1: Peer Tested By | K1: Peer Tested Defects, if any | L1: Peer Reviewed By | M1: Peer Code Review Comments, if any | N1: PR Number/Link | O1: PR Created Date | P1: PR Approved Date | Q1: Reviewer 1 | R1: Code Review Comments, if any | S1: Reviewer 2 | T1: Approved Date | U1: Code Review Comments, if any2 | V1: Internal PO -POV Comments | W1: Client PO -POV Comments | X1: Comments
A2: 1 | B2: GGO 7.21.0 Sprint 3 | C2: SathyaBharathi/Rajesh Kannan | D2: GGO-14325 | E2: Strech--Rewrite and Update BID-06 (Invoice) using RDLC | F2: Inprogress | G2: 5 | H2: 5 | X2: It will get carry forward to next sprint, due to requirement change by MikeH. 2.[12/12/2024] Invoice Email Failed becuase of Quratz service required DB permission
A3: 2 | B3: GGO 7.21.0 Sprint 3 | C3: Saranya | D3: PAPI-725 | E3: High - Weak Encryption: Insecure Mode of Operation - Dukpt.cs: 102 | F3: Completed | G3: 3 | H3: 3 | X3: Waiting for macroscope result 12/12 : Was marked out of Scope by Mike Horihan
A4: 3 | B4: GGO 7.21.0 Sprint 3 | C4: Saranya | D4: GGO-12835 | E4: Update to event date range fields and logic in GGO Project Builder* | F4: Completed | G4: 3 | H4: 3 | N4: https://greatergiving.visualstudio.com/Greater%20Giving/_git/GGO/pullrequest/8056 | O4: 45630 | P4: 45632 | Q4: Rajesh | S4: Loan Troung, Michael Wall | T4: 6-Dec-024
A5: 4 | B5: GGO 7.21.0 Sprint 3 | C5: Rajesh Kannan | D5: GGO-14414 | E5: Investigate GGO Client create/update API to handle Client sync process with SF* | F5: Completed | G5: 2 | H5: 2 | X5: Investigation completed
A6: 5 | B6: GGO 7.21.0 Sprint 3 | C6: Priya | D6: GGO-13319 | E6: Azure Images CRT Testing | F6: Completed | G6: 1 | H6: 1 | X6: Completed from our end
A7: 6 | B7: GGO 7.21.0 Sprint 3 | C7: Priya | D7: GGO-14402 | E7: 03 DEC GGO 7.20.1 CRT Release | F7: Completed | G7: 2 | H7: 2
A8: 7 | B8: GGO 7.21.0 Sprint 3 | C8: Saranya | D8: GGO-14383 | E8: Stretch --Refund Reference Number Not Generating* | F8: Completed | G8: 2 | H8: 2 | N8: https://dev.azure.com/greatergiving/Greater%20Giving/_git/GGO/pullrequest/8071 | O8: 45636 | P8: 45637 | Q8: Rajesh | S8: Loan Troung, Michael Wall | T8: 45637 | X8: Completed from our end
A9: 8 | B9: GGO 7.21.0 Sprint 3 | C9: Priya | D9: PAPI-773 | E9: Update to PAPI TLV response for success / fail Verify (Check-In) if not included | F9: Ready for Testing | G9: 1 | H9: 1 | X9: Did one Round of Payment Regression Testing, Final testing pending for onsite QA
A10: 9 | B10: GGO 7.21.0 Sprint 3 | C10: Priya | D10: PAPI-781 | E10: Required Zip Code Problems with EMV Verify (AMEX Only) | F10: Ready for Testing | G10: 1 | H10: 1 | X10: Did one Round of Payment Regression Testing, Final testing pending for onsite QA
A11: 10 | B11: GGO 7.21.0 Sprint 3 | C11: Priya | D11: GGO-14425 | E11: Remove "Transaction was Successful!" pop-up at the right corner of screen for EMV (Storefront & CheckInOut)* | F11: Completed | G11: 1 | H11: 1 | X11: Did one Round of Payment Regression Testing

Sheet GGO 7.21.0 Sprint 3-Defect
A1: S.No | B1: Sprint # | C1: Story/Defect ID | D1: Developer | E1: Issue Type | F1: Issue Description | G1: Priority | H1: Type | I1: Status | J1: Root Cause Category | K1: Comments
B2: No Defects

Sheet GGO 7.21.0 Sprint 2-Status
A1: S.No | B1: Sprint | C1: Developer | D1: Story ID/Defect ID | E1: Description | F1: Status | G1: Estimated(hrs/sp) | H1: Actual(hrs/sp) | I1: Unit testing | J1: Peer Tested By | K1: Peer Tested Defects, if any | L1: Peer Reviewed By | M1: Peer Code Review Comments, if any | N1: PR Number/Link | O1: PR Created Date | P1: PR Approved Date | Q1: Reviewer 1 | R1: Code Review Comments, if any | S1: Reviewer 2 | T1: Approved Date | U1: Code Review Comments, if any2 | V1: Internal PO -POV Comments | W1: Client PO -POV Comments | X1: Comments
A2: 1 | B2: GGO 7.21.0 Sprint 2 | C2: SathyaBharathi | D2: GGO-14386 | E2: BID-03 RDLC version ignoring grid selection for output | F2: Completed | G2: 3 | H2: 3 | I2: Sathiyabharathi | J2: Priya | N2: https://dev.azure.com/greatergiving/Greater%20Giving/_git/GGO/pullrequest/8003 | O2: 45614 | P2: 45615 | Q2: Rajesh | V2: Bug fix - Completed
A3: 2 | B3: GGO 7.21.0 Sprint 2 | C3: Saranya | D3: GGO-14355 | E3: Update Help Center URLS | F3: Completed | G3: 2 | H3: 2 | I3: Saranya | J3: Priya | N3: https://greatergiving.visualstudio.com/Greater%20Giving/_git/GGO/pullrequest/8000 | O3: 45611 | P3: 45612 | Q3: Rajesh | S3: Loan Troung | T3: 45612 | U3: The target has been assigned with a "_blank" but we still keep this button and ID. Where/which file is this ID being used? Looks like you removed the popup properties for it in file "GoTime.ts" line: 533 | V3: Updated New helpcenter content - Completed
A4: 3 | B4: GGO 7.21.0 Sprint 2 | C4: Priya-QA | D4: GGO-14361 | E4: Add support for additional Card Types | F4: Completed | G4: 1 | H4: 1 | I4: NA | J4: Priya | K4: NA | L4: NA | M4: NA | N4: NA | O4: NA | P4: NA | Q4: NA | R4: NA | S4: NA | T4: NA | U4: NA | V4: NA | W4: NA
A5: 4 | B5: GGO 7.21.0 Sprint 2 | C5: Priya-QA | D5: GGO-13319 | E5: Azure Images CRT Testing | F5: InProgress | G5: 3 | H5: 3 | I5: NA | J5: Priya | K5: NA | L5: NA | M5: NA | N5: NA | O5: NA | P5: NA | Q5: NA | R5: NA | S5: NA | T5: NA | U5: NA | V5: NA | W5: NA
A6: 5 | B6: GGO 7.21.0 Sprint 2 | C6: Saranya | D6: GGO-14395 | E6: Unable to add Discover cards in orgs enabled for Discover | F6: Completed | G6: 1 | H6: 1 | I6: Saranya | J6: Priya | K6: No | L6: Sathiya | M6: No | N6: https://dev.azure.com/greatergiving/Greater%20Giving/_git/GGO/pullrequest/8022 | O6: 45618 | P6: 45618 | Q6: Rajesh | R6: No | S6: Mike Wall | T6: 45618 | U6: No | V6: Defect story for GGO-14361 - Completed | W6: No
A7: 6 | B7: GGO 7.21.0 Sprint 2 | C7: Rajesh | D7: GGO-14397 | E7: Image is not being retrieved from Azure after saving the Project or settings, even though Azure configuration is enabled | F7: Completed | G7: 2 | H7: 2 | I7: Rajesh | J7: Priya | K7: No | L7: Sathiya | M7: No | N7: https://dev.azure.com/greatergiving/Greater%20Giving/_git/GGO/pullrequest/8022 | O7: 45618 | P7: 45618 | Q7: Sathiya | R7: No | S7: Mike Wall | T7: 45618 | U7: No | V7: Bug fix - Completed | W7: No
A8: 7 | B8: GGO 7.21.0 Sprint 2 | C8: SathyaBharathi/Rajesh | D8: GGO-14385 | E8: Investigate New App Svc for OB Queue Replacement | F8: Completed | G8: 2 | H8: 2 | I8: NA | J8: NA | K8: NA | L8: NA | M8: NA | N8: NA | O8: NA | P8: NA | Q8: NA | R8: NA | S8: NA | T8: NA | U8: NA | V8: Investigation - Completed | W8: NA | X8: It's an investingation story we prepared document and attached the jira ticket

Sheet GGO 7.21.0 Sprint 2-Defect
A1: S.No | B1: Sprint # | C1: Story/Defect ID | D1: Developer | E1: Issue Type | F1: Issue Description | G1: Priority | H1: Type | I1: Status | J1: Root Cause Category | K1: Comments

Sheet GGO 7.21.0 Sprint 1-CRC 
A2: S.No | B2: Sprint | C2: Developer | D2: Story ID/Defect ID | E2: Description | F2: Estimated(hrs/sp) | G2: Actual(hrs/sp) | H2: Unit testing | I2: Peer Tested By | J2: Peer Tested Defects, if any | K2: Peer Reviewed By | L2: Peer Code Review Comments, if any | M2: PR Number/Link | N2: PR Created Date | O2: PR Approved Date | P2: Reviewer 1 | Q2: Code Review Comments, if any | R2: Reviewer 2 | S2: Approved Date | T2: Code Review Comments, if any | U2: Internal PO -POV Comments | V2: Client PO -POV Comments | W2: Status
A3: 1 | B3: GGO 7.21.0 Sprint 1 | C3: Rajesh/SathyaBharathi | D3: GGO-14067 | E3: Rewrite BID-03 to a new report toolset | F3: 5 | G3: 5 | H3: Sathiyabharathi/Rajesh | I3: Priya | J3: GGO-14353 Alignment Issues and GGO-14378 Throwing 504 Gateway Timeout error while rendering Bid-03 report | K3: Saranya | L3: No | M3: NA | N3: NA | O3: NA | P3: NA | R3: NA | U3: Moving report to new toolset - Completed | W3: Completed | X3: Cretaed bugs under this story (GGO-14353 and GGO-14378) PR created and completed under those bugs
A4: 2 | B4: GGO 7.21.0 Sprint 1 | C4: Rajesh | D4: GGO-14244 | E4: Error when trying to create project website | F4: 3 | G4: 3 | H4: Rajesh | I4: Priya | J4: No | K4: Sathiya | L4: No | M4: https://dev.azure.com/greatergiving/Greater%20Giving/_git/GGO/pullrequest/7961 | N4: 45602 | O4: 45602 | P4: Loan | Q4: I think if we are going to catch it, then we should log it. Log "info". | S4: 45602 | U4: Bug fix - Completed | W4: Completed
A5: 3 | B5: GGO 7.21.0 Sprint 1 | C5: Sathiyabharathi | D5: GGO-14353 | E5: Alignment Issues | F5: NA | G5: NA | H5: Sathiyabharathi | I5: Priya | J5: No | K5: Saranya | L5: No | M5: https://dev.azure.com/greatergiving/Greater%20Giving/_git/GGO/pullrequest/7949 | N5: 45604 | O5: 45604 | Q5: No Comments | R5: Michael Wall/Loan | S5: 45604 | T5: No Comments | W5: Completed
A6: 4 | B6: GGO 7.21.0 Sprint 1 | C6: Sathiyabharathi | D6: GGO-14378 | E6: Throwing 504 Gateway Timeout error while rendering Bid-03 report | F6: NA | G6: NA | H6: Sathiyabharathi | I6: Priya | K6: Saranya | L6: No | M6: https://dev.azure.com/greatergiving/Greater%20Giving/_git/GGO/pullrequest/7981 | N6: 45608 | O6: 45608 | P6: Rajesh | Q6: No Comments | R6: Michael Wall/Loan | S6: 45608 | T6: 1.is this variable name a typo ? "foud" vs "found" 2.Could we move all these spacing into a variable/constant before using? The variable naming provides meaning to why all these spacing are used. | U6: Defect story for GGO-14067 - Completed | W6: Completed
A7: 5 | B7: GGO 7.21.0 Sprint 1 | C7: Saranya | D7: GGO-14295 | E7: Handle Deleted User Session | F7: 3 | G7: 3 | H7: Saranya | I7: Priya | K7: Sathiya | L7: No | M7: https://greatergiving.visualstudio.com/Greater%20Giving/_git/GGO/pullrequest/7983 | N7: 45609 | O7: 45609 | P7: Rajesh | R7: Michael Wall | S7: 45609 | U7: Rolled over | W7: InProgress | X7: Trying to reproduce the issue in local
A8: 6 | B8: GGO 7.21.0 Sprint 1 | C8: Rajesh | D8: GGO-14373 | E8: ManageSalesAndPayments Error* | F8: 2 | G8: 2 | H8: Rajesh | I8: Priya | J8: No | K8: Sathiya | L8: No | M8: https://dev.azure.com/greatergiving/Greater%20Giving/_git/GGO/pullrequest/7968 | N8: 45603 | O8: 45604 | P8: Loan | Q8: No Comments | U8: Bug fix - Completed | W8: Completed
A9: 6 | B9: GGO 7.21.0 Sprint 1 | C9: Saranya | D9: GGO-14355 | E9: Update Help Center URLS* | F9: 3 | G9: 2 | I9: Priya | M9: https://greatergiving.visualstudio.com/Greater%20Giving/_git/GGO/pullrequest/7988 | N9: 45609 | P9: Rajesh | U9: Rolled over | W9: InProgress | X9: Development completed
A10: 7 | B10: GGO 7.21.0 Sprint 1 | C10: Priya-QA | D10: PAPI-774 | E10: Refunds failing to process | F10: 1 | G10: 1 | H10: NA | I10: Priya | J10: NA | K10: NA | L10: NA | M10: NA | N10: NA | O10: NA | P10: NA | Q10: NA | R10: NA | S10: NA | T10: NA | U10: NA | V10: NA | W10: completed
A11: 8 | B11: GGO 7.21.0 Sprint 1 | C11: Priya-QA | D11: GGO-14361 | E11: Add support for additional Card Types | F11: 1 | G11: 1 | H11: NA | I11: Priya | J11: NA | K11: NA | L11: NA | M11: NA | N11: NA | O11: NA | P11: NA | Q11: NA | R11: NA | S11: NA | T11: NA | U11: NA | V11: NA | W11: InProgress
A12: 9 | B12: GGO 7.21.0 Sprint 1 | C12: Priya-QA | D12: GGO-14373 | E12: ManageSalesAndPayments Error* | F12: 1 | G12: 1 | H12: NA | I12: Priya | J12: NA | K12: NA | L12: NA | M12: NA | N12: NA | O12: NA | P12: NA | Q12: NA | R12: NA | S12: NA | T12: NA | U12: NA | V12: NA | W12: Completed
A13: 10 | B13: GGO 7.21.0 Sprint 1 | C13: Priya-QA | D13: GGO-14244 | E13: Error when trying to create project website | F13: 1 | G13: 1 | H13: NA | I13: Priya | J13: NA | K13: NA | L13: NA | M13: NA | N13: NA | O13: NA | P13: NA | Q13: NA | R13: NA | S13: NA | T13: NA | U13: NA | V13: NA | W13: Completed

Sheet GGO 7.21.0 Sprint 1-Defect 
