Workbook

Sheet Dashboard
A1: Current Sprint | B1: {=INDEX($B$2:$B$102,MATCH(1,(($D$2:$D$102 >=TODAY())*($C$2:$C$102<=TODAY())),0))} -> OB-OP 8.6.0 Sprint 4 | C1: Current Sprint Sheet | D1: =CONCATENATE(B1,"-Status") -> OB-OP 8.6.0 Sprint 4-Status | E1: Sprint Start Date | F1: =VLOOKUP($B$1,$B$1:$C$102,2) -> 46149 | G1: Sprint End Date | H1: =VLOOKUP($B$1,$B$1:$D$102,3) -> 46163 | I1: Application Name | J1: OnlineBidding | K1: Users | L1: karthi.rajendran@relevantz.com;preethi.muthu@relevantz.com;prabu.pandiya@relevantz.com;mercy.hameed@relevantz.com;nivetha.murugadass@relevantz.com | M1: Teams Name(GP-GGO.OnlineBidding) | N1: 19:f86125062bb647689bca347bf687e022@thread.v2
A2: Sprint Type | B2: Sprint # | C2: Sprint Start Date | D2: Sprint End Date | E2: Assigned SP | F2: Completed SP | G2: Story points introduced/removed | H2: Sprint Summary | I2: Accomplishments | J2: Remarks | K2: Retro Points (Internal & External) | L2: Data sanity Audit Status | M2: AuditDate | N2: Planned Leaves | O2: Availed Leaves | P2: Backlog Health
A3: =IF(AND($D$1>=C3,$D$1<=D3),"CurrentSprint","NA") -> NA | B3: OBOP 7.10.0 Sprint 4 | C3: 45296 | D3: 45309 | E3: 12 | F3: 9 | G3: 5/0 | J3: Offshore team faced some challenges while implementing the Rich textbox. | K3: Internal: External:
A4: =IF(AND($D$1>=C4,$D$1<=D4),"CurrentSprint","NA") -> NA | B4: OBOP 7.11.0 Sprint 1,2 | C4: 45310 | D4: 45337 | E4: 25 | F4: 23 | G4: 0/0 | J4: Offshore team got appreciations for more than expected story points completed. Prabhu and Rajesh for helping with the hotfix as well. | K4: Internal: External:
A5: =IF(AND($D$1>=C5,$D$1<=D5),"CurrentSprint","NA") -> NA | B5: OBOP 7.11.0 Sprint 3 | C5: 45338 | D5: 45351 | E5: 13 | F5: 13 | G5: 0 | J5: Overall good sprint, Prabhu and offshore team got appreciated for DNN libraries documentation. | K5: Internal: External:
A6: =IF(AND($D$1>=C6,$D$1<=D6),"CurrentSprint","NA") -> NA | B6: OBOP 7.11.0 Sprint 4 | C6: 45352 | D6: 45365 | E6: 9 | F6: 9 | G6: 0/0 | J6: Offshore team got appreciations for investigating the AHA templates-DNN7(OP) and group filter story(OB). | K6: Internal: External:
A7: =IF(AND($D$1>=C7,$D$1<=D7),"CurrentSprint","NA") -> NA | B7: OBOP 7.12.0 Sprint 1 | C7: 45366 | D7: 45379 | E7: 11 | F7: 11 | G7: 2/0 | J7: Appreciated for completing all the work with good production release. | K7: Internal: External:
A8: =IF(AND($D$1>=C8,$D$1<=D8),"CurrentSprint","NA") -> NA | B8: OBOP 7.12.0 Sprint 2 | C8: 45380 | D8: 45393 | E8: 13 | F8: 10 | G8: 5/0 | J8: 2 DNN-7 story getting carried. Prabhu and Offshore team got appreciated for doing great job in learning and updating AHA templates. | K8: Internal: External:
A9: =IF(AND($D$1>=C9,$D$1<=D9),"CurrentSprint","NA") -> NA | B9: OBOP 7.12.0 Sprint 3 | C9: 45394 | D9: 45407 | E9: 7 | F9: 7 | G9: 0/0 | J9: Client appreciated for completing Recaptcha DNN9 conversion. Addition to this development completed for one stretch story. | K9: Internal: External:
A10: =IF(AND($D$1>=C10,$D$1<=D10),"CurrentSprint","NA") -> NA | B10: OBOP 7.12.0 Sprint 4 | C10: 45408 | D10: 45421 | E10: 15 | F10: 15 | G10: 6/0 | J10: Overall good sprint, Team completed more than expected story points. | K10: Internal: External:
A11: =IF(AND($D$1>=C11,$D$1<=D11),"CurrentSprint","NA") -> NA | B11: OBOP 7.13.1 Sprint 1 | C11: 45422 | D11: 45435 | E11: 17 | F11: 17 | G11: 0/0 | J11: Prabhu got appriciated for getting all AHA fixes completed and Mercy got appriciated for finding lot of issues. | K11: Internal: External:
A12: =IF(AND($D$1>=C12,$D$1<=D12),"CurrentSprint","NA") -> NA | B12: OBOP 7.13.1 Sprint 2 | C12: 45436 | D12: 45449 | E12: 28 | F12: 23 | G12: 8/0 | J12: Completed most of assigned stories/defects | K12: Internal: External:
A13: =IF(AND($D$1>=C13,$D$1<=D13),"CurrentSprint","NA") -> NA | B13: OBOP 7.13.1 Sprint 3 | C13: 45450 | D13: 45463 | E13: 17 | F13: 16 | G13: 5/0 | J13: Appreciated for completing all the work | K13: Internal: External:
A14: =IF(AND($D$1>=C14,$D$1<=D14),"CurrentSprint","NA") -> NA | B14: OBOP 7.13.1 Sprint 4 | C14: 45464 | D14: 45476 | E14: 8 | F14: 8 | G14: 1/0 | J14: Appreciated dev team for Investigation stories and Mercy for finding defect. | K14: Internal: External:
A15: =IF(AND($D$1>=C15,$D$1<=D15),"CurrentSprint","NA") -> NA | B15: OBOP 7.14.0 Sprint 1 | C15: 45477 | D15: 45491 | E15: 13 | F15: 13 | G15: 3/0 | J15: Appreciated Mercy for good testing | K15: Internal: External:
A16: =IF(AND($D$1>=C16,$D$1<=D16),"CurrentSprint","NA") -> NA | B16: OBOP 7.14.0 Sprint 2 | C16: 45492 | D16: 45505 | E16: 12 | F16: 12 | G16: 0/0 | J16: Completing another sprint successfully, Appriciated Prabhu and offshore for completing the work on messaging | K16: Internal: External:
A17: =IF(AND($D$1>=C17,$D$1<=D17),"CurrentSprint","NA") -> NA | B17: OBOP 7.14.0 Sprint 3 | C17: 45506 | D17: 45519 | E17: 11 | F17: 8 | G17: 0/0 | J17: Couldn't complete testing because of release pipeline certificate issue. | K17: Internal: External:
... A19: =IF(AND($D$1>=C19,$D$1<=D19),"CurrentSprint","NA") -> NA | B19: OBOP 8.2.0 Sprint 1 | C19: 45534 | D19: 45547 | E19: 12 | F19: 12 | G19: 0/0 | J19: Appreciated Prabhu for providing KT to quick invoice team | K19: Internal: External:
A20: =IF(AND($D$1>=C20,$D$1<=D20),"CurrentSprint","NA") -> NA | B20: OBOP 8.2.0 Sprint 2 | C20: 45548 | D20: 45561 | E20: 20 | F20: 15 | G20: 5/0 | K20: Internal: External:
A21: =IF(AND($D$1>=C21,$D$1<=D21),"CurrentSprint","NA") -> NA | B21: OBOP 8.2.0 Sprint 3 | C21: 45562 | D21: 45575 | E21: 20 | F21: 17 | G21: 3/3 | J21: TST was down which lead to rolling over one story Peer CRC: 0 Onsite CRC: 2 Client CRC: 0 Internal Defects :2 External Defects:0 Appreciated i)Prabhu for helping Alice on providing info on some stories ii)Mercy for helping out while Alice was unavailable iii) Rajesh and Prabhu for helping Joe set up GGO locally. iv) Lot of challenges while developing the OP page module and offshore continued working through it v) Rajesh for helping Prabhu and team with testing of OP stories. vi) Rajkumar and Prabhu for good coordination for getting the entire flow end to end on Quick invoicing | K21: Internal: External:
A22: =IF(AND($D$1>=C22,$D$1<=D22),"CurrentSprint","NA") -> NA | B22: OBOP 8.2.0 Sprint 4 | C22: 45576 | D22: 45589 | E22: 17 | F22: 17 | G22: 0/0 | I22: 1.Import quick invoice payment page designed, created in GGO and placed in between Registrations & RSVPs 2. Added new convenience fee sale and made reconcile with sale payment association 3.Pending quick invoice imports count included in existing left nav notification counter | J22: i) Appreciated the team for completing all the quick invoice stories. ii) Kudos to Farhath and Mercy for helping with the test planning and testing which made it easier for Alice. iii) Kudos to Prabhu and Rajkumar for coordinating with offshore teams and completing all the planned stories for the sprint iv) Appreciated Offshore for finishing the planned stories and meeting the deadline v) Rajesh and Prabhu helped Rajkumar & offshore with the OP and GGO integration. Peer CRC: 2 Onsite CRC: 0 Client CRC: 0 Internal Defects :0 External Defects:0
A23: =IF(AND($D$1>=C23,$D$1<=D23),"CurrentSprint","NA") -> NA | B23: OBOP 8.3.0 Sprint 1 | C23: 45590 | D23: 45603 | E23: 11 | F23: 8 | G23: 0/0 | I23: 1.Quick Invoice feature release into CRT 2.Added Privacy Police notice on both OB & OP 3.Default application text css changes & Text updates | J23: Nice job with the privacy policy implementation. One story has been moved to next sprint for testing alone Kudos to Offshore QA - has been very helpful , making sure all gaps are covered Peer CRC: 0 Onsite CRC: 0 Client CRC: 0 Internal Defects:2 External Defects: 0
A24: =IF(AND($D$1>=C24,$D$1<=D24),"CurrentSprint","NA") -> NA | B24: OBOP 8.3.0 Sprint 2 | C24: 45604 | D24: 45617 | E24: 14 | F24: 14 | G24: 3/0 | I24: 1.OP 8.2.0 release to CRT & PRD 2.App help url updates 3.Invoicing feature updates - Collected from pilot user's feedback 4.Escalation support | J24: Kudos shared to Mercy for the support in making a lot of test plans and doing thorough testing that really helped out with all the small areas we have to verify, especially with all of the stories we added during the quick invoice effort. Rajkumar and team for the merge field completion. Rajesh for helping with the merge strategies and Prabhu was very helpful for a couple of tickets Joe had. Peer CRC:0 Onsite CRC:0 Client CRC: 6 Internal Defects:2 External Defects: 0 A 3 point story was added towards the end of the Sprint as part of the strech goal and was rolled over to the next sprint
A25: =IF(AND($D$1>=C25,$D$1<=D25),"CurrentSprint","NA") -> NA | B25: OB-OP 8.3.0 Sprint 3 | C25: 45618 | D25: 45631 | E25: 21 | F25: 21 | G25: Ten/0 | I25: 1. We had 8.2.2 OP CRT release 2. completed final set of pending invoicing tasks 3.Macroscope fixes | J25: Kudos to Rajkumar and team for taking invoicing project to finish line, Offshore QA - Mercy and Farhath for putting some good notes for Alice which was helpful when she got back and Preethi and Karthi for managing all the dev work during the US thanksgiving holidays when everyone was away Kalai and Rajiv are very dynamic and all the deliveries were on time Prabhu and Rajesh for the KT and support to the invoicing team Peer CRC:0 Onsite CRC:2 Client CRC: 2 Internal Defects:1 External Defects: 0 A 2 point story was added towards the end of the Sprint as part of the strech goal and was rolled over to the next sprint
A26: =IF(AND($D$1>=C26,$D$1<=D26),"CurrentSprint","NA") -> NA | B26: OB-OP 8.3.0 Sprint 4 | C26: 45632 | D26: 45659 | E26: 11 | F26: 13 | G26: 15/0 | I26: 1.OB 7.12.1 release to CRT& PRD 2. OP 8.2.2 PRD Release 3.Complete Invoicing 4.Macroscope fix | J26: Kudos Offshore in general and offshore QA for keeping up with things when Onsite was away for holidays +2 Mercy for keeping up with test plans when Alice was out Raj kumar and team for a great impact on past few sprints +1 Peer CRC:0 Onsite CRC:1 Client CRC: 0 Internal Defects:0 External Defects: 0 Some of the stories are stretch and got carry forwarded because of client resources unavailability due to holidays
A27: =IF(AND($D$1>=C27,$D$1<=D27),"CurrentSprint","NA") -> NA | B27: OB-OP 8.4.0 Sprint 1 | C27: 45660 | D27: 45673 | E27: 16 | F27: 13 | G27: 0/0 | I27: 1. Release 8.3.0 to CRT and PRD 2. Macroscope fix in OP and OB | J27: Kudos to Given the release, towards the end of the sprint we were seeing a bunch of issues in OP and OB and Mercy was very helpful in testing those Given the product overlap across both teams and the staggered release for both teams, it was confusing but the team did a great job overall staying on top of everything Rajesh for helping Joe set up for the portals To the team on a great job on the overall Invoice project and release Peer CRC:0 Onsite CRC:2 Client CRC: 0 Internal Defects:0 External Defects: 0 3 point story carry forwarded to next sprint. Part of the performance improvement done.Restrictions on DNN9 core functionality prevents us from finding performance improvements. But there is more room left for improvements. So Story was carry forwarded
A28: =IF(AND($D$1>=C28,$D$1<=D28),"CurrentSprint","NA") -> NA | B28: OB-OP 8.4.0 Sprint 2 | C28: 45674 | D28: 45687 | E28: 16 | F28: 10 | G28: 5/0 | I28: RSVP enhancements, continuing with Macroscope work,OP MFA login production hotfix | J28: Peer CRC:0 Onsite CRC:0 Client CRC: 0 Internal Defects:1 External Defects: 0 2 RSVP stories got carried over to the next sprint, RSVP Multiple attendee dynamic control creation has been challenging. Completed major functionalities, local testing and dev testing is in progress and a 3 point story is dependent on that 8 point story so we couldn't proceed that without completing the main story
A29: =IF(AND($D$1>=C29,$D$1<=D29),"CurrentSprint","NA") -> NA | B29: OB-OP 8.4.0 Sprint 3 | C29: 45688 | D29: 45701 | E29: 14 | F29: 12 | G29: 1/0 | I29: Continue RSVP enhancements, Supported OP 8.3.2 Hotfix testing support for delay in OP site creation, RSVP index table update and Apigee threading exception | J29: Kudos to i) Rajesh to take the big feature and manage it +1 ii) Joe,Mike , Rajesh, Derek was handling all the rapid change in the sprint goal iii) Rajesh for handling all on both teams GGO and OB/OP iv) Offshore dev and QA for working hard on multiple attendees and getting all the scenarios covered Peer CRC:2 Onsite CRC:2 Client CRC: 0 Internal Defects:0 External Defects: 2 3 pt bug has been carry forwarded to next sprint as we couldn't able to reproduce the bug in our environment and trying to find the root cause for it
A30: =IF(AND($D$1>=C30,$D$1<=D30),"CurrentSprint","NA") -> NA | B30: OB-OP 8.4.0 Sprint 4 | C30: 45702 | D30: 45715 | E30: 9 | F30: 9 | G30: 6/3 | I30: New card type added with existing ones, OP 8.3.3 and 8.4.0 release to CRT | J30: Kudos to i) Everyone in the team for all the hard work this sprint ii) Joe , Rajesh, Mike and Carlos for all of the release stuff iii) Offshore for taking care of all the sprint stories Peer CRC:0 Onsite CRC:0 Client CRC: 0 Internal Defects:1 External Defects: 3 3 pt bug has been flagged in JIRA as blocker and removed from sprint during sprint end and another 3 pt bug which is in stretch has been carry forwarded to next sprint, in which we have completed the fix for 1 report, need to check for remaining 3 reports
A31: =IF(AND($D$1>=C31,$D$1<=D31),"CurrentSprint","NA") -> NA | B31: OB-OP 8.5.0 Sprint 1 | C31: 45716 | D31: 45729 | E31: 14 | F31: 11 | G31: 0/0 | I31: Release OP 8.4 to PRD, begin investigating OB UX and QoL fixes | J31: Kudos i) Prabhu and Rajesh on assisting Joe on a ticket related to convenience fee ii) Offshore QA Mercy for the test plan put together for catalog verification, very good testing and makes it more secure iii) Karthi and Preethi for great documentation on the investigation stories Peer CRC:0 Onsite CRC:0 Client CRC: 0 Internal Defects:0 External Defects: 2 One of the story got completed at the last minute because the fix wasn't working so the team had to coninue trying out different aproaches till it worked. It was sent for peer review on the last day and hence got carry forwarded to the next sprint for testing
A32: =IF(AND($D$1>=C32,$D$1<=D32),"CurrentSprint","NA") -> NA | B32: OB-OP 8.5.0 Sprint 2 | C32: 45729 | D32: 45743 | E32: 14 | F32: 19 | G32: 7/0 | I32: Begin work on OB UX settings and layouts | J32: Kudos i) We did a stretch AC on the layout and Prabhu assisted Joe on that ii) Prabhu for helping Alice with testing iii) Rajesh for helping Alice on the email issue +1 iv) Offshore for completing all the planned stories and adding some stretch stories Peer CRC:0 Onsite CRC:0 Client CRC: 1 Internal Defects:0 External Defects: 0 OB UX settings and layout implementation Escalation support for investigating the max bid label update Fixed Max Bid label OP negative payment fix
A33: =IF(AND($D$1>=C33,$D$1<=D33),"CurrentSprint","NA") -> NA | B33: OB-OP 8.5.0 Sprint 3 | C33: 45743 | D33: 45757 | E33: 14 | F33: 11 | G33: 0/0 | I33: Continue OB UX and high value OP items Accompolishments: Added new settings in Online bidding settings page Feature flag implementation for OB - sending data from GGO to OB | J33: Peer CRC:0 Onsite CRC:0 Client CRC: 0 Internal Defects:1 External Defects: 2 Pending reason One 3-point story was carried over to the next sprint. While development, local testing, and DEV testing were completed from our side, the peer review and testing for OB-3731 were delayed. This was primarily due to the extended time required for development and testing of OB-3708 (an 8-point story). As a result, OB-3731 has been moved to the next sprint. | K33: What went well? Offshore doing testing in Dev before going to TST helps mitigate issues later in the Sprint What didn’t go well? The development for OB settings page was a little challenging Kudos 1. Nice job team on OB settings page, the mockups really look good 2. Great QA team for being a sport , working last minute to test the stories +1 3. Offshore QA Mercy for finding the issues before it hit TST and helped in not sending it back to Dev later 4. Prabhu and Rajesh for their support to Alice 5. Prabhu, Offshore dev Preethi and Karthi for completing the OB settings page for spending extended hours in completing it +2
A34: =IF(AND($D$1>=C34,$D$1<=D34),"CurrentSprint","NA") -> NA | B34: OB-OP 8.5.0 Sprint 4 | C34: 45757 | D34: 45771 | E34: 11 | F34: 14 | G34: 5/0 | I34: Release and test OP 8.5 and OB 7.13 to CRT. Donor Project continuing work Accomplishment 1. Tested OP 8.5 and OB 7.13 in CRT 2. Upgraded Angular 12 to 13, version got upgraded but facing few routing issues | J34: Peer CRC:0 Onsite CRC:0 Client CRC: 0 Internal Defects:0 External Defects: 0 Pending reason 1 Bug has been carry forwarded to next sprint since it is taking more time than expected. Also PM cannot remember what this report looked like working in Prod, so we may need to do some discovery and explanation in order to come up with a good solution | K34: What went well? 1. CRT testing completed on time 2. Great progress on Angular update 3. Good initial progress on Donor project 4. Completed more stories than planned What didn’t go well? 1. The package dependency made the Angular update challenging 2. Fixing the section report issue has been more complex than planned Kudos Prabhu and Rajesh for supporting the CRT issue fix, Carlos as well Rajesh for leading the way on Donor Project +2 Offshore for the Angular update , that was a big jump +2
A35: =IF(AND($D$1>=C35,$D$1<=D35),"CurrentSprint","NA") -> NA | B35: OB-OP a7.14.0 Sprint 1 | C35: 45771 | D35: 45785 | E35: 15 | F35: 11 | G35: 0/0 | I35: OB & OP PRD release, continue with OB UX and Donor project Accomplishment 1. Passed the new settings value from GGO to OB and mapped the header values in OB side UI 2. Upgraded Angular 12 to 13, Updated node version from 14 to 16, fixing the errors | J35: Peer CRC:0 Onsite CRC:0 Client CRC: 3 Internal Defects:0 External Defects: 0 Pending reason OP-2747-It has been carry forwarded to next sprint since it is taking more time than expected. Also PM cannot remember what this report looked like working in Prod, so we may need to do some discovery and explanation in order to come up with a good solution OB-3680 - Story has been carry forwarded to next sprint - Dependent on OB-3755. Development and peer review is completed, Since PR was shared in the last day testing will be done in next sprint | K35: What went well? The new Donor platform setup went well On pace with OB UX What didn’t go well? Last minute unplanned PTO for team member led to delay in closing a few tickets New OB page and design turned out to be a little challenging Kudos Preethi for updating the node and Angular version as it requires a lot of tracking and patience. Thanks for doing it
A36: =IF(AND($D$1>=C36,$D$1<=D36),"CurrentSprint","NA") -> NA | B36: OB-OP 8.0 Sprint 2 | C36: 45785 | D36: 45799 | E36: 15 | F36: 15 | G36: 0/0 | I36: OB & OP PRD release, continue with OB UX and Donor project Accomplishment 1. The team completed all they planned for and more (initially firebase was spike later converted to story) 2. Fixed the warnings while compiling angular 13, ended up with 1 console error while running application | J36: Peer CRC:0 Onsite CRC:1 Client CRC: 0 Internal Defects:1 External Defects: 0 Escaped defect RCA - Should do proper code review and local testing,DEV testing covering all scenarios Review Comment - Add try catch block here when you connecting with DB to make operations | K36: What went well? The team completed all they planned for and more PRD releases were long and it went well What didn’t go well? Firebase notification was a little tricky to configure Handling Aesgcn decryption for existing URLs cost a little extra time to complete Docker desktop is not authorized so it forced the team to find a different way to communicate with the database Kudos Offshore and Dev Prabhu for completing the investigation and implementation of Firebase notification +2
A37: =IF(AND($D$1>=C37,$D$1<=D37),"CurrentSprint","NA") -> NA | B37: OB-OP 8.0 Sprint 3 | C37: 45800 | D37: 45814 | E37: 16 | F37: 14 | G37: 6/0 | I37: Continue OB UX work, setup for donor platform Accomplishment 1. Updated Node js to version 16 and then to 18, trying to fix the errors 2. Firebase notification is coming correctly to the bidders who are outbidden 3. New team members setup is completed and started the design story | J37: Peer CRC:0 Onsite CRC:0 Client CRC: 2 Internal Defects:0 External Defects: 0 Review comment - 1. Macroscope will ding us for putting apikeys or secrets in the repo. We need to add these as variables, even for local testing the same way we do for the SMS test keys 2. Let's add a general exception catch as well. Pending reason 1. OB-3675 -During the sprint, a few high-priority security issues were introduced that required quick attention. Addressing them took some time away from our originally planned work. Development work has been completed successfully, and dev environment testing was verified by the Relevantz offshore QA team. However, during deployment to the TST environment, we encountered issues related to pipeline variables. As a result, only testing is pending for this story. 2. DON-20 - Stretch story - Development completed, local testing is in progress, Once done will raise the PR in next sprint | K37: What went well? Onboarding went well What didn’t go well? 2 Security issues took about a week of 2 of the team members time New developers onboarding For multiple bidders, Firebase notification is not getting sent randomly Angular upgrade has been challenging Escalation support for OP Login issue Kudos Prabhu nice job get everybody onboarded +3 Takeaways 6/5/2025 Angular Update timebox effort should be significantly lowered - 10 hrs a Sprint Escalation Support should be filtered by Derek Anderson and Mike Horihan so that team can focus on OB UX overhaul and Donor project
A38: =IF(AND($D$1>=C38,$D$1<=D38),"CurrentSprint","NA") -> NA | B38: OB-OP 8.0 Sprint 4 | C38: 45813 | D38: 45826 | E38: 20 | F38: 13 | G38: 1/0 | I38: CRT Release and testing for OB and OP, continue with OB UX and Donor project Accomplishment Completed the firebase notification story and updated the sponsor bar design for new UI | J38: Peer CRC:1 Onsite CRC:1 Client CRC: 0 Internal Defects:0 External Defects: 0 Review comment Rename the css class Move all the numbers to constant file Pending reason 1. OP-2766 - Was having CRT certificate issue so couldn't complete testing 2. OB-3684 - Testing completed from offshore QA end and added comments in JIRA, since onsite QA was occupied with CRT testing, couldn't give signoff to this ticket. We shared the PR on 17/06(Tues) | K38: Overall it was a good sprint even though we didn't meet the Sprint forecast this time. The onsite QA needs to signoff on those tickets before closing and given this was a regression sprint, the onsite QA had her hands full with CRT testing. A special shout out to the new Donor team for coming up to speed very fast and taking control right away. Well done! What went well? Very productive sprint inspite our story point completion What didn’t go well? Cross site scripting was a distraction from our planned work Issues in PAPI CRT caused testing delays Kudos Alice for a lot of of help with initial cross site testing Joe, Rajesh and Prabhu with fixing the update script to get to CRT without a lot of issues New Donor team for completing a lot of the design work +1 Rajesh for helping with the CRT issue +1 Preethi, Karthi and Mercy for completing the Firebase notification and Sponsor bar design
A39: =IF(AND($D$1>=C39,$D$1<=D39),"CurrentSprint","NA") -> NA | B39: OB-OP 8.1 Sprint 1 | C39: 45826 | D39: 45841 | E39: 17 | F39: 17 | G39: 5/0 | I39: Release OB/OP to PRD, continue OB UX and Donor Platform Accomplishment Completed all the sprint stories and took stretch stories and made good progress on that as well | J39: Peer CRC:0 Onsite CRC:0 Client CRC: 0 Internal Defects:0 External Defects: 0 | K39: Great in meeting the Sprint Goal What went well? All planned stories got completed and more Quick turn around on the Hot Fix What didn’t go well? A number of security issues came through which was unplanned and high priority for some old modules The arc review is preventing us from implementing B2C Kudos Offshore team did a great job on OB and Donor work, completed everything +1 Appreciate Rajesh stepping in and covering for Prabhu Joe and Prabhu giving assistance on couple of stories for testing to Alice( specially on Donor project) Quick turn around on the Hot Fix Alice and Offshore QA team has done a great job on automation testing which made both the prod release testing quick +1
A40: =IF(AND($D$1>=C40,$D$1<=D40),"CurrentSprint","NA") -> NA | B40: OB-OP 8.1 Sprint 2 | C40: 45841 | D40: 45855 | E40: 17 | F40: 16 | G40: 2/0 | I40: More OB UX, Donor Platform infrastructure, and OP security remediation. Accomplishment Completed OB UX stories,took a stretch story and completed that as well | J40: Peer CRC:0 Onsite CRC:0 Client CRC: 0 Internal Defects:1 External Defects: 0 Pending reason OB-3784 - Due to few escalation and production login issue couldn't work on this before, but Development is completed, need to do local and DEV testing Internal Defect OB-3790 - Missed in local and DEV testing, need to compare all the scenarios with Old UI | K40: Completed the design stories in OB pages What went well? Design story in OB page is completed along with one more stretch story What didn’t go well? One design story that needs to be updated in GGO page is carry forwarded to next sprint as testing is pending Kudos Offshore team did a great job on OB and Donor work
A41: =IF(AND($D$1>=C41,$D$1<=D41),"CurrentSprint","NA") -> NA | B41: OB-OP 8.1 Sprint 3 | C41: 45855 | D41: 45869 | E41: 13 | F41: 3 | G41: 0/0 | I41: Continue OB UX (Package Cards, Donation Modal), Platform work, Security remediation Accomplishment Implemented the package design in browse page by mapping with API and also the search functionality | J41: Peer CRC:0 Onsite CRC:0 Client CRC: 0 Internal Defects:0 External Defects: 0 Pending reason OB-3689, OB-3724 - Development completed, local testing by pointing DEV DB is done, Peer review for one story is completed(OB 3689), OB 3724 can be reviewed only when the previous story is deployed as it is the dependent story - OB certificate issue blocked testing in Dev | K41: Well Done Team for another great Sprint. The Sprint goal wasn't met because of the certificate issue which is out of our hands. What went well? Donor app progress was good A lot of positive comments from CS on the Donor Platform progress - well done team! “The login page looks great and it will be one of the most visited page” What didn’t go well? OB certificate issue blocked testing in Dev, TST and CRT OB build Pipeline issue The fixes for WhiteHat security findings was challenging Kudos Prabhu for supporting Alice with Donor platform testing Mercy for cross site scripting testing and bringing up some issues Prabhu, Rajesh, Mike H and Joe for getting the Certificate issue resolved, it is very close to getting done Arivalagan - the code he delivered for Don 39 and Don 40 is of high quality
A42: =IF(AND($D$1>=C42,$D$1<=D42),"CurrentSprint","NA") -> NA | B42: OB-OP 8.1 Sprint 4 | C42: 45869 | D42: 45883 | E42: 23 | F42: 20 | G42: 0/0 | I42: Continue OB UX, Platform work, Security remediation Accomplishment Worked on the macroscopic stories related to vulnerable package, CRT testing of OB and OP | J42: Peer CRC:0 Onsite CRC:0 Client CRC: 0 Internal Defects:2 External Defects: 0 Internal Defect OB-3801 - Missed to check in local and DEV testing OB-3802 - Need to edit all the values and check, missed the custom amount scenario Pending reason OP-2786 - CRT testing for OP coudn't be completed | K42: Well Done on completing another big Sprint given all the Challenges! the assistance provide to Onsite QA Alice for the complete all the testing including OB CRT testing was acknowledged and appreciated by all at the Retrospective meeting today. What went well? Most of the planned stories got completed + some stretch stories Upper Management support for getting us out of OP bug bounty What didn’t go well? Implementing the WAF caused us to do additional testing in CRT affecting both OB and OP B2C implementation using MSAL was challenging without having designated MFA policy Kudos Offshore team and Prabhu for the implementation of B2C token, It was difficult and needed a lot of coordination +1 Well Done on the OB Cert issue Prabhu and Joe for the support with all the testing Offshore QA for for helping Alice with all the testing Rajesh for clearing the CRT issue Offshore ( OB/OP and Donor) for completing the planned stories+1
A43: =IF(AND($D$1>=C42,$D$1<=D42),"CurrentSprint","NA") -> NA | B43: OB-OP 8.2 Sprint 1 | C43: 45883 | D43: 45897 | E43: 17 | F43: 17 | G43: 5/0 | I43: Release OB 8.1 to PRD, OB UX, Donor Platform Accomplishment Completed the design for detail page and worked on some improvements in design and fucntionality in new UI | J43: Peer CRC:3 Onsite CRC:0 Client CRC: 0 Internal Defects:0 External Defects: 0 Review Comment 1. Move numbers to constant variables 2. Use bootstrap classes 3. Reduce the code by putting repeated codes as common method | K43: There were few challenges on the Donor stories given it was all the same page, client is aware of it and appreciates the hard work put in What went well? Both OB and Donor feature implementation went well OB Prod release was long but very smooth What didn’t go well? Dependency on B2C token Given multiple stories were for the same Home page there was time spent on fixing merge conflict Kudos OB search functionality was a great win- Prabhu Sankar [C]+1 Prabhu for sticking in there on the Donor app with Joe- coordinating all the updates with offshore +1 Prabhu for supporting Alice on the local setup for Donor testing Offshore for putting in a lot of effort in designing the application the way it is+1
A44: =IF(AND($D$1>=C43,$D$1<=D43),"CurrentSprint","NA") -> NA | B44: OB-OP 8.2 Sprint 2 | C44: 45897 | D44: 45911 | E44: 20 | F44: 17 | G44: 0/0 | I44: OP PRD release, continue Ob UX work, continue Donor Platform Accomplishment Completed the design for filtering the packages with multiple options and added bid modal to allow the users to bid the package | J44: Peer CRC:0 Onsite CRC:1 Client CRC: 0 Internal Defects:2 External Defects: 0 Review Comment - Avoid multiple API calls Internal Defect OB-3818 - Outbid popup didnt occur beacuse of the last minute spelling change which needs to be change in SQL also but we missed that OB-3819 - Issue couldn't be reproduced with the exact steps mentioned in the description, but while using search filter this was reproduceable Pending Reason OB-3718 - Development was started on last friday only since there was a discussion going on with client side designer (Sep 5). Development and DEV testing was completed but we prioritised 8 point story to go for review initially because of DEV deployment failure in last week for 2 days and due to which we had many merge conflict in coding for this story. | K44: Keep up the good work team, kudos on hustling to complete the planned stories given the build issue this Sprint! What went well? Completed way more than planned 2 Prod releases this sprint Over the hump on the security issues (DevOps side) Macroscope report is up to date Macroscope report is up to date What didn’t go well? Implemented security measures that caused pipeline issues The team is putting renewed emphasis to be compliant with FIGMA design Kudos Great job team on completing more than planned given all the challenges Prabhu and Joe for helping setup Dionor platform and general testing support, including the hotfix testing Offshore for fixing the bugs under OB stories really fast To Prabhu for getting offshore to be compliant with Bootstrap +2 Offshore team for being resilient and delivering on the designs meeting all the AC +2
A45: =IF(AND($D$1>=C44,$D$1<=D44),"CurrentSprint","NA") -> NA | B45: OB-OP 8.2 Sprint 3 | C45: 45911 | D45: 45925 | E45: 9 | F45: 17 | G45: 8/0 | I45: Continue OB UX, Donor Platform Accomplishment Took 2 stretch stories and completed that Completed the bid and buy now popup which is most important for bidding application Overall as a team, We forecasted 34 Story points and completed 41 Story points | J45: Peer CRC:0 Onsite CRC:1 Client CRC: 2 Internal Defects:0 External Defects: 0 Review comment 1. Add error callback. 2. Use tab or this.activeTab throughout for consistency. 3. Remove multiple div condition in HTML and use switch case | K45: A big shout out to team for complete more the committed stories yet another Sprint. A special mention for OB/OP offshore team for going above and beyond. What went well? Completed more than planned Lack of any escalation or any distraction lead to a lot getting done by team What didn’t go well? Vega is a new component library and taking some extra time to apply our customization Kudos Joe: Appreciate all the help from Prabhu and Alice especially towards end for review and getting everything tested out Rajesh has been very responsive from the GGO side Prabhu: OB/OP offshore team for completing all that was committed and more +1 from Rajesh Joe: All the ob work looks really great +1 Alice: Shout out to Joe and Prabhu for the support on testing Mike Horihan who is dealing with the cyber security and shielding the team
A46: =IF(AND($D$1>=C45,$D$1<=D45),"CurrentSprint","NA") -> NA | B46: OB-OP 8.2 Sprint 4 | C46: 45925 | D46: 45939 | E46: 16 | F46: 16 | G46: 0/0 | I46: Release OB 8.2. to CRT, continue OB UX and Donor Platform Accomplishment Completed all the sprint stories Good work on the OB UX cleanup Added max bid alert and status banner for the packages | J46: Peer CRC:0 Onsite CRC:0 Client CRC: 0 Internal Defects:2 External Defects: 0 Internal Defect Both defectes were found in CRT regression testing and will be worked in next sprint as it is not of part of this release One defect OB-3837 was developed and tested initially but later while changing the logic, missed this scenario, other bug OB-3836 was missed in development and testing | K46: Well Done on keeping the momentum going and delivering more the planned! What went well? Very few distractions Completed more than planned What didn’t go well? Customization on the google places autocomplete textbox was challenging Kudos Joe : Prabhu for overseeing all the offshore work Prabhu : OB/OP offshore team and Donor offshore team were very productive Alice : Offshore QA Mercy for catching some issues and Murugasen and Mercy doing very good testing
A47: =IF(AND($D$1>=C46,$D$1<=D46),"CurrentSprint","NA") -> NA | B47: OB-OP 8.3 Sprint 1 | C47: 45939 | D47: 45953 | E47: 17 | F47: 19 | G47: 4/0 | I47: Production release, wrap up OB UX and continue work on Donor platform Accomplishment Completed all the sprint stories and took stretch stories as well and completed Good work on the OB UX cleanup Added zoom feature to the package image in detail page | J47: Peer CRC:0 Onsite CRC:0 Client CRC: 0 Internal Defects:1 External Defects: 0 Internal Defect Tested the same behaviour in local and DEV before raising PR it was working fine, bug has come due to merge conflict in the code | K47: Great work Team for for meeting the commit again given the mid sprint changes for Profile and Login, Well Done! What went well? Met the commit goal and more Production release for OB 8.2 went well What didn’t go well? Couple of changes mid Sprint regarding Profile and Login Kudos Joe: Prabhu took a quiet a few to start with making sure everything goes well and leading / managing the big offshore team +2 Good job by offshore team by being Agile for taking all the requirement changes on the stride and changes related to Vega +2 Alice: Offshore QA for great help with testing and writing fantastic test plans both Mercy and Murugesan +1 Prabhu: Joe for putting in a lot effort in multiple stories Thanks to Derek for always being being available with quick responses+1 Rajesh for supporting on the MFA work
A48: =IF(AND($D$1>=C47,$D$1<=D47),"CurrentSprint","NA") -> NA | B48: OB-OP 8.3 Sprint 2 | C48: 45953 | D48: 45967 | E48: 13 | F48: 16 | G48: 3/0 | I48: Wrap up OB UX and continue work on Donor platform Accomplishment Completed all the sprint stories and took a stretch story and completed that as well Implemented sign out feature for the user, even auto logout implemented Implemented buy logic for multisale packages | J48: Peer CRC:0 Onsite CRC:3 Client CRC: 2 Internal Defects:1 External Defects: 0 Internal Defect While testing this story in DEV, eveything was working correctly. Due to the changes done in the before PR, that change has affected in this branch Review comments ONSITE 1. Move the magic string to constants 2. Simplify the if condition to more readable 3. Avoid repeated codes in the same file CLIENT 1. Let's throw some error handling on the methods that aren't just calling other methods. 2. Make sure to implement onDestroy since we're using it. | K48: Here is the well deserved feedback from Onsite including the Managers on how this team is on autopilot, well done! What went well? Well planned Sprint- the tickets were pointed properly and the AC was detailed. The stories coming out in phases for QA to test rather than all together +1 What didn’t go well? Security settings blocking sales appearing in GGO, that let to delay in testing OB Kudos Joe: Arivalangan - The login page styling and Ubai- update to to credit card area Preethi and Karthi- slide out menu stood out and was a big impact to what is seen Alice: Offshore QA- Mercy and Murugasen for putting all the details in written Writing great test plans which frees up Alice to work on automation For Prabhu and Rajesh in helping diagnose all those little issues Prabhu: Joe for taking on both Login flow and Signup flow All offshore team members for completing all the work Rajesh for supporting with Azure work +1 ( Alice) Irsath and Kannan for the work on B2C flow as it was challenging but he was able to get it done +1 (Joe) Owen : Thanks to everyone on the team for being on autopilot mode +1(Mike H)
A49: =IF(AND($D$1>=C48,$D$1<=D48),"CurrentSprint","NA") -> NA | B49: OB-OP 8.3 Sprint 3 | C49: 45967 | D49: 45981 | E49: 17 | F49: 13 | G49: 0/0 | I49: Continue work on OB UX and Donor platform Accomplishment Implemented pagination to our application Completed search functionality with the new updated approach | J49: Peer CRC:0 Onsite CRC:0 Client CRC: 0 Internal Defects:0 External Defects: 0 Pending Reason OB-3846 - We had 2 different set of codes, implemented that and was pending with PO decision, later they gave us the image ratio, but then the focus were on other priority stories( two 5 pointers), so this one couldn’t able to resume work during the sprint OB-3870 - Focus was on other priority stories, so this one couldn’t able to start work during the sprint | K49: Well Done Team for pulling through yet another Sprint meeting the commit given the complexities What went well? Yet again completed all planned stories Work is getting completed for Dev environment What didn’t go well? None Kudos Joe: Profile data management looked really good- Kudos to Kannan and Ubai Profile clean up looks really good- Kudos to Arivalagan Preethi on pagination - very good initial PR given the complexity +1 (Prabhu) Karthi on autocomplete - very good initial PR given the complexity +1 (Prabhu) Prabhu has a big job to look over a lot of developer and work and all the PRs Alice: Offshore QA put a lot extra effort in putting the test plans together and all the testing in taking us to the finish line while Alice could focus on the automation +1 (Prabhu) Prabhu: Joe for providing continuous support +1 (Mike Horihan) Rajesh for supporting the with clarification between Donor and GDon team +1 (Joe), +1 (Mike Horihan)
A50: =IF(AND($D$1>=C49,$D$1<=D49),"CurrentSprint","NA") -> NA | B50: OB-OP 8.3 Sprint 4 | C50: 45981 | D50: 45995 | E50: 13 | F50: 10 | G50: 2/0 | I50: OB CRT release and continue work on OB UX and Donor platform Accomplishment Worked on the package stretch part and updated Started with caching feature Imporoved search and filter functionality | J50: Peer CRC:0 Onsite CRC:0 Client CRC: 2 Internal Defects:6 External Defects: 0 Review Comments 1. No need to check > 0 against length. An empty array returns 0 (falsy), so just _this.selectedFilter?.category?.length. Use (?.) to safely chain it. 2. Better to check price === 'number' than !==null. That's what we really care about. Internal Defect OB-3883 would have been caused due to the recent changes, need to check the root cause yet OB-3884 - this is due to the changes made in the story worked during 8.3 sprint 2 2 bugs OB-3885, OB-3886 are related to the recent pagination changes which we have done, signalr changes causes this issue OB-3887 - This is a known issue since development, tried many approaches in initial days of development itself, but this was not working as expected, so need to research and work on this OB-3888 - Missed from the current sprint story Pending reason 1. OB-3877 - Lot more prerequisite changes were needed to implement the points in the AC and that was covered in OB-3881 - Completed all the points mentioned in AC and did DEV testing. PR was raised on the last day and was pending with Joe's review | K50: Client and everyone at onsite appreciated your efforts during the onsite holidays and PTOs, keep up the good work Team! What went well? Despite multiple PTOs and holiday schedule, the team completed the key commitments What didn’t go well? TST environment was down for 1 day Kudos Joe: The profile initials functionality was super cool- great job Ubai and Kannan Error page again great work Ubai and Kannan while Joe could work on other tickets Ob package alignment and resolving the stretch for that - Great job Karthi and Prabhu for the work Prabhu for organizing and thinking about the approach for caching and search functionality. Great job in specifying the work that needs to be done Alice: Mercy and Murugasen for doing excellent testing while Alice was on PTO +1 (Prabhu) Did excellent test plans which was very helpful Prabhu: Mercy and Murgasen for going over and beyond Preethi for the good progress on caching +1 (Joe) Joe for his consistent support Rajesh for providing support with all Donor stories
A51: =IF(AND($D$1>=C50,$D$1<=D50),"CurrentSprint","NA") -> NA | B51: OB-OP 8.4 Sprint 1 | C51: 45995 | D51: 46009 | E51: 12 | F51: 12 | G51: 4/0 | I51: Release OB 8.3 to PRD, continue OB UX, continue Donor Platform Accomplishment Completed Caching feature Optimised the code for better performance Completed the bugs reported in last sprint | J51: Peer CRC:0 Onsite CRC:0 Client CRC: 2 Internal Defects:0 External Defects: 0 Review comments 1.use of ToLower() will cause significant issues (full table scans, bypassing indexes and unneeded comparisons 2. Stick with the use of hasValue() checks over !=NULL. HasValue translates to IS NOT NULL in SQL. We should flag this for optimization later. It will get called frequently.and If there are more condition in HTML, move it to ts as a method | K51: A strong finish to the year, well done team! What went well? Completed the planned stories and more What didn’t go well? The team had to wait on getting Donor database access Still don’t have our own B2C policy Kudos Joe: Prabhu and offshore team for some really great dev work, pagination, filtering and caching. That's a big ask and they have done a terrific job. OB is looking great (+1 Mike) Alice: Mercy and Murugasen for doing a lot of good testing, creating good test plans, catching bugs early codes come clean letting Alice focus on automation Prabhu for letting me know things are ready for testing and in general very smooth All the pre testing done by dev is ending up with sprints going smoother Prabhu: Joe for all the support he has provided for the team Preethi on the caching , filtering and pagination work. She did a tremendous job on all of these items (+1 Joe) AliCe, Mercy and Murugasen for the thorough testing
A52: =IF(AND($D$1>=C51,$D$1<=D51),"CurrentSprint","NA") -> NA | B52: OB-OP 8.4 Sprint 2 | C52: 46009 | D52: 46037 | E52: 21 | F52: 21.5 | G52: 7.5/0 | I52: Finish OB UX and beginning phase 2 of Donor platform Accomplishment Completed the changes needed for the CRT release | J52: Peer CRC:0 Onsite CRC:0 Client CRC: 0 Internal Defects:3 (2 bugs are not related to the stories done in current sprint, defects found during regression) External Defects: 0 Internal Defect 1. OB-3903 - We have been doing UX cleanup for browse pages, but detail page was missed to add in that, so created a defect for this and will be working in next sprint 2. OB-3905 - This is an existing behaviour in old UX missed to add in new UX and has been found during regression 3. OB-3901 - Due to the past sprint story review comment changes, this scenario got broken but this was working fine while doing DEV testing in past sprint Pending Reason OB-3895, OB-3864 - Prabu was working on the review and making code changes to improve the deliverable, which caused a delay at the peer‑review stage. but offshore development has completed. | K52: Well the retro appreciation for each of you says it all, Well Done Team for yet another great Sprint! Both Devs and QAs were equally appreciated for high delivery quality, keep up the good work Team What went well? Completed more than planned stories even though it was holiday time What didn’t go well? Setting up the new Dev environment for Donor platform is challenging Kudos Joe: Offshore team has done great work particularly OB . It looks great. They are in rhythm and code quality is really great. (+1 Mike +1 Alice +1 Prabhu +1 Rajesh) Prabhu for being a great leader, organizer great PR and testing (+1 Mike +1 Alice +1 Rajesh) Alice: Offshore Qa for some great test plans and great testing, couple issues caught early and resolved A lot of testing happens in Dev before coming to TST Joe, Rajesh and Moose for the environment set up Prabu: Rajesh for supporting and resolving issues whenever requested (+1 Joe) and resolving it the same day Joe and Alice for their support for the entire support Derek for always being available for the team (+1 Joe)
A53: =IF(AND($D$1>=C52,$D$1<=D52),"CurrentSprint","NA") -> NA | B53: OB-OP 8.4 Sprint 4 | C53: 46037 | D53: 46051 | E53: 12 | F53: 19 | G53: 16/0 | I53: Release OB 8.4.0 to CRT. Test it thoroughly. Continue Donor Platform build for b2c Accomplishment Completed current sprint tickets and took bugs and new story requirements from backlog and completed those | J53: Peer CRC:0 Onsite CRC:0 Client CRC: 0 Internal Defects: 6 External Defects: 0 Pending Reason OB-3913 - After CRT release, CS team shared few points to work on, so will be deploying those changes to CRT in upcoming weeks and testing will continue in CRT, hence this story is carry forwarded to next sprint Internal Defects 1. OB-3916 - We need to test all scenarios in all tabs - this occurs in one tab and rest of the 2 tabs are working as expected 2. OB-3917 - Minor issues found during regression in TST, few incosistent issues and few browser specific issues 3. OB-3925 - Came from CS Team during CRT testing. We didn't have any story to handle this button functionality before, so can be considered as new requirement 4. OB-3924 - Came from CS Team during CRT testing. The feature has behaved this way since development and may have been missed in the PO requirements. 5. OB-3926 - Came from CS Team during CRT testing. This was already addressed by QAs during testing of those stories 6. OB-3927 - Came from CS team during CRT testing. We didnt have any story to handle single sponsor scenario and also static sponsors | K53: Great effort, Keep up the good work! What went well? CRT release went and CS team tested and shared their feedback What didn’t go well? Trouble shooting and setting up the new Dev environment has been difficult Kudos Joe: Prabhu really pushes the pace of the team and that's why we were able to bring in those bugs(+1 Rajesh) Consistent high quality work by the team(+1 Prabhu) B2C pages looks great +1 Prabhu Derek for queuing in all those bugs from CS and internal Stakeholders (+1 Alice, +1 Rajesh, +1 Prabhu) Client Services for great testing (+1 Alice) Great testing by CS, Alice and offshore in the past Sprint Alice: Offshore Dev for fixing all the bugs Offshore Qa Mercy for finding few of the bugs Online Bidding sales issue support from Rajesh and Joe Prabhu: Offshore team for taking ownership of the bugs which came and they quickly fixed it. Kudos to Preethi, Karthi and Mercy(+1 Joe, +1 Mike , +1 Alice , +1 Rajesh) All the bugs got discussed and completed because of Joe ‘s support given he already had a lot on his plate
A54: =IF(AND($D$1>=C53,$D$1<=D53),"CurrentSprint","NA") -> NA | B54: OB-OP 8.5 Sprint 1 | C54: 46051 | D54: 46065 | E54: 18 | F54: 21 | G54: 9/0 | I54: Release OB 8.4.0 to CRT. Test it thoroughly. Continue Donor Platform build for b2c Accomplishment Completed current sprint development stories Took stories from backlog and completed those as well Another stretch story related to signalr - made good progress on that Completed almost all necessary items for next CRT release | J54: Peer CRC:0 Onsite CRC:1 Client CRC: 0 Internal Defects: 2 External Defects: 0 Review comment - Remove the dead codes on ts file for the changes removed in HTML Internal Defects 1. OB-3933 - We have updated the popup in one scenario but missed to add the parameter in other places which uses the same popup component. When any change is done we make sure that its reflected in all places 2. OB-3941 - These scenarios will be done in regression only. As part of the original story, TOP icon functionality was tested but having donation bar at the top and bottom separately was not tested Pending Reason OB-3920 - Development completed, PR raised, yet to deploy and test, this change is done in GGO source code OB-3913 - This is CRT testing story, we have planned for next CRT release in next sprint, so will be closing this story once CRT deployment and tested is completed | K54: Well Done Team! What went well? Completed more than planned What didn’t go well? Working with Donor B2C team has been challenging because of the time difference OP escalations taking up time Kudos Joe: All of the offshore team, their quality of work has been really high right now and that has led to more stories as the code quality is high and gets completed after the 1st pull request.No sending back (+1 Alice, +1 Mike H, +1 Prabhu, +1 Rajesh) Derek for keeping tickets up to date, getting all the stories AC up to date as per request (+1 Alice, +1 Prabhu) Alice for getting all the testing done at the end of the sprint and CRT testing as well Alice: Offshore QA for getting all the bases covered and an extra eye on CRT environment Joe and Prabhu for the extra support with testing the stories and completing them Prabhu: The team was able to complete all the stories only because Joe took up the complex tasks Mike: Rajesh for helping me with the Op escalations Joe for helping me with GCP and B2C teams Anything that needs to be highlighted from the past Sprint Donor Dev environment is up and running Takeaways Going forward for the next releases, as a team we need to remind ourselves that given a deadline we need to release the MVP for the release and tackle the rest in the next release instead of stretching ourselves | N54: 1 | O54: 0.5
A55: =IF(AND($D$1>=C54,$D$1<=D54),"CurrentSprint","NA") -> NA | B55: OB-OP 8.5 Sprint 2 | C55: 46065 | D55: 46079 | E55: 14 | F55: 6 | G55: 0/0 | I55: Release OB 8.4.0 to CRT. Test it thoroughly. Continue Donor Platform build for b2c Accomplishment Second CRT release completed successfully Tested all the recently completed stories in CRT Updated the functionality for retaining the previous filters, search during browser back | J55: Peer CRC:0 Onsite CRC:0 Client CRC: 0 Internal Defects: 0 External Defects: 0 Pending Reason OB-3911 - Implementing browser back retain was challenging due to filter handling and required significant code changes. We explored multiple approaches including SessionStorage, QueryParams, and Router Reuse Strategy, but none met the requirements. As a workaround, we finalized the solution by saving the state in a service variable OB-3913 - During the bug bash, the CS team identified a few minor issues in CRT. As a result, we’re planning another CRT release, and this work will be carried forward into the next sprint. | K55: A very challenging Sprint, everyone in retro acknowledged it. What went well? A lot got completed given how complex some of the stories turned out to be What didn’t go well? Checkout Steeper 2 was complex and Stepper 3 was dependent on Stepper 2 which kind of delayed completing Stepper 3 The scenarios for back button were a lot more than the effort originally planned by the team Delay in response from B2C team given the different time zones Kudos Joe: Team did a great job on(+1 Mike H, +1 Rajesh , +1 Alice) OB price sorting as we knew it has potential to cause issues. The team did a great job Donor side - great job on Stepper Kudos to Prabhu for keeping everyone on schedule and peer reviews with the OB release coming up. He has done a lot in leading the team (+1 Mike H, +1 Rajesh , +1 Alice) Alice found some issues which we missed, thanks for the thorough testing( +1 Prabhu) Thanks Mike on taking lead on the OP Apigee URL switch Alice: Joe and Prabhu for support on testing efforts Shout out to Derek for all the last minute information close to release(+1 Joe, +1 Prabhu) Great testing and test plans from Mercy and Murugasen Prabhu: Joe for leading the way for MFA and lot of insights on the work in the Sprint Offshore got a lot done this sprint even though we couldn’t mark those complete | N55: 1 | O55: 1
A56: =IF(AND($D$1>=C55,$D$1<=D55),"CurrentSprint","NA") -> NA | B56: OB-OP 8.5 Sprint 3 | C56: 46079 | D56: 46093 | E56: 11 | F56: 11 | G56: 7/0 | I56: Release OB 8.4.0 to PRD. OP Security Items. Continue Donor Platform work Accomplishment Production release went well Completed the planned stories Made good progress on the OP stretch stories | J56: Peer CRC:0 Onsite CRC:0 Client CRC: 0 Internal Defects: 3 External Defects: 0 Internal Defect 1. OB-3947 - Was working fine in DEV testing with single sponsor, but we had 2 branches with different approaches and in final branch got missed for single sponsor alone 2. OB-3948 - OB-3911 handles this which is almost completed development in previous sprint but that was not included for production release (this can be conisdered as new requirement, not considered as bug. OB-3911 is story only) 3. OB-3949 - This is not part of any of the requirement so far we developed | K56: Well Done team for completed a good Sprint. A lot positive feedback for the foort which went in for the OB release. What went well? Prod release went well Completed all the planned stories What didn’t go well? Working with B2C team took more time than planned given their availability Reproducing OP errors was challenging Kudos Joe: Some really good work on Checkout Irsath and arivalagan and Prabhu backed me on this, don 128 Release went well (+1 Derek) Thanks for offshore for the great work and Prabhu Sankar [C], a lot of time was spent on OB for the last few months. I really appreciate all the work A ton of automation works which goes in with UX changes, thanks to Alice for taking care of all the automation work Derek for dealing with all the client interaction Alice: Entire team for a great release OB 8.4.0 (+1 Prabhu, +1 Rajesh, +1 Mike) Derek for managing all our stories and progression for the OB UX release(+1 Joe) Offshore QA Mercy for good testing leading to a smooth release CS also helped in identifying a lot of issues which the team was able to fix before the release Prabhu: Don 128 and Don 129 Irsath, arivalagan, kanna and Ubai for the progress on it Rajesh for helping in identifying the root cause of the OP issue Mike: Joe for making great strides on the B2c stories (+1 Prabhu) Anything that needs to be highlighted from the past Sprint Ob UX release went well and that will increase the performance going forward Takeaways If we have mock data and put it in a local file and not into the repository Point the stories better to be able to complete the stories without getting stretched Going forward for the next releases, as a team we need to remind ourselves that given a deadline we need to release the MVP for the release and tackle the rest in the next release instead of stretching ourselves | N56: 1 | O56: 2
A57: =IF(AND($D$1>=C56,$D$1<=D56),"CurrentSprint","NA") -> NA | B57: OB-OP 8.5 Sprint 4 | C57: 46093 | D57: 46107 | E57: 16 | F57: 21 | G57: 7/0 | I57: OB 8.5.0 CRT release and continue with Donor work Accomplishment OB CRT release went well Completed current sprint story except one OP story, though development was completed for that Took stretch stories and completed that as well | J57: Peer CRC:0 Onsite CRC:0 Client CRC: 0 Internal Defects: External Defects: Defect 1. OB-3957 - Missed to add the time coversion code based on the project timezone which was implemented in old UI, since this code was deployed in client server, so it was working correctly in client timezone as well in all the past CRT releases tested by CS teams 2. OB-3956 - This was not added as part of any of the AC in the previous stories, we have added this in our observation sheet already Pending Reason OP-2807 - Development completed in the start of the sprint itself, but finding the page in OP UI was challenging to see the code reflection, found a table in DB which had the content, but design changes were not refelcted, so finding a way to update the css as well through DB or any other option | K57: Well Done on another great sprint! What went well? Completed the planned stories and a few stretch What didn’t go well? Dependency on B2C and GCP team was a blocker It was challenging for the team to reproduce the OP splash page error Kudos Joe: Nice job on Checkout : Prabhu has been working on that feature for 2 weeks now Rajesh, Karthi and Preethi were able to find where to make the change for OP splash page issue (+1 Mike Horihan) Thanks for all quick quick work on OB for the Crt release- Alice and offshore Alice: Offshore and Murugasen for good test plans and good testing documentation Dev team for all the work on the release Prabhu: Ob/OP offshore team for completing the bugs for the release fast Donor team did a great job on the checkout step Mike: Joe for continuing to work on B2C (+1 Rajesh, +1 Prabhu) | N57: 0 | O57: 0.5
A58: =IF(AND($D$1>=C57,$D$1<=D57),"CurrentSprint","NA") -> NA | B58: OB-OP 8.6.0 Sprint 1 | C58: 46107 | D58: 46121 | E58: 7 | F58: 7 | G58: 2/0 | H58: OB/OP - Worked on the enhancements changes in OB after recent prod release and also updated the splash page for OP Donor - Worked on the checkout and household functionality, Updated the payment component and cancellation token | I58: OB 8.5.0 Prod release, continue Donor Platform Checkout work, some of OB and OP stories OB/OP Completed the assigned SP Found the splash page in OP and updated that though it was very difficult in initial stages Donor Completed current sprint stories Took 3 stories from backlog and completed 2 Client mentioned in standup that most of the PRs were ready for review in first week of the sprint itself | J58: Peer CRC:0 Onsite CRC:0 Client CRC: 0 Internal Defects: 0 External Defects: 1 External Defect OB-3969 - We have already added this point in the observation sheet and shared to derek long back, but story was not created for this point from PO end Pending Reason OP-2705 - Not able to get the settled date in local OP UI,OP DEV got broken, tried directly in TST as well but couldn't find a way. We have a fix for that but need to reproduce the issue first then deploy our changes and test | K58: Well Done Team for keeping up the momentum and completing more than planned! What went well? Completed more than planned stories What didn’t go well? Connecting with B2C team has been challenging Configuration stuff for Donor environment took a lot of time The audit process for Donor initial release is time taking Kudos Lot of great work on Donor tickets this sprint Appreciate Rajesh's stepping up getting the PRs through and made it seamless Donor - Murugasen has put together a lot of good test plans and good testing The release went well, a lot of good testing over all so kudos to the team on it Offshore Donor and OB team for completing all tickets. Whole team, has always been self managing | N58: 5.5 | O58: 7
A59: =IF(AND($D$1>=C58,$D$1<=D58),"CurrentSprint","NA") -> NA | B59: OB-OP 8.6.0 Sprint 2 | C59: 46121 | D59: 46135 | E59: 14 | F59: 12 | G59: 4/0 | H59: OB/OP 1. OB SYNK remediation - reduced the count 2. Worked on the feedback stories came after the production deployment in OB Donor 1. Integrating login flow with Checkout 2. SNYK Remediation and manually address edit | I59: Continue Donor Platform Checkout work, some of OB and OP stories Accomplishments OB/OP 1. Fixed the SYNK remediations taken in this sprint 2. Completed the defects and the enhancement stories in OB 3. Completed fixing OP SYNK and testing is in progress Donor 1. Completed current sprint stories 2. Completed SYNK remediated stories 3. Took 7 stories from backlog and completed 4, made good progress on others | J59: Peer CRC:0 Onsite CRC:0 Client CRC: 0 Internal Defects: 0 External Defects: 2 External Defect 1. OB-3978 - We have written the code to fetch bidder infoonly after the success of package API, so when no package was there, bidder API wasn't called 2. OB-3974 - We have changed the routes for new UI and missed to test email scenarios Pending Reason 1. OP-2807 - We tested in TST DB and found that the dates were correctly inserted in DB in PST timezone as well as in UI, but this is contradicting with the analysis shared in the story, so once prabu is back, need to confirm with him and proceed 2. OP-2805 - Tested in local, except pages option rest all were working fine and Deployed in DEV for testing | K59: Well Done Team for all the good work! What went well? Met the Sprint commit given we have new team member What didn’t go well? B2C continues to be challenging Kudos Team did a great job , kept their foot on the gas pedal all sprint(+1 Mike ) Rajesh a lot gone done this sprint coordinating with offshore(+1 Mike ) Offshore for delivering high quality work(+1 Mike ) Rajesh supported with setup in Donor platform(+1 Mike ) Murugasen for all the testing and putting really good information on the testing report(+1 Mike ) Nivetha for taking care of testing and creating good reports (+1 Mike ) Ob and Donor offshore team for completing all the stories(+1 Mike ) Alice , Murgasen and Nivetha for all the good testing(+1 Mike ) | N59: 11 | O59: 12
A60: =IF(AND($D$1>=C59,$D$1<=D59),"CurrentSprint","NA") -> NA | B60: OB-OP 8.6.0 Sprint 3 | C60: 46135 | D60: 46149 | E60: 12 | F60: 14 | G60: 5/0 | H60: OB/OP 1. Completed OP SYNK remediation 2. Implemented the navigation to new Donor application from OB application 3. Featured packages content looks similar to browse page 4. Table # for household has been introduced in new UI Donor 1. Full flow needs for the checkout (with project key as well as bidder key) 2. All service health checkup and fixing all identified issues | I60: Continue Donor Platform, some of OB and OP stories Accomplishments OB/OP 1. Completed OP SYNK remediation 2. Though we got GDON API 3 days before the sprint end date, we completed both the stories 3. Completed current sprint stories leaving the OP time conversion as we have difficulties in it, we took from backlog and completed those as well Donor 1. Completed the current sprint stories 2. Great job on maintenance notification and health check work 3. Worked on B2c styling updates | J60: Peer CRC:0 Onsite CRC:0 Client CRC: 0 Internal Defects: 1 External Defects: 1 Pending reason OP-2805 - Cant be reproduced in TST, so need to check directly in Prod with the help of Carlos and also need prabu's input on this as he has already analysed more on the same Internal defect OP-2811 - Checked all pages in OP as well as GGO to OP flow, but missed to check in the new project by creating new project website External Defect OB-3990 - This would have been broken as part of implementing apply filter before. We were working on multiple scenarios of filter and search so some scenarios would have caused this issue. Offshore QA only found the issue, since the code is in production it was marked as external | K60: Well Done Team for all the good work! What went well? ○ B2C CERT/PROD release credentials created and in progress towards implementation. ○ Exceeded expectations of story completion as well as great testing effort in Donor. What didn’t go well? ○ Reliance on 3rd party teams for routine updates in Donor environments delays our potential. Kudos ■ Thank you for the last minute testing of the OB slide out menu so we didn’t have to carry it forward. ■ Thanks for a great pre-PTO hand-off. ■ Thank you for the OP queries ■ Offshore team did a great job working within a looser-than-typical arrangement with DON-360 (catch-all), but was able to catch several bugs, resolve, retest and reiterate on some great improvements. (+1Alice) ■ Preethi was a huge help in Rajeshs’ absence. ■ Great job on B2C styling updates ■ Great job on maintenance notification and health check work ■ Great testing and fixes for OB (filter clearing and featured package appearance) done by offshore team along with some very good testing documentation from Murugesan and Nivetha. (+1 Joe) Takeaways ○ Loosen the rate limiter for DEV/TST | N60: 12 | O60: 12
A61: =IF(AND($D$1>=C60,$D$1<=D60),"CurrentSprint","NA") -> NA | B61: OB-OP 8.6.0 Sprint 4 | C61: 46149 | D61: 46163 | E61: 19 | F61: 11 | G61: 1/0 | I61: Release OP, OB & Donor | J61: Peer CRC:0 Onsite CRC:0 Client CRC: 0 Internal Defects: 0 External Defects: 0 | N61: 3 | O61: 1

Sheet Unplanned Leaves
B1: Resource Name
A2: Sprint Name | B2: Preethi Muthu | C2: Nivetha | D2: Karthi Rajendran | E2: Prabu Sankar | F2: Total UnPlanned Leaves | G2: Total Planned Leaves | H2: Remarks
A3: OB-OP 8.5 Sprint 1 (29-Jan-26 to 12-Feb-2026) | B3: 0 | C3: 0 | D3: 0.5 | E3: 0 | F3: 0.5 | G3: 1 | H3: Karthi - Personal Emergency Mercy had a planned leave but she didnt take that
A4: OB-OP 8.5 Sprint 2 (12-Jan-26 to 26-Feb-2026) | B4: 0 | C4: 0 | D4: 0 | E4: 0 | F4: 0 | G4: 1 | H4: No unplanned leaves
A5: OB-OP 8.5 Sprint 3 (26-Feb-26 to 12-Mar-2026) | B5: 0 | C5: 1 | D5: 0 | E5: 0 | F5: 1 | G5: 1 | H5: Mercy - Daughter not well
A6: OB-OP 8.5 Sprint 4 (12-Mar-26 to 26-Mar-2026) | B6: 0 | C6: 0 | D6: 0.5 | E6: 0 | F6: 0.5 | G6: 0 | H6: Karthi - Not well, ear and nose problem
A7: OB-OP 8.6.0 Sprint 1 (26-Mar-26 to 09-Apr-2026) | B7: 0 | C7: 0 | D7: 0 | E7: 2 | F7: 2 | G7: 5.5 | H7: Prabu - Personal emergency Preethi - didnt take half day planned leave
A8: OB-OP 8.6.0 Sprint 2 (09-Apr-26 to 23-Apr-20260 | B8: 0 | C8: 1 | D8: 0 | E8: 0 | F8: 1 | G8: 1 | H8: Nivetha - Personal reason
A9: OB-OP 8.6.0 Sprint 3 (24-Apr-26 to 07-May-2026) | B9: 0 | C9: 0 | D9: 0 | E9: 0 | F9: 0 | G9: 0 | H9: No unplanned leaves
A10: OB-OP 8.6.0 Sprint 4 (07-May-26 to 21-May-2026) | B10: 0 | C10: 1 | D10: 0 | E10: 0 | F10: 1 | G10: 2 | H10: Nivetha - Not well

Sheet OB-OP 8.6.0 Sprint 4-Status
A1: S.No | B1: Application Name | C1: Sprint Start Date | D1: Sprint End Date | E1: Sprint | F1: Developer | G1: Story ID/Defect ID | H1: Description | I1: Status | J1: Estimated(hrs/sp) | K1: Actual(hrs/sp) | L1: Actual Hours Worklog | M1: Dev Start Date | N1: Dev End Date | O1: Unit testing | P1: Peer Tested By | Q1: Peer Tested Defects, if any | R1: Peer Reviewed By | S1: Peer Code Review Comments, if any | T1: PR Number/Link | U1: PR Created Date | V1: PR Approved Date | W1: Onsite Lead Code Review | X1: Code Review Comments, if any | Y1: Client Code Review | Z1: Approved Date | AA1: Code Review Comments, if any2 | AB1: Internal PO -POV Comments | AC1: Client PO -POV Comments | AD1: Comments | AE1: QA Comments
A2: 1 | B2: OnlineBidding | C2: 46149 | D2: 46163 | E2: OB-OP 8.6.0 Sprint 4 | F2: Nivetha - [TESTING ONLY] | G2: OB-3993 | H2: OB 8.6.0 CRT release | I2: Refinement | J2: 3
A3: 2 | B3: OnlineBidding | C3: 46149 | D3: 46163 | E3: OB-OP 8.6.0 Sprint 4 | F3: Preethi/Karthi | G3: OB-3985 | H3: OB Dashboard failing to open on Safari/iPad | I3: Completed | J3: 3 | M3: 46153 | N3: 46155 | O3: Done | P3: Nivetha | Q3: Nil | R3: Karthi | S3: Nil | T3: https://greatergiving.visualstudio.com/Greater%20Giving/_git/OnlineBidding/pullrequest/9555 | U3: 46155 | V3: 46156 | W3: Rajesh | X3: Nil | Y3: Joe | Z3: 46156 | AA3: Nil | AB3: Nil | AC3: Nil | AD3: Development not yet started, checking on to reproduce the issue using browser stack or some other options as we dont have iOS devices to check 5/8/2026 Trying to fix the issue and check after deployment - 5/11/2026 Fixed the issue and checked in safari browser in mac, but need to check in ipad also, but we dont have the device, so asked mobile QA's help and also will ping alice to test from her side in DEV itself - 5/12/2026 | AE3: DEV testing completed for safari browser alone, need to confirm in ipad as well - 5/12/2026
A4: 3 | B4: OnlineBidding | C4: 46149 | D4: 46163 | E4: OB-OP 8.6.0 Sprint 4 | F4: Preethi | G4: OB-3986 | H4: Bid Assistant - Need to log out | I4: Being Developed | J4: 2 | AD4: Checked with mobile team, but we couldn't find the option of logout bidder in their screen, checking other options as well - 5/8/2026 Checking with mobile team for reproducing the issue - 5/12/2026
A5: 4 | B5: OnlineBidding | C5: 46149 | D5: 46163 | E5: OB-OP 8.6.0 Sprint 4 | F5: Karthi | G5: OB-3962 | H5: Build Switch control between Individual and Household | I5: Being Developed | J5: 3 | M5: 46153 | O5: Done | AD5: Started to analyse and checking if we have all the APIs needed for this or need to check with GDON - 5/8/2026 Started with UI design changes - 5/11/2026 Made the code changes with mock data, as we need new/updated API from GDON side to fetch the bidder info like name, bidder etc if the given bidder key is household - 5/12/2026
A6: 5 | B6: OnlineBidding | C6: 46149 | D6: 46163 | E6: OB-OP 8.6.0 Sprint 4 | F6: Rajesh | G6: OP-2805 | H6: OP Transactions - PST to UTC conversion | I6: Completed | J6: 3 | M6: 46155 | N6: 46155 | O6: Done | P6: Preethi | Q6: Nil | R6: Preethi | S6: Nil | T6: https://greatergiving.visualstudio.com/Greater%20Giving/_git/OP/pullrequest/9451 | U6: 46155 | V6: 46156 | W6: Nil | X6: Nil | Y6: Joe | Z6: 46156 | AA6: Nil | AB6: Nil | AC6: Nil | AD6: Already shared the analysis done so far from our side to client, need to check the scenario in PROD once after Carlos is available 5/8/2026 As carlos was on PTO, rajesh will check with him today and try to reproduce in prod environment if possible - 5/12/2026
A7: 6 | B7: OnlineBidding | C7: 46149 | D7: 46163 | E7: OB-OP 8.6.0 Sprint 4 | F7: Preethi | G7: OB-3996 | H7: Add Checkout Link to OB | I7: Completed | J7: 5 | M7: 46153 | N7: 46154 | O7: Done | P7: Nivetha | Q7: Checkout button is not required for Donor disabled users | R7: Karthi | S7: Nil | T7: https://greatergiving.visualstudio.com/Greater%20Giving/_git/OnlineBidding/pullrequest/9557 | U7: 46154 | V7: 46156 | W7: Rajesh | X7: Nil | Y7: Joe | Z7: 46156 | AA7: Nil | AB7: Nil | AC7: Nil | AD7: Need to check with Rajesh, if only these changes need to be addressed in OB side for this ticket - 5/11/2026 Updated the code to show the button only for donor enabled projects, deployed in DEV for testing - 5/12/2026 | AE7: Dev testing completed 5/12/2026
A8: 7 | B8: OnlineBidding | C8: 46149 | D8: 46163 | E8: OB-OP 8.6.0 Sprint 4 - [SPIKE] | F8: Preethi | G8: OB-3995 | H8: Research Repeated Sent Email | I8: Being Developed | J8: 1 | M8: Its not development task, its an investigation ticket | AD8: Analysed and noted down the points related to sending email and shared to Joe as a document, he attached that document in the JIRA ticket - 5/11/2026 We gave the qquery, waiting for the result, as Sarah was on PTO yesterday, we might get the result today - 5/12/2026

Sheet OB-OP 8.6.0 Sprint 4-Defect
A1: S.No | B1: Sprint | C1: Story/Defect ID | D1: Parent Story | E1: Developer | F1: Issue Type | G1: Issue Description | H1: Priority | I1: Defect Source | J1: Type | K1: Status | L1: Root Cause Category | M1: Comments | N1: Found By | O1: RCA Comment

Sheet OB-OP 8.6.0 Sprint 3-Status
A1: S.No | B1: Application Name | C1: Sprint Start Date | D1: Sprint End Date | E1: Sprint | F1: Developer | G1: Story ID/Defect ID | H1: Description | I1: Status | J1: Estimated(hrs/sp) | K1: Actual(hrs/sp) | L1: Actual Hours Worklog | M1: Dev Start Date | N1: Dev End Date | O1: Unit testing | P1: Peer Tested By | Q1: Peer Tested Defects, if any | R1: Peer Reviewed By | S1: Peer Code Review Comments, if any | T1: PR Number/Link | U1: PR Created Date | V1: PR Approved Date | W1: Onsite Lead Code Review | X1: Code Review Comments, if any | Y1: Client Code Review | Z1: Approved Date | AA1: Code Review Comments, if any2 | AB1: Internal PO -POV Comments | AC1: Client PO -POV Comments | AD1: Comments | AE1: QA Comments
A2: 1 | B2: OnlineBidding | C2: 46135 | D2: 46149 | E2: OB-OP 8.6.0 Sprint 3 | F2: Preethi | G2: OB-3980 | H2: Update Featured Packages (Large) to match Package Browse | I2: Completed | J2: 2 | K2: 2 | M2: 46136 | N2: 46136 | O2: Done | P2: Nivetha | Q2: Nil | R2: Karthi | S2: Nil | T2: https://greatergiving.visualstudio.com/Greater%20Giving/_git/OnlineBidding/pullrequest/9506 | U2: 46139 | V2: 46140 | W2: Rajesh | X2: Nil | Y2: Joe | Z2: 46140 | AA2: Nil | AB2: Nil | AC2: Nil | AD2: Development and local testing completed 4/27/2026 | AE2: Dev testing completed 4/27/2026 TST testing completed 4/28/2026
A3: 2 | B3: OnlineBidding | C3: 46135 | D3: 46149 | E3: OB-OP 8.6.0 Sprint 3 | F3: Karthi | G3: OB-3964 | H3: Add Table # to slide out menu | I3: Completed | J3: 2 | K3: 2 | M3: 46139 | N3: 46148 | O3: Done | P3: Nivetha | Q3: Nil | R3: Preethi | S3: Nil | T3: https://greatergiving.visualstudio.com/Greater%20Giving/_git/OnlineBidding/pullrequest/9541 | U3: 46148 | V3: 46149 | W3: Nil | X3: Nil | Y3: Joe | Z3: 46149 | AA3: Nil | AB3: Nil | AC3: Nil | AD3: Checked with GGO team for the API - 4/27/2026 Starting with integrating existing GDON API - 4/28/2026 Having dependency on GDON API, they have to write new API, once done will resume the work on this, story has been flagged in JIRA, client also knows about this - 4/30/2026 Updated the coe by integreating GDON API, tested in local and DEV and created PR - 5/6/2026 Joe made few changes in this PR and deployed in DEV for our testing, we need to review and confirm this today, and he will complete the PR in our evening - 5/7/2026 | AE3: DEV testing completed 5/6/2026 TST testing completed 5/7/2026
A4: 3 | B4: OnlineBidding | C4: 46135 | D4: 46149 | E4: OB-OP 8.6.0 Sprint 3 | F4: Preethi | G4: OB-3983 | H4: Send Project Key with SignIn/Sign Up | I4: Completed | J4: 2 | K4: 2 | M4: 46139 | N4: 46140 | O4: Donr | P4: Nivetha | Q4: Nil | R4: Karthi | S4: Nil | T4: https://greatergiving.visualstudio.com/Greater%20Giving/_git/OnlineBidding/pullrequest/9511 | U4: 46142 | V4: 46147 | W4: Rajesh | X4: Nil | Y4: Joe | Z4: 46147 | AA4: Nil | AB4: Nil | AC4: Nil | AD4: Started analysis and shared with Rajesh - 4/27/2026 Started development and tested in local by hardcoding values - 4/28/2026 Rajesh approved the PR, waiting for Joe's approval - 5/4/2026 Need some changes in GDON API, so need to implement this in OB - 5/5/2026 | AE4: DEV testing completed 5/4/2026 TST testing completed 5/6/2026
A5: 4 | B5: OnlineBidding | C5: 46135 | D5: 46149 | E5: OB-OP 8.6.0 Sprint 3 | F5: Karthi | G5: OP-2809 | H5: OP - Synk remediation | I5: Completed | J5: 1 | K5: 1 | M5: Only testing needs to be done in this sprint | O5: Done | P5: Nivetha | Q5: Nil | R5: Preethi | S5: Nil | T5: https://greatergiving.visualstudio.com/Greater%20Giving/_git/OP/pullrequest/9497 | U5: 46139 | V5: 46140 | W5: Rajesh | X5: Nil | Y5: Joe | Z5: 46140 | AA5: Nil | AB5: Nil | AC5: Nil | AD5: Local and DEV testing completed 4/27/2026 Defect was added for not able to create project website, worked on that and will be creating PR today - 4/30/2026 Alice tested the sub defect and closed it and said final regression alone pending for this story She was on unplanned PTO on may 1st, so it will be closed today - 5/4/2026 | AE5: Dev testing completed 4/27/2026 TST testing completed 4/28/2026
A6: 5 | B6: OnlineBidding | C6: 46135 | D6: 46149 | E6: OB-OP 8.6.0 Sprint 3 | F6: Preethi/Rajesh | G6: OP-2805 | H6: OP Transactions - PST to UTC conversion | I6: Being Developed | J6: 3 | AD6: Need help from Prabu''s end so kept on hold till he is back, trying to put multiple transactions today and check one more time in TST - 5/4/2026 Rajesh will try to check this in prod and let us know today if possible - 5/5/2026 This will be carry forwarded to next sprint as we cant reproduce this in TST and need to check in production with the help of carlos. Client is also aware of this - 5/6/2026
A7: 6 | B7: OnlineBidding | C7: 46135 | D7: 46149 | E7: OB-OP 8.6.0 Sprint 3 | F7: Preethi/Karthi | G7: OP-2811 - [Defect] | H7: Creating Project Websites Always Fails | I7: Completed | M7: 46141 | N7: 46141 | O7: Done | P7: Karthi | Q7: Nil | R7: Karthi | S7: Nil | T7: https://greatergiving.visualstudio.com/Greater%20Giving/_git/OP/pullrequest/9518 | U7: 46142 | V7: 46142 | W7: Rajesh | X7: NIl | Y7: Joe | Z7: 46142 | AA7: Nil | AB7: Nil | AC7: Nil | AD7: Fixed the bug and tested in local 4/29/2026 Tested in DEV - 4/30/2026 | AE7: TST testing completed 5/4/2026
A8: 7 | B8: OnlineBidding | C8: 46135 | D8: 46149 | E8: OB-OP 8.6.0 Sprint 3 - [Stretch] | F8: Preethi | G8: OB-3990 | H8: OB Filters - Apply button function is not working after when we see “No Packages found.” and then make changes to the filters | I8: Completed | J8: 3 | K8: 3 | M8: 46142 | N8: 46142 | O8: Done | P8: Nivetha | Q8: Nil | R8: Karthi | S8: Nil | T8: https://greatergiving.visualstudio.com/Greater%20Giving/_git/OnlineBidding/pullrequest/9528 | U8: 46146 | V8: 46147 | W8: Rajesh | X8: Nil | Y8: Joe | Z8: 46147 | AA8: Nil | AB8: Nil | AC8: Nil | AD8: Fixed the issue in local and testing multiple scenarios related to filter and search combination - 4/30/2026 | AE8: Devtesting completed 5/4/2026 TST testing completed 5/6/2026
A9: 8 | B9: OnlineBidding | C9: 46135 | D9: 46149 | E9: OB-OP 8.6.0 Sprint 3 - [Stretch] | F9: Preethi | G9: OB-3987 | H9: Update OB Footer to not be hardcoded date | I9: Completed | J9: 1 | K9: 1 | M9: 46142 | N9: 46142 | O9: Done | P9: Preethi | Q9: Nil | R9: Karthi | S9: Nil | T9: https://greatergiving.visualstudio.com/Greater%20Giving/_git/OnlineBidding/pullrequest/9523 | U9: 46142 | V9: 46143 | W9: Rajesh | X9: Nil | Y9: Joe | Z9: 46143 | AA9: Nil | AB9: Nil | AC9: Nil | AD9: Updated the code and tested in local 4/30/2026 | AE9: TST testing completed 5/4/2026
A10: 9 | B10: OnlineBidding | C10: 46135 | D10: 46149 | E10: OB-OP 8.6.0 Sprint 3 - [Stretch] | F10: Preethi | G10: OB-3992 | H10: SMS Null Delivery Status | I10: Completed | J10: 1 | K10: 1 | M10: This is not development ticket, its investigation ticket | AD10: This is an investigation ticket, so no PR has been raised for this, analysed on the points given from PO and shared the analysis along with screenshot and added it in JIRA comments as well. Joe will have a look on it and it will be closed today - 5/7/2026 | AE10: No testing efforts needed for this ticket
A11: 10 | B11: OnlineBidding | C11: 46135 | D11: 46149 | E11: OB-OP 8.6.0 Sprint 3 | F11: Rajesh | G11: OP-2810 | H11: Determine production use case | I11: Completed | J11: 2 | K11: 2 | M11: This is not development ticket, its investigation ticket | AD11: This is an investigation ticket, so no PR has been raised for this, analysed on the points given from PO and shared the analysis along with screenshot and added it in JIRA comments

Sheet OB-OP 8.6.0 Sprint 3-Defect 
A1: S.No | B1: Sprint | C1: Story/Defect ID | D1: Parent Story | E1: Developer | F1: Issue Type | G1: Issue Description | H1: Priority | I1: Defect Source | J1: Type | K1: Status | L1: Root Cause Category | M1: Comments | N1: Found By | O1: RCA Comment
B2: OB-OP 8.6.0 Sprint 3 | C2: OP-2811 | D2: OP-2809 | E2: Preethi | F2: Defect | G2: Creating Project Websites Always Fails | H2: Significant | I2: Manual | J2: Internal | K2: Closed | L2: Development | M2: Created many pages and checked but new project website got failed | N2: Alice | O2: Checked all pages in OP as well as GGO to OP flow, but missed to check in the new project by creating new project website
B3: OB-OP 8.6.0 Sprint 3 | C3: OB-3990 | D3: Regression | E3: Preethi | F3: Defect | G3: OB Filters - Apply button function is not working after when we see “No Packages found.” and then make changes to the filters | H3: Significant | I3: Manual | J3: Internal | K3: Closed | L3: Existing_Issues | M3: This was broken as part of doing something else as we were working on mutltiple scenarios of filter and search | N3: Nivetha | O3: This was broken as part of doing something else as we were working on mutltiple scenarios of filter and search

Sheet OB-OP 8.6.0 Sprint 2-Status
A1: S.No | B1: Application Name | C1: Sprint Start Date | D1: Sprint End Date | E1: Sprint | F1: Developer | G1: Story ID/Defect ID | H1: Description | I1: Status | J1: Estimated(hrs/sp) | K1: Actual(hrs/sp) | L1: Actual Hours Worklog | M1: Dev Start Date | N1: Dev End Date | O1: Unit testing | P1: Peer Tested By | Q1: Peer Tested Defects, if any | R1: Peer Reviewed By | S1: Peer Code Review Comments, if any | T1: PR Number/Link | U1: PR Created Date | V1: PR Approved Date | W1: Onsite Lead Code Review | X1: Code Review Comments, if any | Y1: Client Code Review | Z1: Approved Date | AA1: Code Review Comments, if any2 | AB1: Internal PO -POV Comments | AC1: Client PO -POV Comments | AD1: Comments | AE1: QA Comments
A2: 1 | B2: OnlineBidding | C2: 46121 | D2: 46135 | E2: OB-OP 8.6.0 Sprint 2 | F2: Karthi/Preethi/Rajesh | G2: OP-2805 | H2: OP Transactions - PST to UTC conversion | I2: Being Developed | J2: 3 | AD2: Need Rajesh's help on this to test thorugh TST DB, so will be doing this in next week - 4/10/2026 Couldn't find the place as mentioned in the AC, so need Prabu's help as well on this, hence this will be carry forwarded 4/23/2026
A3: 2 | B3: OnlineBidding | C3: 46121 | D3: 46135 | E3: OB-OP 8.6.0 Sprint 2 | F3: Preethi | G3: OB-3978 | H3: Fix: Bidder Link appearing as anonymous | I3: Completed | J3: 2 | K3: 2 | M3: 46122 | N3: 46122 | O3: Done | P3: Nivetha | Q3: Nil | R3: Karthi | S3: Nil | T3: https://greatergiving.visualstudio.com/Greater%20Giving/_git/OnlineBidding/pullrequest/9458 | U3: 46122 | V3: 46123 | W3: Rajesh | X3: Nil | Y3: Joe | Z3: 46123 | AA3: Nil | AB3: Nil | AC3: Nil | AD3: Completed development and tested in local, Deployed in DEV for testing 4/10/2026 | AE3: Dev testing completed 4/10/2026 TST testing completed 4/13/2026
A4: 3 | B4: OnlineBidding | C4: 46121 | D4: 46135 | E4: OB-OP 8.6.0 Sprint 2 | F4: Preethi | G4: OB-3974 | H4: Outbid texts no longer go to that specific package | I4: Completed | J4: 3 | K4: 3 | M4: 46122 | N4: 46122 | O4: Done | P4: Nivetha | Q4: Nil | R4: Karthi | S4: Nil | T4: https://greatergiving.visualstudio.com/Greater%20Giving/_git/OnlineBidding/pullrequest/9468 | U4: 46126 | V4: 46127 | W4: Rajesh | X4: Nil | Y4: Joe | Z4: 46127 | AA4: Nil | AB4: Nil | AC4: Nil | AD4: Completed development, not getting mail in DEV so deployment cant be done for testing 4/10/2026 Mail received and checked in DEV and created PR - 4/14/2026 | AE4: Dev testing completed 4/15/2026 TST testing completed 4/16/2026
A5: 4 | B5: OnlineBidding | C5: 46121 | D5: 46135 | E5: OB-OP 8.6.0 Sprint 2 | F5: Karthi | G5: OP-2809 | H5: OP - Synk remediation | I5: Being Developed | J5: 3 | M5: 46122 | AD5: Started analysis Fixing the issues one by one 4/17/2026 Tested in local, except pages option rest all working today, 4/22/2026 Deployed in DEV for testing today, once all pages are working, then PR will be sent out today 4/23/2026
A6: 5 | B6: OnlineBidding | C6: 46121 | D6: 46135 | E6: OB-OP 8.6.0 Sprint 2 | F6: Preethi | G6: OB-3977 | H6: OB - SNYK remediation | I6: Completed | J6: 3 | K6: 3 | M6: 46126 | N6: 46129 | O6: Done | P6: Nivetha | Q6: Nil | R6: Karthi | S6: Nil | T6: https://greatergiving.visualstudio.com/Greater%20Giving/_git/OnlineBidding/pullrequest/9484 | U6: 46129 | V6: 46130 | W6: Rajesh | X6: Nil | Y6: Joe | Z6: 46130 | AA6: Nil | AB6: Nil | AC6: Nil | AD6: Trying to fix the sync points 4/17/2026 Updated the points and deployed in DEV for testing, for other points shared the reason 4/17/2026 | AE6: Dev testing completed 4/17/2026 TST testing completed 4/21/2026
A7: 6 | B7: OnlineBidding | C7: 46121 | D7: 46135 | E7: OB-OP 8.6.0 Sprint 2 - [Stretch] | F7: Preethi | G7: OB-3984 | H7: Featured Packages - Should follow order of Packages in OB Settings | I7: Completed | J7: 2 | K7: 2 | M7: 46133 | N7: 46133 | O7: Done | P7: Nivetha | Q7: Nil | R7: Karthi | S7: Nil | T7: https://greatergiving.visualstudio.com/Greater%20Giving/_git/OnlineBidding/pullrequest/9492 | U7: 46133 | V7: 46134 | W7: Rajesh | X7: Nil | Y7: Joe | Z7: 46134 | AA7: Nil | AB7: Nil | AC7: Nil | AD7: Development and local testing completed 4/21/2026 | AE7: Dev testing completed 4/21/2026
A8: 7 | B8: OnlineBidding | C8: 46121 | D8: 46135 | E8: OB-OP 8.6.0 Sprint 2 - [Stretch] | F8: Preethi | G8: OB-3965 | H8: Swap Apply and Clear in filters area | I8: Completed | J8: 2 | K8: 2 | M8: 46134 | N8: 46134 | O8: Done | P8: Nivetha | Q8: Nil | R8: Karthi | S8: Nil | T8: https://dev.azure.com/greatergiving/Greater%20Giving/_git/OnlineBidding/pullrequest/9498 | U8: 46134 | V8: 46135 | W8: Rajesh | X8: Nil | Y8: Joe | Z8: 46135 | AA8: Nil | AB8: Nil | AC8: Nil | AD8: Development and local testing completed 4/22/2026 | AE8: Dev testing completed 4/22/2026

Sheet OB-OP 8.6.0 Sprint 2-Defect
A1: S.No | B1: Sprint | C1: Story/Defect ID | D1: Parent Story | E1: Developer | F1: Issue Type | G1: Issue Description | H1: Priority | I1: Defect Source | J1: Type | K1: Status | L1: Root Cause Category | M1: Comments | N1: Found By | O1: RCA Comment
B2: OB-OP 8.6.0 Sprint 2 | C2: OB-3978 | E2: Preethi | F2: Defect | G2: Fix: Bidder Link appearing as anonymous | H2: Significant | I2: Manual | J2: External | K2: Closed | L2: Development | M2: When no package is created, bidder info is not seen | N2: Client | O2: We have written the code to call bidder only after the success of package API, so when no package was there, bidder API wasn't called
B3: OB-OP 8.6.0 Sprint 2 | C3: OB-3974 | E3: Preethi | F3: Defect | G3: Outbid texts no longer go to that specific package | H3: Significant | I3: Manual | J3: External | K3: Closed | L3: Development | M3: We have changed the routes for new UI and missed to test email scenarios | N3: Client | O3: We have changed the routes for new UI and missed to test email scenarios

Sheet OB-OP 8.6.0 Sprint 1-Status
A1: S.No | B1: Application Name | C1: Sprint Start Date | D1: Sprint End Date | E1: Sprint | F1: Developer | G1: Story ID/Defect ID | H1: Description | I1: Status | J1: Estimated(hrs/sp) | K1: Actual(hrs/sp) | L1: Actual Hours Worklog | M1: Dev Start Date | N1: Dev End Date | O1: Unit testing | P1: Peer Tested By | Q1: Peer Tested Defects, if any | R1: Peer Reviewed By | S1: Peer Code Review Comments, if any | T1: PR Number/Link | U1: PR Created Date | V1: PR Approved Date | W1: Onsite Lead Code Review | X1: Code Review Comments, if any | Y1: Client Code Review | Z1: Approved Date | AA1: Code Review Comments, if any2 | AB1: Internal PO -POV Comments | AC1: Client PO -POV Comments | AD1: Comments | AE1: QA Comments
A2: 1 | B2: OnlineBidding | C2: 46107 | D2: 46121 | E2: OB-OP 8.6.0 Sprint 1 | F2: Prabu | G2: OP-2807 | H2: Update OP splash page | I2: Completed | J2: 2 | K2: 2 | L2: 71.75 | M2: 46108 | N2: 46120 | O2: Done | P2: Nivetha | Q2: Nil | R2: Preethi | S2: Nil | T2: No PR, only SQL queries, those are updated in the JIRA ticket | U2: Nil | V2: Nil | W2: Rajesh | X2: Nil | Y2: Joe | Z2: Nil | AA2: Nil | AB2: Nil | AC2: Nil | AD2: Need to find an approach to update the css 3/27/2026 Found the table in DB and updated in local, when trying to update in DEV , getting error before login page itself, analysing on that - 4/7/2026 | AE2: Tested in TST 4/8/2026 Tested in TST 4/9/2026
A3: 2 | B3: OnlineBidding | C3: 46107 | D3: 46121 | E3: OB-OP 8.6.0 Sprint 1 | F3: Preethi | G3: OB-3968 | H3: OB - Read Donation Settings | I3: Completed | J3: 3 | K3: 3 | L3: 61.75 | M3: 46108 | N3: 46113 | O3: Done | P3: Nivetha | Q3: Nil | R3: Karthi | S3: Nil | T3: https://greatergiving.visualstudio.com/Greater%20Giving/_git/OnlineBidding/pullrequest/9421 | U3: 46113 | V3: 46115 | W3: Prabu | X3: Nil | Y3: Joe | Z3: 46115 | AA3: Nil | AB3: Nil | AC3: Nil | AD3: Started development, added migration script to add new column and updated the condition to show/hide based on the new parameter 3/27/2026 Updated the code by refactoring few approaches 3/30/2026 Prabu suggested to make 2 methods into single method, updated that and tested in local as well as in DEV 4/1/2026 | AE3: Tested in TST 4/3/2026
A4: 3 | B4: OnlineBidding | C4: 46107 | D4: 46121 | E4: OB-OP 8.6.0 Sprint 1 | F4: Karthi/Preethi | G4: OP-2805 | H4: OP Transactions - PST to UTC conversion | I4: Being Developed | J4: 2 | L4: 46 | M4: 46111 | AD4: Started analysis, trying to find the location 3/30/2026 Still analysing to find the place from where the changes are being happening, as far we are saving the value from PAPI to OP,so need to confirm in PAPI as well - 4/7/2026
A5: 4 | B5: OnlineBidding | C5: 46107 | D5: 46121 | E5: OB-OP 8.6.0 Sprint 1 - [Stretch] | F5: Preethi | G5: OB-3969 | H5: UI Artifact around "Show Item Donor Name" selection | I5: Completed | J5: 1 | K5: 1 | L5: 16.75 | M5: 46114 | N5: 46114 | O5: Done | P5: Nivetha | Q5: Nil | R5: Karthi | S5: Nil | T5: https://greatergiving.visualstudio.com/Greater%20Giving/_git/OnlineBidding/pullrequest/9428 | U5: 46115 | V5: 46119 | W5: Prabu | X5: Nil | Y5: Joe | Z5: 46119 | AA5: Nil | AB5: Nil | AC5: Nil | AD5: Development and local testing completed 4/3/2026 Tested in DEV and created PR - 4/3/2026 | AE5: Tested in DEV 4/3/2026 Tested in TST 4/7/2026
A6: 5 | B6: OnlineBidding | C6: 46107 | D6: 46121 | E6: OB-OP 8.6.0 Sprint 1 - [Stretch] | F6: Preethi | G6: OB-3954 | H6: Missing Font resources | I6: Completed | J6: 1 | K6: 1 | L6: 18.5 | M6: 46115 | N6: 46118 | O6: Done | P6: Nivetha | Q6: Nil | R6: Karthi | S6: Nil | T6: https://greatergiving.visualstudio.com/Greater%20Giving/_git/OnlineBidding/pullrequest/9435 | U6: 46119 | V6: 46119 | W6: Prabu | X6: Nil | Y6: Joe | Z6: 46119 | AA6: Nil | AB6: Nil | AC6: Nil | AD6: Updated the code, when checked in DEV, for me and karthi console error is not coming, but for nivetha its coming, so rechecking on that 4/6/2026 | AE6: Tested in DEV - 4/6/2026 Tested in TST - 4/6/2026

Sheet OB-OP 8.6.0 Sprint 1-Defect
A1: S.No | B1: Sprint | C1: Story/Defect ID | D1: Parent Story | E1: Developer | F1: Issue Type | G1: Issue Description | H1: Priority | I1: Defect Source | J1: Type | K1: Status | L1: Root Cause Category | M1: Comments | N1: Found By | O1: RCA Comment
B2: OB-OP 8.6.0 Sprint 1 - [Stretch] | C2: OB-3969 | E2: Preethi | F2: Defect | G2: UI Artifact around "Show Item Donor Name" selection | H2: Significant | I2: Manual | J2: External | K2: Closed | L2: Requirements | M2: We have already added this point in the observation sheet and shared with derek | N2: Client | O2: We already found the missing things in new UI and shared the document with PO, they missed to create story for that

Sheet OB-OP 8.5 Sprint 4-Status
A1: S.No | B1: Application Name | C1: Sprint Start Date | D1: Sprint End Date | E1: Sprint | F1: Developer | G1: Story ID/Defect ID | H1: Description | I1: Status | J1: Estimated(hrs/sp) | K1: Actual(hrs/sp) | L1: Actual Hours Worklog | M1: Dev Start Date | N1: Dev End Date | O1: Unit testing | P1: Peer Tested By | Q1: Peer Tested Defects, if any | R1: Peer Reviewed By | S1: Peer Code Review Comments, if any | T1: PR Number/Link | U1: PR Created Date | V1: PR Approved Date | W1: Onsite Lead Code Review | X1: Code Review Comments, if any | Y1: Client Code Review | Z1: Approved Date | AA1: Code Review Comments, if any2 | AB1: Internal PO -POV Comments | AC1: Client PO -POV Comments | AD1: Comments | AE1: QA Comments
A2: 1 | B2: OnlineBidding | C2: 46093 | D2: 46107 | E2: OB-OP 8.5 Sprint 4 | F2: Karthi | G2: OP-2803 | H2: Add link to privacy policy and terms of use on OP login | I2: Completed | J2: 1 | K2: 1 | L2: 11.75 | M2: Development done in last sprint, only testing in this sprint | N2: Development done in last sprint, only testing in this sprint | O2: Done | P2: Mercy | Q2: Nil | R2: Preethi | S2: Nil | T2: https://greatergiving.visualstudio.com/Greater%20Giving/_git/OP/pullrequest/9346 | U2: 46093 | V2: 46100 | W2: Prabu | X2: Nil | Y2: Joe | Z2: 46100 | AA2: Nil | AB2: Nil | AC2: Nil | AD2: Updated the HTML in azure but seeing console error and we cant able to login to OP after that, since OB CRT release is priority now, it will be done after that 3/13/2026 DEV testing completed 3/20/2026 | AE2: TST testing completed 3/20/2026
A3: 2 | B3: OnlineBidding | C3: 46093 | D3: 46107 | E3: OB-OP 8.5 Sprint 4 | F3: Karthi | G3: OP-2807 | H3: Update OP splash page | I3: Being Developed | J3: 2 | L3: 66.75 | AD3: Updated the splash page in DEV and TST but still the changes didnt get reflected, this will be done after OB CRT release 3/13/2026 Found a table from where the content was coming in UI, tried updating the content and it got worked, but the style changes are not able to be added inside the html content 3/26/2026
A4: 3 | B4: OnlineBidding | C4: 46093 | D4: 46107 | E4: OB-OP 8.5 Sprint 4 | F4: Preethi | G4: OP-2799 | H4: RSVP Receipts showing data tags for certain email clients | I4: Completed | J4: 3 | K4: 3 | L4: 33 | M4: Development done in last sprint, only testing in this sprint | N4: Development done in last sprint, only testing in this sprint | O4: Done | P4: Mercy | Q4: Nil | R4: Karthi | S4: Nil | T4: https://greatergiving.visualstudio.com/Greater%20Giving/_git/OP/pullrequest/9357 | U4: 46101 | V4: 46105 | W4: Prabu | X4: Nil | Y4: Joe | Z4: 46105 | AA4: Nil | AB4: Nil | AC4: Nil | AD4: Not receiving emails in DEV, need to check the email queue in server, but this can be done after OB CRT release as that is the priority for now 3/13/2026 Mail is receiving now, tested in DEV 3/20/2026 | AE4: DEV testing in progress 3/20/2026
A5: 4 | B5: OnlineBidding | C5: 46093 | D5: 46107 | E5: OB-OP 8.5 Sprint 4 | F5: Karthi | G5: OB-3951 | H5: Ensure Package Images are consistent | I5: Completed | J5: 3 | K5: 3 | L5: 41.25 | M5: 46094 | N5: 46100 | O5: Done | P5: Mercy | Q5: 1. overlapping with the banner is seen for an image 2. In mobile view some images seems to be stretched | R5: Preethi | S5: Nil | T5: https://greatergiving.visualstudio.com/Greater%20Giving/_git/OnlineBidding/pullrequest/9391 | U5: 46100 | V5: 46100 | W5: Prabu | X5: Nil | Y5: Joe | Z5: 46100 | AA5: Nil | AB5: Nil | AC5: Nil | AD5: Checking the images in browse, detail, deatured packages and comparing the codes 3/13/2026 Updated the code for browse, detail pages, checked for featured packages 3/16/2026 | AE5: Tested in TST 3/18/2026
A6: 5 | B6: OnlineBidding | C6: 46093 | D6: 46107 | E6: OB-OP 8.5 Sprint 4 | F6: Prabu | G6: OB-3956 | H6: Terms of Use and Privacy Policy Update | I6: Completed | J6: 1 | K6: 1 | L6: 5.75 | M6: 46098 | N6: 46098 | O6: Done | P6: Prabu | Q6: Nil | R6: Nil | S6: Nil | T6: https://greatergiving.visualstudio.com/Greater%20Giving/_git/OnlineBidding/pullrequest/9386 | U6: 46099 | V6: 46099 | W6: Nil | X6: Nil | Y6: Joe | Z6: 46099 | AA6: Nil | AB6: Nil | AC6: Nil | AD6: Development completed and local testing done 3/17/2026 | AE6: Tested in TST 3/18/2026
A7: 6 | B7: OnlineBidding | C7: 46093 | D7: 46107 | E7: OB-OP 8.5 Sprint 4 | F7: Preethi | G7: OB-3957 | H7: Closed packages w/o bids still show bid buttons | I7: Completed | J7: 3 | K7: 3 | L7: 17.5 | M7: 46094 | N7: 46099 | O7: Done | P7: Mercy | Q7: Nil | R7: Karthi | S7: Nil | T7: https://greatergiving.visualstudio.com/Greater%20Giving/_git/OnlineBidding/pullrequest/9378 | U7: 46098 | V7: 46100 | W7: Prabu | X7: Nil | Y7: Joe | Z7: 46100 | AA7: Nil | AB7: Nil | AC7: Nil | AD7: Tried to reproduce by pointing DEV and TST and adding console logs, but working as expected. Added some more safer checks in code to not to display buttons and timer 3/13/2026 Updated the code related to timezone issue and deployed in DEV for testing 3/16/2026 Both OB-3960 and OB-3957 have the same fix so will be raising the same PR | AE7: Trying to reproduce the issue in multiple environments 3/13/2026 Dev testing completed 3/17/2026 Dev testing completed 3/18/2026 TST testing completed 3/20/2026
A8: 7 | B8: OnlineBidding | C8: 46093 | D8: 46107 | E8: OB-OP 8.5 Sprint 4 | F8: Mercy | G8: OB-3959 | H8: OB 8.5.0 Release to CRT. | I8: Completed | J8: 3 | K8: 3 | L8: 53 | AE8: Deployed in CRT and testing started 3/20/2026
A9: 8 | B9: OnlineBidding | C9: 46093 | D9: 46107 | E9: OB-OP 8.5 Sprint 4 - [STRETCH] | F9: Preethi | G9: OB-3960 | H9: Ensure Ob Start Times are using pre-UX logic | I9: Completed | J9: 2 | K9: 2 | L9: 34.25 | M9: 46097 | N9: 46099 | O9: Done | P9: Mercy | Q9: Nil | R9: Karthi | S9: Nil | T9: https://greatergiving.visualstudio.com/Greater%20Giving/_git/OnlineBidding/pullrequest/9378 | U9: 46098 | V9: 46100 | W9: Prabu | X9: Nil | Y9: Joe | Z9: 46100 | AA9: Nil | AB9: Nil | AC9: Nil | AD9: Updated the code, checked with different timezones, we have 2 clarification, need to check with PO 3/16/2026 Worked on the 2 points after confirming from PO, deployed in DEV for testing 3/17/2026 Worked on the point suggested by prabu regarding time interval, updated that and deployed in DEV for testing 3/18/2026 | AE9: Dev testing completed for timezone issue and shared the result with prabu 3/16/2026 TST testing completed 3/18/2026
A10: 9 | B10: OnlineBidding | C10: 46093 | D10: 46107 | E10: OB-OP 8.5 Sprint 4 - [STRETCH] | F10: Preethi | G10: OB-3955 | H10: Donation Bar Updates | I10: Completed | J10: 3 | K10: 3 | L10: 18.75 | M10: 46100 | N10: 46100 | O10: Done | P10: Mercy | Q10: Nil | R10: Karthi | S10: Nil | T10: https://greatergiving.visualstudio.com/Greater%20Giving/_git/OnlineBidding/pullrequest/9388 | U10: 46100 | V10: 46100 | W10: Prabu | X10: Nil | Y10: Joe | Z10: 46100 | AA10: Nil | AB10: Nil | AC10: Nil | AD10: Development completed and local testing done, Deployed in DEV 3/19/2026 | AE10: Dev testing completed 3/19/2026 TST testing completed 3/20/2026
A11: 10 | B11: OnlineBidding | C11: 46093 | D11: 46107 | E11: OB-OP 8.5 Sprint 4 - [STRETCH] | F11: Nivetha | G11: OB-3967 | H11: Set Up & Knowledge Transfer | I11: Completed | J11: 2 | K11: 2 | L11: 44

Sheet OB-OP 8.5 Sprint 4-Defect
A1: S.No | B1: Sprint | C1: Story/Defect ID | D1: Parent Story | E1: Developer | F1: Issue Type | G1: Issue Description | H1: Priority | I1: Defect Source | J1: Type | K1: Status | L1: Root Cause Category | M1: Comments | N1: Found By | O1: RCA Comment
B2: OB-OP 8.5 Sprint 4 | C2: OB-3956 | E2: Prabu | F2: Defect | G2: Terms of Use and Privacy Policy Update | H2: Significant | I2: Manual | J2: External | K2: Closed | L2: Requirements | M2: We have added this point in our regression observation sheet and shared with derek before itself | N2: Derek | O2: Its not a defect, no requirement was given to update the url for those links
B3: OB-OP 8.5 Sprint 4 | C3: OB-3957 | E3: Preethi | F3: Defect | G3: Closed packages w/o bids still show bid buttons | H3: Significant | I3: Manual | J3: External | K3: Inprogress | L3: Development | M3: Time calculation was based on current timezone in which the source code was deployed | N3: Rachelle | O3: Missed to add the time coversion code based on the project timezone which was implemented in old UI

Sheet OB-OP 8.5 Sprint 3-Status
A1: S.No | B1: Application Name | C1: Sprint Start Date | D1: Sprint End Date | E1: Sprint | F1: Developer | G1: Story ID/Defect ID | H1: Description | I1: Status | J1: Estimated(hrs/sp) | K1: Actual(hrs/sp) | L1: Actual Hours Worklog | M1: Dev Start Date | N1: Dev End Date | O1: Unit testing | P1: Peer Tested By | Q1: Peer Tested Defects, if any | R1: Peer Reviewed By | S1: Peer Code Review Comments, if any | T1: PR Number/Link | U1: PR Created Date | V1: PR Approved Date | W1: Onsite Lead Code Review | X1: Code Review Comments, if any | Y1: Client Code Review | Z1: Approved Date | AA1: Code Review Comments, if any2 | AB1: Internal PO -POV Comments | AC1: Client PO -POV Comments | AD1: Comments | AE1: QA Comments
A2: 1 | B2: OnlineBidding | C2: 46079 | D2: 46093 | E2: OB-OP 8.5 Sprint 3 | F2: Mercy - [TESTING ONLY] | G2: OB-3913 | H2: Release and Test OB 8.4.0 to CRT | I2: Completed | J2: 5 | K2: 5 | L2: 67.25 | M2: Nil | N2: Nil | O2: Nil | P2: Nil | Q2: Nil | R2: Nil | S2: Nil | T2: Nil | U2: Nil | V2: Nil | W2: Nil | X2: Nil | Y2: Nil | Z2: Nil | AA2: Nil | AB2: Nil | AC2: Nil | AD2: Release to CRT is completed 3/3/2026 | AE2: Testing in CRT is in progress 3/3/2026 CRT testing completed 3/4/2026
A3: 2 | B3: OnlineBidding | C3: 46079 | D3: 46093 | E3: OB-OP 8.5 Sprint 3 | F3: Preethi/Karthi | G3: OB-3911 | H3: Using the back button should show full search results | I3: Completed | J3: 5 | K3: 5 | L3: 24.25 | M3: 46080 | N3: 46083 | O3: Done | P3: Mercy | Q3: Nil | R3: Karthi/Preethi | S3: Nil | T3: https://greatergiving.visualstudio.com/Greater%20Giving/_git/OnlineBidding/pullrequest/9328 | U3: 46083 | V3: 46083 | W3: Prabu | X3: Nil | Y3: Joe | Z3: 46083 | AA3: Nil | AB3: Nil | AC3: Nil | AD3: Took cut branch and updated the code for making ALL/Home icon click also to retain the filter and search functionality 2/27/2026 Made some more changes related to reducing the API calls and adding X icon in search are added today as part of this story changes for CRT release 3/2/2026 | AE3: Dev testing completed 3/2/2026 CRT testing completed 3/3/2026
A4: 3 | B4: OnlineBidding | C4: 46079 | D4: 46093 | E4: OB-OP 8.5 Sprint 3 | F4: Preethi | G4: OB-3947 | H4: Sponsor Image not always centered on sponsor scroll with single sponsor | I4: Completed | L4: 4 | M4: 46080 | N4: 46080 | O4: Done | P4: Mercy | Q4: Nil | R4: Nil | S4: Nil | T4: https://greatergiving.visualstudio.com/Greater%20Giving/_git/OnlineBidding/pullrequest/9329 | U4: 46080 | V4: 46108 | W4: Prabu | X4: Nil | Y4: Joe | Z4: 46080 | AA4: Nil | AB4: Nil | AC4: Nil | AD4: Development completed in local, deployed in DEV for testing 2/27/2026 | AE4: DEV testing completed 2/27/2026 CRT testing completed 3/3/2026
A5: 4 | B5: OnlineBidding | C5: 46079 | D5: 46093 | E5: OB-OP 8.5 Sprint 3 | F5: Preethi/Prabu | G5: OB-3948 | H5: Searching for a package by pkg # does not have a UX route to all packages | I5: Completed | L5: 6 | M5: 46080 | N5: 46080 | O5: Done | P5: Mercy | Q5: Nil | R5: Nil | S5: Nil | T5: https://greatergiving.visualstudio.com/Greater%20Giving/_git/OnlineBidding/pullrequest/9328 | U5: 46080 | V5: 46083 | W5: Prabu | X5: Nil | Y5: Joe | Z5: 46083 | AA5: Nil | AB5: Nil | AC5: Nil | AD5: Development completed in local, deployed in DEV for testing 2/27/2026 Will be sharing the PR of OB-3911 as most of the scenarios for this are already handled in that story 3/2/2026 | AE5: DEV testing completed 2/27/2026 CRT testing completed 3/3/2026
A6: 5 | B6: OnlineBidding | C6: 46079 | D6: 46093 | E6: OB-OP 8.5 Sprint 3 | F6: Preethi | G6: OB-3949 | H6: Mobile should match Desktop in regards to Hamburger Menu | I6: Completed | L6: 4.5 | M6: 46080 | N6: 46080 | O6: Done | P6: Mercy | Q6: Nil | R6: Nil | S6: Nil | T6: https://greatergiving.visualstudio.com/Greater%20Giving/_git/OnlineBidding/pullrequest/9330 | U6: 46080 | V6: 46080 | W6: Prabu | X6: Nil | Y6: Joe | Z6: 46080 | AA6: Nil | AB6: Nil | AC6: Nil | AD6: Development completed in local, deployed in DEV for testing 2/27/2026 | AE6: DEV testing completed 2/27/2026 CRT testing completed 3/3/2026
A7: 6 | B7: OnlineBidding | C7: 46079 | D7: 46093 | E7: OB-OP 8.5 Sprint 3 | F7: Prabu | G7: OB-3953 | H7: Clean up console logging and missing font resources | I7: Completed | J7: 1 | K7: 1 | L7: 5.75 | M7: 46080 | N7: 46083 | O7: Done | P7: Prabu | Q7: Nil | R7: Nil | S7: Nil | T7: https://greatergiving.visualstudio.com/Greater%20Giving/_git/OnlineBidding/pullrequest/9336 | U7: 46083 | V7: 46083 | W7: Nil | X7: Nil | Y7: Joe | Z7: 46083 | AA7: Nil | AB7: Nil | AC7: Nil | AD7: Removed logs and verified 3/2/2026 | AE7: CRT testing completed 3/3/2026
A8: 7 | B8: OnlineBidding | C8: 46079 | D8: 46093 | E8: OB-OP 8.5 Sprint 3 - [STRETCH] | F8: Karthi | G8: OP-2803 | H8: Add link to privacy policy and terms of use on OP login | I8: Peer Review | J8: 1 | L8: 36 | M8: 46085 | AD8: Added the links in html file and shared the screenshot of the changes 3/4/2026 Need to check the way to deploy this in DEV - kept hold till 3/11/2026 Deployed the changes in DEV 3/12/2026 This file should be updated in azure portal and deployment should be done, after that will be raising the PR 3/12/2026
A9: 8 | B9: OnlineBidding | C9: 46079 | D9: 46093 | E9: OB-OP 8.5 Sprint 3 - [STRETCH] | F9: Preethi | G9: OP-2799 | H9: RSVP Receipts showing data tags for certain email clients | I9: Being Developed | J9: 3 | L9: 50.5 | M9: 46085 | AD9: Analysed and added the code for encoding, tried to reproduce the mentioned issue in DEV but all mails were coming correctly 3/4/2026 Updated the latest zip in DEV to check the fix but mail is not coming in DEV, need to confirm 3/5/2026 Tested in DEV and updated few more places 3/6/2026 Updated the conditions in all possible places 3/9/2026 Not receiving mails from 3/10/2026, so testing is blocked - created draft PR for review purpose | AE9: Tested in DEV, mail didnt have ## -3/6/2026
A10: 9 | B10: OnlineBidding | C10: 46079 | D10: 46093 | E10: OB-OP 8.5 Sprint 3 - [STRETCH] | F10: Mike/Preethi/Karthi | G10: OP-2807 | H10: Update OP splash page | I10: Being Developed | J10: 3 | L10: 37.25 | M10: 46086 | AD10: Initially this story was assigned to Mike, since we had time we took this in the middle of the sprint Trying to find the splash page in solution and in SQL tables as well 3/5/2026 Trying diff ways to find the splash page in our source 3/6/2026 Found the splash page, updating the content 3/9/2026 Updated the content and checked in browser as html page itself 3/10/2026 Trying to deploy in DEV for testing 3/11/2026 Deployed in DEV, but not able to see any splash page in DEV, only in TST we can see splash page 3/12/2026

Sheet OB-OP 8.5 Sprint 3-Defect
A1: S.No | B1: Sprint | C1: Story/Defect ID | D1: Parent Story | E1: Developer | F1: Issue Type | G1: Issue Description | H1: Priority | I1: Defect Source | J1: Type | K1: Status | L1: Root Cause Category | M1: Comments | N1: Found By | O1: RCA Comment
B2: OB-OP 8.5 Sprint 3 | C2: OB-3947 | D2: OB-3913 - CRT regression | E2: Preethi | F2: Defect | G2: Sponsor Image not always centered on sponsor scroll with single sponsor | H2: Significant | I2: Manual | J2: Internal | K2: Closed | L2: Existing_Issues | N2: Alice | O2: Need to check and analyse, we have checked in DEV with 1 sponsors but somehow got broken in TST
B3: OB-OP 8.5 Sprint 3 | C3: OB-3948 | D3: OB-3913 - CRT regression | E3: Prabu | F3: Defect | G3: Searching for a package by pkg # does not have a UX route to all packages | H3: Significant | I3: Manual | J3: Internal | K3: Closed | L3: Enhancements | N3: Alice | O3: This is part of OB-3911 which is almost developed in last sprint but that is not of this production release
B4: OB-OP 8.5 Sprint 3 | C4: OB-3949 | D4: OB-3913 - CRT regression | E4: Preethi | F4: Defect | G4: Mobile should match Desktop in regards to Hamburger Menu | H4: Significant | I4: Manual | J4: Internal | K4: Closed | L4: Enhancements | N4: Alice | O4: This is not part of any of the requirement so far discussed

Sheet OB-OP 8.5 Sprint 2-Status
A1: S.No | B1: Application Name | C1: Sprint Start Date | D1: Sprint End Date | E1: Sprint | F1: Developer | G1: Story ID/Defect ID | H1: Description | I1: Status | J1: Estimated(hrs/sp) | K1: Actual(hrs/sp) | L1: Actual Hours Worklog | M1: Dev Start Date | N1: Dev End Date | O1: Unit testing | P1: Peer Tested By | Q1: Peer Tested Defects, if any | R1: Peer Reviewed By | S1: Peer Code Review Comments, if any | T1: PR Number/Link | U1: PR Created Date | V1: PR Approved Date | W1: Onsite Lead Code Review | X1: Code Review Comments, if any | Y1: Client Code Review | Z1: Approved Date | AA1: Code Review Comments, if any2 | AB1: Internal PO -POV Comments | AC1: Client PO -POV Comments | AD1: Comments | AE1: QA Comments
A2: 1 | B2: OnlineBidding | C2: 46065 | D2: 46079 | E2: OB-OP 8.5 Sprint 2 | F2: Prabu | G2: OB-3920 | H2: Pre-Existing OB Sites are Not updating to new UX | I2: Completed | J2: 1 | L2: 12.75 | M2: PR completed by Joe, yet to deploy in TST and test, so no development in this sprint | N2: Nil | O2: Done | P2: Mercy | Q2: Nil | R2: Preethi | S2: Nil | T2: https://greatergiving.visualstudio.com/Greater%20Giving/_git/GGO/pullrequest/9283 | U2: 46066 | V2: 46066 | W2: Rajesh | X2: Nil | Y2: Joe | Z2: 46066 | AA2: Nil | AB2: Nil | AC2: Nil | AD2: Only QA testing pending in this sprint | AE2: Tested and noted down the org and project names in DEV environment which are not showing up new UI in OB 2/13/2026 Tested the projects in DEV and TST and shared with prabu, all showing new UI in OB 2/16/2026 TST testing completed 2/18/2026
A3: 2 | B3: OnlineBidding | C3: 46065 | D3: 46079 | E3: OB-OP 8.5 Sprint 2 | F3: Mercy - [TESTING ONLY] | G3: OB-3913 | H3: Release and Test OB 8.4.0 to CRT | I3: Being Tested | J3: 3 | L3: 44.75 | M3: Nil | N3: Nil | O3: Nil | P3: Nil | Q3: Nil | R3: Nil | S3: Nil | T3: Nil | U3: Nil | V3: Nil | W3: Nil | X3: Nil | Y3: Nil | Z3: Nil | AA3: Nil | AB3: Nil | AC3: Nil | AD3: Nil | AE3: Completed all CRT stories testing and added screenshots in JIRA 2/26/2026
A4: 3 | B4: OnlineBidding | C4: 46065 | D4: 46079 | E4: OB-OP 8.5 Sprint 2 | F4: Preethi | G4: OB-3940 | H4: SignalR Investigation and Update | I4: Completed | J4: 2 | L4: 39 | M4: 46070 | N4: 46070 | O4: Done | P4: Mercy | Q4: Nil | R4: Karthi | S4: Nil | T4: https://greatergiving.visualstudio.com/Greater%20Giving/_git/OnlineBidding/pullrequest/9276 | U4: 46070 | V4: 46070 | W4: Prabu | X4: Nil | Y4: Joe | Z4: 46070 | AA4: Nil | AB4: Nil | AC4: Nil | AD4: Analysed if any improvements can be done, deployed in DEV for testing 2/13/2026 Worked on showing current high bid during bid again functionality 2/17/2026 | AE4: Dev testing completed 2/13/2026 Retesting in DEV completed 2/16/2026 Retesting in DEV again completed 2/17/2026 TST testing completed 2/18/2026
A5: 4 | B5: OnlineBidding | C5: 46065 | D5: 46079 | E5: OB-OP 8.5 Sprint 2 | F5: Karthi | G5: OB-3939 | H5: OB UX - Sort by price feature enhancement | I5: Completed | J5: 3 | L5: 32.5 | M5: 46066 | N5: 46066 | O5: Done | P5: Mercy | Q5: Nil | R5: Preethi | S5: Nil | T5: https://greatergiving.visualstudio.com/Greater%20Giving/_git/OnlineBidding/pullrequest/9287 | U5: 46070 | V5: 46078 | W5: Prabu | X5: Nil | Y5: Joe | Z5: 46078 | AA5: Nil | AB5: Nil | AC5: Nil | AD5: Development and local testing completed 2/13/2026 DEV testing completed 2/16/2026 Since we are planning for second CRT release, this PR will be shared later after the release 2/18/2026 Both Joe and Prabu reviewed the PR, after CRT release is done they might complete it today 2/19/2026 Joe had few discussuion with prabu regrading the PR, waiting for his reply 2/23/2026 Joe suggested changes, prabu updated that and tested in DEV, waiting for Joe's approval 2/25/2026 PR approved 2/26/2026 | AE5: Tested in DEV completed 2/17/2026 Tested in DEV completed 2/25/2026 Tested in TST completed 2/26/2026
A6: 5 | B6: OnlineBidding | C6: 46065 | D6: 46079 | E6: OB-OP 8.5 Sprint 2 | F6: Preethi/Karthi | G6: OB-3911 | H6: Using the back button should show full search results | I6: Peer Review | J6: 5 | L6: 118 | M6: 46066 | N6: 46079 | O6: Done | P6: Mercy | Q6: 1.Home icon click/All breadcrumb click - not displayig all packages | R6: Karthi/Preethi | S6: Nil | T6: https://greatergiving.visualstudio.com/Greater%20Giving/_git/OnlineBidding/pullrequest/9323 | U6: 46079 | W6: Prabu | Y6: Joe | AD6: Worked on retaining the search text when clicking back from detail page, in progress with filter retain 2/13/2026 Worked on filter retain, in progress with storing scroll position 2/16/2026 Worked on activity and favorite tab retain functionality for sometime since OB-3940 was priority 2/17/2026 Working on scroll position and pagination sceanrio 2/18/2026 Completed devlopment, testing all possible sceanrios in local and fixing the broken scenarios 2/19/2026, 2/20/2026 Home icon/All click scenarios failed because of recent update in branch, fixed that - 2/23/2026 Worked on one failing scenario reported by mercy - both browse and ALL click back to back was showing result wrongly, Fixed all sceanrios, tested in DEV and created PR- 2/24/2026 Worked on the code changes suggested by prabu - not to have too many code changes in browse page and thinking of alternative approach to reduce the number of lines 2/25/2026 Checked all diff approaches, session storage, storing in URL, RouteReuse Strategy, but nothing helps in our scenario, done with service level changes and tested in local and deployed in DEV 2/26/2026 | AE6: Tested in DEV in progress 2/19/2026 Tested in DEV completed - 2/24/2026 Restesting for the recent changes in DEV in progress - 2/25/2026

Sheet OB-OP 8.5 Sprint 2-Defect
A1: S.No | B1: Sprint | C1: Story/Defect ID | D1: Parent Story | E1: Developer | F1: Issue Type | G1: Issue Description | H1: Priority | I1: Defect Source | J1: Type | K1: Status | L1: Root Cause Category | M1: Comments | N1: Found By | O1: RCA Comment

Sheet OB-OP 8.5 Sprint 1-Status
A1: S.No | B1: Application Name | C1: Sprint Start Date | D1: Sprint End Date | E1: Sprint | F1: Developer | G1: Story ID/Defect ID | H1: Description | I1: Status | J1: Estimated(hrs/sp) | K1: Actual(hrs/sp) | L1: Actual Hours Worklog | M1: Dev Start Date | N1: Dev End Date | O1: Unit testing | P1: Peer Tested By | Q1: Peer Tested Defects, if any | R1: Peer Reviewed By | S1: Peer Code Review Comments, if any | T1: PR Number/Link | U1: PR Created Date | V1: PR Approved Date | W1: Onsite Lead Code Review | X1: Code Review Comments, if any | Y1: Client Code Review | Z1: Approved Date | AA1: Code Review Comments, if any2 | AB1: Internal PO -POV Comments | AC1: Client PO -POV Comments | AD1: Comments | AE1: QA Comments
A2: 1 | B2: OnlineBidding | C2: 46051 | D2: 46065 | E2: OB-OP 8.5 Sprint 1 | F2: Mercy - [TESTING ONLY] | G2: OB-3913 | H2: Release and Test OB 8.4.0 to CRT | I2: Being Developed | J2: 3 | L2: 57.75
A3: 2 | B3: OnlineBidding | C3: 46051 | D3: 46065 | E3: OB-OP 8.5 Sprint 1 | F3: Preethi | G3: OB-3922 | H3: Donations do not appear in Acitivty | I3: Completed | J3: 2 | K3: 2 | L3: 28 | M3: 46052 | N3: 46059 | O3: Done | P3: Mercy | Q3: Donation tab keep on loading when there is no count and also when donation is disabled in GGO settings | R3: Karthi | S3: Nil | T3: https://greatergiving.visualstudio.com/Greater%20Giving/_git/OnlineBidding/pullrequest/9238 | U3: 46056 | V3: 46059 | W3: Prabu | X3: Nil | Y3: Joe | Z3: 46059 | AA3: Nil | AB3: Nil | AC3: Nil | AD3: Implemented the slider animation and created 2 branches with different set of donation order and deployed in DEV for testing 1/30/2026 Mercy reported few issues in DEV testing, worked on those and prabu suggested to show difference in the columns, updated that and deployed in DEV for QA testing 2/2/2026 PO didn't want any color backgrounds to the list and added a vertical line for separating the columns and deployed in DEV for testing 2/3/2026 Raised PR waiting for prabu's review, he has got many stories yesterday to review, so he might review this today as this has more code changes 2/4/2026 Prabu approved the PR, waitiing for Joe's review 2/5/2026 Joe asked for a change related to background theme color, working on that today, DEV testin g completed for the change mentioned 2/6/2026 TST testing completed 2/9/2026
A4: 3 | B4: OnlineBidding | C4: 46051 | D4: 46065 | E4: OB-OP 8.5 Sprint 1 | F4: Karthi | G4: OB-3927 | H4: Single Sponsor Logo Stuck on Far Left | I4: Completed | J4: 2 | K4: 2 | L4: 16.25 | M4: 46052 | N4: 46055 | O4: Done | P4: Mercy | Q4: Nil | R4: Preethi | S4: Nil | T4: https://greatergiving.visualstudio.com/Greater%20Giving/_git/OnlineBidding/pullrequest/9250 | U4: 46055 | V4: 46057 | W4: Prabu | X4: Nil | Y4: Joe | Z4: 46057 | AA4: Nil | AB4: Nil | AC4: Nil | AD4: Updated the point suggested by prabu and deployed in DEV for testing 1/30/2026 Updated the points which mercy mentioned during testing and deployed in DEV for QA testing 2/2/2026 Retesting in DEV and created PR 2/3/2026 PR approved, TST testing completed 2/4/2026
A5: 4 | B5: OnlineBidding | C5: 46051 | D5: 46065 | E5: OB-OP 8.5 Sprint 1 | F5: Preethi | G5: OB-3933 | H5: For logged In user unable to donate from slide out menu | I5: Completed | J5: 1 | K5: 1 | L5: 4 | M5: 46052 | N5: 46052 | O5: Done | P5: Mercy | Q5: Nil | R5: Karthi | S5: Nil | T5: https://greatergiving.visualstudio.com/Greater%20Giving/_git/OnlineBidding/pullrequest/9237 | U5: 46052 | V5: 46055 | W5: Prabu | X5: Nil | Y5: Joe | Z5: 46055 | AA5: Nil | AB5: Nil | AC5: Nil | AD5: Development and local testing completed, Deployed in DEV for QA testing, Raised PR - 1/30/2026 Prabu approved on friday itself, waiting for Joe's approval 2/2/2026 TST testing completed 2/3/2026
A6: 5 | B6: OnlineBidding | C6: 46051 | D6: 46065 | E6: OB-OP 8.5 Sprint 1 | F6: Karthi/Preethi | G6: OB-3929 | H6: OB UX - Mobile header clean up | I6: Completed | J6: 3 | K6: 3 | L6: 38.75 | M6: 46056 | N6: 46062 | O6: Done | P6: Mercy | Q6: Nil | R6: Preethi/Karthi | S6: Nil | T6: https://greatergiving.visualstudio.com/Greater%20Giving/_git/OnlineBidding/pullrequest/9275 | U6: 46064 | V6: 46065 | W6: Prabu | X6: Nil | Y6: Joe | Z6: 46065 | AA6: Nil | AB6: Nil | AC6: Nil | AD6: Working on the font changes 2/3/2026 Working on showing full image instead of cropped images 2/4/2026 Updated the height region of the whole container and shared screenshots to prabu 2/5/2026 We dont have mockup or screenshot for this story, so we have made changes as per the AC and shared the before and after screenshots with prabu, once derek confirms the changes, we will deploy in DEV for testing and will be raising PR after that 2/6/2026 Made changes for donation bar spacing and deployed in DEV for testing 2/9/2026 Retested in DEV 2/10/2026 Restested in DEV 2/11/2026 | AE6: Tested in DEV and shared my observation with repect to horizontal and vertical images 2/11/2026
A7: 6 | B7: OnlineBidding | C7: 46051 | D7: 46065 | E7: OB-OP 8.5 Sprint 1 | F7: Preethi | G7: OB-3930 | H7: OB UX - Donations modal should clear 0s on click | I7: Completed | J7: 1 | K7: 1 | L7: 8.5 | M7: 46052 | N7: 46052 | O7: Done | P7: Mercy | Q7: Nil | R7: Karthi | S7: Nil | T7: https://greatergiving.visualstudio.com/Greater%20Giving/_git/OnlineBidding/pullrequest/9240 | U7: 46055 | V7: 46055 | W7: Prabu | X7: Nil | Y7: Joe | Z7: 46055 | AA7: Nil | AB7: Nil | AC7: Nil | AD7: Development and local testing completed, Created draft PR - 1/30/2026 Deployed in DEV for QA testing, no issues found and published the PR 2/2/2026 TST testing completed 2/3/2026
A8: 7 | B8: OnlineBidding | C8: 46051 | D8: 46065 | E8: OB-OP 8.5 Sprint 1 | F8: Preethi | G8: OB-3934 | H8: OB UX - Clickable links should indicate they are such | I8: Completed | J8: 2 | K8: 2 | L8: 9 | M8: 46052 | N8: 46052 | O8: Done | P8: Mercy | Q8: Nil | R8: Karthi | S8: Nil | T8: https://greatergiving.visualstudio.com/Greater%20Giving/_git/OnlineBidding/pullrequest/9241 | U8: 46055 | V8: 46057 | W8: Prabu | X8: Nil | Y8: Joe | Z8: 46057 | AA8: Nil | AB8: Nil | AC8: Nil | AD8: Development and local testing completed, Created draft PR - 1/30/2026 Deployed in DEV for QA testing, no issues found and published the PR 2/2/2026 Prabu approved the PR, waiting for Joe's approval, retesting done in DEV 2/3/2026 PR approved, TST testing completed 2/4/2026
A9: 8 | B9: OnlineBidding | C9: 46051 | D9: 46065 | E9: OB-OP 8.5 Sprint 1 | F9: Preethi | G9: OB-3931 | H9: OB UX - Provide a "Return to Top" option when scrolling | I9: Completed | J9: 2 | K9: 2 | L9: 9 | M9: 46055 | N9: 46055 | O9: Done | P9: Mercy | Q9: Nil | R9: Karthi | S9: Nil | T9: https://greatergiving.visualstudio.com/Greater%20Giving/_git/OnlineBidding/pullrequest/9251 | U9: 46056 | V9: 46057 | W9: Prabu | X9: Nil | Y9: Joe | Z9: 46057 | AA9: Nil | AB9: Nil | AC9: Nil | AD9: Development started and need to do DEV testing tomorrow 2/2/2026 Deployed in DEV for testing and created PR - 2/3/2026 PR approved, TST testing completed 2/4/2026
A10: 9 | B10: OnlineBidding | C10: 46051 | D10: 46065 | E10: OB-OP 8.5 Sprint 1 | F10: Karthi | G10: OB-3936 | H10: OB UX - Notification Bell and User Profile button | I10: Completed | J10: 1 | K10: 1 | L10: 17.5 | M10: 46055 | N10: 46056 | O10: Done | P10: Mercy | Q10: Nil | R10: Preethi | S10: Nil | T10: https://greatergiving.visualstudio.com/Greater%20Giving/_git/OnlineBidding/pullrequest/9252 | U10: 46056 | V10: 46057 | W10: Prabu | X10: Nil | Y10: Joe | Z10: 46057 | AA10: Nil | AB10: Nil | AC10: Nil | AD10: Started development and it is progress 2/2/2026 Deployed in DEV for testing and will create PR today - 2/3/2026 Prabu approved the PR, waiting for Joe's review 2/4/2026 PR approved, TST testing completed 2/5/2026
A11: 10 | B11: OnlineBidding | C11: 46051 | D11: 46065 | E11: OB-OP 8.5 Sprint 1 - [STRETCH] | F11: Karthi | G11: OB-3937 | H11: OB UX - Featured packages text should wrap | I11: Completed | J11: 1 | K11: 1 | L11: 24.5 | M11: 46058 | N11: 46063 | O11: Done | P11: Mercy | Q11: Nil | R11: Preethi | S11: Nil | T11: https://greatergiving.visualstudio.com/Greater%20Giving/_git/OnlineBidding/pullrequest/9267 | U11: 46062 | V11: 46063 | W11: Prabu | X11: Nil | Y11: Joe | Z11: 46063 | AA11: Nil | AB11: Nil | AC11: Nil | AD11: Updated the code, shared screenshots to prabu since we dont have any mockup for this in JIRA 2/5/2026 Prabu asked for a screenshot by displaying show more/show less text , so worked on that 2/6/2026 Tested in DEV with show more/show less text and created PR - 2/9/2026
A12: 11 | B12: OnlineBidding | C12: 46051 | D12: 46065 | E12: OB-OP 8.5 Sprint 1 - [STRETCH] | F12: Karthi | G12: OB-3938 | H12: OB UX - Hamburger menu consistency | I12: Completed | J12: 2 | K12: 2 | L12: 4.5 | M12: 46058 | N12: 46058 | O12: Done | P12: Mercy | Q12: Nil | R12: Preethi | S12: Nil | T12: https://greatergiving.visualstudio.com/Greater%20Giving/_git/OnlineBidding/pullrequest/9259 | U12: 46062 | V12: 46063 | W12: Prabu | X12: Nil | Y12: Joe | Z12: 46063 | AA12: Nil | AB12: Nil | AC12: Nil | AD12: Development and local testing completed, need to deploy in DEV tomorrow 2/5/2026 DEV testing by QA in progress, once done will raise the PR 2/6/2026
A13: 12 | B13: OnlineBidding | C13: 46051 | D13: 46065 | E13: OB-OP 8.5 Sprint 1 - [STRETCH] | F13: Preethi/Karthi | G13: OB-3935 | H13: OB UX - Move Terms and Conditions | I13: Completed | J13: 2 | K13: 2 | L13: 10.25 | M13: 46063 | N13: 46064 | O13: Done | P13: Mercy | Q13: Nil | R13: Karthi/Preethi | S13: Nil | T13: https://greatergiving.visualstudio.com/Greater%20Giving/_git/OnlineBidding/pullrequest/9268 | U13: 46063 | V13: 46064 | W13: Prabu | X13: Remove the dead codes on .ts file for the changes removed in HTML | Y13: Joe | Z13: 46065 | AA13: Nil | AB13: Nil | AC13: Nil | AD13: Development and local testing completed. Deployed in DEV for QA testing 2/10/2026 Worked on the comments given by prabu, retesting in DEV completed, raised PR 2/11/2026 | AE13: DEV testing completed 2/11/2026
A14: 13 | B14: OnlineBidding | C14: 46051 | D14: 46065 | E14: OB-OP 8.5 Sprint 1 - [STRETCH] | F14: Preethi/Prabu | G14: OB-3940 | H14: SignalR Investigation and Update | I14: Being Developed | J14: 3 | K14: 1 | L14: 33.75 | M14: 46062 | N14: 46064 | O14: Done | P14: Mercy | Q14: Nil | T14: https://greatergiving.visualstudio.com/Greater%20Giving/_git/OnlineBidding/pullrequest/9276 | AD14: Started with commenting the signalr related changes and noted down the steps which all affects the signalr 2/9/2026 Tried with stopping reload while signalr and tested in local with multiple users 2/10/2026 Worked on stopping the APIs when signalr is triggered so that cache becomes empty 2/11/2026 | AE14: DEV testing in progress 2/11/2026
A15: 14 | B15: OnlineBidding | C15: 46051 | D15: 46065 | E15: OB-OP 8.5 Sprint 1 - [STRETCH] | F15: Preethi | G15: OB-3941 | H15: When we set donation bar at bottom of the page in GGO, top icon hides behind the footer | I15: Completed | J15: 1 | K15: 1 | L15: 5 | M15: 46064 | N15: 46064 | O15: Done | P15: Mercy | Q15: Nil | R15: Prabu | S15: Nil | T15: https://greatergiving.visualstudio.com/Greater%20Giving/_git/OnlineBidding/pullrequest/9277 | U15: 46064 | V15: 46065 | W15: Prabu | X15: Nil | Y15: Joe | Z15: 46065 | AA15: Nil | AB15: Nil | AC15: Nil | AD15: Fixed and created PR - 2/11/2026
A16: 15 | B16: OnlineBidding | C16: 46051 | D16: 46065 | E16: OB-OP 8.5 Sprint 1 | F16: Prabu | G16: OB-3920 | H16: Pre-Existing OB Sites are Not updating to new UX | I16: Peer Review | J16: 1 | L16: 1 | M16: 46062 | O16: Done | T16: https://greatergiving.visualstudio.com/Greater%20Giving/_git/GGO/pullrequest/9282 | U16: 46065 | AD16: Development and local testing completed and raised PR - 2/12/2026

Sheet OB-OP 8.5 Sprint 1-Defect
A1: S.No | B1: Sprint | C1: Story/Defect ID | D1: Parent Story | E1: Developer | F1: Issue Type | G1: Issue Description | H1: Priority | I1: Defect Source | J1: Type | K1: Status | L1: Root Cause Category | M1: Comments | N1: Found By | O1: RCA Comment
B2: OB-OP 8.5 Sprint 1 | C2: OB-3933 | E2: Preethi | F2: Defect | G2: For logged In user unable to donate from slide out menu | H2: Major | I2: Manual | J2: Internal | K2: Closed | L2: Development | M2: Missed to find in local and DEV testing | N2: Mercy | O2: We have updated the popup in one scenario but missed to add the parameter in other places which uses the same popup component. When any change is done we make sure that its reflected in all places
B3: OB-OP 8.5 Sprint 1 | C3: OB-3941 | D3: Regression | E3: Preethi | F3: Defect | G3: When we set donation bar at bottom of the page in GGO, top icon hides behind the footer | H3: Major | I3: Manual | J3: Internal | K3: Closed | L3: Development | M3: Didn't check by having donation bar at the bottom | N3: Mercy | O3: These scenarios will be done in regression only. As part of the original story, TOP icon functionality was tested but having donation bar at the top and bottom separately was not tested

Sheet OB-OP 8.4 Sprint 4-Status
A1: S.No | B1: Application Name | C1: Sprint Start Date | D1: Sprint End Date | E1: Sprint | F1: Developer | G1: Story ID/Defect ID | H1: Description | I1: Status | J1: Estimated(hrs/sp) | K1: Actual(hrs/sp) | L1: Actual Hours Worklog | M1: Dev Start Date | N1: Dev End Date | O1: Unit testing | P1: Peer Tested By | Q1: Peer Tested Defects, if any | R1: Peer Reviewed By | S1: Peer Code Review Comments, if any | T1: PR Number/Link | U1: PR Created Date | V1: PR Approved Date | W1: Onsite Lead Code Review | X1: Code Review Comments, if any | Y1: Client Code Review | Z1: Approved Date | AA1: Code Review Comments, if any2 | AB1: Internal PO -POV Comments | AC1: Client PO -POV Comments | AD1: Dev Comments | AE1: QA Comments
A2: 1 | B2: OnlineBidding | C2: 46037 | D2: 46051 | E2: OB-OP 8.4 Sprint 4 | F2: Preethi | G2: OB-3895 | H2: Adjust Activity and Favorites to reflect updated search and pagination | I2: Completed | J2: 1 | L2: 8.25 | M2: 46038 | N2: 46041 | O2: Done | P2: Mercy | Q2: Nil | R2: Karthi | S2: Nil | T2: https://greatergiving.visualstudio.com/Greater%20Giving/_git/OnlineBidding/pullrequest/9118 | U2: 46038 | V2: 46039 | W2: Prabu | X2: Nil | Y2: Joe | Z2: 46039 | AA2: Nil | AB2: Nil | AC2: Nil | AD2: DEV testing completed,Need to test the last review changes alone, that will be done on monday - 1/16/2026 Had a defect in it, mercy created bug for that and tested in DEV - 1/19/2026 Partial DEV testing completed for the issue mentioned by mercy as queue stopped in DEV - 1/20/2026 Retesting completed in DEV, TST was having CORS error, so did testing in DEV only 1/21/2026 Queue is stopped, so its a blocker for testing in TST for many scenarios, we can test only with the existing settings - 1/22/2026
A3: 2 | B3: OnlineBidding | C3: 46037 | D3: 46051 | E3: OB-OP 8.4 Sprint 4 | F3: Preethi | G3: OB-3864 | H3: Package Browse Audit | I3: Completed | J3: 2 | L3: 22 | M3: 46038 | N3: 46038 | O3: Done | P3: Mercy | Q3: Nil | R3: Karthi/Preethi | S3: Nil | T3: https://greatergiving.visualstudio.com/Greater%20Giving/_git/OnlineBidding/pullrequest/9165 | U3: 46038 | V3: 46043 | W3: Prabu | X3: Nil | Y3: Joe | Z3: 46043 | AA3: Nil | AB3: Nil | AC3: Nil | AD3: Merged with develop and resolved the conflicts and tested in DEV - 1/16/2026 Since client is having holiday on Monday (Jan 19), PR will be approved once they are back - 1/19/2026 Pending with Prabu and Joe review. DEV testing completed - 1/20/2026 PR approved, Retesting completed in DEV, TST was having CORS error, so did testing in DEV only 1/21/2026 Partial testing is done, need to change in GGO settings and confirm for few scenarios, since queue is not working, it can't be tested today - 1/22/2026
A4: 3 | B4: OnlineBidding | C4: 46037 | D4: 46051 | E4: OB-OP 8.4 Sprint 4 | F4: Karthi/Preethi | G4: OB-3903 | H4: There is no spacing available in the left and right side of detailed page | I4: Completed | J4: 1 | L4: 11.75 | M4: 46038 | N4: 46038 | O4: Done | P4: Mercy | Q4: Nil | R4: Preethi | S4: Nil | T4: https://greatergiving.visualstudio.com/Greater%20Giving/_git/OnlineBidding/pullrequest/9181 | U4: 46038 | V4: 46042 | W4: Prabu | X4: Nil | Y4: Joe | Z4: 46042 | AA4: Nil | AB4: Nil | AC4: Nil | AD4: Development and DEV testing completed and raised PR - 1/16/2026 Prabu approved the PR, waiting for Joe's approval.Since client is having holiday on Monday (Jan 19), PR will be approved once they are back 1/19/2026 Tested in DEV but being queue stopped couldn't change setting in GGO and complete the testing 1/20/2026 PR approved and DEV testing is done, as TST is having CORS error 1/21/2026 TST testing completed 1/22/2026
A5: 4 | B5: OnlineBidding | C5: 46037 | D5: 46051 | E5: OB-OP 8.4 Sprint 4 | F5: Preethi | G5: OB-3909 | H5: Donations must be greater than $0.0 | I5: Completed | J5: 1 | L5: 15 | M5: 46038 | N5: 46038 | O5: Done | P5: Mercy | Q5: Donate button is not seen in featured package section | R5: Prabu | S5: Nil | T5: https://greatergiving.visualstudio.com/Greater%20Giving/_git/OnlineBidding/pullrequest/9182 | U5: 46038 | V5: 46039 | W5: Prabu | X5: Nil | Y5: Joe | Z5: 46039 | AA5: Nil | AB5: Nil | AC5: Nil | AD5: Development completed and mercy found an issue in DEV testing but that is not because of the changes done for this story, it is due to the changes done in previous sprint story OB-3862, the code was updated in browse and detail page but missed to add in featured package section.Raised PR- 1/16/2026 PR is approved, since client is in holiday, it wil be tested once they are back - 1/19/2026 Partial DEV and TST testing completed beacuse of the queue issue - 1/20/2026 DEV testing completed as TST was having CORS error 1/21/2026 TST testing completed 1/22/2026
A6: 5 | B6: OnlineBidding | C6: 46037 | D6: 46051 | E6: OB-OP 8.4 Sprint 4 | F6: Mercy - [TESTING ONLY] | G6: OB-3901 | H6: When we bid or buy any package that appears at the end of the page, after the confirmation pop up box is closed, the page loading is interrupted | I6: Completed | J6: 1 | L6: 0.5 | AD6: Tested and verified in TST and added comments in JIRA as this is not reproduceable in TST anymore and fixed as part of other stories1/16/2026
A7: 6 | B7: OnlineBidding | C7: 46037 | D7: 46051 | E7: OB-OP 8.4 Sprint 4 | F7: Mercy - [TESTING ONLY] | G7: OB-3886 | H7: if we have more than 24 packages but less than 48 packages and the pagination option enabled, some package duplicates are seen | I7: Completed | J7: 1 | L7: 1.5 | AD7: Tested and verified in TST and added comments in JIRA as this is not reproduceable in TST anymore and fixed as part of other stories1/16/2026
A8: 7 | B8: OnlineBidding | C8: 46037 | D8: 46051 | E8: OB-OP 8.4 Sprint 4 | F8: Preethi | G8: OB-3916 - [DEFECT] | H8: Packages do not load inside Activity tab after performing an action | I8: Completed | L8: 19.25 | M8: 46041 | N8: 46041 | O8: Done | P8: Mercy | Q8: Nil | R8: Karthi | S8: Nil | T8: https://greatergiving.visualstudio.com/Greater%20Giving/_git/OnlineBidding/pullrequest/9185 | U8: 46041 | V8: 46042 | W8: Prabu | X8: Nil | Y8: Joe | Z8: 46042 | AA8: Nil | AB8: Nil | AC8: Nil | AD8: Development and local testing completed 1/19/2026 DEV testing completed 1/20/202 Retesting in DEV completed as TST was having CORS error 1/21/2026 Partial testing in TST is completed as queue is a blocker for many scenarios 1/22/2026
A9: 8 | B9: OnlineBidding | C9: 46037 | D9: 46051 | E9: OB-OP 8.4 Sprint 4 - [Stretch] | F9: Preethi | G9: OB-3905 | H9: Pop up should be closed and failure message should be appear when all package gets sold | I9: Completed | J9: 1 | L9: 7.75 | M9: 46041 | N9: 46041 | O9: Done | P9: Mercy | Q9: Nil | R9: Karthi | S9: Nil | T9: https://greatergiving.visualstudio.com/Greater%20Giving/_git/OnlineBidding/pullrequest/9186 | U9: 46041 | V9: 46043 | W9: Prabu | X9: Nil | Y9: Joe | Z9: 46043 | AA9: Nil | AB9: Nil | AC9: Nil | AD9: Development and local testing completed 1/19/2026 DEV testing completed 1/20/2026 Retesting in DEV completed as TST was having CORS error 1/21/2026 TST testing completed 1/22/2026
A10: 9 | B10: OnlineBidding | C10: 46037 | D10: 46051 | E10: OB-OP 8.4 Sprint 4 - [Stretch] | F10: Preethi/Karthi | G10: OB-3917 | H10: Minor Cleanup | I10: Completed | J10: 2 | L10: 22.25 | M10: 46041 | N10: 46041 | O10: Done | P10: Mercy | Q10: In the Mob view Browse page we see less spacing in the right side | R10: Karthi/Preethi | S10: Nil | T10: https://greatergiving.visualstudio.com/Greater%20Giving/_git/OnlineBidding/pullrequest/9189 | U10: 46042 | V10: 46043 | W10: Prabu | X10: Nil | Y10: Joe | Z10: 46043 | AA10: Nil | AB10: Nil | AC10: Nil | AD10: Development and local testing completed 1/19/2026 DEV testing completed 1/20/2026 Retesting in DEV completed as TST was having CORS error 1/21/2026 TST testing completed 1/22/2026
A11: 10 | B11: OnlineBidding | C11: 46037 | D11: 46051 | E11: OB-OP 8.4 Sprint 4 - [Stretch] | F11: Preethi | G11: OB-3918 | H11: Donation button inconsistent enable issue | I11: Completed | J11: 1 | L11: 4.5 | M11: 46043 | N11: 46043 | O11: Done | P11: Mercy | Q11: Nil | R11: Karthi | S11: Nil | T11: https://greatergiving.visualstudio.com/Greater%20Giving/_git/OnlineBidding/pullrequest/9203 | U11: 46044 | V11: 46044 | W11: Prabu | X11: Nil | Y11: Joe | Z11: 46044 | AA11: Nil | AB11: Nil | AC11: Nil | AD11: Local testing completed 1/21/2026 TST testing completed 1/22/2026
A12: 11 | B12: OnlineBidding | C12: 46037 | D12: 46051 | E12: OB-OP 8.4 Sprint 4 - [Stretch] | F12: Preethi/Karthi | G12: OB-3911 | H12: Using the back button should show full search results | I12: Being Developed | J12: 5 | L12: 6 | M12: 46045 | AD12: Started with search functionality and completed that, need to work on retaining filter part 1/23/2026 This has been removed from current sprint board, but we worked on it for 1 day 1/27/2026
A13: 12 | B13: OnlineBidding | C13: 46037 | D13: 46051 | E13: OB-OP 8.4 Sprint 4 | F13: Mercy - [TESTING ONLY] | G13: OB-3913 | H13: Release and Test OB 8.4.0 to CRT | I13: Being Tested | J13: 5 | L13: 79.25 | AD13: Regression Testing in Progress
A14: 13 | B14: OnlineBidding | C14: 46037 | D14: 46051 | E14: OB-OP 8.4 Sprint 4 - [Stretch] | F14: Preethi | G14: OB-3925 | H14: Sign In on Package Details Does Not redirect | I14: Completed | J14: 1 | L14: 7.75 | M14: 46049 | N14: 46049 | O14: Done | P14: Mercy | Q14: Nil | R14: Karthi | S14: Nil | T14: https://greatergiving.visualstudio.com/Greater%20Giving/_git/OnlineBidding/pullrequest/9222 | U14: 46049 | V14: 46050 | W14: Prabu | X14: Nil | Y14: Joe | Z14: 46050 | AA14: Nil | AB14: Nil | AC14: Nil | AD14: Development and local testing completed. DEV testing by QA also completed 1/27/2026 Prabu approved the PR, waiting for Joe's approval 1/28/2026
A15: 14 | B15: OnlineBidding | C15: 46037 | D15: 46051 | E15: OB-OP 8.4 Sprint 4 - [Stretch] | F15: Preethi | G15: OB-3921 | H15: Provide message when user is not logged in - Donate | I15: Completed | J15: 1 | L15: 4.5 | M15: 46049 | N15: 46049 | O15: Done | P15: Mercy | Q15: Nil | R15: Karthi | S15: Nil | T15: https://greatergiving.visualstudio.com/Greater%20Giving/_git/OnlineBidding/pullrequest/9223 | U15: 46050 | V15: 46051 | W15: Prabu | X15: Nil | Y15: Joe | Z15: 46051 | AA15: Nil | AB15: Nil | AC15: Nil | AD15: Development and local testing completed. DEV testing by QA also completed with the mock message, need to the confirm the message text from PO, created draft PR 1/27/2026 Still PO didn't confirm the message text in the popup - 1/28/2026
A16: 15 | B16: OnlineBidding | C16: 46037 | D16: 46051 | E16: OB-OP 8.4 Sprint 4 - [Stretch] | F16: Karthi | G16: OB-3924 | H16: Cannot close bottom drawer on iphone/safari | I16: Completed | J16: 1 | L16: 16.25 | M16: 46049 | N16: 46050 | O16: Done | P16: Mercy | Q16: Nil | R16: Preethi | S16: Nil | T16: https://greatergiving.visualstudio.com/Greater%20Giving/_git/OnlineBidding/pullrequest/9225 | U16: 46050 | V16: 46051 | W16: Prabu | X16: Nil | Y16: Joe | Z16: 46051 | AA16: Nil | AB16: Nil | AC16: Nil | AD16: Development and local testing completed, DEV testing by QA completed 1/27/2026 PR raised today - 1/28/2026
A17: 16 | B17: OnlineBidding | C17: 46037 | D17: 46051 | E17: OB-OP 8.4 Sprint 4 - [Stretch] | F17: Karthi | G17: OB-3926 | H17: Sponsor Logo Images distorted | I17: Completed | J17: 1 | L17: 8.75 | M17: 46049 | N17: 46049 | O17: Done | P17: Mercy | Q17: Nil | R17: Preethi | S17: Nil | T17: https://greatergiving.visualstudio.com/Greater%20Giving/_git/OnlineBidding/pullrequest/9224 | U17: 46049 | V17: 46051 | W17: Prabu | X17: Nil | Y17: Joe | Z17: 46051 | AA17: Nil | AB17: Nil | AC17: Nil | AD17: Development and local testing completed, DEV testing by QA completed 1/27/2026 Prabu approved the PR, waiting for Joe's approval 1/28/2026 | XFD17: 16
A18: 17 | B18: OnlineBidding | C18: 46037 | D18: 46051 | E18: OB-OP 8.4 Sprint 4 - [Stretch] | F18: Preethi | G18: OB-3923 | H18: Mobile - After applying a filter, close the filters area in order to see Package Browse page | I18: Completed | J18: 2 | L18: 5 | M18: 46049 | N18: 46050 | O18: Done | P18: Mercy | Q18: Noted this while testing but its like this in CRT itself, when we are in favorite tab and clicking show filters, canvas appears in mobile and ipad | R18: Karthi | S18: Nil | T18: https://greatergiving.visualstudio.com/Greater%20Giving/_git/OnlineBidding/pullrequest/9230 | U18: 46050 | V18: 46051 | W18: Prabu | X18: Nil | Y18: Joe | Z18: 46051 | AA18: Nil | AB18: Nil | AC18: Nil | AD18: Development and local testing completed 1/27/2026 DEV testing done and found an issuw which is existing in CRT also, worked on that retested in DEV, created PR - 1/28/2026
A19: 18 | B19: OnlineBidding | C19: 46037 | D19: 46051 | E19: OB-OP 8.4 Sprint 4 - [Stretch] | F19: Preethi | G19: OB-3928 | H19: OB UX - Buy Now Price | I19: Completed | J19: 2 | L19: 7 | M19: 46049 | N19: 46049 | O19: Done | P19: Mercy | Q19: Nil | R19: Karthii | S19: Nil | T19: https://greatergiving.visualstudio.com/Greater%20Giving/_git/OnlineBidding/pullrequest/9231 | U19: 46050 | V19: 46051 | W19: Prabu | X19: Nil | Y19: Joe | Z19: 45686 | AA19: Nil | AB19: Nil | AC19: Nil | AD19: Development and local testing completed 1/27/2026 QA tested in DEV, still PO needs to confirm the position of the amount and display text, created draft PR - 1/28/2026
A20: 19 | B20: OnlineBidding | C20: 46037 | D20: 46051 | E20: OB-OP 8.4 Sprint 4 - [Stretch] | F20: Preethi | G20: OB-3922 | H20: Donations do not appear in Acitivty | I20: Being Developed | J20: 1 | L20: 13.25 | M20: 46050 | AD20: SP is not yet given in JIRA, devlopment completed and local testing in progress 1/28/2026 Implemented the slider changes suggested by prabu and shared screen recording to prabu 1/29/2026
A21: 20 | B21: OnlineBidding | C21: 46037 | D21: 46051 | E21: OB-OP 8.4 Sprint 4 - [Stretch] | F21: Karthi | G21: OB-3927 | H21: Single Sponsor Logo Stuck on Far Left | I21: Being Developed | J21: 3 | L21: 12 | M21: 46050 | AD21: Basic development changes are done, checking with multiple scenarios and updating the code accordingly 1/28/2026 Tried another approach which prabu suggested - with respect to devide width and shared the recording to prabu 1/29/2026

Sheet OB-OP 8.4 Sprint 4-Defect
A1: S.No | B1: Sprint | C1: Story/Defect ID | D1: Parent Story | E1: Developer | F1: Issue Type | G1: Issue Description | H1: Priority | I1: Defect Source | J1: Type | K1: Status | L1: Root Cause Category | M1: Comments | N1: Found By | O1: RCA Comment
B2: OB-OP 8.4 Sprint 4 | C2: OB-3916 | D2: OB-3895 | E2: Preethi | F2: Defect | G2: Packages do not load inside Activity tab after performing an action | H2: Significant | I2: Manual | J2: Internal | K2: Closed | L2: Development | M2: Missed to find during development and DEV testing | N2: Mercy | O2: Need to test all scenarios in all tabs carefully
B3: OB-OP 8.4 Sprint 4 | C3: OB-3917 | D3: Regression | E3: Preethi/Karthi | F3: Defect | G3: Minor Cleanup | H3: Significant | I3: Manual | J3: Internal | K3: Closed | L3: Development | M3: Few inconsistent scenarios found in regression | N3: Mercy | O3: Need to test all scenarios in all browsers carefully
B4: OB-OP 8.4 Sprint 4 | C4: OB-3925 | D4: CRT Testing | E4: Preethi | F4: Defect | G4: Sign In on Package Details Does Not redirect | H4: Significant | I4: Manual | J4: Internal | K4: Closed | L4: Requirements | M4: We didn't have any story to handle this button functionality | N4: CS Team | O4: We did not have a dedicated story to address this button’s functionality. While we documented and communicated several points that were missing from the acceptance criteria, this particular item was unfortunately overlooked
B5: OB-OP 8.4 Sprint 4 | C5: OB-3924 | D5: CRT Testing | E5: Karthi | F5: Defect | G5: Cannot close bottom drawer on iphone/safari | H5: Significant | I5: Manual | J5: Internal | K5: Inprogress | L5: Requirements | M5: Its not browser specific, this occurs in all devices, but the scenario is different | N5: CS Team | O5: The feature has behaved this way since development and may have been missed in the PO requirements.
B6: OB-OP 8.4 Sprint 4 | C6: OB-3926 | D6: CRT Testing | E6: Karthi | F6: Defect | G6: Sponsor Logo Images distorted | H6: Significant | I6: Manual | J6: Internal | K6: Closed | L6: Requirements | M6: QA reported this differences while testing the story, PO also mentioned about this in bug as well | N6: CS Team | O6: Addressed during testing and CS team created a bug to work on it
B7: OB-OP 8.4 Sprint 4 | C7: OB-3927 | D7: CRT Testing | E7: Karthi | F7: Defect | G7: Single Sponsor Logo Stuck on Far Left | H7: Significant | I7: Manual | J7: Internal | K7: Inprogress | L7: Requirements | M7: We didnt have any story to handle single sponsor scenario | N7: CS Team | O7: This is new feature of making the sponsor static and making them to move after certain number of sponsor, so this can be considered as new enhancement instead of bug

Sheet OB-OP 8.4 Sprint 2-Status 
A1: S.No | B1: Application Name | C1: Sprint Start Date | D1: Sprint End Date | E1: Sprint | F1: Developer | G1: Story ID/Defect ID | H1: Description | I1: Status | J1: Estimated(hrs/sp) | K1: Actual(hrs/sp) | L1: Actual Hours Worklog | M1: Dev Start Date | N1: Dev End Date | O1: Unit testing | P1: Peer Tested By | Q1: Peer Tested Defects, if any | R1: Peer Reviewed By | S1: Peer Code Review Comments, if any | T1: PR Number/Link | U1: PR Created Date | V1: PR Approved Date | W1: Onsite Lead Code Review | X1: Code Review Comments, if any | Y1: Client Code Review | Z1: Approved Date | AA1: Code Review Comments, if any2 | AB1: Internal PO -POV Comments | AC1: Client PO -POV Comments | AD1: Comments
A2: 1 | B2: OnlineBidding | C2: 46009 | D2: 46037 | E2: OB-OP 8.4 Sprint 2 | F2: Karthi | G2: OB-3887 | H2: opening up a popup from featured packages before closing the confirmation popup the slider moves to the next package | I2: Completed | J2: 1 | L2: 39.5 | M2: 46010 | N2: 46009 | O2: Done | P2: Mercy | Q2: When bidding from 2 tabs, slide is moving | R2: Preethi | S2: Nil | T2: https://greatergiving.visualstudio.com/Greater%20Giving/_git/OnlineBidding/pullrequest/9120 https://greatergiving.visualstudio.com/Greater%20Giving/_git/OnlineBidding/pullrequest/9142 | U2: 46014 | V2: 46022 | W2: Prabu | X2: Nil | Y2: Joe | Z2: 46022 | AA2: Nil | AB2: Nil | AC2: Nil | AD2: Dev testing completed 12/23/2025 TST testing completed 1/6/2026
A3: 2 | B3: OnlineBidding | C3: 46009 | D3: 46037 | E3: OB-OP 8.4 Sprint 2 | F3: Preethi | G3: OB-3895 | H3: Adjust Activity and Favorites to reflect updated search and pagination | I3: Peer Review | J3: 2 | L3: 31.25 | M3: 46010 | N3: 46014 | O3: Done | P3: Mercy | Q3: Sorting does not work in Favorite Tab | R3: Karthi | S3: Nil | T3: https://greatergiving.visualstudio.com/Greater%20Giving/_git/OnlineBidding/pullrequest/9118 | U3: 46014 | W3: Prabu | AD3: Dev testing completed 12/23/2025
A4: 3 | B4: OnlineBidding | C4: 46009 | D4: 46037 | E4: OB-OP 8.4 Sprint 2 | F4: Prabu | G4: OB-3870 | H4: Read API to determine logged in status | I4: Completed | J4: 1 | L4: 16.25 | M4: 46010 | N4: 46015 | O4: Done | P4: Preethi/Mercy | Q4: Nil | R4: Preethi | S4: Nil | T4: https://greatergiving.visualstudio.com/Greater%20Giving/_git/OnlineBidding/pullrequest/9119 | U4: 46015 | V4: 46028 | W4: Rajesh | X4: Nil | Y4: Joe | Z4: 46028 | AA4: Nil | AB4: Nil | AC4: Nil | AD4: Partial DEV and local testing completed 12/23/2025 TST testing completed 1/6/2026
A5: 4 | B5: OnlineBidding | C5: 46009 | D5: 46037 | E5: OB-OP 8.4 Sprint 2 | F5: Preethi | G5: OB-3872 | H5: Add Quantity Remaining to Package Details | I5: Completed | J5: 1 | L5: 13.75 | M5: 46015 | N5: 46029 | O5: Done | P5: Mercy | Q5: Nil | R5: Karthi | S5: Nil | T5: https://greatergiving.visualstudio.com/Greater%20Giving/_git/OnlineBidding/pullrequest/9138 | U5: 46028 | V5: 46029 | W5: Prabu | X5: Nil | Y5: Joe | Z5: 46029 | AA5: Nil | AB5: Nil | AC5: Nil | AD5: Added the field, need to confirm with PO for positioning for all devices 12/29/2025 Created draft PR 12/30/2025 Dev testing completed 1/6/2026 TST testing completed 1/8/2026
A6: 5 | B6: OnlineBidding | C6: 46009 | D6: 46037 | E6: OB-OP 8.4 Sprint 2 | F6: Karthi | G6: OB-3862 | H6: Adjust Donations in OB | I6: Completed | J6: 2 | L6: 52.25 | M6: 46013 | N6: 46034 | O6: Done | P6: Mercy | Q6: Nil | R6: Preethi | S6: Nil | T6: https://greatergiving.visualstudio.com/Greater%20Giving/_git/OnlineBidding/pullrequest/9130 | U6: 46015 | V6: 46035 | W6: Prabu | X6: Nil | Y6: Joe | Z6: 46035 | AA6: Nil | AB6: Nil | AC6: Nil | AD6: Dev testing completed 12/26/2025
A7: 6 | B7: OnlineBidding | C7: 46009 | D7: 46037 | E7: OB-OP 8.4 Sprint 2 | F7: Preethi | G7: OB-3864 | H7: Package Browse Audit | I7: Peer Review | J7: 5 | L7: 34.75 | M7: 46027 | N7: 46031 | R7: Karthi | S7: Nil | T7: https://greatergiving.visualstudio.com/Greater%20Giving/_git/OnlineBidding/pullrequest/9165
A8: 7 | B8: OnlineBidding | C8: 46009 | D8: 46037 | E8: OB-OP 8.4 Sprint 2 | F8: Preethi | G8: OB-3869 | H8: Ensure proper color selections are represented in OB UX | I8: Completed | J8: 3 | L8: 36 | M8: 46021 | N8: 46030 | O8: Done | P8: Mercy | Q8: Nil | R8: Karthi | S8: Nil | T8: https://greatergiving.visualstudio.com/Greater%20Giving/_git/OnlineBidding/pullrequest/9139 | U8: 46030 | V8: 46034 | W8: Prabu | X8: Nil | Y8: Joe | Z8: 46034 | AA8: Nil | AB8: Nil | AC8: Nil | AD8: Created draft PR, need to discuss with PO regarding 2 more places where color is seen in old UI Dev testing completed 1/6/2026
A9: 8 | B9: OnlineBidding | C9: 46009 | D9: 46037 | E9: OB-OP 8.4 Sprint 2 | F9: Karthi | G9: OB-3891 | H9: Include Sponsor Image tiles between packages | I9: Completed | J9: 2 | L9: 53.25 | M9: 46017 | N9: 46031 | O9: Done | P9: Mercy | Q9: Nil | R9: Preethi | S9: Nil | T9: https://greatergiving.visualstudio.com/Greater%20Giving/_git/OnlineBidding/pullrequest/9143 | U9: 46031 | V9: 46034 | W9: Prabu | X9: Nil | Y9: Joe | Z9: 46034 | AA9: Nil | AB9: Nil | AC9: Nil | AD9: DEV testing completed 1/13/2026
A10: 9 | B10: OnlineBidding | C10: 46009 | D10: 46037 | E10: OB-OP 8.4 Sprint 2 | F10: Preethi | G10: OB-3892 | H10: Display market Value on package Details page | I10: Completed | J10: 2 | L10: 17.25 | M10: 46020 | N10: 46029 | O10: Done | P10: Mercy | Q10: Nil | R10: Karthi | S10: Nil | T10: https://greatergiving.visualstudio.com/Greater%20Giving/_git/OnlineBidding/pullrequest/9138 | U10: 46028 | V10: 46029 | W10: Prabu | X10: Nil | Y10: Joe | Z10: 46029 | AA10: Nil | AB10: Nil | AC10: Nil | AD10: Added the field, need to confirm with PO for positioning for all devices 12/29/2025 Created draft PR 12/30/2025 Dev testing completed 1/6/2026 TST testing completed 1/8/2026
A11: 10 | B11: OnlineBidding | C11: 46009 | D11: 46037 | E11: OB-OP 8.4 Sprint 2 | F11: Preethi | G11: OB-3893 | H11: Related Packages should direct to package Details page | I11: Completed | J11: 2 | L11: 24 | M11: 46013 | N11: 46029 | O11: Done | P11: Mercy | Q11: Not a defect, observed that in old UI we have banner for related packages also, need to confirm with PO if we need the same in new UI also | R11: Karthi | S11: Nil | T11: https://greatergiving.visualstudio.com/Greater%20Giving/_git/OnlineBidding/pullrequest/9132 | U11: 46020 | V11: 46029 | W11: Prabu | X11: Nil | Y11: Joe | Z11: 46029 | AA11: Nil | AB11: Nil | AC11: Nil | AD11: Created draft PR, need to discuss with PO regarding banner change in related package 12/24/2025 Dev testing completed 1/6/2026 TST testing completed 1/8/2026
A12: 11 | B12: OnlineBidding | C12: 46009 | D12: 46037 | E12: OB-OP 8.4 Sprint 2 - [STRETCH] | F12: Mercy - [TESTING ONLY] | G12: OB-3904 | H12: Evaluate the functionality of Online Bidding Settings | I12: Completed | J12: 1 | L12: 15.25 | AD12: Testing efforts alone.
A13: 12 | B13: OnlineBidding | C13: 46009 | D13: 46037 | E13: OB-OP 8.4 Sprint 2 - [STRETCH] | F13: Preethi | G13: OB-3906 | H13: Add functionality for Start Bidding | I13: Completed | J13: 2 | L13: 8.25 | M13: 46034 | N13: 46034 | O13: Done | P13: Mercy | Q13: When clicking start bidding from mobile/tablet, need help popup gets closed but canvas is still seen | R13: Karthi | S13: Nil | T13: https://greatergiving.visualstudio.com/Greater%20Giving/_git/OnlineBidding/pullrequest/9162 | U13: 46034 | W13: Prabu | AD13: Dev testing completed 1/12/2026
A14: 13 | B14: OnlineBidding | C14: 46009 | D14: 46037 | E14: OB-OP 8.4 Sprint 2 - [STRETCH] | F14: Preethi | G14: OB-3907 | H14: Add Price to Multisale "Sold" packages | I14: Completed | J14: 1 | L14: 3 | M14: 46034 | N14: 46034 | O14: Done | P14: Mercy | Q14: Nil | R14: Karthi | S14: Nil | T14: https://greatergiving.visualstudio.com/Greater%20Giving/_git/OnlineBidding/pullrequest/9163 | U14: 46034 | W14: Prabu | AD14: Dev testing completed 1/12/2026
A15: 14 | B15: OnlineBidding | C15: 46009 | D15: 46037 | E15: OB-OP 8.4 Sprint 2 - [STRETCH] | F15: Preethi | G15: OB-3908 | H15: Fix logo in GG footer | I15: Completed | J15: 0.5 | L15: 3.75 | M15: 46034 | N15: 46035 | O15: Done | P15: Mercy | Q15: Nil | R15: Karthi | S15: Nil | T15: https://greatergiving.visualstudio.com/Greater%20Giving/_git/OnlineBidding/pullrequest/9171 | U15: 46035 | W15: Prabu | X15: Nil | Y15: Joe | AD15: Need to check for the logo image with PO today 1/12/2026
A16: 15 | B16: OnlineBidding | C16: 46009 | D16: 46037 | E16: OB-OP 8.4 Sprint 2 - [STRETCH] | F16: Preethi | G16: OB-3894 | H16: Opening Soon filter re-applied to Search options | I16: Completed | J16: 3 | L16: 9.5 | M16: 46034 | N16: 46034 | O16: Done | P16: Mercy | Q16: Nil | R16: Karthi | S16: Nil | T16: https://greatergiving.visualstudio.com/Greater%20Giving/_git/OnlineBidding/pullrequest/9164 | U16: 46034 | AD16: Dev testing completed 1/12/2026

Sheet OB-OP 8.4 Sprint 2-Defect 
A1: S.No | B1: Sprint | C1: Story/Defect ID | D1: Parent Story | E1: Developer | F1: Issue Type | G1: Issue Description | H1: Priority | I1: Defect Source | J1: Type | K1: Status | L1: Root Cause Category | M1: Comments | N1: Found By | O1: RCA Comment
B2: OB-OP 8.4 Sprint 2 | C2: OB-3903 | D2: Regression | F2: Defect | G2: There is no spacing available in the left and right side of detailed page | H2: Significant | I2: Manual | J2: Internal | K2: Open | L2: Existing_Issues | M2: We did Cleanup stories based on designer requirement, detail page was not covered in it yet | N2: Mercy | O2: Need to add this into cleanup document and work in the upcoming sprint
B3: OB-OP 8.4 Sprint 2 | C3: OB-3905 | D3: Regression | F3: Defect | G3: Pop up should be closed when package gets sold | H3: Significant | I3: Manual | J3: Internal | K3: Open | L3: Existing_Issues | M3: This is in old UI, but missed to handle the failure scenario in new UI | N3: Mercy | O3: This is in old UI, but missed to handle the failure scenario in new UI, will be working in upcoming sprint
B4: OB-OP 8.4 Sprint 2 | C4: OB-3901 | D4: Regression | F4: Defect | G4: When we bid or buy any package that appears at the end of the page, after the confirmation pop up box is closed, the page loading is interrupted | H4: Major | I4: Manual | J4: Internal | K4: Open | L4: Development | M4: This was working fine in DEV testing before merging to TST | N4: Mercy | O4: Joe updated few lines as part of review which caused this issue and this has been fixed as part of OB-3895

Sheet OB-OP 8.4 Sprint 1-Status 
A1: S.No | B1: Application Name | C1: Sprint Start Date | D1: Sprint End Date | E1: Sprint | F1: Developer | G1: Story ID/Defect ID | H1: Description | I1: Status | J1: Estimated(hrs/sp) | K1: Actual(hrs/sp) | L1: Actual Hours Worklog | M1: Dev Start Date | N1: Dev End Date | O1: Unit testing | P1: Peer Tested By | Q1: Peer Tested Defects, if any | R1: Peer Reviewed By | S1: Peer Code Review Comments, if any | T1: PR Number/Link | U1: PR Created Date | V1: PR Approved Date | W1: Onsite Lead Code Review | X1: Code Review Comments, if any | Y1: Client Code Review | Z1: Approved Date | AA1: Code Review Comments, if any2 | AB1: Internal PO -POV Comments | AC1: Client PO -POV Comments | AD1: Comments
A2: 1 | B2: OnlineBidding | C2: 45995 | D2: 46009 | E2: OB-OP 8.4 Sprint 1 | F2: Prabu | G2: OB-3860 | H2: Update to Privacy Policy | I2: Completed | J2: 1 | M2: 45996 | N2: 46002 | O2: Done | P2: Prabu | Q2: Nil | R2: Joe | S2: Nil | T2: https://greatergiving.visualstudio.com/Greater%20Giving/_git/OnlineBidding/pullrequest/9097 | U2: 46002 | V2: 46002 | W2: Rajesh | X2: Nil | Y2: Joe | Z2: 46002 | AA2: Nil | AB2: Nil | AC2: Nil | AD2: Prabu and client QA tested in CRT
A3: 2 | B3: OnlineBidding | C3: 45995 | D3: 46009 | E3: OB-OP 8.4 Sprint 1 | F3: Preethi | G3: OB-3884 | H3: Sponsor bar when set to top and donation bar are not appearing on the bidding page | I3: Completed | J3: 1 | M3: 45996 | N3: 45996 | O3: Done | P3: Mercy | Q3: Nil | R3: Karthi | S3: Nil | T3: https://greatergiving.visualstudio.com/Greater%20Giving/_git/OnlineBidding/pullrequest/9081 | U3: 45996 | V3: 46001 | W3: Prabu | X3: Nil | Y3: Joe | Z3: 46001 | AA3: Nil | AB3: Nil | AC3: Nil | AD3: Dev testing completed 12/5/2025 TST testing completed 12/16/2025
A4: 3 | B4: OnlineBidding | C4: 45995 | D4: 46009 | E4: OB-OP 8.4 Sprint 1 | F4: Preethi | G4: OB-3883 | H4: multi-sale package purchased text missing from package banner | I4: Completed | J4: 1 | M4: 45996 | N4: 45996 | O4: Done | P4: Mercy | Q4: Nil | R4: Karthi | S4: Nil | T4: https://greatergiving.visualstudio.com/Greater%20Giving/_git/OnlineBidding/pullrequest/9082 | U4: 45996 | V4: 46008 | W4: Prabu | X4: Nil | Y4: Joe | Z4: 46008 | AA4: Move the condition from HTML to ts file | AB4: Nil | AC4: Nil | AD4: Dev testing completed 12/5/2025 TST testing completed 12/17/2025
A5: 4 | B5: OnlineBidding | C5: 45995 | D5: 46009 | E5: OB-OP 8.4 Sprint 1 | F5: Preethi | G5: OB-3885 | H5: when bidding on a package from page 4 and is outbid and bid is clicked again, the page is refreshed and returned to page 1 | I5: Completed | J5: 1 | M5: 45996 | N5: 46006 | O5: Done | P5: Mercy | Q5: when we bid or buy any package that appears at the end of the page, after the confirmation pop up box is closed, the page loading is interrupted | R5: Karthi | S5: Nil | T5: https://greatergiving.visualstudio.com/Greater%20Giving/_git/OnlineBidding/pullrequest/9083 | U5: 45999 | V5: 46009 | W5: Prabu | X5: Nil | Y5: Joe | Z5: 46009 | AA5: Nil | AB5: Nil | AC5: Nil | AD5: Dev testing completed 12/8/2025 Tried a different approach for the bug which mercy mentioned in DEV 12/15/2025 DEV testing completed 12/17/2025 TST testing completed 12/18/2025
A6: 5 | B6: OnlineBidding | C6: 45995 | D6: 46009 | E6: OB-OP 8.4 Sprint 1 | F6: Preethi/Karthi | G6: OB-3887 | H6: Caching Improvements | I6: Completed | J6: 3 | M6: 46001 | N6: 46002 | O6: Done | P6: Mercy | Q6: Nil | R6: Preethi/Karthi | S6: Nil | T6: https://greatergiving.visualstudio.com/Greater%20Giving/_git/OnlineBidding/pullrequest/9072 | U6: 46003 | V6: 46008 | W6: Prabu | X6: Nil | Y6: Joe | Z6: 46008 | AA6: Nil | AD6: Waiting for Joe to review the PR, if he gives any suggestion,will work on that. So as of now it is on hold 12/05/2025 Joe mentioned 2 points will satrt work on that 12/10/2025 Dev testing completed 12/12/2025 TST testing completed 12/17/2025
A7: 6 | B7: OnlineBidding | C7: 45995 | D7: 46009 | E7: OB-OP 8.4 Sprint 1 | F7: Preethi | G7: OB-3897 | H7: Move Pagination from Client to Server | I7: Completed | J7: 5 | M7: 45999 | N7: 46002 | O7: Done | P7: Mercy | Q7: Nil | R7: Karthi | S7: Nil | T7: https://greatergiving.visualstudio.com/Greater%20Giving/_git/OnlineBidding/pullrequest/9101 | U7: 46003 | V7: 46009 | W7: Prabu | X7: Nil | Y7: Joe | Z7: 46009 | AA7: 1.use of ToLower() will cause significant issues (full table scans, bypassing indexes and unneeded comparisons 2. Stick with the use of hasValue() checks over !=NULL. HasValue translates to IS NOT NULL in SQL. We should flag this for optimization later. It will get called frequently. | AB7: Nil | AC7: Nil | AD7: Dev testing completed 12/12/2025
A8: 7 | B8: OnlineBidding | C8: 45995 | D8: 46009 | E8: OB-OP 8.4 Sprint 1 - [STRETCH] | F8: Karthi | G8: OB-3887 | H8: opening up a popup from featured packages before closing the confirmation popup the slider moves to the next package | I8: Being Developed | J8: 1 | M8: 46003 | P8: Mercy | Q8: 1. When we keep the pop up open for multisale packages, slider moves to the next package 2. When a bidder goes outbid, Slider moves to the next package | AD8: Dev testing completed12/16/2025
A9: 8 | B9: OnlineBidding | C9: 45995 | D9: 46009 | E9: OB-OP 8.4 Sprint 1 - [STRETCH] | F9: Preethi | G9: OB-3895 | H9: Adjust Activity and Favorites to reflect updated search and pagination | I9: Being Developed | J9: 3 | M9: 46003

Sheet OB-OP 8.4 Sprint 1-Defect
A1: S.No | B1: Sprint | C1: Story/Defect ID | D1: Parent Story | E1: Developer | F1: Issue Type | G1: Issue Description | H1: Priority | I1: Defect Source | J1: Type | K1: Status | L1: Root Cause Category | M1: Comments | N1: Found By | O1: RCA Comment

Sheet OB-OP 8.3 Sprint 4-Status
A1: S.No | B1: Application Name | C1: Sprint Start Date | D1: Sprint End Date | E1: Sprint | F1: Developer | G1: Story ID/Defect ID | H1: Description | I1: Status | J1: Estimated(hrs/sp) | K1: Actual(hrs/sp) | L1: Actual Hours Worklog | M1: Dev Start Date | N1: Dev End Date | O1: Unit testing | P1: Peer Tested By | Q1: Peer Tested Defects, if any | R1: Peer Reviewed By | S1: Peer Code Review Comments, if any | T1: PR Number/Link | U1: PR Created Date | V1: PR Approved Date | W1: Onsite Lead Code Review | X1: Code Review Comments, if any | Y1: Client Code Review | Z1: Approved Date | AA1: Code Review Comments, if any2 | AB1: Internal PO -POV Comments | AC1: Client PO -POV Comments | AD1: Comments
A2: 1 | B2: OnlineBidding | C2: 45981 | D2: 45995 | E2: OB-OP 8.3 Sprint 4 | F2: Preethi | G2: OB-3877 | H2: Caching Improvements | I2: Peer Review | J2: 5 | L2: 69 | M2: 45982 | N2: 45994 | O2: Done | P2: Mercy | Q2: Nil | R2: Karthi | S2: NIl | T2: https://greatergiving.visualstudio.com/Greater%20Giving/_git/OnlineBidding/pullrequest/9072 | U2: 45994 | W2: Prabu | AD2: Mapping the paramters to the existing calls, working on cache json 11/25/2025 Will close with what we have done for this sprint 12/3/2025
A3: 2 | B3: OnlineBidding | C3: 45981 | D3: 45995 | E3: OB-OP 8.3 Sprint 4 | F3: Karthi | G3: OB-3865 | H3: Package Sort does not appear to apply | I3: Completed | J3: 3 | L3: 47 | M3: 45986 | N3: 45993 | O3: Done | P3: Mercy | Q3: Nil | R3: Preethi | S3: Nil | T3: https://greatergiving.visualstudio.com/Greater%20Giving/_git/OnlineBidding/pullrequest/9059 | U3: 45992 | V3: 45995 | W3: Prabu | X3: Nil | Y3: Joe | Z3: 45995 | AA3: Nil | AB3: Nil | AC3: Nil | AD3: DEV testing completed 12/2/2025 This PR is dependent on OB-3881, once that is completed, this will be moved
A4: 3 | B4: OnlineBidding | C4: 45981 | D4: 45995 | E4: OB-OP 8.3 Sprint 4 | F4: Karthi | G4: OB-3846 | H4: Package Browse area is stretched | I4: Completed | J4: 2 | L4: 20.75 | M4: 45989 | N4: 45993 | O4: Done | P4: Mercy | Q4: Nil | R4: Preethi | S4: Nil | T4: https://greatergiving.visualstudio.com/Greater%20Giving/_git/OnlineBidding/pullrequest/9061 | U4: 45992 | V4: 45993 | W4: Prabu | X4: Nil | Y4: Joe | Z4: 45993 | AA4: Nil | AB4: Nil | AC4: Nil | AD4: Once the priority stories are done, we will be taking this story TST testing done and raised defect 12/3/2025
A5: 4 | B5: OnlineBidding | C5: 45981 | D5: 45995 | E5: OB-OP 8.3 Sprint 4 | F5: Mercy | G5: OB-3880 | H5: OB 8.3.0 CRT release | I5: Completed | J5: 3 | L5: 51 | M5: 11/26/2025 (Not development in this case, testing started date is Nov 26) | N5: 45994 | AD5: Once deployed to CRT, this story will be taken Tested and created bugs under the story
A6: 5 | B6: OnlineBidding | C6: 45981 | D6: 45995 | E6: OB-OP 8.3 Sprint 4 - [STRETCH] | F6: Preethi | G6: OB-3881 | H6: Imrpovement to Search functionality | I6: Completed | J6: 2 | L6: 22.25 | M6: 45988 | N6: 45989 | O6: Done | P6: Mercy | R6: Karthi | S6: Nil | T6: https://greatergiving.visualstudio.com/Greater%20Giving/_git/OnlineBidding/pullrequest/9057 | U6: 45992 | V6: 45994 | W6: Prabu | X6: Nil | Y6: Joe | Z6: 45994 | AA6: 1. No need to check > 0 against length. An empty array returns 0 (falsy), so just _this.selectedFilter?.category?.length. Use (?.) to safely chain it. 2. Better to check price === 'number' than !==null. That's what we really care about. | AB6: Nil | AC6: Nil | AD6: This story was created and added on Nov 27 as some additional work was needed for cache story to be proceed, so that work was done as part of this story DEV testing completed 12/4/2025
A7: 6 | B7: OnlineBidding | C7: 45981 | D7: 45995 | E7: OB-OP 8.3 Sprint 4 | F7: Karthi | G7: OB-3888 - [DEFECT] | H7: Packages under Activity area seems to be stretched | I7: Completed | L7: 11.5 | M7: 45994 | N7: 45994 | O7: Done | P7: Mercy | R7: Preethi | S7: Nil | T7: https://greatergiving.visualstudio.com/Greater%20Giving/_git/OnlineBidding/pullrequest/9071 | U7: 45994 | V7: 45995 | W7: Prabu | X7: Nil | Y7: Joe | Z7: 45995 | AA7: Nil | AB7: Nil | AC7: Nil | AD7: DEV testing completed 12/3/2025

Sheet OB-OP 8.3 Sprint 4-Defect
A1: S.No | B1: Sprint | C1: Story/Defect ID | D1: Parent Story | E1: Developer | F1: Issue Type | G1: Issue Description | H1: Priority | I1: Defect Source | J1: Type | K1: Status | L1: Root Cause Category | M1: Comments | N1: Found By | O1: RCA Comment
B2: OB-OP 8.3 Sprint 2 | C2: OB-3883 | D2: OB-3880 | F2: Defect | G2: Multi-sale package purchased text missing from package banner | H2: Significant | I2: Manual | J2: Internal | K2: Open | L2: Enhancements | M2: This was working fine, Not sure how existing functionalities got broken | N2: Mercy | O2: Need to check the recent changes as we are not sure how it got broken
B3: OB-OP 8.3 Sprint 2 | C3: OB-3884 | D3: OB-3880 | F3: Defect | G3: Sponsor bar when set to top and donation bar are not appearing on the bidding page | H3: Significant | I3: Manual | J3: Internal | K3: Open | L3: Enhancements | M3: This was working fine as part of OB-3684 and OB-3682, broken due to url change story OB-3859 | N3: Mercy | O3: During url change, checked only the url changes, missed to check the existing functionality in the url changed pages
B4: OB-OP 8.3 Sprint 2 | C4: OB-3885 | D4: OB-3880 | F4: Defect | G4: When bidding on a package from page 4 and is outbid and bid is clicked again, the page is refreshed and returned to page 1 | H4: Significant | I4: Manual | J4: Internal | K4: Open | L4: Enhancements | M4: This was a miss from developers and dev environment testing while pagination story was implemented. Concentrated more on Pagination and search functionality along with filter and hence missed to check bidding | N4: Mercy | O4: This is due to the pagination enhancement, need to check signalr behaviour whenever we implement new things
B5: OB-OP 8.3 Sprint 2 | C5: OB-3886 | D5: OB-3880 | F5: Defect | G5: If we have more than 24 packages but less than 48 packages and the pagination option enabled, some package duplicates are seen | H5: Significant | I5: Manual | J5: Internal | K5: Open | L5: Enhancements | M5: This was a miss from developers and dev environment testing while pagination story was implemented. Concentrated more on Pagination and search functionality along with filter and hence missed to check bidding | N5: Mercy | O5: This is due to the pagination enhancement, need to check signalr behaviour whenever we implement new things
B6: OB-OP 8.3 Sprint 2 | C6: OB-3887 | D6: OB-3880 | F6: Defect | G6: Opening up a popup from featured packages before closing the confirmation popup the slider moves to the next package | H6: Significant | I6: Manual | J6: Internal | K6: Open | L6: Enhancements | M6: This is a known issue since development, tried many approaches in initial days of development itself, but this was not working as expected, so need to research and work on this | N6: Mercy | O6: Known issue, need some time to research on the behaviour
B7: OB-OP 8.3 Sprint 2 | C7: OB-3888 | D7: OB-3846 | E7: Karthi | F7: Defect | G7: Packages under Activity area seems to be stretched | H7: Minor | I7: Manual | J7: Internal | K7: Closed | L7: Enhancements | M7: It is missed while making the changes for OB-3846 | N7: Mercy | O7: Need to check all the pages when making any design changes

Sheet OB-OP 8.3 Sprint 3-Status
A1: S.No | B1: Application Name | C1: Sprint Start Date | D1: Sprint End Date | E1: Sprint | F1: Developer | G1: Story ID/Defect ID | H1: Description | I1: Status | J1: Estimated(hrs/sp) | K1: Actual(hrs/sp) | L1: Actual Hours Worklog | M1: Dev Start Date | N1: Dev End Date | O1: Unit testing | P1: Peer Tested By | Q1: Peer Tested Defects, if any | R1: Peer Reviewed By | S1: Peer Code Review Comments, if any | T1: PR Number/Link | U1: PR Created Date | V1: PR Approved Date | W1: Onsite Lead Code Review | X1: Code Review Comments, if any | Y1: Client Code Review | Z1: Approved Date | AA1: Code Review Comments, if any2 | AB1: Internal PO -POV Comments | AC1: Client PO -POV Comments | AD1: Comments
A2: 1 | B2: OnlineBidding | C2: 45967 | D2: 45981 | E2: OB-OP 8.3 Sprint 3 | F2: Preethi | G2: OB-3836 | H2: Package Filters - Clear Filter does not clear any selected checkbox | I2: Completed | J2: 2 | L2: 38 | M2: 45968 | N2: 45973 | O2: Done | P2: Mercy | Q2: 1.When we filter with Category "All" and Status, results are incorrect 2. When we filter status, category and price, results are incorrect | R2: Karthi | S2: Nil | T2: https://greatergiving.visualstudio.com/Greater%20Giving/_git/OnlineBidding/pullrequest/8997 | U2: 45973 | V2: 45974 | W2: Prabu | X2: Nil | Y2: Joe | Z2: 45974 | AA2: Nil | AB2: Nil | AC2: Nil | AD2: Dev testing is in progress 11/10/2025 DEV testing completed 11/12/2025 TST testing completed 11/19/2025
A3: 2 | B3: OnlineBidding | C3: 45967 | D3: 45981 | E3: OB-OP 8.3 Sprint 3 | F3: Karthi | G3: OB-3861 | H3: Add "default" image to package list view | I3: Completed | J3: 1 | L3: 20.5 | M3: 45968 | N3: 45968 | O3: Done | P3: Mercy | Q3: Nil | R3: Preethi | S3: Nil | T3: https://greatergiving.visualstudio.com/Greater%20Giving/_git/OnlineBidding/pullrequest/8992 | U3: 45968 | V3: 45973 | W3: Prabu | X3: Nil | Y3: Joe | Z3: 45973 | AA3: Nil | AB3: Nil | AC3: Nil | AD3: Dev testing completed 11/10/2025 TST testing completed 11/12/2025
A4: 3 | B4: OnlineBidding | C4: 45967 | D4: 45981 | E4: OB-OP 8.3 Sprint 3 | F4: Karthi | G4: OB-3846 | H4: Package Browse area is stretched | I4: Peer Review | J4: 2 | L4: 9.25 | M4: 45968 | N4: 45968 | O4: Done | P4: Mercy | Q4: Nil | R4: Preethi | S4: Nil | T4: https://greatergiving.visualstudio.com/Greater%20Giving/_git/OnlineBidding/pullrequest/8991 | AD4: Updated the code change and shared the branch - yet to confirm with PO
A5: 5 | B5: OnlineBidding | C5: 45967 | D5: 45981 | E5: OB-OP 8.3 Sprint 3 | F5: Preethi | G5: OB-3875 | H5: Implement pagination on OB UX | I5: Completed | J5: 5 | L5: 61.75 | M5: 45972 | N5: 45980 | O5: Done | P5: Mercy | Q5: 1. Pagination is not working during search 2. Clear filter isn't working for status filter alone 3. Category filter results are incorrect | R5: Karthi | S5: Nill | T5: https://greatergiving.visualstudio.com/Greater%20Giving/_git/OnlineBidding/pullrequest/9006 | U5: 45980 | V5: 45981 | W5: Prabhu | X5: Nill | Y5: Joe | Z5: 45981 | AA5: Nil | AB5: Nil | AC5: Nil | AD5: Dev testing in progress 11/18/2025 Dev testing completed 11/19/2025
A6: 6 | B6: OnlineBidding | C6: 45967 | D6: 45981 | E6: OB-OP 8.3 Sprint 3 | F6: Karthi | G6: OB-3876 | H6: Search auto-complete function | I6: Completed | J6: 5 | L6: 59.75 | M6: 45973 | N6: 45980 | P6: Mercy | Q6: 1. When we click out of the search box search drop down is still visible 2. Unable to clear search box 3. Search field box is partially highlighted 4. After a fix, mouse click is not working only keyboard click is working to selct any package 5. Dropdown is seen visible even after we move to any other browser tab and navigate to OB page | R6: Preethi | S6: Nill | T6: https://greatergiving.visualstudio.com/Greater%20Giving/_git/OnlineBidding/pullrequest/9024 | U6: 45980 | V6: 45980 | W6: Prabhu | X6: Nil | Y6: Joe | Z6: 45980 | AA6: Nil | AB6: Nil | AC6: Nil | AD6: Dev testing in progress 11/18/2025 Dev testing completed 11/19/2025 TST testing completed 11/20/2025
A7: 7 | B7: OnlineBidding | C7: 45967 | D7: 45981 | E7: OB-OP 8.3 Sprint 3 | F7: Prabu | G7: OB-3870 | H7: Read API to determine logged in status | I7: Being Developed | J7: 2

Sheet OB-OP 8.3 Sprint 3-Defect
A1: S.No | B1: Sprint | C1: Story/Defect ID | D1: Parent Story | E1: Developer | F1: Issue Type | G1: Issue Description | H1: Priority | I1: Defect Source | J1: Type | K1: Status | L1: Root Cause Category | M1: Comments | N1: Found By | O1: RCA Comment

Sheet OB-OP 8.3 Sprint 2-Status
A1: S.No | B1: Application Name | C1: Sprint Start Date | D1: Sprint End Date | E1: Sprint | F1: Developer | G1: Story ID/Defect ID | H1: Description | I1: Status | J1: Estimated(hrs/sp) | K1: Actual(hrs/sp) | L1: Actual Hours Worklog | M1: Dev Start Date | N1: Dev End Date | O1: Unit testing | P1: Peer Tested By | Q1: Peer Tested Defects, if any | R1: Peer Reviewed By | S1: Peer Code Review Comments, if any | T1: PR Number/Link | U1: PR Created Date | V1: PR Approved Date | W1: Onsite Lead Code Review | X1: Code Review Comments, if any | Y1: Client Code Review | Z1: Approved Date | AA1: Code Review Comments, if any2 | AB1: Internal PO -POV Comments | AC1: Client PO -POV Comments | AD1: Comments
A2: 1 | B2: OnlineBidding | C2: 45953 | D2: 45967 | E2: OB-OP 8.3 Sprint 2 | F2: Preethi | G2: OB-3845 | H2: Connect process and UI for multiple sale packages | I2: Completed | J2: 3 | M2: 45954 | N2: 45958 | O2: Done | P2: Mercy | Q2: 1. Disable + when max quantity is exceeded 2. Hide the price when all are purchased or if the package is closed | R2: Karthi | S2: Nil | T2: https://greatergiving.visualstudio.com/Greater%20Giving/_git/OnlineBidding/pullrequest/8953 | U2: 45958 | V2: 45961 | W2: Prabu | X2: 1. Move the magic string to constants 2. Simplify the if condition to more readable | Y2: Joe | Z2: 45961 | AA2: 1. Let's throw some error handling on the methods that aren't just calling other methods. 2. Make sure to implement onDestroy since we're using it. | AB2: Nil | AC2: Nil | AD2: 10/27/2025 Dev testing in Progress DEV testing completed 10/30/2025 Partial TST testing completed 10/31/2025
A3: 2 | B3: OnlineBidding | C3: 45953 | D3: 45967 | E3: OB-OP 8.3 Sprint 2 | F3: Karthi | G3: OB-3850 | H3: UX - Update to Details Pages | I3: Completed | J3: 1 | M3: 45954 | N3: 45954 | O3: Done | P3: Mercy | Q3: Donation bar was seen in footer | R3: Preethi | S3: Nil | T3: https://greatergiving.visualstudio.com/Greater%20Giving/_git/OnlineBidding/pullrequest/8952 | U3: 45954 | V3: 45955 | W3: Prabu | X3: Nil | Y3: Joe | Z3: 45955 | AA3: Nil | AB3: Nil | AC3: Nil | AD3: Dev testing completed 10/24/2025 TST testing completed 10/27/2025
A4: 3 | B4: OnlineBidding | C4: 45953 | D4: 45967 | E4: OB-OP 8.3 Sprint 2 | F4: Karthi | G4: OB-3847 | H4: Add a Get Started button to the header bar | I4: Completed | J4: 2 | M4: 45954 | N4: 45958 | O4: Done | P4: Mercy | Q4: Nil | R4: Preethi | S4: Nil | T4: https://greatergiving.visualstudio.com/Greater%20Giving/_git/OnlineBidding/pullrequest/8953 | U4: 45958 | V4: 45960 | W4: Prabu | X4: Avoid repeated codes in the same file | Y4: Joe | Z4: 45960 | AA4: Nil | AB4: Nil | AC4: Nil | AD4: Dev testing completed 10/30/2025 TST testing completed 10/31/2025
A5: 4 | B5: OnlineBidding | C5: 45953 | D5: 45967 | E5: OB-OP 8.3 Sprint 2 | F5: Karthi/Preethi | G5: OB-3848 | H5: Create logout function for OB slide out menu | I5: Completed | J5: 3 | M5: 45958 | N5: 45966 | O5: Done | P5: Mercy/Karthi/Preethi | Q5: Nil | R5: Preethi | S5: Nil | T5: https://greatergiving.visualstudio.com/Greater%20Giving/_git/OnlineBidding/pullrequest/8962 | U5: 45965 | V5: 45967 | W5: Prabu | X5: Nil | Y5: Joe | Z5: 45967 | AA5: Nil | AB5: Nil | AC5: Nil | AD5: Partial DEV testing done 10/29/2025
A6: 5 | B6: OnlineBidding | C6: 45953 | D6: 45967 | E6: OB-OP 8.3 Sprint 2 | F6: Prabu/Karthi/Preethi | G6: OB-3858 | H6: Implement functionality for Donate and View Profile | I6: Completed | J6: 3 | M6: 45957 | N6: 45964 | O6: Done | P6: Mercy | Q6: Nil | R6: Karthi/Preethi | S6: Nil | T6: https://greatergiving.visualstudio.com/Greater%20Giving/_git/OnlineBidding/pullrequest/8974 | U6: 45964 | V6: 45965 | W6: Prabu | X6: Nil | Y6: Joe | Z6: 45965 | AA6: Nil | AB6: Nil | AC6: Nil | AD6: Partial DEV testing done 10/30/2025
A7: 6 | B7: OnlineBidding | C7: 45953 | D7: 45967 | E7: OB-OP 8.3 Sprint 2 | F7: Preethi/Karthi/Prabu | G7: OB-3855 | H7: Continue Angular Update | I7: Completed | J7: 1 | M7: 45966
A8: 7 | B8: OnlineBidding | C8: 45953 | D8: 45967 | E8: OB-OP 8.3 Sprint 2 | F8: Preethi | G8: OB-3868 [DEFECT] | H8: Sign In Button is seen on the Detail page instead of Buy button | I8: Completed | M8: 45961 | N8: 45961 | O8: Done | P8: Mercy | Q8: Nil | R8: Karthi | S8: Nil | T8: https://greatergiving.visualstudio.com/Greater%20Giving/_git/OnlineBidding/pullrequest/8973 | U8: 45961 | V8: 45964 | W8: Prabu | X8: Nil | Y8: Joe | Z8: 45964 | AA8: Nil | AB8: Nil | AC8: Nil | AD8: DEV testing completed 10/31/2025
A9: 8 | B9: OnlineBidding | C9: 45953 | D9: 45967 | E9: OB-OP 8.3 Sprint 2 - [STRETCH] | F9: Karthi | G9: OB-3859 | H9: Adjust OB new URLs | I9: Completed | J9: 3 | M9: 45964 | N9: 45965 | O9: Done | P9: Preethi/Karthi | Q9: Nil | R9: Preethi | S9: Nil | T9: https://greatergiving.visualstudio.com/Greater%20Giving/_git/OnlineBidding/pullrequest/8977 | U9: 45966 | V9: 45967 | W9: Prabu | X9: Nil | Y9: Joe | Z9: 45967 | AA9: Nil | AB9: Nil | AC9: Nil

Sheet OB-OP 8.3 Sprint 2-Defect
A1: S.No | B1: Sprint | C1: Story/Defect ID | D1: Parent Story | E1: Developer | F1: Issue Type | G1: Issue Description | H1: Priority | I1: Defect Source | J1: Type | K1: Status | L1: Root Cause Category | M1: Comments | N1: Found By | O1: RCA Comment
B2: OB-OP 8.3 Sprint 2 | C2: OB-3868 | D2: OB-3845 | E2: Preethi | F2: Defect | G2: Sign In Button is seen on the Detail page instead of Buy button | H2: Major | I2: Manual | J2: Internal | K2: Closed | L2: Development | M2: While testing this story in DEV, eveything was working correctly. Due to the changes done in the before PR, that change has affected in this branch | N2: Prabu | O2: While giving multiple PR at the same time, need to do complete testing in all pages. Though we did testing by merging both changes, missed to check in detail page

Sheet OB-OP 8.3 Sprint 1-Status
A1: S.No | B1: Application Name | C1: Sprint Start Date | D1: Sprint End Date | E1: Sprint | F1: Developer | G1: Story ID/Defect ID | H1: Description | I1: Status | J1: Estimated(hrs/sp) | K1: Actual(hrs/sp) | L1: Actual Hours Worklog | M1: Dev Start Date | N1: Dev End Date | O1: Unit testing | P1: Peer Tested By | Q1: Peer Tested Defects, if any | R1: Peer Reviewed By | S1: Peer Code Review Comments, if any | T1: PR Number/Link | U1: PR Created Date | V1: PR Approved Date | W1: Onsite Lead Code Review | X1: Code Review Comments, if any | Y1: Client Code Review | Z1: Approved Date | AA1: Code Review Comments, if any2 | AB1: Internal PO -POV Comments | AC1: Client PO -POV Comments | AD1: Comments
A2: 1 | B2: OnlineBidding | C2: 45939 | D2: 45953 | E2: OB-OP 8.3 Sprint 1 | F2: Preethi | G2: OB-3834 | H2: Clicking a users name should open user slide out menu | I2: Completed | J2: 3 | L2: 45.75 | M2: 45940 | N2: 45947 | O2: Done | P2: Mercy | Q2: 1. When Bidder Number is 0 it should not be displayed in OB side as 0 2. Home Icon should navigate to home page 3. When Ketcy K is given as user name in GGO side, on the OB side K alone is displayed in the icon which is wrong | R2: Karthi | S2: Nil | T2: https://greatergiving.visualstudio.com/Greater%20Giving/_git/OnlineBidding/pullrequest/8920 | U2: 45946 | V2: 45951 | W2: Prabu | X2: Nil | Y2: Joe | Z2: 45951 | AA2: Nil | AB2: Nil | AC2: Nil | AD2: DEV testing completed 10/15/2025 TST testing completed 10/21/2025
A3: 2 | B3: OnlineBidding | C3: 45939 | D3: 45953 | E3: OB-OP 8.3 Sprint 1 | F3: Karthi | G3: OB-3842 | H3: OB Clean Up | I3: Completed | J3: 5 | L3: 62 | M3: 45940 | N3: 45951 | O3: Done | P3: Mercy | Q3: Nil | R3: Preethi | S3: Nil | T3: https://greatergiving.visualstudio.com/Greater%20Giving/_git/OnlineBidding/pullrequest/8927 | U3: 45946 | V3: 45952 | W3: Prabu | X3: Nil | Y3: Joe | Z3: 45952 | AA3: Nil | AB3: Nil | AC3: Nil | AD3: Local testing completed 10/16/2025 DEV testing completed 10/22/2025 TST testing completed 10/23/2025
A4: 3 | B4: OnlineBidding | C4: 45939 | D4: 45953 | E4: OB-OP 8.3 Sprint 1 - [Spike] | F4: Prabu | G4: OB-3835 | H4: Determine if a user is logged into GGAM/Donor Platform on Bidding Site | I4: Completed | J4: 3 | L4: 2.75 | M4: 45939 | N4: 45953 | AD4: Added investigation result in JIRA comments 10/23/2025
A5: 4 | B5: OnlineBidding | C5: 45939 | D5: 45953 | E5: OB-OP 8.3 Sprint 1 | F5: Preethi | G5: OB-3827 | H5: Allow zooming in on Package Details | I5: Completed | J5: 5 | L5: 36.25 | M5: 45945 | N5: 45952 | O5: Done | P5: Mercy | Q5: Nil | R5: Karthi | S5: Nil | T5: https://greatergiving.visualstudio.com/Greater%20Giving/_git/OnlineBidding/pullrequest/8926 | U5: 45947 | V5: 45952 | W5: Prabu | X5: Nil | Y5: Joe | Z5: 45952 | AA5: Nil | AB5: Nil | AC5: Nil | AD5: DEV testing in progress 10/17/2025 DEV testing completed for the bug under this story 10/22/2025 TST testing completed 10/23/2025
A6: 5 | B6: OnlineBidding | C6: 45939 | D6: 45953 | E6: OB-OP 8.3 Sprint 1 | F6: Preethi | G6: OB-3843 | H6: Ob - Continue Angular update | I6: Completed | J6: 1 | L6: 9 | M6: 45951 | N6: 45953 | AD6: Added current sprint pogress in JIRA comments 10/23/2025
A7: 6 | B7: OnlineBidding | C7: 45939 | D7: 45953 | E7: OB-OP 8.3 Sprint 1 - [Stretch] | F7: Karthi | G7: OB-3838 | H7: Remove image borders on Package Details page | I7: Completed | J7: 1 | L7: 20.5 | M7: 45947 | N7: 45951 | O7: Done | P7: Mercy | Q7: Few images are seen as stretched in some scenarios but this is an existing scenario in browse page also | R7: Preethi | S7: Nil | T7: https://greatergiving.visualstudio.com/Greater%20Giving/_git/OnlineBidding/pullrequest/8929 | U7: 45951 | V7: 45952 | W7: Prabu | X7: Nil | Y7: Joe | Z7: 45952 | AA7: Nil | AB7: Nil | AC7: Nil | AD7: DEV testing completed 10/21/2025 TST testing completed 10/22/2025
A8: 7 | B8: OnlineBidding | C8: 45939 | D8: 45953 | E8: OB-OP 8.3 Sprint 1 - [Stretch] | F8: Karthi | G8: OB-3841 | H8: Update Help area to be clickable | I8: Completed | J8: 1 | L8: 6.75 | M8: 45947 | N8: 45951 | O8: Done | P8: Mercy | Q8: When clicking the link inside need help, it is opening in same tab and clicking browser back refreshes the page, but in old UI the links are opening in separate tab | R8: Preethi | S8: Nil | T8: https://greatergiving.visualstudio.com/Greater%20Giving/_git/OnlineBidding/pullrequest/8930 | U8: 45951 | V8: 45952 | W8: Prabu | X8: Nil | Y8: Joe | Z8: 45952 | AA8: Nil | AB8: Nil | AC8: Nil | AD8: DEV testing completed 10/21/2025 TST testing completed 10/22/2025
A9: 8 | B9: OnlineBidding | C9: 45939 | D9: 45953 | E9: OB-OP 8.3 Sprint 1 - [Stretch] | F9: Karthi | G9: OB-3846 | H9: Package Browse area is stretched | I9: Being Developed | J9: 2 | L9: 15 | M9: 45947 | AD9: out of 2 points, one point is developed but regarding other point, need to discuss and confirm with PO 10/17/2025 Pending point will be done in upcoming sprint as the requirement is not decided fully
A10: 9 | B10: OnlineBidding | C10: 45939 | D10: 45953 | E10: OB-OP 8.3 Sprint 1 | F10: Preethi | G10: OB-3852 - Defect | H10: zoomed section of image does not display when hovering over an image | I10: Completed | L10: 8.5 | M10: 45952 | N10: 45952 | O10: Done | P10: Mercy | Q10: Nil | R10: Prabu | S10: Nil | T10: https://greatergiving.visualstudio.com/Greater%20Giving/_git/OnlineBidding/pullrequest/8940 | U10: 45952 | V10: 45952 | W10: Prabu | X10: Nil | Y10: Joe | Z10: 45952 | AA10: Nil | AB10: Nil | AC10: Nil | AD10: DEV testing completed 10/22/2025 TST testing completed 10/23/2025

Sheet OB-OP 8.3 Sprint 1-Defect
A1: S.No | B1: Sprint | C1: Story/Defect ID | D1: Parent Story | E1: Developer | F1: Issue Type | G1: Issue Description | H1: Priority | I1: Defect Source | J1: Type | K1: Status | L1: Root Cause Category | M1: Comments | N1: Found By | O1: RCA Comment
B2: OB-OP 8.3 Sprint 1 | C2: OB-3852 | D2: OB-3827 | E2: Preethi | F2: Defect | G2: zoomed section of image does not display when hovering over an image | H2: Significant | I2: Manual | J2: Internal | K2: Closed | L2: Development | M2: It is not due to development, while merging the PR some code would have been missed | N2: Alice | O2: Some code would have been missed while resolving merge conflict, need to investigate that. Because this was working fine in local and DEV till yesterday night 10/22/2025

Sheet OB-OP 8.2 Sprint 4-Status
A1: S.No | B1: Application Name | C1: Sprint Start Date | D1: Sprint End Date | E1: Sprint | F1: Developer | G1: Story ID/Defect ID | H1: Description | I1: Status | J1: Estimated(hrs/sp) | K1: Actual(hrs/sp) | L1: Actual Hours Worklog | M1: Dev Start Date | N1: Dev End Date | O1: Unit testing | P1: Peer Tested By | Q1: Peer Tested Defects, if any | R1: Peer Reviewed By | S1: Peer Code Review Comments, if any | T1: PR Number/Link | U1: PR Created Date | V1: PR Approved Date | W1: Onsite Lead Code Review | X1: Code Review Comments, if any | Y1: Client Code Review | Z1: Approved Date | AA1: Code Review Comments, if any2 | AB1: Internal PO -POV Comments | AC1: Client PO -POV Comments | AD1: Comments
A2: 1 | B2: OnlineBidding | C2: 45925 | D2: 45939 | E2: OB-OP 8.2 Sprint 4 | F2: Karthi | G2: OB-3826 | H2: Featured Package should link to Package Details | I2: Completed | J2: 2 | L2: 13 | M2: 45926 | N2: 45926 | O2: Done | P2: Mercy | Q2: Nil | R2: Preethi | S2: Nil | T2: https://greatergiving.visualstudio.com/Greater%20Giving/_git/OnlineBidding/pullrequest/8877 | U2: 45926 | V2: 45927 | W2: Prabu | X2: Nil | Y2: Joe | Z2: 45927 | AA2: Nil | AB2: Nil | AC2: Nil | AD2: TST testing completed 9/29/2025
A3: 2 | B3: OnlineBidding | C3: 45925 | D3: 45939 | E3: OB-OP 8.2 Sprint 4 | F3: Preethi | G3: OB-3726 | H3: Add Package Banners to Package Cards/Detail pages | I3: Completed | J3: 3 | L3: 44.75 | M3: 45926 | N3: 45937 | O3: Done | P3: Mercy | Q3: Nil | R3: Karthi | S3: Nil | T3: https://greatergiving.visualstudio.com/Greater%20Giving/_git/OnlineBidding/pullrequest/8884 | U3: 45936 | V3: 45938 | W3: Prabu | X3: Nil | Y3: Joe | Z3: 45938 | AA3: Nil | AB3: Nil | AC3: Nil | AD3: Created draft PR - need to check with PO for UI placement and color 9/30/2025 Dev testing completed 10/6/2025
A4: 3 | B4: OnlineBidding | C4: 45925 | D4: 45939 | E4: OB-OP 8.2 Sprint 4 | F4: Karthi | G4: OB-3831 | H4: OB UX - Clean Up | I4: Completed | J4: 2 | L4: 34.25 | M4: 45929 | N4: 45936 | O4: Done | P4: Mercy | Q4: Nil | R4: Preethi | S4: Nil | T4: https://greatergiving.visualstudio.com/Greater%20Giving/_git/OnlineBidding/pullrequest/8886 | U4: 45930 | V4: 45936 | W4: Prabu | X4: Nil | Y4: Joe | Z4: 45937 | AA4: Nil | AB4: Nil | AC4: Nil | AD4: Need to check with client designer for padding update and that will be done on upcoming monday -10/3/2025 TST testing completed 10/7/2025
A5: 4 | B5: OnlineBidding | C5: 45925 | D5: 45939 | E5: OB-OP 8.2 Sprint 4 | F5: Preethi | G5: OB-3828 | H5: Create Max Bid alerts | I5: Completed | J5: 5 | L5: 30 | M5: 45933 | N5: 45937 | O5: Done | P5: Mercy | Q5: - button for max bid is enabled when both bid and max bid is having same value | R5: Karthi | S5: Nil | T5: https://greatergiving.visualstudio.com/Greater%20Giving/_git/OnlineBidding/pullrequest/8903 | U5: 45937 | V5: 45938 | W5: Prabu | X5: Nil | Y5: Joe | Z5: 45938 | AA5: Nil | AB5: Nil | AC5: Nil | AD5: Have done the changes - need to check UI placement with PO 10/6/2025 DEV testing in progress 10/7/2025
A6: 5 | B6: OnlineBidding | C6: 45925 | D6: 45939 | E6: OB-OP 8.2 Sprint 4 | F6: Karthi/Preethi | G6: OB-3833 | H6: Continue Angular Update | I6: Completed | J6: 1 | L6: 21 | M6: 45938 | N6: 45939 | AD6: Document is attached in JIRA story
A7: 6 | B7: OnlineBidding | C7: 45925 | D7: 45939 | E7: OB-OP 8.2 Sprint 4 | F7: Mercy - Testing only story | G7: OB-3830 | H7: Release Ob 8.2.0 to CRT | I7: Completed | J7: 3 | L7: 39

Sheet OB-OP 8.2 Sprint-4-Defect
A1: S.No | B1: Sprint | C1: Story/Defect ID | D1: Parent Story | E1: Developer | F1: Issue Type | G1: Issue Description | H1: Priority | I1: Defect Source | J1: Type | K1: Status | L1: Root Cause Category | M1: Comments | N1: Found By | O1: RCA Comment
B2: OB-OP 8.2 Sprint 4 | C2: OB-3836 | D2: OB-3830 | F2: Defect | G2: Package Filters - 'All' check box is seen checked even after clicking clear filter | H2: Significant | I2: Manual | J2: Internal | K2: Open | L2: Development | M2: Will be worked in next sprint as this is not planned for current release | N2: Mercy | O2: Missed during development and testing, other textbox gets cleared, only when all checkbox is clicked, this issue is happening
B3: OB-OP 8.2 Sprint 4 | C3: OB-3837 | D3: OB-3830 | F3: Defect | G3: Activity and Favorites Area - searching for a package name in the search field displays results based on the 'All' filter | H3: Significant | I3: Manual | J3: Internal | K3: Open | L3: Development | M3: Will be worked in next sprint as this is not planned for current release | N3: Mercy | O3: During initial development and testing these scenarios were addressed, missed after updating the logic by making the filters as separate component

Sheet OB-OP 8.2 Sprint 3-Status
A1: S.No | B1: Application Name | C1: Sprint Start Date | D1: Sprint End Date | E1: Sprint | F1: Developer | G1: Story ID/Defect ID | H1: Description | I1: Status | J1: Estimated(hrs/sp) | K1: Actual(hrs/sp) | L1: Actual Hours Worklog | M1: Dev Start Date | N1: Dev End Date | O1: Unit testing | P1: Peer Tested By | Q1: Peer Tested Defects, if any | R1: Peer Reviewed By | S1: Peer Code Review Comments, if any | T1: PR Number/Link | U1: PR Created Date | V1: PR Approved Date | W1: Onsite Lead Code Review | X1: Code Review Comments, if any | Y1: Client Code Review | Z1: Approved Date | AA1: Code Review Comments, if any2 | AB1: Internal PO -POV Comments | AC1: Client PO -POV Comments | AD1: Comments
A2: 1 | B2: OnlineBidding | C2: 45911 | D2: 45925 | E2: OB-OP 8.2 Sprint 3 | F2: Preethi | G2: OB-3718 | H2: Implement Activity and Favorites area | I2: Completed | J2: 2 | L2: 60.75 | M2: 45912 | N2: 45918 | O2: Done | P2: Mercy | Q2: 1. When we bid as auctioneer for the package that is in ALL filter, page gets refreshed and then loading first 24 packages which is not expected, should refresh and display and load the packages that is inside ALL filter alone 2. After closing a package from Auction control center, page loads and showing 24 packages instead of ALL filter packages 3. When i bid any package which is in ALL filter, TOP BID amount not getting updated, only after manual page refresh value getting updated 4. When two bidders bid for a package Bidder A bids higher value than bidder B and takes Winning place, Bidder B which was previously under winning tab has to be moved to Outbid tab. but actual result is because of signalR issue Bidder B is still seen under Winning tab | R2: Karthi | S2: Nil | T2: https://greatergiving.visualstudio.com/Greater%20Giving/_git/OnlineBidding/pullrequest/8837 | U2: 45918 | V2: 45922 | W2: Prabu | X2: Nil | Y2: Joe | Z2: 45922 | AA2: 1. Add error callback. 2. Use tab or this.activeTab throughout for consistency. | AB2: Nil | AC2: Nil | AD2: DEV testing completed 9/18/2025 TST testing completed 9/23/2025
A3: 2 | B3: OnlineBidding | C3: 45911 | D3: 45925 | E3: OB-OP 8.2 Sprint 3 | F3: Preethi | G3: OB-3727 | H3: Add Bid History to Package Detail Pages | I3: Completed | J3: 3 | L3: 31 | M3: 45918 | N3: 45922 | O3: Done | P3: Mercy | Q3: 1. When we bid as a auctioneer , auctioneer number not getting updated in Bidding history | R3: Karthi | S3: Nil | T3: https://greatergiving.visualstudio.com/Greater%20Giving/_git/OnlineBidding/pullrequest/8847 | U3: 45922 | V3: 45923 | W3: Prabu | X3: Nil | Y3: Joe | Z3: 45923 | AA3: Nil | AB3: Nil | AC3: Nil | AD3: DEV testing completed 9/22/2025 TST testing completed 9/23/2025
A4: 3 | B4: OnlineBidding | C4: 45911 | D4: 45925 | E4: OB-OP 8.2 Sprint 3 | F4: Karthi | G4: OB-3821 | H4: OB UX - Clean Up | I4: Completed | J4: 3 | L4: 30.25 | M4: 45912 | N4: 45918 | O4: Done | P4: Mercy | R4: Preethi | S4: Nil | T4: https://greatergiving.visualstudio.com/Greater%20Giving/_git/OnlineBidding/pullrequest/8843 | U4: 45918 | V4: 45923 | W4: Prabu | X4: Nil | Y4: Joe | Z4: 45923 | AA4: Nil | AB4: Nil | AC4: Nil | AD4: DEV testing completed 9/18/2025 TST testing completed 9/23/2025
A5: 4 | B5: OnlineBidding | C5: 45911 | D5: 45925 | E5: OB-OP 8.2 Sprint 3 | F5: Karthi/Preethi | G5: OB-3822 | H5: Continue Angular Update | I5: Completed | J5: 1 | L5: 12 | M5: 45925 | AD5: Added comments in JIRA
A6: 5 | B6: OnlineBidding | C6: 45911 | D6: 45925 | E6: OB-OP 8.2 Sprint 3 - [Stretch] | F6: Preethi | G6: OB-3720 | H6: Implement Bid Modal (Max Bidding) | I6: Completed | J6: 3 | L6: 43.25 | M6: 45919 | N6: 45924 | O6: Done | P6: Mercy | Q6: 1. When Max bid toggle is enabled in ggo side we should see the text as "Choose the amount to bid below. You can also set a max bid value" 2. Congratulation pop up should not show up when error is still seen 3. When Confirm bid is clicked twice even if set max bid is lesser than original bid congratulations pop up is seen 4. Fav Icon is different, only red border is seen entire heart has to be in red 5. I have made Bidder A set max bid for $5200.5 and now i tried to set max bid for Bidder B as $650, confirm bid button is clickable but no action is seen | R6: Karthi | S6: Nil | T6: https://greatergiving.visualstudio.com/Greater%20Giving/_git/OnlineBidding/pullrequest/8851 | U6: 45924 | V6: 45925 | W6: Prabu | X6: Remove multiple div condition and use switch case | Y6: Joe | Z6: 45925 | AA6: Nil | AB6: Nil | AC6: Nil | AD6: Dev testing in progress 9/22/2025 TST testing completed 9/25/2025
A7: 6 | B7: OnlineBidding | C7: 45911 | D7: 45925 | E7: OB-OP 8.2 Sprint 3 - [Stretch] | F7: Karthi | G7: OB-3693 | H7: Implement Buy Now Modal | I7: Completed | J7: 5 | L7: 42.75 | M7: 45919 | N7: 45924 | O7: Done | P7: Mercy | Q7: When clicked buy now simultaneously popup is not getting closed until we click no | R7: Preethi | S7: Nil | T7: https://greatergiving.visualstudio.com/Greater%20Giving/_git/OnlineBidding/pullrequest/8858 | U7: 45924 | V7: 45925 | W7: Prabu | X7: Nil | Y7: Joe | Z7: 45925 | AA7: Nil | AB7: Nil | AC7: Nil | AD7: Dev testing completed 9/24/2025 TST testing completed 9/25/2025

Sheet OB-OP 8.2 Sprint-3-Defect
A1: S.No | B1: Sprint | C1: Story/Defect ID | D1: Parent Story | E1: Developer | F1: Issue Type | G1: Issue Description | H1: Priority | I1: Defect Source | J1: Type | K1: Status | L1: Root Cause Category | M1: Comments | N1: Found By | O1: RCA Comment

Sheet OB-OP 8.2 Sprint 2-Status
A1: S.No | B1: Application Name | C1: Sprint Start Date | D1: Sprint End Date | E1: Sprint | F1: Developer | G1: Story ID/Defect ID | H1: Description | I1: Status | J1: Estimated(hrs/sp) | K1: Actual(hrs/sp) | L1: Actual Hours Worklog | M1: Dev Start Date | N1: Dev End Date | O1: Unit testing | P1: Peer Tested By | Q1: Peer Tested Defects, if any | R1: Peer Reviewed By | S1: Peer Code Review Comments, if any | T1: PR Number/Link | U1: PR Created Date | V1: PR Approved Date | W1: Onsite Lead Code Review | X1: Code Review Comments, if any | Y1: Client Code Review | Z1: Approved Date | AA1: Code Review Comments, if any2 | AB1: Internal PO -POV Comments | AC1: Client PO -POV Comments | AD1: Comments
A2: 1 | B2: OnlineBidding | C2: 45897 | D2: 45911 | E2: OB-OP 8.2 Sprint 2 | F2: Preethi | G2: OB-3718 | H2: Implement Activity and Favorites area | I2: Peer Review | J2: 3 | L2: 45.75 | M2: 45905 | O2: Done | P2: Mercy | Q2: 1. Activity batch count is not updating correctly 2. When we deselect fav icon under Favorite tab, particular package not getting removed immediately 3. When the outbid checkbox is selected package list gets updated correctly. However after placing bid on any one of the package, bidding completes and page gets refreshed loading entire packages which is not expected | R2: Karthi | S2: Nil | T2: https://greatergiving.visualstudio.com/Greater%20Giving/_git/OnlineBidding/pullrequest/8785 | U2: 45910 | W2: Prabu | X2: Reduce multiple API calls | Y2: Joe | AD2: Development completed, waiting for client designer to confirm the position of few options 9/9/2025 Dev testing completed Have got many conflicts because of the other 2 stories, since we prioritised 8 point story, this is carry forwarded to next sprint
A3: 2 | B3: OnlineBidding | C3: 45897 | D3: 45911 | E3: OB-OP 8.2 Sprint 2 | F3: Karthi | G3: OB-3688 | H3: Implement Package Filters | I3: Completed | J3: 8 | L3: 98.25 | M3: 45898 | N3: 45911 | O3: Done | P3: Mercy | Q3: 1. Show More and Show Less not proper 2. When Min and Max is updated as 1 to 3, entire package list is displayed which is wrong 3. When All is checked other boxes are also checked, but as per AC uncheck all other boxes when All is checked | R3: Preethi | S3: Nil | T3: https://greatergiving.visualstudio.com/Greater%20Giving/_git/OnlineBidding/pullrequest/8816 | U3: 45910 | V3: 45910 | W3: Prabu | X3: Nil | Y3: Joe | Z3: 45910 | AA3: Nil | AB3: Nil | AC3: Nil | AD3: 9/9/2025 Dev testing completed
A4: 3 | B4: OnlineBidding | C4: 45897 | D4: 45911 | E4: OB-OP 8.2 Sprint 2 | F4: Preethi | G4: OB-3692 | H4: Implement Bid Modal | I4: Completed | J4: 8 | L4: 66.5 | M4: 45898 | N4: 45911 | O4: Done | P4: Mercy | Q4: 1. When bidding is done between 2 bidders (Bid amount incremented twice by both the bidder) one bidders gets bummer pop up with the button "Bid Again", when bid again is clicked incorrect bid value is displayed 2. When we set minimum increment value as 5.5 in ggo, and on OB page when we click + button to increment the value by 5.5 , "please enter the valid amount" pop up is seen which is wrong 3. When starting bid is mentioned as 5.5 in ggo, and on OB page when we click + button to increment the value by 5 , "please enter the valid amount" pop up is seen which is wrong 4. Include dollar symbol where bid amount is displayed in Bid modal 5. Font size mismatch for "Place your bid" and "Your offer" text within the bid modal | R4: Karthi | S4: Nil | T4: https://greatergiving.visualstudio.com/Greater%20Giving/_git/OnlineBidding/pullrequest/8794 | U4: 45909 | V4: 45910 | W4: Prabu | X4: Nil | Y4: Joe | Z4: 45910 | AA4: Nil | AB4: Nil | AC4: Nil | AD4: Dev testing Completed
A5: 4 | B5: OnlineBidding | C5: 45897 | D5: 45911 | E5: OB-OP 8.2 Sprint 2 | F5: Karthi/Preethi/Prabu | G5: OB-3814 | H5: Continue Angular Update | I5: Completed | J5: 1 | L5: 4 | M5: 45911 | N5: 45912
A6: 5 | B6: OnlineBidding | C6: 45897 | D6: 45897 | E6: OB-OP 8.2 Sprint 2 | F6: Preethi | G6: OB-3818 - Defect | H6: When a bidder is pre-emptively outbid the "bummer!" message does not display | I6: Completed | L6: 4.25 | M6: 45911 | N6: 45911 | O6: Done | P6: Mercy | Q6: Nil | R6: Karthi | S6: Nil | T6: https://greatergiving.visualstudio.com/Greater%20Giving/_git/OnlineBidding/pullrequest/8834 | U6: 45911 | V6: 45911 | W6: Prabu | X6: Nil | Y6: Joe | Z6: 45911 | AA6: Nil | AB6: Nil | AC6: Nil | AD6: Dev testing Completed
A7: 6 | B7: OnlineBidding | C7: 45897 | D7: 45897 | E7: OB-OP 8.2 Sprint 2 | F7: Karthi | G7: OB-3819 -Defect | H7: closed packages show up under the currently open filter | I7: Completed | L7: 4 | M7: 45911 | N7: 45911 | O7: Done | P7: Mercy | Q7: Nil | R7: Preethi | S7: Nil | T7: https://greatergiving.visualstudio.com/Greater%20Giving/_git/OnlineBidding/pullrequest/8835 | U7: 45911 | V7: 45911 | W7: Prabu | X7: Nil | Y7: Joe | Z7: 45911 | AA7: Nil | AB7: Nil | AC7: Nil | AD7: Dev testing Completed

Sheet OB-OP 8.2 Sprint-2-Defect
A1: S.No | B1: Sprint | C1: Story/Defect ID | D1: Parent Story | E1: Developer | F1: Issue Type | G1: Issue Description | H1: Priority | I1: Defect Source | J1: Type | K1: Status | L1: Root Cause Category | M1: Comments | N1: Found By | O1: RCA Comment
