Workbook

Sheet Dashboard
A1: Current Sprint | B1: {=INDEX($B$2:$B$97,MATCH(1,(($D$2:$D$97 >=TODAY())*($C$2:$C$97<=TODAY())),0))} -> MCS 26 Sprint 9 | C1: Current Sprint Sheet | D1: =CONCATENATE(B1,"-Status") -> MCS 26 Sprint 9-Status | E1: Sprint Start Date | F1: =VLOOKUP($B$1,$B$1:$C$97,2) -> 46150 | G1: Sprint End Date | H1: =VLOOKUP($B$1,$B$1:$D$97,3) -> 46163 | I1: Application Name | J1: MCS | K1: Users | L1: ganesh.vaidyanath@relevantz.com;hariharan.dhandapani@relevantz.com;shriveni.baskaran@relevantz.com;vaishnavi.vinoth@relevantz.com;florina.barani@relevantz.com;kalaivani.vijaya@relevantz.com;sathishkumar.velusamy@relevantz.com;srinivasu.ponnaganti@relevantz.com;jayapriya.suresh@relevantz.com | M1: Teams Name(GP-HSS_MCS Product) | N1: 19:3b0279a924ab4f35985570b471228dd7@thread.v2
A2: Sprint Type | B2: Sprint # | C2: Sprint Start Date | D2: Sprint End Date | E2: Assigned | F2: Completed | G2: Story points introduced/removed | H2: Sprint Summary | I2: Accomplishments | J2: Remarks | K2: Retro Points (Internal & External) | L2: Unplanned Leaves | M2: Data sanity Audit Status | N2: AuditDate | O2: Backlog Health | P2: Completed Stretch
A3: =IF(AND($D$1>=C3,$D$1<=D3),"CurrentSprint","NA") -> NA | B3: MCS 24 Sprint 17 | C3: 45520 | D3: 45533 | E3: 3 | F3: 3 | G3: Nil | I3: 1.Change Cafe Enterprise application export image format to JPG 2. UserName Length issue in the MCS Tool fixed | J3: Onboarding Sprint - Worked on access related items. Hariharan and BoobalaKrishnan has only got the access. Dinesh has not got access to the Client Tools. | K3: Internal: External:
A4: =IF(AND($D$1>=C4,$D$1<=D4),"CurrentSprint","NA") -> NA | B4: MCS 24 Sprint 18 | C4: 45534 | D4: 45547 | E4: 19 | F4: 13 | G4: 45689 and 45690 tasks has been moved to the next sprint (6SP) | I4: 1. Meal Pattern Flexibility. 2. SFTP sent to orders method. | J4: Dinesh has not still got the access to the code repo hence no points picked by him. | K4: Internal: External:
A5: =IF(AND($D$1>=C5,$D$1<=D5),"CurrentSprint","NA") -> NA | B5: MCS 24 Sprint 19 | C5: 45548 | D5: 45561 | E5: 12 | F5: 12 | G5: New ACs were added for #45900 - 1SP | I5: 1. New ACs for Meal Pattern Flexibility. 2. MCS - FR - Add "Test Email" button to SMTP settings 3. 2 user defect were closed. | J5: #45900(New ACs) is Moved to Sprint Stretch. #45444 is moved to Sprint Stretch | K5: Internal: External:
A6: =IF(AND($D$1>=C6,$D$1<=D6),"CurrentSprint","NA") -> NA | B6: MCS 24 Sprint 20 | C6: 45562 | D6: 45575 | E6: 18 | F6: 18 | G6: 6 (Assigned from Sprint Strech) Carry forwarded to next sprint | I6: 1. Report Layout Overrides. 2. Total Sugar Vaidation across application | J6: #45539 - Product Expiration Report. #45908 - MCS - ED - Inventory On Hand report. Pulled from the sprint strech, will move to sprint 20 | K6: Internal: External: Relevanz team for quickly becoming comfortable in the codebase and the quality work we did for this sprint
A7: =IF(AND($D$1>=C7,$D$1<=D7),"CurrentSprint","NA") -> NA | B7: MCS 24 Sprint 21 | C7: 45576 | D7: 45589 | E7: 11 | F7: 11 | G7: 3 (Assigned from Sprint Strech) | I7: 1. Report Layout Override - Group by. 2. Product Expiration Report. 3. Inventory On-hand Report | J7: #46255 - Pulled from the sprint strech, will move to sprint 22 | K7: Internal: External:Relevantz team members contributions & ramp up going well
A8: =IF(AND($D$1>=C8,$D$1<=D8),"CurrentSprint","NA") -> NA | B8: MCS 24 - Sprint 22 | C8: 45590 | D8: 45603 | E8: 11 | F8: 11 | G8: Nil | I8: 1. FOH/BOH Integration calculation issues 2. Cafeteria Filter Dashboard Refresh. 3. Balance Recolination Discripency | J8: Completed as planned. This Sprint Involved tasks with More analysis. | K8: External : Good Team Work
A9: =IF(AND($D$1>=C9,$D$1<=D9),"CurrentSprint","NA") -> NA | B9: MCS 24 Sprint 23 | C9: 45604 | D9: 45617 | E9: 13 | F9: 7 | I9: 1. Layout Override for Student Rooster Report 2. Newton Dashboard loading faster 3. Permissions for Employee and Special Adult key in Newton POS 4. Leftover calculations fixed in Edison report | J9: Internal CRC - 0 External CRC - 2 QA Defects - 1 Escaped Defects - 1 | K9: Internal: External:
A10: =IF(AND($D$1>=C10,$D$1<=D10),"CurrentSprint","NA") -> NA | B10: MCS 24 Sprint 24 | C10: 45618 | D10: 45636 | E10: 25 (9 +16) | F10: 12 | G10: 1+8+8 | I10: 1. POS - Function Keys Enable or Disable. 2. Production Escalation - Breakfast POS Hotfix. | J10: 1. POV is delayed due to unavailabilty of PO- Josh. 2. Since only one QA was available for this sprint, stories for this sprint was backloged in testing. (Milan - Client QA is on Vacation) 3. Introduced new stories in the last few of days of sprint closure (client) Internal CRC - 0 External CRC - 4 QA Defects - 0 Escaped Defects - 0 | K10: Internal: External: Relevanz team for quickly becoming comfortable in the codebase and the quality work we did for this sprint
A11: =IF(AND($D$1>=C11,$D$1<=D11),"CurrentSprint","NA") -> NA | B11: MCS 24 Sprint 25 | C11: 45637 | D11: 45659 | E11: 30 (25+5) | F11: 12 | G11: 5 | I11: 1. Completed the Production Escalation Task for Item Importers. 2.Completed Grouping and Sorting for Layout Overrides in Student Roster and Student Barcode Roster Report. 3. Price Contract Import UI part was completed. 4. Oauth2.0 R&D was completed successfully. 5. Analysis for POS Optimization. | J11: FYI SRX25080 - was introduced as a new production escalation task from Josh. Requested to Prioritize and release it as a HotFix. Client was out for last week hence PR approval and confirmation for any blockers were on-hold. Since Client QA(Milan) was on leave for the entire month. Only 1 QA - Andrews was available for testing. He was Involved in testing Client DEV stories as well. Internal CRC - 0 External CRC - 4 QA Defects - 2 Escaped Defects - 0 | K11: Internal: External: Relevantz team was very productive during holidays.
A12: =IF(AND($D$1>=C12,$D$1<=D12),"CurrentSprint","NA") -> NA | B12: MCS 25 Sprint 1 | C12: 45660 | D12: 45673 | E12: 22 (17 +5) | F12: 9 | G12: 5 | I12: 1.Completed the role importers. 2.Completed the GSDN Item importer. | J12: OAuth integration has dependency on SMTP approval from Relevantz for dev testing to be done. Import proce contracts - UI has been completed after initial POV approval and working on backend for the same Optiomazation of cafeteria permission - Need to combine the cafeteria category based user role permissions into the fetch query while login Internal CRC - 0 External CRC - 4 QA Defects - 0 Escaped Defects - 0 | K12: Internal: Andrews for handling testing effort on his plate External: Relevantz team provided Good dev support this sprint
A13: =IF(AND($D$1>=C13,$D$1<=D13),"CurrentSprint","NA") -> NA | B13: MCS 25 Sprint 2 | C13: 45674 | D13: 45687 | E13: 9 | F13: 9 | G13: 5 | I13: 1. Optimized Cafeteria Cache Permissions: Improved efficiency and security of the cafeteria system by optimizing cache permissions, ensuring smoother operations. 2. Implemented OAuth2.0: Successfully integrated OAuth2.0 for secure and seamless authentication, which was demonstrated effectively, showcasing our system's enhanced security measures. 3. Developed Import Price Contracts: Completed development changes for the implementation of import price contracts, paving the way for streamlined contract management. A Proof of Value (POV) has been scheduled to demonstrate the impact and effectiveness of these changes. | J13: Not able to close the stories within the sprint as planned since we have less bandwidth in testing New AC's were introduced at mid of the sprint that caused delay in executing the stories.(#45301 and #46563) Internal CRC - 1 External CRC - 2 QA Defects - 0 Escaped Defects - 0 | K13: Internal: Onboarded wave team successfully. Completed business KT sessions for all applications in MCS. External: Appreciation received from client team(Andrea, Rudy, Milan and Patrick) for Hari for Oauth implemention.
A14: =IF(AND($D$1>=C14,$D$1<=D14),"CurrentSprint","NA") -> NA | B14: MCS 25 Sprint 3 | C14: 45688 | D14: 45701 | E14: 26 | F14: 23 | G14: 4 | I14: 1. Bootstrap Migration Research: Completed the research and documented the findings. Identified the affected pages from this migration and created stories to fix the layout issues to complete the migration. 2. New ACs for Oauth2.0 Integration: New ACs for the Oauth2.0 Integration for the FRANKLIN application is completed. 3. New AC Developed Import Price Contracts: Completed development changes for the implementation of import price contracts, paving the way for streamlined contract management. 4. New Field for Item Importer: New field "Generate Recipe" for item importer has added. 5. Wave Team completed the analysis on SQLite Migration. | J14: Two Storieds #45301 and #46563 has its testign effort of 3SP carry forwarded to next sprint. #47119 and #21529 was was picked from the Sprint Stretch. Internal CRC - 0 External CRC - 1 QA Defects - 1 Escaped Defects - 0 | K14: Internal: Overall Team Collabration was good. External: Patrick mentioned in the retro that wave Team Ramp-up was good
A15: =IF(AND($D$1>=C15,$D$1<=D15),"CurrentSprint","NA") -> NA | B15: MCS 25 Sprint 4 | C15: 45702 | D15: 45715 | E15: 34 | F15: 29 | G15: 2 | I15: 1. Bootstrap Migration: Completed the implementations of the bootstrap changes for the following pages. Home, Application Pages (8 sub modules) 2. New ACs for Oauth2.0 Integration: New ACs for the Oauth2.0 Integration for the FRANKLIN application is completed. 3.Named Site Filter Defect: Script fix for the defect named side filter is completed. 4. New Field for Item Importer: New field "Generate Recipe" for item importer has been completed. which was demonstrated successfully. 5. Wave Team completed the SQLite Task as planned for this sprint. 6.Accessability Fix: Identified the places where we need to fix WCAG2.2 issues on MSA Web using Wave and AC Lite plugin | J15: Story #47120 has its testing pending so carry forwarded to next sprint. Story #46563 has its testing pending so carry forwarded to next sprint. Internal CRC - 1 External CRC - 1 QA Defects - 0 Escaped Defects - 1 | K15: Internal: Overall Team Collabration was good. Sprint went well as we were able to complete assigned tasks. External: Clients mentioned Sprint went well as we were able to complete assigned tasks.
A16: =IF(AND($D$1>=C16,$D$1<=D16),"CurrentSprint","NA") -> NA | B16: MCS 25 Sprint 5 | C16: 45716 | D16: 45729 | E16: 38 | F16: 35 | G16: 5 | I16: 1. Bootstrap Migration: Completed the implementations of the bootstrap changes for the following pages. Home, Application Pages (8 sub modules) 2.New Item Importing to price contract: New item adding to price contract has been completed. which was demonstrated successfully. 3. New Field for Item Importer: New field "Generate Recipe" for item importer has been completed. which was demonstrated successfully. 4. Wave Team completed the SQLite Task as planned for this sprint. | J16: "Story #47120 has its testing pending so carry forwarded to next sprint. Story #46563 has its testing pending so carry forwarded to next sprint. Hari had a laptop replacement which took 3 days and had to setup the entire environment from the scratch. Internal CRC - 1 External CRC - 5 QA Defects - 0 Escaped Defects - 1 | K16: Internal: Overall Team Collabration was good. Sprint went well as we were able to complete assigned tasks. External: Clients mentioned Sprint went well as we were able to complete assigned tasks.
A17: =IF(AND($D$1>=C17,$D$1<=D17),"CurrentSprint","NA") -> NA | B17: MCS 25 Sprint 6 | C17: 45730 | D17: 45743 | E17: 54 | F17: 40 | G17: 3 | I17: 1. Wave Team completed the Unit testing in xUnit (unit testing frameworks) for the Admin colsole and MCS Application Server and Started to analyze and create the Approach Document for the Newtom POS 2. Boostrap Migration changes completed for Admin Pages. 3. Price Contracts Import Implementation is completed. 4. Oauth 2.0 Integration for SMTP in POS is completed. | J17: Internal CRC - 1 External CRC - 1 QA Defects - 0 Escaped Defects - 0 | K17: Internal: Overall Team Collabration was good. Transition for Shriveni and Rajesh was smooth. External: Testing team has to sync-up with DEV for task inputs. Patrick Mentioned Wave Team shows good Progress. Andrea Mentioned Bootstrap Migration by Krish is going excellent
A18: =IF(AND($D$1>=C18,$D$1<=D18),"CurrentSprint","NA") -> NA | B18: MCS 25 Sprint 7 | C18: 45744 | D18: 45757 | E18: 36 | F18: 31 | G18: 8 | I18: 1. Wave Team completed the Development for Admin console and MCS Application server for Sqlite Migration. 2. Boostrap Migration changes completed for - Admin - Audit Logs and WCAG related changes have been done. 3. Production Defect for Production Bulk editor is fixed. | J18: Internal CRC - 0 External CRC - 1 QA Defects - 0 Escaped Defects - 0 | K18: Internal: Overall Team Collabration was good.. External: Patrick Mentioned Overall Relevantz team shows good progress.
A19: =IF(AND($D$1>=C19,$D$1<=D19),"CurrentSprint","NA") -> NA | B19: MCS 25 Sprint 8 | C19: 45758 | D19: 45771 | E19: 12 | F19: 25 | G19: 34 | I19: 1. Wave Team Started Newton POS i Started working on the Newton POS application and the development is inprogress . DB has been completed for writting the scripts for SQLite for Newtom POS 2. Boostrap Migration changes completed for Admin Pages 3. Price Contracts Import Implementation is completed. 4. Oauth 2.0 Integration for SMTP in POS is completed. | J19: Internal CRC - 0 External CRC - 1 QA Defects - 2 Escaped Defects - 0 | K19: Internal: Overall Team Collabration was good.. External: Patrick Mentioned Overall Relevantz team shows good progress. And RJ has mentioned the Wave team has the visibility of what they are working
A20: =IF(AND($D$1>=C20,$D$1<=D20),"CurrentSprint","NA") -> NA | B20: MCS 25 Sprint 9 | C20: 45772 | D20: 45785 | E20: 2 | F20: 2 | G20: 21 | I20: 1. Defects for the production bulk editor is completed. 2. Shriveni is working on the tesing backlogs on MSA. 3. Vaishnavi's onboarding was completed. | J20: Internal CRC - 0 External CRC - 1 QA Defects - 2 Escaped Defects - 0 | K20: Internal: Overall Team Collabration was good.. External: Vaishnavi's KT and onboarding was smooth and started to work on the stories. Defects on the bulk editor was closed
A21: =IF(AND($D$1>=C21,$D$1<=D21),"CurrentSprint","NA") -> NA | B21: MCS 25 Sprint 10 | C21: 45786 | D21: 45799 | E21: 2 | F21: 2 | G21: 13 | I21: 1.Shriveni-Completed the defect-User-Defined Report is Truncating Generic SQL Queries -Edison and Newton Application 2.Vaishnavi working on the story #47496 3.Hariharan Completed on the story #48013 | J21: Internal CRC - 0 External CRC - 0 QA Defects - 2 Escaped Defects - 0 | K21: Overall Team Collaboration was good.. Ganesh-Good communication for Pre-POV- by Josh
A22: =IF(AND($D$1>=C22,$D$1<=D22),"CurrentSprint","NA") -> NA | B22: MCS 25 Sprint 11 | C22: 45800 | D22: 45813 | E22: 16 | F22: 3 | G22: 12 | I22: 1.Shriveni-Completed the testing-48112, other two story back to develop. 2.Vaishnavi-working on the story #48520, and 47496-Ready for testing. 3..Hariharan - Send Approved Orders to vendor task was integreated in scheduled Job. 4. Hariharan - TLS encryption was integrated to Newton SMTP Email Configuration. | J22: "Internal CRC - 4 External CRC - 0 QA Defects - 0 Escaped Defects - 0 " | K22: Overall Team Collaboration was good..
A23: NA | B23: MCS 25 Sprint 12 | C23: 45814 | D23: 45828 | E23: 19 | F23: 10 | G23: 4 | I23: 1. Hariharan - Completed the Cherry Creek Production Report and Delivered to the Customer. 2. Hariharan - Completed the SQL Alert changes Version Update.. 3. Vaishnavi - Completed the Scrub Scripts Update for the apps. 4. Shriveni - MSA Client Testing has been completed. | J23: "Internal CRC - 1 External CRC - 3 QA Defects - 0 Escaped Defects - 0 " | K23: Overall Team Collaboration was good.. Shriveni Was helping a lot on the testing Progress.
A24: NA | B24: MCS 25 Sprint 13 | C24: 45831 | D24: 45841 | E24: 18 | F24: 9 | G24: 9 | I24: 1 Hari- Completed the Apply security changes to Email for Permissive TLS. 2.Shriveni - Completed the testing for Apply security changes to Email for Permissive TLS 3. Vaishnavi - Completed the Scrub Scripts Update2 for the apps. 4.Vaishnavi - Completed Permissions for Ad-Hoc Inventory. 5.Hariharan - Account Balances Affecting Adjustments Export. | J24: "Internal CRC - 2 External CRC - 0 QA Defects - 0 Escaped Defects - 0 " | K24: Overall Team Collaboration was good..
A25: NA | B25: MCS 25 Sprint 14 | C25: 45842 | D25: 45855 | E25: 18 | F25: 10 | G25: 8 | I25: 1.Hariharan - Completed Alert for SQL Version older than 2016. 2.Hariharan - Delivered CSUSA Plugin for Account Balance Adjustments Export 3.Hariharan - Completed LAUSD Production Plugin. 4.Shriveni - Completed the testing for Add ability to schedule sending orders to vendor. 5.Shriveni - Custom Report Changes for Elk Grove | J25: "Internal CRC - 3 External CRC - 5 QA Defects - 0 Escaped Defects - 0 " | K25: Internal: Overall Team Collabration was good. External: Successful sprint on completed the assigned task.
A26: NA | B26: MCS 25 Sprint 15 | C26: 45856 | D26: 45869 | E26: 13 | F26: 3 | G26: 7 | I26: 1.Hariharan - Completed Defect on the POS Batches. 2. Vaishnavi - Completed the Nebulizer SSO Parameter with Testing. 3. Progressing on the MCS DC SFTP. | J26: "Internal CRC - 5 External CRC - 1 QA Defects - 0 Escaped Defects - 0 " | K26: Internal: Overall Team Collabration was good. External: Vaishnavi on building up good rapo with Codebase
A27: NA | B27: MCS 25 Sprint 16 | C27: 45870 | D27: 45883 | E27: 12 | F27: 2 | G27: 6 | I27: 1.Completed Defect -Inventory On Hand is showing a parameter window. 2.Hariharan - Completed Apply mapping changes to PeopleSoft export | J27: "Internal CRC - 2 External CRC - 0 QA Defects - 0 Escaped Defects - 0 " | K27: Internal: Overall Team Collabration was good.
A28: NA | B28: MCS 25 Sprint 17 | C28: 45884 | D28: 45897 | E28: 16 | F28: 6 | G28: 6 | I28: 1.Vaishnavi-Completed the story -Add new bid group as a copy of existing bid group 2.Hariharan - Completed the story -Custom Report Changes (additional) for Elk Grove. 3.Hariharan -Completed the story -Apply mapping changes to Peoplesoft Export 4.Hariharan -Completed the story -Add an LaSIDs Export File to the Louisiana Plugin 5.-Shriveni -Completed the story(testing) -Add Support for Added Sugars Analysis | J28: "Internal CRC - 2 External CRC - 0 QA Defects - 0 Escaped Defects - 0 " | K28: Internal: Overall Team Collabration was good.
A29: NA | B29: MCS 25 Sprint 18 | C29: 45898 | D29: 45911 | E29: 12 | F29: 9 | G29: 6 | I29: 1.Vaishnavi-Completed the story -LAUSD Production Record Enhancement 2.Vaishnavi-Completed the story -Add SQL Version to District Details Report 3.Vaishnavi-Completed the story -Allow overwriting of default Captions and Tool Tips 4.Hariharan -Completed the story -City Paid Meals and Export to SAP | J29: "Internal CRC - 2 External CRC - 0 QA Defects - 0 Escaped Defects - 0 " | K29: Internal: Overall Team Collabration was good.
A30: NA | B30: MCS 25 Sprint 19 | C30: 45912 | D30: 45924 | E30: 8 | F30: 2 | G30: 0 | I30: 1.Hariharan -Completed the defect-Item Importer change detection not recognizing allergen changes | J30: "Internal CRC - 2 External CRC - 0 QA Defects - 0 Escaped Defects - 0 " | K30: Internal: Overall Team Collabration was good.
A31: NA | B31: MCS 25 Sprint 20 | C31: 45925 | D31: 45939 | E31: 4 | F31: 2 | G31: 10 | I31: 1.Vaishnavi-Completed the story -Add Sorting for Allergen Filter in Item Allergen Report 2.Vaishnavi-Completed the defect-Line Details Not Sorting Properly | J31: "Internal CRC - 10 External CRC - 1 QA Defects - 0 Escaped Defects - 0 " | K31: Internal: Overall Team Collabration was good.
A32: NA | B32: MCS 25 Sprint 21 | C32: 45940 | D32: 45953 | E32: 6 | F32: 2 | G32: 10 | I32: 1.Vaishnavi-Completed the story -Cherry Creek Production Report Change. | J32: "Internal CRC - 0 External CRC - 0 QA Defects - 0 Escaped Defects - 0 " | K32: Internal: Overall Team Collabration was good.
A33: NA | B33: MCS 25 Sprint 22 | C33: 45954 | D33: 45967 | E33: 6 | F33: 6 | G33: 5 | I33: 1.Hariharan-Completed the story -Improve Handling of Unconfirmed/Canceled In-Person Credit Card Transactions 2.Hariharan-Completed the story -Prevent Managers from Zeroing out Production Quantities | J33: "Internal CRC - 5 External CRC - 5 QA Defects - 0 Escaped Defects - 0 " | K33: Internal: Overall Team Collabration was good.
A34: NA | B34: MCS 25 Sprint 23 | C34: 45968 | D34: 45981 | E34: 8 | F34: 5 | G34: 11 | I34: 1.Hariharan -Completed the story-Plugin - CCSD Claim Plugin Update Needed 2.Vaishnavi-Completed the defect-Production Report Numbers are Not Correct | J34: "Internal CRC - 0 External CRC - 3 QA Defects - 0 Escaped Defects - 0 " | K34: Internal: The team collaborated well overall
A35: NA | B35: MCS 25 Sprint 24 | C35: 45982 | D35: 46009 | E35: 14 | F35: 12 | G35: 10 | I35: 1.Hariharan -Completed the story-Plugin - Implement Generic ERP Export. 2.Hariharan -Completed the story-Cannot print request for bid quote bid period. 3.Vaishnavi-Completed the story-Add support for District Tags. 4.Vaishnavi-Completed the story-Lee County PSD Export (Revert Changes) | J35: "Internal CRC - 0 External CRC -2 QA Defects - 0 Escaped Defects - 0 "
A36: NA | B36: MCS 25 Sprint 25 | C36: 46010 | D36: 46037 | E36: 9 | F36: 4 | G36: 12 | I36: 1.Vaishnavi-Completed the story-Link Privacy Statement in T&C's 2.Vaishnavi-Completed the story- Update Customer support link | J36: "Internal CRC - 0 External CRC -0 QA Defects - 0 Escaped Defects - 0 "
A37: NA | B37: MCS 26 Sprint 1 | C37: 46038 | D37: 46051 | E37: 9 | F37: 3 | G37: 7 | I37: 1.Vaishnavi-Completed the story-Add Buy American exception dropdown in Item-Specifics 2.Vaishnavi-Completed the story- Add Support for "Bulk Production" preference to the checklist 3.Hariharan -Completed the story- Plugin - Add Support for Non-Reimbursable Snack to GA Claim Export | J37: "Internal CRC - 4 External CRC -1 QA Defects - 0 Escaped Defects - 0 " | K37: External:Hari received kudos from Kalai for his support with clarifications, handling struggles, and bounce back, and from Joshua for his excellent communication. Internal: The team collaborated smoothly and efficiently. | P37: 2
A38: NA | B38: MCS 26 Sprint 2 | C38: 46052 | D38: 46065 | E38: 6 | F38: 4 | G38: 5 | I38: 1.Vaishnavi-Completed the story-Checklists Visibility Settings. 2.Hariharan -Completed the story- Plugin - Import Price Contract Update - Append and Inactivate | J38: "Internal CRC - 2 External CRC -1 QA Defects - 0 Escaped Defects - 0 " | K38: Internal: Hari– Successfully completed the Buy American initiative.He managed to continue the story even though the acceptance criteria were unclear. The attendance report work was delayed due to Vaishnavi’s unplanned PTO, but he adjusted and kept moving forward. He also faced bouncebacks on Import Price Contracts and updates, yet completed the task successfully. he had trouble validating Sioux City Schools at first because of missing details, but he followed up and got the needed information. Florina – Effectively executed the changes to test cases from writing. External: The team collaborated smoothly and efficiently.. | L38: Hari - Vaishnavi - 6 Florina - Ganesh - | P38: 0
A39: NA | B39: MCS 26 Sprint 3 | C39: 46066 | D39: 46079 | E39: 8 | F39: 5 | G39: 8 | I39: 1.Vaishnavi-Completed the story-Fix sorting in Allergen Reports. 2.Vaishnavi-Completed the story-Apply USDA Feedback to Meal Planning Reports. 3.Hariharan -Completed the story-Enable SmartSense Integration in System Settings. 4.Hariharan -Completed the story-Plugin - Generic ERP Export SFTP support | J39: "Internal CRC - 1 External CRC -0 QA Defects - 0 Escaped Defects - 0 | K39: Internal: Overall Team Collabration was good.. External: Teams should regularly practice Git, rebasing, and merging to establish these as standard habits. | L39: Hari - Vaishnavi - Florina - 1 Ganesh - | P39: 1
A40: NA | B40: MCS 26 Sprint 4 | C40: 46080 | D40: 46093 | E40: 4 | F40: 4 | G40: 7 | I40: 1.Hariharan -Completed the story-Atlanta Report Request Built off of Record of Attendance Report. 2.Hariharan -Completed the story-Buy American Tracking Report. 3.Hariharan -Completed the defect-Log File is Almost 200 gig. | J40: "Internal CRC - 0 External CRC -0 QA Defects - 0 Escaped Defects - 2 | K40: Internal: Overall Team Collabration was good.. External: All code changes need peer review. If changes are requested, the PR creator must ask for another review after updates | L40: Hari - Vaishnavi - Florina - Ganesh - | P40: 1
A41: NA | B41: MCS 26 Sprint 5 | C41: 46094 | D41: 46107 | E41: Nil | F41: 1 | G41: 17 | I41: 1.Hariharan -Completed the story-Federal Edit Check - Flag when Attendance < total claim | J41: "Internal CRC - 4 External CRC -1 QA Defects - 0 Escaped Defects - 2 | K41: Internal: The team collaborated well overall External: | L41: Hari - Vaishnavi - Florina - Ganesh - | P41: Nil
A42: NA | B42: MCS 26 Sprint 6 | C42: 46108 | D42: 46121 | E42: 8 | F42: 8 | G42: 8 | H42: 1.Sprint went smoothly with all committed work completed. 2.Hariharan Dhandapani delivered an additional stretch story. 3.Production issues were addressed effectively during the sprint. 4.No blockers. 5.The sprint was efficient and productive. 6.Extra value was delivered beyond the committed scope. 7.Teamwork kept progress steady. | I42: 1.Hariharan -Completed the story-SunBucks & Summer EBT Printable Notification Letter. 2.Hariharan -Completed the story-Update Receiving Screen to Prioritize Vendor Item Number. 3.Hariharan -Completed the story-Georgia Plugin DE0118 report error after Newton 26.3 release 4.Hariharan -Completed the story- Add a new custom token for the Application Approval Result Status. 5.Hariharan -Completed the defect-Benefits Explanation Letter for CEP Schools Needs to Show Status From Processed Application. 6.Hariharan -Completed the defect-Production Report Duplicating Discarded | J42: "Internal CRC - 1 External CRC -4 QA Defects - 0 Escaped Defects - 2 | K42: What went well: Overall, this sprint went smoothly. We completed the committed story and Hariharan Dhandapani successfully delivered a small stretch story along with addressing production issues. What Didn't go well: N/A | L42: Hari - Vaishnavi - Florina - Ganesh - | P42: 2
A43: NA | B43: MCS 26 Sprint 7 | C43: 46122 | D43: 46135 | E43: 5 | F43: 5 | G43: 7 | H43: 1.The sprint was efficient and productive. 2.No blockers. | I43: 1.Vaishnavi-Completed the story- Add support for Hyperlinks to Email. 2.Vaishnavi -Completed the story- Edison Report Layout Override - Additional Data Field Additions Needed. 3.Vaishnavi -Completed the story- Expand Temperature Log Records that are Required on Recipe. | J43: "Internal CRC - 4 External CRC -0 QA Defects - 0 Escaped Defects - 0 | K43: What went well: Overall, this sprint went smoothly. We completed the committed story. What Didn't go well: N/A | L43: Hari - Vaishnavi - Florina - 1 Ganesh -1.5 | P43: Nil
A44: NA | B44: MCS 26 Sprint 8 | C44: 46136 | D44: 46149 | E44: 2 | F44: 2 | G44: 10 | H44: 1.Sprint went smoothly with all committed work completed. 2.Hariharan Dhandapani delivered an additional stretch story. 3.No blockers. | I44: 1.Hariharan -Completed the story- Add Permissions to Add/Remove Inventory Used for Production 2.Hariharan -Completed the story-Add Generic SunBucks/Summer EBT Notification. 3.Hariharan -Completed the story- Plugin - Add MenuPlanSequence Number to Dataset for Production Reports (Table, Long, Standard). | J44: "Internal CRC -3 External CRC -2 QA Defects - 0 Escaped Defects - 0 " | K44: What went well: Overall, this sprint went smoothly. We completed the committed story and Hariharan Dhandapani successfully delivered a small stretch What Didn't go well: N/A | L44: Hari - Vaishnavi - Florina - Ganesh - | P44: 3
A45: NA | B45: MCS 26 Sprint 9 | C45: 46150 | D45: 46163 | E45: 5 | F45: Nil | G45: Nil | H45: Nil | I45: Nil | J45: "Internal CRC - 0 External CRC -0 QA Defects - 0 Escaped Defects - 0 " | L45: Hari - Vaishnavi - Florina - Ganesh - | P45: Nil

Sheet Defect-template
A1: S.No | B1: Sprint # | C1: Story/Defect ID | D1: Parent Story | E1: Developer | F1: Issue Type | G1: Issue Description | H1: Priority | I1: Defect Source | J1: Type | K1: Status | L1: Root Cause Category | M1: Comments

Sheet Unlplanned Leaves
A2: Total Unplanned Leaves | B2: =SUM(B18:E18) -> 9.5
B3: Resource Name
A4: Sprint Name | B4: Hariharan Dhandapani | C4: Vaishnavi Vinothkumar | D4: Florina Bharani Kumar | E4: Ganesh Vaidyanathan | F4: Remarks
A5: MCS 26 Sprint 2 (30-Jan-26 to 12-Feb-26) | C5: 6 | F5: Vaishnavi was on leave between 4th and 12th February because of a family emergency.
A6: MCS 26 Sprint 3 (13-Feb-26 to 26-Feb-26) | D6: 1 | F6: Florina was on leave on 23 February due to the passing of her uncle
A7: MCS 26 Sprint 4 (27-Feb-26 to 12-Mar-26)
A8: MCS 26 Sprint 5 (13-Mar-26 to 26-Mar-26)
A9: MCS 26 Sprint 6 (27-Mar-26 to 09-Apr-26)
A10: MCS 26 Sprint 6 (09-Apr-26 to 23-Apr-26 ) | D10: 1 | E10: 1.5 | F10: Florina was on leave on 23rd Apr due to voting And Ganesh was on leave on 14th Apr(half day) and 20th Apr due to mother's health
A11: MCS 26 Sprint 6 (24-Apr-26 to 07-May-26 )
A18: Total | B18: =SUM(B5:B17) -> 0 | C18: =SUM(C5:C17) -> 6 | D18: =SUM(D5:D17) -> 2 | E18: =SUM(E5:E17) -> 1.5

Sheet MCS 26 Sprint 9-Status
A1: S.No | B1: Application Name | C1: Sprint Start Date | D1: Sprint End Date | E1: Sprint | F1: Developer | G1: Story ID/Defect ID | H1: Description | I1: Status | J1: Estimated(hrs/sp) | K1: Actual(hrs/sp) | L1: Actual Hours (Worklog) | M1: Dev Start Date | N1: Dev End Date | O1: Unit testing | P1: Peer Tested By | Q1: Peer Tested Defects, if any | R1: Peer Reviewed By | S1: Peer Code Review Comments, if any | T1: PR Number/Link | U1: PR Created Date | V1: Reviewer 1 | W1: PR Approved Date | X1: Code Review Comments, if any | Y1: Reviewer 2 | Z1: Approved Date | AA1: Code Review Comments, if any2 | AB1: Internal PO -POV Comments | AC1: Client PO -POV Comments | AD1: Comments | AE1: Column1
A2: =ROW() - ROW(Table1459678101112314151316171920211823[[#Headers],[S.No]]) -> 1 | B2: =Dashboard!$J$1 -> MCS | C2: 46150 | D2: 46163 | E2: MCS 26 Sprint 9 | F2: Vaishnavi | G2: 51826 | H2: Safety Check in Franklin for MSA (Web) | I2: Story Ready For Testing | J2: 3 | K2: =Table14596781011123141513161719202118232224252627282930313233343536373839[[#This Row],[Estimated(hrs/sp)]] * 4 -> 12 | L2: 25 | M2: 46150 | N2: Nil | O2: Nil | P2: Nil | Q2: Nil | R2: Nil | S2: Nil | T2: https://dev.azure.com/heartlandschools/MCS/_git/Franklin/pullrequest/48851 | U2: 46147 | V2: Hari | W2: 46147 | X2: Nil | Y2: Andrea | Z2: 46148 | AA2: Nil | AB2: Nil | AC2: Nil
A3: =ROW() - ROW(Table1459678101112314151316171920211823[[#Headers],[S.No]]) -> 2 | B3: =Dashboard!$J$1 -> MCS | C3: 46150 | D3: 46163 | E3: MCS 26 Sprint 9 | F3: Vaishnavi | G3: 43179 | H3: Align Edison Fact Label with FDA Food Fact Label | I3: Story Ready For Testing | J3: 1 | K3: =Table14596781011123141513161719202118232224252627282930313233343536373839[[#This Row],[Estimated(hrs/sp)]] * 4 -> 4 | L3: 17 | M3: 46150 | N3: Nil | O3: Nil | P3: Nil | Q3: Nil | R3: Nil | S3: Nil | T3: https://dev.azure.com/heartlandschools/MCS/_git/Edison/pullrequest/48965 | U3: 46153 | V3: Hari | W3: 46154 | X3: Nil | Y3: Andrea | Z3: 46154 | AA3: Nil | AB3: Nil | AC3: Nil
A4: =ROW() - ROW(Table1459678101112314151316171920211823[[#Headers],[S.No]]) -> 3 | B4: =Dashboard!$J$1 -> MCS | C4: 46150 | D4: 46163 | E4: MCS 26 Sprint 9 Stretch | F4: Hariharan Dhandapani | G4: 53117 | H4: Improve Handling of Incomplete In-Person Credit Card Transactions | I4: Story Being Developed | J4: 1 | K4: =Table14596781011123141513161719202118232224252627282930313233343536373839[[#This Row],[Estimated(hrs/sp)]] * 4 -> 4 | L4: 10 | M4: 46150 | N4: Nil | O4: Nil | P4: Nil | Q4: Nil | R4: Nil | S4: Nil | T4: Nil | U4: Nil | V4: Nil | W4: Nil | X4: Nil | Y4: Nil | Z4: Nil | AA4: Nil | AB4: Nil | AC4: Nil
A5: =ROW() - ROW(Table1459678101112314151316171920211823[[#Headers],[S.No]]) -> 4 | B5: =Dashboard!$J$1 -> MCS | C5: 46150 | D5: 46163 | E5: MCS 26 Sprint 9 | F5: Vaishnavi | G5: 52692 | H5: Add Start/End Date to Price Contract in Item Usage Repo | I5: Story Peer Review | J5: 1 | K5: =Table14596781011123141513161719202118232224252627282930313233343536373839[[#This Row],[Estimated(hrs/sp)]] * 4 -> 4 | L5: 17 | M5: 46153 | N5: Nil | O5: Nil | P5: Nil | Q5: Nil | R5: Nil | S5: Nil | T5: https://dev.azure.com/heartlandschools/MCS/_git/Edison/pullrequest/49035 | U5: 46155 | V5: Hari | W5: Nil | X5: Nil | Y5: Nil | Z5: Nil | AA5: Nil | AB5: Nil | AC5: Nil
A6: =ROW() - ROW(Table1459678101112314151316171920211823[[#Headers],[S.No]]) -> 5 | B6: =Dashboard!$J$1 -> MCS | C6: 46150 | D6: 46163 | E6: MCS 26 Sprint 9 | F6: Vaishnavi | G6: 51328 | H6: Sort "orders available to receive" by Delivery Date | I6: Story Being Developed | J6: 2 | K6: =Table14596781011123141513161719202118232224252627282930313233343536373839[[#This Row],[Estimated(hrs/sp)]] * 4 -> 8 | L6: 6 | M6: 46153 | N6: Nil | O6: Nil | P6: Nil | Q6: Nil | R6: Nil | S6: Nil | T6: Nil | U6: Nil | V6: Nil | W6: Nil | X6: Nil | Y6: Nil | Z6: Nil | AA6: Nil | AB6: Nil | AC6: Nil

Sheet MCS 26 Sprint 9-Defects
A1: S.No | B1: Sprint # | C1: Story/Defect ID | D1: Parent Story | E1: Developer | F1: Issue Type | G1: Issue Description | H1: Priority | I1: Defect Source | J1: Type | K1: Status | L1: Root Cause Category | M1: Comments

Sheet MCS 26 Sprint 8-Status
A1: S.No | B1: Application Name | C1: Sprint Start Date | D1: Sprint End Date | E1: Sprint | F1: Developer | G1: Story ID/Defect ID | H1: Description | I1: Status | J1: Estimated(hrs/sp) | K1: Actual(hrs/sp) | L1: Actual Hours (Worklog) | M1: Dev Start Date | N1: Dev End Date | O1: Unit testing | P1: Peer Tested By | Q1: Peer Tested Defects, if any | R1: Peer Reviewed By | S1: Peer Code Review Comments, if any | T1: PR Number/Link | U1: PR Created Date | V1: Reviewer 1 | W1: PR Approved Date | X1: Code Review Comments, if any | Y1: Reviewer 2 | Z1: Approved Date | AA1: Code Review Comments, if any2 | AB1: Internal PO -POV Comments | AC1: Client PO -POV Comments | AD1: Comments | AE1: Column1
A2: =ROW() - ROW(Table1459678101112314151316171920211823[[#Headers],[S.No]]) -> 1 | B2: =Dashboard!$J$1 -> MCS | C2: 46136 | D2: 46149 | E2: MCS 26 Sprint 8 | F2: Hariharan Dhandapani | G2: 52664 | H2: Add Permissions to Add/Remove Inventory Used for Production | I2: Story Completed | J2: 2 | K2: =Table145967810111231415131617192021182322242526272829303132333435363738[[#This Row],[Estimated(hrs/sp)]] * 4 -> 8 | L2: Nil | M2: Nil | N2: Nil | O2: Done | P2: Ganesh | Q2: Nil | R2: Nil | S2: Nil | T2: https://dev.azure.com/heartlandschools/MCS/_git/Edison/pullrequest/48565?tracking_data=ew0KICAic291cmNlIjogIlNsYWNrUmVwb3NBcHAiLA0KICAic291cmNlX2V2ZW50X25hbWUiOiAiZ2l0LnB1bGxyZXF1ZXN0LmNyZWF0ZWQiDQp9 | U2: 46133 | V2: Andrea | W2: 46134 | X2: Nil | Y2: Nil | Z2: Nil | AA2: Nil | AB2: Nil | AC2: Nil
A3: =ROW() - ROW(Table1459678101112314151316171920211823[[#Headers],[S.No]]) -> 2 | B3: =Dashboard!$J$1 -> MCS | C3: 46136 | D3: 46149 | E3: MCS 26 Sprint 8 Stretch | F3: Vaishnavi | G3: 51826 | H3: Safety Check in Franklin for MSA (Web) | I3: Story Ready For Testing | J3: 3 | K3: =Table145967810111231415131617192021182322242526272829303132333435363738[[#This Row],[Estimated(hrs/sp)]] * 4 -> 12 | L3: 25 | M3: 46136 | N3: 46149 | O3: Nil | P3: Nil | Q3: Nil | R3: Nil | S3: Nil | T3: https://dev.azure.com/heartlandschools/MCS/_git/Franklin/pullrequest/48851 | U3: 46147 | V3: Hari | W3: 46148 | X3: 1. Change the button order . 2. Follow the existing validation and query format. 3. No need the bool datatype(sql) for Enum type. | Y3: Andrea | Z3: 46148 | AA3: Suggested a variable name | AB3: Nil | AC3: Nil
A4: =ROW() - ROW(Table1459678101112314151316171920211823[[#Headers],[S.No]]) -> 3 | B4: =Dashboard!$J$1 -> MCS | C4: 46136 | D4: 46149 | E4: MCS 26 Sprint 8 Stretch | F4: Hariharan Dhandapani | G4: 52660 | H4: MSA Client - Add Generic SunBucks/Summer EBT Notification | I4: Story Completed | J4: 1 | K4: =Table145967810111231415131617192021182322242526272829303132333435363738[[#This Row],[Estimated(hrs/sp)]] * 4 -> 4 | L4: 5 | M4: 46136 | N4: 46140 | O4: Nil | P4: Nil | Q4: Nil | R4: Nil | S4: Nil | T4: https://dev.azure.com/heartlandschools/MCS/_git/MSAClient/pullrequest/48660 | U4: 46139 | V4: Rudy | W4: 46139 | X4: Nil | Y4: Nil | Z4: Nil | AA4: Nil | AB4: Nil | AC4: Nil
A5: =ROW() - ROW(Table1459678101112314151316171920211823[[#Headers],[S.No]]) -> 4 | B5: =Dashboard!$J$1 -> MCS | C5: 46136 | D5: 46149 | E5: MCS 26 Sprint 8 Stretch | F5: Vaishnavi | G5: 43179 | H5: Align Edison Fact Label with FDA Food Fact Label | I5: Story Being Developed | J5: 3 | K5: =Table145967810111231415131617192021182322242526272829303132333435363738[[#This Row],[Estimated(hrs/sp)]] * 4 -> 12 | L5: 17 | M5: 46136 | N5: 46149 | O5: Nil | P5: Nil | Q5: Nil | R5: Nil | S5: Nil | T5: Nil | U5: Nil | V5: Nil | W5: Nil | X5: Nil | Y5: Nil | Z5: Nil | AA5: Nil | AB5: Nil | AC5: Nil
A6: =ROW() - ROW(Table1459678101112314151316171920211823[[#Headers],[S.No]]) -> 5 | B6: =Dashboard!$J$1 -> MCS | C6: 46136 | D6: 46149 | E6: MCS 26 Sprint 8 Stretch | F6: Hariharan Dhandapani | G6: 52971 | H6: Add MenuPlanSequence Number to Dataset for Production Reports (Table, Long, Standard) | I6: Story Completed | J6: 2 | K6: =Table145967810111231415131617192021182322242526272829303132333435363738[[#This Row],[Estimated(hrs/sp)]] * 4 -> 8 | L6: 27 | M6: 46136 | N6: 46149 | O6: Nil | P6: Nil | Q6: Nil | R6: Nil | S6: Nil | T6: https://dev.azure.com/heartlandschools/MCS/_git/Edison/pullrequest/48823 | U6: 46146 | V6: Andrea | W6: 46147 | X6: To add a space before parentheses. | Y6: Nil | Z6: Nil | AA6: Nil | AB6: Nil | AC6: Nil
A7: =ROW() - ROW(Table1459678101112314151316171920211823[[#Headers],[S.No]]) -> 6 | B7: =Dashboard!$J$1 -> MCS | C7: 46136 | D7: 46149 | E7: MCS 26 Sprint 8 Stretch | F7: Hariharan Dhandapani | G7: 53117 | H7: Improve Handling of Incomplete In-Person Credit Card Transactions | I7: Story Being Developed | J7: 1 | K7: =Table145967810111231415131617192021182322242526272829303132333435363738[[#This Row],[Estimated(hrs/sp)]] * 4 -> 4 | L7: 10 | M7: 46147 | N7: 46149 | O7: Nil | P7: Nil | Q7: Nil | R7: Nil | S7: Nil | T7: Nil | U7: Nil | V7: Nil | W7: Nil | X7: Nil | Y7: Nil | Z7: Nil | AA7: Nil | AB7: Nil | AC7: Nil

Sheet MCS 26 Sprint 8-Defects
A1: S.No | B1: Sprint # | C1: Story/Defect ID | D1: Parent Story | E1: Developer | F1: Issue Type | G1: Issue Description | H1: Priority | I1: Defect Source | J1: Type | K1: Status | L1: Root Cause Category | M1: Comments

Sheet MCS 26 Sprint 7-Status
A1: S.No | B1: Application Name | C1: Sprint Start Date | D1: Sprint End Date | E1: Sprint | F1: Developer | G1: Story ID/Defect ID | H1: Description | I1: Status | J1: Estimated(hrs/sp) | K1: Actual(hrs/sp) | L1: Actual Hours (Worklog) | M1: Dev Start Date | N1: Dev End Date | O1: Unit testing | P1: Peer Tested By | Q1: Peer Tested Defects, if any | R1: Peer Reviewed By | S1: Peer Code Review Comments, if any | T1: PR Number/Link | U1: PR Created Date | V1: Reviewer 1 | W1: PR Approved Date | X1: Code Review Comments, if any | Y1: Reviewer 2 | Z1: Approved Date | AA1: Code Review Comments, if any2 | AB1: Internal PO -POV Comments | AC1: Client PO -POV Comments | AD1: Comments | AE1: Column1
A2: =ROW() - ROW(Table1459678101112314151316171920211823[[#Headers],[S.No]]) -> 1 | B2: =Dashboard!$J$1 -> MCS | C2: 46122 | D2: 46135 | E2: MCS 26 Sprint 7 | F2: Vaishnavi | G2: 50607 | H2: Add support for Hyperlinks to Email | I2: Story Completed | J2: 2 | K2: =Table1459678101112314151316171920211823222425262728293031323334353637[[#This Row],[Estimated(hrs/sp)]] * 4 -> 8 | L2: 8 | M2: 46128 | N2: 46132 | O2: Done | P2: Ganesh | Q2: Nil | R2: Nil | S2: Nil | T2: https://dev.azure.com/heartlandschools/MCS/_git/Franklin/pullrequest/47949 | U2: 46104 | V2: Hariharan Dhandapani | W2: 46105 | X2: Nil | Y2: Rudy | Z2: 46112 | AA2: Nil | AB2: Nil | AC2: Nil
A3: =ROW() - ROW(Table1459678101112314151316171920211823[[#Headers],[S.No]]) -> 2 | B3: =Dashboard!$J$1 -> MCS | C3: 46122 | D3: 46135 | E3: MCS 26 Sprint 7 | F3: Vaishnavi | G3: 52486 | H3: Edison Report Layout Override - Additional Data Field Additions Needed | I3: Story Completed | J3: 1 | K3: =Table1459678101112314151316171920211823222425262728293031323334353637[[#This Row],[Estimated(hrs/sp)]] * 4 -> 4 | L3: 6 | M3: 46126 | N3: 46126 | O3: Done | P3: Ganesh | Q3: Nil | R3: Nil | S3: Nil | T3: https://dev.azure.com/heartlandschools/MCS/_git/Edison/pullrequest/48380 | U3: 46125 | V3: Hariharan Dhandapani | W3: 46128 | X3: 1.Use the function intead of select query and avoid the unwanted code | Y3: Andrea | Z3: 46128 | AA3: Nil | AB3: Nil | AC3: Nil
A4: =ROW() - ROW(Table1459678101112314151316171920211823[[#Headers],[S.No]]) -> 3 | B4: =Dashboard!$J$1 -> MCS | C4: 46122 | D4: 46135 | E4: MCS 26 Sprint 7 | F4: Vaishnavi | G4: 52669 | H4: Expand Temperature Log Records that are Required on Recipe | I4: Story Completed | J4: 2 | K4: =Table1459678101112314151316171920211823222425262728293031323334353637[[#This Row],[Estimated(hrs/sp)]] * 4 -> 8 | L4: 12 | M4: 46125 | N4: 46132 | O4: Done | P4: Ganesh | Q4: Nil | R4: Nil | S4: Nil | T4: https://dev.azure.com/heartlandschools/MCS/_git/Edison/pullrequest/48381 | U4: 46127 | V4: Hariharan Dhandapani | W4: 46133 | X4: 1.Place it in a sorted order. 2.To follow the exsiting same functionality. 3.To avoid unwanted automatically generated UI code. | Y4: Andrea | Z4: 46134 | AA4: Nil | AB4: Nil | AC4: Nil
A5: =ROW() - ROW(Table1459678101112314151316171920211823[[#Headers],[S.No]]) -> 4 | B5: =Dashboard!$J$1 -> MCS | C5: 46122 | D5: 46135 | E5: MCS 26 Sprint 7 Stretch | F5: Hariharan Dhandapani | G5: 52664 | H5: Add Permissions to Add/Remove Inventory Used for Production | I5: Story Ready For Testing | J5: 3 | K5: =Table1459678101112314151316171920211823222425262728293031323334353637[[#This Row],[Estimated(hrs/sp)]] * 4 -> 12 | L5: 12 | M5: 46125 | N5: 46134 | O5: Done | P5: Ganesh | Q5: Nil | R5: Nil | S5: Nil | T5: https://dev.azure.com/heartlandschools/MCS/_git/Edison/pullrequest/48565?tracking_data=ew0KICAic291cmNlIjogIlNsYWNrUmVwb3NBcHAiLA0KICAic291cmNlX2V2ZW50X25hbWUiOiAiZ2l0LnB1bGxyZXF1ZXN0LmNyZWF0ZWQiDQp9 | U5: 46133 | V5: Andrea | W5: 46134 | X5: Nil | Y5: Nil | Z5: Nil | AA5: Nil | AB5: Nil | AC5: Nil
A6: =ROW() - ROW(Table1459678101112314151316171920211823[[#Headers],[S.No]]) -> 5 | B6: =Dashboard!$J$1 -> MCS | C6: 46122 | D6: 46135 | E6: MCS 26 Sprint 7 Stretch | F6: Vaishnavi | G6: 51826 | H6: Safety Check in Franklin for MSA (Web) | I6: Story Being Developed | J6: 3 | K6: =Table1459678101112314151316171920211823222425262728293031323334353637[[#This Row],[Estimated(hrs/sp)]] * 4 -> 12 | L6: 21 | M6: 46128 | N6: 46135 | O6: Nil | P6: Nil | Q6: Nil | R6: Nil | S6: Nil | T6: Nil | U6: Nil | V6: Nil | W6: Nil | X6: Nil | Y6: Nil | Z6: Nil | AA6: Nil | AB6: Nil | AC6: Nil
A7: =ROW() - ROW(Table1459678101112314151316171920211823[[#Headers],[S.No]]) -> 6 | B7: =Dashboard!$J$1 -> MCS | C7: 46122 | D7: 46135 | E7: MCS 26 Sprint 7 Stretch | F7: Hariharan Dhandapani | G7: 52660 | H7: Client - Add Generic SunBucks/Summer EBT Notification | I7: Story Being Developed | J7: 1 | K7: =Table1459678101112314151316171920211823222425262728293031323334353637[[#This Row],[Estimated(hrs/sp)]] * 4 -> 4 | L7: 10 | M7: 46133 | N7: 46134 | O7: Nil | P7: Nil | Q7: Nil | R7: Nil | S7: Nil | T7: Nil | U7: Nil | V7: Nil | W7: Nil | X7: Nil | Y7: Nil | Z7: Nil | AA7: Nil | AB7: Nil | AC7: Nil

Sheet MCS 26 Sprint 7-Defects
A1: S.No | B1: Sprint # | C1: Story/Defect ID | D1: Parent Story | E1: Developer | F1: Issue Type | G1: Issue Description | H1: Priority | I1: Defect Source | J1: Type | K1: Status | L1: Root Cause Category | M1: Comments

Sheet MCS 26 Sprint 6-Status 
A1: S.No | B1: Application Name | C1: Sprint Start Date | D1: Sprint End Date | E1: Sprint | F1: Developer | G1: Story ID/Defect ID | H1: Description | I1: Status | J1: Estimated(hrs/sp) | K1: Actual(hrs/sp) | L1: Actual Hours (Worklog) | M1: Dev Start Date | N1: Dev End Date | O1: Unit testing | P1: Peer Tested By | Q1: Peer Tested Defects, if any | R1: Peer Reviewed By | S1: Peer Code Review Comments, if any | T1: PR Number/Link | U1: PR Created Date | V1: Reviewer 1 | W1: PR Approved Date | X1: Code Review Comments, if any | Y1: Reviewer 2 | Z1: Approved Date | AA1: Code Review Comments, if any2 | AB1: Internal PO -POV Comments | AC1: Client PO -POV Comments | AD1: Comments | AE1: Column1
A2: =ROW() - ROW(Table1459678101112314151316171920211823[[#Headers],[S.No]]) -> 1 | B2: =Dashboard!$J$1 -> MCS | C2: 46108 | D2: 46121 | E2: MCS 26 Sprint 6 Stretch | F2: Vaishnavi | G2: 50607 | H2: Add support for Hyperlinks to Email | I2: Story Ready For Testing | J2: 2 | K2: =Table14596781011123141513161719202118232224252627282930313233343536[[#This Row],[Estimated(hrs/sp)]] * 4 -> 8 | L2: 2 | M2: 46111 | N2: 46111 | O2: Done | P2: Ganesh | Q2: Nil | R2: Hariharan Dhandapani | S2: Nil | T2: https://dev.azure.com/heartlandschools/MCS/_git/Franklin/pullrequest/47949 | U2: 46104 | V2: Hariharan Dhandapani | W2: 46105 | X2: Nil | Y2: Rudy | Z2: 46112 | AA2: 1.Use ParserTemplate function and include nested tokens 2.Constructor and reuse it during the lifetime of the object | AB2: Nil | AC2: Nil
A3: =ROW() - ROW(Table1459678101112314151316171920211823[[#Headers],[S.No]]) -> 2 | B3: =Dashboard!$J$1 -> MCS | C3: 46108 | D3: 46121 | E3: MCS 26 Sprint 6 | F3: Vaishnavi | G3: 52340 | H3: Add a new custom token for the Application Approval Result Status | I3: Story Completed | J3: 2 | K3: =Table14596781011123141513161719202118232224252627282930313233343536[[#This Row],[Estimated(hrs/sp)]] * 4 -> 8 | L3: Nil | M3: Nil | N3: Nil | O3: Done | P3: Ganesh | Q3: Nil | R3: Hariharan Dhandapani | S3: Nil | T3: https://dev.azure.com/heartlandschools/MCS/_git/Franklin/pullrequest/47906 | U3: 46100 | V3: Hariharan Dhandapani | W3: 46106 | X3: Nil | Y3: Andrea | Z3: 46107 | AA3: Nil | AB3: Nil | AC3: Nil
A4: =ROW() - ROW(Table1459678101112314151316171920211823[[#Headers],[S.No]]) -> 3 | B4: =Dashboard!$J$1 -> MCS | C4: 46108 | D4: 46121 | E4: MCS 26 Sprint 6 | F4: Hariharan Dhandapani | G4: 52337 | H4: SunBucks & Summer EBT Printable Notification Letter | I4: Story Completed | J4: 2 | K4: =Table14596781011123141513161719202118232224252627282930313233343536[[#This Row],[Estimated(hrs/sp)]] * 4 -> 8 | L4: 15 | M4: 46111 | N4: 46115 | O4: Done | P4: Ganesh | Q4: Nil | R4: Nil | S4: Nil | T4: https://dev.azure.com/heartlandschools/MCS/_git/MSAClient/pullrequest/48234 | U4: 46119 | V4: Andrea | W4: 46120 | X4: Uuse var instead of string | Y4: Nil | Z4: Nil | AA4: Nil | AB4: Nil | AC4: Nil
A5: =ROW() - ROW(Table1459678101112314151316171920211823[[#Headers],[S.No]]) -> 4 | B5: =Dashboard!$J$1 -> MCS | C5: 46108 | D5: 46121 | E5: MCS 26 Sprint 6 Stretch | F5: Vaishnavi | G5: 52486 | H5: Edison Report Layout Override - Additional Data Field Additions Needed | I5: Story Peer Review | J5: 2 | K5: =Table14596781011123141513161719202118232224252627282930313233343536[[#This Row],[Estimated(hrs/sp)]] * 4 -> 8 | L5: 24 | M5: 46113 | N5: 46118 | O5: Nil | P5: Nil | Q5: Nil | R5: Nil | S5: Nil | T5: Nil | U5: Nil | V5: Nil | W5: Nil | X5: Nil | Y5: Nil | Z5: Nil | AA5: Nil | AB5: Nil | AC5: Nil
A6: =ROW() - ROW(Table1459678101112314151316171920211823[[#Headers],[S.No]]) -> 5 | B6: =Dashboard!$J$1 -> MCS | C6: 46108 | D6: 46121 | E6: MCS 26 Sprint 6 Stretch | F6: Hariharan Dhandapani | G6: 52672 | H6: Update Receiving Screen to Prioritize Vendor Item Number | I6: Story Completed | J6: 1 | K6: =Table14596781011123141513161719202118232224252627282930313233343536[[#This Row],[Estimated(hrs/sp)]] * 4 -> 4 | L6: 2 | M6: 46118 | N6: 46118 | O6: Done | P6: Ganesh | Q6: Nil | R6: Nil | S6: Nil | T6: https://dev.azure.com/heartlandschools/MCS/_git/Edison/pullrequest/48247 | U6: 46118 | V6: Andrea | W6: 46119 | X6: To set the propertie name. | Y6: Nil | Z6: Nil | AA6: Nil | AB6: Nil | AC6: Nil
A7: =ROW() - ROW(Table1459678101112314151316171920211823[[#Headers],[S.No]]) -> 6 | B7: =Dashboard!$J$1 -> MCS | C7: 46108 | D7: 46121 | E7: MCS 26 Sprint 6 Stretch | F7: Vaishnavi | G7: 52669 | H7: Expand Temperature Log Records that are Required on Recipe | I7: Product Owner - Verify | J7: 2 | K7: =Table14596781011123141513161719202118232224252627282930313233343536[[#This Row],[Estimated(hrs/sp)]] * 4 -> 8 | L7: 12 | M7: 46119 | N7: 46120 | O7: Nil | P7: Nil | Q7: Nil | R7: Nil | S7: Nil | T7: Nil | U7: Nil | V7: Nil | W7: Nil | X7: Nil | Y7: Nil | Z7: Nil | AA7: Nil | AB7: Nil | AC7: Nil
A8: =ROW() - ROW(Table1459678101112314151316171920211823[[#Headers],[S.No]]) -> 7 | B8: =Dashboard!$J$1 -> MCS | C8: 46108 | D8: 46121 | E8: MCS 26 Sprint 6 Stretch | F8: Hariharan Dhandapani | G8: SRX28855 | H8: Georgia Plugin DE0118 report error after Newton 26.3 release | I8: Story Completed | J8: 1 | K8: =Table14596781011123141513161719202118232224252627282930313233343536[[#This Row],[Estimated(hrs/sp)]] * 4 -> 4 | L8: 4 | M8: 46118 | N8: 46118 | O8: Done | P8: Ganesh | Q8: Nil | R8: Nil | S8: Nil | T8: https://dev.azure.com/heartlandschools/MCS/_git/Newton/pullrequest/48249 | U8: 46118 | V8: Nil | W8: Nil | X8: Nil | Y8: Nil | Z8: Nil | AA8: Nil | AB8: Nil | AC8: Nil

Sheet MCS 26 Sprint 6-Defects
A1: S.No | B1: Sprint # | C1: Story/Defect ID | D1: Parent Story | E1: Developer | F1: Issue Type | G1: Issue Description | H1: Priority | I1: Defect Source | J1: Type | K1: Status | L1: Root Cause Category | M1: Comments
B2: MCS 26 Sprint 6 | C2: 26756 | E2: Vaishnavi | F2: Defect | G2: Benefits Explanation Letter for CEP Schools Needs to Show Status From Processed Application | H2: Minor | I2: Manual | J2: External | K2: Story Completed | L2: Existing Issue
B3: MCS 26 Sprint 6 | C3: 26994 | E3: Vaishnavi | F3: Defect | G3: Production Report Duplicating Discarded | H3: Minor | I3: Manual | J3: External | K3: Story Completed | L3: Existing Issue | M3: Suggested to enough the one new line for sql query

Sheet MCS 26 Sprint 5-Status
A1: S.No | B1: Application Name | C1: Sprint Start Date | D1: Sprint End Date | E1: Sprint | F1: Developer | G1: Story ID/Defect ID | H1: Description | I1: Status | J1: Estimated(hrs/sp) | K1: Actual(hrs/sp) | L1: Actual Hours (Worklog) | M1: Dev Start Date | N1: Dev End Date | O1: Unit testing | P1: Peer Tested By | Q1: Peer Tested Defects, if any | R1: Peer Reviewed By | S1: Peer Code Review Comments, if any | T1: PR Number/Link | U1: PR Created Date | V1: Reviewer 1 | W1: PR Approved Date | X1: Code Review Comments, if any | Y1: Reviewer 2 | Z1: Approved Date | AA1: Code Review Comments, if any2 | AB1: Internal PO -POV Comments | AC1: Client PO -POV Comments | AD1: Comments | AE1: Column1
A2: =ROW() - ROW(Table1459678101112314151316171920211823[[#Headers],[S.No]]) -> 1 | B2: =Dashboard!$J$1 -> MCS | C2: 46094 | D2: 46107 | E2: MCS 26 Sprint 5 Stretch | F2: Vaishnavi | G2: 50607 | H2: Add support for Hyperlinks to Email | I2: Story Peer Review | J2: 2 | K2: =Table145967810111231415131617192021182322242526272829303132333435[[#This Row],[Estimated(hrs/sp)]] * 4 -> 8 | L2: 2 | M2: 46100 | N2: 46100 | O2: Done | P2: Ganesh | Q2: Nil | R2: Nil | S2: Nil | T2: https://dev.azure.com/heartlandschools/MCS/_git/Franklin/pullrequest/47949 | U2: 46104 | V2: Hariharan Dhandapani | W2: 46105 | X2: 1.Remove inline comments. 2. Call the reference directly instead of importing. 3.Replace separately and Avoid Regex . | Y2: Rudy | Z2: 46105 | AA2: Create a reusable method for repeated functions. | AB2: Nil | AC2: Nil | AD2: Done With POV.
A3: =ROW() - ROW(Table1459678101112314151316171920211823[[#Headers],[S.No]]) -> 2 | B3: =Dashboard!$J$1 -> MCS | C3: 46094 | D3: 46107 | E3: MCS 26 Sprint 5 Stretch | F3: Hariharan Dhandapani | G3: 43641 | H3: Federal Edit Check - Flag when Attendance < total claim | I3: Story Completed | J3: 1 | K3: =Table145967810111231415131617192021182322242526272829303132333435[[#This Row],[Estimated(hrs/sp)]] * 4 -> 4 | L3: 14 | M3: 46100 | N3: 46100 | O3: Done | P3: Ganesh | Q3: Nil | R3: Nil | S3: Nil | T3: https://dev.azure.com/heartlandschools/MCS/_git/Newton/pullrequest/47592 | U3: 46057 | V3: Andrea | W3: 46057 | X3: Nil | Y3: Nil | Z3: Nil | AA3: Nil | AB3: Nil | AC3: Nil
A4: =ROW() - ROW(Table1459678101112314151316171920211823[[#Headers],[S.No]]) -> 3 | B4: =Dashboard!$J$1 -> MCS | C4: 46094 | D4: 46107 | E4: MCS 26 Sprint 5 Stretch | F4: Vaishnavi | G4: 52340 | H4: MCS - FR - Add a new custom token for the Application Approval Result Status | I4: Story Ready For Testing | J4: 2 | K4: =Table145967810111231415131617192021182322242526272829303132333435[[#This Row],[Estimated(hrs/sp)]] * 4 -> 8 | L4: 12 | M4: 46094 | N4: 46106 | O4: Done | P4: Ganesh | Q4: Nil | R4: Hariharan Dhandapani | S4: Avoid DB call and Include description. | T4: https://dev.azure.com/heartlandschools/MCS/_git/Franklin/pullrequest/47906 | U4: 46100 | V4: Hariharan Dhandapani | W4: 46106 | X4: Nil | Y4: 46107 | Z4: Nil | AA4: Nil | AB4: Nil | AC4: Nil
A5: =ROW() - ROW(Table1459678101112314151316171920211823[[#Headers],[S.No]]) -> 4 | B5: =Dashboard!$J$1 -> MCS | C5: 46094 | D5: 46107 | E5: MCS 26 Sprint 5 Stretch | F5: Hariharan Dhandapani | G5: 52337 | H5: SunBucks & Summer EBT Printable Notification Letter | I5: Story Being Developed | J5: 8 | K5: =Table145967810111231415131617192021182322242526272829303132333435[[#This Row],[Estimated(hrs/sp)]] * 4 -> 32 | L5: 35 | M5: 46100 | N5: 46100 | O5: Nil | P5: Nil | Q5: Nil | R5: Nil | S5: Nil | T5: Nil | U5: Nil | V5: Nil | W5: Nil | X5: Nil | Y5: Nil | Z5: Nil | AA5: Nil | AB5: Nil | AC5: Nil

Sheet MCS 26 Sprint 5-Defects
A1: S.No | B1: Sprint # | C1: Story/Defect ID | D1: Parent Story | E1: Developer | F1: Issue Type | G1: Issue Description | H1: Priority | I1: Defect Source | J1: Type | K1: Status | L1: Root Cause Category | M1: Comments
B2: MCS 26 Sprint 5 Stretch | C2: 26756 | E2: Vaishnavi | F2: Defect | G2: Benefits Explanation Letter for CEP Schools Needs to Show Status From Processed Application | H2: Minor | I2: Manual | J2: External | K2: Story Peer Review | L2: Existing Issue | M2: The analysis took longer because the changes were made about 15 years ago, and it took extra time to get the functionality working. They asked for a second round POV.
B3: MCS 26 Sprint 5 Stretch | C3: 26994 | E3: Vaishnavi | F3: Defect | G3: Production Report Duplicating Discarded | H3: Minor | I3: Manual | J3: External | K3: Defect Being Fixed | L3: Existing Issue | M3: The defect was taken mid‑sprint. The implementation was completed, and dev testing is in progress.

Sheet MCS 26 Sprint 4-Status
A1: S.No | B1: Application Name | C1: Sprint Start Date | D1: Sprint End Date | E1: Sprint | F1: Developer | G1: Story ID/Defect ID | H1: Description | I1: Status | J1: Estimated(hrs/sp) | K1: Actual(hrs/sp) | L1: Actual Hours (Worklog) | M1: Dev Start Date | N1: Dev End Date | O1: Unit testing | P1: Peer Tested By | Q1: Peer Tested Defects, if any | R1: Peer Reviewed By | S1: Peer Code Review Comments, if any | T1: PR Number/Link | U1: PR Created Date | V1: Reviewer 1 | W1: PR Approved Date | X1: Code Review Comments, if any | Y1: Reviewer 2 | Z1: Approved Date | AA1: Code Review Comments, if any2 | AB1: Internal PO -POV Comments | AC1: Client PO -POV Comments | AD1: Comments | AE1: Column1
A2: =ROW() - ROW(Table1459678101112314151316171920211823[[#Headers],[S.No]]) -> 1 | B2: =Dashboard!$J$1 -> MCS | C2: 46080 | D2: 46093 | E2: MCS 26 Sprint 4 | F2: Hariharan Dhandapani | G2: 50900 | H2: Atlanta Report Request Built off of Record of Attendance Report | I2: Story Completed | J2: 1 | K2: =Table1459678101112314151316171920211823222425262728293031323334[[#This Row],[Estimated(hrs/sp)]] * 4 -> 4 | L2: Nil | M2: Nil | N2: Nil | O2: Done | P2: Vaishnavi | Q2: Nil | R2: Nil | S2: Nil | T2: https://dev.azure.com/heartlandschools/MCS/_git/Newton/pullrequest/47309 | U2: 46072 | V2: Nil | W2: 46072 | X2: Nil | Y2: Nil | Z2: Nil | AA2: Nil | AB2: Nil | AC2: Nil
A3: =ROW() - ROW(Table1459678101112314151316171920211823[[#Headers],[S.No]]) -> 2 | B3: =Dashboard!$J$1 -> MCS | C3: 46080 | D3: 46093 | E3: MCS 26 Sprint 4 | F3: Hariharan Dhandapani | G3: 49673 | H3: Buy American Tracking Report | I3: Story Completed | J3: 3 | K3: =Table1459678101112314151316171920211823222425262728293031323334[[#This Row],[Estimated(hrs/sp)]] * 4 -> 12 | L3: 4 | M3: Nil | N3: Nil | O3: Nil | P3: Nil | Q3: Nil | R3: Nil | S3: Nil | T3: https://dev.azure.com/heartlandschools/MCS/_git/Edison/pullrequest/47308 | U3: 46071 | V3: Andrea | W3: 46071 | X3: Nil | Y3: Nil | Z3: Nil | AA3: Nil | AB3: Nil | AC3: Nil | AD3: Current sprint focuses only on testing.
A4: =ROW() - ROW(Table1459678101112314151316171920211823[[#Headers],[S.No]]) -> 3 | B4: =Dashboard!$J$1 -> MCS | C4: 46080 | D4: 46093 | E4: MCS 26 Sprint 4 Stretch | F4: Vaishnavi | G4: 50607 | H4: Add support for Hyperlinks to Email | I4: Story Peer Review | J4: 2 | K4: =Table1459678101112314151316171920211823222425262728293031323334[[#This Row],[Estimated(hrs/sp)]] * 4 -> 8 | L4: 30 | M4: 46080 | N4: 46056 | O4: Done | P4: Ganesh | Q4: Nil | R4: Nil | S4: Nil | T4: Nil | U4: Nil | V4: Nil | W4: Nil | X4: Nil | Y4: Nil | Z4: Nil | AA4: Nil | AB4: Nil | AC4: Nil | AD4: Done With POV, Created PR
A5: =ROW() - ROW(Table1459678101112314151316171920211823[[#Headers],[S.No]]) -> 4 | B5: =Dashboard!$J$1 -> MCS | C5: 46080 | D5: 46093 | E5: MCS 26 Sprint 4 Stretch | F5: Hariharan Dhandapani | G5: 43641 | H5: Federal Edit Check - Flag when Attendance < total claim | I5: Story Being Tested | J5: 2 | K5: =Table1459678101112314151316171920211823222425262728293031323334[[#This Row],[Estimated(hrs/sp)]] * 4 -> 8 | L5: 14 | M5: 46080 | N5: 46057 | O5: Done | P5: Nil | Q5: Nil | R5: Nil | S5: Nil | T5: https://dev.azure.com/heartlandschools/MCS/_git/Newton/pullrequest/47592 | U5: 46057 | V5: Andrea | W5: 46057 | X5: Nil | Y5: Nil | Z5: Nil | AA5: Nil | AB5: Nil | AC5: Nil

Sheet MCS 26 Sprint 4-Defects
A1: S.No | B1: Sprint # | C1: Story/Defect ID | D1: Parent Story | E1: Developer | F1: Issue Type | G1: Issue Description | H1: Priority | I1: Defect Source | J1: Type | K1: Status | L1: Root Cause Category | M1: Comments
B2: MCS 26 Sprint 4 Stretch | C2: 26756 | E2: Vaishnavi | F2: Defect | G2: Benefits Explanation Letter for CEP Schools Needs to Show Status From Processed Application | H2: Minor | I2: Manual | J2: External | K2: Product Owner - Verify | L2: Existing Issue | M2: The development work has been completed, and we are now waiting for the Product Owner to verify and provide feedback before moving forward
B3: MCS 26 Sprint 4 Stretch | C3: 26820 | E3: Hariharan Dhandapani | F3: Defect | G3: Log File is Almost 200 gig | H3: Minor | I3: Manual | J3: External | K3: Defect Fixed | L3: Existing Issue

Sheet MCS 26 Sprint 3-Status
A1: S.No | B1: Application Name | C1: Sprint Start Date | D1: Sprint End Date | E1: Sprint | F1: Developer | G1: Story ID/Defect ID | H1: Description | I1: Status | J1: Estimated(hrs/sp) | K1: Actual(hrs/sp) | L1: Actual Hours (Worklog) | M1: Dev Start Date | N1: Dev End Date | O1: Unit testing | P1: Peer Tested By | Q1: Peer Tested Defects, if any | R1: Peer Reviewed By | S1: Peer Code Review Comments, if any | T1: PR Number/Link | U1: PR Created Date | V1: Reviewer 1 | W1: PR Approved Date | X1: Code Review Comments, if any | Y1: Reviewer 2 | Z1: Approved Date | AA1: Code Review Comments, if any2 | AB1: Internal PO -POV Comments | AC1: Client PO -POV Comments | AD1: Comments | AE1: Column1
A2: =ROW() - ROW(Table1459678101112314151316171920211823[[#Headers],[S.No]]) -> 1 | B2: =Dashboard!$J$1 -> MCS | C2: 46066 | D2: 46079 | E2: MCS 26 Sprint 3 | F2: Vaishnavi | G2: 51943 | H2: Fix sorting in Allergen Reports | I2: Story Completed | J2: 1 | K2: =Table14596781011123141513161719202118232224252627282930313233[[#This Row],[Estimated(hrs/sp)]] * 4 -> 4 | L2: 10 | M2: 46066 | N2: 46072 | O2: Done | P2: Ganesh | Q2: Nil | R2: Nil | S2: Follow the correct boolean format | T2: https://dev.azure.com/heartlandschools/MCS/_git/Edison/pullrequest/47359 | U2: 46072 | V2: Hariharan Dhandapani | W2: 46073 | X2: Nil | Y2: Andrea | Z2: 46073 | AA2: Nil | AB2: Nil | AC2: Nil
A3: =ROW() - ROW(Table1459678101112314151316171920211823[[#Headers],[S.No]]) -> 2 | B3: =Dashboard!$J$1 -> MCS | C3: 46066 | D3: 46079 | E3: MCS 26 Sprint 3 Stretch | F3: Hariharan Dhandapani | G3: 50900 | H3: Atlanta Report Request Built off of Record of Attendance Report | I3: Story Ready For Testing | J3: 2 | K3: =Table14596781011123141513161719202118232224252627282930313233[[#This Row],[Estimated(hrs/sp)]] * 4 -> 8 | L3: 6 | M3: 46066 | N3: 46072 | O3: Done | P3: Vaishnavi | Q3: Nil | R3: Nil | S3: Nil | T3: https://dev.azure.com/heartlandschools/MCS/_git/Newton/pullrequest/47309 | U3: 46072 | V3: Nil | W3: 46072 | X3: Nil | Y3: Nil | Z3: Nil | AA3: Nil | AB3: Nil | AC3: Nil
A4: =ROW() - ROW(Table1459678101112314151316171920211823[[#Headers],[S.No]]) -> 3 | B4: =Dashboard!$J$1 -> MCS | C4: 46066 | D4: 46079 | E4: MCS 26 Sprint 3 | F4: Vaishnavi | G4: 51542 | H4: Apply USDA Feedback to Meal Planning Reports | I4: Story Completed | J4: 1 | K4: =Table145967810111231415131617192021182322242526272829303132[[#This Row],[Estimated(hrs/sp)]] * 4 -> 8 | L4: Nil | M4: Nil | N4: Nil | O4: Done | P4: Ganesh | Q4: Nil | R4: Nil | S4: 1.Handle the repeated code in a common way. 2. Avoid Margins and use same verson for report UI. 3. Use common functions for repeated condition. | T4: https://dev.azure.com/heartlandschools/MCS/_git/Edison/pullrequest/46873 | U4: 46049 | V4: Hariharan Dhandapani | W4: 46051 | X4: Suggested variable name | Y4: Andrea | Z4: 46058 | AA4: Nil | AB4: Nil | AC4: Nil
A5: =ROW() - ROW(Table1459678101112314151316171920211823[[#Headers],[S.No]]) -> 4 | B5: =Dashboard!$J$1 -> MCS | C5: 46066 | D5: 46079 | E5: MCS 26 Sprint 3 | F5: Hariharan Dhandapani | G5: 49673 | H5: Buy American Tracking Report | I5: Story Being Tested | J5: 3 | K5: =Table14596781011123141513161719202118232224252627282930313233[[#This Row],[Estimated(hrs/sp)]] * 4 -> 12 | L5: Nil | M5: Nil | N5: Nil | O5: Done | P5: Done | Q5: Nil | R5: Nil | S5: Nil | T5: https://dev.azure.com/heartlandschools/MCS/_git/Edison/pullrequest/47308 | U5: 46071 | V5: Andrea | W5: 46071 | X5: Nil | Y5: Nil | Z5: Nil | AA5: Nil | AB5: Nil | AC5: Nil | AD5: Current sprint focuses only on testing. The Testing Team has not yet begun actual test execution. they have only started preparing test cases and have been engaged on another story.
A6: =ROW() - ROW(Table1459678101112314151316171920211823[[#Headers],[S.No]]) -> 5 | B6: =Dashboard!$J$1 -> MCS | C6: 46066 | D6: 46079 | E6: MCS 26 Sprint 3 Stretch | F6: Vaishnavi | G6: 50607 | H6: Add support for Hyperlinks to Email | I6: Story Being Developed | J6: 5 | K6: =Table14596781011123141513161719202118232224252627282930313233[[#This Row],[Estimated(hrs/sp)]] * 4 -> 20 | L6: 42 | M6: 46069 | N6: Nil | O6: Nil | P6: Nil | Q6: Nil | R6: Nil | S6: Nil | T6: Nil | U6: Nil | V6: Nil | W6: Nil | X6: Nil | Y6: Nil | Z6: Nil | AA6: Nil | AB6: Nil | AC6: Nil
A7: =ROW() - ROW(Table1459678101112314151316171920211823[[#Headers],[S.No]]) -> 6 | B7: =Dashboard!$J$1 -> MCS | C7: 46066 | D7: 46079 | E7: MCS 26 Sprint 3 | F7: Hariharan Dhandapani | G7: 51888 | H7: Enable SmartSense Integration in System Settings | I7: Story Completed | J7: 3 | K7: =Table14596781011123141513161719202118232224252627282930313233[[#This Row],[Estimated(hrs/sp)]] * 4 -> 12 | L7: 20 | M7: 46069 | N7: 46076 | O7: Done | P7: Ganesh | Q7: Nil | R7: Nil | S7: Nil | T7: https://dev.azure.com/heartlandschools/MCS/_git/Edison/pullrequest/47442 | U7: 46076 | V7: Andrea | W7: 46076 | X7: Nil | Y7: Nil | Z7: Nil | AA7: Nil | AB7: Nil | AC7: Nil
A8: =ROW() - ROW(Table1459678101112314151316171920211823[[#Headers],[S.No]]) -> 7 | B8: =Dashboard!$J$1 -> MCS | C8: 46066 | D8: 46079 | E8: MCS 26 Sprint 3 Stretch | F8: Hariharan Dhandapani | G8: 52035 | H8: Plugin - Generic ERP Export SFTP support | I8: Story Completed | J8: 1 | K8: =Table14596781011123141513161719202118232224252627282930313233[[#This Row],[Estimated(hrs/sp)]] * 4 -> 4 | L8: 10 | M8: 46073 | N8: Nil | O8: Done | P8: Ganesh | Q8: Nil | R8: Nil | S8: Nil | T8: https://dev.azure.com/heartlandschools/MCS/_git/Newton/pullrequest/47462 | U8: 46077 | V8: Andrea | W8: 46078 | X8: Nil | Y8: Nil | Z8: Nil | AA8: Nil | AB8: Nil | AC8: Nil

Sheet MCS 26 Sprint 3-Defects
A1: S.No | B1: Sprint # | C1: Story/Defect ID | D1: Parent Story | E1: Developer | F1: Issue Type | G1: Issue Description | H1: Priority | I1: Defect Source | J1: Type | K1: Status | L1: Root Cause Category | M1: Comments

Sheet MCS 26 Sprint 2-Status
A1: S.No | B1: Application Name | C1: Sprint Start Date | D1: Sprint End Date | E1: Sprint | F1: Developer | G1: Story ID/Defect ID | H1: Description | I1: Status | J1: Estimated(hrs/sp) | K1: Actual(hrs/sp) | L1: Actual Hours (Worklog) | M1: Dev Start Date | N1: Dev End Date | O1: Unit testing | P1: Peer Tested By | Q1: Peer Tested Defects, if any | R1: Peer Reviewed By | S1: Peer Code Review Comments, if any | T1: PR Number/Link | U1: PR Created Date | V1: Reviewer 1 | W1: PR Approved Date | X1: Code Review Comments, if any | Y1: Reviewer 2 | Z1: Approved Date | AA1: Code Review Comments, if any2 | AB1: Internal PO -POV Comments | AC1: Client PO -POV Comments | AD1: Comments | AE1: Mitigation Plan
A2: =ROW() - ROW(Table1459678101112314151316171920211823[[#Headers],[S.No]]) -> 1 | B2: =Dashboard!$J$1 -> MCS | C2: 46052 | D2: 46065 | E2: MCS 26 Sprint 2 | F2: Vaishnavi | G2: 48686 | H2: Checklists Visibility Settings | I2: Story Completed | J2: 2 | K2: =Table145967810111231415131617192021182322242526272829303132[[#This Row],[Estimated(hrs/sp)]] * 4 -> 8 | L2: Nil | M2: Nil | N2: Nil | O2: Done | P2: Ganesh | Q2: Nil | R2: Nil | S2: Nil | T2: https://dev.azure.com/heartlandschools/MCS/_git/Edison/pullrequest/45228 | U2: 45952 | V2: Hariharan Dhandapani | W2: Nil | X2: Nil | Y2: Rudy | Z2: 45966 | AA2: Nil | AB2: Nil | AC2: Nil | AD2: Development was completed in Sprint 22.The current sprint focuses only on testing
A3: =ROW() - ROW(Table1459678101112314151316171920211823[[#Headers],[S.No]]) -> 2 | B3: =Dashboard!$J$1 -> MCS | C3: 46052 | D3: 46065 | E3: MCS 26 Sprint 2 Stretch | F3: Vaishnavi | G3: 50900 | H3: Atlanta Report Request Built off of Record of Attendance Report | I3: Story Being Developed | J3: 2 | K3: =Table145967810111231415131617192021182322242526272829303132[[#This Row],[Estimated(hrs/sp)]] * 4 -> 8 | L3: 8 | M3: 46055 | N3: 46056 | O3: Nil | P3: Nil | Q3: Nil | R3: Nil | S3: Nil | T3: Nil | U3: Nil | V3: Nil | W3: Nil | X3: Nil | Y3: Nil | Z3: Nil | AA3: Nil | AB3: Nil | AC3: Nil | AD3: Pre-POV completed. After internal discussion with Hari, overall implementation has been modified and work is ongoing.
A4: =ROW() - ROW(Table1459678101112314151316171920211823[[#Headers],[S.No]]) -> 3 | B4: =Dashboard!$J$1 -> MCS | C4: 46052 | D4: 46065 | E4: MCS 26 Sprint 2 | F4: Hariharan Dhandapani | G4: 47376 | H4: Import Price Contract Update - Append and Inactivate | I4: Story Completed | J4: 2 | K4: =Table145967810111231415131617192021182322242526272829303132[[#This Row],[Estimated(hrs/sp)]] * 4 -> 8 | L4: 4 | M4: 46055 | N4: 46056 | O4: Done | P4: Ganesh | Q4: Nil | R4: Nil | S4: Nil | T4: Nil | U4: Nil | V4: Nil | W4: Nil | X4: Nil | Y4: Nil | Z4: Nil | AA4: Nil | AB4: Nil | AC4: Nil | AD4: Nil
A5: =ROW() - ROW(Table1459678101112314151316171920211823[[#Headers],[S.No]]) -> 4 | B5: =Dashboard!$J$1 -> MCS | C5: 46052 | D5: 46065 | E5: MCS 26 Sprint 2 | F5: Vaishnavi | G5: 51542 | H5: Apply USDA Feedback to Meal Planning Reports | I5: Story Being Tested | J5: 2 | K5: =Table145967810111231415131617192021182322242526272829303132[[#This Row],[Estimated(hrs/sp)]] * 4 -> 8 | L5: 4 | M5: 46055 | N5: 46056 | O5: Done | P5: Ganesh | Q5: Nil | R5: Nil | S5: 1.Handle the repeated code in a common way. 2. Avoid Margins and use same verson for report UI. 3. Use common functions for repeated condition. | T5: https://dev.azure.com/heartlandschools/MCS/_git/Edison/pullrequest/46873 | U5: 46049 | V5: Hariharan Dhandapani | W5: 46051 | X5: Suggested variable name | Y5: Andrea | Z5: 46058 | AA5: Nil | AB5: Nil | AC5: Nil | AD5: POV Completed and Raised PR. Testing is in progress. As we have only one QA for Internal and External Development teams we are facing teating Backlogs for some of the tickts wheich we have completed the development | AE5: Previously, our mitigation plan involved limiting each ticket to only UI and backend development tasks, since we already had a QA backlog. However, with the recent influx of client-driven enhancements, we have adjusted our approach by prioritizing testing efforts to focus on the most critical tasks required for each sprint.
A6: =ROW() - ROW(Table1459678101112314151316171920211823[[#Headers],[S.No]]) -> 5 | B6: =Dashboard!$J$1 -> MCS | C6: 46052 | D6: 46065 | E6: MCS 26 Sprint 2 Stretch | F6: Hariharan Dhandapani | G6: 49673 | H6: Buy American Tracking Report | I6: Product Owner - Verify | J6: 3 | K6: =Table145967810111231415131617192021182322242526272829303132[[#This Row],[Estimated(hrs/sp)]] * 4 -> 12 | L6: 42 | M6: 46051 | N6: 46050 | O6: Nil | P6: Nil | Q6: Nil | R6: Nil | S6: Nil | T6: Nil | U6: Nil | V6: Nil | W6: Nil | X6: Nil | Y6: Nil | Z6: Nil | AA6: Nil | AB6: Nil | AC6: Nil | AD6: Development is complete, awaiting POV feedback.

Sheet MCS 26 Sprint 2-Defects
A1: S.No | B1: Sprint # | C1: Story/Defect ID | D1: Parent Story | E1: Developer | F1: Issue Type | G1: Issue Description | H1: Priority | I1: Defect Source | J1: Type | K1: Status | L1: Root Cause Category | M1: Comments

Sheet MCS 26 Sprint 1-Status
A1: S.No | B1: Application Name | C1: Sprint Start Date | D1: Sprint End Date | E1: Sprint | F1: Developer | G1: Story ID/Defect ID | H1: Description | I1: Status | J1: Estimated(hrs/sp) | K1: Actual(hrs/sp) | L1: Actual Hours (Worklog) | M1: Dev Start Date | N1: Dev End Date | O1: Unit testing | P1: Peer Tested By | Q1: Peer Tested Defects, if any | R1: Peer Reviewed By | S1: Peer Code Review Comments, if any | T1: PR Number/Link | U1: PR Created Date | V1: Reviewer 1 | W1: PR Approved Date | X1: Code Review Comments, if any | Y1: Reviewer 2 | Z1: Approved Date | AA1: Code Review Comments, if any2 | AB1: Internal PO -POV Comments | AC1: Client PO -POV Comments | AD1: Comments | AE1: Mitigation Plan
A2: =ROW() - ROW(Table1459678101112314151316171920211823[[#Headers],[S.No]]) -> 1 | B2: =Dashboard!$J$1 -> MCS | C2: 46038 | D2: 46051 | E2: MCS 26 Sprint 1 | F2: Vaishnavi | G2: 48686 | H2: Checklists Visibility Settings | I2: Story Ready For Testing | J2: 3 | K2: =Table1459678101112314151316171920211823222425262728293031[[#This Row],[Estimated(hrs/sp)]] * 4 -> 12 | L2: 3 | M2: 46049 | N2: 46049 | O2: Done | P2: Ganesh | Q2: Nil | R2: Nil | S2: Nil | T2: https://dev.azure.com/heartlandschools/MCS/_git/Edison/pullrequest/45228 | U2: 45952 | V2: Hariharan Dhandapani | W2: Nil | X2: Nil | Y2: Rudy | Z2: 45966 | AA2: Nil | AB2: Nil | AC2: Nil | AD2: According to the given acceptance criteria, development was completed. During the POV, several modifications and enhancements were raised by the client, and we are currently addressing these in the ongoing sprint. I would also like to highlight a concern: a few bouncebacks were raised, and upon analysis, we found that they were actually earlier defects. However, since the client preferred not to log them as defects, we addressed them as bouncebacks. While we have resolved the issues, handling them in this way can inadvertently reflect on developer quality. I wanted to make a note of this so that we can ensure proper categorization going forward. | AE2: To avoid similar rework in the future, we will ensure that clear and complete acceptance criteria are obtained from the client during planning. Additionally, tickets will be thoroughly analyzed before development begins, so that scope and expectations are aligned upfront.
A3: =ROW() - ROW(Table1459678101112314151316171920211823[[#Headers],[S.No]]) -> 2 | B3: =Dashboard!$J$1 -> MCS | C3: 46038 | D3: 46051 | E3: MCS 26 Sprint 1 Stretch | F3: Vaishnavi | G3: 50900 | H3: Atlanta Report Request Built off of Record of Attendance Report | I3: Story Being Developed | J3: 2 | K3: =Table1459678101112314151316171920211823222425262728293031[[#This Row],[Estimated(hrs/sp)]] * 4 -> 8 | L3: 5 | M3: 46014 | N3: 46049 | O3: Nil | P3: Nil | Q3: Nil | R3: Nil | S3: Nil | T3: Nil | U3: Nil | V3: Nil | W3: Nil | X3: Nil | Y3: Nil | Z3: Nil | AA3: Nil | AB3: Nil | AC3: Nil | AD3: I would also like to highlight a concern: a few bouncebacks were raised, and upon analysis, we found that they were actually earlier defects. However, since the client preferred not to log them as defects, we addressed them as bouncebacks. While we have resolved the issues, handling them in this way can inadvertently reflect on developer quality. I wanted to make a note of this so that we can ensure proper categorization going forward.
A4: =ROW() - ROW(Table1459678101112314151316171920211823[[#Headers],[S.No]]) -> 3 | B4: =Dashboard!$J$1 -> MCS | C4: 46038 | D4: 46051 | E4: MCS 26 Sprint 1 | F4: Hariharan Dhandapani | G4: 47376 | H4: MCS - ED - Import Price Contract Update - Append and Inactivate | I4: Story Ready For Testing | J4: 3 | K4: =Table1459678101112314151316171920211823222425262728293031[[#This Row],[Estimated(hrs/sp)]] * 4 -> 12 | L4: Nil | M4: Nil | N4: Nil | O4: Done | P4: Ganesh | Q4: Nil | R4: Nil | S4: Nil | T4: Nil | U4: Nil | V4: Nil | W4: Nil | X4: Nil | Y4: Nil | Z4: Nil | AA4: Nil | AB4: Nil | AC4: Nil | AD4: Development for this story was completed in Sprint 25. However, since we had a number of high‑priority stories that needed to be pushed into production during the current sprint, the testing team focused on those items to ensure timely delivery. As a result, this story has been scheduled for completion in the next sprint. | AE4: Going forward, we will factor in QA team availability when planning tickets and align development tasks accordingly. This will ensure that testing capacity is balanced with development output, reducing backlog and maintaining quality standards.
A5: =ROW() - ROW(Table1459678101112314151316171920211823[[#Headers],[S.No]]) -> 4 | B5: =Dashboard!$J$1 -> MCS | C5: 46038 | D5: 46051 | E5: MCS 26 Sprint 1 | F5: Vaishnavi | G5: 51313 | H5: Add Buy American exception dropdown in Item-Specifics | I5: Story Completed | J5: 2 | K5: =Table1459678101112314151316171920211823222425262728293031[[#This Row],[Estimated(hrs/sp)]] * 4 -> 8 | L5: 6 | M5: 46041 | N5: 46042 | O5: Done | P5: Ganesh | Q5: Nil | R5: Nil | S5: 1.Avoid the unwanted null check. 2.Follow the existing standard for writing the upgrade queries. 3.Verify the case for the description string and move the same to the localization 4.Adjust the spacing as given for other properties. 5.Use the enum type value while initialize the property value. | T5: https://dev.azure.com/heartlandschools/MCS/_git/Edison/pullrequest/46577?path=%2FForms%2FFormMaintItem.Designer.cs&_a=files | U5: 46034 | V5: Hariharan Dhandapani | W5: 46043 | X5: Nil | Y5: Andrea | Z5: 46043 | AA5: Nil | AB5: Nil | AC5: Nil | AD5: Nil
A6: =ROW() - ROW(Table1459678101112314151316171920211823[[#Headers],[S.No]]) -> 5 | B6: =Dashboard!$J$1 -> MCS | C6: 46038 | D6: 46051 | E6: MCS 26 Sprint 1 | F6: Vaishnavi | G6: 51471 | H6: Add Support for "Bulk Production" preference to the checklist | I6: Story Completed | J6: 1 | K6: =Table1459678101112314151316171920211823222425262728293031[[#This Row],[Estimated(hrs/sp)]] * 4 -> 4 | L6: 1 | M6: 46041 | N6: 46041 | O6: Done | P6: Ganesh | Q6: Nil | R6: Nil | S6: Nil | T6: https://dev.azure.com/heartlandschools/MCS/_git/Edison/pullrequest/46778 | U6: 46043 | V6: Hariharan Dhandapani | W6: 46045 | X6: Nil | Y6: Andrea | Z6: 46045 | AA6: Nil | AB6: Nil | AC6: Nil | AD6: Nil
A7: =ROW() - ROW(Table1459678101112314151316171920211823[[#Headers],[S.No]]) -> 6 | B7: =Dashboard!$J$1 -> MCS | C7: 46038 | D7: 46051 | E7: MCS 26 Sprint 1 Stretch | F7: Vaishnavi | G7: 51542 | H7: Apply USDA Feedback to Meal Planning Reports | I7: Story Peer Review | J7: 3 | K7: =Table1459678101112314151316171920211823222425262728293031[[#This Row],[Estimated(hrs/sp)]] * 4 -> 12 | L7: 21 | M7: 46042 | N7: 46049 | O7: Done | P7: Ganesh | Q7: Nil | R7: Nil | S7: Nil | T7: https://dev.azure.com/heartlandschools/MCS/_git/Edison/pullrequest/46873 | U7: 46049 | V7: Hariharan Dhandapani | W7: Nil | X7: Nil | Y7: Nil | Z7: Nil | AA7: Nil | AB7: Nil | AC7: Nil | AD7: Completed POV, submitted the PR, and now working through the review feedback.
A8: =ROW() - ROW(Table1459678101112314151316171920211823[[#Headers],[S.No]]) -> 7 | B8: =Dashboard!$J$1 -> MCS | C8: 46038 | D8: 46051 | E8: MCS 26 Sprint 1 Stretch | F8: Hariharan Dhandapani | G8: 51537 | H8: Plugin - Add Support for Non-Reimbursable Snack to GA Claim Export | I8: Story Completed | J8: 2 | K8: =Table1459678101112314151316171920211823222425262728293031[[#This Row],[Estimated(hrs/sp)]] * 4 -> 8 | L8: 30 | M8: 46042 | N8: 46045 | O8: Done | P8: Ganesh | Q8: Nil | R8: Nil | S8: To update the prefix format for numericode | T8: https://dev.azure.com/heartlandschools/MCS/_git/Newton/pullrequest/46857 | U8: 46045 | V8: Patric | W8: 46048 | X8: Nil | Y8: Nil | Z8: Nil | AA8: Nil | AB8: Nil | AC8: Nil | AD8: Dev Testing only

Sheet MCS 26 Sprint 1-Defects
A1: S.No | B1: Sprint # | C1: Story/Defect ID | D1: Parent Story | E1: Developer | F1: Issue Type | G1: Issue Description | H1: Priority | I1: Defect Source | J1: Type | K1: Status | L1: Root Cause Category | M1: Comments

Sheet MCS 25 Sprint 25-Status
A1: S.No | B1: Application Name | C1: Sprint Start Date | D1: Sprint End Date | E1: Sprint | F1: Developer | G1: Story ID/Defect ID | H1: Description | I1: Status | J1: Estimated(hrs/sp) | K1: Actual(hrs/sp) | L1: Actual Hours (Worklog) | M1: Dev Start Date | N1: Dev End Date | O1: Unit testing | P1: Peer Tested By | Q1: Peer Tested Defects, if any | R1: Peer Reviewed By | S1: Peer Code Review Comments, if any | T1: PR Number/Link | U1: PR Created Date | V1: Reviewer 1 | W1: PR Approved Date | X1: Code Review Comments, if any | Y1: Reviewer 2 | Z1: Approved Date | AA1: Code Review Comments, if any2 | AB1: Internal PO -POV Comments | AC1: Client PO -POV Comments | AD1: Comments | AE1: Column1
A2: =ROW() - ROW(Table1459678101112314151316171920211823[[#Headers],[S.No]]) -> 1 | B2: =Dashboard!$J$1 -> MCS | C2: 46010 | D2: 46037 | E2: MCS 25 Sprint 25 | F2: Vaishnavi | G2: 48686 | H2: Checklists Visibility Settings | I2: Story Ready For Testing | J2: 3 | K2: =Table14596781011123141513161719202118232224252627282930[[#This Row],[Estimated(hrs/sp)]] * 4 -> 12 | L2: 1 | M2: 46035 | N2: 46035 | O2: Done | P2: Ganesh | Q2: Nil | R2: Nil | S2: Nil | T2: https://dev.azure.com/heartlandschools/MCS/_git/Edison/pullrequest/45228 | U2: 45952 | V2: Hariharan Dhandapani | W2: Nil | X2: Nil | Y2: Rudy | Z2: 45966 | AA2: Nil | AB2: Nil | AC2: Nil | AD2: Development was completed in the sprint 22; the current sprint focuses only on testing, but small ui implemention updated for Weekly format
A3: =ROW() - ROW(Table1459678101112314151316171920211823[[#Headers],[S.No]]) -> 2 | B3: =Dashboard!$J$1 -> MCS | C3: 46010 | D3: 46037 | E3: MCS 25 Sprint 25 | F3: Vaishnavi | G3: 49387 | H3: MSA (web) - Link Privacy Statement in T&C's | I3: Story Completed | J3: 3 | K3: =Table14596781011123141513161719202118232224252627282930[[#This Row],[Estimated(hrs/sp)]] * 4 -> 12 | L3: 2 | M3: 46035 | N3: 46035 | O3: Done | P3: Ganesh | Q3: Nil | R3: Nil | S3: Nil | T3: https://dev.azure.com/heartlandschools/MCS/_git/MySchoolApps/pullrequest/46014 | U3: 45994 | V3: Hariharan Dhandapani | W3: Nil | X3: Nil | Y3: Nil | Z3: Nil | AA3: Nil | AB3: Nil | AC3: Nil | AD3: The current sprint focuses only on testing.
A4: =ROW() - ROW(Table1459678101112314151316171920211823[[#Headers],[S.No]]) -> 3 | B4: =Dashboard!$J$1 -> MCS | C4: 46010 | D4: 46037 | E4: MCS 25 Sprint 25 | F4: Vaishnavi | G4: 50900 | H4: Atlanta Report Request Built off of Record of Attendance Report | I4: Story Being Developed | J4: 3 | K4: =Table14596781011123141513161719202118232224252627282930[[#This Row],[Estimated(hrs/sp)]] * 4 -> 12 | L4: 15 | M4: 46010 | N4: 46010 | O4: Nil | P4: Nil | Q4: Nil | R4: Nil | S4: Nil | T4: Nil | U4: Nil | V4: Nil | W4: Nil | X4: Nil | Y4: Nil | Z4: Nil | AA4: Nil | AB4: Nil | AC4: Nil | AD4: Completed Pre-POV. After internal discussion with Hari, overall implementation has been modified and work is ongoing.
A5: =ROW() - ROW(Table1459678101112314151316171920211823[[#Headers],[S.No]]) -> 4 | B5: =Dashboard!$J$1 -> MCS | C5: 46010 | D5: 46037 | E5: MCS 25 Sprint 25 Stretch | F5: Hariharan Dhandapani | G5: 47376 | H5: MCS - ED - Import Price Contract Update - Append and Inactivate | I5: Story Ready For Testing | J5: 8 | K5: =Table14596781011123141513161719202118232224252627282930[[#This Row],[Estimated(hrs/sp)]] * 4 -> 32 | L5: 30 | M5: 46003 | N5: 46009 | O5: Done | P5: Ganesh | Q5: Nil | R5: Nil | S5: Nil | T5: Nil | U5: Nil | V5: Nil | W5: Nil | X5: Nil | Y5: Nil | Z5: Nil | AA5: Nil | AB5: Nil | AC5: Nil
A6: =ROW() - ROW(Table1459678101112314151316171920211823[[#Headers],[S.No]]) -> 5 | B6: =Dashboard!$J$1 -> MCS | C6: 46010 | D6: 46037 | E6: MCS 25 Sprint 25 Stretch | F6: Vaishnavi | G6: 51241 | H6: Update Customer support link | I6: Story Completed | J6: 1 | K6: =Table14596781011123141513161719202118232224252627282930[[#This Row],[Estimated(hrs/sp)]] * 4 -> 4 | L6: 8 | M6: 46015 | N6: 46017 | O6: Done | P6: Ganesh | Q6: Nil | R6: Nil | S6: Nil | T6: https://dev.azure.com/heartlandschools/MCS/_git/MCSTechWeb/pullrequest/46373 | U6: 46017 | V6: Hariharan Dhandapani | W6: Nil | X6: Nil | Y6: Nil | Z6: Nil | AA6: Nil | AB6: Nil | AC6: Nil
A7: =ROW() - ROW(Table1459678101112314151316171920211823[[#Headers],[S.No]]) -> 6 | B7: =Dashboard!$J$1 -> MCS | C7: 46010 | D7: 46037 | E7: MCS 25 Sprint 25 Stretch | F7: Vaishnavi | G7: 51313 | H7: Add Buy American exception dropdown in Item-Specifics | I7: Story Peer Review | J7: 3 | K7: =Table14596781011123141513161719202118232224252627282930[[#This Row],[Estimated(hrs/sp)]] * 4 -> 12 | L7: 41 | M7: 46022 | N7: 46035 | O7: Done | P7: Ganesh | Q7: Nil | R7: Nil | S7: Nil | T7: https://dev.azure.com/heartlandschools/MCS/_git/Edison/pullrequest/46577?path=%2FForms%2FFormMaintItem.Designer.cs&_a=files | U7: 46034 | V7: Nil | W7: Nil | X7: Nil | Y7: Nil | Z7: Nil | AA7: Nil | AB7: Nil | AC7: Nil | AD7: Completed POV and raised PR; currently addressing internal review comments.

Sheet MCS 25 Sprint 25-Defects
A1: S.No | B1: Sprint # | C1: Story/Defect ID | D1: Parent Story | E1: Developer | F1: Issue Type | G1: Issue Description | H1: Priority | I1: Defect Source | J1: Type | K1: Status | L1: Root Cause Category | M1: Comments

Sheet MCS 25 Sprint 24-Status
A1: S.No | B1: Application Name | C1: Sprint Start Date | D1: Sprint End Date | E1: Sprint | F1: Developer | G1: Story ID/Defect ID | H1: Description | I1: Status | J1: Estimated(hrs/sp) | K1: Actual(hrs/sp) | L1: Actual Hours (Worklog) | M1: Dev Start Date | N1: Dev End Date | O1: Unit testing | P1: Peer Tested By | Q1: Peer Tested Defects, if any | R1: Peer Reviewed By | S1: Peer Code Review Comments, if any | T1: PR Number/Link | U1: PR Created Date | V1: Reviewer 1 | W1: PR Approved Date | X1: Code Review Comments, if any | Y1: Reviewer 2 | Z1: Approved Date | AA1: Code Review Comments, if any2 | AB1: Internal PO -POV Comments | AC1: Client PO -POV Comments | AD1: Comments | AE1: Column1
A2: =ROW() - ROW(Table1459678101112314151316171920211823[[#Headers],[S.No]]) -> 1 | B2: =Dashboard!$J$1 -> MCS | C2: 45981 | D2: 46009 | E2: MCS 25 Sprint 24 | F2: Vaishnavi | G2: 47853 | H2: Add support for District Tags | I2: Story Completed | J2: 3 | K2: =Table145967810111231415131617192021182322242526272829[[#This Row],[Estimated(hrs/sp)]] * 4 -> 12 | L2: Nil | M2: Nil | N2: Nil | O2: Done | P2: Ganesh | Q2: Nil | R2: Nil | S2: Nil | T2: https://dev.azure.com/heartlandschools/MCS/_git/Nebulizer/pullrequest/44723 | U2: 45924 | V2: Hariharan Dhandapani | W2: 45930 | X2: Nil | Y2: Andrea | Z2: 45930 | AA2: Nil | AB2: Nil | AC2: Nil | AD2: Development was completed in the last sprint; the current sprint focuses only on testing
A3: =ROW() - ROW(Table1459678101112314151316171920211823[[#Headers],[S.No]]) -> 2 | B3: =Dashboard!$J$1 -> MCS | C3: 45981 | D3: 46009 | E3: MCS 25 Sprint 24 | F3: Vaishnavi | G3: 48686 | H3: Checklists Visibility Settings | I3: Story Being Tested | J3: 3 | K3: =Table145967810111231415131617192021182322242526272829[[#This Row],[Estimated(hrs/sp)]] * 4 -> 12 | L3: Nil | M3: Nil | N3: Nil | O3: Done | P3: Ganesh | Q3: Nil | R3: Nil | S3: Nil | T3: https://dev.azure.com/heartlandschools/MCS/_git/Edison/pullrequest/45228 | U3: 45952 | V3: Hariharan Dhandapani | W3: Nil | X3: Nil | Y3: Rudy | Z3: 45966 | AA3: Nil | AB3: Nil | AC3: Nil | AD3: Development was completed in the sprint 22; the current sprint focuses only on testing
A4: =ROW() - ROW(Table1459678101112314151316171920211823[[#Headers],[S.No]]) -> 3 | B4: =Dashboard!$J$1 -> MCS | C4: 45981 | D4: 46009 | E4: MCS 25 Sprint 24 | F4: Vaishnavi | G4: 49387 | H4: MSA (web) - Link Privacy Statement in T&C's | I4: Story Ready For Testing | J4: 3 | K4: =Table145967810111231415131617192021182322242526272829[[#This Row],[Estimated(hrs/sp)]] * 4 -> 12 | L4: 24 | M4: 45971 | N4: 45981 | O4: Nil | P4: Nil | Q4: Nil | R4: Nil | S4: Nil | T4: https://dev.azure.com/heartlandschools/MCS/_git/MySchoolApps/pullrequest/46014 | U4: 45994 | V4: Hariharan Dhandapani | W4: Nil | X4: Avoid the inline style and Rename the variable | Y4: Andrea | Z4: 46000 | AA4: Nil | AB4: Nil | AC4: Nil | AD4: We got 2 bounce backs from QA team. 1. The first bounce back was related to firewall. For debugging it I changed some code. Patrick later told us it was a firewall issue and has asked Hari to coordinate with the IT team. I have then reverted the changes made. 2. The second bounce back was related to URL validation. Here Patrick advised that new URL() would be sufficient and asked me to use.
A5: =ROW() - ROW(Table1459678101112314151316171920211823[[#Headers],[S.No]]) -> 4 | B5: =Dashboard!$J$1 -> MCS | C5: 45981 | D5: 46009 | E5: MCS 25 Sprint 24 | F5: Hariharan Dhandapani | G5: 50522 | H5: Plugin - Implement Generic ERP Export | I5: Story Completed | J5: 5 | K5: =Table145967810111231415131617192021182322242526272829[[#This Row],[Estimated(hrs/sp)]] * 4 -> 20 | L5: 38 | M5: 45972 | N5: 45981 | O5: Nil | P5: Nil | Q5: Nil | R5: Nil | S5: Nil | T5: https://dev.azure.com/heartlandschools/MCS/_git/Newton/pullrequest/46071 | U5: 45996 | V5: Patrick | W5: 46000 | X5: Nil | Y5: Nil | Z5: Nil | AA5: Nil | AB5: Nil | AC5: Nil
A6: =ROW() - ROW(Table1459678101112314151316171920211823[[#Headers],[S.No]]) -> 5 | B6: =Dashboard!$J$1 -> MCS | C6: 45981 | D6: 46009 | E6: MCS 25 Sprint 24 Stretch | F6: Vaishnavi | G6: 51034 | H6: Lee County PSD Export (Revert Changes) | I6: Story Completed | J6: 2 | K6: =Table145967810111231415131617192021182322242526272829[[#This Row],[Estimated(hrs/sp)]] * 4 -> 8 | L6: 9 | M6: 45988 | N6: 45996 | O6: Nil | P6: Nil | Q6: Nil | R6: Nil | S6: Nil | T6: https://dev.azure.com/heartlandschools/MCS/_git/Newton/pullrequest/46087 | U6: 45996 | V6: Hariharan Dhandapani | W6: Nil | X6: Nil | Y6: Nil | Z6: Nil | AA6: Nil | AB6: Nil | AC6: Nil
A7: =ROW() - ROW(Table1459678101112314151316171920211823[[#Headers],[S.No]]) -> 6 | B7: =Dashboard!$J$1 -> MCS | C7: 45981 | D7: 46009 | E7: MCS 25 Sprint 24 Stretch | F7: Vaishnavi | G7: 50900 | H7: Atlanta Report Request Built off of Record of Attendance Report | I7: Story Being Developed | J7: 3 | K7: =Table145967810111231415131617192021182322242526272829[[#This Row],[Estimated(hrs/sp)]] * 4 -> 12 | L7: 67 | M7: 45992 | N7: 46009 | O7: Nil | P7: Nil | Q7: Nil | R7: Nil | S7: Nil | T7: Nil | U7: Nil | V7: Nil | W7: Nil | X7: Nil | Y7: Nil | Z7: Nil | AA7: Nil | AB7: Nil | AC7: Nil | AD7: After discussion with Josh, the requirement has changed.
A8: =ROW() - ROW(Table1459678101112314151316171920211823[[#Headers],[S.No]]) -> 7 | B8: =Dashboard!$J$1 -> MCS | C8: 45981 | D8: 46009 | E8: MCS 25 Sprint 24 Stretch | F8: Hariharan Dhandapani | G8: SRX28622 | H8: Cannot print request for bid quote bid period | I8: Story Completed | J8: 2 | K8: =Table145967810111231415131617192021182322242526272829[[#This Row],[Estimated(hrs/sp)]] * 4 -> 8 | L8: 14 | M8: 46001 | N8: 46009 | O8: Nil | P8: Nil | Q8: Nil | R8: Nil | S8: Nil | T8: Nil | U8: Nil | V8: Nil | W8: Nil | X8: Nil | Y8: Nil | Z8: Nil | AA8: Nil | AB8: Nil | AC8: Nil
A9: =ROW() - ROW(Table1459678101112314151316171920211823[[#Headers],[S.No]]) -> 8 | B9: =Dashboard!$J$1 -> MCS | C9: 45981 | D9: 46009 | E9: MCS 25 Sprint 24 Stretch | F9: Hariharan Dhandapani | G9: 47376 | H9: MCS - ED - Import Price Contract Update - Append and Inactivate | I9: Story Being Developed | J9: 3 | K9: =Table145967810111231415131617192021182322242526272829[[#This Row],[Estimated(hrs/sp)]] * 4 -> 12 | L9: 24 | M9: 46003 | N9: 46009 | O9: Nil | P9: Nil | Q9: Nil | R9: Nil | S9: Nil | T9: Nil | U9: Nil | V9: Nil | W9: Nil | X9: Nil | Y9: Nil | Z9: Nil | AA9: Nil | AB9: Nil | AC9: Nil

Sheet MCS 25 Sprint 24-Defects 
A1: S.No | B1: Sprint # | C1: Story/Defect ID | D1: Parent Story | E1: Developer | F1: Issue Type | G1: Issue Description | H1: Priority | I1: Defect Source | J1: Type | K1: Status | L1: Root Cause Category | M1: Comments

Sheet MCS 25 Sprint 23-Status 
A1: S.No | B1: Application Name | C1: Sprint Start Date | D1: Sprint End Date | E1: Sprint | F1: Developer | G1: Story ID/Defect ID | H1: Description | I1: Status | J1: Estimated(hrs/sp) | K1: Actual(hrs/sp) | L1: Actual Hours (Worklog) | M1: Dev Start Date | N1: Dev End Date | O1: Unit testing | P1: Peer Tested By | Q1: Peer Tested Defects, if any | R1: Peer Reviewed By | S1: Peer Code Review Comments, if any | T1: PR Number/Link | U1: PR Created Date | V1: Reviewer 1 | W1: PR Approved Date | X1: Code Review Comments, if any | Y1: Reviewer 2 | Z1: Approved Date | AA1: Code Review Comments, if any2 | AB1: Internal PO -POV Comments | AC1: Client PO -POV Comments | AD1: Comments | AE1: Column1
A2: =ROW() - ROW(Table1459678101112314151316171920211823[[#Headers],[S.No]]) -> 1 | B2: =Dashboard!$J$1 -> MCS | C2: 45968 | D2: 45981 | E2: MCS 25 Sprint 23 | F2: Hariharan Dhandapani | G2: 50608 | H2: Plugin - CCSD Claim Plugin Update Needed | I2: Story Completed | J2: 3 | K2: =Table1459678101112314151316171920211823222425262728[[#This Row],[Estimated(hrs/sp)]] * 4 -> 12 | L2: 24 | M2: 45971 | N2: 45973 | O2: Done | P2: Ganesh | Q2: Nil | R2: Nil | S2: Nil | T2: Nil | U2: Nil | V2: Nil | W2: Nil | X2: Nil | Y2: Nil | Z2: Nil | AA2: Nil | AB2: Nil | AC2: Nil
A3: =ROW() - ROW(Table1459678101112314151316171920211823[[#Headers],[S.No]]) -> 2 | B3: =Dashboard!$J$1 -> MCS | C3: 45968 | D3: 45981 | E3: MCS 25 Sprint 23 | F3: Vaishnavi | G3: 47853 | H3: Add support for District Tags | I3: Story Being Tested | J3: 2 | K3: =Table1459678101112314151316171920211823222425262728[[#This Row],[Estimated(hrs/sp)]] * 4 -> 8 | L3: Nil | M3: Nil | N3: Nil | O3: Done | P3: Ganesh | Q3: Nil | R3: Nil | S3: Nil | T3: https://dev.azure.com/heartlandschools/MCS/_git/Nebulizer/pullrequest/44723 | U3: 45924 | V3: Hariharan Dhandapani | W3: 45930 | X3: Nil | Y3: Andrea | Z3: 45930 | AA3: Nil | AB3: Nil | AC3: Nil | AD3: Development was completed in the last sprint; the current sprint focuses only on testing
A4: =ROW() - ROW(Table1459678101112314151316171920211823[[#Headers],[S.No]]) -> 3 | B4: =Dashboard!$J$1 -> MCS | C4: 45968 | D4: 45981 | E4: MCS 25 Sprint 23 Stretch | F4: Vaishnavi | G4: 48686 | H4: Checklists Visibility Settings | I4: Story Ready For Testing | J4: 2 | K4: =Table1459678101112314151316171920211823222425262728[[#This Row],[Estimated(hrs/sp)]] * 4 -> 8 | L4: Nil | M4: Nil | N4: Nil | O4: Done | P4: Ganesh | Q4: Nil | R4: Nil | S4: Nil | T4: https://dev.azure.com/heartlandschools/MCS/_git/Edison/pullrequest/45228 | U4: 45952 | V4: Hariharan Dhandapani | W4: Nil | X4: Nil | Y4: Rudy | Z4: 45966 | AA4: Nil | AB4: Nil | AC4: Nil | AD4: Development was completed in the sprint 22; the current sprint focuses only on testing
A5: =ROW() - ROW(Table1459678101112314151316171920211823[[#Headers],[S.No]]) -> 4 | B5: =Dashboard!$J$1 -> MCS | C5: 45968 | D5: 45981 | E5: MCS 25 Sprint 23 Stretch | F5: Vaishnavi | G5: 49387 | H5: MSA (web) - Link Privacy Statement in T&C's | I5: Story Being Developed | J5: 3 | K5: 3 | L5: 24 | M5: 45971 | N5: 45981 | O5: Nil | P5: Nil | Q5: Nil | R5: Nil | S5: Nil | T5: Nil | U5: Nil | V5: Nil | W5: Nil | X5: Nil | Y5: Nil | Z5: Nil | AA5: Nil | AB5: Nil | AC5: Nil | AD5: Done with expected functionality.
A6: =ROW() - ROW(Table1459678101112314151316171920211823[[#Headers],[S.No]]) -> 5 | B6: =Dashboard!$J$1 -> MCS | C6: 45968 | D6: 45981 | E6: MCS 25 Sprint 23 Stretch | F6: Hariharan Dhandapani | G6: 50522 | H6: Plugin - Implement Generic ERP Export | I6: Story Being Developed | J6: 5 | K6: 20 | L6: 24 | M6: 45972 | N6: 45981 | O6: Nil | P6: Nil | Q6: Nil | R6: Nil | S6: Nil | T6: Nil | U6: Nil | V6: Nil | W6: Nil | X6: Nil | Y6: Nil | Z6: Nil | AA6: Nil | AB6: Nil | AC6: Nil

Sheet MCS 25 Sprint 23-Defects 
A1: S.No | B1: Sprint # | C1: Story/Defect ID | D1: Parent Story | E1: Developer | F1: Issue Type | G1: Issue Description | H1: Priority | I1: Defect Source | J1: Type | K1: Status | L1: Root Cause Category | M1: Comments
B2: MCS 25 Sprint 23 Stretch | C2: 26156 | E2: Hariharan Dhandapani | F2: Defect | G2: Error saving new bid analysis group created as a copy of another | H2: Minor | I2: Manual | J2: External | K2: Defect Fixed | L2: Existing Issue
B3: MCS 25 Sprint 23 | C3: 25870 | E3: Vaishnavi | F3: Defect | G3: Production Report Numbers are Not Correct | H3: Minor | I3: Manual | J3: External | K3: Defect Fixed | L3: Existing Issue | M3: Andrea suggested adding code review comments to make the code more readable, improve CTE functionality, and rename it

Sheet MCS 25 Sprint 22-Status
A1: S.No | B1: Application Name | C1: Sprint Start Date | D1: Sprint End Date | E1: Sprint | F1: Developer | G1: Story ID/Defect ID | H1: Description | I1: Status | J1: Estimated(hrs/sp) | K1: Actual(hrs/sp) | L1: Actual Hours (Worklog) | M1: Dev Start Date | N1: Dev End Date | O1: Unit testing | P1: Peer Tested By | Q1: Peer Tested Defects, if any | R1: Peer Reviewed By | S1: Peer Code Review Comments, if any | T1: PR Number/Link | U1: PR Created Date | V1: Reviewer 1 | W1: PR Approved Date | X1: Code Review Comments, if any | Y1: Reviewer 2 | Z1: Approved Date | AA1: Code Review Comments, if any2 | AB1: Internal PO -POV Comments | AC1: Client PO -POV Comments | AD1: Comments | AE1: Column1
A2: =ROW() - ROW(Table1459678101112314151316171920211823[[#Headers],[S.No]]) -> 1 | B2: =Dashboard!$J$1 -> MCS | C2: 45954 | D2: 45967 | E2: MCS 25 Sprint 22 | F2: Vaishnavi | G2: 47853 | H2: Add support for District Tags | I2: Story Being Tested | J2: 2 | K2: =Table14596781011123141513161719202118232224252627[[#This Row],[Estimated(hrs/sp)]] * 4 -> 8 | L2: 7 | M2: 45954 | N2: 45958 | O2: Done | P2: Ganesh | Q2: Nil | R2: Nil | S2: Nil | T2: https://dev.azure.com/heartlandschools/MCS/_git/Nebulizer/pullrequest/44723 | U2: 45924 | V2: Hariharan Dhandapani | W2: 45930 | X2: Nil | Y2: Andrea | Z2: 45930 | AA2: Nil | AB2: Nil | AC2: Nil | AD2: Completed 1 Bounceback tickets and moved to testing
A3: =ROW() - ROW(Table1459678101112314151316171920211823[[#Headers],[S.No]]) -> 2 | B3: MCS | C3: 45954 | D3: 45967 | E3: MCS 25 Sprint 22 | F3: Hariharan Dhandapani | G3: 39453 | H3: Prevent Managers from Zeroing out Production Quantities | I3: Story Completed | J3: 3 | K3: =Table14596781011123141513161719202118232224252627[[#This Row],[Estimated(hrs/sp)]] * 4 -> 12 | L3: Nil | M3: Nil | N3: Nil | O3: Done | P3: Ganesh | Q3: Nil | R3: Nil | S3: Nil | T3: https://dev.azure.com/heartlandschools/MCS/_git/Edison/pullrequest/44956 | U3: 45933 | V3: Andrea | W3: 45936 | X3: Nil | Y3: Nil | Z3: Nil | AA3: Nil | AB3: Nil | AC3: Nil | AD3: Development was completed in the last sprint; the current sprint focuses only on testing
A4: =ROW() - ROW(Table1459678101112314151316171920211823[[#Headers],[S.No]]) -> 3 | B4: =Dashboard!$J$1 -> MCS | C4: 45954 | D4: 45967 | E4: MCS 25 Sprint 22 Stretch | F4: Vaishnavi | G4: 48686 | H4: Checklists Visibility Settings | I4: Story Ready For Testing | J4: 3 | K4: =Table14596781011123141513161719202118232224252627[[#This Row],[Estimated(hrs/sp)]] * 4 -> 12 | L4: 16 | M4: 45958 | N4: 45965 | O4: Done | P4: Ganesh | Q4: Nil | R4: Nil | S4: 1.To avoid condtion checks repeat across lines. 2.Replace tuple return with bool + out parameter. 3.Consider renaming numericUpDownOffsetDays_KeyUp to match the control name 4.Bool Variable(status) rename like "IsOffsetEnabled". 5.Consider rewriting for clarity code | T4: https://dev.azure.com/heartlandschools/MCS/_git/Edison/pullrequest/45228 | U4: 45952 | V4: Hariharan Dhandapani | W4: Nil | X4: 1.Use just nullable OffsetDays and remove isOffsetEnabled. 2.Use schema and CamelCase for column name. 3.Need to implement the Import functionality. 4.Don't stop the timer. Keep it refreshing the checklist. 5.Call refreshTimer.Stop() when Tick is triggered and refreshTimer.Start() after new Interval is set | Y4: Rudy | Z4: 45966 | AA4: Nil | AB4: Nil | AC4: Nil | AD4: The AC was modified during PR, then moved to development, completed, and subsequently transitioned to testing.
A5: =ROW() - ROW(Table1459678101112314151316171920211823[[#Headers],[S.No]]) -> 4 | B5: =Dashboard!$J$1 -> MCS | C5: 45954 | D5: 45967 | E5: MCS 25 Sprint 22 | F5: Hariharan Dhandapani | G5: 50048 | H5: Improve Handling of Unconfirmed/Canceled In-Person Credit Card Transactions | I5: Story Completed | J5: 3 | K5: =Table14596781011123141513161719202118232224252627[[#This Row],[Estimated(hrs/sp)]] * 4 -> 12 | L5: 36 | M5: 45964 | N5: 45966 | O5: Done | P5: Ganesh | Q5: Nil | R5: Nil | S5: Nil | T5: https://dev.azure.com/heartlandschools/MCS/_git/Newton/pullrequest/45510 | U5: 45952 | V5: Hariharan Dhandapani | W5: Nil | X5: Nil | Y5: Rudy | Z5: 45966 | AA5: Nil | AB5: Nil | AC5: Nil

Sheet MCS 25 Sprint 22-Defects
A1: S.No | B1: Sprint # | C1: Story/Defect ID | D1: Parent Story | E1: Developer | F1: Issue Type | G1: Issue Description | H1: Priority | I1: Defect Source | J1: Type | K1: Status | L1: Root Cause Category | M1: Comments
B2: MCS 25 Sprint 22 Stretch | C2: 26156 | E2: Hariharan Dhandapani | F2: Defect | G2: Error saving new bid analysis group created as a copy of another | H2: Minor | I2: Manual | J2: External | K2: Defect Peer Review | L2: Existing Issue
B3: MCS 25 Sprint 22 | C3: 25870 | E3: Vaishnavi | F3: Defect | G3: Production Report Numbers are Not Correct | H3: Minor | I3: Manual | J3: External | K3: Defect Being Fixed | L3: Existing Issue

Sheet MCS 25 Sprint 21-Status
A1: S.No | B1: Application Name | C1: Sprint Start Date | D1: Sprint End Date | E1: Sprint | F1: Developer | G1: Story ID/Defect ID | H1: Description | I1: Status | J1: Estimated(hrs/sp) | K1: Actual(hrs/sp) | L1: Actual Hours (Worklog) | M1: Dev Start Date | N1: Dev End Date | O1: Unit testing | P1: Peer Tested By | Q1: Peer Tested Defects, if any | R1: Peer Reviewed By | S1: Peer Code Review Comments, if any | T1: PR Number/Link | U1: PR Created Date | V1: Reviewer 1 | W1: PR Approved Date | X1: Code Review Comments, if any | Y1: Reviewer 2 | Z1: Approved Date | AA1: Code Review Comments, if any2 | AB1: Internal PO -POV Comments | AC1: Client PO -POV Comments | AD1: Comments | AE1: Column1
A2: =ROW() - ROW(Table1459678101112314151316171920211823[[#Headers],[S.No]]) -> 1 | B2: =Dashboard!$J$1 -> MCS | C2: 45940 | D2: 45953 | E2: MCS 25 Sprint 21 | F2: Vaishnavi | G2: 47853 | H2: Add support for District Tags | I2: Story Being Tested | J2: 3 | K2: =Table145967810111231415131617192021182322242526[[#This Row],[Estimated(hrs/sp)]] * 4 -> 12 | L2: 4 | M2: 45925 | N2: 45929 | O2: Done | P2: Ganesh | Q2: Nil | R2: Nil | S2: Nil | T2: https://dev.azure.com/heartlandschools/MCS/_git/Nebulizer/pullrequest/44723 | U2: 45924 | V2: Hariharan Dhandapani | W2: 45930 | X2: Nil | Y2: Andrea | Z2: 45930 | AA2: Nil | AB2: Nil | AC2: Nil
A3: =ROW() - ROW(Table1459678101112314151316171920211823[[#Headers],[S.No]]) -> 2 | B3: MCS | C3: 45940 | D3: 45953 | E3: MCS 25 Sprint 21 | F3: Hariharan Dhandapani | G3: 39453 | H3: Prevent Managers from Zeroing out Production Quantities | I3: Story Ready For Testing | J3: 3 | K3: =Table145967810111231415131617192021182322242526[[#This Row],[Estimated(hrs/sp)]] * 4 -> 12 | L3: Nil | M3: Nil | N3: Nil | O3: Done | P3: Ganesh | Q3: Nil | R3: Nil | S3: Nil | T3: https://dev.azure.com/heartlandschools/MCS/_git/Edison/pullrequest/44956 | U3: 45933 | V3: Andrea | W3: 45936 | X3: Nil | Y3: Nil | Z3: Nil | AA3: Nil | AB3: Nil | AC3: Nil
A4: =ROW() - ROW(Table1459678101112314151316171920211823[[#Headers],[S.No]]) -> 3 | B4: =Dashboard!$J$1 -> MCS | C4: 45940 | D4: 45953 | E4: MCS 25 Sprint 21 Stretch | F4: Vaishnavi | G4: 48686 | H4: Checklists Visibility Settings | I4: Story Peer Review | J4: 5 | K4: =Table145967810111231415131617192021182322242526[[#This Row],[Estimated(hrs/sp)]] * 4 -> 20 | L4: 31 | M4: 45938 | N4: 45952 | O4: Done | P4: Ganesh | Q4: Nil | R4: Nil | S4: Nil | T4: https://dev.azure.com/heartlandschools/MCS/_git/Edison/pullrequest/45228 | U4: 45952 | V4: Hariharan Dhandapani | W4: Nil | X4: Nil | Y4: Nil | Z4: Nil | AA4: Nil | AB4: Nil | AC4: Nil
A5: =ROW() - ROW(Table1459678101112314151316171920211823[[#Headers],[S.No]]) -> 4 | B5: =Dashboard!$J$1 -> MCS | C5: 45940 | D5: 45953 | E5: MCS 25 Sprint 21 Stretch | F5: Vaishnavi | G5: 50501 | H5: Cherry Creek Production Report Change | I5: Story Completed | J5: 2 | K5: =Table145967810111231415131617192021182322242526[[#This Row],[Estimated(hrs/sp)]] * 4 -> 8 | L5: 8 | M5: 45952 | N5: 45953 | O5: Done | P5: Ganesh | Q5: Nil | R5: Nil | S5: Nil | T5: https://dev.azure.com/heartlandschools/MCS/_git/Edison/pullrequest/45268 | U5: 45952 | V5: Hariharan Dhandapani | W5: 45936 | X5: Nil | Y5: Rudy | Z5: Nil | AA5: Nil | AB5: Nil | AC5: Nil

Sheet MCS 25 Sprint 21-Defects
A1: S.No | B1: Sprint # | C1: Story/Defect ID | D1: Parent Story | E1: Developer | F1: Issue Type | G1: Issue Description | H1: Priority | I1: Defect Source | J1: Type | K1: Status | L1: Root Cause Category | M1: Comments
B2: MCS 25 Sprint 21 Stretch | C2: 26156 | E2: Hariharan Dhandapani | F2: Defect | G2: Error saving new bid analysis group created as a copy of another | H2: Minor | I2: Manual | J2: External | K2: Defect Peer Review | L2: Existing Issue

Sheet MCS 25 Sprint 20-Status
A1: S.No | B1: Application Name | C1: Sprint Start Date | D1: Sprint End Date | E1: Sprint | F1: Developer | G1: Story ID/Defect ID | H1: Description | I1: Status | J1: Estimated(hrs/sp) | K1: Actual(hrs/sp) | L1: Actual Hours (Worklog) | M1: Dev Start Date | N1: Dev End Date | O1: Unit testing | P1: Peer Tested By | Q1: Peer Tested Defects, if any | R1: Peer Reviewed By | S1: Peer Code Review Comments, if any | T1: PR Number/Link | U1: PR Created Date | V1: Reviewer 1 | W1: PR Approved Date | X1: Code Review Comments, if any | Y1: Reviewer 2 | Z1: Approved Date | AA1: Code Review Comments, if any2 | AB1: Internal PO -POV Comments | AC1: Client PO -POV Comments | AD1: Comments | AE1: Column1
A2: =ROW() - ROW(Table1459678101112314151316171920211823[[#Headers],[S.No]]) -> 1 | B2: =Dashboard!$J$1 -> MCS | C2: 45925 | D2: 45939 | E2: MCS 25 Sprint 20 | F2: Vaishnavi | G2: 47853 | H2: Add support for District Tags | I2: Story Being Tested | J2: 3 | K2: =Table1459678101112314151316171920211823222425[[#This Row],[Estimated(hrs/sp)]] * 4 -> 12 | L2: 18 | M2: 45925 | N2: 45929 | O2: Done | P2: Ganesh | Q2: Nil | R2: Nil | S2: Follow the correct styling format. Don't not expose the ID in the throw. Just Throw the message. use dbLib.CSqlList. Inconsistent success feedback . Avoid multiple TryGetValue calls per row and db call; Avoid Null risk iterating and Duplicate district grouping logic To handles the permission separately for TagMaintenance. Remove the ',' at the end. Potential KeyNotFound in cache. | T2: https://dev.azure.com/heartlandschools/MCS/_git/Nebulizer/pullrequest/44723 | U2: 45924 | V2: Hariharan Dhandapani | W2: 45930 | X2: Nil | Y2: Andrea | Z2: 45930 | AA2: Nil | AB2: Nil | AC2: Nil | AD2: Resolved PR Comments and moved to testing.
A3: =ROW() - ROW(Table1459678101112314151316171920211823[[#Headers],[S.No]]) -> 2 | B3: MCS | C3: 45925 | D3: 45939 | E3: MCS 25 Sprint 20 Stretch | F3: Hariharan Dhandapani | G3: 39453 | H3: Prevent Managers from Zeroing out Production Quantities | I3: Story Being Tested | J3: 3 | K3: =Table1459678101112314151316171920211823222425[[#This Row],[Estimated(hrs/sp)]] * 4 -> 12 | L3: 28 | M3: 45925 | N3: 45933 | O3: Done | P3: Ganesh | Q3: Nil | R3: Nil | S3: use var more often in the future | T3: https://dev.azure.com/heartlandschools/MCS/_git/Edison/pullrequest/44956 | U3: 45933 | V3: Andrea | W3: 45936 | X3: Nil | Y3: Nil | Z3: Nil | AA3: Nil | AB3: Nil | AC3: Nil | AD3: Had a discussion with Josh and vendor. Added a new requirement and updated the AC. Development has started based on the changes.
A4: =ROW() - ROW(Table1459678101112314151316171920211823[[#Headers],[S.No]]) -> 3 | B4: =Dashboard!$J$1 -> MCS | C4: 45925 | D4: 45939 | E4: MCS 25 Sprint 20 Stretch | F4: Vaishnavi | G4: 50289 | H4: Add Sorting for Allergen Filter in Item Allergen Report | I4: Story Completed | J4: 1 | K4: =Table1459678101112314151316171920211823222425[[#This Row],[Estimated(hrs/sp)]] * 4 -> 4 | L4: 6 | M4: 45933 | N4: 45933 | O4: Done | P4: Ganesh | Q4: Nil | R4: Nil | S4: Nil | T4: https://dev.azure.com/heartlandschools/MCS/_git/Edison/pullrequest/44947 | U4: 45933 | V4: Hariharan Dhandapani | W4: 45933 | X4: Nil | Y4: Nil | Z4: Nil | AA4: Nil | AB4: Nil | AC4: Nil
A5: =ROW() - ROW(Table1459678101112314151316171920211823[[#Headers],[S.No]]) -> 4 | B5: =Dashboard!$J$1 -> MCS | C5: 45925 | D5: 45939 | E5: MCS 25 Sprint 20 Stretch | F5: Vaishnavi | G5: 48686 | H5: Checklists Visibility Settings | I5: Story Being Developed | J5: 5 | K5: =Table1459678101112314151316171920211823222425[[#This Row],[Estimated(hrs/sp)]] * 4 -> 20 | L5: 12 | M5: 45938 | N5: 45939 | O5: Nil | P5: Nil | Q5: Nil | R5: Nil | S5: Nil | T5: Nil | U5: Nil | V5: Nil | W5: Nil | X5: Nil | Y5: Nil | Z5: Nil | AA5: Nil | AB5: Nil | AC5: Nil

Sheet MCS 25 Sprint 20-Defects
A1: S.No | B1: Sprint # | C1: Story/Defect ID | D1: Parent Story | E1: Developer | F1: Issue Type | G1: Issue Description | H1: Priority | I1: Defect Source | J1: Type | K1: Status | L1: Root Cause Category | M1: Comments
B2: MCS 25 Sprint 20 | C2: 25860 | E2: Vaishnavi | F2: Defect | G2: Line Details Not Sorting Properly | H2: Minor | I2: Manual | J2: External | K2: Defect Fixed | L2: Existing Issue
B3: MCS 25 Sprint 20 Stretch | C3: 25870 | E3: Vaishnavi | F3: Defect | G3: Production Report Numbers are Not Correct | H3: Minor | I3: Manual | J3: External | K3: Defect Needs More Info | L3: Existing Issue | M3: Discussed the defect with Josh, Ganesh, and Hari. Based on the conversation, the defect status was updated to "Need more information" for further clarification.

Sheet MCS 25 Sprint 19-Status
A1: S.No | B1: Application Name | C1: Sprint Start Date | D1: Sprint End Date | E1: Sprint | F1: Developer | G1: Story ID/Defect ID | H1: Description | I1: Status | J1: Estimated(hrs/sp) | K1: Actual(hrs/sp) | L1: Actual Hours (Worklog) | M1: Dev Start Date | N1: Dev End Date | O1: Unit testing | P1: Peer Tested By | Q1: Peer Tested Defects, if any | R1: Peer Reviewed By | S1: Peer Code Review Comments, if any | T1: PR Number/Link | U1: PR Created Date | V1: Reviewer 1 | W1: PR Approved Date | X1: Code Review Comments, if any | Y1: Reviewer 2 | Z1: Approved Date | AA1: Code Review Comments, if any2 | AB1: Internal PO -POV Comments | AC1: Client PO -POV Comments | AD1: Comments | AE1: Column1
A2: =ROW() - ROW(Table1459678101112314151316171920211823[[#Headers],[S.No]]) -> 1 | B2: =Dashboard!$J$1 -> MCS | C2: 45912 | D2: 45924 | E2: MCS 25 Sprint 19 Stretch | F2: Vaishnavi | G2: 47853 | H2: Add support for District Tags | I2: Story Peer Review | J2: 5 | K2: =Table14596781011123141513161719202118232224[[#This Row],[Estimated(hrs/sp)]] * 4 -> 20 | L2: 46 | M2: 45915 | N2: 45924 | O2: Done | P2: Ganesh | Q2: Nil | R2: Nil | S2: Nil | T2: https://dev.azure.com/heartlandschools/MCS/_git/Nebulizer/pullrequest/44723 | U2: 45924 | V2: Hariharan Dhandapani | W2: Nil | X2: Remove the Comma, and Group the permissions and add it as one. | Y2: Nil | Z2: Nil | AA2: Nil | AB2: Nil | AC2: Nil | AD2: Added new requirements to the pre-POV phase and removed certain requirements from the POV and then created PR
A3: =ROW() - ROW(Table1459678101112314151316171920211823[[#Headers],[S.No]]) -> 2 | B3: MCS | C3: 45912 | D3: 45924 | E3: MCS 25 Sprint 19 Stretch | F3: Hariharan Dhandapani | G3: 39453 | H3: Prevent Managers from Zeroing out Production Quantities | I3: Product Owner - Verify | J3: 3 | K3: =Table14596781011123141513161719202118232224[[#This Row],[Estimated(hrs/sp)]] * 4 -> 12 | L3: 41 | M3: 45912 | N3: 45924 | O3: Done | P3: Ganesh | Q3: Nil | R3: Nil | S3: Nil | T3: Nil | U3: Nil | V3: Nil | W3: Nil | X3: Nil | Y3: Nil | Z3: Nil | AA3: Nil | AB3: Nil | AC3: Nil | AD3: Development completed. Waiting for POV

Sheet MCS 25 Sprint 19-Defects
A1: S.No | B1: Sprint # | C1: Story/Defect ID | D1: Parent Story | E1: Developer | F1: Issue Type | G1: Issue Description | H1: Priority | I1: Defect Source | J1: Type | K1: Status | L1: Root Cause Category | M1: Comments
B2: MCS 25 Sprint 19 | C2: 25305 | E2: Hariharan Dhandapani | F2: Defect | G2: Item Importer change detection not recognizing allergen changes | H2: Minor | I2: Manual | J2: External | K2: Story Ready For Testing | L2: Existing Issue

Sheet MCS 25 Sprint 18-Status
A1: S.No | B1: Application Name | C1: Sprint Start Date | D1: Sprint End Date | E1: Sprint | F1: Developer | G1: Story ID/Defect ID | H1: Description | I1: Status | J1: Estimated(hrs/sp) | K1: Actual(hrs/sp) | L1: Actual Hours (Worklog) | M1: Dev Start Date | N1: Dev End Date | O1: Unit testing | P1: Peer Tested By | Q1: Peer Tested Defects, if any | R1: Peer Reviewed By | S1: Peer Code Review Comments, if any | T1: PR Number/Link | U1: PR Created Date | V1: Reviewer 1 | W1: PR Approved Date | X1: Code Review Comments, if any | Y1: Reviewer 2 | Z1: Approved Date | AA1: Code Review Comments, if any2 | AB1: Internal PO -POV Comments | AC1: Client PO -POV Comments | AD1: Comments | AE1: Column1
A2: =ROW() - ROW(Table1459678101112314151316171920211823[[#Headers],[S.No]]) -> 1 | B2: MCS | C2: 45898 | D2: 45911 | E2: MCS 25 Sprint 18 | F2: Vaishnavi | G2: 49483 | H2: LAUSD Production Record Enhancement | I2: Story Completed | J2: 1 | K2: =Table1459678101112314151316171920211823[[#This Row],[Estimated(hrs/sp)]] * 4 -> 12 | L2: 7 | M2: 45898 | N2: 45901 | O2: Done | P2: Ganesh | Q2: Nil | R2: Nil | S2: Nil | T2: https://dev.azure.com/heartlandschools/MCS/_git/Edison/pullrequest/44295?_a=commits&path=%2FExternalPlugins%2FReportDesigner%2FReportDesigner.csproj | U2: 45901 | V2: Andrea | W2: 45902 | X2: use <> 0 instead of != | Y2: Nil | Z2: Nil | AA2: Nil | AB2: Nil | AC2: Nil
A3: =ROW() - ROW(Table1459678101112314151316171920211823[[#Headers],[S.No]]) -> 2 | B3: MCS | C3: 45898 | D3: 45911 | E3: MCS 25 Sprint 18 Stretch | F3: Vaishnavi | G3: 23528 | H3: MCS - MCSTech - Add SQL Version to District Details Report | I3: Story Completed | J3: 3 | K3: =Table145967810111231415131617192021182322[[#This Row],[Estimated(hrs/sp)]] * 4 -> 12 | L3: 48 | M3: 45901 | N3: 45911 | O3: Done | P3: Ganesh | Q3: Nil | R3: Hariharan Dhandapani | S3: Avoid more parameters for the helper methods and Do not initialize the object, get the version using property | T3: Newton: https://dev.azure.com/heartlandschools/MCS/_git/Newton/pullrequest/44491?path=/Helpers.cs MCSTechWeb: https://dev.azure.com/heartlandschools/MCS/_git/MCSTechWeb/pullrequest/44490 | U3: 45910 | V3: Andrea | W3: 45911 | X3: Nil | Y3: Nil | Z3: Nil | AA3: Nil | AB3: Nil | AC3: Nil
A4: =ROW() - ROW(Table1459678101112314151316171920211823[[#Headers],[S.No]]) -> 3 | B4: =Dashboard!$J$1 -> MCS | C4: 45884 | D4: 45897 | E4: MCS 25 Sprint 18 | F4: Vaishnavi | G4: 48516 | H4: MCS - ED - Allow overwriting of default Captions and Tool Tips | I4: Story Completed | J4: 2 | K4: =Table145967810111231415131617192021182322[[#This Row],[Estimated(hrs/sp)]] * 4 -> 8 | L4: Nil | M4: 45899 | N4: 45873 | O4: Done | P4: Ganesh | Q4: Nil | R4: Hariharan Dhandapani | S4: Nil | T4: https://dev.azure.com/heartlandschools/MCS/_git/Edison/pullrequest/43356 | U4: 45875 | V4: Hariharan Dhandapani | W4: 45877 | X4: Nil | Y4: Patrick | Z4: 45883 | AA4: Nil | AB4: Nil | AC4: Nil
A5: =ROW() - ROW(Table1459678101112314151316171920211823[[#Headers],[S.No]]) -> 4 | B5: MCS | C5: 45898 | D5: 45911 | E5: MCS 25 Sprint 18 Stretch | F5: Hariharan Dhandapani | G5: 49852 | H5: MCS - POS - Plugin - City Paid Meals and Export to SAP | I5: Story Completed | J5: 3 | K5: =Table145967810111231415131617192021182322[[#This Row],[Estimated(hrs/sp)]] * 4 -> 12 | L5: 24 | M5: 45874 | N5: 45880 | O5: Done | P5: Done | Q5: Nil | R5: Nil | S5: Nil | T5: https://dev.azure.com/heartlandschools/MCS/_git/Newton/pullrequest/44482 | U5: 45910 | V5: Andrea | W5: 37509 | X5: Nil | Y5: Nil | Z5: Nil | AA5: Nil | AB5: Nil | AC5: Nil
A6: 5 | B6: MCS | C6: 45898 | D6: 45911 | E6: MCS 25 Sprint 18 | F6: Hariharan Dhandapani | G6: 25305 | H6: Item Importer change detection not recognizing allergen changes | I6: Defect Ready For Testing | J6: 3 | K6: 12 | L6: 24 | M6: 45899 | N6: 45873 | O6: Done | P6: Done | Q6: Nil | R6: Nil | S6: Nil | T6: https://dev.azure.com/heartlandschools/MCS/_git/Edison/pullrequest/44350 | U6: 45903 | V6: Rudy | W6: 38599 | X6: Nil | Y6: Patrick | Z6: Nil | AA6: Nil | AB6: Nil | AC6: Nil

Sheet MCS 25 Sprint 18-Defects
A1: S.No | B1: Sprint # | C1: Story/Defect ID | D1: Parent Story | E1: Developer | F1: Issue Type | G1: Issue Description | H1: Priority | I1: Defect Source | J1: Type | K1: Status | L1: Root Cause Category | M1: Comments
B2: MCS 25 Sprint 18 | C2: 25305 | E2: Hariharan Dhandapani | F2: Defect | G2: Item Importer change detection not recognizing allergen changes | H2: Minor | I2: Manual | J2: External | K2: Story Ready For Testing | L2: Existing Issue

Sheet MCS 25 Sprint 17-Status
A1: S.No | B1: Application Name | C1: Sprint Start Date | D1: Sprint End Date | E1: Sprint | F1: Developer | G1: Story ID/Defect ID | H1: Description | I1: Status | J1: Estimated(hrs/sp) | K1: Actual(hrs/sp) | L1: Actual Hours (Worklog) | M1: Dev Start Date | N1: Dev End Date | O1: Unit testing | P1: Peer Tested By | Q1: Peer Tested Defects, if any | R1: Peer Reviewed By | S1: Peer Code Review Comments, if any | T1: PR Number/Link | U1: PR Created Date | V1: Reviewer 1 | W1: PR Approved Date | X1: Code Review Comments, if any | Y1: Reviewer 2 | Z1: Approved Date | AA1: Code Review Comments, if any2 | AB1: Internal PO -POV Comments | AC1: Client PO -POV Comments | AD1: Comments | AE1: Column1
A2: =ROW() - ROW(Table1459678101112314151316171920211823[[#Headers],[S.No]]) -> 1 | B2: MCS | C2: 45884 | D2: 45897 | E2: MCS 25 Sprint 17 | F2: Hariharan Dhandapani | G2: 49044 | H2: MCS - DC - Add SFTP functionality to SIS import using generic text file | I2: Story Being Tested | J2: 3 | K2: =Table1459678101112314151316171920211823[[#This Row],[Estimated(hrs/sp)]] * 4 -> 12 | L2: Nil | M2: Nil | N2: Nil | O2: Done | P2: Ganesh | Q2: Nil | R2: Nil | S2: Nil | T2: https://dev.azure.com/heartlandschools/MCS/_git/Datacenter/pullrequest/43923 | U2: Nil | V2: Nil | W2: Nil | X2: Nil | Y2: Nil | Z2: Nil | AA2: Nil | AB2: Nil | AC2: Nil | AD2: Development completed, Waiting for PR
A3: =ROW() - ROW(Table1459678101112314151316171920211823[[#Headers],[S.No]]) -> 2 | B3: MCS | C3: 45884 | D3: 45897 | E3: MCS 25 Sprint 17 | F3: Vaishnavi | G3: 49483 | H3: LAUSD Production Record Enhancement | I3: Story Being Developed | J3: 2 | K3: =Table1459678101112314151316171920211823[[#This Row],[Estimated(hrs/sp)]] * 4 -> 8 | L3: 39 | M3: 45887 | N3: Nil | O3: Nil | P3: Nil | Q3: Nil | R3: Nil | S3: Nil | T3: Nil | U3: Nil | V3: Nil | W3: Nil | X3: Nil | Y3: Nil | Z3: Nil | AA3: Nil | AB3: Nil | AC3: Nil | AD3: Initially The story is currently on hold pending additional information. And also I have a blocker to run the report application.
A4: =ROW() - ROW(Table1459678101112314151316171920211823[[#Headers],[S.No]]) -> 3 | B4: =Dashboard!$J$1 -> MCS | C4: 45884 | D4: 45897 | E4: MCS 25 Sprint 17 | F4: Vaishnavi | G4: 48516 | H4: MCS - ED - Allow overwriting of default Captions and Tool Tips | I4: Story Being Tested | J4: 2 | K4: =Table1459678101112314151316171920211823[[#This Row],[Estimated(hrs/sp)]] * 4 -> 8 | L4: Nil | M4: Nil | N4: Nil | O4: Done | P4: Ganesh | Q4: Nil | R4: Hariharan Dhandapani | S4: Nil | T4: https://dev.azure.com/heartlandschools/MCS/_git/Edison/pullrequest/43356 | U4: 45875 | V4: Hariharan Dhandapani | W4: 45877 | X4: Nil | Y4: Patrick | Z4: 45883 | AA4: Nil | AB4: Nil | AC4: Nil | AD4: Completed development and POV. Waiting for PR Testing
A5: =ROW() - ROW(Table1459678101112314151316171920211823[[#Headers],[S.No]]) -> 4 | B5: MCS | C5: 45884 | D5: 45897 | E5: MCS 25 Sprint 17 | F5: Vaishnavi | G5: 49445 | H5: Add new bid group as a copy of existing bid group | I5: Story Completed | J5: 2 | K5: =Table1459678101112314151316171920211823[[#This Row],[Estimated(hrs/sp)]] * 4 -> 8 | L5: 3 | O5: Done | P5: Ganesh | Q5: Nil | R5: Nil | S5: Nil | T5: https://dev.azure.com/heartlandschools/MCS/_git/Edison/pullrequest/43914 | U5: 45882 | V5: Andrea | W5: 45888 | X5: To use Var type instead of ROW | Y5: Nil | Z5: Nil | AA5: Nil | AB5: Nil | AC5: Nil | AD5: Completed development and POV. Waiting for PR
A6: =ROW() - ROW(Table1459678101112314151316171920211823[[#Headers],[S.No]]) -> 5 | B6: MCS | C6: 45884 | D6: 45897 | E6: MCS 25 Sprint 17 | F6: Shriveni Baskaran | G6: 49566 | H6: MCS - ED - Add Support for Added Sugars Analysis | I6: Story Completed | J6: 1 | K6: 1 | L6: 2 | M6: Nil | N6: Nil | O6: Nil | P6: Nil | Q6: Nil | R6: Nil | S6: Nil | T6: Nil | U6: Nil | V6: Nil | W6: Nil | X6: Nil | Y6: Nil | Z6: Nil | AA6: Nil | AB6: Nil | AC6: Nil | AD6: Testing passed and completed
A7: =ROW() - ROW(Table1459678101112314151316171920211823[[#Headers],[S.No]]) -> 6 | B7: MCS | C7: 45884 | D7: 45897 | E7: MCS 25 Sprint 17-Strech | F7: Hariharan Dhandapani | G7: 49756 | H7: MCS-ED - Plugin - Custom Report Changes (additional) for Elk Grove | I7: Story Completed | J7: 1 | K7: =Table1459678101112314151316171920211823[[#This Row],[Estimated(hrs/sp)]] * 4 -> 4 | L7: 3 | M7: 45897 | N7: 45897 | O7: Done | P7: Ganesh | Q7: Nil | R7: Nil | S7: Nil | T7: Nil | U7: Nil | V7: Nil | W7: Nil | X7: Nil | Y7: Nil | Z7: Nil | AA7: Nil | AB7: Nil | AC7: Nil | AD7: Dev Testing completed
A8: =ROW() - ROW(Table1459678101112314151316171920211823[[#Headers],[S.No]]) -> 7 | B8: MCS | C8: 45884 | D8: 45897 | E8: MCS 25 Sprint 17-Strech | F8: Hariharan Dhandapani | G8: 49810 | H8: MCS - Plugin - Apply mapping changes to Peoplesoft Export | I8: Story Completed | J8: 1 | K8: =Table1459678101112314151316171920211823[[#This Row],[Estimated(hrs/sp)]] * 4 -> 4 | L8: 2 | M8: 45896 | N8: 45896 | O8: Done | P8: Ganesh | Q8: Nil | R8: Nil | S8: Nil | T8: Nil | U8: Nil | V8: Nil | W8: Nil | X8: Nil | Y8: Nil | Z8: Nil | AA8: Nil | AB8: Nil | AC8: Nil | AD8: Dev Testing completed
A9: =ROW() - ROW(Table1459678101112314151316171920211823[[#Headers],[S.No]]) -> 8 | B9: MCS | C9: 45884 | D9: 45897 | E9: MCS 25 Sprint 17-Strech | F9: Hariharan Dhandapani | G9: 49654 | H9: MCS - FR - Plugin - Add an LaSIDs Export File to the Louisiana Plugin | I9: Story Completed | J9: 1 | K9: =Table1459678101112314151316171920211823[[#This Row],[Estimated(hrs/sp)]] * 4 -> 4 | L9: 2 | M9: 45894 | N9: 45894 | O9: Done | P9: Ganesh | Q9: Nil | R9: Nil | S9: Nil | T9: Nil | U9: Nil | V9: Nil | W9: Nil | X9: Nil | Y9: Nil | Z9: Nil | AA9: Nil | AB9: Nil | AC9: Nil | AD9: Dev Testing completed
A10: =ROW() - ROW(Table1459678101112314151316171920211823[[#Headers],[S.No]]) -> 9 | B10: MCS | C10: 45884 | D10: 45897 | E10: MCS 25 Sprint 17 | F10: Hariharan Dhandapani | G10: 49545 | H10: MCS - DC - Improve SFTP Support for SIS Import | I10: Story Ready For Testing | J10: 3 | K10: =Table1459678101112314151316171920211823[[#This Row],[Estimated(hrs/sp)]] * 4 -> 12 | L10: 3 | M10: 45888 | N10: 45897 | O10: Done | P10: Ganesh | Q10: Nil | R10: Nil | S10: Nil | T10: Nil | U10: Nil | V10: Nil | W10: Nil | X10: Nil | Y10: Nil | Z10: Nil | AA10: Nil | AB10: Nil | AC10: Nil

Sheet MCS 25 Sprint 17-Defects
A1: S.No | B1: Sprint # | C1: Story/Defect ID | D1: Parent Story | E1: Developer | F1: Issue Type | G1: Issue Description | H1: Priority | I1: Defect Source | J1: Type | K1: Status | L1: Root Cause Category | M1: Comments

Sheet MCS 25 Sprint 16-Status
A1: S.No | B1: Application Name | C1: Sprint Start Date | D1: Sprint End Date | E1: Sprint | F1: Developer | G1: Story ID/Defect ID | H1: Description | I1: Status | J1: Estimated(hrs/sp) | K1: Actual(hrs/sp) | L1: Actual Hours (Worklog) | M1: Dev Start Date | N1: Dev End Date | O1: Unit testing | P1: Peer Tested By | Q1: Peer Tested Defects, if any | R1: Peer Reviewed By | S1: Peer Code Review Comments, if any | T1: PR Number/Link | U1: PR Created Date | V1: Reviewer 1 | W1: PR Approved Date | X1: Code Review Comments, if any | Y1: Reviewer 2 | Z1: Approved Date | AA1: Code Review Comments, if any2 | AB1: Internal PO -POV Comments | AC1: Client PO -POV Comments | AD1: Comments | AE1: Column1
A2: =ROW() - ROW(Table14596781011123141513161719202118[[#Headers],[S.No]]) -> 1 | B2: MCS | C2: 45870 | D2: 45883 | E2: MCS 25 Sprint 16 | F2: Hariharan Dhandapani | G2: 49044 | H2: MCS - DC - Add SFTP functionality to SIS import using generic text file | I2: Story Peer Review | J2: 3 | K2: =Table14596781011123141513161719202118[[#This Row],[Estimated(hrs/sp)]] * 4 -> 12 | L2: 34 | M2: 45870 | N2: 45882 | O2: Done | P2: Ganesh | Q2: Nil | R2: Nil | S2: Nil | T2: https://dev.azure.com/heartlandschools/MCS/_git/Datacenter/pullrequest/43923 | U2: Nil | V2: Nil | W2: Nil | X2: Nil | Y2: Nil | Z2: Nil | AA2: Nil | AB2: Nil | AC2: Nil | AD2: Development completed, Waiting for PR
A3: =ROW() - ROW(Table14596781011123141513161719202118[[#Headers],[S.No]]) -> 2 | B3: MCS | C3: 45870 | D3: 45883 | E3: MCS 25 Sprint 16 | F3: Vaishnavi | G3: 49483 | H3: LAUSD Production Record Enhancement | I3: Defect Needs More Info | J3: 2 | K3: =Table14596781011123141513161719202118[[#This Row],[Estimated(hrs/sp)]] * 4 -> 8 | L3: 8 | M3: 45874 | N3: Nil | O3: Nil | P3: Nil | Q3: Nil | R3: Nil | S3: Nil | T3: Nil | U3: Nil | V3: Nil | W3: Nil | X3: Nil | Y3: Nil | Z3: Nil | AA3: Nil | AB3: Nil | AC3: Nil | AD3: The story is currently on hold pending additional information. We're unable to move forward without the required inputs
A4: 4 | B4: MCS | C4: 45870 | D4: 45883 | E4: MCS 25 Sprint 16 | F4: Vaishnavi | G4: 25638 | H4: Inventory On Hand is showing a parameter window | I4: Defect Fixed | J4: 1 | K4: =Table14596781011123141513161719202118[[#This Row],[Estimated(hrs/sp)]] * 4 -> 4 | M4: 45867 | N4: 45868 | O4: Done | P4: Ganesh | Q4: Nil | R4: Hariharan Dhandapani | S4: Nil | T4: https://dev.azure.com/heartlandschools/MCS/_git/Edison/pullrequest/43689 | U4: 45869 | V4: Patric | W4: 45870 | X4: Nil | Y4: Nil | Z4: Nil | AA4: Nil | AB4: Nil | AC4: Nil
A5: =ROW() - ROW(Table14596781011123141513161719202118[[#Headers],[S.No]]) -> 4 | B5: =Dashboard!$J$1 -> MCS | C5: 45870 | D5: 45883 | E5: MCS 25 Sprint 16 Strech | F5: Vaishnavi | G5: 48516 | H5: MCS - ED - Allow overwriting of default Captions and Tool Tips | I5: Story Ready For Testing | J5: 2 | K5: =Table14596781011123141513161719202118[[#This Row],[Estimated(hrs/sp)]] * 4 -> 8 | L5: 13 | M5: 45873 | N5: 45882 | O5: Done | P5: Ganesh | Q5: Nil | R5: Hariharan Dhandapani | S5: Expose these properties as protected and Change naming conventions | T5: https://dev.azure.com/heartlandschools/MCS/_git/Edison/pullrequest/43356 | U5: 45875 | V5: Hariharan Dhandapani | W5: 45877 | X5: Nil | Y5: Patrick | Z5: 45883 | AA5: Nil | AB5: Nil | AC5: Nil | AD5: Had several discussions for implementation, updated the code, and resolved all comments.
A6: =ROW() - ROW(Table14596781011123141513161719202118[[#Headers],[S.No]]) -> 5 | B6: MCS | C6: 45870 | D6: 45883 | E6: MCS 25 Sprint 16 Strech | F6: Vaishnavi | G6: 49445 | H6: Add new bid group as a copy of existing bid group | I6: Story Peer Review | J6: 3 | K6: =Table14596781011123141513161719202118[[#This Row],[Estimated(hrs/sp)]] * 4 -> 12 | L6: 27 | M6: 45876 | N6: 45882 | O6: Done | P6: Ganesh | Q6: Nil | R6: Nil | S6: Nil | T6: https://dev.azure.com/heartlandschools/MCS/_git/Edison/pullrequest/43914 | U6: 45882 | V6: Nil | W6: Nil | X6: Nil | Y6: Nil | Z6: Nil | AA6: Nil | AB6: Nil | AC6: Nil | AD6: Completed development and POV. Waiting for PR
A7: 5 | B7: =Dashboard!$J$1 -> MCS | C7: 45870 | D7: 45883 | E7: MCS 25 Sprint 16 Strech | F7: Hariharan Dhandapani | G7: 49512 | H7: MCS - POS - Plugin - Apply mapping changes to PeopleSoft export | I7: Story Completed | J7: 1 | K7: =Table14596781011123141513161719202118[[#This Row],[Estimated(hrs/sp)]] * 4 -> 4 | L7: 3 | M7: 45877 | N7: 45877 | O7: Done | P7: Ganesh | Q7: Nil | R7: Nil | S7: Nil | T7: https://dev.azure.com/heartlandschools/MCS/_git/Newton/pullrequest/43822 | U7: 45876 | V7: Patric | W7: 45876 | X7: Nil | Y7: Nil | Z7: Nil | AA7: Nil | AB7: Nil | AC7: Nil

Sheet MCS 25 Sprint 16-Defects
A1: S.No | B1: Sprint # | C1: Story/Defect ID | D1: Parent Story | E1: Developer | F1: Issue Type | G1: Issue Description | H1: Priority | I1: Defect Source | J1: Type | K1: Status | L1: Root Cause Category | M1: Comments

Sheet MCS 25 Sprint 15-Status
A1: S.No | B1: Application Name | C1: Sprint Start Date | D1: Sprint End Date | E1: Sprint | F1: Developer | G1: Story ID/Defect ID | H1: Description | I1: Status | J1: Estimated(hrs/sp) | K1: Actual(hrs/sp) | L1: Actual Hours (Worklog) | M1: Dev Start Date | N1: Dev End Date | O1: Unit testing | P1: Peer Tested By | Q1: Peer Tested Defects, if any | R1: Peer Reviewed By | S1: Peer Code Review Comments, if any | T1: PR Number/Link | U1: PR Created Date | V1: Reviewer 1 | W1: PR Approved Date | X1: Code Review Comments, if any | Y1: Reviewer 2 | Z1: Approved Date | AA1: Code Review Comments, if any2 | AB1: Internal PO -POV Comments | AC1: Client PO -POV Comments | AD1: Comments | AE1: Column1
A2: =ROW() - ROW(Table145967810111231415131617192021[[#Headers],[S.No]]) -> 1 | B2: =Dashboard!$J$1 -> MCS | C2: 45856 | D2: 45869 | E2: MCS 25 Sprint 15 | F2: Vaishnavi | G2: 48516 | H2: MCS - ED - Allow overwriting of default Captions and Tool Tips | I2: Story Peer Review | J2: 3 | K2: =Table145967810111231415131617192021[[#This Row],[Estimated(hrs/sp)]] * 4 -> 12 | L2: 26 | M2: 45856 | O2: Done | P2: Ganesh | Q2: Nil | R2: Hariharan Dhandapani | S2: 1.To change the variable name. 2.To change the method name. 3.To remove the newline 4.To use the dictionary instead of a list. 5. | T2: https://dev.azure.com/heartlandschools/MCS/_git/Edison/pullrequest/43356 | U2: 45852 | V2: Hariharan Dhandapani | W2: Nil | X2: Nil | Y2: Nil | Z2: Nil | AA2: Nil | AB2: Nil | AC2: Nil | AD2: Had several discussions for implementation, updated the code, and resolved all comments.
A3: 2 | B3: MCS | C3: 45859 | D3: 45869 | E3: MCS 25 Sprint 15 | F3: Vaishnavi | G3: 49057 | H3: MCS - Cloud - Add Support for kc_idp_hint parameter in MSB SSO Integration | I3: Story Completed | J3: 1 | K3: =Table145967810111231415131617192021[[#This Row],[Estimated(hrs/sp)]] * 4 -> 4 | L3: 17 | M3: 45856 | N3: 45868 | O3: Done | P3: Ganesh | Q3: Nil | R3: Hariharan Dhandapani | S3: Access the hint through the Settings property | T3: https://dev.azure.com/heartlandschools/MCS/_git/Nebulizer/pullrequest/43662 | U3: 45867 | V3: Hariharan Dhandapani | W3: 45868 | X3: Nil | Y3: Nil | Z3: Nil | AA3: Nil | AB3: Nil | AC3: Nil | AD3: We are blocked in last stage on dev testing and connected with Patrick and resolved, and then done with dev testing. Finally completed the POV. | AE3: Dev testing only
A4: 3 | B4: MCS | C4: 45856 | D4: 45869 | E4: MCS 25 Sprint 15 | F4: Hariharan Dhandapani | G4: 22177 | H4: POS - Users can skip POS batches even with the Toggle/Skip permission set to None | I4: Story Completed | J4: 2 | K4: =Table145967810111231415131617192021[[#This Row],[Estimated(hrs/sp)]] * 4 -> 8 | L4: 9 | M4: 45856 | N4: 45859 | O4: Done | P4: Ganesh | Q4: Nil | R4: Nil | S4: Nil | T4: https://dev.azure.com/heartlandschools/MCS/_git/Newton/pullrequest/43508 | U4: 45860 | V4: Andrea | W4: 45860 | X4: Nil | Y4: Nil | Z4: Nil | AA4: Nil | AB4: Nil | AC4: Nil
A5: 4 | B5: MCS | C5: 45856 | D5: 45869 | E5: MCS 25 Sprint 15 Strech | F5: Vaishnavi | G5: 25638 | H5: Inventory On Hand is showing a parameter window | I5: Story Ready For Testing | J5: 2 | K5: =Table145967810111231415131617192021[[#This Row],[Estimated(hrs/sp)]] * 4 -> 8 | L5: 9 | M5: 45867 | N5: 45868 | O5: Done | P5: Ganesh | Q5: Nil | R5: Hariharan Dhandapani | S5: Nil | T5: https://dev.azure.com/heartlandschools/MCS/_git/Edison/pullrequest/43689 | U5: 45869 | V5: Nil | W5: Nil | X5: Nil | Y5: Nil | Z5: Nil | AA5: Nil | AB5: Nil | AC5: Nil | AD5: Completed development and POV. Created Draft PR
A6: 5 | B6: MCS | C6: 45856 | D6: 45869 | E6: MCS 25 Sprint 15 Strech | F6: Hariharan Dhandapani | G6: 49044 | H6: MCS - DC - Add SFTP functionality to SIS import using generic text file | I6: Story Being Developed | J6: 5 | K6: =Table145967810111231415131617192021[[#This Row],[Estimated(hrs/sp)]] * 4 -> 20 | L6: 24 | M6: 45860 | O6: Done | P6: Ganesh | Q6: Nil | R6: Nil | S6: Nil | T6: Nil | U6: Nil | V6: Nil | W6: Nil | X6: Nil | Y6: Nil | Z6: Nil | AA6: Nil | AB6: Nil | AC6: Nil | AD6: Development completed, dev testing is in progress

Sheet MCS 25 Sprint 15-Defects
A1: S.No | B1: Sprint # | C1: Story/Defect ID | D1: Parent Story | E1: Developer | F1: Issue Type | G1: Issue Description | H1: Priority | I1: Defect Source | J1: Type | K1: Status | L1: Root Cause Category | M1: Comments
B2: MCS 25 Sprint 15 | C2: 22177 | E2: Hariharan Dhandapani | F2: Defect | G2: POS - Users can skip POS batches even with the Toggle/Skip permission set to None | H2: Minor | I2: Manual | J2: External | K2: Defect Being Fixed | L2: Existing Issue
B3: MCS 25 Sprint 15 Strech | C3: 25638 | E3: Vaishnavi | F3: Defect | G3: Inventory On Hand is showing a parameter window | H3: Minor | I3: Manual | J3: External | K3: Defect Being Fixed | L3: Existing Issue

Sheet MCS 25 Sprint 14-Status
A1: S.No | B1: Application Name | C1: Sprint Start Date | D1: Sprint End Date | E1: Sprint | F1: Developer | G1: Story ID/Defect ID | H1: Description | I1: Status | J1: Estimated(hrs/sp) | K1: Actual(hrs/sp) | L1: Actual Hours (Worklog) | M1: Dev Start Date | N1: Dev End Date | O1: Unit testing | P1: Peer Tested By | Q1: Peer Tested Defects, if any | R1: Peer Reviewed By | S1: Peer Code Review Comments, if any | T1: PR Number/Link | U1: PR Created Date | V1: Reviewer 1 | W1: PR Approved Date | X1: Code Review Comments, if any | Y1: Reviewer 2 | Z1: Approved Date | AA1: Code Review Comments, if any2 | AB1: Internal PO -POV Comments | AC1: Client PO -POV Comments | AD1: Comments | AE1: Column1
A2: =ROW() - ROW(Table1459678101112314151316171920[[#Headers],[S.No]]) -> 1 | B2: =Dashboard!$J$1 -> MCS | C2: 45842 | D2: 45855 | E2: MCS 25 - Sprint 14 | F2: Shriveni Baskaran | G2: 48104 | H2: MCS - ED - Custom Report Changes for Elk Grove | I2: Story Completed | J2: 1 | K2: 2 | L2: 8 | M2: 45842 | N2: 45849 | O2: Done | P2: Nil | Q2: Nil | R2: Harihara Dhandapani | S2: Nil | T2: https://heartlandschools.visualstudio.com/MCS/_git/Edison/pullrequest/43311 | U2: 45848 | V2: HariHara Dhandapani | W2: 45848 | X2: Update script xml changes to be done | Y2: Rudolf Svaby | Z2: 45849 | AA2: LeftoversReceived] and [LeftoversDiscarded] have their special purpose which is same all over the production reports. Keeping the same name and replacing their logic is bad practice | AB2: Nil | AC2: Nil | AD2: Implementation modified to create a new pluggin for ElkGrove, added ElkGrove Production Report, created a new PR, and approved by Hari. 12-7-25 Rudy approved PR Aand build released to Josh.
A3: =ROW() - ROW(Table1459678101112314151316171920[[#Headers],[S.No]]) -> 2 | B3: =Dashboard!$J$1 -> MCS | C3: 45842 | D3: 45855 | E3: MCS 25 - Sprint 14 | F3: Vaishnavi | G3: 48516 | H3: MCS - ED - Allow overwriting of default Captions and Tool Tips | I3: Story Being Developed | J3: 3 | K3: =Table1459678101112314151316171920[[#This Row],[Estimated(hrs/sp)]] * 4 -> 12 | L3: 10 | M3: 45854 | N3: 17/16/2025 | O3: Done | P3: Ganesh | Q3: 1.To avoid the optional and ref parameter. 2.To change the method name. | R3: Harihara Dhandapani | S3: 1.To access to member variables .2.No need to make base class Action in the derived classes.3.Implement a solution for ShowSetupScreen on base class. 4.Create common variable on Action base class. | T3: https://dev.azure.com/heartlandschools/MCS/_git/Edison/pullrequest/43356 | U3: 45852 | V3: Rudy | W3: Nil | X3: Nil | Y3: Nil | Z3: Nil | AA3: Nil | AB3: Nil | AC3: Nil | AD3: Development And POV(15/07/25) Completed. Working on review comments
A4: =ROW() - ROW(Table1459678101112314151316171920[[#Headers],[S.No]]) -> 3 | B4: MCS | C4: 45842 | D4: 45855 | E4: MCS 25 - Sprint 14 | F4: Vaishnavi | G4: 49057 | H4: MCS - Cloud - Add Support for kc_idp_hint parameter in MSB SSO Integration | I4: Story Being Developed | J4: 3 | K4: =Table1459678101112314151316171920[[#This Row],[Estimated(hrs/sp)]] * 4 -> 12 | L4: 43 | M4: 45849 | N4: 17/16/2025 | O4: In Progress | P4: Nil | Q4: Nil | R4: Nil | S4: Nil | T4: Nil | U4: Nil | V4: Nil | W4: Nil | X4: Nil | Y4: Nil | Z4: Nil | AA4: Nil | AB4: Nil | AC4: Nil | AD4: Initially faced some issues with the dev setup based on the steps shared by Andrea. After checking with him, he confirmed that not all steps are needed as it's specific to the NublizerWeb App/. Then completed the development. While doing dev testing using the steps shared by Patrick, but the expected scenarios not work. Discussed with Adrea, but the issue still exists. We have informed Ramu and will proceed based on his response
A5: =ROW() - ROW(Table1459678101112314151316171920[[#Headers],[S.No]]) -> 4 | B5: =Dashboard!$J$1 -> MCS | C5: 45842 | D5: 45855 | E5: MCS 25 - Sprint 14 | F5: Hari/Shriveni Baskaran[Testing] | G5: 48013 | H5: MCS - ED - Add ability to schedule sending orders to vendor | I5: Story Completed | J5: 3 | K5: 1 | L5: 3 | M5: Nil | N5: Nil | O5: Nil | P5: Nil | Q5: Nil | R5: Nil | S5: Nil | T5: Nil | U5: Nil | V5: Nil | W5: Nil | X5: Nil | Y5: Nil | Z5: Nil | AA5: Nil | AB5: Nil | AC5: Nil | AD5: Completed test case exeution, and it passed.
A6: =ROW() - ROW(Table1459678101112314151316171920[[#Headers],[S.No]]) -> 5 | B6: MCS | C6: 45842 | D6: 45855 | E6: MCS 25 - Sprint 14 Strech | F6: Hari | G6: 48984 | H6: MCS - ED - Create LAUSD Production Plugin | I6: Story Completed | J6: 2 | K6: =Table1459678101112314151316171920[[#This Row],[Estimated(hrs/sp)]] * 4 -> 8 | L6: 12 | M6: 45845 | N6: 45846 | O6: Done | P6: Ganesh | Q6: Nil | R6: Rajith | S6: Nil | T6: https://dev.azure.com/heartlandschools/MCS/_git/Edison/pullrequest/43285 | U6: 45848 | V6: Rudy | W6: 45849 | X6: Nil | Y6: Nil | Z6: Nil | AA6: Nil | AB6: Nil | AC6: Nil
A7: =ROW() - ROW(Table1459678101112314151316171920[[#Headers],[S.No]]) -> 6 | B7: MCS | C7: 45842 | D7: 45855 | E7: MCS 25 - Sprint 14 Strech | F7: Hari | G7: 49173 | H7: System - Alert for SQL Version older than 2016 | I7: Story Completed | J7: 2 | K7: =Table1459678101112314151316171920[[#This Row],[Estimated(hrs/sp)]] * 4 -> 8 | L7: 6 | M7: 45854 | N7: 45854 | O7: Done | P7: Ganesh | Q7: Nil | R7: Nil | S7: Nil | T7: Nil | U7: Nil | V7: Nil | W7: Nil | X7: Nil | Y7: Nil | Z7: Nil | AA7: Nil | AB7: Nil | AC7: Nil | AD7: Dev Testing Only
A8: =ROW() - ROW(Table1459678101112314151316171920[[#Headers],[S.No]]) -> 7 | B8: MCS | C8: 45842 | D8: 45855 | E8: MCS 25 - Sprint 14 Strech | F8: Hari | G8: 49230 | H8: MCS - POS - Update CSUSA Plugin for Account Balance Adjustments Export | I8: Story Completed | J8: 2 | K8: =Table1459678101112314151316171920[[#This Row],[Estimated(hrs/sp)]] * 4 -> 8 | L8: 4 | M8: 45854 | N8: 45854 | O8: Done | P8: Nil | Q8: Nil | R8: Nil | S8: Nil | T8: Nil | U8: Nil | V8: Nil | W8: Nil | X8: Nil | Y8: Nil | Z8: Nil | AA8: Nil | AB8: Nil | AC8: NIl | AD8: Export has been handed over to josh, upon his confirmation closing this story.
A9: =ROW() - ROW(Table1459678101112314151316171920[[#Headers],[S.No]]) -> 8 | B9: =Dashboard!$J$1 -> MCS | C9: 45842 | D9: 45855 | E9: MCS 25 - Sprint 14 Strech | F9: Vaishnavi | G9: 24244 | H9: MCS - ED - Product Expiration system defined report-Scheduled Job Parameters are not saving | I9: Story Ready For Testing | J9: 2 | K9: =Table1459678101112314151316171920[[#This Row],[Estimated(hrs/sp)]] * 4 -> 8 | L9: 0 | M9: Nil | N9: Nil | O9: Done | P9: Ganesh | Q9: Nil | R9: Hari | S9: Nil | T9: https://dev.azure.com/heartlandschools/MCS/_git/Edison/pullrequest/42977 | U9: 45832 | V9: Andrea | W9: 45839 | X9: Nil | Y9: Nil | Z9: Nil | AA9: Nil | AB9: Nil | AC9: Nil | AD9: Development , POV and Peer review completed on last sprint.Defect move to next sprint.

Sheet MCS 25 Sprint 14-Defects
A1: S.No | B1: Sprint # | C1: Story/Defect ID | D1: Parent Story | E1: Developer | F1: Issue Type | G1: Issue Description | H1: Priority | I1: Defect Source | J1: Type | K1: Status | L1: Root Cause Category | M1: Comments
B2: MCS 25 Sprint 14 Stretch | C2: 24244 | E2: Vaishnavi | F2: Defect | G2: MCS - ED - Product Expiration system defined report-Scheduled Job Parameters are not saving | H2: Minor | I2: Manual | J2: External | K2: Defect Being Fixed | L2: Existing Issue

Sheet MCS 25 Sprint 13-Status
A1: S.No | B1: Application Name | C1: Sprint Start Date | D1: Sprint End Date | E1: Sprint | F1: Developer | G1: Story ID/Defect ID | H1: Description | I1: Status | J1: Estimated(hrs/sp) | K1: Actual(hrs/sp) | L1: Actual Hours (Worklog) | M1: Unit testing | N1: Peer Tested By | O1: Peer Tested Defects, if any | P1: Peer Reviewed By | Q1: Peer Code Review Comments, if any | R1: PR Number/Link | S1: PR Created Date | T1: Reviewer 1 | U1: PR Approved Date | V1: Code Review Comments, if any | W1: Reviewer 2 | X1: Approved Date | Y1: Code Review Comments, if any2 | Z1: Internal PO -POV Comments | AA1: Client PO -POV Comments | AB1: Comments | AC1: Column1
A2: =ROW() - ROW(Table14596781011123141513161719[[#Headers],[S.No]]) -> 1 | B2: =Dashboard!$J$1 -> MCS | C2: 45831 | D2: 45841 | E2: MCS 25 - Sprint 13 | F2: vaishnavi | G2: 47496 | H2: MCS - ED - Add Permissions for Ad-Hoc Inventory (PR - Billable) | I2: Story Completed | J2: 1 | K2: =Table14596781011123141513161719[[#This Row],[Estimated(hrs/sp)]] * 4 -> 4 | L2: 1 | M2: Done | N2: Hari | O2: Nil | P2: Hari | Q2: Nil | R2: https://dev.azure.com/heartlandschools/MCS/_git/Edison/pullrequest/42494 | S2: 45807 | T2: Hari | U2: 45811 | V2: Nil | W2: Rudy | X2: 45840 | Y2: Nil | Z2: Nil | AA2: Nil | AB2: Rudy has suggested to ignore cosmetic issues
A3: =ROW() - ROW(Table14596781011123141513161719[[#Headers],[S.No]]) -> 2 | B3: =Dashboard!$J$1 -> MCS | C3: 45831 | D3: 45841 | E3: MCS 25 - Sprint 13 | F3: Shriveni Baskaran | G3: 48104 | H3: MCS - ED - Custom Report Changes for Elk Grove | I3: Story Peer Review | J3: 3 | K3: 7 | L3: 20 | M3: Done | N3: Hari | O3: Nil | P3: Hari | Q3: 1.naming conventions to be followed, also 2.passing a copy of one datatable need to changed. | R3: Nil | S3: Nil | T3: Nil | U3: Nil | V3: Nil | W3: Nil | X3: Nil | Y3: Nil | Z3: Nil | AA3: Nil | AB3: 01/7/25 - POV video shared with Josh and Ashley, yet to be verified. 02/7/25 - no change in status 03/7/25 - POV verified by Josh - can be closed and moved to district for testing | AC3: Nil
A4: =ROW() - ROW(Table14596781011123141513161719[[#Headers],[S.No]]) -> 3 | B4: =Dashboard!$J$1 -> MCS | C4: 45831 | D4: 45841 | E4: MCS 25 - Sprint 13 | F4: Hariharan/Shriveni[Testing] | G4: 48462 | H4: MCS - POS - Apply security changes to Email for Permissive TLS | I4: Story Completed | J4: 3 | K4: =Table14596781011123141513161719[[#This Row],[Estimated(hrs/sp)]] * 4 -> 12 | L4: 27 | M4: Done | N4: Andrea | O4: Nil | P4: Andrea | Q4: Nil | R4: https://dev.azure.com/heartlandschools/MCS/_git/Newton/pullrequest/42735 | S4: 45819 | T4: Patrick | U4: 45818 | V4: Nil | W4: Andrea | X4: 45819 | Y4: Nil | Z4: Nil | AA4: Nil | AB4: 01/7/25 - Both Franklin, and Newton completed - but many test cases failed, should check with Milan. 02/7/25 - checked with Milan, Milan corrected the test cases and my settings, I completed retest for Franklin, all TC succeeded. 03/7/25 - Milan marked this story completed
A5: =ROW() - ROW(Table14596781011123141513161719[[#Headers],[S.No]]) -> 4 | B5: =Dashboard!$J$1 -> MCS | C5: 45831 | D5: 45841 | E5: MCS 25 - Sprint 13 | F5: vaishnavi | G5: 48766 | H5: MCS Scrub Scripts Update - 2 | I5: Story Completed | J5: 2 | K5: =Table14596781011123141513161719[[#This Row],[Estimated(hrs/sp)]] * 4 -> 8 | L5: 14 | M5: Done | N5: Ganesh | O5: Nil | P5: Hari | Q5: Nil | R5: Edison: https://dev.azure.com/heartlandschools/MCS/_git/Edison/pullrequest/43094?path=/Database/UpgradeDatabase.cs Franklin: https://dev.azure.com/heartlandschools/MCS/_git/Franklin/pullrequest/43095 Datacenter:https://dev.azure.com/heartlandschools/MCS/_git/Datacenter/pullrequest/43093 MSA Client: https://dev.azure.com/heartlandschools/MCS/_git/MSAClient/pullrequest/43096 MCS Tech: https://dev.azure.com/heartlandschools/MCS/_git/MCSTech/pullrequest/43097 | S5: 45839 | T5: Andrea | U5: 45839 | V5: Nil | W5: Rudy | X5: 45840 | Y5: Nil | Z5: Nil | AA5: Nil
A6: =ROW() - ROW(Table14596781011123141513161719[[#Headers],[S.No]]) -> 5 | B6: =Dashboard!$J$1 -> MCS | C6: 45831 | D6: 45841 | E6: MCS 25 - Sprint 13 Strech | F6: vaishnavi | G6: 48516 | H6: MCS - ED - Allow overwriting of default Captions and Tool Tips | I6: Story Being Developed | J6: 3 | K6: =Table14596781011123141513161719[[#This Row],[Estimated(hrs/sp)]] * 4 -> 12 | L6: 27 | M6: Done | N6: Ganesh | O6: Nil | P6: Nil | Q6: Nil | R6: Nil | S6: Nil | T6: Nil | U6: Nil | V6: Nil | W6: Nil | X6: Nil | Y6: Nil | Z6: Nil | AA6: Nil | AB6: During development, clarified a few points with Josh and made the necessary changes. Functionality has been implemented and I will provide the POV.
A7: =ROW() - ROW(Table14596781011123141513161719[[#Headers],[S.No]]) -> 6 | B7: =Dashboard!$J$1 -> MCS | C7: 45831 | D7: 45841 | E7: MCS 25 - Sprint 13 Strech | F7: vaishnavi | G7: 24244 | H7: MCS - ED - Product Expiration system defined report-Scheduled Job Parameters are not saving | I7: Story Ready For Testing | J7: 3 | K7: =Table14596781011123141513161719[[#This Row],[Estimated(hrs/sp)]] * 4 -> 12 | L7: 6 | M7: Done | N7: Hari | O7: Nil | P7: Hari | Q7: Nil | R7: https://dev.azure.com/heartlandschools/MCS/_git/Edison/pullrequest/42977 | S7: 45832 | T7: Andrea | U7: 45839 | V7: Nil | W7: Nil | X7: Nil | Y7: Nil | Z7: Nil | AA7: Nil
A8: 7 | B8: MCS | C8: 45831 | D8: 45841 | E8: MCS 25 - Sprint 13 Strech | F8: Hariharan | G8: 48654 | H8: MCS - POS - Account Balances Affecting Adjustments Export | I8: Story Completed | J8: 3 | K8: =Table14596781011123141513161719[[#This Row],[Estimated(hrs/sp)]] * 4 -> 12 | L8: 24 | M8: Done | N8: Ganesh | O8: Nil | P8: Nil | Q8: Nil | R8: Nil | S8: Nil | T8: Nil | U8: Nil | V8: Nil | W8: Nil | X8: Nil | Y8: Nil | Z8: Nil | AA8: Nil | AB8: Only DEV testing .

Sheet MCS 25 Sprint 13-Defects
A1: S.No | B1: Sprint # | C1: Story/Defect ID | D1: Parent Story | E1: Developer | F1: Issue Type | G1: Issue Description | H1: Priority | I1: Defect Source | J1: Type | K1: Status | L1: Root Cause Category | M1: Comments
B2: MCS 25 Sprint 13 Stretch | C2: 24244 | E2: Vaishnavi | F2: Defect | G2: MCS - ED - Product Expiration system defined report-Scheduled Job Parameters are not saving | H2: Minor | I2: Manual | J2: External | K2: Defect Being Fixed | L2: Existing Issue

Sheet MCS 25 Sprint 12-Status
A1: S.No | B1: Application Name | C1: Sprint Start Date | D1: Sprint End Date | E1: Sprint | F1: Developer | G1: Story ID/Defect ID | H1: Description | I1: Status | J1: Estimated(hrs/sp) | K1: Actual(hrs/sp) | L1: Actual Hours (Worklog) | M1: Unit testing | N1: Peer Tested By | O1: Peer Tested Defects, if any | P1: Peer Reviewed By | Q1: Peer Code Review Comments, if any | R1: PR Number/Link | S1: PR Created Date | T1: Reviewer 1 | U1: PR Approved Date | V1: Code Review Comments, if any | W1: Reviewer 2 | X1: Approved Date | Y1: Code Review Comments, if any2 | Z1: Internal PO -POV Comments | AA1: Client PO -POV Comments | AB1: Comments | AC1: Column1
A2: 1 | B2: =Dashboard!$J$1 -> MCS | C2: 45814 | D2: 45828 | E2: MCS 25 - Sprint 12 | F2: Hariharan | G2: 47443 | H2: MCS - ED - Cherry Creek Production report plugin modification | I2: Story Completed | J2: 3 | K2: =Table145967810111231415131617[[#This Row],[Estimated(hrs/sp)]] * 4 -> 12 | L2: 20 | M2: Done | N2: Ganesh | R2: https://dev.azure.com/heartlandschools/MCS/_git/Edison/pullrequest/42899 | S2: 45825 | T2: Rudy | U2: 45825 | V2: Nil | AA2: Client Requested to Change the Label Name from "Meal Comments" to "User" | AB2: Plugin Build delivered to the Josh, to hanover to the Customer.
A3: =ROW() - ROW(Table145967810111231415131617[[#Headers],[S.No]]) -> 2 | B3: =Dashboard!$J$1 -> MCS | C3: 45814 | D3: 45828 | E3: MCS 25 - Sprint 12 | F3: vaishnavi | G3: 48520 | H3: MCS - Scrub Scripts update | I3: Story Completed | J3: 3 | K3: =Table1459678101112314151316[[#This Row],[Estimated(hrs/sp)]] * 4 -> 12 | L3: 22 | M3: Done | N3: Ganesh | O3: Nil | P3: Hari | Q3: To add the duplicate name instead of actual name | R3: https://dev.azure.com/heartlandschools/MCS/_git/Newton/pullrequest/42882 https://dev.azure.com/heartlandschools/MCS/_git/MCSTech/pullrequest/42883 Franklin:https://dev.azure.com/heartlandschools/MCS/_git/Franklin/pullrequest/42881 | S3: 45825 | T3: Rudy | U3: 45828 | V3: 1.Instead of dbLib.CSql use dbLib.CSqlList 2.This is a verbatim text, do not use \n 3.To change the email format for school table | W3: Nil | X3: Nil | Y3: Nil
A4: =ROW() - ROW(Table145967810111231415131617[[#Headers],[S.No]]) -> 3 | B4: =Dashboard!$J$1 -> MCS | C4: 45814 | D4: 45828 | E4: MCS 25 - Sprint 12 | F4: vaishnavi | G4: 47496 | H4: MCS - ED - Add Permissions for Ad-Hoc Inventory (PR - Billable) | I4: Story Being Tested | J4: 2 | K4: =Table145967810111231415131617[[#This Row],[Estimated(hrs/sp)]] * 4 -> 8 | M4: Done | N4: Ganesh | O4: Nil | Q4: .1.Handle the single function instead of two function 2. Remove the new line 3. Remove the "\n" | R4: https://dev.azure.com/heartlandschools/MCS/_git/Edison/pullrequest/42494 | S4: 45807 | T4: Hari | U4: 45811 | AB4: Prepared the documentation for the upgrade scripts functionality and shared it with Josh and Ganesh for review. After their verification, I submitted the development code for peer review and subsequently resolved the review comments.
A5: =ROW() - ROW(Table145967810111231415131617[[#Headers],[S.No]]) -> 4 | B5: =Dashboard!$J$1 -> MCS | C5: 45814 | D5: 45828 | E5: MCS 25 - Sprint 12 | F5: Shriveni Baskaran | G5: 48104 | H5: MCS - ED - Custom Report Changes for Elk Grove | I5: Story Being Developed | J5: 5 | K5: =Table145967810111231415131617[[#This Row],[Estimated(hrs/sp)]] * 4 -> 20 | L5: 39 | AB5: Completed first four reqirements from document.
A6: =ROW() - ROW(Table145967810111231415131617[[#Headers],[S.No]]) -> 5 | B6: =Dashboard!$J$1 -> MCS | C6: 45814 | D6: 45828 | E6: MCS 25 - Sprint 12 | F6: Hariharan | G6: 48462 | H6: MCS - POS - Apply security changes to Email for Permissive TLS | I6: Story Being Tested | J6: 3 | K6: =Table145967810111231415131617[[#This Row],[Estimated(hrs/sp)]] * 4 -> 12 | L6: 8 | M6: Done | N6: Andrea | R6: https://dev.azure.com/heartlandschools/MCS/_git/Newton/pullrequest/42735 | S6: 45819 | T6: Patrick | U6: 45818 | V6: Nil | W6: Andrea | X6: 45819 | Y6: Nil | Z6: Currently In Testing Phase, if not completed will carryforwarded to the next sprint with new estimates
A7: =ROW() - ROW(Table1459678101112314151316[[#Headers],[S.No]]) -> 6 | B7: =Dashboard!$J$1 -> MCS | C7: 45814 | D7: 45828 | E7: MCS 25 - Sprint 12 | F7: Shriveni Baskaran | G7: 48112 | H7: MSA (Web) - Bootstrap/WCAG - Admin Portal Testing | I7: Story Completed | J7: 3 | K7: =Table145967810111231415131617[[#This Row],[Estimated(hrs/sp)]] * 4 -> 12 | L7: =Table145967810111231415131617[[#This Row],[S.No]] + 19 -> 25 | AB7: Testing completed.
A8: =ROW() - ROW(Table145967810111231415131617[[#Headers],[S.No]]) -> 7 | B8: =Dashboard!$J$1 -> MCS | C8: 45814 | D8: 45828 | E8: MCS 25 - Sprint 12 Strech | F8: Hariharan | G8: 48462 | H8: MCS - System - Update Old Version of SQL Alert to SQL 2014 | I8: Story Completed | J8: 1 | K8: =Table145967810111231415131617[[#This Row],[Estimated(hrs/sp)]] * 4 -> 4 | L8: 6 | M8: Done | N8: Ganesh | R8: https://dev.azure.com/heartlandschools/MCS/_git/Newton/pullrequest/42925 https://dev.azure.com/heartlandschools/MCS/_git/Franklin/pullrequest/42926 https://dev.azure.com/heartlandschools/MCS/_git/MSAClient/pullrequest/42924 https://dev.azure.com/heartlandschools/MCS/_git/Edison/pullrequest/42927 | S8: 45826 | T8: Andrea | U8: 45826 | V8: Nil | W8: Andrea | X8: 45819 | Y8: Nil | Z8: Story Completed and only DEV testing is enough.
A9: =ROW() - ROW(Table145967810111231415131617[[#Headers],[S.No]]) -> 8 | B9: =Dashboard!$J$1 -> MCS | C9: 45814 | D9: 45828 | E9: MCS 25 - Sprint 12 Strech | F9: vaishnavi | G9: 24244 | H9: MCS - ED - Product Expiration system defined report-Scheduled Job Parameters are not saving | I9: Product Owner - Verify | J9: 3 | K9: =Table145967810111231415131617[[#This Row],[Estimated(hrs/sp)]] * 4 -> 12 | L9: 43 | M9: Done | N9: Ganesh | O9: Nil | AB9: There was a delay in resolving issue 24244 as it was difficult to find the root cause. Spent more time in analysis and debugging. Once the root cause was identified, the fix was implemented quickly.

Sheet MCS 25 Sprint 12-Defects
A1: S.No | B1: Sprint # | C1: Story/Defect ID | D1: Parent Story | E1: Developer | F1: Issue Type | G1: Issue Description | H1: Priority | I1: Defect Source | J1: Type | K1: Status | L1: Root Cause Category | M1: Comments
B2: MCS 25 Sprint 12 Stretch | C2: 24244 | E2: Vaishnavi | F2: Defect | G2: MCS - ED - Product Expiration system defined report-Scheduled Job Parameters are not saving | H2: Minor | I2: Manual | J2: External | K2: Defect Being Fixed | L2: Existing Issue

Sheet MCS 25 Sprint 11-Status
A1: S.No | B1: Application Name | C1: Sprint Start Date | D1: Sprint End Date | E1: Sprint | F1: Developer | G1: Story ID/Defect ID | H1: Description | I1: Status | J1: Estimated(hrs/sp) | K1: Actual(hrs/sp) | L1: Actual Hours (Worklog) | M1: Unit testing | N1: Peer Tested By | O1: Peer Tested Defects, if any | P1: Peer Reviewed By | Q1: Peer Code Review Comments, if any | R1: PR Number/Link | S1: PR Created Date | T1: Reviewer 1 | U1: PR Approved Date | V1: Code Review Comments, if any | W1: Reviewer 2 | X1: Approved Date | Y1: Code Review Comments, if any2 | Z1: Internal PO -POV Comments | AA1: Client PO -POV Comments | AB1: Comments | AC1: Column1
A2: =ROW() - ROW(Table1459678101112314151316[[#Headers],[S.No]]) -> 1 | B2: =Dashboard!$J$1 -> MCS | C2: 45800 | D2: 45813 | E2: MCS 25 - Sprint 11 | F2: vaishnavi | G2: 47496 | H2: MCS -- ED - Add Permissions for Ad-Hoc Inventory (PR - Billable) | I2: Story Being Tested | J2: 2 | K2: =Table1459678101112314151316[[#This Row],[Estimated(hrs/sp)]] * 4 -> 8 | L2: 9 | M2: Done | N2: Ganesh | O2: Nil | Q2: .1.Handle the single function instead of two function 2. Remove the new line 3. Remove the "\n" | R2: https://dev.azure.com/heartlandschools/MCS/_git/Edison/pullrequest/42494 | S2: 45807 | T2: Hari | U2: 45811 | AB2: Prepared the documentation for the upgrade scripts functionality and shared it with Josh and Ganesh for review. After their verification, I submitted the development code for peer review and subsequently resolved the review comments.
A3: =ROW() - ROW(Table1459678101112314151316[[#Headers],[S.No]]) -> 2 | B3: =Dashboard!$J$1 -> MCS | C3: 45800 | D3: 45813 | E3: MCS 25 - Sprint 11 | F3: Hariharan | G3: 48013 | H3: MCS - ED - Add ability to schedule sending orders to vendor | I3: Story Being Tested | J3: 3 | K3: =Table1459678101112314151316[[#This Row],[Estimated(hrs/sp)]] * 4 -> 12 | L3: 16 | M3: Done | N3: Ganesh | Q3: Builder class recommandation | R3: https://dev.azure.com/heartlandschools/MCS/_git/Edison/pullrequest/42423 | S3: 45804 | T3: Mike | U3: 45807 | AB3: Testing is still pending. Carryforwarded to the next sprint
A4: =ROW() - ROW(Table1459678101112314151316[[#Headers],[S.No]]) -> 3 | B4: =Dashboard!$J$1 -> MCS | C4: 45800 | D4: 45813 | E4: MCS 25 - Sprint 11 | F4: Shriveni Baskaran | G4: 48025 | H4: MSA (Web) - Bootstrap/WCAG - Parent Site Testing | I4: Story Completed | J4: 3 | K4: =Table1459678101112314151316[[#This Row],[Estimated(hrs/sp)]] * 4 -> 12 | L4: =Table1459678101112314[[#This Row],[Estimated(hrs/sp)]] * 4 -> 4 | AB4: I have completed testing for Chrome, Ipad and Iphone 15 configurations. All test cases passed.
A5: =ROW() - ROW(Table1459678101112314151316[[#Headers],[S.No]]) -> 4 | B5: =Dashboard!$J$1 -> MCS | C5: 45800 | D5: 45813 | E5: MCS 25 - Sprint 11 | F5: Hariharan | G5: 48462 | H5: MCS - POS - Apply security changes to Email for Permissive TLS | I5: Story Being Tested | J5: 3 | K5: =Table1459678101112314151316[[#This Row],[Estimated(hrs/sp)]] * 4 -> 12 | L5: 12 | M5: Done | N5: Ganesh | R5: https://dev.azure.com/heartlandschools/MCS/_git/Newton/pullrequest/42524 | S5: 45809 | T5: Mike | U5: 45810 | AB5: Testing is still pending. Carryforwarded to the next sprint
A6: =ROW() - ROW(Table1459678101112314151316[[#Headers],[S.No]]) -> 5 | B6: =Dashboard!$J$1 -> MCS | C6: 45800 | D6: 45813 | E6: MCS 25 - Sprint 11 | F6: Shriveni Baskaran | G6: 48112 | H6: MSA (Web) - Bootstrap/WCAG - Admin Portal Testing | I6: Story Being Developed | J6: 5 | K6: =Table1459678101112314151316[[#This Row],[Estimated(hrs/sp)]] * 4 -> 20 | AB6: Testing suspended - story moved to development.
A7: =ROW() - ROW(Table1459678101112314151316[[#Headers],[S.No]]) -> 6 | B7: =Dashboard!$J$1 -> MCS | C7: 45800 | D7: 45813 | E7: MCS 25 - Sprint 11 Stretch | F7: vaishnavi | G7: 48520 | H7: MCS - Scrub Scripts update | I7: Story Being Developed | J7: 2 | K7: =Table1459678101112314151316[[#This Row],[Estimated(hrs/sp)]] * 4 -> 8 | L7: 16 | AB7: Additional time was required for analysis and to run application.
A8: =ROW() - ROW(Table1459678101112314151316[[#Headers],[S.No]]) -> 7 | B8: =Dashboard!$J$1 -> MCS | C8: 45800 | D8: 45813 | E8: MCS 25 - Sprint 11 Stretch | F8: Shriveni Baskaran | G8: 48104 | H8: MCS - ED - Custom Report Changes for Elk Grove | I8: Story Being Developed | J8: 5 | K8: =Table1459678101112314151316[[#This Row],[Estimated(hrs/sp)]] * 4 -> 20 | L8: 15
A9: =ROW() - ROW(Table1459678101112314151316[[#Headers],[S.No]]) -> 8 | B9: =Dashboard!$J$1 -> MCS | C9: 45800 | D9: 45813 | E9: MCS 25 - Sprint 11 Stretch | F9: Shriveni Baskaran/vaishnavi | G9: 47376 | H9: MCS - ED - Import Price Contract Update - Conflict resolution | I9: Defect Needs More Info | J9: 5 | K9: =Table1459678101112314151316[[#This Row],[Estimated(hrs/sp)]] * 4 -> 20 | L9: 33 | AB9: Started the development work , but I encountered few doubts during the initial phase, which I discussed with Ganesh. He informed me that I have the same doubts..one more refinement meeting is pending so we will check. As a result, the client has currently put the story on hold.

Sheet MCS 25 Sprint 11-Defects 
A1: S.No | B1: Sprint # | C1: Story/Defect ID | D1: Parent Story | E1: Developer | F1: Issue Type | G1: Issue Description | H1: Priority | I1: Defect Source | J1: Type | K1: Status | L1: Root Cause Category | M1: Comments

Sheet MCS 25 Sprint 10-Status
A1: S.No | B1: Application Name | C1: Sprint Start Date | D1: Sprint End Date | E1: Sprint | F1: Developer | G1: Story ID/Defect ID | H1: Description | I1: Status | J1: Estimated(hrs/sp) | K1: Actual(hrs/sp) | L1: Actual Hours (Worklog) | M1: Unit testing | N1: Peer Tested By | O1: Peer Tested Defects, if any | P1: Peer Reviewed By | Q1: Peer Code Review Comments, if any | R1: PR Number/Link | S1: PR Created Date | T1: Reviewer 1 | U1: PR Approved Date | V1: Code Review Comments, if any | W1: Reviewer 2 | X1: Approved Date | Y1: Code Review Comments, if any2 | Z1: Internal PO -POV Comments | AA1: Client PO -POV Comments | AB1: Comments | AC1: Column1
A2: 1 | B2: =Dashboard!$J$1 -> MCS | C2: 45786 | D2: 45799 | E2: MCS 25 - Sprint 10 Stretch | F2: vaishnavi | G2: 47496 | H2: MCS -- ED - Add Permissions for Ad-Hoc Inventory (PR - Billable) | I2: Story Being Tested | J2: 3 | K2: =Table14596781011123141513[[#This Row],[Estimated(hrs/sp)]] * 4 -> 12 | L2: 55 | M2: Done | Z2: N/A | AA2: New scenario added for upgrading db and creating new db | AB2: The development work was completed. During the development testing phase, a few blockers were encountered, which impacted progress. The initial POV was also completed, however, during the recent POV meeting, some new changes were identified. These changes were developed
A3: 2 | B3: MCS | C3: 45786 | D3: 45799 | E3: MCS 25 - Sprint 10 Stretch | F3: Hariharan | G3: 48013 | H3: MCS - ED - Add ability to schedule sending orders to vendor | I3: Product Owner - Verify | J3: 5 | K3: =Table14596781011123141513[[#This Row],[Estimated(hrs/sp)]] * 4 -> 20 | L3: 36 | M3: Done | N3: Ganesh | AB3: DEV is completed, Waiting for Josh to verify the Feature. Once done will raise a PR and move it forward for testing.
A4: 3 | B4: =Dashboard!$J$1 -> MCS | C4: 45786 | D4: 45799 | E4: MCS 25 - Sprint 10 Stretch | F4: Shriveni | G4: 47376 | H4: MCS - ED - Import Price Contract Update - Conflict resolution | I4: Story Being Developed | J4: 5 | K4: =Table14596781011123141513[[#This Row],[Estimated(hrs/sp)]] * 4 -> 20 | L4: 6

Sheet MCS 25 Sprint 10-Defects
A1: S.No | B1: Sprint # | C1: Story/Defect ID | D1: Parent Story | E1: Developer | F1: Issue Type | G1: Issue Description | H1: Priority | I1: Defect Source | J1: Type | K1: Status | L1: Root Cause Category | M1: Comments
B2: MCS 25 Sprint 10 | C2: 25163 | E2: Shriveni | F2: Defect | G2: MCS - POS - User-Defined Report is Truncating Generic SQL Queries - Newton | H2: Minor | I2: Manual | J2: External | K2: Defect Fixed | L2: Existing Issue | M2: Defect was tested and fixed.
B3: MCS 25 Sprint 10 | C3: 25217 | E3: Shriveni | F3: Defect | G3: MCS - POS - User-Defined Report is Truncating Generic SQL Queries -Edison | H3: Minor | I3: Manual | J3: External | K3: Defect Fixed | L3: Existing Issue | M3: Defect was tested and fixed.

Sheet MCS 25 Sprint 9-Status
A1: S.No | B1: Application Name | C1: Sprint Start Date | D1: Sprint End Date | E1: Sprint | F1: Developer | G1: Story ID/Defect ID | H1: Description | I1: Status | J1: Estimated(hrs/sp) | K1: Actual(hrs/sp) | L1: Actual Hours (Worklog) | M1: Unit testing | N1: Peer Tested By | O1: Peer Tested Defects, if any | P1: Peer Reviewed By | Q1: Peer Code Review Comments, if any | R1: PR Number/Link | S1: PR Created Date | T1: Reviewer 1 | U1: PR Approved Date | V1: Code Review Comments, if any | W1: Reviewer 2 | X1: Approved Date | Y1: Code Review Comments, if any2 | Z1: Internal PO -POV Comments | AA1: Client PO -POV Comments | AB1: Comments | AC1: Column1
A2: 1 | B2: =Dashboard!$J$1 -> MCS | C2: 45772 | D2: 45785 | E2: MCS25 - Sprint 9 Stretch | F2: vaishnavi | G2: 47496 | H2: MCS -- ED - Add Permissions for Ad-Hoc Inventory (PR - Billable) | I2: Story Being Developed | J2: 2 | K2: =Table1459678101112314[[#This Row],[Actual Hours (Worklog)]]/4 -> 8 | L2: =Table1459678101112314[[#This Row],[Estimated(hrs/sp)]] * 4 -> 32
A3: 2 | B3: =Dashboard!$J$1 -> MCS | C3: 45772 | D3: 45785 | E3: MCS25 - Sprint 9 Stretch | F3: Shriveni | G3: 48112 | H3: MSA(Web) - Bootstrap/WCAG - Admin Portal Testing | I3: Story Being Tested | J3: 5 | K3: =Table1459678101112314[[#This Row],[Actual Hours (Worklog)]]/4 -> 3 | L3: =Table1459678101112314[[#This Row],[Estimated(hrs/sp)]] * 4 -> 12 | AB3: Requires inputs from Andrea. Assigned the story to him.
A4: 3 | B4: =Dashboard!$J$1 -> MCS | C4: 45772 | D4: 45785 | E4: MCS25 - Sprint 9 | F4: Hariharan | G4: 23405 | H4: MCS - ED - No Serving Records Attached Using Bulk Editor | I4: Defect Fixed | J4: 2 | K4: 2 | L4: 8 | M4: Done | N4: Ganesh | O4: Nil | P4: Krish | Q4: Nil | R4: https://dev.azure.com/heartlandschools/MCS/_git/Edison/pullrequest/41818 | S4: 45768 | T4: Rudy | U4: 45770 | W4: Rudy | X4: 45770 | AB4: Defect was tested and fixed.
A5: 3 | B5: =Dashboard!$J$1 -> MCS | C5: 45772 | D5: 45785 | E5: MCS25 - Sprint 9 Stretch | F5: Hariharan | G5: 25054 | H5: Inventory used for production in bulk editor story Error | I5: Defect Peer Review | J5: 2 | K5: 5 | L5: 20 | M5: Done | N5: Ganesh | O5: Nil | P5: Krish | Q5: Nil | R5: https://dev.azure.com/heartlandschools/MCS/_git/Edison/pullrequest/42014 | S5: 45779 | T5: Rudy | V5: row.IssueBinder.builder and row.BuildProductionRecord must be the same | W5: Rudy | AB5: This was a existing defect, while fixing new ACs were added and completed this as a enhancement. Defect Ready for peer review state.
A6: 4 | B6: MCS | C6: 45772 | D6: 45785 | E6: MCS25 - Sprint 9 Stretch | F6: Hariharan | G6: 48013 | H6: MCS - ED - Add ability to schedule sending orders to vendor | I6: Story Being Developed | J6: 5 | K6: 5 | L6: 20 | AB6: This Story is a major enhancement (Including the agent service scheduler inside the windows app). Analysis for this story is completed and started to implement this. Will be carry forwarded to next sprint.

Sheet MCS 25 Sprint 9-Defects
A1: S.No | B1: Sprint # | C1: Story/Defect ID | D1: Parent Story | E1: Developer | F1: Issue Type | G1: Issue Description | H1: Priority | I1: Defect Source | J1: Type | K1: Status | L1: Root Cause Category | M1: Comments
B2: MCS 25 Sprint 9 | C2: 23405 | E2: Hariharan Dhandapani | F2: Defect | G2: MCS - ED - No Serving Records Attached Using Bulk Editor | H2: Minor | I2: Manual | J2: External | K2: Defect Fixed | L2: Existing Issue | M2: Defect was tested and fixed.
B3: MCS 25 Sprint 9 Stretch | C3: 25054 | E3: Hariharan Dhandapani | F3: Defect | G3: Inventory used for production in bulk editor story Error | H3: Minor | I3: Manual | J3: External | K3: Defect Peer Review | L3: Existing Issue | M3: This was a existing defect, while fixing new ACs were added and completed this as a enhancement. Defect Ready for peer review state.

Sheet MCS 25 Sprint 8-Status
A1: S.No | B1: Application Name | C1: Sprint Start Date | D1: Sprint End Date | E1: Sprint | F1: Developer | G1: Story ID/Defect ID | H1: Description | I1: Status | J1: Estimated(hrs/sp) | K1: Actual(hrs/sp) | L1: Actual Hours (Worklog) | M1: Unit testing | N1: Peer Tested By | O1: Peer Tested Defects, if any | P1: Peer Reviewed By | Q1: Peer Code Review Comments, if any | R1: PR Number/Link | S1: PR Created Date | T1: Reviewer 1 | U1: PR Approved Date | V1: Code Review Comments, if any | W1: Reviewer 2 | X1: Approved Date | Y1: Code Review Comments, if any2 | Z1: Internal PO -POV Comments | AA1: Client PO -POV Comments | AB1: Comments | AC1: Column1
A2: 1 | B2: =Dashboard!$J$1 -> MCS | C2: 45758 | D2: 45771 | E2: MCS 25 Sprint 8 | F2: Srini | G2: 47880 | H2: MCS - Cloud - (WAVE #68527) Modernize MCS : Migrate to SQLite | Newton POS Database Creation: Build SQLite DB with Schema | I2: Story Completed | J2: 8 | K2: =Table1459678101112314[[#This Row],[Actual Hours (Worklog)]]/4 -> 8 | L2: =Table1459678101112314[[#This Row],[Estimated(hrs/sp)]] * 4 -> 32
A3: 2 | B3: =Dashboard!$J$1 -> MCS | C3: 45758 | D3: 45771 | E3: MCS 25 Sprint 8 | F3: Srini | G3: 47576 | H3: MCS - Cloud - (WAVE #68527) Modernize MCS : Migrate from Vista DB to SQLite | Application Server | I3: Story Completed | J3: 3 | K3: =Table1459678101112314[[#This Row],[Actual Hours (Worklog)]]/4 -> 3 | L3: =Table1459678101112314[[#This Row],[Estimated(hrs/sp)]] * 4 -> 12
A4: 3 | B4: =Dashboard!$J$1 -> MCS | C4: 45758 | D4: 45771 | E4: MCS 25 Sprint 8 | F4: Krish | G4: 47774 | H4: MSA - Web - Update MSA to accept @globalpayments.sk | I4: Story Completed | J4: 1 | K4: =Table1459678101112314[[#This Row],[Actual Hours (Worklog)]]/4 -> 1 | L4: =Table1459678101112314[[#This Row],[Estimated(hrs/sp)]] * 4 -> 4 | M4: Done | N4: Hari | P4: Hari | R4: https://dev.azure.com/heartlandschools/MCS/_git/MySchoolApps/pullrequest/41724 | S4: 45761 | T4: Andrea | U4: 45761 | W4: Rudy | X4: 45761
A5: 4 | B5: =Dashboard!$J$1 -> MCS | C5: 45744 | D5: 45757 | E5: MCS25 - Sprint 8 Stretch | F5: Hari | G5: 23400 | H5: MCS - ED - Leftovers being set to zero when they are not zero when using Bulk Editor | I5: Defect Ready For Testing | J5: 3 | K5: =Table1459678101112314[[#This Row],[Actual Hours (Worklog)]]/4 -> 3 | L5: =Table1459678101112314[[#This Row],[Estimated(hrs/sp)]] * 4 -> 12 | M5: Done | N5: Ganesh | O5: Nil | P5: Krish | Q5: Nil | R5: https://dev.azure.com/heartlandschools/MCS/_git/Edison/pullrequest/41615 | S5: 45754 | T5: Rudy | U5: 45756 | W5: Rudy | X5: 45756 | AB5: Defect Ready for Testing. Will be carryforwarded to next sprint with new estimate for testing.
A6: 5 | B6: =Dashboard!$J$1 -> MCS | C6: 45758 | D6: 45771 | E6: MCS25 - Sprint 8 Stretch | F6: Sathish | G6: 47881 | H6: MCS - Cloud - (WAVE #68527) Modernize MCS : Migrate to SQLite | Transition to SQLite with Offline Database Creation Replacing Vista DB | I6: Story Being Developed | J6: 13 | K6: =Table1459678101112314[[#This Row],[Actual Hours (Worklog)]]/4 -> 12.5 | L6: 50
A7: 6 | B7: =Dashboard!$J$1 -> MCS | C7: 45758 | D7: 45771 | E7: MCS25 - Sprint 8 Stretch | F7: Kalai | G7: 47879 | H7: MCS - Cloud - (WAVE #68527) Modernize MCS : Migrate to SQLite | Create SQLite Upgrade Database and Segregate the Vista and SQLite DBAC | I7: Story Completed | J7: 13 | K7: =Table1459678101112314[[#This Row],[Actual Hours (Worklog)]]/4 -> 15 | L7: 60
A8: 7 | B8: =Dashboard!$J$1 -> MCS | C8: 45758 | D8: 45771 | E8: MCS25 - Sprint 8 Stretch | F8: Hari | G8: 23405 | H8: MCS - ED - No Serving Records Attached Using Bulk Editor | I8: Defect Ready For Testing | J8: 5 | K8: =Table1459678101112314[[#This Row],[Actual Hours (Worklog)]]/4 -> 5 | L8: =Table1459678101112314[[#This Row],[Estimated(hrs/sp)]] * 4 -> 20 | M8: Done | N8: Ganesh | O8: Nil | P8: Krish | Q8: Nil | R8: https://dev.azure.com/heartlandschools/MCS/_git/Edison/pullrequest/41818 | S8: 45768 | T8: Rudy | U8: 45770 | V8: add || row.IsPlannedTotalZero here. So all groups with missing Planned qty will be shown even if "Include Unplanned" checkbox is not checked | W8: Rudy | X8: 45770 | AB8: After the defect analysis, New Acs were added and did a enhancement to this functionality of the application. Defect Ready for Testing. Will be carryforwarded to next sprint with new estimate for testing.
A9: 8 | B9: =Dashboard!$J$1 -> MCS | C9: 45758 | D9: 45771 | E9: MCS 25 Sprint 8 | K9: =Table1459678101112314[[#This Row],[Actual Hours (Worklog)]]/4 -> 0 | L9: =Table1459678101112314[[#This Row],[Estimated(hrs/sp)]] * 4 -> 0

Sheet MCS 25 Sprint 8-Defects
A1: S.No | B1: Sprint # | C1: Story/Defect ID | D1: Parent Story | E1: Developer | F1: Issue Type | G1: Issue Description | H1: Priority | I1: Defect Source | J1: Type | K1: Status | L1: Root Cause Category | M1: Comments
B2: MCS 25 Sprint 8 Stretch | C2: 23400 | E2: Hariharan Dhandapani | F2: Defect | G2: 23400 MCS - ED - Leftovers being set to zero when they are not zero when using Bulk Editor | H2: Minor | I2: Manual | J2: External | K2: Defect Ready For Testing | L2: Existing Issue | M2: This is an existing Issue and has been fixed and Defect Ready for testing.
B3: MCS 25 Sprint 8 Stretch | C3: 23405 | E3: Hariharan Dhandapani | F3: Defect | G3: MCS - ED - No Serving Records Attached Using Bulk Editor | H3: Minor | I3: Manual | J3: External | K3: Defect Ready For Testing | L3: Existing Issue | M3: After the defect analysis, New Acs were added and did a enhancement to this functionality of the application. Defect Ready for Testing. Will be carryforwarded to next sprint with new estimate for testing.

Sheet MCS 25 Sprint 7-Status
A1: S.No | B1: Application Name | C1: Sprint Start Date | D1: Sprint End Date | E1: Sprint | F1: Developer | G1: Story ID/Defect ID | H1: Description | I1: Status | J1: Estimated(hrs/sp) | K1: Actual(hrs/sp) | L1: Actual Hours (Worklog) | M1: Unit testing | N1: Peer Tested By | O1: Peer Tested Defects, if any | P1: Peer Reviewed By | Q1: Peer Code Review Comments, if any | R1: PR Number/Link | S1: PR Created Date | T1: Reviewer 1 | U1: PR Approved Date | V1: Code Review Comments, if any | W1: Reviewer 2 | X1: Approved Date | Y1: Code Review Comments, if any2 | Z1: Internal PO -POV Comments | AA1: Client PO -POV Comments | AB1: Comments | AC1: Column1
A2: 1 | B2: =Dashboard!$J$1 -> MCS | C2: 45744 | D2: 45757 | E2: MCS 25 Sprint 7 | F2: Srini | G2: 47724 | H2: MCS - Cloud - (WAVE #68527) Modernize MCS : Migrate to SQLite | Analysis of Newton POS | I2: Story Completed | J2: 3 | K2: =(Table14596781011123[[#This Row],[Actual Hours (Worklog)]])/4 -> 12 | L2: 48 | N2: Patrick | O2: Nil | P2: Kalai | Q2: Nil
A3: 2 | B3: =Dashboard!$J$1 -> MCS | C3: 45744 | D3: 45757 | E3: MCS 25 Sprint 7 | F3: Srini | G3: 47725 | H3: MCS - Cloud - (WAVE #68527) Modernize MCS : Migrate to SQLite | Create SQLite db for Newton POS | I3: Story Completed | J3: 8 | K3: =(Table14596781011123[[#This Row],[Actual Hours (Worklog)]])/4 -> 12.5 | L3: 50 | N3: Patrick | O3: Nil | P3: Srini | Q3: Nil
A4: 3 | B4: =Dashboard!$J$1 -> MCS | C4: 45744 | D4: 45757 | E4: MCS 25 Sprint 7 | F4: Sathish | G4: 47576 | H4: MCS - Cloud - (WAVE #68527) Modernize MCS : Migrate from Vista DB to SQLite | Application Server | I4: Defect Ready For Testing | J4: 5 | K4: =(Table14596781011123[[#This Row],[Actual Hours (Worklog)]])/4 -> 8 | L4: 32 | M4: Done | N4: Patrick | O4: Nil | P4: Sathish | Q4: Nil | R4: https://dev.azure.com/heartlandschools/MCS/_git/MCSApplicationServer/pullrequest/41173 | S4: 45745 | T4: Patrick | U4: 45756 | AB4: We have created a build for the MCS Application Server and the Admin Console and Provided it to Farhath (Internal QA) to test the application from Vista Db to SQLite Migration.
A5: 4 | B5: =Dashboard!$J$1 -> MCS | C5: 45744 | D5: 45757 | E5: MCS 25 Sprint 7 | F5: Sathish / Kalai | G5: 47726 | H5: MCS - Cloud - (WAVE #68527) Modernize MCS : Migrate to SQLite | Migrate from VisaDB to SQLite for Newton POS | I5: Story Completed | J5: 8 | K5: =(Table14596781011123[[#This Row],[Actual Hours (Worklog)]])/4 -> 11.75 | L5: 47 | N5: Patrick | O5: Nil | P5: Srini | Q5: Nil
A6: 5 | B6: =Dashboard!$J$1 -> MCS | C6: 45744 | D6: 45757 | E6: MCS 25 Sprint 7 | F6: Krish | G6: 47721 | H6: MSA - Web- Bootstrap Migration - Admin - Audit Logs & Utilities | I6: Story Completed | J6: 2 | K6: 2 | L6: 10 | M6: Done | N6: Hari | O6: Nil | P6: Hari | Q6: Nil | R6: https://dev.azure.com/heartlandschools/MCS/_git/MySchoolApps/pullrequest/41522 | S6: 45747 | T6: Andrea | U6: 45748 | AB6: QA testing is not needed now. We need to fix the bootstrap issues in all modules. Once everything is fixed we need to test all pages.
A7: 6 | B7: =Dashboard!$J$1 -> MCS | C7: 45744 | D7: 45757 | E7: MCS 25 Sprint 7 | F7: Krish | G7: 47720 | H7: MSA - Web - Accessibility Changes required for WCAG 2.2 compliance - Admin Pages | I7: Story Completed | J7: 5 | K7: =(Table14596781011123[[#This Row],[Actual Hours (Worklog)]])/4 -> 10 | L7: 40 | M7: Done | N7: Hari | O7: Nil | P7: Hari | Q7: Nil | R7: https://dev.azure.com/heartlandschools/MCS/_git/MySchoolApps/pullrequest/41631 | S7: 45755 | T7: Andrea | U7: 45755 | AB7: QA testing is not needed now. We need to fix the bootstrap issues in all modules. Once everything is fixed we need to test all pages.
A8: 7 | B8: =Dashboard!$J$1 -> MCS | C8: 45744 | D8: 45757 | E8: MCS 25 Sprint 7 | F8: Hari | G8: 46619 | H8: MCS - POS - Replace System.Net.Mail with MailKit and enable OAuth2 for email | I8: Story Completed | J8: 5 | K8: =(Table14596781011123[[#This Row],[Actual Hours (Worklog)]])/4 -> 8 | L8: 32 | M8: Done | N8: Krish | O8: Nil | P8: Krish | Q8: Nil | R8: https://dev.azure.com/heartlandschools/MCS/_git/Newton/pullrequest/41326/ | S8: 45736 | T8: Patrick Dellinger | U8: 45741 | W8: Patrick Dellinger | X8: 45741 | Y8: Nil | AB8: Story Completed
A9: 8 | B9: =Dashboard!$J$1 -> MCS | C9: 45744 | D9: 45757 | E9: MCS 25 Sprint 7 - Stretch | F9: Hari | G9: 23400 | H9: MCS - ED - Leftovers being set to zero when they are not zero when using Bulk Editor | I9: Defect Ready For Testing | J9: 3 | K9: =(Table14596781011123[[#This Row],[Actual Hours (Worklog)]])/4 -> 5 | L9: 20 | M9: Done | N9: Ganesh | O9: Nil | P9: Krish | Q9: Nil | R9: https://dev.azure.com/heartlandschools/MCS/_git/Edison/pullrequest/41615 | S9: 45754 | T9: Rudy | U9: 45756 | W9: Rudy | X9: 45756 | Y9: The original Planned value is not tracked. Meal Planning UI should overwrite only unchanged Planned values conflicted Planned values | AB9: Defect Ready for Testing. Will be carryforwarded to next sprint with new estimate for testing. The Reason for CRC is after POV Josh added a new AC.
A10: 9 | B10: =Dashboard!$J$1 -> MCS | C10: 45744 | D10: 45757 | E10: MCS 25 Sprint 7 - Stretch | F10: Shriveni | G10: 47376 | H10: MCS - ED - Import Price Contract Update - Conflict resolution | I10: Story Being Developed | J10: 5 | K10: =(Table14596781011123[[#This Row],[Actual Hours (Worklog)]])/4 -> 8 | L10: 32 | M10: Done | N10: Hari | O10: Nil | P10: Hari | AB10: Since this is the first story for Shriveni in the Project that took additional time for analysis and development. In the Sprint Planning, Josh has some conflict with the ACs hence advised to hold this Story and will be discussed further and re-estimated in the refinement meeting.

Sheet MCS 25 Sprint 7-Defects
A1: S.No | B1: Sprint # | C1: Story/Defect ID | D1: Parent Story | E1: Developer | F1: Issue Type | G1: Issue Description | H1: Priority | I1: Defect Source | J1: Type | K1: Status | L1: Root Cause Category | M1: Comments
B2: MCS 25 Sprint 7 Stretch | C2: 23400 | E2: Hariharan Dhandapani | F2: Defect | G2: 23400 MCS - ED - Leftovers being set to zero when they are not zero when using Bulk Editor | H2: Minor | I2: Manual | J2: External | K2: Defect Ready For Testing | L2: Existing Issue | M2: This is an existing Issue and has been fixed and Defect Ready for testing.

Sheet MCS 25 Sprint 6-Status
A1: S.No | B1: Application Name | C1: Sprint Start Date | D1: Sprint End Date | E1: Sprint | F1: Developer | G1: Story ID/Defect ID | H1: Description | I1: Status | J1: Estimated(hrs/sp) | K1: Actual(hrs/sp) | L1: Actual Hours (Worklog) | M1: Unit testing | N1: Peer Tested By | O1: Peer Tested Defects, if any | P1: Peer Reviewed By | Q1: Peer Code Review Comments, if any | R1: PR Number/Link | S1: PR Created Date | T1: Reviewer 1 | U1: PR Approved Date | V1: Code Review Comments, if any | W1: Reviewer 2 | X1: Approved Date | Y1: Code Review Comments, if any2 | Z1: Internal PO -POV Comments | AA1: Client PO -POV Comments | AB1: Comments | AC1: Column1
A2: 1 | B2: =Dashboard!$J$1 -> MCS | C2: 45730 | D2: 45743 | E2: MCS 25 Sprint 6 | F2: Srini | G2: 47572 | H2: MCS - Cloud - (WAVE #68527) Modernize MCS : Migrate to SQLite | Application Tab | I2: Story Completed | J2: 5 | K2: 7 | L2: 28 | M2: Done | N2: Patrick | O2: fix this brace | P2: Kalai | R2: https://dev.azure.com/heartlandschools/MCS/_git/MCSApplicationServer/pullrequest/41173 | S2: 45727 | T2: Patrick | U2: 45742 | AB2: Development and unit test testing has been completed and created a pulled request and got approved by Patrick
A3: 2 | B3: =Dashboard!$J$1 -> MCS | C3: 45730 | D3: 45743 | E3: MCS 25 Sprint 6 | F3: Sathish | G3: 47573 | H3: MCS - Cloud - (WAVE #68527) Modernize MCS : Migrate to SQLite | Security Tab | I3: Story Completed | J3: 5 | K3: 8 | L3: 32 | M3: Done | N3: Patrick | O3: this should be an integer | P3: Srini | R3: https://dev.azure.com/heartlandschools/MCS/_git/MCSApplicationServer/pullrequest/41173 | S3: 45727 | T3: Patrick | U3: 45742 | AB3: Development and unit test testing has been completed and created a pulled request and got approved by Patrick
A4: 3 | B4: =Dashboard!$J$1 -> MCS | C4: 45730 | D4: 45743 | E4: MCS 25 Sprint 6 | F4: Kalai | G4: 47574 | H4: MCS - Cloud - (WAVE #68527) Modernize MCS : Migrate to SQLite | File & Server Admin Tab | I4: Story Completed | J4: 5 | K4: 7 | L4: 28 | M4: Done | N4: Patrick | O4: This code is redundant. Just use the ActiveDatabaseType and ActiveDatabaseName functions from AuthDB. Or move them here, since it makes more sense for them to live in the Parameter file anyway. | P4: Sathish | Q4: Assign parsed flavour into flavour variable to get the value globally | R4: https://dev.azure.com/heartlandschools/MCS/_git/MCSApplicationServer/pullrequest/41173 | S4: 45727 | T4: Patrick | U4: 45742 | AB4: Development and unit test testing has been completed and created a pulled request and got approved by Patrick
A5: 4 | B5: =Dashboard!$J$1 -> MCS | C5: 45730 | D5: 45743 | E5: MCS 25 Sprint 6 | F5: Sathish | G5: 47576 | H5: MCS - Cloud - (WAVE #68527) Modernize MCS : Migrate from Vista DB to SQLite | I5: Story Being Developed | J5: 8 | K5: 10 | L5: 40 | AB5: As, we took this ticket in the mid of the sprint, 100% analysis and requirement gathering for this ticket has been completed. 50% of the development has been completed. Negative Scenarios are yet to be developed. onsite team is fine to carry forward this story to the current sprint.
A6: 5 | B6: =Dashboard!$J$1 -> MCS | C6: 45730 | D6: 45743 | E6: MCS 25 Sprint 6 | F6: Srini / Kalai | G6: 47577 | H6: MCS - Cloud - (WAVE #68527) Modernize MCS : Migrate to SQLite | Analysis of Newton POS [Timebox] | I6: Story Completed | J6: 8 | K6: 11.5 | L6: 46 | AB6: Approach document has been created and need to discuss the flow with patrick. once got the approval will start working on the development.
A7: 6 | B7: =Dashboard!$J$1 -> MCS | C7: 45730 | D7: 45743 | E7: MCS 25 Sprint 6 | F7: Krish | G7: 47380 | H7: MSA - Web- Bootstrap Migration - Admin - District Page | I7: Story Completed | J7: 2 | K7: 2 | L7: 8 | M7: Done | N7: Krish | R7: https://dev.azure.com/heartlandschools/MCS/_git/MySchoolApps/pullrequest/41261 | S7: 45733 | T7: Andrea | U7: 45733 | AB7: QA testing is not needed now. We need to fix the bootstrap issues in all modules. Once everything is fixed we need to test all pages.
A8: 7 | B8: =Dashboard!$J$1 -> MCS | C8: 45730 | D8: 45743 | E8: MCS 25 Sprint 6 | F8: Krish | G8: 47381 | H8: MSA - Web- Bootstrap Migration - Admin - Schools Page | I8: Story Completed | J8: 2 | K8: 2 | L8: 8 | M8: Done | N8: Krish | R8: https://dev.azure.com/heartlandschools/MCS/_git/MySchoolApps/pullrequest/41261 | S8: 45733 | T8: Andrea | U8: 45733 | AB8: QA testing is not needed now. We need to fix the bootstrap issues in all modules. Once everything is fixed we need to test all pages.
A9: 8 | B9: =Dashboard!$J$1 -> MCS | C9: 45730 | D9: 45743 | E9: MCS 25 Sprint 6 | F9: Krish | G9: 47382 | H9: MSA - Web- Bootstrap Migration - Admin - Kiosks Page | I9: Story Completed | J9: 3 | K9: 3 | L9: 12 | M9: Done | N9: Krish | R9: https://dev.azure.com/heartlandschools/MCS/_git/MySchoolApps/pullrequest/41306 | S9: 45735 | T9: Andrea | U9: 45735
A10: 9 | B10: =Dashboard!$J$1 -> MCS | C10: 45730 | D10: 45743 | E10: MCS 25 Sprint 6 | F10: Krish | G10: 47383 | H10: MSA - Web- Bootstrap Migration - Admin - Reports Page | I10: Story Completed | J10: 3 | K10: 3 | L10: 12 | M10: Done | N10: Krish | R10: https://dev.azure.com/heartlandschools/MCS/_git/MySchoolApps/pullrequest/41306 | S10: 45735 | T10: Andrea | U10: 45735
A11: 10 | B11: =Dashboard!$J$1 -> MCS | C11: 45730 | D11: 45743 | E11: MCS 25 Sprint 6 | F11: Krish | G11: 47384 | H11: MSA - Web- Bootstrap Migration - Admin - Setup Page | I11: Story Completed | J11: 3 | K11: 3 | L11: 12 | M11: Done | N11: Krish | R11: https://dev.azure.com/heartlandschools/MCS/_git/MySchoolApps/pullrequest/41392 | S11: 45741 | T11: Andrea | U11: 45741
A12: 11 | B12: =Dashboard!$J$1 -> MCS | C12: 45730 | D12: 45743 | E12: MCS 25 Sprint 6 | F12: Hari | G12: 47120 | H12: MCS - ED - Generate Recipe field in Item Importer - Part 2 | I12: Story Ready For Testing | J12: 3 | M12: Done | N12: Ganesh | P12: Krish | R12: https://dev.azure.com/heartlandschools/MCS/_git/Edison/pullrequest/41196 | S12: 45728 | T12: Rudy Svaby | U12: 45729 | X12: 45729 | AB12: Testing is on Hold as testers dont have bandwidth in this Sprint to test it. Carry forwarded to the Next Sprint
A13: 12 | B13: =Dashboard!$J$1 -> MCS | C13: 45730 | D13: 45743 | E13: MCS 25 Sprint 6 | F13: Hari | G13: 46563 | H13: MCS - FR - Replace System.Net.Mail with MailKit and enable OAuth2 for email | I13: Story Completed | J13: 3 | K13: 3 | L13: 12 | M13: Done | N13: Ganesh | O13: Nil | P13: Krish | Q13: Nil | R13: https://dev.azure.com/heartlandschools/MCS/_git/MCSLib/pullrequest/40432 https://dev.azure.com/heartlandschools/MCS/_git/Franklin/pullrequest/40430 | S13: 45680 | T13: Patrick Dellinger | U13: 45712 | W13: Patrick Dellinger | X13: 45712 | Y13: Nil | AB13: New AC Changes were completed and tested in this Sprint. Story Completed.
A14: 13 | B14: =Dashboard!$J$1 -> MCS | C14: 45730 | D14: 45743 | E14: MCS 25 Sprint 6 - Stretch | F14: Hari | G14: 20939 | H14: MCS - ED - Recipes showing 47.25 tsp instead of converting to cups | I14: Defect Needs More Info | J14: 3 | K14: 5 | L14: 20 | AB14: Shared our analysis with Josh 03/19/25, since he is OOO we unable to connect with him and dervie the solution for the same. Story is on hold as Josh needs some inputs from nutrition Team, hence kept on hold and moved to backlog
A15: 14 | B15: =Dashboard!$J$1 -> MCS | C15: 45730 | D15: 45743 | E15: MCS 25 Sprint 6 | F15: Hari | G15: 46619 | H15: MCS - POS - Replace System.Net.Mail with MailKit and enable OAuth2 for email | I15: Story Ready For Testing | J15: 3 | K15: 5 | L15: 20 | M15: Done | N15: Krish | O15: Nil | P15: Krish | Q15: Nil | R15: https://dev.azure.com/heartlandschools/MCS/_git/Newton/pullrequest/41326 | S15: 45736 | T15: Patrick Dellinger | U15: 45741 | V15: I forgot to mention this during the FR story, but I don't expect this to work. It depends on how its configured and coded, but I expect the browser window to need to successfully load a webpage to be able to retrieve the token it needs. So how is this working, and will it work on a customer's machine? Also how was this tested? | W15: Patrick Dellinger | X15: 45741 | Y15: Nil | AB15: DEV is completed and story is ready for testing. Required additional DEV effort to complete this story, Testing effort will be re-esitmated and carry forwarded to the next sprint.
A16: 15 | B16: MCS | C16: 45730 | D16: 45743 | E16: MCS 25 Sprint 6 | F16: Dinesh | G16: 47674 | H16: MCS - ED - Price Contract Import Enhancements | I16: Story Completed | J16: 1 | K16: 1 | L16: 4 | M16: Done | N16: Ganesh | O16: Nil | P16: Hari | Q16: Nil | R16: https://dev.azure.com/heartlandschools/MCS/_git/Edison/pullrequest/41244 | T16: Rudy Svaby | AB16: Its is enhancement story code changes are done committed to the branch.Testing will happen along with #45301

Sheet MCS 25 Sprint 6-Defects
A1: S.No | B1: Sprint # | C1: Story/Defect ID | D1: Parent Story | E1: Developer | F1: Issue Type | G1: Issue Description | H1: Priority | I1: Defect Source | J1: Type | K1: Status | L1: Root Cause Category | M1: Comments
B2: MCS 25 Sprint 6 Stretch | C2: 20939 | E2: Hariharan Dhandapani | F2: Defect | G2: MCS - ED - Recipes showing 47.25 tsp instead of converting to cups | H2: Minor | I2: Manual | J2: External | K2: Defect Needs More Info | L2: Existing Issue | M2: Shared our analysis with Josh 03/19/25, since he is OOO we unable to connect with him and dervie the solution for the same. Story is on hold as Josh needs some inputs from nutrition Team, hence kept on hold and moved to backlog

Sheet MCS 25 Sprint 5-Status
A1: S.No | B1: Application Name | C1: Sprint Start Date | D1: Sprint End Date | E1: Sprint | F1: Developer | G1: Story ID/Defect ID | H1: Description | I1: Status | J1: Estimated(hrs/sp) | K1: Actual(hrs/sp) | L1: Actual Hours (Worklog) | M1: Unit testing | N1: Peer Tested By | O1: Peer Tested Defects, if any | P1: Peer Reviewed By | Q1: Peer Code Review Comments, if any | R1: PR Number/Link | S1: PR Created Date | T1: Reviewer 1 | U1: PR Approved Date | V1: Code Review Comments, if any | W1: Reviewer 2 | X1: Approved Date | Y1: Code Review Comments, if any2 | Z1: Internal PO -POV Comments | AA1: Client PO -POV Comments | AB1: Comments | AC1: Column1
A2: 1 | B2: =Dashboard!$J$1 -> MCS | C2: 45716 | D2: 45729 | E2: MCS 25 Sprint 5 | F2: Boobalakrishnan Ramasamy | G2: 47378 | H2: MSA - Web- Bootstrap Migration - Admin - Log In Page | I2: Story Completed | J2: 2 | K2: 2 | L2: 12 | M2: Done | N2: Krish | P2: Ganesh | R2: https://dev.azure.com/heartlandschools/MCS/_git/MySchoolApps/pullrequest/41072 | S2: 45720 | T2: Andrea | U2: 45720 | AB2: QA testing is not needed now. We need to fix the bootstrap issues in all modules. Once everything is fixed we need to test all pages.
A3: 2 | B3: =Dashboard!$J$1 -> MCS | C3: 45716 | D3: 45729 | E3: MCS 25 Sprint 5 | F3: Boobalakrishnan Ramasamy | G3: 47379 | H3: MSA - Web- Bootstrap Migration - Admin - User Page | I3: Story Completed | J3: 3 | K3: 3 | L3: 15 | M3: Done | N3: Krish | R3: https://dev.azure.com/heartlandschools/MCS/_git/MySchoolApps/pullrequest/41141 | S3: 45723 | T3: Andrea | U3: 45723 | AB3: QA testing is not needed now. We need to fix the bootstrap issues in all modules. Once everything is fixed we need to test all pages.
A4: 3 | B4: =Dashboard!$J$1 -> MCS | C4: 45716 | D4: 45729 | E4: MCS 25 Sprint 5 | F4: Boobalakrishnan Ramasamy | G4: 47385 | H4: MSA - Web - Accessibility Changes required for WCAG 2.2 compliance - Home Page & Application Page | I4: Story Completed | J4: 3 | K4: 3 | L4: 25 | M4: Done | N4: Krish | R4: https://dev.azure.com/heartlandschools/MCS/_git/MySchoolApps/pullrequest/41191 | S4: 45727 | T4: Andrea | U4: 45728 | AB4: QA testing is not needed now. We need to fix the bootstrap issues in all modules. Once everything is fixed we need to test all pages.
A5: 4 | B5: =Dashboard!$J$1 -> MCS | C5: 45716 | D5: 45729 | E5: MCS 25 Sprint 5 | F5: Hariharan Dhandapani | G5: 47120 | H5: MCS - ED - Generate Recipe field in Item Importer - Part 2 | I5: Story Ready For Testing | J5: 3 | K5: 3 | L5: 16 | M5: Done | N5: Ganesh | P5: Krish | R5: https://dev.azure.com/heartlandschools/MCS/_git/Edison/pullrequest/41196 | S5: 45728 | T5: Rudy Svaby | U5: 45729 | V5: 1. When we will use DBItems.Cache.TryGetCatalogNumberInfo, this will not be needed anymore | X5: 45729 | AB5: Testing effor for this story is still pending, hence will be re-estimated and moved to the next sprint.
A6: 5 | B6: =Dashboard!$J$1 -> MCS | C6: 45716 | D6: 45729 | E6: MCS 25 Sprint 5 Stretch | F6: Hariharan Dhandapani | G6: 20939 | H6: MCS - ED - Recipes showing 47.25 tsp instead of converting to cups | I6: Defect Being Fixed | J6: 5 | K6: 5 | L6: 20 | AB6: We had a discussion with the nutrition team, along with Josh and Ganesh, and concluded that we need to analyze all the cases within our system to understand how it behaves for all measurement values and their conversion. As a result, we will need more effort for this story, which will be reestimated and carried forward to the next sprint.
A7: 6 | B7: =Dashboard!$J$1 -> MCS | C7: 45716 | D7: 45729 | E7: MCS 25 Sprint 5 | F7: Hariharan Dhandapani | G7: 46563 | H7: MCS - FR - Replace System.Net.Mail with MailKit and enable OAuth2 for email | I7: Story Being Tested | J7: 3 | K7: 3 | L7: 12 | M7: Done | N7: Ganesh | O7: Nil | P7: Boobalakrishnan | Q7: Nil | R7: https://dev.azure.com/heartlandschools/MCS/_git/MCSLib/pullrequest/40432 https://dev.azure.com/heartlandschools/MCS/_git/Franklin/pullrequest/40430 | S7: 45680 | T7: Patrick Dellinger | U7: 45712 | V7: I do like your Helpers.CreateEmailMessage though. I think you should improve the code within the Helpers class, by adding your own Email class that wraps this functionality. Then, this code would look something like: | W7: Patrick Dellinger | X7: 45712 | Y7: Nil | AB7: Story is Being tested and estimated again as 2SP and carry forwarded to next sprint.
A8: 7 | B8: =Dashboard!$J$1 -> MCS | C8: 45716 | D8: 45729 | E8: MCS 25 Sprint 5 Stretch | F8: Dineshkumar Sathasivam | G8: 47346 | H8: MCS - ED - Import new items in price contract import | I8: Story Completed | J8: 3 | K8: 3 | L8: 12 | M8: Done | N8: Ganesh | O8: Nil | P8: Hariharan | Q8: Usage Of DBNull.value should be replaced with some other valid conditions | R8: https://dev.azure.com/heartlandschools/MCS/_git/Edison/pullrequest/41244 | S8: 45733 | T8: Rudy Svaby | U8: 45733 | V8: Fix the catalog number picker button. | W8: Rudy Svaby | X8: 45733 | Z8: ACs met the expectations and POV verified successfully. | AA8: ACs met the expectations and POV verified successfully. | AB8: The feature developement is completed and completed POV. Client added two more features to the AC's and AC is updated during POV. It took additional time of 2SP for development and it is completed and POV is verified. Demonstrated to the client successfully during sprint review. PR will be created after demo. Creating PR may cause issue in DB restortion during sprint review.Code review was done in branch commit. PR is cretaed after demo.
A9: 8 | B9: =Dashboard!$J$1 -> MCS | C9: 45716 | D9: 45729 | E9: MCS 25 Sprint 5 | F9: Kalaivani | G9: 47414 | H9: MCS - Cloud - (WAVE #68527) Modernize MCS : Migrate to SQLite | File & Server Admin Tab | I9: Story Completed | J9: 8 | K9: 8 | L9: 32 | M9: Done | N9: Srini | O9: Nil | P9: Srini | Q9: Nil | R9: Pull request 41173: [axof:47240] Being SQLite Support - Repos | S9: 45727 | T9: Patrick | V9: This will not return a usable path | AB9: All the important stuff looks pretty good so far. There are just some style tweaks needed
A10: 9 | B10: =Dashboard!$J$1 -> MCS | C10: 45716 | D10: 45729 | E10: MCS 25 Sprint 5 | F10: Srinivasu | G10: 47398 | H10: MCS - Cloud - (WAVE #68527) Modernize MCS : Migrate to SQLite | Application Tab | I10: Story Completed | J10: 8 | K10: 8 | L10: 32 | M10: Done | N10: Sathish | O10: Nil | P10: Sathish | Q10: Nil | R10: Pull request 41173: [axof:47240] Being SQLite Support - Repos | S10: 45727 | T10: Patrick | V10: instead of all this, let's just use one setting, called DatabaseType, which will correspond to the DatabaseType enum. The names will be hardcoded. | AB10: All the important stuff looks pretty good so far. . Given the Suggession for a better understanding
A11: 10 | B11: =Dashboard!$J$1 -> MCS | C11: 45716 | D11: 45729 | E11: MCS 25 Sprint 5 | F11: SathishKumar | G11: 47413 | H11: MCS - Cloud - (WAVE #68527) Modernize MCS : Migrate to SQLite | Security Tab | I11: Story Completed | J11: 8 | K11: 8 | L11: 32 | M11: Done | N11: Kalai | O11: Nil | P11: Kalai | Q11: Nil | R11: Pull request 41173: [axof:47240] Being SQLite Support - Repos | S11: 45727 | T11: Patrick | V11: These should be in PascalCase | AB11: All the important stuff looks pretty good so far. A minor case sensitive change

Sheet MCS 25 Sprint 5-Defects
A1: S.No | B1: Sprint # | C1: Story/Defect ID | D1: Parent Story | E1: Developer | F1: Issue Type | G1: Issue Description | H1: Priority | I1: Defect Source | J1: Type | K1: Status | L1: Root Cause Category | M1: Comments
B2: MCS 25 Sprint 5 Stretch | C2: 20939 | E2: Hariharan Dhandapani | F2: Defect | G2: MCS - ED - Recipes showing 47.25 tsp instead of converting to cups | H2: Minor | I2: Manual | J2: External | K2: Defect Being Fixed | L2: Existing Issue | M2: We had a discussion with the nutrition team, along with Josh and Ganesh, and concluded that we need to analyze all the cases within our system to understand how it behaves for all measurement values and their conversion. As a result, we will need more effort for this story, which will be reestimated and carried forward to the next sprint.

Sheet MCS 25 Sprint 4-Status
A1: S.No | B1: Application Name | C1: Sprint Start Date | D1: Sprint End Date | E1: Sprint | F1: Developer | G1: Story ID/Defect ID | H1: Description | I1: Status | J1: Estimated(hrs/sp) | K1: Actual(hrs/sp) | L1: Actual Hours (Worklog) | M1: Unit testing | N1: Peer Tested By | O1: Peer Tested Defects, if any | P1: Peer Reviewed By | Q1: Peer Code Review Comments, if any | R1: PR Number/Link | S1: PR Created Date | T1: Reviewer 1 | U1: PR Approved Date | V1: Code Review Comments, if any | W1: Reviewer 2 | X1: Approved Date | Y1: Code Review Comments, if any2 | Z1: Internal PO -POV Comments | AA1: Client PO -POV Comments | AB1: Comments | AC1: Column1
A2: 1 | B2: =Dashboard!$J$1 -> MCS | C2: 45702 | D2: 45715 | E2: MCS 25 Sprint 4 | F2: Boobalakrishnan Ramasamy | G2: 46615 | H2: MCS - MSA(web) - Determine Scope of Accessibility Changes Required for 2.2 Compliance | I2: Story Completed | J2: 2 | K2: 2 | M2: Done | N2: Krish | P2: Ganesh | R2: https://docs.google.com/spreadsheets/d/1ZKzwseHgtzP5o5iA1lSu_zehVAY2B_lA-sDGi_n7Bjw/edit?gid=417185395#gid=417185395 | S2: 45705
A3: 2 | B3: =Dashboard!$J$1 -> MCS | C3: 45702 | D3: 45715 | E3: MCS 25 Sprint 4 Stretch | F3: Boobalakrishnan Ramasamy | G3: 47185 | H3: MSA - Web- Bootstrap Migration - Home Page | I3: Story Completed | J3: 3 | K3: 3 | M3: Done | N3: Krish | P3: Andrea | R3: https://dev.azure.com/heartlandschools/MCS/_git/MySchoolApps/pullrequest/40747 | S3: 45700 | T3: Andrea | U3: 45702 | V3: Nil | AB3: QA testing is not needed now. We need to fix the bootstrap issues in all modules. Once everything is fixed we need to test all pages.
A4: 3 | B4: =Dashboard!$J$1 -> MCS | C4: 45702 | D4: 45715 | E4: MCS 25 Sprint 4 Stretch | F4: Boobalakrishnan Ramasamy | G4: 47186 | H4: MSA - Web- Bootstrap Migration - Application Creation Page | I4: Story Completed | J4: 5 | K4: 5 | M4: Done | N4: Krish | R4: https://dev.azure.com/heartlandschools/MCS/_git/MySchoolApps/pullrequest/40879 | S4: 45708 | T4: Andrea | U4: 45709 | V4: Nil | AB4: QA testing is not needed now. We need to fix the bootstrap issues in all modules. Once everything is fixed we need to test all pages.
A5: 4 | B5: MCS-Wave | C5: 45702 | D5: 45715 | E5: MCS 25 Sprint 4 Stretch | F5: Kalai / Srini / Sathish/Farhath | G5: 47240 | H5: MCS - Cloud - Modernize MCS (initiative #68527): Migrate MCS Application Server to SQLite | (Timebox) | I5: Story Completed | J5: 13 | K5: 58.5 | L5: 234 | AB5: We have completed the Admin console code changes related to SQLite and started to work on the LibDatabase , MCSApplicationServer, and SQLite Database. Its in Progress. What ever we did related to SQLIte changes we have checked in the code in Azure Devops and reviewed by Patrick.
A6: 5 | B6: =Dashboard!$J$1 -> MCS | C6: 45702 | D6: 45715 | E6: MCS 25 Sprint 4 Stretch | F6: Dineshkumar Sathasivam | G6: 21529 | H6: MCS - ED - Named Site Filter randomly not including newly added sites | I6: Defect Fixed | J6: 1 | K6: 1 | M6: Done | N6: Ganesh | O6: Nil | P6: Hariharan | Q6: Logic change for SP @force shoud be revisited. | R6: It is DB script change so no PR is required | T6: Rudy Svalby | V6: Nil | Y6: Nil | Z6: Nil | AA6: Nil | AB6: Root causse is found and it is fixed and while reviewing the code it is found that there may be issue in the district Database itself and so I have brought this up to Patrick and he is going to contact the district admin about the database issue. As of now they are going to fix the issue with script change provide by us. Defect is fixed.
A7: 6 | B7: =Dashboard!$J$1 -> MCS | C7: 45702 | D7: 45715 | E7: MCS 25 Sprint 4 | F7: Hariharan Dhandapani | G7: 46563 | H7: MCS - FR - Replace System.Net.Mail with MailKit and enable OAuth2 for email | I7: Story Being Tested | J7: 2 | K7: 2 | L7: 8 | M7: Done | N7: Ganesh | O7: Nil | P7: Boobalakrishnan | Q7: Nil | R7: https://dev.azure.com/heartlandschools/MCS/_git/MCSLib/pullrequest/40432 https://dev.azure.com/heartlandschools/MCS/_git/Franklin/pullrequest/40430 | S7: 45680 | T7: Patrick Dellinger | U7: 45712 | V7: I do like your Helpers.CreateEmailMessage though. I think you should improve the code within the Helpers class, by adding your own Email class that wraps this functionality. Then, this code would look something like: | W7: Patrick Dellinger | X7: 45712 | Y7: Nil | AB7: Again Added a New AC for using Local Pickup Directory logic. Which Involved 2SP Dev effort in this sprint. The Story is now moved to Testing again. Remaining Testing of 3SP effort will be carry forwarded to the next sprint.
A8: 7 | B8: =Dashboard!$J$1 -> MCS | C8: 45702 | D8: 45715 | E8: MCS 25 Sprint 4 | F8: Hariharan Dhandapani | G8: 47119 | H8: MCS - ED - Single Item Recipe field in Item Importer - I | I8: Story Completed | J8: 3 | K8: 3 | L8: 12 | M8: Done | N8: Ganesh | O8: Nil | P8: Rudy | Q8: Nil | R8: https://dev.azure.com/heartlandschools/MCS/_git/Edison/pullrequest/40776 | S8: 45702 | T8: Rudy Svalby | U8: 45708 | V8: Nil | W8: Patrick Dellinger | Y8: Nil | AB8: Story Completed.
A9: 8 | B9: =Dashboard!$J$1 -> MCS | C9: 45702 | D9: 45715 | E9: MCS 25 Sprint 4 | F9: Hariharan Dhandapani | G9: 47120 | H9: MCS - ED - Single Item Recipe field in Item Importer - II | I9: Product Owner - Verify | J9: 5 | L9: 20 | AB9: DEV Effort of 5SP completed will be having POV session on 02/28. Once POV completed will raise PR and move to testing Testing effort of 3 SP is re-estimated and carry forwarded for testing to next sprint.

Sheet MCS 25 Sprint 4-Defects
A1: S.No | B1: Sprint # | C1: Story/Defect ID | D1: Parent Story | E1: Developer | F1: Issue Type | G1: Issue Description | H1: Priority | I1: Defect Source | J1: Type | K1: Status | L1: Root Cause Category | M1: Comments
B2: MCS Sprint 4 | C2: 21529 | E2: Dineshkumar Sathasivam | F2: Defect | G2: When adding new sites to Edison, sometimes Named Site Filters (system defined or custom) will not update to include the newly added site when it should be included. | H2: Minor | I2: Manual | J2: Internal | K2: Defect Fixed | L2: Existing Issue | M2: This is Client Development Root causse is found and it is fixed. As of now they are going fix the issue with script change provide by us. Defect is fixed as of now. (Store Procedure Script) It is fixed in the PROD

Sheet MCS 25 Sprint 3-Status
A1: S.No | B1: Application Name | C1: Sprint Start Date | D1: Sprint End Date | E1: Sprint | F1: Developer | G1: Story ID/Defect ID | H1: Description | I1: Status | J1: Estimated(hrs/sp) | K1: Actual(hrs/sp) | L1: Actual Hours (Worklog) | M1: Unit testing | N1: Peer Tested By | O1: Peer Tested Defects, if any | P1: Peer Reviewed By | Q1: Peer Code Review Comments, if any | R1: PR Number/Link | S1: PR Created Date | T1: Reviewer 1 | U1: PR Approved Date | V1: Code Review Comments, if any | W1: Reviewer 2 | X1: Approved Date | Y1: Code Review Comments, if any2 | Z1: Internal PO -POV Comments | AA1: Client PO -POV Comments | AB1: Comments
