Workbook

Sheet Dashboard
A1: Current Sprint | B1: {=INDEX($B$2:$B$101,MATCH(1,(($D$2:$D$101 >=TODAY())*($C$2:$C$101<=TODAY())),0))} -> 2.5 KaleidaNutrition S24 | C1: Current Sprint Sheet | D1: =CONCATENATE(B1,"-Status") -> 2.5 KaleidaNutrition S24-Status | E1: Sprint Start Date | F1: =VLOOKUP($B$1,$B$1:$C$101,2) -> 46157 | G1: Sprint End Date | H1: =VLOOKUP($B$1,$B$1:$D$101,3) -> 46170 | I1: Application Name | J1: Meal Order | K1: Users | L1: charu.sharma@relevantz.com;kiruthiga.ganapathi@relevantz.com;sudheer.dokku@relevantz.com;rubansanthosh.stephen@relevantz.com;karthikeyan.elumalai@relevantz.com;vidhya.subramaniam@relevantz.com;ganesh.veerannan@relevantz.com;shikha.p@relevantz.com;nathiya.palanisamy@relevantz.com | M1: Teams Name(GP -Meal Orders) | N1: 19:33c225e109bb48d58dd1e9a89b0261a7@thread.v2
A2: Sprint Type | B2: Sprint # | C2: Sprint Start Date | D2: Sprint End Date | E2: Assigned | F2: Completed | G2: Story points introduced/removed | H2: Sprint Summary | I2: Accomplishments | J2: Remarks | K2: Retro Points (Internal & External) | L2: Unplanned Leaves | M2: Data sanity Audit Status | N2: AuditDate | O2: Backlog Health
A3: =IF(AND($D$1>=C3,$D$1<=D3),"CurrentSprint","NA") -> NA | B3: 1.8 Sprint 3 | C3: 45303 | D3: 45316 | E3: 27 | F3: 29 | G3: 0 | J3: Regression Sprint - Release 1/2/2024 In addition completed one stretch story (2 sp). | K3: Internal: External:
A4: =IF(AND($D$1>=C4,$D$1<=D4),"CurrentSprint","NA") -> NA | B4: 1.9 Sprint 1 | C4: 45317 | D4: 45330 | E4: 25 | F4: 33 | G4: 0 | J4: New Version 1.9 - One Story from Stretch and Two defects from the Stretch was completed One Story was carry-forward due to additional AC after completing the story | K4: Internal: External:
A5: =IF(AND($D$1>=C5,$D$1<=D5),"CurrentSprint","NA") -> NA | B5: 1.9 Sprint 2 | C5: 45331 | D5: 45344 | E5: 22 | F5: 30 | G5: 0 | J5: Ruban will be unavailable for the next three weeks, Compensating the 8sp with a 9sp from stretch (since the 8sp couldn't be completed as it involves more effort). Refer to story number 40282 for more info | K5: Internal: External:
A6: =IF(AND($D$1>=C6,$D$1<=D6),"CurrentSprint","NA") -> NA | B6: 1.9 Sprint 3 | C6: 45345 | D6: 45358 | E6: 19 | F6: 19 | G6: 0 | J6: Ruban will be unavailable for the first half of the Sprint. Addition to this, development completed for 2 stretch stories and testing is in progress. | K6: Internal: External:
A7: =IF(AND($D$1>=C7,$D$1<=D7),"CurrentSprint","NA") -> NA | B7: 1.9 Sprint 4 | C7: 45359 | D7: 45372 | E7: 37 | F7: =40+13 -> 53 | G7: 0 | J7: Regression Sprint -- Release Targeted on March 20, 21 (Cert, Prod) | K7: Internal: External:
A8: =IF(AND($D$1>=C8,$D$1<=D8),"CurrentSprint","NA") -> NA | B8: 2.0 Sprint 1 | C8: 45373 | D8: 45386 | E8: 11 | F8: 29 | G8: 18SP | J8: New Version - Commit has Two Project Unite Discovery Stories for Clients (13+13) Relevantz has 4 Defects and 1 Story in the Commit | K8: Internal: External:
A9: =IF(AND($D$1>=C9,$D$1<=D9),"CurrentSprint","NA") -> NA | B9: 2.0 Sprint 2 | C9: 45387 | D9: 45400 | E9: 15 | F9: 36 | G9: 21SP | J9: Relevantz has 2 Stories and 1 Defects in the Commit. Relevantz completed 2 Commit Stories, 1 Commit Defect and 4 Stretch Stories | K9: Internal: External:
A10: =IF(AND($D$1>=C10,$D$1<=D10),"CurrentSprint","NA") -> NA | B10: 2.0 Sprint 3 | C10: 45401 | D10: 45414 | E10: 13 | F10: 18 | G10: 10SP | J10: Due to scope change one main commit story spilled over.ST #44162 | K10: Internal: External:
A11: =IF(AND($D$1>=C11,$D$1<=D11),"CurrentSprint","NA") -> NA | B11: 2.0 Sprint 4 | C11: 45415 | D11: 45428 | E11: 10 | F11: 22 | G11: 12SP | J11: Completed more than committed Completed - 2 Commit Stories and 4 Stretch Stories and 3 Stories are Code Completed and in PR | K11: Internal: External:
A12: =IF(AND($D$1>=C12,$D$1<=D12),"CurrentSprint","NA") -> NA | B12: 2.0 Sprint 5 | C12: 45429 | D12: 45442 | E12: 12 | F12: 16 | G12: 4SP | J12: We had additional requirements, requests and enhancements from the Client after the POV (New AC) Completed Dev in a short period targeting release and release goal Found one Critical issue in the Prod and gave fix on the same day and had release on the next day | K12: Internal: External:
A13: =IF(AND($D$1>=C13,$D$1<=D13),"CurrentSprint","NA") -> NA | B13: 2.0 Sprint 6 | C13: 45443 | D13: 45456 | E13: 13 | F13: 17 | G13: Introduced - 18SP Removed - 9SP | J13: Release Goal have been changed. So new requirement has been captured and the team is currently working on that. Reason - A New Schedule Printer is needed. On going Progress Hot-fix for Order Price Mismatch | K13: Internal: External:
A14: =IF(AND($D$1>=C14,$D$1<=D14),"CurrentSprint","NA") -> NA | B14: 2.0 Sprint 7 | C14: 45457 | D14: 45470 | E14: 34 | F14: 18 | J14: The Stories commited are new requirment which is different from the release goal. Completed two reports fully. The Third report is in progress (UI Completed) | K14: Internal: External:
A15: =IF(AND($D$1>=C15,$D$1<=D15),"CurrentSprint","NA") -> NA | B15: 2.0 Sprint 8 | C15: 45471 | D15: 45484 | E15: 39 | F15: 26 | J15: Regression Sprint Order Receipts was carry forwarded (Dev Completed) | K15: Internal: External:
A16: =IF(AND($D$1>=C16,$D$1<=D16),"CurrentSprint","NA") -> NA | B16: 2.1 | K16: Internal: External:
A17: =IF(AND($D$1>=C17,$D$1<=D17),"CurrentSprint","NA") -> NA | B17: 2.1 Sprint 1 | C17: 45485 | D17: 45498 | E17: 25 | F17: 30 | G17: 5 | J17: The Release was in mid sprint, the team started to work on Prod Defects and Stock Management by Sarath. Ruban and Kiruthiga are working on finding solution for Cloud Print (Automatic Receipt Scheduler) | K17: Internal: External:
A18: =IF(AND($D$1>=C18,$D$1<=D18),"CurrentSprint","NA") -> NA | B18: 2.1 Sprint 2 | C18: 45499 | D18: 45512 | E18: 13 | F18: 24 | G18: 11 | J18: Receipt Scheduler will be on hold until we find a feasible approach. Will be moving to 2.2 Release. | K18: Internal: External:
A19: =IF(AND($D$1>=C19,$D$1<=D19),"CurrentSprint","NA") -> NA | B19: 2.1 Sprint 3 | C19: 45513 | D19: 45526 | E19: 14 | F19: 20 | G19: 6 | J19: Targeting Stock Management, NSLP and Defect Clean up
A20: =IF(AND($D$1>=C20,$D$1<=D20),"CurrentSprint","NA") -> NA | B20: 2.1 Sprint 4 | C20: 45527 | D20: 45540 | E20: 33 | F20: 20 | G20: Removed - 13 | J20: The Stories are carry forwarded for Admin Integration with Individual and Teacher Ordering
A21: =IF(AND($D$1>=C21,$D$1<=D21),"CurrentSprint","NA") -> NA | B21: 2.1 Sprint 5 | C21: 45541 | D21: 45554 | E21: 38 | F21: 17 | G21: Removed - 21 | J21: Regression Sprint There was a scope creep for Stock Management, rather than regression was on-going. We found few issues that the team is fixing related to Site and Site groups. | K21: Internal: External: Team Collaboration
A22: =IF(AND($D$1>=C22,$D$1<=D22),"CurrentSprint","NA") -> NA | B22: 2.1 Sprint 6 | C22: 45555 | D22: 45568 | E22: 29 | F22: 50 | G22: Introduced - 21 | J22: Regression Sprint Ruban and Sudheer were involved in Regression Testing Ruban was involved in Escalation Internal CRC - 0, External CRC - 0, QA Defects - 11, Escaped Defects - 0 | K22: Internal: External:
A23: =IF(AND($D$1>=C23,$D$1<=D23),"CurrentSprint","NA") -> NA | B23: 2.2
A24: =IF(AND($D$1>=C24,$D$1<=D24),"CurrentSprint","NA") -> NA | B24: 2.2 Sprint 0 | C24: 45569 | D24: 45582 | E24: 15 | F24: 20 | G24: Introduced - 5 | I24: Performance Optimization in Cart for Individual and Teacher Ordering | J24: Internal CRC - 0 External CRC - 0 QA Defects - 4 Escaped Defects - 0
A25: =IF(AND($D$1>=C25,$D$1<=D25),"CurrentSprint","NA") -> NA | B25: 2.2 Sprint 1 | C25: 45583 | D25: 45596 | E25: 20 | F25: 17 | G25: Carry Forwarded - 3 | I25: Adding First Name, Last Name and Copy Email to the Order Details | J25: Due to Build Issues and ChromeDriver Issue one Regression Automation Story was carry forwarded Internal CRC - 0 External CRC - 0 QA Defects - 2 Escaped Defects - 0
A26: =IF(AND($D$1>=C26,$D$1<=D26),"CurrentSprint","NA") -> NA | B26: 2.2 Sprint 2 | C26: 45597 | D26: 45610 | E26: 23 | F26: 23 | I26: Stock Management UI Changes for Admin and Soft Refresh of Stock Items in End User | J26: Internal CRC - 0 External CRC - 0 QA Defects - 3 Escaped Defects - 0
A27: =IF(AND($D$1>=C27,$D$1<=D27),"CurrentSprint","NA") -> NA | B27: 2.2 Sprint 3 | C27: 45611 | D27: 45638 | E27: 41 | F27: 53 | I27: Stock Management Complete Changes, Stock Report, Regression Automation | J27: 4 - Weeks Sprint Internal CRC - 0 External CRC - 0 QA Defects - 5 Escaped Defects - 0
A28: =IF(AND($D$1>=C28,$D$1<=D28),"CurrentSprint","NA") -> NA | B28: 2.2 Sprint 4 | C28: 45639 | D28: 45666 | E28: 36 | F28: 51 | I28: Stock Management Complete Changes, Stock Report | J28: 4 Weeks Sprint. Two stories were Carry Forwarded - Development is completed, Testing is in Progress. End - End Testing is required for this EPIC Feature Internal CRC - 0 External CRC - 0 QA Defects - 4 Escaped Defects - 0
A29: =IF(AND($D$1>=C29,$D$1<=D29),"CurrentSprint","NA") -> NA | B29: 2.2 Sprint 5 | C29: 45667 | D29: 45680 | E29: 42 | F29: 43 | I29: Regression Sprint - Stock Management Complete Changes, Stock Report | J29: Will be carry forwarded to continue other reports. We have 13 reports with run reports and schedule reports with report inbox. Sentral had a new PR for CSV Format, so we will re running the tests We have completed Order Management, Menu Item, Menu Template, Menu Calendar, Settings Module. We have Stock Management Module inprogress for regression. Internal CRC - 0 External CRC - 0 QA Defects - 4 Escaped Defects - 9 | K29: External - Rachel appreciated Preethi, Ruban for their extensive support in the absence of Tino
A30: =IF(AND($D$1>=C30,$D$1<=D30),"CurrentSprint","NA") -> NA | B30: 2.2 Sprint 6 | C30: 45681 | D30: 45694 | E30: 20 | F30: 27 | I30: Regression Sprint - Stock Management Complete Changes, Stock Report and Analysis on Bulk Order Cancellation/Open, Menu Template Report and Student Fullfillment Enhancement | J30: Internal CRC - 0 External CRC - 0 QA Defects - 3 Escaped Defects - 1 | K30: External - Received appreciation mail from Tino, Director/PM for our commitment, coordination and attitude. Ruban has been assigned as an PR approver to merge PR
B31: 2.3
A32: =IF(AND($D$1>=C32,$D$1<=D32),"CurrentSprint","NA") -> NA | B32: 2.3 Sprint 1 | C32: 45695 | D32: 45708 | E32: 7 | F32: 25.75 | I32: Analysis on Bulk Order Cancellation/Open, Menu Template Report and Student Fullfillment Enhancement | J32: Internal CRC - 0 External CRC - 0 QA Defects - 1 Escaped Defects - 1 | K32: External - Received appreciation on the overall team work & Ruban has been appreciated for the support provided to Rachel.
A33: =IF(AND($D$1>=C33,$D$1<=D33),"CurrentSprint","NA") -> NA | B33: 2.3 Sprint 2 | C33: 45709 | D33: 45722 | E33: 18 | F33: 27 | I33: Bulk order open/cancellation, Menu Template Report & Student fulfillment enhancement, Report Headers | J33: Internal CRC - 0 External CRC - 0 QA Defects - 6 Escaped Defects - 0 | K33: External: Rachel, Tino and other Clients appreciated Ruban for his commitment towards Sentral and Heartland
A34: =IF(AND($D$1>=C34,$D$1<=D34),"CurrentSprint","NA") -> NA | B34: 2.3 Sprint 3 | C34: 45723 | D34: 45736 | E34: 21 | F34: 34 | I34: Enhancement to Report Headers,Customer Count Report, Student Fulfillmen report & Stock Management code refactoring | J34: Internal CRC - 0 External CRC - 0 Bouncebacks-2 QA Defects - 2 Escaped Defects - 1 | K34: Team was appreciated for the overall work & co-ordination.
A35: =IF(AND($D$1>=C35,$D$1<=D35),"CurrentSprint","NA") -> NA | B35: 2.3 Sprint 4 | C35: 45737 | D35: 45750 | E35: 35 | F35: 35 | I35: Regression - Stock Management, Report Enhancements, Order management changes, Complete Teacher, Parent & Admin. Student Product Sales Report changes | J35: Internal CRC - 0 External CRC - 0 Bouncebacks- 0 QA Defects - 9 Escaped Defects - 0 | K35: Entire team was commended for their work & efforts during the regression.
B36: 2.4
A37: =IF(AND($D$1>=C37,$D$1<=D37),"CurrentSprint","NA") -> NA | B37: 2.4 Sprint 0 | C37: 45751 | D37: 45764 | E37: 23 | F37: 32 | I37: Tech Debt work [Added API settings to the tenant cache, Job added for item type update, Unsplash update to use thumbnail URL] & Multiple defect fixes | J37: Internal CRC - 0 External CRC - 0 Bouncebacks- 0 QA Defects - 7 Escaped Defects - 0
A38: =IF(AND($D$1>=C38,$D$1<=D38),"CurrentSprint","NA") -> NA | B38: 2.4 Sprint 1 | C38: 45765 | D38: 45778 | E38: 29 | F38: 29 | I38: User information display on order cancellation, Menu items export, Regression automation fixes & defect fixes | J38: Internal CRC - 0 External CRC - 0 Bouncebacks- 0 QA Defects - 1 Escaped Defects - 1 | K38: Good team effort in completing the stories .
A39: =IF(AND($D$1>=C39,$D$1<=D39),"CurrentSprint","NA") -> NA | B39: 2.4 Sprint 2 | C39: 45779 | D39: 45792 | E39: 16 | F39: 10 | G39: Carry forwarded - 6 | I39: Import config settings, Nutritional unit update, sample script for item type [automation], Timeboxed Discovery for Localization Language Translation | J39: Internal CRC - 0 External CRC - 0 Bouncebacks- 0 QA Defects - 1 Escaped Defects - 0 | K39: Owen appreciated Sudheer for his work regarding the newly automated framework.
A40: =IF(AND($D$1>=C40,$D$1<=D40),"CurrentSprint","NA") -> NA | B40: 2.4 Sprint 3 | C40: 45793 | D40: 45806 | E40: 24 | F40: 24 | G40: Carry forwarded - 2 | I40: Regression | J40: Internal CRC - 0 External CRC - 0 Bouncebacks- 0 QA Defects - 2 Escaped Defects - 0 | K40: 1. Ken appreciated Sudheer for his efforts in Regression testing. 2. Hunter appreciated Charu in helping him align the requirements & documentation. 3. Ruban was appreciated by the client team for his prompt and effective handling of the escalation.
B41: 2.5
A42: =IF(AND($D$1>=C42,$D$1<=D42),"CurrentSprint","NA") -> NA | B42: 2.5 Kaleida Nutrition S1 | C42: 45807 | D42: 45820 | E42: 23 | F42: 23 | I42: Import functionality work in Progress, FOH & BOH Kaleida setup, Auto Cart update for orderable day restriction, Automation (Admin settings) | J42: Internal CRC - 0 External CRC - 0 Bouncebacks- 0 QA Defects - 2 Escaped Defects - 0
A43: =IF(AND($D$1>=C43,$D$1<=D43),"CurrentSprint","NA") -> NA | B43: 2.5 Kaleida Nutrition S2 | C43: 45821 | D43: 45834 | E43: 11 | F43: 21 | I43: Completed Import functionality, Auto cart fix and Kaleida footer update for MealOrders and Mosaic Point of Sale. | J43: Internal CRC - 0 External CRC - 0 Bouncebacks- 0 QA Defects - 2 Escaped Defects - 1
A44: =IF(AND($D$1>=C44,$D$1<=D44),"CurrentSprint","NA") -> NA | B44: 2.5 Kaleida Nutrition S3 | C44: 45835 | D44: 45848 | E44: 15 | F44: 28 | I44: Updated Footer for BOH Kaleida work, Completed Admin side District messages, Export changes to text qualifier, completed automation for admin settings. | J44: Internal CRC - 0 External CRC - 0 Bouncebacks- 3 QA Defects - 0 Escaped Defects - 0 | K44: - The communication efforts demonstrated by the entire team - both across teams and internally- were highly appreciated, contributing significantly to our ability to stay aligned. - Ken appreciated Ruban's efforts in helping the stories completion in time
A45: =IF(AND($D$1>=C45,$D$1<=D45),"CurrentSprint","NA") -> NA | B45: 2.5 Kaleida Nutrition S4 | C45: 45849 | D45: 45862 | E45: 20 | F45: 20 | I45: Regression Sprint | J45: Internal CRC - 0 External CRC - 0 Bouncebacks- 0 QA Defects - 0 Escaped Defects - 0 | K45: Offshore team was appreciated for their efforts in completing Regression in time. Offhore DM suggested all the team members to enable their cameras during team meeting
A46: =IF(AND($D$1>=C46,$D$1<=D46),"CurrentSprint","NA") -> NA | B46: 2.5 Kaleida Nutrition S5 | C46: 45863 | D46: 45876 | E46: 10 | F46: 12 | H46: - FOH Side Nav Loading/Flickering issues resolved - Updated BOH Breadcrumbs - Fixed BOH Side Nav loading/flickering issues - MSA Discovery & setup | I46: Kaleida work updates for FOH & defect fix for close of receipt printing | J46: Internal CRC - 0 External CRC - 0 Bouncebacks- 0 QA Defects - 1 Escaped Defects - 0 | K46: What went well : Team was commended by the client for the excellent work, co-ordination & communication. What didn't go so well : Issues with MSA setup. Improvements going forward : N/A
A47: =IF(AND($D$1>=C47,$D$1<=D47),"CurrentSprint","NA") -> NA | B47: 2.5 Kaleida Nutrition S6 | C47: 45877 | D47: 45890 | E47: 8 | F47: 11 | H47: 1. FOH Breadcrumb & Navigation issue fixes 2. Completed Header Dashboard icon updates 3. Introduce district selector dropdown in Header 4. Updated automation scripts for old framework 5. Mosaic BOH - Completed update to Filter window background color 6. Mosaic BOH - Completed breadcrumb issue fixes & ellipsis fixes to district dropdown | I47: FOH Dashboard UI & breadcrumb issue fixes | J47: Internal CRC - 2 External CRC - 0 Bouncebacks- 1 QA Defects - 0 Escaped Defects - 0 | K47: What went well : Very good progress, completed good amount of work. What didn't go so well : FOH Deployment pipeline,seems to break after every deployment. Improvements going forward : N/A
A48: =IF(AND($D$1>=C48,$D$1<=D48),"CurrentSprint","NA") -> NA | B48: 2.5 Kaleida Nutrition S7 | C48: 45891 | D48: 45904 | E48: 3 | F48: 11 | H48: 1. FOH Header dashboard icon & Dropdown menu fixes 2. Meal Orders Springfield new role creation completed 3. BOH - Breadcrumb issue fixes 4. MSA Kaleida - Breadcrumbs updates | I48: Kaleida work progress has been excellent. | J48: Internal CRC - 0 External CRC - 1 Bouncebacks- 1 QA Defects - 0 Escaped Defects - 0 | K48: What went well : - Team was applauded for the good work, ability to juggle multiple applications at a time. - QA work around test cases & automation scripts was appreciated by Ken. What didn't go well : - FOH Dashboard issues
A49: =IF(AND($D$1>=C49,$D$1<=D49),"CurrentSprint","NA") -> NA | B49: 2.5 Kaleida Nutrition S8 | C49: 45905 | D49: 45918 | E49: 10 | F49: 15 | H49: 1. FOH - Login screen Kaleida updates 2. Stock Management Update 3. Defect Fixes 4. Automation | I49: Kaleida work progress has been excellent. | J49: Internal CRC - 0 External CRC - 0 Bouncebacks- 2 QA Defects - 0 Escaped Defects - 0 | K49: What went well : - MSA Recorded POV's - Great overall team work & progress What didn't go well : - Switching between all the s/w programs being worked on [Challenging for team] - Mosaic login screens UI, multiple UI scenerios which are not covered in Figma
A50: =IF(AND($D$1>=C50,$D$1<=D50),"CurrentSprint","NA") -> NA | B50: 2.5 Kaleida Nutrition S9 | C50: 45919 | D50: 45932 | E50: 26 | F50: 26 | H50: 1. Interim Release preperation 2. FOH issue fixes 3. Meal Orders defect fixes 4. MSA Header updates 5. MSA sitemap implementation 6. Automation | I50: Interim Release fixes | J50: Internal CRC - 0 External CRC - 0 Bouncebacks- 0 QA Defects - 0 Escaped Defects - 0 | K50: What went well : - Interim Release - Good Work progress What didn't go well : - UI changes for FOH Login screens.
A51: =IF(AND($D$1>=C51,$D$1<=D51),"CurrentSprint","NA") -> NA | B51: 2.5 KaleidaNutrition S10 | C51: 45933 | D51: 45946 | E51: 8 | F51: 13 | H51: 1. Mosaic FOH Kaleida performance fixes 2. Automation completion for specififc modules new framework 3. FOH Login screen footer changes completion 4. BOH Login screen updates completion 5. MSA - left navigation updates | I51: Kalieda work progress. | J51: Internal CRC - 0 External CRC - 0 Bouncebacks- 0 QA Defects - 0 Escaped Defects - 0 | K51: What went well : - Good work progress overall What didn't go well : - NA
A52: =IF(AND($D$1>=C52,$D$1<=D52),"CurrentSprint","NA") -> NA | B52: 2.5 KaleidaNutrition S11 | C52: 45947 | D52: 45960 | E52: 10 | F52: 18 | H52: 1. Mosaic FOH Login screen Pending updates. 2. Automation data cleanup 3. Mosaic FOH Kaleida - Manage Catering Orders from Results Table screen completion | I52: Kaleida work progress has been going great. | J52: Internal CRC - 0 External CRC - 0 Bouncebacks- 1 QA Defects - 0 Escaped Defects - 0 | K52: What went well : - Team was applauded for the good work, ability to juggle multiple applications at a time. - QA work around test cases & automation scripts was appreciated by Ken. What didn't go well : - Vega component limitations
A53: =IF(AND($D$1>=C53,$D$1<=D53),"CurrentSprint","NA") -> NA | B53: 2.5 KaleidaNutrition S12 | C53: 45961 | D53: 45974 | E53: 17 | F53: 9 | H53: 1. Mosaic FOH Kaleida - Interior Pages update - Record Training, Catering & add/edit order screens completion 2. Meal Orders enhancement - District selector 3. Discovery on Report controls | I53: Kalieda work progress - multiple screens completed. | J53: Internal CRC - 0 External CRC - 0 Bouncebacks- 0 QA Defects - 0 Escaped Defects - 0 | K53: What went well : - Team was applauded for the good work - Vega updates work progress What didn't go well : - POV's at times could not be completed due to limitations in client availability which eventually delayed testing.
A54: =IF(AND($D$1>=C54,$D$1<=D54),"CurrentSprint","NA") -> NA | B54: 2.5 KaleidaNutrition S13 | C54: 45975 | D54: 46002 | E54: 39 | F54: 46 | H54: 1. Mosaic FOH Kaleida - SSO Login screen & server side validation error UI completed 2. Multiple interior pages completion - FOH Kaleida 3. Display of Title on Pages Without Breadcrumb-Level Navigation completed 4. Fixed left navigation highlight issues 5. MSB Accounting [setup/Discovery] completion | I54: 1. Kalieda work progress 2. MSB Accouting Setup completion to further start kaleida changes for the application | J54: Internal CRC - 0 External CRC - 0 Bouncebacks- 0 QA Defects - 0 Escaped Defects - 0 | K54: What went well : - Team was applauded for the good work - Vega updates work progress What didn't go well : - N/A.
A55: =IF(AND($D$1>=C55,$D$1<=D55),"CurrentSprint","NA") -> NA | B55: 2.5 KaleidaNutrition S14 | C55: 46003 | D55: 46030 | E55: 25 | F55: 25 | H55: 1. App switcher Implemenation for FOH 2. Scheduler task implemenation for FOH 3. MSB Accoutning Footer implementation 4. Interior Pages - Annual setup implementation for FOH 5. Meal Orders - Automation Regression in progress | I55: App switcher implementation for FOH | J55: Internal CRC - 0 External CRC - 0 Bouncebacks- 0 QA Defects - 0 Escaped Defects - 0 | K55: What went well : - Teamwork - Work was shared and managed well during holidays. - FOH App switcher implementation What didn't go well : - FOH issues - Close day report - underestimated - Laptop issues
A56: =IF(AND($D$1>=C56,$D$1<=D56),"CurrentSprint","NA") -> NA | B56: 2.5 KaleidaNutrition S15 | C56: 46031 | D56: 46044 | E56: 16 | F56: 16 | H56: 1. App switcher implementation for BOH 2. MSB Accounting - Header updation to Vega 3. Automation Regression for Serving periods | I56: 1. App switcher implementation for BOH 2. MSB Accouting Header updates | J56: Internal CRC - 0 External CRC - 0 Bouncebacks- 0 QA Defects - 0 Escaped Defects - 0 | K56: What went well : - BOH app switcher implementation - MSB Accounting Header updates What didn't go well : - N/A
A57: =IF(AND($D$1>=C57,$D$1<=D57),"CurrentSprint","NA") -> NA | B57: 2.5 KaleidaNutrition S16 | C57: 46045 | D57: 46058 | E57: 19 | F57: 19 | H57: 1. App switcher implementation for Meal Orders 2. MSB Accounting - Kaleida Updates to Login screen 3. Completion of close day module in FOH interior pages | I57: App switcher implementation for Meal Orders | J57: Internal CRC - 0 External CRC - 0 Bouncebacks- 0 QA Defects - 0 Escaped Defects - 0 | K57: What went well : - Teams ability to Pivot - Meal Orders App switcher completion What did't go so well : - Rework on completed screens due to delayed feedback.
A58: =IF(AND($D$1>=C58,$D$1<=D58),"CurrentSprint","NA") -> NA | B58: 2.5 KaleidaNutrition S17 | C58: 46059 | D58: 46072 | E58: 12 | F58: 33 | H58: 1. App switcher defects fixes 2. Search functionality implemenation for Meal Orders District selector 3. Multiple BOH interior pages updated to Kaleida 4. App switcher installation on MSA 5. FOH - Root Menus updation to Kaleida | I58: 1. Search functionality implemenation for Meal Orders District selector 2. Multiple BOH interior pages updated to Kaleida | J58: Internal CRC - 0 External CRC - 0 Bouncebacks- 1 QA Defects - 0 Escaped Defects - 0 | K58: What went well : - Teams ability to Pivot - Completed more than forecasted - QA support What did't go so well : - N/A | L58: 3
A59: =IF(AND($D$1>=C59,$D$1<=D59),"CurrentSprint","NA") -> NA | B59: 2.5 KaleidaNutrition S18 | C59: 46073 | D59: 46086 | E59: 15 | F59: 15 | H59: 1. Mosaic BOH - Root Menu updates 2. Mosaic BOH - Interior Pages update - Ingredients allergens list | I59: Mosaic BOH Kaleida updates | J59: Internal CRC - 0 External CRC - 0 Bouncebacks- 2 QA Defects - 0 Escaped Defects - 0 | K59: What went well : - Kaleida work progress What did't go so well : - BOH Testing environment issues - Root pages complications | L59: 0
A60: =IF(AND($D$1>=C60,$D$1<=D60),"CurrentSprint","NA") -> NA | B60: 2.5 KaleidaNutrition S19 | C60: 46087 | D60: 46100 | E60: 15 | F60: 26 | H60: 1. Mosaic BOH - Root Menu updates & interior pages updates 2. Mosaic BOH - defect fixes 3. Meal Orders Regression completion | I60: Meal Orders Regression completion Mosaic BOH defect fixes | J60: Internal CRC - 0 External CRC - 0 Bouncebacks- 0 QA Defects - 0 Escaped Defects - 0 | K60: What went well : - Client appreciated the team’s responsiveness in quickly addressing the BOH defects and ensuring they were resolved in a timely manner. What did't go so well : - None | L60: 4
A61: =IF(AND($D$1>=C61,$D$1<=D61),"CurrentSprint","NA") -> NA | B61: 2.5 KN Sprint 20 | C61: 46101 | D61: 46114 | E61: 18 | F61: 21 | H61: 1. BOH Interior Pages Updates 2. FOH Root Menu updates 3. BOH Search enhancements | I61: Kalieda work progress - multiple screens completed. | J61: Internal CRC - 1 External CRC - 0 Bouncebacks- 1 QA Defects - 0 Escaped Defects - 0 | K61: What went well : - Lot of work completed during Regression - Demos received client appreciation - BOH regression issue fixes - Timely delivered work What did't go so well : - None | L61: 0
A62: =IF(AND($D$1>=C62,$D$1<=D62),"CurrentSprint","NA") -> NA | B62: 2.5 KaleidaNutrition S21 | C62: 46115 | D62: 46128 | E62: 16 | F62: 20 | H62: 1. BOH Interior Pages Updates 2. Multiple Defect fixes | I62: Kalieda work progress - multiple screens completed. | J62: Internal CRC - 0 External CRC - 0 Bouncebacks- 1 QA Defects - 0 Escaped Defects - 0 | K62: What went well : - Lot of work completed [Sprint & Stretch] - Client appreciated the refinement sessions - Good teamwork What did't go so well : - Vega table performance [issues with larger datasets] | L62: 1
A63: =IF(AND($D$1>=C63,$D$1<=D63),"CurrentSprint","NA") -> NA | B63: 2.5 KaleidaNutrition S22 | C63: 46129 | D63: 46142 | E63: 10 | F63: 31 | H63: 1. BOH Interior Pages updates to Kaleida - Multiple pages completed. 2. Accessibility defect fixes | I63: Kalieda work progress - multiple screens completed. | J63: Internal CRC - 0 External CRC - 1 Bouncebacks- 1 QA Defects - 0 Escaped Defects - 0 | K63: What went well : - Lot of work completed [Sprint & Stretch] - Client appreciated the team's responsiveness What did't go so well : - N/A. | L63: 4
A64: =IF(AND($D$1>=C64,$D$1<=D64),"CurrentSprint","NA") -> NA | B64: 2.5 KaleidaNutrition S23 | C64: 46143 | D64: 46156 | E64: 19 | F64: 30 | H64: 1. FOH & BOH interior Pages Vega updates | I64: Good work progress on Kaleida updates | J64: Internal CRC - 0 External CRC - 0 Bouncebacks- 0 QA Defects - 1 Escaped Defects - 0 | K64: What went well : Although Vega-related impediments posed some challenges, the team maintained good momentum What didn't go so well : Vega related impediments | L64: 1
A65: =IF(AND($D$1>=C65,$D$1<=D65),"CurrentSprint","NA") -> NA | B65: 2.5 KaleidaNutrition S24 | C65: 46157 | D65: 46170 | E65: 19

Sheet Unplanned Leaves
A1: Total Leaves | B1: =SUM(B21:D21) -> 0
B2: Resource Name
A3: Sprint | B3: Rupan Santhosh | C3: Kiruthiga Ganapathi | D3: Sudheer Dokku | E3: Charu Sharma | F3: Nathiya | G3: Kathikeyan Elumalai | H3: Ganesh Veerannan | I3: Shikha Pradhan | J3: Vidhaya Subramaniam | K3: Total | L3: Remarks
A4: Sprint 17 (6-Feb-2026 to 19-Feb-2026) | B4: 0 | C4: 0 | D4: 0 | E4: 1 | F4: 0 | G4: 1 | H4: 0 | I4: 0 | J4: 1 | K4: 3
A5: Sprint 18 (20-Feb-2026 to 5-Mar-2026) | B5: 0 | C5: 0 | D5: 0 | E5: 0 | F5: 0 | G5: 0 | H5: 0 | I5: 0 | J5: 0 | K5: 0
A6: Sprint 19 (6Mar-2026 to 19-Mar-2026) | B6: 0 | C6: 0 | D6: 0 | E6: 0 | F6: 0 | G6: 4 | H6: 0 | I6: 0 | J6: 0 | K6: 4
A7: Sprint 20 (20Mar-2026 to 2-Apr-2026) | B7: 0 | C7: 0 | D7: 0 | E7: 0 | F7: 0 | G7: 0 | H7: 0 | I7: 0 | J7: 0 | K7: 0
A8: Sprint 21 (3-Apr-2026 to 16-Apr-2026) | B8: 0 | C8: 0 | D8: 1 | E8: 1 | F8: 0 | G8: 0 | H8: 0 | I8: 0 | J8: 0 | K8: 2
A9: Sprint 22 (17-Apr-2026 to 30-Apr-2026) | B9: 0 | C9: 0 | D9: 1 | E9: 3 | F9: 0 | G9: 0 | H9: 0 | I9: 0 | J9: 0 | K9: 4
A10: Sprint 23 (1-May-2026 to 14-May-2026) | B10: 0 | C10: 0 | D10: 0 | E10: 0 | F10: 0 | G10: 1 | H10: 0 | J10: 0 | K10: 1

Sheet 2.5 KaleidaNutrition S24-Status
A1: S.No | B1: Application Name | C1: Sprint Start Date | D1: Sprint End Date | E1: Sprint | F1: Developer | G1: Story ID/Defect ID | H1: Description | I1: Status | J1: Estimated(sp) | K1: Actual(sp) | L1: Actual Hours Worklog | M1: Dev Start Date | N1: Dev End Date | O1: Unit testing | P1: Peer Tested By | Q1: Peer Tested Defects, if any | R1: Peer Reviewed By | S1: Peer Code Review Comments, if any | T1: PR Number/Link | U1: PR Created Date | V1: PR Approved Date | W1: Reviewer 1 | X1: Code Review Comments, if any | Y1: Reviewer 2 | Z1: Approved Date | AA1: Code Review Comments, if any2 | AB1: Internal PO -POV Comments | AC1: Client PO -POV Comments | AD1: Comments | AE1: Does this story meets expectations
A2: 1 | B2: Meal Order | C2: 46157 | D2: 46170 | E2: 2.5 KaleidaNutrition S24 Stretch | F2: Sudheer | G2: 53109 | H2: Meal Orders - Automation - Settings - Meal Pricing Template | I2: Story Being Developed | J2: 8 | M2: 46154
A3: 2 | B3: Meal Order | C3: 46157 | D3: 46170 | E3: 2.5 KaleidaNutrition S24 | F3: Kiruthiga | G3: 53298 | H3: [WAVE] Mosaic FOH - Update to login behavior | I3: Story Being Developed | J3: 8 | M3: 46157
A4: 3 | B4: Meal Order | C4: 46157 | D4: 46170 | E4: 2.5 KaleidaNutrition S24 | F4: Nathiya | G4: 53023 | H4: [WAVE] Mosaic BOH Kaleida - Interior Pages Update - Reports - Ingredients List/print | I4: Story Being Developed | J4: 8 | M4: 46154

Sheet 2.5 KaleidaNutrition S23-Status
A1: S.No | B1: Application Name | C1: Sprint Start Date | D1: Sprint End Date | E1: Sprint | F1: Developer | G1: Story ID/Defect ID | H1: Description | I1: Status | J1: Estimated(sp) | K1: Actual(sp) | L1: Actual Hours Worklog | M1: Dev Start Date | N1: Dev End Date | O1: Unit testing | P1: Peer Tested By | Q1: Peer Tested Defects, if any | R1: Peer Reviewed By | S1: Peer Code Review Comments, if any | T1: PR Number/Link | U1: PR Created Date | V1: PR Approved Date | W1: Reviewer 1 | X1: Code Review Comments, if any | Y1: Reviewer 2 | Z1: Approved Date | AA1: Code Review Comments, if any2 | AB1: Internal PO -POV Comments | AC1: Client PO -POV Comments | AD1: Comments | AE1: Does this story meets expectations
A2: 1 | B2: Meal Order | C2: 46143 | D2: 46156 | E2: 2.5 KaleidaNutrition S23 Stretch | F2: Sudheer | G2: 52478 | H2: Meal Orders - Automation - Settings - Taxes Test Cases | I2: Story Completed | J2: 11 | K2: 11 | L2: 44 | M2: 46150 | N2: 46153 | O2: Completed | P2: Sudheer | Q2: None | R2: None | S2: None | T2: https://dev.azure.com/heartlandschools/Meal%20Orders/_git/MealOrdersAutomation/pullrequest/48688 | U2: 46153 | V2: 46153 | W2: Owen | X2: None | Y2: Owen | Z2: 46153 | AA2: None | AB2: None | AC2: None | AE2: Meets Expectations
A3: 2 | B3: Meal Order | C3: 46143 | D3: 46156 | E3: 2.5 KaleidaNutrition S23 | F3: Kiruthiga | G3: 52987 | H3: [WAVE] Mosaic Boh Kaleida - Interior Pages Updates - Recipes Component List | I3: Story Completed | J3: 8 | K3: 7 | L3: 26 | M3: 46146 | N3: 46150 | O3: Completed | P3: Nathiya | Q3: None | R3: Nathiya | S3: None | T3: https://dev.azure.com/heartlandschools/Mosaic/_git/BOH/pullrequest/48933 | U3: 46150 | V3: 46153 | W3: Ruban | X3: None | Y3: Charles | Z3: 46153 | AA3: None | AB3: None | AC3: None | AE3: Meets Expectations
A4: 3 | B4: Meal Order | C4: 46143 | D4: 46156 | E4: 2.5 KaleidaNutrition S23 | F4: Nathiya | G4: 52981 | H4: [WAVE] MOsaic BOH Kaleida - Interior Pages Update - Reports - Recipes - Recipe Allergen list | I4: Story Completed | J4: 8 | K4: 8 | L4: 36 | M4: 46146 | N4: 46153 | O4: Completed | P4: Sudheer | Q4: None | R4: Kiruthiga | S4: None | T4: https://dev.azure.com/heartlandschools/Mosaic/_git/BOH/pullrequest/48968 | U4: 46153 | V4: 46153 | W4: Ruban | X4: None | Y4: Charles | Z4: 46153 | AA4: None | AB4: None | AC4: None | AE4: Meets Expectations
A5: 4 | B5: Meal Order | C5: 46143 | D5: 46156 | E5: 2.5 KaleidaNutrition S23 | F5: Ruban | G5: 53059 | H5: Kaleida Mosaic BOH - Allergen Search Screen(Move Status Toggle to Edit Screen) | I5: Story Completed | J5: 2 | K5: 2 | L5: 12 | M5: 46135 | N5: 46142 | O5: Completed | P5: Ken | Q5: None | R5: Kiruthiga | S5: None | T5: https://dev.azure.com/heartlandschools/Mosaic/_git/BOH/pullrequest/48758 | U5: 46142 | V5: 46142 | W5: Charles | X5: None | Y5: Charles | Z5: 46142 | AA5: None | AB5: None | AC5: None | AE5: Meets Expectations
A6: 5 | B6: Meal Order | C6: 46143 | D6: 46156 | E6: 2.5 KaleidaNutrition S23 Stretch | F6: Sudheer | G6: 53109 | H6: Meal Orders - Automation - Settings - Meal Pricing Template | I6: Story Being Developed | J6: 8 | M6: 46154
A7: 6 | B7: Meal Order | C7: 46143 | D7: 46156 | E7: 2.5 KaleidaNutrition S23 | F7: Kiruthiga | G7: 27109 | H7: [WAVE] Mosaic FOH (LogIn Screen) - Label must be correctly associated with a form control | I7: Defect Fixed | J7: 1 | K7: 1 | L7: 4 | M7: 46155 | N7: 46155 | O7: Completed | P7: Nathiya | Q7: None | R7: Nathiya | S7: None | T7: https://dev.azure.com/heartlandschools/Mosaic/_git/FOH/pullrequest/49025 | U7: 46155 | V7: 46155 | W7: Ruban | X7: None | Y7: Charles | Z7: 46155 | AA7: None | AB7: None | AC7: None | AE7: Meets Expectations

Sheet 2.5Kaleida Nutrition S23-Defect
A1: Sprint # | B1: Story/Defect ID | C1: Parent Story | D1: Developer | E1: Issue Type | F1: Issue Description | G1: Priority | H1: Defect Source | I1: Type | J1: Found By | K1: Status | L1: Root Cause Category | M1: RCA Comment *
A2: 2.5 KaleidaNutrition S23 | B2: 52987 | D2: Kiruthiga | E2: Minor | F2: Numeric Range Start and End fields unable to be edited after inputting 6 characters | G2: low | H2: Gap in unit testing | I2: External | J2: Onsite QA | K2: Completed | L2: New Issue | M2: It an edge case not a blocker or harmful one. Missed it to notice in unit testing

Sheet 2.5 KaleidaNutrition S22-Status
A1: S.No | B1: Application Name | C1: Sprint Start Date | D1: Sprint End Date | E1: Sprint | F1: Developer | G1: Story ID/Defect ID | H1: Description | I1: Status | J1: Estimated(sp) | K1: Actual(sp) | L1: Actual Hours Worklog | M1: Dev Start Date | N1: Dev End Date | O1: Unit testing | P1: Peer Tested By | Q1: Peer Tested Defects, if any | R1: Peer Reviewed By | S1: Peer Code Review Comments, if any | T1: PR Number/Link | U1: PR Created Date | V1: PR Approved Date | W1: Reviewer 1 | X1: Code Review Comments, if any | Y1: Reviewer 2 | Z1: Approved Date | AA1: Code Review Comments, if any2 | AB1: Internal PO -POV Comments | AC1: Client PO -POV Comments | AD1: Comments | AE1: Does this story meets expectations
A2: 1 | B2: Meal Order | C2: 46129 | D2: 46142 | E2: 2.5 KaleidaNutrition S22 | F2: Kiruthiga | G2: 52843 | H2: [WAVE] Mosaic BOH - Interior pages update - Setup - Sites Search | I2: Story Completed | J2: 8 | K2: 8 | L2: 32 | M2: 46129 | N2: 46140 | O2: Completed | P2: Nathiya | Q2: None | R2: None | S2: None | T2: https://dev.azure.com/heartlandschools/Mosaic/_git/BOH/pullrequest/48694 | U2: 46140 | V2: 46140 | W2: Ruban | Y2: Charles | Z2: 46140 | AA2: None | AB2: None | AD2: 28th Apr : Client POV is completed. But there is a finding on unit testing, Once it is fixed branch will be shared for testing around 3PM (28th Apr) | AE2: Meets Expectations
A3: 2 | B3: Meal Order | C3: 46129 | D3: 46142 | E3: 2.5 KaleidaNutrition S22 Stretch | F3: Nathiya | G3: 52621 | H3: [WAVE] Mosaic BOH Kaleida - Interior Pages Update - Setup - Users add/edit | I3: Story Completed | J3: 13 | K3: 13 | L3: 52 | M3: 46127 | N3: 46141 | O3: Completed | P3: Sudheer | Q3: None | R3: Kiruthiga | S3: None | T3: https://dev.azure.com/heartlandschools/Mosaic/_git/BOH/pullrequest/48730 | U3: 46141 | V3: 46141 | W3: Ruban | X3: None | Y3: Richard | Z3: 46141 | AA3: None | AB3: None | AC3: Suggestion to remove the Edit icon in User Maintenance page and show the Actions column only when delete action applicable. | AD3: 04/28 : Client POV completed. 04/29 : Shared branch for peer testing. | AE3: Meets Expectations
A4: 3 | B4: Meal Order | C4: 46129 | D4: 46142 | E4: 2.5 KaleidaNutrition S22 Stretch | F4: sudheer | G4: 52478 | H4: Meal Orders - Automation - Settings - Taxes Test Cases | I4: Story Being Developed | J4: 8 | K4: 8 | L4: 40 | M4: 46129 | N4: 46140 | O4: Completed | P4: Sudheer | Q4: None | R4: None | S4: None | T4: https://dev.azure.com/heartlandschools/Meal%20Orders/_git/MealOrdersAutomation/pullrequest/48688 | U4: 46140 | W4: Owen | Y4: Owen | AD4: That is a Pendo guide that was added by the Pendo team. We didn't add it ourselves but yes, it is expected to be there. We need to update the scripts
A5: 4 | B5: Meal Order | C5: 46129 | D5: 46142 | E5: 2.5 KaleidaNutrition S22 Stretch | F5: Ruban | G5: 52610 | H5: [WAVE] Mosaic BOH Kaleida - Interior Pages Update - Setup- Import/Export execute | I5: Story Completed | J5: 8 | K5: 8 | L5: 40 | M5: 46129 | N5: 46140 | O5: Completed | P5: Vidhya | Q5: None | R5: None | S5: None | T5: https://dev.azure.com/heartlandschools/Mosaic/_git/BOH/pullrequest/48674 | U5: 46139 | V5: 46140 | W5: Charles | Y5: Charles | Z5: 46140 | AA5: None | AB5: None | AE5: Meets Expectations
A6: 5 | B6: Meal Order | C6: 46129 | D6: 46142 | E6: 2.5 KaleidaNutrition S22 | F6: Kiruthiga | G6: 27107 | H6: WAVE] Mosaic FOH - Image must have alternative text | I6: Defect Fixed | J6: 2 | K6: 1 | L6: 4 | M6: 46141 | N6: 46141 | O6: Completed | P6: Shikha | Q6: None | R6: Shikha | S6: None | T6: https://dev.azure.com/heartlandschools/Mosaic/_git/FOH/pullrequest/48724 | U6: 46141 | V6: 46141 | W6: Ruban | Y6: Charles | Z6: 46141 | AA6: None | AB6: None

Sheet 2.5Kaleida Nutrition S22-Defect
A1: Sprint # | B1: Story/Defect ID | C1: Parent Story | D1: Developer | E1: Issue Type | F1: Issue Description | G1: Priority | H1: Defect Source | I1: Type | J1: Found By | K1: Status | L1: Root Cause Category | M1: RCA Comment *
A2: 2.5 KaleidaNutrition S22 Stretch | B2: 52621 | D2: Nathiya | F2: Linking to a POS Menu Product not always successful in QA. Console error received | G2: Medium | H2: Manual | I2: External | J2: Ken | K2: Completed | L2: New Issue | M2: The issue reported in 52419. The root cause of this issue - In changes for 52621 - User Add/Edit, there was an bunding issue due to which we get the console errors. We fixed and closed the issue.

Sheet 2.5 KaleidaNutrition S21-Status
A1: S.No | B1: Application Name | C1: Sprint Start Date | D1: Sprint End Date | E1: Sprint | F1: Developer | G1: Story ID/Defect ID | H1: Description | I1: Status | J1: Estimated(sp) | K1: Actual(sp) | L1: Actual Hours Worklog | M1: Dev Start Date | N1: Dev End Date | O1: Unit testing | P1: Peer Tested By | Q1: Peer Tested Defects, if any | R1: Peer Reviewed By | S1: Peer Code Review Comments, if any | T1: PR Number/Link | U1: PR Created Date | V1: PR Approved Date | W1: Reviewer 1 | X1: Code Review Comments, if any | Y1: Reviewer 2 | Z1: Approved Date | AA1: Code Review Comments, if any2 | AB1: Internal PO -POV Comments | AC1: Client PO -POV Comments | AD1: Comments | AE1: Does this story meets expectations
A2: 1 | B2: Meal Order | C2: 46115 | D2: 46128 | E2: 2.5 KaleidaNutrition S21 | F2: Kiruthiga | G2: 52850 | H2: [WAVE] Mosaic BOH Kaleida - Interior Pages Update - Setup - System Settings | I2: Story Completed | J2: 8 | K2: 8 | L2: 32 | M2: 46115 | N2: 46126 | O2: Done | P2: Sudheer | Q2: None | R2: Ruban | S2: None | T2: https://dev.azure.com/heartlandschools/Mosaic/_git/BOH/pullrequest/48407 | U2: 46126 | V2: 46126 | W2: Ruban | X2: None | Y2: Richard | Z2: 46126 | AA2: None | AB2: None | AC2: Suggested to remove search feture from the drop down | AE2: Meets Expectations
A3: 2 | B3: Meal Order | C3: 46115 | D3: 46128 | E3: 2.5 KaleidaNutrition S21 | F3: Nathiya | G3: 52222 | H3: [WAVE] Mosaic BOH Kaleida - Interior Pages Update - Setup - Mealviewer Display Groups | I3: Story Completed | J3: 5 | K3: 5 | L3: 42 | M3: 46106 | N3: 46121 | O3: Done | P3: Vidhya | Q3: None | R3: Kiruthiga | S3: None | T3: https://dev.azure.com/heartlandschools/Mosaic/_git/BOH/pullrequest/48383 | U3: 46125 | V3: 46125 | W3: Ruban | X3: None | Y3: Charles | Z3: 46125 | AA3: None | AB3: None | AC3: Deactivate and Activate button should be grouped along with the other buttons. | AE3: Meets Expectations
A4: 3 | B4: Meal Order | C4: 46115 | D4: 46128 | E4: 2.5 KaleidaNutrition S21 | F4: Ruban | G4: 52568 | H4: [WAVE] Mosaic FOH - Updating the Apply Filters with a Search button on Vega updated screens | I4: Story Completed | J4: 3 | K4: 3 | L4: 12 | M4: 46115 | N4: 46122 | O4: Done | P4: Vidhya | Q4: None | R4: Kiruthiga | S4: None | T4: https://dev.azure.com/heartlandschools/Mosaic/_git/FOH/pullrequest/48362 | U4: 46123 | V4: 46123 | W4: Charles | X4: None | Y4: Charles | Z4: 46123 | AA4: None | AB4: None | AC4: None
A5: 4 | B5: Meal Order | C5: 46115 | D5: 46128 | E5: 2.5 KaleidaNutrition S21 Stretch | F5: sudheer | G5: 52478 | H5: Meal Orders - Automation - Settings - Taxes Test Cases | I5: Story Being Developed | J5: 8 | L5: 8 | M5: 46115
A6: 5 | B6: Meal Order | C6: 46115 | D6: 46128 | E6: 2.5 KaleidaNutrition S21 Stretch | F6: Ruban | G6: 52610 | H6: [WAVE] Mosaic BOH Kaleida - Interior Pages Update - Setup- Import/Export execute | I6: Story Being Developed | J6: 8 | M6: 46115
A7: 6 | B7: Meal Order | C7: 46115 | D7: 46128 | E7: 2.5 KaleidaNutrition S21 Stretch | F7: Nathiya | G7: 27191 | H7: [WAVE] Mosaic BOH - Blank option missing in some dropdowns | I7: Defect Fixed | J7: 2 | K7: 1 | L7: 6 | M7: 46126 | N7: 46126 | O7: Done | P7: Sudheer | Q7: None | R7: Kiruthiga | S7: None | T7: https://dev.azure.com/heartlandschools/Mosaic/_git/BOH/pullrequest/48432 | U7: 46127 | V7: 46127 | W7: Ruban | X7: None | Y7: Richard | Z7: 46127 | AA7: None | AB7: None | AC7: None | AE7: Meets Expectations
A8: 7 | B8: Meal Order | C8: 46115 | D8: 46128 | E8: 2.5 KaleidaNutrition S21 Stretch | F8: Kiruthiga | G8: 27205 | H8: [WAVE] Mosaic BOH Kaleida - Update the date picker implementation | I8: Defect Fixed | J8: 2 | K8: 2 | L8: 8 | M8: 46127 | N8: 46127 | O8: Done | P8: Sudheer | Q8: None | R8: Kiruthiga | S8: None | T8: https://dev.azure.com/heartlandschools/Mosaic/_git/BOH/pullrequest/48431 | U8: 46127 | V8: 46127 | W8: Ruban | X8: None | Y8: Richard | Z8: 46127 | AA8: None | AB8: None | AC8: None
A9: 8 | B9: Meal Order | C9: 46115 | D9: 46128 | E9: 2.5 KaleidaNutrition S21 Stretch | F9: Nathiya | G9: 52621 | H9: [WAVE] Mosaic BOH Kaleida - Interior Pages Update - Setup - Users add/edit | I9: Story Being Developed | J9: 13 | M9: 46127

Sheet 2.5 KaleidaNutrition S20-Status
A1: S.No | B1: Application Name | C1: Sprint Start Date | D1: Sprint End Date | E1: Sprint | F1: Developer | G1: Story ID/Defect ID | H1: Description | I1: Status | J1: Estimated(sp) | K1: Actual(sp) | L1: Actual Hours Worklog | M1: Dev Start Date | N1: Dev End Date | O1: Unit testing | P1: Peer Tested By | Q1: Peer Tested Defects, if any | R1: Peer Reviewed By | S1: Peer Code Review Comments, if any | T1: PR Number/Link | U1: PR Created Date | V1: PR Approved Date | W1: Reviewer 1 | X1: Code Review Comments, if any | Y1: Reviewer 2 | Z1: Approved Date | AA1: Code Review Comments, if any2 | AB1: Internal PO -POV Comments | AC1: Client PO -POV Comments | AD1: Comments | AE1: Does this story meets expectations
A2: 1 | B2: Meal Order | C2: 46101 | D2: 46114 | E2: 2.5 KaleidaNutrition S20 | F2: Kiruthiga | G2: 52041 | H2: [WAVE] Mosaic BOH Kaleida - Interior Pages Update - Reports - Price Lists Report | I2: Story Completed | J2: 5 | K2: 4 | L2: 15 | M2: 46087 | N2: 46108 | O2: Done | P2: Sudheer | Q2: None | R2: Ruban | T2: https://dev.azure.com/heartlandschools/Mosaic/_git/BOH/pullrequest/48101 | U2: 46111 | V2: 46111 | W2: Ruban | X2: None | Y2: Richard | Z2: 46111 | AA2: None | AB2: None | AC2: None | AE2: Meets Expectations
A3: 2 | B3: Meal Order | C3: 46101 | D3: 46114 | E3: 2.5 KaleidaNutrition S20 | F3: Nathiya | G3: 52042 | H3: [WAVE] Mosaic BOH Kaleida - Interior Pages Update - Reports - Product Notes Report | I3: Story Completed | J3: 5 | K3: 4 | L3: 16 | M3: 46087 | N3: 46105 | O3: Done | P3: Sudheer | Q3: None | R3: Kiruthiga | S3: Move Navigation logic to common file | T3: https://dev.azure.com/heartlandschools/Mosaic/_git/BOH/pullrequest/48030 | U3: 46106 | V3: 46107 | W3: Charles | X3: None | Y3: Charles | Z3: 46107 | AA3: None | AB3: None | AC3: None | AE3: Meets Expectations
A4: 3 | B4: Meal Order | C4: 46101 | D4: 46114 | E4: 2.5 KaleidaNutrition S20 | F4: Ruban | G4: 52553 | H4: [WAVE] Mosaic BOH - Kaleida - Interior Pages Update - Import/Export Search | I4: Story Completed | J4: 3 | K4: 3 | L4: 12 | M4: 46104 | N4: 46113 | O4: Done | P4: Vidhya | Q4: None | R4: Kiruthiga | T4: https://dev.azure.com/heartlandschools/Mosaic/_git/BOH/pullrequest/48072 | U4: 46113 | V4: 46113 | W4: Charles | X4: None | Y4: Charles | Z4: 46113 | AA4: None | AB4: None | AC4: None | AE4: Meets Expectations
A5: 4 | B5: Meal Order | C5: 46101 | D5: 46114 | E5: 2.5 KaleidaNutrition S20 | F5: Ruban | G5: 52198 | H5: [WAVE] Mosaic BOH Kaleida - Interior Pages Update - Setup- Import/Export | I5: Story Completed | J5: 5 | K5: 5 | L5: 45 | M5: 46093 | N5: 46108 | O5: Done | P5: Vidhya | Q5: None | R5: Kiruthiga | T5: https://dev.azure.com/heartlandschools/Mosaic/_git/BOH/pullrequest/48116 | U5: 46108 | V5: 46109 | W5: Charles | X5: None | Y5: Charles | Z5: 46109 | AA5: None | AB5: None | AC5: None | AE5: Meets Expectations
A6: 5 | B6: Meal Order | C6: 46101 | D6: 46114 | E6: 2.5 KaleidaNutrition S20 Stretch | F6: Nathiya | G6: 52222 | H6: [WAVE] Mosaic BOH Kaleida - Interior Pages Update - Setup - Mealviewer Display Groups | I6: Story Being Developed | J6: 8 | M6: 46106
A7: 6 | B7: Meal Order | C7: 46101 | D7: 46114 | E7: 2.5 KaleidaNutrition S20 Stretch | F7: Ruban | G7: 52427 | H7: [WAVE] Mosaic BOH - Updating the Apply Filters with a Search button on Vega updated screens | I7: Story Completed | J7: 3 | K7: 3 | L7: 12 | M7: 46104 | N7: 46105 | O7: Done | P7: Vidhya | Q7: None | R7: Kiruthiga | T7: https://dev.azure.com/heartlandschools/Mosaic/_git/BOH/pullrequest/47977?_a=files | U7: 46105 | V7: 46105 | W7: Charles | X7: None | Y7: Charles | Z7: 46105 | AA7: None | AB7: None | AC7: None | AE7: Meets Expectations

Sheet 2.5Kaleida Nutrition S21-Defect
A1: Sprint # | B1: Story/Defect ID | C1: Parent Story | D1: Developer | E1: Issue Type | F1: Issue Description | G1: Priority | H1: Defect Source | I1: Type | J1: Found By | K1: Status | L1: Root Cause Category | M1: RCA Comment *
A2: 2.5 KaleidaNutrition S21 | B2: 52850 | D2: Kiruthiga | F2: .Breadcrumb (“Setup > System Settings”) sits slightly left of the page title container, while the title is padded inside a white card. | G2: Medium | H2: Manual | I2: Internal | J2: Sudheer | K2: Completed | L2: New Issue | M2: The misalignment occurred because both the page content container and the Vega tab were using white backgrounds. This created an unnecessary extra background layer that did not align properly with the breadcrumb. To resolve this, we applied CSS changes to ensure proper alignment.

Sheet 2.5Kaleida Nutrition S20-Defect
A1: Sprint # | B1: Story/Defect ID | C1: Parent Story | D1: Developer | E1: Issue Type | F1: Issue Description | G1: Priority | H1: Defect Source | I1: Type | J1: Found By | K1: Status | L1: Root Cause Category | M1: RCA Comment *
A2: 2.5 KaleidaNutrition S20 | B2: 52553 | D2: Ruban | E2: Bounceback | F2: After deleting the grid data, I received a success message. Subsequently, when I opened another data set, an additional success message was displayed. | G2: Medium | H2: Manual | I2: External | J2: Vidhya | K2: Not Fixed | M2: Based on my earlier observations, I did not see this behavior before. Previously, after deleting the grid data, I would only receive the single expected success message, and opening another data set did not trigger an additional success notification. The extra success message is something I noticed only recently.

Sheet 2.5 KaleidaNutrition S19-Status
A1: S.No | B1: Application Name | C1: Sprint Start Date | D1: Sprint End Date | E1: Sprint | F1: Developer | G1: Story ID/Defect ID | H1: Description | I1: Status | J1: Estimated(sp) | K1: Actual(sp) | L1: Actual Hours Worklog | M1: Dev Start Date | N1: Dev End Date | O1: Unit testing | P1: Peer Tested By | Q1: Peer Tested Defects, if any | R1: Peer Reviewed By | S1: Peer Code Review Comments, if any | T1: PR Number/Link | U1: PR Created Date | V1: PR Approved Date | W1: Reviewer 1 | X1: Code Review Comments, if any | Y1: Reviewer 2 | Z1: Approved Date | AA1: Code Review Comments, if any2 | AB1: Internal PO -POV Comments | AC1: Client PO -POV Comments | AD1: Comments | AE1: Does this story meets expectations
A2: 1 | B2: Meal Order | C2: 46087 | D2: 46100 | E2: 2.5 KaleidaNutrition S19 Stretch | F2: Kiruthiga | G2: 52041 | H2: [WAVE] Mosaic BOH Kaleida - Interior Pages Update - Reports - Price Lists Report | I2: Story Being Tested | J2: 8 | M2: 46087
A3: 2 | B3: Meal Order | C3: 46087 | D3: 46100 | E3: 2.5 KaleidaNutrition S19 Stretch | F3: Nathiya | G3: 52042 | H3: [WAVE] Mosaic BOH Kaleida - Interior Pages Update - Reports - Product Notes Report | I3: Story Being Developed | J3: 13 | M3: 46087
A4: 3 | B4: Meal Order | C4: 46087 | D4: 46100 | E4: 2.5 KaleidaNutrition S19 Stretch | F4: Sudheer | G4: 51890 | H4: Meal Orders - Automation - Settings - Item Type Test Cases | I4: Story Completed | J4: 11 | K4: 11 | L4: 44 | M4: 46087 | N4: 46094 | O4: Sudheer | P4: Sudheer | T4: https://dev.azure.com/heartlandschools/Meal%20Orders/_git/MealOrdersAutomation/pullrequest/47595 | U4: 46093 | V4: 46094 | W4: owen | Y4: owen | Z4: 46094 | AE4: Meets Expectations
A5: 4 | B5: Meal Order | C5: 46087 | D5: 46100 | E5: 2.5 KaleidaNutrition S19 | F5: Sudheer | G5: 52197 | H5: Meal Orders - Regression - Admin Mode | I5: Story Completed | J5: 8 | K5: 8 | L5: 36 | M5: 46090 | N5: 46097 | P5: None | U5: None | V5: None | W5: None | Y5: None | Z5: None | AD5: Regression story | AE5: Meets Expectations
A6: 5 | B6: Meal Order | C6: 46087 | D6: 46100 | E6: 2.5 KaleidaNutrition S19 | F6: Sudheer | G6: 52223 | H6: Meal Orders(26.3) - Regression - Reports | I6: Story Completed | J6: 2 | K6: 2 | L6: 12 | M6: 46097 | N6: 46100 | P6: None | U6: None | V6: None | W6: None | Y6: None | Z6: None | AD6: Regression story | AE6: Meets Expectations
A7: 6 | B7: Meal Order | C7: 46087 | D7: 46100 | E7: 2.5 KaleidaNutrition S19 | F7: Ruban | G7: 52143 | H7: [WAVE] Mosaic BOH Kaleida - Interior Pages - HACCP - Categories | I7: Story Completed | J7: 5 | K7: 6 | L7: 24 | M7: 46097 | N7: 46100 | O7: Completed | P7: Vidhya | T7: https://dev.azure.com/heartlandschools/Mosaic/_git/BOH/pullrequest/47828 | U7: 46097 | V7: 46097 | W7: Ruban | Y7: Richard | Z7: 46097 | AE7: Meets Expectations

Sheet 2.5Kaleida Nutrition S18-Defect
A1: Sprint # | B1: Story/Defect ID | C1: Parent Story | D1: Developer | E1: Issue Type | F1: Issue Description | G1: Priority | H1: Defect Source | I1: Type | J1: Found By | K1: Status | L1: Root Cause Category | M1: RCA Comment *
A2: 2.5 KaleidaNutrition S18 | B2: 52007 | D2: Kiruthiga | E2: Bounceback | F2: The Ingredients module is displaying an incorrect page name. The main Maintenance section name has unexpectedly changed to “Search,” resulting in inconsistent menu labeling compared to previous versions and other related modules. | G2: Medium | H2: Manual | I2: External | J2: Sudheer | K2: Defect Fixed | L2: New Issue | M2: When navigating through the application, the labels displayed in the Ingredients and Products menu tiles do not match the expected configuration. In the Slack screenshot, the UI shows two cards labeled “Ingredients” and “Products,” each containing buttons such as Maintenance, Ingredient Search, and Bulk Fulfillment. However, the conversation indicates that the name of the main Maintenance section has unexpectedly changed to “Search.” This behavior suggests that the page title is being replaced incorrectly, resulting in inconsistent UI naming across the module.
A3: 2.5 KaleidaNutrition S18 | B3: 51818 | D3: Nathiya | E3: Bounceback | F3: Allergen dropdown flickering & Table Container Overlapping Header and Double Scroll Appearing Across All BOH Screens | G3: Medium | H3: Manual | I3: Internal | J3: Vidhya | K3: Defect Fixed | L3: New Issue | M3: A UI issue is observed in all BOH (Back of House) screens where a double scroll bar appears. When this double scroll is present, the table container shifts upward and overlaps or hides the page header. This behavior disrupts the layout structure and impacts readability and navigation across all implemented BOH screens.

Sheet 2.5 KaleidaNutrition S18-Status
A1: S.No | B1: Application Name | C1: Sprint Start Date | D1: Sprint End Date | E1: Sprint | F1: Developer | G1: Story ID/Defect ID | H1: Description | I1: Status | J1: Estimated(sp) | K1: Actual(sp) | L1: Actual Hours Worklog | M1: Dev Start Date | N1: Dev End Date | O1: Unit testing | P1: Peer Tested By | Q1: Peer Tested Defects, if any | R1: Peer Reviewed By | S1: Peer Code Review Comments, if any | T1: PR Number/Link | U1: PR Created Date | V1: PR Approved Date | W1: Reviewer 1 | X1: Code Review Comments, if any | Y1: Reviewer 2 | Z1: Approved Date | AA1: Code Review Comments, if any2 | AB1: Internal PO -POV Comments | AC1: Client PO -POV Comments | AD1: Comments | AE1: Does this story meets expectations
A2: 1 | B2: Meal Order | C2: 46073 | D2: 46086 | E2: 2.5 KaleidaNutrition S18 | F2: Kiruthiga | G2: 52007 | H2: [WAVE] - Mosaic BOH Kaleida - Left Navigation - Update Root Menus - Ingredients, Menus, Recipes, Products, Inventory, Ordering | I2: Story Completed | J2: 8 | K2: 8 | L2: 40 | M2: 46073 | N2: 46083 | O2: Completed | P2: Sudheer | Q2: None | T2: https://dev.azure.com/heartlandschools/Mosaic/_git/BOH/pullrequest/47555?_a=files | U2: 46083 | V2: 46084 | W2: Ruban | X2: None | Y2: Richard | Z2: 46084 | AA2: None | AB2: None | AE2: Meets Expectations
A3: 2 | B3: Meal Order | C3: 46073 | D3: 46086 | E3: 2.5 KaleidaNutrition S18 | F3: Kiruthiga | G3: 26813 | H3: BOH - App switcher - App tray underline issues | I3: Defect Fixed | J3: 1 | K3: 1 | L3: 2 | M3: 46073 | N3: 46073 | O3: Completed | P3: Vidhya | Q3: None | T3: https://dev.azure.com/heartlandschools/Mosaic/_git/BOH/pullrequest/47367 | U3: 46073 | V3: 46073 | W3: Ruban | X3: None | Y3: Richard | Z3: 46073 | AA3: None | AB3: None | AE3: Meets Expectations
A4: 3 | B4: Meal Order | C4: 46073 | D4: 46086 | E4: 2.5 KaleidaNutrition S18 | F4: Kiruthiga | G4: 26813 | H4: FOH - App switcher - App tray underline issues | I4: Defect Fixed | J4: 1 | K4: 1 | L4: 2 | M4: 46073 | N4: 46073 | O4: Completed | P4: Vidhya | Q4: None | T4: https://dev.azure.com/heartlandschools/Mosaic/_git/FOH/pullrequest/47362 | U4: 46073 | V4: 46073 | W4: Ruban | X4: None | Y4: Richard | Z4: 46073 | AA4: None | AB4: None | AE4: Meets Expectations
A5: 4 | B5: Meal Order | C5: 46073 | D5: 46086 | E5: 2.5 KaleidaNutrition S18 | F5: Nathiya | G5: 51818 | H5: [WAVE] - Mosaic BOH Kaleida - Interior Pages Update - Reports - Ingredients Allergens List | I5: Story Completed | J5: 5 | K5: 13 | L5: 60 | M5: 46073 | N5: 46084 | O5: Completed | P5: Vidhya | Q5: None | R5: Kiruthiga | S5: Code optimization to have a common function to set/get element values. | T5: https://dev.azure.com/heartlandschools/Mosaic/_git/BOH/pullrequest/47586 | U5: 46084 | V5: 46084 | W5: Ruban | X5: None | Y5: Richard | Z5: 46084 | AA5: None | AB5: None | AC5: Use Vega Combo box instead of Vega Input Select | AD5: We included additional functionalities - Retain filters on page refresh which required additional efforts | AE5: Meets Expectations
A6: 5 | B6: Meal Order | C6: 46073 | D6: 46086 | E6: 2.5 KaleidaNutrition S18 Stretch | F6: Sudheer | G6: 51890 | H6: Meal Orders - Automation - Settings - Item Type Test Cases | I6: Story Being Developed | J6: 8 | K6: 8 | L6: 40 | M6: 46076 | N6: 46085 | O6: Completed | P6: Sudheer | T6: https://dev.azure.com/heartlandschools/Meal%20Orders/_git/MealOrdersAutomation/pullrequest/47595 | U6: 46085 | W6: Owen | Y6: Owen | AD6: Few validations are missing , after creating the test data

Sheet 2.5 KaleidaNutrition S17-Status
A1: S.No | B1: Application Name | C1: Sprint Start Date | D1: Sprint End Date | E1: Sprint | F1: Developer | G1: Story ID/Defect ID | H1: Description | I1: Status | J1: Estimated(sp) | K1: Actual(sp) | L1: Actual Hours Worklog | M1: Dev Start Date | N1: Dev End Date | O1: Unit testing | P1: Peer Tested By | Q1: Peer Tested Defects, if any | R1: Peer Reviewed By | S1: Peer Code Review Comments, if any | T1: PR Number/Link | U1: PR Created Date | V1: PR Approved Date | W1: Reviewer 1 | X1: Code Review Comments, if any | Y1: Reviewer 2 | Z1: Approved Date | AA1: Code Review Comments, if any2 | AB1: Internal PO -POV Comments | AC1: Client PO -POV Comments | AD1: Comments | AE1: Does this story meets expectations
A2: 1 | B2: Meal Order | C2: 46059 | D2: 46072 | E2: 2.5 KaleidaNutrition S17 | F2: Ruban | G2: 26741 | H2: Mosaic FOH- App switcher issues with item availability | I2: Defect Fixed | J2: 2 | K2: 2 | L2: 5 | M2: 46058 | N2: 46059 | O2: Completed | P2: Kiruthiga | R2: Kiruthiga | T2: https://dev.azure.com/heartlandschools/Mosaic/_git/FOH/pullrequest/47117?_a=files | U2: 46059 | V2: 46059 | W2: Ruban | Y2: Steven | Z2: 46059
A3: 2 | B3: Meal Order | C3: 46059 | D3: 46072 | E3: 2.5 KaleidaNutrition S17 | F3: Kiruthiga | G3: 26742 | H3: Mosaic BOH- App switcher issues with item availability | I3: Defect Fixed | J3: 2 | K3: 2 | L3: 5 | M3: 46058 | N3: 46059 | O3: Completed | P3: Ruban | R3: Ruban | T3: https://dev.azure.com/heartlandschools/Mosaic/_git/BOH/pullrequest/47124?_a=files | U3: 46059 | V3: 46059 | W3: Ruban | Y3: Richard | Z3: 46059
A4: 3 | B4: Meal Order | C4: 46059 | D4: 46072 | E4: 2.5 KaleidaNutrition S17 | F4: Dhivyalakshmi | G4: 51380 | H4: [WAVE] - BOH Kaleida - Interior Pages Update - Setup - Inventory Adjustment Reasons | I4: Story Completed | J4: 3 | K4: 6 | L4: 24 | M4: 46050 | N4: 46064 | O4: Completed | P4: Vidya | R4: Kiruthiga | T4: https://dev.azure.com/heartlandschools/Mosaic/_git/BOH/pullrequest/47204 | U4: 46064 | V4: 46064 | W4: Ruban | Y4: Richard | Z4: 46064
A5: 4 | B5: Meal Order | C5: 46059 | D5: 46072 | E5: 2.5 KaleidaNutrition S17 | F5: Kiruthiga | G5: 50603 | H5: [WAVE] - Meal Orders - Add Search Functionality to the District selector | I5: Story Completed | J5: 5 | K5: 5 | L5: 20 | M5: 46062 | N5: 46065 | O5: Completed | P5: Sudheer | R5: Ruban | T5: https://dev.azure.com/heartlandschools/Meal%20Orders/_git/Meal%20Orders/pullrequest/47226 | U5: 46065 | V5: 46066 | W5: Ruban | Y5: Ruban | Z5: 46066
A6: 5 | B6: Meal Order | C6: 46059 | D6: 46072 | E6: 2.5 KaleidaNutrition S17 Stretch | F6: Sudheer | G6: 51890 | H6: Meal Orders - Automation - Settings - Item Type Test Cases | I6: Story Being Developed | J6: 8 | M6: 46065
A7: 6 | B7: Meal Order | C7: 46059 | D7: 46072 | E7: 2.5 KaleidaNutrition S17 Stretch | F7: Sudheer | G7: 51384 | H7: Meal Orders - Automation - Settings - Serving Periods And data related issue fixes | I7: Story Completed | J7: 13 | K7: 13 | L7: 60 | M7: 46045 | N7: 46062 | O7: Completed | P7: Sudheer | R7: Owen | T7: https://dev.azure.com/heartlandschools/Meal%20Orders/_git/MealOrdersAutomation/pullrequest/46761 | U7: 46062 | V7: 46063 | W7: Owen | Y7: Owen | Z7: 46063
A8: 7 | B8: Meal Order | C8: 46059 | D8: 46072 | E8: 2.5 KaleidaNutrition S17 Stretch | F8: Kiruthiga | G8: 51917 | H8: Meal Orders - App switcher - listing apptray item based on logged in user | I8: Story Peer Review | J8: 3 | K8: 3 | L8: 12 | M8: 46065 | N8: 46072 | O8: Completed | P8: Sudheer | T8: https://dev.azure.com/heartlandschools/Meal%20Orders/_git/Meal%20Orders/pullrequest/47358 | U8: 46072
A9: 8 | B9: Meal Order | C9: 46059 | D9: 46072 | E9: 2.5 KaleidaNutrition S17 Stretch | F9: Ruban | G9: 51731 | H9: [WAVE] - Mosaic BOH Kaleida - Interior Pages Update - Vendors Search | I9: Story Completed | J9: 8 | K9: 8 | L9: 36 | M9: 46059 | N9: 46066 | O9: Completed | P9: ken/Sudheer | R9: Kiruthiga | T9: https://dev.azure.com/heartlandschools/Meal%20Orders/_git/Meal%20Orders/pullrequest/47226 | U9: 46066 | V9: 46069 | W9: Ruban | Y9: Steven | Z9: 46069

Sheet 2.5Kaleida Nutrition S17-Defect
A1: Sprint # | B1: Story/Defect ID | C1: Parent Story | D1: Developer | E1: Issue Type | F1: Issue Description | G1: Priority | H1: Defect Source | I1: Type | J1: Found By | K1: Status | L1: Root Cause Category | M1: RCA Comment *
A2: 2.5 KaleidaNutrition S17 | B2: 51380 | D2: Dhivyalakshmi / Nathiya | E2: Bounceback | F2: 1.Page title briefly flashes during load: “Inventory Adjustment Reasons” is visible before UI is ready and Row background color mismatches on row ends when adding a new Adjustment Reason | G2: Medium | H2: Manual | I2: External | J2: Vidhya | K2: Defect Fixed | L2: New Issue
A3: 2.5 KaleidaNutrition S17 | B3: 51380 | D3: Dhivyalakshmi / Nathiya | E3: Bounceback | F3: 2.Input row not visible when +Add is clicked on page >1; user must be navigated to page 1 | G3: Medium | H3: Manual | I3: External | J3: Vidhya | K3: Defect Fixed | L3: New Issue
A4: 2.5 KaleidaNutrition S17 Stretch | B4: 51731 | D4: Ruban | E4: Bounceback | F4: Reset button disabled when filter applied | G4: Medium | H4: Manual | I4: External | J4: Sudheer | K4: Defect Fixed | L4: New Issue

Sheet 2.5 KaleidaNutrition S16-Status
A1: S.No | B1: Application Name | C1: Sprint Start Date | D1: Sprint End Date | E1: Sprint | F1: Developer | G1: Story ID/Defect ID | H1: Description | I1: Status | J1: Estimated(sp) | K1: Actual(sp) | L1: Actual Hours Worklog | M1: Dev Start Date | N1: Dev End Date | O1: Unit testing | P1: Peer Tested By | Q1: Peer Tested Defects, if any | R1: Peer Reviewed By | S1: Peer Code Review Comments, if any | T1: PR Number/Link | U1: PR Created Date | V1: PR Approved Date | W1: Reviewer 1 | X1: Code Review Comments, if any | Y1: Reviewer 2 | Z1: Approved Date | AA1: Code Review Comments, if any2 | AB1: Internal PO -POV Comments | AC1: Client PO -POV Comments | AD1: Comments | AE1: Does this story meets expectations
A2: 1 | B2: Meal Order | C2: 46045 | D2: 46058 | E2: 2.5 KaleidaNutrition S16 | F2: Kiruthiga | G2: 51246 | H2: [WAVE] - App switcher - Install on Meal Orders | I2: Story Completed | J2: 8 | K2: 6 | L2: 24 | M2: 46045 | N2: 46056 | O2: Completed | P2: Sudheer | T2: https://dev.azure.com/heartlandschools/Meal%20Orders/_git/Meal%20Orders/pullrequest/47029 | U2: 46056 | V2: 46056 | W2: Ruba | Y2: Mike | Z2: 46056 | AD2: 30/1: There is an issue with Cosmo DB installation. It has been resolved now.
A3: 2 | B3: Meal Order | C3: 46045 | D3: 46058 | E3: 2.5 KaleidaNutrition S16 | F3: Ruban | G3: 51377 | H3: [WAVE] - Mosaic BOH Kaleida - Interior Pages Update - Setup - Allergens - Search & Add | I3: Story Completed | J3: 8 | K3: 8 | L3: 36 | M3: 46031 | N3: 46051 | O3: Completed | P3: Vidhya | T3: https://dev.azure.com/heartlandschools/Mosaic/_git/BOH/pullrequest/46960 | U3: 46051 | V3: 46052 | W3: Richard | Y3: Richard | Z3: 46052 | AC3: We have Active as the filter at the top and Enabled at the bottom.
A4: 3 | B4: Meal Order | C4: 46045 | D4: 46058 | E4: 2.5 KaleidaNutrition S16 | F4: Dhivyalakshmi | G4: 51359 | H4: [WAVE] MSB Accounting Kaleida - Update Login screen | I4: Story Completed | J4: 3 | K4: 8 | L4: 12 | M4: 46023 | N4: 46050 | O4: Completed | P4: Vidhya | T4: https://dev.azure.com/heartlandschools/Accounting/_git/MSBAccounting-NewSchoolBooks/pullrequest/469… | U4: 46050 | V4: NA | W4: NA | Y4: NA | Z4: NA | AD4: Draft PR has been created, Due to priority change it been hold and we have less possibilty to close this story
A5: 4 | B5: Meal Order | C5: 46045 | D5: 46058 | E5: 2.5 KaleidaNutrition S16 Stretch | F5: Dhivyalakshmi | G5: 51380 | H5: [WAVE] - BOH Kaleida - Interior Pages Update - Setup - Inventory Adjustment Reasons | I5: Story Being Developed | J5: 8 | M5: 46050
A6: 5 | B6: Meal Order | C6: 46045 | D6: 46058 | E6: 2.5 KaleidaNutrition S16 Stretch | F6: Sudheer | G6: 51384 | H6: Meal Orders - Automation - Settings - Serving Periods And data related issue fixes | I6: Story Being Developed | J6: 8 | M6: 46028 | T6: https://dev.azure.com/heartlandschools/Meal%20Orders/_git/MealOrdersAutomation/pullrequest/46761 | U6: 46043 | W6: Owen | Y6: Owen | AD6: PR created. After the login loop code changes, when executing the test scripts multiple times, a few tests failed due to data-related issues. After discussion, we decided to fix these issues as part of this PR, and the story points were increased accordingly.

Sheet 2.5 KaleidaNutrition S15-Status
A1: S.No | B1: Application Name | C1: Sprint Start Date | D1: Sprint End Date | E1: Sprint | F1: Developer | G1: Story ID/Defect ID | H1: Description | I1: Status | J1: Estimated(sp) | K1: Actual(sp) | L1: Actual Hours Worklog | M1: Dev Start Date | N1: Dev End Date | O1: Unit testing | P1: Peer Tested By | Q1: Peer Tested Defects, if any | R1: Peer Reviewed By | S1: Peer Code Review Comments, if any | T1: PR Number/Link | U1: PR Created Date | V1: PR Approved Date | W1: Reviewer 1 | X1: Code Review Comments, if any | Y1: Reviewer 2 | Z1: Approved Date | AA1: Code Review Comments, if any2 | AB1: Internal PO -POV Comments | AC1: Client PO -POV Comments | AD1: Comments | AE1: Does this story meets expectations
A2: 1 | B2: Meal Order | C2: 46031 | D2: 46044 | E2: 2.5 KaleidaNutrition S15 | F2: Kiruthiga | G2: 50838 | H2: [WAVE] - Web - BOH Kaleida - App switcher | I2: Story Completed | J2: 8 | K2: 6 | L2: 29 | M2: 46031 | N2: 46042 | O2: Completed | P2: Vidhya | T2: https://dev.azure.com/heartlandschools/Mosaic/_git/BOH/pullrequest/46745 | U2: 46042 | V2: 46042 | W2: Ruban | Y2: Richard | Z2: 46042 | AD2: Dev changes has been completed but still need a confirmation about the reflection of feature flag update as it requires logout action
A3: 2 | B3: Meal Order | C3: 46031 | D3: 46044 | E3: 2.5 KaleidaNutrition S15 Stretch | F3: Sudheer | G3: 51384 | H3: Meal Orders - Automation - Settings - Serving Periods | I3: Story Being Developed | J3: 8 | K3: 8 | L3: 32 | M3: 46028 | N3: 46043 | O3: Completed | P3: Sudheer | T3: https://dev.azure.com/heartlandschools/Meal%20Orders/_git/MealOrdersAutomation/pullrequest/46761 | U3: 46043 | W3: Owen | Y3: Owen | AD3: PR is ceated but one of the test got failed for owen due to date related issue, looking into issue.
A4: 3 | B4: Meal Order | C4: 46031 | D4: 46044 | E4: 2.5 KaleidaNutrition S15 | F4: Sudheer | G4: 51122 | H4: Meal Orders - Automation - Settings - Special Diet | I4: Story Completed | J4: 8 | K4: 8 | L4: 32 | M4: 46031 | N4: 46042 | O4: Completed | P4: Sudheer | T4: https://dev.azure.com/heartlandschools/Meal%20Orders/_git/MealOrdersAutomation/pullrequest/46399 | U4: 46031 | V4: 46043 | W4: Owen | Y4: Owen | Z4: 46043
A5: 4 | B5: Meal Order | C5: 46031 | D5: 46044 | E5: 2.5 KaleidaNutrition S15 Stretch | F5: Ruban | G5: 51377 | H5: [WAVE] - Mosaic BOH Kaleida - Interior Pages Update - Setup - Allergens - Search & Add | I5: Story Being Developed | J5: 13 | M5: 46031
A6: 5 | B6: Meal Order | C6: 46031 | D6: 46044 | E6: 2.5 KaleidaNutrition S15 Stretch | F6: Dhivyalakshmi | G6: 51359 | H6: [WAVE] MSB Accounting Kaleida - Update Login screen | I6: Story Being Developed | J6: 8 | K6: 11 | L6: 52 | M6: 46037

Sheet 2.5Kaleida Nutrition S14-Defect
A1: Sprint # | B1: Story/Defect ID | C1: Parent Story | D1: Developer | E1: Issue Type | F1: Issue Description | G1: Priority | H1: Defect Source | I1: Type | J1: Found By | K1: Status | L1: Root Cause Category | M1: RCA Comment *

Sheet 2.5 KaleidaNutrition S14-Status
A1: S.No | B1: Application Name | C1: Sprint Start Date | D1: Sprint End Date | E1: Sprint | F1: Developer | G1: Story ID/Defect ID | H1: Description | I1: Status | J1: Estimated(sp) | K1: Actual(sp) | L1: Actual Hours Worklog | M1: Dev Start Date | N1: Dev End Date | O1: Unit testing | P1: Peer Tested By | Q1: Peer Tested Defects, if any | R1: Peer Reviewed By | S1: Peer Code Review Comments, if any | T1: PR Number/Link | U1: PR Created Date | V1: PR Approved Date | W1: Reviewer 1 | X1: Code Review Comments, if any | Y1: Reviewer 2 | Z1: Approved Date | AA1: Code Review Comments, if any2 | AB1: Internal PO -POV Comments | AC1: Client PO -POV Comments | AD1: Comments | AE1: Does this story meets expectations
A2: 1 | B2: Meal Order | C2: 46003 | D2: 46030 | E2: 2.5 KaleidaNutrition S14 | F2: Sudheer | G2: 50670 | H2: Meal Orders - Automation - Regression - Allergens | I2: Story Completed | J2: 1 | K2: 1 | L2: 4 | M2: 46003 | N2: 46009 | O2: Sudheer | R2: Owen | T2: https://dev.azure.com/heartlandschools/Meal%20Orders/_git/MealOrdersAutomation/pullrequest/46004 | U2: 46009 | V2: 46009 | W2: Owen | Y2: NA
A3: 2 | B3: Meal Order | C3: 46003 | D3: 46030 | E3: 2.5 KaleidaNutrition S14 | F3: Kiruthiga | G3: 50839 | H3: [WAVE] - Web - FOH Kaleida - App switcher | I3: Story Completed | J3: 8 | K3: 8 | L3: 41 | M3: 46003 | N3: 46024 | O3: Completed | P3: Vidhya | R3: Ruban | T3: https://dev.azure.com/heartlandschools/Mosaic/_git/FOH/pullrequest/46412 | U3: 46027 | V3: 46027 | W3: Ruban | Y3: Ying | Z3: 46027
A4: 3 | B4: Meal Order | C4: 46003 | D4: 46030 | E4: 2.5 KaleidaNutrition S14 | F4: Dhivyalakshmi | G4: 49084 | H4: [WAVE] MSB Accounting - Update Page Footer - Webview | I4: Story Completed | J4: 8 | K4: 15 | L4: 70 | M4: 46003 | N4: 46027 | O4: Completed | P4: Kiruthiga | R4: Kiruthiga | T4: https://dev.azure.com/heartlandschools/Accounting/_git/MSBAccounting-NewSchoolBooks/pullrequest/46416 | U4: 46027 | V4: 46027 | W4: Ruban | Y4: Qadir | Z4: 46027
A5: 4 | B5: Meal Order | C5: 46003 | D5: 46030 | E5: 2.5 KaleidaNutrition S14 | F5: Ruban/Karthikeyan | G5: 50980 | H5: [WAVE] - Mosaic FOH - Interior Pages - Close day Reports search | I5: Story Completed | J5: 8 | K5: 22 | L5: 90 | M5: 46003 | N5: 46029 | O5: Completed | P5: Vidhya | R5: Kiruthiga | T5: https://dev.azure.com/heartlandschools/Mosaic/_git/FOH/pullrequest/46489 | U5: 46029 | V5: 46029 | W5: Ruban | Y5: Ying | Z5: 46030 | AD5: There was a delay on testing this story because of the deployment issue also story was under estimated
A6: 5 | B6: Meal Order | C6: 46003 | D6: 46030 | E6: 2.5 KaleidaNutrition S14 Stretch | F6: Sudheer | G6: 51122 | H6: Meal Orders - Automation - Settings - Special Diet | I6: Story Peer Review | J6: 8 | K6: 8 | L6: 36 | M6: 46022 | O6: Completed | P6: Sudheer | R6: Owen | T6: https://dev.azure.com/heartlandschools/Meal%20Orders/_git/MealOrdersAutomation/pullrequest/46399
A7: 6 | B7: Meal Order | C7: 46003 | D7: 46030 | E7: 2.5 KaleidaNutrition S14 Stretch | F7: Sudheer | G7: 51384 | H7: Meal Orders - Automation - Settings - Serving Periods | I7: Story Being Developed | J7: 8 | K7: 8 | L7: 40 | M7: 46028
F9: Wave | G9: MealOrders | H9: Total
E10: Completed Story Points | F10: 8 | G10: 19 | H10: 27

Sheet Defect-template
A1: S.No | B1: Sprint # | C1: Story/Defect ID | D1: Parent Story | E1: Developer | F1: Issue Type | G1: Issue Description | H1: Priority | I1: Defect Source | J1: Type | K1: Status | L1: Root Cause Category | M1: Comments
F2: None

Sheet 2.5 KaleidaNutrition S13-Status
A1: S.No | B1: Application Name | C1: Sprint Start Date | D1: Sprint End Date | E1: Sprint | F1: Developer | G1: Story ID/Defect ID | H1: Description | I1: Status | J1: Estimated(sp) | K1: Actual(sp) | L1: Actual Hours Worklog | M1: Dev Start Date | N1: Dev End Date | O1: Unit testing | P1: Peer Tested By | Q1: Peer Tested Defects, if any | R1: Peer Reviewed By | S1: Peer Code Review Comments, if any | T1: PR Number/Link | U1: PR Created Date | V1: PR Approved Date | W1: Reviewer 1 | X1: Code Review Comments, if any | Y1: Reviewer 2 | Z1: Approved Date | AA1: Code Review Comments, if any2 | AB1: Internal PO -POV Comments | AC1: Client PO -POV Comments | AD1: Comments | AE1: Does this story meets expectations
A2: 1 | B2: Meal Order | C2: 45975 | D2: 46002 | E2: 2.5 KaleidaNutrition S13 | F2: Kiruthiga | G2: 50774 | H2: [WAVE] FOH Kaleida - Login - Update server-side validation error message UI | I2: Story Completed | J2: 2 | K2: 2 | L2: 8 | M2: 45975 | N2: 45978 | O2: Completed | P2: Vidhya | R2: Ruban | T2: https://dev.azure.com/heartlandschools/Mosaic/_git/FOH/pullrequest/45763 | U2: 45978 | V2: 45978 | W2: Ruban | Y2: Ying | Z2: 45978 | AE2: Meets Expectation
A3: 2 | B3: Meal Order | C3: 45975 | D3: 46002 | E3: 2.5 KaleidaNutrition S13 | F3: Kiruthiga/Dhivya/Shikha | G3: 50756 | H3: [WAVE] - MSB Accounting (Setup/Discovery) | I3: Story Completed | J3: 13 | K3: 13 | L3: 52 | M3: 45975 | N3: 46001 | O3: Completed | P3: NA | R3: NA | T3: NA | AD3: It is a discovery story, Completed dev setup for the new project to update Kaleida changes | AE3: Meets Expectation
A4: 3 | B4: Meal Order | C4: 45975 | D4: 46002 | E4: 2.5 KaleidaNutrition S13 | F4: Ruban | G4: 50463 | H4: [WAVE] Mosaic FOH Kaleida - Interior Pages update - Catering - Add Catering Menus | I4: Story Completed | J4: 8 | K4: 8 | L4: 32 | M4: 45975 | N4: 45995 | O4: Completed | P4: Vidhya | R4: NA | T4: https://dev.azure.com/heartlandschools/Mosaic/_git/FOH/pullrequest/46084 | U4: 45995 | V4: 45995 | W4: Ruban | Y4: Ying | Z4: 45995 | AE4: Meets Expectation
A5: 4 | B5: Meal Order | C5: 45975 | D5: 46002 | E5: 2.5 KaleidaNutrition S13 | F5: Kiruthiga | G5: 50132 | H5: [WAVE] - SSO Login screen - Mosaic FOH Kaleida update | I5: Story Completed | J5: 3 | K5: 3 | L5: 12 | M5: 45965 | N5: 45974 | O5: Completed | P5: Ken | R5: Kiruthiga | T5: https://dev.azure.com/heartlandschools/Mosaic/_git/FOH/pullrequest/45654 | U5: 45965 | V5: 45974 | W5: Ruban | Y5: Mills | Z5: 45974 | AE5: Meets Expectation
A6: 5 | B6: Meal Order | C6: 45975 | D6: 46002 | E6: 2.5 KaleidaNutrition S13 | F6: Dhivyalakshmi | G6: 50465 | H6: [WAVE] Mosaic FOH Kaleida - Interior Pages update - Professional standards screens - ​Employees | I6: Story Completed | J6: 13 | K6: 13 | L6: 52 | M6: 45995 | N6: 45996 | O6: Completed | P6: Vidhya | R6: Kiruthiga | T6: https://dev.azure.com/heartlandschools/Mosaic/_git/FOH/pullrequest/46088 | U6: 45996 | V6: 45996 | W6: Ruban | Y6: Ying | Z6: 45996 | AE6: Meets Expectation
A7: 6 | B7: Meal Order | C7: 45975 | D7: 46002 | E7: 2.5 KaleidaNutrition S13 Stretch | F7: Kiruthiga | G7: 50896 | H7: [WAVE] - FOH - Display Page Title on Pages Without Breadcrumb-Level Navigation | I7: Story Completed | J7: 3 | K7: 3 | L7: 12 | M7: 45980 | N7: 45982 | O7: Completed | P7: Vidhya | R7: Ruban | T7: https://dev.azure.com/heartlandschools/Mosaic/_git/FOH/pullrequest/45892 | U7: 45985 | V7: 45986 | W7: Ruban | Y7: Mills | Z7: 45986 | AE7: Meets Expectation
A8: 7 | B8: Meal Order | C8: 45975 | D8: 46002 | E8: 2.5 KaleidaNutrition S13 Stretch | F8: Kiruthiga | G8: 26326 | H8: [WAVE] - FOH - Left navigation not highlighted properly | I8: Story Completed | J8: 3 | K8: 3 | L8: 12 | M8: 45985 | N8: 45988 | O8: Completed | P8: Vidhya | R8: Ruban | T8: https://dev.azure.com/heartlandschools/Mosaic/_git/FOH/pullrequest/45953 | U8: 46018 | V8: 45992 | W8: Ruban | Y8: Ying | Z8: 45992 | AE8: Meets Expectation
A9: 8 | B9: Meal Order | C9: 45975 | D9: 46002 | E9: 2.5 KaleidaNutrition S13 Stretch | F9: Kiruthiga | G9: 26420 | H9: Mosaic FOH Kaleida - Left nav auto expands when browser window resized | I9: Story Completed | J9: 1 | K9: 1 | L9: 4 | M9: 45999 | N9: 45999 | O9: Completed | P9: Ken | R9: Ruban | T9: https://dev.azure.com/heartlandschools/Mosaic/_git/FOH/pullrequest/46109?_a=files | U9: 45999 | V9: 45999 | W9: Ruban | Y9: Ying | Z9: 45999 | AE9: Meets Expectation
A10: 9 | B10: Meal Order | C10: 45975 | D10: 46002 | E10: 2.5 KaleidaNutrition S13 Stretch | F10: Sudheer | G10: 50670 | H10: Meal Orders - Automation - Regression - Allergens | I10: Story Being Developed | J10: 8 | K10: 8 | L10: 32 | M10: 45978 | N10: 45999 | O10: Completed | P10: Sudher | R10: owen | T10: https://dev.azure.com/heartlandschools/Meal%20Orders/_git/MealOrdersAutomation/pullrequests?_a=mine | U10: 46000 | W10: Owen | Y10: owen | AD10: One test case got failed due to data
A11: 10 | B11: Meal Order | C11: 45975 | D11: 46002 | E11: 2.5 KaleidaNutrition S13 Stretch | F11: Kiruthiga | G11: 50838 | H11: [WAVE] - Web- BOH Kaleida - App switcher | I11: Story Being Developed | J11: 8 | M11: 45992

Sheet 2.5 KaleidaNutrition S12-Status
A1: S.No | B1: Application Name | C1: Sprint Start Date | D1: Sprint End Date | E1: Sprint | F1: Developer | G1: Story ID/Defect ID | H1: Description | I1: Status | J1: Estimated(sp) | K1: Actual(sp) | L1: Actual Hours Worklog | M1: Dev Start Date | N1: Dev End Date | O1: Unit testing | P1: Peer Tested By | Q1: Peer Tested Defects, if any | R1: Peer Reviewed By | S1: Peer Code Review Comments, if any | T1: PR Number/Link | U1: PR Created Date | V1: PR Approved Date | W1: Reviewer 1 | X1: Code Review Comments, if any | Y1: Reviewer 2 | Z1: Approved Date | AA1: Code Review Comments, if any2 | AB1: Internal PO -POV Comments | AC1: Client PO -POV Comments | AD1: Comments | AE1: Does this story meets expectations
A2: 1 | B2: Meal Order | C2: 45961 | D2: 45974 | E2: 2.5 KaleidaNutrition S12 Stretch | F2: Sudheer | G2: 50670 | H2: Meal Orders - Automation - Regression - Allergens | I2: Story Completed | J2: 8 | K2: 8 | L2: 32 | M2: 45967 | N2: 45993 | O2: Sudheer | R2: Owen | T2: https://dev.azure.com/heartlandschools/Meal%20Orders/_git/MealOrdersAutomation/pullrequests?_a=mine | U2: 45993 | V2: 46000 | W2: Owen | Y2: Owen | Z2: 46000
A3: 2 | B3: Meal Order | C3: 45961 | D3: 45974 | E3: 2.5 KaleidaNutrition S12 | F3: Kiruthiga | G3: 50132 | H3: [WAVE] - SSO Login screen - Mosaic FOH Kaleida update | I3: Story Ready For Testing | J3: 8 | K3: 10 | L3: 40 | M3: 45961 | N3: 45968 | O3: Completed | P3: Vidhya | R3: Ruban | T3: https://dev.azure.com/heartlandschools/Mosaic/_git/FOH/pullrequest/45654 | U3: 45965 | V3: 45974 | W3: Ruban | Y3: Mills | Z3: 45974 | AD3: Although the development changes were completed on time and a recording of the changes was shared, the client expected a POV to test all scenarios. However, due to the client's unavailability, there was a delay in presenting the POV and receiving feedback, which resulted in a delay in testing
A4: 3 | B4: Meal Order | C4: 45961 | D4: 45974 | E4: 2.5 KaleidaNutrition S12 | F4: Dhivyalakshmi | G4: 50133 | H4: [WAVE] Mosaic FOH Kaleida - Interior Pages update - Catering | I4: Story Completed | J4: 2 | K4: 2 | L4: 6 | M4: 45961 | N4: 45961 | P4: Vidhya | R4: Kiruthiga | T4: https://dev.azure.com/heartlandschools/Mosaic/_git/FOH/pullrequest/45405 | U4: 45961 | V4: 45964 | W4: Ruban | Y4: Mills | Z4: 45964 | AE4: Meets Expectation
A5: 4 | B5: Meal Order | C5: 45961 | D5: 45974 | E5: 2.5 KaleidaNutrition S12 | F5: Ruban | G5: 50146 | H5: [WAVE] Mosaic FOH Kaleida - Interior Pages update - Catering - Add Order & edit Order | I5: Story Completed | J5: 4 | K5: 4 | L5: 24 | M5: 45961 | N5: 45969 | P5: Vidhya | R5: Kiruthiga | T5: https://dev.azure.com/heartlandschools/Mosaic/_git/FOH/pullrequest/45583 | U5: 45969 | V5: 45969 | W5: Ying | Y5: Ying | Z5: 45969 | AE5: Meets Expectation
A6: 5 | B6: Meal Order | C6: 45961 | D6: 45974 | E6: 2.5 KaleidaNutrition S12 | F6: Dhivyalakshmi | G6: 50602 | H6: [WAVE] - Meal Orders - District Selector - Arrange the districts in Alphabetical Order | I6: Story Completed | J6: 3 | K6: 3 | L6: 12 | M6: 45964 | N6: 45966 | P6: Sudheer | R6: Ruban | T6: https://dev.azure.com/heartlandschools/Meal%20Orders/_git/Meal%20Orders/pullrequest/45527 | U6: 45967 | V6: 45968 | W6: Ruban | Y6: Mike | Z6: 45968 | AE6: Meets Expectation
A7: 6 | B7: Meal Order | C7: 45961 | D7: 45974 | E7: 2.5 KaleidaNutrition S12 Stretch | F7: Dhivyalakshmi | G7: 50465 | H7: [WAVE] Mosaic FOH Kaleida - Interior Pages update - Professional standards screens - ​Employees | I7: Story Completed | J7: 13 | K7: 13 | L7: 52 | M7: 45967 | N7: 46000 | O7: Completed | P7: Vidhya | R7: Ruban | U7: 46000 | V7: 46001 | W7: Ruban | Y7: Mike | Z7: 46001 | AE7: Meets Expectation

Sheet 2.5 KaleidaNutrition S11-Status
A1: S.No | B1: Application Name | C1: Sprint Start Date | D1: Sprint End Date | E1: Sprint | F1: Developer | G1: Story ID/Defect ID | H1: Description | I1: Status | J1: Estimated(sp) | K1: Actual(sp) | L1: Actual Hours Worklog | M1: Dev Start Date | N1: Dev End Date | O1: Unit testing | P1: Peer Tested By | Q1: Peer Tested Defects, if any | R1: Peer Reviewed By | S1: Peer Code Review Comments, if any | T1: PR Number/Link | U1: PR Created Date | V1: PR Approved Date | W1: Reviewer 1 | X1: Code Review Comments, if any | Y1: Reviewer 2 | Z1: Approved Date | AA1: Code Review Comments, if any2 | AB1: Internal PO -POV Comments | AC1: Client PO -POV Comments | AD1: Comments | AE1: Does this story meets expectations
A2: 1 | B2: Meal Order | C2: 45947 | D2: 45960 | E2: 2.5 KaleidaNutrition S11 | F2: Kiruthiga | G2: 50151 | H2: [WAVE] Mosaic FOH Kaleida - Login - Pending Updates | I2: Story Completed | J2: 5 | K2: 8 | L2: 33 | M2: 45951 | N2: 45957 | O2: Completed | P2: Vidhya | T2: https://dev.azure.com/heartlandschools/Mosaic/_git/FOH/pullrequest/45311 | U2: 45957 | V2: 45957 | W2: Ruban | Y2: Steve | Z2: 45957 | AE2: Meets Expectation
A3: 2 | B3: Meal Order | C3: 45947 | D3: 45960 | E3: 2.5 KaleidaNutrition S11 | F3: Dhivyalakshmi | G3: 50133 | H3: [WAVE] Mosaic FOH Kaleida - Interior Pages update - Catering | I3: Story Being Tested | J3: 5 | K3: 5 | L3: 30 | M3: 45952 | N3: 45959 | O3: Completed | P3: Vidya Subramaniam | R3: Ruban | T3: https://dev.azure.com/heartlandschools/Mosaic/_git/FOH/pullrequest/45368 | U3: 45959 | V3: 45959 | W3: Ruban | Y3: Steve | Z3: 45959 | AD3: Working on the issue reported by Ken regarding Filter changes.
A4: 3 | B4: Meal Order | C4: 45947 | D4: 45960 | E4: 2.5 KaleidaNutrition S11 Stretch | F4: Ruban | G4: 50146 | H4: [WAVE] Mosaic FOH Kaleida - Interior Pages update - Catering - Add Order & edit Order | I4: Story Being Developed | J4: 13 | M4: 45947
A5: 4 | B5: Meal Order | C5: 45947 | D5: 45960 | E5: 2.5 KaleidaNutrition S11 Stretch | F5: Sudheer | G5: 50474 | H5: Meal Orders - Automation - Data Cleanup | I5: Story Completed | J5: 13 | K5: 10 | L5: 40 | M5: 45947 | N5: 45959 | O5: Completed | P5: NA | R5: Owen | T5: https://dev.azure.com/heartlandschools/Meal%20Orders/_git/MealOrdersAutomation/pullrequest/45045 | U5: 45959 | V5: 45960 | W5: Owen | Y5: NA | AD5: Yet to approve PR and need to work on if any Issues/comments from Owen | AE5: Meets Expectation

Sheet 2.5Kaleida Nutrition S13-D
A1: ect | B1: Story/Defect ID | C1: Parent Story | D1: Developer | E1: Issue Type | F1: Issue Description | G1: Priority | H1: Defect Source | I1: Type | J1: Found By | K1: Status | L1: Root Cause Category | M1: RCA Comment *

Sheet 2.5Kaleida Nutrition S12-Defect
A1: Sprint # | B1: Story/Defect ID | C1: Parent Story | D1: Developer | E1: Issue Type | F1: Issue Description | G1: Priority | H1: Defect Source | I1: Type | J1: Found By | K1: Status | L1: Root Cause Category | M1: RCA Comment *

Sheet 2.5Kaleida Nutrition S11-Defect
A1: Sprint # | B1: Story/Defect ID | C1: Parent Story | D1: Developer | E1: Issue Type | F1: Issue Description | G1: Priority | H1: Defect Source | I1: Type | J1: Found By | K1: Status | L1: Root Cause Category | M1: RCA Comment *
A2: 2.5 KaleidaNutrition S11 | B2: 50133 | D2: Dhivyalakshmi | E2: Bounceback | F2: 1)When the user enters values in the input fields , In hide filter button there is a counter , that value count changes based on input fields enters ,Now the issue is it should only change whenever the user enters the value and they click apply filter button | G2: Medium | H2: Manual | I2: External | J2: Onsite QA | K2: Defect Being Developed | L2: New Issue

Sheet 2.5 KaleidaNutrition S10-Status
A1: S.No | B1: Application Name | C1: Sprint Start Date | D1: Sprint End Date | E1: Sprint | F1: Developer | G1: Story ID/Defect ID | H1: Description | I1: Status | J1: Estimated(sp) | K1: Actual(sp) | L1: Actual Hours Worklog | M1: Dev Start Date | N1: Dev End Date | O1: Unit testing | P1: Peer Tested By | Q1: Peer Tested Defects, if any | R1: Peer Reviewed By | S1: Peer Code Review Comments, if any | T1: PR Number/Link | U1: PR Created Date | V1: PR Approved Date | W1: Reviewer 1 | X1: Code Review Comments, if any | Y1: Reviewer 2 | Z1: Approved Date | AA1: Code Review Comments, if any2 | AB1: Internal PO -POV Comments | AC1: Client PO -POV Comments | AD1: Comments | AE1: Does this story meets expectations
A2: 1 | B2: Meal Order | C2: 45933 | D2: 45946 | E2: 2.5 KaleidaNutrition S10 | F2: Kiruthiga | G2: 50168 | H2: [WAVE] - Mosaic FOH - Improve header responsiveness to reduce slowness during navigation | I2: Story Completed | J2: 5 | K2: 5 | L2: 16 | M2: 45933 | N2: 45940 | O2: Kiruthiga | P2: Sudheer | R2: Ruban | T2: https://dev.azure.com/heartlandschools/Mosaic/_git/FOH/pullrequest/45073 | U2: 45940 | V2: 45943 | W2: Ruban | Y2: Steve | Z2: 45943 | AE2: Meets Expectation
A3: 2 | B3: Meal Order | C3: 45933 | D3: 45946 | E3: 2.5 KaleidaNutrition S10 | F3: Dhivyalakshmi | G3: 50241 | H3: [WAVE] - FOH - Issue fixes 2 | I3: Story Completed | J3: 3 | K3: 3 | L3: 12 | M3: 45943 | N3: 45944 | O3: Dhivyalakshmi | P3: Kiruthiga | R3: Ruban | T3: https://dev.azure.com/heartlandschools/Mosaic/_git/FOH/pullrequest/45111 | U3: 45944 | V3: 45944 | W3: Ruban | Y3: Steven | Z3: 45944 | AE3: Meets Expectation
A4: 3 | B4: Meal Order | C4: 45933 | D4: 45946 | E4: 2.5 KaleidaNutrition S10 Stretch | F4: Sudheer | G4: 49940 | H4: Meal Orders - Automation - New Framework Stock Management, Orders, and Settings. | I4: Story Completed | J4: 5 | K4: 7 | L4: 28 | M4: 45933 | N4: 45940 | O4: Sudheer | P4: Sudheer | R4: Owen | T4: https://dev.azure.com/heartlandschools/Meal%20Orders/_git/MealOrdersAutomation/pullrequest/45045 | U4: 45940 | V4: 45945 | W4: Owen | Y4: Owen | Z4: 45945 | AE4: Meets Expectation
A5: 4 | B5: Meal Order | C5: 45933 | D5: 45946 | E5: 2.5 KaleidaNutrition S10 Stretch | F5: Dhivyalakshmi | G5: 50133 | H5: [WAVE] Mosaic FOH Kaleida - Interior Pages update - Catering. | I5: Story Being Developed | J5: 8 | M5: 45933
A6: 5 | B6: Meal Order | C6: 45933 | D6: 45946 | E6: 2.5 KaleidaNutrition S10 Stretch | F6: Ruban | G6: 50146 | H6: [WAVE] Mosaic FOH Kaleida - Interior Pages update - Catering - Add Order | I6: Story Being Developed | J6: 13 | M6: 45933

Sheet 2.5 Kaleida Nutrition S9-Status
A1: S.No | B1: Application Name | C1: Sprint Start Date | D1: Sprint End Date | E1: Sprint | F1: Developer | G1: Story ID/Defect ID | H1: Description | I1: Status | J1: Estimated(sp) | K1: Actual(sp) | L1: Actual Hours Worklog | M1: Dev Start Date | N1: Dev End Date | O1: Unit testing | P1: Peer Tested By | Q1: Peer Tested Defects, if any | R1: Peer Reviewed By | S1: Peer Code Review Comments, if any | T1: PR Number/Link | U1: PR Created Date | V1: PR Approved Date | W1: Reviewer 1 | X1: Code Review Comments, if any | Y1: Reviewer 2 | Z1: Approved Date | AA1: Code Review Comments, if any2 | AB1: Internal PO -POV Comments | AC1: Client PO -POV Comments | AD1: Comments | AE1: Does this story meets expectations
A2: 1 | B2: Meal Order | C2: 45919 | D2: 45932 | E2: 2.5 Kaleida Nutrition S9 | F2: Sudheer | G2: 50206 | H2: Meal Orders - Interim Release(2.5.2) - Prep and Deployment | I2: Story Completed | J2: 8 | K2: 8 | L2: 40 | M2: N/A | N2: N/A | O2: N/A | P2: N/A | Q2: N/A | R2: N/A | S2: N/A | T2: N/A | U2: N/A | V2: N/A | W2: N/A | Y2: N/A | Z2: N/A | AE2: Meets Expectation
A3: 2 | B3: Meal Order | C3: 45919 | D3: 42279 | E3: 2.5 Kaleida Nutrition S9 | F3: Dhivyalakshmi | G3: 25250 | H3: Meal Orders - Admin - Menu Calendars > Site Groups nav menu highlight incorrect | I3: Story Completed | J3: 2 | K3: 4 | L3: 18 | M3: 45923 | N3: 45924 | O3: Ruban | P3: Sudheer | R3: Kiruthiga | T3: https://dev.azure.com/heartlandschools/Meal%20Orders/_git/Meal%20Orders/pullrequest/44695 | U3: 45924 | V3: 45924 | W3: Mike | Y3: Mike | Z3: 45924 | AE3: Meets Expectation
A4: 3 | B4: Meal Order | C4: 45919 | D4: 45932 | E4: 2.5 Kaleida Nutrition S9 | F4: Dhivyalakshmi | G4: 50180 | H4: [WAVE] - Mosaic FOH - Issues with theme switching | I4: Story Completed | J4: 3 | K4: 4 | L4: 15 | M4: 45923 | N4: 45924 | O4: Kiruthiga | P4: Sudheer/Ken | R4: Kiruthiga | T4: https://dev.azure.com/heartlandschools/Mosaic/_git/FOH/pullrequest/44749 | U4: 45924 | V4: 45924 | W4: Ruban | Y4: Ying | Z4: 45924 | AE4: Meets Expectation
A5: 4 | B5: Meal Order | C5: 45919 | D5: 45932 | E5: 2.5 Kaleida Nutrition S9 | F5: Ruban | G5: 25967 | H5: Meal Orders - Blank Page on Reports | I5: Story Completed | J5: 8 | K5: 8 | L5: 40 | M5: 45919 | N5: 45923 | O5: Kiruthiga | P5: Sudheer | R5: Kiruthiga | T5: https://dev.azure.com/heartlandschools/Meal%20Orders/_git/Meal%20Orders/pullrequest/44695 | U5: 45923 | V5: 45924 | W5: Mike | Y5: Mike | Z5: 45924 | AE5: Meets Expectation
A6: 5 | B6: Meal Order | C6: 45919 | D6: 45932 | E6: 2.5 Kaleida Nutrition S9 | F6: Dhivyalakshmi | G6: 50203 | H6: [WAVE]- FOH issue fixes | I6: Story Completed | J6: 5 | K6: 8 | L6: 31 | M6: 45924 | N6: 45926 | O6: Kiruthiga | P6: Sudheer | R6: Kiruthiga | T6: https://dev.azure.com/heartlandschools/Mosaic/_git/FOH/pullrequest/44808 | U6: 45926 | V6: 45926 | W6: Ruban | Y6: Ying | Z6: 45926
A7: 6 | B7: Meal Order | C7: 45919 | D7: 45932 | E7: 2.5 Kaleida Nutrition S9 Stretch | F7: Sudheer | G7: 49940 | H7: Meal Orders - Automation - New Framework Stock Management, Orders, and Settings. | I7: Story Being Developed | J7: 8 | L7: 24 | M7: 45919
A8: 7 | B8: Meal Order | C8: 45919 | D8: 45932 | E8: 2.5 Kaleida Nutrition S9 Stretch | F8: Kiruthiga | G8: 50168 | H8: [WAVE] - Mosaic FOH - Improve header responsiveness to reduce slowness during navigation | I8: Story Being Developed | J8: 5 | L8: 6 | M8: 45924
A9: 8 | B9: Meal Order | C9: 45919 | D9: 45932 | E9: 2.5 Kaleida Nutrition S9 Stretch | F9: Dhivyalakshmi | G9: 50241 | H9: FOH - Issue fixes 2 | I9: Story Ready For Testing | J9: 3 | M9: 45929 | N9: 30/9/2025 | O9: Kiruthiga | P9: Dhivyalakshmi | R9: Kiruthiga | T9: https://dev.azure.com/heartlandschools/Mosaic/_git/FOH/pullrequest/44920 | U9: 45931 | W9: Ruban | Y9: Ying
A10: 9 | B10: Meal Order | C10: 45919 | D10: 45932 | E10: 2.5 Kaleida Nutrition S9 Stretch | F10: Kiruthiga | G10: 50151 | H10: [WAVE] Mosaic FOH Kaleida - Login - Pending Updates | I10: Story Being Developed | J10: 8 | M10: 45919 | AD10: Due to priority change this story is on hold, though it is a sprint story and not planned for upcoming release , developer is assigned with a high priority performance issue

Sheet 2.5 Kaleida Nutrition S9-Defect
A1: Sprint # | B1: Story/Defect ID | C1: Parent Story | D1: Developer | E1: Issue Type | F1: Issue Description | G1: Priority | H1: Defect Source | I1: Type | J1: Found By | K1: Status | L1: Root Cause Category | M1: RCA Comment *

Sheet 2.5 Kaleida Nutrition S8-Status
A1: S.No | B1: Application Name | C1: Sprint Start Date | D1: Sprint End Date | E1: Sprint | F1: Developer | G1: Story ID/Defect ID | H1: Description | I1: Status | J1: Estimated(sp) | K1: Actual(sp) | L1: Actual Hours Worklog | M1: Dev Start Date | N1: Dev End Date | O1: Unit testing | P1: Peer Tested By | Q1: Peer Tested Defects, if any | R1: Peer Reviewed By | S1: Peer Code Review Comments, if any | T1: PR Number/Link | U1: PR Created Date | V1: PR Approved Date | W1: Reviewer 1 | X1: Code Review Comments, if any | Y1: Reviewer 2 | Z1: Approved Date | AA1: Code Review Comments, if any2 | AB1: Internal PO -POV Comments | AC1: Client PO -POV Comments | AD1: Comments | AE1: Does this story meets expectations
A2: 1 | B2: Meal Order | C2: 45905 | D2: 45918 | E2: 2.5 Kaleida Nutrition S8 | F2: Kiruthiga | G2: 49688 | H2: [WAVE] - Mosaic FOH Kaleida - Update Login screen | I2: Story Being Tested | J2: 8 | K2: 7 | L2: 26 | M2: 45905 | N2: 45915 | O2: Completed | R2: Ruban | T2: https://dev.azure.com/heartlandschools/Mosaic/_git/FOH/pullrequest/44461?path=/src/FOH/Mosaic.Web/Views/Account/Login.cshtml | U2: 45915 | V2: 45916 | W2: Ruban | Y2: Ying | Z2: 45916 | AC2: Button color code and stylying changes to MSB Sign In And Mosaic Sign In buttons | AD2: It is being tested by onsite QA, Mostly that will closed by today(19th Sep) EOD
A3: 2 | B3: Meal Order | C3: 45905 | D3: 45918 | E3: 2.5 Kaleida Nutrition S8 | F3: Ruban | G3: 25841 | H3: Meal Orders - Admin - Error publishing new site/site group empty menu calendar | I3: Story Completed | J3: 2 | K3: 2 | L3: 10 | M3: .9/9/2025 | N3: .10/9/2025 | O3: Completed | P3: Sudheer | R3: Mike | T3: https://dev.azure.com/heartlandschools/Meal%20Orders/_git/Meal%20Orders/pullrequest/44467 | U3: . 10/9/2025 | V3: .11/9/2025 | W3: Mike | Y3: MIke | Z3: .11/9/2025 | AE3: Meets Expectation
A4: 3 | B4: Meal Order | C4: 45905 | D4: 45918 | E4: 2.5 Kaleida Nutrition S8 Stretch | F4: Sudheer | G4: 49361 | H4: Meal Orders - Automation - New Framework Menu Items/Templates/Calendars | I4: Story Completed | J4: 3 | K4: 3 | L4: 12 | M4: 45905 | N4: 45908 | O4: Completed | P4: Sudheer | R4: Owen | T4: approve.https://dev.azure.com/heartlandschools/Meal%20Orders/_git/MealOrdersAutomation/pullrequest/44414 | U4: 45908 | V4: 45908 | W4: Owen | Y4: Owen | Z4: .9/8/2025 | AE4: Meets Expectation
A5: 4 | B5: Meal Order | C5: 45905 | D5: 45918 | E5: 2.5 Kaleida Nutrition S8 Stretch | F5: Dhivyalakshmi | G5: 25710 | H5: Meal Orders - Admin - Site Settings - Menu Item Restrictions Add button enabled when override off | I5: Story Completed | J5: 2 | K5: 3 | L5: 12 | M5: 45905 | N5: 45908 | O5: Completed | P5: Sudheer | R5: Kiruthiga | T5: https://dev.azure.com/heartlandschools/Meal%20Orders/_git/Meal%20Orders/pullrequest/44386 | U5: 45908 | V5: 45908 | W5: Ruban | Y5: Mike | Z5: 45908 | AE5: Meets Expectation
A6: 5 | B6: Meal Order | C6: 45905 | D6: 45918 | E6: 2.5 Kaleida Nutrition S8 Stretch | F6: Dhivyalakshmi | G6: 25709 | H6: Meal Orders - Admin - Ordering Parameters actions not disabled when district settings off | I6: Story Completed | J6: 3 | K6: 4 | L6: 17 | M6: .9/8/2025 | N6: 45909 | O6: Completed | P6: Sudheer | R6: Kiruthiga | T6: https://dev.azure.com/heartlandschools/Meal%20Orders/_git/Meal%20Orders/pullrequest/44471 | U6: 45909 | V6: . 10/9/2025 | W6: Ruban | Y6: Mike | Z6: . 10/9/2025 | AE6: Meets Expectation
A7: 6 | B7: Meal Order | C7: 45905 | D7: 45918 | E7: 2.5 Kaleida Nutrition S8 Stretch | F7: Sudheer | G7: 49940 | H7: Meal Orders - Automation - New Framework Stock Management, Orders, and Settings. | I7: Story Being Developed | J7: 8 | K7: 2 | L7: 8 | M7: .9/9/2025
A8: 7 | B8: Meal Order | C8: 45905 | D8: 45918 | E8: 2.5 Kaleida Nutrition S8 Stretch | F8: Ruban | G8: 48712 | H8: Meal Orders - Stock Management - Change Heading & Description text for Qty in Stock | I8: Story Completed | J8: 5 | K8: 5 | L8: 20 | M8: .9/8/2025 | N8: .9/9/2025 | O8: Kiruthiga | P8: Ken | R8: Kiruthiga | T8: https://dev.azure.com/heartlandschools/Meal%20Orders/_git/Meal%20Orders/pullrequest/44445 | U8: .9/8/2025 | V8: .9/9/2025 | W8: Mike | Y8: Mike | Z8: .9/9/2025 | AE8: Meets Expectation
A9: 8 | B9: Meal Order | C9: 45905 | D9: 45918 | E9: 2.5 Kaleida Nutrition S8 Stretch | F9: Dhivyalakshmi | G9: 25250 | H9: Meal Orders - Admin - Menu Calendars > Site Groups nav menu highlight incorrect | I9: Defect Being Developed | J9: 3 | K9: 3 | L9: 12 | M9: .9/12/2025

Sheet 2.5 Kaleida Nutrition S8-Defect
A1: Sprint # | B1: Story/Defect ID | C1: Parent Story | D1: Developer | E1: Issue Type | F1: 2 | G1: Priority | H1: Defect Source | I1: Type | J1: Found By | K1: Status | L1: Root Cause Category | M1: RCA Comment *
A2: 2.5 Kaleida Nutrition S8 | B2: 25841 | D2: Ruban | E2: Bounceback | F2: 1. Open Site/Site Group and Clickthe publish button. then user getting console error . | G2: Medium | H2: Manual | I2: External | J2: OffShore QA | K2: Testing completed | L2: New Issue | M2: Getting 500 server Issue on console while we trying to publish the menu template
A3: 2.5 Kaleida Nutrition S8 | B3: 49688 | D3: Kiruthiga | E3: Bounceback | F3: 1.MFOH Logo not rendering on login screen. Receiving console errors 2.Footer overlaps with login box content when window is resized and with certain screen resolutions 3.Color code differnce | G3: low | H3: Manual | I3: External | J3: Onsite QA | K3: Being Tested | L3: New Issue | M3: Issue 2 is related to screen resolution and 1 & 3 are cosmetic changes

Sheet 2.5 Kaleida Nutrition S7-Status
A1: S.No | B1: Application Name | C1: Sprint Start Date | D1: Sprint End Date | E1: Sprint | F1: Developer | G1: Story ID/Defect ID | H1: Description | I1: Status | J1: Estimated(sp) | K1: Actual(sp) | L1: Actual Hours Worklog | M1: Dev Start Date | N1: Dev End Date | O1: Unit testing | P1: Peer Tested By | Q1: Peer Tested Defects, if any | R1: Peer Reviewed By | S1: Peer Code Review Comments, if any | T1: PR Number/Link | U1: PR Created Date | V1: PR Approved Date | W1: Reviewer 1 | X1: Code Review Comments, if any | Y1: Reviewer 2 | Z1: Approved Date | AA1: Code Review Comments, if any2 | AB1: Internal PO -POV Comments | AC1: Client PO -POV Comments | AD1: Comments | AE1: Does this story meets expectations
A2: 1 | B2: Meal Order | C2: 45891 | D2: 45904 | E2: 2.5 Kaleida Nutrition S7 Stretch | F2: Sudheer | G2: 49361 | H2: Meal Orders - Automation - New Framework Menu Items/Templates/Calendars | I2: Story Being Developed | J2: 13 | L2: 42 | M2: 45891 | AD2: Implementation of automation scripts are completed . Execution and PR creation only pending itens as part of this story .
A3: 2 | B3: Meal Order | C3: 45891 | D3: 45904 | E3: 2.5 Kaleida Nutrition S7 Stretch | F3: Dhivyalakshmi | G3: 49528 | H3: [WAVE] Kaleida - Meal Orders - Teacher - Webview - Update Header & Left Navigation | I3: Story Being Developed | J3: 13 | L3: 31 | M3: 45891
A4: 3 | B4: Meal Order | C4: 45891 | D4: 45904 | E4: 2.5 Kaleida Nutrition S7 | F4: Dhivyalakshmi | G4: 49514 | H4: [WAVE] FOH - Header Dashboard Icon & Dropdown Menu | I4: Story Completed | J4: 3 | K4: 5 | L4: 20 | O4: Completed | P4: Vidhya | R4: Kiruthiga | S4: 1)CSS Style Changes which i need to check with BOH code and adjust the width and spacing. 2)Code Cleanup and need to remove commented lines. | T4: https://dev.azure.com/heartlandschools/Mosaic/_git/FOH/pullrequest/44007 | U4: 45887 | V4: 45888 | W4: Ruban | Y4: Ying | Z4: 45888 | AD4: Testing is inprogress, Onsite QA reported an issue but its not reproducing in local , investigation is going on. Root cause has been identified and because of the un availability of a column there was an exception. There is no change required from our end | AE4: Meets Expectation
A5: 4 | B5: Meal Order | C5: 45891 | D5: 45904 | E5: 2.5 Kaleida Nutrition S7 Stretch | F5: Kiruthiga | G5: 49688 | H5: [WAVE] - Mosaic FOH Kaleida - Update Login screen | I5: Story Being Developed | J5: 13 | L5: 26 | M5: 45891
A6: 5 | B6: Meal Order | C6: 45891 | D6: 45904 | E6: 2.5 Kaleida Nutrition S7 Stretch | F6: Ruban/Sudheer | G6: 49498 | H6: [WAVE] - Kaleida (#55582) Meal Orders - Admin - Webview - Introduce District selector dropdown | I6: Story Completed | J6: 5 | K6: 5 | L6: 20 | M6: 45891 | O6: Completed | P6: Sudheer | R6: Kiruthiga | T6: https://dev.azure.com/heartlandschools/Meal%20Orders/_git/Meal%20Orders/pullrequest/44089 | U6: 45891 | V6: 45898 | Y6: mike | Z6: 45903 | AA6: Add a conditional logic for rendering a setting in Fake login | AE6: Meets Expectation
A7: 6 | B7: Meal Order | C7: 45891 | D7: 45904 | E7: 2.5 Kaleida Nutrition S7 Stretch | F7: Ruban | G7: 49725 | H7: Meal Orders - Springfield New Role Creation | I7: Story Completed | J7: 3 | K7: 3 | L7: 12 | M7: 45897 | O7: NA | AD7: Based on the analysis Ruban made code changes. Later part we realized Springfield caused confusion that with the error they had with the login caused by Sentral's code change to Roles update are not working too. So upon confirmation from them we realized no code changes are needed.

Sheet 2.5 Kaleida Nutrition S7-Defect
A1: S.No | B1: Sprint # | C1: Story/Defect ID | D1: Parent Story | E1: Developer | F1: Issue Type | G1: Issue Description | H1: Priority | I1: Defect Source | J1: Type | K1: Found By | L1: Status | M1: Root Cause Category | N1: RCA Comment *
B2: 2.5 Kaleida Nutrition S7 Stretch | D2: 49498 | E2: Ruban | F2: Bounceback | G2: When we select inactive districts from the district dropdown user getting error like The tenant record you requested was not found | H2: Medium | I2: Manual | J2: External | K2: OffShore QA | L2: Testing Completed | M2: New Issue | N2: Inactive districts should not appear in the districts dropdown list.

Sheet 2.5 Kaleida Nutrition S6-Status
A1: S.No | B1: Application Name | C1: Sprint Start Date | D1: Sprint End Date | E1: Sprint | F1: Developer | G1: Story ID/Defect ID | H1: Description | I1: Status | J1: Estimated(sp) | K1: Actual(sp) | L1: Actual Hours Worklog | M1: Dev Start Date | N1: Dev End Date | O1: Unit testing | P1: Peer Tested By | Q1: Peer Tested Defects, if any | R1: Peer Reviewed By | S1: Peer Code Review Comments, if any | T1: PR Number/Link | U1: PR Created Date | V1: PR Approved Date | W1: Reviewer 1 | X1: Code Review Comments, if any | Y1: Reviewer 2 | Z1: Approved Date | AA1: Code Review Comments, if any2 | AB1: Internal PO -POV Comments | AC1: Client PO -POV Comments | AD1: Comments | AE1: Does this story meets expectations
A2: 1 | B2: Meal Order | C2: 45877 | D2: 45890 | E2: 2.5 Kaleida Nutrition S6 | F2: Kiruthiga | G2: 49499 | H2: [WAVE] Mosaic FOH - Breadcrumb & navigation fixes | I2: Story Completed | J2: 8 | K2: 8 | L2: 24 | M2: 45877 | N2: 45883 | O2: Completed | P2: Sudheer | R2: Ruban | T2: https://dev.azure.com/heartlandschools/Mosaic/_git/FOH/pullrequest/43971, https://dev.azure.com/heartlandschools/Mosaic/_git/FOH/pullrequest/44077 | U2: 45883 | V2: 45883 | W2: Ruban | Y2: Ying | Z2: 45883 | AD2: It is being tested by onsite QA and Max it will be closed be closed on 22nd Aug | AE2: Meets Expectation
A3: 2 | B3: Meal Order | C3: 45877 | D3: 45890 | E3: 2.5 Kaleida Nutrition S6 Stretch | F3: Dhivyalakshmi | G3: 49514 | H3: [WAVE] FOH - Header Dashboard Icon & Dropdown Menu | I3: Story Being Tested | J3: 8 | K3: 11 | L3: 43 | M3: 45877 | N3: 19/8/2025 | O3: Completed | P3: Vidhya | R3: Kiruthiga | S3: 1)CSS Style Changes which i need to check with BOH code and adjust the width and spacing. 2)Code Cleanup and need to remove commented lines. | T3: https://dev.azure.com/heartlandschools/Mosaic/_git/FOH/pullrequest/44007 | U3: 45887 | V3: 45888 | W3: Ruban | Y3: Ying | Z3: 45888 | AD3: This Story is currently testing Inprogress by onsite QA.
A4: 3 | B4: Meal Order | C4: 45877 | D4: 45890 | E4: 2.5 Kaleida Nutrition S6 Stretch | F4: Sudheer | G4: 49360 | H4: Meal Orders - Automation - Update Scripts for Old Framework | I4: Story Completed | J4: 3 | K4: 5 | L4: 19 | M4: 45877 | N4: 45887 | O4: Completed | P4: Owen | R4: Owen | T4: https://dev.azure.com/heartlandschools/Meal%20Orders/_git/Meal%20Orders/pullrequest/43967 | U4: 45887 | V4: 45889 | W4: Owen | Y4: Owen | Z4: 45889 | AE4: Meets Expectation
A5: 3 | B5: Meal Order | C5: 45877 | D5: 45890 | E5: 2.5 Kaleida Nutrition S6 Stretch | F5: Sudheer | G5: 49361 | H5: Meal Orders - Automation - New Framework Menu Items/Templates/Calendars | I5: Story Being Developed | J5: 13 | M5: 45888
A6: 4 | B6: Meal Order | C6: 45877 | D6: 45890 | E6: 2.5 Kaleida Nutrition S6 Stretch | F6: Dhivyalakshmi | G6: 49528 | H6: [WAVE] Kaleida - Meal Orders - Teacher - Webview - Update Header & Left Navigation | I6: Story Being Developed | J6: 13 | M6: 20/8/2025
A7: 5 | B7: Meal Order | C7: 45877 | D7: 45890 | E7: 2.5 Kaleida Nutrition S6 Stretch | F7: Ruban | G7: 49498 | H7: [WAVE] - Kaleida (#55582) Meal Orders - Admin - Webview - Introduce District selector dropdown | I7: Story Peer Review | J7: 8 | K7: 8 | L7: 41 | M7: 45877 | N7: 20/8/2025 | O7: Completed | R7: Kiruthiga | T7: https://heartlandschools.visualstudio.com/Meal%20Orders/_git/Meal%20Orders/pullrequest/44089?_a=files | U7: 45890 | AD7: Vega team has to add the Searchable property to VegaDropdown and we would be waiting to get merged until its completed.

Sheet 2.5 Kaleida Nutrition S6-Defect
A1: S.No | B1: Sprint # | C1: Story/Defect ID | D1: Parent Story | E1: Developer | F1: Issue Type | G1: Issue Description | H1: Priority | I1: Defect Source | J1: Type | K1: Found By | L1: Status | M1: Root Cause Category | N1: RCA Comment *
B2: 2.5 Kaleida Nutrition S6 | D2: 49499 | E2: Kiruthiga | F2: Bounceback | G2: 404 Error received when using breadcrumbs to return to User/Employee search from user/employee page | H2: Medium | I2: Manual | J2: External | K2: Client | L2: Defect Peer Review | M2: New Issue | N2: This issue not reproducible in local but occurs in deployed url. Need to append application path in the url in addition to breadcrumb information

Sheet 2.5 Kaleida Nutrition S5-Status
A1: S.No | B1: Application Name | C1: Sprint Start Date | D1: Sprint End Date | E1: Sprint | F1: Developer | G1: Story ID/Defect ID | H1: Description | I1: Status | J1: Estimated(sp) | K1: Actual(sp) | L1: Actual Hours Worklog | M1: Dev Start Date | N1: Dev End Date | O1: Unit testing | P1: Peer Tested By | Q1: Peer Tested Defects, if any | R1: Peer Reviewed By | S1: Peer Code Review Comments, if any | T1: PR Number/Link | U1: PR Created Date | V1: PR Approved Date | W1: Reviewer 1 | X1: Code Review Comments, if any | Y1: Reviewer 2 | Z1: Approved Date | AA1: Code Review Comments, if any2 | AB1: Internal PO -POV Comments | AC1: Client PO -POV Comments | AD1: Comments | AE1: Does this story meets expectations
A2: 1 | B2: Meal Order | C2: 45863 | D2: 45876 | E2: 2.5 Kaleida Nutrition S5 | F2: Kiruthiga | G2: 49358 | H2: [WAVE] Mosaic FOH Kaleida - Breadcrumbs | I2: Story Being Tested | J2: 5 | K2: 5 | L2: 20 | M2: 45866 | N2: 45873 | O2: Completed | P2: Dhivya | T2: https://dev.azure.com/heartlandschools/Mosaic/_git/FOH/pullrequest/43801 | U2: 45875 | V2: 45875 | W2: Ruban | Y2: Ying | Z2: 45875 | AD2: Facing an issue on deploying latest build into QA environment and it is blocking story testing | AE2: Meets Expectation
A3: 2 | B3: Meal Order | C3: 45863 | D3: 45876 | E3: 2.5 Kaleida Nutrition S5 Stretch | F3: Sudheer | G3: 49360 | H3: Meal Orders - Automation - Update Scripts for Old Framework(Since Vega ID's are changed for Left Navgation Menus ) | I3: Story Being Developed | J3: 5 | K3: 8 | L3: 35 | M3: 45868 | O3: In Progress | AD3: 1.Underestimated the impact of Vega changes-which has led to unexpected challenges in test automation and DOM handling. 2.Facing code-level issues-particularly in retrieving XPath or CSS selectors due to elements being encapsulated within shadow DOM, making them inaccessible through standard methods. Encountering timeout issues-such as "Waiting for server message", likely due to delayed rendering or server response times associated with the Vega components.
A4: 3 | B4: Meal Order | C4: 45863 | D4: 45876 | E4: 2.5 Kaleida Nutrition S5 Stretch | F4: Dhivyalakshmi | G4: 49143 | H4: [WAVE] Mosaic FOH - Side navigation loading/Flickering issues | I4: Story Being Tested | J4: 5 | K4: 9 | L4: 43 | M4: 45868 | N4: 45876 | O4: Completed | P4: Kiruthiga | R4: Kiruthiga | T4: https://dev.azure.com/heartlandschools/Mosaic/_git/FOH/pullrequest/43809 | U4: 45875 | V4: 45876 | W4: Ruban | Y4: Ying | Z4: 45876 | AD4: Facing an issue on deploying latest build into QA environment and it is blocking story testing | AE4: Meets Expectation
A5: 4 | B5: Meal Order | C5: 45863 | D5: 45876 | E5: 2.5 Kaleida Nutrition S5 | F5: Ruban | G5: 25291 | H5: Meal Orders - Admin - Order Mgmt. - Closing receipt print template modal prompts close of receipt printing | I5: Defect Fixed | J5: 2 | K5: 2 | L5: 3 | M5: 45863 | N5: 45867 | O5: Completed | P5: Sudheer | T5: https://dev.azure.com/heartlandschools/Meal%20Orders/_git/Meal%20Orders/pullrequest/43660 | U5: 45867 | V5: 45867 | W5: Ruban | Y5: Mike | Z5: 45867 | AE5: Meets Expectation

Sheet 2.5 Kaleida Nutrition S5-Defect
A1: S.No | B1: Sprint # | C1: Story/Defect ID | D1: Parent Story | E1: Developer | F1: Issue Type | G1: Issue Description | H1: Priority | I1: Defect Source | J1: Type | K1: Found By | L1: Status | M1: Root Cause Category | N1: RCA Comment *

Sheet 2.5 Kaleida Nutrition S4-Status
A1: S.No | B1: Application Name | C1: Sprint Start Date | D1: Sprint End Date | E1: Sprint | F1: Developer | G1: Story ID/Defect ID | H1: Description | I1: Status | J1: Estimated(sp) | K1: Actual(sp) | L1: Actual Hours Worklog | M1: Dev Start Date | N1: Dev End Date | O1: Unit testing | P1: Peer Tested By | Q1: Peer Tested Defects, if any | R1: Peer Reviewed By | S1: Peer Code Review Comments, if any | T1: PR Number/Link | U1: PR Created Date | V1: PR Approved Date | W1: Reviewer 1 | X1: Code Review Comments, if any | Y1: Reviewer 2 | Z1: Approved Date | AA1: Code Review Comments, if any2 | AB1: Internal PO -POV Comments | AC1: Client PO -POV Comments | AD1: Comments | AE1: Does this story meets expectations
A2: 1 | B2: Meal Order | C2: 45849 | D2: 45862 | E2: 2.5 Kaleida Nutrition S4 | F2: Kiruthiga | G2: 48732 | H2: [WAVE] Mosaic FOH Kaleida - Breadcrumbs | I2: Story Completed | J2: 3 | K2: 3 | L2: 10 | M2: 45855 | N2: 45859 | O2: Completed | P2: Rachel | R2: Rachel | T2: https://dev.azure.com/heartlandschools/Mosaic/_git/FOH/pullrequest/43497 | U2: 45859 | V2: 45860 | W2: Ruban | Y2: Ying | Z2: 45860 | AD2: Support to onsite developer to address routing and breadcrumb issue | AE2: Meets Expectation
A3: 2 | B3: Meal Order | C3: 45849 | D3: 45862 | E3: 2.5 Kaleida Nutrition S4 | F3: Sudheer | G3: 49162 | H3: Meal Orders (2.4) - Regression - Teacher | I3: Story Completed | J3: 5 | K3: 5 | L3: 20 | M3: NA | N3: NA | O3: NA
A4: 3 | B4: Meal Order | C4: 45849 | D4: 45862 | E4: 2.5 Kaleida Nutrition S4 Stretch | F4: Dhivyalakshmi | G4: 24962 | H4: Meal Orders - Admin - Email unsubscribe does not work if active login | I4: Story Approved | J4: 3 | M4: NA | N4: NA | O4: NA
A5: 4 | B5: Meal Order | C5: 45849 | D5: 45862 | E5: 2.5 Kaleida Nutrition S4 | F5: Dhivyalakshmi | G5: 49166 | H5: Meal Orders(2.5) - Regression - Report | I5: Story Completed | J5: 2 | K5: 3 | L5: 14 | M5: NA | N5: NA | O5: NA
A6: 5 | B6: Meal Order | C6: 45849 | D6: 45862 | E6: 2.5 Kaleida Nutrition S4 | F6: Sudheer | G6: 49165 | H6: Meal Orders(2.5) - Regression - Admin | I6: Story Completed | J6: 8 | K6: 10 | L6: 44 | M6: NA | N6: NA | O6: NA
A7: 6 | B7: Meal Order | C7: 45849 | D7: 45862 | E7: 2.5 Kaleida Nutrition S4 Stretch | F7: Dhivyalakshmi | G7: 49146 | H7: [WAVE] Mosaic FOH Kaleida - District Name to Header (web view) | I7: Story Peer Review | J7: 3 | K7: 6 | L7: 22 | M7: 45859 | N7: 45862 | O7: Completed | P7: Ruban | R7: Kiruthiga | T7: https://dev.azure.com/heartlandschools/Mosaic/_git/FOH/pullrequest/43558 | U7: 45861 | V7: 45861 | W7: Ruban | Y7: Ying | Z7: 45862 | AD7: There was challenge on restoring vega dependencies due to authentication issue. It took additional time for this story. | AE7: Meets Expectation
A8: 7 | B8: Meal Order | C8: 45849 | D8: 45862 | E8: 2.5 Kaleida Nutrition S4 | F8: Ruban | G8: 49179 | H8: Meal Orders - Item Import Update - Restrict Item Name / Item Type | I8: Story Completed | J8: 2 | K8: 2 | M8: 45852 | N8: 45853 | O8: Completed | P8: Dhivya | R8: Rachel | T8: https://heartlandschools.visualstudio.com/Meal%20Orders/_git/Meal%20Orders/pullrequest/43360 | U8: 45853 | V8: 45853 | W8: Mike | Y8: Mike | Z8: 45853 | AE8: Meets Expectation

Sheet 2.5 Kaleida Nutrition S4-Defect
A1: S.No | B1: Sprint # | C1: Story/Defect ID | D1: Parent Story | E1: Developer | F1: Issue Type | G1: Issue Description | H1: Priority | I1: Defect Source | J1: Type | K1: Found By | L1: Status | M1: Root Cause Category | N1: RCA Comment *

Sheet 2.5 Kaleida Nutrition S3-Status
A1: S.No | B1: Application Name | C1: Sprint Start Date | D1: Sprint End Date | E1: Sprint | F1: Developer | G1: Story ID/Defect ID | H1: Description | I1: Status | J1: Estimated(sp) | K1: Actual(sp) | L1: Actual Hours Worklog | M1: Unit testing | N1: Peer Tested By | O1: Peer Tested Defects, if any | P1: Peer Reviewed By | Q1: Peer Code Review Comments, if any | R1: PR Number/Link | S1: PR Created Date | T1: PR Approved Date | U1: Reviewer 1 | V1: Code Review Comments, if any | W1: Reviewer 2 | X1: Approved Date | Y1: Code Review Comments, if any2 | Z1: Internal PO -POV Comments | AA1: Client PO -POV Comments | AB1: Comments | AC1: Does this story meets expectations
A2: 1 | B2: Meal Order | C2: 45835 | D2: 45848 | E2: 2.5 Kaleida Nutrition S3 | F2: Kiruthiga | G2: 48346 | H2: [WAVE] Mosaic FOH Kaleida - Update Page Footer | I2: Story Completed | J2: 3 | K2: 3 | L2: 15 | M2: Completed | N2: Sudheer | P2: Ruban | R2: https://dev.azure.com/heartlandschools/Mosaic/_git/FOH/pullrequest/43195?_a=files | S2: 45845 | T2: 45845 | U2: Ruban | W2: Ying | X2: 45845 | AB2: There is a dependent pr that needs to be merged before to this PR. Hence waiting for clients update on this. | AC2: Meets Expectation
A3: 2 | B3: Meal Order | C3: 45835 | D3: 45848 | E3: 2.5 Kaleida Nutrition S3 Stretch | F3: Sudheer | G3: 48735 | H3: Meal Orders(Automation) - Admin - Settings | I3: Story Completed | J3: 8 | K3: 8 | L3: 30 | M3: NA | N3: Sudheer | P3: Owen | R3: https://dev.azure.com/heartlandschools/Meal%20Orders/_git/MealOrdersAutomation/pullrequest/43266 | S3: 45845 | U3: Owen | W3: Owen | AC3: Meets Expectation
A4: 3 | B4: Meal Order | C4: 45835 | D4: 45848 | E4: 2.5 Kaleida Nutrition S3 | F4: Dhivyalakshmi/Sudheer | G4: 25483 | H4: Meal Orders - Parent - Order Timings - Auto Cart update for orderable day restriction on Submit Orders | I4: Defect Fixed | J4: 2 | K4: 3 | L4: 15 | M4: Completed | N4: Sudheer | P4: Ruban | R4: https://dev.azure.com/heartlandschools/Meal%20Orders/_git/Meal%20Orders/pullrequest/43050 | S4: 45835 | T4: 45839 | U4: Ruban | W4: Mike | X4: 45839 | AC4: Meets Expectation
A5: 4 | B5: Meal Order | C5: 45835 | D5: 45848 | E5: 2.5 Kaleida Nutrition S3 | F5: Kiruthiga | G5: 48502 | H5: [WAVE] Mosaic BOH Kaleida - Update Page Footer | I5: Story Completed | J5: 5 | K5: 5 | L5: 19 | M5: Completed | N5: Sudheer | P5: Ruban | R5: https://dev.azure.com/heartlandschools/Mosaic/_git/BOH/pullrequest/43098 | S5: 45845 | T5: 45845 | U5: Ruban | W5: Charles | X5: 45845 | AC5: Meets Expectation
A6: 5 | B6: Meal Order | C6: 45835 | D6: 45848 | E6: 2.5 Kaleida Nutrition S3 Stretch | F6: Dhivyalakshmi/Sudheer | G6: 48383 | H6: District Messages/Announcements [Admin] | I6: Story Completed | J6: 5 | K6: 7 | L6: 29 | M6: Completed | N6: Sudheer | P6: Ruban | R6: https://dev.azure.com/heartlandschools/Meal%20Orders/_git/Meal%20Orders/pullrequest/43200 | S6: 45845 | T6: 45847 | U6: Ruban | W6: Mike | X6: 45847 | AC6: Meets Expectation
A7: 6 | B7: Meal Order | C7: 45835 | D7: 45848 | E7: 2.5 Kaleida Nutrition S3 | F7: Ruban | G7: 48966 | H7: Meal Orders - Export Menu item changes to accommodate new Menu Item Import Changes | I7: Story Completed | J7: 8 | K7: 9 | L7: 39 | M7: Completed | N7: Ken/Sudheer | P7: Kiruthiga | R7: https://dev.azure.com/heartlandschools/Meal%20Orders/_git/Meal%20Orders/pullrequest/43222 | S7: 45845 | T7: 45847 | U7: Mike, Ruban | W7: Mike | X7: 45847 | AC7: Meets Expectation

Sheet 2.5 Kaleida Nutrition S3-Defect
A1: S.No | B1: Sprint # | C1: Story/Defect ID | D1: Parent Story | E1: Developer | F1: Issue Type | G1: Issue Description | H1: Priority | I1: Defect Source | J1: Type | K1: Found By | L1: Status | M1: Root Cause Category | N1: RCA Comment *
B2: 2.5 Kaleida Nutrition S3 | D2: 48346 | E2: Kiruthiga | F2: Bounceback | G2: Padding to bottom of the footer component is required | H2: low | I2: Manual | J2: Internal | K2: Offshore | L2: Defect Fixed | M2: New Issue | N2: Addition of footer component need style change in the Content part
B3: 2.5 Kaleida Nutrition S3 | D3: 48383 | E3: Dhivyalakshmi | F3: Bounceback | G3: Validation not required for description when same description is Edited | H3: low | I3: Manual | J3: Internal | K3: Offshore | L3: Defect Fixed | M3: New Issue | N3: Validation popup is shown when editing same description , so removed that
B4: 2.5 Kaleida Nutrition S3 | D4: 48966 | E4: Ruban | F4: Bounceback | G4: Timeout issue on test import | H4: Medium | I4: Manual | J4: Internal | K4: Client | L4: Defect Fixed | M4: New Issue | N4: Unwanted db calls causing timeout

Sheet 2.5 Kaleida Nutrition S2-Status
A1: S.No | B1: Application Name | C1: Sprint Start Date | D1: Sprint End Date | E1: Sprint | F1: Developer | G1: Story ID/Defect ID | H1: Description | I1: Status | J1: Estimated(sp) | K1: Actual(sp) | L1: Actual Hours Worklog | M1: Unit testing | N1: Peer Tested By | O1: Peer Tested Defects, if any | P1: Peer Reviewed By | Q1: Peer Code Review Comments, if any | R1: PR Number/Link | S1: PR Created Date | T1: PR Approved Date | U1: Reviewer 1 | V1: Code Review Comments, if any | W1: Reviewer 2 | X1: Approved Date | Y1: Code Review Comments, if any2 | Z1: Internal PO -POV Comments | AA1: Client PO -POV Comments | AB1: Comments | AC1: Does this story meets expectations
A2: 1 | B2: Meal Order | C2: 45821 | D2: 45834 | E2: 2.5 Kaleida Nutrition S2 | F2: Kiruthiga | G2: 48685 | H2: Meal Orders - Remove Hyperlink on the "?" icon in the header | I2: Story Completed | J2: 2 | K2: 2 | L2: 7 | M2: Completed | N2: Sudheer | P2: Ruban | R2: https://dev.azure.com/heartlandschools/Meal%20Orders/_git/Meal%20Orders/pullrequest/42857 | S2: 45824 | T2: 45825 | U2: Ruban | W2: Mike | X2: 45825 | AC2: Meets Expectation
A3: 2 | B3: Meal Order | C3: 45821 | D3: 45834 | E3: 2.5 Kaleida Nutrition S2 Stretch | F3: Sudheer | G3: 48735 | H3: Meal Orders(Automation) - Admin - Settings | I3: Story Being Developed | J3: 13 | K3: 5 | L3: 20
A4: 3 | B4: Meal Order | C4: 45821 | D4: 45834 | E4: 2.5 Kaleida Nutrition S2 | F4: Kiruthiga | G4: 48734 | H4: [WAVE] Meal Orders Kaleida - Update Page Footer | I4: Story Completed | J4: 3 | K4: 3 | L4: 12 | M4: Completed | N4: Sudheer | P4: Ruban | R4: https://dev.azure.com/heartlandschools/Meal%20Orders/_build/results?buildId=144390&view=results | S4: 45832 | T4: 45833 | U4: Ruban | W4: Mike | X4: 45833 | AC4: Meets Expectation
A5: 4 | B5: Meal Order | C5: 45821 | D5: 45834 | E5: 2.5 Kaleida Nutrition S2 | F5: Kiruthiga | G5: 48346 | H5: [WAVE] Mosaic FOH Kaleida - Update Page Footer | I5: Story Peer Review | J5: 3 | K5: 3 | L5: 12 | M5: Completed | N5: Sudheer | P5: Ruban | R5: https://dev.azure.com/heartlandschools/Mosaic/_git/FOH/pullrequest/43008 | S5: 45833 | U5: Ruban | W5: Mike | AB5: There is a dependent pr that needs to be merged before to this PR. Hence waiting for clients update on this. | AC5: Meets Expectation
A6: 5 | B6: Meal Order | C6: 45821 | D6: 45834 | E6: 2.5 Kaleida Nutrition S2 | F6: Dhivyalakshmi | G6: 25295 | H6: Meal Orders - Parent - Order Timings - Auto Cart update for orderable day restriction | I6: Defect Fixed | J6: 3 | K6: 5 | L6: 21.5 | M6: Completed | N6: Ruban | P6: Ruban | Q6: Had comments to change the property and function name to a appropriate word | R6: https://dev.azure.com/heartlandschools/Meal%20Orders/_git/Meal%20Orders/pullrequest/42938 | S6: 45831 | T6: 45831 | U6: Ruban | W6: Mike | X6: 45831 | AC6: Meets Expectation
A7: 6 | B7: Meal Order | C7: 45821 | D7: 45834 | E7: 2.5 Kaleida Nutrition S2 Stretch | F7: Ruban / Dhivya | G7: 48145 | H7: Meal Orders [v?]- Import Menu Items | I7: Story Completed | J7: 13 | K7: 17 | L7: 67 | M7: Completed | N7: Dhivya | P7: Kiruthiga | R7: https://dev.azure.com/heartlandschools/Meal%20Orders/_git/Meal%20Orders/pullrequest/42972 | S7: 45833 | T7: 45833 | U7: Ruban | W7: Mike | X7: 45834

Sheet 2.5 Kaleida Nutrition S2-Defect
A1: S.No | B1: Sprint # | C1: Story/Defect ID | D1: Parent Story | E1: Developer | F1: Issue Type | G1: Issue Description | H1: Priority | I1: Defect Source | J1: Type | K1: Found By | L1: Status | M1: Root Cause Category | N1: RCA Comment *

Sheet 2.5 Kaleida Nutrition S1-Status
A1: S.No | B1: Application Name | C1: Sprint Start Date | D1: Sprint End Date | E1: Sprint | F1: Developer | G1: Story ID/Defect ID | H1: Description | I1: Status | J1: Estimated(sp) | K1: Actual(sp) | L1: Actual Hours Worklog | M1: Unit testing | N1: Peer Tested By | O1: Peer Tested Defects, if any | P1: Peer Reviewed By | Q1: Peer Code Review Comments, if any | R1: PR Number/Link | S1: PR Created Date | T1: PR Approved Date | U1: Reviewer 1 | V1: Code Review Comments, if any | W1: Reviewer 2 | X1: Approved Date | Y1: Code Review Comments, if any2 | Z1: Internal PO -POV Comments | AA1: Client PO -POV Comments | AB1: Comments | AC1: Does this story meets expectations
A2: 1 | B2: Meal Order | C2: 45807 | D2: 45820 | E2: 2.5 Kaleida Nutrition S1 | F2: Kiruthiga | G2: 25162 | H2: Meal Orders - Admin - Login after session timeout shows old screen with cards | I2: Defect Fixed | J2: 3 | K2: 3 | L2: 12 | M2: completed | N2: Ruban | R2: https://dev.azure.com/heartlandschools/Meal%20Orders/_git/Meal%20Orders/pullrequest/42424 | S2: 45811 | T2: 45811 | U2: Ruban | W2: Mike | X2: 45811 | AC2: Meets Expectation
A3: 2 | B3: Meal Order | C3: 45807 | D3: 45820 | E3: 2.5 Kaleida Nutrition S1 | F3: Sudheer | G3: 48350 | H3: Meal Orders(2.4) - Regression - Report | I3: Story Completed | J3: 2 | K3: 2 | L3: 10 | AC3: Meets Expectation
A4: 3 | B4: Meal Order | C4: 45807 | D4: 45820 | E4: 2.5 Kaleida Nutrition S1 stretch | F4: Dhivyalakshmi | G4: 25295 | H4: Meal Orders - Parent - Order Timings - Auto Cart update for orderable day restriction | I4: Defect Being Fixed | J4: 5 | K4: 2 | L4: 8
A5: 4 | B5: Meal Order | C5: 45807 | D5: 45820 | E5: 2.5 Kaleida Nutrition S1 | F5: Dhivyalakshmi / Kiruthiga / Ruban | G5: 48533 | H5: Mosaic FOH- Kaleida - Discovery & Setup | I5: Story Completed | J5: 13 | K5: 13 | L5: 46 | AB5: This story is intended for doing dev setup for FOH and BOH project. Hence PR link and other inputs are not applicable | AC5: Meets Expectation
A6: 5 | B6: Meal Order | C6: 45807 | D6: 45820 | E6: 2.5 Kaleida Nutrition S1 stretch | F6: Ruban | G6: 48145 | H6: Meal Orders [v?]- Import Menu Items | I6: Story Being Developed | J6: 13 | K6: 7 | L6: 29
A7: 6 | B7: Meal Order | C7: 45807 | D7: 45820 | E7: 2.5 Kaleida Nutrition S1 | F7: Sudheer | G7: 48607 | H7: Meal Orders(Automation) - Admin - Settings | I7: Story Completed | J7: 5 | K7: 5 | L7: 22 | P7: Owen | R7: https://dev.azure.com/heartlandschools/Meal%20Orders/_git/MealOrdersAutomation/pullrequest/42734 | S7: 45818 | T7: 45820 | W7: Owen | Y7: Structural things that could be improved New automation framework | AC7: Meets Expectation

Sheet 2.5 Kaleida Nutrition S1-Defect
A1: S.No | B1: Sprint # | C1: Story/Defect ID | D1: Parent Story | E1: Developer | F1: Issue Type | G1: Issue Description | H1: Priority | I1: Defect Source | J1: Type | K1: Found By | L1: Status | M1: Root Cause Category | N1: RCA Comment *

Sheet 2.4 Sprint 3-Status
A1: S.No | B1: Application Name | C1: Sprint Start Date | D1: Sprint End Date | E1: Sprint | F1: Developer | G1: Story ID/Defect ID | H1: Description | I1: Status | J1: Estimated(sp) | K1: Actual(sp) | L1: Actual Hours Worklog | M1: Unit testing | N1: Peer Tested By | O1: Peer Tested Defects, if any | P1: Peer Reviewed By | Q1: Peer Code Review Comments, if any | R1: PR Number/Link | S1: PR Created Date | T1: PR Approved Date | U1: Reviewer 1 | V1: Code Review Comments, if any | W1: Reviewer 2 | X1: Approved Date | Y1: Code Review Comments, if any2 | Z1: Internal PO -POV Comments | AA1: Client PO -POV Comments | AB1: Comments | AC1: Does this story meets expectations
A2: 1 | B2: Meal Order | C2: 45793 | D2: 45806 | E2: 2.4 Sprint 3 | F2: Ruban/Dhivya | G2: 47562 | H2: Meal Orders [v?]- Import Menu Items - Template Settings | I2: Story Completed | J2: 5 | K2: 5 | L2: 20
A3: 2 | B3: Meal Order | C3: 45793 | D3: 45806 | E3: 2.4 Sprint 3 Stretch | F3: Sudheer | G3: 48235 | H3: Meal Orders - Automation(Adding Sample script for Item Type by using New Automation Framework (MS Test)) | I3: Story Completed | J3: 3 | K3: 5 | L3: 29 | N3: Owen | P3: Owen | R3: https://heartlandschools.visualstudio.com/Meal%20Orders/_git/MealOrdersAutomation/pullrequest/42232 | S3: 45796 | T3: 45798 | W3: Owen | X3: 45798 | AB3: Recently we moved to new automation framework because of that got bit delay to complete the task.
A4: 3 | B4: Meal Order | C4: 45793 | D4: 45806 | E4: 2.4 Sprint 3 | F4: Sudheer | G4: 48347 | H4: Meal Orders (2.4) - Regression - Teacher | I4: Story Completed | J4: 5 | K4: 5 | L4: 22
A5: 4 | B5: Meal Order | C5: 45793 | D5: 45806 | E5: 2.4 Sprint 3 | F5: Sudheer | G5: 48351 | H5: Meal Orders (2.4) - Regression - Admin | I5: Story Completed | J5: 8 | K5: 8 | L5: 32
A6: 5 | B6: Meal Order | C6: 45793 | D6: 45806 | E6: 2.4 Sprint 3 | F6: Kiruthiga | G6: 25162 | H6: Meal Orders - Admin - Login after session timeout shows old screen with cards | I6: Defect Being Fixed | J6: 3 | K6: 8 | L6: 32 | AB6: This defect is bit challanged, reported issue has been fixed but still need improvement on showing browser url when log in back
A7: 6 | B7: Meal Order | C7: 45793 | D7: 45806 | E7: 2.4 Sprint 3 | F7: Dhivyalakshmi | G7: 25282 | H7: (Regression) Meal Orders - Admin - Grid item hover text obstructed by nav menu | I7: Defect Fixed | N7: Sudheer | P7: Kiruthiga | R7: https://dev.azure.com/heartlandschools/Meal%20Orders/_git/Meal%20Orders/pullrequest/42401 | S7: 45804 | T7: 45804 | U7: Ruban | W7: Mike | X7: 45805
A8: 7 | B8: Meal Order | C8: 45793 | D8: 45806 | E8: 2.4 Sprint 3 | F8: Dhivyalakshmi | G8: 25302 | H8: (Regression) Meal Orders - Parent - Inactive Special diet displayed | I8: Defect Fixed | N8: Sudheer | P8: Kiruthiga | R8: https://dev.azure.com/heartlandschools/Meal%20Orders/_git/Meal%20Orders/pullrequest/42404 | S8: 45804 | T8: 45804 | U8: Ruban | W8: Mike | X8: 45805
A9: 8 | B9: Meal Order | C9: 45793 | D9: 45806 | E9: 2.4 Sprint 3 Stretch | F9: Ruban/Sudheer | G9: 47610 | H9: Meal orders - Restrict cancel order Option Availability to the Day Before Serving Date [Integrated districts] - Admin | I9: Story Completed | J9: 3 | K9: 3 | L9: 12 | P9: Ruban | R9: https://heartlandschools.visualstudio.com/Meal%20Orders/_git/Meal%20Orders/pullrequest/42367 | S9: 45800 | T9: 45800 | U9: Ruban | W9: Mike | X9: 45800

Sheet 2.4 Sprint 3-Defect
A1: S.No | B1: Sprint # | C1: Story/Defect ID | D1: Parent Story | E1: Developer | F1: Issue Type | G1: Issue Description | H1: Priority | I1: Defect Source | J1: Type | K1: Found By | L1: Status | M1: Root Cause Category | N1: RCA Comment *
B2: 2.4 Sprint 3 | C2: 25282 | E2: Dhivyalakshmi | F2: Defect | G2: (Regression) Meal Orders - Admin - Grid item hover text obstructed by nav menu | H2: low | I2: Manual | J2: Internal | K2: Client | L2: Defect Fixed | M2: New Issue | N2: Due to change in UI Screen with sidebar changes , the style changes in the page required
B3: 2.4 Sprint 3 | C3: 25302 | E3: Dhivyalakshmi | F3: Defect | G3: (Regression) Meal Orders - Parent - Inactive Special diet displayed | H3: low | I3: Manual | J3: Internal | K3: Off shore | L3: Defect Fixed | M3: Existing issue | N3: Inactive Special diets are displayed in parent order screen under menu item , condition has changed and now it is hided.

Sheet 2.4 Sprint 2-Status
A1: S.No | B1: Application Name | C1: Sprint Start Date | D1: Sprint End Date | E1: Sprint | F1: Developer | G1: Story ID/Defect ID | H1: Description | I1: Status | J1: Estimated(sp) | K1: Actual(sp) | L1: Actual Hours Worklog | M1: Unit testing | N1: Peer Tested By | O1: Peer Tested Defects, if any | P1: Peer Reviewed By | Q1: Peer Code Review Comments, if any | R1: PR Number/Link | S1: PR Created Date | T1: PR Approved Date | U1: Reviewer 1 | V1: Code Review Comments, if any | W1: Reviewer 2 | X1: Approved Date | Y1: Code Review Comments, if any2 | Z1: Internal PO -POV Comments | AA1: Client PO -POV Comments | AB1: Comments | AC1: Does this story meets expectations
A2: 1 | B2: Meal Order | C2: 45779 | D2: 45792 | E2: 2.4 Sprint 2 | F2: Kiruthiga | G2: 48127 | H2: Meal Orders - Timeboxed Discovery for Localization Language Translation | I2: Story Completed | J2: 3 | K2: 3 | L2: 14 | R2: Not Applicable | AB2: It is a Discovery story, PR and Testing is not applicable | AC2: Exceeds Expectation
A3: 2 | B3: Meal Order | C3: 45779 | D3: 45792 | E3: 2.4 Sprint 2 | F3: Dhivyalakshmi | G3: 48070 | H3: Meal Orders - Replace Vitamin A mcg with Vitamin A RAE | I3: Story Completed | J3: 5 | K3: 5 | L3: 23 | N3: sudheer | P3: Ruban | R3: https://dev.azure.com/heartlandschools/Meal%20Orders/_git/Meal%20Orders/pullrequest/42090 | S3: 45785 | T3: 45786 | U3: Ruban | W3: Mike | X3: 45786 | AC3: Meets Expectation
A4: 3 | B4: Meal Order | C4: 45779 | D4: 45792 | E4: 2.4 Sprint 2 Stretch | F4: Sudheer | G4: 48235 | H4: Meal Orders - Automation(Adding Sample script for Item Type by using New Automation Framework (MS Test)) | I4: Story Being Developed | J4: 5 | K4: 5 | L4: 20
A5: 4 | B5: Meal Order | C5: 45779 | D5: 45792 | E5: 2.4 Sprint 2 | F5: Ruban/Kiruthiga | G5: 47562 | H5: Meal Orders [v?]- Import Menu Items - Template Settings | I5: Story Being Developed | J5: 8 | K5: 8 | L5: 34 | AB5: Story under estimated ,It will take few more days to complete all the scenarios
A6: 5 | B6: Meal Order | C6: 45779 | D6: 45792 | E6: 2.4 Sprint 2 Stretch | F6: Ruban/Kiruthiga | G6: 25206 | H6: Meal Orders - Admin - Users - District Level role of None not saving | I6: Story Completed | J6: 2 | K6: 2 | L6: 6 | R6: https://dev.azure.com/heartlandschools/Meal%20Orders/_git/Meal%20Orders/pullrequest/42143 | S6: 45790 | T6: 45790 | U6: Ruban | W6: Mike | X6: 45790 | AC6: Meets Expectation

Sheet 2.4 Sprint 2-Defect
A1: S.No | B1: Sprint # | C1: Story/Defect ID | D1: Parent Story | E1: Developer | F1: Issue Type | G1: Issue Description | H1: Priority | I1: Defect Source | J1: Type | K1: Found By | L1: Status | M1: Root Cause Category | N1: RCA Comment *
B2: 2.4 Sprint 2 Stretch | C2: 25206 | E2: Ruban | F2: Defect | G2: Meal Orders - Admin - Users - District Level role of None not saving | H2: Medium | I2: Manual | J2: Internal | K2: Client | L2: Defect Fixed | M2: Existing Issue | N2: When a user's Primary Role is set to (None) and saved, a success toast message is shown but the user's role is not actually updated. This issue only occurs for users whose User Type = District Level

Sheet 2.4 Sprint 1-Status
A1: S.No | B1: Application Name | C1: Sprint Start Date | D1: Sprint End Date | E1: Sprint | F1: Developer | G1: Story ID/Defect ID | H1: Description | I1: Status | J1: Estimated(sp) | K1: Actual(sp) | L1: Actual Hours Worklog | M1: Unit testing | N1: Peer Tested By | O1: Peer Tested Defects, if any | P1: Peer Reviewed By | Q1: Peer Code Review Comments, if any | R1: PR Number/Link | S1: PR Created Date | T1: PR Approved Date | U1: Reviewer 1 | V1: Code Review Comments, if any | W1: Reviewer 2 | X1: Approved Date | Y1: Code Review Comments, if any2 | Z1: Internal PO -POV Comments | AA1: Client PO -POV Comments | AB1: Comments
A2: 1 | B2: Meal Order | C2: 45765 | D2: 45778 | E2: 2.4 Sprint 1 | F2: Kiruthiga | G2: 22944 | H2: Meal Orders(2.?) - Menu Items - Unsplash Results not showing last page | I2: Defect Fixed | J2: 3 | K2: 3 | L2: 16 | N2: Sudheer | R2: https://dev.azure.com/heartlandschools/Meal%20Orders/_git/Meal%20Orders/pullrequest/41941 | S2: 45776 | T2: 45776 | U2: Mike | W2: Mike | X2: 45776
A3: 2 | B3: Meal Order | C3: 45765 | D3: 45778 | E3: 2.4 Sprint 1 | F3: Sudheer | G3: 47805 | H3: Meal Orders - Regression Automation Fixes and Script Updates | I3: Story Completed | J3: 8 | K3: 8 | L3: 32 | N3: Own | P3: Own | R3: https://dev.azure.com/heartlandschools/Meal%20Orders/_git/Meal%20Orders/pullrequest/41887 | S3: 45772 | T3: 45776 | U3: Owen | X3: 45776
A4: 3 | B4: Meal Order | C4: 45765 | D4: 45778 | E4: 2.4 Sprint 1 | F4: Dhivyalakshmi | G4: 24944 | H4: Meal Orders - Admin - Item/Grade restrictions radio button issue on first add | I4: Defect Fixed | J4: 2 | K4: 2 | L4: 15 | N4: Sudheer | P4: Ruban | R4: https://dev.azure.com/heartlandschools/Meal%20Orders/_git/Meal%20Orders/pullrequest/41830 | S4: 45769 | T4: 45769 | U4: Kiruthiga | W4: Mike | X4: 45769
A5: 4 | B5: Meal Order | C5: 45765 | D5: 45778 | E5: 2.4 Sprint 1 | F5: Ruban/Kiruthiga/sudheer | G5: 47964 | H5: Meal Orders [v2.4] - Displaying user information when an order is cancelled | I5: Story Completed | J5: 5 | K5: 5 | L5: 40 | N5: Sudheer | R5: https://dev.azure.com/heartlandschools/Meal%20Orders/_git/Meal%20Orders/pullrequest/41871 | S5: 45771 | T5: 45771 | U5: Ruban | W5: Mike | X5: 45771
A6: 5 | B6: Meal Order | C6: 45765 | D6: 45778 | E6: 2.4 Sprint 1 | F6: Dhivyalakshmi/sudheer | G6: 47988 | H6: Meal Orders - Menu Items Export functionality | I6: Story Completed | J6: 8 | K6: 8 | L6: 27 | R6: https://dev.azure.com/heartlandschools/Meal%20Orders/_git/Meal%20Orders/pullrequest/41968 | S6: 45777 | U6: Kiruthiga | W6: Mike
A7: 6 | B7: Meal Order | C7: 45765 | D7: 45778 | E7: 2.4 Sprint 1 | F7: Rachel/Kiruthiga/Sudheer | G7: 47973 | H7: [WAVE] Kaleida (#55582) Meal Orders - Admin - Update Header & Side Navigation based to include Vega Components | I7: Story Completed | J7: 3 | K7: 3 | L7: 15 | R7: NA | AB7: Support to onsite developer and testing

Sheet 2.4 Sprint 1-Defect
A1: S.No | B1: Sprint # | C1: Story/Defect ID | D1: Parent Story | E1: Developer | F1: Issue Type | G1: Issue Description | H1: Priority | I1: Defect Source | J1: Type | K1: Found By | L1: Status | M1: Root Cause Category | N1: RCA Comment *
B2: 2.4 Sprint 1 | C2: 24944 | E2: Dhivyalakshmi | F2: Defect | G2: Meal Orders - Admin - Item/Grade restrictions radio button issue on first add | H2: low | I2: Manual | J2: Internal | K2: Client | L2: Defect Fixed | M2: Existing Issue | N2: Issue Occured only for the first hit when there is no grade restriction added
B3: 2.4 Sprint 1 | C3: 22944 | E3: Kiruthiga | F3: Defect | G3: Meal Orders(2.?) - Menu Items - Unsplash Results not showing last page | H3: low | I3: Automation | J3: Internal | K3: Off shore | L3: Defect Fixed | M3: Existing Issue | N3: Because of the API limitation this issue is occured

Sheet 2.4 Sprint 0-Status
A1: S.No | B1: Application Name | C1: Sprint Start Date | D1: Sprint End Date | E1: Sprint | F1: Developer | G1: Story ID/Defect ID | H1: Description | I1: Status | J1: Estimated(sp) | K1: Actual(sp) | L1: Actual Hours Worklog | M1: Unit testing | N1: Peer Tested By | O1: Peer Tested Defects, if any | P1: Peer Reviewed By | Q1: Peer Code Review Comments, if any | R1: PR Number/Link | S1: PR Created Date | T1: PR Approved Date | U1: Reviewer 1 | V1: Code Review Comments, if any | W1: Reviewer 2 | X1: Approved Date | Y1: Code Review Comments, if any2 | Z1: Internal PO -POV Comments | AA1: Client PO -POV Comments | AB1: Comments
A2: 1 | B2: Meal Order | C2: 45751 | D2: 45764 | E2: 2.4 Sprint 0 | F2: Kiruthiga | G2: 24915 | H2: Meal Orders - Admin - Stock Mgmt. grid UI issue after edit columns | I2: Defect Fixed | J2: 5 | K2: 5 | L2: 24 | N2: Dhivya | R2: https://dev.azure.com/heartlandschools/Meal%20Orders/_git/Meal%20Orders/pullrequest/41655 | S2: 45756 | T2: 45756 | U2: Ruban | W2: Mike | X2: 45756
A3: 2 | B3: Meal Order | C3: 45751 | D3: 45764 | E3: 2.4 Sprint 0 Stretch | F3: Sudheer | G3: 47805 | H3: Meal Orders - Regression Automation Fixes and Script Updates | I3: Story Being Developed | J3: 13 | K3: 6 | L3: 23 | AB3: 1. Order test cases are failed Since Bulk Order Cancel dropdown added into Order management screen (Completed ) 2. Stock Management test case got failed since UI changes (Completed ) 3.Added New automation script for Bulk Order Cancellation functionality (Completed ) 4. Few data related issues and time out issue (Yet to complete) 5. Requried associate the automation with the test case from Visual Studio to Azure.(Yet to complete)
A4: 3 | B4: Meal Order | C4: 45751 | D4: 45764 | E4: 2.4 Sprint 0 | F4: Dhivyalakshmi | G4: 24882 | H4: Meal Orders - Order Management - Need to retain the multi selection of the orders in grid | I4: Defect Fixed | J4: 5 | K4: 5 | L4: 29 | N4: Sudheer | R4: https://dev.azure.com/heartlandschools/Meal%20Orders/_git/Meal%20Orders/pullrequest/41658 | S4: 45756 | T4: 45756 | U4: Ruban | W4: Mike | X4: 45756
A5: 4 | B5: Meal Order | C5: 45751 | D5: 45764 | E5: 2.4 Sprint 0 Stretch | F5: Kiruthiga | G5: 38108 | H5: Meal Orders (1.5) - TECH DEBT - Update Unsplash Images to use Thumbnail URL | I5: Story Completed | J5: 3 | K5: 1 | L5: 5 | R5: Not applicable as it is a tech debt story | AB5: After code analysis it was deemed to be already done.
A6: 5 | B6: Meal Order | C6: 45751 | D6: 45764 | E6: 2.4 Sprint 0 Stretch | F6: Dhivyalakshmi | G6: 24951 | H6: Meal Orders - Admin - Stock Menu Items report shows 'return' when site/site group not selected | I6: Defect Fixed | J6: 1 | K6: 1 | L6: 4 | N6: Sudheer | P6: Ruban | R6: https://dev.azure.com/heartlandschools/Meal%20Orders/_git/Meal%20Orders/pullrequest/41713 | S6: 45761 | T6: 45761 | U6: Ruban | W6: Mike | X6: 45761
A7: 6 | B7: Meal Order | C7: 45751 | D7: 45764 | E7: 2.4 Sprint 0 Stretch | F7: Dhivyalakshmi | G7: 24953 | H7: Meal Orders - Admin - Stock Management - Exported stocks file name shows incorrect date | I7: Defect Fixed | J7: 2 | K7: 2 | L7: 7 | N7: Sudheer | P7: Ruban | R7: https://dev.azure.com/heartlandschools/Meal%20Orders/_git/Meal%20Orders/pullrequest/41714 | S7: 45761 | T7: 45761 | U7: Ruban | W7: Mike | X7: 45761
A8: 7 | B8: Meal Order | C8: 45751 | D8: 45764 | E8: 2.4 Sprint 0 | F8: Dhivyalakshmi | G8: 24997 | H8: Meal Orders - Student Fulfillment Report - CSV Filename | I8: Defect Fixed | J8: 2 | K8: 2 | L8: 8 | N8: Sudheer | P8: Ruban | R8: https://dev.azure.com/heartlandschools/Meal%20Orders/_git/Meal%20Orders/pullrequest/41715 | S8: 45761 | T8: 45761 | U8: Ruban | W8: Mike | X8: 45761
A9: 8 | B9: Meal Order | C9: 45751 | D9: 45764 | E9: 2.4 Sprint 0 Stretch | F9: Dhivyalakshmi | G9: 25022 | H9: Meal Orders - SysAdmin Login Not Functional | I9: Defect Fixed | J9: 2 | K9: 2 | L9: 8 | N9: Sudheer | P9: Ruban | R9: https://dev.azure.com/heartlandschools/Meal%20Orders/_git/Meal%20Orders/pullrequest/41753 | S9: 45763 | T9: 45763 | U9: Ruban | W9: Mike | X9: 45763
A10: 9 | B10: Meal Order | C10: 45751 | D10: 45764 | E10: 2.4 Sprint 0 Stretch | F10: Kiruthiga | G10: 24217 | H10: Meal Orders (2.?) - Reports - Order Receipts - New default template not recognized | I10: Defect Fixed | J10: 3 | K10: 3 | L10: 10 | N10: Sudheer | P10: Ruban | R10: https://dev.azure.com/heartlandschools/Meal%20Orders/_git/Meal%20Orders/pullrequest/41770 | S10: 45763 | U10: Ruban | W10: Mike
A11: 10 | B11: Meal Order | C11: 45751 | D11: 45764 | E11: 2.4 Sprint 0 | F11: Ruban | G11: 34180 | H11: Meal Orders (v??) - TECH DEBT - Add the API settings into the tenant cache | I11: Story Completed | J11: 3 | K11: 3 | L11: 5 | R11: Not applicable as it is a tech debt story | AB11: After code analysis it was deemed to be already done.
A12: 11 | B12: Meal Order | C12: 45751 | D12: 45764 | E12: 2.4 Sprint 0 | F12: Ruban | G12: 47832 | H12: Meal Orders - Admin - Add Job for Item Type update | I12: Story Completed | J12: 8 | K12: 8 | L12: 35 | R12: https://dev.azure.com/heartlandschools/Meal%20Orders/_git/Meal%20Orders/pullrequest/41754 | S12: 45762 | T12: 45762 | U12: Ruban | W12: Mike | X12: 45762
A13: 12 | B13: Meal Order | C13: 45751 | D13: 45764 | E13: 2.4 Sprint 0 Stretch | F13: Dhivyalakshmi | G13: 24944 | H13: Meal Orders - Admin - Item/Grade restrictions radio button issue on first add | I13: Defect Being Fixed | J13: 3

Sheet 2.4 Sprint 0-Defect
A1: S.No | B1: Sprint # | C1: Story/Defect ID | D1: Parent Story | E1: Developer | F1: Issue Type | G1: Issue Description | H1: Priority | I1: Defect Source | J1: Type | K1: Found By | L1: Status | M1: Root Cause Category | N1: RCA Comment *
B2: 2.4 Sprint 0 | C2: 24882 | E2: Dhivyalakshmi/sudheer | F2: Defect | G2: Meal Orders - Order Management - Need to retain the multi selection of the orders in grid | H2: low | I2: Manual | J2: Internal | K2: Relevantz | L2: Closed | M2: Existing Issue | N2: While Performing after selecting checkbox ,action like status change ,the selected row become unselected , that is resolved by retaining the value.
B3: 2.4 Sprint 0 | C3: 24915 | E3: Kiruthiga/sudheer | F3: Defect | G3: Meal Orders - Admin - Stock Mgmt. grid UI issue after edit columns | H3: Significant | I3: Manual | J3: External | K3: Sentral Team | L3: Closed | M3: Existing Issue | N3: Issue occured only when add/remove grid column and then click on Open Stock Edit
B4: 2.4 Sprint 0 Stretch | C4: 24951 | E4: Dhivyalakshmi/sudheer | F4: Defect | G4: Meal Orders - Admin - Stock Menu Items report shows 'return' when site/site group not selected | H4: low | I4: Manual | J4: Internal | K4: Relevantz | L4: Closed | M4: Existing Issue | N4: Added Return text incorrectly inside modal popup
B5: 2.4 Sprint 0 Stretch | C5: 24953 | E5: Dhivyalakshmi/sudheer | F5: Defect | G5: Meal Orders - Admin - Stock Management - Exported stocks file name shows incorrect date | H5: low | I5: Manual | J5: Internal | K5: Relevantz | L5: Closed | M5: Existing Issue | N5: Exported name contains both filename and serving date , serving date showed incorrectly while formatting date string to date format
B6: 2.4 Sprint 0 | C6: 24997 | E6: Dhivyalakshmi/sudheer | F6: Defect | G6: Meal Orders - Student Fulfillment Report - CSV Filename | H6: low | I6: Manual | J6: Internal | K6: Client | L6: Closed | M6: Existing Issue | N6: Exported csv name contains both filename and serving date , serving date showed incorrectly while formatting date string to date format
B7: 2.4 Sprint 0 Stretch | C7: 25022 | E7: Dhivyalakshmi | F7: Defect | G7: Meal Orders - SysAdmin Login Not Functional | H7: low | I7: Manual | J7: Internal | K7: Relevantz | L7: Closed | M7: Internal Issue | N7: Needed additional conditional logic in existing functionality for logout
B8: 2.4 Sprint 0 Stretch | C8: 24217 | E8: Kiruthiga/sudheer | G8: Meal Orders (2.?) - Reports - Order Receipts - New default template not recognized | H8: low | I8: Manual | J8: External | K8: Client | L8: Closed | M8: Existing Issue | N8: Issue occured when change any of the report filter on completion of template creation
B9: 2.4 Sprint 0 Stretch | C9: 24944 | E9: Dhivyalakshmi | F9: Defect | G9: Meal Orders - Admin - Item/Grade restrictions radio button issue on first add | H9: low | I9: Manual | J9: External | K9: Client | L9: Open | M9: Existing Issue | N9: Issue Occured first time , without there is no grade restriction table data.

Sheet 2.3 Sprint 4-Status
A1: S.No | B1: Application Name | C1: Sprint Start Date | D1: Sprint End Date | E1: Sprint | F1: Developer | G1: Story ID/Defect ID | H1: Description | I1: Status | J1: Estimated(sp) | K1: Actual(sp) | L1: Actual Hours Worklog | M1: Unit testing | N1: Peer Tested By | O1: Peer Tested Defects, if any | P1: Peer Reviewed By | Q1: Peer Code Review Comments, if any | R1: PR Number/Link | S1: PR Created Date | T1: PR Approved Date | U1: Reviewer 1 | V1: Code Review Comments, if any | W1: Reviewer 2 | X1: Approved Date | Y1: Code Review Comments, if any2 | Z1: Internal PO -POV Comments | AA1: Client PO -POV Comments | AB1: Comments
A2: 1 | B2: Meal Order | C2: 45737 | D2: 45750 | E2: 2.3 Sprint 4 | F2: Kiruthiga | G2: 47109 | H2: Meal Orders(v2.?) - Admin - Reports - Student Product Sales Report - Group By Serving Date | I2: Story Completed | J2: 5 | K2: 5 | L2: 38 | M2: Completed | R2: https://dev.azure.com/heartlandschools/Meal%20Orders/_build/results?buildId=140100&view=logs&j=ca395085-040a-526b-2ce8-bdc85f692774 | S2: 45744 | T2: 45744 | U2: Ruban | W2: Mike | X2: 45744 | AA2: 1.Reduce width of SubTotal column and use that space for Item Type 2. Forceset the value of Sub-Group By when Group By filter value is selected as None | AB2: Due technical feasibility constraint development took additianl efforts also received UI suggestion during POV
A3: 2 | B3: Meal Order | C3: 45737 | D3: 45750 | E3: 2.3 Sprint 4 | F3: Sudheer | G3: 47151 | H3: Meal Orders(v2.3) - Implementation Regression Automation for Reports Module(All Reports) | I3: Story Completed | J3: 5 | K3: 5 | L3: 12 | N3: Rachel | P3: Owe Siber | Q3: None | R3: https://dev.azure.com/heartlandschools/Meal%20Orders/_git/Meal%20Orders/pullrequest/41331 | S3: 45736 | T3: 45741 | U3: Owe siber | V3: None | X3: 45741
A4: 3 | B4: Meal Order | C4: 45737 | D4: 45750 | E4: 2.3 Sprint 4 | F4: Dhivyalakshmi | G4: 24927 | H4: (Regression) Admin - Serving Period - Inactivate modal missing when deletion not an option | I4: Defect Fixed | M4: Completed | N4: Kiruthiga | P4: Ruban | R4: https://dev.azure.com/heartlandschools/Meal%20Orders/_git/Meal%20Orders/pullrequest/41490 | S4: 45747 | T4: 45748 | U4: Ruban | W4: Mike | X4: 45748
A5: 4 | B5: Meal Order | C5: 45737 | D5: 45750 | E5: 2.3 Sprint 4 | F5: Sudheer | G5: 47656 | H5: Meal Orders (2.3) - Regression - Teacher | I5: Story Completed | J5: 5 | K5: 5 | L5: 22
A6: 5 | B6: Meal Order | C6: 45737 | D6: 45750 | E6: 2.3 Sprint 4 | F6: Sudheer | G6: 47660 | H6: Meal Orders (2.3) - Regression - Admin | I6: Story Completed | J6: 8 | K6: 8 | L6: 60
A7: 6 | B7: Meal Order | C7: 45737 | D7: 45750 | E7: 2.3 Sprint 4 | F7: Dhivyalakshmi | G7: 24933 | H7: (Regression) Admin - Serving Period unable to be reactivated after inactivation | I7: Defect Fixed | M7: Completed | N7: Kiruthiga | P7: Ruban | R7: https://dev.azure.com/heartlandschools/Meal%20Orders/_git/Meal%20Orders/pullrequest/41490 | S7: 45747 | T7: 45748 | U7: Ruban | W7: Mike | X7: 45748
A8: 7 | B8: Meal Order | C8: 45737 | D8: 45750 | E8: 2.3 Sprint 4 | F8: Sudheer | G8: 47659 | H8: Meal Orders(2.3) - Regression - Report | I8: Story Completed | J8: 4 | K8: 4 | L8: 18
A9: 8 | B9: Meal Order | C9: 45737 | D9: 45750 | E9: 2.3 Sprint 4 Stretch | F9: Dhivyalakshmi | G9: 24915 | H9: Meal Orders - Admin - Stock Mgmt. grid UI issue after edit columns | I9: Defect Being Fixed | J9: 5 | K9: 5 | L9: 13
A10: 9 | B10: Meal Order | C10: 45737 | D10: 45750 | E10: 2.3 Sprint 4 | F10: Ruban | G10: 24934 | H10: (Regression) Admin - Stock Management - Serving Period and Menu Items filters not functional | I10: Defect Fixed | N10: Dhivya | P10: Ruban | R10: https://heartlandschools.visualstudio.com/Meal%20Orders/_git/Meal%20Orders/pullrequest/41511 | S10: 45748 | T10: 45748 | U10: Ruban | W10: Mike | X10: 45748
A11: 10 | B11: Meal Order | C11: 45737 | D11: 45750 | E11: 2.3 Sprint 4 | F11: Ruban | G11: 24904 | H11: (Regression) - Admin - Exports display all data as undefined | I11: Defect Fixed | R11: https://heartlandschools.visualstudio.com/Meal%20Orders/_git/Meal%20Orders/pullrequest/41445 | S11: 45744 | T11: 45744 | U11: Ruban | W11: Mike | X11: 45744
A12: 11 | B12: Meal Order | C12: 45737 | D12: 45750 | E12: 2.3 Sprint 4 Stretch | F12: Ruban | G12: 24947 | H12: (Regression) Meal Orders - Admin - Stock Mgmt. - Order from canceled to fulfilled not withdrawing stock | I12: Defect Fixed | R12: https://heartlandschools.visualstudio.com/Meal%20Orders/_git/Meal%20Orders/pullrequest/41478 | S12: 45748 | T12: 45748 | U12: Ruban | W12: Mike | X12: 45748
A13: 12 | B13: Meal Order | C13: 45737 | D13: 45750 | E13: 2.3 Sprint 4 Stretch | F13: Dhivyalakshmi | G13: 24882 | H13: Meal Orders - Order Management - Need to retain the multi selection of the orders in grid | I13: Defect Being Fixed | J13: 3 | K13: 3 | L13: 8

Sheet 2.3 Sprint 4-Defect
A1: S.No | B1: Sprint # | C1: Story/Defect ID | D1: Parent Story | E1: Developer | F1: Issue Type | G1: Issue Description | H1: Priority | I1: Defect Source | J1: Type | K1: Found By | L1: Status | M1: Root Cause Category | N1: RCA Comment *
B2: 2.3 Sprint 4 | C2: 24933 | E2: Dhivyalakshmi/Sudheer | F2: Defect | G2: (Regression) Admin - Serving Period unable to be reactivated after inactivation | H2: low | I2: Automation | J2: Internal | K2: Relevantz | L2: Closed | M2: Existing Issue | N2: Conditioanl logic was missed out for the particular scenario also missed out in testing, Identified by Offshore QA
B3: 2.3 Sprint 4 | C3: 24927 | E3: Dhivyalakshmi/Sudheer | F3: Defect | G3: (Regression) Admin - Serving Period - Inactivate modal missing when deletion not an option | H3: low | I3: Automation | J3: Internal | K3: Relevantz | L3: Closed | M3: Existing Issue | N3: It is a usability suggestion suggested by Offshore QA
B4: 2.3 Sprint 4 Stretch | C4: 24915 | E4: Dhivyalakshmi/Sudheer | F4: Defect | G4: Meal Orders - Admin - Stock Mgmt. grid UI issue after edit columns | H4: low | I4: Manual | J4: Internal | K4: Relevantz | L4: Open | M4: Existing Issue | N4: Functional issue with respect to column order change - Reported Sentral
B5: 2.3 Sprint 4 Stretch | C5: 24882 | E5: Dhivyalakshmi/Sudheer | F5: Defect | G5: Meal Orders - Order Management - Need to retain the multi selection of the orders in grid | H5: low | I5: Manual | J5: Internal | K5: Relevantz | L5: Open | M5: Existing Issue | N5: Analysis is in progress
B6: 2.3 Sprint 4 | C6: 24934 | E6: Ruban/Sudheer | F6: Defect | G6: (Regression) Admin - Stock Management - Serving Period and Menu Items filters not functional | H6: low | I6: Manual | J6: Internal | K6: Client | L6: Closed | M6: Existing Issue | N6: Serving period filter that was applied does not affect stock rules shown within grid. If Filters are opened back up, the applied Serving Period selection is no longer shown.
B7: 2.3 Sprint 4 | C7: 24904 | E7: Ruban/Sudheer | F7: Defect | G7: (Regression) - Admin - Exports display all data as undefined | H7: low | I7: Manual | J7: Internal | K7: Client | L7: Closed | M7: Internal Issue | N7: Existing export package was not supported after Mik's build changes (Formatting & lint changes)
B8: 2.3 Sprint 4 Stretch | C8: 24947 | E8: Ruban | F8: Defect | G8: Meal Orders - Admin - Stock Mgmt. - Order from canceled to fulfilled not withdrawing stock | H8: low | I8: Manual | J8: Internal | K8: Relevantz | L8: Closed | M8: Existing Issue | N8: Functional issue, Additional conditional logic is required
B9: 2.3 Sprint 4 | C9: 24932 | E9: Ruban/Sudheer | F9: Defect | G9: (Regression) Stock Management - Inactive rules still considered when ordering | H9: low | I9: Manual | J9: Internal | K9: Client | L9: Closed | M9: Internal Issue | N9: Functional issue, Additional conditional logic is required

Sheet 2.3 Sprint 3-Status
A1: S.No | B1: Application Name | C1: Sprint Start Date | D1: Sprint End Date | E1: Sprint | F1: Developer | G1: Story ID/Defect ID | H1: Description | I1: Status | J1: Estimated(sp) | K1: Actual(sp) | L1: Actual Hours Worklog | M1: Unit testing | N1: Peer Tested By | O1: Peer Tested Defects, if any | P1: Peer Reviewed By | Q1: Peer Code Review Comments, if any | R1: PR Number/Link | S1: PR Created Date | T1: PR Approved Date | U1: Reviewer 1 | V1: Code Review Comments, if any | W1: Reviewer 2 | X1: Approved Date | Y1: Code Review Comments, if any2 | Z1: Internal PO -POV Comments | AA1: Client PO -POV Comments | AB1: Comments
A2: 1 | B2: Meal Order | C2: 45723 | D2: 45736 | E2: 2.3 Sprint 3 | F2: Kiruthiga | G2: 46826 | H2: Meal Orders(v2.?) - Admin - Reports - Header Section | I2: Story Completed | J2: 5 | K2: 5 | L2: 41 | M2: Completed | N2: Ruban | R2: https://dev.azure.com/heartlandschools/Meal%20Orders/_git/Meal%20Orders/pullrequest/41206 | S2: 45728 | T2: 45728 | U2: Ruban | W2: Mike | X2: 45728 | AA2: There was a suggession to show Report name and district name in all the reports for each page. That took additioanl effort to complete the story. | AB2: There was a suggession to show Report name and district name in all the reports for each page. That took additioanl effort to complete the story.
A3: 2 | B3: Meal Order | C3: 45723 | D3: 45736 | E3: 2.3 Sprint 3 | F3: Sudheer | G3: 47308 | H3: Meal Orders(v2.3) - Stock Management - Code Refactoring | I3: Story Completed | J3: 3 | K3: 5 | L3: 20 | M3: Completed | N3: Ruban/Mike | R3: https://dev.azure.com/heartlandschools/Meal%20Orders/_git/Meal%20Orders/pullrequest/41243 | S3: 45733 | T3: 45733 | X3: 45733 | AB3: During Testinf found 2 intenal issues , Because of code Refactoring and sentral got removed code for parent cart
A4: 3 | B4: Meal Order | C4: 45723 | D4: 45736 | E4: 2.3 Sprint 3 | F4: Dhivyalakshmi | G4: 24717 | H4: Meal Orders(2.2)- Admin - Order Management Filter Retain issue For Recipient Printing | I4: Story Completed | J4: 2 | K4: 2 | L4: 12.5 | M4: Completed | N4: kiruthiga | P4: Ruban | R4: https://dev.azure.com/heartlandschools/Meal%20Orders/_git/Meal%20Orders/pullrequest/41296 | S4: 45735 | T4: 45735 | U4: Ruban | W4: Mike | X4: 45735
A5: 4 | B5: Meal Order | C5: 45723 | D5: 45736 | E5: 2.3 Sprint 3 | F5: Kiruthiga | G5: 47109 | H5: Meal Orders(v2.?) - Admin - Reports - Student Product Sales Report - Group By Serving Date | I5: Story Being Developed | J5: 8 | L5: 21 | AB5: Due to the suggested changes in the Report Header story(46826) made a delay in starting the Student Product sales report work item
A6: 5 | B6: Meal Order | C6: 45723 | D6: 45736 | E6: 2.3 Sprint 3 Stretch | F6: Sudheer | G6: 47151 | H6: Meal Orders(v2.3) - Implementation Regression Automation for Reports Module(All Reports) | I6: Story Completed | J6: 13 | K6: 10 | L6: 35 | R6: https://dev.azure.com/heartlandschools/Meal%20Orders/_git/Meal%20Orders/pullrequest/41331 | S6: 45736 | W6: Rachel | AB6: PR got created , But facing few Biuld errors . Completed on Mar 21
A7: 6 | B7: Meal Order | C7: 45723 | D7: 45736 | E7: 2.3 Sprint 3 Stretch | F7: Dhivyalakshmi/Sudheer | G7: 24831 | H7: Meal Order - Admin - Stock Management - Serving Period dropdown not getting reset , when user click on reset button at Admin stock management | I7: Story Completed | J7: 2 | K7: 2 | L7: 2 | M7: Completed | N7: Kiruthiga | P7: Ruban | R7: https://dev.azure.com/heartlandschools/Meal%20Orders/_git/Meal%20Orders/pullrequest/41260 | S7: 45733 | T7: 45733 | U7: Ruban | W7: Mike | X7: 45733
A8: 7 | B8: Meal Order | C8: 45723 | D8: 45736 | E8: 2.3 Sprint 3 Stretch | F8: Dhivyalakshmi | G8: 47158 | H8: Meal Orders (2.3?) - Admin - Errors after applying reduced permission role for actively signed in user | I8: Story Completed | J8: 5 | K8: 5 | L8: 16 | M8: Completed | N8: Kiruthiga | P8: Ruban | R8: https://dev.azure.com/heartlandschools/Meal%20Orders/_git/Meal%20Orders/pullrequest/41325 | S8: 45736 | T8: 45736 | U8: Ruban | W8: Mike | X8: 45736
A9: 8 | B9: Meal Order | C9: 45723 | D9: 45736 | E9: 2.3 Sprint 3 Stretch | F9: Ruban | G9: 24863 | H9: Meal Orders - Admin - Preview open template opens incorrect day | I9: Defect Fixed | J9: 2 | K9: 2 | L9: 8 | M9: Completed | R9: https://heartlandschools.visualstudio.com/Meal%20Orders/_git/Meal%20Orders/pullrequest/41314 | S9: 45735 | T9: 45735 | U9: Ruban | W9: Mike | X9: 45735
A10: 9 | B10: Meal Order | C10: 45723 | D10: 45736 | E10: 2.3 Sprint 3 | F10: Ruban | G10: 47493 | H10: Meal Orders(v2.3) - SSO - Customer Order Count - Enhancement | I10: Story Completed | J10: 3 | K10: 3 | L10: 12 | M10: Completed | N10: Kiruthiga | R10: https://heartlandschools.visualstudio.com/Meal%20Orders/_git/Meal%20Orders/pullrequest/41187 | S10: 45728 | T10: 45728 | U10: Ruban | W10: Mike | X10: 45728

Sheet 2.3 Sprint 3-Defect
A1: S.No | B1: Sprint # | C1: Story/Defect ID | D1: Parent Story | E1: Developer | F1: Issue Type | G1: Issue Description | H1: Priority | I1: Defect Source | J1: Type | K1: Found By | L1: Status | M1: Root Cause Category | N1: RCA Comment *
B2: 2.3 Sprint 3 | C2: 24717 | E2: Dhivyalakshmi/Sudheer | F2: Defect | G2: Meal Orders(2.2)- Admin - Order Management Filter Retain issue For Recipient Printing | H2: Minor | I2: Manual | J2: Internal | K2: Relevantz | L2: Closed | M2: Existing Issue | N2: Internal issue - Identified in Offshore QA
B3: 2.3 Sprint 3 Stretch | C3: 24831 | E3: Dhivyalakshmi/Sudheer | F3: Defect | G3: Meal Order - Admin - Stock Management - Serving Period dropdown not getting reset , when user click on reset button at Admin stock management | H3: Significant | I3: Manual | J3: Internal | K3: Relevantz | L3: Closed | M3: Existing_Issues | N3: Internal issue - Identified in Offshore QA
B4: 2.3 Sprint 3 | C4: 47308 | D4: 47308 | E4: Ruban/Sudheer | F4: Bounceback | G4: Unable to update Customization menu item and Quantity in Parent cart | H4: Significant | I4: Manual | J4: Internal | K4: Relevantz | L4: Closed | M4: Internal | N4: During Stock Management Code Refactoring story testing - Identified in Offshore QA is found
B5: 2.3 Sprint 3 | C5: 47308 | D5: 47308 | E5: Ruban/Sudheer | F5: Bounceback | G5: Unable to update Normal Customization and Customization Group Items in Parent | H5: Significant | I5: Manual | J5: Internal | K5: Relevantz | L5: Closed | M5: Internal | N5: Since sental team has removed code about Parent cart - Identified inOffshore QA
B6: 2.3 Sprint 3 Stretch | C6: 24863 | E6: Ruban/Sudheer | F6: Defect | G6: Meal Orders - Admin - Preview open template opens incorrect day | H6: Significant | I6: Manual | J6: External | K6: Relevantz | L6: Closed | M6: Existing_Issues | N6: Production issue - Identified by Ruban, Resolved by addiding addtioanl conditional logic

Sheet 2.3 Sprint 2-Status
A1: S.No | B1: Application Name | C1: Sprint Start Date | D1: Sprint End Date | E1: Sprint | F1: Developer | G1: Story ID/Defect ID | H1: Description | I1: Status | J1: Estimated(sp) | K1: Actual(sp) | L1: Actual Hours Worklog | M1: Unit testing | N1: Peer Tested By | O1: Peer Tested Defects, if any | P1: Peer Reviewed By | Q1: Peer Code Review Comments, if any | R1: PR Number/Link | S1: PR Created Date | T1: PR Approved Date | U1: Reviewer 1 | V1: Code Review Comments, if any | W1: Reviewer 2 | X1: Approved Date | Y1: Code Review Comments, if any2 | Z1: Internal PO -POV Comments | AA1: Client PO -POV Comments | AB1: Comments
A2: 1 | B2: Meal Order | C2: =Dashboard!$F$1 -> 46157 | D2: =Dashboard!$H$1 -> 46170 | E2: 2.3 Sprint 2 Stretch | F2: Sudheer | G2: 47151 | H2: Meal Orders(v2.3) - Implementation Regression Automation for Reports Module(All Reports) | I2: Story Being Developed | J2: 13 | K2: 7.5 | L2: 30 | AB2: 1.AS part of this sprint , I have completed implementation for all reports with date format .Xlsx and also included Schedule tab functionality for all reports 2. The pending is like to impalement few more formats like PDF , Html , CSV export (CSV Applicable for few reports only)
A3: 2 | B3: Meal Order | C3: =Dashboard!$F$1 -> 46157 | D3: =Dashboard!$H$1 -> 46170 | E3: 2.3 Sprint 2 | F3: Dhivyalakshmi/Sudheer | G3: 30125 | H3: Meal Orders - Reports - Menu Template (Parameter Screen + Schedule Report) | I3: Story Completed | J3: 5 | K3: 5 | L3: 20 | M3: Completed | R3: https://heartlandschools.visualstudio.com/Meal%20Orders/_git/Meal%20Orders/pullrequest/41033 | S3: 45716 | T3: 45716 | U3: Ruban | W3: Mike | X3: 45716 | AB3: Added test case link and executed as well . All steps are got passed .
A4: 3 | B4: Meal Order | C4: =Dashboard!$F$1 -> 46157 | D4: =Dashboard!$H$1 -> 46170 | E4: 2.3 Sprint 2 | F4: Kiruthiga | G4: 47108 | H4: Menu Calendar Preview - Styling issue | I4: Story Completed | J4: 5 | K4: 3 | L4: 10 | M4: Completed | R4: https://dev.azure.com/heartlandschools/Meal%20Orders/_git/Meal%20Orders/pullrequest/40942 | S4: 45713 | T4: 45713 | U4: Ruban | W4: Mike | X4: 45713 | AB4: In recent code there is an impact in Menu Calendar style, working on finding root cause analysis
A5: 4 | B5: Meal Order | C5: =Dashboard!$F$1 -> 46157 | D5: =Dashboard!$H$1 -> 46170 | E5: 2.3 Sprint 2 Stretch | F5: Kiruthiga | G5: 46826 | H5: Meal Orders(v2.?) - Admin - Reports - Header Section | I5: Story Being Developed | J5: 13 | K5: 8 | L5: 30
A6: 5 | B6: Meal Order | C6: =Dashboard!$F$1 -> 46157 | D6: =Dashboard!$H$1 -> 46170 | E6: 2.3 Sprint 2 Stretch | F6: Kiruthiga | G6: 24720 | H6: Meal Orders - Order Management - Receipt Print console error | I6: Defect Fixed | J6: 3 | K6: 3 | L6: 5 | M6: Completed | R6: https://dev.azure.com/heartlandschools/Meal%20Orders/_git/Meal%20Orders/pullrequest/41023 | S6: 45716 | T6: 45716 | U6: Ruban | W6: Mike | X6: 45716
A7: 6 | B7: Meal Order | C7: =Dashboard!$F$1 -> 46157 | D7: =Dashboard!$H$1 -> 46170 | E7: 2.3 Sprint 2 Stretch | F7: Dhivyalakshmi/Sudheer | G7: 24524 | H7: Meal Orders - HSS User - Provider switch site search not functional | I7: Story Completed | J7: 3 | K7: 3 | L7: 9 | R7: https://dev.azure.com/heartlandschools/Meal%20Orders/_git/Meal%20Orders/pullrequest/41046 | S7: 45719 | T7: 45719 | U7: Ruban | W7: Mike | X7: 45719
A8: 7 | B8: Meal Order | C8: =Dashboard!$F$1 -> 46157 | D8: =Dashboard!$H$1 -> 46170 | E8: 2.3 Sprint 2 | F8: Ruban | G8: 46219 | H8: Meal Orders(v2.2) - Admin - Order Management - Mark as Open (Non-Integrated District) | I8: Story Completed | J8: 8 | K8: 8 | L8: 22 | M8: Completed | R8: https://heartlandschools.visualstudio.com/Meal%20Orders/_git/Meal%20Orders/pullrequest/41029 | S8: 45716 | T8: 45716 | U8: Ruban | W8: Mike | X8: 45716
A9: 8 | B9: Meal Order | C9: =Dashboard!$F$1 -> 46157 | D9: =Dashboard!$H$1 -> 46170 | E9: 2.3 Sprint 2 Stretch | F9: Ruban | G9: 24743 | H9: Meal Orders - Admin - Order Mgmt. - Mark open confirmation for unfulfilled order | I9: Defect Fixed | J9: 1 | K9: 1 | L9: 6 | M9: Completed | R9: https://heartlandschools.visualstudio.com/Meal%20Orders/_git/Meal%20Orders/pullrequest/41029 | S9: 45716 | T9: 45716 | U9: Ruban | W9: Mike | X9: 45716
A10: 9 | B10: Meal Order | C10: =Dashboard!$F$1 -> 46157 | D10: =Dashboard!$H$1 -> 46170 | E10: 2.3 Sprint 2 Stretch | F10: Ruban/Sudheer | G10: 47308 | H10: Meal Orders(v2.3) - Stock Management - Code Refactoring | I10: Story Ready For Testing | J10: 5 | K10: 3 | L10: 12 | M10: Completed | R10: https://heartlandschools.visualstudio.com/Meal%20Orders/_git/Meal%20Orders/pullrequest/41054 | S10: 45719 | T10: 45719 | U10: Ruban | W10: Mike | X10: 45719
A11: 10 | B11: Meal Order | C11: =Dashboard!$F$1 -> 46157 | D11: =Dashboard!$H$1 -> 46170 | E11: 2.3 Sprint 2 Stretch | F11: Dhivyalakshmi/Sudheer | G11: 24717 | H11: Meal Orders(2.2)- Admin - Order Management Filter Retain issue For Recipient Printing | I11: Story Being Developed | J11: 2 | K11: 2 | L11: 6
A12: 11 | B12: Meal Order | C12: 45709 | D12: 45722 | E12: 2.3 Sprint 2 Stretch | F12: Ruban/Sudheer | G12: 24778 | H12: Meal Orders - Parent/Teacher - Stock Mgmt. customization validation updating item in cart | I12: Defect Fixed | J12: 2 | K12: 2 | L12: 8 | M12: Completed | R12: https://heartlandschools.visualstudio.com/Meal%20Orders/_git/Meal%20Orders/pullrequest/41088 | S12: 45721 | T12: 45721 | U12: Ruban | W12: Mike | X12: 45721
A13: 12 | B13: Meal Order | C13: 45709 | D13: 45722 | E13: 2.3 Sprint 2 Stretch | F13: Ruban/Sudheer | G13: 24788 | H13: Meal Orders - Parent - Cart editing custom reimb meals missing customizations | I13: Defect Fixed | J13: 2 | K13: 2 | L13: 8 | M13: Completed | R13: https://heartlandschools.visualstudio.com/Meal%20Orders/_git/Meal%20Orders/pullrequest/41087 | S13: 45721 | T13: 45721 | U13: Ruban | W13: Mike | X13: 45721

Sheet 2.3 Sprint 1-Status
A1: S.No | B1: Application Name | C1: Sprint Start Date | D1: Sprint End Date | E1: Sprint | F1: Developer | G1: Story ID/Defect ID | H1: Description | I1: Status | J1: Estimated(sp) | K1: Actual(sp) | L1: Actual Hours Worklog | M1: Unit testing | N1: Peer Tested By | O1: Peer Tested Defects, if any | P1: Peer Reviewed By | Q1: Peer Code Review Comments, if any | R1: PR Number/Link | S1: PR Created Date | T1: PR Approved Date | U1: Reviewer 1 | V1: Code Review Comments, if any | W1: Reviewer 2 | X1: Approved Date | Y1: Code Review Comments, if any2 | Z1: Internal PO -POV Comments | AA1: Client PO -POV Comments | AB1: Comments
A2: 1 | B2: =Dashboard!$J$1 -> Meal Order | C2: =Dashboard!$F$1 -> 46157 | D2: =Dashboard!$H$1 -> 46170 | E2: 2.3 Sprint 1 | F2: Kiruthiga | G2: 47110 | H2: Meal Orders(v2.3) - Admin - Reports - Student Fulfillment (Portrait Model) | I2: Story Completed | J2: 5 | K2: 5 | L2: 24 | M2: Completed | P2: Ruban | R2: https://heartlandschools.visualstudio.com/Meal%20Orders/_git/Meal%20Orders/pullrequest/40756 | S2: 45702 | T2: 45702 | U2: Ruban | W2: Mike | X2: 45702 | AB2: Onsite QA has reported 3 bounce back for this story. Fixed one item and other two will be addressed in a separate defect as it is occuring in other reports too.
A3: 2 | B3: =Dashboard!$J$1 -> Meal Order | C3: =Dashboard!$F$1 -> 46157 | D3: =Dashboard!$H$1 -> 46170 | E3: 2.3 Sprint 1 Stretch | F3: Ruban | G3: 46209 | H3: Meal Orders( v2.3) - Admin - Order Management - Bulk Order Cancellation | I3: Story Completed | J3: 13 | K3: 13 | L3: 50 | M3: Completed | P3: Mike | R3: https://heartlandschools.visualstudio.com/Meal%20Orders/_git/Meal%20Orders/pullrequest/40835?_a=files | S3: 45707 | T3: 45707 | U3: Ruban | W3: Mike | X3: 45707
A4: 3 | B4: =Dashboard!$J$1 -> Meal Order | C4: =Dashboard!$F$1 -> 46157 | D4: =Dashboard!$H$1 -> 46170 | E4: 2.3 Sprint 1 Stretch | F4: Sudheer | G4: 47151 | H4: Meal Orders(v2.3) - Implementation Regression Automation for Reports Module(All Reports) | I4: Story Being Developed | J4: 13 | K4: 4.75 | L4: 19 | AB4: As part story I have completed automation for 6 Reports and committed into feature brnach . Continue to working on rest of the reports .
A5: 4 | B5: =Dashboard!$J$1 -> Meal Order | C5: =Dashboard!$F$1 -> 46157 | D5: =Dashboard!$H$1 -> 46170 | E5: 2.3 Sprint 1 Stretch | F5: Dhivyalakshmi | G5: 30125 | H5: Meal Orders - Reports - Menu Template (Parameter Screen + Schedule Report) | I5: Story Being Developed | J5: 13 | L5: 64
A6: 5 | B6: =Dashboard!$J$1 -> Meal Order | C6: =Dashboard!$F$1 -> 46157 | D6: =Dashboard!$H$1 -> 46170 | E6: 2.3 Sprint 1 | F6: Ruban/ Sudheer | G6: 24571 | H6: Meal Orders(2.2)- Admin - Order Management Filter Retain issue | I6: Defect Fixed | J6: 2 | K6: 2 | L6: 13 | M6: Completed | P6: Mike | R6: https://heartlandschools.visualstudio.com/Meal%20Orders/_git/Meal%20Orders/pullrequest/40843 | S6: 45707 | T6: 45707 | U6: Ruban | W6: Mike | X6: 45707
A7: 6 | B7: =Dashboard!$J$1 -> Meal Order | C7: =Dashboard!$F$1 -> 46157 | D7: =Dashboard!$H$1 -> 46170 | E7: 2.3 Sprint 1 Stretch | F7: Ruban /Sudheer | G7: 47192 | H7: Meal Orders(v2.3) - Admin - Integrated Districts - Hide Reactivation | I7: Story Completed | J7: 1 | K7: 1 | L7: 6 | M7: Completed | P7: Mike | R7: https://heartlandschools.visualstudio.com/Meal%20Orders/_git/Meal%20Orders/pullrequest/40835?_a=files | S7: 45707 | T7: 45707 | U7: Ruban | W7: Mike | X7: 45707
A8: 7 | B8: =Dashboard!$J$1 -> Meal Order | C8: =Dashboard!$F$1 -> 46157 | D8: =Dashboard!$H$1 -> 46170 | E8: 2.3 Sprint 1 | F8: Kiruthiga | G8: 47108 | H8: Meal Orders(v2.3) - Admin - Menu Calendar Preview - Teacher Ordering - Site | I8: Story Being Tested | J8: 1 | L8: 6 | AB8: Support to Onsite developer

Sheet 2.3 Sprint 1-Defect
A1: S.No | B1: Sprint # | C1: Story/Defect ID | D1: Parent Story | E1: Developer | F1: Issue Type | G1: Issue Description | H1: Priority | I1: Defect Source | J1: Type | K1: Found By | L1: Status | M1: Root Cause Category | N1: RCA Comment *
B2: 2.3 Sprint 1 | C2: 24571 | E2: Ruban | F2: Defect | G2: Meal Orders(2.2)- Admin - Order Management Filter Retain issue | H2: Minor | I2: Manual | J2: External | K2: Relevantz | L2: Closed | M2: Existing_Issues | N2: Production Issue. Existing_Issues found during regression testing . And fixed
B3: 2.3 Sprint 1 | C3: 47110 | D3: 47110 | E3: Kiruthiga | F3: Bounceback | G3: Meal Orders(v2.3) - Admin - Reports - Student Fulfillment (Portrait Model) | H3: Minor | I3: Manual | J3: Internal | K3: Client | L3: Closed | M3: Design | N3: Internal issue - Identified by onsite QA during story testing Retention Issue

Sheet 2.2 Sprint 6-Status
A1: S.No | B1: Application Name | C1: Sprint Start Date | D1: Sprint End Date | E1: Sprint | F1: Developer | G1: Story ID/Defect ID | H1: Description | I1: Status | J1: Estimated(sp) | K1: Actual(sp) | L1: Actual Hours Worklog | M1: Unit testing | N1: Peer Tested By | O1: Peer Tested Defects, if any | P1: Peer Reviewed By | Q1: Peer Code Review Comments, if any | R1: PR Number/Link | S1: PR Created Date | T1: PR Approved Date | U1: Reviewer 1 | V1: Code Review Comments, if any | W1: Reviewer 2 | X1: Approved Date | Y1: Code Review Comments, if any2 | Z1: Internal PO -POV Comments | AA1: Client PO -POV Comments | AB1: Comments
A2: 1 | B2: =Dashboard!$J$1 -> Meal Order | C2: =Dashboard!$F$1 -> 46157 | D2: =Dashboard!$H$1 -> 46170 | E2: 2.2 Sprint 6 | F2: Ruban/Sudheer | G2: 46887 | H2: Meal Orders (2.2) - Regression - Report | I2: Story Completed | J2: 5 | K2: 5 | L2: 11
A3: 2 | B3: =Dashboard!$J$1 -> Meal Order | C3: =Dashboard!$F$1 -> 46157 | D3: =Dashboard!$H$1 -> 46170 | E3: 2.2 Sprint 6 | F3: Ruban/Sudheer | G3: 46890 | H3: Meal Orders (2.2) - Regression - Admin | I3: Story Completed | J3: 8 | K3: 8 | L3: 20
A4: 3 | B4: =Dashboard!$J$1 -> Meal Order | C4: =Dashboard!$F$1 -> 46157 | D4: =Dashboard!$H$1 -> 46170 | E4: 2.2 Sprint 6 | F4: Kiruthiga | G4: 24526 | H4: (Regression) Meal Orders - Stock Management - Daily Limit/Qty In Stock removed when cursor placed in field | I4: Defect Fixed | J4: 1 | K4: 1 | L4: 3 | P4: Ruban | R4: https://dev.azure.com/heartlandschools/Meal%20Orders/_git/Meal%20Orders/pullrequest/40402?_a=files | S4: 45678 | T4: 45678 | U4: Ruban | W4: Mike | X4: 45678
A5: 4 | B5: =Dashboard!$J$1 -> Meal Order | C5: =Dashboard!$F$1 -> 46157 | D5: =Dashboard!$H$1 -> 46170 | E5: 2.2 Sprint 6 | F5: Kiruthiga | G5: 24527 | H5: Meal Orders - Admin - Site Order Timings not refreshing after ordering parameter override | I5: Defect Fixed | J5: 2 | K5: 2 | L5: 1 | R5: https://dev.azure.com/heartlandschools/Meal%20Orders/_git/Meal%20Orders/pullrequest/40493 | S5: 45684 | U5: Ruban
A6: 5 | B6: =Dashboard!$J$1 -> Meal Order | C6: =Dashboard!$F$1 -> 46157 | D6: =Dashboard!$H$1 -> 46170 | E6: 2.2 Sprint 6 | F6: Kiruthiga | G6: 24543 | H6: (Regression) Admin - Stock Mgmt - Stock Edit validation occurs immediately upon input | I6: Defect Fixed | J6: 1 | K6: 1 | L6: 3 | M6: Completed | P6: Ruban | R6: https://dev.azure.com/heartlandschools/Meal%20Orders/_git/Meal%20Orders/pullrequest/40475 | S6: 45681 | T6: 45681 | U6: Ruban | W6: Mike | X6: 45681
A7: 6 | B7: =Dashboard!$J$1 -> Meal Order | C7: =Dashboard!$F$1 -> 46157 | D7: =Dashboard!$H$1 -> 46170 | E7: 2.2 Sprint 6 | F7: Ruban | G7: 24573 | H7: Meal Orders - Parents unable to login (redirect loop) | I7: Defect Fixed | J7: 3 | K7: 3 | L7: 6 | AB7: Production Release (Jan 30th) was rolled back due to an issue with Parent Login, the issue was fixed and the release is postponed on Feb 06th. The issue was Sentral AUS had made change Household API to include new fields(Which is not applicable for US)). There was no proper null checks for enrollments for these fields. When a Parent has inactive enrollments for a student then causes to error and prevent Parent Login
A8: 7 | B8: =Dashboard!$J$1 -> Meal Order | C8: =Dashboard!$F$1 -> 46157 | D8: =Dashboard!$H$1 -> 46170 | E8: 2.2 Sprint 6 Stretch | F8: Dhivyalakshmi | G8: 30125 | H8: Meal Orders - Reports - Menu Template (Parameter Screen + Schedule Report | I8: Story Being Developed | J8: 13 | L8: 20 | AB8: Its an new report story ,which is used to view menu template details and get full menu details which is added in menu template.
A9: 8 | B9: =Dashboard!$J$1 -> Meal Order | C9: =Dashboard!$F$1 -> 46157 | D9: =Dashboard!$H$1 -> 46170 | E9: 2.2 Sprint 6 Stretch | F9: Sudheer | G9: 47106 | H9: Meal Orders (v2.3) - Stock Management - Test Cases | I9: Story Completed | J9: 3 | K9: 3 | L9: 14
A10: 9 | B10: =Dashboard!$J$1 -> Meal Order | C10: =Dashboard!$F$1 -> 46157 | D10: 45694 | E10: 2.2 Sprint 6 Stretch | F10: Kiruthiga | G10: 46454 | H10: Meal Orders(v2.3) - Reports - Student Fulfillment (Portrait Model) - Analysis | I10: Story Completed | J10: 2 | K10: 2 | L10: 9 | M10: NA | P10: NA | AB10: It is a analysis story and there is no specific PR link and further details
A11: 10 | B11: =Dashboard!$J$1 -> Meal Order | C11: =Dashboard!$F$1 -> 46157 | D11: 45694 | E11: 2.2 Sprint 6 Stretch | F11: Kiruthiga | G11: 47110 | H11: Meal Orders(v2.3) - Admin - Reports - Student Fulfillment (Portrait Model) | I11: Story Peer Review | J11: 5 | K11: 5 | L11: 5 | M11: completed | P11: Ruban | R11: https://dev.azure.com/heartlandschools/Meal%20Orders/_git/Meal%20Orders/pullrequest/40756 | S11: 45701 | U11: Ruban | W11: Mike
A12: 11 | B12: =Dashboard!$J$1 -> Meal Order | C12: =Dashboard!$F$1 -> 46157 | D12: =Dashboard!$H$1 -> 46170 | E12: 2.2 Sprint 6 Stretch | F12: Ruban | G12: 47004 | H12: Meal Orders(v2.3) - Admin - Bulk Order Cancellation/Open - Analysis & Discovery | I12: Story Completed | J12: 2 | K12: 2 | L12: 8
A13: 12 | B13: MealOrders | C13: 45681 | D13: 45694 | E13: 2.2 Sprint 6 Stretch | F13: Dhivyalakshmi | G13: 24571 | H13: Meal Orders(2.2)- Admin - Order Management Filter Retain issue | I13: Story Being Developed | J13: 3 | L13: 7

Sheet 2.2 Sprint 6-Defect
A3: S.No | B3: Sprint # | C3: Story/Defect ID | D3: Developer | E3: Issue Type | F3: Issue Description | G3: Priority | H3: Type | I3: Status | J3: Root Cause Category | K3: RCA Reason Mandatory* | L3: Comments
A4: 1 | B4: 2.2 Sprint 6 | C4: 24526 | D4: Kiruthiga | E4: Bounceback | F4: (Regression) Meal Orders - Stock Management - Daily Limit/Qty In Stock removed when cursor placed in field | G4: Major | H4: Internal | I4: Closed | J4: Existing_Issues | K4: Bounce Back Issue and fixed by OffShore team. Completed Testing by QA
A5: 2 | B5: 2.2 Sprint 6 | C5: 24543 | D5: Kiruthiga | E5: Defect | F5: (Regression) Admin - Stock Mgmt - Stock Edit validation occurs immediately upon input | G5: Significant | H5: Internal | I5: Closed | J5: Existing_Issues | K5: Found as part of Regression , Fixed by Offshore Team and Tested by QA (Offshore)
A6: 3 | B6: 2.2 Sprint 6 | C6: 24527 | D6: Kiruthiga | E6: Defect | F6: Meal Orders - Admin - Site Order Timings not refreshing after ordering parameter override | G6: Significant | H6: Internal | I6: Closed | J6: Existing_Issues | K6: UI retention issue , Fixed by OffShore Team and Tested By both Onshore and Offshore QA
A7: 4 | B7: 2.2 Sprint 6 | C7: 24573 | D7: Ruban | E7: Defect | F7: Meal Orders - Parents unable to login (redirect loop) | G7: Major | H7: External | I7: Closed | J7: Existing_Issues | K7: Issue form Sentral side And Onsite devloper fixed and Tested by both Onshore and Offshore QA
A34: Root Cause category
A35: Enhancements
A36: Existing_Issues
A37: Requirements
A38: QA
A39: Design
A40: Documentation
A41: Development
A42: Project_Management
A43: Environment_Related

Sheet 2.3 Sprint 2-Defect
A1: S.No | B1: Sprint # | C1: Story/Defect ID | D1: Parent Story | E1: Developer | F1: Issue Type | G1: Issue Description | H1: Priority | I1: Defect Source | J1: Type | K1: Found By | L1: Status | M1: Root Cause Category | N1: RCA Comment *
B2: 2.3 Sprint 2 | C2: 24720 | E2: Kiruthiga/Sudheer | F2: Defect | G2: Meal Orders - Order Management - Receipt Print console error | H2: Minor | I2: Manual | J2: Internal | K2: Relevantz | L2: Closed | M2: Environment_Related | N2: Issue occuring in local environment alone
B3: 2.3 Sprint 2 | C3: 24524 | E3: Dhivyalakshmi/Sudheer | F3: Defect | G3: Meal Orders - HSS User - Provider switch site search not functional | H3: Minor | I3: Manual | J3: Internal | K3: Client | L3: Closed | M3: Existing Issue | N3: Internal issue - Identified by onsite QA during story testing
B4: 2.3 Sprint 2 Stretch | C4: 24743 | E4: Ruban | F4: Defect | G4: Meal Orders - Admin - Order Mgmt. - Mark open confirmation for unfulfilled order | H4: Minor | I4: Manual | J4: Internal | K4: Client | L4: Closed | M4: Existing_Issues | N4: Internal issue - Identified by onsite QA , It is a minor content change'
B5: 2.3 Sprint 2 Stretch | C5: 24717 | E5: Dhivyalakshmi/Sudheer | F5: Defect | G5: Meal Orders(2.2)- Admin - Order Management Filter Retain issue For Recipient Printing | H5: Minor | I5: Manual | J5: Internal | K5: Relevantz | L5: Open | M5: Existing Issue | N5: Internal issue - Identified in Offshore QA
B6: 2.3 Sprint 2 Stretch | C6: 24778 | E6: Ruban | F6: Defect | G6: Meal Orders - Parent/Teacher - Stock Mgmt. customization validation updating item in cart | H6: Minor | I6: Manual | J6: Internal | K6: Relevantz | L6: Closed | M6: Existing_Issues | N6: Internal Issue identified by developer
B7: 2.3 Sprint 2 Stretch | C7: 24788 | E7: Ruban | F7: Defect | G7: Meal Orders - Parent - Cart editing custom reimb meals missing customizations | H7: Significant | I7: Manual | J7: Internal | K7: Relevantz | L7: Closed | M7: Existing_Issues | N7: Internal Issue identified by developer

Sheet 2.2 Sprint 5-Defect
A3: S.No | B3: Sprint # | C3: Story/Defect ID | D3: Developer | E3: Issue Type | F3: Issue Description | G3: Priority | H3: Type | I3: Status | J3: Root Cause Category | K3: RCA Reason Mandatory* | L3: Comments
A4: 1 | B4: 2.2 Sprint 5 Stretch | C4: 23746 | D4: Dhivyalakshmi | E4: Defect | F4: Meal Order - Admin -Disable the Active/Inactive column in the serving period when the user has only one serving period available. | G4: Significant | H4: External | I4: Defect Fixed | J4: Existing_Issues | K4: Existing Functionality issue | L4: Fixed by OffShore Developer
A5: 3 | B5: 2.2 Sprint 5 | C5: 24480 | D5: Kiruthiga/Ruban | E5: Defect | F5: Meal Orders(v2.2) - Admin - Stock Management - Values of Daily Limit and Qty In Stock are retaining even after deleting the values | G5: Significant | H5: External | I5: Closed | J5: Existing_Issues | K5: Existing Functionality issue
A6: 4 | B6: 2.2 Sprint 5 | C6: 24500 | D6: Kiruthiga | E6: Defect | F6: (Regression) Meal Orders - Reverted Menu Template item edits from Menu Calendar affecting template preview | G6: Minor | H6: External | I6: Defect Fixed | J6: Existing_Issues | K6: Existing Functionality issue
A7: 5 | B7: 2.2 Sprint 5 | C7: 24517 | D7: Kiruthiga | E7: Defect | F7: (Regression) Meal Orders - Stock Management - TypeError when sorting certain columns | G7: Minor | H7: External | I7: Defect Fixed | J7: Existing_Issues | K7: Existing Functionality issue
A8: 6 | B8: 2.2 Sprint 5 | C8: 24526 | D8: Kiruthiga | E8: Defect | F8: (Regression) Meal Orders - Stock Management - Daily Limit/Qty In Stock removed when cursor placed in field | G8: Significant | H8: External | I8: Inprogress | J8: Existing_Issues | K8: Existing Functionality issue
A9: 7 | B9: 2.2 Sprint 5 | C9: 24468 | D9: Kiruthiga | E9: Defect | F9: Meal Orders(v2.2) - Admin - Ordering Parameters and Site Settings - Filter and Order Timing | G9: Significant | H9: Internal | I9: Inprogress | J9: Existing_Issues | K9: Bounce back
A10: 8 | B10: 2.2 Sprint 5 Stretch | C10: 24523 | D10: Dhivyalakshmi | E10: Defect | F10: (Regression) Meal Orders - Admin - Serving Period delete messaging change | G10: Significant | H10: External | I10: Defect Fixed | J10: Existing_Issues | K10: Existing Functionality issue caused by additional changes in that pages. | L10: Fixed by OffShore Developer
A11: 9 | B11: 2.2 Sprint 5 | C11: 24502 | D11: Kiruthiga | E11: Defect | F11: (Regression) Meal Orders - Admin - Menu Calendar daily menu template name field not read only | G11: Significant | H11: External | I11: Defect Fixed | J11: Existing_Issues | K11: Sentral changed the functianlity but it is not required for US
A12: 10 | B12: 2.2 Sprint 5 | C12: 24514 | D12: Ruban | E12: Defect | F12: (Regression) Meal Orders - Teacher - Items added to teacher order from cart not visible | G12: Significant | H12: External | I12: Defect Fixed | J12: Existing_Issues | K12: Logical issue in recent changes
A13: 11 | B13: 2.2 Sprint 5 | C13: 24528 | D13: Ruban | E13: Defect | F13: (Regression) Meal Orders - Stock Management - Rule not set when order cancelled from my orders | G13: Significant | H13: Internal | I13: Defect Fixed | J13: Logical issue in recent changes | K13: Logical issue in recent changes
A14: 12 | B14: 2.2 Sprint 5 Stretch | C14: 24527 | D14: Kiruthiga | E14: Defect | F14: Meal Orders - Admin - Site Order Timings not refreshing after ordering parameter override | G14: Significant | H14: External | I14: Defect Being Fixed | J14: Existing_Issues | K14: Existing Functionality issue
A15: 13 | B15: 2.2 Sprint 5 Stretch | C15: 24531 | D15: Ruban | E15: Defect | F15: Meal Orders - Parent - Automatic Cart Item Update text alignment issue | G15: Minor | H15: Internal | I15: Defect Fixed | J15: Existing_Issues | K15: Existing UI issue
A16: 14 | B16: 2.2 Sprint 5 Stretch | C16: 24532 | D16: Ruban | E16: Defect | F16: Meal Orders - Admin - Reactivation validation messaging duplicated | G16: Minor | H16: Internal | I16: Defect Fixed | J16: Logical issue in recent changes | K16: Logical issue in recent changes
A17: 15
A33: Root Cause category
A34: Enhancements
A35: Existing_Issues
A36: Requirements
A37: QA
A38: Design
A39: Documentation
A40: Development
A41: Project_Management
A42: Environment_Related

Sheet 2.2 Sprint 4-Status
A1: S.No | B1: Application Name | C1: Sprint Start Date | D1: Sprint End Date | E1: Sprint | F1: Developer | G1: Story ID/Defect ID | H1: Description | I1: Status | J1: Estimated(hrs/sp) | K1: Actual(hrs/sp) | L1: Column1 | M1: Unit testing | N1: Peer Tested By | O1: Peer Tested Defects, if any | P1: Peer Reviewed By | Q1: Peer Code Review Comments, if any | R1: PR Number/Link | S1: PR Created Date | T1: PR Approved Date | U1: Reviewer 1 | V1: Code Review Comments, if any | W1: Reviewer 2 | X1: Approved Date | Y1: Code Review Comments, if any2 | Z1: Internal PO -POV Comments | AA1: Client PO -POV Comments | AB1: Comments
A2: 1 | B2: =Dashboard!$J$1 -> Meal Order | C2: =Dashboard!$F$1 -> 46157 | D2: =Dashboard!$H$1 -> 46170 | E2: 2.2 Sprint 4 | F2: Kiruthiga | G2: 46521 | H2: Meal Orders(v2.2) - Stock Management - Teacher Ordering - Site and Site Groups | I2: Completed | J2: 8 | K2: 8 | P2: Ruban | R2: https://dev.azure.com/heartlandschools/Meal%20Orders/_git/Meal%20Orders/pullrequest/40188 | S2: 45717 | U2: Ruban | W2: Mike | X2: 45660
A3: =A2+1 -> 2 | B3: =Dashboard!$J$1 -> Meal Order | C3: =Dashboard!$F$1 -> 46157 | D3: =Dashboard!$H$1 -> 46170 | E3: 2.2 Sprint 4 | F3: Rachel/Sudheer | G3: 44110 | H3: Meal Orders(v2.1) - SSO & Admin - Multi-Select Dropdown - Eliminating the Selected once | I3: Completed | J3: 4 | K3: 4 | M3: Rachel | N3: Rachel | P3: Mike | R3: https://dev.azure.com/heartlandschools/Meal%20Orders/_git/Meal%20Orders/pullrequest/40068 | S3: 13/12/2024 | T3: 13/12/2024 | U3: Mike | W3: Mike
A4: =A3+1 -> 3 | B4: =Dashboard!$J$1 -> Meal Order | C4: =Dashboard!$F$1 -> 46157 | D4: =Dashboard!$H$1 -> 46170 | E4: 2.2 Sprint 4 | F4: Ruban | G4: 46705 | H4: Meal Orders(v2.2) - Report - Stock Menu Items - Adding Serving Period | I4: Completed | J4: 3 | K4: 3 | R4: https://dev.azure.com/heartlandschools/Meal%20Orders/_git/Meal%20Orders/pullrequest/40188 | S4: 45717 | T4: 45717 | U4: Ruban | W4: Mike | X4: 45660
A5: =A4+1 -> 4 | B5: =Dashboard!$J$1 -> Meal Order | C5: =Dashboard!$F$1 -> 46157 | D5: =Dashboard!$H$1 -> 46170 | E5: 2.2 Sprint 4 | F5: Kiruthiga | G5: 46713 | H5: Meal Orders(v2.2) - Stock Management - Individual Ordering - Include Serving Period | I5: QA | J5: 8 | K5: 8 | P5: Ruban | R5: https://dev.azure.com/heartlandschools/Meal%20Orders/_git/Meal%20Orders/pullrequest/40188 | S5: 45717 | T5: 45717 | U5: Ruban | W5: Mike | X5: 45660 | AA5: 1. Adding static text when there is no order(s) available 2. Validation content change for out of stock case | AB5: Development is completed, Testing is in Progress. End - End Testing is required for this EPIC Feature
A6: =A5+1 -> 5 | B6: =Dashboard!$J$1 -> Meal Order | C6: =Dashboard!$F$1 -> 46157 | D6: =Dashboard!$H$1 -> 46170 | E6: 2.2 Sprint 4 | F6: Kiruthiga | G6: 46458 | H6: Meal Orders (v2.2) - Stock Management - Admin - Cancellation & Reactivation | I6: Completed | J6: 5 | K6: 5 | P6: Ruban | R6: https://dev.azure.com/heartlandschools/Meal%20Orders/_git/Meal%20Orders/pullrequest/40188 | S6: 45717 | T6: 45717 | U6: Ruban | W6: Mike | X6: 45660
A7: =A6+1 -> 6 | B7: =Dashboard!$J$1 -> Meal Order | C7: =Dashboard!$F$1 -> 46157 | D7: =Dashboard!$H$1 -> 46170 | E7: 2.2 Sprint 4 | F7: Ruban | G7: 46714 | H7: Meal Orders(v2.2) - Stock Management - Teacher Ordering - Include Serving Period | I7: QA | J7: 8 | K7: 8 | R7: https://dev.azure.com/heartlandschools/Meal%20Orders/_git/Meal%20Orders/pullrequest/40188 | S7: 45717 | T7: 45717 | U7: Ruban | W7: Mike | X7: 45660 | AB7: Development is completed, Testing is in Progress. End - End Testing is required for this EPIC Feature
A8: =A7+1 -> 7 | B8: =Dashboard!$J$1 -> Meal Order | C8: =Dashboard!$F$1 -> 46157 | D8: =Dashboard!$H$1 -> 46170 | E8: 2.2 Sprint 4 Strech | F8: Dhivyalakshmi/sudeer | G8: 24397 | H8: Meal Orders - Admin - Navigation Menu text font size inconsistent | I8: Completed | J8: 2 | K8: 2 | M8: Dhivyalakshmi | N8: Ruban | P8: Kiruthiga | R8: https://dev.azure.com/heartlandschools/Meal%20Orders/_git/Meal%20Orders/pullrequest/40131 | S8: 45646 | T8: 45660 | U8: Ruban | W8: Mike | X8: 45660
A9: =A8+1 -> 8 | B9: =Dashboard!$J$1 -> Meal Order | C9: =Dashboard!$F$1 -> 46157 | D9: =Dashboard!$H$1 -> 46170 | E9: 2.2 Sprint 4 Stretch | F9: Dhivyalakshmi/sudeer | G9: 23861 | H9: Meal Orders - Admin - Item Type Not Updated On Menu Template | I9: Completed | J9: 3 | K9: 3 | M9: Dhivyalakshmi | N9: Ruban | P9: Kiruthiga | R9: https://dev.azure.com/heartlandschools/Meal%20Orders/_git/Meal%20Orders/pullrequest/40132 | S9: 45646 | T9: 45660 | U9: Ruban | W9: Mike | X9: 45660
A10: =A9+1 -> 9 | B10: =Dashboard!$J$1 -> Meal Order | C10: =Dashboard!$F$1 -> 46157 | D10: =Dashboard!$H$1 -> 46170 | E10: 2.2 Sprint 4 Strech | F10: Dhivyalakshmi | G10: 23746 | H10: Meal Order - Admin -Disable the Active/Inactive column in the serving period when the user has only one serving period available. | I10: Story Peer Review | J10: 3 | K10: 3 | M10: Dhivyalakshmi | N10: Ruban | P10: Kiruthiga | R10: https://dev.azure.com/heartlandschools/Meal%20Orders/_git/Meal%20Orders/pullrequest/40254 | S10: 45666 | U10: Ruban | W10: Mike
A11: =A10+1 -> 10 | B11: =Dashboard!$J$1 -> Meal Order | C11: =Dashboard!$F$1 -> 46157 | D11: =Dashboard!$H$1 -> 46170 | E11: 2.2 Sprint 4 Strech | F11: Dhivyalakshmi | G11: 24468 | H11: Meal Orders(v2.2) - Admin - Ordering Parameters and Site Settings - Filter and Order Timing | I11: Story Peer Review | J11: 2 | K11: 2 | M11: Dhivyalakshmi | N11: Ruban | P11: Kiruthiga | R11: https://dev.azure.com/heartlandschools/Meal%20Orders/_git/Meal%20Orders/pullrequest/40236 | S11: 45665 | U11: Ruban | W11: Mike
A12: =A11+1 -> 11 | B12: =Dashboard!$J$1 -> Meal Order | C12: =Dashboard!$F$1 -> 46157 | D12: =Dashboard!$H$1 -> 46170 | E12: 2.2 Sprint 4 Stretch | F12: Rachel/Sudheer | G12: 24395 | H12: Meal Orders - Parent/Teacher - Correct Customization Group details formatting and wording | I12: Completed | J12: 1 | K12: 1
A13: =A12+1 -> 12 | B13: =Dashboard!$J$1 -> Meal Order | C13: =Dashboard!$F$1 -> 46157 | D13: =Dashboard!$H$1 -> 46170 | E13: 2.2 Sprint 4 Stretch | F13: Sudheer | G13: 85707 | H13: Meal Orders(v2.2) - Tracking Regression Automation and Manual | I13: Completed | J13: 1 | K13: 1
A14: =A13+1 -> 13 | B14: =Dashboard!$J$1 -> Meal Order | C14: =Dashboard!$F$1 -> 46157 | D14: =Dashboard!$H$1 -> 46170 | E14: 2.2 Sprint 4 Stretch | F14: Ruban | G14: 24474 | H14: Meal Orders - Admin - Unable to reactivate cancelled orders containing reimbursable meal | I14: Completed | J14: 3 | K14: 3 | P14: Ruban | R14: https://dev.azure.com/heartlandschools/Meal%20Orders/_git/Meal%20Orders/pullrequest/40251

Sheet 2.2 Sprint 4-Defect
A3: S.No | B3: Sprint # | C3: Story/Defect ID | D3: Developer | E3: Issue Type | F3: Issue Description | G3: Priority | H3: Type | I3: Status | J3: Root Cause Category | K3: RCA Reason Mandatory* | L3: Comments
A4: 1 | B4: 2.2 Sprint 4 Stretch | C4: 24395 | D4: Rachel | E4: Defect | F4: Meal Orders - Parent/Teacher - Correct Customization Group details formatting and wording | G4: Significant | H4: External | I4: Completed | J4: Enhancements | K4: Onsite QA has found the issue and it is relaited some UI enhancements for Correct Customization Group details formatting | L4: Fixed By Onsite Developer and tested by Offshore QA
A5: 2 | B5: 2.2 Sprint 4 Stretch | C5: 24397 | D5: Dhivyalakshmi | E5: Defect | F5: Meal Orders - Admin - Navigation Menu text font size inconsistent | G5: Significant | H5: External | I5: Completed | J5: Existing_Issues | K5: Its related to UI Font Formatting issue | L5: Fixed by Offshore Developer and tested by Offshore QA
A6: 3 | B6: 2.2 Sprint 4 Stretch | C6: 23861 | D6: Dhivyalakshmi | E6: Defect | F6: Meal Orders - Admin - Item Type Not Updated On Menu Template | G6: Significant | H6: External | I6: Completed | J6: Existing_Issues | K6: Onsite QA has found the issue and it is functional code changes. | L6: Fixed by Offshore Developer and tested by Offshore QA
A7: 4 | B7: 2.2 Sprint 4 Stretch | C7: 23746 | D7: Dhivyalakshmi | E7: Defect | F7: Meal Order - Admin -Disable the Active/Inactive column in the serving period when the user has only one serving period available. | G7: Significant | H7: External | I7: Inprogress | J7: Existing_Issues | K7: Existing Functionality issue | L7: Fixed by Offshore Developer
A8: 5 | B8: 2.2 Sprint 4 Stretch | C8: 24468 | D8: Dhivyalakshmi | E8: Defect | F8: Meal Orders(v2.2) - Admin - Ordering Parameters and Site Settings - Filter and Order Timing | G8: Minor | H8: External | I8: Inprogress | J8: Existing_Issues | K8: Due to changes in adding functionality in ordering parameter page ,this defect occured. | L8: Fixed by OffShore Developer
A9: 6 | B9: 2.2 Sprint 4 Stretch | C9: 24474 | D9: Ruban | E9: Defect | F9: Meal Orders - Admin - Unable to reactivate cancelled orders containing reimbursable meal | G9: Significant | H9: External | I9: Completed | J9: Existing_Issues | K9: Existing Functionality issue
A34: Root Cause category
A35: Enhancements
A36: Existing_Issues
A37: Requirements
A38: QA
A39: Design
A40: Documentation
A41: Development
A42: Project_Management
A43: Environment_Related

Sheet 2.2 Sprint 5-Status
A1: S.No | B1: Application Name | C1: Sprint Start Date | D1: Sprint End Date | E1: Sprint | F1: Developer | G1: Story ID/Defect ID | H1: Description | I1: Status | J1: Estimated(hrs/sp) | K1: Actual(hrs/sp) | L1: Actual Hours Worklog | M1: Unit testing | N1: Peer Tested By | O1: Peer Tested Defects, if any | P1: Peer Reviewed By | Q1: Peer Code Review Comments, if any | R1: PR Number/Link | S1: PR Created Date | T1: PR Approved Date | U1: Reviewer 1 | V1: Code Review Comments, if any | W1: Reviewer 2 | X1: Approved Date | Y1: Code Review Comments, if any2 | Z1: Internal PO -POV Comments | AA1: Client PO -POV Comments | AB1: Comments
A2: 1 | B2: =Dashboard!$J$1 -> Meal Order | C2: =Dashboard!$F$1 -> 46157 | D2: =Dashboard!$H$1 -> 46170 | E2: 2.2 Sprint 5 | F2: Kiruthiga | G2: 46713 | H2: Meal Orders(v2.2) - Stock Management - Individual Ordering - Include Serving Period | I2: Story Completed | J2: 8 | K2: 8 | P2: Ruban | R2: https://dev.azure.com/heartlandschools/Meal%20Orders/_git/Meal%20Orders/pullrequest/40188 | S2: 45717 | T2: 45717 | U2: Ruban | W2: Mike | X2: 45660
A3: 2 | B3: =Dashboard!$J$1 -> Meal Order | C3: =Dashboard!$F$1 -> 46157 | D3: =Dashboard!$H$1 -> 46170 | E3: 2.2 Sprint 5 | F3: Ruban | G3: 46714 | H3: Meal Orders(v2.2) - Stock Management - Teacher Ordering - Include Serving Period | I3: Story Completed | J3: 8 | K3: 8 | R3: https://dev.azure.com/heartlandschools/Meal%20Orders/_git/Meal%20Orders/pullrequest/40188 | S3: 45717 | T3: 45717 | U3: Ruban | W3: Mike | X3: 45660
A4: 3 | B4: =Dashboard!$J$1 -> Meal Order | C4: =Dashboard!$F$1 -> 46157 | D4: =Dashboard!$H$1 -> 46170 | E4: 2.2 Sprint 5 | F4: Kiruthiga/Ruban | G4: 24480 | H4: Meal Orders(v2.2) - Admin - Stock Management - Values of Daily Limit and Qty In Stock are retaining even after deleting the values | I4: Defect Fixed | J4: 5 | K4: 5 | P4: Ruban | R4: https://dev.azure.com/heartlandschools/Meal%20Orders/_git/Meal%20Orders/pullrequest/40295?_a=files&path=/MealOrders.Web/Features/Teacher/TeacherController.cs | S4: 45670 | T4: 45670 | U4: Ruban | W4: Mike | X4: 45670
A5: 4 | B5: =Dashboard!$J$1 -> Meal Order | C5: =Dashboard!$F$1 -> 46157 | D5: =Dashboard!$H$1 -> 46170 | E5: 2.2 Sprint 5 | F5: Kiruthiga | G5: 24500 | H5: (Regression) Meal Orders - Reverted Menu Template item edits from Menu Calendar affecting template preview | I5: Defect Fixed | J5: 1 | K5: 1 | R5: https://dev.azure.com/heartlandschools/Meal%20Orders/_git/Meal%20Orders/pullrequest/40319 | S5: 45672 | T5: 45672 | U5: Ruban | W5: Mike | X5: 45672
A6: 5 | B6: =Dashboard!$J$1 -> Meal Order | C6: =Dashboard!$F$1 -> 46157 | D6: =Dashboard!$H$1 -> 46170 | E6: 2.2 Sprint 5 | F6: Dhivyalakshmi | G6: 23746 | H6: Meal Order - Admin -Disable the Active/Inactive column in the serving period when the user has only one serving period available. | I6: Defect Fixed | J6: 2 | K6: 2 | M6: Dhivyalakshmi | N6: Ruban | P6: Kiruthiga | R6: https://dev.azure.com/heartlandschools/Meal%20Orders/_git/Meal%20Orders/pullrequest/40254 | S6: 45666 | T6: 45673 | U6: Ruban | W6: Mike | X6: 45673
A7: 6 | B7: =Dashboard!$J$1 -> Meal Order | C7: =Dashboard!$F$1 -> 46157 | D7: =Dashboard!$H$1 -> 46170 | E7: 2.2 Sprint 5 | F7: Kiruthiga | G7: 24468 | H7: Meal Orders(v2.2) - Admin - Ordering Parameters and Site Settings - Filter and Order Timing | I7: Defect Ready For Testing | J7: 2 | M7: Dhivyalakshmi | N7: Ruban | P7: Kiruthiga | R7: https://dev.azure.com/heartlandschools/Meal%20Orders/_git/Meal%20Orders/pullrequest/40399 | S7: 45678 | T7: 45678 | U7: Ruban | W7: Mike | X7: 45678
A8: 7 | B8: =Dashboard!$J$1 -> Meal Order | C8: =Dashboard!$F$1 -> 46157 | D8: =Dashboard!$H$1 -> 46170 | E8: 2.2 Sprint 5 | F8: Kiruthiga | G8: 24517 | H8: (Regression) Meal Orders - Stock Management - TypeError when sorting certain columns | I8: Defect Fixed | J8: 1 | K8: 1 | P8: Ruban | R8: https://dev.azure.com/heartlandschools/Meal%20Orders/_git/Meal%20Orders/pullrequest/40373 | S8: 45675 | T8: 45678 | U8: Ruban | W8: Mike | X8: 45678
A9: 8 | B9: =Dashboard!$J$1 -> Meal Order | C9: =Dashboard!$F$1 -> 46157 | D9: =Dashboard!$H$1 -> 46170 | E9: 2.2 Sprint 5 | F9: Dhivyalakshmi | G9: 24523 | H9: (Regression) Meal Orders - Admin - Serving Period delete messaging change | I9: Defect Fixed | J9: 2 | K9: 2 | M9: Dhivyalakshmi | N9: Ruban | P9: Kiruthiga | R9: https://dev.azure.com/heartlandschools/Meal%20Orders/_git/Meal%20Orders/pullrequest/40374 | S9: 45675 | T9: 45678 | U9: Ruban | W9: Mike | X9: 45678
A10: 9 | B10: =Dashboard!$J$1 -> Meal Order | C10: =Dashboard!$F$1 -> 46157 | D10: =Dashboard!$H$1 -> 46170 | E10: 2.2 Sprint 5 | F10: Sudheer | G10: 46888 | H10: Meal Orders (2.2) - Regression - Teacher | I10: Story Completed | J10: 3 | K10: 3
A11: 10 | B11: =Dashboard!$J$1 -> Meal Order | C11: =Dashboard!$F$1 -> 46157 | D11: =Dashboard!$H$1 -> 46170 | E11: 2.2 Sprint 5 | F11: Sudheer | G11: 46889 | H11: Meal Orders (2.2) - Regression - Parent | I11: Story Completed | J11: 3 | K11: 3
A12: 11 | B12: =Dashboard!$J$1 -> Meal Order | C12: =Dashboard!$F$1 -> 46157 | D12: =Dashboard!$H$1 -> 46170 | E12: 2.2 Sprint 5 | F12: Dhivyalakshmi/Ruban | G12: 46887 | H12: Meal Orders (2.2) - Regression - Report | I12: Story Being Developed | J12: 5 | AB12: Will be carry forwarded to continue other reports. We have 13 reports with run reports and schedule reports with report inbox. Sentral had a new PR for CSV Format, so we will re running the tests
A13: 11 | B13: =Dashboard!$J$1 -> Meal Order | C13: =Dashboard!$F$1 -> 46157 | D13: =Dashboard!$H$1 -> 46170 | E13: 2.2 Sprint 5 | F13: Kiruthiga | G13: 24526 | H13: (Regression) Meal Orders - Stock Management - Daily Limit/Qty In Stock removed when cursor placed in field | I13: Defect Being Tested | J13: 1 | P13: Ruban | R13: https://dev.azure.com/heartlandschools/Meal%20Orders/_git/Meal%20Orders/pullrequest/40402?_a=files | S13: 45678 | T13: 45678 | U13: Ruban | W13: Mike | X13: 45678
A14: 12 | B14: =Dashboard!$J$1 -> Meal Order | C14: =Dashboard!$F$1 -> 46157 | D14: =Dashboard!$H$1 -> 46170 | E14: 2.2 Sprint 5 | F14: Ruban/Kiruthiga | G14: 48890 | H14: Meal Orders (2.2) - Regression - Admin | I14: Story Being Developed | J14: 8 | K14: 8 | AB14: We have completed Order Management, Menu Item, Menu Template, Menu Calendar, Settings Module. We have Stock Management Module inprogress for regression.
A15: 13 | B15: =Dashboard!$J$1 -> Meal Order | C15: =Dashboard!$F$1 -> 46157 | D15: =Dashboard!$H$1 -> 46170 | E15: 2.2 Sprint 5 | F15: Kiruthiga | G15: 24502 | H15: (Regression) Meal Orders - Admin - Menu Calendar daily menu template name field not read only | I15: Defect Fixed | J15: 1 | K15: 1 | R15: https://dev.azure.com/heartlandschools/Meal%20Orders/_git/Meal%20Orders/pullrequest/40387 | S15: 45678 | T15: 45678 | U15: Ruban | W15: Mike | X15: 45678
A16: 14 | B16: MealOrders | C16: =Dashboard!$F$1 -> 46157 | D16: =Dashboard!$H$1 -> 46170 | E16: 2.2 Sprint 5 | F16: Ruban | G16: 24514 | H16: (Regression) Meal Orders - Teacher - Items added to teacher order from cart not visible | I16: Defect Fixed
A17: 15 | B17: =Dashboard!$J$1 -> Meal Order | C17: =Dashboard!$F$1 -> 46157 | D17: =Dashboard!$H$1 -> 46170 | E17: 2.2 Sprint 5 | F17: Ruban | G17: 24528 | H17: (Regression) Meal Orders - Stock Management - Rule not set when order cancelled from my orders | I17: Defect Fixed | J17: 1 | K17: 1 | R17: https://dev.azure.com/heartlandschools/Meal%20Orders/_git/Meal%20Orders/pullrequest/40397 | S17: 45678 | T17: 45678 | U17: Ruban | W17: Mike | X17: 45678
A18: 16 | B18: =Dashboard!$J$1 -> Meal Order | C18: =Dashboard!$F$1 -> 46157 | D18: =Dashboard!$H$1 -> 46170 | E18: 2.2 Sprint 5 Stretch | F18: Kiruthiga | G18: 24527 | H18: Meal Orders - Admin - Site Order Timings not refreshing after ordering parameter override | I18: Defect Being Fixed | J18: 2
A19: 17 | B19: =Dashboard!$J$1 -> Meal Order | C19: =Dashboard!$F$1 -> 46157 | D19: =Dashboard!$H$1 -> 46170 | E19: 2.2 Sprint 5 Stretch | F19: Ruban | G19: 24531 | H19: Meal Orders - Parent - Automatic Cart Item Update text alignment issue | I19: Defect Fixed | R19: https://dev.azure.com/heartlandschools/Meal%20Orders/_git/Meal%20Orders/pullrequest/40405?_a=files | S19: 45679 | T19: 45679 | U19: Ruban | W19: Mike | X19: 45679
A20: 18 | B20: =Dashboard!$J$1 -> Meal Order | C20: =Dashboard!$F$1 -> 46157 | D20: =Dashboard!$H$1 -> 46170 | E20: 2.2 Sprint 5 Stretch | F20: Ruban | G20: 24532 | H20: Meal Orders - Admin - Reactivation validation messaging duplicated | I20: Defect Fixed | R20: https://dev.azure.com/heartlandschools/Meal%20Orders/_git/Meal%20Orders/pullrequest/40405?_a=files | S20: 45679 | T20: 45679 | U20: Ruban | W20: Mike | X20: 45679

Sheet 2.2 Sprint 3-Status
A1: S.No | B1: Sprint | C1: Developer | D1: Story ID/Defect ID | E1: Description | F1: Status | G1: Estimated(hrs/sp) | H1: Actual(hrs/sp) | I1: Unit testing | J1: Peer Tested By | K1: Peer Tested Defects, if any | L1: Peer Reviewed By | M1: Peer Code Review Comments, if any | N1: PR Number/Link | O1: PR Created Date | P1: PR Approved Date | Q1: Reviewer 1 | R1: Code Review Comments, if any | S1: Reviewer 2 | T1: Approved Date | U1: Code Review Comments, if any2 | V1: Internal PO -POV Comments | W1: Client PO -POV Comments | X1: Comments
