Workbook

Sheet Dashboard
A1: Current Sprint | B1: {=INDEX($B$2:$B$112,MATCH(1,(($D$2:$D$112 >=TODAY())*($C$2:$C$112<=TODAY())),0))} -> 26.6 Sprint S1 | C1: Current Sprint Sheet | D1: =CONCATENATE(B1,"-Status") -> 26.6 Sprint S1-Status | E1: Sprint Start Date | F1: =VLOOKUP($B$1,$B$1:$C$112,2) -> 46148 | G1: Sprint End Date | H1: =VLOOKUP($B$1,$B$1:$D$112,3) -> 46161 | I1: Application Name | J1: MSB Activities | K1: Users | L1: allen.xavier@relevantz.com;kanchanamala.umakanthan@relevantz.com;manjunathan.dharman@relevantz.com;athinarayanan.ramar@relevantz.com;ramprabu.sakthivel@relevantz.com | M1: Teams Name(GP- MSB Activities) | N1: 19:1e38c92221534f43aaff617f2f44a82e@thread.v2
A2: Sprint Type | B2: Sprint # | C2: Sprint Start Date | D2: Sprint End Date | E2: Assigned | F2: Completed | G2: Story points introduced/removed | H2: Sprint Summary | I2: Accomplishments | J2: Remarks | K2: Client Appreciations | L2: Retro Points (Internal & External) | M2: Unplanned Leaves | N2: Data sanity Audit Status | O2: AuditDate | P2: Backlog Health
A3: =IF(AND(#REF!>=C3,#REF!<=D3),"CurrentSprint","NA") -> #REF! | B3: 2.9 Sprint S1 | C3: 45294 | D3: 45307 | E3: 9 (47 sp - assigned) | F3: 9 - Development completed 4 - Testing completed 2 - Testing in progress 3 - Peer review (23 sp - completed) | J3: 42924, 42923, 42989 - Story peer review, 22646, 37677, 22653, 22655 - Testing completed , 22642, 42917 - Testing in progress. | L3: Internal: External:
A4: =IF(AND(#REF!>=C4,#REF!<=D4),"CurrentSprint","NA") -> #REF! | B4: 2.9 Sprint S2 | C4: 45308 | D4: 45321 | E4: 5 (31 sp - assigned) | F4: 4 - Testing completed [22682, 22676, 22657,43155] 2 - defect/story carried from last sprint for testing [22642, 42917] - Testing Completed (19 sp - completed) | J4: 2 - client peer review [42924, 42923], 2 - Testing [22642, 42917] - Carried from last sprint [2.9 sprint s1] 5 - Development [22682, 22676, 22657,43155, 43149- timeboxed] - Current sprint [2.9 sprint s2] | L4: Internal: External:
A5: =IF(AND(#REF!>=C5,#REF!<=D5),"CurrentSprint","NA") -> #REF! | B5: 2.9 Sprint S3 | C5: 45322 | D5: 45335 | E5: 9 (31 sp - assigned) | F5: Development completed (8) -22756, 43550, 43336,43335,43334,43388, 43536,43486 Development inprogress -42874 | J5: 2 - Testing pending [42924, 42923], 1- stretch [ 43313 ] - Testing pending - Carried from last sprint [2.9 sprint s2] Total 9 - [43334 (Main -1), [Stretch -22756, 43486, 43336,43335,43550,43388, 42874,43536=8] This Regressin sprint,team worked on stretch stories | L5: Internal: External:
A6: =IF(AND(#REF!>=C6,#REF!<=D6),"CurrentSprint","NA") -> #REF! | B6: 2.9.5 Sprint S1 | C6: 45336 | D6: 45349 | E6: 5 Total - 46 Sp (7+5) | F6: 21 Sp | G6: 2 sp | J6: Carried from last sprint for client Peer review and Testing: 43633,22756,43550,43586,43335,43336,43486 = 7 Current Sprint stories assigned Main :42874,43531,43659; Stretch: 43629,43582 Total:5 Introduced story in stretch - 43208 | L6: Internal: External:
A7: =IF(AND(#REF!>=C7,#REF!<=D7),"CurrentSprint","NA") -> #REF! | B7: 2.9.5 Sprint S2 | C7: 45350 | D7: 45363 | E7: 9 [50 Sp] | F7: 53 sp | J7: Carried from last sprint for client Peer review and Testing: =3 Current Sprint stories assigned Main and stretch : 9 Total: 9+3 = 12 | L7: Internal: External:
A8: =IF(AND(#REF!>=C8,#REF!<=D8),"CurrentSprint","NA") -> #REF! | B8: 2.9.5 Sprint S3 | C8: 45364 | D8: 45377 | E8: 7 [ 33 Sp] | F8: 26.5 Sp | J8: Regression Sprint | L8: Internal: External:
A9: =IF(AND(#REF!>=C9,#REF!<=D9),"CurrentSprint","NA") -> #REF! | B9: 3.0 Sprint S1 | C9: 45378 | D9: 45391 | E9: 14 | F9: 9 | J9: One of the offshore developer is on planned leave for the entire Sprint. Development completed for all 4 committed stories. (3 - Closed, 1 - Client POV pending) Development completed for 3 out of 4 stretch stories. (3 - PR approval pending from client, 1 - Development in progress) | L9: Internal: External:
A10: =IF(AND(#REF!>=C10,#REF!<=D10),"CurrentSprint","NA") -> #REF! | B10: 3.0 Sprint S2 | C10: 45392 | D10: 45405 | E10: 9 [37 Sp] | F10: 22 Sp | J10: 2 development story 1 Automation and 6 - testing =9 | L10: Internal: External:
A11: =IF(AND(#REF!>=C11,#REF!<=D11),"CurrentSprint","NA") -> #REF! | B11: 3.0 Sprint S3 | C11: 45406 | D11: 45419 | E11: 31 sp | F11: 31 Sp | J11: Regression Sprint | L11: Internal: External:
A12: =IF(AND(#REF!>=C12,#REF!<=D12),"CurrentSprint","NA") -> #REF! | B12: 3.1 Sprint S1 | C12: 45420 | D12: 45433 | E12: 29 Sp | F12: 16 Sp | L12: Internal: External:
A13: =IF(AND(#REF!>=C13,#REF!<=D13),"CurrentSprint","NA") -> #REF! | B13: 3.1 Sprint S2 | C13: 45434 | D13: 45447 | E13: 23 Sp | F13: 23 Sp | J13: Testing will be covered in next sprint for 3 stories. | L13: Internal: External:
A14: =IF(AND(#REF!>=C14,#REF!<=D14),"CurrentSprint","NA") -> #REF! | B14: 3.1 Sprint S3 | C14: 45448 | D14: 45461 | E14: 29 Sp | F14: 29 Sp | J14: Regression Sprint | L14: Internal: External:
A15: =IF(AND(#REF!>=C15,#REF!<=D15),"CurrentSprint","NA") -> #REF! | B15: 3.2 Sprint S1 | C15: 45462 | D15: 45475 | E15: 30 Sp | F15: 14 sp | L15: Internal: External:
A16: =IF(AND(#REF!>=C16,#REF!<=D16),"CurrentSprint","NA") -> #REF! | B16: 3.2 Sprint S2 | C16: 45476 | D16: 45489 | E16: 26 Sp | F16: 26 Sp | J16: Completed all committed stories with testing and 45114 and 45203 took more efforts than the initial estimation in closing out along with testing. | K16: 3.2 Sprint S2 Retro Appreciation : Assignees: Kristy MacCheyne - Client PO Kudos to everyone on the team. This was an awesome sprint. Allen - Leadership ensuring the team is all on the same page working toward our goals, helping out with getting stories completed to make 3.2 even better. His research for upcoming efforts and suggestions for how to best handle everything. Hari - Always extremely grateful for all of Hari's efforts. I can always trust that anything Hari takes on will be great. Kanchana - Kanchana continuously does an incredible job in this role ensuring we are all communicating effectively and that if/when there are questions we are able to discuss them to get on the same page. Her efforts to ensure we have stories written up for Refinements based on prioritized efforts is greatly appreciated. I also appreciate her collaboration with my new Business Analyst for my other team, Kanchana models how helpful her role can be to Product Management and I appreciate her willingness to provide guidance to my other team's BA. Kaliammal - Great work on wrapping up her first stories since getting access figured out. Manjunathan - Attention to detail and catching impressive finds while testing stories (ie: the final bounceback on 44444), ensuring testing wrapped up on everything heading into Planning for Regression. | L16: Internal: External:
A17: =IF(AND(#REF!>=C17,#REF!<=D17),"CurrentSprint","NA") -> #REF! | B17: 3.2 Sprint S3 | C17: 45490 | D17: 45503 | E17: 29 Sp | F17: 29 Sp | G17: 14 | J17: Regression Sprint | L17: Internal: External:
A18: =IF(AND(#REF!>=C18,#REF!<=D18),"CurrentSprint","NA") -> #REF! | B18: 3.3 Sprint S1 | C18: 45504 | D18: 45517 | E18: 24 Sp | F18: 24 | K18: 3.3 Sprint S1 Retro Appreciation : Assignees: Kristy MacCheyne - Client PO Manjunathan - Did a great job at staying on top of the large testing effort we had for Sprint 1. Manjunathan and Jeff both made this sprint look easy despite a lot of work being on their shoulders. Kaliammal - Kaliammal is doing a great job getting up to speed, she did great work on the No Cost Retainer Fee story. Hari - Thank you Hari for always doing an exceptional job with whatever story you take on. You are always ready to take on stories/epics for our Release Goals and I really appreciate it. Kanchana - I appreciate all of Kanchana's efforts. She does an exceptional job in this role and allows me to jump back and forth between teams and spend time supporting my other team when they had escalations coming up. Kanchana is always extremely thoughtful, detail oriented, and a true team player Allen - Thank you for your incredible ideas and suggestions for approach, Allen really helped me ahead of our last Planning meeting to ensure we were setting QA up for success with a large number of stories ready for testing. Allen's leadership is always greatly appreciated. . | L18: Internal: External:
A19: =IF(AND(#REF!>=C19,#REF!<=D19),"CurrentSprint","NA") -> #REF! | B19: 3.3 Sprint S2 | C19: 45518 | D19: 45531 | E19: 32 Sp | F19: 19 Sp | J19: Completed most of the committed stories with one story 45116 in QA which will be carry forwarded to next sprint for QA. | L19: Internal: External:
A20: =IF(AND(#REF!>=C20,#REF!<=D20),"CurrentSprint","NA") -> #REF! | B20: 3.3 Sprint S3 | C20: 45532 | D20: 45545 | E20: 21 Sp | F20: 19 Sp | J20: 23905, 44143 - Client moved to next release 10-Sep-2024 Peer CRC: 0 Onsite CRC: 0 Client CRC: 2 Internal Defects: 5 External Defects: 1 | N20: Completed
A21: =IF(AND(#REF!>=C21,#REF!<=D21),"CurrentSprint","NA") -> #REF! | B21: 3.4 Sprint S1 | C21: 45546 | D21: 45559 | E21: 23 Sp | F21: 23 Sp | G21: 18 Sp | J21: 24-Sep-2024 Peer CRC: 0 Onsite CRC: 0 Client CRC: 1 Internal Defects: 2 External Defects: 0 | N21: Completed
A22: =IF(AND(#REF!>=C22,#REF!<=D22),"CurrentSprint","NA") -> #REF! | B22: 3.4 Sprint S2 | C22: 45560 | D22: 45573 | E22: 22 Sp | F22: 21 Sp | J22: 09-Oct-2024 Peer CRC: 2 Onsite CRC: 0 Client CRC: 2 Internal Defects: 3 External Defects: 0
A23: =IF(AND(#REF!>=C23,#REF!<=D23),"CurrentSprint","NA") -> #REF! | B23: 3.4 Sprint S3 | C23: 45574 | D23: 45587 | E23: 14 Sp | F23: 22 Sp | G23: Introduced - 8 | J23: Regression Sprint 23-Oct-2024 Peer CRC: 0 Onsite CRC: 1 Client CRC: 0 Internal Defects: 0 External Defects: 0
A24: =IF(AND(#REF!>=C24,#REF!<=D24),"CurrentSprint","NA") -> #REF! | B24: 3.5 Sprint S1 | C24: 45588 | D24: 45601 | E24: 24 Sp | F24: 11 Sp | I24: Completed 46329 - Bulk Copy Enrollment Common component creation which is pre-requisite for two other stories | J24: Reason for not Completing the Story Points --- 46323 - Testing not completed due to PTO of both offshore and client QA 46336 - PR delayed due to existing issues in related component Regression Sprint 46355 - Timebox story 46032 - Stretch story Peer CRC: 0 Onsite CRC: 1 Client CRC: 0 Internal Defects: 0 External Defects: 0 | K24: Client PO Appreciations for the team : Kanchana - Partnering with Kanchana also brings me joy - she has a desire to learn, grow, and take on whatever task comes up. She inspires me with her organization skills and attention to detail and helps make everything much smoother and easier for me (and the team)! Hari - I appreciate your thoroughness, great questions, and agility. You're always ready to take on challenging efforts. Kaliammal - I appreciate that you are always ready to take on whatever story/defect requires attention. You're a great addition to our team! Manjunathan - I appreciate seeing your growth on this team! Your attention to detail and thoughtfulness in testing is really appreciated as well! Jeff always speaks highly of you and both of you collaborating on testing efforts! Allen - I appreciate your dedication, steadiness, and thoughtful approach to solving problems. You always have great ideas, and it helps with each effort we take on (especially ones that have been hanging out in the backlog without a clear path for us).
A25: =IF(AND(#REF!>=C25,#REF!<=D25),"CurrentSprint","NA") -> #REF! | B25: 3.5 Sprint S2 | C25: 45602 | D25: 45615 | E25: 29 | F25: 37 | G25: Story points introduced in the mid of the sprint : 46499 -3sp 46511 - 5sp 46557 - 8 sp Defect points introduced : 24286 - 1sp 24301 - 1sp Total Introduced - 18 Total Completed - 8 | I25: Completed Enrollment Plans - Selected Actions Bulk Edit (Seminole) and Capacity Report - Dropdown Tree for Activity and EP Filters (Seminole) | J25: Peer CRC: 0 Onsite CRC: 0 Client CRC: 0 Internal Defects: 2 External Defects: 1 (Production Issue - Minor) | K25: Excellent communication skills, frequent check-ins, excellent collaboration, and always working to build an environment where we can share ideas to work towards common goals! The great discussions, sharing of ideas, collaboration, and identifying new paths to solve problems that have left us stuck in the past. Hearing positivity from internal stakeholders and customers (and then sharing with the team) about how our work has helped product growth and quality of life.
A26: =IF(AND(#REF!>=C26,#REF!<=D26),"CurrentSprint","NA") -> #REF! | B26: 3.5 Sprint S3 | C26: 45616 | D26: 45629 | E26: 21 Sp | F26: 39 sp | G26: Stories Introduced Introduced - 5sp Defects Introduced Introduced - 3sp Total Introduced - 8 Total Completed - 8 | I26: 1.Completed Enrollment Plan Maintenance - Limit number for Selected Actions & Config Prop, 2.Capacity Report - Total "All Enrollment Plans" count in Excel Output Format, 3.Attendance Report - Group By Grade, 4.Update "Description" to Item Name [UI Labels Only](PR & QA) | J26: Peer CRC: 1 Onsite CRC:1 Client CRC: 2 Internal Defects: 6 External Defects: 0 | K26: The team continues to do a great job and accomplish everything they set out to do despite any disruptions. This sprint we had a ton of Client PTO and difficult timing to work around and the team still managed to close out the commit and make some progress in the stretch despite all of that. It's exciting to see the team continuing to knock it out of the park. I’m just so proud of this team! Keep up the great work!
A27: =IF(AND(#REF!>=C27,#REF!<=D27),"CurrentSprint","NA") -> #REF! | B27: 3.5 Sprint S4 | C27: 45630 | D27: 45659 | E27: 24 | F27: 55 | G27: Total Introduced: 31 | I27: 1.Completed the development work for React conversion stories for Users, Home page and District level. 2.Completed the development work for Enrollment Plan/Activity - Update "Description" to Item Name in SQL Tables (SYSTEM). 3. Completed the development work for Spilt billing audit log and Term Capture Attendance Calendar modifications in Audit Log | J27: Peer CRC: 6 Onsite CRC:0 Client CRC: 0 Internal Defects: 7 External Defects: 0 | K27: Keep up the great work and continue efforts we started in 3.5 Sprint 4 (with the intention of holding for 3.6)
A28: =IF(AND(#REF!>=C28,#REF!<=D28),"CurrentSprint","NA") -> #REF! | B28: 3.6 Sprint S1 | C28: 45660 | D28: 45671 | E28: 14 | F28: 32 | I28: 1.Modified the common component Date Selector to Display as an Expanded Calendar Overlay 2.Fixed production defect regarding the billing Prepaid Billing Used Instead of Drop In - Logic defect fixed 3.Admin Home Page has been converted to react 4.Students page to Server Side sorting | J28: Few Stories are moved to 3.7 that Contains DataBase Column Name Changes - Slated for 3.7 release. One Story is On hold by Client QA Peer CRC: 1 Onsite CRC:1 Client CRC: 1 Internal Defects: 2 External Defects: 2
A29: =IF(AND(#REF!>=C29,#REF!<=D29),"CurrentSprint","NA") -> #REF! | B29: 3.6 Sprint S2 | C29: 45672 | D29: 45685 | E29: 43 | F29: 50 | G29: Introduced - 10 | I29: 1.Completion of District level view of Open Operating Days 2.Completion of React conversion for Tenant and Heartland Staff users 3.Fixed Production defect regarding Operating day checkout errors 4.Updated Enrollment Plan - Update "Required Forms" page with Sorting and Pagination. 5 Updated the.MSB Invoice Profile - Remove filter by Provider for GL Codes | J29: Peer CRC: 0 Onsite CRC:0 Client CRC: 2 Internal Defects: 7 External Defects: 2 | K29: Feedback from Beth Boyack, Payments Account Specialist after using this for the first time: "Hey! I'm using the copy enrollment plan for the first time. Yay!! Definitely helps!" & "I was only copying 4 plans and the performance was good, no lag or anything". Great feedback on the new Selected Actions effort! | L29: Kristy MacCheyne Product Manager - MSB Activities & MSB Tickets - "I think we have great commitment to our team, as well as to our sprint goals. If we are struggling on one story/defect, we communicate with each other and identify a path forward. I think the strong individual commitment to the sprint is a side effect of our commitment to our team and collective goals."
A30: =IF(AND(#REF!>=C30,#REF!<=D30),"CurrentSprint","NA") -> #REF! | B30: 3.6 Sprint S3 | C30: 45686 | D30: 45699 | E30: 20 | F30: 31 | I30: 1.Completed Filter By Registration status for Custom Registration with highlighting updated fields for Updated Registrations 2.Completion of Performance improvement to reduce the time taken to copy large number of Enrollment plans which required Framework level changes. 3.Completed converting Description Table column to Name for SecurityGroup, Kiosk, District, Custom Fields and Dynamic Report 4.Fixed existing production defect in Custom Registration Report | J30: Peer CRC: 0 Onsite CRC:1 Client CRC: 0 Internal Defects: 7 External Defects:1 | L30: Kristy MacCheyne Product Manager - MSB Activities & MSB Tickets - "The team did an excellent job at working through Regression testing, identifying and resolving defects, making progress on some Performance Improvements, updating description to item names in SQL tables, Automation, and had some great discussions for some upcoming larger efforts. I think we also have been doing a great job at communicating and relaying concerns/needs to re-estimate certain efforts as we learn more and have been able to reforecast as needed to ensure we are capturing as much of the full picture of these efforts as we can.Also, we are seeing things pick up on the sales side for Activities and I have been working closely with the new dedicated sales rep for Activities (Ed), we are partnering for an upcoming webinar that I am really excited about."
A31: =IF(AND(#REF!>=C31,#REF!<=D31),"CurrentSprint","NA") -> #REF! | B31: 3.7 Sprint S1 | C31: 45700 | D31: 45713 | E31: 23 | F31: 37 | G31: Introduced - 5 Removed - 8 | I31: 1.Completed Customizable column headers for the Datatable in Parent Accounts. 2.Completed Description change to Item Name for Activity, Enrollment plan, Security Group, Kiosk and District Maintenance. 3.Development completed to Improve performance for Bulk edit of Enrollment plans. | J31: Peer CRC: 0 Onsite CRC:0 Client CRC: 2 Internal Defects:2 External Defects:1 | K31: Feedback from Ramsey Whitley, Implementation Coordinator Ramsey's comment was towards the customizable parent table column headers in the sprint demo review, like this is a wonderful feature. | L31: Kristy MacCheyne Product Manager - MSB Activities & MSB Tickets - Dedication, determination, and collaboration from the team! We had some great discussions to ensure we are all on the same page. We also got some really great new features added this Sprint. I loved Hari's approach for displaying Students in the Student column (Customizable Columns for Parents). Shoutout to Andy for his patience and determination as we made various changes to the District view of Terms. Jeff and Manjunathan did a great job at getting things over the finish line this sprint. Brian Newby, Senior Manager, Software Development Mentioned: "The team is communicating well and doing great work".
A32: =IF(AND(#REF!>=C32,#REF!<=D32),"CurrentSprint","NA") -> #REF! | B32: 3.7 Sprint S2 | C32: 45714 | D32: 45727 | E32: 23 | F32: 38 | G32: Introduced - 7 | I32: 1.Completed the Other Contacts Customizable column Header. 2.Completed updating Setup icons, text position, order for tiles and, page headers. 3.Completed the Custom Registration Report - Include Student Number for Output Format. 4.Completed Description change to Item Name for Term and Site. 5.Completed the Performance Improvements for Enrollment Plan for Bulk Edit. 6. Fixed existing PROD defects. | J32: Peer CRC: 0 Onsite CRC:1 Client CRC:5 Internal Defects:2 External Defects:3 | K32: Feedback from Beth Boyack, Payments Account Specialist "OMG I just used the Dynamic Report Generator for Updated Student Counts and it's AMAZING!! I don't think I can thank you enough for this!" Feedback from Kristy MacCheyne Product Manager - MSB Activities & MSB Tickets @Allen Xavier : all the time you have spent on the dynamic report generator is paying off! | L32: Kristy MacCheyne Product Manager - MSB Activities & MSB Tickets - I think the number 1 thing we do that we do well/should continue doing is communicating with each other. This team does an exceptional job at communicating progress, challenges, etc. I think the team's collaborative approach helps ensure we are successful each sprint - we discuss problems/challenges as a team, share ideas to fix/improve, and work together each step of the way to make it happen. I find the discussions with the team the most fulfilling for my day to day.
A33: =IF(AND(#REF!>=C33,#REF!<=D33),"CurrentSprint","NA") -> #REF! | B33: 3.7 Sprint S3 | C33: 45728 | D33: 45741 | E33: 15 | F33: 25 | I33: 1.Completed Research for Split billing improvements to upload invoices by MSB UserId 2.Development completion of Next set of Description changes for Fees,FormTypes,Discounts,Custom Fields and Dynamic Report. 3.Development completion of enhancement in the Datatable to show total Entries | J33: Peer CRC: 0 Onsite CRC:0 Client CRC:1 Internal Defects:0 External Defects:0
A34: =IF(AND(#REF!>=C34,#REF!<=D34),"CurrentSprint","NA") -> #REF! | B34: 3.8 Sprint S1 | C34: 45742 | D34: 45755 | E34: 36 | F34: 28 | I34: 1.Development completion of Split billing improvements to invoice by MSB User ID 2.UI Enhancement - Ability to select multiple fields of Student, Parent and Contact fields in Enrollment plan 3.Reports - Improve Student Filter Multi-Select dropdowns | J34: Peer CRC: 5 Onsite CRC:1 Client CRC:0 Internal Defects:3 External Defects:0 | K34: Feedback from Kristy MacCheyne about the team Product Manager - MSB Activities & MSB Tickets Ganapathi Sent: Hello team, I just got off a call with Kristy where in she was so happy with the team's transformation and progress. I've no words to express the excitement that she expressed talking about everyone on the team under Allen's leadership. Kudos to your hardwork and commitment | L34: Kristy MacCheyne: Product Manager - MSB Activities & MSB Tickets Kanchana's attention to detail always helps us be prepared. I also think our Refinements and discussions at standups helped us keep momentum. I also think that the new process for Pendo guides worked well this sprint. Jeff Dean - QA Team collaboration is always a great line for success with this team. Each strand in our team does great work in completing and making sure we are successful.
A35: =IF(AND(#REF!>=C35,#REF!<=D35),"CurrentSprint","NA") -> #REF! | B35: 3.8 Sprint S2 | C35: 45756 | D35: 45769 | E35: 29 | F35: 27 | G35: Introduced - 22 | I35: 1.Student Filter Improvements in Report 2.Enhancement in Field Selection in EnrollmentPlan 3.Split Billing Updates 4.Tile Icon updates in Registration Page 5.New SearchableSelect Component creation to be reused across the application | J35: Peer CRC: 2 Onsite CRC:0 Client CRC:2 Internal Defects:0 External Defects:2 | L35: Kristy MacCheyne: Product Manager - MSB Activities & MSB Tickets Kudos to the entire team! Everyone did really great work this sprint from Allen cruising through the split billing story, Hari providing great ideas for UI and calling out scenarios we may not think of, Kaliammal also did great work and showcased that getting quick feedback during POVs in 2nd rounds. Manjunathan did a great job working with Jeff to get through a LOT of testing efforts, Kanchana always does a fantastic job at supporting the team, her attention to detail is great - catching some defects that we have been able to fix before anyone notices, and keeping things moving.
A36: =IF(AND(#REF!>=C36,#REF!<=D36),"CurrentSprint","NA") -> #REF! | B36: 3.8 Sprint S3 | C36: 45770 | D36: 45783 | E36: 9 | F36: 19 | G36: 16 | I36: 1.Completed Regression testing with no regression defect 2.Completed Research to display Split billing invoices under purchases 3.Completed Research on tracking split billing changes in Audit log 4.Completed Research on Custom registration report to support multiple enrollmentplans | J36: Peer CRC: 2 Onsite CRC:1 Client CRC:1 Internal Defects:0 External Defects:0 | K36: NIL | L36: NIL
A37: =IF(AND(#REF!>=C37,#REF!<=D37),"CurrentSprint","NA") -> #REF! | B37: 3.9 Sprint S1 | C37: 45784 | D37: 45797 | E37: 26 | F37: 23 | G37: 9 | I37: Conversion of Auditlog view into a Grid with search,sort and customisable column header functionality, Improvements in Add tenant Page, Split Billing settings which was displayed as a Popup/Modal has been converted in to a separate page for ease of access. | J37: Peer CRC: 1 Onsite CRC:1 Client CRC:2 Internal Defects:4 External Defects:0 | K37: We have implemented the existing audit log in a table grid format for student maintenance. Feedback from Jeff Dean - QA This makes me happy: I'm sure our support members will LOVE it as much as I am, if not more! makes it SO MUCH easier to find information Feedback from Brian Newby:Senior Manager Good stuff. Sometimes its hard to step back and see the impact that our work is having. Thanks for all you you guys do. | L37: Kristy MacCheyne: Product Manager - MSB Activities & MSB Tickets We made great progress on updating the display of audit logging for student maintenance - the new grid view looks great! We also made excellent progress on split billing updates for audit logging, displaying split billing as a separate tab from the Student record (instead of needing to drill into editing the student details to find the split billing setup), improving and expediting the add district/tenant process, automation, and tech debt. Overall, it was a great sprint for the team with great communication. Excellent communication, trust, determination, and Kanchana 😂 (I don’t think I need to say much more than her name - she helps lock in on our goal and help guide everyone forward).
A38: =IF(AND(#REF!>=C38,#REF!<=D38),"CurrentSprint","NA") -> #REF! | B38: 3.9 Sprint S2 | C38: 45798 | D38: 45811 | E38: 24 | F38: 29 | G38: Introduced - 20 | I38: 1.Inclusion of Splitbilling invoices in Purchases, 2.Relocation of Splitbilling settings to a separate tab with readonly and edit view 3.Additional fields in Tenant Add/Edit page | J38: Peer CRC: 5 Onsite CRC:0 Client CRC:0 Internal Defects:3 External Defects:3 | K38: NIL | L38: Jeff Dean - QA Analyst: Manjunathan and Kanchana’s attention to detail, Allens willingness to go above and beyond (and check in late at night lol). Being ourselves. Kristy MacCheyne: : Product Manager - MSB Activities & MSB Tickets The team is always great at working together and providing support in whatever area needs it most. This sprint I had to take some unexpected time off for my health and the team did a great job at filling in and keeping everything moving in the right direction. Shout out to Kanchana!
A39: =IF(AND(#REF!>=C39,#REF!<=D39),"CurrentSprint","NA") -> #REF! | B39: 3.9 Sprint S3 | C39: 45812 | D39: 45825 | E39: 32 | F39: 52 | G39: Introduced - 20 | I39: 1.Regression went well. 2.Fixed Regression Split Billing Defects. 3.Completed People - Update Icons and Tile Layout 4.Split Billing Audit Log changes and UI Changes. 5.Converted Tile layout pages, Admin Header & Left Navigation Menu to React. 6.Good Progress on Vega UI updates on Admin Header and Left Navigation Menu 7.Completed few discovery stories like Notification Hub & Registration - Specific URLs 8.Conversion of Functional Components | J39: Peer CRC:0 Onsite CRC:0 Client CRC:0 Internal Defects:2 External Defects:2 | K39: NIL | L39: Kristy MacCheyne: : Product Manager - MSB Activities & MSB Tickets The team had some great conversations this sprint during standups, refinement, and planning prep calls. The team also made great progress on converting the admin header and left nav to React, and getting a start on implementing the new vega components with the new designs (exceeded my expectations for where I thought we would be)! The team also did a great job with regression (as usual). The team has done a great job at focusing on what is within our control though, and providing great feedback to help make the designs better for everyone (not just our team). Shoutout to Allen for his attention to detail/eye for the customer UX in pointing out risks with the District/Site dropdown placement within the new design.Shoutout to Kanchana for her great ideas of upcoming improvements to the Parent UX.
A40: =IF(AND(#REF!>=C40,#REF!<=D40),"CurrentSprint","NA") -> #REF! | B40: 4.0 Sprint S1 | C40: 45826 | D40: 45839 | E40: 13 | F40: 13 | G40: Introduced - 5 | I40: 1. Completed development for Multi Selection Enrollment Plan Filter in Custom Registration Report. 2. Completed Split Billing - Partial Invoice Upload Failures 3. Completed updating Tile Layout Pages to React 4. Added a new "State" column in Districts maintenance table grid page. | J40: Peer CRC:2 Onsite CRC:0 Client CRC:1 Internal Defects:0 External Defects:0 | K40: NIL | L40: Brian Newby: Senior Manager, Software Development Making progress on Azure AD group and Notification Hub integration. Vega stuff looks good. Kristy MacCheyne: Product Manager - MSB Activities & MSB Tickets Great progress on the Kaleida designs, worked together as a team to identify the best path forward for our District/Site selector (despite it being different from the initial designs, I feel that we are making the right decision and the design team and platform PM are aligned on our approach.
A41: =IF(AND(#REF!>=C41,#REF!<=D41),"CurrentSprint","NA") -> #REF! | B41: 4.0 Sprint S2 | C41: 45840 | D41: 45853 | E41: 15 | F41: 17 | G41: Introduced -2 | I41: 1. Implemented Multi Selection Enrollment Plan Filter in Custom Registration Report. 2. Completed Setup Tile Reorder. 3. Completed URL Update for react converted page. 4. Completed Retain Historical Split Billing Invoice By Value. | J41: Peer CRC:0 Onsite CRC:0 Client CRC:2 Internal Defects:2 External Defects:0 | K41: Joe: Sr. Product Specialist for MealViewer, MSB Activities & Tickets Mentioned in the Sprint Review Demo: I just want to add that you ALL do great work. | L41: Jeff Dean - QA Analyst : Manjunathan and Siva did great work vetting our new features, so much so that I got to do some dev work! "Kristy MacCheyne: Product Manager - MSB Activities & MSB Tickets The team wrapped up everything in the main commit and made great progress in stretch. It was a great team effort towards the end of the sprint getting everything closed out. Shout out to Kanchana for taking on more ownership of enhancement requests from internal stakeholders! Also shout out to the whole team for the collaborative and platform centric energy brought to the table for the Kaleida efforts - great questions, concerns, and suggestions have been brought up that I think have helped guide the design process for the entire platform. And us keeping an eye on progress in MSB and Meal Orders has helped keep us aligned and even helped identify defects for others"
A42: =IF(AND(#REF!>=C42,#REF!<=D42),"CurrentSprint","NA") -> #REF! | B42: 4.0 Sprint S3 | C42: 45854 | D42: 45867 | E42: 16 | F42: 11 | G42: Introduced -1 | I42: 1.Completed the development of converting the CSHTML pages to React a) Record-Not-Found b) Tenant mismatch c) Site mismatch 2.Removed unused CSHTML pages. 3.Completed the enhancement of adding MSB District ID to Job Request Queue page. 4.Good progress on implementing the Integrating Notification Hub to MSB Activities. 5.Completion of Regression Testing within the sprint. | J42: Peer CRC:0 Onsite CRC:0 Client CRC:0 Internal Defects:0 External Defects:0 Note: Story# 48830 Activities - Integrating Notification Hub to MSB Activities [4.1] - Development Completed and the story is carried to next sprint for PR & QA. | K42: NIL | L42: Received retro appreciations from each team member from - Kristy MacCheyne Product Manager - MSB Activities & MSB Tickets: Kanchana (always Kanchana deserving a shoutout for all she does!) for her dedication to supporting the team, asking great questions, and being an expert at juggling whenever we find ourselves in that position. Manjunathan did an incredible job this entire release but definitely this sprint. Allen - doing an incredible job at juggling everything, getting our newer team members up to speed, and still finding time to make progress towards our goals Kaliammal - Making sure we are making great progress towards BAU efforts while we take on Kaleida updates. Sivaraja - Doing a great job getting up to speed!
A43: =IF(AND(#REF!>=C43,#REF!<=D43),"CurrentSprint","NA") -> #REF! | B43: 4.1 Sprint S1 | C43: 45868 | D43: 45881 | E43: 20 | F43: 17 | G43: Introduced-0 | H43: Discovery for Site Registration URL, Implemented View All[Registrations] page to Server Side sorting, Converting the CSHTML pages to React (Records not found, Tenant and Site mismatch), Integrating Notification Hub for Parent Admin. | I43: 1. Completed View All[Registrations] page to Server Side sorting. 2. Completed converting the CSHTML pages to React. 3. Completed converting the Record-Not-FoundL pages to React. 4. Completed converting the Tenant mismatch pages to React. 5. Completed converting the Site mismatch pages to React. 6. Completed the analysis of Site Registrations URL (discovery). 7. Defect fixes and bouncebacks fixed. | J43: Peer CRC:2 Onsite CRC:0 Client CRC:1 Internal Defects:4 External Defects:1 Note: Story# 48830 Activities - Parent- Integrating Notification Hub to MSB Activities [4.1] - Reason :Story carried to next sprint for testing.The notification hub story was carried over to the next sprint to allow for integration with the existing email template, thorough testing in the development environment to ensure compatibility with our NuGet package, and to address additional peer and PR reviews.This approach ensures seamless integration and robust unit test coverage. | L43: Good Sprint and appreciated the team for great communication and collaboration.
A44: =IF(AND(#REF!>=C44,#REF!<=D44),"CurrentSprint","NA") -> #REF! | B44: 4.1 Sprint S2 | C44: 45882 | D44: 45895 | E44: 18 | F44: 14 | G44: Introduced- 4 | H44: 4.1 Sprint 2 delivered key outcomes, including defect resolutions for student selection in Reports and fees icon alignment in Admin Accounting. The team completed integration of the Notification Hub for both Parent and Admin users, enhanced the Site Home Page user experience, and advanced the Site Registrations URL update through peer review. Progress also continued on the Job Request Queue Tree component and improvements to the Admin Reports multiselect functionality. | I44: 1. Resolved the issue where unselected students were being chosen from the student dropdown list in Reports. 2. Completed integration of the Notification Hub with MSB Activities for Parent users. 3. Fixed the vertical scroll bar on the Site Home Page to enhance user experience. 4. Completed integration of the Notification Hub with MSB Activities for Admin users. 5. Corrected the fees icon mismatch in the page header of the Fees Page in Admin Accounting. 6. Completed the development of Site Registrations URL. | J44: Peer CRC:0 Onsite CRC:0 Client CRC:1 Internal Defects:0 External Defects:3 Note: Story# 49407-"Site Registration Url" development has been completed, and the story is carried to the next sprint by client for client code review. The client team mentioned that this will not be part of this release 4.1 and will be pushed to the 4.2 release for QA efforts. | K44: Nil | L44: What slowed us down or caused friction this sprint? Jeff Dean - QA: Didn’t have the best communication this sprint and Perhaps we prioritized incorrectly, underestimated, upon further review we realized our approach changed. Andy Ritzman - Developer-We had a few stories that were underestimated in this sprint. I think in some cases like the Site URLs and React conversion they just ended up having more complexity than we expected. In the case of the NotificationHub integration we adjusted our approach mid sprint, which I believe was the right call but it slowed us down a bit. We also estimated the stories for just the work to tie the new library into activities without considering this was the first real review of the new library and it may need updating as well. Kristy MacCheyne-Product Manager- There were some things that came up that caused us to change our approach for the NH stories, additional fixes needed for the update admin login page to react, and the Site Registrations URL effort potentially being larger than anticipated. I think the team did a great job at communicating the concerns, we then prioritized discussion and getting on the same page about each main commit item at refinement, and worked together to reset/refocus. I think the team did a great job at figuring out how we should pivot to make sure we are focusing on the right things with the remaining time left in the sprint.
A45: =IF(AND(#REF!>=C45,#REF!<=D45),"CurrentSprint","NA") -> #REF! | B45: 4.1 Sprint S3 | C45: 45896 | D45: 45909 | E45: 11 | F45: 11 | G45: Introduced - 0 | H45: 4.1 Sprint 3 delivered key outcomes, including regression testing went well, completed the development of the job request queue page changes, and Multi-student component selection Defect. | I45: 1. Completed Regression Sprint. 2. Completed development and unit testing for the Job Request Queue screen with features below. a)Multi selection dropdown for Districts, and Request Kind b)Pagination, Sorting and Search c)New filter for Status | J45: Peer CRC:5 Onsite CRC:0 Client CRC:0 Internal Defects:1 External Defects:0 Note: Defect has been blocked by Client # :25807, 25853, 25859 Three defects are currently blocked because multiple issues exist in the same component, which impact component selection. Fixing one defect causes another to appear. As comprehensive unit testing is required for all scenarios, we have decided to revamp the component. Therefore, this defect will remain blocked in the current sprint, and a new story will be created for the new implementation in the next sprint. | K45: NIL | L45: Andy Ritzman - Developer Kristy MacCheyne-Product Manager Finished regression without major findings. Finding additional issues with the tree component (and planned to have a separate story to address those defects - its a good approach), and we made strategic decisions while completing regression and worked on research/discovery.
A46: =IF(AND(#REF!>=C46,#REF!<=D46),"CurrentSprint","NA") -> #REF! | B46: 4.2 Sprint S1 | C46: 45910 | D46: 45923 | E46: 9 | F46: 9 | G46: Introduced - 0 | H46: 4.2 Sprint 1 delivered key outcomes, including the completion of Site-Registrations URL feature for New-Parent flow, enhanced the Job Request Queue page and fixed bounce back for SiteRegistration URL and Job Request Queue screen. | I46: 1. Completed the feature Site-Registrations URL for New-Parent flow. 2. Enhanced the Job Request Queue Page for the HSS Users. 3. Completed fixing the Bounce back for Site-Registrations URL and Job Request Queue. | J46: Peer CRC:1 Onsite CRC:0 Client CRC:0 Internal Defects:4 External Defects:0 | K46: NIL | L46: Jeff Dean - QA Closed out the main commit, Was able to integrate our notifications into notification hub. Great steps with the Site URL stories to eventually get us to a point that anyone can be registered for an activity.
A47: =IF(AND(#REF!>=C47,#REF!<=D47),"CurrentSprint","NA") -> #REF! | B47: 4.2 Sprint S2 | C47: 45924 | D47: 45937 | E47: 8 | F47: 6 | G47: Introduced - 0 | H47: 4.2 Sprint 2 delivered key outcomes, the analysis was completed for new term Enrollment-registration-url changes. | I47: 1. Completed development for the issues in the Multi-Tree component Search & Selection. 2. Analyzed the changes for the new' Term Enrollment-registration-url' | J47: Peer CRC:0 Onsite CRC:0 Client CRC:0 Internal Defects:0 External Defects:0 Note:This Story # 49964 Activities - Reports - Multi Tree Select Component (Search & Selection) - Development is completed and unit testing in-progress and carried to next sprint for [PR ,POV and QA] and focused for 4.3 release. Reason: Initially, we attempted multi-student to handle it with the common tree select component, but it wasn't feasible, so we moved it to separate component. This approach took a lot of effort and additional time. Unit testing also required time to validate multiple scenarios. | K47: NIL | L47: Team took a step back to review big picture, found several issues early on, created Stories,fixed all initial issues. Team then discovered prod issues as part of Stories (existing issues)
A48: =IF(AND(#REF!>=C48,#REF!<=D48),"CurrentSprint","NA") -> #REF! | B48: 4.2 Sprint S3 | C48: 45938 | D48: 45951 | E48: 10 | F48: 11 | G48: Introduced - 9 | H48: 4.2 Sprint 3 delivered key outcomes, the analysis and inital development is completed for Term-Enrollment plan registrations url changes. Multi Tree component issues are fixed. Also an issue sprlit billing is fixed. Initial development is completed to handle the error scenarios in Site-Registrations url. Changes made in to Districts page to hide the Advanced tools button for Customer support role. | I48: 1.Initial development is completed for Term Enrollment Registrations url. 2.Multi Tree Select - component changes are completed. | J48: Peer CRC:0 Onsite CRC:0 Client CRC:1 Internal Defects:0 External Defects:0
A49: =IF(AND(#REF!>=C49,#REF!<=D49),"CurrentSprint","NA") -> #REF! | B49: 4.3 Sprint S1 | C49: 45952 | D49: 45965 | E49: 20 | F49: 22 | G49: Introduced - 2 | H49: 4.3 sprint 1 Implemented new verbiage for Parent Term Enrollment Plan URLs and addressed related registration scenarios.Resolved server errors in admin search functionality caused by special character inputs.Completed quality assurance for the Multi Tree Select Component in Reports (v4.3). Enhanced user access by updating district and parent views, including advanced tool restrictions and role-based button visibility for HSS Customer Support. | I49: 1.Integrated new verbiage for Parent Term Enrollment Plan URLs. 2.Resolved server errors caused by special characters in admin search criteria. 3.Completed QA for Multi Tree Select Component in Reports (v4.3). 4.Addressed registration and site URL issues for inactive sites, sites without EPs, and Term Enrollment Plan URLs. 5.Updated district and parent views to hide advanced tools and restricted 'Add'/'Edit' buttons for HSS Customer Support roles. | J49: Peer CRC:8 Onsite CRC:1 Client CRC:4 Internal Defects:0 External Defects:0 | L49: Kristy MacCheyne-Product Manager Really strong first sprint of the release completing almost everything in the main, and a bunch in stretch. We wrapped up a couple of efforts that we have been working on for a while (multi-tree select component fixes, term EP URL, and are very close to being wrapped up with the admin manual registration for the non student/guest registration work!). 4.2 is live. Shoutouts Everyone. Kanchana’s efforts to ensure the team is supported. Allen’s guidance and forward thinking with efforts he takes on with the team. Everyone who worked on documents for discovery stories. QA for staying on top of everything as we closed out a ton of stories this sprint.
A50: =IF(AND(#REF!>=C50,#REF!<=D50),"CurrentSprint","NA") -> #REF! | B50: 4.3 Sprint S2 | C50: 45966 | D50: 45979 | E50: 15 | F50: 18 | G50: Introduced - 4 | H50: In 4.3 sprint 2, The team successfully delivered all planned work items plus two additional stretch goals, demonstrating strong execution and exceptional productivity throughout the sprint. Additionally, the team proactively addressed external defects and peer review comments, maintaining high quality standards. Enhanced the Enrollments screen with improved error prevention of payment method ,added 'Actions' Dropdown in Term Maintenance for Activities & Enrollment Plan Tab, upgraded the Audit Log to a table grid for Form Types, and resolved issues with prompt closure and manual registration errors. Stretch Stories Completion The team exceeded sprint goals by successfully delivering stretch stories which are development is completed: 1.Enrollment plan field validation 2.Discovery story for Term Enrollment plan capacity. | I50: 1. Implemented prevention of Payment Method errors on the Enrollments screen. 2. Added a new feature 'Actions' Dropdown in Term Maintenance for Activities & Enrollment Plan Tab. 3. Completed existing Audit Log to a Table Grid for Form Types Maintenance. 4. Resolved the issue where the Enrollment Plan Capacity Reached prompt was not closing properly. 5. Resolved the issue in Manual Registration where a null Student Info caused an error. | J50: Peer CRC:5 Onsite CRC:0 Client CRC:0 Internal Defects:0 External Defects:2 | K50: NIL | L50: Good Sprint and appreciated the team for great communication and collaboration.
A51: =IF(AND(#REF!>=C51,#REF!<=D51),"CurrentSprint","NA") -> #REF! | B51: 4.3 Sprint S3 | C51: 45980 | D51: 45993 | E51: 9 | F51: 19 | G51: Introduced - 0 | H51: In this 4.3 sprint S3 was primarily focused on regression testing, which was successfully completed. All stories addressed during the sprint were development-only items. The team prioritized stretch stories and technical improvements, ensuring stability and readiness for future releases. | I51: 1. Successfully completed full regression testing, ensuring system stability and readiness for release. 2. Delivered a universal search feature for the Students page, improving user experience and data accessibility as Discovery. 3. Enhanced field validation in the Enrollment Plan administration, addressing technical debt and improving data quality. 4. Implemented validation to prevent starting a registration for students with a null student number in the development environment. 5. Removed obsolete "Original Description" columns from the system, streamlining data structures and supporting future maintainability. | J51: Peer CRC:0 Onsite CRC:0 Client CRC:0 Internal Defects:0 External Defects:0 | K51: NIL | L51: NIL [Retro meeting was not held]
A52: =IF(AND(#REF!>=C52,#REF!<=D52),"CurrentSprint","NA") -> #REF! | B52: 26.2 Sprint S1 | C52: 45994 | D52: 46007 | E52: 12 | F52: 19 | G52: Introduced - 16 | H52: In Sprint 26.2 S1 we completed field validation for Form Type and Term, implemented new Universal Search and Datagrid components, and removed the Original Description column to simplify the data model. | I52: 1.Strengthened validation for Form Type and Term to address technical debt and improve data quality. 2.Completed reusable Universal Search component for cross‑context lookups. 3.Implemented the Datagrid component and updated pagination design for a cleaner, more responsive UX. 4.Removed the Original Description column to simplify data structures and make future maintenance easier. 5.Added a check that prevents starting a registration for students with a null studentNumber. | J52: Peer CRC:4 Onsite CRC:0 Client CRC:0 Internal Defects:2 External Defects:3 | K52: NIL | L52: NIL
A53: =IF(AND(#REF!>=C53,#REF!<=D53),"CurrentSprint","NA") -> #REF! | B53: 26.2 Sprint S2 | C53: 46008 | D53: 46035 | E53: 35 | F53: 43 | G53: Introduced - 8 | H53: In Sprint 26.2 S2 we completed customizable columns for Enrollment Plans,universal search for Student Maintenance, Upgraded audit log to table grid for Activities and Custom Fields,added a spinning loader on the Purchases & Fees tab,Completed discovery work for Activity Pricing under prepaid Enrollment Plans, Added a new “No Students” screen, Fixed the capacity modal popup issue development completed for custom grid implementation across Enrollment Plans, Activities, Discounts, and Terms . | I53: 1.Implemented the Enrollment Plan grid with configurable/customizable columns. 2.Upgraded the existing Activities audit log to use the new table grid. 3.Upgraded the existing Custom Fields audit log to use the new table grid. 4.Implemented universal search for Student Maintenance. 5.Replaced the message-based indicator with a spinning loader on the Purchases & Fees tab. 6.Completed discovery for Activity Pricing for prepaid Enrollment Plans. 7. Added a new “No Students” screen and a provision to manually add students even when no MSB students exist. 8.Fixed the capacity modal popup issue. 9.Completed development of the custom grid for Enrollment Plans, Activities, Discounts, and Terms. | J53: Peer CRC:0 Onsite CRC:0 Client CRC:2 Internal Defects:3 External Defects:0 Note:This Story # 51138 - Activities - Non Student Registration - Update validation for checking for students in the msb household - Development is completed and pending for client approval Note :Reason – There were dependencies on MSB APIs, which became blockers for this story. The blockers were identified one after another and discussed with Allen and the client developer, Andy, for confirmation. The PR has been approved by Allen and is currently pending approval from the client developer, Andy. | K53: Nil | L53: Good Sprint and appreciated to completed main as well stretch items. Continue excellent communication, collaboration, and open-minded reflection/retrospectives.
A54: =IF(AND(#REF!>=C54,#REF!<=D54),"CurrentSprint","NA") -> #REF! | B54: 26.2 Sprint S3 | C54: 46036 | D54: 46049 | E54: 9 | F54: 7 | H54: In this 26.2 sprint S3 was primarily focused on regression testing, which was successfully completed. We are completed Editable data grid chanes and UI updates for HSS menu, etc. | I54: Completed the following stories: 1.Activities - Non Student Registration: Updated validation to check for students in the MSB household. 2.Activities - Kaleida: Updated table grid design for Term Maintenance [26.3]. 3.Activities - Kaleida: Admin - Created component for Editable Grid Table with updated design [26.3]. 4.Activities - Kaleida: Updated table grid design for HSS Maintenance. 5.All regression tests passed successfully, ensuring stability for release. | J54: Peer CRC:0 Onsite CRC:0 Client CRC:0 Internal Defects:0 External Defects:0 Note:This Story # 51367 Activities - Kaleida - Update table grid design for Enrollment Plans/ Activities/ Discounts [26.3] - Development is completed and pending QA testing Reason – During the regression sprint, we completed development and Product Owner verification. The pull request will be merged only after the regression sprint ends. Note: As informed by the client, this story will be carried over to the next sprint for PR merging and testing efforts. | K54: Nil | L54: Good Sprint and appreciated to completed main as well stretch items.
A55: =IF(AND(#REF!>=C55,#REF!<=D55),"CurrentSprint","NA") -> #REF! | B55: 26.3 Sprint S1 | C55: 46050 | D55: 46063 | E55: 26 | F55: 39 | G55: 13 | H55: In this 26.3 sprint S1, We have successfully completed all main stories and stretch stories for this sprint. The primary focus was on data table conversion, migrating legacy components to the new CustomDataGrid with improved sorting and filtering capabilities. We also completed comprehensive parent UI updates to enhance the overall user experience and component consistency. Additionally, we addressed various general updates and bug fixes across the system. This sprint demonstrates strong execution with all planned work delivered on schedule. | I55: 1.Data Table Conversion - Successfully migrated 12+ admin modules to the new CustomDataGrid architecture with improved sorting and filtering. 2.Parent UI Updates - Completed Payment History, Kiosk PIN, and loading experience redesigns to enhance user interface consistency. 3.Shared Component Framework - Established shared folder structure for parent components to reduce code duplication and improve maintainability. 4.Universal Search Implementation - Replaced legacy global search with new Universal Search backend functionality. 5.Bug Fixes & Refinements - Addressed action menu alignment, breadcrumb navigation, and general system improvements across all modules. | J55: Peer CRC:0 Onsite CRC:0 Client CRC:1 Internal Defects:5 External Defects:0 | K55: Nil | L55: Overrall a good Sprint and appreciated to completed main as well stretch items. Andy Onsite Developer – Wave team’s last day during this Sprint, the team pushed through and it was a smooth transition. Kristy Client PO - Great communication and collaboration pushed us forward. | M55: 0
A56: =IF(AND(#REF!>=C56,#REF!<=D56),"CurrentSprint","NA") -> #REF! | B56: 26.3 Sprint S2 | C56: 46064 | D56: 46077 | E56: 25 | F56: 35 | G56: 6 | H56: In this 26.3 sprint S2, we successfully completed all main and stretch stories as planned. The primary focus was on updating and standardizing data tables, including migrating legacy components to the new CustomDataGrid with enhanced sorting and filtering features. Significant progress was made on parent UI improvements, delivering a more consistent and user-friendly experience across key areas. We also implemented important component upgrades such as updating to the latest Vega version and converting class components to functional ones. In addition, several general updates and critical bug fixes were addressed, ensuring improved stability and performance throughout the system. This sprint reflects strong execution, with all objectives delivered on schedule. | I56: 1. UI/UX Enhancements: Updated table grid designs for Students, Contacts, Enrollment Plan tabs, People > Documents, and Registrations > Enrollments in Kaleida. Implemented new Parent Breadcrumb UI and updated Parent Footer with Kiosk PIN & Payment History Report. 2. Component Improvements: Converted Student Info Class Components to Functional Components. Created Student Info Card Component for Parent Registration. Updated Vega component to the latest version. 3.Admin Features & Fixes: Added filter for "Completed with Errors" in JobRequest DataGrid. Improved App Switcher initialization for HSSAppTray (26.2.1 dot release). 4.Defect Resolutions: Hid inactive districts from parent selection in Kaleida. Fixed calendar display issues in transfer/withdraw modal. Corrected status column in Parent Accounts to display proper values. Resolved universal search freezing when returning ":" from query. | J56: Peer CRC:0 Onsite CRC:0 Client CRC:1 Internal Defects:5 External Defects:2 | K56: Nil | L56: Overrall a good Sprint and appreciated to completed main as well and few stretch items. Great communication (as always). | M56: 0
A57: =IF(AND(#REF!>=C57,#REF!<=D57),"CurrentSprint","NA") -> #REF! | B57: 26.3 Sprint S3 | C57: 46078 | D57: 46091 | E57: 6 | F57: 12 | G57: 1 | H57: Sprint 26.3 S3 was successfully completed with all regression tests and related defect fixes. Development was finalized for the App Switcher button visibility enhancement. Timeboxed work on Kaleida Admin Breadcrumbs [26.5] was completed. Stretch stories, including updates to Parent Registration, Admin UI improvements, Universal Search, and API token handling, were also delivered for 26.5. All planned and stretch objectives for this sprint were achieved on schedule. | I57: Accomplishments for Sprint 26.3 S3: Completed all regression testing and resolved related defects. Delivered the App Switcher enhancement to hide the button until the script loads. Finished timeboxed development for Kaleida Admin Breadcrumbs [26.5]. Completed stretch stories: Parent Registration updates, Admin UI improvements, Universal Search for Student Purchases, and API token session handling [26.5]. Achieved all planned and stretch sprint objectives on time. | J57: Peer CRC:0 Onsite CRC:0 Client CRC:2 Internal Defects:1 External Defects:3 | K57: Nil | L57: Shoutout to offshore team, engaged, great communication to Vega team. I think we made the most of our refinement, standups, and planning prep call had a great discussions! The collaboration and communication is always top-notch. | M57: 0
A58: =IF(AND(#REF!>=C58,#REF!<=D58),"CurrentSprint","NA") -> #REF! | B58: 26.5 Sprint S1 | C58: 46092 | D58: 46105 | E58: 28 | F58: 23 | H58: Sprint 26.5 S1 was successfully Completed key Kaleida Parent Registration updates, including Student Info, Your Info design, Schedule Landing updates, and Admin Breadcrumbs,Fixed multiple Admin issues, including Bulk Copy/Edit selector defects, Enhanced Registrations Table Grid header text, and Preview EP Forms errors, Completed Parent Accounts registration status navigation so Pending and Waitlisted statuses route correctly to the Review page, Delivered Admin search improvements with Universal Search for Student Purchases,Finished discovery work for the Admin calendar display issue and system-level config props access. | I58: - Completed Add/Edit Student Info updates for Kaleida Parent Registration in 26.5. - Completed the Your Info design updates for Kaleida Parent Registration. - Completed development and internal POV for Schedule Landing updates in Kaleida Parent Registration. - Fixed the Bulk Copy/Edit Selector defect in Admin. - Completed removal of header text from the Registrations Table Grid in 26.5. - Completed navigation from Parent Accounts Registration statuses like Pending and Waitlisted to the Review page in 26.5. - Completed fixes for Preview EP Forms errors in Admin. - Completed Universal Search for Student Purchases in Admin. - Completed discovery for the Admin calendar display issue. - Completed Admin Breadcrumbs updates for Kaleida. - Completed stretch discovery for system-level access to config props | J58: Peer CRC:0 Onsite CRC:0 Client CRC:8 Internal Defects:2 External Defects:0 Note: This #52259 story is being carried forward to the testing phase only due to a last-minute design change request that modified the originally accepted design specifications and acceptance criteria.The client stakeholder has been informed and acknowledges the current status and the revised scope resulting from the design change | K58: Nil | L58: Overrall a good Sprint and Great communication (as always). | M58: 0
A59: =IF(AND(#REF!>=C59,#REF!<=D59),"CurrentSprint","NA") -> #REF! | B59: 26.5 Sprint S2 | C59: 46106 | D59: 46119 | E59: 35 | F59: 28 | G59: 0 | H59: Sprint 26.5 S2 successfully completed key development work across Kaleida and Parent experiences, including Parent Withdraw/Transferred UI verbiage cutoff updates, the Physician's Name field spacing fix, Admin Breadcrumbs [V1], Parent Registration Design updates for Contacts, and Schedule-related enhancements. The sprint also delivered system-level improvements by enabling the App Switcher for HSS users and adding access to configuration properties at the system level, while resolving the Admin calendar display issue. In addition, development was completed for stretch items such as Preview EP Forms Errors, post-submission navigation to the Enrollments page, and redirect button updates to return users to previous screens. Development was also completed for the Schedule Status Indicator and Schedule Landing Updates; however, testing for these items has been carried forward due to a 2.5-day outage across lower environments, including Dev, QA, and Integration. Throughout the sprint, the team maintained strong communication and kept stakeholders informed of the blocker and its impact. | I59: 1. Successfully completed all planned main stories, including Parent Withdraw/Transferred UI verbiage updates, the Physician's Name field spacing fix, Admin Breadcrumbs [V1], Parent Registration Design updates for Contacts, and the Admin calendar display fix. 2. Delivered key system-level enhancements by enabling the App Switcher for HSS users and adding access to configuration properties at the system level. 3. Completed development for stretch stories, including Preview EP Forms error handling, post-submission navigation to the Enrollments page, and redirect button updates to previous screens. 4. Finished development for Schedule Status Indicator and Schedule Landing Updates as part of the Parent Registration enhancements. | J59: Peer CRC:0 Onsite CRC:0 Client CRC:3 Internal Defects:2 External Defects:1 Notes :Stories #52259 and #52461 are deferred pending testing. A 2.5-day blocker affecting all lower environments (Development, Quality Assurance, and Integration) prevented the team from conducting peer code reviews, peer testing, and quality assurance testing. The client is fully aware of this issue. | K59: Nil | L59: What went well: strong communication, good use of meeting times, great attention to detail from the team. What didn't go well : Lower Environments being down delayed being able to test | M59: 0
A60: =IF(AND(#REF!>=C60,#REF!<=D60),"CurrentSprint","NA") -> #REF! | B60: 26.5 Sprint S3 | C60: 46120 | D60: 46133 | E60: 16 | F60: 22 | G60: 9 | H60: Sprint 26.5 S3 was a mini regression sprint focused on strengthening the Activities experience across Parent, Admin, and Kaleida workflows. The team completed key updates including Schedule Landing Updates, Schedule Status Indicator development, parent registration usability improvements, Admin redirect and search enhancements, and Enrollments page navigation updates. Several regression and defect fixes were also completed, including the haspendingUpdates refresh error, incorrect modified field indicators, calendar header spacing, and withdrawn student enrollment counts. Stretch progress included preview handling for manually added student sources, past registration interaction prevention, Admin calendar modal fixes, and Dynamic Reports student count corrections. A small number of items remain in peer review or Product Owner verification. | I60: 1.Successfully completed the planned Sprint 26.5 S3 work across Parent, Admin, and Kaleida experiences, including Schedule Landing Updates, Schedule Status Indicator development, parent registration UI improvements, redirect button updates, and Enrollments page navigation updates. 2.Delivered important usability and stability improvements by enhancing special character support in Universal and Global Search, improving enrollment count visibility, and strengthening the overall registration experience. 3.Resolved key regression and defect items, including the haspendingUpdates refresh issue, incorrect modified field indicators for DOB, School, and Grade, calendar header spacing issues, and Admin calendar modal behavior. 4.Completed stretch development items, including manually added student source preview handling, prevention of interaction with past program registrations, and Dynamic Reports student count fixes, while carrying a small number of items into verification and peer review. | J60: Peer CRC:0 Onsite CRC:0 Client CRC:1 Internal Defects:6 External Defects:2 Notes: Regression defect #27238 was identified at the end of the sprint and has been classified as low priority. Development has been completed, and the related testing effort will be carried forward to the next sprint. | K60: Nil | L60: What Went Well : The team did an incredible job getting almost all of the main commit closed out as well as a bunch in stretch. Carryover is limited to a regression defect, some NotificationHub wrap up, and stretch work. A tremendous amount of work was wrapped up including some finishing touches on the parent redesign V1 What didn't go well : We lost some time to the secret expiring in lower environments blocking us from deploying newer builds as they became available (lost roughly 0.5-1 day of planned work with this). Inconsistency on the environments between non prod and prod. Which made the analysis time a bit longer. | M60: 0 | P60: 62 sp
A61: =IF(AND(#REF!>=C61,#REF!<=D61),"CurrentSprint","NA") -> #REF! | B61: 26.5 Sprint S4 | C61: 46134 | D61: 46147 | E61: 9 | F61: 9 | H61: Sprint 26.5 S4 was successfully completed with all regression tests and related defect fixes. Stretch stories, including updates to Parent Registration, Admin UI improvements, Universal Search , All planned and stretch objectives for this sprint were achieved on time. | I61: Accomplishments for Sprint 26.5 S4: 1.Completed all regression testing and resolved related defects. 2. Adjust registration status chip display. 3. Disable Next button when no eligible students. 4. Pendo - Registration Student Source Event Tagging 5. Achieved all planned and stretch sprint objectives on time. | J61: Peer CRC:0 Onsite CRC:0 Client CRC:1 Internal Defects:9 External Defects:0 | K61: Nil | L61: What Went Well : Allen assigned offshore to regression, more issues identified, manju assisted “the star”, huge undertaking this regression sprint, Team showed the good communication What didn't go well : MSB being down/login issue which delayed Unit testing and PR. | M61: 0 | P61: 75 sp
A62: =IF(AND(#REF!>=C62,#REF!<=D62),"CurrentSprint","NA") -> #REF! | B62: 26.6 Sprint S1 | C62: 46148 | D62: 46161 | E62: 22 | J62: Peer CRC:0 Onsite CRC:0 Client CRC:0 Internal Defects:1 External Defects:4 | M62: 0 | P62: 84 sp

Sheet Defect-template
A1: S.No | B1: Sprint # | C1: Story/Defect ID | D1: Parent Story | E1: Developer | F1: Issue Type | G1: Issue Description | H1: Priority | I1: Defect Source | J1: Type | K1: Status | L1: Root Cause Category | M1: Comments

Sheet Unplanned Leaves
A1: Total Leaves | B1: =SUM(B20:F20) -> 0
B2: Resource Name
A3: Sprint | B3: Allen Xavier | C3: Athinarayanana Ramar | D3: Ramprabhu Sakthivel | E3: Manjunathan Dharaman | F3: Kanchana Umakanthan | G3: Remarks
A4: 26.3 Sprint S1(26-Jan-2026 to 10-Feb-2026)
A5: 26.3 Sprint S2(11-Feb-2026 to 24-Feb-2026)
A6: 26.3 Sprint S3(25-Feb-2026 to 10-Mar-2026)
A7: 26.5 Sprint S1(11-Mar-2026 to 24-Mar-2026)
A8: 26.5 Sprint S2(25-Mar-2026 to 07-Apr-2026)
A9: 26.5 Sprint S3( 08-Apr-2026 to 21-Apr-2026
A10: 26.5 Sprint S4( 22-Apr-2026 to 05-May-2026)
A20: Total | B20: =SUM(B4:B19) -> 0 | C20: =SUM(C4:C19) -> 0 | D20: =SUM(D4:D19) -> 0 | E20: =SUM(E4:E19) -> 0 | F20: =SUM(F4:F19) -> 0

Sheet 26.6 Sprint S1-Status
A1: S.No | B1: Application Name | C1: Sprint Start Date | D1: Sprint End Date | E1: Sprint | F1: Developer | G1: Story ID/Defect ID | H1: Description | I1: Status | J1: Estimated(sp) | K1: Actual(sp) | L1: Actual Hours Worklog | M1: Dev Start Date | N1: Dev End Date | O1: Unit testing | P1: Peer Tested By | Q1: Peer Tested Comments, if any | R1: Peer Reviewed By | S1: Peer Code Review Comments, if any | T1: PR Number/Link | U1: PR Created Date | V1: PR Approved Date | W1: Onsite Lead Code Review | X1: Onsite Lead Code Review Comments, if any | Y1: Client Code Review | Z1: PR Approved Date2 | AA1: Client Code Review Comments, if any | AB1: Internal PO -POV Comments | AC1: Client PO -POV Comments | AD1: Comments | AE1: Does this story Meet Expectations?
A2: =ROW() - ROW(Table1456789101214161817222426283132333637394143454749515355575961636567[[#Headers],[S.No]]) - 1 -> 0
A3: =ROW() - ROW(Table1456789101214161817222426283132333637394143454749515355575961636567[[#Headers],[S.No]]) - 1 -> 1 | B3: MSB Activities | C3: 46148 | D3: 46161 | E3: 26.6 Sprint S1 | F3: Athi | G3: 27161 | H3: Activities - Admin - Pending Registration not showing updated weeks | I3: Defect Fixed | J3: 5 | K3: 3 | L3: 12 | M3: 46149 | N3: 46153 | O3: Done | P3: Ram | Q3: Nil | R3: Ram | S3: Nil | T3: https://dev.azure.com/heartlandschools/Activities/_git/Activities/pullrequest/48962 | U3: 46153 | V3: 46153 | W3: Allen | X3: Nil | Y3: Ethan | Z3: 46153 | AA3: Nil | AB3: NA | AC3: NA | AD3: NA | AE3: Meets Expectation
A4: =ROW() - ROW(Table1456789101214161817222426283132333637394143454749515355575961636567[[#Headers],[S.No]]) - 1 -> 2 | B4: MSB Activities | C4: 46148 | D4: 46161 | E4: 26.6 Sprint S1 | F4: Allen | G4: 52738 | H4: Activities - Admin - Place cursor in search box for expanded Site selector | I4: Story Completed | J4: 2 | K4: 2 | L4: 8 | M4: 46153 | N4: 46153 | O4: Done | P4: Athi | Q4: Nil | R4: Athi | S4: Nil | T4: https://dev.azure.com/heartlandschools/Activities/_git/Activities/pullrequest/49000 | U4: 46154 | V4: 46154 | W4: Allen | X4: Nil | Y4: Ethan | Z4: 46154 | AA4: Nil | AB4: Approved | AC4: Approved | AE4: Meets Expectation
A5: =ROW() - ROW(Table1456789101214161817222426283132333637394143454749515355575961636567[[#Headers],[S.No]]) - 1 -> 3 | B5: MSB Activities | C5: 46148 | D5: 46161 | E5: 26.6 Sprint S1 | F5: Athi | G5: 53146 | H5: Activities - Parent - Hide download/print schedule from Enrollments page [26.5] | I5: Story Completed | J5: 2 | K5: 1 | L5: 4 | M5: 46148 | N5: 46148 | O5: Done | P5: Ram | Q5: Nil | R5: Ram | S5: Nil | T5: https://dev.azure.com/heartlandschools/Activities/_git/Activities/pullrequest/48873 | U5: 46148 | V5: 46148 | W5: Allen | X5: Nil | Y5: Andy | Z5: 46148 | AA5: Nil | AB5: Approved | AC5: Approved | AE5: Meets Expectation
A6: =ROW() - ROW(Table1456789101214161817222426283132333637394143454749515355575961636567[[#Headers],[S.No]]) - 1 -> 4 | B6: MSB Activities | C6: 46148 | D6: 46161 | E6: 26.6 Sprint S1 | F6: Allen | G6: 27358 | H6: Activities - Fake parent login is not working | I6: Defect Being Fixed | J6: 1 | M6: 46148 | N6: 46153 | O6: Done | P6: Athi | Q6: Nil | R6: Athi | S6: Nil | T6: https://dev.azure.com/heartlandschools/Activities/_git/Activities/pullrequest/48794 | U6: 46153 | AB6: NA | AC6: NA | AD6: Its not release canditate | AE6: Meets Expectation
A7: =ROW() - ROW(Table1456789101214161817222426283132333637394143454749515355575961636567[[#Headers],[S.No]]) - 1 -> 5 | B7: MSB Activities | C7: 46148 | D7: 46161 | E7: 26.6 Sprint S1 | F7: Allen | G7: 52940 | H7: Activities - Pendo - Move Pendo into global config prop settings so that it can be accessed prior to a tenant being selected | I7: Story Completed | J7: 1 | M7: 46143 | N7: 46146 | O7: Done | P7: Athi | Q7: Nil | R7: Athi | S7: Nil | T7: https://dev.azure.com/heartlandschools/Activities/_git/Activities/pullrequest/49068 | U7: 46157 | V7: 46157 | W7: Allen | X7: Nil | Y7: Andy | Z7: 46157 | AA7: Nil | AB7: NA | AC7: NA | AE7: Meets Expectation
A8: =ROW() - ROW(Table1456789101214161817222426283132333637394143454749515355575961636567[[#Headers],[S.No]]) - 1 -> 6 | B8: MSB Activities | C8: 46148 | D8: 46161 | E8: 26.6 Sprint S1 | F8: Ram | G8: 52700 | H8: Activities - Kaleida - Update Parent Registration Design (Forms) | I8: Story Being Tested | J8: 8 | K8: 4 | L8: 21 | M8: 46148 | N8: 46153 | O8: Done | P8: Athi | Q8: Nil | R8: Athi | S8: Nil | T8: https://dev.azure.com/heartlandschools/Activities/_git/Activities/pullrequest/48987 | U8: 46154 | V8: 46154 | W8: Allen | X8: Nil | Y8: Andy | Z8: 46154 | AA8: Nil | AB8: Approved | AC8: Approved | AE8: Meets Expectation
A9: =ROW() - ROW(Table1456789101214161817222426283132333637394143454749515355575961636567[[#Headers],[S.No]]) - 1 -> 7 | B9: MSB Activities | C9: 46148 | D9: 46161 | E9: 26.6 Sprint S1 | F9: Athi | G9: 52689 | H9: Activities - Kaleida - Update delete registration confirmation modals (Parent) | I9: Story Completed | J9: 2 | K9: 1 | L9: 4 | M9: 46154 | N9: 46154 | O9: Done | P9: Ram | Q9: Nil | R9: Ram | S9: Nil | T9: https://dev.azure.com/heartlandschools/Activities/_git/Activities/pullrequest/48997 | U9: 46154 | V9: 46154 | W9: Allen | X9: Nil | Y9: Ethan | Z9: 46154 | AA9: Nil | AB9: Approved | AC9: Approved | AE9: Meets Expectation
A10: =ROW() - ROW(Table1456789101214161817222426283132333637394143454749515355575961636567[[#Headers],[S.No]]) - 1 -> 8 | B10: MSB Activities | C10: 46148 | D10: 46161 | E10: 26.6 Sprint S1 | F10: Allen | G10: 27298 | H10: Activities - Admin - District Settings - Edit screen save validation when Provider ID blank is not working | I10: Defect Fixed | J10: 1 | K10: 1 | L10: 4 | M10: 46147 | N10: 46148 | O10: Done | P10: Athi | Q10: Nil | R10: Athi | S10: Nil | T10: https://dev.azure.com/heartlandschools/Activities/_git/Activities/pullrequest/48835 | U10: 46148 | V10: 46148 | W10: Allen | X10: Nil | Y10: Andy | AA10: What if both the password and providerid are blank, wouldn't this hide the validation about the password? We are going to circle back on this discussion - it seems like perhaps the actual solution here is to just remove the X (unselect) option from the dropdown and never allow this to be unset | AB10: NA | AC10: NA | AE10: Meets Expectation
A11: =ROW() - ROW(Table1456789101214161817222426283132333637394143454749515355575961636567[[#Headers],[S.No]]) - 1 -> 9 | B11: MSB Activities | C11: 46148 | D11: 46161 | E11: 26.6 Sprint S1 Stretch | F11: Allen | G11: 53123 | H11: Activities - Pendo - Registration Student Source Event Tagging | I11: Story Completed | J11: 2 | M11: 46148 | N11: 46153 | O11: Done | P11: Athi | Q11: Nil | R11: Athi | S11: Nil | T11: https://dev.azure.com/heartlandschools/Activities/_git/Activities/pullrequest/48834 | U11: 46156 | V11: 46156 | W11: Allen | X11: Nil | Y11: Andy | Z11: 46156 | AA11: Nil | AB11: NA | AC11: NA | AE11: Meets Expectation
A12: 10 | B12: MSB Activities | C12: 46148 | D12: 46161 | E12: 26.6 Sprint S1 Stretch | F12: Ram | G12: 52786 | H12: Activities - Parent - Place cursor in search box for District & Site selector | I12: Story Completed | J12: 2 | K12: 1 | L12: 4 | M12: 46155 | N12: 46155 | O12: Done | P12: Athi | Q12: Nil | R12: Athi | S12: Nil | T12: https://dev.azure.com/heartlandschools/Activities/_git/Activities/pullrequest/49049 | U12: 46156 | V12: 46156 | W12: Allen | X12: Nil | Y12: Ethan | Z12: 46156 | AA12: Nil | AB12: Approved | AC12: Approved | AE12: Meets Expectation
A13: =ROW() - ROW(Table1456789101214161817222426283132333637394143454749515355575961636567[[#Headers],[S.No]]) - 1 -> 11 | B13: MSB Activities | C13: 46148 | D13: 46161 | E13: 26.6 Sprint S1 Stretch | F13: Ram | G13: 52455 | H13: Activities - Parent - Update Default Relationship Field Selection to "Parent" | I13: Story Being Tested | J13: 3 | K13: 1 | L13: 6 | M13: 46154 | N13: 46154 | O13: Done | P13: Athi | Q13: Nil | R13: Athi | S13: Nil | T13: https://dev.azure.com/heartlandschools/Activities/_git/Activities/pullrequest/49050 | U13: 46156 | V13: 46156 | W13: Allen | X13: Nil | Y13: Ethan | Z13: 46156 | AA13: Nil | AB13: Approved | AC13: Approved | AE13: Meets Expectation
A14: =ROW() - ROW(Table1456789101214161817222426283132333637394143454749515355575961636567[[#Headers],[S.No]]) - 1 -> 12 | B14: MSB Activities | C14: 46148 | D14: 46161 | E14: 26.6 Sprint S1 Stretch | F14: Athi | G14: 27410 | H14: Activities - Reject Updated Registration modal is formatted poorly | I14: Defect Fixed | J14: 1 | K14: 1 | L14: 2 | M14: 46156 | N14: 46156 | O14: Done | P14: Ram | Q14: Nil | R14: Ram | S14: Nil | T14: https://dev.azure.com/heartlandschools/Activities/_git/Activities/pullrequest/49057 | U14: 46156 | V14: 46156 | W14: Allen | X14: Nil | Y14: Ethan | Z14: 46156 | AA14: Nil | AB14: NA | AC14: NA | AE14: Meets Expectation
A15: =ROW() - ROW(Table1456789101214161817222426283132333637394143454749515355575961636567[[#Headers],[S.No]]) - 1 -> 13 | B15: MSB Activities | C15: 46148 | D15: 46161 | E15: 26.6 Sprint S1 Stretch | F15: Athi | G15: 27416 | H15: Activities - Admin - Clear Discount Modal triggering when no discount exists | I15: Defect Fixed | J15: 1 | K15: 1 | L15: 4 | M15: 46157 | N15: 46157 | O15: Done | P15: Ram | Q15: Nil | R15: Ram | S15: Nil | T15: https://dev.azure.com/heartlandschools/Activities/_git/Activities/pullrequest/49082 | U15: 46157 | V15: 46157 | W15: Allen | X15: Nil | Y15: Ethan | Z15: 46157 | AA15: Nil | AB15: NA | AC15: NA | AE15: Meets Expectation
A16: =ROW() - ROW(Table1456789101214161817222426283132333637394143454749515355575961636567[[#Headers],[S.No]]) - 1 -> 14 | B16: MSB Activities | C16: 46148 | D16: 46161 | E16: 26.6 Sprint S1 Stretch | F16: Athi | G16: 52834 | H16: Activities - SYSTEM - TECH DEBT - Database - Investigate usage of LOCKs in DB queries [26.6] | I16: Story Being Developed | J16: 8 | K16: 0 | L16: 2 | M16: 46156 | AB16: NA | AC16: NA | AE16: Meets Expectation

Sheet 26.6 Sprint 1 - Defects 
A1: S.No | B1: Sprint # | C1: Story/Defect ID | D1: Parent Story | E1: Developer | F1: Issue Type | G1: Issue Description | H1: Root Cause Analysis | I1: Priority | J1: Defect Source | K1: Type | L1: Status | M1: Root Cause Category | N1: Comments | O1: Defect Raised
A2: 1 | B2: 26.6 Sprint S1 | C2: 27298 Activities - Admin - District Settings - Edit screen save validation when Provider ID blank is not working | E2: Allen | F2: Defect | G2: If you go into a district in Hss Staff - Districts and proceed to the edit screen, remove the MSB Provider Id (setting it to not set) then try to save. The button does nothing and there is no validation messaging. | I2: Minor | J2: Manual | K2: External | L2: Defect Fixed | M2: Existing_Issues | O2: Offshore PO - Kanchana
A3: 2 | B3: 26.6 Sprint S1 | C3: 27161 Activities - Admin - Pending Registration not showing updated weeks | E3: Athi | F3: Defect | G3: Defect: 1 - When using the weekly calendar. If you update the weeks on a pending registration and then navigate to that registration in Admin. We are not showing the update. Defect: 2 - I verified in the integration environment that in the parent, I scheduled only for one week (weekly calendar) and submitted my registration. When I viewed it as an admin on the pending/waitlist/View all/ Student enrollment pages, it showed all the weeks as selected. | I3: Major | J3: Manual | K3: External | L3: Defect Fixed | M3: Existing_Issues | O3: Offshore PO - Kanchana
A4: 3 | B4: 26.6 Sprint S1 | C4: 27358 Activities - Fake parent login is not working | E4: Allen | F4: Defect | G4: The fake parent login is not working | I4: Minor | J4: Manual | K4: Internal | L4: Defect Being Fixed | M4: Development | O4: Onshore Manager - Ethan
A5: 4 | B5: 26.6 Sprint S1 Stretch | C5: 27410 - Activities - Reject Updated Registration modal is formatted poorly | E5: Athi | F5: Defect | G5: The Reject Updated Registration modal formatting could be improved. | I5: Minor | J5: Manual | K5: External | L5: Defect Fixed | M5: Existing_Issues | O5: Onsite QA - Jeff
A6: 5 | B6: 26.6 Sprint S1 Stretch | C6: 27416 Activities - Admin - Clear Discount Modal triggering when no discount exists | E6: Athi | F6: Defect | G6: In admin, it looks like once a discount is set, and then removed. If you change the pricing of the enrollment plan, it triggers the "Clear Discounts" modal, even though a discount does not exist. Most likely we are not updating the state of the prop once a discount has been set. | I6: Significant | J6: Manual | K6: External | L6: Defect Fixed | M6: Existing_Issues | O6: Onsite QA - Jeff

Sheet 26.5 Sprint S4-Status
A1: S.No | B1: Application Name | C1: Sprint Start Date | D1: Sprint End Date | E1: Sprint | F1: Developer | G1: Story ID/Defect ID | H1: Description | I1: Status | J1: Estimated(sp) | K1: Actual(sp) | L1: Actual Hours Worklog | M1: Dev Start Date | N1: Dev End Date | O1: Unit testing | P1: Peer Tested By | Q1: Peer Tested Comments, if any | R1: Peer Reviewed By | S1: Peer Code Review Comments, if any | T1: PR Number/Link | U1: PR Created Date | V1: PR Approved Date | W1: Onsite Lead Code Review | X1: Onsite Lead Code Review Comments, if any | Y1: Client Code Review | Z1: PR Approved Date2 | AA1: Client Code Review Comments, if any | AB1: Internal PO -POV Comments | AC1: Client PO -POV Comments | AD1: Comments | AE1: Does this story Meet Expectations?
A2: =ROW() - ROW(Table14567891012141618172224262831323336373941434547495153555759616365[[#Headers],[S.No]]) - 1 -> 0
A3: =ROW() - ROW(Table14567891012141618172224262831323336373941434547495153555759616365[[#Headers],[S.No]]) - 1 -> 1 | B3: MSB Activities | C3: 46134 | D3: 46147 | E3: 26.5 Sprint S4 | F3: Athi | G3: 27238 | H3: Activities - Regression - Parent - Not able to see Screen "No Student Yet" when no student are available for a parent. | I3: Defect Fixed | J3: 0 | K3: 1 | L3: 3 | M3: 46132 | N3: 46133 | O3: Done | P3: Ram | Q3: Nil | R3: Ram | S3: Nil | T3: https://dev.azure.com/heartlandschools/Activities/_git/Activities/pullrequest/48541 | U3: 46133 | V3: 46134 | W3: Allen | X3: Nil | Y3: Andy | Z3: 46134 | AA3: Nil | AB3: NA | AC3: NA | AD3: Carried from last sprint - Testing effort only:This defect found on end of the sprint, its low priority, and development effort is completed in the last sprint. | AE3: Meets Expectation
A4: =ROW() - ROW(Table14567891012141618172224262831323336373941434547495153555759616365[[#Headers],[S.No]]) - 1 -> 2 | B4: MSB Activities | C4: 46134 | D4: 46147 | E4: 26.5 Sprint S4 | F4: Ram | G4: 27267 | H4: Activities - Regression - Student Card - The data-testid field is displaying the UID instead of the Student Name | I4: Defect Fixed | J4: 0 | K4: 1 | L4: 2 | M4: 46134 | N4: 46134 | O4: Done | P4: Athi | Q4: Nil | R4: Athi | S4: Nil | T4: https://dev.azure.com/heartlandschools/Activities/_git/Activities/pullrequest/48574 | U4: 46134 | V4: 46134 | W4: Allen | X4: Nil | Y4: Ethan | Z4: 46134 | AA4: Nil | AB4: NA | AC4: NA | AE4: Meets Expectation
A5: =ROW() - ROW(Table14567891012141618172224262831323336373941434547495153555759616365[[#Headers],[S.No]]) - 1 -> 3 | B5: MSB Activities | C5: 46134 | D5: 46147 | E5: 26.5 Sprint S4 | F5: Ram | G5: 27266 | H5: Activities - Regression - Site Selector - The data-testid field is displaying the UID instead of the Site Name | I5: Defect Fixed | J5: 0 | K5: 1 | L5: 2 | M5: 46134 | N5: 46134 | O5: Done | P5: Athi | Q5: Nil | R5: Athi | S5: Nil | T5: https://dev.azure.com/heartlandschools/Activities/_git/Activities/pullrequest/48573 | U5: 46134 | V5: 46134 | W5: Allen | X5: Nil | Y5: Ethan | Z5: 46134 | AA5: Nil | AB5: NA | AC5: NA | AE5: Meets Expectation
A6: =ROW() - ROW(Table14567891012141618172224262831323336373941434547495153555759616365[[#Headers],[S.No]]) - 1 -> 4 | B6: MSB Activities | C6: 46134 | D6: 46147 | E6: 26.5 Sprint S4 | F6: Ram | G6: 52882 | H6: Activities - Parent - Disable Next button when no eligible students | I6: Story Completed | J6: 2 | K6: 2 | L6: 2 | M6: 46129 | N6: 46132 | O6: Done | P6: Athi | Q6: Nil | R6: Athi | S6: Nil | T6: https://dev.azure.com/heartlandschools/Activities/_git/Activities/pullrequest/48583 | U6: 46134 | V6: 46134 | W6: Allen | X6: Nil | Y6: Ethan | Z6: 46134 | AA6: Nil | AB6: Approved | AC6: Approved | AE6: Meets Expectation
A7: =ROW() - ROW(Table14567891012141618172224262831323336373941434547495153555759616365[[#Headers],[S.No]]) - 1 -> 5 | B7: MSB Activities | C7: 46134 | D7: 46147 | E7: 26.5 Sprint S4 | F7: Athi | G7: 52883 | H7: Activities - Parent - Adjust registration status chip display [26.5?] | I7: Story Completed | J7: 2 | K7: 2 | L7: 2 | M7: 46128 | N7: 46132 | O7: Done | P7: Ram | Q7: Nil | R7: Ram | S7: Nil | T7: https://dev.azure.com/heartlandschools/Activities/_git/Activities/pullrequest/48579 | U7: 46134 | V7: 46134 | W7: Allen | X7: Nil | Y7: Ethan | Z7: 46134 | AA7: Nil | AB7: Approved | AC7: Approved | AE7: Meets Expectation
A8: =ROW() - ROW(Table14567891012141618172224262831323336373941434547495153555759616365[[#Headers],[S.No]]) - 1 -> 6 | B8: MSB Activities | C8: 46134 | D8: 46147 | E8: 26.5 Sprint S4 | F8: Allen | G8: 52939 | H8: Activities - Pendo - Registration Student Source Event Tagging (Discovery) | I8: Story Completed | J8: 5 | K8: 5 | L8: 5 | M8: 46134 | O8: NA | P8: NA | Q8: NA | R8: NA | S8: NA | T8: NA | U8: NA | V8: NA | W8: NA | X8: NA | Y8: NA | Z8: NA | AA8: NA | AB8: NA | AC8: NA | AD8: Its Discovery story | AE8: Meets Expectation
A9: =ROW() - ROW(Table14567891012141618172224262831323336373941434547495153555759616365[[#Headers],[S.No]]) - 1 -> 7 | B9: MSB Activities | C9: 46134 | D9: 46147 | E9: 26.5 Sprint S4 | F9: Athi | G9: 27272 | H9: Activities - REGRESSION - Admin - Missing breadcrumb link in Config Props - Add and Roles – Edit | I9: Defect Fixed | J9: 0 | K9: 1 | L9: 3 | M9: 46135 | N9: 46135 | O9: Done | P9: Ram | Q9: Nil | R9: Ram | S9: Nil | T9: https://dev.azure.com/heartlandschools/Activities/_git/Activities/pullrequest/48610 | U9: 46135 | V9: 46135 | W9: Allen | X9: Nil | Y9: Ethan | Z9: 46135 | AA9: Very minor, but this should be an "else if" | AB9: NA | AC9: NA | AD9: Minor suggestion in CRC | AE9: Meets Expectation
A10: =ROW() - ROW(Table14567891012141618172224262831323336373941434547495153555759616365[[#Headers],[S.No]]) - 1 -> 8 | B10: MSB Activities | C10: 46134 | D10: 46147 | E10: 26.5 Sprint S4 | F10: Athi | G10: 27306 | H10: Activities - Regression - Admin - Universal search is not filtering when we provide invalid date and Amount Field. | I10: Defect Fixed | J10: 0 | K10: 1 | L10: 3 | M10: 46140 | N10: 46140 | O10: Done | P10: Ram | Q10: Nil | R10: Ram | S10: Nil | T10: https://dev.azure.com/heartlandschools/Activities/_git/Activities/pullrequest/48689 | U10: 46142 | V10: 46143 | W10: Allen | X10: Nil | Y10: Andy | Z10: 46143 | AA10: Nil | AB10: NA | AC10: NA | AE10: Meets Expectation
A11: =ROW() - ROW(Table14567891012141618172224262831323336373941434547495153555759616365[[#Headers],[S.No]]) - 1 -> 9 | B11: MSB Activities | C11: 46134 | D11: 46147 | E11: 26.5 Sprint S4 | F11: Athi | G11: 27311 | H11: Activities - REGRESSION - Parent - Removed day still showing in parent after removing it from the schedule | I11: Defect Fixed | J11: 0 | K11: 1 | L11: 3 | M11: 46141 | N11: 46141 | O11: Done | P11: Ram | Q11: Nil | R11: Ram | S11: Nil | T11: https://dev.azure.com/heartlandschools/Activities/_git/Activities/pullrequest/48716 | U11: 46141 | V11: 46141 | W11: Allen | X11: Nil | Y11: Andy | Z11: 46141 | AA11: Nil | AB11: NA | AC11: NA | AE11: Meets Expectation
A12: 10 | B12: MSB Activities | C12: 46134 | D12: 46147 | E12: 26.5 Sprint S4 | F12: Ram | G12: 27308 | H12: Activities - Regression - Parent - Custom Field Email Validation is not working | I12: Defect Fixed | J12: 0 | K12: 1 | L12: 3 | M12: 46140 | N12: 46140 | O12: Done | P12: Athi | Q12: Nil | R12: Athi | S12: Nil | T12: https://dev.azure.com/heartlandschools/Activities/_git/Activities/pullrequest/48680 | U12: 46140 | V12: 46140 | W12: Allen | X12: Nil | Y12: Ethan | Z12: 46140 | AA12: Nil | AB12: Nil | AC12: Nil | AE12: Meets Expectation
A13: =ROW() - ROW(Table14567891012141618172224262831323336373941434547495153555759616365[[#Headers],[S.No]]) - 1 -> 11 | B13: MSB Activities | C13: 46134 | D13: 46147 | E13: 26.5 Sprint S4 | F13: Athi | G13: 27317 | H13: Activities - Regression - Parent - Incorrect display of Download & Print schedule data on Enrollments page card details | I13: Defect Fixed | J13: 0 | K13: 1 | L13: 3 | M13: 46142 | N13: 46142 | O13: Done | P13: Ram | Q13: Nil | R13: Ram | S13: Nil | T13: https://dev.azure.com/heartlandschools/Activities/_git/Activities/pullrequest/48772 | U13: 46142 | V13: 46143 | W13: Allen | X13: Nil | Y13: Andy | Z13: 46143 | AA13: Nil | AB13: NA | AC13: NA | AE13: Meets Expectation
A14: =ROW() - ROW(Table14567891012141618172224262831323336373941434547495153555759616365[[#Headers],[S.No]]) - 1 -> 12 | B14: MSB Activities | C14: 46134 | D14: 46147 | E14: 26.5 Sprint S4 | F14: Ram | G14: 27325 | H14: Activities - Regression - Parent - Page is not responding while changing the custom field Radio button values. | I14: Defect Fixed | J14: 0 | K14: 1 | L14: 4 | M14: 46142 | N14: 46142 | O14: Done | P14: Athi | Q14: Nil | R14: Athi | S14: Nil | T14: https://dev.azure.com/heartlandschools/Activities/_git/Activities/pullrequest/48768 | U14: 46142 | V14: 46142 | W14: Allen | X14: Nil | Y14: Andy | Z14: 46142 | AA14: Nil | AB14: NA | AC14: NA | AE14: Meets Expectation
A15: =ROW() - ROW(Table14567891012141618172224262831323336373941434547495153555759616365[[#Headers],[S.No]]) - 1 -> 13 | B15: MSB Activities | C15: 46134 | D15: 46147 | E15: 26.5 Sprint S4 Stretch | F15: Athi | G15: 52834 | H15: Activities - SYSTEM - TECH DEBT - Database - Investigate usage of LOCKs in DB queries [26.6] | I15: Story Being Developed | J15: 8 | K15: 1 | L15: 6 | M15: 46134 | N15: NA | O15: NA | P15: NA | Q15: NA | R15: NA | S15: NA | T15: NA | U15: NA | V15: NA | W15: NA | X15: NA | Y15: NA | Z15: NA | AA15: NA | AB15: NA | AC15: NA | AD15: Its Tech debt story | AE15: Meets Expectation
A19: =ROW() - ROW(Table14567891012141618172224262831323336373941434547495153555759616365[[#Headers],[S.No]]) - 1 -> 17
A20: =ROW() - ROW(Table14567891012141618172224262831323336373941434547495153555759616365[[#Headers],[S.No]]) - 1 -> 18

Sheet 26.5 Sprint 4 - Defects 
A1: S.No | B1: Sprint # | C1: Story/Defect ID | D1: Parent Story | E1: Developer | F1: Issue Type | G1: Issue Description | H1: Root Cause Analysis | I1: Priority | J1: Defect Source | K1: Type | L1: Status | M1: Root Cause Category | N1: Comments | O1: Defect Raised
A2: 1 | B2: 26.5 Sprint S4 | C2: Activities - Regression - Site Selector - The data-testid field is displaying the UID instead of the Site Name | E2: Ram | F2: Defect | G2: In the Site Selector, the data-testid field is displaying the UID instead of the Site Name | H2: Datatest Id renamed in the UI compenent which is used for automation test | I2: Minor | J2: Manual | K2: Internal | L2: Defect Fixed | M2: Existing_Issues | O2: Onshore - QA - Jeff
A3: 2 | B3: 26.5 Sprint S4 | C3: 27267 Activities - Regression - Student Card - The data-testid field is displaying the UID instead of the Student Name | E3: Ram | F3: Defect | G3: On the updated Student Cart, the data-testid field is displaying the UID instead of the Student Name | H3: Datatest Id renamed in the UI compenent which is used for automation test | I3: Minor | J3: Manual | K3: Internal | L3: Defect Fixed | M3: Existing_Issues | O3: Onshore - Manager - Ethan
A4: 3 | B4: 26.5 Sprint S4 | C4: 27272 Activities - REGRESSION - Admin - Missing breadcrumb link in Config Props - Add and Roles – Edit | E4: Athinarayanan | F4: Defect | G4: Missing breadcrumb link issue in Config Props Add and Roles – Edit Config Props > Add (Home> Heartland Staff ) Roles > Edit. (Home > Setup > Roles) | H4: This breadcrumb path is missed in the AC point. | I4: Minor | J4: Manual | K4: Internal | L4: Defect Fixed | M4: QA | O4: Ram - Offshore Developer
A5: 4 | B5: 26.5 Sprint S4 | C5: 27238 - Activities - Regression - Parent - Not able to see Screen "No Student Yet" when no student are available for a parent. | E5: Athinarayanan | F5: Defect | G5: Not able to see Screen "No Student Yet" when no student are available for a parent. | H5: Student count validation is missed | I5: Minor | J5: Manual | K5: Internal | L5: Defect Fixed | M5: Development | N5: Carried from last sprint - Testing effort only:This defect found on end of the sprint, its low priority, and development effort is completed in the last sprint. | O5: Athinarayanan - Offshore Developer
A6: 5 | B6: 26.5 Sprint S4 | C6: 27311 Activities - REGRESSION - Parent - Removed day still showing in parent after removing it from the schedule | E6: Athinarayanan | F6: Defect | G6: In parent with daily calendar on, if you put in that you will be attending everyday. Then deselect all of a specific day (remove Mondays by deselecting it). In the Schedules section it still shows Monday as being part of the schedule. This is occurring with updating an accepted registration as well. | H6: Model Validation is missed | I6: Minor | J6: Manual | K6: Internal | L6: Defect Fixed | M6: Development | N6: . | O6: Offshore QA - manjunath
A7: 6 | B7: 26.5 Sprint S4 | C7: 27308 Activities - Regression - Parent - Custom Field Email Validation is not working | E7: Ram | F7: Defect | G7: Custom Field Email Validation is not working Custom Field Email Validation is missing for students Info screen, Contacts screen and parent info Screen. | H7: Email validation for custom field is missed. | I7: Minor | J7: Manual | K7: Internal | L7: Defect Fixed | M7: Development | N7: . | O7: Offshore QA - manjunath
A8: 7 | B8: 26.5 Sprint S4 | C8: 27325 Activities - Regression - Parent - Page is not responding while changing the custom field Radio button values. | E8: Ram | F8: Defect | G8: Page is not responding while changing the Radio button values. This happens for Student info, parent Info and contacts info screen. | H8: Sync event handling which affected the performance of the page. | I8: Significant | J8: Manual | K8: Internal | L8: Defect Fixed | M8: Development | N8: . | O8: Offshore QA - manjunath
A9: 8 | B9: 26.5 Sprint S4 | C9: 27306 Activities - Regression - Admin - Purchases Universal search is not filtering when we provide invalid date and Amount Field | E9: Athinarayanan | F9: Defect | G9: Universal search is not filtering when we provide invalid date and Amount Field | H9: Invalid or edge case validation are missed in the query builder. | I9: Significant | J9: Manual | K9: Internal | L9: Defect Fixed | M9: Development | O9: Ram - Offshore Developer
A10: 9 | B10: 26.5 Sprint S4 | C10: 27317 Activities - Regression - Parent - Incorrect display of Download & Print schedule data on Enrollments page card details | F10: Defect | G10: Defect:1 Validation message persists after clearing To Date in Payment History Report In the Payment History Report, when a user enters a From Date later than the To Date (e.g., From Date: 05/02/2026, To Date: 04/28/2026), the system correctly displays a validation message indicating the invalid date range. However, after clearing the To Date field, the validation message continues to persist even though the input is now valid. This suggests that the validation logic is not being reset when the To Date field is cleared. Defect: 2: Incorrect display of Download and Print schedule data on Enrollments & Registration page card details On the Enrollments & Registration page, the enrollment card details section is showing incorrect data for the Download and Print schedule options. The information displayed does not match the actual schedule data, leading to inconsistencies between what is downloaded/printed and what is shown on the schedule page. | H10: Clearing error message was missed after proper date.Updated scheduled date are not printed in the sheet. | I10: Significant | J10: Manual | K10: Internal | L10: Defect Fixed | M10: Development | O10: Kanchana - Offshore PO

Sheet 26.5 Sprint S3-Status
A1: S.No | B1: Application Name | C1: Sprint Start Date | D1: Sprint End Date | E1: Sprint | F1: Developer | G1: Story ID/Defect ID | H1: Description | I1: Status | J1: Estimated(sp) | K1: Actual(sp) | L1: Actual Hours Worklog | M1: Dev Start Date | N1: Dev End Date | O1: Unit testing | P1: Peer Tested By | Q1: Peer Tested Comments, if any | R1: Peer Reviewed By | S1: Peer Code Review Comments, if any | T1: PR Number/Link | U1: PR Created Date | V1: PR Approved Date | W1: Onsite Lead Code Review | X1: Onsite Lead Code Review Comments, if any | Y1: Client Code Review | Z1: PR Approved Date2 | AA1: Client Code Review Comments, if any | AB1: Internal PO -POV Comments | AC1: Client PO -POV Comments | AD1: Comments | AE1: Does this story Meet Expectations?
A2: =ROW() - ROW(Table145678910121416181722242628313233363739414345474951535557596163[[#Headers],[S.No]]) - 1 -> 0
A3: =ROW() - ROW(Table145678910121416181722242628313233363739414345474951535557596163[[#Headers],[S.No]]) - 1 -> 1 | B3: MSB Activities | C3: 46120 | D3: 46133 | E3: 26.5 Sprint S3 | F3: Athi | G3: 52259 | H3: Activities - Kaleida - Update Parent Registration - Schedule Landing Updates | I3: Story Completed | J3: 2 | K3: 1 | L3: 1 | M3: 46092 | N3: 46104 | O3: Done | P3: Ram | Q3: Nil | R3: Ram | S3: Nil | T3: https://dev.azure.com/heartlandschools/Activities/_git/Activities/pullrequest/47981 | U3: 46105 | V3: 46105 | W3: Allen | X3: Nil | Y3: Ethan | Z3: 46106 | AA3: Nil | AB3: Approved. POV Comments: When two different calendar activities are scheduled, the system displays similar data for both, instead of distinct activity details. Download - Empty PDF is downloading | AC3: Approved. During POV additional scope is added to the story | AE3: Meets Expectation
A4: =ROW() - ROW(Table1456789101214161817222426283132333637394143454749515355575961[[#Headers],[S.No]]) - 1 -> 2 | B4: MSB Activities | C4: 46120 | D4: 46133 | E4: 26.5 Sprint S3 | F4: Athi | G4: 52461 | H4: Activities - Kaleida - Update Parent Registration - Schedule Status indicator | I4: Story Completed | J4: 1 | K4: 1 | L4: 1 | M4: 46107 | N4: 46111 | O4: Done | P4: Ram | Q4: Nil | R4: Ram | S4: Nil | T4: https://dev.azure.com/heartlandschools/Activities/_git/Activities/pullrequest/48198 | U4: 46114 | V4: 46114 | W4: Allen | X4: Nil | Y4: Ethan | Z4: 46114 | AA4: Nil | AB4: POV comment: Incomplete and Complete status showing at the same time. Approved | AC4: Approved | AE4: Meets Expectation
A5: =ROW() - ROW(Table1456789101214161817222426283132333637394143454749515355575961[[#Headers],[S.No]]) - 1 -> 3 | B5: MSB Activities | C5: 46120 | D5: 46133 | E5: 26.5 Sprint S3 | F5: Ram | G5: 52686 | H5: Activities - Parent - Hide unselected students and checkboxes for submitted registrations | I5: Story Completed | J5: 5 | K5: 3 | L5: 10 | M5: 46120 | N5: 46120 | O5: Done | P5: Athi | Q5: Nil | R5: Athi | S5: Nil | T5: https://dev.azure.com/heartlandschools/Activities/_git/Activities/pullrequest/48328 | U5: 46121 | V5: 46121 | W5: Allen | X5: Nil | Y5: Ethan | Z5: 46121 | AA5: Nil | AB5: Approved. | AC5: Approved | AE5: Meets Expectation
A6: =ROW() - ROW(Table145678910121416181722242628313233363739414345474951535557596163[[#Headers],[S.No]]) - 1 -> 4 | B6: MSB Activities | C6: 46120 | D6: 46133 | E6: 26.5 Sprint S3 | F6: Ram | G6: 52687 | H6: Activities - Parent - Hide pencil/edit icon for students not selected | I6: Story Completed | J6: 2 | K6: 2 | L6: 5 | M6: 46122 | N6: 46122 | O6: Done | P6: Athi | Q6: Nil | R6: Athi | S6: Nil | T6: https://dev.azure.com/heartlandschools/Activities/_git/Activities/pullrequest/48354 | U6: 46122 | V6: 46122 | W6: Allen | X6: Nil | Y6: Ethan | Z6: 46122 | AA6: Nil | AB6: Approved. | AC6: Approved. | AE6: Meets Expectation
A7: =ROW() - ROW(Table145678910121416181722242628313233363739414345474951535557596163[[#Headers],[S.No]]) - 1 -> 5 | B7: MSB Activities | C7: 46120 | D7: 46133 | E7: 26.5 Sprint S3 | F7: Athi | G7: 52048 | H7: Activities - Admin - Redirect buttons to previous screens | I7: Story Completed | J7: 1 | K7: 1 | L7: 1 | M7: 46112 | N7: 46114 | O7: Done | P7: Ram | Q7: Nil | R7: Ram | S7: Nil | T7: https://dev.azure.com/heartlandschools/Activities/_git/Activities/pullrequest/48318 | U7: 46121 | V7: 46122 | W7: Allen | X7: Nil | Y7: Ethan | Z7: 46122 | AB7: Approved. | AC7: Approved | AE7: Meets Expectation
A8: =ROW() - ROW(Table145678910121416181722242628313233363739414345474951535557596163[[#Headers],[S.No]]) - 1 -> 6 | B8: MSB Activities | C8: 46120 | D8: 46133 | E8: 26.5 Sprint S3 | F8: Allen | G8: 52480 | H8: Activities - Parent - Land on Enrollments page after interacting with a registration | I8: Story Completed | J8: 1 | M8: 46113 | N8: 46113 | O8: Done | P8: Athi | Q8: Nil | R8: Athi | S8: Nil | T8: https://dev.azure.com/heartlandschools/Activities/_git/Activities/pullrequest/48250 | U8: 46118 | V8: 46118 | W8: Allen | X8: Nil | Y8: Ethan | Z8: 46118 | AA8: Nil | AB8: Approved. | AC8: Approved. | AE8: Meets Expectation
A9: =ROW() - ROW(Table145678910121416181722242628313233363739414345474951535557596163[[#Headers],[S.No]]) - 1 -> 7 | B9: MSB Activities | C9: 46120 | D9: 46133 | E9: 26.5 Sprint S3 | F9: Athi | G9: 52528 | H9: Activities - Admin - Universal & Global Search – Support for Special Characters | I9: Story Completed | J9: 3 | K9: 1 | L9: 2 | M9: 46120 | N9: 46121 | O9: Done | P9: Ram | Q9: Nil | R9: Ram | S9: Nil | T9: https://dev.azure.com/heartlandschools/Activities/_git/Activities/pullrequest/48353 https://dev.azure.com/heartlandschools/Activities/_git/Activities/pullrequest/48500 | U9: 46122 | V9: 46132 | W9: Allen | X9: Nil | Y9: Andy | Z9: 46132 | AA9: Nil | AB9: Approved. | AC9: Approved | AE9: Meets Expectation
A10: =ROW() - ROW(Table145678910121416181722242628313233363739414345474951535557596163[[#Headers],[S.No]]) - 1 -> 8 | B10: MSB Activities | C10: 46120 | D10: 46133 | E10: 26.5 Sprint S3 | F10: Allen | G10: 26974 | H10: Activities - Parent - Enrollments count including withdrawn [26.5] | I10: Defect Fixed | J10: 1 | K10: 1 | L10: 1 | M10: 46119 | N10: 46119 | O10: Done | P10: Athi | Q10: Nil | R10: Athi | S10: Nil | T10: https://dev.azure.com/heartlandschools/Activities/_git/Activities/pullrequest/48277 | U10: 46119 | V10: 46119 | W10: Allen | X10: Nil | Y10: Ethan | Z10: 46119 | AA10: Nil | AB10: NA | AC10: NA | AE10: Meets Expectation
A11: =ROW() - ROW(Table145678910121416181722242628313233363739414345474951535557596163[[#Headers],[S.No]]) - 1 -> 9 | B11: MSB Activities | C11: 46120 | D11: 46133 | E11: 26.5 Sprint S3 | F11: Athi | G11: 27171 | H11: Activities - REGRESSION - Parent - Facing "haspendingUpdates" error while refreshing the screen | I11: Defect Fixed | K11: 1 | L11: 2 | M11: 46125 | N11: 46125 | O11: Done | P11: Ram | Q11: Nil | R11: Ram | S11: Nil | T11: https://dev.azure.com/heartlandschools/Activities/_git/Activities/pullrequest/48427 | U11: 46127 | V11: 46127 | W11: Allen | X11: Nil | Y11: Ethan | Z11: 46127 | AA11: Nil | AB11: NA | AC11: NA | AE11: Meets Expectation
A12: =ROW() - ROW(Table145678910121416181722242628313233363739414345474951535557596163[[#Headers],[S.No]]) - 1 -> 10 | B12: MSB Activities | C12: 46120 | D12: 46133 | E12: 26.5 Sprint S3 | F12: Ram | G12: 27211 | H12: Activities - REGRESSION - Parent - DOB,School and Grade fields shown as modified while updating the registration | I12: Defect Fixed | K12: 2 | L12: 4 | M12: 46129 | N12: 46129 | O12: Done | P12: Athi | Q12: Nil | R12: Athi | S12: Nil | T12: https://dev.azure.com/heartlandschools/Activities/_git/Activities/pullrequest/48497 | U12: 46129 | V12: 46132 | W12: Allen | X12: Nil | Y12: Andy | Z12: 46132 | AA12: Nil | AB12: NA | AC12: NA | AE12: Meets Expectation
A13: =ROW() - ROW(Table145678910121416181722242628313233363739414345474951535557596163[[#Headers],[S.No]]) - 1 -> 11 | B13: MSB Activities | C13: 46120 | D13: 46133 | E13: 26.5 Sprint S3 | F13: Athi | G13: 27217 | H13: Activities - REGRESSION - Parent - Calendar showing space above header | I13: Defect Fixed | K13: 1 | L13: 2 | M13: 46129 | N13: 46129 | O13: Done | P13: Ram | Q13: Nil | R13: Ram | S13: Nil | T13: https://dev.azure.com/heartlandschools/Activities/_git/Activities/pullrequest/48512 | U13: 46132 | V13: 46132 | W13: Allen | X13: Nil | Y13: Andy | Z13: 46132 | AA13: Nil | AB13: NA | AC13: NA | AE13: Meets Expectation
A14: =ROW() - ROW(Table145678910121416181722242628313233363739414345474951535557596163[[#Headers],[S.No]]) - 1 -> 12 | B14: MSB Activities | C14: 46120 | D14: 46133 | E14: 26.5 Sprint S3 | F14: Athi | G14: 27238 | H14: Activities - Regression - Parent - Not able to see Screen "No Student Yet" when no student are available for a parent. | I14: Defect Peer Review | K14: 1 | L14: 2 | M14: 46132 | N14: 46133 | O14: Done | P14: Ram | Q14: Nil | R14: Ram | S14: Nil | T14: https://dev.azure.com/heartlandschools/Activities/_git/Activities/pullrequest/48541 | U14: 46133 | V14: NA | W14: NA | X14: NA | Y14: NA | Z14: NA | AA14: NA | AB14: NA | AC14: NA | AD14: This Regression defect found in end-of-sprint. May be Test effort will be carry forward to the next sprint. | AE14: Meets Expectation
A15: =ROW() - ROW(Table1456789101214161817222426283132333637394143454749515355575961[[#Headers],[S.No]]) - 1 -> 13 | B15: MSB Activities | C15: 46120 | D15: 46133 | E15: 26.5 Sprint S3 Stretch | F15: Allen\Athi | G15: 52709 | H15: Activities - Enrollment Plans - Handle Preview tab for manually added student source | I15: Story Completed | J15: 2 | K15: 1 | L15: 2 | M15: 46120 | N15: 46121 | O15: Done | P15: Ram | Q15: Nil | R15: Ram | S15: Nil | T15: https://dev.azure.com/heartlandschools/Activities/_git/Activities/pullrequest/48351 | U15: 46122 | V15: 46122 | W15: Allen | X15: Nil | Y15: Ethan | Z15: 46125 | AA15: What is the purpose of this iVBORw0KG check? | AB15: Given POV Comments: PNG File format is not worked | AC15: Approved | AD15: CRC: Request clarificatin and explain. There is no code change | AE15: Meets Expectation
A16: =ROW() - ROW(Table1456789101214161817222426283132333637394143454749515355575961[[#Headers],[S.No]]) - 1 -> 14 | B16: MSB Activities | C16: 46120 | D16: 46133 | E16: 26.5 Sprint S3 Stretch | F16: Allen | G16: 27160 | H16: Activities - Admin - Calendar Modal is not working properly, when we select year or month and then use scroll bar | I16: Defect Fixed | J16: 1 | M16: 46120 | N16: 46121 | O16: Done | P16: Ram | Q16: Nil | R16: Ram | S16: Nil | T16: https://dev.azure.com/heartlandschools/Activities/_git/Activities/pullrequest/48338 | U16: 46120 | V16: 46120 | W16: Allen | X16: Nil | Y16: Ethan | Z16: 46120 | AA16: Nil | AB16: NA | AC16: NA | AE16: Meets Expectation
A17: =ROW() - ROW(Table1456789101214161817222426283132333637394143454749515355575961[[#Headers],[S.No]]) - 1 -> 15 | B17: MSB Activities | C17: 46120 | D17: 46133 | E17: 26.5 Sprint S3 Stretch | F17: Athi | G17: 52885 | H17: Activities - Parent - Prevent parent from interacting with past program registrations | I17: Story Completed | J17: 2 | K17: 1 | L17: 4 | M17: 46128 | N17: 46128 | O17: Done | P17: Ram | Q17: Nil | R17: Ram | S17: Nil | T17: https://dev.azure.com/heartlandschools/Activities/_git/Activities/pullrequest/48501 | U17: 46129 | V17: 46129 | W17: Allen | X17: Nil | Y17: Ethan | Z17: 46129 | AA17: Nil | AB17: Approved | AC17: Approved | AE17: Meets Expectation
A18: =ROW() - ROW(Table1456789101214161817222426283132333637394143454749515355575961[[#Headers],[S.No]]) - 1 -> 16 | B18: MSB Activities | C18: 46120 | D18: 46133 | E18: 26.5 Sprint S3 Stretch | F18: Ram | G18: 52882 | H18: Activities - Parent - Disable Next button when no eligible students | I18: Product Owner - Verify | J18: 5 | K18: 1 | L18: 4 | M18: 46129 | N18: 46132 | O18: Done | P18: Athi | Q18: Nil | R18: Athi | S18: Nil | T18: NA | U18: NA | V18: NA | W18: NA | X18: NA | Y18: NA | Z18: NA | AA18: NA | AB18: NA | AC18: NA | AE18: Meets Expectation
A19: =ROW() - ROW(Table1456789101214161817222426283132333637394143454749515355575961[[#Headers],[S.No]]) - 1 -> 17 | B19: MSB Activities | C19: 46120 | D19: 46133 | E19: 26.5 Sprint S3 Stretch | F19: Allen | G19: 27212 | H19: Activities - Error running the Update Student Counts in the Dynamic Reports | I19: Defect Fixed | J19: 1 | M19: 46128 | N19: 46128 | O19: Done | P19: Athi | Q19: Nil | R19: Athi | S19: Nil | T19: https://dev.azure.com/heartlandschools/Activities/_git/Activities/pullrequest/48472 | U19: 46128 | V19: 46128 | W19: Allen | X19: Nil | Y19: Ethan | Z19: 46128 | AA19: Nil | AB19: NA | AC19: NA | AE19: Meets Expectation
A20: =ROW() - ROW(Table1456789101214161817222426283132333637394143454749515355575961[[#Headers],[S.No]]) - 1 -> 18 | B20: MSB Activities | C20: 46120 | D20: 46133 | E20: 26.5 Sprint S3 Stretch | F20: Athi | G20: 52883 | H20: Activities - Parent - Adjust registration status chip display [26.5?] | I20: Product Owner - Verify | J20: 3 | L20: 2 | M20: 46128 | N20: 46132 | O20: Done | P20: Ram | Q20: Nil | R20: Ram | S20: Nil | T20: NA | U20: NA | V20: NA | W20: NA | X20: NA | Y20: NA | Z20: NA | AA20: NA | AB20: NA | AC20: NA | AD20: NA | AE20: Meets Expectation

Sheet 26.5 Sprint 3 - Defects
A1: S.No | B1: Sprint # | C1: Story/Defect ID | D1: Parent Story | E1: Developer | F1: Issue Type | G1: Issue Description | H1: Root Cause Analysis | I1: Priority | J1: Defect Source | K1: Type | L1: Status | M1: Root Cause Category | N1: Comments | O1: Defect Raised
A2: 1 | B2: 26.5 Sprint S3 | C2: 26974 Activities - Parent - Enrollments count including withdrawn [26.5] | E2: Allen | F2: Defect | G2: As a parent, when I log in I am seeing programs my student was withdrawn from counted in the number of Enrollments on the landing page. | H2: Enrollment count is not showing accuretly , incorrect SQL query logic | I2: Minor | J2: Manual | K2: External | L2: Defect Fixed | M2: Existing_Issues | O2: Stakeholder
A3: 2 | B3: 26.5 Sprint S3 | C3: 52528 Activities - Admin - Universal & Global Search – Support for Special Characters | E3: Athinarayanan | F3: Bounceback/Sub-Defect | G3: Special Character [ ] brackets are not working for District Maintenance and FormType Screens, | H3: ] is not considered as escape literal in sql query | I3: Minor | J3: Manual | K3: Internal | L3: Defect Fixed | M3: Development | O3: Offshore QA - Manjunath
A4: 3 | B4: 26.5 Sprint S3 | C4: 27211 Activities - REGRESSION - Parent - DOB,School and Grade fields shown as modified while updating the registration | E4: Ramkumar | F4: Defect | G4: Defect:1 DOB, School, and Grade fields shown as modified while updating the registration. Defect 2: When we enter the text and place the cursor at the beginning of the text cursor automatically go to end of the text. So Couldn't enter the text continuously. | H4: Defect1 : Model validation , Defect 2 : Issue caused by text onchange event | I4: Minor | J4: Manual | K4: Internal | L4: Defect Fixed | M4: Development | O4: Offshore QA - Manjunath
A5: 4 | B5: 26.5 Sprint S3 | C5: 27171 - Activities - REGRESSION - Parent - Facing "haspendingUpdates" error while refreshing the screen | E5: Athinarayanan | F5: Defect | G5: Issue: Facing "haspendingUpdates" error while refreshing the screen. Issue2: When the ‘From Date’ field is cleared, the ‘To Date’ field is automatically populated with a date in Payment History Page. | H5: Null check is not handled | I5: Minor | J5: Manual | K5: Internal | L5: Defect Fixed | M5: Development | O5: Offshore QA - Manjunath
A6: 5 | B6: 26.5 Sprint S3 | C6: 27160 - Activities - Admin - Calendar Modal is not working properly, when we select year or month and then use scroll bar | E6: Allen | F6: Defect | G6: Calendar modal is not working properly, when we select year or month and then use the scroll bar the dropdown closes. This happens throughout the application where Calendar modal is applicable. (see video) | H6: Onchange event is not handled | I6: Minor | J6: Manual | K6: Internal | L6: Defect Fixed | M6: Development | O6: Offshore QA - Manjunath
A7: 6 | B7: 26.5 Sprint S3 | C7: 27217 Activities - REGRESSION - Parent - Calendar showing space above header | E7: Athinarayanan | F7: Defect | G7: With calendar turned on for parent. We are getting a space between the top of the container and the top of the SMTWTFS header. | H7: UI alignment is mismatch while scorll | I7: Minor | J7: Manual | K7: Internal | L7: Defect Fixed | M7: Development | O7: Onshore QA - Jeff
A8: 7 | B8: 26.5 Sprint S3 | C8: 27212 Activities - Error running the Update Student Counts in the Dynamic Reports | E8: Allen | F8: Defect | G8: The query needs to be updated after we changed the description column. This one was missed, and it now errors when running. | H8: Database upgrade | I8: Minor | J8: Manual | K8: External | L8: Defect Fixed | M8: Development | O8: Stakeholder
A9: 8 | B9: 26.5 Sprint S3 | C9: 27238 - Activities - Regression - Parent - Not able to see Screen "No Student Yet" when no student are available for a parent. | E9: Athinarayanan | F9: Defect | G9: Not able to see Screen "No Student Yet" when no student are available for a parent. | H9: Student count validation is missed | I9: Minor | J9: Manual | K9: Internal | L9: Defect Peer Review | M9: Development | N9: This defect found on end of the sprint, its low priority, and development effort is completed, test effort will be carry forward. | O9: Developer- Athinarayanan

Sheet 26.5 Sprint S2-Status
A1: S.No | B1: Application Name | C1: Sprint Start Date | D1: Sprint End Date | E1: Sprint | F1: Developer | G1: Story ID/Defect ID | H1: Description | I1: Status | J1: Estimated(sp) | K1: Actual(sp) | L1: Actual Hours Worklog | M1: Dev Start Date | N1: Dev End Date | O1: Unit testing | P1: Peer Tested By | Q1: Peer Tested Comments, if any | R1: Peer Reviewed By | S1: Peer Code Review Comments, if any | T1: PR Number/Link | U1: PR Created Date | V1: PR Approved Date | W1: Onsite Lead Code Review | X1: Onsite Lead Code Review Comments, if any | Y1: Client Code Review | Z1: PR Approved Date2 | AA1: Client Code Review Comments, if any | AB1: Internal PO -POV Comments | AC1: Client PO -POV Comments | AD1: Comments | AE1: Does this story Meet Expectations?
A3: =ROW() - ROW(Table1456789101214161817222426283132333637394143454749515355575961[[#Headers],[S.No]]) - 1 -> 1 | B3: MSB Activities | C3: 46106 | D3: 46119 | E3: 26.5 Sprint S2 | F3: Athi | G3: 52259 | H3: Activities - Kaleida - Update Parent Registration - Schedule Landing Updates | I3: Story Being Tested | J3: 5 | K3: 1 | L3: 2 | M3: 46092 | N3: 46104 | O3: Done | P3: Ram | Q3: Nil | R3: Ram | S3: Nil | T3: https://dev.azure.com/heartlandschools/Activities/_git/Activities/pullrequest/47981 | U3: 46105 | V3: 46105 | W3: Allen | X3: Nil | Y3: Ethan | Z3: 46106 | AA3: Nil | AB3: Approved. POV Comments: When two different calendar activities are scheduled, the system displays similar data for both, instead of distinct activity details. Download - Empty PDF is downloading | AC3: Approved. During POV additional scope is added to the story | AD3: This story is carry forward to next sprint due to team got blocker as all lower environment were down for two days during this sprint. So Test effort will be carry forward. | AE3: Meets Expectation
A4: =ROW() - ROW(Table1456789101214161817222426283132333637394143454749515355575961[[#Headers],[S.No]]) - 1 -> 2 | B4: MSB Activities | C4: 46106 | D4: 46119 | E4: 26.5 Sprint S2 | F4: Ram | G4: 27042 | H4: Activities - Kaleida - Parent Withdraw/Transferred UI - Verbiage Cutoff | I4: Defect Fixed | J4: 3 | K4: 1 | L4: 4 | M4: 46106 | N4: 46106 | O4: Done | P4: Athi | Q4: Nil | R4: Athi | S4: Nil | T4: https://dev.azure.com/heartlandschools/Activities/_git/Activities/pullrequest/48020 | U4: 46106 | V4: 46106 | W4: Allen | X4: Nil | Y4: Ethan | Z4: 46106 | AA4: Nil | AB4: NA | AC4: NA | AE4: Meets Expectation
A5: =ROW() - ROW(Table1456789101214161817222426283132333637394143454749515355575961[[#Headers],[S.No]]) - 1 -> 3 | B5: MSB Activities | C5: 46106 | D5: 46119 | E5: 26.5 Sprint S2 | F5: Allen | G5: 27051 | H5: Activities - Parent - Physician's Name field not allowing spaces | I5: Defect Fixed | J5: 2 | K5: 2 | L5: 4 | M5: 46106 | N5: 46106 | O5: Done | P5: Athi | Q5: Nil | R5: Ram | S5: Nil | T5: https://dev.azure.com/heartlandschools/Activities/_git/Activities/pullrequest/48027 | U5: 46106 | V5: 46106 | W5: Allen | X5: Nil | Y5: Ethan | Z5: 46106 | AA5: Nil | AB5: NA | AC5: NA | AE5: Meets Expectation
A6: =ROW() - ROW(Table1456789101214161817222426283132333637394143454749515355575961[[#Headers],[S.No]]) - 1 -> 4 | B6: MSB Activities | C6: 46106 | D6: 46119 | E6: 26.5 Sprint S2 | F6: Athi | G6: 52475 | H6: Activities - Kaleida - Admin Breadcrumbs [V1] | I6: Story Completed | J6: 3 | K6: 2 | L6: 6 | M6: 46106 | N6: 46106 | O6: Done | P6: Ram | Q6: Nil | R6: Ram | S6: Nil | T6: https://dev.azure.com/heartlandschools/Activities/_git/Activities/pullrequest/48088 | U6: 46108 | V6: 46111 | W6: Allen | X6: Nil | Y6: Ethan | Z6: 46111 | AA6: Nil | AB6: POV Comments: Breadcrumb is displaying wrongly 1. Activities > Edit > Displays Details 2. Enrollment Plan> Edit > EP name is missing 3. Roles> Edit > Role name missing 4.Security Groups> Edit> Display Details Suggestions: Include District Name for District Breadcrumb and Include View Job Request Queue and View Config props - Breadcrumb links. Approved | AC6: Approved | AE6: Meets Expectation
A7: =ROW() - ROW(Table1456789101214161817222426283132333637394143454749515355575961[[#Headers],[S.No]]) - 1 -> 5 | B7: MSB Activities | C7: 46106 | D7: 46119 | E7: 26.5 Sprint S2 | F7: Ram | G7: 52049 | H7: Activities - Kaleida - Update Parent Registration Design (Contacts) | I7: Story Completed | J7: 8 | K7: 7 | L7: 29 | M7: 46107 | N7: 46112 | O7: Done | P7: Athi | Q7: Nil | R7: Athi | S7: Nil | T7: https://dev.azure.com/heartlandschools/Activities/_git/Activities/pullrequest/48196 | U7: 46114 | V7: 46114 | W7: Allen | X7: Nil | Y7: Ethan | Z7: 46114 | AA7: Nil | AB7: POV comment: The delete modal popup is animated when clicking the delete contact icon. Approved | AC7: Approved | AE7: Meets Expectation
A8: =ROW() - ROW(Table1456789101214161817222426283132333637394143454749515355575961[[#Headers],[S.No]]) - 1 -> 6 | B8: MSB Activities | C8: 46106 | D8: 46119 | E8: 26.5 Sprint S2 | F8: Allen | G8: 52284 | H8: Activities - App Switcher - Show for HSS users at system level | I8: Story Completed | J8: 1 | K8: 1 | L8: 2 | M8: 46106 | N8: 46107 | O8: Done | P8: Ram | Q8: Nil | R8: Athi | S8: Nil | T8: https://dev.azure.com/heartlandschools/Activities/_git/Activities/pullrequest/48213 | U8: 46114 | V8: 46114 | W8: Allen | X8: Nil | Y8: Ethan | Z8: 46114 | AA8: Nil | AB8: Approved. | AC8: Approved. | AE8: Meets Expectation
A9: =ROW() - ROW(Table1456789101214161817222426283132333637394143454749515355575961[[#Headers],[S.No]]) - 1 -> 7 | B9: MSB Activities | C9: 46106 | D9: 46119 | E9: 26.5 Sprint S2 | F9: Allen | G9: 52432 | H9: Activities - Config Props - Add the ability to access config props at the system level | I9: Story Completed | J9: 3 | K9: 2 | L9: 9 | M9: 46106 | N9: 46108 | O9: Done | P9: Ram | Q9: Nil | R9: Athi | S9: Nil | T9: https://dev.azure.com/heartlandschools/Activities/_git/Activities/pullrequest/48213 | U9: 46114 | V9: 46114 | W9: Allen | X9: Nil | Y9: Ethan | Z9: 46115 | AA9: Should this be updated to use the GetGlobalConfigPropValue/GetConfigPropValue methods instead of the Tenant.ConfigPropCache.GetConfigPropValue method? Are there other areas within the application that need to be updated? Per the above suggestion, I don't think there is a reason to do the user check. I believe we should just be able to call to the GetGlobalConfigPropValue method regardless | AB9: POV comment: App switcher config props not working for following cases: 1. I haven’t configured the App Switcher in Config Props at both the system level and the tenant level , but the app tray icon is still showing for HSS User . 2. Set the config prop App Switcher false at district level, and true at system level and Log in as an HSS user, do not select any districts, go directly to HSS > Configprops page, and click the App Switcher icon — the app tray does not open. 3. Set the config prop App Switcher to true at both the system level and the tenant level for my Kanchana sandbox district. I could not see the App Switcher icon for the tenant-level. | AC9: Approved | AD9: We got sugesstion as CRC to add cache for system level config and remove the user check validation and call the mentioned methods | AE9: Meets Expectation
A10: =ROW() - ROW(Table1456789101214161817222426283132333637394143454749515355575961[[#Headers],[S.No]]) - 1 -> 8 | B10: MSB Activities | C10: 46106 | D10: 46119 | E10: 26.5 Sprint S2 | F10: Athi | G10: 52461 | H10: Activities - Kaleida - Update Parent Registration - Schedule Status indicator | I10: Story Being Tested | J10: 5 | K10: 3 | L10: 12 | M10: 46107 | N10: 46111 | O10: Done | P10: Ram | Q10: Nil | R10: Ram | S10: Nil | T10: https://dev.azure.com/heartlandschools/Activities/_git/Activities/pullrequest/48198 | U10: 46114 | V10: 46114 | W10: Allen | X10: Nil | Y10: Ethan | Z10: 46114 | AA10: Nil | AB10: POV comment: Incomplete and Complete status showing at the same time. Approved | AC10: Approved | AD10: This story is carry forward to next sprint due to team got blocker as all lower environment were down for two days during this sprint. So Test effort will be carry forward. | AE10: Meets Expectation
A11: =ROW() - ROW(Table1456789101214161817222426283132333637394143454749515355575961[[#Headers],[S.No]]) - 1 -> 9 | B11: MSB Activities | C11: 46106 | D11: 46119 | E11: 26.5 Sprint S2 | F11: Allen | G11: 52431 | H11: Activities - Admin - Calendar not displaying properly | I11: Story Completed | J11: 5 | K11: 3 | L11: 13 | M11: 46106 | N11: 46108 | O11: Done | P11: Ram | Q11: Nil | R11: Athi | S11: Nil | T11: https://dev.azure.com/heartlandschools/Activities/_git/Activities/pullrequest/48173 | U11: 46113 | V11: 46113 | W11: Allen | X11: Nil | Y11: Ethan | Z11: 46114 | AA11: Nil | AB11: POV comment: Opening the calendar does not close it when switching tabs. Approved | AC11: Approved | AE11: Meets Expectation
A12: =ROW() - ROW(Table1456789101214161817222426283132333637394143454749515355575961[[#Headers],[S.No]]) - 1 -> 10 | B12: MSB Activities | C12: 46106 | D12: 46119 | E12: 26.5 Sprint S2 Stretch | F12: Ram | G12: 52410 | H12: Activities - Admin - Preview EP Forms Errors | I12: Story Completed | J12: 3 | K12: 1 | L12: 4 | M12: 46114 | N12: 46115 | O12: Done | P12: Athi | Q12: Nil | R12: Athi | S12: Nil | T12: https://dev.azure.com/heartlandschools/Activities/_git/Activities/pullrequest/48219 | U12: 46115 | V12: 46115 | W12: Allen | X12: Nil | Y12: Ethan | Z12: 46115 | AA12: Nil | AB12: NA | AC12: NA | AE12: Meets Expectation
A13: =ROW() - ROW(Table1456789101214161817222426283132333637394143454749515355575961[[#Headers],[S.No]]) - 1 -> 11 | B13: MSB Activities | C13: 46106 | D13: 46119 | E13: 26.5 Sprint S2 Stretch | F13: Allen | G13: 52480 | H13: Activities - Parent - Land on Enrollments page after submitting a registration | I13: Story Being Tested | J13: 2 | K13: 1 | L13: 1 | M13: 46113 | N13: 46113 | O13: Done | P13: Athi | Q13: Nil | R13: Athi | S13: Nil | T13: https://dev.azure.com/heartlandschools/Activities/_git/Activities/pullrequest/48250 | U13: 46118 | V13: 46118 | W13: Allen | X13: Nil | Y13: Ethan | Z13: 46118 | AA13: Nil | AB13: Approved. | AC13: Approved. | AE13: Meets Expectation
A14: =ROW() - ROW(Table1456789101214161817222426283132333637394143454749515355575961[[#Headers],[S.No]]) - 1 -> 12 | B14: MSB Activities | C14: 46106 | D14: 46119 | E14: 26.5 Sprint S2 Stretch | F14: Athi | G14: 52048 | H14: Activities - Admin - Redirect buttons to previous screens | I14: Product Owner - Verify | J14: 5 | K14: 3 | L14: 12.5 | M14: 46112 | N14: 46114 | O14: Done | P14: Ram | Q14: Nil | R14: Ram | S14: Nil | T14: NA | U14: NA | V14: NA | W14: NA | X14: NA | Y14: NA | Z14: NA | AA14: NA | AB14: Pending | AC14: Pending | AE14: Meets Expectation

Sheet 26.5 Sprint 2 - Defects
A1: S.No | B1: Sprint # | C1: Story/Defect ID | D1: Parent Story | E1: Developer | F1: Issue Type | G1: Issue Description | H1: Root Cause Analysis | I1: Priority | J1: Defect Source | K1: Type | L1: Status | M1: Root Cause Category | N1: Comments | O1: Defect Raised
A2: 1 | B2: 26.5 Sprint S2 | C2: 27051 Activities - Parent - Physician's Name field not allowing spaces | E2: Ram | F2: Defect | G2: As a logged in parent registering their student for an Enrollment Plan with the Physician's Name Stock Custom Field set as required, I am unable to enter a full name (First and Last Names) because I am not able to use spaces. | H2: We removed the space in the entered text to handle the field validations in the UI | I2: Minor | J2: Manual | K2: Internal | L2: Defect Fixed | M2: Development | O2: Onshore PO - Kristy
A3: 2 | B3: 26.5 Sprint S2 | C3: 27042 Activities - Kaleida - Parent Withdraw/Transferred UI - Verbiage Cutoff | E3: Ram | F3: Defect | G3: Withdraw/Transferred - Displayed in the new design, but the verbiage cutoff; needs to be greyed out, and the checkbox should either be disabled or hidden. | H3: This verbiage text needs to remove and use the vegachip . Its UI change request. | I3: Minor | J3: Manual | K3: Internal | L3: Defect Fixed | M3: Development | O3: Offshore PO - Kanchana
A4: 3 | B4: 26.5 Sprint S3 | C4: 26974 Activities - Parent - Enrollments count including withdrawn [26.5] | E4: Allen | F4: Defect | G4: As a parent, when I log in I am seeing programs my student was withdrawn from counted in the number of Enrollments on the landing page. | H4: Enrollment count is not showing accuretly , incorrect SQL query logic | I4: Minor | J4: Manual | K4: External | L4: Defect Verified | M4: Existing_Issues | N4: This defect is added on stretch with low priority, which is carry forwarded to next sprint main commit | O4: Stakeholder

Sheet 26.5 Sprint S1-Status
A1: S.No | B1: Application Name | C1: Sprint Start Date | D1: Sprint End Date | E1: Sprint | F1: Developer | G1: Story ID/Defect ID | H1: Description | I1: Status | J1: Estimated(sp) | K1: Actual(sp) | L1: Actual Hours Worklog | M1: Dev Start Date | N1: Dev End Date | O1: Unit testing | P1: Peer Tested By | Q1: Peer Tested Comments, if any | R1: Peer Reviewed By | S1: Peer Code Review Comments, if any | T1: PR Number/Link | U1: PR Created Date | V1: PR Approved Date | W1: Onsite Lead Code Review | X1: Onsite Lead Code Review Comments, if any | Y1: Client Code Review | Z1: PR Approved Date2 | AA1: Client Code Review Comments, if any | AB1: Internal PO -POV Comments | AC1: Client PO -POV Comments | AD1: Comments | AE1: Does this story Meet Expectations?
A2: =ROW() - ROW(Table14567891012141618172224262831323336373941434547495153555759[[#Headers],[S.No]]) - 1 -> 0
A3: =ROW() - ROW(Table14567891012141618172224262831323336373941434547495153555759[[#Headers],[S.No]]) - 1 -> 1 | B3: MSB Activities | C3: 46092 | D3: 46105 | E3: 26.5 Sprint S1 | F3: Ram | G3: 51885 | H3: Activities - Kaleida - Update Parent Registration - Add/Edit Student Info [26.5] | I3: Story Completed | J3: 2 | K3: 2 | L3: 7 | M3: 46078 | N3: 46084 | O3: Done | P3: Athi | Q3: Nil | R3: Athi | S3: Nil | T3: https://dev.azure.com/heartlandschools/Activities/_git/Activities/pullrequest/47558 | U3: 46086 | V3: 46087 | W3: Allen | X3: Nil | Y3: Ethan | Z3: 46090 | AA3: Remove unused imports | AB3: Approved. | AC3: Approved. | AD3: CRC Suggestion : Which requested to remove unused imports | AE3: Meets Expectation
A4: =ROW() - ROW(Table14567891012141618172224262831323336373941434547495153555759[[#Headers],[S.No]]) - 1 -> 2 | B4: MSB Activities | C4: 46092 | D4: 46105 | E4: 26.5 Sprint S1 | F4: Ram | G4: 51671 | H4: Activities - Kaleida - Update Parent Registration Design (Your Info) | I4: Story Completed | J4: 5 | K4: 4 | L4: 17.5 | M4: 46094 | N4: 46097 | O4: Done | P4: Athi | Q4: Nil | R4: Athi | S4: Nil | T4: https://dev.azure.com/heartlandschools/Activities/_git/Activities/pullrequest/47829 | U4: 46097 | V4: 46097 | W4: Allen | X4: Nil | Y4: Ethan | Z4: 46097 | AA4: Nil | AB4: Nil | AC4: Nil | AD4: Nil | AE4: Meets Expectation
A5: =ROW() - ROW(Table14567891012141618172224262831323336373941434547495153555759[[#Headers],[S.No]]) - 1 -> 3 | B5: MSB Activities | C5: 46092 | D5: 46105 | E5: 26.5 Sprint S1 | F5: Athi | G5: 52259 | H5: Activities - Kaleida - Update Parent Registration - Schedule Landing Updates | I5: Story Peer Review | J5: 8 | K5: 7 | L5: 28 | M5: 46092 | N5: 46104 | O5: Done | P5: Ram | Q5: Nil | R5: Ram | S5: Nil | T5: https://dev.azure.com/heartlandschools/Activities/_git/Activities/pullrequest/47981 | U5: 46105 | V5: NA | W5: NA | X5: NA | Y5: NA | Z5: NA | AA5: NA | AB5: Approved. POV Comments: When two different calendar activities are scheduled, the system displays similar data for both, instead of distinct activity details. Download - Empty PDF is downloading | AC5: Approved. During POV additional scope is added to the story | AD5: This story is being carried forward to the testing phase only due to a last-minute design change request that modified the originally accepted design specifications and acceptance criteria.The client stakeholder has been informed and acknowledges the current status and the revised scope resulting from the design change | AE5: Meets Expectation
A6: =ROW() - ROW(Table14567891012141618172224262831323336373941434547495153555759[[#Headers],[S.No]]) - 1 -> 4 | B6: MSB Activities | C6: 46092 | D6: 46105 | E6: 26.5 Sprint S1 | F6: Allen | G6: 26946 | H6: Activites - Admin - Bulk Copy/Edit Selector issues | I6: Defect Fixed | J6: 1 | K6: 1 | L6: 0.5 | M6: 46090 | N6: 46090 | O6: Done | P6: Athi | Q6: Nil | R6: Athi | S6: Nil | T6: https://dev.azure.com/heartlandschools/Activities/_git/Activities/pullrequest/47708 | U6: 46090 | V6: 46091 | W6: Allen | X6: Nil | Y6: Ethan | Z6: 46091 | AA6: Nil | AB6: NA | AC6: NA | AE6: Meets Expectation
A7: =ROW() - ROW(Table14567891012141618172224262831323336373941434547495153555759[[#Headers],[S.No]]) - 1 -> 5 | B7: MSB Activities | C7: 46092 | D7: 46105 | E7: 26.5 Sprint S1 | F7: Allen | G7: 51918 | H7: Activities - Admin - Remove Header Text from Registrations Table Grid [26.5] | I7: Story Completed | J7: 1 | K7: 1 | L7: 4 | M7: 46078 | N7: 46078 | O7: Done | P7: Ram | Q7: Nil | R7: Ram | S7: Nil | T7: https://dev.azure.com/heartlandschools/Activities/_git/Activities/pullrequest/47545 | U7: 46083 | V7: 46083 | W7: Allen | X7: Nil | Y7: Andy | Z7: 46084 | AA7: Nil | AB7: Approved | AC7: Approved | AE7: Meets Expectation
A8: =ROW() - ROW(Table14567891012141618172224262831323336373941434547495153555759[[#Headers],[S.No]]) - 1 -> 6 | B8: MSB Activities | C8: 46092 | D8: 46105 | E8: 26.5 Sprint S1 | F8: Allen | G8: 52010 | H8: Activities - Admin - Parent Accounts - Registrations Tab > Status (Pending, Waitlisted) Navigate to the Review page [26.5] | I8: Story Completed | J8: 1 | K8: 1 | L8: 4 | M8: 46078 | N8: 46079 | O8: Done | P8: Athi | Q8: Nil | R8: Ram | S8: Nil | T8: https://dev.azure.com/heartlandschools/Activities/_git/Activities/pullrequest/47566 | U8: 46083 | V8: 46083 | W8: Allen | X8: Nil | Y8: Andy | Z8: 46084 | AA8: 1. Both sides of the result of this conditional operator look the same outside of casing, IsActiveTerm (uppercase i) and isActiveTerm (lowercase i). Looking at the model it seems like we should be using isActiveTerm, is there a reason I'm not considering that we need this check? If we're getting the incorrect casing coming back from the API we may need to add [JsonProperty("isActiveTerm") to the property declaration or otherwise correct the issue from the server. 2. Similar question here as above, were you seeing inconsistent casing from the server? I think we're missing the [JsonProperty(...) attribute on the server side model declaration if that is the case | AB8: If the term is inactive but the registration is still pending or waitlisted, should we redirect to the Registrations Review page, or continue redirecting to the View All page (as per our current behavior)? Approved | AC8: Include: "This Registration is no longer valid, as it is not associated with an active program." | AD8: Both observations from the CRC are hereby noted as suggestive improvements. The recommendations encompass: (i) case sensitivity validation, and (ii) JSON attribute integration within the Modal component. This user story is designated for delivery in Release 26.5. | AE8: Meets Expectation
A9: =ROW() - ROW(Table14567891012141618172224262831323336373941434547495153555759[[#Headers],[S.No]]) - 1 -> 7 | B9: MSB Activities | C9: 46092 | D9: 46105 | E9: 26.5 Sprint S1 | F9: Allen | G9: 26913 | H9: Activities - Admin - Preview EP Forms Errors | I9: Defect Rejected | J9: 2 | K9: 2 | L9: 8 | M9: 46093 | N9: 46094 | O9: NA | P9: NA | Q9: NA | R9: NA | S9: NA | T9: NA | U9: NA | V9: NA | W9: NA | X9: NA | Y9: NA | Z9: NA | AA9: NA | AB9: NA | AC9: NA | AD9: This defect will be consider as new feature in next sprint as a story based on our analysis. So this defect is rejected now. | AE9: Meets Expectation
A10: =ROW() - ROW(Table14567891012141618172224262831323336373941434547495153555759[[#Headers],[S.No]]) - 1 -> 8 | B10: MSB Activities | C10: 46092 | D10: 46105 | E10: 26.5 Sprint S1 | F10: Athi | G10: 43597 | H10: Activities - Admin - Universal Search for Student Purchases | I10: Story Completed | J10: 2 | M10: 46083 | N10: 46087 | O10: Done | P10: Ram | Q10: NA | R10: Ram | S10: Nil | T10: https://dev.azure.com/heartlandschools/Activities/_git/Activities/pullrequest/47858 | U10: 46098 | V10: 46098 | W10: Allen | X10: Nil | Y10: Andy | Z10: 46098 | AA10: Nil | AB10: The drop-down list shows ‘Loading...’ when there is no data for Purchase and Student universal search. However, in the Staging/PROD environments, this issue does not occur in Universal Search for Student. I can see it in DEV and QA. Common search is only retrieving data for the enrollment plan & Amount column and not for other columns (Purchase Date, Period). I am getting a ‘Forbidden’ error when I search using Start Date and End Date in the dev environment. | AC10: update placeholder text to "Search Purchases" (capitalize the P in purchases) | AD10: This Internal POV comment will not covered in the story scope, will be addressed in another story | AE10: Meets Expectation
A11: =ROW() - ROW(Table14567891012141618172224262831323336373941434547495153555759[[#Headers],[S.No]]) - 1 -> 9 | B11: MSB Activities | C11: 46092 | D11: 46105 | E11: 26.5 Sprint S1 | F11: Allen | G11: 52069 | H11: Activities - Admin - Calendar not displaying properly (DISCOVERY) | I11: Story Completed | J11: 3 | K11: 3 | L11: 15 | M11: NA | N11: NA | O11: NA | P11: NA | Q11: NA | R11: NA | S11: NA | T11: NA | U11: NA | V11: NA | W11: NA | X11: NA | Y11: NA | Z11: NA | AA11: NA | AB11: NA | AC11: NA | AD11: This is discovery story | AE11: Meets Expectation
A12: =ROW() - ROW(Table14567891012141618172224262831323336373941434547495153555759[[#Headers],[S.No]]) - 1 -> 10 | B12: MSB Activities | C12: 46092 | D12: 46105 | E12: 26.5 Sprint S1 | F12: Athi | G12: 52248 | H12: Activities - Kaleida - Admin Breadcrumbs | I12: Story Completed | J12: 3 | M12: 46078 | N12: 46079 | O12: Done | P12: Ram | Q12: Nil | R12: Ram | S12: Nil | T12: https://dev.azure.com/heartlandschools/Activities/_git/Activities/pullrequest/47574 | U12: 46086 | V12: 46090 | W12: Allen | X12: Nil | Y12: Ethan | Z12: 46090 | AA12: Should this have a breadcrumbCaption? Could you change the caption value as well? Curiosity question: Are we displaying the text "EnrollmentName" to end users? If so, is there a reason it is that format instead of "Enrollment Name" (space between the words)? Is this the correct breadcrumbCaption? Most have been shorter/same length as the caption, but this one is longer? Is this the correct breadcrumbCaption? Most have been shorter/same length as the caption, but this one is longer? | AB12: Given POV comments for few section . Approved | AC12: Approved | AD12: Ethan, as a new member of the team, inquired about these changes, and we provided him with a detailed explanation of the requirements. | AE12: Meets Expectation
A13: =ROW() - ROW(Table14567891012141618172224262831323336373941434547495153555759[[#Headers],[S.No]]) - 1 -> 11 | B13: MSB Activities | C13: 46092 | D13: 46105 | E13: 26.5 Sprint S1 Stretch | F13: Ram | G13: 52049 | H13: Activities - Kaleida - Update Parent Registration Design (Contacts) | I13: Story Being Developed | J13: 8 | K13: 1 | L13: 2 | M13: 46100 | N13: NA | O13: NA | P13: NA | Q13: NA | R13: NA | S13: NA | T13: NA | U13: NA | V13: NA | W13: NA | X13: NA | Y13: NA | Z13: NA | AA13: NA | AB13: NA | AC13: NA
A14: =ROW() - ROW(Table14567891012141618172224262831323336373941434547495153555759[[#Headers],[S.No]]) - 1 -> 12 | B14: MSB Activities | C14: 46092 | D14: 46105 | E14: 26.5 Sprint S1 Stretch | F14: Allen | G14: 52353 | H14: Activities - Config Props - Add the ability to access config props at the system level (DISCOVERY) | I14: Story Completed | J14: 3 | M14: 46076 | O14: NA | P14: NA | Q14: NA | R14: NA | S14: NA | T14: NA | U14: NA | V14: NA | W14: NA | X14: NA | Y14: NA | Z14: NA | AA14: NA | AB14: NA | AC14: NA | AD14: This is discovery story

Sheet 26.5 Sprint 1 - Defects
A1: S.No | B1: Sprint # | C1: Story/Defect ID | D1: Parent Story | E1: Developer | F1: Issue Type | G1: Issue Description | H1: Root Cause Analysis | I1: Priority | J1: Defect Source | K1: Type | L1: Status | M1: Root Cause Category | N1: Comments | O1: Defect Raised
A2: 1 | B2: 26.5 Sprint S1 | C2: 43597 Activities - Admin - Universal Search for Student Purchases | D2: 43597 | E2: Athinarayanan | F2: Bounceback/Sub-Defect | G2: Numeric values are not searchable for student purchases. | H2: Numeric values considered for amount feild by conditional, now its optimized to support all feild | I2: Significant | J2: Manual | K2: Internal | L2: Defect Fixed | M2: Development | O2: OffShore QA - Manjunath
A3: 2 | B3: 26.5 Sprint S1 | C3: 43597 Activities - Admin - Universal Search for Student Purchases | D3: 43597 | E3: Athinarayanan | F3: Bounceback/Sub-Defect | G3: Able to see JSON format if we search with start date and end date. | H3: JSON Format as Searhc keyword | I3: Minor | J3: Manual | K3: Internal | L3: Defect Fixed | M3: Development | O3: OffShore QA - Manjunath

Sheet 26.3 Sprint S3-Status
A1: S.No | B1: Application Name | C1: Sprint Start Date | D1: Sprint End Date | E1: Sprint | F1: Developer | G1: Story ID/Defect ID | H1: Description | I1: Status | J1: Estimated(sp) | K1: Actual(sp) | L1: Actual Hours Worklog | M1: Dev Start Date | N1: Dev End Date | O1: Unit testing | P1: Peer Tested By | Q1: Peer Tested Comments, if any | R1: Peer Reviewed By | S1: Peer Code Review Comments, if any | T1: PR Number/Link | U1: PR Created Date | V1: PR Approved Date | W1: Onsite Lead Code Review | X1: Onsite Lead Code Review Comments, if any | Y1: Client Code Review | Z1: PR Approved Date2 | AA1: Client Code Review Comments, if any | AB1: Internal PO -POV Comments | AC1: Client PO -POV Comments | AD1: Comments | AE1: Does this story Meet Expectations?
A2: =ROW() - ROW(Table145678910121416181722242628313233363739414345474951535557[[#Headers],[S.No]]) - 1 -> 0
A3: =ROW() - ROW(Table145678910121416181722242628313233363739414345474951535557[[#Headers],[S.No]]) - 1 -> 1 | B3: MSB Activities | C3: 46078 | D3: 46091 | E3: 26.3 Sprint S3 | F3: Allen | G3: 52039 | H3: Activities - App Switcher - Hide button until script loads | I3: Story Completed | J3: 1 | K3: 1 | L3: 2 | M3: 46078 | N3: 46078 | O3: Done | P3: Ram | Q3: Nil | R3: Athi | S3: Nil | T3: https://dev.azure.com/heartlandschools/Activities/_git/Activities/pullrequest/47470 https://dev.azure.com/heartlandschools/Activities/_git/Activities/pullrequest/47440 | U3: 46078 | V3: 46078 | W3: Allen | X3: Nil | Y3: Andy | Z3: 46078 | AA3: Nil | AB3: NA | AC3: NA | AE3: Meets Expectation
A4: =ROW() - ROW(Table145678910121416181722242628313233363739414345474951535557[[#Headers],[S.No]]) - 1 -> 2 | B4: MSB Activities | C4: 46078 | D4: 46091 | E4: 26.3 Sprint S3 | F4: Athi | G4: 51662 | H4: Activities - Kaleida - Admin Breadcrumbs [26.5] (Timeboxed) | I4: Story Completed | J4: 5 | K4: 5 | L4: 20 | M4: 46078 | N4: 46079 | O4: Done | P4: Ram | Q4: Nil | R4: Ram | S4: Nil | T4: https://dev.azure.com/heartlandschools/Activities/_git/Activities/pullrequest/47574 | U4: 46086 | V4: 46090 | W4: Allen | X4: Nil | Y4: Ethan | Z4: 46090 | AA4: Nil | AB4: Given POV comments for few section . | AC4: Approved | AD4: Hold for 26.5 Release and it is regression sprint | AE4: Meets Expectation
A5: =ROW() - ROW(Table145678910121416181722242628313233363739414345474951535557[[#Headers],[S.No]]) - 1 -> 3 | B5: MSB Activities | C5: 46078 | D5: 46091 | E5: 26.3 Sprint S3 | F5: Allen | G5: 26866 | H5: Activities - Regression - Admin - Facing an error in the Converted Table Grid Audit Log | I5: Defect Fixed | J5: 0 | K5: 1 | L5: 4 | M5: 46080 | N5: 46108 | O5: Done | P5: Athi | Q5: Nil | R5: Athi | S5: Nil | T5: https://dev.azure.com/heartlandschools/Activities/_git/Activities/pullrequest/47536 | U5: 46080 | V5: 46080 | W5: Allen | X5: Nil | Y5: Andy | Z5: 46080 | AA5: Nil | AB5: NA | AC5: NA | AE5: Meets Expectation
A6: =ROW() - ROW(Table145678910121416181722242628313233363739414345474951535557[[#Headers],[S.No]]) - 1 -> 4 | B6: MSB Activities | C6: 46078 | D6: 46091 | E6: 26.3 Sprint S3 | F6: Allen/Ram | G6: 26875 | H6: Activities - Regression - Admin - Open operating days default sort, sorting incorrectly | I6: Defect Fixed | J6: 0 | K6: 1 | L6: 1 | M6: 46085 | N6: 46085 | O6: Done | P6: Athi | Q6: Nil | R6: Ram | S6: Nil | T6: https://dev.azure.com/heartlandschools/Activities/_git/Activities/pullrequest/47601 | U6: 46085 | V6: 46085 | W6: Allen | X6: Nil | Y6: Ethan | Z6: 46085 | AA6: Nil | AB6: NA | AC6: NA | AE6: Meets Expectation
A7: =ROW() - ROW(Table145678910121416181722242628313233363739414345474951535557[[#Headers],[S.No]]) - 1 -> 5 | B7: MSB Activities | C7: 46078 | D7: 46091 | E7: 26.3 Sprint S3 | F7: Allen | G7: 26914 | H7: Activities - Regression - Admin > Setup - Some of the icons are off center | I7: Defect Fixed | J7: 0 | K7: 1 | L7: 2 | M7: 46087 | N7: 46087 | O7: Done | P7: Athi | Q7: Nil | R7: Ram | S7: Nil | T7: https://dev.azure.com/heartlandschools/Activities/_git/Activities/pullrequest/47659 | U7: 46087 | V7: 46087 | W7: Allen | X7: Nil | Y7: Ethan | Z7: 46088 | AA7: Nil | AB7: NA | AC7: NA | AE7: Meets Expectation
A8: =ROW() - ROW(Table145678910121416181722242628313233363739414345474951535557[[#Headers],[S.No]]) - 1 -> 6 | B8: MSB Activities | C8: 46078 | D8: 46091 | E8: 26.3 Sprint S3 Stretch | F8: Ram | G8: 51885 | H8: Activities - Kaleida - Update Parent Registration - Add/Edit Student Info [26.5] | I8: Story Ready For Testing | J8: 8 | K8: 7 | L8: 30 | M8: 46078 | N8: 46084 | O8: Done | P8: Athi | Q8: Nil | R8: Athi | S8: Nil | T8: https://dev.azure.com/heartlandschools/Activities/_git/Activities/pullrequest/47558 | U8: 46086 | V8: 46087 | W8: Allen | X8: Nil | Y8: Ethan | Z8: 46090 | AA8: Remove unused imports | AB8: Nil | AC8: Nil | AD8: CRC Suggestion : Which requested to remove unused imports Hold for 26.5 Release | AE8: Meets Expectation
A9: =ROW() - ROW(Table145678910121416181722242628313233363739414345474951535557[[#Headers],[S.No]]) - 1 -> 7 | B9: MSB Activities | C9: 46078 | D9: 46091 | E9: 26.3 Sprint S3 Stretch | F9: Allen | G9: 51918 | H9: Activities - Admin - Remove Header Text from Registrations Table Grid [26.5] | I9: Story Ready For Testing | J9: 1 | K9: 1 | L9: 2 | M9: 46078 | N9: 46078 | O9: Done | P9: Ram | Q9: Nil | R9: Ram | S9: Nil | T9: https://dev.azure.com/heartlandschools/Activities/_git/Activities/pullrequest/47545 | U9: 46083 | V9: 46083 | W9: Allen | X9: Nil | Y9: Andy | Z9: 46084 | AA9: Nil | AB9: Approved | AC9: Approved | AD9: Hold for 26.5 Release | AE9: Meets Expectation
A10: =ROW() - ROW(Table145678910121416181722242628313233363739414345474951535557[[#Headers],[S.No]]) - 1 -> 8 | B10: MSB Activities | C10: 46078 | D10: 46091 | E10: 26.3 Sprint S3 Stretch | F10: Allen | G10: 52010 | H10: Activities - Admin - Parent Accounts - Registrations Tab > Status (Pending, Waitlisted) Navigate to the Review page [26.5] | I10: Story Ready For Testing | J10: 5 | K10: 2 | L10: 8 | M10: 46078 | N10: 46079 | O10: Done | P10: Athi | Q10: Nil | R10: Ram | S10: Nil | T10: https://dev.azure.com/heartlandschools/Activities/_git/Activities/pullrequest/47566 | U10: 46083 | V10: 46083 | W10: Allen | X10: Nil | Y10: Andy | Z10: 46084 | AA10: 1. Both sides of the result of this conditional operator look the same outside of casing, IsActiveTerm (uppercase i) and isActiveTerm (lowercase i). Looking at the model it seems like we should be using isActiveTerm, is there a reason I'm not considering that we need this check? If we're getting the incorrect casing coming back from the API we may need to add [JsonProperty("isActiveTerm") to the property declaration or otherwise correct the issue from the server. 2. Similar question here as above, were you seeing inconsistent casing from the server? I think we're missing the [JsonProperty(...) attribute on the server side model declaration if that is the case | AB10: If the term is inactive but the registration is still pending or waitlisted, should we redirect to the Registrations Review page, or continue redirecting to the View All page (as per our current behavior)? Approved | AC10: Include: "This Registration is no longer valid, as it is not associated with an active program." | AD10: Both observations from the CRC are hereby noted as suggestive improvements. The recommendations encompass: (i) case sensitivity validation, and (ii) JSON attribute integration within the Modal component. This user story is designated for delivery in Release 26.5. | AE10: Meets Expectation
A11: =ROW() - ROW(Table145678910121416181722242628313233363739414345474951535557[[#Headers],[S.No]]) - 1 -> 9 | B11: MSB Activities | C11: 46078 | D11: 46091 | E11: 26.3 Sprint S3 Stretch | F11: Athi | G11: 43597 | H11: Activities - Admin - Universal Search for Student Purchases [26.5] | I11: Product Owner - Verify | J11: 5 | K11: 5 | L11: 20 | M11: 46083 | N11: 46087 | O11: Done | P11: Ram | Q11: NA | R11: Ram | S11: Nil | T11: NA | U11: NA | V11: NA | W11: NA | X11: NA | Y11: NA | Z11: NA | AA11: NA | AB11: NA | AC11: NA | AD11: POV and QA will be carry forward to next sprint.Target to 26.5 Release | AE11: Meets Expectation
A12: =ROW() - ROW(Table145678910121416181722242628313233363739414345474951535557[[#Headers],[S.No]]) - 1 -> 10 | B12: MSB Activities | C12: 46078 | D12: 46091 | E12: 26.3 Sprint S3 Stretch | F12: Allen | G12: 52070 | H12: Activities - Parent - API token expiring before user session [26.5] | I12: Story Completed | J12: 5 | K12: 3 | L12: 12 | M12: 46078 | N12: 46084 | O12: NA | P12: NA | Q12: NA | R12: NA | S12: NA | T12: NA | U12: NA | V12: NA | W12: NA | X12: NA | Y12: NA | Z12: NA | AA12: NA | AB12: NA | AC12: NA | AD12: This issue could not be reproduced in the QA environment or other environments, with the issue observed only in the development environment. Consequently, this story will be closed. | AE12: Meets Expectation
A13: =ROW() - ROW(Table145678910121416181722242628313233363739414345474951535557[[#Headers],[S.No]]) - 1 -> 11 | B13: MSB Activities | C13: 46078 | D13: 46091 | E13: 26.3 Sprint S3 Stretch | F13: Athi | G13: 52219 | H13: Activities - Kaleida - Parent Registration Design Schedule w/o Calendar Updates (DISCOVERY) [Timebox] | I13: Story Completed | J13: 1 | K13: 1 | L13: 4 | M13: 46091 | N13: 46091 | O13: NA | P13: NA | Q13: NA | R13: NA | S13: NA | T13: NA | U13: NA | V13: NA | W13: NA | X13: NA | Y13: NA | Z13: NA | AA13: NA | AB13: NA | AC13: NA | AD13: The Discovery document and points added in the story note section
A14: =ROW() - ROW(Table145678910121416181722242628313233363739414345474951535557[[#Headers],[S.No]]) - 1 -> 12 | B14: MSB Activities | C14: 46078 | D14: 46091 | E14: 26.3 Sprint S3 Stretch | F14: Allen | G14: 26946 | H14: Activites - Admin - Bulk Copy/Edit Selector issues | I14: Defect Being Fixed | J14: 1 | K14: 1 | L14: 0.5 | M14: 46090 | N14: 46090 | O14: Done | P14: Athi | Q14: Nil | R14: Athi | S14: Nil | T14: https://dev.azure.com/heartlandschools/Activities/_git/Activities/pullrequest/47708 | U14: 46090 | V14: 46091 | W14: Allen | X14: Nil | Y14: Ethan | Z14: NA | AA14: NA | AB14: NA | AC14: NA | AD14: Carried to next sprint Main commit

Sheet 26.3 Sprint 3 - Defects
A1: S.No | B1: Sprint # | C1: Story/Defect ID | D1: Parent Story | E1: Developer | F1: Issue Type | G1: Issue Description | H1: Root Cause Analysis | I1: Priority | J1: Defect Source | K1: Type | L1: Status | M1: Root Cause Category | N1: Comments | O1: Defect Raised
A2: 1 | B2: 26.3 Sprint S3 | C2: 26866 Activities - Regression - Admin - Facing an error in the Converted Table Grid Audit Log | E2: Allen | F2: Defect | G2: Facing an error while clicking on the audit log for the converted table grid . Following are the pages 1.Activities. 2.Form type. 3.Student maintenance. 4.Custom Field Maintenance. | H2: Missed the Data test id in the custom data grid component | I2: Significant | J2: Manual | K2: Internal | L2: Defect Fixed | M2: Development | O2: OffShore Dev - Athinarayanan
A3: 2 | B3: 26.3 Sprint S3 | C3: 26875 Activities - Regression - Admin - Open operating days default sort, sorting incorrectly | E3: Athinarayanan | F3: Defect | G3: The default sorting for the district level open operating days should by default sort by the newest day to the oldest day | H3: We had primary sorting initially and now we are implementing secondary sorting as well | I3: Minor | J3: Manual | K3: External | L3: Defect Fixed | M3: Existing_Issues | N3: Existing PROD Issue. | O3: OffShore PO- Kanchana
A4: 3 | B4: 26.3 Sprint S3 | C4: 26914 Activities - Regression - Admin > Setup - Some of the icons are off center | E4: Allen | F4: Defect | G4: On the Admin > Setup page, some of the icons are slightly off center. Specifically, the Fee Items, Custom Fields, and Kiosk Maintenance icons have this issue. | H4: Tiles Icons is not aligned centerly. | I4: Minor | J4: Manual | K4: External | L4: Defect Fixed | M4: Existing_Issues | N4: Existing PROD Issue. | O4: Onsite Manager - Ethan Coggin
A5: 4 | B5: 26.3 Sprint S3 Stretch | C5: 26946 - Activites - Admin - Bulk Copy/Edit Selector issues | E5: Allen | F5: Defect | G5: We Internally found a couple issues with the selector for bulk copy/edit (see videos) | H5: Existing production issue | I5: Minor | J5: Manual | K5: External | L5: Defect Being Fixed | M5: Existing_Issues | N5: Existing PROD Issue. Carry to next sprint | O5: Onsite lead - Allen Xavier

Sheet 26.3 Sprint S2-Status
A1: S.No | B1: Application Name | C1: Sprint Start Date | D1: Sprint End Date | E1: Sprint | F1: Developer | G1: Story ID/Defect ID | H1: Description | I1: Status | J1: Estimated(sp) | K1: Actual(sp) | L1: Actual Hours Worklog | M1: Dev Start Date | N1: Dev End Date | O1: Unit testing | P1: Peer Tested By | Q1: Peer Tested Comments, if any | R1: Peer Reviewed By | S1: Peer Code Review Comments, if any | T1: PR Number/Link | U1: PR Created Date | V1: PR Approved Date | W1: Onsite Lead Code Review | X1: Onsite Lead Code Review Comments, if any | Y1: Client Code Review | Z1: PR Approved Date2 | AA1: Client Code Review Comments, if any | AB1: Internal PO -POV Comments | AC1: Client PO -POV Comments | AD1: Comments | AE1: Does this story Meet Expectations?
A2: =ROW() - ROW(Table1456789101214161817222426283132333637394143454749515355[[#Headers],[S.No]]) - 1 -> 0
A3: =ROW() - ROW(Table1456789101214161817222426283132333637394143454749515355[[#Headers],[S.No]]) - 1 -> 1 | B3: MSB Activities | C3: 46064 | D3: 46077 | E3: 26.3 Sprint S2 | F3: Allen | G3: 51752 | H3: Activities - Admin - Filter Completed with Errors in JobRequest DataGrid | I3: Story Completed | J3: 1 | K3: 2.5 | L3: 9 | M3: 46055 | N3: 46058 | O3: Done | P3: Ram | Q3: Nil | R3: Ram | S3: Nil | T3: https://dev.azure.com/heartlandschools/Activities/_git/Activities/pullrequest/47285 https://dev.azure.com/heartlandschools/Activities/_git/Activities/pullrequest/47405 | U3: 46070 | V3: 46070 | W3: Allen | X3: Nil | Y3: Andy | Z3: 46071 | AA3: Nil | AB3: Approved | AC3: Approved | AE3: Meets Expectation
A4: =ROW() - ROW(Table1456789101214161817222426283132333637394143454749515355[[#Headers],[S.No]]) - 1 -> 2 | B4: MSB Activities | C4: 46064 | D4: 46077 | E4: 26.3 Sprint S2 | F4: Ram | G4: 51787 | H4: Activities - SYSTEM - Update Vega component to Latest Version | I4: Story Completed | J4: 1 | K4: 1 | L4: 4 | M4: 46064 | N4: 46064 | O4: Done | P4: Athi | Q4: Nil | R4: Athi | S4: Nil | T4: https://dev.azure.com/heartlandschools/Activities/_git/Activities/pullrequest/47174 | U4: 46063 | V4: 46064 | W4: Allen | X4: Nil | Y4: Andy | Z4: 46064 | AA4: Nil | AB4: NA | AC4: NA | AE4: Meets Expectation
A5: =ROW() - ROW(Table1456789101214161817222426283132333637394143454749515355[[#Headers],[S.No]]) - 1 -> 3 | B5: MSB Activities | C5: 46064 | D5: 46077 | E5: 26.3 Sprint S2 | F5: Allen | G5: 51847 | H5: Activities - Kaleida - Update table grid design for Students & Contacts >Missing Tabs | I5: Story Completed | J5: 1 | K5: 1 | L5: 4 | M5: 46063 | N5: 46064 | O5: Done | P5: Ram | Q5: Nil | R5: Athi | S5: Nil | T5: https://dev.azure.com/heartlandschools/Activities/_git/Activities/pullrequest/47211 | U5: 46065 | V5: 46065 | W5: Allen | X5: Nil | Y5: Andy | Z5: 46065 | AA5: Nil | AB5: Given POV comments | AC5: Approved | AE5: Meets Expectation
A6: =ROW() - ROW(Table1456789101214161817222426283132333637394143454749515355[[#Headers],[S.No]]) - 1 -> 4 | B6: MSB Activities | C6: 46064 | D6: 46077 | E6: 26.3 Sprint S2 | F6: Allen | G6: 51849 | H6: Activities - Kaleida - Update table grid design for Enrollment Plan tabs (Required Forms,Discount & Activity Prices) | I6: Story Completed | J6: 1 | K6: 1 | L6: 4 | M6: 46063 | N6: 46064 | O6: Done | P6: Ram | Q6: Nil | R6: Athi | S6: Nil | T6: https://dev.azure.com/heartlandschools/Activities/_git/Activities/pullrequest/47208 | U6: 46065 | V6: 46065 | W6: Allen | X6: Nil | Y6: Andy | Z6: 46065 | AA6: Nil | AB6: Approved | AC6: Approved | AE6: Meets Expectation
A7: =ROW() - ROW(Table1456789101214161817222426283132333637394143454749515355[[#Headers],[S.No]]) - 1 -> 5 | B7: MSB Activities | C7: 46064 | D7: 46077 | E7: 26.3 Sprint S2 | F7: Allen | G7: 51886 | H7: Activities - Kaleida - Update New design for Registrations> Enrollments | I7: Story Completed | J7: 1 | K7: 1 | L7: 4 | M7: 46063 | N7: 46064 | O7: Done | P7: Ram | Q7: Nil | R7: Athi | S7: Nil | T7: https://dev.azure.com/heartlandschools/Activities/_git/Activities/pullrequest/47211 | U7: 46065 | V7: 46065 | W7: Allen | X7: Nil | Y7: Andy | Z7: 46065 | AA7: Nil | AB7: Given POV comments | AC7: Approved | AE7: Meets Expectation
A8: =ROW() - ROW(Table1456789101214161817222426283132333637394143454749515355[[#Headers],[S.No]]) - 1 -> 6 | B8: MSB Activities | C8: 46064 | D8: 46077 | E8: 26.3 Sprint S2 | F8: Allen | G8: 51887 | H8: Activities - Kaleida - Update table grid design for People > Documents Tab | I8: Story Completed | J8: 1 | K8: 1 | L8: 4 | M8: 46063 | N8: 46064 | O8: Done | P8: Ram | Q8: Nil | R8: Athi | S8: Nil | T8: https://dev.azure.com/heartlandschools/Activities/_git/Activities/pullrequest/47211 https://dev.azure.com/heartlandschools/Activities/_git/Activities/pullrequest/47246 | U8: 46065 | V8: 46065 | W8: Allen | X8: Nil | Y8: Andy | Z8: 46065 | AA8: Nil | AB8: Given POV comments | AC8: Approved | AE8: Meets Expectation
A9: =ROW() - ROW(Table1456789101214161817222426283132333637394143454749515355[[#Headers],[S.No]]) - 1 -> 7 | B9: MSB Activities | C9: 46064 | D9: 46077 | E9: 26.3 Sprint S2 | F9: Athi | G9: 51807 | H9: Activities - Kaleida - Parent Breadcrumb UI | I9: Story Completed | J9: 2 | K9: 1 | L9: 1.5 | M9: 46050 | N9: 46058 | O9: Done | P9: Ram | Q9: Nil | R9: Ram | S9: Nil | T9: https://dev.azure.com/heartlandschools/Activities/_git/Activities/pullrequest/47228 | U9: 46066 | V9: 46066 | W9: Allen | X9: Nil | Y9: Andy | Z9: 46066 | AA9: Nil | AB9: Given POV comments | AC9: Approved | AE9: Meets Expectation
A10: =ROW() - ROW(Table1456789101214161817222426283132333637394143454749515355[[#Headers],[S.No]]) - 1 -> 8 | B10: MSB Activities | C10: 46064 | D10: 46077 | E10: 26.3 Sprint S2 | F10: Athi | G10: 51256 | H10: Activities - Kaleida - Update Parent Footer (Kiosk PIN & Payment History Report) | I10: Story Completed | J10: 3 | K10: 1 | L10: 4 | M10: 46064 | N10: 46064 | O10: Done | P10: Ram | Q10: Nil | R10: Ram | S10: Nil | T10: https://dev.azure.com/heartlandschools/Activities/_git/Activities/pullrequest/47229 | U10: 46066 | V10: 46066 | W10: Allen | X10: Nil | Y10: Andy | Z10: 46066 | AA10: Nil | AB10: Given POV comments | AC10: Approved | AE10: Meets Expectation
A11: =ROW() - ROW(Table1456789101214161817222426283132333637394143454749515355[[#Headers],[S.No]]) - 1 -> 9 | B11: MSB Activities | C11: 46064 | D11: 46077 | E11: 26.3 Sprint S2 | F11: Ram | G11: 51809 | H11: Activities - Kaleida - Convert Class Components → Functional Components for Student Info | I11: Story Completed | J11: 1 | K11: 1 | L11: 4 | M11: 46064 | N11: 46064 | O11: Done | P11: Athi | Q11: Nil | R11: Athi | S11: Nil | T11: NA | U11: NA | V11: NA | W11: NA | X11: NA | Y11: NA | Z11: NA | AA11: NA | AB11: NA | AC11: NA | AD11: Development completed , PR will addressed with Parent Story 51670 Activities - Kaleida - Update Parent Registration - Student Info Card Component Creation | AE11: Meets Expectation
A12: =ROW() - ROW(Table1456789101214161817222426283132333637394143454749515355[[#Headers],[S.No]]) - 1 -> 10 | B12: MSB Activities | C12: 46064 | D12: 46077 | E12: 26.3 Sprint S2 | F12: Allen | G12: 51837 | H12: Activities - Admin App Switcher - Updates to initializing HSSAppTray [26.2.1 dot Release] | I12: Story Completed | J12: 5 | K12: 1 | L12: 3 | M12: 46063 | N12: 46064 | O12: Done | P12: Ram | Q12: Nil | R12: Ram | S12: Nil | T12: https://dev.azure.com/heartlandschools/Activities/_git/Activities/pullrequest/47200 | U12: 46065 | V12: 46065 | W12: Allen | X12: Nil | Y12: Andy | Z12: 46065 | AA12: Nil | AB12: NA | AC12: NA | AE12: Meets Expectation
A13: =ROW() - ROW(Table1456789101214161817222426283132333637394143454749515355[[#Headers],[S.No]]) - 1 -> 11 | B13: MSB Activities | C13: 46064 | D13: 46077 | E13: 26.3 Sprint S2 | F13: Ram | G13: 51670 | H13: Activities - Kaleida - Update Parent Registration - Student Info Card Component Creation | I13: Story Completed | J13: 8 | K13: 7 | L13: 28 | M13: 46065 | N13: 46070 | O13: Done | P13: Athi | Q13: Nil | R13: Athi | S13: Nil | T13: https://dev.azure.com/heartlandschools/Activities/_git/Activities/pullrequest/47378 | U13: 46072 | V13: 46073 | W13: Allen | X13: Nil | Y13: Andy | Z13: 46076 | AA13: Nil | AB13: Nil | AC13: Nil | AE13: Meets Expectation
A14: =ROW() - ROW(Table1456789101214161817222426283132333637394143454749515355[[#Headers],[S.No]]) - 1 -> 12 | B14: MSB Activities | C14: 46064 | D14: 46077 | E14: 26.3 Sprint S2 Stretch | F14: Ram | G14: 51885 | H14: Activities - Kaleida - Update Parent Registration - Add/Edit Student Info | I14: Story Being Developed | J14: 8 | K14: 1 | L14: 4 | M14: 46076 | O14: NA | P14: NA | Q14: NA | R14: NA | S14: NA | T14: NA | U14: NA | V14: NA | W14: NA | X14: NA | Y14: NA | Z14: NA | AA14: NA | AB14: NA | AC14: NA | AE14: Meets Expectation
A15: =ROW() - ROW(Table1456789101214161817222426283132333637394143454749515355[[#Headers],[S.No]]) - 1 -> 13 | B15: MSB Activities | C15: 46064 | D15: 46077 | E15: 26.3 Sprint S2 Stretch | F15: Athi | G15: 51662 | H15: Activities - Kaleida - Admin Breadcrumbs | I15: Story Being Developed | J15: 8 | K15: 4 | L15: 16 | M15: 46065 | O15: NA | P15: NA | Q15: NA | R15: NA | S15: NA | T15: NA | U15: NA | V15: NA | W15: NA | X15: NA | Y15: NA | Z15: NA | AA15: NA | AB15: NA | AC15: NA | AE15: Meets Expectation
A16: =ROW() - ROW(Table1456789101214161817222426283132333637394143454749515355[[#Headers],[S.No]]) - 1 -> 14 | B16: MSB Activities | C16: 46064 | D16: 46077 | E16: 26.3 Sprint S2 Stretch | F16: Allen | G16: 51753 | H16: Activities - Kaleida - Hide Inactive Districts from Parent Selection | I16: Story Completed | J16: 5 | K16: 4 | L16: 16 | M16: 46069 | N16: 46071 | O16: Done | P16: Ram | Q16: Nil | R16: Athi | S16: Nil | T16: https://dev.azure.com/heartlandschools/Activities/_git/Activities/pullrequest/47429 | U16: 46074 | V16: 46074 | W16: Allen | X16: Nil | Y16: Andy | Z16: 46076 | AA16: Nil | AB16: Given POV comments - Not handled for Single tenant | AC16: Approved | AE16: Meets Expectation
A17: =ROW() - ROW(Table1456789101214161817222426283132333637394143454749515355[[#Headers],[S.No]]) - 1 -> 15 | B17: MSB Activities | C17: 46064 | D17: 46077 | E17: 26.3 Sprint S2 Stretch | F17: Athi | G17: 26810 | H17: Activities - Admin - Calendar not displaying properly for transfer/withdraw modal | I17: Defect Fixed | J17: 1 | K17: 1 | L17: 2 | M17: 46070 | N17: 46070 | O17: Done | P17: Ram | Q17: Nil | R17: Ram | S17: Nil | T17: https://dev.azure.com/heartlandschools/Activities/_git/Activities/pullrequest/47300 | U17: 46070 | V17: 46070 | W17: Allen | X17: Nil | Y17: Andy | Z17: 46070 | AA17: Nil | AB17: NA | AC17: NA | AE17: Meets Expectation
A18: =ROW() - ROW(Table1456789101214161817222426283132333637394143454749515355[[#Headers],[S.No]]) - 1 -> 16 | B18: MSB Activities | C18: 46064 | D18: 46077 | E18: 26.3 Sprint S2 Stretch | F18: Allen | G18: 26788 | H18: Activities - Admin - Status column in the Parent Accounts of the Registrations tab displays numeric values. | I18: Defect Fixed | J18: 2 | K18: 2 | L18: 6 | M18: 46070 | N18: 46072 | O18: Done | P18: Ram | Q18: Nil | R18: Athi | S18: Nil | T18: https://dev.azure.com/heartlandschools/Activities/_git/Activities/pullrequest/47246 | U18: 46070 | V18: 46070 | W18: Allen | X18: Nil | Y18: Andy | Z18: 46071 | AA18: Nil | AB18: NA | AC18: NA | AE18: Meets Expectation
A19: =ROW() - ROW(Table1456789101214161817222426283132333637394143454749515355[[#Headers],[S.No]]) - 1 -> 17 | B19: MSB Activities | C19: 46064 | D19: 46077 | E19: 26.3 Sprint S2 Stretch | F19: Allen | G19: 26811 | H19: Activities - Parent - API token expiring before user session | I19: Defect Being Fixed | J19: 1 | M19: 46076 | N19: 46077 | O19: Done | P19: NA | Q19: NA | R19: NA | S19: NA | T19: NA | U19: NA | V19: NA | W19: NA | X19: NA | Y19: NA | Z19: NA | AA19: NA | AB19: NA | AC19: NA | AD19: During planning discussions, we decided to convert it into a story and move it to the next sprint stretch.
A20: =ROW() - ROW(Table1456789101214161817222426283132333637394143454749515355[[#Headers],[S.No]]) - 1 -> 18 | B20: MSB Activities | C20: 46064 | D20: 46077 | E20: 26.3 Sprint S2 Stretch | F20: Allen/Ram | G20: 26824 | H20: Activities - Admin - Universal search freezing when returning : from query | I20: Defect Fixed | J20: 2 | K20: 1 | L20: 2 | M20: 46071 | N20: 46072 | O20: Done | P20: Athi | Q20: Nil | R20: Athi | S20: Nil | T20: https://dev.azure.com/heartlandschools/Activities/_git/Activities/pullrequest/47382 | U20: 46072 | V20: 46072 | W20: Allen | X20: Nil | Y20: Andy | Z20: 46072 | AA20: Can you add a comment to each of the regex replaces to explain what they are looking for to make this easier if we ever have to modify them, or move these into helper functions similar to the escape SQL characters one and comment the function? | AB20: NA | AC20: NA | AD20: Suggestions from client to add comments in code for future understanding | AE20: Meets Expectation
A21: =ROW() - ROW(Table1456789101214161817222426283132333637394143454749515355[[#Headers],[S.No]]) - 1 -> 19 | B21: MSB Activities | C21: 46064 | D21: 46077 | E21: 26.3 Sprint S2 Stretch | F21: Allen | G21: 52039 | H21: Activities - App Switcher - Hide button until script loads | I21: Story Being Developed | J21: 1 | K21: 1 | L21: 2 | M21: 46076 | N21: 46076 | O21: Done | P21: Ram | Q21: Nil | R21: Ram | S21: Nil | T21: https://dev.azure.com/heartlandschools/Activities/_git/Activities/pullrequest/47440 | U21: 46076 | V21: 46076 | W21: Allen | X21: Nil | Y21: Andy | Z21: 46076 | AA21: Nil | AB21: NA | AC21: NA | AD21: Moved to Next sprint Main | AE21: Meets Expectation

Sheet 26.3 Sprint 2 - Defects
A1: S.No | B1: Sprint # | C1: Story/Defect ID | D1: Parent Story | E1: Developer | F1: Issue Type | G1: Issue Description | H1: Root Cause Analysis | I1: Priority | J1: Defect Source | K1: Type | L1: Status | M1: Root Cause Category | N1: Comments | O1: Defect Raised
A2: 1 | B2: 26.3 Sprint S2 | C2: 51887 Activities - Kaleida - Update table grid design for People > Documents Tab | D2: 51887 | E2: Allen | F2: Bounceback/Sub-Defect | G2: View icon is only working for pdf files and not working for photo | H2: During the process of resolving a merge conflict, an issue was introduced due to incorrect or incomplete integration of code changes from different branches. | I2: Significant | J2: Manual | K2: Internal | L2: Story Completed | M2: Development | O2: Offshore QA - Manjunath
A3: 2 | B3: 26.3 Sprint S2 Stretch | C3: 26788 Activities - Admin - Status column in the Parent Accounts of the Registrations tab displays numeric values. | E3: Allen | F3: Defect | G3: The Status column in the Parent Accounts of the Registrations tab displays numeric values, such as 3 or 5. | H3: The mapping between the enum value and its corresponding display string was not implemented or was incorrectly handled. | I3: Significant | J3: Manual | K3: Internal | L3: Defect Fixed | M3: Development | O3: Offshore PO - Kanchana
A4: 3 | B4: 26.3 Sprint S2 Stretch | C4: 26810 Activities - Admin - Calendar not displaying properly for transfer/withdraw modal. | E4: Athinarayanan | F4: Defect | G4: A recent CSS change is causing the calendar modal to not display properly | H4: Date picker is not displayed properly in Modal popup | I4: Significant | J4: Manual | K4: External | L4: Defect Fixed | M4: Existing_Issues | N4: PROD Issue: This issue was raised due to the fix for adjusting padding and spacing in the modal pop-up during an earlier sprint. | O4: Offshore PO - Kanchana
A5: 4 | B5: 26.3 Sprint S2 Stretch | C5: 26824 Activities - Admin - Universal search freezing when returning : from query | E5: Allen | F5: Defect | G5: In admin if you perform a search with the character : the input box freezes and the grid does not refresh with the filtered data. It looks to only occur when the grid actually contains the character : (so the EP name has 1:00 it would cause the search to not function properly) | H5: The search query lacked proper input validation, allowing invalid or unexpected values to be processed, which led to invalid results. | I5: Minor | J5: Manual | K5: Internal | L5: Defect Fixed | M5: Development | O5: Onsite QA - Jeff
A6: 5 | B6: 26.3 Sprint S2 Stretch | C6: 26811 Activities - Parent - API token expiring before user session | E6: Allen | F6: Defect | G6: After logging into parent, after 15 minutes expires, the get district modal is not being retrieved. It looks to be an issue with the API token to MSB expiring before the users session | H6: Access token is getting expired | I6: Significant | J6: Manual | K6: External | L6: Defect Being Fixed | M6: Existing_Issues | N6: PROD Issue: Existing Issue from MSB Token and converted as Story in next sprint | O6: Onsite QA - Jeff
A7: 6 | B7: 26.3 Sprint S2 | C7: 51752 - Activities - Admin - Filter Completed with Errors in JobRequest DataGrid | D7: 51752 | E7: Athinarayanan | F7: Bounceback/Sub-Defect | G7: Search is not getting retained, while we go to next page and get back | H7: The data table was not refreshed appropriately after executing the search query, resulting in outdated or incorrect data being displayed to the user. | I7: Significant | J7: Manual | K7: Internal | L7: Defect Fixed | M7: Development | O7: Offshore QA - Manjunath
A8: 7 | B8: 26.3 Sprint S2 | C8: 51752 - Activities - Admin - Filter Completed with Errors in JobRequest DataGrid | D8: 51752 | E8: Athinarayanan | F8: Bounceback/Sub-Defect | G8: Completed with error status records also shown in the table grid even if we are not selected in the status filter | H8: The logic used to compare the filter keyword in the data table was incorrect, resulting in improper filtering and inaccurate search results being displayed to the user | I8: Significant | J8: Manual | K8: Internal | L8: Defect Fixed | M8: Development | O8: Offshore QA - Manjunath

Sheet 26.3 Sprint S1-Status
A1: S.No | B1: Application Name | C1: Sprint Start Date | D1: Sprint End Date | E1: Sprint | F1: Developer | G1: Story ID/Defect ID | H1: Description | I1: Status | J1: Estimated(sp) | K1: Actual(sp) | L1: Actual Hours Worklog | M1: Dev Start Date | N1: Dev End Date | O1: Unit testing | P1: Peer Tested By | Q1: Peer Tested Comments, if any | R1: Peer Reviewed By | S1: Peer Code Review Comments, if any | T1: PR Number/Link | U1: PR Created Date | V1: PR Approved Date | W1: Onsite Lead Code Review | X1: Onsite Lead Code Review Comments, if any | Y1: Client Code Review | Z1: PR Approved Date2 | AA1: Client Code Review Comments, if any | AB1: Internal PO -POV Comments | AC1: Client PO -POV Comments | AD1: Comments | AE1: Does this story Meet Expectations?
A2: =ROW() - ROW(Table14567891012141618172224262831323336373941434547495153[[#Headers],[S.No]]) - 1 -> 0
A3: =ROW() - ROW(Table14567891012141618172224262831323336373941434547495153[[#Headers],[S.No]]) - 1 -> 1 | B3: MSB Activities | C3: 46050 | D3: 46063 | E3: 26.3 Sprint S1 | F3: Allen | G3: 26675 | H3: Activities - Term Enrollment Plans - Action menu text alignment | I3: Defect Fixed | J3: 1 | K3: 1 | L3: 3 | M3: 46050 | N3: 46058 | O3: Done | P3: Athi | Q3: Nil | R3: Ram | S3: Nil | T3: https://dev.azure.com/heartlandschools/Activities/_git/Activities/pullrequest/46894 | U3: 46050 | V3: 46051 | W3: Allen | X3: Nil | Y3: Andy | Z3: 46051 | AA3: Nil | AB3: NA | AC3: NA | AE3: Meets Expectation
A4: =ROW() - ROW(Table14567891012141618172224262831323336373941434547495153[[#Headers],[S.No]]) - 1 -> 2 | B4: MSB Activities | C4: 46050 | D4: 46063 | E4: 26.3 Sprint S1 | F4: Athi | G4: 51254 | H4: Activities - Kaleida - Update Parent Payment History Design [26.3] | I4: Story Completed | J4: 1 | K4: 1 | L4: 1 | M4: 46038 | N4: 46043 | O4: Done | P4: Kaliammal/Sivaraja | Q4: Nil | R4: Ram | S4: Nil | T4: https://dev.azure.com/heartlandschools/Activities/_git/Activities/pullrequest/46835 | U4: 46045 | V4: 46050 | W4: Allen | X4: Nil | Y4: Andy | Z4: 46051 | AA4: Suggestion, Remove the scorllbar | AB4: Given POV comments. Approved | AC4: Approved | AD4: Dev is completed in Last Sprint , it just carry forward for testing only | AE4: Meets Expectation
A5: =ROW() - ROW(Table14567891012141618172224262831323336373941434547495153[[#Headers],[S.No]]) - 1 -> 3 | B5: MSB Activities | C5: 46050 | D5: 46063 | E5: 26.3 Sprint S1 | F5: Nathiya | G5: 51255 | H5: Activities - Kaleida - Update Parent Kiosk PIN Design [26.3] | I5: Story Completed | J5: 1 | K5: 1 | L5: 4 | M5: 46015 | N5: 46022 | O5: Done | P5: Ram,Kaliammal | Q5: Nil | R5: Ram,Kaliammal | S5: Nil | T5: https://dev.azure.com/heartlandschools/Activities/_git/Activities/pullrequest/46513 https://dev.azure.com/heartlandschools/Activities/_git/Activities/pullrequest/46972 | U5: 46030 | V5: 46050 | W5: Allen | X5: Nil | Y5: Andy | Z5: 46051 | AA5: Nil | AB5: Nil | AC5: Approved | AD5: Dev is completed in Last Sprint , it just carry forward for testing only | AE5: Meets Expectation
A6: =ROW() - ROW(Table14567891012141618172224262831323336373941434547495153[[#Headers],[S.No]]) - 1 -> 4 | B6: MSB Activities | C6: 46050 | D6: 46063 | E6: 26.3 Sprint S1 | F6: Kaliammal | G6: 51367 | H6: Activities - Kaleida - Update table grid design for Enrollment Plans/ Activities/ Discounts [26.3] | I6: Story Completed | J6: 2 | K6: 1 | L6: 3 | M6: 46023 | N6: 46036 | O6: Done | P6: Ram,Nathiya | Q6: Nil | R6: Ram,Nathiya | S6: Nil | T6: https://dev.azure.com/heartlandschools/Activities/_git/Activities/pullrequest/46619 | U6: 46045 | V6: 46050 | W6: Allen | X6: Nil | Y6: Andy | Z6: 46050 | AA6: Nil | AB6: Nil | AC6: Nil | AD6: Dev is completed in Last Sprint , it just carry forward for testing only | AE6: Meets Expectation
A7: =ROW() - ROW(Table14567891012141618172224262831323336373941434547495153[[#Headers],[S.No]]) - 1 -> 5 | B7: MSB Activities | C7: 46050 | D7: 46063 | E7: 26.3 Sprint S1 | F7: Ram | G7: 51667 | H7: Activities - Tech Debt - Create Shared Folder for Parent Shared Component | I7: Story Completed | J7: 2 | K7: 1 | L7: 3 | M7: 46038 | N7: 46049 | O7: Done | P7: Athi | Q7: Nil | R7: Athi | S7: Nil | T7: https://dev.azure.com/heartlandschools/Activities/_git/Activities/pullrequest/46872 | U7: 46049 | V7: 46050 | W7: Allen | X7: Nil | Y7: Andy | Z7: 46050 | AA7: Nil | AB7: NA | AC7: NA | AD7: Dev is completed in Last Sprint , it just carry forward for testing only | AE7: Meets Expectation
A8: =ROW() - ROW(Table14567891012141618172224262831323336373941434547495153[[#Headers],[S.No]]) - 1 -> 6 | B8: MSB Activities | C8: 46050 | D8: 46063 | E8: 26.3 Sprint S1 | F8: Nathiya | G8: 51178 | H8: Activities - Kaleida - Parent - Remove "Loading message" with New Spinning Loader Design[26.3] | I8: Story Completed | J8: 3 | K8: 2 | L8: 8 | M8: 46050 | N8: 46051 | O8: Done | P8: Sivaraj | Q8: Nil | R8: SivaRaja,Kaliammal | S8: Nil | T8: https://dev.azure.com/heartlandschools/Activities/_git/Activities/pullrequest/46937 | U8: 46052 | V8: 46053 | W8: Allen | X8: Nil | Y8: Andy | Z8: 46053 | AA8: Nil | AB8: Approved | AC8: Approved | AE8: Meets Expectation
A9: =ROW() - ROW(Table14567891012141618172224262831323336373941434547495153[[#Headers],[S.No]]) - 1 -> 7 | B9: MSB Activities | C9: 46050 | D9: 46063 | E9: 26.3 Sprint S1 | F9: Athi | G9: 51167 | H9: Activities - Kaleida - Breadcrumb in the Parent UI (DISCOVERY & DEV) | I9: Story Completed | J9: 8 | K9: 8 | L9: 32 | M9: 46050 | N9: 46058 | O9: Done | P9: NA | Q9: NA | R9: NA | S9: NA | T9: NA | U9: NA | V9: NA | W9: NA | X9: NA | Y9: NA | Z9: NA | AA9: NA | AB9: NA | AC9: NA | AD9: Discovery and Dev work is completed | AE9: Meets Expectation
A10: =ROW() - ROW(Table14567891012141618172224262831323336373941434547495153[[#Headers],[S.No]]) - 1 -> 8 | B10: MSB Activities | C10: 46050 | D10: 46063 | E10: 26.3 Sprint S1 | F10: Ram | G10: 51659 | H10: Activities - Kaleida - Update Parent Registration Design (DISCOVERY) | I10: Story Completed | J10: 8 | K10: 8 | L10: 32 | M10: 46050 | N10: 46058 | O10: NA | P10: NA | Q10: NA | R10: NA | S10: NA | T10: NA | U10: NA | V10: NA | W10: NA | X10: NA | Y10: NA | Z10: NA | AA10: NA | AB10: NA | AC10: NA | AD10: Discovery completed and document updated in Axosoft | AE10: Meets Expectation
A11: =ROW() - ROW(Table14567891012141618172224262831323336373941434547495153[[#Headers],[S.No]]) - 1 -> 9 | B11: MSB Activities | C11: 46050 | D11: 46063 | E11: 26.3 Sprint S1 Stretch | F11: Nathiya | G11: 51472 | H11: Activities - Admin - Implement the Existing Global Search to be Replaced with Universal Search (Backend) | I11: Story Completed | J11: 3 | L11: 1 | M11: 46041 | N11: 46045 | O11: Done | P11: Ram | Q11: Nil | R11: Ram | S11: Nil | T11: https://dev.azure.com/heartlandschools/Activities/_git/Activities/pullrequest/46912 | U11: 46055 | V11: 46055 | W11: Allen | X11: Nil | Y11: Andy | Z11: 46055 | AA11: Nil | AE11: Meets Expectation
A12: =ROW() - ROW(Table14567891012141618172224262831323336373941434547495153[[#Headers],[S.No]]) - 1 -> 10 | B12: MSB Activities | C12: 46050 | D12: 46063 | E12: 26.3 Sprint S1 Stretch | F12: Allen | G12: 51573 | H12: Activities - Kaleida - Update table grid design for Roles/Users/Security Groups/District ACL [26.3] | I12: Story Completed | J12: 1 | K12: 1 | L12: 1 | M12: 46050 | N12: 46052 | O12: Done | P12: Ram | Q12: Nil | R12: Ram | S12: Nil | T12: https://dev.azure.com/heartlandschools/Activities/_git/Activities/pullrequest/46969 | U12: 46052 | V12: 46052 | W12: Allen | X12: Nil | Y12: Andy | Z12: 46052 | AA12: Nil | AE12: Meets Expectation
A13: =ROW() - ROW(Table14567891012141618172224262831323336373941434547495153[[#Headers],[S.No]]) - 1 -> 11 | B13: MSB Activities | C13: 46050 | D13: 46063 | E13: 26.3 Sprint S1 Stretch | F13: Allen | G13: 51574 | H13: Activities - Kaleida - Update table grid design for Form Types/Kiosk/PIN Maintenance [26.3] | I13: Story Completed | J13: 1 | K13: 1 | L13: 1 | M13: 46050 | N13: 46052 | O13: Done | P13: Ram | Q13: Nil | R13: Ram | S13: Nil | T13: https://dev.azure.com/heartlandschools/Activities/_git/Activities/pullrequest/46970 | U13: 46052 | V13: 46052 | W13: Allen | X13: Nil | Y13: Andy | Z13: 46052 | AA13: NIl | AE13: Meets Expectation
A14: =ROW() - ROW(Table14567891012141618172224262831323336373941434547495153[[#Headers],[S.No]]) - 1 -> 12 | B14: MSB Activities | C14: 46050 | D14: 46063 | E14: 26.3 Sprint S1 Stretch | F14: Allen | G14: 51488 | H14: Activities - Kaleida - Update table grid design for Student Maintenance [26.3] | I14: Story Completed | J14: 1 | K14: 1 | L14: 1 | M14: 46050 | N14: 46055 | O14: Done | P14: Ram | Q14: Nil | R14: Ram | S14: Nil | T14: https://dev.azure.com/heartlandschools/Activities/_git/Activities/pullrequest/46912 | U14: 46055 | V14: 46055 | W14: Allen | X14: Nil | Y14: Andy | Z14: 46055 | AA14: Nil | AE14: Meets Expectation
A15: =ROW() - ROW(Table14567891012141618172224262831323336373941434547495153[[#Headers],[S.No]]) - 1 -> 13 | B15: MSB Activities | C15: 46050 | D15: 46063 | E15: 26.3 Sprint S1 Stretch | F15: Allen/Athi | G15: 51752 | H15: Activities - Admin - Filter Completed with Errors in JobRequest DataGrid | I15: Story Peer Review | J15: 5 | K15: 3 | L15: 11 | M15: 46055 | N15: 46058 | O15: Done | P15: Ram | Q15: Nil | R15: Ram | S15: Nil | AE15: Meets Expectation
A16: =ROW() - ROW(Table14567891012141618172224262831323336373941434547495153[[#Headers],[S.No]]) - 1 -> 14 | B16: MSB Activities | C16: 46050 | D16: 46063 | E16: 26.3 Sprint S1 Stretch | F16: Allen | G16: 51596 | H16: Activities - Kaleida - Update table grid design for Parent Accounts (People) [26.3] | I16: Story Completed | J16: 1 | K16: 1 | L16: 1 | M16: 46050 | N16: 46050 | O16: Done | P16: Ram | Q16: Nil | R16: Athi | S16: Nil | T16: https://dev.azure.com/heartlandschools/Activities/_git/Activities/pullrequest/46829 | U16: 46056 | V16: 46056 | W16: Allen | X16: Nil | Y16: Andy | Z16: 46056 | AA16: Nil | AB16: Nil | AC16: Nil | AE16: Meets Expectation
A17: =ROW() - ROW(Table14567891012141618172224262831323336373941434547495153[[#Headers],[S.No]]) - 1 -> 15 | B17: MSB Activities | C17: 46050 | D17: 46063 | E17: 26.3 Sprint S1 Stretch | F17: Allen | G17: 51597 | H17: Activities - Kaleida - Update table grid design for Others Contacts (People) [26.3] | I17: Story Completed | J17: 1 | K17: 1 | L17: 1 | M17: 46050 | N17: 46050 | O17: Done | P17: Ram | Q17: Nil | R17: Athi | S17: Nil | T17: https://dev.azure.com/heartlandschools/Activities/_git/Activities/pullrequest/46792 | U17: 46056 | V17: 46056 | W17: Allen | X17: Nil | Y17: Andy | Z17: 46056 | AA17: Nil | AB17: Nil | AC17: Nil | AE17: Meets Expectation
A18: =ROW() - ROW(Table14567891012141618172224262831323336373941434547495153[[#Headers],[S.No]]) - 1 -> 16 | B18: MSB Activities | C18: 46050 | D18: 46063 | E18: 26.3 Sprint S1 Stretch | F18: Allen | G18: 51618 | H18: Activities - Kaleida - Update table grid design for Accounting [26.3] | I18: Story Completed | J18: 1 | K18: 1 | L18: 1 | M18: 46050 | N18: 46050 | O18: Done | P18: Ram | Q18: Nil | R18: Athi | S18: Nil | T18: https://dev.azure.com/heartlandschools/Activities/_git/Activities/pullrequest/47024 | U18: 46056 | V18: 46056 | W18: Allen | X18: Nil | Y18: Andy | Z18: 46056 | AA18: Nil | AB18: Nil | AC18: Nil | AE18: Meets Expectation
A19: =ROW() - ROW(Table14567891012141618172224262831323336373941434547495153[[#Headers],[S.No]]) - 1 -> 17 | B19: MSB Activities | C19: 46050 | D19: 46063 | E19: 26.3 Sprint S1 Stretch | F19: Allen | G19: 51646 | H19: Activities - Kaleida - Update table grid design for Registrations [26.3] | I19: Story Completed | J19: 1 | K19: 1 | L19: 1 | M19: 46050 | N19: 46050 | O19: Done | P19: Ram | Q19: Nil | R19: Athi | S19: Nil | T19: https://dev.azure.com/heartlandschools/Activities/_git/Activities/pullrequest/47019 | U19: 46056 | V19: 46056 | W19: Allen | X19: Nil | Y19: Andy | Z19: 46056 | AA19: Nil | AB19: Nil | AC19: Nil | AE19: Meets Expectation
A20: =ROW() - ROW(Table14567891012141618172224262831323336373941434547495153[[#Headers],[S.No]]) - 1 -> 18 | B20: MSB Activities | C20: 46050 | D20: 46063 | E20: 26.3 Sprint S1 Stretch | F20: Allen | G20: 51656 | H20: Activities - Kaleida - Update table grid design for Home Screen(District/Site)/Events [26.3] | I20: Story Completed | J20: 1 | K20: 1 | L20: 1 | M20: 46050 | N20: 46050 | O20: Done | P20: Ram | Q20: Nil | R20: Athi | S20: Nil | T20: https://dev.azure.com/heartlandschools/Activities/_git/Activities/pullrequest/47026 | U20: 46056 | V20: 46056 | W20: Allen | X20: Nil | Y20: Andy | Z20: 46057 | AA20: Nil | AB20: Nil | AC20: Nil | AE20: Meets Expectation
A21: =ROW() - ROW(Table14567891012141618172224262831323336373941434547495153[[#Headers],[S.No]]) - 1 -> 19 | B21: MSB Activities | C21: 46050 | D21: 46063 | E21: 26.3 Sprint S1 Stretch | F21: Allen | G21: 51657 | H21: Activities - Kaleida - Update table grid design for Operating Days [26.3] | I21: Story Completed | J21: 1 | K21: 1 | L21: 1 | M21: 46050 | N21: 46050 | O21: Done | P21: Ram | Q21: Nil | R21: Athi | S21: Nil | T21: https://dev.azure.com/heartlandschools/Activities/_git/Activities/pullrequest/47021 | U21: 46056 | V21: 46056 | W21: Allen | X21: Nil | Y21: Andy | Z21: 46056 | AA21: Nil | AB21: Nil | AC21: Nil | AE21: Meets Expectation
A22: =ROW() - ROW(Table14567891012141618172224262831323336373941434547495153[[#Headers],[S.No]]) - 1 -> 20 | B22: MSB Activities | C22: 46050 | D22: 46063 | E22: 26.3 Sprint S1 Stretch | F22: Allen | G22: 51572 | H22: Activities - Kaleida - Update table grid design for Fee Items/Custom Fields/Sites [26.3] | I22: Story Completed | J22: 1 | K22: 1 | L22: 1 | M22: 46050 | N22: 46050 | O22: Done | P22: Ram | Q22: Nil | R22: Athi | S22: Nil | T22: https://dev.azure.com/heartlandschools/Activities/_git/Activities/pullrequest/46791 | U22: 46056 | V22: 46056 | W22: Allen | X22: Nil | Y22: Andy | Z22: 46056 | AA22: Nil | AB22: Nil | AC22: Nil

Sheet 26.3 Sprint 1 - Defects
A1: S.No | B1: Sprint # | C1: Story/Defect ID | D1: Parent Story | E1: Developer | F1: Issue Type | G1: Issue Description | H1: Root Cause Analysis | I1: Priority | J1: Defect Source | K1: Type | L1: Status | M1: Root Cause Category | N1: Comments | O1: Defect Raised
A2: 1 | B2: 26.3 Sprint S1 | C2: 26675 | D2: 26675 | E2: Allen | F2: Defect | G2: 26675 - Activities - Term Enrollment Plans - Action menu text alignment | H2: UI Changes caused Alignmant issue | I2: Minor | J2: Manual | K2: Internal | L2: Story Completed | M2: Design | O2: Offshore - Kanchana
A3: 2 | B3: 26.3 Sprint S1 | C3: 51255 | D3: 51255 | E3: Nathiya | F3: Bounceback/Sub-Defect | G3: 51255 - Activities - Kaleida - Update Parent Kiosk PIN Design [26.3] | H3: UI Changes caused Alignmant issue | I3: Minor | J3: Manual | K3: Internal | L3: Story Completed | M3: Design | O3: Offshore QA - SivaMohan
A4: 3 | B4: 26.3 Sprint S1 | C4: 51574 | D4: 51574 | E4: Allen | F4: Bounceback/Sub-Defect | G4: We are able to checkin for past date, Even if have have tooltip notification. | I4: Significant | J4: Manual | K4: Internal | L4: Story Completed | M4: Development | O4: Offshore QA - Manjunath
A5: 4 | B5: 26.3 Sprint S1 | C5: 51597 | D5: 51597 | E5: Allen | F5: Bounceback/Sub-Defect | G5: We are able to see two search field in the screen | I5: Significant | J5: Manual | K5: Internal | L5: Story Completed | M5: Development | O5: Offshore QA - Manjunath
A6: 5 | B6: 26.3 Sprint S1 | C6: 51646 | D6: 51646 | E6: Allen | F6: Bounceback/Sub-Defect | G6: Facing No record found issue when we click on table grid record | I6: Significant | J6: Manual | K6: Internal | L6: Story Completed | M6: Development | O6: Offshore QA - Manjunath

Sheet 26.2 Sprint S3-Status
A1: S.No | B1: Application Name | C1: Sprint Start Date | D1: Sprint End Date | E1: Sprint | F1: Developer | G1: Story ID/Defect ID | H1: Description | I1: Status | J1: Estimated(sp) | K1: Actual(sp) | L1: Actual Hours Worklog | M1: Dev Start Date | N1: Dev End Date | O1: Unit testing | P1: Peer Tested By | Q1: Peer Tested Comments, if any | R1: Peer Reviewed By | S1: Peer Code Review Comments, if any | T1: PR Number/Link | U1: PR Created Date | V1: PR Approved Date | W1: Onsite Lead Code Review | X1: Onsite Lead Code Review Comments, if any | Y1: Client Code Review | Z1: PR Approved Date2 | AA1: Client Code Review Comments, if any | AB1: Internal PO -POV Comments | AC1: Client PO -POV Comments | AD1: Comments | AE1: Does this story Meet Expectations?
A3: 1 | B3: MSB Activities | C3: 46036 | D3: 46049 | E3: 26.2 Sprint S3 | F3: Sivaraja | G3: 51138 | H3: Activities - Non Student Registration - Update validation for checking for students in the msb household | I3: Story Completed | J3: 2 | K3: 1 | L3: 4 | M3: 46009 | N3: 46028 | O3: Done | P3: Ram,Kaliammal | Q3: Nil | R3: Ram, Kaliammal | S3: Nil | T3: https://dev.azure.com/heartlandschools/Activities/_git/Activities/pullrequest/46602 | U3: 46034 | V3: 46034 | W3: Allen | X3: Nil | Y3: Done | Z3: 46035 | AA3: Nil | AB3: Nil | AC3: Nil | AD3: Nil | AE3: Meets Expectation
A4: 2 | B4: MSB Activities | C4: 46036 | D4: 46049 | E4: 26.2 Sprint S3 | F4: Allen | G4: 51279 | H4: Activities - Kaleida - Update table grid design for Term Maintenance [26.3] | I4: Story Completed | J4: 2 | K4: 2 | L4: 8 | M4: 46003 | N4: 46005 | O4: Done | P4: Ram | Q4: Nil | R4: Ram | S4: Nil | T4: https://dev.azure.com/heartlandschools/Activities/_git/Activities/pullrequest/46584 | U4: 46036 | V4: 46037 | W4: Allen | X4: Nil | Y4: Andy | Z4: 46037 | AA4: Nil | AB4: Nil | AC4: Nil | AE4: Meets Expectation
A5: 3 | B5: MSB Activities | C5: 46036 | D5: 46049 | E5: 26.2 Sprint S3 | F5: Allen | G5: 51332 | H5: Activities - Kaleida - Admin - Component Creation for Editable Grid Table with Updated Design [26.3] | I5: Story Completed | J5: 2 | K5: 1 | L5: 2 | M5: 46003 | N5: 46005 | O5: Done | P5: Ram,Nathiya | Q5: NIl | R5: Ram,Nathiya | S5: NIl | T5: https://dev.azure.com/heartlandschools/Activities/_git/Activities/pullrequest/46625 | U5: 46036 | V5: 46036 | W5: Allen | X5: Nil | Y5: Andy | Z5: 46036 | AA5: Nil | AB5: Nil | AC5: NIl | AE5: Meets Expectation
A6: 4 | B6: MSB Activities | C6: 46036 | D6: 46049 | E6: 26.2 Sprint S3 | F6: Kaliammal | G6: 51367 | H6: Activities - Kaleida - Update table grid design for Enrollment Plans/ Activities/ Discounts [26.3] | I6: Story Peer Review | J6: 3 | K6: 5 | L6: 20 | M6: 46023 | N6: 46036 | O6: Done | P6: Ram,Nathiya | Q6: Nil | R6: Ram,Nathiya | S6: Nil | T6: https://dev.azure.com/heartlandschools/Activities/_git/Activities/pullrequest/46619 | U6: 46045 | V6: NA | W6: NA | X6: NA | Y6: NA | Z6: NA | AA6: NA | AB6: Given POV Comments. | AC6: Nil | AD6: During the regression sprint, we completed development and Product Owner verification. The pull request will be merged only after the regression sprint ends. Note: As informed by the client, this story will be carried over to the next sprint for PR merging and testing efforts. | AE6: Meets Expectation
A7: 5 | B7: MSB Activities | C7: 46036 | D7: 46049 | E7: 26.2 Sprint S3 Stretch | F7: Allen | G7: 51489 | H7: Activities - Kaleida - Update table grid design for HSS Maintenance | I7: Story Completed | J7: 3 | K7: 3 | L7: 12 | M7: 46036 | N7: 46038 | O7: Done | P7: Ram,Nathiya | Q7: Nil | R7: Ram,Nathiya | S7: Nil | T7: https://dev.azure.com/heartlandschools/Activities/_git/Activities/pullrequest/46671 | U7: 46036 | V7: 46038 | W7: Allen | X7: Nil | Y7: Andy | Z7: 46038 | AA7: Nil | AB7: Nil | AC7: Nil | AE7: Meets Expectation
A8: 6 | B8: MSB Activities | C8: 46036 | D8: 46049 | E8: 26.2 Sprint S3 Stretch | F8: Nathiya | G8: 51472 | H8: Activities - Admin - Implement the Existing Global Search to be Replaced with Universal Search (Backend) | I8: Story Peer Review | J8: 5 | K8: 5 | L8: 20 | M8: 46041 | N8: 46045 | O8: Done | P8: Ram | Q8: Nil | R8: Ram | S8: Nil | T8: https://dev.azure.com/heartlandschools/Activities/_git/Activities/pullrequest/46885 | U8: 46049 | V8: NA | W8: NA | X8: NA | Y8: NA | Z8: NA | AA8: NA | AB8: NA | AC8: NA | AD8: During the regression sprint, we completed development and Product Owner verification. The pull request will be merged only after the regression sprint ends. Note: As informed by the client, this story will be carried over to the next sprint for PR merging and testing efforts. | AE8: Meets Expectation

Sheet 26.2 Sprint 3 - Defects
A1: S.No | B1: Sprint # | C1: Story/Defect ID | D1: Parent Story | E1: Developer | F1: Issue Type | G1: Issue Description | H1: Root Cause Analysis | I1: Priority | J1: Defect Source | K1: Type | L1: Status | M1: Root Cause Category | N1: Comments | O1: Defect Raised

Sheet 26.2 Sprint S2-Status
A1: S.No | B1: Application Name | C1: Sprint Start Date | D1: Sprint End Date | E1: Sprint | F1: Developer | G1: Story ID/Defect ID | H1: Description | I1: Status | J1: Estimated(sp) | K1: Actual(sp) | L1: Actual Hours Worklog | M1: Dev Start Date | N1: Dev End Date | O1: Unit testing | P1: Peer Tested By | Q1: Peer Tested Comments, if any | R1: Peer Reviewed By | S1: Peer Code Review Comments, if any | T1: PR Number/Link | U1: PR Created Date | V1: PR Approved Date | W1: Onsite Lead Code Review | X1: Onsite Lead Code Review Comments, if any | Y1: Client Code Review | Z1: PR Approved Date2 | AA1: Client Code Review Comments, if any | AB1: Internal PO -POV Comments | AC1: Client PO -POV Comments | AD1: Comments | AE1: Does this story Meet Expectations?
A2: 1 | B2: MSB Activities | C2: 46008 | D2: 46035 | E2: 26.2 Sprint S2 | F2: Sivaraja | G2: 51138 | H2: Activities - Non Student Registration - Update validation for checking for students in the msb household | I2: Story Ready For Testing | J2: 3 | K2: 3 | L2: 12 | M2: 46008 | N2: 46028 | O2: Done | P2: Ram, Kaliammal | Q2: Nil | R2: Ram, Kaliammal | S2: Nil | T2: https://dev.azure.com/heartlandschools/Activities/_git/Activities/pullrequest/46602 | U2: 46034 | V2: 46034 | W2: Allen | X2: Nil | Y2: Done | Z2: 46035 | AA2: Nil | AB2: Approved | AC2: Approved | AD2: Reason – There were dependencies on MSB APIs, which became blockers for this story. The blockers were identified one after another and discussed with Allen and the client developer, Andy, for confirmation. The PR has been approved by Allen and is currently pending approval from the client developer, Andy. Carried to Next Sprint for QA | AE2: Meets Expectation
A3: 2 | B3: MSB Activities | C3: 46008 | D3: 46035 | E3: 26.2 Sprint S2 | F3: Sivaraja | G3: 26419 | H3: Activities - Admin - Validation is missing the start and end time when editing a term activity | I3: Defect Fixed | J3: 1 | K3: 1 | L3: 4 | M3: 46002 | N3: 46003 | O3: Done | P3: Ram, Kaliammal | Q3: Nil | R3: Ram, Kaliammal | S3: Nil | T3: https://dev.azure.com/heartlandschools/Activities/_git/Activities/pullrequest/46261 | U3: 46002 | V3: 46010 | W3: Done | X3: Nil | Y3: Done | Z3: 46013 | AA3: Nil | AB3: NA | AC3: NA | AD3: NA | AE3: Meets Expectation
A4: 3 | B4: MSB Activities | C4: 46008 | D4: 46035 | E4: 26.2 Sprint S2 | F4: Kaliammal | G4: 47253 | H4: Activities - Enrollment Plans - Customizable Column Headers | I4: Story Completed | J4: 5 | K4: 6 | L4: 26 | M4: 46008 | N4: 46028 | O4: Done | P4: Sivaraja | Q4: Nil | R4: Sivaraja,Athi | S4: Nil | T4: https://dev.azure.com/heartlandschools/Activities/_git/Activities/pullrequest/46437 | U4: 46028 | V4: 46028 | W4: Done | X4: Nil | Y4: Done | Z4: 46030 | AA4: Nil | AB4: Need to check copy/Edit . | AC4: Remove SorBy for regitration Start and End.Status alignment to center | AD4: NA | AE4: Meets Expectation
A5: 4 | B5: MSB Activities | C5: 46008 | D5: 46035 | E5: 26.2 Sprint S2 | F5: Kaliammal | G5: 26460 | H5: Activities - Admin - Pending Registrations - Capacity modal appearing when approving non-capacity registrations | I5: Defect Fixed | J5: 1 | K5: 1 | L5: 10 | M5: 46003 | N5: 46006 | O5: Done | P5: Athi | Q5: Nil | R5: Athi | S5: Nil | T5: https://dev.azure.com/heartlandschools/Activities/_git/Activities/pullrequest/46263 | U5: 46008 | V5: 46011 | W5: Done | X5: Nil | Y5: Done | Z5: 46013 | AA5: Nil | AB5: NA | AC5: NA | AD5: NA | AE5: Meets Expectation
A6: 5 | B6: MSB Activities | C6: 46008 | D6: 46035 | E6: 26.2 Sprint S2 | F6: Sivaraja | G6: 51079 | H6: Activities - Admin - Upgrade Existing Audit Log to a Table Grid for 'Activities' | I6: Story Completed | J6: 2 | K6: 1 | L6: 3 | M6: 45995 | N6: 45996 | O6: Done | P6: Ram | Q6: Nil | R6: Ram, Kaliammal | S6: Nil | T6: https://dev.azure.com/heartlandschools/Activities/_git/Activities/pullrequest/46162 | U6: 46002 | V6: 46002 | W6: Done | X6: Nil | Y6: Done | Z6: 46008 | AA6: I don't know if we have the ability to do any better, but this would show us the current name of the custom field, not what it was named when it was added, correct? This could cause confusion if fields have been renamed. Is the name not stored as a part of the audit log? | AB6: Approved | AC6: Approved | AD6: NA | AE6: Meets Expectation
A7: 6 | B7: MSB Activities | C7: 46008 | D7: 46035 | E7: 26.2 Sprint S2 | F7: Kaliammal | G7: 51093 | H7: Activities - Admin - Upgrade Existing Audit Log to a Table Grid for 'Custom Fields' | I7: Story Completed | J7: 2 | K7: 1 | L7: 4 | M7: 45995 | N7: 46000 | O7: Done | P7: Sivaraja | Q7: Nil | R7: Athi,Sivaraja | S7: Nil | T7: https://dev.azure.com/heartlandschools/Activities/_git/Activities/pullrequest/46163 https://dev.azure.com/heartlandschools/Activities/_git/Activities/pullrequest/46355 | U7: 46002 | V7: 46002 | W7: Done | X7: Nil | Y7: Done | Z7: 46001 | AA7: I don't know if we have the ability to do any better, but this would show us the current name of the custom field, not what it was named when it was added, correct? This could cause confusion if fields have been renamed. Is the name not stored as a part of the audit log? | AB7: Approved | AC7: Approved | AD7: NA | AE7: Meets Expectation
A8: 7 | B8: MSB Activities | C8: 46008 | D8: 46035 | E8: 26.2 Sprint S2 | F8: Nathiya | G8: 51175 | H8: Activities - Admin - Integrate the Data into Universal Search for Student Maintenanace | I8: Story Completed | J8: 8 | K8: 5.5 | L8: 22 | M8: 46008 | N8: 46013 | O8: Done | P8: Sivaraja | Q8: Nil | R8: Athi,Sivaraja | S8: Nil | T8: https://dev.azure.com/heartlandschools/Activities/_git/Activities/pullrequest/46417 | U8: 46027 | V8: 46028 | W8: Allen | X8: Nil | Y8: Andy | Z8: 46029 | AA8: Nil | AB8: Given POV comments. | AC8: Approved | AD8: NA | AE8: Meets Expectation
A9: 8 | B9: MSB Activities | C9: 46008 | D9: 46035 | E9: 26.2 Sprint S2 | F9: Manju/Siva | G9: 51217 | H9: Activities - SYSTEM - Automation [Timeboxed] | I9: Story Completed | J9: 13 | K9: 13 | L9: 16 | M9: 46013 | N9: 46035 | O9: NA | P9: NA | Q9: NA | R9: NA | S9: NA | T9: NA | U9: NA | V9: NA | W9: NA | X9: NA | Y9: NA | Z9: NA | AA9: NA | AB9: NA | AC9: NA | AD9: NA | AE9: Meets Expectation
A10: 9 | B10: MSB Activities | C10: 46008 | D10: 46035 | E10: 26.2 Sprint S2 Stretch | F10: Nathiya | G10: 51186 | H10: Activities - Admin - Display a Spinning Loader instead of Message for (Purchases & Fees) Tab | I10: Story Completed | J10: 2 | K10: 1 | L10: 4 | M10: 46014 | N10: 46014 | O10: Done | P10: Ram | Q10: Nil | R10: Ram, Kaliammal | S10: Nil | T10: https://dev.azure.com/heartlandschools/Activities/_git/Activities/pullrequest/46213 | U10: 46006 | V10: 46030 | W10: Allen | X10: Nil | Y10: Andy | Z10: 46030 | AA10: Nil | AB10: Approved | AC10: Approved | AE10: Meets Expectation
A11: 10 | B11: MSB Activities | C11: 46008 | D11: 46035 | E11: 26.2 Sprint S2 Stretch | F11: Allen | G11: 51279 | H11: Activities - Kaleida - Update table grid design for Term Maintenance | I11: Story Peer Review | J11: 8 | K11: 6 | L11: 24 | M11: 46008 | N11: 46014 | O11: Done | P11: Ram | Q11: Nil | R11: Ram | S11: NIL | T11: NA | U11: NA | V11: NA | W11: NA | X11: NA | Y11: NA | Z11: NA | AA11: NA | AB11: NA | AC11: NA | AD11: Development has been completed, but the PR is delayed due to pending confirmation from the client. As discussed with the client, we planned to merge the data table grid changes into a separate branch instead of Master. Today, the client developer created a new branch to merge these changes. The testing effort may be carried out after the regression sprint. | AE11: Meets Expectation
A12: 11 | B12: MSB Activities | C12: 46008 | D12: 46035 | E12: 26.2 Sprint S2 Stretch | F12: Nathiya | G12: 51335 | H12: Activities - Students - Update Nickname column label | I12: Story Completed | J12: 1 | K12: 0.5 | L12: 2 | M12: 46013 | N12: 46013 | O12: Done | P12: Sivaraja | Q12: Nil | R12: Athi,Sivaraja | S12: Nil | T12: https://dev.azure.com/heartlandschools/Activities/_git/Activities/pullrequest/46417 | U12: 46027 | V12: 46028 | W12: Allen | X12: Nil | Y12: Andy | Z12: 46029 | AA12: Nil | AB12: Approved | AC12: Approved | AD12: NA | AE12: Meets Expectation
A13: 12 | B13: MSB Activities | C13: 46008 | D13: 46035 | E13: 26.2 Sprint S2 Stretch | F13: Sivaraja | G13: 47410 | H13: Activities - DISCOVERY - Activity Pricing for Prepaid Enrollment Plans | I13: Story Completed | J13: 8 | K13: 6.5 | L13: 26 | M13: 46020 | N13: 46034 | O13: NA | P13: NA | Q13: NA | R13: NA | S13: NA | T13: NA | U13: NA | V13: NA | W13: NA | X13: NA | Y13: NA | Z13: NA | AA13: NA | AB13: NA | AC13: NA | AD13: NA | AE13: Meets Expectation
A14: 13 | B14: MSB Activities | C14: 46008 | D14: 46035 | E14: 26.2 Sprint S2 Stretch | F14: Kaliammal | G14: 51367 | H14: Activities - Kaleida - Update table grid design for Enrollment Plans/ Activities/ Discounts | I14: Story Peer Review | J14: 8 | K14: 5 | L14: 20 | M14: 46022 | N14: 46034 | O14: Done | P14: Sivaraja,Nathiya | Q14: Nil | R14: Sivaraja,Nathiya | S14: Nil | T14: NA | U14: NA | V14: NA | W14: NA | X14: NA | Y14: NA | Z14: NA | AA14: NA | AB14: NA | AC14: NA | AD14: Development has been completed, but the PR is delayed due to pending confirmation from the client. As discussed with the client, we planned to merge the data table grid changes into a separate branch instead of Master. Today, the client developer created a new branch to merge these changes. The testing effort may be carried out after the regression sprint. | AE14: Meets Expectation

Sheet 26.2 Sprint 2- Defects
A1: S.No | B1: Sprint # | C1: Story/Defect ID | D1: Parent Story | E1: Developer | F1: Issue Type | G1: Issue Description | H1: Root Cause Analysis | I1: Priority | J1: Defect Source | K1: Type | L1: Status | M1: Root Cause Category | N1: Comments | O1: Defect Raised
A2: 1 | B2: 26.2 Sprint S2 | C2: 51093 | D2: 51093 | E2: Kaliammal | F2: Bounceback/Sub-Defect | G2: First column should be field Column in table grid and in custom column header, But when we apply custom column header order changes. | H2: NA | I2: Significant | J2: Manual | K2: Internal | L2: Story Completed | M2: Development | N2: Story Bounceback | O2: Manjunath - Offshore QA
A3: 2 | B3: 26.2 Sprint S2 | C3: 51079 | D3: 51079 | E3: Kaliammal | F3: Bounceback/Sub-Defect | G3: First column should be field Column in table grid and in custom column header, But when we apply custom column header order changes. | H3: NA | I3: Significant | J3: Manual | K3: Internal | L3: Story Completed | M3: Development | N3: Story Bounceback | O3: Manjunath - Offshore QA
A4: 3 | B4: 26.2 Sprint S2 | C4: 47253 | D4: 47253 | E4: Kaliammal | F4: Bounceback/Sub-Defect | G4: when selecting columns and then navigating away and back, the selector no longer shows the columns selected (but columns do show)(see image) | H4: NA | I4: Minor | J4: Manual | K4: Internal | L4: Story Completed | M4: Development | N4: Story Bounceback | O4: Jeff - Onshore QA

Sheet 26.2 Sprint S1-Status
A1: S.No | B1: Application Name | C1: Sprint Start Date | D1: Sprint End Date | E1: Sprint | F1: Developer | G1: Story ID/Defect ID | H1: Description | I1: Status | J1: Estimated(sp) | K1: Actual(sp) | L1: Actual Hours Worklog | M1: Dev Start Date | N1: Dev End Date | O1: Unit testing | P1: Peer Tested By | Q1: Peer Tested Comments, if any | R1: Peer Reviewed By | S1: Peer Code Review Comments, if any | T1: PR Number/Link | U1: PR Created Date | V1: PR Approved Date | W1: Onsite Lead Code Review | X1: Onsite Lead Code Review Comments, if any | Y1: Client Code Review | Z1: PR Approved Date2 | AA1: Client Code Review Comments, if any | AB1: Internal PO -POV Comments | AC1: Client PO -POV Comments | AD1: Comments | AE1: Does this story Meet Expectations?
A2: 1 | B2: MSB Activities | C2: 45994 | D2: 46007 | E2: 26.2 Sprint S1 | F2: Sivaraja | G2: 45772 | H2: Activities - Admin - Term - Tech Debt Field Validation | I2: Story Completed | J2: 1 | K2: 0.5 | L2: 2.5 | M2: 45994 | N2: 45994 | O2: Done | P2: Ram, Kaliammal | Q2: Nil | R2: Ram, Kaliammal | S2: Nil | T2: https://dev.azure.com/heartlandschools/Activities/_git/Activities/pullrequest/46062 | U2: 45995 | V2: 45995 | W2: Done | X2: Nil | Y2: Done | Z2: 45996 | AA2: Nil | AB2: Approved | AC2: Approved | AD2: NA | AE2: Meets Expectation
A3: 2 | B3: MSB Activities | C3: 45994 | D3: 46007 | E3: 26.2 Sprint S1 | F3: Kaliammal | G3: 51052 | H3: Activities - SYSTEM - Removing the Original Description Columns [PR & QA] | I3: Story Completed | J3: 1 | K3: 1 | L3: 6 | M3: 45980 | N3: 45989 | O3: Done | P3: Sivaraja,Athi | Q3: Include Report Changes | R3: Sivaraja,Athi | S3: Nil | T3: https://dev.azure.com/heartlandschools/Activities/_git/Activities/pullrequest/45981 | U3: 45992 | V3: 45993 | W3: Done | X3: Nil | Y3: Done | Z3: 45996 | AA3: Nil | AB3: NA | AC3: NA | AD3: NA | AE3: Meets Expectation
