Workbook

Sheet Dashboard-2025
A1: Current Sprint | B1: {=INDEX($B$2:$B$65,MATCH(1,(($D$2:$D$65 >=TODAY())*($C$2:$C$65<=TODAY())),0))} -> #N/A | C1: Current Sprint Sheet | D1: =CONCATENATE(B1,"-Status") -> #N/A | E1: Sprint Start Date | F1: =VLOOKUP($B$1,$B$1:$C$110,2) -> #N/A | G1: Sprint End Date | I1: =VLOOKUP($B$1,$B$1:$D$65,3) -> #N/A | J1: Application Name | K1: FOH Wave | L1: Users | M1: sabir.shaikh@relevantz.com;subbulakshmi.namasivayam@relevantz.com;vidhya.subramani@relevantz.com;balamurugan.kandasamy@relevantz.com | N1: Teams Name
A2: Sprint Type | B2: Sprint # | C2: Sprint Start Date | D2: Sprint End Date | E2: Assigned | F2: Completed | G2: Story points introduced/removed | H2: Sprint Summary | I2: Accomplishments | J2: Remarks | K2: Retro Points (Internal & External) | L2: Planned Leave | M2: Total Leave | N2: Data sanity Audit Status | O2: AuditDate
A3: =IF(AND($D$1>=C3,$D$1<=D3),"CurrentSprint","NA") -> #N/A | B3: 4.22 - Sprint 2 | C3: 45786 | D3: 45799 | E3: 30 | F3: 38 | G3: Introduced - 8 | I3: Adding new templates to Custom Reports, Tier Model, State Level EIG updates, and Admin View of Real Time Transactions updates. | J3: CRC Internal -- 1 CRC External -- 0 QA Defects -- 1 Escaped Defects -- 0 Stretch Story: 0 | K3: Internal: External:
A4: =IF(AND($D$1>=C4,$D$1<=D4),"CurrentSprint","NA") -> #N/A | B4: 4.22 - Sprint 3 | C4: 45800 | D4: 45813 | E4: 40 | F4: 37.75 | G4: Nil | I4: Cutom Report for Eligibility Student Listing | J4: CRC Internal -- 0 CRC External -- 0 QA Defects -- 0 Escaped Defects -- 0 Stretch Story: 3 | K4: Internal: External:
A5: =IF(AND($D$1>=C5,$D$1<=D5),"CurrentSprint","NA") -> #N/A | B5: 4.23 - Sprint 1 | C5: 45814 | D5: 45826 | E5: 10 | F5: 10 | G5: Introduced - 21 | J5: CRC Internal -- 2 CRC External -- 0 QA Defects -- 0 Escaped Defects -- 0 Stretch Story: 4 | K5: Internal: External:
A6: =IF(AND($D$1>=C6,$D$1<=D6),"CurrentSprint","NA") -> #N/A | B6: 4.23 - Sprint 2 | C6: 45827 | D6: 45841 | E6: 20 | F6: 20 | G6: Introduced - 16 | I6: Supplemental Programs Claim Report | J6: CRC Internal -- 1 CRC External -- 0 QA Defects -- 1 Escaped Defects -- 0 Stretch Story: 3 | K6: Internal: External:
A7: =IF(AND($D$1>=C7,$D$1<=D7),"CurrentSprint","NA") -> #N/A | B7: 4.23 - Sprint 3 | C7: 45842 | D7: 45855 | E7: 14 | F7: 14 | G7: Introduced-7 | I7: Custom Report for Transaction History, Modifications to Louisiana SFS-8C Report | J7: CRC Internal -- 4 CRC External -- 0 QA Defects -- 1 Escaped Defects -- 0 Stretch Story: 4 | K7: Internal: External: What went well: Successfully completed the assigned stories What didn't go well: Nil
A8: =IF(AND($D$1>=C8,$D$1<=D8),"CurrentSprint","NA") -> #N/A | B8: 4.23 - Sprint 4 | C8: 45856 | D8: 45869 | E8: 14 | F8: 16 | G8: Introduced - 17 | I8: Defect fixes and 4.23 Regression testing | J8: CRC Internal -- 2 CRC External -- 0 QA Defects -- 1 Escaped Defects -- 0 Stretch Story: 7 | K8: Internal: External: What went well: Successfully completed the Regression testing, Completed the assigned stories What didn't go well: Nil
A9: =IF(AND($D$1>=C9,$D$1<=D9),"CurrentSprint","NA") -> #N/A | B9: 4.24 - Sprint 1 | C9: 45870 | D9: 45883 | E9: 12 | F9: 15 | G9: Introduced - 15 | I9: Support for Credit Card in Additional Meal Programs for Reports,Delete functionality for User Custom Report | J9: CRC Internal -- 11 CRC External -- 0 QA Defects -- 1 Escaped Defects -- 0 Stretch Story: 6 | K9: Internal: External: What went well: Successfully completed the assigned stories What didn't go well: Nil
A10: =IF(AND($D$1>=C10,$D$1<=D10),"CurrentSprint","NA") -> #N/A | B10: 4.24 - Sprint 2 | C10: 45884 | D10: 45897 | E10: 10 | F10: 13 | G10: Introduced - 22 | I10: Dashboard feature for copy and enlarge wiidgets, implemented new datasource in custom report. | J10: CRC Internal -- 1 CRC External -- 0 QA Defects -- 1 Escaped Defects -- 0 Stretch Story: 5 | K10: Internal: External: What went well: Successfully completed the assigned stories. Successfully completed the dashboard related features. What didn't go well: Nil
A11: =IF(AND($D$1>=C11,$D$1<=D11),"CurrentSprint","NA") -> #N/A | B11: 4.24 - Sprint 3 | C11: 45898 | D11: 45911 | E11: 8 | F11: 18 | G11: Introduced - 28 | I11: New Template for Daily Sales Summary Report,Daily Sales By Serving Line Report,Dashboard UI Enhancement and Other Reports Improvements, Automation | J11: CRC Internal -- 1 CRC External -- 0 Peer Testing - 1 POV Comments - 4 QA Defects -- 1 Escaped Defects -- 0 Stretch Story: 7 | K11: Internal: External: What went well: Completed Forecast and lot more, Automation progress, Hosted platforms - SYSU, All schools back in session, Esclation down from previous years (Note: Esclations from coustomer support are handled by client developer Steve) What didn't go well: Lost Ying to BOH team Esclations
A12: =IF(AND($D$1>=C12,$D$1<=D12),"CurrentSprint","NA") -> #N/A | B12: 4.24 - Sprint 4 | C12: 45912 | D12: 45925 | E12: 14 | F12: 15 | G12: Introduced - 11 | I12: Defect fixes and 4.24 Regression testing | J12: "CRC Internal --0 CRC External -- 0 Peer Testing - 3 POV Comments - QA Defects -- 0 Escaped Defects -- 0 Stretch Story: 4" | K12: Internal: External: What went well: Offshore Completed regression and defects including testing, Completed Forecast and more, Defects fixed into releases What didn't go well: Esclations (Note: Esclations from coustomer support are handled by client developer Steve), Added items in last minute to include in release
A13: =IF(AND($D$1>=C13,$D$1<=D13),"CurrentSprint","NA") -> #N/A | B13: 4.25 - Sprint 1 | C13: 45926 | D13: 45939 | E13: 13 | F13: 13 | G13: Introduced - 16 | I13: Modifications to Operating Days, new filter for ‘Participation by’ to Standard Claim Report, and New Template to ‘Daily Sales By Serving Line Report’. | J13: CRC Internal -- 3 CRC External -- 0 Peer Testing - 2 POV Comments - 4 QA Defects -- 1 Escaped Defects -- 0 Stretch Story: 4 | K13: Internal: External: What went well: Completed more than Forecast , Esclations (not too bad this week), mike completed testing before PTO, Team completed rest of testing after Mike PTO What didn't go well: Apigee issue (platformops and apigee team)
A14: =IF(AND($D$1>=C14,$D$1<=D14),"CurrentSprint","NA") -> #N/A | B14: 4.25 - Sprint 2 | C14: 45940 | D14: 45953 | E14: 15 | F14: 21 | G14: Introduced - 18 | H14: New Dashboard Widgets, Ability to flip between Apigee & Existing endpoints, ‘Participation By’ filter to Supplemental Programs Claim Report, Tyler Munis Export Modifications, update to VA SNP-12 Report, Add Active Flag to Student Export Setup, and 4.24 Release Prep | I14: New Dashboard Widgets, ‘Participation By’ filter to Supplemental Programs Claim Report, Updating report format to meet Mosaic standards | J14: CRC Internal -- 0 CRC External -- 0 Peer Testing - 6 POV Comments - 6 QA Defects -- 1 Escaped Defects -- 0 Stretch Story: 6 | K14: Internal: External: What went well: Completed more than Forecast What didn't go well: NA
A15: =IF(AND($D$1>=C15,$D$1<=D15),"CurrentSprint","NA") -> #N/A | B15: 4.25 - Sprint 3 | C15: 45954 | D15: 45967 | E15: 12 | F15: 23 | G15: Introduced - 23 | H15: Adding a Student Debt Chart to the Dashboard, Replacing Master Serving Period with Serving Period Program, New ‘Group By School’ filter to Students w/out an Elig. Determination Report, DC Import Improvements, and NJ Master Eligibility List report Modifications | I15: Export 'User Created Custom Reports', 'User Assignments Report' to meet Mosaic Standard, Legacy imports are moved to Utilities | J15: CRC Internal -- 0 CRC External -- 0 Peer Testing - 1 POV Comments - 6 QA Defects -- 0 Escaped Defects -- 0 Stretch Story: 10 | K15: Internal: External: What went well: Releases, Exceeded Forecast What didn't go well: Esclations (Note: Esclations from coustomer support are handled by client developer Steve)
A16: =IF(AND($D$1>=C16,$D$1<=D16),"CurrentSprint","NA") -> #N/A | B16: 4.25 - Sprint 4 | C16: 45968 | D16: 45981 | E16: 10 | F16: 12 | G16: Introduced - 36 | H16: IL WINS Export Scheduler Task, Importing Custom Report Format, Added new data source to report designer | I16: IL WINS Export Scheduler Task, Importing Custom Report Format, NSS ID in Visual Report, Added new datasource to the Report designer | J16: CRC Internal -- 15 CRC External -- 1 Peer Testing - 3 POV Comments - 2 QA Defects -- 2 Escaped Defects -- 0 Stretch Story: 10 | K16: Internal: External: What went well: Hit Forecast, SNYK progress in stretch What didn't go well: CPS Release, Apigee work, MSB Endpoint Change.
A17: =IF(AND($D$1>=C17,$D$1<=D17),"CurrentSprint","NA") -> #N/A | B17: 4.25 - Sprint 5 | C17: 45982 | D17: 46009 | E17: 23 | F17: 37 | G17: Introduced - 37 | H17: New Templates for Custom Reports, New Data Sources for Report Designer, and 4.25 Regression Testing | I17: Completed 4.25 regression testing with defect fixes. | J17: CRC Internal -- 2 CRC External -- 0 QA Defects -- 2 Escaped Defects -- 0 Stretch Story: 8 Defects RC: 1. Calculation mismatch not captured in unit testing. 2. It is the data issue which occurred in other developer's DB. It is handled now. Internal CRC comments RC: 1. Missed to ensure SQL script file naming standards 2. Misunderstood the acceptance criteria | K17: Internal: External: What went well: Insane no.of stories completed(Sp's), started using Browser Stack for automation. What didn't go well: Escalations, MSB Endpoint Change.

Sheet Defect-template
A1: S.No | B1: Sprint # | C1: Story/Defect ID | D1: Parent Story | E1: Developer | F1: Issue Type | G1: Issue Description | H1: Priority | I1: Defect Source | J1: Type | K1: Status | L1: Root Cause Category | M1: Comments

Sheet Dashboard
A1: Current Sprint | B1: {=INDEX($B$2:$B$48,MATCH(1,(($D$2:$D$48 >=TODAY())*($C$2:$C$48<=TODAY())),0))} -> 26.07 Sprint 1 | C1: Current Sprint Sheet | D1: =CONCATENATE(B1,"-Status") -> 26.07 Sprint 1-Status | E1: Sprint Start Date | F1: =VLOOKUP($B$1,$B$1:$C$120,2) -> 46136 | G1: Sprint End Date | H1: =VLOOKUP($B$1,$B$1:$D$120,3) -> 46163 | I1: Application Name | J1: FOH Wave | K1: Users | L1: sabir.shaikh@relevantz.com;subbulakshmi.namasivayam@relevantz.com;vidhya.subramani@relevantz.com;balamurugan.kandasamy@relevantz.com | M1: Teams Name(GP - FOH Acceleration Initiative) | N1: 19:e340939441a74ca5938ca3ad602ee553@thread.v2
A2: Sprint Type | B2: Sprint # | C2: Sprint Start Date | D2: Sprint End Date | E2: Assigned | F2: Completed | G2: Story points introduced/removed | H2: Sprint Summary | I2: Accomplishments | J2: Remarks | K2: Retro Points (Internal & External) | L2: Planned Leaves | M2: Total Leaves | N2: Data sanity Audit Status | O2: AuditDate | P2: Backlog Health
A3: =IF(AND($D$1>=C3,$D$1<=D3),"CurrentSprint","NA") -> NA | B3: 26.1 - Sprint 1 | C3: 46010 | D3: 46037 | E3: 27 | F3: 32 | G3: Introduced - 30 | H3: Support for Multiple Languages in SL, Automation, Meal Count Entry Audit Report, Feature flag changes | I3: Completed Support for Multiple Languages in SL, Automation, Meal Count Entry Audit Report, Feature flag changes | J3: CRC Internal -- 24 CRC External -- 2 QA Defects -- 4 Escaped Defects -- 0 Stretch Story: 9 Defects RC: 1. Missed UI validation for the textbox. 2. Missed to handle the scenario of enable/disable Language feature flag. 3. Missed to test around the UI changes 4. Missed to check Parent table column's lenght and Language tables column's length Internal CRC comments RC: 1. Missed UI validations 2. Missed SQL script file standards 3. Missed to ensure date format 4. Not keeping common table name in SQL script 5. Some implicit stuff needs to be incorporated as part of the requirement which I'm not aware of 6. I missed to clean up or refactor some portion of the SQL code | K3: What went well: Completed the forecast and almost the same in the stretch. 2. Holidays. 3. 502 gateway Apigee issues solving (prod) What didn't go well: 365 migration, MSB from www to etransfer issue.
A4: =IF(AND($D$1>=C4,$D$1<=D4),"CurrentSprint","NA") -> NA | B4: 26.1 - Sprint 2 | C4: 46038 | D4: 46051 | E4: 17 | F4: 17 | G4: Introduced - 0 | H4: Updates to Meal Report and User Report, Mosaic BOH Knowledge transfer | I4: Completed the Mosaic Standards for User Reports and Meals Reports, Mosaic BOH Knowledge transfer | J4: CRC Internal -- 0 CRC External --0 QA Defects -- 1 Escaped Defects -- 0 Stretch Story: 0 Defects RC: 1. Pre existing UI design which was there originally. PO wanted to fix it as part of this story hence it was fixed. Internal CRC comments RC: None | K4: Internal: External: What went well: Completed commit and stretch items. 2. 4.24 Hot fix/4.25 Beta 3. BOH KT What didn't go well: 1. Vending QA, 2. Missing App switcher script in 4.25 Beta 3. App switcher button is not always working. Recieved appretiaton from QA during retro that offshore helped to close the testing stories during the sprint end.
A5: =IF(AND($D$1>=C5,$D$1<=D5),"CurrentSprint","NA") -> NA | B5: 26.1 - Sprint 3 | C5: 46052 | D5: 46065 | E5: 5 | F5: 16 | G5: Introduced - 30 | H5: Modified Prepay Report to Mosaic Standard, Defect Fixes, Hide Tier Feature from UI BOH Reverse KT, Automation | I5: Completed the Prepay Report to meet Mosaic Standard, BOH Reverse KT | J5: CRC Internal -- 0 Peer testing - 1 CRC External -- 0 QA Defects -- 2 Escaped Defects -- 0 POV Comments - 5 Stretch Story: 13 CRC RC: Nil Defects RC: 1. css styling not handled and so improper visual spacing between UI components occured 2. Missed to show proper version format | K5: "Internal: External: What went well: 1. Exceeded the forcast story points. 2. 4.25 release. What didn't go well: 1. Escalations, 2. 4.25 rused out(App switcher not working), 3. Dashboard issues." | L5: 0 | M5: 1
A6: =IF(AND($D$1>=C6,$D$1<=D6),"CurrentSprint","NA") -> NA | B6: 26.1 - Sprint 4 | C6: 46066 | D6: 46079 | E6: 2 | F6: 4 | G6: Introduced - 26 | H6: Add New Security page for Report Designer, Edit Report button to the Custom Reports UI, Automation | I6: Completed the Report Designer feature in Security Page | J6: CRC Internal -- 0 Peer testing - 0 CRC External -- 0 QA Defects -- 0 Escaped Defects -- 0 POV Comments - 0 Stretch Story: 4 CRC RC: Nil Defects RC: Nil | K6: Internal: External: What went well: 1. Offshore work on regression, 2. Hosted Test environment(Mike getting builds up) What didn't go well: 1. SQL cypher(Not working with .460) | L6: 1 | M6: 5
A7: =IF(AND($D$1>=C7,$D$1<=D7),"CurrentSprint","NA") -> NA | B7: 26.05 Sprint 1 | C7: 46080 | D7: 46093 | E7: 6 | F7: 8 | G7: Introduced - 20 | H7: User Tasks Maintenance and Setup, Automation | I7: Added User Tasks Maintenance and Setup screen, Automation | J7: CRC Internal -- 5 Peer testing - 3 CRC External -- 0 QA Defects -- 15 Escaped Defects -- 0 POV Comments - 6 Stretch Story: 4 CRC RC: 1. Missed to follow localization support (2) 2. Missed to follow exsiting coding standards (1) 3. unwanted code (1) 4. returning entity directly (1) Defects RC: 1. UI validations should be added properly (4) 2. UI design issues (8) 3. Data issue (3) | K7: Internal: External: What went well: 1. Exceeded commit, 2. SQLCypher progress, 3. Regression completed on time | L7: 3 | M7: 5
A8: =IF(AND($D$1>=C8,$D$1<=D8),"CurrentSprint","NA") -> NA | B8: 26.05 Sprint 2 | C8: 46094 | D8: 46107 | E8: 13 | F8: 13 | G8: Introduced - 27 | H8: User Assignment in User Task, Mosaic BOH - Transfers - Bulk Replace, Automation | I8: User Assignment in User Task, Mosaic BOH - Transfers - Bulk Replace, Add, Delete | J8: "CRC Internal -- 1 Peer testing - 4 CRC External -- 0 QA Defects -- 3 Escaped Defects -- 0 POV Comments - 11 Stretch Story: 6 CRC RC: 1. Missed to remove the unwanted code Defects RC: 1. UI design issues 2. Backend validation did not match the UI validation. (2) POV RC: Cosmetic changes (4) Sugeestions (3) Data issue (2) | K8: Internal: External: What went well: 1. 26.1 Release 2. Exceeded commit What didn't go well: Apigee & WAF issues | L8: 3 | M8: 4.5
A9: =IF(AND($D$1>=C9,$D$1<=D9),"CurrentSprint","NA") -> NA | B9: 26.05 Sprint 3 | C9: 46108 | D9: 46121 | E9: 20 | F9: 12 | G9: Introduced - 16 | H9: Review Task in User Task,Bidding - Allow vendors to indicate "No Response",ER Improve the Search functionality,Automation | I9: Review Task in User Task,Bidding - Allow vendors to indicate "No Response",ER Improve the Search functionality | J9: "CRC Internal -- 0 Peer testing - 1 CRC External -- 0 QA Defects -- 4 Escaped Defects -- 0 POV Comments - 3 Stretch Story: 2 CRC RC: NIL Defects RC: 1. UI design issues 2. Add more than 40 user then it gives an error in QA envirornment POV RC: Missed adding logic for bottom-line bidding and checkbox visibility control (2) Data issue (2) Missed to save the value of checkebox | K9: What went well: 1. Exceeded Commit 2. Migration Work 3. Multi Language on POS 4. Offshore Support on QA 5. Defect fixes for 26.1 What didn't go so well? 1. AG's workable | L9: 2 | M9: 2
A10: =IF(AND($D$1>=C10,$D$1<=D10),"CurrentSprint","NA") -> NA | B10: 26.05 Sprint 4 | C10: 46122 | D10: 46135 | E10: 9 | F10: 20 | G10: Introduced - 40 | H10: Review Task in User Task, Ingredients - Search Functionality, 26.5 Regression Testing, Bidding | I10: Completed 26.5 Regression Testing for Setup, User Tasks for Review Task, Ingredients - Search Functionality, Bidding Issues, Transfers - Bulk Add - UI | J10: CRC Internal -- 0 Peer testing - 0 CRC External -- 0 QA Defects -- 0 Escaped Defects -- 0 POV Comments - 0 Stretch Story: 5 CRC RC: Nil Defects RC: Nil POV RC: Nil | K10: What went well: 1. Completed Regression stories assigned in the sprint 2. Fixed all the regression defects 3. No review comments What didn't go well: Nil | L10: 2 | M10: 2
A11: =IF(AND($D$1>=C11,$D$1<=D11),"CurrentSprint","NA") -> NA | B11: 26.07 Sprint 1 | C11: 46136 | D11: 46163

Sheet 26.07 Sprint 1-Status
A1: S.No | B1: Application Name | C1: Sprint Start Date | D1: Sprint End Date | E1: Sprint | F1: Developer/Tester | G1: Story ID/Defect ID | H1: Description | I1: Story Being Developed | J1: Estimated(hrs/sp) | K1: Actual(hrs/sp) | L1: Actual Worklog (Hours) | M1: Dev Start Date | N1: Dev End Date | O1: Unit testing | P1: Peer Tested By | Q1: Peer Tested Comments, if any | R1: Peer Reviewed By | S1: Peer Code Review Comments, if any | T1: PR Number/Link | U1: PR Created Date | V1: PR Approved Date | W1: Onsite Lead Code Review | X1: Code Review Comments, if any | Y1: Client Code Review | Z1: Approved Date | AA1: Code Review Comments, if any2 | AB1: Internal PO -POV Comments | AC1: Client PO -POV Comments | AD1: Comments | AE1: Does this story meet expectations?
A2: 1 | B2: ='Dashboard-2025'!$K$1 -> FOH Wave | C2: 46136 | D2: 46163 | E2: 26.07 Sprint 1 | F2: Balamurugan | G2: 52062 | H2: [Wave]Mosaic BOH - Transfers - Bulk Add (2) - UI Only | I2: Story Being Tested | J2: 8 | K2: 7.5 | L2: 30 | M2: 46142 | N2: 46149 | O2: Balamurugan | P2: Rajiv Gandhi Sugumaran | Q2: NA | R2: Rajiv Gandhi Sugumaran | S2: NA | T2: 48943 | U2: 46150 | V2: 46154 | W2: Charles | X2: NA | Y2: NA | Z2: NA | AA2: NA | AB2: NA | AC2: NA
A3: 2 | B3: FOH Wave | C3: 46136 | D3: 46163 | E3: 26.07 Sprint 1 | F3: Sabir | G3: 47770 | H3: [WAVE] Mosaic BOH - (7) User Task List - End User UI | I3: Story Peer Review | J3: 8 | K3: 7.5 | L3: 30 | M3: 46136 | N3: 46149 | O3: Sabir | P3: Krupa Bhatkar | R3: Krupa Bhatkar | T3: 49014 | U3: 46154
A4: 3 | B4: FOH Wave | C4: 46136 | D4: 46163 | E4: 26.07 Sprint 1 | F4: Balamurugan | G4: 52178 | H4: [Wave]Mosaic BOH - Transfers - Bulk Add (2) - Data Retrieval | I4: Story Being Tested | J4: 8 | K4: 7.5 | L4: 30 | M4: 46136 | N4: 46149 | O4: Balamurugan | P4: Rajiv Gandhi Sugumaran | Q4: NA | R4: Rajiv Gandhi Sugumaran | S4: NA | T4: 48943 | U4: 46150 | V4: 46154 | W4: Charles | X4: NA | Y4: NA | Z4: NA | AA4: NA | AB4: NA | AC4: NA
A5: 4 | B5: FOH Wave | C5: 46136 | D5: 46163 | E5: 26.07 Sprint 1 | F5: Subbulakshmi | G5: 52915 | H5: Add an 'Aramark Financial Export' Scheduler Task Step | I5: Story Completed | J5: 2 | K5: 1 | L5: 4 | M5: 46139 | N5: 46155 | O5: NA | P5: NA | Q5: NA | R5: NA | S5: NA | T5: NA | U5: NA | V5: NA | W5: NA | X5: NA | Y5: NA | Z5: NA | AA5: NA | AB5: NA | AC5: NA | AD5: NA | AE5: NA
A6: 5 | B6: FOH Wave | C6: 46136 | D6: 46163 | E6: 26.07 Sprint 1 | F6: Subbulakshmi | G6: 52827 | H6: Update Federal IEGs (2026-27) | I6: Story Completed | J6: 1 | K6: 1 | L6: 4 | M6: 46140 | N6: 46140 | O6: NA | P6: NA | Q6: NA | R6: NA | S6: NA | T6: NA | U6: NA | V6: NA | W6: NA | X6: NA | Y6: NA | Z6: NA | AA6: NA | AB6: NA | AC6: NA | AD6: NA | AE6: NA
A7: 6 | B7: FOH Wave | C7: 46136 | D7: 46163 | E7: 26.07 Sprint 1 Stretch | F7: Pradeepa | G7: 47412 | H7: [WAVE] Mosaic BOH - Vendor Invoice Management - Create new Vendor Invoice Import Template 1 | I7: Story Being Developed | J7: 8 | K7: 12 | L7: 48 | M7: 46140
A8: 7 | B8: FOH Wave | C8: 46136 | D8: 46163 | E8: 26.07 Sprint 1 | F8: Subbulakshmi | G8: 52256 | H8: Open Previous Day Maintenance - Add Multiselect Site & Convert Screen to Vega | I8: Story Being Tested | J8: 1 | K8: 1 | L8: 4 | M8: 46141 | AD8: Need to test in Hosted Environment
A9: 8 | B9: FOH Wave | C9: 46136 | D9: 46163 | E9: 26.07 Sprint 1 Stretch | F9: Subbulakshmi | G9: 53098 | H9: MFOH [BAU] - Automation (46670) | I9: Story Being Developed | J9: 2 | K9: 2 | L9: 8 | M9: 46142
A10: 9 | B10: FOH Wave | C10: 46136 | D10: 46163 | E10: 26.07 Sprint 1 Stretch | F10: Sabir | G10: 29833 | H10: [WAVE] Mosaic BOH - Recipes - Search for Recipes that Contain or Do Not Contain Specified Allergens (CPS C0030) | I10: Story Being Developed | J10: 8 | K10: 7.5 | L10: 30 | M10: 46147
A11: 10 | B11: FOH Wave | C11: 46136 | D11: 46163 | E11: 26.07 Sprint 1 Stretch | F11: Subbulakshmi | G11: 53138 | H11: MFOH - Automation (51180) | I11: Story Completed | J11: 2 | K11: 2 | L11: 8 | M11: 46147 | N11: 46147 | O11: Subbulakshmi | P11: NA | Q11: NA | R11: NA | S11: NA | T11: 48897 | U11: 05/072026 | V11: 46147 | W11: NA | X11: NA | Y11: Steve | Z11: NA | AA11: NA | AB11: NA | AC11: NA | AD11: NA | AE11: NA
A12: 11 | B12: FOH Wave | C12: 46136 | D12: 46163 | E12: 26.07 Sprint 1 Stretch | F12: Balamurugan | G12: 45251 | H12: Mosaic BOH - Vendors - Add a setting to make invoice # mandatory on receiving orders | I12: Story Peer Review | J12: 5 | K12: 4.5 | L12: 18 | M12: 46150 | N12: 46155 | O12: Balamurugan | P12: Rajiv Gandhi Sugumaran | Q12: 1. Add the below script in Script.PostDeployment1.Sql - A script for adding a new column has been included in PostDeployment1.sql. | R12: Rajiv Gandhi Sugumaran | S12: NA | T12: 49027 | U12: 05/132026 | AB12: NA | AC12: NA
A13: 12 | B13: FOH Wave | C13: 46136 | D13: 46163 | E13: 26.07 Sprint 1 Stretch | F13: Subbulakshmi | G13: 53172 | H13: MFOH [WAVE] - Automation (51785) | I13: Story Completed | J13: 1 | K13: 1 | L13: 4 | M13: 46154 | N13: 46155 | O13: Subbulakshmi | P13: NA | Q13: NA | R13: NA | S13: NA | T13: 49052 | U13: 46156 | V13: 46156 | W13: NA | X13: NA | Y13: Ying | Z13: NA | AA13: NA | AB13: NA | AC13: NA | AD13: NA | AE13: NA
A14: 13 | B14: FOH Wave | C14: 46136 | D14: 46163 | E14: 26.07 Sprint 1 Stretch | F14: Sabir | G14: 52731 | H14: [WAVE] Mosaic BOH - Ingredients - Contains no known Allergens impacts | I14: Story Being Developed | J14: 8 | K14: 3 | L14: 12 | M14: 46155
A15: 14 | B15: FOH Wave | C15: 46136 | D15: 46163 | E15: 26.07 Sprint 1 Stretch | F15: Balamurugan | G15: 52146 | H15: Mosaic BOH - Transfers - Bulk Remove Item (3) | I15: Story Approved | J15: 13 | M15: 46155

Sheet 26.07 Sprint 1-Defect
A1: S.No | B1: Sprint # | C1: Story/Defect ID | D1: Parent Story | E1: Developer | F1: Issue Type | G1: Issue Description | H1: Priority | I1: Defect Source | J1: Type | K1: Status | L1: Dev Start Date | M1: Dev End Date | N1: Root Cause Category | O1: Comments
B2: 26.07 Sprint 1 | C2: 52256 | D2: 52256 | E2: Venkatesan | F2: Bounceback/Sub-Defect | G2: Schools listed based on School Group (1-All Schools), but School Group is not available in Open Previous day Maintenance screen. | H2: Significant | I2: Manual | J2: Internal | K2: Story Being Developed | L2: 46141 | N2: Data Issue
B3: 26.07 Sprint 1 | C3: 52062 | D3: 52062 | E3: Balamurugan | F3: Bounceback/Sub-Defect | G3: 1. Asterisk symbol is missing in Sending Site Field 2. If I click on Find and select a product, then reset and cancel it, the Products popup appears again. | H3: Minor | I3: Manual | J3: Internal | K3: Story Being Developed | L3: 46156 | N3: Design Issue

Sheet 26.05 Sprint 4-Status
A1: S.No | B1: Application Name | C1: Sprint Start Date | D1: Sprint End Date | E1: Sprint | F1: Developer/Tester | G1: Story ID/Defect ID | H1: Description | I1: Story Being Tested | J1: Estimated(hrs/sp) | K1: Actual(hrs/sp) | L1: Actual Worklog (Hours) | M1: Dev Start Date | N1: Dev End Date | O1: Unit testing | P1: Peer Tested By | Q1: Peer Tested Comments, if any | R1: Peer Reviewed By | S1: Peer Code Review Comments, if any | T1: PR Number/Link | U1: PR Created Date | V1: PR Approved Date | W1: Onsite Lead Code Review | X1: Code Review Comments, if any | Y1: Client Code Review | Z1: Approved Date | AA1: Code Review Comments, if any2 | AB1: Internal PO -POV Comments | AC1: Client PO -POV Comments | AD1: Comments | AE1: Does this story meet expectations?
A2: 1 | B2: FOH Wave | C2: 46122 | D2: 46135 | E2: 26.05 Sprint 4 | F2: Subbulakshmi | G2: 51845 | H2: [WAVE] Mosaic BOH - (6) User Tasks - Review Task Setup | I2: Story Completed | J2: 1 | K2: 1 | L2: 4 | M2: 46122 | N2: 46125 | O2: NA | P2: NA | Q2: NA | R2: NA | S2: NA | T2: NA | U2: NA | V2: NA | W2: NA | X2: NA | Y2: NA | Z2: NA | AA2: NA | AB2: NA | AC2: NA | AD2: NA | AE2: NA
A3: 2 | B3: FOH Wave | C3: 46122 | D3: 46135 | E3: 26.05 Sprint 4 | F3: Subbulakshmi | G3: 52797 | H3: Mosaic - FOH 26.5(Regression) - Setup | I3: Story Completed | J3: 8 | K3: 5.75 | L3: 23 | M3: 46125 | N3: 46129 | O3: NA | P3: NA | Q3: NA | R3: NA | S3: NA | T3: NA | U3: NA | V3: NA | W3: NA | X3: NA | Y3: NA | Z3: NA | AA3: NA | AB3: NA | AC3: NA | AD3: NA | AE3: NA
A4: 3 | B4: ='Dashboard-2025'!$K$1 -> FOH Wave | C4: 46122 | D4: 46135 | E4: 26.05 Sprint 4 Stretch | F4: Balamurugan | G4: 52062 | H4: [Wave]Mosaic BOH - Transfers - Bulk Add (2) - UI Only | I4: Story Being Developed | J4: 8 | K4: =Table245689102121314111617111819202115222324252627282930313233343536[[#This Row],[Actual Worklog (Hours)]] / 4 -> 6 | L4: 24 | M4: 46122 | N4: NA | O4: NA | P4: NA | Q4: NA | R4: NA | S4: NA | T4: NA | U4: NA | V4: NA | W4: NA | X4: NA | Y4: NA | Z4: NA | AA4: NA | AB4: NA | AC4: NA | AD4: NA | AE4: NA
A5: 4 | B5: ='Dashboard-2025'!$K$1 -> FOH Wave | C5: 46122 | D5: 46135 | E5: 26.05 Sprint 4 Stretch | F5: Sabir | G5: 52044 | H5: [WAVE] Mosaic BOH - Ingredients - Search for Ingredients that Do Not Contain Specified Allergens | I5: Story Completed | J5: 8 | K5: 4 | L5: 16 | M5: 46122 | N5: 46127 | O5: Sabir | P5: Rajiv | Q5: NA | R5: Rajiv | S5: NA | T5: 48420 | U5: 46127 | V5: 46129 | W5: Charles | X5: NA | Y5: NA | Z5: 46129 | AA5: NA | AB5: NA | AC5: NA | AD5: NA | AE5: meet expectation
A6: 5 | B6: FOH Wave | C6: 46122 | D6: 46135 | E6: 26.05 Sprint 4 Stretch | F6: Balamurugan | G6: 27176 | H6: MFOH - BOH WAVE - Fix the issues in bidding that showed up from the changes done in 52172 | I6: Defect Fixed | J6: 3 | K6: 3 | L6: 12 | M6: 46125 | N6: 46129 | O6: Balamurugan | P6: NA | Q6: NA | R6: NA | S6: NA | T6: 48489 | U6: 46129 | V6: 46132 | W6: Charles | X6: NA | Y6: NA | Z6: NA | AA6: NA | AB6: NA | AC6: NA | AD6: NA | AE6: NA
A7: 6 | B7: FOH Wave | C7: 46122 | D7: 46135 | E7: 26.05 Sprint 4 Stretch | F7: Sabir | G7: 47770 | H7: [WAVE] Mosaic BOH - (7) User Task List - End User UI | I7: Story Being Developed | J7: 13 | K7: 5 | L7: 20 | M7: 46128 | N7: NA | O7: NA | P7: NA | Q7: NA | R7: NA | S7: NA | T7: NA | U7: NA | V7: NA | W7: NA | X7: NA | Y7: NA | Z7: NA | AA7: NA | AB7: NA | AC7: NA | AD7: NA | AE7: NA
A8: 7 | B8: FOH Wave | C8: 46122 | D8: 46135 | E8: 26.05 Sprint 4 Stretch | F8: Balamurugan | G8: 52178 | H8: [Wave]Mosaic BOH - Transfers - Bulk Add (2) - Data Retrieval | I8: Story Being Developed | J8: 8 | K8: 4.5 | L8: 18 | M8: 46133 | N8: NA | O8: NA | P8: NA | Q8: NA | R8: NA | S8: NA | T8: NA | U8: NA | V8: NA | W8: NA | X8: NA | Y8: NA | Z8: NA | AA8: NA | AB8: NA | AC8: NA | AD8: NA | AE8: NA

Sheet 26.05 Sprint 4-Defect
A1: S.No | B1: Sprint # | C1: Story/Defect ID | D1: Parent Story | E1: Developer | F1: Issue Type | G1: Issue Description | H1: Priority | I1: Defect Source | J1: Type | K1: Status | L1: Dev Start Date | M1: Dev End Date | N1: Root Cause Category | O1: Comments

Sheet 26.5 - Sprint 3-Status
A1: S.No | B1: Application Name | C1: Sprint Start Date | D1: Sprint End Date | E1: Sprint | F1: Developer/Tester | G1: Story ID/Defect ID | H1: Description | I1: Story Being Tested | J1: Estimated(hrs/sp) | K1: Actual(hrs/sp) | L1: Actual Worklog (Hours) | M1: Dev Start Date | N1: Dev End Date | O1: Unit testing | P1: Peer Tested By | Q1: Peer Tested Comments, if any | R1: Peer Reviewed By | S1: Peer Code Review Comments, if any | T1: PR Number/Link | U1: PR Created Date | V1: PR Approved Date | W1: Onsite Lead Code Review | X1: Code Review Comments, if any | Y1: Client Code Review | Z1: Approved Date | AA1: Code Review Comments, if any2 | AB1: Internal PO -POV Comments | AC1: Client PO -POV Comments | AD1: Comments | AE1: Does this story meet expectations?
A2: 1 | B2: FOH Wave | C2: 46108 | D2: 46121 | E2: 26.5 - Sprint 3 | F2: Subbulakshmi | G2: 26993 | H2: [Wave]Mosaic BOH - Fix the alignment issues with the User Tasks List Search Screen | I2: Defect Fixed | J2: 1 | K2: =Table2456891021213141116171118192021152223242526272829303132333435[[#This Row],[Actual Worklog (Hours)]] / 4 -> 0.5 | L2: 2 | M2: 46108 | N2: 46118 | O2: NA | P2: NA | Q2: NA | R2: NA | S2: NA | T2: NA | U2: NA | V2: NA | W2: NA | X2: NA | Y2: NA | Z2: NA | AA2: NA | AB2: NA | AC2: NA | AD2: NA | AE2: NA
A3: 2 | B3: FOH Wave | C3: 46108 | D3: 46121 | E3: 26.5 - Sprint 3 | F3: Subbulakshmi | G3: 52329 | H3: MFOH - Automation - Kaleida changes update to the Setup - Annual Setup - Nondiscrimination Statement | I3: Story Completed | J3: 1 | K3: =Table2456891021213141116171118192021152223242526272829303132333435[[#This Row],[Actual Worklog (Hours)]] / 4 -> 1 | L3: 4 | M3: 46108 | N3: 46112 | O3: Subbulakshmi | P3: NA | Q3: NA | R3: NA | S3: NA | T3: 48145 | U3: 46112 | V3: 46112 | W3: NA | X3: NA | Y3: Steve | Z3: 46112 | AA3: NA | AB3: NA | AC3: NA | AD3: NA | AE3: NA
A4: 3 | B4: FOH Wave | C4: 46108 | D4: 46121 | E4: 26.5 - Sprint 3 | F4: Sabir | G4: 43501 | H4: [WAVE] Mosaic BOH - ER - Improve the Search functionality | I4: Story Completed | J4: 1 | K4: =Table2456891021213141116171118192021152223242526272829303132333435[[#This Row],[Actual Worklog (Hours)]] / 4 -> 0 | M4: 46108 | N4: 46108 | O4: Sabir | P4: Deepika | Q4: NA | R4: Deepika | S4: NA | T4: 48014 | U4: 46112 | V4: 46112 | W4: Charles | X4: NA | Y4: NA | Z4: 46112 | AA4: NA | AB4: NA | AC4: NA | AD4: NA | AE4: meet expectation
A5: 4 | B5: FOH Wave | C5: 46108 | D5: 46121 | E5: 26.5 - Sprint 3 | F5: Balamurugan | G5: 52172 | H5: [WAVE] Mosaic BOH - Bidding - Allow vendors to indicate "No Response" on line items | I5: Story Completed | J5: 5 | K5: =Table2456891021213141116171118192021152223242526272829303132333435[[#This Row],[Actual Worklog (Hours)]] / 4 -> 7.5 | L5: 30 | M5: 46108 | N5: 46114 | O5: Balamurugan | P5: Deepika | Q5: NA | R5: Deepika | S5: NA | T5: 48197 | U5: 46114 | V5: 46119 | W5: Charles | X5: NA | Y5: NA | Z5: 46119 | AA5: NA | AB5: POV Comments: 1. If decline to respond -> yes -> though data is filled, then the check box should not be visible in bid analysis 2. Bottom Line -> When declined to respond is checked, though the vendor quoted price is added, it should not consider that item for responded items | AC5: NA | AD5: NA | AE5: NA
A6: 5 | B6: FOH Wave | C6: 46108 | D6: 46121 | E6: 26.5 - Sprint 3 | F6: Vidhya | G6: 51845 | H6: [WAVE] Mosaic BOH - (6) User Tasks - Review Task Setup | I6: Story Being Tested | J6: 8 | K6: 5.5 | L6: 22 | M6: 46108 | N6: 46114 | O6: Sabir | P6: Deepika | Q6: User list grid doen't retain the checked specific User's | R6: Deepika | S6: NA | T6: 48240 | U6: 46119 | V6: 46119 | W6: Charles | X6: NA | Y6: NA | Z6: 46119 | AA6: NA | AB6: NA | AC6: NA | AD6: NA | AE6: meet expectation
A7: 6 | B7: ='Dashboard-2025'!$K$1 -> FOH Wave | C7: 46108 | D7: 46121 | E7: 26.5 - Sprint 3 | F7: Sabir | G7: 52169 | H7: [WAVE] Mosaic BOH - Ingredient Allergens - Add "Contains No Allergens" option | I7: Story Completed | J7: 3 | K7: 2 | L7: 8 | M7: 46108 | N7: 46111 | O7: Sabir | P7: Mohammad Zawahir | Q7: None | R7: Mohammad Zawahir | S7: None | T7: 48091 | U7: 46173 | V7: 46114 | W7: Charles | X7: None | Y7: NA | Z7: 46114 | AA7: None | AB7: POV Comments: Saved changes are not reflected for the checkbox "This ingredient contains no known allergens." | AD7: NA | AE7: meet expectation
A8: 7 | B8: ='Dashboard-2025'!$K$1 -> FOH Wave | C8: 46108 | D8: 46121 | E8: 26.5 - Sprint 3 | F8: Subbulakshmi | G8: 51891 | H8: MFOH [WAVE] - Modify the Dashboard Setup Maintenance (Allow to add Widgets one by one) | I8: Story Completed | J8: 1 | K8: 0.5 | L8: 2 | M8: 46108 | N8: 46113 | O8: NA | P8: NA | Q8: NA | R8: NA | S8: NA | T8: NA | U8: NA | V8: NA | W8: NA | X8: NA | Y8: NA | Z8: NA | AA8: NA | AB8: NA | AC8: NA | AD8: NA | AE8: NA
A9: 8 | B9: ='Dashboard-2025'!$K$1 -> FOH Wave | C9: 46108 | D9: 46121 | E9: 26.5 - Sprint 3 Stretch | F9: Balamurugan | G9: 52062 | H9: [Wave]Mosaic BOH - Transfers - Bulk Add (2) - UI Only | I9: Story Being Developed | J9: 8 | K9: =Table2456891021213141116171118192021152223242526272829303132333435[[#This Row],[Actual Worklog (Hours)]] / 4 -> 6 | L9: 24 | M9: 46118 | N9: NA | O9: NA | P9: NA | Q9: NA | R9: NA | S9: NA | T9: NA | U9: NA | V9: NA | W9: NA | X9: NA | Y9: NA | Z9: NA | AA9: NA | AB9: NA | AC9: NA | AD9: NA | AE9: NA
A10: 9 | B10: ='Dashboard-2025'!$K$1 -> FOH Wave | C10: 46108 | D10: 46121 | E10: 26.5 - Sprint 3 Stretch | F10: Sabir | G10: 52044 | H10: [WAVE] Mosaic BOH - Ingredients - Search for Ingredients that Do Not Contain Specified Allergens | I10: Story Approved | J10: 8 | K10: 3 | L10: 12 | M10: 46118 | N10: NA | O10: NA | P10: NA | Q10: NA | R10: NA | S10: NA | T10: NA | U10: NA | V10: NA | W10: NA | X10: NA | Y10: NA | Z10: NA | AA10: NA | AB10: NA | AC10: NA | AD10: NA | AE10: NA

Sheet 26.5 - Sprint 3-Defect
A1: S.No | B1: Sprint # | C1: Story/Defect ID | D1: Parent Story | E1: Developer | F1: Issue Type | G1: Issue Description | H1: Priority | I1: Defect Source | J1: Type | K1: Status | L1: Dev Start Date | M1: Dev End Date | N1: Root Cause Category | O1: Comments
B2: 26.5 - Sprint 3 | C2: 51845 | D2: 51845 | E2: Vidhya/Sabir | F2: Bounceback/Sub-Defect | G2: 1. Task Type tool tip is showing incorrectly 2. Tool tip issue in Task Name 3. End Date is not showing for Daily Recurrence 4. Getting on Exception error while Added more than 40 Users(Workking fine in Local, issue only is QA Test) | H2: Minor | I2: Manual | J2: Internal | K2: Story Completed | L2: 46120 | M2: 46121 | N2: UI Issue | O2: Tool tip issues in Task Type, Task Name, Recurrence

Sheet 26.5 - Sprint 2-Status
A1: S.No | B1: Application Name | C1: Sprint Start Date | D1: Sprint End Date | E1: Sprint | F1: Developer/Tester | G1: Story ID/Defect ID | H1: Description | I1: Status | J1: Estimated(hrs/sp) | K1: Actual(hrs/sp) | L1: Actual Worklog (Hours) | M1: Dev Start Date | N1: Dev End Date | O1: Unit testing | P1: Peer Tested By | Q1: Peer Tested Comments, if any | R1: Peer Reviewed By | S1: Peer Code Review Comments, if any | T1: PR Number/Link | U1: PR Created Date | V1: PR Approved Date | W1: Onsite Lead Code Review | X1: Code Review Comments, if any | Y1: Client Code Review | Z1: Approved Date | AA1: Code Review Comments, if any2 | AB1: Internal PO -POV Comments | AC1: Client PO -POV Comments | AD1: Comments | AE1: Does this story meet expectations?
A2: 1 | B2: FOH Wave | C2: 46094 | D2: 46107 | E2: 26.5 - Sprint 2 | F2: Vidhya | G2: 47929 | H2: [WAVE] Mosaic BOH - (5) User Tasks - Assigning Users | I2: Story Completed | J2: 8 | K2: =Table24568910212131411161711181920211522232425262728293031323334[[#This Row],[Actual Worklog (Hours)]] / 4 -> 9 | L2: 36 | M2: 46094 | N2: 46101 | O2: Vidhya | P2: Mohammed Jawahir | Q2: 1. After pagination, continue button turned disable mode. 2. Show Selected Only is not working correctly 3. I was added task with due date 23rd, then edit the same task it shows 22nd. 4. I can able to add task for past dates. | R2: Jawahir | S2: None | T2: 47942 | U2: 46101 | V2: 46105 | W2: Charles | X2: None | Y2: NA | Z2: 46105 | AA2: None | AB2: POV comments: 1. Either Site Group/ site should be selected to apply filters 2. User Assignment - space required 3. Uncheck any selected users when selecting yes in the pop-up | AC2: NA | AD2: NA | AE2: NA
A3: 2 | B3: FOH Wave | C3: 46094 | D3: 46107 | E3: 26.5 - Sprint 2 | F3: Subbulakshmi | G3: 52330 | H3: Kaleida changes update to the Global Report Layout File for Kaleida Reports | I3: Story Completed | J3: 2 | K3: =Table24568910212131411161711181920211522232425262728293031323334[[#This Row],[Actual Worklog (Hours)]] / 4 -> 2.25 | L3: 9 | M3: 46094 | N3: 46098 | O3: Subbulakshmi | P3: NA | Q3: NA | R3: NA | S3: NA | T3: 47876 | U3: 46099 | V3: 46099 | W3: NA | X3: NA | Y3: NA | Z3: 46099 | AA3: NA | AB3: NA | AC3: NA | AD3: NA | AE3: NA
A4: 3 | B4: FOH Wave | C4: 46094 | D4: 46107 | E4: 26.5 - Sprint 2 | F4: Balamurugan | G4: 52099 | H4: [Wave]Mosaic BOH - Transfers - Bulk Replace (1) | I4: Story Completed | J4: 3 | K4: 6.5 | L4: 26 | M4: 46094 | N4: 46099 | O4: Balamurugan | P4: Mohammed Jawahir | Q4: None | R4: Mohammed Jawahir | S4: 1. Please remove unused variables | T4: 47875 | U4: 46099 | V4: 46100 | W4: Charles Antonysamy | X4: NA | Y4: NA | Z4: 46101 | AA4: NA | AB4: 1) Parent Menu -> Icon and underline 2) add, remove -> Add “Coming soon” text 3) Replace position edit.. in view only mode 4) comment box position -> check image 5) append the existing comments | AC4: NA | AD4: Internal POV done on 03/17/2026. Working on POV 4 design comments and one 1 suggestion. Get POV confirmation after share the screen shot design changes on 03/17/2026 Reasons for story points exceeded: Since this is first story with BOH, it took time to align with existing application's coding standards and structure | AE4: NA
A5: 4 | B5: FOH Wave | C5: 46094 | D5: 46107 | E5: 26.5 - Sprint 2 Stretch | F5: Sabir | G5: 26993 | H5: [Wave]Mosaic BOH - Fix the alignment issues with the User Tasks List Search Screen | I5: Defect Being Tested | J5: 3 | K5: 2 | L5: 12 | M5: 46097 | N5: 46099 | O5: Sabir | P5: Krupa Bhatkar | Q5: NA | R5: Krupa Bhatkar | S5: NA | T5: 47865 | U5: 46099 | V5: 46105 | W5: Charles Antonysamy | X5: NA | Y5: NA | Z5: 46105 | AA5: NA | AB5: POV comments: 1. Tool tip Do not Repeat- Due on June 28- correction show the exact date in saved format 03/25/2026 Daily - Every 5 Days until 03/18/2026 Weekly - On Monday, Tuesday until 03/18/2026 Monthly - On the 1st Sunday until 09/22/2029 Annually - On June 28 until 09/22/2030 2. When opening a task from the search screen, the saved selection is not retained 3. Security Group, Site Group, and Site - List all the values | AC5: NA | AD5: NA | AE5: NA
A6: 5 | B6: FOH Wave | C6: 46094 | D6: 46107 | E6: 26.5 - Sprint 2 Stretch | F6: Subbulakshmi | G6: 52329 | H6: MFOH - Automation - Kaleida changes update to the Setup - Annual Setup - Nondiscrimination Statement | I6: Story Being Developed | J6: 1 | K6: =Table24568910212131411161711181920211522232425262728293031323334[[#This Row],[Actual Worklog (Hours)]] / 4 -> 1 | L6: 4 | M6: 46099 | N6: NA | O6: NA | P6: NA | Q6: NA | R6: NA | S6: NA | T6: NA | U6: NA | V6: NA | W6: NA | X6: NA | Y6: NA | Z6: NA | AA6: NA | AB6: None | AC6: NA | AD6: NA | AE6: NA
A7: 6 | B7: FOH Wave | C7: 46094 | D7: 46107 | E7: 26.5 - Sprint 2 Stretch | F7: Sabir | G7: 43501 | H7: [WAVE] Mosaic BOH - ER - Improve the Search functionality | I7: Story Being Developed | J7: 5 | K7: 3 | L7: 12 | M7: 46099 | N7: 46105 | O7: Sabir | P7: Rajiv | Q7: NA | R7: Rajiv | S7: NA | T7: NA | U7: NA | V7: NA | W7: NA | X7: NA | Y7: NA | Z7: NA | AA7: NA | AB7: NA | AC7: NA | AD7: NA | AE7: NA
A8: 7 | B8: FOH Wave | C8: 46094 | D8: 46107 | E8: 26.5 - Sprint 2 Stretch | F8: Balamurugan | G8: 52172 | H8: [WAVE] Mosaic BOH - Bidding - Allow vendors to indicate "No Response" on line items | I8: Story Being Developed | J8: 8 | K8: =Table24568910212131411161711181920211522232425262728293031323334[[#This Row],[Actual Worklog (Hours)]] / 4 -> 8 | L8: 32 | M8: 46100 | N8: 46107 | O8: Balamurugan | P8: NA | Q8: NA | R8: NA | S8: NA | T8: NA | U8: NA | V8: NA | W8: NA | X8: NA | Y8: NA | Z8: NA | AA8: NA | AB8: NA | AC8: NA | AD8: NA | AE8: NA
A9: 8 | B9: FOH Wave | C9: 46094 | D9: 46107 | E9: 26.5 - Sprint 2 Stretch | F9: Vidhya | G9: 51845 | H9: [WAVE] Mosaic BOH - (6) User Tasks - Review Task Setup | I9: Story Being Developed | J9: 5 | K9: =Table24568910212131411161711181920211522232425262728293031323334[[#This Row],[Actual Worklog (Hours)]] / 4 -> 4 | L9: 16 | M9: 46106 | N9: NA | O9: NA | P9: NA | Q9: NA | R9: NA | S9: NA | T9: NA | U9: NA | V9: NA | W9: NA | X9: NA | Y9: NA | Z9: NA | AA9: NA | AB9: NA | AC9: NA | AD9: NA | AE9: NA
A10: 9 | B10: ='Dashboard-2025'!$K$1 -> FOH Wave | C10: 46094 | D10: 46107 | E10: 26.5 - Sprint 2 Stretch | F10: Sabir | G10: 52169 | H10: [WAVE] Mosaic BOH - Ingredient Allergens - Add "Contains No Allergens" option | I10: Story Being Developed | J10: 5 | K10: 2 | L10: 8 | M10: 46106 | N10: NA | O10: NA | P10: NA | Q10: NA | R10: NA | S10: NA | T10: NA | U10: NA | V10: NA | W10: NA | X10: NA | Y10: NA | Z10: NA | AA10: NA | AB10: NA | AC10: NA | AD10: NA | AE10: Na

Sheet 26.5 - Sprint 2-Defect
A1: S.No | B1: Sprint # | C1: Story/Defect ID | D1: Parent Story | E1: Developer | F1: Issue Type | G1: Issue Description | H1: Priority | I1: Defect Source | J1: Type | K1: Status | L1: Dev Start Date | M1: Dev End Date | N1: Root Cause Category | O1: Comments
B2: 26.5 - Sprint 1 | C2: 52099 | D2: 52099 | E2: Balamurugan | F2: Bounceback/Sub-Defect | G2: 1. Comment is not appended when I added the text length is 4000 2. UI issue in Comment text box scroll 3. Getting an Exception error while I replace the transfer in MenuPlanningPlannedMenu file | H2: Minor | I2: Manual | J2: Internal | K2: Story Completed | L2: 46094 | M2: 46099 | N2: UI Validations
B3: 26.5 - Sprint 2 Stretch | C3: 26993 | D3: 26993 | E3: Sabir | F3: Bounceback/Sub-Defect | G3: 1. If I open the Task in new tab, data is not showing for Annually and Monthly Recurrence 2. Space needed between Custom and Link/Simple and Task – Previously showing correctly. 3. Fluctuation issue in Assigned To User tooltip 4. Continue button is enabled when I’m not filling the Mandatory field – Previously its working 5. Need to Display all the Site Groups and Site Name irrespective of the logged in User | H3: Minor | I3: Manual | J3: Internal | K3: Story Completed | L3: 46104 | M3: 46106 | N3: UI Validations

Sheet 26.5 - Sprint 1-Status
A1: S.No | B1: Application Name | C1: Sprint Start Date | D1: Sprint End Date | E1: Sprint | F1: Developer/Tester | G1: Story ID/Defect ID | H1: Description | I1: Status | J1: Estimated(hrs/sp) | K1: Actual(hrs/sp) | L1: Actual Worklog (Hours) | M1: Dev Start Date | N1: Dev End Date | O1: Unit testing | P1: Peer Tested By | Q1: Peer Tested Comments, if any | R1: Peer Reviewed By | S1: Peer Code Review Comments, if any | T1: PR Number/Link | U1: PR Created Date | V1: PR Approved Date | W1: Onsite Lead Code Review | X1: Code Review Comments, if any | Y1: Client Code Review | Z1: Approved Date | AA1: Code Review Comments, if any2 | AB1: Internal PO -POV Comments | AC1: Client PO -POV Comments | AD1: Comments | AE1: Does this story meet expectations?
A2: 1 | B2: FOH Wave | C2: 46080 | D2: 46093 | E2: 26.5 - Sprint 1 | F2: Vidhya | G2: 51349 | H2: [WAVE] Mosaic BOH - (3) User Tasks - Add/Edit Tasks | I2: Story Completed | J2: 3 | K2: =Table245689102121314111617111819202115222324252627282930313233[[#This Row],[Actual Worklog (Hours)]] / 4 -> 10.5 | L2: 42 | M2: 46080 | N2: 46087 | O2: Vidhya | P2: Deepika (BOH) | Q2: 1. At first time without any clicks on the submenus, there is an spacing at right side 2. When O&I is disabled.. Inventory has different submenu’s | R2: Deepika (BOH) | S2: 1. Remove the hard-coded value in controller instead use resource files 2. Revert this blank Line | T2: 47641 | U2: 46087 | V2: 46092 | W2: Charles (BOH) | X2: Suggested to cover unit test cases. Should add dedicated files for scripts and styles | Y2: NA | Z2: 46092 | AA2: None | AB2: 1. Custom Url is empty -> Click eye icon. Navigating to empty page 2. Daily recurrence - Set default value to 1 3. Monthly recurrence - Change 5th to Last 4. Breadcrumb - Change Add Task to Edit task after save | AC2: NA | AD2: Internal POV done on 03/04/2026. Working on POV comments. Next POV happened on 06/04/2026. Reasons for story points exceeded: 1. Initially, development started using Kendo controls, but later it was confirmed to proceed with Vega controls which causes revisiting part of the implementations again 2. As this was the first time implementing Vega controls, some additional time was required to understand it. 3. The requirement included a specific dropdown behavior that needed customization using Vega controls to match the expected UI design 4. Additional effort was spent ensuring the UI matched the design specifications 5. Since this is first story with BOH, it took time to align with existing application's coding standards and structure | AE2: NA
A3: 2 | B3: FOH Wave | C3: 46080 | D3: 46093 | E3: 26.5 - Sprint 1 | F3: Sabir | G3: 21786 | H3: [WAVE] Mosaic BOH - (2) User Tasks - Add to the Setup - UI Implementation | I3: Story Completed | J3: 3 | K3: 7.5 | L3: 30 | M3: 46080 | N3: 46090 | O3: Sabir | P3: Rajiv (BOH) | Q3: When O&I is disabled.. Inventory has different submenu’s | R3: Rajiv (BOH) | S3: 1. Remove the hard-coded value in controller instead use resource files 2. Revert this blank Line 3. Remove the hard-coded value in contants instead use resource files 4. Lable name should displayed from resource file. 5. use seperate css file from styles. | T3: 47657 | U3: 46090 | V3: 46091 | W3: Charles (BOH) | X3: None | Y3: NA | Z3: 46091 | AA3: None | AB3: 1. User Task list under setup - need to change the position 2. "Links User To" - Rename it | AC3: NA | AD3: Reasons for story points exceeded: 1. Initially, development started using Kendo controls, but later it was confirmed to proceed with Vega vontrols which causes revisiting part of the implementations again 2. As this was the first time implementing Vega controls, some additional time was required to understand it. 3. The requirement included a specific dropdown behavior that needed customization using Vega controls to match the expected UI design 4. Additional effort was spent ensuring the UI matched the design specifications 5. Since this is first story with BOH, it took time to align with existing application's coding standards and structure | AE3: NA
A4: 3 | B4: FOH Wave | C4: 46080 | D4: 46093 | E4: 26.5 - Sprint 1 Stretch | F4: Subbulakshmi | G4: 51803 | H4: MFOH - Automation (Smoke) - Kaleida changes update to the close day search screen & close day maintenance screen | I4: Story Completed | J4: 2 | K4: =Table245689102121314111617111819202115222324252627282930313233[[#This Row],[Actual Worklog (Hours)]] / 4 -> 3.5 | L4: 14 | M4: 46087 | N4: 46091 | O4: NA | P4: NA | Q4: NA | R4: NA | S4: NA | T4: 47738 | U4: 46091 | V4: 46092 | W4: NA | X4: NA | Y4: NA | Z4: 46092 | AA4: NA | AB4: NA | AC4: NA | AD4: None | AE4: NA
A5: 4 | B5: FOH Wave | C5: 46080 | D5: 46093 | E5: 26.5 - Sprint 1 Stretch | F5: Balamurugan | G5: 52099 | H5: [Wave]Mosaic BOH - Transfers - Bulk Replace (1) | I5: Story Being Developed | J5: 5 | K5: =Table245689102121314111617111819202115222324252627282930313233[[#This Row],[Actual Worklog (Hours)]] / 4 -> 7 | L5: 28 | M5: 46087 | N5: NA | O5: NA | P5: NA | Q5: NA | R5: NA | S5: NA | T5: NA | U5: NA | V5: NA | W5: NA | X5: NA | Y5: NA | Z5: NA | AA5: NA | AB5: NA | AC5: NA | AD5: None | AE5: NA
A6: 6 | B6: FOH Wave | C6: 46080 | D6: 46093 | E6: 26.5 - Sprint 1 Stretch | F6: Vidhya | G6: 47929 | H6: [WAVE] Mosaic BOH - (5) User Tasks - Assigning Users | I6: Story Being Developed | J6: 5 | K6: =Table245689102121314111617111819202115222324252627282930313233[[#This Row],[Actual Worklog (Hours)]] / 4 -> 2.25 | L6: 9 | M6: 46093 | N6: NA | O6: NA | P6: NA | Q6: NA | R6: NA | S6: NA | T6: NA | U6: NA | V6: NA | W6: NA | X6: NA | Y6: NA | Z6: NA | AA6: NA | AB6: NA | AC6: NA | AD6: None | AE6: NA
A7: 7 | B7: FOH Wave | C7: 46080 | D7: 46093 | E7: 26.5 - Sprint 1 Stretch | F7: Sabir | G7: 52062 | H7: [Wave]Mosaic BOH - Transfers - Bulk Add (2) - UI Only | I7: Story Being Developed | J7: 8 | K7: 1.5 | L7: 6 | M7: 46093 | N7: NA | O7: NA | P7: NA | Q7: NA | R7: NA | S7: NA | T7: NA | U7: NA | V7: NA | W7: NA | X7: NA | Y7: NA | Z7: NA | AA7: NA | AB7: NA | AC7: NA | AD7: None | AE7: NA

Sheet Dashboard (2)
A1: Current Sprint | B1: {=INDEX($B$2:$B$96,MATCH(1,(($D$2:$D$96 >=TODAY())*($C$2:$C$96<=TODAY())),0))} -> #N/A | C1: Current Sprint Sheet | D1: =CONCATENATE(B1,"-Status") -> #N/A | E1: Sprint Start Date | F1: =VLOOKUP($B$1,$B$1:$C$96,2) -> #N/A | G1: Sprint End Date | I1: =VLOOKUP($B$1,$B$1:$D$96,3) -> #N/A | J1: Application Name | K1: FOH Wave | L1: sabir.shaikh@relevantz.com;subbulakshmi.namasivayam@relevantz.com;vidhya.subramani@relevantz.com;balamurugan.kandasamy@relevantz.com | N1: hemanath.jayaraman@relevantz.com;sabir.shaikh@relevantz.com;subbulakshmi.namasivayam@relevantz.com;vidhya.subramani@relevantz.com | O1: satarupa.mohanty@relevantz.com;ashwin.majella@relevantz.com;ganapathiraman.balasubramanian@relevantz.com;subhasri.ponnappan@relevantz.com;hemanath.jayaraman@relevantz.com;subbulakshmi.namasivayam@relevantz.com;vidhya.subramani@relevantz.com;sabir.shaikh@relevantz.com
A2: Sprint Type | B2: Sprint # | C2: Sprint Start Date | D2: Sprint End Date | E2: Assigned | F2: Completed | G2: Story points introduced/removed | H2: Sprint Summary | I2: Accomplishments | J2: Remarks | K2: Retro Points (Internal & External) | L2: Planned Leave | M2: Total Leave | N2: Data sanity Audit Status | O2: AuditDate
A3: =IF(AND($D$1>=C3,$D$1<=D3),"CurrentSprint","NA") -> #N/A | B3: 4.15 - Sprint 4 | C3: 45296 | D3: 45309 | E3: 28 | F3: 28 | G3: 0 | J3: Regression Sprint so completed all the modules testing, No code review comments / Defects applicable. Also we fixed few regression defects. | K3: Internal: External:
A4: =IF(AND($D$1>=C4,$D$1<=D4),"CurrentSprint","NA") -> #N/A | B4: 4.16 - Sprint 1 | C4: 45310 | D4: 45323 | E4: 26 | F4: 23 | G4: 0 | J4: Developers supported to clear the QA backlogs. [Testing Stories = 18, Development Stories = 8 Total Sprint Stories =20 completed = 20; Stretch Stories = 6 completed = 3] | K4: Internal: External:
A5: =IF(AND($D$1>=C5,$D$1<=D5),"CurrentSprint","NA") -> #N/A | B5: 4.16 - Sprint 2 | C5: 45324 | D5: 45337 | E5: 41 | F5: 39 | G5: 0 | J5: Developers supported to clear the QA backlogs. | K5: Internal: External:
A6: =IF(AND($D$1>=C6,$D$1<=D6),"CurrentSprint","NA") -> #N/A | B6: 4.16 - Sprint 3 | C6: 45338 | D6: 45351 | E6: 35 | F6: 35 | G6: 0 | J6: Got appreciation for a feature developed in the sprint and also in the sprint review demo from stake holder (#42670) | K6: Internal: External:
A7: =IF(AND($D$1>=C7,$D$1<=D7),"CurrentSprint","NA") -> #N/A | B7: 4.16 - Sprint 4 | C7: 45352 | D7: 45365 | E7: 19 | F7: 30 | G7: 0 | J7: Stretch Story: 11-SP | K7: Internal: External:
A8: =IF(AND($D$1>=C8,$D$1<=D8),"CurrentSprint","NA") -> #N/A | B8: 4.16 - Sprint 5 | C8: 45366 | D8: 45379 | E8: 38 | F8: 38 | G8: 0 | J8: Regression Sprint so completed all the modules testing, No code review comments / Defects applicable. Also we fixed few regression defects. Appreciation on Retro:Regression went well | K8: Internal: External:
A9: =IF(AND($D$1>=C9,$D$1<=D9),"CurrentSprint","NA") -> #N/A | B9: 4.17 - Sprint 1 | C9: 45380 | D9: 45393 | E9: 32 | F9: 32 | J9: Regression wrap up was done in this sprint and along with that completed few stretch stories(Sprint Story only 13SP for the regression wrap up). | K9: Internal: External:
A10: =IF(AND($D$1>=C10,$D$1<=D10),"CurrentSprint","NA") -> #N/A | B10: 4.17 - Sprint 2 | C10: 45394 | D10: 45407 | E10: 21 | F10: 39 | G10: 0 | J10: Completed all the assigned stories and addition to that completed Stretch Stories - 18 SP. | K10: Internal: External:
A11: =IF(AND($D$1>=C11,$D$1<=D11),"CurrentSprint","NA") -> #N/A | B11: 4.17 - Sprint 3 | C11: 45408 | D11: 45421 | E11: 29 | F11: 10 | G11: 0 | J11: Completed all the stories - 29 SP in Sprint and 10 SP in stretch. Onsite team was on PTO, so no one there to approve the PR. Carryforwading 21 SP in sprint and 8 SP in stretch to next sprint as per Gary's suggestion. | K11: Internal: External:
A12: =IF(AND($D$1>=C12,$D$1<=D12),"CurrentSprint","NA") -> #N/A | B12: 4.17 - Sprint 4 | C12: 45422 | D12: 45435 | E12: 13 | F12: 13 | G12: 0 | J12: Regression Sprint(Targeted) so completed all the modules testing, Also we fixed few regression defects. Stretch Story: 5-SP Appreciation on Retro:Regression went well | K12: Internal: External:
A13: =IF(AND($D$1>=C13,$D$1<=D13),"CurrentSprint","NA") -> #N/A | B13: 4.18 - Sprint 1 | C13: 45436 | D13: 45449 | E13: 40 | F13: 32 | G13: 0 | J13: Carryforwaded one story 8 SP, as POV with onsite team need to done. | K13: Internal: External:
A14: =IF(AND($D$1>=C14,$D$1<=D14),"CurrentSprint","NA") -> #N/A | B14: 4.18 - Sprint 2 | C14: 45450 | D14: 45463 | E14: 13 | F14: 21 | G14: 0 | J14: Completed all the committed stories. Stretch Story: 8-SP | K14: Internal: External:
A15: =IF(AND($D$1>=C15,$D$1<=D15),"CurrentSprint","NA") -> #N/A | B15: 4.18 - Sprint 3 | C15: 45464 | D15: 45491 | E15: 44 | F15: 44 | G15: 22 | J15: Completed all the committed stories. Supported to clear the QA backlogs. Stretch Story: 22-SP. Appreciation on Retro: For helping on QA backlogs | K15: Internal: External:
A16: =IF(AND($D$1>=C16,$D$1<=D16),"CurrentSprint","NA") -> #N/A | B16: 4.18 - Sprint 4 | C16: 45492 | D16: 45505 | E16: 37 | F16: 37 | G16: 37 | J16: No delevopment stories added to sprint. Supported to clear the QA backlogs. Stretch Story: 37-SP. | K16: Internal: External:
A17: =IF(AND($D$1>=C17,$D$1<=D17),"CurrentSprint","NA") -> #N/A | B17: 4.18 - Sprint 5 | C17: 45506 | D17: 45519 | E17: 15 | F17: 15 | G17: 3 | J17: Completed the committed stories. Supported to clear the QA backlogs. 14-SP completed development and waiting to raise PR. Stretch Story: 3-SP. | K17: Internal: External:
A18: =IF(AND($D$1>=C18,$D$1<=D18),"CurrentSprint","NA") -> #N/A | B18: 4.18 - Sprint 6 | C18: 45520 | D18: 45533 | E18: 21 | F18: 21 | G18: 7 | J18: Completed the committed stories. Supported to clear the QA backlogs. Stretch Story: 11-SP. | K18: Internal: External:
A19: =IF(AND($D$1>=C19,$D$1<=D19),"CurrentSprint","NA") -> #N/A | B19: 4.18 - Sprint 7 | C19: 45534 | D19: 45547 | E19: 38 | F19: 38 | G19: 8 | J19: Note: 1. Related to fix for 4.17: There was an issue with Student Import potential match catch logic. From Steve: a parsing issue - the birthdate of 09112009 fails to parse w/the code being used. It's trying to parse with only this pattern MM/dd/yyyy (hardcoded) 2. Related to hotfix for CPS: There was an issue found at MSB end in their API. Data is not being sent to Mosaic due an issue with the date. It can be fixed at either end (MSB or Mosaic) but if is fixed in Mosaic it will be a simple fix because if MSB team fix it may take much more time. The real issue is MSB is expecting for a date time for start and end date. Currently we send only date and due to that data is not pulled properly. Completed all regression stories in sprint. Stretch Story: 8-SP | K19: Internal: External:
A20: =IF(AND($D$1>=C20,$D$1<=D20),"CurrentSprint","NA") -> #N/A | B20: 4.19 - Sprint 1 | C20: 45548 | D20: 45561 | E20: 31 | F20: 31 | G20: 0 | J20: CRC Internal -- 2 CRC External -- 0 QA Defects -- 3 (1-Rejected) Escaped Defects -- 0 Completed all the committed stories. Supported to clear the QA backlogs. Stretch Story: 18-SP. 45834 is POC which is Carry Forwarded | K20: Internal: External: Appreciation on Retro: For helping on QA backlogs
A21: =IF(AND($D$1>=C21,$D$1<=D21),"CurrentSprint","NA") -> #N/A | B21: 4.19 - Sprint 2 | C21: 45562 | D21: 45589 | E21: 33 | F21: 45.5 | G21: Introduced - 12.5 | J21: CRC Internal -- 4 CRC External -- 0 QA Defects -- 8 (2-Rejected) Escaped Defects -- 0 Supported to clear the QA backlogs. Stretch Story: 20-SP. | K21: Internal: Alpha recieved appreciation for support in dashboard. Jagan and Arvinth recieved appreciation for good presentation in sprint review. External: Recieved appreciation from Tino for Dashbord Story done by Subha. Appreciation on Retro: For helping on QA backlogs
A22: =IF(AND($D$1>=C22,$D$1<=D22),"CurrentSprint","NA") -> #N/A | B22: 4.19 - Sprint 3 | C22: 45590 | D22: 45603 | E22: 16 | F22: 35 | G22: Introduced - 19 | I22: Feature Flags, Student Barcode Report Update, Louisiana SFS-8A Report update, and Defects | J22: CRC Internal -- 0 CRC External -- 1 QA Defects -- 2 Escaped Defects -- 0 Supported to clear the QA backlogs. Stretch Story: 19-SP. | K22: Internal: External:
A23: =IF(AND($D$1>=C23,$D$1<=D23),"CurrentSprint","NA") -> #N/A | B23: 4.19 - Sprint 4 | C23: 45604 | D23: 45617 | E23: 25 | F23: 33 | G23: Introduced - 8 | I23: Improvements to Scheduler Task, Showing Actual Bank Deposit Amount in Online Payment Detail Report, Update to Alachua Meal Count export(2 decimal places to labor hours), and Defects | J23: CRC Internal -- 0 CRC External -- 0 QA Defects -- 3 (2-Rejected) Escaped Defects -- 0 Stretch Story: 8-SP. | K23: Internal: Online payment report story done without any deviation. External:
A24: =IF(AND($D$1>=C24,$D$1<=D24),"CurrentSprint","NA") -> #N/A | B24: 4.19 - Sprint 5 | C24: 45618 | D24: 45645 | E24: 60 | F24: 70 | G24: Introduced - 10 | I24: Add Ability to Print Machine Info, Add date of inactive to Student Maintenance, Add Notes to Elig Record Report, Add Active Filter to User Assignments Report, Defects, and then begin 4.19 Regression Testing. | J24: CRC Internal -- 2 CRC External -- 1 QA Defects -- 3 Escaped Defects -- 0 Stretch Story: 10-SP. | K24: Internal:Change comment,Change in adding the SQL paramer External:Merge conflict with revision history
A25: =IF(AND($D$1>=C25,$D$1<=D25),"CurrentSprint","NA") -> #N/A | B25: 4.20 - Sprint 1 | C25: 45646 | D25: 45673 | E25: 35 | F25: 46 | G25: Introduced - 12 | I25: multiple Defects for 4.19 and complete 4.19 Regression, Add report for “Schools not in School Group”, and Add new report type to POS Roster Reports | J25: Release Date - March 2025 (Tentative) CRC Internal -- 1 CRC External -- 0 QA Defects -- 15 (1-Rejected) Escaped Defects -- 0 Stretch Story: 12-SP. | K25: Internal: External: Appreciation on Retro: For helping on QA backlogs
A26: =IF(AND($D$1>=C26,$D$1<=D26),"CurrentSprint","NA") -> #N/A | B26: 4.20 - Sprint 2 | C26: 45674 | D26: 45687 | E26: 22 | F26: 27 | G26: Introduced - 5 | I26: Menu Management Improvements(Assign POS Menus to multiple POS numbers & Re-Alphabetize Menu Products), Dashboard update(CPS), Speed-e Mode option to fulfill Meal Order or not, and use CEP Reimbursement Calculations in Claim Report(KDE) | J26: Release Date - March 2025 (Tentative) CRC Internal -- 0 CRC External -- 0 QA Defects -- 0 Escaped Defects -- 0 Stretch Story: 5-SP. | K26: Internal: External: Appreciation on Retro: Mike(QA) appreciated for helping on QA backlogs
A27: =IF(AND($D$1>=C27,$D$1<=D27),"CurrentSprint","NA") -> #N/A | B27: 4.20 - Sprint 3 | C27: 45688 | D27: 45701 | E27: 25 | F27: 31 | G27: Introduced - 6 | I27: Add Student Effective Date and Eligibility Reason to Student Maint., Attaching Verification Reports, Add Serving Period Program and Serving Period droplist to Special Provision Edit Check Report, Performance Improvements to Imports(CPS), and Defect Fixes | J27: Release Date - March 2025 (Tentative) CRC Internal -- 0 CRC External -- 0 QA Defects -- 0 Escaped Defects -- 0 Stretch Story: 6-SP. | K27: Internal: External: Appreciation on Retro: Mike(QA) appreciated for helping on QA backlogs
A28: =IF(AND($D$1>=C28,$D$1<=D28),"CurrentSprint","NA") -> #N/A | B28: 4.20 - Sprint 4 | C28: 45702 | D28: 45715 | E28: 38 | F28: 38 | G28: Introduced - 0 | I28: 4.20 Regression Testing | J28: Release Date - March 2025 (Tentative) CRC Internal -- 0 CRC External -- 0 QA Defects -- 13 Escaped Defects -- 0 Stretch Story: 0 | K28: Internal: External: Appreciation on Retro: Mike(QA) appreciated for helping on QA backlogs and Regression Testing completion
A29: =IF(AND($D$1>=C29,$D$1<=D29),"CurrentSprint","NA") -> #N/A | B29: 4.21 - Sprint 1 | C29: 45716 | D29: 45729 | E29: 26 | F29: 31 | G29: Introduced - 5 | I29: Tyler-MUNIS Financial Export(NC), Adding Checks to Student Account Summary Report, Label Format Options to Barcode Report | J29: CRC Internal -- 4 CRC External -- 0 QA Defects -- 0 Escaped Defects -- 0 Stretch Story: 0 | K29: Internal: External:
A30: =IF(AND($D$1>=C30,$D$1<=D30),"CurrentSprint","NA") -> #N/A | B30: 4.21 - Sprint 2 | C30: 45730 | D30: 45743 | E30: 32 | F30: 32 | G30: Introduced - 0 | I30: North Carolina Export, Ability to see transactions marked for review(SL), A La Carte Report Update, Ability to Add Transactions after Re-opening a day, and adding CEP ISP calculations to Chartwell’s Export | J30: CRC Internal -- 1 CRC External -- 2 QA Defects -- 0 Escaped Defects -- 0 Stretch Story: 0 | K30: Internal: External: Appreciation on Retro: Mike(QA) appreciated for helping on QA backlogs
A31: =IF(AND($D$1>=C31,$D$1<=D31),"CurrentSprint","NA") -> #N/A | B31: 4.21 - Sprint 3 | C31: 45744 | D31: 45757 | E31: 31 | F31: 34 | G31: Introduced - 3 | I31: CPS Dashboard Improvements, IEG Updates, ‘Carryover Expiration Date’ added as Import field, adding, NC SFS-4 Export update, and Adding ISP values for Mult schools. | J31: CRC Internal -- 3 CRC External -- 1 QA Defects -- 0 Escaped Defects -- 0 Stretch Story: 0 | K31: Internal: External:
A32: =IF(AND($D$1>=C32,$D$1<=D32),"CurrentSprint","NA") -> #N/A | B32: 4.21 - Sprint 4 | C32: 45758 | D32: 45771 | E32: 41 | F32: 33 | G32: Introduced - 0 | I32: 4.21 Regression Testing | J32: CRC Internal -- 1 CRC External -- 0 QA Defects -- 3 Escaped Defects -- 0 Stretch Story: 0 | K32: Internal: External: Appreciation for completing most of the regression stories eventhough it is a full regression
A33: =IF(AND($D$1>=C33,$D$1<=D33),"CurrentSprint","NA") -> #N/A | B33: 4.22 - Sprint 1 | C33: 45772 | D33: 45785 | E33: 35 | F33: 31 | G33: Introduced - 3 | I33: Wrap up 4.21 Regression(Defects found), Adding new templates to Custom Reports, Tier Model, Add Menu Product Sold Qtys to Daily Sales Preview, and MSB Reconciliation. | J33: CRC Internal -- 5 CRC External -- 0 QA Defects -- 2 Escaped Defects -- 0 Stretch Story: 0 | K33: Internal: External:
... A35: =IF(AND($D$1>=C35,$D$1<=D35),"CurrentSprint","NA") -> #N/A | B35: 4.22 - Sprint 3 | C35: 45800 | D35: 45813 | E35: 40 | F35: 37.75 | G35: Nil | I35: Cutom Report for Eligibility Student Listing | J35: CRC Internal -- 0 CRC External -- 0 QA Defects -- 0 Escaped Defects -- 0 Stretch Story: 3 | K35: Internal: External:
A36: =IF(AND($D$1>=C36,$D$1<=D36),"CurrentSprint","NA") -> #N/A | B36: 4.23 - Sprint 1 | C36: 45814 | D36: 45826 | E36: 10 | F36: 10 | G36: Introduced - 21 | J36: CRC Internal -- 2 CRC External -- 0 QA Defects -- 0 Escaped Defects -- 0 Stretch Story: 4 | K36: Internal: External:
A37: =IF(AND($D$1>=C37,$D$1<=D37),"CurrentSprint","NA") -> #N/A | B37: 4.23 - Sprint 2 | C37: 45827 | D37: 45841 | E37: 20 | F37: 20 | G37: Introduced - 16 | I37: Supplemental Programs Claim Report | J37: CRC Internal -- 1 CRC External -- 0 QA Defects -- 1 Escaped Defects -- 0 Stretch Story: 3 | K37: Internal: External:
A38: =IF(AND($D$1>=C38,$D$1<=D38),"CurrentSprint","NA") -> #N/A | B38: 4.23 - Sprint 3 | C38: 45842 | D38: 45855 | E38: 14 | F38: 14 | G38: Introduced-7 | I38: Custom Report for Transaction History, Modifications to Louisiana SFS-8C Report | J38: CRC Internal -- 4 CRC External -- 0 QA Defects -- 1 Escaped Defects -- 0 Stretch Story: 4 | K38: Internal: External: What went well: Successfully completed the assigned stories What didn't go well: Nil
A39: =IF(AND($D$1>=C39,$D$1<=D39),"CurrentSprint","NA") -> #N/A | B39: 4.23 - Sprint 4 | C39: 45856 | D39: 45869 | E39: 14 | F39: 16 | G39: Introduced - 17 | I39: Defect fixes and 4.23 Regression testing | J39: CRC Internal -- 2 CRC External -- 0 QA Defects -- 1 Escaped Defects -- 0 Stretch Story: 7 | K39: Internal: External: What went well: Successfully completed the Regression testing, Completed the assigned stories What didn't go well: Nil
A40: =IF(AND($D$1>=C40,$D$1<=D40),"CurrentSprint","NA") -> #N/A | B40: 4.24 - Sprint 1 | C40: 45870 | D40: 45883 | E40: 12 | F40: 15 | G40: Introduced - 15 | I40: Support for Credit Card in Additional Meal Programs for Reports,Delete functionality for User Custom Report | J40: CRC Internal -- 11 CRC External -- 0 QA Defects -- 1 Escaped Defects -- 0 Stretch Story: 6 | K40: Internal: External: What went well: Successfully completed the assigned stories What didn't go well: Nil
A41: =IF(AND($D$1>=C41,$D$1<=D41),"CurrentSprint","NA") -> #N/A | B41: 4.24 - Sprint 2 | C41: 45884 | D41: 45897 | E41: 10 | F41: 13 | G41: Introduced - 22 | I41: Dashboard feature for copy and enlarge wiidgets, implemented new datasource in custom report. | J41: CRC Internal -- 1 CRC External -- 0 QA Defects -- 1 Escaped Defects -- 0 Stretch Story: 5 | K41: Internal: External: What went well: Successfully completed the assigned stories. Successfully completed the dashboard related features. What didn't go well: Nil
A42: =IF(AND($D$1>=C42,$D$1<=D42),"CurrentSprint","NA") -> #N/A | B42: 4.24 - Sprint 3 | C42: 45898 | D42: 45911 | E42: 8 | F42: 18 | G42: Introduced - 28 | I42: New Template for Daily Sales Summary Report,Daily Sales By Serving Line Report,Dashboard UI Enhancement and Other Reports Improvements, Automation | J42: CRC Internal -- 1 CRC External -- 0 Peer Testing - 1 POV Comments - 4 QA Defects -- 1 Escaped Defects -- 0 Stretch Story: 7 | K42: Internal: External: What went well: Completed Forecast and lot more, Automation progress, Hosted platforms - SYSU, All schools back in session, Esclation down from previous years (Note: Esclations from coustomer support are handled by client developer Steve) What didn't go well: Lost Ying to BOH team Esclations
A43: =IF(AND($D$1>=C43,$D$1<=D43),"CurrentSprint","NA") -> #N/A | B43: 4.24 - Sprint 4 | C43: 45912 | D43: 45925 | E43: 14 | F43: 15 | G43: Introduced - 11 | I43: Defect fixes and 4.24 Regression testing | J43: "CRC Internal --0 CRC External -- 0 Peer Testing - 3 POV Comments - QA Defects -- 0 Escaped Defects -- 0 Stretch Story: 4" | K43: Internal: External: What went well: Offshore Completed regression and defects including testing, Completed Forecast and more, Defects fixed into releases What didn't go well: Esclations (Note: Esclations from coustomer support are handled by client developer Steve), Added items in last minute to include in release
A44: =IF(AND($D$1>=C44,$D$1<=D44),"CurrentSprint","NA") -> #N/A | B44: 4.25 - Sprint 1 | C44: 45926 | D44: 45939 | E44: 13 | F44: 13 | G44: Introduced - 16 | I44: Modifications to Operating Days, new filter for ‘Participation by’ to Standard Claim Report, and New Template to ‘Daily Sales By Serving Line Report’. | J44: CRC Internal -- 3 CRC External -- 0 Peer Testing - 2 POV Comments - 4 QA Defects -- 1 Escaped Defects -- 0 Stretch Story: 4 | K44: Internal: External: What went well: Completed more than Forecast , Esclations (not too bad this week), mike completed testing before PTO, Team completed rest of testing after Mike PTO What didn't go well: Apigee issue (platformops and apigee team)
A45: =IF(AND($D$1>=C45,$D$1<=D45),"CurrentSprint","NA") -> #N/A | B45: 4.25 - Sprint 2 | C45: 45940 | D45: 45953 | E45: 15 | F45: 21 | G45: Introduced - 18 | H45: New Dashboard Widgets, Ability to flip between Apigee & Existing endpoints, ‘Participation By’ filter to Supplemental Programs Claim Report, Tyler Munis Export Modifications, update to VA SNP-12 Report, Add Active Flag to Student Export Setup, and 4.24 Release Prep | I45: New Dashboard Widgets, ‘Participation By’ filter to Supplemental Programs Claim Report, Updating report format to meet Mosaic standards | J45: CRC Internal -- 0 CRC External -- 0 Peer Testing - 6 POV Comments - 6 QA Defects -- 1 Escaped Defects -- 0 Stretch Story: 6 | K45: Internal: External: What went well: Completed more than Forecast What didn't go well: NA
A46: =IF(AND($D$1>=C46,$D$1<=D46),"CurrentSprint","NA") -> #N/A | B46: 4.25 - Sprint 3 | C46: 45954 | D46: 45967 | E46: 12 | F46: 23 | G46: Introduced - 23 | H46: Adding a Student Debt Chart to the Dashboard, Replacing Master Serving Period with Serving Period Program, New ‘Group By School’ filter to Students w/out an Elig. Determination Report, DC Import Improvements, and NJ Master Eligibility List report Modifications | I46: Export 'User Created Custom Reports', 'User Assignments Report' to meet Mosaic Standard, Legacy imports are moved to Utilities | J46: CRC Internal -- 0 CRC External -- 0 Peer Testing - 1 POV Comments - 6 QA Defects -- 0 Escaped Defects -- 0 Stretch Story: 10 | K46: Internal: External: What went well: Releases, Exceeded Forecast What didn't go well: Esclations (Note: Esclations from coustomer support are handled by client developer Steve)
A47: =IF(AND($D$1>=C47,$D$1<=D47),"CurrentSprint","NA") -> #N/A | B47: 4.25 - Sprint 4 | C47: 45968 | D47: 45981 | E47: 10 | F47: 12 | G47: Introduced - 36 | H47: IL WINS Export Scheduler Task, Importing Custom Report Format, Added new data source to report designer | I47: IL WINS Export Scheduler Task, Importing Custom Report Format, NSS ID in Visual Report, Added new datasource to the Report designer | J47: CRC Internal -- 15 CRC External -- 1 Peer Testing - 3 POV Comments - 2 QA Defects -- 2 Escaped Defects -- 0 Stretch Story: 10 | K47: Internal: External: What went well: Hit Forecast, SNYK progress in stretch What didn't go well: CPS Release, Apigee work, MSB Endpoint Change.
A48: =IF(AND($D$1>=C48,$D$1<=D48),"CurrentSprint","NA") -> #N/A | B48: 4.25 - Sprint 5 | C48: 45982 | D48: 46009 | E48: 23 | F48: 37 | G48: Introduced - 37 | H48: New Templates for Custom Reports, New Data Sources for Report Designer, and 4.25 Regression Testing | I48: Completed 4.25 regression testing with defect fixes. | J48: CRC Internal -- 2 CRC External -- 0 QA Defects -- 2 Escaped Defects -- 0 Stretch Story: 8 Defects RC: 1. Calculation mismatch not captured in unit testing. 2. It is the data issue which occurred in other developer's DB. It is handled now. Internal CRC comments RC: 1. Missed to ensure SQL script file naming standards 2. Misunderstood the acceptance criteria | K48: Internal: External: What went well: Insane no.of stories completed(Sp's), started using Browser Stack for automation. What didn't go well: Escalations, MSB Endpoint Change.
A49: =IF(AND($D$1>=C49,$D$1<=D49),"CurrentSprint","NA") -> #N/A | B49: 26.1 - Sprint 1 | C49: 46010 | D49: 46037 | E49: 27 | F49: 32 | G49: Introduced - 30 | H49: Support for Multiple Languages in SL, Automation, Meal Count Entry Audit Report, Feature flag changes | I49: Completed Support for Multiple Languages in SL, Automation, Meal Count Entry Audit Report, Feature flag changes | J49: CRC Internal -- 24 CRC External -- 2 QA Defects -- 4 Escaped Defects -- 0 Stretch Story: 9 Defects RC: 1. Missed UI validation for the textbox. 2. Missed to handle the scenario of enable/disable Language feature flag. 3. Missed to test around the UI changes 4. Missed to check Parent table column's lenght and Language tables column's length Internal CRC comments RC: 1. Missed UI validations 2. Missed SQL script file standards 3. Missed to ensure date format 4. Not keeping common table name in SQL script 5. Some implicit stuff needs to be incorporated as part of the requirement which I'm not aware of 6. I missed to clean up or refactor some portion of the SQL code | K49: What went well: Completed the forecast and almost the same in the stretch. 2. Holidays. 3. 502 gateway Apigee issues solving (prod) What didn't go well: 365 migration, MSB from www to etransfer issue.
A50: =IF(AND($D$1>=C50,$D$1<=D50),"CurrentSprint","NA") -> #N/A | B50: 26.1 - Sprint 2 | C50: 46038 | D50: 46051 | E50: 17 | F50: 17 | G50: Introduced - 0 | H50: Updates to Meal Report and User Report, Mosaic BOH Knowledge transfer | I50: Completed the Mosaic Standards for User Reports and Meals Reports, Mosaic BOH Knowledge transfer | J50: CRC Internal -- 0 CRC External --0 QA Defects -- 1 Escaped Defects -- 0 Stretch Story: 0 Defects RC: 1. Pre existing UI design which was there originally. PO wanted to fix it as part of this story hence it was fixed. Internal CRC comments RC: None | K50: Internal: External: What went well: Completed commit and stretch items. 2. 4.24 Hot fix/4.25 Beta 3. BOH KT What didn't go well: 1. Vending QA, 2. Missing App switcher script in 4.25 Beta 3. App switcher button is not always working. Recieved appretiaton from QA during retro that offshore helped to close the testing stories during the sprint end.
A51: =IF(AND($D$1>=C51,$D$1<=D51),"CurrentSprint","NA") -> #N/A | B51: 26.1 - Sprint 3 | C51: 46052 | D51: 46065 | E51: 5 | F51: 16 | G51: Introduced - 30 | H51: Modified Prepay Report to Mosaic Standard, Defect Fixes, Hide Tier Feature from UI BOH Reverse KT, Automation | I51: Completed the Prepay Report to meet Mosaic Standard, BOH Reverse KT | J51: CRC Internal -- 0 Peer testing - 1 CRC External -- 0 QA Defects -- 2 Escaped Defects -- 0 POV Comments - 5 Stretch Story: 13 CRC RC: Nil Defects RC: 1. css styling not handled and so improper visual spacing between UI components occured 2. Missed to show proper version format | K51: "Internal: External: What went well: 1. Exceeded the forcast story points. 2. 4.25 release. What didn't go well: 1. Escalations, 2. 4.25 rused out(App switcher not working), 3. Dashboard issues." | L51: 0 | M51: 1
A52: =IF(AND($D$1>=C52,$D$1<=D52),"CurrentSprint","NA") -> #N/A | B52: 26.1 - Sprint 4 | C52: 46066 | D52: 46079 | E52: 2 | F52: 4 | G52: Introduced - 26 | H52: Add New Security page for Report Designer, Edit Report button to the Custom Reports UI, Automation | I52: Completed the Report Designer feature in Security Page | J52: CRC Internal -- 0 Peer testing - 0 CRC External -- 0 QA Defects -- 0 Escaped Defects -- 0 POV Comments - 0 Stretch Story: 4 CRC RC: Nil Defects RC: Nil | K52: Internal: External: What went well: 1. Offshore work on regression, 2. Hosted Test environment(Mike getting builds up) What didn't go well: 1. SQL cypher(Not working with .460) | L52: 1 | M52: 5
A53: =IF(AND($D$1>=C53,$D$1<=D53),"CurrentSprint","NA") -> #N/A | B53: 26.5 - Sprint 1 | C53: 46080 | D53: 46093 | E53: 6 | F53: 8 | G53: Introduced - 20 | H53: User Tasks Maintenance and Setup, Automation | I53: Added User Tasks Maintenance and Setup screen, Automation | J53: CRC Internal -- 5 Peer testing - 3 CRC External -- 0 QA Defects -- 15 Escaped Defects -- 0 POV Comments - 6 Stretch Story: 4 CRC RC: 1. Missed to follow localization support (2) 2. Missed to follow exsiting coding standards (1) 3. unwanted code (1) 4. returning entity directly (1) Defects RC: 1. UI validations should be added properly (4) 2. UI design issues (8) 3. Data issue (3) | K53: Internal: External: What went well: 1. Exceeded commit, 2. SQLCypher progress, 3. Regression completed on time | L53: 3 | M53: 5
A54: =IF(AND($D$1>=C54,$D$1<=D54),"CurrentSprint","NA") -> #N/A | B54: 26.5 - Sprint 2 | C54: 46094 | D54: 46107 | E54: 13 | F54: 13 | G54: Introduced - 27 | H54: User Assignment in User Task, Mosaic BOH - Transfers - Bulk Replace, Automation | I54: User Assignment in User Task, Mosaic BOH - Transfers - Bulk Replace, Add, Delete | J54: "CRC Internal -- 1 Peer testing - 4 CRC External -- 0 QA Defects -- 3 Escaped Defects -- 0 POV Comments - 11 Stretch Story: 6 CRC RC: 1. Missed to remove the unwanted code Defects RC: 1. UI design issues 2. Backend validation did not match the UI validation. (2) POV RC: Cosmetic changes (4) Sugeestions (3) Data issue (2) | K54: Internal: External: What went well: 1. 26.1 Release 2. Exceeded commit What didn't go well: Apigee & WAF issues | L54: 3 | M54: 4.5
A55: =IF(AND($D$1>=C55,$D$1<=D55),"CurrentSprint","NA") -> #N/A | B55: 26.5 - Sprint 3 | C55: 46108 | D55: 46121

Sheet 26.5 - Sprint 1-Defect
A1: S.No | B1: Sprint # | C1: Story/Defect ID | D1: Parent Story | E1: Developer | F1: Issue Type | G1: Issue Description | H1: Priority | I1: Defect Source | J1: Type | K1: Status | L1: Dev Start Date | M1: Dev End Date | N1: Root Cause Category | O1: Comments
B2: 26.5 - Sprint 1 | C2: 51349 | D2: 51349 | E2: Vidhya | F2: Bounceback/Sub-Defect | G2: 1. Alert message coming for Simple Task 2. Continue button is disabled / Continue button is not enabled when I Edit the details from Simple Task to Custom Link 3. Getting popup without edit details 4. Getting an error when editing the details from Custom link to Simple Task | H2: Minor | I2: Manual | J2: Internal | K2: Story Being Developed | L2: 46093 | N2: UI Validations
B3: 26.5 - Sprint 1 | C3: 21786 | D3: 21786 | E3: Sabir | F3: Bounceback/Sub-Defect | G3: 1. Alignment Issues in User Task Search Screen 2. Lengthy text for Task Name / Test Description 3. Data showing incorrectly 4. If I click the Hide Filters, Reset is not working 5. Selected Value is not updated 6. When O&I is disabled, still User task created using O& I, I think it should not come 7. Recurrence is showing Yearly instead of Annually 8. Newly added record should be showing in first but now it shows last 9. Data is not showing based on filters 10.Assigned To should show only Name not Username 11. Text wrap issue in Status column | H3: Significant | I3: Manual | J3: Internal | K3: Story Being Developed

Sheet 26.1 - Sprint 4-Status
A1: S.No | B1: Application Name | C1: Sprint Start Date | D1: Sprint End Date | E1: Sprint | F1: Developer/Tester | G1: Story ID/Defect ID | H1: Description | I1: Status | J1: Estimated(hrs/sp) | K1: Actual(hrs/sp) | L1: Actual Worklog (Hours) | M1: Dev Start Date | N1: Dev End Date | O1: Unit testing | P1: Peer Tested By | Q1: Peer Tested Comments, if any | R1: Peer Reviewed By | S1: Peer Code Review Comments, if any | T1: PR Number/Link | U1: PR Created Date | V1: PR Approved Date | W1: Onsite Lead Code Review | X1: Code Review Comments, if any | Y1: Client Code Review | Z1: Approved Date | AA1: Code Review Comments, if any2 | AB1: Internal PO -POV Comments | AC1: Client PO -POV Comments | AD1: Comments | AE1: Does this story meet expectations?
A2: 1 | B2: FOH Wave | C2: 46066 | D2: 46079 | E2: 26.1 - Sprint 4 - Stretch | F2: Vidhya | G2: 51349 | H2: [WAVE] Mosaic BOH - (3) User Tasks - Add/Edit Tasks | I2: Story Being Developed | J2: 13 | K2: =Table2456891021213141116171118192021152223242526272829303132[[#This Row],[Actual Worklog (Hours)]] / 4 -> 12 | L2: 48 | M2: 46066 | N2: NA | O2: NA | P2: NA | Q2: NA | R2: NA | S2: NA | T2: NA | U2: NA | V2: NA | W2: NA | X2: NA | Y2: NA | Z2: NA | AA2: NA | AB2: NA | AC2: NA | AD2: NA | AE2: NA
A3: 2 | B3: FOH Wave | C3: 46066 | D3: 46079 | E3: 26.1 - Sprint 4 | F3: Subbulakshmi | G3: 51456 | H3: MFOH (WAVE) - Add a new security page for Report Designer | I3: Story Completed | J3: 1 | K3: =Table2456891021213141116171118192021152223242526272829303132[[#This Row],[Actual Worklog (Hours)]] / 4 -> 1 | L3: 4 | M3: 46066 | N3: 46066 | O3: NA | P3: NA | Q3: NA | R3: NA | S3: NA | T3: NA | U3: NA | V3: NA | W3: NA | X3: NA | Y3: NA | Z3: NA | AA3: NA | AB3: NA | AC3: NA | AD3: NA | AE3: NA
A4: 3 | B4: FOH Wave | C4: 46066 | D4: 46079 | E4: 26.1 - Sprint 4 | F4: Subbulakshmi | G4: 51457 | H4: MFOH (WAVE) - Add an Edit Report button to the Custom Reports UI | I4: Story Completed | J4: 1 | K4: =Table2456891021213141116171118192021152223242526272829303132[[#This Row],[Actual Worklog (Hours)]] / 4 -> 1 | L4: 4 | M4: 46066 | N4: 46069 | O4: NA | P4: NA | Q4: NA | R4: NA | S4: NA | T4: NA | U4: NA | V4: NA | W4: NA | X4: NA | Y4: NA | Z4: NA | AA4: NA | AB4: NA | AC4: NA | AD4: NA | AE4: NA
A5: 4 | B5: FOH Wave | C5: 46066 | D5: 46079 | E5: 26.1 - Sprint 4 - Stretch | F5: Subbulakshmi | G5: 51803 | H5: MFOH - Automation (Smoke) - Kaleida changes update to the close day search screen & close day maintenance screen | I5: Story Being Developed | J5: 3 | K5: =Table2456891021213141116171118192021152223242526272829303132[[#This Row],[Actual Worklog (Hours)]] / 4 -> 2.5 | L5: 10 | M5: 46070 | N5: NA | O5: NA | P5: NA | Q5: NA | R5: NA | S5: NA | T5: NA | U5: NA | V5: NA | W5: NA | X5: NA | Y5: NA | Z5: NA | AA5: NA | AB5: NA | AC5: NA | AD5: NA | AE5: NA
A6: 5 | B6: FOH Wave | C6: 46066 | D6: 46079 | E6: 26.1 - Sprint 4 - Stretch | F6: Subbulakshmi | G6: 51804 | H6: MFOH - Automation (Smoke) - Kaleida changes update to the close day report search screen & close day report maintenance screen | I6: Story Completed | J6: 2 | K6: =Table2456891021213141116171118192021152223242526272829303132[[#This Row],[Actual Worklog (Hours)]] / 4 -> 3 | L6: 12 | M6: 46069 | N6: 46072 | O6: Subbulakshmi | P6: NA | Q6: NA | R6: NA | S6: NA | T6: 47411 | U6: 46073 | V6: 46073 | W6: Subha | X6: NA | Y6: NA | Z6: 46073 | AA6: NA | AB6: NA | AC6: NA | AD6: NA | AE6: NA
A7: 6 | B7: FOH Wave | C7: 46066 | D7: 46079 | E7: 26.1 - Sprint 4 - Stretch | F7: Sabir | G7: 21786 | H7: [WAVE] Mosaic BOH - (2) User Tasks - Add to the Setup - UI Implementation | I7: Story Being Developed | J7: 8 | K7: 10.5 | L7: 42 | M7: 46066 | N7: NA | O7: NA | P7: NA | Q7: NA | R7: NA | S7: NA | T7: NA | U7: NA | V7: NA | W7: NA | X7: NA | Y7: NA | Z7: NA | AA7: NA | AB7: NA | AC7: NA | AD7: Nested Menu dropdown using Vega control is new for FOH and BOH team also. we ask help for Vega technical team. They sent link for refrence. Based on that reference i am trying to implement Nested Menu dropdown. that is the reason story points exceed. | AE7: NA

Sheet 26.1 - Sprint 4-Defect
A1: S.No | B1: Sprint # | C1: Story/Defect ID | D1: Parent Story | E1: Developer | F1: Issue Type | G1: Issue Description | H1: Priority | I1: Defect Source | J1: Type | K1: Status | L1: Dev Start Date | M1: Dev End Date | N1: Root Cause Category | O1: Comments

Sheet 26.1 - Sprint 3-Status
A1: S.No | B1: Application Name | C1: Sprint Start Date | D1: Sprint End Date | E1: Sprint | F1: Developer/Tester | G1: Story ID/Defect ID | H1: Description | I1: Status | J1: Estimated(hrs/sp) | K1: Actual(hrs/sp) | L1: Actual Worklog (Hours) | M1: Dev Start Date | N1: Dev End Date | O1: Unit testing | P1: Peer Tested By | Q1: Peer Tested Comments, if any | R1: Peer Reviewed By | S1: Peer Code Review Comments, if any | T1: PR Number/Link | U1: PR Created Date | V1: PR Approved Date | W1: Onsite Lead Code Review | X1: Code Review Comments, if any | Y1: Client Code Review | Z1: Approved Date | AA1: Code Review Comments, if any2 | AB1: Internal PO -POV Comments | AC1: Client PO -POV Comments | AD1: Comments | AE1: Does this story meet expectations?
A2: 1 | B2: FOH Wave | C2: 46052 | D2: 46065 | E2: 26.1 - Sprint 3 | F2: Subbulakshmi / Hemanath Jayaraman / Sabir / Vidhya | G2: 51719 | H2: MFOH [WAVE] - Knowledge Transfer from Mosaic BOH Team (Continuation Story) | I2: Story Completed | J2: 5 | K2: =Table24568910212131411161711181920211522232425262728293031[[#This Row],[Actual Worklog (Hours)]] / 4 -> 14.75 | L2: 59 | M2: 46052 | N2: 46059 | O2: NA | P2: NA | Q2: NA | R2: NA | S2: NA | T2: NA | U2: NA | V2: NA | W2: NA | X2: NA | Y2: NA | Z2: NA | AA2: NA | AB2: NA | AC2: NA | AD2: NA | AE2: NA
A3: 2 | B3: FOH Wave | C3: 46052 | D3: 46065 | E3: 26.1 - Sprint 3 - Stretch | F3: Sabir | G3: 51647 | H3: MFOH [WAVE] - Add a School as an Order By option to the Custom Student Report (New Hanover) | I3: Story Need More Info | J3: 2 | K3: =Table24568910212131411161711181920211522232425262728293031[[#This Row],[Actual Worklog (Hours)]] / 4 -> 0.5 | L3: 2 | M3: 46052 | N3: 46052 | O3: NA | P3: NA | Q3: NA | R3: NA | S3: NA | T3: NA | U3: NA | V3: NA | W3: NA | X3: NA | Y3: NA | Z3: NA | AA3: None | AB3: NA | AC3: NA | AD3: needs clarification with gary(client) | AE3: NA
A4: 3 | B4: FOH Wave | C4: 46052 | D4: 46065 | E4: 26.1 - Sprint 3 - Stretch | F4: Vidhya | G4: 51456 | H4: MFOH (WAVE) - Add a new security page for Report Designer | I4: Story Ready For Testing | J4: 3 | K4: =Table24568910212131411161711181920211522232425262728293031[[#This Row],[Actual Worklog (Hours)]] / 4 -> 4 | L4: 16 | M4: 46052 | N4: 46057 | O4: Vidhya | P4: Sabir | Q4: None | R4: Sabir | S4: None | T4: 47222 | U4: 46065 | V4: 46065 | W4: Subha | X4: None | Y4: Steve | Z4: 46065 | AA4: None | AB4: 1) POV Date: 02/09/2025 The field level security wasn't working 2) POV Date: 02/10/2025 The Main security setting for report designer was unchecked in both central and local, but still the report designer is visible in the reports menu. | AC4: NA | AD4: Exceeded the given time because there is some issue with the existing Custom Report node which has been discussed to be fixed along with this story. Actual implementation for this story was done and finished the POV on 02/04/2026 | AE4: Meets Expectation
A5: 4 | B5: FOH Wave | C5: 46052 | D5: 46065 | E5: 26.1 - Sprint 3 - Stretch | F5: Hemanath / Vidhya | G5: 51704 | H5: MFOH [WAVE] - Hide Tier Feature from Mosaic Screens | I5: Story Completed | J5: 3 | K5: =Table24568910212131411161711181920211522232425262728293031[[#This Row],[Actual Worklog (Hours)]] / 4 -> 3.375 | L5: 13.5 | M5: 46055 | N5: 46056 | O5: Hemanath | P5: Vidhya | Q5: Security field popup spacing needs to be adjusted | R5: Vidhya | S5: None | T5: 47180 | U5: 46063 | V5: 46063 | W5: Subha | X5: None | Y5: Steve | Z5: 46063 | AA5: None | AB5: None | AC5: None | AD5: None | AE5: Meets Expectation
A6: 5 | B6: FOH Wave | C6: 46052 | D6: 46065 | E6: 26.1 - Sprint 3 - Stretch | F6: Subbulakshmi | G6: 51751 | H6: MFOH [WAVE] - Automation (50749) | I6: Story Completed | J6: 2 | K6: =Table24568910212131411161711181920211522232425262728293031[[#This Row],[Actual Worklog (Hours)]] / 4 -> 2 | L6: 8 | M6: 46056 | N6: 46058 | O6: Subbulakshmi | P6: NA | Q6: NA | R6: NA | S6: NA | T6: 47153 | U6: 46062 | V6: 46062 | W6: Subha | X6: None | Y6: None | Z6: 46062 | AA6: None | AB6: NA | AC6: NA | AD6: None | AE6: Meets Expectation
A7: 6 | B7: FOH Wave | C7: 46052 | D7: 46065 | E7: 26.1 - Sprint 3 - Stretch | F7: Sabir | G7: 51755 | H7: MFOH [WAVE] - Modify the 'Prepay Report' to meet Mosaic Standard | I7: Story Completed | J7: 3 | K7: 3 | L7: 12 | M7: 46057 | N7: 46058 | O7: Sabir | P7: Ashwin | Q7: NA | R7: Ashwin | S7: NA | T7: 47176 | U7: 46063 | V7: 46063 | W7: Subha | X7: None | Y7: None | Z7: 46063 | AA7: None | AB7: POV Date: 02/05/2025 1) Serving date header was misplaced 2) There was an empty column added for the totals 3) Alignment issue with the serving period header | AC7: NA | AD7: None | AE7: Meets Expectation
A8: 7 | B8: FOH Wave | C8: 46052 | D8: 46065 | E8: 26.1 - Sprint 3 - Stretch | F8: Hemanath / Vidhya | G8: 51785 | H8: MFOH [WAVE] - Add a Homeroom filter to NJ Master Eligibility List Report | I8: Story Completed | J8: 3 | K8: =Table24568910212131411161711181920211522232425262728293031[[#This Row],[Actual Worklog (Hours)]] / 4 -> 3.375 | L8: 13.5 | M8: 46057 | N8: 46058 | O8: Hemanath | P8: Vidhya | Q8: None | R8: Vidhya | S8: None | T8: 47165 | U8: 46063 | V8: 46063 | W8: Subha | X8: None | Y8: Steve | Z8: 46063 | AA8: None | AB8: None | AC8: NA | AD8: None | AE8: Meets Expectation
A9: 8 | B9: FOH Wave | C9: 46052 | D9: 46065 | E9: 26.1 - Sprint 3 - Stretch | F9: Vidhya | G9: 26732 | H9: MFoH - Reports - Custom - Daily Sales and A la Carte report templates broken | I9: Defect Fixed | J9: 0 | K9: 0 | L9: 6 | M9: 46058 | N9: 46058 | O9: Vidhya | P9: Subbulakshmi | Q9: None | R9: Hemanath | S9: None | T9: 47108 | U9: 46058 | V9: 46058 | W9: Subha | X9: None | Y9: Steve | Z9: 46058 | AA9: None | AB9: None | AC9: None | AD9: None | AE9: Meets Expectation
A10: 9 | B10: FOH Wave | C10: 46052 | D10: 46065 | E10: 26.1 - Sprint 3 - Stretch | F10: Subbulakshmi | G10: 51803 | H10: MFOH - Automation (Smoke) - Kaleida changes update to the close day search screen & close day maintenance screen | I10: Story Being Developed | J10: 5 | K10: =Table24568910212131411161711181920211522232425262728293031[[#This Row],[Actual Worklog (Hours)]] / 4 -> 1.5 | L10: 6 | M10: 46062 | N10: NA | O10: NA | P10: NA | Q10: NA | R10: NA | S10: NA | T10: NA | U10: NA | V10: NA | W10: NA | X10: NA | Y10: NA | Z10: NA | AA10: NA | AB10: NA | AC10: NA | AD10: NA | AE10: NA
A11: 10 | B11: FOH Wave | C11: 46052 | D11: 46065 | E11: 26.1 - Sprint 3 - Stretch | F11: Vidhya | G11: 51457 | H11: MFOH (WAVE) - Add an Edit Report button to the Custom Reports UI | I11: Story Ready For Testing | J11: 1 | K11: =Table24568910212131411161711181920211522232425262728293031[[#This Row],[Actual Worklog (Hours)]] / 4 -> 0.75 | L11: 3 | M11: 46059 | N11: 46059 | O11: Vidhya | P11: Sabir | Q11: None | R11: Sabir | S11: None | T11: 47223 | U11: 46065 | V11: 46065 | W11: Subha | X11: None | Y11: Steve | Z11: 46065 | AA11: None | AB11: None | AC11: NA | AD11: There was an issue in the Custom Report when we create it with the name "Student Listing Report" due to name conflicts in Kaleida changes. We have fixed it along with this story | AE11: Meets Expectation
A12: 11 | B12: FOH Wave | C12: 46052 | D12: 46065 | E12: 26.1 - Sprint 3 - Stretch | F12: Sabir | G12: 51829 | H12: MFOH [WAVE] Mosaic BOH - User Tasks - Add to Security Group - (1) | I12: Story Being Developed | J12: 3 | K12: 3 | L12: 12 | M12: 46059 | N12: 46063 | O12: Sabir | P12: NA | Q12: NA | R12: NA | S12: NA | T12: NA | U12: NA | V12: NA | W12: NA | X12: None | Y12: NA | Z12: NA | AA12: NA | AB12: none | AD12: POV is completed. waiting for peer testing and code review
A13: 12 | B13: FOH Wave | C13: 46052 | D13: 46065 | E13: 26.1 - Sprint 3 - Stretch | F13: Subbulakshmi | G13: 51804 | H13: MFOH - Automation (Smoke) - Kaleida changes update to the close day report search screen & close day report maintenance screen | I13: Story Being Developed | J13: 3 | K13: =Table24568910212131411161711181920211522232425262728293031[[#This Row],[Actual Worklog (Hours)]] / 4 -> 1.5 | L13: 6 | M13: 46063 | N13: NA | O13: NA | P13: NA | Q13: NA | R13: NA | S13: NA | T13: NA | U13: NA | V13: NA | W13: NA | X13: NA | Y13: NA | Z13: NA | AA13: NA | AB13: NA | AC13: NA | AD13: NA | AE13: NA
A14: 13 | B14: FOH Wave | C14: 46052 | D14: 46065 | E14: 26.1 - Sprint 3 - Stretch | F14: Vidhya | G14: 26760 | H14: MFOH [WAVE] - Fix the error when exporting the dashboard widget | I14: Defect Ready For Testing | J14: 2 | K14: =Table24568910212131411161711181920211522232425262728293031[[#This Row],[Actual Worklog (Hours)]] / 4 -> 1.5 | L14: 6 | M14: 46063 | N14: 46063 | O14: Vidhya | P14: Subbulakshmi | Q14: None | R14: Subha | S14: None | T14: 47179 | U14: 46063 | V14: 46063 | W14: Subha | X14: None | Y14: Steve | Z14: 46063 | AA14: None | AB14: NA | AC14: NA | AD14: None | AE14: Meets Expectation
A15: 14 | B15: FOH Wave | C15: 46052 | D15: 46065 | E15: 26.1 - Sprint 3 - Stretch | F15: Vidhya | G15: 26749 | H15: MFOH [WAVE] - Fix the console error that blocks the save and retrieval of the dashboard | I15: Defect Being Fixed | J15: 0 | K15: 0 | L15: 12 | M15: 46062 | N15: 46064 | O15: NA | P15: NA | Q15: NA | R15: NA | S15: NA | T15: NA | U15: NA | V15: NA | W15: NA | X15: NA | Y15: NA | Z15: NA | AA15: NA | AB15: NA | AC15: NA | AD15: NA | AE15: Meets Expectation

Sheet 26.1 - Sprint 3-Defect
A1: S.No | B1: Sprint # | C1: Story/Defect ID | D1: Parent Story | E1: Developer | F1: Issue Type | G1: Issue Description | H1: Priority | I1: Defect Source | J1: Type | K1: Status | L1: Dev Start Date | M1: Dev End Date | N1: Root Cause Category | O1: Comments
B2: 26.1 - Sprint 3 - Stretch | C2: 51704 | D2: 51704 | E2: Hemanath | F2: Bounceback/Sub-Defect | G2: Spacing issue in District Maintenance screen - Others tab | H2: Minor | I2: Manual | J2: Internal | K2: Story Completed | L2: 46064 | M2: 46065 | N2: Design Issue | O2: Spacing issue in District Maintenance screen - Others tab
B3: 26.1 - Sprint 3 - Stretch | C3: 51755 | D3: 51755 | E3: Sabir | F3: Bounceback/Sub-Defect | G3: Reports generated by the Mosaic POS system are showing "0.0.0.0" in the footer instead of displaying the correct version number like Mosaic POS v0.0.0.0 | H3: Minor | I3: Manual | J3: Internal | K3: Story Completed | L3: 46065 | M3: 46065 | N3: Design Issue | O3: Reports generated by the Mosaic POS system are showing "0.0.0.0" in the footer instead of displaying the correct version number like Mosaic POS v0.0.0.0

Sheet 26.1 - Sprint 2-Status
A1: S.No | B1: Application Name | C1: Sprint Start Date | D1: Sprint End Date | E1: Sprint | F1: Developer/Tester | G1: Story ID/Defect ID | H1: Description | I1: Status | J1: Estimated(hrs/sp) | K1: Actual(hrs/sp) | L1: Actual Worklog (Hours) | M1: Dev Start Date | N1: Dev End Date | O1: Unit testing | P1: Peer Tested By | Q1: Peer Tested Comments, if any | R1: Peer Reviewed By | S1: Peer Code Review Comments, if any | T1: PR Number/Link | U1: PR Created Date | V1: PR Approved Date | W1: Onsite Lead Code Review | X1: Code Review Comments, if any | Y1: Client Code Review | Z1: Approved Date | AA1: Code Review Comments, if any2 | AB1: Internal PO -POV Comments | AC1: Client PO -POV Comments | AD1: Comments | AE1: Does this story meet expectations?
A2: 1 | B2: FOH Wave | C2: 46038 | D2: 46051 | E2: 26.1 - Sprint 2 | F2: Subbulakshmi | G2: 51358 | H2: MFOH [WAVE] - Automation (50441) | I2: Story Completed | J2: 1 | K2: =Table245689102121314111617111819202115222324252627282930[[#This Row],[Actual Worklog (Hours)]] / 4 -> 0.75 | L2: 3 | M2: 46038 | N2: 46043 | O2: NA | P2: NA | Q2: NA | R2: NA | S2: NA | T2: 46772 | U2: 46043 | V2: 46043 | W2: Subha | X2: None | Y2: Steve | Z2: 46043 | AA2: None | AB2: None | AC2: None | AD2: None | AE2: Meets Expectation
A3: 2 | B3: ='Dashboard-2025'!$K$1 -> FOH Wave | C3: 46038 | D3: 46051 | E3: 26.1 - Sprint 2 | F3: Hemanath Jayaraman | G3: 51469 | H3: MFOH - Modify the 'Meal Report' to meet Mosaic Standard | I3: Story Completed | J3: 1 | K3: =Table245689102121314111617111819202115222324252627282930[[#This Row],[Actual Worklog (Hours)]] / 4 -> 3 | L3: 12 | M3: 46038 | N3: 46051 | O3: Hemanath | P3: Sabir | Q3: None | R3: Sabir | S3: None | T3: 46737 | U3: 46042 | V3: 46042 | W3: Subha | X3: None | Y3: Steve | Z3: 46042 | AA3: None | AB3: None | AC3: None | AD3: This is a testing only story. Testing started from 23rd Jan and found some observations. Afterweekend and few days of planned PTO this story has been tested and closed on 29th Jan as per the plan | AE3: Meets Expectation
A4: 3 | B4: ='Dashboard-2025'!$K$1 -> FOH Wave | C4: 46038 | D4: 46051 | E4: 26.1 - Sprint 2 | F4: Sabir Shaikh | G4: 51470 | H4: MFOH [WAVE] - Modify the 'User Report' to meet Mosaic Standard | I4: Story Completed | J4: 1 | K4: =Table245689102121314111617111819202115222324252627282930[[#This Row],[Actual Worklog (Hours)]] / 4 -> 1 | L4: 4 | M4: 46038 | N4: 46038 | O4: Sabir | P4: Vidhya | Q4: None | R4: Vidhya | S4: None | T4: 46739 | U4: 46042 | V4: 46042 | W4: Subha | X4: None | Y4: Steve | Z4: 46042 | AA4: None | AB4: None | AC4: None | AD4: None | AE4: Meets Expectation
A5: 4 | B5: ='Dashboard-2025'!$K$1 -> FOH Wave | C5: 46038 | D5: 46051 | E5: 26.1 - Sprint 2 | F5: Vidhya | G5: 51458 | H5: Change common table with category for Serving Period, Menu products, Void Reason, Medical alert (Default Language) | I5: Story Completed | J5: 1 | K5: =Table245689102121314111617111819202115222324252627282930[[#This Row],[Actual Worklog (Hours)]] / 4 -> 1.75 | L5: 7 | M5: 46038 | N5: 46043 | O5: Vidhya | P5: Hemanath | Q5: None | R5: Hemanath | S5: None | T5: 46741 | U5: 46042 | V5: 46042 | W5: Subha | X5: None | Y5: Steve | Z5: 46042 | AA5: None | AB5: None | AC5: NA | AD5: None | AE5: Meets Expectation
A6: 5 | B6: FOH Wave | C6: 46038 | D6: 46051 | E6: 26.1 - Sprint 2 | F6: Subbulakshmi / Hemanath / Sabir / Vidhya | G6: 51125 | H6: [WAVE] Mosaic FOH - Knowledge Transfer from Mosaic BOH Team | I6: Story Completed | J6: 13 | K6: =Table245689102121314111617111819202115222324252627282930[[#This Row],[Actual Worklog (Hours)]] / 4 -> 41.125 | L6: 164.5 | M6: 46036 | N6: 46051 | O6: NA | P6: NA | Q6: NA | R6: NA | S6: NA | T6: NA | U6: NA | V6: NA | W6: NA | X6: NA | Y6: NA | Z6: NA | AA6: NA | AB6: NA | AC6: NA | AD6: NA | AE6: NA

Sheet 26.1 - Sprint 2-Defect
A1: S.No | B1: Sprint # | C1: Story/Defect ID | D1: Parent Story | E1: Developer | F1: Issue Type | G1: Issue Description | H1: Priority | I1: Defect Source | J1: Type | K1: Status | L1: Dev Start Date | M1: Dev End Date | N1: Root Cause Category | O1: Comments
B2: 26.1 - Sprint 2 | C2: 51469 | D2: 51469 | E2: Hemanath | F2: Bounceback/Sub-Defect | G2: 1. The serving period header in the first page has lot of empty spaces above and below the header 2. The next serving period header has no space after the 1st serving period grid | H2: Minor | I2: Manual | J2: Internal | K2: Defect Fixed | L2: 46049 | M2: 46049 | N2: Design Issue | O2: Pre existing one which was there originally. PO wanted to fix it as part of this story hence it was fixed.

Sheet 26.1 - Sprint 1-Status
A1: S.No | B1: Application Name | C1: Sprint Start Date | D1: Sprint End Date | E1: Sprint | F1: Developer/Tester | G1: Story ID/Defect ID | H1: Description | I1: Status | J1: Estimated(hrs/sp) | K1: Actual(hrs/sp) | L1: Actual Worklog (Hours) | M1: Dev Start Date | N1: Dev End Date | O1: Unit testing | P1: Peer Tested By | Q1: Peer Tested Comments, if any | R1: Peer Reviewed By | S1: Peer Code Review Comments, if any | T1: PR Number/Link | U1: PR Created Date | V1: PR Approved Date | W1: Onsite Lead Code Review | X1: Code Review Comments, if any | Y1: Client Code Review | Z1: Approved Date | AA1: Code Review Comments, if any2 | AB1: Internal PO -POV Comments | AC1: Client PO -POV Comments | AD1: Comments | AE1: Does this story meet expectations?
A2: 1 | B2: ='Dashboard-2025'!$K$1 -> FOH Wave | C2: 46010 | D2: 46037 | E2: 26.1 - Sprint 1 | F2: Hemanath Jayaraman | G2: 51249 | H2: [WAVE] Mosaic FOH - Add "App Switcher" to Feature Flag | I2: Story Completed | J2: 1 | K2: =Table2456891021213141116171118192021152223242526272829[[#This Row],[Actual Worklog (Hours)]] / 4 -> 1 | L2: 4 | M2: 46009 | N2: 46009 | O2: Hemanath | P2: Vidhya | Q2: None | R2: Vidhya | S2: None | T2: 46319 | U2: 46010 | V2: 46010 | W2: Subha | X2: None | Y2: Ying | Z2: 46010 | AA2: None | AB2: None | AC2: None | AD2: None | AE2: Meets Expectation
A3: 2 | B3: ='Dashboard-2025'!$K$1 -> FOH Wave | C3: 46010 | D3: 46037 | E3: 26.1 - Sprint 1 | F3: Hemanath Jayaraman | G3: 51110 | H3: MFOH [WAVE] - Add 'Default Language' to the User Maintenance screen | I3: Story Completed | J3: 3 | K3: =Table2456891021213141116171118192021152223242526272829[[#This Row],[Actual Worklog (Hours)]] / 4 -> 2.5 | L3: 10 | M3: 46010 | N3: 46013 | O3: Hemanath | P3: Vidhya | Q3: None | R3: Vidhya | S3: None | T3: 46445 | U3: 46028 | V3: 46028 | W3: Subha | X3: We don't need to add extended property for the foreign key, which is needed for new columns or altered columns in the script. Remove that in the script. | Y3: Steve | Z3: 46028 | AA3: None | AB3: None | AC3: None | AD3: None | AE3: Meets Expectation
A4: 3 | B4: ='Dashboard-2025'!$K$1 -> FOH Wave | C4: 46010 | D4: 46037 | E4: 26.1 - Sprint 1 | F4: Vidhya | G4: 50856 | H4: MFOH [WAVE] - Add a new template 'Extended Sales Report' to Custom > Report Templates | I4: Story Completed | J4: 1 | K4: =Table2456891021213141116171118192021152223242526272829[[#This Row],[Actual Worklog (Hours)]] / 4 -> 0.5 | L4: 2 | M4: 46010 | N4: 46010 | O4: Vidhya | P4: Hemanath | Q4: None | R4: Hemanath | S4: None | T4: 46316 | U4: 46010 | V4: 46010 | W4: Subha | X4: None | Y4: Ying | Z4: 46010 | AA4: None | AB4: None | AC4: None | AD4: None | AE4: Meets Expectation
A5: 4 | B5: FOH Wave | C5: 46010 | D5: 46037 | E5: 26.1 - Sprint 1 | F5: Vidhya | G5: 48154 | H5: MFOH [WAVE] - Add a Language tab to POS Menu Products | I5: Story Completed | J5: 5 | K5: =Table2456891021213141116171118192021152223242526272829[[#This Row],[Actual Worklog (Hours)]] / 4 -> 6 | L5: 24 | M5: 46013 | N5: 46017 | O5: Vidhya | P5: Hemanath | Q5: None | R5: Hemanath | S5: None | T5: 46484 | U5: 46029 | V5: 46029 | W5: Subha | X5: 1. Add 1_ and 2_ or the scripts in the order of execution | Y5: Steve | Z5: 46029 | AA5: None | AB5: POV Date: 12/26/2025 Pov Comment 1: The POS Display Name field (textbox) inside the add language pop up allows to save the language record only with blank spaces. POV Comment 2: During edit of a menu product, the language tab goes to the second line POV Comment 3: In the Add Language popup, there is a mismatch between the width of the Language and POS Display Name fields. | AC5: NA | AD5: None | AE5: Meets Expectation
A6: 5 | B6: FOH Wave | C6: 46010 | D6: 46037 | E6: 26.1 - Sprint 1 | F6: Subbulakshmi | G6: 50857 | H6: MFOH [WAVE] - Add a new template 'Revenue Report' to Custom > Report Templates | I6: Story Completed | J6: 1 | K6: =Table2456891021213141116171118192021152223242526272829[[#This Row],[Actual Worklog (Hours)]] / 4 -> 1 | L6: 4 | M6: NA | N6: NA | O6: NA | P6: NA | Q6: NA | R6: NA | S6: None | T6: NA | U6: NA | V6: NA | W6: NA | X6: NA | Y6: NA | Z6: NA | AA6: NA | AB6: None | AC6: NA | AD6: None | AE6: Meets Expectation
A7: 6 | B7: FOH Wave | C7: 46010 | D7: 46037 | E7: 26.1 - Sprint 1 | F7: Sabir Shaikh | G7: 51323 | H7: MFOH [WAVE] - Add a Language tab to Void Reasons | I7: Story Completed | J7: 5 | K7: =Table2456891021213141116171118192021152223242526272829[[#This Row],[Actual Worklog (Hours)]] / 4 -> 4 | L7: 16 | M7: 46020 | N7: 46028 | O7: Sabir | P7: Vidhya | Q7: None | R7: Vidhya | S7: None | T7: 46627 | U7: 46035 | V7: 46035 | W7: Subhasri | X7: 1.In this story, Mosaic.Web.csproj this file doesn't have any changes. If no changes required then remove this file. | Y7: Steve | Z7: 46035 | AA7: Remove instance of VoidReasonLanguage List in VoidReasonsWCF.cs | AB7: POV Date: 01/06/2026 POV Comment 1: There was an error message that shows up during the save of a void reason record (after sorting the column headers in the language tab and try clicking save). | AC7: NA | AD7: NA | AE7: Meets Expectation
A8: 7 | B8: ='Dashboard-2025'!$K$1 -> FOH Wave | C8: 46010 | D8: 46037 | E8: 26.1 - Sprint 1 | F8: Sabir Shaikh | G8: 51321 | H8: MFOH [WAVE] - Add a Language tab to Medical Alerts | I8: Story Completed | J8: 3 | K8: 2 | L8: 8 | M8: 46029 | N8: 46030 | O8: Sabir | P8: Vidhya | Q8: None | R8: Vidhya | S8: None | T8: 46594 | U8: 46034 | V8: 46034 | W8: Subhasri | X8: None | Y8: Steve | Z8: 46034 | AA8: None | AB8: None | AC8: NA | AE8: Meets Expectation
A9: 8 | B9: FOH Wave | C9: 46010 | D9: 46037 | E9: 26.1 - Sprint 1 | F9: Subbulakshmi | G9: 51077 | H9: MFOH [WAVE] - Add 'Default Language' to Feature Flag | I9: Story Completed | J9: 1 | K9: =Table2456891021213141116171118192021152223242526272829[[#This Row],[Actual Worklog (Hours)]] / 4 -> 1 | L9: 4 | M9: NA | N9: NA | O9: NA | P9: NA | Q9: NA | R9: NA | S9: None | T9: NA | U9: NA | V9: NA | W9: NA | X9: NA | Y9: NA | Z9: NA | AA9: NA | AB9: None | AC9: NA | AD9: None | AE9: Meets Expectation
A10: 9 | B10: ='Dashboard-2025'!$K$1 -> FOH Wave | C10: 46010 | D10: 46037 | E10: 26.1 - Sprint 1 | F10: Vidhya | G10: 48514 | H10: MFOH [WAVE] - Add a Language tab to Serving Period | I10: Story Completed | J10: 3 | K10: =Table2456891021213141116171118192021152223242526272829[[#This Row],[Actual Worklog (Hours)]] / 4 -> 4.25 | L10: 17 | M10: 46024 | N10: 46027 | O10: Vidhya | P10: Sabir | Q10: None | R10: Sabir | S10: None | T10: 46480 | U10: 46029 | V10: 46029 | W10: Subha | X10: 1. Add 1_ and 2_ or the scripts in the order of execution 2. DB length is 50, but why is it restricted to 15 in the UI 3. Wrong date format | Y10: Steve | Z10: 46029 | AA10: None | AB10: POV Date: 01/05/2026 POV Comment 1: The font size of the values between the Language droplist and POS Display Name is mismatching. | AC10: NA | AD10: None | AE10: Meets Expectation
A11: 10 | B11: ='Dashboard-2025'!$K$1 -> FOH Wave | C11: 46010 | D11: 46037 | E11: 26.1 - Sprint 1 | F11: Vidhya | G11: 51322 | H11: MFOH [WAVE] - Add a Language tab to POS Menu | I11: Story Completed | J11: 3 | K11: =Table2456891021213141116171118192021152223242526272829[[#This Row],[Actual Worklog (Hours)]] / 4 -> 3.75 | L11: 15 | M11: 46028 | N11: 46029 | O11: Vidhya | P11: Ashwin | Q11: Getting exception when click OK for the existing languages | R11: Sabir | S11: None | T11: 46562 | U11: 46031 | V11: 46031 | W11: Subha | X11: It doesn’t have any changes, so remove this file. | Y11: Steve | Z11: 46031 | AA11: it's checking for if exits for name POSMenuLanguage, but it creates the table with name ServingLineMenuLanguage. So if you re-run the script it throws an error. | AB11: POV Date: 01/07/2026 POV Comment 1: There was an error message that shows up during the save of a POS Menu r record (after sorting the column headers in the language tab and try clicking save). | AC11: NA | AD11: None | AE11: Meets Expectation
B12: ='Dashboard-2025'!$K$1 -> FOH Wave | C12: 46010 | D12: 46037 | E12: 26.1 - Sprint 1 | F12: Vidhya | G12: 51156 | H12: MFOH [WAVE] - Add a new System Setting 'Default Language' | I12: Story Completed | J12: 1 | K12: =Table2456891021213141116171118192021152223242526272829[[#This Row],[Actual Worklog (Hours)]] / 4 -> 0.5 | L12: 2 | M12: 46031 | N12: 46031 | O12: Vidhya | P12: Sabir | Q12: None | R12: Sabir | S12: None | T12: 46563 | U12: 46031 | V12: 46031 | W12: Subha | X12: None | Y12: Steve | Z12: 46031 | AA12: None | AB12: None | AC12: NA | AD12: None | AE12: Meets Expectation
A13: 11 | B13: FOH Wave | C13: 46010 | D13: 46037 | E13: 26.1 - Sprint 1 Stretch | F13: Hemanath Jayaraman | G13: 50645 | H13: [WAVE] Mosaic FOH(CPS C0224) - Meal Count Entry Audit Report | I13: Story Completed | J13: 13 | K13: =Table2456891021213141116171118192021152223242526272829[[#This Row],[Actual Worklog (Hours)]] / 4 -> 18.5 | L13: 74 | M13: 46014 | N13: 46035 | O13: Hemanath | P13: Arvinth | Q13: 1. If the selected month is current month or future month the data should not show for the future dates. 2.If a date has only non reimbursable meal count, that date should display in the report. 3. If a date has only ala carte or dept. count, that date should display in the report. | R13: Arvinth | S13: In the SPROC , 1.This condition is not required as the future year will not list down in the year dropdown. 2. We don’t need separate query for both NR meal and Alacarte/Dept 3. Add all the school name in actual query, instead of updating it separately. | T13: 46628 | U13: 46035 | V13: 46035 | W13: Subha | X13: 1. A New method is added only for sorting the result set. This can be handled in the .cshtml file 2.Give a clear view of naming conventions for the script files as follows: InsertMealCountEntryAuditReport to Insert_MealCountEntryAudit_Report 3.[dbo].POSTransaction table is used in if NOT exists conditions, which is not recommended, as this will cause performance or screen freeze issues if it is a large district like CPS. Use any alternate way. 4.As discussed already in the catch-up call to use close day summary tables, I don’t see any summary table for the condition 5.I don’t see any query for a serving date that is closed and had 0 meal counts. | Y13: Steve | Z13: 46035 | AA13: None | AB13: POV Date: 01/09/2026 POV Comment 1: After performing a close day for a transaction (dated 1/9/26 and Breakfast Serving Period) done through Serving In the Classroom for a school, the report shows that particular school, that serving date, and that serving period in the report POV Comment 2: When the report is run for a school, the school is not showing in the display parameter section Once the above 2 gets fixed, please proceed to peer testing, code review, and PR. Its a basic standard that we follow for the mosaic reports and it will not be mentioned in the AC. | AC13: NA | AD13: None | AE13: Meets Expectation
A14: 12 | B14: FOH Wave | C14: 46010 | D14: 46037 | E14: 26.1 - Sprint 1 Stretch | F14: Subbulakshmi | G14: 51353 | H14: MFOH [WAVE] - Automation (50851) | I14: Story Completed | J14: 1 | K14: =Table2456891021213141116171118192021152223242526272829[[#This Row],[Actual Worklog (Hours)]] / 4 -> 1 | L14: 4 | M14: 46017 | N14: 46028 | O14: None | P14: NA | Q14: NA | R14: NA | S14: None | T14: 46448 | U14: 46028 | V14: 46028 | W14: Subha | X14: None | Y14: Steve | Z14: 46028 | AA14: None | AB14: NA | AC14: NA | AD14: None | AE14: Meets Expectation
A15: 13 | B15: FOH Wave | C15: 46010 | D15: 46037 | E15: 26.1 - Sprint 1 Stretch | F15: Subbulakshmi | G15: 51355 | H15: MFOH [WAVE] - Automation (50854) | I15: Story Completed | J15: 1 | K15: =Table2456891021213141116171118192021152223242526272829[[#This Row],[Actual Worklog (Hours)]] / 4 -> 1 | L15: 4 | M15: 46017 | N15: 46028 | O15: None | P15: NA | Q15: NA | R15: NA | S15: None | T15: 46449 | U15: 46028 | V15: 46028 | W15: Subha | X15: None | Y15: Steve | Z15: 46028 | AA15: None | AB15: NA | AC15: NA | AD15: None | AE15: Meets Expectation
A16: 14 | B16: FOH Wave | C16: 46010 | D16: 46037 | E16: 26.1 - Sprint 1 Stretch | F16: Subbulakshmi | G16: 51354 | H16: MFOH [WAVE] - Automation (50853) | I16: Story Completed | J16: 1 | K16: =Table2456891021213141116171118192021152223242526272829[[#This Row],[Actual Worklog (Hours)]] / 4 -> 1 | L16: 4 | M16: 46020 | N16: 46028 | O16: None | P16: NA | Q16: NA | R16: NA | S16: None | T16: 46452 | U16: 46028 | V16: 46028 | W16: Subha | X16: None | Y16: Steve | Z16: 46028 | AA16: None | AB16: NA | AC16: NA | AD16: None | AE16: Meets Expectation
A17: 15 | B17: FOH Wave | C17: 46010 | D17: 46037 | E17: 26.1 - Sprint 1 Stretch | F17: Subbulakshmi | G17: 51356 | H17: MFOH [WAVE] - Automation (49952) | I17: Story Completed | J17: 2 | K17: =Table2456891021213141116171118192021152223242526272829[[#This Row],[Actual Worklog (Hours)]] / 4 -> 2 | L17: 8 | M17: 46020 | N17: 46028 | O17: None | P17: NA | Q17: NA | R17: NA | S17: None | T17: 46451 | U17: 46028 | V17: 46028 | W17: Subha | X17: Suggested to add the Dashboard Testcases in Regression Test folder | Y17: Steve | Z17: 46028 | AA17: None | AB17: NA | AC17: NA | AD17: None | AE17: Meets Expectation
A18: 16 | B18: FOH Wave | C18: 46010 | D18: 46037 | E18: 26.1 - Sprint 1 Stretch | F18: Subbulakshmi | G18: 51358 | H18: MFOH [WAVE] - Automation (50441) | I18: Story Being Developed | J18: 3 | K18: 4 | L18: 16 | M18: 46024 | N18: None | O18: None | P18: None | Q18: None | R18: None | S18: None | T18: None | U18: None | V18: None | W18: None | X18: Suggested to use string.empty instead of "" | Y18: None | Z18: None | AA18: None | AB18: None | AC18: None | AD18: None | AE18: None
A19: 17 | B19: ='Dashboard-2025'!$K$1 -> FOH Wave | C19: 46010 | D19: 46037 | E19: 26.1 - Sprint 1 Stretch | F19: Hemanath Jayaraman | G19: 51469 | H19: MFOH - Modify the 'Meal Report' to meet Mosaic Standard | I19: Story Being Developed | J19: 3 | K19: =Table2456891021213141116171118192021152223242526272829[[#This Row],[Actual Worklog (Hours)]] / 4 -> 2 | L19: 8 | M19: 46034 | AE19: Meets Expectation
A20: 18 | B20: ='Dashboard-2025'!$K$1 -> FOH Wave | C20: 46010 | D20: 46037 | E20: 26.1 - Sprint 1 Stretch | F20: Sabir Shaikh | G20: 51470 | H20: MFOH [WAVE] - Modify the 'User Report' to meet Mosaic Standard | I20: Story Being Developed | J20: 3 | K20: 2 | L20: 8 | M20: 46034 | N20: 46035
A21: 19 | B21: ='Dashboard-2025'!$K$1 -> FOH Wave | C21: 46010 | D21: 46037 | E21: 26.1 - Sprint 1 Stretch | F21: Vidhya | G21: 51458 | H21: Change common table with category for Serving Period, Menu products, Void Reason, Medical alert (Default Language) | I21: Story Being Developed | J21: 3 | K21: =Table2456891021213141116171118192021152223242526272829[[#This Row],[Actual Worklog (Hours)]] / 4 -> 1.5 | L21: 6 | M21: 46035

Sheet 26.1 - Sprint 1-Defect
A1: S.No | B1: Sprint # | C1: Story/Defect ID | D1: Parent Story | E1: Developer | F1: Issue Type | G1: Issue Description | H1: Priority | I1: Defect Source | J1: Type | K1: Status | L1: Dev Start Date | M1: Dev End Date | N1: Root Cause Category | O1: Comments
B2: 26.1 - Sprint 1 | C2: 48514 | D2: 48514 | E2: Vidhya | F2: Bounceback/Sub-Defect | G2: MFOH [WAVE] - Add a Language tab to Serving Period Getting on Error popup while I'm entered the POS Display name more than 20 Characters in Language tab Reproduction Steps: 1. Go to Setup> Initial Setup> Serving Period Search> Serving Period Maintenance 2. Go to Language tab 3. Click on Add Language and Select the Language from dropdown 4. Enter the POS Display Name more than 20 characters 5. Click on Save 6. Observe the Exception error | H2: Minor | I2: Manual | J2: Internal | K2: Story Completed | L2: 46030 | M2: 46031 | N2: Validation is missing | O2: Getting on Error popup while I'm entring the POS Display name more than 20 Characters in Serving Period Language tab
B3: 26.1 - Sprint 1 | C3: 48514 | D3: 48514 | E3: Vidhya | F3: Bounceback/Sub-Defect | G3: MFOH [WAVE] - Add a Language tab to Serving Period Added Languages are not showing in Language tab after updating the Serving Period details when show and Hide the Default Language in Feature Flag Reproduction Steps: 1. Go to Setup> Initial Setup> Serving Period Search> Serving Period Maintenance 2. Go to Language tab 3. Click on Add Language and Select the Language from dropdown and Enter the POS Display Name 4. Click on Save 5. Login with Level 1 Support User(Terri) 6. Go to Setup> Initial Setup> District Search>District Maintenance>Other tab 7. Delete the Default Language in Feature Flag and Save it 8. Login with Level 2 User(Debbie) 9. Go to Setup> Initial Setup> Serving Period Search> Serving Period Maintenance 10. Update the Serving Period Name and Save it 11. Login with Level 1 Support User(Terri) 12. Go to Setup> Initial Setup> District Search>District Maintenance>Other tab 13. Add the Default Language in Feature Flag and Save it 14. Login with Level 2 User(Debbie) 15. Go to Setup> Initial Setup> Serving Period Search> Serving Period Maintenance 16. Click on updated Serving Period and Go to Language tab 17. Observe that issue(English Language only showing in Language tab) | H3: Minor | I3: Manual | J3: Internal | K3: Story Completed | L3: 46030 | M3: 46031 | N3: Issue with Language tab data when the feature flag is enabled/disabled | O3: Added Languages are not showing in Language tab after updating the Serving Period details when show and Hide the Default Language in Feature Flag
B4: 26.1 - Sprint 1 | C4: 48154 | D4: 48154 | E4: Vidhya | F4: Bounceback/Sub-Defect | G4: MFOH [WAVE] - Add a Language tab to POS Menu Products Gettion on Exception when I choose/Upload/Remove the Menu Product Image and then default language(English) also not showing in Menu Product Language tab Reproduction Steps: 1. Go to Setup> System Settings and Options>Menu Product Search>Menu Product Maintenance 2. Click on Choose and Select Images 3. Go to Language Tab 4. Click on Save 5. Observe that Exception Error | H4: Minor | I4: Manual | J4: Internal | K4: Story Completed | L4: 46031 | M4: 46031 | N4: Issue with Menu product images | O4: Gettion on Exception when I choose/Upload/Remove the Menu Product Image and then default language(English) also not showing in Menu Product Language tab
B5: 26.1 - Sprint 1 | C5: 51323 | D5: 51323 | E5: Sabir | F5: Bounceback/Sub-Defect | G5: MFOH [WAVE] - Add a Language tab to Void Reasons - Getting on Error popup while I'm entered the Void reason Description more than 50 Characters and try to save the added Languages in Language tab Reproduction Steps: 1. Go to Setup> System Settings and Options> Void Reason Search> Void Reason Maintenance 2. Enter the Void Description more than 50 characters 3. Go to Language tab 4. Click on Add Language 5. Select the Language from dropdown 6. Enter the POS Display Name 7. Click on Ok 8. Click on Save 9. Observe this Error popup message | H5: Minor | I5: Manual | J5: Internal | K5: Story Completed | L5: 46035 | M5: 46035 | N5: Validation Missing | O5: MFOH [WAVE] - Add a Language tab to Void Reasons - Getting on Error popup while I'm entered the Void reason Description more than 50 Characters and try to save the added Languages in Language tab

Sheet 4.25 - Sprint 5-Status
A1: S.No | B1: Application Name | C1: Sprint Start Date | D1: Sprint End Date | E1: Sprint | F1: Developer/Tester | G1: Story ID/Defect ID | H1: Description | I1: Status | J1: Estimated(hrs/sp) | K1: Actual(hrs/sp) | L1: Actual Worklog (Hours) | M1: Dev Start Date | N1: Dev End Date | O1: Unit testing | P1: Peer Tested By | Q1: Peer Tested Comments, if any | R1: Peer Reviewed By | S1: Peer Code Review Comments, if any | T1: PR Number/Link | U1: PR Created Date | V1: PR Approved Date | W1: Onsite Lead Code Review | X1: Code Review Comments, if any | Y1: Client Code Review | Z1: Approved Date | AA1: Code Review Comments, if any2 | AB1: Internal PO -POV Comments | AC1: Client PO -POV Comments | AD1: Comments | AE1: Does this story meet expectations?
A2: 1 | B2: FOH Wave | C2: 45982 | D2: 46009 | E2: 4.25 - Sprint 5 | F2: Vidhya | G2: 50850 | H2: MFOH [WAVE] - Add an indication when the filters are applied in the Visual Report | I2: Story Completed | J2: 1 | K2: 1 | L2: 4 | M2: NA | N2: NA | O2: NA | P2: NA | Q2: NA | R2: NA | S2: NA | T2: 45868 | U2: 45982 | V2: 45982 | W2: NA | X2: NA | Y2: Steve | Z2: 45982 | AA2: None | AB2: NA | AC2: NA | AD2: None | AE2: Meets Expectation
A3: 2 | B3: FOH Wave | C3: 45982 | D3: 46009 | E3: 4.25 - Sprint 5 | F3: Sabir | G3: 50851 | H3: MFOH [WAVE] - Add a new Data Source 'Extended Daily Sales Summary Report' to Report Designer | I3: Story Completed | J3: 1 | K3: NA | L3: NA | M3: NA | N3: NA | O3: NA | P3: NA | Q3: NA | R3: NA | S3: NA | T3: 45875 | U3: 45982 | V3: 45982 | W3: NA | X3: NA | Y3: Steve | Z3: 45982 | AA3: None | AB3: NA | AC3: NA | AD3: None | AE3: Meets Expectation
A4: 3 | B4: FOH Wave | C4: 45982 | D4: 46009 | E4: 4.25 - Sprint 5 | F4: Vidhya | G4: 50852 | H4: MFOH [WAVE] - Add a new Data Source 'Extended Sales Report' to Report Designer | I4: Story Completed | J4: 1 | K4: 1 | L4: 4 | M4: NA | N4: NA | O4: NA | P4: NA | Q4: NA | R4: NA | S4: NA | T4: 45867 | U4: 45982 | V4: 45982 | W4: NA | X4: NA | Y4: Steve | Z4: 45982 | AA4: None | AB4: NA | AC4: NA | AD4: None | AE4: Meets Expectation
A5: 4 | B5: FOH Wave | C5: 45982 | D5: 46009 | E5: 4.25 - Sprint 5 | F5: Sabir | G5: 50855 | H5: MFOH [WAVE] - Add a new template 'Extended Daily Sales Summary Report' to Custom > Report Templates | I5: Story Completed | J5: 3 | K5: 2.5 | L5: 10 | M5: 45982 | N5: 45985 | O5: Sabir | P5: Vidhya | Q5: None | R5: Vidhya | S5: None | T5: 45989 | U5: 45992 | V5: 45992 | W5: Subha | X5: rename the script file name | Y5: Ying | Z5: 45992 | AA5: None | AB5: None | AC5: None | AD5: None | AE5: Meets Expectation
A6: 5 | B6: FOH Wave | C6: 45982 | D6: 46009 | E6: 4.25 - Sprint 5 | F6: Hemanath Jayaraman | G6: 50853 | H6: MFOH [WAVE] - Add a new Data Source 'Revenue Report' to Report Designer | I6: Story Completed | J6: 1 | K6: NA | L6: NA | M6: NA | N6: NA | O6: NA | P6: NA | Q6: NA | R6: NA | S6: NA | T6: 45870 | U6: 45982 | V6: 45982 | W6: NA | X6: NA | Y6: Steve | Z6: 45982 | AA6: None | AB6: NA | AC6: NA | AD6: None | AE6: Meets Expectation
A7: 6 | B7: FOH Wave | C7: 45982 | D7: 46009 | E7: 4.25 - Sprint 5 | F7: Subbulakshmi | G7: 50930 | H7: MFOH [WAVE] - Automation (50722) | I7: Story Completed | J7: 1 | K7: 1 | L7: 4 | M7: 45980 | N7: 45982 | O7: Subbulakshmi | P7: NA | Q7: NA | R7: NA | S7: NA | T7: 45879 | U7: 45982 | V7: 45982 | W7: Subha | X7: NA | Y7: Ying | Z7: 45982 | AA7: None | AB7: NA | AC7: NA | AD7: None | AE7: Meets Expectation
A8: 7 | B8: FOH Wave | C8: 45982 | D8: 46009 | E8: 4.25 - Sprint 5 | F8: Vidhya | G8: 50728 | H8: MFOH [WAVE] - Modify the Missing Sales Data Report to include the Sub-Site (CPS C0209) | I8: Story Completed | J8: 1 | K8: 1 | L8: 4 | M8: NA | N8: NA | O8: NA | P8: NA | Q8: NA | R8: NA | S8: NA | T8: 45869 | U8: 45982 | V8: 45982 | W8: NA | X8: NA | Y8: Steve | Z8: 45982 | AA8: None | AB8: NA | AC8: NA | AD8: None | AE8: Meets Expectation
A9: 8 | B9: FOH Wave | C9: 45982 | D9: 46009 | E9: 4.25 - Sprint 5 | F9: Sabir | G9: 50721 | H9: MFOH [WAVE] - Add a new template for Standard Claim to Custom Report | I9: Story Completed | J9: 1 | K9: NA | L9: NA | M9: NA | N9: NA | O9: NA | P9: NA | Q9: NA | R9: NA | S9: NA | T9: 45872 | U9: 45982 | V9: 45982 | W9: NA | X9: NA | Y9: Steve | Z9: 45982 | AA9: None | AB9: NA | AC9: NA | AD9: None | AE9: Meets Expectation
A10: 9 | B10: ='Dashboard-2025'!$K$1 -> FOH Wave | C10: 45982 | D10: 46009 | E10: 4.25 - Sprint 5 | F10: Vidhya / Sabir/Hemanath | G10: 50954 | H10: [WAVE] Mosaic - FOH 4.25(Regression) - Reports - (Excluding Free/Reduced) | I10: Story Completed | J10: 8 | K10: 28 | L10: 112 | M10: 45994 | N10: 46008 | O10: NA | P10: NA | Q10: NA | R10: NA | S10: NA | T10: NA | U10: NA | V10: NA | W10: NA | X10: NA | Y10: NA | Z10: NA | AA10: NA | AB10: NA | AC10: NA | AD10: NA | AE10: Meets Expectation
A11: 10 | B11: ='Dashboard-2025'!$K$1 -> FOH Wave | C11: 45982 | D11: 46009 | E11: 4.25 - Sprint 5 | F11: Vidhya / Hemanath | G11: 50956 | H11: [WAVE]Mosaic - FOH 4.25(Regression) - Setup | I11: Story Completed | J11: 2 | K11: 7 | L11: 31 | M11: 45999 | N11: 46008 | O11: NA | P11: NA | Q11: NA | R11: NA | S11: NA | T11: NA | U11: NA | V11: NA | W11: NA | X11: NA | Y11: NA | Z11: NA | AA11: NA | AB11: NA | AC11: NA | AD11: NA | AE11: NA
A12: 11 | B12: FOH Wave | C12: 45982 | D12: 46009 | E12: 4.25 - Sprint 5 | F12: Sabir | G12: 50955 | H12: [WAVE]Mosaic - FOH 4.25(Regression) - Utilities | I12: Story Completed | J12: 3 | K12: 4.5 | L12: 19 | M12: 45999 | N12: 46009 | O12: Sabir | P12: NA | Q12: NA | R12: NA | S12: NA | T12: NA | U12: NA | V12: NA | W12: NA | X12: NA | Y12: NA | Z12: NA | AA12: NA | AB12: NA | AC12: NA | AD12: NA | AE12: NA
A13: 12 | B13: ='Dashboard-2025'!$K$1 -> FOH Wave | C13: 45982 | D13: 46009 | E13: 4.25 - Sprint 5 | F13: Hemanath Jayaraman | G13: 26441 | H13: MFOH (4.25 Regression) - Credit Card Listing Report order by filter is not working | I13: Defect Fixed | J13: 0 | K13: 0 | L13: 0 | M13: 46001 | N13: 46002 | O13: Hemanath | P13: Vidhya | Q13: None | R13: Vidhya | S13: None | T13: 46189 | U13: 46003 | V13: 46003 | W13: Subha | X13: None | Y13: Ying | Z13: 46003 | AA13: None | AB13: None | AC13: None | AD13: None | AE13: Meets Expectation
A14: 13 | B14: ='Dashboard-2025'!$K$1 -> FOH Wave | C14: 45982 | D14: 46009 | E14: 4.25 - Sprint 5 | F14: Sabir | G14: 26442 | H14: MFOH (4.25 Regression) - Claim month is missing in Standard Claim Report Template | I14: Defect Fixed | J14: 0 | K14: 0 | L14: 0 | M14: 46001 | N14: 46001 | O14: Sabir | P14: Vidhya | Q14: None | R14: Vidhya | S14: None | T14: 46199 | U14: 46003 | V14: 46003 | W14: Subha | X14: None | Y14: Ying | Z14: 46003 | AA14: None | AB14: None | AC14: None | AD14: None | AE14: Meets Expectation
A15: 14 | B15: ='Dashboard-2025'!$K$1 -> FOH Wave | C15: 45982 | D15: 46009 | E15: 4.25 - Sprint 5 | F15: Sabir | G15: 26444 | H15: MFOH (4.25 Regression) - Mosaic Global Search textbox lists the custom sub report names | I15: Defect Fixed | J15: 0 | K15: 0 | L15: 0 | M15: 46002 | N15: 46002 | O15: Sabir | P15: Hemanath | Q15: None | R15: Hemanath | S15: None | T15: 46201 | U15: 46003 | V15: 46003 | W15: Subha | X15: None | Y15: Ying | Z15: 46003 | AA15: None | AB15: None | AC15: None | AD15: None | AE15: Meets Expectation
A16: 15 | B16: ='Dashboard-2025'!$K$1 -> FOH Wave | C16: 45982 | D16: 46009 | E16: 4.25 - Sprint 5 | F16: Vidhya | G16: 26443 | H16: MFOH (4.25 Regression) - User Maintenance Screen has a console error | I16: Defect Fixed | J16: 0 | K16: 0 | L16: 0 | M16: 46002 | N16: 46002 | O16: Vidhya | P16: Sabir | Q16: None | R16: Sabir | S16: None | T16: 46186 | U16: 46003 | V16: 46003 | W16: Subha | X16: None | Y16: Ying | Z16: 46003 | AA16: None | AB16: NA | AC16: NA | AD16: None | AE16: Meets Expectation
A17: 16 | B17: ='Dashboard-2025'!$K$1 -> FOH Wave | C17: 45982 | D17: 46009 | E17: 4.25 - Sprint 5 | F17: Vidhya | G17: 26463 | H17: MFOH (4.25 Regression) - Getting an Exception error while generating the Report using Display Type - Word/Word 2003 in Custom Report Templates | I17: Defect Fixed | J17: 0 | K17: 0 | L17: 0 | M17: 46006 | N17: 46006 | O17: Vidhya | P17: Hemanath | Q17: None | R17: Hemanath | S17: None | T17: 46244 | U17: 46007 | V17: 46007 | W17: Arvinth | X17: None | Y17: Ying | Z17: 46007 | AA17: None | AB17: NA | AC17: NA | AD17: None | AE17: Meets Expectation
A18: 17 | B18: ='Dashboard-2025'!$K$1 -> FOH Wave | C18: 45982 | D18: 46009 | E18: 4.25 - Sprint 5 | F18: Vidhya | G18: 26464 | H18: MFOH (4.25 Regression) - Alachua Skyward Financial Export success popup is not displayed | I18: Defect Fixed | J18: 0 | K18: 0 | L18: 0 | M18: 46006 | N18: 46006 | O18: Vidhya | P18: Hemanath | Q18: None | R18: Hemanath | S18: None | T18: 46241 | U18: 46007 | V18: 46007 | W18: Arvinth | X18: None | Y18: Ying | Z18: 46007 | AA18: None | AB18: NA | AC18: NA | AD18: None | AE18: Meets Expectation
A19: 18 | B19: ='Dashboard-2025'!$K$1 -> FOH Wave | C19: 45982 | D19: 46009 | E19: 4.25 - Sprint 5 Stretch | F19: Hemanath Jayaraman | G19: 51249 | H19: [WAVE] Mosaic FOH - Add "App Switcher" to Feature Flag | I19: Story Being Developed | J19: 1 | K19: 1 | L19: 4 | M19: 46009 | N19: 46009 | O19: Hemanath | P19: NA | Q19: NA | R19: NA | S19: NA | T19: NA | U19: NA | V19: NA | W19: NA | X19: NA | Y19: NA | Z19: NA | AA19: NA | AB19: NA | AC19: NA | AD19: None | AE19: Meets Expectation
A20: 19 | B20: ='Dashboard-2025'!$K$1 -> FOH Wave | C20: 45982 | D20: 46009 | E20: 4.25 - Sprint 5 Stretch | F20: Hemanath Jayaraman | G20: 50857 | H20: MFOH [WAVE] - Add a new template 'Revenue Report' to Custom > Report Templates | I20: Story Being Tested | J20: 8 | K20: 7 | L20: 29 | M20: 45982 | N20: 45992 | O20: Hemanath | P20: Sabir | Q20: None | R20: Sabir | S20: None | T20: 46134 | U20: 46000 | V20: 46000 | W20: Subha | X20: None | Y20: Steve | Z20: 46000 | AA20: None | AB20: None | AC20: None | AD20: None | AE20: Meets Expectation
A21: 20 | B21: FOH Wave | C21: 45982 | D21: 46009 | E21: 4.25 - Sprint 5 Stretch | F21: Vidhya | G21: 50856 | H21: MFOH [WAVE] - Add a new template 'Extended Sales Report' to Custom > Report Templates | I21: Story Being Developed | J21: 13 | K21: 13 | L21: 56 | M21: 45985 | N21: 46009 | O21: Vidhya | P21: NA | Q21: NA | R21: NA | S21: NA | T21: NA | U21: NA | V21: NA | W21: NA | X21: NA | Y21: NA | Z21: NA | AA21: NA | AB21: NA | AC21: NA | AD21: None | AE21: Meets Expectation
A22: 21 | B22: ='Dashboard-2025'!$K$1 -> FOH Wave | C22: 45982 | D22: 46009 | E22: 4.25 - Sprint 5 Stretch | F22: Sabir | G22: 50854 | H22: MFOH [WAVE] - Add a new Data Source 'Total Income Report' to Report Designer | I22: Story Completed | J22: 2 | K22: 1.5 | L22: 6 | M22: 45986 | N22: 45987 | O22: Sabir | P22: Vidhya | Q22: None | R22: Vidhya | S22: None | T22: 46145 | U22: 46001 | V22: 46001 | W22: Subha | X22: None | Y22: Steve | Z22: 46001 | AA22: None | AB22: POV Comment: The name of the datasource is incorrect and doesn't match the name given in the AC | AC22: NA | AD22: None | AE22: Meets Expectation
A23: 22 | B23: ='Dashboard-2025'!$K$1 -> FOH Wave | C23: 45982 | D23: 46009 | E23: 4.25 - Sprint 5 Stretch | F23: Sabir | G23: 50858 | H23: MFOH [WAVE] - Add a new template 'Total Income Report' to Custom > Report Templates | I23: Story Completed | J23: 8 | K23: 7 | L23: 27 | M23: 45987 | N23: 45993 | O23: Sabir | P23: Hemanath | Q23: None | R23: Hemanath | S23: None | T23: 46146 | U23: 46001 | V23: 46001 | W23: Subha | X23: None | Y23: Steve | Z23: 46001 | AA23: None | AB23: None | AC23: None | AD23: None | AE23: Meets Expectation
A24: 25 | B24: ='Dashboard-2025'!$K$1 -> FOH Wave | C24: 45982 | D24: 46009 | E24: 4.25 - Sprint 5 Stretch | F24: Hemanath Jayaraman | G24: 51077 | H24: MFOH [WAVE] - Add 'Default Language' to Feature Flag | I24: Story Ready For Testing | J24: 1 | K24: 1 | L24: 4 | M24: 46008 | N24: 46008 | O24: Hemanath | P24: Vidhya | Q24: None | R24: Vidhya | S24: None | T24: 46277 | U24: 46008 | V24: 46008 | W24: Subha | X24: None | Y24: Ying | Z24: 46008 | AA24: None | AB24: None | AC24: None | AD24: None | AE24: Meets Expectation
A25: 23 | B25: FOH Wave | C25: 45982 | D25: 46009 | E25: 4.25 - Sprint 5 Stretch | F25: Subbulakshmi | G25: 51041 | H25: 51041 MFOH [WAVE] - Automation (50851) | I25: Story Completed | J25: 2 | K25: 2 | L25: 8 | M25: 45989 | N25: 45994 | O25: Subbulakshmi | P25: NA | Q25: NA | R25: NA | S25: NA | T25: 46042 | U25: 45994 | V25: 45994 | W25: Subha | X25: None | Y25: Ying | Z25: 45994 | AA25: None | AB25: NA | AC25: NA | AD25: None | AE25: Meets Expectation
A26: 24 | B26: FOH Wave | C26: 45982 | D26: 46009 | E26: 4.25 - Sprint 5 Stretch | F26: Subbulakshmi | G26: 51042 | H26: 51042 MFOH [WAVE] - Automation (50852) | I26: Story Completed | J26: 2 | K26: 2 | L26: 8 | M26: 45992 | N26: 45994 | O26: Subbulakshmi | P26: NA | Q26: NA | R26: NA | S26: NA | T26: 46042 | U26: 45994 | V26: 45994 | W26: Subha | X26: None | Y26: Ying | Z26: 45994 | AA26: None | AB26: NA | AC26: NA | AD26: None | AE26: Meets Expectation

Sheet 4.25 - Sprint 5-Defect
A1: S.No | B1: Sprint # | C1: Story/Defect ID | D1: Parent Story | E1: Developer | F1: Issue Type | G1: Issue Description | H1: Priority | I1: Defect Source | J1: Type | K1: Status | L1: Dev Start Date | M1: Dev End Date | N1: Root Cause Category | O1: Comments
B2: 4.25 - Sprint 5 | C2: 50721 | D2: 50721 | E2: Sabir | F2: Bounceback/Sub-Defect | G2: Incorrect data is showing in Participation total table in Standart Claim Report (Template) | H2: Major | I2: Manual | J2: Internal | K2: Defect Fixed | L2: 45987 | M2: 45989 | N2: Design | O2: Incorrect data is showing in Participation Total table in Standart Claim Report (Template) while I select the Filter is Participation by Entrollment
B3: 4.25 - Sprint 5 | C3: 26441 | D3: 26441 | E3: Hemanath | F3: Bounceback/Sub-Defect | G3: Getting on Exception while generating the Credit card listing report when the Authorization number is empty | H3: Minor | I3: Manual | J3: Internal | K3: Defect Fixed | L3: 46007 | M3: 46007 | N3: Data Issue | O3: This is the data issue which occurred in other developer's DB. It is handled now.

Sheet 4.25 - Sprint 4-Status
A1: S.No | B1: Application Name | C1: Sprint Start Date | D1: Sprint End Date | E1: Sprint | F1: Developer/Tester | G1: Story ID/Defect ID | H1: Description | I1: Status | J1: Estimated(hrs/sp) | K1: Actual(hrs/sp) | L1: Actual Worklog (Hours) | M1: Dev Start Date | N1: Dev End Date | O1: Unit testing | P1: Peer Tested By | Q1: Peer Tested Comments, if any | R1: Peer Reviewed By | S1: Peer Code Review Comments, if any | T1: PR Number/Link | U1: PR Created Date | V1: PR Approved Date | W1: Onsite Lead Code Review | X1: Code Review Comments, if any | Y1: Client Code Review | Z1: Approved Date | AA1: Code Review Comments, if any2 | AB1: Internal PO -POV Comments | AC1: Client PO -POV Comments | AD1: Comments | AE1: Does this story meet expectations?
A2: 1 | B2: FOH Wave | C2: 45968 | D2: 45981 | E2: 4.25 - Sprint 4 | F2: Vidhya | G2: 50731 | H2: MFOH [WAVE] - Add NSS ID to Visual Report (CPS) | I2: Story Completed | J2: 2 | K2: 1.5 | L2: 6 | M2: 45968 | N2: 45968 | O2: Vidhya | P2: Sabir | Q2: None | R2: Sabir | S2: None | T2: 45692 | U2: 45974 | V2: 45974 | W2: Subha | X2: Change the procedure name properly and check in | Y2: Steve | Z2: 45974 | AA2: None | AB2: None | AC2: NA | AD2: None | AE2: Meets Expectation
A3: 2 | B3: FOH Wave | C3: 45968 | D3: 45981 | E3: 4.25 - Sprint 4 | F3: Sabir | G3: 50722 | H3: MFOH [WAVE] - Add a new Data Source 'Standard Claim' to Report Designer | I3: Story Completed | J3: 3 | K3: 2 | L3: 8 | M3: 45968 | N3: 45972 | O3: sabir | P3: Vidhya | Q3: NA | R3: Vidhya | S3: NA | T3: 45648 | U3: 45972 | V3: 45972 | W3: Subha | X3: None | Y3: NA | Z3: 45972 | AA3: NA | AB3: POV Date: 11/11/25 1. Additional unrelated UI parameters were added to the report UI. | AC3: NA | AD3: NA | AE3: Meets Expectation
A4: 3 | B4: FOH Wave | C4: 45968 | D4: 45981 | E4: 4.25 - Sprint 4 | F4: Sabir | G4: 50441 | H4: MFOH [WAVE] - Import the format of the Custom Report | I4: Story Completed | J4: 1 | K4: 1 | L4: 4 | M4: NA | N4: NA | O4: NA | P4: NA | Q4: NA | R4: NA | S4: NA | T4: 45649 | U4: 45972 | V4: 45972 | W4: Subha | X4: 1.This class doesn’t have a serialize annotation 2.Change the method Name to IsCustomReportNameExists 3.Check the spelling in the method name. Also, change the method name to IsCustomReportNameExists. 4.Change the method name to IsFilePathExists | Y4: NA | Z4: 45972 | AA4: NA | AB4: NA | AC4: NA | AD4: NA | AE4: Meets Expectation
A5: 4 | B5: FOH Wave | C5: 45968 | D5: 45981 | E5: 4.25 - Sprint 4 | F5: Vidhya | G5: 50712 | H5: MFOH [WAVE] - Rename 'Serving Period Program' to Reimbursable Program | I5: Story Completed | J5: 1 | K5: 1 | L5: 4 | M5: NA | N5: NA | O5: NA | P5: NA | Q5: NA | R5: NA | S5: NA | T5: 45556 | U5: 45968 | V5: 45968 | W5: NA | X5: NA | Y5: Steve | Z5: 45968 | AA5: None | AB5: NA | AC5: NA | AD5: None | AE5: Meets Expectation
A6: 5 | B6: FOH Wave | C6: 45968 | D6: 45981 | E6: 4.25 - Sprint 4 | F6: Hemanath Jayaraman | G6: 50749 | H6: MFOH [WAVE] - Add a Scheduler Task Step for the IL WINS Export (CPS C0101) | I6: Story Completed | J6: 3 | K6: 5 | L6: 20 | M6: 45968 | N6: 45975 | O6: Hemanath | P6: Vidhya | Q6: None | R6: Vidhya | S6: None | T6: 45693 | U6: 45974 | V6: 45975 | W6: Subhasri | X6: 1.You don't need any change in the SP - ILWINSExport.sql for adding a scheduler step. Please revert that change and look for an example - Alachua Meal Count Export. 2.Don't hardcode the filename in the scheduler. Use the model value using substring. | Y6: Steve | Z6: 45975 | AA6: I don't think this is the correct way to handle this. The School Group should be a scheduler task parameter. Please reach out to Jagan and Gary about this | AB6: None | AC6: None | AD6: Requirement change lead to deviation in the timeline | AE6: Meets Expectation
A7: 6 | B7: FOH Wave | C7: 45968 | D7: 45981 | E7: 4.25 - Sprint 4 Stretch | F7: Sabir | G7: 50721 | H7: MFOH [WAVE] - Add a new template for Standard Claim to Custom Report | I7: Product Owner - Verify | J7: 5 | K7: 4 | L7: 16 | M7: 45971 | N7: 45978 | O7: Sabir | P7: Vidhya | Q7: 1. The selected school name is not appearing in the report 2. Number Formating is missing 3. Font size not match with for label 'Total Reimbursement Due' | R7: Vidhya | S7: None | T7: NA | U7: NA | V7: NA | W7: Subhasri | X7: 1. You're adding report parameters in the xtrareportrunner. But report parameters lines removed for standardClaimreport if condition. Why this change is required then? | Y7: NA | Z7: NA | AA7: None | AB7: None | AC7: None | AD7: None | AE7: Meets Expectation
A8: 7 | B8: FOH Wave | C8: 45968 | D8: 45981 | E8: 4.25 - Sprint 4 Stretch | F8: Vidhya | G8: 50728 | H8: MFOH [WAVE] - Modify the Missing Sales Data Report to include the Sub-Site (CPS C0209) | I8: Product Owner - Verify | J8: 5 | K8: 4.5 | L8: 18 | M8: 45971 | N8: 45974 | O8: Vidhya | P8: Hemanath | Q8: None | R8: Hemanath | S8: 1. In MissingSalesDataReport.Sql - Please fix the indentation and set quoted identifier like the old one on the left, please refer the screen below 2. In MissingSalesDataReport.cshtml - Is there any specific reason why the first school is loaded in the document ready below | T8: NA | U8: NA | V8: NA | W8: Subha | X8: None | Y8: NA | Z8: NA | AA8: NA | AB8: POV Date: 11/12/25 1. The report doesn't meet the standard format requirements. | AC8: NA | AD8: None | AE8: Meets Expectation
A9: 8 | B9: FOH Wave | C9: 45968 | D9: 45981 | E9: 4.25 - Sprint 4 Stretch | F9: Subbulakshmi | G9: 50553 | H9: MFOH [WAVE] - Automation | I9: Story Completed | J9: 2 | K9: 2 | L9: 8 | M9: 45971 | N9: 45980 | O9: NA | P9: NA | Q9: NA | R9: NA | S9: NA | T9: 45823 | U9: 45980 | V9: 45980 | W9: Subha | X9: None | Y9: Steve | Z9: 45980 | AA9: None | AB9: None | AC9: None | AD9: None | AE9: Meet Expectation
A10: 9 | B10: FOH Wave | C10: 45968 | D10: 45981 | E10: 4.25 - Sprint 4 Stretch | F10: Hemanath Jayaraman | G10: 48356 | H10: [WAVE] Mosaic FOH - Standard Claim Report- Replace master serving period with serving period program | I10: Product Owner - Verify | J10: 5 | K10: 3.75 | L10: 15 | M10: 45974 | N10: 45979 | O10: Hemanath | P10: Sabir | Q10: None | R10: Sabir | S10: None | T10: NA | U10: NA | V10: NA | W10: Subhasri | X10: None | Y10: NA | Z10: NA | AA10: NA | AB10: None | AC10: None | AD10: This will be tested by QA in the feature branch. Its put on hold as there are some queries from Jagan that needs to be discussed with Gary | AE10: Meets Expectation
A11: 10 | B11: FOH Wave | C11: 45968 | D11: 45981 | E11: 4.25 - Sprint 4 Stretch | F11: Vidhya | G11: 50850 | H11: MFOH [WAVE] - Add an indication when the filters are applied in the Visual Report | I11: Product Owner - Verify | J11: 3 | K11: 3 | L11: 12 | M11: 45974 | N11: 45979 | O11: Vidhya | P11: Hemanath | Q11: None | R11: Hemanath | S11: None | T11: NA | U11: NA | V11: NA | W11: Subha | X11: 1. Suggeated to change the method name to isDefaultFiltersSelected 2. Correct the typo for "default" | Y11: NA | Z11: NA | AA11: NA | AB11: None | AC11: NA | AD11: None | AE11: Meets Expectation
A12: 11 | B12: FOH Wave | C12: 45968 | D12: 45981 | E12: 4.25 - Sprint 4 Stretch | F12: Sabir | G12: 50851 | H12: MFOH [WAVE] - Add a new Data Source 'Extended Daily Sales Summary Report' to Report Designer | I12: Product Owner - Verify | J12: 3 | K12: 1.5 | L12: 6 | M12: 45978 | N12: 45979 | O12: Sabir | P12: Hemanath | Q12: None | R12: Hemanath | S12: None | T12: NA | U12: NA | V12: NA | W12: Subha | X12: this should be always [axof:<Space><story ID> ] | Y12: NA | Z12: NA | AA12: NA | AB12: NA | AC12: None | AD12: None | AE12: Meets Expectation
A13: 12 | B13: FOH Wave | C13: 45968 | D13: 45981 | E13: 4.25 - Sprint 4 Stretch | F13: Vidhya | G13: 50852 | H13: MFOH [WAVE] - Add a new Data Source 'Extended Sales Report' to Report Designer | I13: Story Being Developed | J13: 3 | K13: 3 | L13: 12 | M13: 45979 | N13: 45980 | O13: Vidhya | P13: Hemanath | Q13: None | R13: Hemanath | S13: None | T13: NA | U13: NA | V13: NA | W13: Subha | X13: Should be always [axof:<Space><story ID> ] | Y13: NA | Z13: NA | AA13: NA | AB13: None | AC13: NA | AD13: None | AE13: Meets Expectation
A14: 13 | B14: FOH Wave | C14: 45968 | D14: 45981 | E14: 4.25 - Sprint 4 Stretch | F14: Sabir | G14: 50855 | H14: MFOH [WAVE] - Add a new template 'Extended Daily Sales Summary Report' to Custom > Report Templates | I14: Story Being Developed | J14: 5 | K14: 2.5 | L14: 10 | M14: 45979 | N14: NA | O14: NA | P14: NA | Q14: NA | R14: NA | S14: NA | T14: NA | U14: NA | V14: NA | W14: NA | X14: NA | Y14: NA | Z14: NA | AA14: NA | AB14: NA | AC14: NA | AD14: NA | AE14: Meets Expectation
A15: 14 | B15: FOH Wave | C15: 45968 | D15: 45981 | E15: 4.25 - Sprint 4 Stretch | F15: Hemanath Jayaraman | G15: 50853 | H15: MFOH [WAVE] - Add a new Data Source 'Revenue Report' to Report Designer | I15: Product Owner - Verify | J15: 3 | K15: 1.75 | L15: 7 | M15: 45979 | N15: 45980 | O15: Hemanath | P15: Vidhya | Q15: None | R15: Vidhya | S15: None | T15: NA | U15: NA | V15: NA | W15: Subhasri | X15: 1.Change it to display the entire report name as Name in the script. We must always consider the User's point of view. Displaying single word is not consistent in the application. | Y15: NA | Z15: NA | AA15: NA | AB15: None | AC15: None | AD15: None | AE15: Meets Expectation
A16: 15 | B16: FOH Wave | C16: 45968 | D16: 45981 | E16: 4.25 - Sprint 4 Stretch | F16: Subbulakshmi | G16: 50930 | H16: MFOH [WAVE] - Automation (50722) | I16: Story Being Developed | J16: 2 | K16: 1 | L16: 4 | M16: 45980 | N16: NA | O16: NA | P16: NA | Q16: NA | R16: NA | S16: NA | T16: NA | U16: NA | V16: NA | W16: NA | X16: NA | Y16: NA | Z16: NA | AA16: NA | AB16: NA | AC16: NA | AD16: None | AE16: Meet Expectation

Sheet 4.25 - Sprint 4-Defect
A1: S.No | B1: Sprint # | C1: Story/Defect ID | D1: Parent Story | E1: Developer | F1: Issue Type | G1: Issue Description | H1: Priority | I1: Defect Source | J1: Type | K1: Status | L1: Dev Start Date | M1: Dev End Date | N1: Root Cause Category | O1: Comments
B2: 4.25 - Sprint 4 | C2: 50441 | D2: 50441 | E2: Sabir | F2: Bounceback/Sub-Defect | G2: Success Popup is showing in Error Message | H2: Minor | I2: Manual | J2: Internal | K2: Story Ready For Testing | L2: 45979 | M2: 45979 | N2: Design | O2: Success Popup Issue
B3: 4.25 - Sprint 4 | C3: 50731 | D3: 50731 | E3: Vidhya | F3: Bounceback/Sub-Defect | G3: Tool tip is not appears in when NSS Id is exactly equal to 8 characters | H3: Minor | I3: Manual | J3: Internal | K3: Product Owner - Verify | L3: 45972 | M3: 45972 | N3: Design | O3: Tool tip is not appears in when NSS Id is exactly equal to 8 characters

Sheet 4.25 - Sprint 3-Status
A1: S.No | B1: Application Name | C1: Sprint Start Date | D1: Sprint End Date | E1: Sprint | F1: Developer/Tester | G1: Story ID/Defect ID | H1: Description | I1: Status | J1: Estimated(hrs/sp) | K1: Actual(hrs/sp) | L1: Actual Worklog (Hours) | M1: Dev Start Date | N1: Dev End Date | O1: Unit testing | P1: Peer Tested By | Q1: Peer Tested Comments, if any | R1: Peer Reviewed By | S1: Peer Code Review Comments, if any | T1: PR Number/Link | U1: PR Created Date | V1: PR Approved Date | W1: Onsite Lead Code Review | X1: Code Review Comments, if any | Y1: Client Code Review | Z1: Approved Date | AA1: Code Review Comments, if any2 | AB1: Internal PO -POV Comments | AC1: Client PO -POV Comments | AD1: Comments | AE1: Does this story meet expectations?
A2: 1 | B2: FOH Wave | C2: 45954 | D2: 45967 | E2: 4.25 - Sprint 3 | F2: Hemanath Jayaraman | G2: 43944 | H2: MFOH - Modify the 'User Assignments Report' to meet Mosaic Standard | I2: Story Completed | J2: 1 | K2: 1.5 | L2: 6 | M2: 45954 | N2: 45954 | O2: Hemanath | P2: Sabir | Q2: None | R2: Sabir | S2: None | T2: 45293 | U2: 45957 | V2: 45957 | W2: Subha | X2: None | Y2: Steve | Z2: 45957 | AA2: None | AB2: None | AC2: None | AE2: Meets Expectation
A3: 2 | B3: FOH Wave | C3: 45954 | D3: 45967 | E3: 4.25 - Sprint 3 | F3: Hemanath Jayaraman | G3: 48361 | H3: [WAVE] Mosaic FOH - KY CNIPS Export NSLP - Replace master serving period with serving period program | I3: Story Completed | J3: 2 | K3: 2.5 | L3: 10 | M3: 45957 | N3: 45958 | O3: Hemanath | P3: Sabir | Q3: None | R3: Sabir | S3: None | T3: NA | U3: NA | V3: NA | W3: Subha | X3: None | Y3: NA | Z3: NA | AA3: None | AB3: POV Comment: 1. The story was developed incorrectly. 2. The story development didn't meet any of the expectation. | AC3: None | AD3: This will be tested by QA using the feature branch | AE3: Meets Expectation
A4: 3 | B4: FOH Wave | C4: 45954 | D4: 45967 | E4: 4.25 - Sprint 3 | F4: Sabir Shaikh | G4: 48339 | H4: [WAVE] Mosaic FOH - CNPWeb Export - Replace master serving period with serving period program | I4: Story Completed | J4: 3 | K4: 2 | L4: 8 | M4: 45954 | N4: 45957 | O4: Sabir | P4: Vidhya | Q4: None | R4: Vidhya | S4: None | T4: NA | U4: NA | V4: NA | W4: Subha | X4: None | Y4: NA | Z4: NA | AA4: None | AB4: NA | AC4: None | AD4: This will be tested by QA using the feature branch | AE4: Meets Expectation
A5: 4 | B5: FOH Wave | C5: 45954 | D5: 45967 | E5: 4.25 - Sprint 3 | F5: Vidhya | G5: 50500 | H5: MFOH[WAVE]- FOH-Legacy Imports to be moved to Utilities System setup | I5: Story Completed | J5: 3 | K5: 3 | L5: 12 | M5: 45954 | N5: 45957 | O5: Vidhya | P5: Hemanath | Q5: None | R5: Hemanath | S5: None | T5: 45338 | U5: 45958 | V5: 45958 | W5: Subha | X5: None | Y5: Steve | Z5: 45958 | AA5: None | AB5: None | AC5: None | AD5: None | AE5: Meets Expectation
A6: 5 | B6: FOH Wave | C6: 45954 | D6: 45967 | E6: 4.25 - Sprint 3 Stretch | F6: Subbulakshmi | G6: 50553 | H6: MFOH [WAVE] - Automation | I6: Story Being Developed | J6: 2 | K6: None | L6: None | M6: None | N6: None | O6: None | P6: None | Q6: None | R6: None | S6: None | T6: None | U6: None | V6: None | W6: None | X6: None | Y6: None | Z6: None | AA6: None | AB6: None | AC6: None | AD6: None | AE6: None
A7: 6 | B7: FOH Wave | C7: 45954 | D7: 45967 | E7: 4.25 - Sprint 3 | F7: Sabir Shaikh | G7: 48282 | H7: [WAVE] Mosaic FOH - OR Est Reimb Due Report - Replace master serving period with serving period program | I7: Story Completed | J7: 3 | K7: 2 | L7: 8 | M7: 45957 | N7: 45958 | O7: Sabir | P7: Hemanath | Q7: None | R7: Hemanath | S7: None | T7: NA | U7: NA | V7: NA | W7: Subha | X7: None | Y7: NA | Z7: NA | AA7: None | AB7: None | AC7: None | AD7: This will be tested by QA using the feature branch | AE7: Meets Expectation
A8: 7 | B8: FOH Wave | C8: 45954 | D8: 45967 | E8: 4.25 - Sprint 3 Stretch | F8: Vidhya | G8: 50548 | H8: MFOH [WAVE] - Copied widgets have issues when enlarged (Dashboard) | I8: Story Completed | J8: 5 | K8: 6.5 | L8: 26 | M8: 45958 | N8: 45965 | O8: Vidhya | P8: Hemanath | Q8: None | R8: Hemanath | S8: None | T8: 45473 | U8: 45965 | V8: 45965 | W8: Subha | X8: None | Y8: Steve | Z8: 45965 | AA8: None | AB8: POV Comment: 1. Mismatch of data between the Standard claim and the ADP % single value widget. | AC8: None | AD8: None | AE8: Meets Expectation
A9: 8 | B9: FOH Wave | C9: 45954 | D9: 45967 | E9: 4.25 - Sprint 3 Stretch | F9: Hemanath Jayaraman | G9: 50440 | H9: MFOH [WAVE] - Export the format of the 'User Created Custom Reports' | I9: Story Completed | J9: 5 | K9: 6.5 | L9: 26 | M9: 45958 | N9: 45965 | O9: Hemanath | P9: Vidhya | Q9: None | R9: Vidhya | S9: None | T9: 45475 | U9: 45965 | V9: 45965 | W9: Subha | X9: None | Y9: Steve | Z9: 45965 | AA9: None | AB9: None | AC9: None | AD9: None | AE9: Meets Expectation
A10: 9 | B10: FOH Wave | C10: 45954 | D10: 45967 | E10: 4.25 - Sprint 3 Stretch | F10: Sabir Shaikh | G10: 50441 | H10: MFOH [WAVE] - Import the format of the Custom Report | I10: Product Owner - Verify | J10: 5 | K10: 5 | L10: 20 | M10: 45959 | N10: 45965 | O10: Sabir | P10: Vidhya | Q10: check repotname exist condition with space and without space | R10: Vidhya | S10: NA | W10: Subha | X10: NA | AB10: POV Comment: 1. The story didn't meet any of the ACs given for the UI elements. 2. In the second POV, the validation for the xml file (custom report vs some other random files) wasn't set. 3. The import and cancel button arrangement is incorrect
A11: 10 | B11: FOH Wave | C11: 45954 | D11: 45967 | E11: 4.25 - Sprint 3 Stretch | F11: Hemanath Jayaraman | G11: 48360 | H11: [WAVE] Mosaic FOH - Meals Per Labor Hour Report - Replace master serving period with serving period program | I11: Story Need More Info | J11: 3 | K11: 2 | L11: 10 | M11: 45966
A12: 11 | B12: FOH Wave | C12: 45954 | D12: 45967 | E12: 4.25 - Sprint 3 Stretch | F12: Vidhya | G12: 50712 | H12: MFOH [WAVE] - Rename 'Serving Period Program' to Reimbursable Program | I12: Story Being Developed | J12: 2 | K12: 2 | L12: 8 | M12: 45966 | N12: 45967 | O12: Vidhya | P12: Hemanath | Q12: None | R12: Hemanath | S12: None | W12: Subha | X12: None | AB12: None | AC12: None | AD12: None | AE12: Meets Expectation
A13: 12 | B13: FOH Wave | C13: 45954 | D13: 45967 | E13: 4.25 - Sprint 3 Stretch | F13: Sabir Shaikh | G13: 48333 | H13: [WAVE] Mosaic FOH - Kentucky D3 Report - Replace master serving period with serving period program | I13: Story Need More Info | J13: 3 | K13: 1 | L13: 4 | M13: 45966
A14: 13 | B14: FOH Wave | C14: 45954 | D14: 45967 | E14: 4.25 - Sprint 3 Stretch | F14: Sabir Shaikh | G14: 50722 | H14: MFOH [WAVE] - Add a new Data Source 'Standard Claim' to Report Designer | I14: Story Being Developed | J14: 3 | K14: 1 | L14: 4 | M14: 45967
A15: 14 | B15: FOH Wave | C15: 45954 | D15: 45967 | E15: 4.25 - Sprint 3 Stretch | F15: Sabir Shaikh | G15: 48337 | H15: [WAVE] Mosaic FOH - North Carolina SFS4 Export - Replace master serving period with serving period program | I15: Story Completed | J15: 1 | K15: 1 | L15: 4 | M15: 45967 | N15: 45967 | O15: Sabir | P15: Hemanath | Q15: None | R15: Hemanath | S15: None | T15: NA | U15: NA | V15: NA | W15: Subha | X15: None | Y15: NA | Z15: NA | AA15: None | AB15: NA | AC15: NA | AD15: This will be tested by QA using the feature branch | AE15: Meets Expectation

Sheet 4.25 - Sprint 3-Defect
A1: S.No | B1: Sprint # | C1: Story/Defect ID | D1: Parent Story | E1: Developer | F1: Issue Type | G1: Issue Description | H1: Priority | I1: Defect Source | J1: Type | K1: Status | L1: Dev Start Date | M1: Dev End Date | N1: Root Cause Category | O1: Comments

Sheet 4.25 - Sprint 2-Status
A1: S.No | B1: Application Name | C1: Sprint Start Date | D1: Sprint End Date | E1: Sprint | F1: Developer/Tester | G1: Story ID/Defect ID | H1: Description | I1: Status | J1: Estimated(hrs/sp) | K1: Actual(hrs/sp) | L1: Actual Worklog (Hours) | M1: Dev Start Date | N1: Dev End Date | O1: Unit testing | P1: Peer Tested By | Q1: Peer Tested Comments, if any | R1: Peer Reviewed By | S1: Peer Code Review Comments, if any | T1: PR Number/Link | U1: PR Created Date | V1: PR Approved Date | W1: Onsite Lead Code Review | X1: Code Review Comments, if any | Y1: Client Code Review | Z1: Approved Date | AA1: Code Review Comments, if any2 | AB1: Internal PO -POV Comments | AC1: Client PO -POV Comments | AD1: Comments | AE1: Does this story meet expectations?
A2: 1 | B2: FOH Wave | C2: 45940 | D2: 45953 | E2: 4.25 - Sprint 2 | F2: Subbulakshmi | G2: 50315 | H2: MFOH [WAVE] - Add 'Participation By' filter to the Supplemental Programs Claim Report | I2: Story Completed | J2: 1 | K2: 1 | L2: 4 | M2: NA | N2: NA | O2: NA | P2: NA | Q2: NA | R2: NA | S2: NA | T2: NA | U2: NA | V2: NA | W2: NA | X2: NA | Y2: NA | Z2: NA | AA2: NA | AB2: NA | AC2: NA | AD2: NA | AE2: Meets Expectation
A3: 2 | B3: FOH Wave | C3: 45940 | D3: 45953 | E3: 4.25 - Sprint 2 | F3: Subbulakshmi | G3: 50182 | H3: MFOH [WAVE] - Automation (49176) | I3: Story Completed | J3: 2 | K3: 2 | L3: 8 | M3: 45940 | N3: 45952 | O3: Subbulakshmi | P3: NA | Q3: NA | R3: NA | S3: NA | T3: 45242 | U3: 45952 | V3: 45952 | W3: Subha | X3: NA | Y3: NA | Z3: 45952 | AA3: NA | AB3: NA | AC3: NA | AD3: NA | AE3: Meets Expectation
A4: 3 | B4: FOH Wave | C4: 45940 | D4: 45953 | E4: 4.25 - Sprint 2 | F4: Vidhya | G4: 49952 | H4: MFOH [WAVE] - Add a Numerical Widget for MPLH | I4: Story Completed | J4: 3 | K4: 3 | L4: 12 | M4: 45940 | N4: 45943 | O4: Vidhya | P4: Alpha | Q4: NA | R4: Alpha | S4: NA | T4: 45123 | U4: 45944 | V4: 45944 | W4: Subha | X4: NA | Y4: Steve | Z4: 45944 | AA4: NA | AB4: POV Comment: 1. The handling for the exception when the labor hour is 0 was missing and hence throwed an error. | AC4: NA | AD4: NA | AE4: Meets Expectation
A5: 4 | B5: FOH Wave | C5: 45940 | D5: 45953 | E5: 4.25 - Sprint 2 | F5: Subbulakshmi | G5: 48340 | H5: [WAVE] Mosaic FOH - Wisconsin Claim Export - Replace master serving period with serving period program | I5: Story Completed | J5: 1 | K5: 1 | L5: 4 | M5: NA | N5: NA | O5: NA | P5: NA | Q5: NA | R5: NA | S5: NA | T5: NA | U5: NA | V5: NA | W5: NA | X5: NA | Y5: NA | Z5: NA | AA5: NA | AB5: NA | AC5: NA | AD5: NA | AE5: Meets Expectation
A6: 5 | B6: FOH Wave | C6: 45940 | D6: 45953 | E6: 4.25 - Sprint 2 | F6: Vidhya | G6: 49953 | H6: MFOH [WAVE] - Add a Numerical Widget for ADP% | I6: Story Completed | J6: 8 | K6: 9 | L6: 38 | M6: 45944 | N6: 45953 | O6: Vidhya | P6: Hemanath | Q6: ADP values not matching | R6: Hemanath | S6: NA | T6: 45249 | U6: 45952 | V6: 45952 | W6: Subha | X6: NA | Y6: Steve | Z6: 45952 | AA6: NA | AB6: 1. Missing % symbol inside the widget and copied widget. 2. Widget value doesn't match with the standard claim report value for the school group selection. | AC6: NA | AD6: NA | AE6: Meets Expectation
A7: 5 | B7: FOH Wave | C7: 45940 | D7: 45953 | E7: 4.25 - Sprint 2 Stretch | F7: Sabir Shaikh | G7: 50406 | H7: MFOH - Modify Custom Student Report to meet Mosaic Standard | I7: Story Completed | J7: 3 | K7: 4 | L7: 16 | M7: 45940 | N7: 45946 | O7: Sabir | P7: Hemanath | Q7: 1.School Name is showing in Page Header 2. Decrease the space of right side of the page | R7: Hemanath | S7: NA | T7: 45195 | U7: 45947 | V7: 45947 | W7: Subha | X7: NA | Y7: NA | Z7: 45947 | AA7: NA | AB7: POV Comment: 1. The color coding was missing for the rows. 2. The vertical and horizontal lines were missing. | AC7: NA | AD7: I have worked and done the changes on two reports. one is for potrait and second is landscape | AE7: Meets Expectation
A8: 6 | B8: FOH Wave | C8: 45940 | D8: 45953 | E8: 4.25 - Sprint 2 Stretch | F8: Hemanath Jayaraman | G8: 50407 | H8: FOH - Modify Student Attendance Import Results Report to meet Mosaic Standard | I8: Story Completed | J8: 3 | K8: 3 | L8: 12 | M8: 45940 | N8: 45945 | O8: Hemanath | P8: Vidhya | Q8: NA | R8: Vidhya | S8: NA | T8: 45144 | U8: 45945 | V8: 45945 | W8: Subha | X8: NA | Y8: Steve | Z8: 45945 | AA8: NA | AB8: POV Comment: 1. The column headers were misplaced and it affected the understanding of the report. | AC8: NA | AD8: NA | AE8: Meets Expectation
A9: 7 | B9: FOH Wave | C9: 45940 | D9: 45953 | E9: 4.25 - Sprint 2 Stretch | F9: Hemanath Jayaraman | G9: 43944 | H9: MFOH - Modify the 'User Assignments Report' to meet Mosaic Standard | I9: Story Being Developed | J9: 3 | K9: 3 | L9: 12 | M9: 45946 | N9: 45952 | O9: Hemanath | P9: Sabir | Q9: If no parameters selected, then display parameters showing with empty borders | R9: Sabir | S9: NA | AB9: NA | AC9: NA | AD9: NA | AE9: Meets Expectation
A10: 8 | B10: FOH Wave | C10: 45940 | D10: 45953 | E10: 4.25 - Sprint 2 Stretch | F10: Sabir Shaikh | G10: 50453 | H10: MFOH - Modify the 'Kershaw Condensed Daily Sales Summary' to meet Mosaic Standard | I10: Story Ready For Testing | J10: 3 | K10: 2 | L10: 8 | M10: 45946 | N10: 45953 | O10: Sabir | P10: Hemanath | Q10: Page Footer Line is missing | R10: Hemanath | S10: NA | T10: 45263 | U10: 45953 | V10: 45953 | W10: Subha | X10: NA | Y10: Steve | Z10: 45953 | AA10: NA | AB10: NA | AC10: NA | AD10: NA | AE10: Meets Expectation
A11: 9 | B11: FOH Wave | C11: 45940 | D11: 45953 | E11: 4.25 - Sprint 2 Stretch | F11: Hemanath Jayaraman | G11: 48361 | H11: [WAVE] Mosaic FOH - KY CNIPS Export NSLP - Replace master serving period with serving period program | I11: Story Being Developed | J11: 3 | K11: 1.25 | L11: 5 | M11: 45952 | AE11: Meets Expectation
A12: 10 | B12: FOH Wave | C12: 45940 | D12: 45953 | E12: 4.25 - Sprint 2 Stretch | F12: Sabir Shaikh | G12: 48337 | H12: [WAVE] Mosaic FOH - North Carolina SFS4 Export - Replace master serving period with serving period program | I12: Story Being Developed | J12: 3 | K12: 2 | L12: 8 | M12: 45951

Sheet 4.25 - Sprint 2-Defect
A1: S.No | B1: Sprint # | C1: Story/Defect ID | D1: Parent Story | E1: Developer | F1: Issue Type | G1: Issue Description | H1: Priority | I1: Defect Source | J1: Type | K1: Status | L1: Dev Start Date | M1: Dev End Date | N1: Root Cause Category | O1: Comments

Sheet 4.25 - Sprint 1-Status
A1: S.No | B1: Application Name | C1: Sprint Start Date | D1: Sprint End Date | E1: Sprint | F1: Developer/Tester | G1: Story ID/Defect ID | H1: Description | I1: Status | J1: Estimated(hrs/sp) | K1: Actual(hrs/sp) | L1: Actual Worklog (Hours) | M1: Dev Start Date | N1: Dev End Date | O1: Unit testing | P1: Peer Tested By | Q1: Peer Tested Comments, if any | R1: Peer Reviewed By | S1: Peer Code Review Comments, if any | T1: PR Number/Link | U1: PR Created Date | V1: PR Approved Date | W1: Onsite Lead Code Review | X1: Code Review Comments, if any | Y1: Client Code Review | Z1: Approved Date | AA1: Code Review Comments, if any2 | AB1: Internal PO -POV Comments | AC1: Client PO -POV Comments | AD1: Comments | AE1: Does this story meet expectations?
A2: 1 | B2: FOH Wave | C2: 45926 | D2: 45939 | E2: 4.25 - Sprint 1 | F2: Hemanath Jayaraman | G2: 49762 | H2: MFOH [WAVE] - Add 'Participation By' filter to the Standard Claim Report | I2: Story Completed | J2: 2 | K2: 2.25 | L2: 9 | M2: 45926 | N2: 45929 | O2: Hemanath | P2: Alpha | Q2: NA | R2: Alpha | S2: NA | T2: 44885 | U2: 45930 | V2: 45930 | W2: Subhasri | X2: 1.This is not needed in DirectorServiceClient.cs. 2. In a few pages, the revision history is still 4.24; change it to 4.25. | Y2: Steve | Z2: 45930 | AA2: NA | AB2: This story was taken for development on 9/3. POV was done twice since the development didn't meet the expected criteria during first time of POV. 2nd POV date was 9/29. Totally 63.5 hours logged in the story for development. | AC2: NA | AD2: Listed the reasons below for delay 1.I faced a technical issue wrt school grouping which took some time to figure and sort it out. 2.I missed to note a piece of stuff in the AC 3.I had to change from one to another approach due to an existing behaviour with RDLC report. 4.I don't have prior experience in RDLC reports too. 5. POV comment to add a parameter in the report is not mentioned in the AC. | AE2: Meets Expectation
A3: 2 | B3: FOH Wave | C3: 45926 | D3: 45939 | E3: 4.25 - Sprint 1 | F3: Sabir Shaikh | G3: 49592 | H3: MFOH [WAVE] - Add a new template 'Daily Sales By Serving Line Report' to Custom > Report Templates | I3: Story Completed | J3: 1 | K3: 1 | L3: 4 | M3: 45926 | N3: 45926 | O3: Sabir | P3: Vidhya | Q3: 1.Page number format not matching with existing report. 2. increase the space between these two fields | R3: Vidhya | S3: Unnecessary empty lines are added. Please remove it | T3: 44873 | U3: 45929 | V3: 45929 | W3: Subhasri | X3: NA | Y3: Steve | Z3: 45929 | AA3: NA | AB3: NA | AC3: NA | AD3: UI Issues in Daily Sales By Serving Line Report(Template) | AE3: Meets Expectation
A4: 3 | B4: FOH Wave | C4: 45926 | D4: 45939 | E4: 4.25 - Sprint 1 | F4: Sabir Shaikh | G4: 49989 | H4: [WAVE] Mosaic FOH- Addition of Serving Period Program to Reimbursement Rate screen | I4: Story Need More Info | J4: 3 | K4: 2 | L4: 8 | M4: 45926 | N4: 45926 | O4: Sabir | P4: Vidhya | Q4: NA | R4: Vidhya | S4: NA | T4: 44911 | U4: 45930 | V4: 45930 | W4: Subhasri | X4: NA | Y4: Steve | Z4: 45930 | AA4: NA | AB4: NA | AC4: NA | AD4: Story AC got changed after moving the story to Ready for Testing. Hold on this story since we are waiting for Gary's reply. | AE4: Meets Expectation
A5: 4 | B5: FOH Wave | C5: 45926 | D5: 45939 | E5: 4.25 - Sprint 1 | F5: Vidhya | G5: 49997 | H5: [WAVE] Mosaic FOH- Site level settings for SFSP Site Type | I5: Story Completed | J5: 3 | K5: 3 | L5: 12 | M5: 45926 | N5: 45929 | O5: Vidhya | P5: Hemanath | Q5: NA | R5: Hemanath | S5: NA | T5: 44872 | U5: 45929 | V5: 45929 | W5: Subhasri | X5: NA | Y5: Steve | Z5: 45929 | AA5: NA | AB5: NA | AC5: NA | AD5: NA | AE5: Meets Expectation
A6: 5 | B6: ='Dashboard-2025'!$K$1 -> FOH Wave | C6: 45926 | D6: 45939 | E6: 4.25 - Sprint 1 | F6: Hemanath Jayaraman | G6: 49992 | H6: [WAVE]- Mosaic FOH- Reimbursable Program field in Serving Period Maintenance | I6: Story Completed | J6: 1 | K6: 1 | L6: 4 | M6: 45926 | N6: 45929 | O6: Hemanath | P6: Sabir | Q6: NA | R6: Sabir | S6: NA | T6: 44899 | U6: 45930 | V6: 45930 | W6: Subhasri | X6: NA | Y6: Steve | Z6: 45930 | AA6: NA | AB6: The story was partially developed. Had suggested comments during POV for changing the label in the serving period search grid since it was missing. Its a simple change but didn't meet the expectation during the POV. | AC6: NA | AD6: NA | AE6: Meets Expectation
A7: 6 | B7: FOH Wave | C7: 45926 | D7: 45939 | E7: 4.25 - Sprint 1 | F7: Vidhya | G7: 50214 | H7: MFOH - Modifications to Rhode Island Claim Export (Operating Days) | I7: Story Completed | J7: 2 | K7: 2 | L7: 8 | M7: 45929 | N7: 45930 | O7: Vidhya | P7: Sabir | Q7: NA | R7: Arvinth | S7: NA | T7: 44945 | U7: 45933 | V7: 45933 | W7: NA | X7: NA | Y7: Steve | Z7: 45933 | AA7: NA | AB7: NA | AC7: NA | AD7: Arvinth did Peer review for this story since subha is on PTO | AE7: Meets Expectation
A8: 7 | B8: FOH Wave | C8: 45926 | D8: 45939 | E8: 4.25 - Sprint 1 | F8: Sabir Shaikh | G8: 50212 | H8: MFOH - Modifications to Colorado Claim Export (Operating Days) | I8: Story Completed | J8: 2 | K8: 2 | L8: 8 | M8: 45929 | N8: 45930 | O8: Sabir | P8: Hemanath | Q8: NA | R8: Hemanath | S8: NA | T8: 44950 | U8: 45933 | V8: 45933 | W8: Subhasri | X8: NA | Y8: Steve | Z8: 45933 | AA8: NA | AB8: POV was seen on Sep 30. The data wasn't entered and was unable to show the POV for the changes. Hence, asked to work on the data and show the pov once again. 2nd POV date Oct 3. | AC8: NA | AD8: NA | AE8: Meets Expectation
A9: 8 | B9: ='Dashboard-2025'!$K$1 -> FOH Wave | C9: 45926 | D9: 45939 | E9: 4.25 - Sprint 1 | F9: Hemanath Jayaraman | G9: 50215 | H9: MFOH - Modifications to Tennessee Claim Export (Operating Days) | I9: Story Completed | J9: 2 | K9: 1.8 | L9: 7.5 | M9: 45930 | N9: 45933 | O9: Hemanath | P9: Vidhya | Q9: NA | R9: Vidhya | S9: NA | T9: 44967 | U9: 45936 | V9: 45936 | W9: Subhasri | X9: NA | Y9: Steve | Z9: 45936 | AA9: NA | AB9: NA | AC9: NA | AD9: NA | AE9: Meets Expectation
A10: 9 | B10: FOH Wave | C10: 45926 | D10: 45939 | E10: 4.25 - Sprint 1 Stretch | F10: Subbulakshmi | G10: 50182 | H10: MFOH [WAVE] - Automation (49176) | I10: Story Being Developed | J10: 3 | K10: 2 | L10: 4 | M10: 45923 | N10: NA | O10: NA | P10: NA | Q10: NA | R10: NA | S10: NA | T10: NA | U10: NA | V10: NA | W10: NA | X10: NA | Y10: NA | Z10: NA | AA10: NA | AB10: NA | AC10: NA | AD10: NA | AE10: NA
A11: 10 | B11: FOH Wave | C11: 45926 | D11: 45939 | E11: 4.25 - Sprint 1 Stretch | F11: Vidhya | G11: 49952 | H11: MFOH [WAVE] - Add a Numerical Widget for MPLH | I11: Story Being Developed | J11: 5 | K11: 5 | L11: 20 | M11: 45933 | O11: NA | P11: NA | Q11: NA | R11: NA | S11: NA | T11: NA | U11: NA | V11: NA | W11: NA | X11: NA | Y11: NA | Z11: NA | AA11: NA | AB11: NA | AC11: NA | AD11: NA | AE11: Meets Expectation
A12: 11 | B12: FOH Wave | C12: 45926 | D12: 45939 | E12: 4.25 - Sprint 1 Stretch | F12: Sabir Shaikh | G12: 48340 | H12: [WAVE] Mosaic FOH - Wisconsin Claim Export - Replace master serving period with serving period program | I12: Story Being Developed | J12: 3 | K12: 3 | L12: 12 | M12: 45933 | N12: 45940 | O12: Sabir | P12: Hemanath | Q12: NA | R12: NA | S12: NA | T12: 45065 | U12: 45940 | V12: 45940 | W12: Subhasri | X12: NA | Y12: Steve | Z12: 45940 | AA12: NA | AB12: NA | AC12: NA | AD12: NA | AE12: Meets Expectation
A13: 12 | B13: FOH Wave | C13: 45926 | D13: 45939 | E13: 4.25 - Sprint 1 Stretch | F13: Hemanath Jayaraman | G13: 50315 | H13: MFOH [WAVE] - Add 'Participation By' filter to the Supplemental Programs Claim Report | I13: Story Being Developed | J13: 5 | K13: 4 | L13: 15.5 | M13: 45936 | N13: 45938 | O13: Hemanath | P13: Sabir | Q13: NA | R13: Sabir | S13: NA | T13: 45064 | U13: 45940 | V13: 45940 | W13: Subhasri | X13: NA | Y13: Steve | Z13: 45940 | AA13: NA | AB13: POV date: 10/9/2025. The display parameter was not in the expected position after multiple discussions before POV and it looks wierd. Asked to fix it. | AC13: NA | AD13: NA | AE13: Meets Expectation

Sheet 4.25 - Sprint 1-Defect
A1: S.No | B1: Sprint # | C1: Story/Defect ID | D1: Parent Story | E1: Developer | F1: Issue Type | G1: Issue Description | H1: Priority | I1: Defect Source | J1: Type | K1: Status | L1: Dev Start Date | M1: Dev End Date | N1: Root Cause Category | O1: Comments
B2: 4.25 - Sprint 1 | C2: 49592 | D2: 49592 | E2: Sabir Shaikh | F2: Bounceback/Sub-Defect | G2: UI Issues in Daily Sales By Serving Line Report(Template) | H2: Minor | I2: Manual | J2: Internal | K2: Story Completed | L2: 45925 | M2: 45926 | N2: Design | O2: UI Issue

Sheet 4.24 - Sprint 4-Status
A1: S.No | B1: Application Name | C1: Sprint Start Date | D1: Sprint End Date | E1: Sprint | F1: Developer/Tester | G1: Story ID/Defect ID | H1: Description | I1: Status | J1: Estimated(hrs/sp) | K1: Actual(hrs/sp) | L1: Actual Worklog (Hours) | M1: Dev Start Date | N1: Dev End Date | O1: Unit testing | P1: Peer Tested By | Q1: Peer Tested Comments, if any | R1: Peer Reviewed By | S1: Peer Code Review Comments, if any | T1: PR Number/Link | U1: PR Created Date | V1: PR Approved Date | W1: Onsite Lead Code Review | X1: Code Review Comments, if any | Y1: Client Code Review | Z1: Approved Date | AA1: Code Review Comments, if any2 | AB1: Internal PO -POV Comments | AC1: Client PO -POV Comments | AD1: Comments | AE1: Does this story meet expectations?
A2: 1 | B2: FOH Wave | C2: 45912 | D2: 45925 | E2: 4.24 - Sprint 4 | F2: Vidhya | G2: 50003 | H2: MFOH [WAVE] - Apply the new improvements to the existing Dashboard Setups | I2: Story Completed | J2: 1 | K2: 1 | L2: 4 | M2: NA | N2: NA | O2: NA | P2: NA | Q2: NA | R2: NA | S2: NA | T2: NA | U2: NA | V2: NA | W2: NA | X2: NA | Y2: NA | Z2: NA | AA2: NA | AB2: NA | AC2: NA | AD2: NA | AE2: Meets Expectation
A3: 2 | B3: FOH Wave | C3: 45912 | D3: 45925 | E3: 4.24 - Sprint 4 | F3: All | G3: 50032 | H3: [WAVE] Mosaic - FOH 4.24(Regression) - Reports - (Excluding Free/Reduced) | I3: Story Completed | J3: 8 | K3: 16 | L3: 65 | M3: 45915 | N3: 45924 | O3: NA | P3: NA | Q3: NA | R3: NA | S3: NA | T3: NA | U3: NA | V3: NA | W3: NA | X3: NA | Y3: NA | Z3: NA | AA3: NA | AB3: NA | AC3: NA | AD3: NA | AE3: Meets Expectation
A4: 3 | B4: FOH Wave | C4: 45912 | D4: 45925 | E4: 4.24 - Sprint 4 | F4: All | G4: 50033 | H4: [WAVE]Mosaic - FOH 4.24(Regression) - Utilities | I4: Story Completed | J4: 3 | K4: 6 | L4: 24 | M4: 45916 | N4: 45924 | O4: NA | P4: NA | Q4: NA | R4: NA | S4: NA | T4: NA | U4: NA | V4: NA | W4: NA | X4: NA | Y4: NA | Z4: NA | AA4: NA | AB4: NA | AC4: NA | AD4: NA | AE4: Meets Expectation
A5: 4 | B5: FOH Wave | C5: 45912 | D5: 45925 | E5: 4.24 - Sprint 4 | F5: All | G5: 50034 | H5: [WAVE]Mosaic - FOH 4.24(Regression) - SetUp | I5: Story Completed | J5: 2 | K5: 10 | L5: 40 | M5: 45918 | N5: 45924 | O5: NA | P5: NA | Q5: NA | R5: NA | S5: NA | T5: NA | U5: NA | V5: NA | W5: NA | X5: NA | Y5: NA | Z5: NA | AA5: NA | AB5: NA | AC5: NA | AD5: NA | AE5: Meets Expectation
A6: 5 | B6: FOH Wave | C6: 45912 | D6: 45925 | E6: 4.24 - Sprint 4 | F6: Vidhya | G6: 25981 | H6: MFOH (WAVE) (4.24 Regression) - Multiple extra pages are getting added when there is no data (Daily Sales Summary) | I6: Defect Rejected | M6: 45922 | N6: 45923 | O6: NA | P6: NA | Q6: NA | R6: NA | S6: NA | T6: NA | U6: NA | V6: NA | W6: NA | X6: NA | Y6: NA | Z6: NA | AA6: NA | AB6: NA | AC6: NA | AD6: NA | AE6: Meets Expectation
A7: 6 | B7: FOH Wave | C7: 45912 | D7: 45925 | E7: 4.24 - Sprint 4 | F7: Sabir | G7: 25999 | H7: MFOH [WAVE] (4.24 Regression) - POS Offline Incident Report-Data is not bounding to report even though store procedure returning data. | I7: Defect Fixed | M7: 45923 | N7: 45923 | O7: Sabir | P7: Vidhya | Q7: NA | R7: Vidhya | S7: NA | T7: 44764 | U7: 45924 | V7: 45924 | W7: Subha | X7: NA | Y7: Ying | Z7: 45924 | AA7: Nil | AB7: NA | AC7: NA | AD7: NA | AE7: Meets Expectation
A8: 7 | B8: FOH Wave | C8: 45912 | D8: 45925 | E8: 4.24 - Sprint 4 | F8: Vidhya | G8: 25983 | H8: MFOH (4.24 Regression) - When editing the price for each eligibility status in the meal price template, got a console error and couldn't change the pr | I8: Defect Fixed | M8: 45924 | N8: 45924 | O8: Vidhya | P8: Sabir | Q8: NA | R8: Sabir | S8: NA | T8: 44759 | U8: 45924 | V8: 45924 | W8: Subha | X8: NA | Y8: Ying | Z8: 45924 | AA8: Nil | AB8: NA | AC8: NA | AD8: NA | AE8: Meets Expectation
A9: 8 | B9: FOH Wave | C9: 45912 | D9: 45925 | E9: 4.24 - Sprint 4 Stretch | F9: Subbulakshmi | G9: 50182 | H9: MFOH [WAVE] - Automation (49176) | I9: Story Being Developed | J9: 5 | K9: 2 | L9: 12 | M9: 45923 | N9: NA | O9: NA | P9: NA | Q9: NA | R9: NA | S9: NA | T9: NA | U9: NA | V9: NA | W9: NA | X9: NA | Y9: NA | Z9: NA | AA9: NA | AB9: NA | AC9: NA | AD9: NA | AE9: Meets Expectation
A10: 9 | B10: FOH Wave | C10: 45912 | D10: 45925 | E10: 4.24 - Sprint 4 Stretch | F10: Hemanath Jayaraman | G10: 49762 | H10: MFOH [WAVE] - Add 'Participation By' filter to the Standard Claim Report | I10: Story Being Developed | J10: 3 | K10: 6.25 | L10: 25 | M10: 45912 | O10: Hemanath | P10: Alpha | Q10: The ADP percentage is not matching with sales overview report for one school alone. | R10: Alpha | AD10: Listed the reasons below for delay 1.I faced a technical issue wrt school grouping which took some time to figure and sort it out. 2.I missed to note a piece of stuff in the AC 3.I had to change from one to another approach due to an existing behaviour with RDLC report. 4.I don't have prior experience in RDLC reports too. | AE10: Meets Expectation
A11: 10 | B11: FOH Wave | C11: 45912 | D11: 45925 | E11: 4.24 - Sprint 4 Stretch | F11: Sabir | G11: 49592 | H11: MFOH [WAVE] - Add a new template 'Daily Sales By Serving Line Report' to Custom > Report Templates | I11: Story Being Developed | J11: 2 | K11: 2 | L11: 6 | M11: 45912 | O11: Sabir | P11: Vidhya | Q11: 1. Could not open the template in Report Designer. 2. Increase the space between 'Taxable Total' and 'Total Tax Collected' | R11: Vidhya | S11: NA | AE11: Meets Expectation
A12: 11 | B12: FOH Wave | C12: 45912 | D12: 45925 | E12: 4.24 - Sprint 4 Stretch | F12: Subbulakshmi | G12: 50002 | H12: MFOH [WAVE] - Automation (49591) | I12: Story Completed | J12: 1 | K12: 1 | L12: 4 | M12: 45911 | N12: 45912 | O12: Subbulakshmi | P12: NA | Q12: NA | R12: NA | S12: NA | T12: 44541 | U12: 45912 | V12: 45912 | W12: Subha | X12: NA | Y12: Steve | Z12: 45912 | AA12: NA | AB12: NA | AC12: NA | AD12: NA | AE12: Meets Expectation

Sheet 4.24 - Sprint 4-Defect
A1: S.No | B1: Sprint # | C1: Story/Defect ID | D1: Parent Story | E1: Developer | F1: Issue Type | G1: Issue Description | H1: Priority | I1: Defect Source | J1: Type | K1: Status | L1: Dev Start Date | M1: Dev End Date | N1: Root Cause Category | O1: Comments

Sheet 4.24 - Sprint 3-Status
A1: S.No | B1: Application Name | C1: Sprint Start Date | D1: Sprint End Date | E1: Sprint | F1: Developer/Tester | G1: Story ID/Defect ID | H1: Description | I1: Status | J1: Estimated(hrs/sp) | K1: Actual(hrs/sp) | L1: Actual Worklog (Hours) | M1: Dev Start Date | N1: Dev End Date | O1: Unit testing | P1: Peer Tested By | Q1: Peer Tested Comments, if any | R1: Peer Reviewed By | S1: Peer Code Review Comments, if any | T1: PR Number/Link | U1: PR Created Date | V1: PR Approved Date | W1: Onsite Lead Code Review | X1: Code Review Comments, if any | Y1: Client Code Review | Z1: Approved Date | AA1: Code Review Comments, if any2 | AB1: Internal PO -POV Comments | AC1: Client PO -POV Comments | AD1: Comments | AE1: Does this story meet expectations?
A2: 1 | B2: FOH Wave | C2: 45898 | D2: 45911 | E2: 4.24 - Sprint 3 | F2: Vidhya | G2: 49801 | H2: MFOH [WAVE] - Fix the alignment issues in the Dashboard | I2: Story Completed | J2: 5 | K2: 8.5 | L2: 35 | M2: 45898 | N2: 45903 | O2: Vidhya | P2: Hemanath Jayaraman | Q2: NA | R2: Hemanath Jayaraman | S2: NA | T2: 44369 | U2: 45904 | V2: 45904 | W2: Subha | X2: NA | Y2: Steve | Z2: 45904 | AA2: NA | AB2: 1. Multiple POVs and given suggestions for fixes during the POV. 2. Missed the serving period wrap changes which was the main reason for adding this story. 3. Alignment issues were there during the initial POVs | AC2: NA | AD2: Exceeded the given time as there were some R&D required for the UI enhancements. Support given for different screen resolutions additionally. Changes has been done and reverted back for admin side reload functionality | AE2: Meets Expectation
A3: 2 | B3: FOH Wave | C3: 45898 | D3: 45911 | E3: 4.24 - Sprint 3 | F3: Sabir | G3: 49591 | H3: MFOH [WAVE] - Add a new Data Source 'Daily Sales By Serving Line Report' to Report Designer | I3: Story Completed | J3: 1 | K3: 1 | L3: 4 | M3: 45898 | N3: 45908 | O3: Sabir | P3: Vidhya | Q3: NA | R3: Vidhya | S3: Version history is missing | T3: 44315 | U3: 45902 | V3: 45902 | W3: Subha | X3: NA | Y3: Steve | Z3: 45902 | AA3: NA | AB3: NA | AC3: NA | AD3: NA | AE3: Meets Expectation
A4: 3 | B4: FOH Wave | C4: 45898 | D4: 45911 | E4: 4.24 - Sprint 3 | F4: Subbulakshmi | G4: 49687 | H4: MFOH [WAVE] - Automation (49465) | I4: Story Completed | J4: 2 | K4: 2 | L4: 8 | M4: 45897 | N4: 45903 | O4: Subbulakshmi | P4: NA | Q4: NA | R4: NA | S4: NA | T4: 44331 | U4: 45903 | V4: 45903 | W4: Subha | X4: NA | Y4: Steve | Z4: 45903 | AA4: NA | AB4: NA | AC4: NA | AD4: NA | AE4: Meets Expectation
A5: 4 | B5: FOH Wave | C5: 45898 | D5: 45911 | E5: 4.24 - Sprint 3 Stretch | F5: Hemanath Jayaraman | G5: 49594 | H5: MFOH [WAVE] - Add a new template 'Daily Sales Summary' to Custom > Report Templates | I5: Story Completed | J5: 8 | K5: 4.5 | L5: 18 | M5: 45898 | N5: 45902 | O5: Hemanath | P5: Sabir | Q5: NA | R5: Sabir | S5: NA | T5: 44325 | U5: 45903 | V5: 45903 | W5: Subha | X5: NA | Y5: Steve | Z5: 45903 | AA5: NA | AB5: NA | AC5: NA | AD5: NA | AE5: Meets Expectation
A6: 5 | B6: FOH Wave | C6: 45898 | D6: 45911 | E6: 4.24 - Sprint 3 Stretch | F6: Sabir | G6: 49592 | H6: MFOH [WAVE] - Add a new template 'Daily Sales By Serving Line Report' to Custom > Report Templates | I6: Story Being Developed | J6: 8 | K6: 8 | L6: 32 | M6: 45901 | AD6: This report involves nested sub-reports where it is very new to implement in the report designer as of now. Taken some time to analyse and implement the same. Since the difficulty level is increased and was facing slight complexity to achieve it. | AE6: Meets Expectation
A7: 6 | B7: FOH Wave | C7: 45898 | D7: 45911 | E7: 4.24 - Sprint 3 Stretch | F7: Vidhya | G7: 49923 | H7: MFOH [WAVE] - Make the new improvements to the Dashboard affect the existing Setups (Analysis) | I7: Story Completed | K7: 3.5 | L7: 15 | M7: 45904 | N7: 45909 | O7: NA | P7: NA | Q7: NA | R7: NA | S7: NA | T7: NA | U7: NA | V7: NA | W7: NA | X7: NA | Y7: NA | Z7: NA | AA7: NA | AB7: NA | AC7: NA | AD7: NA | AE7: Meets Expectation
A8: 7 | B8: FOH Wave | C8: 45898 | D8: 45911 | E8: 4.24 - Sprint 3 Stretch | F8: Hemanath Jayaraman | G8: 49762 | H8: MFOH [WAVE] - Add 'Participation By' filter to the Standard Claim Report | I8: Story Being Developed | J8: 5 | K8: 7.6 | L8: 30.5 | M8: 45903 | O8: Hemanath | AB8: 1. Shown POV exceeding the planned date and after multiple followps 2. Data error and suggested to fix it. | AD8: Reasons for delay : 1.While unit testing found an issue which requires technical clarification from existing dev team waited for them as they were busy. 2.Missed to note a piece of stuff in the acceptance criteria resulted in the code rework. | AE8: Meets Expectation
A9: 8 | B9: FOH Wave | C9: 45898 | D9: 45911 | E9: 4.24 - Sprint 3 Stretch | F9: Subbulakshmi | G9: 50001 | H9: MFOH [WAVE] - Automation (49593) | I9: Story Completed | J9: 2 | K9: 2 | L9: 8 | M9: 45910 | N9: 45911 | O9: Subbulakshmi | P9: NA | Q9: NA | R9: NA | S9: NA | T9: 44519 | U9: 45911 | V9: 45911 | W9: Subha | X9: NA | Y9: Steve | Z9: 45911 | AA9: NA | AB9: NA | AC9: NA | AD9: NA | AE9: Meets Expectation
A10: 9 | B10: FOH Wave | C10: 45898 | D10: 45911 | E10: 4.24 - Sprint 3 Stretch | F10: Vidhya | G10: 50003 | H10: MFOH [WAVE] - Apply the new improvements to the existing Dashboard Setups | I10: Story Being Developed | J10: 3 | K10: 1.5 | L10: 6 | M10: 45910 | N10: 45911 | O10: Vidhya | P10: Alpha | Q10: Getting an exception while copying the widget | AE10: Meets Expectation
A11: 8 | B11: FOH Wave | C11: 45898 | D11: 45911 | E11: 4.24 - Sprint 3 Stretch | F11: Subbulakshmi | G11: 50002 | H11: MFOH [WAVE] - Automation (49591) | I11: Story Being Developed | J11: 2 | K11: 0.75 | L11: 5 | M11: 45911 | N11: NA | O11: NA | P11: NA | Q11: NA | R11: NA | S11: NA | T11: NA | U11: NA | V11: NA | W11: NA | X11: NA | Y11: NA | Z11: NA | AA11: NA | AB11: NA | AC11: NA | AD11: NA | AE11: Meets Expectation

Sheet 4.24 - Sprint 3-Defect
A1: S.No | B1: Sprint # | C1: Story/Defect ID | D1: Parent Story | E1: Developer | F1: Issue Type | G1: Issue Description | H1: Priority | I1: Defect Source | J1: Type | K1: Status | L1: Dev Start Date | M1: Dev End Date | N1: Root Cause Category | O1: Comments
B2: 4.24 - Sprint 3 | C2: 49801 | D2: 49801 | E2: Vidhya | F2: Bounceback/Sub-Defect | G2: Alignment Issue in user's global filter Text | H2: Minor | I2: Manual | J2: Internal | K2: Defect Fixed | L2: 45908 | M2: 45908 | N2: Design | O2: UI Issue

Sheet 4.24 - Sprint 2-Status
A1: S.No | B1: Application Name | C1: Sprint Start Date | D1: Sprint End Date | E1: Sprint | F1: Developer/Tester | G1: Story ID/Defect ID | H1: Description | I1: Status | J1: Estimated(hrs/sp) | K1: Actual(hrs/sp) | L1: Actual Worklog (Hours) | M1: Dev Start Date | N1: Dev End Date | O1: Unit testing | P1: Peer Tested By | Q1: Peer Tested Comments, if any | R1: Peer Reviewed By | S1: Peer Code Review Comments, if any | T1: PR Number/Link | U1: PR Created Date | V1: PR Approved Date | W1: Onsite Lead Code Review | X1: Code Review Comments, if any | Y1: Client Code Review | Z1: Approved Date | AA1: Code Review Comments, if any2 | AB1: Internal PO -POV Comments | AC1: Client PO -POV Comments | AD1: Comments | AE1: Does this story meet expectations?
A2: 1 | B2: FOH Wave | C2: 45884 | D2: 45897 | E2: 4.24 - Sprint 2 | F2: Vidhya | G2: 49176 | H2: MFOH [WAVE] - Duplicating/copying the Dashboard Widgets | I2: Story Completed | J2: 3 | K2: 4.5 | L2: 18 | M2: 45887 | N2: 45894 | O2: Vidhya | P2: Alpha | Q2: NA | R2: Alpha | S2: NA | T2: 44155 | U2: 45894 | V2: 45894 | W2: Subha | X2: NA | Y2: Ying | Z2: 45894 | AA2: NA | AB2: NA | AC2: NA | AD2: Exceeded the given time to copy the widgets filters as well | AE2: Meets Expectation
A3: 2 | B3: FOH Wave | C3: 45884 | D3: 45897 | E3: 4.24 - Sprint 2 | F3: Subbulakshmi | G3: 49465 | H3: MFOH [WAVE] - Add a 'Delete' option to delete the User Created Custom Reports | I3: Story Completed | J3: 2 | K3: 2 | L3: 6 | M3: NA | N3: NA | O3: NA | P3: NA | Q3: NA | R3: NA | S3: NA | T3: NA | U3: NA | V3: NA | W3: NA | X3: NA | Y3: NA | Z3: NA | AA3: NA | AB3: NA | AC3: NA | AD3: NA | AE3: Meets Expectation
A4: 3 | B4: FOH Wave | C4: 45884 | D4: 45897 | E4: 4.24 - Sprint 2 | F4: Subbulakshmi | G4: 48362 | H4: [WAVE] Mosaic FOH - MARS Claim Export - Replace master serving period with serving period program | I4: Story Completed | J4: 1 | K4: 1 | L4: 4 | M4: NA | N4: NA | O4: NA | P4: NA | Q4: NA | R4: NA | S4: NA | T4: NA | U4: NA | V4: NA | W4: NA | X4: NA | Y4: NA | Z4: NA | AA4: NA | AB4: NA | AC4: NA | AD4: NA | AE4: Meets Expectation
A5: 4 | B5: FOH Wave | C5: 45884 | D5: 45897 | E5: 4.24 - Sprint 2 | F5: Sabir Shaikh | G5: 49428 | H5: MFOH [WAVE] - Allow the users to view the Dashboard Widgets in an enlarged version | I5: Story Completed | J5: 3 | K5: 5 | L5: 20 | M5: 45887 | N5: 45897 | O5: Sabir | P5: Arvinth | Q5: NA | R5: Arvinth | S5: NA | T5: 44159 | U5: 45894 | V5: 45894 | W5: Subha | X5: NA | Y5: NA | Z5: 45894 | AA5: NA | AB5: NA | AC5: NA | AD5: Taken some time for UI improvements | AE5: Meets Expectation
A6: 5 | B6: FOH Wave | C6: 45884 | D6: 45897 | E6: 4.24 - Sprint 2 | F6: Hemanath Jayaraman | G6: 49596 | H6: MFOH [WAVE]- Support for Credit Card in Additional Meal Programs (Extended Sales Report) | I6: Story Completed | J6: 1 | K6: 1 | L6: 6 | M6: 45887 | N6: 45888 | O6: Hemanath | P6: Vidhya | Q6: Huge amounts getting wrapped up in next line | R6: Vidhya | S6: NA | T6: 44041 | U6: 45888 | V6: 45890 | W6: Subha | X6: NA | Y6: Ying | Z6: 45890 | AA6: NA | AB6: NA | AC6: NA | AD6: NA | AE6: Meets Expectation
A7: 6 | B7: FOH Wave | C7: 45884 | D7: 45897 | E7: 4.24 - Sprint 2 Stretch | F7: Hemanath Jayaraman | G7: 49593 | H7: MFOH [WAVE] - Add a new Data Source 'Daily Sales Summary Report' to Report Designer | I7: Story Completed | J7: 3 | K7: 3 | L7: 11 | M7: 45889 | N7: 45890 | O7: Hemanath | P7: Vidhya | Q7: NA | R7: Vidhya | S7: NA | T7: 44093 | U7: 45890 | V7: 45890 | W7: Subha | X7: NA | Y7: Ying | Z7: 45890 | AA7: NA | AB7: NA | AC7: NA | AD7: NA | AE7: Meets Expectation
A8: 7 | B8: FOH Wave | C8: 45884 | D8: 45897 | E8: 4.24 - Sprint 2 Stretch | F8: Subbulakshmi | G8: 49687 | H8: MFOH [WAVE] - Automation (49465) | I8: Story Being Developed | J8: 3 | K8: 1 | L8: 8 | M8: 45889 | N8: NA | O8: NA | P8: NA | Q8: NA | R8: NA | S8: NA | T8: NA | U8: NA | V8: NA | W8: NA | X8: NA | Y8: NA | Z8: NA | AA8: NA | AB8: NA | AC8: NA | AD8: NA | AE8: Meets Expectation
A9: 8 | B9: FOH Wave | C9: 45884 | D9: 45897 | E9: 4.24 - Sprint 2 Stretch | F9: Hemanath Jayaraman | G9: 49594 | H9: MFOH [WAVE] - Add a new template 'Daily Sales Summary' to Custom > Report Templates | I9: Story Being Developed | J9: 8 | K9: 3 | L9: 12 | M9: 45891 | AC9: NA | AD9: NA | AE9: Meets Expectation
A10: 9 | B10: FOH Wave | C10: 45884 | D10: 45897 | E10: 4.24 - Sprint 2 Stretch | F10: Vidhya | G10: 49801 | H10: MFOH [WAVE] - Fix the alignment issues in the Dashboard | I10: Story Being Developed | J10: 5 | K10: 3 | L10: 12 | M10: 45895 | AC10: NA | AD10: NA | AE10: Meets Expectation
A11: 10 | B11: FOH Wave | C11: 45884 | D11: 45897 | E11: 4.24 - Sprint 2 Stretch | F11: Sabir Shaikh | G11: 49591 | H11: MFOH [WAVE] - Add a new Data Source 'Daily Sales By Serving Line Report' to Report Designer | I11: Story Being Developed | J11: 3 | K11: 3 | L11: 12 | M11: 45894 | AC11: NA | AD11: NA | AE11: Meets Expectation

Sheet 4.24 - Sprint 2-Defect
A1: S.No | B1: Sprint # | C1: Story/Defect ID | D1: Parent Story | E1: Developer | F1: Issue Type | G1: Issue Description | H1: Priority | I1: Defect Source | J1: Type | K1: Status | L1: Dev Start Date | M1: Dev End Date | N1: Root Cause Category | O1: Comments
B2: 4.24 - Sprint 2 | C2: 49428 | D2: 49428 | E2: Sabir Shaikh | F2: Defect | G2: Try to add more than 8 widget, scroll down and enlarge the last widget, the screen automatically scrolls up. This will be an issue if there are more widgets | H2: Minor | I2: Manual | J2: Internal | K2: Defect Fixed | L2: 45887 | M2: 45887 | N2: Enhancements | O2: Functionality Issue

Sheet 4.24 - Sprint 1-Status
A1: S.No | B1: Application Name | C1: Sprint Start Date | D1: Sprint End Date | E1: Sprint | F1: Developer/Tester | G1: Story ID/Defect ID | H1: Description | I1: Status | J1: Estimated(hrs/sp) | K1: Actual(hrs/sp) | L1: Actual Worklog (Hours) | M1: Dev Start Date | N1: Dev End Date | O1: Unit testing | P1: Peer Tested By | Q1: Peer Tested Comments, if any | R1: Peer Reviewed By | S1: Peer Code Review Comments, if any | T1: PR Number/Link | U1: PR Created Date | V1: PR Approved Date | W1: Onsite Lead Code Review | X1: Code Review Comments, if any | Y1: Client Code Review | Z1: Approved Date | AA1: Code Review Comments, if any2 | AB1: Internal PO -POV Comments | AC1: Client PO -POV Comments | AD1: Comments | AE1: Does this story meet expectations?
A2: 1 | B2: FOH Wave | C2: 45870 | D2: 45883 | E2: 4.24 - Sprint 1 | F2: Subbulakshmi | G2: 48354 | H2: [WAVE] Mosaic FOH - Tennessee Claim Export - Replace master serving period with serving period program | I2: Story Completed | J2: 1 | K2: 1 | L2: 4 | M2: 45870 | N2: 45870 | O2: NA | P2: NA | Q2: NA | R2: NA | S2: NA | T2: NA | U2: NA | V2: NA | W2: NA | X2: NA | Y2: NA | Z2: NA | AA2: NA | AB2: NA | AC2: NA | AD2: Manual Testing | AE2: Meets Expectation
A3: 2 | B3: FOH Wave | C3: 45870 | D3: 45883 | E3: 4.24 - Sprint 1 | F3: Subbulakshmi | G3: 48338 | H3: [WAVE] Mosaic FOH - Rhode Island Claim Export - Replace master serving period with serving period program. | I3: Story Completed | J3: 1 | K3: 1 | L3: 4 | M3: 45873 | N3: 45874 | O3: NA | P3: NA | Q3: NA | R3: NA | S3: NA | T3: NA | U3: NA | V3: NA | W3: NA | X3: NA | Y3: NA | Z3: NA | AA3: NA | AB3: NA | AC3: NA | AD3: Manual Testing | AE3: Meets Expectation
A4: 3 | B4: FOH Wave | C4: 45870 | D4: 45883 | E4: 4.24 - Sprint 1 | F4: Subbulakshmi | G4: 48336 | H4: [WAVE] Mosaic FOH - NorthCarolina Claim Export - Replace master serving period with serving period program | I4: Story Completed | J4: 1 | K4: 1 | L4: 4 | M4: 45870 | N4: 45873 | O4: NA | P4: NA | Q4: NA | R4: NA | S4: NA | T4: NA | U4: NA | V4: NA | W4: NA | X4: NA | Y4: NA | Z4: NA | AA4: NA | AB4: NA | AC4: NA | AD4: Manual Testing | AE4: Meets Expectation
A5: 4 | B5: FOH Wave | C5: 45870 | D5: 45883 | E5: 4.24 - Sprint 1 | F5: Hemanath Jayaraman | G5: 49422 | H5: MFOH [WAVE]- Support for Credit Card in Additional Meal Programs (Condensed Daily Sales Summary Report) | I5: Story Completed | J5: 3 | K5: 3 | L5: 12 | M5: 45870 | N5: 45876 | O5: Hemanath | P5: Sabir | Q5: NA | R5: Sabir | S5: NA | T5: 43838 | U5: 45876 | V5: 45876 | W5: Subha | X5: 1. Add revision history 2. Change the text lunch box to Mosaic 3. Update the SQL parameter passing syntax. | Y5: Ying | Z5: 45876 | AA5: NA | AB5: NA | AC5: NA | AD5: NA | AE5: Meets Expectation
A6: 5 | B6: FOH Wave | C6: 45870 | D6: 45883 | E6: 4.24 - Sprint 1 | F6: Vidhya | G6: 48991 | H6: MFOH [WAVE] - Support for Credit Card in Additional Meal Programs (Daily Sales by Serving Line Report) | I6: Story Completed | J6: 3 | K6: 9 | L6: 37 | M6: 45870 | N6: 45882 | O6: Vidhya | P6: Arvinth | Q6: NA | R6: Arvinth | S6: NA | T6: 43950 | U6: 45882 | V6: 45882 | W6: Subha | X6: Serializable attribute is missing | Y6: Ying | Z6: 45882 | AA6: NA | AB6: NA | AC6: NA | AD6: Low estimated story. There is a lack of support in the DB design to get the data. Faced more technical challanges during its implementation which was unexpected. | AE6: Meets Expectation
A7: 6 | B7: FOH Wave | C7: 45870 | D7: 45883 | E7: 4.24 - Sprint 1 | F7: Sabir Shaikh | G7: 49421 | H7: MFOH [WAVE]- Support for Credit Card in Additional Meal Programs (Daily Sales Summary Report) | I7: Story Completed | J7: 3 | K7: 3 | L7: 12 | M7: 45870 | N7: 45876 | O7: Sabir | P7: Hemanath | Q7: NA | R7: Hemanath | S7: NA | T7: 43846 | U7: 45876 | V7: 45876 | W7: Subha | X7: 1. Add revision history 2. Change the text lunch box to Mosaic 3. Update the SQL parameter passing syntax. | Y7: Ying | Z7: 45876 | AA7: NA | AB7: NA | AC7: NA | AD7: NA | AE7: Meets Expectation
A8: 7 | B8: FOH Wave | C8: 45870 | D8: 45883 | E8: 4.24 - Sprint 1 Stretch | F8: Subbulakshmi | G8: 49475 | H8: 49475 MFOH [WAVE] - Automation (48015) | I8: Story Completed | J8: 3 | K8: 3 | L8: 12 | M8: 45874 | N8: 45876 | O8: Subbulakshmi | P8: NA | Q8: NA | R8: NA | S8: NA | T8: 43842 | U8: 45876 | V8: 45876 | W8: Subha | X8: NA | Y8: Ying | Z8: 45876 | AA8: NA | AB8: NA | AC8: NA | AD8: Automation Testing | AE8: Meets Expectation
A9: 8 | B9: FOH Wave | C9: 45870 | D9: 45883 | E9: 4.24 - Sprint 1 Stretch | F9: Sabir Shaikh | G9: 49465 | H9: MFOH [WAVE] - Add a 'Delete' option to delete the User Created Custom Reports | I9: Story Ready For Testing | J9: 3 | K9: 4 | L9: 16 | M9: 45874 | N9: 45877 | O9: Sabir | P9: Hemanath | Q9: NA | R9: Hemanath | S9: NA | T9: 43948 | U9: 45882 | V9: 45882 | W9: Subha | X9: 1. Add ReportResultSharedRecipient table in the delete query | Y9: Ying | Z9: 45882 | AA9: NA | AB9: NA | AC9: NA | AD9: NA | AE9: Meets Expectation
A10: 9 | B10: FOH Wave | C10: 45870 | D10: 45883 | E10: 4.24 - Sprint 1 Stretch | F10: Hemanath Jayaraman | G10: 48362 | H10: [WAVE] Mosaic FOH - MARS Claim Export - Replace master serving period with serving period program | I10: Story Being Tested | J10: 3 | K10: 3.5 | L10: 14 | M10: 45877 | N10: 45880 | O10: Hemanath | P10: Sabir | Q10: NA | R10: Sabir | S10: NA | T10: NA | U10: NA | V10: NA | W10: Subha | X10: NA | Y10: NA | Z10: NA | AA10: NA | AB10: NA | AC10: NA | AD10: QA will test this in the feature branch and close it | AE10: Meets Expectation
A11: 10 | B11: FOH Wave | C11: 45870 | D11: 45883 | E11: 4.24 - Sprint 1 Stretch | F11: Sabir Shaikh | G11: 49428 | H11: MFOH [WAVE] - Allow the users to view the Dashboard Widgets in an enlarged version | I11: Story Being Developed | J11: 3 | K11: 3 | L11: 12
A12: 11 | B12: FOH Wave | C12: 45870 | D12: 45883 | E12: 4.24 - Sprint 1 Stretch | F12: Hemanath Jayaraman | G12: 49596 | H12: MFOH [WAVE]- Support for Credit Card in Additional Meal Programs (Extended Sales Report) | I12: Story Being Developed | J12: 3 | K12: 3 | L12: 13 | M12: 45880 | AE12: Meets Expectation
A13: 12 | B13: FOH Wave | C13: 45870 | D13: 45883 | E13: 4.24 - Sprint 1 Stretch | F13: Vidhya | G13: 49176 | H13: MFOH [WAVE] - Duplicating/copying the Dashboard Widgets | I13: Story Being Developed | K13: 2.5 | L13: 10

Sheet 4.24 - Sprint 1-Defect
A1: S.No | B1: Sprint # | C1: Story/Defect ID | D1: Parent Story | E1: Developer | F1: Issue Type | G1: Issue Description | H1: Priority | I1: Defect Source | J1: Type | K1: Status | L1: Dev Start Date | M1: Dev End Date | N1: Root Cause Category | O1: Comments
B2: 4.24 - Sprint 1 | C2: 49421 | D2: 49421 | E2: Sabir | F2: Bounceback/Sub-Defect | G2: showing StudentPaidAmount wrong value | H2: Major | I2: Manual | J2: Internal | K2: Defect Fixed | L2: 45882 | M2: 45882 | N2: Enhancements | O2: Functionality Issue

Sheet 4.23 - Sprint 4-Status
A1: S.No | B1: Application Name | C1: Sprint Start Date | D1: Sprint End Date | E1: Sprint | F1: Developer | G1: Story ID/Defect ID | H1: Description | I1: Status | J1: Estimated(hrs/sp) | K1: Actual(hrs/sp) | L1: Actual Worklog (Hours) | M1: Dev Start Date | N1: Dev End Date | O1: Unit testing | P1: Peer Tested By | Q1: Peer Tested Comments, if any | R1: Peer Reviewed By | S1: Peer Code Review Comments, if any | T1: PR Number/Link | U1: PR Created Date | V1: PR Approved Date | W1: Onsite Lead Code Review | X1: Code Review Comments, if any | Y1: Client Code Review | Z1: Approved Date | AA1: Code Review Comments, if any2 | AB1: Internal PO -POV Comments | AC1: Client PO -POV Comments | AD1: Comments | AE1: Does this story meet expectations?
A2: 1 | B2: FOH Wave | C2: 45856 | D2: 45869 | E2: 4.23 - Sprint 4 | F2: Sabir Shaikh | G2: 48411 | H2: MFOH [WAVE] - Custom Report (Navigation) | I2: Story Completed | J2: 1 | K2: 1 | L2: 4 | M2: 45859 | N2: 45859 | O2: Sabir | P2: Hemanath | Q2: None | R2: Hemanath | S2: None | T2: 43472 | U2: 45856 | V2: 45856 | W2: Subhashri | X2: None | Y2: Ying | Z2: 45856 | AA2: None | AB2: NA | AC2: NA | AD2: NA | AE2: Meets Expectation
A3: 2 | B3: FOH Wave | C3: 45856 | D3: 45869 | E3: 4.23 - Sprint 4 | F3: Hemanath Jayaraman | G3: 49267 | H3: [WAVE]Mosaic - FOH 4.23(Regression) - Setup | I3: Story Completed | J3: 2 | K3: 2 | L3: 23 | M3: 45860 | N3: 45863 | O3: Hemanath | P3: NA | Q3: NA | R3: NA | S3: NA | T3: NA | U3: NA | V3: NA | W3: NA | X3: NA | Y3: NA | Z3: NA | AA3: NA | AB3: NA | AC3: NA | AD3: NA | AE3: Meets Expectation
A4: 3 | B4: FOH Wave | C4: 45856 | D4: 45869 | E4: 4.23 - Sprint 4 | F4: Vidhya | G4: 49266 | H4: [WAVE]Mosaic - FOH 4.23(Regression) - Utilities | I4: Story Completed | J4: 3 | K4: 3 | L4: 27 | M4: 45860 | N4: 45864 | O4: Vidhya | P4: NA | Q4: NA | R4: NA | S4: NA | T4: NA | U4: NA | V4: NA | W4: NA | X4: NA | Y4: NA | Z4: NA | AA4: NA | AB4: NA | AC4: NA | AD4: NA | AE4: Meets Expectation
A5: 4 | B5: FOH Wave | C5: 45856 | D5: 45869 | E5: 4.23 - Sprint 4 | F5: Sabir Shaikh/Subbulakshmi | G5: 49263 | H5: [WAVE] Mosaic - FOH 4.23(Regression) - Reports - (Excluding Free/Reduced) | I5: Story Completed | J5: 8 | K5: 8 | L5: 43 | M5: 45860 | N5: 45863 | O5: Sabir/Subbu | P5: NA | Q5: NA | R5: NA | S5: NA | T5: NA | U5: NA | V5: NA | W5: NA | X5: NA | Y5: NA | Z5: NA | AA5: NA | AB5: NA | AC5: NA | AD5: NA | AE5: Meets Expectation
A6: 5 | B6: FOH Wave | C6: 45856 | D6: 45869 | E6: 4.23 - Sprint 4 Stretch | F6: Hemanath Jayaraman | G6: 48354 | H6: [WAVE] Mosaic FOH - Tennessee Claim Export - Replace master serving period with serving period program | I6: Story Ready For Testing | J6: 3 | K6: 2.75 | L6: 11 | M6: 45856 | N6: 45859 | O6: Hemanath | P6: Vidhya | Q6: NA | R6: Vidhya | S6: NA | T6: NA | U6: NA | V6: NA | W6: Subha | X6: NA | Y6: NA | Z6: NA | AA6: NA | AB6: NA | AC6: NA | AD6: Development has been completed. Will circle back after the relase regression testing is completed since its the top priority | AE6: Meets Expectation
A7: 6 | B7: FOH Wave | C7: 45856 | D7: 45869 | E7: 4.23 - Sprint 4 Stretch | F7: Sabir Shaikh | G7: 48338 | H7: [WAVE] Mosaic FOH - Rhode Island Claim Export - Replace master serving period with serving period program. | I7: Story Ready For Testing | J7: 3 | K7: 2 | L7: 12 | M7: 45856 | N7: 45859 | O7: Sabir | P7: Hemanath | Q7: None | R7: Hemanath | S7: NA | T7: NA | U7: NA | V7: NA | W7: Subhashri | X7: change the updateddate in SQL Script | Y7: NA | Z7: NA | AA7: NA | AB7: NA | AC7: NA | AD7: Development has been completed. Will circle back after the relase regression testing is completed since its the top priority | AE7: Meets Expectation
A8: 7 | B8: FOH Wave | C8: 45856 | D8: 45869 | E8: 4.23 - Sprint 4 Stretch | F8: Vidhya | G8: 49176 | H8: MFOH [WAVE] - Analysis on new widgets for Dashboard | I8: Story Being Developed | J8: 0 | K8: 7.75 | L8: 31 | M8: 45856 | N8: 45869 | O8: NA | P8: NA | Q8: NA | R8: NA | S8: NA | T8: NA | U8: NA | V8: NA | W8: NA | X8: NA | Y8: NA | Z8: NA | AA8: NA | AB8: NA | AC8: NA | AD8: Offshore PO going to have discussion with Onshore PO to get more details on this story
A9: 8 | B9: FOH Wave | C9: 45856 | D9: 45869 | E9: 4.23 - Sprint 4 Stretch | F9: Subbulakshmi | G9: 49380 | H9: 49380 MFOH [WAVE] - Automation (46542) | I9: Story Completed | J9: 2 | K9: 2 | L9: 8 | M9: 45866 | N9: 45867 | O9: Subbu | P9: NA | Q9: NA | R9: NA | S9: NA | T9: 43669 | U9: 45868 | V9: 45868 | W9: Subhashri | X9: NA | Y9: YIng | Z9: 45868 | AA9: NA | AB9: NA | AC9: NA | AD9: NA | AE9: Meets Expectation
A10: 9 | B10: FOH Wave | C10: 45856 | D10: 45869 | E10: 4.23 - Sprint 4 Stretch | F10: Hemanath Jayaraman | G10: 48362 | H10: [WAVE] Mosaic FOH - MARS Claim Export - Replace master serving period with serving period program | I10: Story Need More Info | J10: 3 | K10: 2.25 | L10: 9 | M10: 45866 | AD10: Offshore PO going to have discussion with Onshore PO to get his approval | AE10: Meets Expectation
A11: 10 | B11: FOH Wave | C11: 45856 | D11: 45869 | E11: 4.23 - Sprint 4 Stretch | F11: Sabir Shaikh | G11: 48363 | H11: [WAVE] Mosaic FOH - KY CNIPS Export SSO - Replace master serving period with serving period program | I11: Story Need More Info | J11: 3 | K11: 2 | L11: 10 | M11: 45866 | AD11: Offshore PO going to have discussion with Onshore PO to get his approval | AE11: Meets Expectation
A12: 11 | B12: FOH Wave | C12: 45856 | D12: 45869 | E12: 4.23 - Sprint 4 Stretch | F12: Sabir Shaikh | G12: 48336 | H12: [WAVE] Mosaic FOH - NorthCarolina Claim Export - Replace master serving period with serving period program | I12: Story Ready For Testing | J12: 3 | K12: 2 | L12: 10 | M12: 45866 | N12: 45867 | O12: Sabir | P12: Hemanath | Q12: NA | R12: Hemanath | S12: NA | T12: NA | U12: NA | V12: NA | W12: Subhashri | X12: change the updateddate in SQL Script | Y12: NA | Z12: NA | AA12: NA | AB12: NA | AC12: NA | AD12: NA | AE12: Meets Expectation

Sheet 4.23 - Sprint 4-Defect
A1: S.No | B1: Sprint # | C1: Story/Defect ID | D1: Parent Story | E1: Developer | F1: Issue Type | G1: Issue Description | H1: Priority | I1: Defect Source | J1: Type | K1: Status | L1: Dev Start Date | M1: Dev End Date | N1: Root Cause Category | O1: Comments
B2: 4.23 - Sprint 4 | C2: 25681 | D2: NA | E2: Hemanath Jayaraman | F2: Defect | G2: MFOH - (4.23 Regression) - Console errors while editing the cells in the grid in the provision 2 tab under school maintenance | H2: Minor | I2: Manual | J2: Internal | K2: Defect Fixed | L2: 45867 | M2: 45868 | N2: Existing_Issues | O2: Regression defect

Sheet 4.23 - Sprint 3-Status
A1: S.No | B1: Application Name | C1: Sprint Start Date | D1: Sprint End Date | E1: Sprint | F1: Developer | G1: Story ID/Defect ID | H1: Description | I1: Status | J1: Estimated(hrs/sp) | K1: Actual(hrs/sp) | L1: Actual Worklog (Hours) | M1: Unit testing | N1: Peer Tested By | O1: Peer Tested Comments, if any | P1: Peer Reviewed By | Q1: Peer Code Review Comments, if any | R1: PR Number/Link | S1: PR Created Date | T1: PR Approved Date | U1: Onsite Lead Code Review | V1: Code Review Comments, if any | W1: Client Code Review | X1: Approved Date | Y1: Code Review Comments, if any2 | Z1: Internal PO -POV Comments | AA1: Client PO -POV Comments | AB1: Comments | AC1: Does this story meet expectations?
A2: 1 | B2: FOH Wave | C2: 45842 | D2: 45855 | E2: 4.23 - Sprint 3 | F2: Vidhya | G2: 46542 | H2: MFOH [WAVE] - Modifications to Louisiana SFS-8C Report if a school qualifies for CEP | I2: Story Completed | J2: 3 | K2: 3 | L2: 3 | M2: Vidhya | N2: Sabir/Alpha | O2: None | P2: Sabir/Alpha | Q2: Correct the version year and typo | R2: 43331 | S2: 45849 | T2: 45849 | U2: Subha | V2: Set Quoted Identifier ON | W2: Ying | X2: 45849 | Y2: None | Z2: None | AA2: None | AC2: Meets Expectation
A3: 2 | B3: FOH Wave | C3: 45842 | D3: 45855 | E3: 4.23 - Sprint 3 | F3: Sabir Shaikh | G3: 47903 | H3: MFOH [WAVE] - Add a new template for Transaction History to Custom Report | I3: Story Completed | J3: 2 | K3: 2 | L3: 12 | M3: Sabir | N3: Vidhya | O3: ActiveDate is not showing when select DateType as ActiveDate | P3: Vidhya | Q3: None | R3: 43229 | S3: 45846 | T3: 45846 | U3: Subhashri | V3: Remove virtual keyword from method | W3: Ying | X3: 45846 | Y3: None | Z3: None | AA3: None | AB3: NA | AC3: Meets Expectation
A4: 3 | B4: ='Dashboard-2025'!$K$1 -> FOH Wave | C4: 45842 | D4: 45855 | E4: 4.23 - Sprint 3 Stretch | F4: Subhasri | G4: 46537 | H4: [WAVE] Mosaic - POS (Web) - Improvements to MA FP-9 Report (Silver Lake Regional School District) | I4: Story Needs More Info | J4: 3 | K4: 2.5 | L4: 11
A5: 4 | B5: FOH Wave | C5: 45842 | D5: 45855 | E5: 4.23 - Sprint 3 | F5: Sabir Shaikh | G5: 48714 | H5: Mosaic FOH - Replace Serving Period with Serving Period Program GUID in Georgia DE0112 | I5: Story Completed | J5: 2 | K5: 2 | L5: 12 | M5: Sabir | N5: Ashwin | O5: None | P5: Ashwin | Q5: None | R5: 43228 | S5: 45846 | T5: 45846 | U5: Subhashri | V5: None | W5: Ying | X5: 45846 | Y5: None | Z5: None | AA5: None | AB5: NA | AC5: Meets Expectation
A6: 5 | B6: FOH Wave | C6: 45842 | D6: 45855 | E6: 4.23 - Sprint 3 | F6: Sabir Shaikh | G6: 48334 | H6: [WAVE] Mosaic FOH - Colorado Claim Export - Replace master serving period with serving period program | I6: Story Completed | J6: 3 | K6: 3 | L6: 18 | M6: Sabir | N6: Ashwin | O6: None | P6: Ashwin | Q6: None | U6: Subhashri | V6: None | Y6: None | Z6: None | AA6: None | AB6: Testing is done in feature branch by QA .Yet to create PR | AC6: Meets Expectation
A7: 6 | B7: FOH Wave | C7: 45842 | D7: 45855 | E7: 4.23 - Sprint 3 Stretch | F7: Sabir Shaikh | G7: 48411 | H7: MFOH [WAVE] - Custom Report (Navigation) | I7: Story Being Developed | J7: 3 | K7: 3 | L7: 18 | AC7: Meets Expectation
A8: 7 | B8: FOH Wave | C8: 45842 | D8: 45855 | E8: 4.23 - Sprint 3 Stretch | F8: Hemanath Jayaraman | G8: 25568 | H8: MFOH [WAVE] - Custom and Report Designer should be accessible only by Tier 1 districts | I8: Story Completed | J8: 3 | K8: 2.75 | L8: 11 | M8: Hemanath | N8: Sabir | O8: NA | P8: Sabir | Q8: NA | R8: 43376 | S8: 45853 | T8: 45853 | U8: Subhashri | V8: NA | W8: Ying | X8: 45853 | Y8: NA | Z8: NA | AA8: NA | AC8: Meets Expectation
A9: 8 | B9: FOH Wave | C9: 45842 | D9: 45855 | E9: 4.23 - Sprint 3 Stretch | F9: Subbulakshmi | G9: 48862 | H9: MFOH Automation | I9: Story Completed | J9: 1 | K9: 1 | L9: 3 | M9: Subbulaxmi | N9: NA | O9: NA | P9: NA | Q9: NA | R9: 43275 | S9: 45847 | T9: 45847 | U9: NA | V9: NA | W9: Ying | X9: 45847 | Y9: NA | Z9: NA | AA9: NA | AC9: Meets Expectation
A10: 9 | B10: FOH Wave | C10: 45842 | D10: 45855 | F10: Vidhya | G10: 49176 | H10: MFOH - Analysis on new widgets for Dashboard | I10: Story Being Developed

Sheet 4.23 - Sprint 3-Defect
