Workbook

Sheet BOH Wave Team
A1: S.no | B1: Application Name | C1: Developer | D1: Description | E1: Status | F1: Comments
A2: 1 | B2: Extensions AI | C2: Rajiv / Deepika / Joel | D2: Extensions AI packages in console application | E2: Completed
A3: 2 | B3: Extensions AI | C3: Rajiv / Deepika / Joel | D3: Extensions AI packages integration in BOH application | E3: Completed
A4: 3 | B4: Extensions AI | C4: Rajiv / Deepika / Joel | D4: Extensions AI packages integration in BOH application with OpenAI | E4: Completed
A5: 4 | B5: Extensions AI | C5: Rajiv / Deepika / Joel | D5: Extensions AI packages integration in BOH application with AzureAI | E5: Completed
A6: 5 | B6: Extensions AI | C6: Rajiv / Deepika / Joel | D6: Extensions AI packages integration in BOH application with Vertex AI | E6: Completed | F6: Vertex not supported
A7: 6 | B7: Sementic Kernal | C7: Rajiv / Deepika / Joel | D7: Using Sementic Kernal In Console application | E7: Completed
A8: 7 | B8: Sementic Kernal | C8: Rajiv / Deepika / Joel | D8: Using Sementic Kernal In BOH application with Openai | E8: Completed
A9: 8 | B9: Sementic Kernal | C9: Rajiv / Deepika / Joel | D9: Using Sementic Kernal In BOH application with Azureai | E9: Completed
A10: 9 | B10: Sementic Kernal | C10: Rajiv / Deepika / Joel | D10: Using Sementic Kernal In BOH application with Vertexai | E10: Completed
A11: 10 | B11: Prompt Optimization | C11: Rajiv / Deepika / Joel | D11: Optimized prompt using sementic kernal in console application | E11: Completed
A12: 11 | B12: Prompt Optimization | C12: Rajiv / Deepika / Joel | D12: Optimized prompt using sementic kernal with Vertex & Openai | E12: Completed
A13: 12 | B13: API | C13: Rajiv / Deepika / Joel | D13: New API using sementic kernal with multiple LLM's | E13: Completed
A14: 13 | B14: API | C14: Rajiv / Deepika / Joel | D14: New API without using sementic kernal with multiple LLM's | E14: Completed
A15: 14 | B15: BOH AI Connectivity | C15: Rajiv / Deepika / Joel | D15: Creating new option in existing AI menu | E15: Completed
A16: 15 | B16: BOH AI Connectivity | C16: Rajiv / Deepika / Joel | D16: Consume the new API to integrate with existing BOH | E16: Completed
A17: 16 | B17: BOH AI Connectivity | C17: Rajiv / Deepika / Joel | D17: UI Changes to pass the LLM | E17: Completed
A18: 17 | B18: BOH AI Connectivity | C18: Rajiv / Deepika / Joel | D18: Pass Token counts and display to the AI connectivity output | E18: Completed
... A39: 38 | B39: Story - 46935 | C39: Joel & Rajiv | D39: Additional Instructions Improvements | E39: Completed

Sheet Defect-template
A1: S.No | B1: Sprint # | C1: Story/Defect ID | D1: Parent Story | E1: Developer | F1: Issue Type | G1: Issue Description | H1: Priority | I1: Defect Source | J1: Type | K1: Status | L1: Root Cause Category | M1: Comments

Sheet Dashboard
A1: Current Sprint | B1: {=INDEX($B$2:$B$108,MATCH(1,(($D$2:$D$108 >=TODAY())*($C$2:$C$108<=TODAY())),0))} -> 26.06 Sprint 4 | C1: Current Sprint Sheet | D1: =CONCATENATE(B1,"-Status") -> 26.06 Sprint 4-Status | E1: Sprint Start Date | F1: =VLOOKUP($B$1,$B$1:$C$108,2) -> 46155 | G1: Sprint End Date | H1: =VLOOKUP($B$1,$B$1:$D$108,3) -> 46168 | I1: Application Name | J1: BOH | K1: Users | L1: suresh.perumal@relevantz.com;shenbagavalli.srinivasan@relevantz.com;charles.antonysamy@relevantz.com;mohamed.mohamed@relevantz.com;ganapathiraman.balasubramanian@relevantz.com;kavitha.j@relevantz.com;rajivgandhi.sugumaran@relevantz.com;deepika.saravanan@relevantz.com;priyadharsini.kamalakannan@relevantz.com;krupa.bhatkar@relevantz.com;pradeepa.shanmugham@relevantz.com | M1: Teams Name(GP-Mosaic.BOH) | N1: 19:530ff4bdea8f4bbd9ac5dabcec987b9e@thread.v2
A2: Sprint Type | B2: Sprint # | C2: Sprint Start Date | D2: Sprint End Date | E2: Assigned | F2: Completed | G2: Story points introduced/removed | H2: Sprint Summary | I2: Accomplishments (Sprint Goal) | J2: Remarks | K2: Retro Points | L2: Planned Leave | M2: Total Leave | N2: Data sanity Audit Status | O2: AuditDate | P2: Backlog Health
A3: =IF(AND($D$1>=C3,$D$1<=D3),"CurrentSprint","NA") -> NA | B3: 3.18 Sprint 7 | C3: 45300 | D3: 45314 | E3: 25 | F3: 22 | J3: Regression sprint | K3: Internal: External:
A4: =IF(AND($D$1>=C4,$D$1<=D4),"CurrentSprint","NA") -> NA | B4: 3.18 Sprint 8 | C4: 45315 | D4: 45328 | E4: 26 | F4: 21 | J4: 43230 - Story carried due to reports validation pending in Regression | K4: Internal: External:
A5: =IF(AND($D$1>=C5,$D$1<=D5),"CurrentSprint","NA") -> NA | B5: 3.18 Sprint 9 | C5: 45329 | D5: 45342 | E5: 16 | F5: 16 | J5: Regression sprint | K5: Internal: External:
A6: =IF(AND($D$1>=C6,$D$1<=D6),"CurrentSprint","NA") -> NA | B6: 3.19 Sprint 1 | C6: 45343 | D6: 45356 | E6: 23 | F6: 16 | J6: Took a long time for regression of the production record and production record formats. Dev and QA focusing on 3.18 release, so not started testing 3.19 release stories. | K6: Internal: External:
A7: =IF(AND($D$1>=C7,$D$1<=D7),"CurrentSprint","NA") -> NA | B7: 3.19 Sprint 2 | C7: 45357 | D7: 45370 | E7: 20 | F7: 26 | J7: 1 story carry forwarded and completed 4 stories from stretch. | K7: Internal: External:
A8: =IF(AND($D$1>=C8,$D$1<=D8),"CurrentSprint","NA") -> NA | B8: 3.19 Sprint 3 | C8: 45371 | D8: 45384 | E8: 22 | F8: 17 | J8: 1 Story carried due to lot of testing scope involved and underestimated the effort. 2 Stretch stories completed. | K8: Internal: External:
A9: =IF(AND($D$1>=C9,$D$1<=D9),"CurrentSprint","NA") -> NA | B9: 3.19 Sprint 4 | C9: 45385 | D9: 45398 | E9: 21 | F9: 27 | J9: Addition to current sprint, completed 3 stories from stretch | K9: Internal: External:
A10: =IF(AND($D$1>=C10,$D$1<=D10),"CurrentSprint","NA") -> NA | B10: 3.19 Sprint 5 | C10: 45399 | D10: 45412 | E10: 18 | F10: 18 | J10: One 13 SP carried to next sprint, Client CRC fix is inprogress. | K10: Internal: External:
A11: =IF(AND($D$1>=C11,$D$1<=D11),"CurrentSprint","NA") -> NA | B11: 3.19 Sprint 6 | C11: 45413 | D11: 45426 | E11: 36 | F11: 36 | J11: Regression sprint | K11: Internal: External:
A12: =IF(AND($D$1>=C12,$D$1<=D12),"CurrentSprint","NA") -> NA | B12: 3.19 Sprint 7 | C12: 45427 | D12: 45440 | E12: 30 | F12: 30 | J12: Regression sprint | K12: Internal: External:
A13: =IF(AND($D$1>=C13,$D$1<=D13),"CurrentSprint","NA") -> NA | B13: 3.19 Sprint 8 | C13: 45441 | D13: 45454 | E13: 14 | F13: 14 | J13: Regression sprint and worked on regression defects(which doesn't have sp) | K13: Internal: External:
A14: =IF(AND($D$1>=C14,$D$1<=D14),"CurrentSprint","NA") -> NA | B14: 3.20 Sprint 1 | C14: 45455 | D14: 45468 | E14: 18 | F14: 18 | J14: Completed all the assigned stories | K14: Internal: External:
... A17: =IF(AND($D$1>=C17,$D$1<=D17),"CurrentSprint","NA") -> NA | B17: 3.20 Sprint 4 | C17: 45511 | D17: 45524 | E17: 19 | F17: 24 | J17: Addition to current sprint, completed 1 story from stretch | K17: Internal: External:
A18: =IF(AND($D$1>=C18,$D$1<=D18),"CurrentSprint","NA") -> NA | B18: 3.20 Sprint 5 | C18: 45525 | D18: 45538 | E18: 17 | F18: 17 | J18: Due to Public Holiday(2 Days) and onsite QA PTO, dev scope was reduced in the sprint and team worked and completed development on stretch stories. Even though development completed, those stories are pending for onsite QA testing, so carried to the next sprint. 03-Sep-24: CRC Peer - 0, Onsite - 0, Client - 1. Internal Defect - 0, External Defect - 1. | K18: Internal: External: | N18: Completed
A19: =IF(AND($D$1>=C19,$D$1<=D19),"CurrentSprint","NA") -> NA | B19: 3.20 Sprint 6 | C19: 45539 | D19: 45552 | E19: 23 | F19: 37 | G19: 14 sp - Introduced | J19: Addition to current sprint, completed 2 stories from stretch 17-Sep-24: CRC Peer - 0, Onsite - 0, Client - 0. Internal Defect - 0, External Defect - 2. | K19: Internal: External: | N19: Completed
A20: =IF(AND($D$1>=C20,$D$1<=D20),"CurrentSprint","NA") -> NA | B20: 3.20 Sprint 7 | C20: 45553 | D20: 45566 | E20: 8 | F20: 20 | J20: Addition to current sprint, completed 3 stories and 1 defect from stretch 01-Oct-24: CRC Peer - 0, Onsite - 0, Client - 0. Internal Defect - 0, External Defect - 1. | K20: Internal: External: | N20: Completed
A21: =IF(AND($D$1>=C21,$D$1<=D21),"CurrentSprint","NA") -> NA | B21: 3.20 Sprint 8 | C21: 45567 | D21: 45580 | E21: 18 | F21: 15 | J21: "Addition to current sprint, completed 1 stories from stretch and 2 Stories in QA 15-Oct-24: CRC Peer - 1, Onsite - 0, Client - 0. Internal Defect - 0, External Defect - 0." | K21: Internal: External: | N21: Completed
A22: =IF(AND($D$1>=C22,$D$1<=D22),"CurrentSprint","NA") -> NA | B22: 3.20 Sprint 9 | C22: 45581 | D22: 45594 | E22: 25 | F22: 30 | J22: Addition to current sprint, completed 1 stories from stretch 29-Oct-24: CRC Peer - 0, Onsite - 0, Client - 0. Internal Defect - 0, External Defect - 0. | K22: Internal: External: Completed sprint and stretch stories | N22: Completed
A23: =IF(AND($D$1>=C23,$D$1<=D23),"CurrentSprint","NA") -> NA | B23: 3.20 Sprint 10 | C23: 45595 | D23: 45608 | E23: 30 | F23: 30 | G23: 4/3 | I23: Completed regression on "Recipes",''Ingredients","Products" and "Inventory" Modules | J23: "46411" Mosaic BOH - 3.20 Regression - Ordering (Big Module) - Currently being in progress was removed and introduced 46412 and 46413. Development Cum Regression sprint CRC Peer - 0, CRC Onsite - 0, CRC Client - 0. Internal Defect - 0, External Defect - 0. | K23: Internal: External: | N23: Completed
A24: NA | B24: 3.20 Sprint 11 | C24: 45609 | D24: 45636 | E24: 25 | F24: 20 | I24: Completed Regression and Regression defects and worked on few production defects | J24: The development for story "46525"-Mosaic BOH - Bidding - Add the ability to attach any doc in bid analysis - is completed however the testing and review is incomplete due to hot fix release and one of the hot fix change was affecting the story. Until that is fixed it could not be pushed Development Cum Regression sprint CRC Peer - 0, CRC Onsite - 0, CRC Client - 0. Internal Defect - 2 Regression Defect- 10 External Defect - 0. | K24: Internal: External: Performance issue after 3.20 release | N24: Completed
A25: =IF(AND($D$1>=C25,$D$1<=D25),"CurrentSprint","NA") -> NA | B25: 3.21 Sprint 1 | C25: 45637 | D25: 45664 | E25: 25 | F25: 25 | I25: Completed committed stories on time and worked on a few production defects. | J25: The development for story "46743" - is in progress as we have to update the Kendo controls to latest version and fix affected components across the application.The story could spill over few more sprints as the same was done earlier (story 35612) which took total 316 hrs. It is a Development ---- Working control wise,once done with one will move to next control CRC Peer - 1, CRC Onsite - 0, CRC Client - 0. Internal Defect - 1 External Defect - 0. | K25: External: Kendo Update broke many screens Completed a few defects from stretch Completed the committed stories other than Kendo | N25: Completed
A26: =IF(AND($D$1>=C26,$D$1<=D26),"CurrentSprint","NA") -> NA | B26: 3.21 Sprint 2 | C26: 45665 | D26: 45678 | E26: 20 | F26: 20 | I26: Bidding - Ability to Edit Bid Pricelist, Adding Substitute Recipes(by site in Production Qtys), Adding User Visibility/Last Modified details to Menus and Vendors, and Defects. | J26: 46674 - Fixed the failed test cases in the Product and Ingredient Module 43702 - Development completed and in QA CRC Peer - 1, CRC Onsite - 1, CRC Client - 0. Internal Defect - 2 External Defect - 2. | K26: External: Automation parallel execution Substitution Recipe Story progress | N26: Completed
A27: =IF(AND($D$1>=C27,$D$1<=D27),"CurrentSprint","NA") -> NA | B27: 3.21 Sprint 3 | C27: 45679 | D27: 45692 | E27: 15 | F27: 47.25 | I27: Add substitute recipe in the Production Quantities for a site for a menu date - (Step 3), Adding Privacy Policy and Terms of Use, Combining “copy” buttons to dropdown option on Menu/Production Qty’s page, and Defect fixes for 3.21.. | J27: Addition to current sprint, completed 2 stories from stretch and 2 more stories in QA 46674 - Fixed the failed test cases in the Inventory Module (10.75 StP) CRC Peer - 0, CRC Onsite -1, CRC Client - 0. Internal Defect - 0 External Defect - 0. | K27: Internal: External: Completed sprint and stretch stories.Client appreciated for completing all the stories and defect in the actual commit | N27: Completed
A28: =IF(AND($D$1>=C28,$D$1<=D28),"CurrentSprint","NA") -> NA | B28: 3.21 Sprint 4 | C28: 45693 | D28: 45706 | E28: 16 | F28: 17 | I28: Adding Substituted Recipes in Production Record Report, Adding note to Bid Analysis Page, and begin 3.21 Regression Testing. WAVE(Gen AI) - UI Design. | J28: Addition to current sprint, worked on stories from stretch and 1 story in QA CRC Peer - 0, CRC Onsite -0, CRC Client - 0. Internal Defect - 3 External Defect - 0. | K28: Internal: External: Completed Regression, Completed committed stories and a few from stretch | N28: Completed
A29: =IF(AND($D$1>=C29,$D$1<=D29),"CurrentSprint","NA") -> NA | B29: 3.22 Sprint 1 | C29: 45707 | D29: 45720 | E29: 13 | F29: 26 | I29: Substitute Recipes - Updating Inventory Usage, Tech Debt(Updating 3rd parties), Separating Order Quantities(Vendor, Warehouse, & CK), and Defects. | J29: Addition to current sprint, worked on stories from stretch and 2 stories in QA CRC Peer - 0, CRC Onsite -0, CRC Client - 0. Internal Defect - 2 External Defect - 1. | K29: Internal: External: Completed sprint and stretch stories.Craig and Richard B appreciated for completing all the stories and defect in the actual commit | N29: Completed
A30: =IF(AND($D$1>=C30,$D$1<=D30),"CurrentSprint","NA") -> NA | B30: 3.22 Sprint 2 | C30: 45721 | D30: 45734 | E30: 21 | F30: 38 | I30: Substitute Recipes - Include in MealViewer, Auto-Generate Production Planning Recap, Add Product Status in Product List report, and Tiered Access Levels(WAVE Acceleration) . | J30: Addition to current sprint, completed 1 story from the stretch 46857 - Carry over to next sprint, due to the lot of scenarios to cover from menu planning screen to meal viewer sync. We completed menus and working on meal viewer sync.Also Unplanned PTO. Krupa working on Stretch story 46743 - Kendo Update, this requires more dev hours to fix the broken component and test all over the application, we keep the stories in stretch and working on. The effort we put into this was not included. CRC Peer - 0, CRC Onsite -1, CRC Client - 1. Internal Defect - 0 External Defect - 1. | K30: Internal: External: Richard Boutin and Andrew - Got lot of work completed and reviewed. What didn't go well: Unplanned PTO MV - Substitute recipe story. | N30: Completed
A31: =IF(AND($D$1>=C31,$D$1<=D31),"CurrentSprint","NA") -> NA | B31: 3.22 Sprint 3 | C31: 45735 | D31: 45748 | E31: 32 | F31: 50 | I31: Substitute Recipes (Include in MealViewer and Add to Production Costing Report), Location change for Vendor Orders Export Formats, Defects, and WAVE GenAI: Importing Suggested Menus | J31: 47441 -[WAVE]Mosaic BOH - Gen AI (Initiative #37515) - Import Suggested Menus Carry over to next sprint due to amount of work and testing involved. Underestimated the effort during planning. CRC Peer - 0, CRC Onsite -0, CRC Client - 0. Internal Defect - 3 External Defect - 1. Considerd 47615 and 47461 - 13sp/ each for automation coverage | K31: Internal: External: Richard Boutin and Andrew - Got lot of work completed and reviewed. What didn't go well: MV - Substitute recipe story. Underestimated AI story (47441) | N31: Completed
A32: =IF(AND($D$1>=C32,$D$1<=D32),"CurrentSprint","NA") -> NA | B32: 3.22 Sprint 4 | C32: 45749 | D32: 45762 | E32: 37 | F32: 34 | I32: CN2025 Updates, Tech Debt(Kendo Update), Substitute Recipes - Include in MealViewer, and WAVE GenAI(QR Code Login, Import Suggested Menus, and Implement AI Abstraction Layer). | J32: CRC Peer - 1, CRC Onsite -3, CRC Client - 3. Internal Defect - 0 External Defect - 0. | K32: Internal: External: What went well : Gen AI work Kendo ready for testing What didn’t go well : AI story not compatible with . Net | N32: Completed
A33: =IF(AND($D$1>=C33,$D$1<=D33),"CurrentSprint","NA") -> NA | B33: 3.22 Sprint 5 | C33: 45763 | D33: 45776 | E33: 35 | F33: 32 | I33: Tech Debt(Kendo Update), WAVE GenAI, and begin 3.22 Regression Testing | J33: 47441 - story got carry forwarded - Issues found by the team and needs rework 47902 - Dev completed, Testing pending CRC Peer - 0, CRC Onsite -1, CRC Client - 0, Internal Defect - 0 External Defect - 0. | K33: Internal: External: What went well : 1)Regression Testing 2)AI Development What didn’t go well : 1)COVID(unexpected PTO) 2)Accidental workflow step changes(defect marked for POV when was PR) 3)Underestimated work Wave/UI - Andrew's story | N33: Completed
A34: =IF(AND($D$1>=C34,$D$1<=D34),"CurrentSprint","NA") -> NA | B34: 3.22 Sprint 6 | C34: 45777 | D34: 45790 | E34: 24 | F34: 31 | G34: Introduced - 10 SP 48174 - 5 SP 48175 - 5 SP | I34: 3.22 Regression Testing and WAVE GenAI | J34: CRC Peer - 0, CRC Onsite -0, CRC Client - 0, Internal Defect - 0 External Defect - 0. | K34: Internal: External: What went well : 1) Defects fixed turnaround. 2)Regression time reduced 3) AI development What didn’t go well : 1)Regression defects found(Most caused by Kendo updates) 2)Web server authentication issues with AI. 3)Craig locked out of computer/system | N34: Completed
A35: =IF(AND($D$1>=C35,$D$1<=D35),"CurrentSprint","NA") -> NA | B35: 3.23 Sprint 1 | C35: 45791 | D35: 45804 | E35: 15 | F35: 21 | I35: 3.22 Regression Testing, Defect fixes for 3.22.1 Interim release, and WAVE GenAI & Tier Model. | J35: CRC Peer - 0, CRC Onsite -0, CRC Client - 0, Internal Defect - 0 External Defect - 0. | K35: Internal: External: What went well :Completed many defects What didn’t go well : Nil | N35: Completed
A36: =IF(AND($D$1>=C36,$D$1<=D36),"CurrentSprint","NA") -> NA | B36: 3.23 Sprint 2 | C36: 45805 | D36: 45818 | E36: 27 | F36: 28 | I36: Fixed a lot of defects, Good progress in the AI work | J36: CRC Peer - 0, CRC Onsite -0, CRC Client - 0, Internal Defect - 0 External Defect - 0. | K36: Internal: External: What went well : Completed many defects and good progress in the AI work What didn’t go well : Could not test wave stories, no test environment due to interim release | N36: Completed
A37: =IF(AND($D$1>=C37,$D$1<=D37),"CurrentSprint","NA") -> NA | B37: 3.23 Sprint 3 | C37: 45819 | D37: 45832 | E37: 17 | F37: 11.75 | I37: Five defect fixes, 3.22.1 Interim Release Prep/Checkout, and WAVE GenAI & Tier Model. | J37: Two defects were completed but not tested, so got spilled over.And completed one defect from stretch. CRC Peer - 0, CRC Onsite -0, CRC Client - 0, Internal Defect - 0 External Defect - 0 | K37: Internal: External: What went well :1)Fixed Lot of Defects(Total 5) 2)Interim release (no major issues reported post release) 3)Good progress in Jmeter What didn’t go well : | N37: Completed
A38: =IF(AND($D$1>=C38,$D$1<=D38),"CurrentSprint","NA") -> NA | B38: 3.23 Sprint 4 | C38: 45833 | D38: 45846 | E38: 18 | F38: 17 | H38: Ability to set fulfillment for each item under a product, and Defect fixes.Tier Model , Nutrition Facts Labels, Create Ingredient, Creative Recipe - Portion size - Update the original response, Parent Data Table - Child Data Table , Add Allergens details to the Get Creative Recipes , Nutrients - measurement conversion | I38: Ability to set fulfillment for each item under a product, and 2 Defect fixes and also completed two stories from stretch | J38: CRC Peer - 0, CRC Onsite -1, CRC Client - 0, Internal Defect - 0 External Defect - 0. | K38: Internal: External: What went well : Load testing went well What didn’t go well : Issues in VDI Setup | N38: Completed
A39: =IF(AND($D$1>=C39,$D$1<=D39),"CurrentSprint","NA") -> NA | B39: 3.23 Sprint 5 | C39: 45847 | D39: 45860 | E39: 15 | F39: 12 | G39: 5 sp introduced Defect ID -25534 | H39: Kendo - All Scrollable Grid screens - print issue, Recipes - The nutrients don't update on the menu, Recipe checkbox deselect on load, CSV file report, Ability to set fulfilment for each item level. Tier Model - Feature/Menus visibility based on the Tier levels, Nutrition Facts Label-Attach Image, Filter Task by list, Adjust background to Full screen, Physical Count worksheet. | I39: 1) Kendo scroll grid - print screen issue, CSV report, and few stories and defects completed from stretch. 2) Completed AI Implementation Tickets. Tier Level, Image attachment from nutrition fact label | J39: Committed Stories: Total 2 stories, 1 story completed, and 1 story development completed, testing spilled over to next sprint. Stretch: 1 story completed. Committed Defects: Total 2 defects,1 defect completed and 1 defect spilled over to next sprint. Introduced during sprint: 1 defect completed (5 SP) Stretch: 1 defect completed. CRC Peer - 0, CRC Onsite -0, CRC Client - 0, Internal Defect - 0 External Defect - 0 | K39: What went well : CSV report, few stories and defects completed from stretch. Tier Models, Introduction of grooming session What didn’t go well : Kendo update changes caused a few issues, Unplanned leave. Test Data was not clear, Due to introduction of Vega Components issue in testing DOM elements Story 49064 under estimated and Defect 25472 (initially not able to reproduce) | N39: Completed
A40: =IF(AND($D$1>=C40,$D$1<=D40),"CurrentSprint","NA") -> NA | B40: 3.23 Sprint 6 | C40: 45861 | D40: 45874 | E40: 7 | F40: 9 | H40: Bidding - Setup for Discounts, ER - Display "Number of Items" in Requisition, DC Central Kitchen Export - Add Reimbursable served quantity to the export data,Deactivated on-hand products not appearing on End of Month Inventory report,Mosaic BOH (CPS C0026) - Add Meal Totals to the Production Recap report Iterative AI call to parse Inventory Worksheet images, UI for verification and Editing the AI Response of the Inventory Parsing, Model switching, Ability to upload images from the system for nutrition fact label | I40: WAVE GenAI, devlopment for Ability to Set fulfillment to Item Level ,Bidding - Setup for Discounts, Bidding - Add Price per S/U to the Bid Analysis, and DC central kitchen export completed,Display number of item in requisition completed. | J40: Stories: 1 story completed from main commit, and 1 story completed from stretch. Note: 4 stories development completed from stretch and ready for testing Defects: (Total 2 defects Completed) Main commit defect - 1, Stretch defect - 1 CRC Peer - 0, CRC Onsite -0, CRC Client - 0, Internal Defect - 0 External Defect - 4 | K40: What went well: Development was completed for committed stories and defects, including stretch items. A few committed stories and defects were completed What didn’t go well: Onsite QA was on leave, so testing and completion of stories were not possible.
A41: =IF(AND($D$1>=C41,$D$1<=D41),"CurrentSprint","NA") -> NA | B41: 4.0 Sprint 1 | C41: 45875 | D41: 45888 | E41: 13 | F41: 25 | H41: Added Sugar Target values in Menus, Cycle Menus Setup, Weekly Nutrients check popup in Menus,Cycle Menus,Nutrient Breakdown Report, Menu Names & Nutrient Standards Report, Menus and Cycle Menu Spreadsheets, Bidding - Setup for Discounts, AI Assistant - Add the ability to upload images from the system, Improve Quality of Breakfast Menu Suggestions, Offer More Recipe Variety, Model switching - UI, Rework on the Mobile experience for Image/doc upload. | I41: Complete Gen AI, adding notes to indicate Added Sugars (<10% coming in July 2027) on multiple screens & reports (USDA requirement), Set Fulfillment by Item | J41: Stories: 5 stories completed from main commit, and 3 stories completed from stretch. Defects: (Total 4 defects Completed) Main commit defect - 1, Stretch defect - 3 CRC Peer - 0, CRC Onsite -0, CRC Client - 0, Internal Defect - 1 External Defect - 3 | K41: What went well: Completed committed stories and defects, including 3 stretch items. Wave Team: Completed all the committed stories and some stretch stories: What didn’t go well: Offshore unplanned leave and a bounceback
A42: =IF(AND($D$1>=C42,$D$1<=D42),"CurrentSprint","NA") -> NA | B42: 4.0 Sprint 2 | C42: 45889 | D42: 45902 | E42: 6 | F42: 14 | H42: Added Sugars Cals% into the Menus and Cycle Menus, Add Meal Totals to the Production Recap report and Bidding stories Rework on the Mobile experience for Image/doc upload, Import AI-extracted Physical Count values into products/items,User Ratings, UI Refresh (Import Menu Popup Changes), Submit physical count, AI Entry Point screen 4 columns, UI Refresh (Nutrition Facts Labels Edit Screen), Gen AI Assistant and Tasks Pages | I42: Gen AI(Performance Improvements, Importing Physical Count, and Mobile), Added Sugars Cals% into Menus/Cycle Menus, and Adding Meal Totals to Production Recap report, Bidding stories | J42: Stories: 2 stories completed from main commit, and 3 stories completed from stretch. Defects: (Total 1 defect Completed) Stretch defect - 1 CRC Peer - 0, CRC Onsite -0, CRC Client - 0, Internal Defect - 1 External Defect - 1 | K42: What went well: Completed 2 committed stories, and 4 stretch items. Wave Team: Completed all the committed stories and 2 stretch stories. What didn’t go well: Added sugars AC change
A43: =IF(AND($D$1>=C43,$D$1<=D43),"CurrentSprint","NA") -> NA | B43: 4.0 Sprint 3 | C43: 45903 | D43: 45930 | E43: 30 | F43: 40 | H43: Regression sprint - completed regression stories - Inventory, Order, Menu, Report, Setup, and completed regression defects Gen AI UI Refresh - AI Entry Point screen 4 columns, UI Refresh (Nutrition Facts Labels Edit Screen), Gen AI Assistant and Tasks Pages, Additional search details to identify a unique physical count record, Gen AI - Conversation Workflow, Refactor AI Code to use common API call, Nutrition facts label UI changes, UI changes for physical count upload, Mobile Workflow Changes, UI changes for Production Records, Gen AI - Terms of Service,Additional Physical Count Assistant UXUI Modifications (23 SEP 2025), Production Record Assistant - AI Production Record Format & Execute | I43: 4.0 Regression Testing Gen AI Improvements: Data from Images (Nutrient Fact Labels), Production Record, UI changes for physical count | J43: Stories: Completed regression stories - Inventory, Order, Menu, Report, Setup Defects: Total 16 regression defects (13 - Completed, 2 - Development Completed, 1 - Rejected) CRC Peer - 0, CRC Onsite -0, CRC Client - 0, Internal Defect - 0 External Defect - 0 | K43: What went well: Completed regression and regression defects on time. Wave Team: Completed all the committed stories and most of the stretch stories What didn’t go well: Offshore unplanned leaves
A44: =IF(AND($D$1>=C44,$D$1<=D44),"CurrentSprint","NA") -> NA | B44: 4.1 Sprint 1 | C44: 45931 | D44: 45944 | E44: 24 | F44: 24 | H44: Ability to copy Production Record Format from one District to another,Bidding remove UPC code validation, Visibility to Last modified Date/User for Products, Meal Totals in Production Summary Report, Gen AI, and Defect Fixes AI Task Grid Status values, Physical Count - Freeze Column Headers from scrolling, Production Record UI changes, Menu Generation Additional Instructions workflow issue, Support multiple images for a Production Record Import, Move prompts to the database, Sanitize uploaded image parsing. | I44: Ability to copy Production Record Format from one District to another, Visibility to Last modified Date/User for Products, Gen AI, and Defect Fixes . | J44: Stories: Completed commited stories CRC Peer - 0, CRC Onsite -0, CRC Client - 0, Internal Defect - 0 External Defect - 0 | K44: What went well:Completed all the 6 commited stories Wave Team: 1.AI release 2.Completed committed stories What didn’t go well: 1.Terms of service 2.Token Limits AI
A45: =IF(AND($D$1>=C45,$D$1<=D45),"CurrentSprint","NA") -> NA | B45: 4.1 Sprint 2 | C45: 45945 | D45: 45958 | E45: 10 | F45: 9 | H45: Add CSV format to the Production Planning Shopping List Report, Add Default Mosaic Price Lists Import/Export Template Add the Ability to Export Price Lists by using 'Default Mosaic Price Lists Import/Export' Template , Transfers Bulk Substitution - Product Search and Replace (UI only) GEN AI - Production Record - Move Image to top & Edit grid to botton & freeze column headers & Recipe column, Move prompts to the database, Physical Count, Production Record, and Nutrition Facts Label Image viewer, Filter Site selectors based on the user's Site Group access, AI Task Status Values (Menu Gen & Nutrition Facts), Add Additional Logs in AI, AI Should be 'Edit Fields' not individual Security Page items. | I45: Delivered Gen AI(Physical Count, Production Record, and Nutrition Facts Label Image viewer, Filter Site selectors based on the user's Site Group) & BOH: Implemented 'Default Mosaic Price Lists Import/Export' so that users can Export the pricelists | J45: Stories: Completed 2 commited stories & 3 defects. CRC Peer - 0, CRC Onsite -0, CRC Client - 0, Internal Defect - 1 External Defect - 2 | K45: BOH: What went well: Completed committed 2 stories and completed 3 defects What didn’t go well: could not complete one committed story 49692. Wave Team: What went well :Completed all the committed stories and 2 from stretch What didn’t go well: Scheduler some times not working in QA Environment.
A46: =IF(AND($D$1>=C46,$D$1<=D46),"CurrentSprint","NA") -> NA | B46: 4.1 Sprint 3 | C46: 45959 | D46: 45972 | E46: 7 | F46: 15 | H46: BOH Last Login Date is not being recorded in some cases (4.1) AI- Menu Planning - PQ screen - Print Blank AI Production Record link disappears after save, AI -(ON QA MPtest)Production Record Upload Screen - Print Blank AI Production Record link does not work, Add the ability to print warehouse orders from within the orders Users - Improve usability District Maintenance Improvements (NCESID, HSSCustomerID). WAVE GEN AI - Nutrition Facts Label - Create a Measurement from the Serving Size, Image upload functionality should filter to acceptable document types, Gen AI - In-App AI Marketing, Production Record Upload - Add Note that only menus with Planned Quantities will show up. | I46: Delivered Print Blank AI Production Record link disappears after Save, AI- Create a Measurement from the Serving Size, Image upload functionality with acceptable document types, QA Environmental Issues & other few AI Defects. | J46: Stories: Completed 3 Stretch stories & 4 defects. CRC Peer - 1, CRC Onsite -1, CRC Client - 0, Internal Defect - 1 External Defect - 3 | K46: BOH: What went well: Completed 3 stretch stories & 4 defects. What didn't go well Firewall issue/Random messages appearing in the application. Wave: What went well : Completed all the committed , stretch stories & defects. What didn't go well Firewall issue/Random messages appearing in the application & environmental issues in QA.
A47: =IF(AND($D$1>=C47,$D$1<=D47),"CurrentSprint","NA") -> NA | B47: 4.2 Sprint 1 | C47: 45973 | D47: 46000 | E47: 28 | F47: 40 | G47: 5 (Story No: 50281) | H47: BOH Transfers Bulk Substitution - Product Search and Replace, User Assignment Report, Ingredient Export, Bidding - Add serving size, number serving in the Bid specification document, Add Item Origin filter on the Product Maintenance screen, Production Costing Report - Make available for non-HHFKA menus, User Assignment Report - Add a new column 'Active' WAVE: ER Have categories or more specific storage categories be able to be filtered out on the Transfer Pull Sheet report, Requisition# needs to be shown in the Transfers for Warehouse orders, Persist filter options on Receiving screen, Bidding - Estimated Quantity - Warning message, Bidding - Expand the Vendor Quotes - Bid Analysis grid for better view, Warehouse - Add Delivery Route field to Transfers screen, Warehouse - Add Delivery Route field to Warehouse Orders Bulk Approval screen, Warehouse - Add Delivery Route field to Warehouse Orders screen, Inventory Inquiry - Item Availability Report, Mosaic BOH - Bidding - Add Bid Status search filter under bidding response | I47: Transfers Bulk Substitution - Product Search and Replace, User Assignment Report, Production Costing Report make available for non-HHFKA menus, Ingredient Export Script(KDE), Bidding - additional fields to Bid Specification Document, and Defect Fixes. | J47: Stories: Completed all committed stories and 2 stretch story. CRC Peer - 0, CRC Onsite - 0, CRC Client - 0, Internal Defect - 1 External Defect - 0 | K47: BOH: What went well: Completed all the committed stories and 2 from stretch. What didn't go well: Wave: What went well: Completed all the committed stories and 7 from stretch What didn't go well:
A48: =IF(AND($D$1>=C48,$D$1<=D48),"CurrentSprint","NA") -> NA | B48: 4.2 Sprint 2 | C48: 46001 | D48: 46028 | E48: 34 | F48: 40 | H48: BOH Nutrition Facts Label - Ability to upload PDF files Nutrition Facts Label - Ability to update an Existing Ingredient's Nutrients instead of create a new ingredient USDA Guidance - Updates needed for certification 4.2 Regression - Ordering 4.2 Regression - Menus/Cycle Menus 4.2 Regression - Recipes WAVE Add page-break between days option to Production record report format setup (NK conversion feature gap), Warehouse Orders - 'View Report' - show the status with the date, Addition of new filter for Inventory Worksheet Physical counts, Warehouse - Add Delivery Route to Warehouse Orders report, Bidding Status Change, Regression - Inventory, Products, Bidding | I48: Nutrition Facts Label - Ability to upload PDF files Nutrition Facts Label - Ability to update an Existing Ingredient's Nutrients instead of create a new ingredient USDA Guidance - Updates needed for certification and Regression | J48: Stories: Completed committed stories and regression testing and 3 stretch stories. CRC Peer - 0, CRC Onsite - 0, CRC Client - 0, Internal Defect - 1, External Defect - 3 | K48: BOH: What went well: Completed all the committed stories and regression testing and 3 stories from stretch. What didn't go well:Nil Wave: What went well: Completed all the committed stories and 3 stories from stretch. What didn't go well:NiL
A49: =IF(AND($D$1>=C49,$D$1<=D49),"CurrentSprint","NA") -> NA | B49: 26.1 Sprint 3 | C49: 46029 | D49: 46042 | E49: 23 | F49: 23 | H49: BOH: Product List Report - Add a new filter for Notes - Has Notes, Add a column to Ingredients search to tell if the Ingredient has any attachment, 26.1 Regression - Menus/Cycle Menus 26.1 Regression - Reports 26.1 Regression - Setup 26.1 Regression - Community 26.1 Regression - AI WAVE: Inventory - Option to Export Inventory Worksheet,Regression - Bidding, Regression - Inventory, Regression - Inventory | I49: Completed Regression and Regression defects, and completed two committed stories, and releasing BOH version 26.1 on Jan 22nd | J49: Stories: Completed committed stories, regression stories, and 21 regression defects CRC Peer - 0, CRC Onsite - 0, CRC Client - 0, Internal Defect - 21, External Defect - 0 | K49: BOH: What went well: Completed all the committed stories and regression testing, and 21 regression defects What didn't go well: Nil Wave: What went well: Completed all the committed stories and 1 from stretch What didn't go well: NiL | N49: Completed
A50: =IF(AND($D$1>=C50,$D$1<=D50),"CurrentSprint","NA") -> NA | B50: 26.3 Sprint 1 | C50: 46043 | D50: 46056 | E50: 27 | F50: 30 | H50: BOH: Mosaic BOH - Reports - Production Records - Substitutions with Prod Specs should show the ingredient under recipe Mosaic BOH(Tech Debt) - Kendo Update Mosaic BOH - Contribution Report - Add ability to run for non HHFKA menus (Athens City) WAVE: Mosaic BOH - Bidding - Bid Status Change from Awarded - Deactivate/Delete Pricelist Mosaic BOH - Warehouse/Central Kitchen Item Availability Report - Add site level order quantity details Mosaic BOH - Bidding - Calculate Estimated Qty Mosaic BOH - Inventory Transfer Report - Add "consolidated" filter (Nampa) Mosaic BOH - Bidding - Remove Bid Priority column from Bid Maintenance Mosaic BOH - Bidding - Hide Bidding Setup menu | I50: Kendo Update, Bidding, Inventory Transfer Report (Adding consolidated Filter), and Defect Fixes. | J50: Completed all the committed stories and 1 story from stretch Completed 2 committed defects CRC Peer - 0, CRC Onsite - 0, CRC Client - 0, Internal Defect - 2 External Defect - 0 | K50: BOH: What went well: Completed all the committed stories and 1 story from stretch Completed 2 committed defects What didn't go well: AI menu generation broken in QA Wave: What went well: Completed all the 4 committed stories and 2 stories from stretch. Completed 2 commited defects and 1 from stretch . What didn't go well: Nil | L50: 4 | M50: 6 | N50: Completed
A51: =IF(AND($D$1>=C51,$D$1<=D51),"CurrentSprint","NA") -> NA | B51: 26.3 Sprint 2 | C51: 46057 | D51: 46070 | E51: 25 | F51: 36 | H51: BOH Implemented USDA Whole Milk features for the HHKFA Lunch menus. Added all Milk Types in the Reim.Meal Groups for HHFKA Lunch menus. Applied recent Kendo updates across the application & Fixed couple of defects. WAVE Implemented the Add Items On Hand filter in the Warehouse/Central Kitchen Item Availability Report. Developed enhancements in Bidding – Bid Response/Analysis, including handling Requested Item vs. Quoted Item. Added a Print Bidding Responses button in the Bid Maintenance screen. Displayed Warehouse Current Availability while creating Warehouse Orders. Implemented logic to hide Bid Priority on the Product Maintenance screen. | I51: USDA Whole Milk features for HHKFA Lunch menus, Recent Kendo updates & Defects. | J51: Completed all the committed stories and 2 stories from stretch Completed 3 committed defects CRC Peer - 0, CRC Onsite - 0, CRC Client - 0, Internal Defect - 0 External Defect - 6 | K51: BOH: What went well: Completed all committed 4 stories and 2 stories from stretch Completed 3 committed defects and 3 stretch defects. What didn't go well: Nil Wave: What went well: Completed all 5 committed stories. What didn't go well: Nil | L51: 5 | M51: 7 | N51: Completed
A52: =IF(AND($D$1>=C52,$D$1<=D52),"CurrentSprint","NA") -> NA | B52: 26.03 Sprint 3 | C52: 46071 | D52: 46084 | E52: 31 | F52: 34 | G52: 1 Story Completed from Stretch (3 SP) | H52: BOH: USDA: Whole Milk features for the HHKFA Lunch menus. Menu Spreadsheet Report, Nutrients Breakdown Reports. Recent Kendo updates. Include last modified details in Production Record Report. BOH WAVE: Central Kitchen - Bulk Order Approval. Bidding - Cleanup Bid Priority related code in the backend. Add the ability to Bulk commit transfers. Bidding - Bid Response/Analysis - Requested item vs Quoted Item [Substitution Workflow] - Bottom Line. Transfers - Search By Warehouse Order Number. | I52: USDA: Whole Milk Changes, Report updates, Include last modified details in Production Record Report and Recent Kendo updates. | J52: Completed 6 committed stories, and 1 story from stretch CRC Peer - 0 CRC Onsite - 0 CRC Client - 0 Internal Defect - 0 External Defect - 0 | K52: BOH: What went well: Completed 6 committed stories, and 1 story from stretch What didn't go well: Nil Wave: What went well: Completed 3 committed stories and 2 stories from stretch. Completed 2 committed defects. What didn't go well: Nil | L52: 2 | M52: 3 | N52: Completed
A53: =IF(AND($D$1>=C53,$D$1<=D53),"CurrentSprint","NA") -> NA | B53: 26.03 Sprint 4 | C53: 46085 | D53: 46112 | E53: 46 | F53: 51 | G53: 3 SP - Completed stretch story 2 SP - Completed stretch Defects | H53: BOH: Regression - Menus, Ordering, Reports, and Setup. Kendo update to version 2026.1.212 BOH Wave: Regression - Inventory,Products and Bidding modules. Transfers - Search and Replace - View Report, Products - Add security group for Products - Bulk Fulfillment (1), Ability to sort P/U Quantity and S/U Quantity for the physical counts screen, Products - Add Bulk Fulfillment menu option (2) | I53: Kendo Update, and 26.3 Regression Testing | J53: Completed 5 committed stories. CRC Peer - 0 CRC Onsite - 0 CRC Client - 0 Internal Defect - 5 External Defect - 0 | K53: BOH: What went well: Completed all (5) committed stories. Got through regression quicker than estimated (3 weeks) Found and Fixed Lots of Defects Updates to regression test cases What didn't go well: Found 5 defects during regression Wave: What went well: Completed all (7) commited stories and 1 story from stretch Completed 4 Defects. Got through regression quicker than estimated (3 weeks) Found and Fixed Lots of Defects Updates to regression test cases What didn't go well: Found 4 defects during regression | L53: 7 | M53: 7 | N53: Completed
A54: =IF(AND($D$1>=C54,$D$1<=D54),"CurrentSprint","NA") -> NA | B54: 26.06 Sprint 1 | C54: 46113 | D54: 46126 | E54: 7 | F54: 9 | G54: 2 SP - Defects completed from stretch | H54: BOH: USDA Guideline changes for M/MA & Grains Updated Report schema to the latest version Implemented logic to display the added and last modified information and also implemented the soft delete concept in Vendor Order Export Format. BOH Wave: Bid Analysis - Implemented the ability to add the Bid import document to the Bid Analysis attachment Implemented logic to Inventory - Restrict duplicate items(Transfers and Usage) Product List Report - Add a new filter for Item Origin Products - Origin - Added new option ""Non-Domestic (unspecified)"" to droplist Implemented logic to Ingredients - To add Notes Bidding - Added Last modified details in Bid Response and Bid Analysis Implemented logic to Inventory - Bulk Adjustments - Security page & Search for Products | I54: BOH: USDA Guideline changes , Updated Report Schema to latest version BOH Wave: Bidding, Bulk Adjustments, Adding Item Origin Filter to Product List report, and Defect Fixes | J54: Completed 2 committed stories. CRC Peer - 0 CRC Onsite - 0 CRC Client - 0 Internal Defect - 0 External Defect - 3 | K54: What went well: Completed all commited stories Defect Fixes(sprint/stretch) What didn't go well: Nil | L54: 5 | M54: 5 | N54: Completed
A55: =IF(AND($D$1>=C55,$D$1<=D55),"CurrentSprint","NA") -> NA | B55: 26.06 Sprint 2 | C55: 46127 | D55: 46140 | E55: 29 | F55: 29 | H55: BOH: USDA- Display Combined M/MA & Grains Component for HHFKA Breakfast Menus Reports - Ability to Select Weekly/Daily/Average Nutrients Report - Add Tooltip Description and Preview Image for Buy American report Pendo updates. BOH Wave: Inventory - Bulk Adjustments - New screen to update the bulk adjustments, Inventory - Search Transfers by Transfer # - added new filter to search by transfer #, Performance improvisation on product group to retrieve the data faster to show in the result grid, Inventory - Add User Tracking for Physical Count transactions to who added, modified and committed the record, Item Maintenance - Left Side Nav Menu and landing page, Products - Addition of new Bulk Fulfillment screen to update the bulk fulfillment | I55: BOH: Combined M/MA & Grains Component for HHFKA Breakfast Menus, Ability View Report based on Daily/Weekly/Average Nutrients, Tooltip Description for Buy American report, Pendo updates BOH Wave: New screen to update the bulk adjustments,added new filter to search by transfer # , Add User Tracking for Physical Count transactions, Item Maintenance - Left Side Nav Menu and landing page, Products- Bulk Fillfillment. | J55: Completed 7 committed stories. CRC Peer - 0 CRC Onsite - 0 CRC Client - 0 Internal Defect - 0 External Defect - 2 | K55: BOH: What went well: Completed 7 committed stories & 2 defects. Fixed build issues. Completed more than forecasted What didn't go well: Pipeline build issues Underestimated story(52862). Wave: What went well: Completed 5 committed stories and 1 stretch defect What didn't go well: Pipeline build issues. Bulk Adjustment issues in certain environments | L55: 1 | M55: 1 | N55: Completed | P55: 140
A56: =IF(AND($D$1>=C56,$D$1<=D56),"CurrentSprint","NA") -> NA | B56: 26.06 Sprint 3 | C56: 46141 | D56: 46154 | E56: 21 | F56: 23 | G56: 2 SP - Stories from stretch | H56: BOH: USDA - Display Combined M/MA & Grains Component for HHFKA Breakfast Menus Reports - Ability to Select Weekly/Daily/Average Nutrients BOH Wave: Inventory - Bulk Adjustments - Create Bulk Adjustments screen, Products - Adding Bulk Fulfillment by Group (4), Report - Inventory Transfer - Add category filters to filter the data Report - Shopping List - Add the ability to exclude a product from the shopping list report. | I56: BOH: USDA Updates, and Menu Calendar Report – ability to select Weekly/Daily/Average nutrients BOH Wave: Bulk Adjustments, Bulk fulfillment, Report filters, Exclustion list in reports | J56: Completed 2 committed stories and 2 stretch stories. CRC Peer - 0 CRC Onsite - 0 CRC Client - 0 Internal Defect - 0 External Defect - 0 | K56: BOH: What went well: Completed 2 committed stories and 2 stretch stories What didn't go well: PTOs BOH Wave: What went well: Completed 4 committed stories What didn't go well: PTOs | L56: 9 | M56: 9 | N56: Completed
A57: =IF(AND($D$1>=C57,$D$1<=D57),"CurrentSprint","NA") -> NA | B57: 26.06 Sprint 4 | C57: 46155 | D57: 46168

Sheet 26.06 Sprint 4-Status
A1: S.No | B1: Application Name | C1: Sprint Start Date | D1: Sprint End Date | E1: Sprint | F1: Developer | G1: Story ID/Defect ID | H1: Description | I1: Status | J1: Estimated(sp) | K1: Actual(sp) | L1: Actual Hours Worklog | M1: Dev Start Date | N1: Dev End Date | O1: Unit testing | P1: Peer Tested By | Q1: Peer Tested Comments, if any | R1: Peer Reviewed By | S1: Peer Code Review Comments, if any | T1: PR Number/Link | U1: PR Created Date | V1: PR Approved Date | W1: Reviewer 1 | X1: Code Review Comments, if any | Y1: Reviewer 2 | Z1: Approved Date | AA1: Code Review Comments, if any2 | AB1: Internal PO -POV Comments | AC1: Client PO -POV Comments | AD1: Comments | AE1: Does this story meet expectations?
A2: 1 | B2: BOH | C2: 46155 | D2: 46168 | E2: 26.06 Sprint 4 | F2: Mohamed | G2: 52618 | H2: [WAVE] Mosaic BOH - Inventory - Bulk Adjustments - 4 - Managing Bulk Adjustments | I2: Story Being Developed | J2: 5 | K2: =L2/4 -> 1.75 | L2: 7 | M2: 46155 | AB2: When changing any data in the bulk adjustment and clicking cancel should ask for saving the work
A3: 2 | B3: BOH | C3: 46155 | D3: 46168 | E3: 26.06 Sprint 4 | F3: Mohamed | G3: 52828 | H3: Mosaic BOH - Report - Production Entry Audit Report - CPS (C0009) | I3: Story Being Developed | J3: 5 | K3: =L3/4 -> 0.75 | L3: 3 | M3: 46156
A4: 3 | B4: BOH | C4: 46155 | D4: 46168 | E4: 26.06 Sprint 4 | F4: Kavitha | G4: 53250 | H4: Mosaic BOH - USDA - Whole Milk - Menu Screen Updates (1 - Breakfast) | I4: Story Being Developed | J4: 2 | K4: 1 | L4: 3 | M4: 46155
A5: 4 | B5: BOH | C5: 46155 | D5: 46168 | E5: 26.06 Sprint 4 | F5: Kavitha | G5: 53253 | H5: Mosaic BOH - USDA - Whole Milk - Cycle Menu Screen Updates (2 - Breakfast) | I5: Story Being Developed | J5: 2 | K5: 0.5 | L5: 1 | M5: 46155
A6: 5 | B6: BOH | C6: 46155 | D6: 46168 | E6: 26.06 Sprint 5 | F6: Kavitha | G6: 53256 | H6: Mosaic BOH - USDA - Whole Milk - Menu - Reimburse Meal Groups(3) (Breakfast) | I6: Story Being Developed | J6: 2 | K6: 1 | L6: 3
A7: 5 | B7: BOH | C7: 46155 | D7: 46168 | E7: 26.06 Sprint 4 Stretch | F7: Suresh | G7: 53268 | H7: Mosaic BOH - Update Automation Testcases based on Vega Component changes & adding new Testcases | I7: Story Being Developed | J7: 13 | K7: 3 | L7: 12 | M7: 46155

Sheet 26.06 Sprint 4 - Defect Tracker
A1: Sprint # | B1: Story/Defect ID | C1: Parent Story | D1: Developer | E1: Issue Type | F1: Issue Description | G1: Priority | H1: Defect Source | I1: Type | J1: Status | K1: Estimated(sp) | L1: Actual(sp) | M1: Actual Hours Worklog | N1: Root Cause Category | O1: Comments

Sheet 26.06 Sprint 3-Status
A1: S.No | B1: Application Name | C1: Sprint Start Date | D1: Sprint End Date | E1: Sprint | F1: Developer | G1: Story ID/Defect ID | H1: Description | I1: Status | J1: Estimated(sp) | K1: Actual(sp) | L1: Actual Hours Worklog | M1: Dev Start Date | N1: Dev End Date | O1: Unit testing | P1: Peer Tested By | Q1: Peer Tested Comments, if any | R1: Peer Reviewed By | S1: Peer Code Review Comments, if any | T1: PR Number/Link | U1: PR Created Date | V1: PR Approved Date | W1: Reviewer 1 | X1: Code Review Comments, if any | Y1: Reviewer 2 | Z1: Approved Date | AA1: Code Review Comments, if any2 | AB1: Internal PO -POV Comments | AC1: Client PO -POV Comments | AD1: Comments | AE1: Does this story meet expectations?
A2: 1 | B2: BOH | C2: 46141 | D2: 46154 | E2: 26.06 Sprint 3 | F2: Mohamed | G2: 52862 | H2: Mosaic BOH - Menus - Menu Calendar Report to display Daily, Weekly and Average in the same page | I2: Story Completed | J2: 5 | K2: =L2/4 -> 2 | L2: 8 | M2: 46141 | N2: 46142 | O2: Done | P2: Suresh | Q2: Nil | R2: Kavitha | S2: Nil | T2: https://dev.azure.com/heartlandschools/Mosaic/_git/BOH/pullrequest/48718 | U2: 46141 | V2: 46141 | W2: Charles | X2: Nil | Y2: NA | Z2: NA | AA2: Nil | AB2: Nil | AC2: Nil | AD2: Nil | AE2: Meets Expectation
A3: 2 | B3: BOH | C3: 46141 | D3: 46154 | E3: 26.06 Sprint 3 | F3: Charles | G3: 51709 | H3: Mosaic BOH - USDA Guidance - Menu Spreadsheet Report - Update Sodium Guidelines | I3: Story Completed | J3: 3 | K3: 2.5 | L3: 10 | M3: 46141 | N3: 46146 | O3: Done | P3: Suresh | Q3: Nil | R3: Mohammed | S3: Nil | T3: https://dev.azure.com/heartlandschools/Mosaic/_git/BOH/pullrequest/48863 | U3: 46148 | V3: 46148 | W3: Charles | X3: Nil | Y3: NA | Z3: NA | AA3: Nil | AB3: Nil | AC3: Nil | AD3: Nil | AE3: Meets Expectation
A4: 3 | B4: BOH | C4: 46141 | D4: 46154 | E4: 26.06 Sprint 3 | F4: Charles | G4: 52873 | H4: Mosaic BOH - USDA - Display Combined M/MA & Grains Component for HHFKA Breakfast Menus (Reimbursable Meal Group) | I4: Story Being Tested | J4: 13 | K4: =L4/4 -> 8 | L4: 32 | M4: 46141 | N4: 46143 | O4: Done | P4: Suresh | Q4: Nil | R4: Mohammed | S4: Nil | T4: https://dev.azure.com/heartlandschools/Mosaic/_git/BOH/pullrequest/48918 | U4: 46149 | V4: 46149 | W4: Charles | X4: Nil | Y4: Em | Z4: NA | AA4: Nil | AB4: Nil | AC4: Nil | AD4: Development completed and moved to testing, Onsite QA took vacation and needs to test more scenarios so testing only carry forward to next sprint. | AE4: Meets Expectation
A5: 4 | B5: BOH | C5: 46141 | D5: 46154 | E5: 26.06 Sprint 3 Stretch | F5: Suresh | G5: 53065 | H5: Mosaic BOH - Adding Automation Testcases in Products | I5: Story Completed | J5: 13 | K5: =L5/4 -> 12 | L5: 48 | M5: 46141 | N5: 46154 | O5: NA | P5: NA | Q5: NA | R5: NA | S5: NA | T5: https://dev.azure.com/heartlandschools/Mosaic/_git/BOH/pullrequest/49021 | U5: 46154 | V5: 46154 | W5: Charles | X5: NA | Y5: NA | Z5: NA | AA5: NA | AB5: NA | AC5: NA | AD5: NA | AE5: NA
A6: 5 | B6: BOH | C6: 46141 | D6: 46154 | E6: 26.06 Sprint 3 Stretch | F6: Mohamed | G6: 53078 | H6: Mosaic BOH - Price List - Save vs. Save & Close | I6: Story Completed | J6: 1 | K6: 1 | L6: 4 | M6: 46147 | N6: 46147 | O6: Done | P6: Kavitha | Q6: Nil | R6: Kavitha | S6: Nil | T6: https://dev.azure.com/heartlandschools/Mosaic/_git/BOH/pullrequest/48818 | U6: 46147 | V6: 46147 | W6: Charles | X6: Nil | Y6: NA | Z6: NA | AA6: Nil | AB6: Nil | AC6: Nil | AD6: Nil | AE6: Meets Expectation
A7: 6 | B7: BOH | C7: 46141 | D7: 46154 | E7: 26.06 Sprint 3 Stretch | F7: Charles | G7: 53196 | H7: Mosaic BOH - Update Employee SSO Hint | I7: Story Completed | J7: 1 | K7: 0.5 | L7: 2 | M7: 46150 | N7: 46150 | O7: Done | P7: Suresh | Q7: Nil | R7: Kavitha | S7: Nil | T7: https://dev.azure.com/heartlandschools/Mosaic/_git/BOH/pullrequest/48946 | U7: 46150 | V7: 46150 | W7: Charles | X7: Nil | Y7: Em | Z7: NA | AA7: Nil | AB7: Nil | AC7: Nil | AD7: Nil | AE7: Meets Expectation
A8: 7 | B8: BOH | C8: 46141 | D8: 46154 | E8: 26.06 Sprint 3 Stretch | F8: Kavitha | G8: 42397 | H8: Mosaic BOH - Production Qtys screen - Add the Ability to Calculate Reimbursable Served Qty | I8: Story Ready For Testing | J8: 5 | K8: =L8/4 -> 2.5 | L8: 10 | M8: 46148 | N8: 46149 | O8: Done | P8: Mohammed | Q8: Nil | R8: Mohammed | S8: Nil | T8: https://dev.azure.com/heartlandschools/Mosaic/_git/BOH/pullrequest/48895 | U8: 46149 | V8: 46150 | W8: Charles | X8: Nil | Y8: NA | Z8: NA | AA8: Nil | AB8: Nil | AC8: Nil | AD8: Nil | AE8: Meets Expectation
A9: 8 | B9: BOH | C9: 46141 | D9: 46154 | E9: 26.06 Sprint 3 Stretch | F9: Kavitha | G9: 48508 | H9: Mosaic BOH - Include substitute recipes in the Production Summary | I9: Story Ready For Testing | J9: 5 | K9: =L9/4 -> 3 | L9: 12 | M9: 46141 | N9: 46147 | O9: Done | P9: Suresh | Q9: Nil | R9: Mohammed | S9: Nil | T9: https://dev.azure.com/heartlandschools/Mosaic/_git/BOH/pullrequest/48819 | U9: 46146 | V9: 46147 | W9: Charles | X9: Nil | Y9: NA | Z9: NA | AA9: Nil | AB9: Nil | AC9: Nil | AD9: Nil | AE9: Meets Expectation
A10: 9 | B10: BOH | C10: 46141 | D10: 46154 | E10: 26.06 Sprint 3 Stretch | F10: Kavitha | G10: 53163 | H10: [WAVE] Mosaic BOH - Recipes - Add "Needs Attention" flag | I10: Story Peer Review | J10: 3 | K10: =L10/4 -> 3.75 | L10: 15 | M10: 46150 | N10: 46154 | O10: Done | P10: Suresh | Q10: 1) Need Attentipn Search filter is not working.2) Suggested the validation popup change. | T10: https://dev.azure.com/heartlandschools/Mosaic/_git/BOH/pullrequest/48981 | AB10: 1.Need some space in Notes tab 2.Need to include Deactivate and Delete check (new AC)
A11: 10 | B11: BOH | C11: 46141 | D11: 46154 | E11: 26.06 Sprint 3 Stretch | F11: Mohamed | G11: 52828 | H11: Mosaic BOH - Report - Production Entry Audit Report - CPS (C0009) | I11: Story Being Developed | J11: 8 | K11: =L11/4 -> 2 | L11: 8 | M11: 46141
A12: 11 | B12: BOH | C12: 46141 | D12: 46154 | E12: 26.06 Sprint 3 Stretch | F12: Mohamed | G12: 52235 | H12: [WAVE] Mosaic BOH - Receiving - Add 'View Report' option (West Hartford) | I12: Story Being Developed | J12: 8 | K12: =L12/4 -> 2.5 | L12: 10 | M12: 46147

Sheet 26.06 Sprint 3 - Defect Tracker
A1: Sprint # | B1: Story/Defect ID | C1: Parent Story | D1: Developer | E1: Issue Type | F1: Issue Description | G1: Priority | H1: Defect Source | I1: Type | J1: Status | K1: Estimated(sp) | L1: Actual(sp) | M1: Actual Hours Worklog | N1: Root Cause Category | O1: Comments

Sheet 26.06 Sprint 2-Status
A1: S.No | B1: Application Name | C1: Sprint Start Date | D1: Sprint End Date | E1: Sprint | F1: Developer | G1: Story ID/Defect ID | H1: Description | I1: Status | J1: Estimated(sp) | K1: Actual(sp) | L1: Actual Hours Worklog | M1: Dev Start Date | N1: Dev End Date | O1: Unit testing | P1: Peer Tested By | Q1: Peer Tested Comments, if any | R1: Peer Reviewed By | S1: Peer Code Review Comments, if any | T1: PR Number/Link | U1: PR Created Date | V1: PR Approved Date | W1: Reviewer 1 | X1: Code Review Comments, if any | Y1: Reviewer 2 | Z1: Approved Date | AA1: Code Review Comments, if any2 | AB1: Internal PO -POV Comments | AC1: Client PO -POV Comments | AD1: Comments | AE1: Does this story meet expectations?
A2: 1 | B2: BOH | C2: 46127 | D2: 46140 | E2: 26.06 Sprint 2 | F2: Mohamed | G2: 25871 | H2: Mosaic BOH - Reports - Menu Calendar - Ability to Select Weekly/Daily/Average Nutrients | I2: Story Completed | J2: 5 | K2: =L2/4 -> 3 | L2: 12 | M2: 46127 | N2: 46132 | O2: Done | P2: Suresh | Q2: Nil | R2: Kavitha | S2: Nil | T2: https://dev.azure.com/heartlandschools/Mosaic/_git/BOH/pullrequest/48488 | U2: 46132 | V2: 46136 | W2: Charles | X2: Nil | Y2: NA | Z2: NA | AA2: NA | AB2: Nil | AC2: NA | AD2: Nil | AE2: Meets Expectation
A3: 3 | B3: BOH | C3: 46127 | D3: 46140 | E3: 26.06 Sprint 2 | F3: Kavitha | G3: 52861 | H3: Mosaic BOH - Report - Add Tooltip Description and Preview Image for Buy American report | I3: Story Completed | J3: 2 | K3: 1.5 | L3: 6 | M3: 46129 | N3: 46129 | O3: Nil | P3: Nil | Q3: Nil | R3: Mohammed | S3: Nil | T3: https://dev.azure.com/heartlandschools/Mosaic/_git/BOH/pullrequest/48494 | U3: 46129 | V3: 46132 | W3: Charles | X3: Nil | Y3: NA | Z3: NA | AA3: NA | AB3: Nil | AC3: NA | AD3: Nil | AE3: Meets Expectation
A4: 4 | B4: BOH | C4: 46127 | D4: 46140 | E4: 26.06 Sprint 2 | F4: Charles | G4: 52173 | H4: Mosaic BOH - Pendo Snippet Updates, Phase 1 | I4: Story Completed | J4: 3 | K4: =L4/4 -> 1.5 | L4: 6 | M4: 46128 | N4: 46129 | O4: Nil | P4: Nil | Q4: Nil | R4: Mohammed | S4: Nil | T4: https://dev.azure.com/heartlandschools/Mosaic/_git/BOH/pullrequest/48517 | U4: 46129 | V4: 46129 | W4: NA | X4: NA | Y4: Richard | Z4: 46132 | AA4: Nil | AB4: Nil | AC4: Nil | AD4: Nil | AE4: Meets Expectation
A5: 5 | B5: BOH | C5: 46127 | D5: 46140 | E5: 26.06 Sprint 2 | F5: Charles | G5: 43904 | H5: Mosaic BOH - Pendo - Changes Needed | I5: Story Completed | J5: 5 | K5: =L5/4 -> 2.5 | L5: 10 | M5: 46132 | N5: 46136 | O5: Nil | P5: Nil | Q5: Nil | R5: Mohammed | S5: Nil | T5: https://dev.azure.com/heartlandschools/Mosaic/_git/BOH/pullrequest/48625 | U5: 46136 | V5: 46136 | W5: NA | X5: NA | Y5: Em | Z5: 46136 | AA5: Nil | AB5: Nil | AC5: Nil | AD5: Nil | AE5: Meets Expectation
A6: 6 | B6: BOH | C6: 46127 | D6: 46140 | E6: 26.06 Sprint 2 | F6: Charles | G6: 52609 | H6: [WAVE] Mosaic BOH - Item Maintenance - 1 - Add to Feature Flag list | I6: Story Completed | J6: 1 | K6: 1 | L6: 1 | M6: 46127 | N6: 46127 | O6: Nil | P6: Nil | Q6: Nil | R6: Mohammed | S6: Nil | T6: https://dev.azure.com/heartlandschools/Mosaic/_git/BOH/pullrequest/48450 | U6: 46127 | V6: 46128 | W6: NA | X6: NA | Y6: Em | Z6: 46127 | AA6: Nil | AB6: Nil | AC6: Nil | AD6: Nil | AE6: Meets Expectation
A7: 7 | B7: BOH | C7: 46127 | D7: 46140 | E7: 26.06 Sprint 2 | F7: Charles | G7: 52608 | H7: [WAVE] Mosaic BOH - Item Maintenance - 2 - Create Security Group | I7: Story Completed | J7: 2 | K7: =L7/4 -> 1.125 | L7: 4.5 | M7: 46129 | N7: 46132 | O7: Nil | P7: Nil | Q7: Nil | R7: Mohammed | S7: Nil | T7: https://dev.azure.com/heartlandschools/Mosaic/_git/BOH/pullrequest/48520 | U7: 46132 | V7: 46132 | W7: NA | X7: NA | Y7: Richard | Z7: 46132 | AA7: Nil | AB7: Nil | AC7: Nil | AD7: Nil | AE7: Meets Expectation
A8: 9 | B8: BOH | C8: 46127 | D8: 46140 | E8: 26.06 Sprint 2 Stretch | F8: Suresh | G8: 52875 | H8: Mosaic BOH - Adding Automation Testcases in SetUp-Allergens | I8: Story Completed | J8: 13 | K8: 12 | L8: 48 | M8: 46127 | N8: 46140 | O8: Nil | P8: Nil | Q8: Nil | R8: Charles | T8: https://dev.azure.com/heartlandschools/Mosaic/_git/BOH/pullrequest/48691 | U8: 46140 | V8: 46140 | W8: Charles | X8: Nil | Y8: NA | Z8: NA | AA8: Nil | AB8: Nil | AC8: Nil | AD8: Nil | AE8: Meets Expectation
A9: 11 | B9: BOH | C9: 46127 | D9: 46140 | E9: 26.06 Sprint 2 | F9: Charles | G9: 52875 | H9: Mosaic BOH - (USDA) (4.3) Display Combined M/MA & Grains Component for HHFKA Breakfast Menus | I9: Story Completed | J9: 2 | K9: 1 | L9: 4 | M9: 46129 | N9: 46133 | O9: Nil | P9: Nil | Q9: Nil | R9: Mohammed | S9: Nil | T9: https://dev.azure.com/heartlandschools/Mosaic/_git/BOH/pullrequest/48559 | U9: 46133 | V9: 46140 | W9: NA | X9: NA | Y9: Richard | Z9: 46133 | AA9: Nil | AB9: Nil | AC9: Nil | AD9: Nil | AE9: Meets Expectation

Sheet 26.06 Sprint 2 - Defect Tracker
A1: Sprint # | B1: Story/Defect ID | C1: Parent Story | D1: Developer | E1: Issue Type | F1: Issue Description | G1: Priority | H1: Defect Source | I1: Type | J1: Status | K1: Estimated(sp) | L1: Actual(sp) | M1: Actual Hours Worklog | N1: Root Cause Category | O1: Comments
A2: 26.06 - Sprint 2 | B2: 26988 | D2: Kavitha | E2: Defect | F2: Mosaic BOH - Recipes - Maintenance - Water - Missing Nutrients (N/A) showing as *0* in the totals. | G2: Minor | H2: Manual | I2: External | J2: Defect Fixed | K2: 3 | L2: 2 | M2: 0.8 | N2: Existing_Issues | O2: Existing Production Issue, defect was not identified in the previous test cycles
A3: 26.06 - Sprint 2 | B3: 27147 | D3: Kavitha | E3: Defect | F3: Mosaic BOH - Menus - Maintenance & Cycle - Breakfast Menus - Not flagging 2% and Whole milk as being restricted | G3: Minor | H3: Manual | I3: External | J3: Defect Fixed | K3: 3 | L3: 2.5 | M3: 10 | N3: Existing_Issues | O3: Existing Production Issue, defect was not identified in the previous test cycles

Sheet 26.06 Sprint 1-Status
A1: S.No | B1: Application Name | C1: Sprint Start Date | D1: Sprint End Date | E1: Sprint | F1: Developer | G1: Story ID/Defect ID | H1: Description | I1: Status | J1: Estimated(sp) | K1: Actual(sp) | L1: Actual Hours Worklog | M1: Dev Start Date | N1: Dev End Date | O1: Unit testing | P1: Peer Tested By | Q1: Peer Tested Comments, if any | R1: Peer Reviewed By | S1: Peer Code Review Comments, if any | T1: PR Number/Link | U1: PR Created Date | V1: PR Approved Date | W1: Reviewer 1 | X1: Code Review Comments, if any | Y1: Reviewer 2 | Z1: Approved Date | AA1: Code Review Comments, if any2 | AB1: Internal PO -POV Comments | AC1: Client PO -POV Comments | AD1: Comments | AE1: Does this story meet expectations?
A2: 1 | B2: BOH | C2: 46113 | D2: 46126 | E2: 26.06 Sprint 1 | F2: Kavitha | G2: 52276 | H2: Mosaic BOH - VOEF - Add the Added By and Last Modified By details | I2: Story Completed | J2: 3 | K2: 2.5 | L2: 12 | M2: 46113 | N2: 46118 | O2: Done | P2: Suresh | Q2: Nil | R2: Mohammed | S2: Nil | T2: https://dev.azure.com/heartlandschools/Mosaic/_git/BOH/pullrequest/48263 | U2: 46119 | V2: 46120 | W2: Charles | X2: Nil | Y2: NA | Z2: NA | AA2: NA | AB2: NIL | AC2: NIL | AD2: NIL | AE2: Meets Expectation
A3: 2 | B3: BOH | C3: 46113 | D3: 46126 | E3: 26.06 Sprint 1 Stretch | F3: Suresh | G3: 52619 | H3: Mosaic BOH - Adding Automation Testcases in SetUp | I3: Story Completed | J3: 13 | K3: 10 | L3: 40 | M3: 46113 | N3: 46125 | O3: Nil | P3: Nil | Q3: Nil | R3: Charles | S3: Nil | T3: https://dev.azure.com/heartlandschools/Mosaic/_git/BOH/pullrequest/48417 | U3: 46125 | V3: 46126 | W3: Charles | X3: Nil | Y3: NA | Z3: NA | AA3: NA | AB3: NIL | AC3: NIL | AD3: NIL
A4: 3 | B4: BOH | C4: 46113 | D4: 46126 | E4: 26.06 Sprint 1 | F4: Charles | G4: 51421 | H4: Mosaic BOH(Tech Debt) - Update Report schema to the latest version - Products | I4: Story Completed | J4: 3 | K4: 2 | L4: 8 | M4: 46113 | N4: 46115 | O4: Done | P4: Suresh | Q4: Nil | R4: Mohammed | S4: Nil | T4: https://dev.azure.com/heartlandschools/Mosaic/_git/BOH/pullrequest/48215 | U4: 46114 | V4: 46114 | W4: NA | X4: NA | Y4: Richard | Z4: 46114 | AA4: NA | AB4: NA | AC4: NA | AD4: NIL | AE4: Meets Expectation

Sheet 26.06 Sprint 1 - Defect Tracker
A1: Sprint # | B1: Story/Defect ID | C1: Parent Story | D1: Developer | E1: Issue Type | F1: Issue Description | G1: Priority | H1: Defect Source | I1: Type | J1: Status | K1: Estimated(sp) | L1: Actual(sp) | M1: Actual Hours Worklog | N1: Root Cause Category | O1: Comments
A2: 26.06 - Sprint 1 Stretch | B2: 27116 | D2: Charles | E2: Defect | F2: Mosaic BOH [Wave] - Ordering - Central Kitchen Orders invalid date format not showing error message | G2: Minor | H2: Manual | I2: External | J2: Defect Fixed | K2: 1 | L2: 1 | M2: 4 | N2: Existing_Issues | O2: The recent Kendo update changed the way it pulls the element for error validation. It was found during testing and fixed as a defect.
A3: 26.06 - Sprint 1 | B3: 27101 | D3: Charles | E3: Defect | F3: Mosaic BOH - Adjustments - Single or Bulk - Program allows you to change Adjustment Type after adjustment is committed | G3: Minor | H3: Manual | I3: External | J3: Defect Fixed | K3: 1 | L3: 1 | M3: 4 | N3: Existing_Issues | O3: The recent Kendo update changed the way it pulls the element for error validation. It was found during testing and fixed as a defect.
A4: 26.06 - Sprint 1 Stretch | B4: 27131 | D4: Charles | E4: Defect | F4: Mosaic BOH [Wave] -Inventory- Physical count P/U & S/U Quantity values allowing to type decimal values even Inventory - Allow Partial Stock Units asNO | G4: Minor | H4: Manual | I4: External | J4: Defect Fixed | K4: 1 | L4: 1 | M4: 4 | N4: Existing_Issues | O4: Existing production Issue, It's an edge case where user will copy paste decimal point where it shouldn't allow.

Sheet 26.3 Sprint 4-Status
A1: S.No | B1: Application Name | C1: Sprint Start Date | D1: Sprint End Date | E1: Sprint | F1: Developer | G1: Story ID/Defect ID | H1: Description | I1: Status | J1: Estimated(sp) | K1: Actual(sp) | L1: Actual Hours Worklog | M1: Dev Start Date | N1: Dev End Date | O1: Unit testing | P1: Peer Tested By | Q1: Peer Tested Comments, if any | R1: Peer Reviewed By | S1: Peer Code Review Comments, if any | T1: PR Number/Link | U1: PR Created Date | V1: PR Approved Date | W1: Reviewer 1 | X1: Code Review Comments, if any | Y1: Reviewer 2 | Z1: Approved Date | AA1: Code Review Comments, if any2 | AB1: Internal PO -POV Comments | AC1: Client PO -POV Comments | AD1: Comments | AE1: Does this story meet expectations?
A2: 1 | B2: BOH | C2: 46085 | D2: 46112 | E2: 26.3 Sprint 4 | F2: Team | G2: 52154 | H2: Mosaic BOH - 26.3 Regression - Menus/Cycle Menus | I2: Story Completed | J2: 13 | K2: =L2/4 -> 31.5 | L2: 126 | M2: 46086 | N2: 46098 | O2: NA | P2: NA | Q2: NA | R2: NA | S2: NA | T2: NA | U2: NA | V2: NA | W2: NA | X2: NA | Y2: NA | Z2: NA | AA2: NA | AB2: NA | AC2: NA | AD2: It's regression story, where several test cases are missing data. Consequently, we setup the data and execute the tests, and actual working hours including regression defects. | AE2: NA
A3: 2 | B3: BOH | C3: 46085 | D3: 46112 | E3: 26.3 Sprint 4 | F3: Team | G3: 52160 | H3: Mosaic BOH - 26.3 Regression - Ordering | I3: Story Completed | J3: 3 | K3: =L3/4 -> 10 | L3: 40 | M3: 46098 | N3: 46100 | O3: NA | P3: NA | Q3: NA | R3: NA | S3: NA | T3: NA | U3: NA | V3: NA | W3: NA | X3: NA | Y3: NA | Z3: NA | AA3: NA | AB3: NA | AC3: NA | AD3: It's regression story, where several test cases are missing data. Consequently, we setup the data and execute the tests, and actual working hours including regression defects. | AE3: NA
A4: 3 | B4: BOH | C4: 46085 | D4: 46112 | E4: 26.3 Sprint 4 | F4: Team | G4: 52155 | H4: Mosaic BOH - 26.3 Regression - Reports | I4: Story Completed | J4: 13 | K4: =L4/4 -> 10.5 | L4: 42 | M4: 46099 | N4: 46101 | O4: NA | P4: NA | Q4: NA | R4: NA | S4: NA | T4: NA | U4: NA | V4: NA | W4: NA | X4: NA | Y4: NA | Z4: NA | AA4: NA | AB4: NA | AC4: NA | AD4: NIL | AE4: NA
A5: 4 | B5: BOH | C5: 46085 | D5: 46112 | E5: 26.3 Sprint 4 | F5: Team | G5: 52156 | H5: Mosaic BOH - 26.3 Regression - Setup | I5: Story Completed | J5: 13 | K5: =L5/4 -> 6 | L5: 24 | M5: 46101 | N5: 46104 | O5: NA | P5: NA | Q5: NA | R5: NA | S5: NA | T5: NA | U5: NA | V5: NA | W5: NA | X5: NA | Y5: NA | Z5: NA | AA5: NA | AB5: NA | AC5: NA | AD5: NIL | AE5: NA
A6: 5 | B6: BOH | C6: 46085 | D6: 46112 | E6: 26.3 Sprint 4 | F6: Charles | G6: 52110 | H6: Mosaic BOH - Kendo update to version 2026.1.212 | I6: Story Completed | J6: 3 | K6: =L6/4 -> 6 | L6: 24 | M6: 46086 | N6: 46091 | O6: NA | P6: Suresh | Q6: NIL | R6: Mohammed | S6: NIL | T6: https://dev.azure.com/heartlandschools/Mosaic/_git/BOH/pullrequest/47693 | U6: 46090 | V6: 46090 | W6: NIL | X6: NIL | Y6: Em | Z6: 46090 | AA6: NIL | AB6: NIL | AC6: NIL | AD6: NIL | AE6: Meets Expectation
A7: 6 | B7: BOH | C7: 46085 | D7: 46112 | E7: 26.3 Sprint 4 Stretch | F7: Suresh | G7: 52224 | H7: Mosaic BOH - Adding Automation Testcases in SetUp | I7: Story Completed | J7: 13 | K7: 10 | L7: 40 | M7: 46086 | N7: 46112 | O7: NA | P7: NA | Q7: NA | R7: Charles | S7: NIL | T7: https://heartlandschools.visualstudio.com/Mosaic/_git/BOH/pullrequest/48133 | U7: 46112 | V7: 46112 | W7: Charles | X7: NIL | Y7: NIL | Z7: NIL | AA7: NIL | AB7: NIL | AC7: NIL | AD7: NIL | AE7: NIL
A8: 7 | B8: BOH | C8: 46085 | D8: 46112 | E8: 26.3 Sprint 4 Stretch | F8: Charles | G8: 52203 | H8: Mosaic BOH - Refactor asset handling for Vega UI | I8: Story Completed | J8: 3 | K8: 3 | L8: 12 | M8: 46085 | O8: NA | P8: NA | Q8: NA | T8: https://dev.azure.com/heartlandschools/Mosaic/_git/BOH/pullrequest/47618 | U8: 46087 | V8: 46087 | W8: NIL | X8: NIL | Y8: Em | Z8: 46087 | AA8: NIL | AB8: NIL | AC8: NIL | AD8: NIL | AE8: Meets Expectation

Sheet 26.3 Sprint 4 - Defect Tracker
A1: Sprint # | B1: Story/Defect ID | C1: Parent Story | D1: Developer | E1: Issue Type | F1: Issue Description | G1: Priority | H1: Defect Source | I1: Type | J1: Status | K1: Estimated(sp) | L1: Actual(sp) | M1: Actual Hours Worklog | N1: Root Cause Category | O1: Comments
A2: 26.3 Sprint 4 Stretch | B2: 26894 | D2: Mohamed | E2: Defect | F2: Mosaic BOH - Vendor Order Template - "Gold Star Food" having issue when Exporting in Vendor Bulk Approal | G2: Minor | H2: Manual | I2: External | J2: Defect Fixed | K2: 1 | L2: =M2/4 -> 1.25 | M2: 5 | N2: Existing_Issues | O2: Existing Issue, defect was not identified in the previous test cycles
A3: 26.3 Sprint 4 Stretch | B3: 26932 | D3: Charles | E3: Defect | F3: Mosaic BOH - AI - Scan Inventory Worksheets pulling from the wrong column | G3: Significant | H3: Manual | I3: External | J3: Defect Fixed | K3: 1 | L3: 1 | M3: 3 | N3: Enhancements | O3: AI Prompt Improvement
A4: 26.3 Sprint 4 | B4: 26667 | D4: Mohamed | E4: Defect | F4: Mosaic BoH - Multiple - Weekly Check report different than Weekly Certification Report | G4: Significant | H4: Manual | I4: External | J4: Defect Fixed | K4: 1 | L4: =M4/4 -> 0.75 | M4: 3 | N4: Existing_Issues | O4: Existing Issue, defect was not identified in the previous test cycles
A5: 26.3 Sprint 4 | B5: 26931 | D5: Mohamed | E5: Defect | F5: Mosaic BOH - Regression - Menus - Adding menu items can't be done as fast as it used to be | G5: Minor | H5: Manual | I5: External | J5: Defect Fixed | K5: NA | L5: NA | M5: NA | N5: Existing_Issues | O5: Existing Issue, defect was not identified in the previous test cycles
A6: 26.3 Sprint 4 | B6: 27013 | D6: Mohamed | E6: Defect | F6: Mosaic BOH - Regression - Reports - Recipes - Recipe List By Menu - You can select Site Group and Site dropdowns | G6: Minor | H6: Manual | I6: External | J6: Defect Fixed | K6: NA | L6: NA | M6: NA | N6: Existing_Issues | O6: Existing Issue, defect was not identified in the previous test cycles
A7: 26.3 Sprint 4 | B7: 27037 | D7: Mohamed | E7: Defect | F7: Mosaic BOH - Regression - Production Records - Header and Footer are showing over the menu items | G7: Significant | H7: Manual | I7: External | J7: Defect Fixed | K7: NA | L7: NA | M7: NA | N7: Existing_Issues | O7: Existing Issue, defect was not identified in the previous test cycles
A8: 26.3 Sprint 4 | B8: 27029 | D8: Charles | E8: Defect | F8: Mosaic BOH - Regression - Bidding - Analysis - Icon for legend is not showing correctly | G8: Minor | H8: Manual | I8: External | J8: Defect Fixed | K8: NA | L8: NA | M8: NA | N8: Development | O8: CSS issue from the kaleida team
A9: 26.3 Sprint 4 | B9: 27082 | D9: Charles | E9: Defect | F9: Mosaic BOH - Regression - Menus - Maintenance - Copy screen - dropdown not showing full scroll bar | G9: Minor | H9: Manual | I9: External | J9: Defect Fixed | K9: NA | L9: NA | M9: NA | N9: Development | O9: The Kendo update resulted in a few minor UI issues, with no functional impact. We completed full regression testing as planned, addressed some design and alignment issues, and found nothing critical.
A10: 26.3 Sprint 4 | B10: 27054 | D10: Charles | E10: Defect | F10: Mosaic BOH - Regression - Inv - Physical Count - Validation highlight not showing on Site and Site Group dropdowns | G10: Minor | H10: Manual | I10: External | J10: Defect Fixed | K10: NA | L10: NA | M10: NA | N10: Development | O10: The Kendo update resulted in a few minor UI issues, with no functional impact. We completed full regression testing as planned, addressed some design and alignment issues, and found nothing critical.
A11: 26.3 Sprint 4 | B11: 27062 | D11: Charles | E11: Defect | F11: Mosaic BOH - Regression - Setup - Allergens - Search filters don't stay when you open and then cancel an allergen | G11: Minor | H11: Manual | I11: External | J11: Defect Fixed | K11: NA | L11: NA | M11: NA | N11: Development | O11: CSS issue from the kaleida team
A12: 26.3 Sprint 4 | B12: 27044 | D12: Charles | E12: Defect | F12: Mosaic BOH - Regression - Setup - Security Groups - If you have Add Only rights to menus you should not be able to change values | G12: Minor | H12: Manual | I12: External | J12: Defect Fixed | K12: NA | L12: NA | M12: NA | N12: Existing_Issues | O12: Existing Issue, defect was not identified in the previous test cycles
A13: 26.3 Sprint 4 | B13: 27043 | D13: Charles | E13: Defect | F13: Mosaic BOH - Regression - Setup - Security Groups - WH Hot Shot Transfers - Clicking Cancel on Edit Fields edit page deselects other check boxes | G13: Minor | H13: Manual | I13: External | J13: Defect Fixed | K13: NA | L13: NA | M13: NA | N13: Existing_Issues | O13: The Kendo update resulted in a few minor UI issues, with no functional impact. We completed full regression testing as planned, addressed some design and alignment issues, and found nothing critical.
A14: 26.3 Sprint 4 | B14: 27039 | D14: Charles | E14: Defect | F14: Mosaic BOH - Regression - Setup - Storage Locations - Enter on keyboard doesn't initiate search | G14: Minor | H14: Manual | I14: External | J14: Defect Fixed | K14: NA | L14: NA | M14: NA | N14: Development | O14: The Kendo update resulted in a few minor UI issues, with no functional impact. We completed full regression testing as planned, addressed some design and alignment issues, and found nothing critical.
A15: 26.3 Sprint 4 | B15: 27040 | D15: Charles | E15: Defect | F15: Mosaic BOH - Regression - Setup - Warehouse Delivery routes - Search - Active column sorting doesn't work | G15: Minor | H15: Manual | I15: External | J15: Defect Fixed | K15: NA | L15: NA | M15: NA | N15: Development | O15: Existing Issue, defect was not identified in the previous test cycles
A16: 26.3 Sprint 4 | B16: 27005 | D16: Charles | E16: Defect | F16: Mosaic BOH - Regression - Vendor Order Bulk Approval - Sending Via SFTP - Failure not shown in popup. Is in the Log though | G16: Minor | H16: Manual | I16: External | J16: Defect Fixed | K16: NA | L16: NA | M16: NA | N16: Development | O16: The Kendo update resulted in a few minor UI issues, with no functional impact. We completed full regression testing as planned, addressed some design and alignment issues, and found nothing critical.
A17: 26.3 Sprint 4 | B17: 27018 | D17: Charles | E17: Defect | F17: Mosaic BOH - Regression - Bidding - User with View Only permissions can add items to a bid (Not Save though) | G17: Minor | H17: Manual | I17: External | J17: Defect Fixed | K17: NA | L17: NA | M17: NA | O17: Existing Issue, defect was not identified in the previous test cycles
A18: 26.3 Sprint 4 | B18: 27020 | D18: Charles | E18: Defect | F18: Mosaic BOH - Setup - Vendors - Order Export Template dropdown - Need to show full description or offer tooltip | G18: Minor | H18: Manual | I18: External | J18: Defect Fixed | K18: NA | L18: NA | M18: NA | N18: Development | O18: The Kendo update resulted in a few minor UI issues, with no functional impact. We completed full regression testing as planned, addressed some design and alignment issues, and found nothing critical.
A19: 26.3 Sprint 4 | B19: 27025 | D19: Charles | E19: Defect | F19: Mosaic BOH - Ingredients - Validation not showing on dropdowns. | G19: Minor | H19: Manual | I19: External | J19: Defect Fixed | K19: NA | L19: NA | M19: NA | N19: Development | O19: The Kendo update resulted in a few minor UI issues, with no functional impact. We completed full regression testing as planned, addressed some design and alignment issues, and found nothing critical.
A20: 26.3 Sprint 4 | B20: 26997 | D20: Charles | E20: Defect | F20: Mosaic BOH - Mealviewer Tab - Need to expand Site dropdown | G20: Minor | H20: Manual | I20: External | J20: Defect Fixed | K20: NA | L20: NA | M20: NA | N20: Development | O20: The Kendo update resulted in a few minor UI issues, with no functional impact. We completed full regression testing as planned, addressed some design and alignment issues, and found nothing critical.
A21: 26.3 Sprint 4 | B21: 26981 | D21: Charles | E21: Defect | F21: Mosaic BOH - Regression - Bidding - Responses - Bid Response # field not searching correctly | G21: Minor | H21: Manual | I21: External | J21: Defect Fixed | K21: NA | L21: NA | M21: NA | N21: Development | O21: The Kendo update resulted in a few minor UI issues, with no functional impact. We completed full regression testing as planned, addressed some design and alignment issues, and found nothing critical.
A22: 26.3 Sprint 4 | B22: 26929 | D22: Charles | E22: Defect | F22: Mosaic BOH - Regression - Reports - Weekly Requirement - Two issues | G22: Minor | H22: Manual | I22: External | J22: Defect Fixed | K22: NA | L22: NA | M22: NA | N22: Development | O22: The Kendo update resulted in a few minor UI issues, with no functional impact. We completed full regression testing as planned, addressed some design and alignment issues, and found nothing critical.
A23: 26.3 Sprint 4 | B23: 26934 | D23: Charles | E23: Defect | F23: Mosaic BOH - Recipes - Maintenance - Report tab - We should show the full labels in the dropdown | G23: Minor | H23: Manual | I23: External | J23: Defect Fixed | K23: NA | L23: NA | M23: NA | N23: Development | O23: The Kendo update resulted in a few minor UI issues, with no functional impact. We completed full regression testing as planned, addressed some design and alignment issues, and found nothing critical.
A24: 26.3 Sprint 4 | B24: 26943 | D24: Charles | E24: Defect | F24: Mosaic BOH - Menus - Maintenance and Cycles - Have to scroll down to get to buttons. | G24: Minor | H24: Manual | I24: External | J24: Defect Fixed | K24: NA | L24: NA | M24: NA | N24: Development | O24: The Kendo update resulted in a few minor UI issues, with no functional impact. We completed full regression testing as planned, addressed some design and alignment issues, and found nothing critical.
A25: 26.3 Sprint 4 | B25: 26969 | D25: Charles | E25: Defect | F25: Mosaic BOH - Regression - Recipes - Maintenance - Print Report - Vitamin C label is cut off | G25: Minor | H25: Manual | I25: External | J25: Defect Fixed | K25: NA | L25: NA | M25: NA | N25: Development | O25: The Kendo update resulted in a few minor UI issues, with no functional impact. We completed full regression testing as planned, addressed some design and alignment issues, and found nothing critical.
A26: 26.3 Sprint 4 | B26: 26970 | D26: Charles | E26: Defect | F26: Mosaic BOH - Regression - Recipes - Maintenance - If screen resized large portions of screen are shifted to the right | G26: Minor | H26: Manual | I26: External | J26: Defect Fixed | K26: NA | L26: NA | M26: NA | N26: Development | O26: The Kendo update resulted in a few minor UI issues, with no functional impact. We completed full regression testing as planned, addressed some design and alignment issues, and found nothing critical.

Sheet 26.3 Sprint 3-Status
A1: S.No | B1: Application Name | C1: Sprint Start Date | D1: Sprint End Date | E1: Sprint | F1: Developer | G1: Story ID/Defect ID | H1: Description | I1: Status | J1: Estimated(sp) | K1: Actual(sp) | L1: Actual Hours Worklog | M1: Dev Start Date | N1: Dev End Date | O1: Unit testing | P1: Peer Tested By | Q1: Peer Tested Comments, if any | R1: Peer Reviewed By | S1: Peer Code Review Comments, if any | T1: PR Number/Link | U1: PR Created Date | V1: PR Approved Date | W1: Reviewer 1 | X1: Code Review Comments, if any | Y1: Reviewer 2 | Z1: Approved Date | AA1: Code Review Comments, if any2 | AB1: Internal PO -POV Comments | AC1: Client PO -POV Comments | AD1: Comments | AE1: Does this story meet expectations?
A2: 1 | B2: BOH | C2: 46071 | D2: 46084 | E2: 26.3 Sprint 3 | F2: Mohamed | G2: 51614 | H2: Mosaic BOH - USDA - Whole Milk - Weekly Nutrients Check (6) | I2: Story Completed | J2: 5 | K2: =L2/4 -> 4 | L2: 16 | M2: 46071 | N2: 46076 | O2: Done | P2: Suresh | Q2: Nil | R2: Kavitha | S2: Nil | T2: https://dev.azure.com/heartlandschools/Mosaic/_git/BOH/pullrequest/47480 | U2: 46078 | V2: 46078 | W2: Charles | X2: Nil | Y2: NA | Z2: NA | AA2: NA | AB2: Nil | AC2: Nil | AD2: Nil | AE2: Meets Expectation
A3: 2 | B3: BOH | C3: 46071 | D3: 46084 | E3: 26.3 Sprint 3 | F3: Mohamed | G3: 51616 | H3: Mosaic BOH - USDA - Whole Milk - Nutrients Breakdown Reports Updates (7) | I3: Story Completed | J3: 8 | K3: =L3/4 -> 5.25 | L3: 21 | M3: 46077 | N3: 46078 | O3: Done | P3: Suresh | Q3: Nil | R3: Kavitha | S3: Nil | T3: https://dev.azure.com/heartlandschools/Mosaic/_git/BOH/pullrequest/47480 | U3: 46078 | V3: 46078 | W3: Charles | X3: Nil | Y3: NA | Z3: NA | AA3: NA | AB3: Nil | AC3: Nil | AD3: Nil | AE3: Meets Expectation
A4: 3 | B4: BOH | C4: 46071 | D4: 46084 | E4: 26.3 Sprint 3 | F4: Kavitha | G4: 51612 | H4: Mosaic BOH - USDA - Whole Milk - Menu Screen Updates (1) | I4: Story Completed | J4: 5 | K4: =L4/4 -> 5.25 | L4: 21 | M4: 46071 | N4: 46078 | O4: Done | P4: Suresh | Q4: Nil | R4: Mohamed | S4: Nil | T4: https://dev.azure.com/heartlandschools/Mosaic/_git/BOH/pullrequest/47480 | U4: 46078 | V4: 46078 | W4: Charles | X4: Nil | Y4: NA | Z4: NA | AA4: NA | AB4: Nil | AC4: Nil | AD4: Nil | AE4: Meets Expectation
A5: 4 | B5: BOH | C5: 46071 | D5: 46084 | E5: 26.3 Sprint 3 | F5: Kavitha | G5: 51640 | H5: Mosaic BOH - USDA - Whole Milk - Cycle Menu Screen Updates (2) | I5: Story Completed | J5: 5 | K5: =L5/4 -> 3 | L5: 12 | M5: 46076 | N5: 46078 | O5: Done | P5: Suresh | Q5: Nil | R5: Mohamed | S5: Nil | T5: https://dev.azure.com/heartlandschools/Mosaic/_git/BOH/pullrequest/47480 | U5: 46078 | V5: 46078 | W5: Charles | X5: Nil | Y5: NA | Z5: NA | AA5: NA | AB5: Nil | AC5: Nil | AD5: Nil | AE5: Meets Expectation
A6: 5 | B6: BOH | C6: 46071 | D6: 46084 | E6: 26.3 Sprint 3 | F6: Charles | G6: 51644 | H6: Mosaic BOH - USDA - Whole Milk - Menu Spreadsheets (8) | I6: Story Completed | J6: 5 | K6: =L6/4 -> 5.5 | L6: 22 | M6: 46072 | N6: 46078 | O6: Done | P6: Suresh | Q6: Nil | R6: Mohamed | S6: Nil | T6: https://dev.azure.com/heartlandschools/Mosaic/_git/BOH/pullrequest/47480 | U6: 46078 | V6: 46078 | W6: Charles | X6: Nil | Y6: NA | Z6: NA | AA6: NA | AB6: Nil | AC6: Nil | AD6: Nil | AE6: Meets Expectation
A7: 6 | B7: BOH | C7: 46071 | D7: 46084 | E7: 26.3 Sprint 3 | F7: Mohamed | G7: 50635 | H7: Mosaic BOH - Add the Last modified details in the Production Record Report (Athens City) | I7: Story Completed | J7: 3 | K7: =L7/4 -> 5 | L7: 20 | M7: 46071 | N7: 46080 | O7: Done | P7: Suresh | Q7: Suggestion - Existing alignment issue and its fixed. Existing production issue - Menu Name title alignment Issue - Shenba get confirmation from Craig and then create new defect. | R7: Kavitha | S7: Nil | T7: https://dev.azure.com/heartlandschools/Mosaic/_git/BOH/pullrequest/47533 | U7: 46080 | V7: 46080 | W7: Charles | X7: Nil | Y7: NA | Z7: NA | AA7: NA | AB7: Date Format needs to be updated | AC7: Nil | AD7: Worked on Change Request after moved to Testing | AE7: Meets Expectation
A8: 7 | B8: BOH | C8: 46071 | D8: 46084 | E8: 26.3 Sprint 3 Stretch | F8: Charles | G8: 51419 | H8: Mosaic BOH(Tech Debt) - Update Report schema to the latest version - Recipe | I8: Story Completed | J8: 3 | K8: 5 | L8: 20 | M8: 46071 | N8: 46079 | O8: Done | P8: Suresh | Q8: Nil | R8: Mohamed | S8: Nil | T8: https://dev.azure.com/heartlandschools/Mosaic/_git/BOH/pullrequest/47424 | U8: 46080 | V8: 46080 | W8: Charles | X8: Nil | Y8: Ying | Z8: NA | AA8: NA | AB8: NA | AC8: Nil | AD8: All effort spent on deploying to QA and resolving the QA server issues was logged under the same story, even though the deployment to QA was not originally estimated as part of that story. | AE8: Exceeds Expectation

Sheet 26.3 Sprint 3 - Defect Tracker
A1: Sprint # | B1: Story/Defect ID | C1: Parent Story | D1: Developer | E1: Issue Type | F1: Issue Description | G1: Priority | H1: Defect Source | I1: Type | J1: Status | K1: Estimated(sp) | L1: Actual(sp) | M1: Actual Hours Worklog | N1: Root Cause Category | O1: Comments
A2: 26.3 Sprint 3 Stretch | B2: 26876 | D2: Charles | F2: Mosaic BOH - VOEF Export Field Name fixing | G2: Minor | H2: Manual | I2: Internal | J2: Defect Fixed | K2: 1 | L2: 1 | M2: 3 | N2: Existing_Issues | O2: Data Issue in Prod env

Sheet 26.3 Sprint 2-Status
A1: S.No | B1: Application Name | C1: Sprint Start Date | D1: Sprint End Date | E1: Sprint | F1: Developer | G1: Story ID/Defect ID | H1: Description | I1: Status | J1: Estimated(sp) | K1: Actual(sp) | L1: Actual Hours Worklog | M1: Dev Start Date | N1: Dev End Date | O1: Unit testing | P1: Peer Tested By | Q1: Peer Tested Comments, if any | R1: Peer Reviewed By | S1: Peer Code Review Comments, if any | T1: PR Number/Link | U1: PR Created Date | V1: PR Approved Date | W1: Reviewer 1 | X1: Code Review Comments, if any | Y1: Reviewer 2 | Z1: Approved Date | AA1: Code Review Comments, if any2 | AB1: Internal PO -POV Comments | AC1: Client PO -POV Comments | AD1: Comments | AE1: Does this story meet expectations?
A2: 1 | B2: BOH | C2: 46057 | D2: 46070 | E2: 26.3 Sprint 2 | F2: Mohamed | G2: 51641 | H2: Mosaic BOH - USDA - Whole Milk - Weekly Requirements Check | I2: Story Completed | J2: 3 | K2: =L2/4 -> 2.5 | L2: 10 | M2: 46057 | N2: 46059 | O2: Done | P2: Suresh | Q2: Nil | R2: Kavitha | S2: Nil | T2: https://dev.azure.com/heartlandschools/Mosaic/_git/BOH/pullrequest/47190 | U2: 46065 | V2: 46066 | W2: Charles | X2: Nil | Y2: Nil | Z2: Nil | AA2: Nil | AB2: Nil | AC2: Nil | AD2: Nil | AE2: Meets Expectation
A3: 2 | B3: BOH | C3: 46057 | D3: 46070 | E3: 26.3 Sprint 2 | F3: Mohamed | G3: 51642 | H3: Mosaic BOH - USDA - Whole Milk - Weekly Requirements Report | I3: Story Completed | J3: 5 | K3: =L3/4 -> 4 | L3: 16 | M3: 46062 | N3: 46065 | O3: Done | P3: Suresh | Q3: Nil | R3: Kavitha | S3: Nil | T3: https://dev.azure.com/heartlandschools/Mosaic/_git/BOH/pullrequest/47190 | U3: 46065 | V3: 46066 | W3: Charles | X3: Nil | Y3: Nil | Z3: Nil | AA3: Nil | AB3: Nil | AC3: Nil | AD3: Nil | AE3: Meets Expectation
A4: 3 | B4: BOH | C4: 46057 | D4: 46070 | E4: 26.3 Sprint 2 | F4: Kavitha | G4: 51643 | H4: Mosaic BOH - USDA - Whole Milk - Menu - Reimburse Meal Groups(3) | I4: Story Completed | J4: 3 | K4: =L4/4 -> 2.5 | L4: 10 | M4: 46058 | N4: 46062 | O4: Done | P4: Suresh | Q4: Nil | R4: Mohamed | S4: Nil | T4: https://dev.azure.com/heartlandschools/Mosaic/_git/BOH/pullrequest/47145 | U4: 46062 | V4: 46063 | W4: Charles | X4: Nil | Y4: NA | Z4: NA | AA4: NA | AB4: Nil | AC4: Nil | AD4: Nil | AE4: Meets Expectation
A5: 4 | B5: BOH | C5: 46057 | D5: 46070 | E5: 26.3 Sprint 2 | F5: Charles | G5: 51778 | H5: Mosaic BOH - Kendo Update Adjustments | I5: Story Completed | J5: 8 | K5: =L5/4 -> 6.5 | L5: 26 | M5: 46056 | N5: 46069 | O5: Done | P5: Suresh | Q5: Nil | R5: Mohamed | S5: Nil | T5: https://dev.azure.com/heartlandschools/Mosaic/_git/BOH/pullrequest/47081 | U5: 46069 | V5: 46069 | W5: Richard | X5: Nil | Y5: NA | Z5: NA | AA5: NA | AB5: Nil | AC5: Nil | AD5: Nil | AE5: Meets Expectation
A6: 5 | B6: BOH | C6: 46057 | D6: 46070 | E6: 26.3 Sprint 2 Stretch | F6: Suresh | G6: 51784 | H6: Mosaic BOH - 26.3 Automation -Fixing Failed AI & Other Automation Testcases | I6: Story Completed | J6: 13 | K6: =L6/4 -> 12.5 | L6: 50 | M6: 46057 | N6: 46070 | O6: NA | P6: NA | Q6: Nil | R6: Charles | S6: CleanUp commented codes | T6: PR1 : https://dev.azure.com/heartlandschools/Mosaic/_git/BOH/pullrequest/47193 PR2: https://dev.azure.com/heartlandschools/Mosaic/_git/BOH/pullrequest/47244 | U6: 46064 | V6: 46064 | W6: Charles | X6: Nil | Y6: NA | Z6: NA | AA6: NA | AB6: Nil | AC6: Nil | AD6: FIxed Automation Pipeline issues due to Kendo update TestResults : https://ibb.co/LdhpWnW3 | AE6: Meets Expectation
A7: 7 | B7: BOH | C7: 46057 | D7: 46070 | E7: 26.3 Sprint 2 Stretch | F7: Charles | G7: 51903 | H7: Mosaic BOH - Performance - Query analysis | I7: Story Completed | J7: 1 | K7: =L7/4 -> 0.75 | L7: 3 | M7: 46063 | N7: 46064 | O7: NA | P7: NA | Q7: NA | R7: NA | S7: NA | T7: NA | U7: NA | V7: NA | W7: NA | X7: NA | Y7: NA | Z7: NA | AA7: NA | AB7: NA | AC7: NA | AD7: Research Stories, finding updated in the comment section | AE7: Meets Expectation
A8: 9 | B8: BOH | C8: 46057 | D8: 46070 | E8: 26.3 Sprint 2 Stretch | F8: Kavitha | G8: 51961 | H8: Mosaic BOH - Add Milk Types in the Reim.Meal Groups for HHFKA Lunch menus | I8: Story Completed | J8: 2 | K8: =L8/4 -> 1.75 | L8: 7 | M8: 46069 | N8: 46069 | O8: Done | P8: Suresh | Q8: Nil | R8: Mohammed | S8: Nil | T8: https://dev.azure.com/heartlandschools/Mosaic/_git/BOH/pullrequest/47268 | U8: 46069 | V8: 46069 | W8: Charles | X8: Nil | Y8: NA | Z8: NA | AA8: NA | AB8: Nil | AC8: Nil | AD8: Nil | AE8: Meets Expectation

Sheet 26.3 Sprint 2 - Defect Tracker
A1: Sprint # | B1: Story/Defect ID | C1: Parent Story | D1: Developer | E1: Issue Type | F1: Issue Description | G1: Priority | H1: Defect Source | I1: Type | J1: Status | K1: Estimated(sp) | L1: Actual(sp) | M1: Actual Hours Worklog | N1: Root Cause Category | O1: Comments
A2: 26.3 Sprint 2 | B2: 26688 | D2: Kavitha | E2: Defect | F2: Mosaic BoH - Multiple districts - issues with commodity items on price lists | G2: Minor | H2: Manual | I2: External | J2: Defect Fixed | K2: 3 | L2: =M2/4 -> 2.5 | M2: 10 | N2: Existing_Issues | O2: Existing Issue, missed the field while updating data on grid
A3: 26.3 Sprint 2 | B3: 26709 | D3: Mohamed | E3: Defect | F3: [WAVE] Mosaic BOH - Inventory Transfer Search & Replace Search is not working properly | G3: Minor | H3: Manual | I3: External | J3: Defect Fixed | K3: 2 | L3: =M3/4 -> 1.5 | M3: 6 | N3: Existing_Issues | O3: Existing UI Issue, defect was not identified in the previous test cycles
A4: 26.3 Sprint 2 | B4: 26723 | D4: Mohamed | E4: Defect | F4: Mosaic BOH - Ingredient Export Script Column Headers Wrong | G4: Minor | H4: Manual | I4: External | J4: Defect Fixed | K4: 1 | L4: =M4/4 -> 0.5 | M4: 2 | N4: Existing_Issues | O4: DB script file shared to Gary.
A5: 26.3 Sprint 2 Stretch | B5: 26740 | D5: Mohamed | E5: Defect | F5: Mosaic BOH - Vendor Orders Bulk Approval - Alignment issue | G5: Minor | H5: Manual | I5: External | J5: Defect Fixed | K5: 1 | L5: =M5/4 -> 0.5 | M5: 2 | N5: Existing_Issues | O5: Existing UI Issue, Vega component updates breaking the exisitng UI.
A6: 26.3 Sprint 2 Stretch | B6: 26752 | D6: Mohamed | E6: Defect | F6: Mosaic BOH - UI Alignment issues | G6: Minor | H6: Manual | I6: External | J6: Defect Fixed | K6: 1 | L6: =M6/4 -> 1.5 | M6: 6 | N6: Existing_Issues | O6: Existing UI Issue, Vega component updates breaking the exisitng UI.
A7: 26.3 Sprint 2 Stretch | B7: 26793 | D7: Mohamed | E7: Defect | F7: Mosaic BOH - Menus - Maint. and Cycle Menus - Recipes Tab - Weekly Requirement not honoring the correct date | G7: Minor | H7: Manual | I7: External | J7: Defect Fixed | K7: 1 | L7: =M7/4 -> 0.5 | M7: 2 | N7: Existing_Issues | O7: Existing Issue, missed to handle null exception
A8: 26.3 Sprint 2 Stretch | B8: 26580 | D8: Charles | E8: Defect | F8: Mosaic BOH - Setup - Changing user's site group causes a popup when they log in that doesn't go away | G8: Minor | H8: Manual | I8: External | J8: Defect Fixed | K8: 5 | L8: 3 | M8: 12 | N8: Existing_Issues | O8: Impacted durnig Kaleida changes on login screen

Sheet 26.3 Sprint 1-Status
A1: S.No | B1: Application Name | C1: Sprint Start Date | D1: Sprint End Date | E1: Sprint | F1: Developer | G1: Story ID/Defect ID | H1: Description | I1: Status | J1: Estimated(sp) | K1: Actual(sp) | L1: Actual Hours Worklog | M1: Dev Start Date | N1: Dev End Date | O1: Unit testing | P1: Peer Tested By | Q1: Peer Tested Comments, if any | R1: Peer Reviewed By | S1: Peer Code Review Comments, if any | T1: PR Number/Link | U1: PR Created Date | V1: PR Approved Date | W1: Reviewer 1 | X1: Code Review Comments, if any | Y1: Reviewer 2 | Z1: Approved Date | AA1: Code Review Comments, if any2 | AB1: Internal PO -POV Comments | AC1: Client PO -POV Comments | AD1: Comments | AE1: Does this story meet expectations?
A2: 1 | B2: BOH | C2: 46043 | D2: 46056 | E2: 26.3 Sprint 1 | F2: Mohamed | G2: 51593 | H2: Mosaic BOH - Reports - Production Records - Substitutions with Prod Specs should show the ingredient under recipe | I2: Story Completed | J2: 8 | K2: =L2/4 -> 6 | L2: 24 | M2: 46043 | N2: 46045 | O2: Done | P2: Suresh | Q2: Nil | R2: Kavitha | S2: Nil | T2: https://dev.azure.com/heartlandschools/Mosaic/_git/BOH/pullrequest/46821 | U2: 46042 | V2: 46043 | W2: Charles | X2: Nil | Y2: NA | Z2: NA | AA2: NA | AB2: Nil | AC2: Nil | AD2: Nil | AE2: Meets Expectation
A3: 2 | B3: BOH | C3: 46043 | D3: 46056 | E3: 26.3 Sprint 1 | F3: Charles | G3: 51424 | H3: Mosaic BOH(Tech Debt) - Kendo Update | I3: Story Completed | J3: 13 | K3: =L3/4 -> 9.5 | L3: 38 | M3: 46043 | N3: 46052 | O3: Done | P3: Suresh | Q3: Nil | R3: Mohamed | S3: Nil | T3: https://dev.azure.com/heartlandschools/Mosaic/_git/BOH/pullrequest/46800 | U3: 46052 | V3: 46052 | W3: Richard | X3: Nil | Y3: NA | Z3: NA | AA3: NA | AB3: Nil | AC3: Nil | AD3: Nil | AE3: Exceeds Expectation
A4: 3 | B4: BOH | C4: 46043 | D4: 46056 | E4: 26.3 Sprint 1Stretch | F4: Kavitha | G4: 51331 | H4: Mosaic BOH - Contribution Report - Add ability to run for non HHFKA menus (Athens City) | I4: Story Completed | J4: 3 | K4: =L4/4 -> 2.5 | L4: 10 | M4: 46043 | N4: 46044 | O4: Done | P4: Suresh | Q4: Nil | R4: Mohamed | S4: Nil | T4: https://dev.azure.com/heartlandschools/Mosaic/_git/BOH/pullrequest/46793 | U4: 46044 | V4: 46045 | W4: Charles | X4: Nil | Y4: NA | Z4: NA | AA4: NA | AB4: Nil | AC4: Nil | AD4: Nil | AE4: Meets Expectation
A5: 4 | B5: BOH | C5: 46043 | D5: 46056 | E5: 26.3 Sprint 1 Stretch | F5: Suresh | G5: 51598 | H5: Mosaic BOH - 26.3 Automation -Fixing Failed AI & Other Automation Testcases | I5: Story Completed | J5: 13 | K5: =L5/4 -> 12 | L5: 48 | M5: 46043 | N5: 46056 | O5: Nil | P5: Nil | Q5: Nil | R5: Charles | S5: Nil | T5: https://dev.azure.com/heartlandschools/Mosaic/_git/BOH/pullrequest/47039 | U5: 46056 | V5: 46056 | W5: Charles | X5: Nil | Y5: NA | Z5: NA | AA5: NA | AB5: Nil | AC5: Nil | AD5: Fixed few AI Automation Testcase & added 4 setup tests | AE5: Meets Expectation

Sheet 26.3 Sprint 1 - Defect Tracker
A1: Sprint # | B1: Story/Defect ID | C1: Parent Story | D1: Developer | E1: Issue Type | F1: Issue Description | G1: Priority | H1: Defect Source | I1: Type | J1: Status | K1: Estimated(sp) | L1: Actual(sp) | M1: Actual Hours Worklog | N1: Root Cause Category | O1: Comments
A2: 26.3 Sprint 1 | B2: 26535 | D2: Kavitha | E2: Defect | F2: Mosaic BOH - Menus - Cycle Menus - RMG - Click Edit causes server error | G2: Minor | H2: Manual | I2: External | J2: Defect Fixed | K2: 3 | L2: =M2/4 -> 2.75 | M2: 11 | N2: Existing_Issues | O2: Vega component breadcrumb issue causes server error .Proper testing may prevent this
A3: 26.3 Sprint 1 | B3: 26652 | D3: Charles | E3: Defect | F3: Mosaic BoH - Multiple - Shopping List not consolidating products after update | G3: Minor | H3: Manual | I3: External | J3: Defect Fixed | K3: 3 | L3: 3 | M3: 12 | N3: Existing_Issues | O3: Code Issue broke few scenario's in other type of report. Proper testing may prevent this

Sheet 26.1 Sprint 3-Status
A1: S.No | B1: Application Name | C1: Sprint Start Date | D1: Sprint End Date | E1: Sprint | F1: Developer | G1: Story ID/Defect ID | H1: Description | I1: Status | J1: Estimated(sp) | K1: Actual(sp) | L1: Actual Hours Worklog | M1: Dev Start Date | N1: Dev End Date | O1: Unit testing | P1: Peer Tested By | Q1: Peer Tested Comments, if any | R1: Peer Reviewed By | S1: Peer Code Review Comments, if any | T1: PR Number/Link | U1: PR Created Date | V1: PR Approved Date | W1: Reviewer 1 | X1: Code Review Comments, if any | Y1: Reviewer 2 | Z1: Approved Date | AA1: Code Review Comments, if any2 | AB1: Internal PO -POV Comments | AC1: Client PO -POV Comments | AD1: Comments | AE1: Does this story meet expectations?
A2: 1 | B2: BOH | C2: 46029 | D2: 46042 | E2: 26.1 Sprint 3 | F2: Team | G2: 50796 | H2: Mosaic BOH - 26.1 Regression - Reports | I2: Story Completed | J2: 8 | K2: 23.75 | L2: 95 | M2: 46029 | N2: 46031 | O2: Nil | P2: Nil | Q2: Nil | R2: Nil | S2: Nil | T2: Nil | U2: Nil | V2: Nil | W2: Craig | X2: Nil | Y2: Nil | Z2: Nil | AA2: Nil | AB2: Nil | AC2: Nil | AD2: It's regression story and actual working hours including regression defects
A3: 2 | B3: BOH | C3: 46029 | D3: 46042 | E3: 26.1 Sprint 3 | F3: Team | G3: 50795 | H3: Mosaic BOH - 26.1 Regression - Menus/Cycle Menus | I3: Story Completed | J3: 5 | K3: 30 | L3: 120 | M3: 46029 | N3: 46035 | O3: Nil | P3: Nil | Q3: Nil | R3: Nil | S3: Nil | T3: Nil | U3: Nil | V3: Nil | W3: Craig | X3: Nil | Y3: Nil | Z3: Nil | AA3: Nil | AB3: Nil | AC3: Nil | AD3: It's regression story and actual working hours including regression defects
A4: 3 | B4: BOH | C4: 46029 | D4: 46042 | E4: 26.1 Sprint 3 | F4: Team | G4: 50797 | H4: Mosaic BOH - 26.1 Regression - Setup | I4: Story Completed | J4: 3 | K4: 5.25 | L4: 28 | M4: 46035 | N4: 46036 | O4: Nil | P4: Nil | Q4: Nil | R4: Nil | S4: Nil | T4: Nil | U4: Nil | V4: Nil | W4: Craig | X4: Nil | Y4: Nil | Z4: Nil | AA4: Nil | AB4: Nil | AC4: Nil | AD4: It's regression story and actual working hours including regression defects
A5: 4 | B5: BOH | C5: 46029 | D5: 46042 | E5: 26.1 Sprint 3 | F5: Team | G5: 51262 | H5: Mosaic BOH - 26.1 Regression - AI | I5: Story Completed | J5: 5 | K5: 1.25 | L5: 5 | M5: 46038 | N5: 46038 | O5: Nil | P5: Nil | Q5: Nil | R5: Nil | S5: Nil | T5: Nil | U5: Nil | V5: Nil | W5: Craig | X5: Nil | Y5: Nil | Z5: Nil | AA5: Nil | AB5: Nil | AC5: Nil | AD5: It's regression story and actual working hours including regression defects
A6: 5 | B6: BOH | C6: 46029 | D6: 46042 | E6: 26.1 Sprint 3 | F6: Mohamed | G6: 42586 | H6: Mosaic BOH - ER - Product List Report - Add a new filter for Notes - Has Notes | I6: Story Completed | J6: 1 | K6: 3 | L6: 12 | M6: 46035 | N6: 46038 | O6: Yes | P6: Kavitha | Q6: Nil | R6: Kavitha | S6: Nil | T6: https://dev.azure.com/heartlandschools/Mosaic/_git/BOH/pullrequest/46696 | U6: 46038 | V6: 46038 | W6: Charles | X6: Nil | Y6: Nil | Z6: Nil | AA6: Nil | AB6: 1. Display Type is not properly aligned in the UI 2. Switch the Has Notes, Needs attention in the header as per the column position 3. Alignment not proper in the report | AC6: Nil | AD6: This story worked by Praveen, Initially we estimate this story only for review and tesing, found few changes in review, so that it took additional 2SP to finish this story. | AE6: Meets Expectation
A7: 6 | B7: BOH | C7: 46029 | D7: 46042 | E7: 26.1 Sprint 3 Stretch | F7: Suresh | G7: 51433 | H7: Mosaic BOH - 26.1 Automation Regression - Fixing Failed AI & Other Testcases | I7: Story Completed | J7: 13 | K7: 4.25 | L7: 17 | M7: 46030 | N7: 46042 | O7: Nil | P7: Nil | Q7: Nil | R7: Charles | S7: Nil | T7: https://dev.azure.com/heartlandschools/Mosaic/_git/BOH/pullrequest/46740 | U7: Nil | V7: Nil | W7: Charles | X7: Nil | Y7: Nil | Z7: Nil | AA7: Nil | AB7: Nil | AC7: Nil | AD7: Fixed 6 AI Automation Testcase failures.
A8: 7 | B8: BOH | C8: 46029 | D8: 46042 | E8: 26.1 Sprint 3 | F8: Charles | G8: 50937 | H8: Mosaic BOH - Add a column to Ingredients search to tell if the Ingredient has any attachment | I8: Story Completed | J8: 1 | K8: 1 | L8: 1 | M8: 46029 | N8: 46038 | O8: Yes | P8: Mohamed | Q8: Nil | R8: Mohamed | S8: Nil | T8: https://dev.azure.com/heartlandschools/Mosaic/_git/BOH/pullrequest/46344 | U8: 46037 | V8: 46038 | W8: EM | X8: Nil | Y8: Nil | Z8: Nil | AA8: Nil | AB8: 0 | AC8: Nil | AE8: Exceeds Expectation

Sheet 26.1 Sprint 3 - Defect Tracker
A1: Sprint # | B1: Story/Defect ID | C1: Parent Story | D1: Developer | E1: Issue Type | F1: Issue Description | G1: Priority | H1: Defect Source | I1: Type | J1: Status | K1: Estimated(sp) | L1: Actual(sp) | M1: Actual Hours Worklog | N1: Root Cause Category | O1: Comments
A2: 26.1 Sprint 3 | B2: 26531 | D2: Mohamed | E2: Defect | F2: Mosaic BOH - Regression - Menus - Maint - Locking Menu Days - Unlocked By label is not there. It showing Last Modified instead | G2: Minor | H2: Manual | I2: Internal | J2: Defect Fixed | K2: NA | L2: NA | M2: NA | N2: Existing_Issues | O2: Existing UI issue identified during regression testing, but was not detected in the earlier test cycles
A3: 26.1 Sprint 3 | B3: 26530 | D3: Mohamed | E3: Defect | F3: Mosaic BOH - Regression - Menus - Lock Menus - Menu is editable when locked in certain scenario | G3: Minor | H3: Manual | I3: Internal | J3: Defect Fixed | K3: NA | L3: NA | M3: NA | N3: Existing_Issues | O3: Existing issue identified during regression testing, a Javascript function is required to implement the menu editing scenario.
A4: 26.1 Sprint 3 | B4: 26533 | D4: Kavitha | E4: Defect | F4: Mosaic BOH - Setup - District Setup - Getting an error when uploading image | G4: Minor | H4: Manual | I4: Internal | J4: Defect Fixed | K4: NA | L4: NA | M4: NA | N4: Existing_Issues | O4: Existing UI issue identified during regression testing, using javascript code to fix this issue
A5: 26.1 Sprint 3 | B5: 26525 | D5: Kavitha | E5: Defect | F5: Mosaic BOH - Regression - Ingredients - Validation causing Save button to become inactive | G5: Minor | H5: Manual | I5: Internal | J5: Defect Fixed | K5: NA | L5: NA | M5: NA | N5: Existing_Issues | O5: Existing issue identified during regression testing, using javascript code to fix this issue
A6: 26.1 Sprint 3 | B6: 26606 | D6: Charles | E6: Defect | F6: Mosaic BOH - Regression - Setup - Security Groups - Getting popup that won't go away when selecting certain settings | G6: Minor | H6: Manual | I6: Internal | J6: Defect Fixed | K6: NA | L6: NA | M6: NA | N6: Existing_Issues | O6: Existing UI issue identified during regression testing, but was not detected in the earlier test cycles
A7: 26.1 Sprint 3 | B7: 26582 | D7: Charles | E7: Defect | F7: Mosaic BOH - Regression - Report Inbox - View All Reports option not working in certain instances | G7: Minor | H7: Manual | I7: Internal | J7: Defect Fixed | K7: NA | L7: NA | M7: NA | N7: Existing_Issues | O7: Existing UI issue identified during regression testing, but was not detected in the earlier test cycles
A8: 26.1 Sprint 3 | B8: 26566 | D8: Charles | E8: Defect | F8: Mosaic BOH - Regression - Production Records - Option for Print Menu Page is not showing the correct info for 2nd Alternate Menu Name | G8: Minor | H8: Manual | I8: Internal | J8: Defect Fixed | K8: NA | L8: NA | M8: NA | N8: Existing_Issues | O8: Existing UI issue identified during regression testing, but was not detected in the earlier test cycles
A9: 26.1 Sprint 3 | B9: 26575 | D9: Charles | E9: Defect | F9: Mosaic BOH - Regression - Reports - Shopping List - Getting error when linked item not on price list | G9: Minor | H9: Manual | I9: Internal | J9: Defect Fixed | K9: NA | L9: NA | M9: NA | N9: Existing_Issues | O9: Existing UI issue identified during regression testing, but was not detected in the earlier test cycles
A10: 26.1 Sprint 3 | B10: 26564 | D10: Charles | E10: Defect | F10: Mosaic BOH - Regression - Reports - Product List - Validation highlight for missing site or site group doesn't go away when selecting All Sites | G10: Minor | H10: Manual | I10: Internal | J10: Defect Fixed | K10: NA | L10: NA | M10: NA | N10: Existing_Issues | O10: Existing UI issue identified during regression testing, but was not detected in the earlier test cycles
A11: 26.1 Sprint 3 | B11: 26603 | D11: Charles | E11: Defect | F11: Mosaic BOH - Regression - Community - Clicking headers causes blue box to appear | G11: Minor | H11: Manual | I11: Internal | J11: Defect Fixed | K11: NA | L11: NA | M11: NA | N11: Existing_Issues | O11: Existing UI issue identified during regression testing, but was not detected in the earlier test cycles
A12: 26.1 Sprint 3 | B12: 26581 | D12: Charles | E12: Defect | F12: Mosaic BOH - Regression - Inventory - Phys count - Site or Site Group fields locked in certain instances | G12: Minor | H12: Manual | I12: Internal | J12: Defect Fixed | K12: NA | L12: NA | M12: NA | N12: Existing_Issues | O12: Existing UI issue identified during regression testing, but was not detected in the earlier test cycles
A13: 26.1 Sprint 3 | B13: 26584 | D13: Charles | E13: Defect | F13: Mosaic BOH - Regression - Reports - Production Records - Schedule | G13: Minor | H13: Manual | I13: Internal | J13: Defect Fixed | K13: NA | L13: NA | M13: NA | N13: Existing_Issues | O13: Existing UI issue identified during regression testing, but was not detected in the earlier test cycles
... A22: 26.1 Sprint 3 | B22: 26516 | D22: Charles | E22: Defect | F22: Mosaic BOH - Regression - Menus - Maintenance - Replace Recipe search page not allowing scroll to right until you search | G22: Minor | H22: Manual | I22: Internal | J22: Defect Fixed | K22: NA | L22: NA | M22: NA | N22: Existing_Issues | O22: Existing UI issue identified during regression testing, but was not detected in the earlier test cycles

Sheet 4.2 Sprint 2-Status
A1: S.No | B1: Application Name | C1: Sprint Start Date | D1: Sprint End Date | E1: Sprint | F1: Developer | G1: Story ID/Defect ID | H1: Description | I1: Status | J1: Estimated(sp) | K1: Actual(sp) | L1: Actual Hours Worklog | M1: Dev Start Date | N1: Dev End Date | O1: Unit testing | P1: Peer Tested By | Q1: Peer Tested Comments, if any | R1: Peer Reviewed By | S1: Peer Code Review Comments, if any | T1: PR Number/Link | U1: PR Created Date | V1: PR Approved Date | W1: Reviewer 1 | X1: Code Review Comments, if any | Y1: Reviewer 2 | Z1: Approved Date | AA1: Code Review Comments, if any2 | AB1: Internal PO -POV Comments | AC1: Client PO -POV Comments | AD1: Comments | AE1: Does this story meet expectations?
A2: 1 | B2: BOH | C2: 46001 | D2: 46028 | E2: 4.2 Sprint 2 | F2: Krupa | G2: 50933 | H2: [BAU]Mosaic BOH - AI - Nutrition Facts Label - Ability to update an Existing Ingredient's Nutrients instead of create a new ingredient | I2: Story Completed | J2: 5 | K2: 5 | L2: 8 | M2: 46001 | N2: 46002 | O2: Done | P2: Mohammed | R2: Mohammed | T2: https://dev.azure.com/heartlandschools/Mosaic/_git/BOH/pullrequest/46167 | U2: 46002 | W2: Charles | X2: Nil | Y2: Nil | Z2: Nil | AA2: Nil | AB2: Move Cancel and Update button to center and change the color to green | AC2: Nil | AE2: Meets Expectation
A3: 2 | B3: BOH | C3: 46001 | D3: 46028 | E3: 4.2 Sprint 2 | F3: Mohamed | G3: 50932 | H3: [BAU]Mosaic BOH - Nutrition Facts Label - Ability to upload PDF files | I3: Story Completed | J3: 8 | K3: 7 | L3: 28 | M3: 46001 | N3: 46007 | O3: Done | P3: Krupa | Q3: Nil | R3: Krupa | S3: Nil | T3: https://dev.azure.com/heartlandschools/Mosaic/_git/BOH/pullrequest/46236 | U3: 46007 | V3: 46009 | W3: Charles | X3: Nil | Y3: Nil | Z3: Nil | AA3: Nil | AB3: Nil | AC3: Nil | AE3: Meets Expectation
A4: 3 | B4: BOH | C4: 46001 | D4: 46028 | E4: 4.2 Sprint 2 | F4: Krupa | G4: 51099 | H4: Mosaic BOH - USDA Guidance - Updates needed for certification | I4: Story Completed | J4: 5 | K4: 5 | L4: 19 | M4: 46001 | N4: 46013 | O4: Done | P4: Mohammed | R4: Mohammed | S4: Nil | T4: https://dev.azure.com/heartlandschools/Mosaic/_git/BOH/pullrequest/46333 | U4: 46013 | V4: 46013 | W4: Charles | X4: Nil | Y4: Nil | Z4: Nil | AA4: Nil | AB4: Nil | AC4: Nil | AE4: Needs Improvement
A5: 4 | B5: BOH | C5: 46001 | D5: 46028 | E5: 4.2 Sprint 2 Stretch | F5: Mohamed | G5: 51307 | H5: [BAU]Mosaic BOH - Nutrition Facts label - PDF upload - Label change | I5: Story Completed | J5: 2 | K5: 1.5 | L5: 6 | M5: 46007 | N5: 46010 | O5: Done | P5: Krupa | Q5: Nil | R5: Krupa | S5: Nil | T5: https://dev.azure.com/heartlandschools/Mosaic/_git/BOH/pullrequest/46328 | U5: 46013 | V5: 46013 | W5: Charles | X5: Nil | Y5: Nil | Z5: Nil | AA5: Nil | AB5: Nil | AC5: Nil | AD5: Nil | AE5: Meets Expectation
A6: 5 | B6: BOH | C6: 46001 | D6: 46028 | E6: 4.2 Sprint 2 Stretch | F6: Suresh | G6: 51174 | H6: [BAU]Mosaic BOH - Automation - for Setup | I6: Story Completed | J6: 13 | K6: 6.5 | L6: 26 | M6: 46001 | N6: 46008 | O6: Done | Q6: Nil | R6: Charles | S6: Nil | T6: https://dev.azure.com/heartlandschools/Mosaic/_git/BOH/pullrequest/46226 | U6: 46006 | V6: 46007 | W6: Charles | X6: Nil | Y6: Nil | Z6: Nil | AA6: Nil | AB6: Nil | AC6: Nil | AD6: Nil
A7: 6 | B7: BOH | C7: 46001 | D7: 46028 | E7: 4.2 Sprint 2 Stretch | F7: Krupa | G7: 51273 | H7: [BAU] Mosaic BOH - AI - Nutrition Facts label - Update Existing Ingredient | I7: Story Completed | J7: 2 | K7: 2 | L7: 4 | M7: 46008 | N7: 46008 | O7: Done | P7: Mohammed | R7: Mohammed | T7: https://dev.azure.com/heartlandschools/Mosaic/_git/BOH/pullrequest/46276 | U7: 46008 | V7: 46008 | W7: Charles | X7: Nil | Y7: Nil | Z7: Nil | AA7: Nil | AB7: Nil | AC7: Nil | AD7: Nil | AE7: Meets Expectation
A8: 7 | B8: BOH | C8: 46001 | D8: 46028 | E8: 4.2 Sprint 2 Stretch | F8: Krupa | G8: 51274 | H8: [BAU]Mosaic BOH - Nutrition Facts label - show *N/A* Missing Nutrient Values | I8: Story Completed | J8: 2 | K8: 2 | L8: 6 | M8: 46008 | N8: 46008 | O8: Done | P8: Mohammed | R8: Mohammed | T8: https://dev.azure.com/heartlandschools/Mosaic/_git/BOH/pullrequest/46275 | U8: 46008 | V8: 46008 | W8: Charles | X8: Nil | Y8: Nil | Z8: Nil | AA8: Nil | AB8: Nil | AC8: Nil | AD8: Nil | AE8: Meets Expectation
A9: 8 | B9: BOH | C9: 46001 | D9: 46028 | E9: 4.2 Sprint 2 | F9: Team | G9: 50801 | H9: Mosaic BOH - 4.2 Regression - Ordering | I9: Story Completed | J9: 3 | K9: 19.25 | L9: 77 | M9: 46013 | N9: 46020 | O9: NIL | P9: NIL | Q9: NIL | R9: NIL | S9: NIL | T9: NIL | U9: NIL | V9: NIL | W9: NIL | X9: NIL | Y9: NIL | Z9: NIL | AA9: NIL | AB9: NIL | AC9: NIL
A10: 9 | B10: BOH | C10: 46001 | D10: 46028 | E10: 4.2 Sprint 2 | F10: Team | G10: 50795 | H10: Mosaic BOH - 4.2 Regression - Menus/Cycle Menus | I10: Story Being Developed | J10: 3 | K10: 10.25 | L10: 55 | M10: 46014 | N10: 46027 | O10: NIL | P10: NIL | Q10: NIL | R10: NIL | S10: NIL | T10: NIL | U10: NIL | V10: NIL | W10: NIL | X10: NIL | Y10: NIL | Z10: NIL | AA10: NIL | AB10: NIL | AC10: NIL
A11: 10 | B11: BOH | C11: 46001 | D11: 46028 | E11: 4.2 Sprint 2 | F11: Team | G11: 50802 | H11: 50802 Mosaic BOH - 4.2 Regression - Recipes | I11: Story Completed | J11: 3 | K11: 10.5 | L11: 56 | M11: 46014 | N11: 46027 | O11: NIL | P11: NIL | Q11: NIL | R11: NIL | S11: NIL | T11: NIL | U11: NIL | V11: NIL | W11: NIL | X11: NIL | Y11: NIL | Z11: NIL | AA11: NIL | AB11: NIL | AC11: NIL

Sheet 4.2 Sprint 2 - Defect Tracker
A1: Sprint # | B1: Story/Defect ID | C1: Parent Story | D1: Developer | E1: Issue Type | F1: Issue Description | G1: Priority | H1: Defect Source | I1: Type | J1: Status | K1: Estimated(sp) | L1: Actual(sp) | M1: Actual Hours Worklog | N1: Root Cause Category | O1: Comments
A2: 4.2 Sprint 2 | B2: 26369 | D2: Mohamed | E2: Defect | F2: [BAU]Mosaic BOH- GEN AI- CommonUIDefects | G2: Significant | H2: Manual | I2: Internal | J2: Defect Fixed | K2: 5 | L2: 2.5 | M2: 10 | N2: Existing_Issues | O2: Existing production issue, as the development was done by Kalaida team and testing by onshore tester. RCA: Vega component updates breaking the exisitng UI.
A3: 4.2 Sprint 2 | B3: 26204 | D3: Charles | E3: Defect | F3: (BAU) Mosaic BOH - AI - Next Navigation is not working in the Physical Count | G3: Significant | H3: Manual | I3: Internal | J3: Defect Fixed | K3: 2 | L3: 3 | M3: 12 | N3: Existing_Issues | O3: Existing production issue, as the development was done by Kalaida team and testing by onshore tester. RCA: Vega component updates breaking the exisitng UI.
A4: 4.2 Sprint 2 | B4: 25851 | D4: Charles | E4: Defect | F4: Mosaic BOH - GEN AI - Scan Handwritten Counts Not Allowing to Upload the Large Files | G4: Significant | H4: Manual | I4: External | J4: Defect Fixed | K4: 1 | L4: 4 | M4: 16 | N4: Existing_Issues | O4: Existing production issue, it was found by internal QA. Due to delivery release deadline we couldn't fix it on that time, So we fixed it now. Mitigation Plan: Manage the time for fixing the QA issues.
A5: 4.2 Sprint 2 | B5: 26493 | D5: Mohamed | E5: Defect | F5: (BAU) Mosaic BOH - AI - Calorie Nutrient Value is displaying as "N/A" if we are providing decimal Nutrient values in Ingredients page. | G5: Significant | H5: Manual | I5: External | J5: Defect Fixed | K5: 2 | L5: 1.5 | M5: 6 | N5: Existing_Issues | O5: Existing production issue, missing the decimal convertion on development. Mitigation Plan: Strictly following the Unit Testing to prevent issues

Sheet 4.2 Sprint 1-Status
A1: S.No | B1: Application Name | C1: Sprint Start Date | D1: Sprint End Date | E1: Sprint | F1: Developer | G1: Story ID/Defect ID | H1: Description | I1: Status | J1: Estimated(sp) | K1: Actual(sp) | L1: Actual Hours Worklog | M1: Dev Start Date | N1: Dev End Date | O1: Unit testing | P1: Peer Tested By | Q1: Peer Tested Comments, if any | R1: Peer Reviewed By | S1: Peer Code Review Comments, if any | T1: PR Number/Link | U1: PR Created Date | V1: PR Approved Date | W1: Reviewer 1 | X1: Code Review Comments, if any | Y1: Reviewer 2 | Z1: Approved Date | AA1: Code Review Comments, if any2 | AB1: Internal PO -POV Comments | AC1: Client PO -POV Comments | AD1: Comments | AE1: Does this story meet expectations?
A2: 1 | B2: BOH | C2: 45973 | D2: 46000 | E2: 4.2 Sprint 1 | F2: Mohamed | G2: 48990 | H2: Mosaic BOH - User Assignment Report | I2: Story Completed | J2: 8 | K2: 10 | L2: 40 | M2: 45973 | N2: 45986 | O2: Done | P2: Krupa | Q2: Nil | R2: Krupa | S2: Nil | T2: https://dev.azure.com/heartlandschools/Mosaic/_git/BOH/pullrequest/45921 | U2: 45987 | V2: 45987 | W2: Charles | X2: Nil | Y2: Nil | Z2: Nil | AA2: Nil | AB2: 1. Add the Sites to the column name (updated AC) 2. Show the individual sites instead of showing 'My Sites' | AC2: Nil | AD2: Nil | AE2: Meets Expectation
A3: 2 | B3: BOH | C3: 45973 | D3: 46000 | E3: 4.2 Sprint 1 | F3: Mohamed | G3: 48399 | H3: [WAVE] Mosaic BOH(WH) - Transfers Bulk Substitution - Product Search and Replace (UI only) | I3: Story Completed | J3: 2 | K3: 3.5 | L3: 14 | M3: 45978 | N3: 45980 | O3: Done | P3: Krupa | Q3: Nil | R3: Krupa | S3: Nil | T3: https://dev.azure.com/heartlandschools/Mosaic/_git/BOH/pullrequest/45807 | U3: 45980 | V3: 45980 | W3: Charles | X3: Nil | Y3: Nil | Z3: Nil | AA3: Nil | AB3: Nil | AC3: Nil | AD3: Nil | AE3: Meets Expectation
A4: 3 | B4: BOH | C4: 45973 | D4: 46000 | E4: 4.2 Sprint 1 | F4: Mohamed | G4: 47591 | H4: [WAVE] Mosaic BOH(WH) - Transfers Bulk Substitution - Product Search and Replace (functionality) | I4: Story Completed | J4: 2 | K4: 1.5 | L4: 6 | M4: 45978 | N4: 45980 | O4: Done | P4: Krupa | Q4: Nil | R4: Krupa | S4: Nil | T4: https://dev.azure.com/heartlandschools/Mosaic/_git/BOH/pullrequest/45807 | U4: 45980 | V4: 45980 | W4: Charles | X4: Nil | Y4: Nil | Z4: Nil | AA4: Nil | AB4: Nil | AC4: Nil | AD4: Nil | AE4: Meets Expectation
A5: 4 | B5: BOH | C5: 45973 | D5: 46000 | E5: 4.2 Sprint 1 | F5: Krupa | G5: 50579 | H5: [Wave]Mosaic BOH - Bidding - Add serving size, number serving in the Bid specification document | I5: Story Completed | J5: 3 | K5: 2 | L5: 6 | M5: 45973 | N5: 45973 | O5: Done | P5: Mohammed | Q5: Nil | R5: Mohammed | S5: Nil | T5: https://dev.azure.com/heartlandschools/Mosaic/_git/BOH/pullrequest/45671 | U5: 45973 | V5: 45976 | W5: Charles | X5: Nil | Y5: Nil | Z5: Nil | AA5: Nil | AB5: Correct the name: Number of Servings per P/U | AC5: Nil | AD5: Nil | AE5: Meets Expectation
A6: 5 | B6: BOH | C6: 45973 | D6: 46000 | E6: 4.2 Sprint 1 | F6: Krupa | G6: 50767 | H6: Mosaic BOH - Add Item Origin filter on the Product Maintenance screen | I6: Story Completed | J6: 3 | K6: 3 | L6: 6 | M6: 45975 | N6: 45978 | O6: Done | P6: Mohammed | Q6: Nil | R6: Mohammed | S6: Nil | T6: https://dev.azure.com/heartlandschools/Mosaic/_git/BOH/pullrequest/45750 | U6: 45978 | V6: 45978 | W6: Charles | X6: Nil | Y6: Nil | Z6: Nil | AA6: Nil | AB6: Nil | AC6: Nil | AD6: Nil | AE6: Meets Expectation
A7: 7 | B7: BOH | C7: 45973 | D7: 46000 | E7: 4.2 Sprint 1 | F7: Charles | G7: 49945 | H7: Mosaic BOH - (KDE Commitment) Ingredient Export Script | I7: Story Completed | J7: 3 | K7: 3 | L7: 12 | M7: 45973 | N7: 45974 | O7: Done | P7: Mohammed | Q7: Nil | R7: Nil | S7: Nil | T7: https://dev.azure.com/heartlandschools/Mosaic/_git/BOH/pullrequest/45689 | U7: 45974 | V7: 45974 | W7: Richard | X7: Nil | Y7: Nil | Z7: Nil | AA7: Nil | AB7: Nil | AC7: Nil | AD7: Nil | AE7: Exceeds Expectation
A8: 8 | B8: BOH | C8: 45973 | D8: 46000 | E8: 4.2 Sprint 1 | F8: Charles | G8: 49991 | H8: Mosaic BOH - Copy District - Missing data that is not getting copied | I8: Story Completed | J8: 5 | K8: 4 | L8: 16 | M8: 45975 | N8: 45979 | O8: Done | P8: Krupa | Q8: Nil | R8: Nil | S8: Nil | T8: https://dev.azure.com/heartlandschools/Mosaic/_git/BOH/pullrequest/45799 | U8: 45979 | V8: 45979 | W8: Richard | X8: Nil | Y8: Nil | Z8: Nil | AA8: Nil | AB8: Nil | AC8: Nil | AD8: Nil | AE8: Exceeds Expectation
A9: 9 | B9: BOH | C9: 45973 | D9: 46000 | E9: 4.2 Sprint 1 | F9: Charles | G9: 50281 | H9: Mosaic BOH - Production Costing Report - Make available for non-HHFKA menus | I9: Story Completed | J9: 5 | K9: 3 | L9: 12 | M9: 45986 | N9: 45996 | O9: Done | P9: Krupa | Q9: Nil | R9: Nil | S9: Nil | T9: https://dev.azure.com/heartlandschools/Mosaic/_git/BOH/pullrequest/46069 | U9: 45995 | V9: 45996 | W9: Ying | X9: Nil | Y9: Nil | Z9: Nil | AA9: Nil | AB9: Nil | AC9: Nil | AD9: Nil | AE9: Meets Expectation
A10: 10 | B10: BOH | C10: 45973 | D10: 46000 | E10: 4.2 Sprint 1 Stretch | F10: Charles | G10: 50931 | H10: Mosaic BOH - Delete District Proc - Delete all the missing district dependencies table data. | I10: Story Completed | J10: 5 | K10: 4 | L10: 16 | M10: 45982 | N10: 45986 | O10: Done | P10: Mohammed | Q10: Nil | R10: Nil | S10: Nil | T10: https://dev.azure.com/heartlandschools/Mosaic/_git/BOH/pullrequest/45935 | U10: 45986 | V10: 45986 | W10: Richard | X10: Nil | Y10: Nil | Z10: Nil | AA10: Nil | AB10: Nil | AC10: Nil | AD10: Nil | AE10: Exceeds Expectation
A11: 12 | B11: BOH | C11: 45973 | D11: 46000 | E11: 4.2 Sprint 1 Stretch | F11: Mohamed | G11: 51091 | H11: Mosaic BOH - User Assignment Report - Add a new column 'Active' | I11: Story Completed | J11: 2 | K11: 2 | L11: 8 | M11: 45995 | N11: 45995 | O11: Done | P11: Krupa | Q11: Nil | R11: Nil | S11: Nil | T11: https://dev.azure.com/heartlandschools/Mosaic/_git/BOH/pullrequest/46055 | U11: 45995 | V11: 45995 | W11: Charles | X11: Nil | Y11: Nil | Z11: Nil | AA11: Nil | AB11: Nil | AC11: Nil | AD11: Nil | AE11: Meets Expectation
A12: 6 | B12: BOH | C12: 45973 | D12: 46000 | E12: 4.2 Sprint 1 Stretch | F12: Suresh | G12: 50828 | H12: Mosaic BOH - Automation - for Setup | I12: Story Completed | J12: 13 | K12: 26 | L12: 107 | M12: 45973 | N12: 46000 | O12: Done | Q12: Nil | R12: Nil | S12: Nil | T12: 1) https://dev.azure.com/heartlandschools/Mosaic/_git/BOH/pullrequest/45959 2) https://dev.azure.com/heartlandschools/Mosaic/_git/BOH/pullrequest/46079 | U12: 45996 | V12: 46002 | W12: Charles | X12: Nil | Y12: Nil | Z12: Nil | AA12: Nil | AB12: Nil | AC12: Nil | AD12: Total No of Testcases created : 15 | AE12: Meets Expectation

Sheet 4.2 Sprint 1 - Defect Tracker
A1: Sprint # | B1: Story/Defect ID | C1: Parent Story | D1: Developer | E1: Issue Type | F1: Issue Description | G1: Priority | H1: Defect Source | I1: Type | J1: Status | K1: Estimated(sp) | L1: Actual(sp) | M1: Actual Hours Worklog | N1: Root Cause Category | O1: Comments
A2: 4.2 Sprint 1 | C2: 48399 | D2: Mohamed | E2: Bounceback | F2: 1. Site Product Info not updating to the new site if changing the sending site 2. Find window coming up very slowly if you click it once and then put value in and hitting find 3. Inactive products not showing on both search popups | G2: Significant | H2: Manual | I2: Internal | J2: Defect Fixed | N2: Development | O2: Development issue
A3: 4.2 Sprint 1 Stretch | B3: 26321 | D3: Charles | E3: Defect | F3: Mosaic BOH - Dunkirk City Schools - CN Update - Not updating Ingredient Class with what is in the new CN district | G3: Significant | H3: Manual | I3: External | J3: Defect Being Tested | K3: 2 | L3: 2 | M3: 8 | N3: Design | O3: Not a defect, it's a new requiremwent. Worked and completed as part of this defect.

Sheet 4.1 Sprint 3-Status
A1: S.No | B1: Application Name | C1: Sprint Start Date | D1: Sprint End Date | E1: Sprint | F1: Developer | G1: Story ID/Defect ID | H1: Description | I1: Status | J1: Estimated(sp) | K1: Actual(sp) | L1: Actual Hours Worklog | M1: Dev Start Date | N1: Dev End Date | O1: Unit testing | P1: Peer Tested By | Q1: Peer Tested Comments, if any | R1: Peer Reviewed By | S1: Peer Code Review Comments, if any | T1: PR Number/Link | U1: PR Created Date | V1: PR Approved Date | W1: Reviewer 1 | X1: Code Review Comments, if any | Y1: Reviewer 2 | Z1: Approved Date | AA1: Code Review Comments, if any2 | AB1: Internal PO -POV Comments | AC1: Client PO -POV Comments | AD1: Comments | AE1: Does this story meet expectations?
A2: 1 | B2: BOH | C2: 45959 | D2: 45972 | E2: 4.1 Sprint 3 Stretch | F2: Mohamed | G2: 48399 | H2: [WAVE] Mosaic BOH(WH) - Transfers Bulk Substitution - Product Search and Replace (UI only) | I2: Story Being Tested | J2: 3 | K2: 3 | L2: 15 | M2: 45959 | N2: 45964 | O2: Done | P2: Krupa | Q2: Nil | R2: Krupa | S2: Nil | T2: https://dev.azure.com/heartlandschools/Mosaic/_git/BOH/pullrequest/45331 | U2: 45959 | V2: 45961 | W2: Charles | X2: Nil | Y2: Nil | Z2: Nil | AA2: Nil | AB2: Nil | AC2: Nil | AD2: Development done, Testing only carry forward to next sprint | AE2: Meets Expectation
A3: 2 | B3: BOH | C3: 45959 | D3: 45972 | E3: 4.1 Sprint 3 Stretch | F3: Mohamed | G3: 47591 | H3: [WAVE] Mosaic BOH(WH) - Transfers Bulk Substitution - Product Search and Replace (functionality) | I3: Story Being Tested | J3: 8 | K3: 9 | L3: 36 | M3: 45959 | N3: 45966 | O3: Done | P3: Krupa | Q3: Nil | R3: Krupa | S3: Avoid using inline styles | T3: https://dev.azure.com/heartlandschools/Mosaic/_git/BOH/pullrequest/45497 | U3: 45966 | V3: 45967 | W3: Charles | X3: Nil | Y3: Nil | Z3: Nil | AA3: Nil | AB3: Apply - You must select a transfer # to Apply. Replace - You must select a transfer # to Replace. | AC3: Nil | AD3: Development done, Testing only carry forward to next sprint | AE3: Meets Expectation
A4: 3 | B4: BOH | C4: 45959 | D4: 45972 | E4: 4.1 Sprint 3 Stretch | F4: Suresh | G4: 50624 | H4: Mosaic BOH - Automation - Ingredients | I4: Story Completed | J4: 13 | K4: 8.75 | L4: 35 | M4: 45959 | N4: 45972 | O4: Done | P4: Nil | Q4: Nil | R4: Nil | S4: Nil | T4: https://dev.azure.com/heartlandschools/Mosaic/_git/BOH/pullrequest/45565, https://dev.azure.com/heartlandschools/Mosaic/_git/BOH/pullrequest/45655 | U4: 45968 | V4: 45972 | W4: Charles | X4: Nil | Y4: Nil | Z4: Nil | AA4: Nil | AB4: Nil | AC4: Nil | AD4: Total No of Automation TC's added :14
A5: 4 | B5: BOH | C5: 45959 | D5: 45972 | E5: 4.1 Sprint 3 Stretch | F5: Charles | G5: 49945 | H5: Mosaic BOH - (KDE Commitment) Ingredient Export Script | I5: Story Being Tested | J5: 5 | K5: 5 | L5: 20 | M5: 45958 | N5: 45968 | O5: Done | P5: Krupa | Q5: Nil | R5: Krupa | S5: Nil | T5: https://dev.azure.com/heartlandschools/Mosaic/_git/BOH/pullrequest/45395 | U5: 45960 | V5: 45960 | Y5: Richard | Z5: 45960 | AD5: There are multiple scenario and data sets to test. It's taking time to complete by QA due to back and forth changes based on data. | AE5: Meets Expectation
A6: 5 | B6: BOH | C6: 45959 | D6: 45972 | E6: 4.1 Sprint 3 Stretch | F6: Charles | G6: 43710 | H6: Mosaic BOH - Setup > Users - Improve usability | I6: Story Completed | J6: 3 | K6: 1 | L6: 4 | M6: 45964 | N6: 45964 | O6: Done | P6: Mohammed | Q6: Nil | R6: Mohammed | S6: Nil | T6: https://dev.azure.com/heartlandschools/Mosaic/_git/BOH/pullrequest/45439 | U6: 45964 | V6: 45964 | Y6: Richard | Z6: 45964 | AA6: Verbiage correction(Spelling mistake) - Linked, not Linket | AB6: Nil | AC6: Nil | AE6: Exceeds Expectation
A7: 6 | B7: BOH | C7: 45959 | D7: 45972 | E7: 4.1 Sprint 3 Stretch | F7: Charles | G7: 44326 | H7: Add the ability to print warehouse orders from within the orders | I7: Story Completed | J7: 2 | K7: 1.5 | L7: 6 | M7: 45971 | N7: 45971 | O7: Done | P7: Mohammed | Q7: Nil | R7: Mohammed | S7: Nil | T7: https://dev.azure.com/heartlandschools/Mosaic/_git/BOH/pullrequest/45619 | U7: 45971 | V7: 45971 | Y7: James | Z7: 45971 | AB7: Nil | AC7: Nil | AE7: Exceeds Expectation
A8: 7 | B8: BOH | C8: 45959 | D8: 45972 | E8: 4.1 Sprint 3 Stretch | F8: Charles | G8: 48073 | H8: Mosaic BOH - Application Settings - District Maintenance Improvements (NCESID, HSSCustomerID) | I8: Story Completed | J8: 3 | K8: 2 | L8: 8 | M8: 45969 | N8: 45972 | O8: Done | P8: Krupa | Q8: Nil | R8: Krupa | S8: Nil | T8: https://dev.azure.com/heartlandschools/Mosaic/_git/BOH/pullrequest/45619 | U8: 45967 | V8: 45967 | Y8: Richard | Z8: 45967 | AB8: Nil | AC8: Nil | AE8: Exceeds Expectation

Sheet 4.1 Sprint 3 - Defect Tracker
A1: Sprint # | B1: Story/Defect ID | C1: Parent Story | D1: Developer | E1: Issue Type | F1: Issue Description | G1: Priority | H1: Defect Source | I1: Type | J1: Status | K1: Estimated(sp) | L1: Actual(sp) | M1: Actual Hours Worklog | N1: Root Cause Category | O1: Comments
A2: 4.1 Sprint 3 | B2: 26183 | D2: Krupa | E2: Defect | F2: (WAVE)Mosaic BOH - AI - Menu Planning - PQ screen - Print Blank AI Production Record link disappears after save | G2: Significant | H2: Manual | I2: External | J2: Defect Fixed | K2: 2 | L2: 2 | M2: 6 | N2: Existing_Issues | O2: Production issue
A3: 4.1 Sprint 3 | B3: 26184 | D3: Krupa | E3: Defect | F3: (WAVE)Mosaic BOH - AI - (ON QA MPtest)Production Record Upload Screen - Print Blank AI Production Record link does not work | G3: Significant | H3: Manual | I3: External | J3: Defect Fixed | K3: 1 | L3: =M3/4 -> 1 | M3: 4 | N3: Existing_Issues | O3: Existing issue
A4: 4.1 Sprint 3 | B4: 26234 | D4: Charles | E4: Defect | F4: Mosaic BOH - Last Login Date is not being recorded in some cases (4.1) | G4: Significant | H4: Manual | I4: External | J4: Defect Fixed | K4: 3 | L4: 2 | M4: 8 | N4: Existing_Issues | O4: Existing production issue
A5: 4.1 Sprint 3 | C5: 49692 | D5: Krupa | E5: Bounceback | F5: Showing values as dates instead of a number. Like 1/2 shows a January 2nd , etc | G5: Significant | H5: Manual | I5: Internal | J5: Defect Fixed | K5: 1 | L5: 1 | M5: 2 | N5: Development | O5: Development issue

Sheet 4.1 Sprint 2-Status
A1: S.No | B1: Application Name | C1: Sprint Start Date | D1: Sprint End Date | E1: Sprint | F1: Developer | G1: Story ID/Defect ID | H1: Description | I1: Status | J1: Estimated(sp) | K1: Actual(sp) | L1: Actual Hours Worklog | M1: Dev Start Date | N1: Dev End Date | O1: Unit testing | P1: Peer Tested By | Q1: Peer Tested Comments, if any | R1: Peer Reviewed By | S1: Peer Code Review Comments, if any | T1: PR Number/Link | U1: PR Created Date | V1: PR Approved Date | W1: Reviewer 1 | X1: Code Review Comments, if any | Y1: Reviewer 2 | Z1: Approved Date | AA1: Code Review Comments, if any2 | AB1: Internal PO -POV Comments | AC1: Client PO -POV Comments | AD1: Comments | AE1: Does this story meet expectations?
A2: 1 | B2: BOH | C2: 45945 | D2: 45958 | E2: 4.1 Sprint 2 | F2: Krupa | G2: 49692 | H2: Mosaic BOH - Add CSV format to the Production Planning Shopping List Report | I2: Story Peer Review | J2: 5 | K2: =L2/4 -> 6 | L2: 24 | M2: 45946 | N2: 45958 | O2: Done | P2: Mohammed | Q2: Nil | R2: Mohammed | S2: Nil | T2: https://dev.azure.com/heartlandschools/Mosaic/_git/BOH/pullrequest/45340 | U2: 45958 | V2: Nil | W2: Charles | X2: Nil | Y2: Nil | Z2: Nil | AA2: Nil | AB2: Linked prod no. not visisble Product #/Ingredient# should be shown Column ' Mfr/Vendor Prod #' is showing wrong value | AD2: The existing stored procedure has to be updated as it was not giving expected data, which was little challenging so took more time. | AE2: Meets Expectation
A3: 3 | B3: BOH | C3: 45945 | D3: 45958 | E3: 4.1 Sprint 2 Stretch | F3: Suresh | G3: 50449 | H3: Mosaic BOH - Automation - Ingredients | I3: Story Peer Review | J3: 13 | K3: 12 | L3: 48 | M3: 45945 | N3: 45958 | O3: Done | P3: Chales | Q3: Nil | R3: Chales | S3: Nil | T3: https://dev.azure.com/heartlandschools/Mosaic/_git/BOH/pullrequest/45315 | U3: 45957 | V3: Nil | W3: Charles | X3: Nil | Y3: Nil | Z3: Nil | AA3: Nil | AD3: Total No of Testcases created :11 | AE3: Meets Expectation
A4: 4 | B4: BOH | C4: 45945 | D4: 45958 | E4: 4.1 Sprint 2 Stretch | F4: Mohamed | G4: 48399 | H4: [WAVE] Mosaic BOH(WH) - Transfers Bulk Substitution - Product Search and Replace (UI only) | I4: Story Peer Review | J4: 8 | K4: 8.5 | L4: 34 | M4: 45945 | N4: 45958 | O4: Done | P4: Krupa | Q4: Nil | R4: Krupa | S4: Nil | T4: https://dev.azure.com/heartlandschools/Mosaic/_git/BOH/pullrequest/45331 | U4: 45958 | V4: Nil | W4: Charles | X4: Nil | Y4: Nil | Z4: Nil | AA4: Nil | AB4: 1.Products popup alignment 2.Add item number to the product number 3.By default sending site should be selected and its a required field | AD4: Development completed ready for peer review | AE4: Meets Expectation
A5: 6 | B5: BOH | C5: 45945 | D5: 45958 | E5: 4.1 Sprint 2 | F5: Mohamed | G5: 49797 | H5: Mosaic BOH - Add Default Mosaic Price Lists Import/Export Template | I5: Story Completed | J5: 2 | K5: 2 | L5: 2 | M5: 45945 | N5: 45946 | O5: Done | P5: Krupa | Q5: Nil | R5: Krupa | S5: Nil | T5: https://dev.azure.com/heartlandschools/Mosaic/_git/BOH/pullrequest/45105 | U5: 45944 | V5: 45947 | W5: Charles | X5: Nil | Y5: Nil | Z5: Nil | AA5: Nil | AB5: Nil | AC5: Nil | AD5: Nil | AE5: Meets Expectation
A6: 7 | B6: BOH | C6: 45945 | D6: 45958 | E6: 4.1 Sprint 2 | F6: Mohamed | G6: 49750 | H6: MOSAIC BOH - Add the Ability to Export Price Lists by using 'Default Mosaic Price Lists Import/Export' Template | I6: Story Completed | J6: 2 | K6: 2 | L6: 2 | M6: 45946 | N6: 45947 | O6: Done | P6: Krupa | Q6: Nil | R6: Krupa | S6: Nil | T6: https://dev.azure.com/heartlandschools/Mosaic/_git/BOH/pullrequest/45105 | U6: 45944 | V6: 45947 | W6: Charles | X6: Nil | Y6: Nil | Z6: Nil | AA6: Nil | AB6: Nil | AC6: Nil | AD6: Nil | AE6: Meets Expectation
A7: 8 | B7: BOH | C7: 45945 | D7: 45958 | E7: 4.1 Sprint 2 Stretch | F7: Charles | G7: 49945 | H7: Mosaic BOH - (KDE Commitment) Ingredient Export Script | I7: Story Being Developed | J7: 8 | K7: 7 | L7: 28 | M7: 45945 | N7: 45958 | AD7: Development Inprogress

Sheet 4.1 Sprint 2 - Defect Tracker
A1: Sprint # | B1: Story/Defect ID | C1: Parent Story | D1: Developer | E1: Issue Type | F1: Issue Description | G1: Priority | H1: Defect Source | I1: Type | J1: Status | K1: Estimated(sp) | L1: Actual(sp) | M1: Actual Hours Worklog | N1: Root Cause Category | O1: Comments
A2: 4.1 Sprint 2 | B2: 26053 | D2: Mohamed | E2: Defect | F2: Mosaic BOH - Saving Changes to the DistrictEdit page disables MV settings | G2: Major | H2: Manual | I2: Internal | J2: Defect Fixed | K2: 1 | L2: 1 | M2: 3 | N2: Existing_Issues | O2: Production Issue
A3: 4.1 Sprint 2 Stretch | C3: 47500 | D3: Krupa | E3: Bounceback | F3: Mosaic BOH - ER - Add 'Use Prod. Specifications' in Recipes List By Menu | G3: Significant | H3: Manual | I3: Internal | J3: Defect Fixed | K3: 1 | L3: 1 | M3: 4 | N3: Existing_Issues | O3: This issue was identified by onshore QA - Craig, due to the development of story 47500
A4: 4.1 Sprint 2 Stretch | B4: 26098 | D4: Charles | E4: Defect | F4: Mosaic BOH - Fix failing testcases | G4: Significant | H4: Manual | I4: Internal | J4: Defect Fixed | K4: 3 | L4: 3 | M4: 12 | N4: Environment_Related | O4: Test cases failing in the pipeline due to ServiceLocator issue caused by missing or misconfigured DI containers

Sheet 4.1 Sprint 1-Status
A1: S.No | B1: Application Name | C1: Sprint Start Date | D1: Sprint End Date | E1: Sprint | F1: Developer | G1: Story ID/Defect ID | H1: Description | I1: Status | J1: Estimated(sp) | K1: Actual(sp) | L1: Actual Hours Worklog | M1: Dev Start Date | N1: Dev End Date | O1: Unit testing | P1: Peer Tested By | Q1: Peer Tested Comments, if any | R1: Peer Reviewed By | S1: Peer Code Review Comments, if any | T1: PR Number/Link | U1: PR Created Date | V1: PR Approved Date | W1: Reviewer 1 | X1: Code Review Comments, if any | Y1: Reviewer 2 | Z1: Approved Date | AA1: Code Review Comments, if any2 | AB1: Internal PO -POV Comments | AC1: Client PO -POV Comments | AD1: Comments | AE1: Does this story meet expectations?
A2: 1 | B2: BOH | C2: 45931 | D2: 45944 | E2: 4.1 Sprint 1 | F2: Krupa | G2: 43049 | H2: Mosaic BOH - Bidding - Remove UPC Code(GTIN) validation when importing bid response | I2: Story Completed | J2: 3 | K2: 3 | L2: 13 | M2: 45933 | N2: 45938 | O2: Done | P2: Mohammed | Q2: Nil | R2: Mohammed | S2: Nil | T2: https://dev.azure.com/heartlandschools/Mosaic/_git/BOH/pullrequest/45039 | U2: 45939 | V2: 45939 | W2: Charles | X2: Nil | Y2: Nil | Z2: Nil | AA2: Nil | AB2: Nil | AC2: Nil | AD2: Nil | AE2: Meets Expectation
A3: 2 | B3: BOH | C3: 45931 | D3: 45944 | E3: 4.1 Sprint 1 | F3: Krupa | G3: 45285 | H3: Mosaic BOH - ER - Last modified date/user visibility for Products (Round 2) | I3: Story Completed | J3: 8 | K3: 3 | L3: 9 | M3: 45933 | N3: 45937 | O3: Done | P3: Mohammed | Q3: Nil | R3: Mohammed | S3: Nil | T3: https://dev.azure.com/heartlandschools/Mosaic/_git/BOH/pullrequest/45038 | U3: 45939 | V3: 45939 | W3: Charles | X3: Nil | Y3: Nil | Z3: Nil | AA3: Nil | AB3: Nil | AC3: Nil | AD3: Nil | AE3: Meets Expectation
A4: 3 | B4: BOH | C4: 45931 | D4: 45944 | E4: 4.1 - Sprint 1 Stretch | F4: Krupa | G4: 47500 | H4: Mosaic BOH - ER - Add 'Use Prod. Specifications' in Recipes List By Menu | I4: Story Ready For Testing | J4: 5 | K4: =L4/4 -> 3.5 | L4: 14 | M4: 45938 | N4: 45943 | O4: Done | P4: Mohammed | Q4: Nil | R4: Mohammed | S4: Nil | T4: https://dev.azure.com/heartlandschools/Mosaic/_git/BOH/pullrequest/45080 | U4: 45943 | V4: 45943 | W4: Charles | X4: Nil | Y4: Nil | Z4: Nil | AA4: Nil | AB4: Nil | AC4: Nil | AD4: Nil | AE4: Meets Expectation
A5: 4 | B5: BOH | C5: 45931 | D5: 45944 | E5: 4.1 Sprint 1 | F5: Mohamed | G5: 44438 | H5: Mosaic BOH - ER - Inventory Physical Count screen to display default P/U price | I5: Story Completed | J5: 2 | K5: 2 | L5: 8 | M5: 45933 | N5: 45937 | O5: Done | P5: Krupa | Q5: Nil | R5: Krupa | S5: Nil | T5: https://dev.azure.com/heartlandschools/Mosaic/_git/BOH/pullrequest/44985 | U5: 45937 | V5: 45937 | W5: Charles | X5: Nil | Y5: Nil | Z5: Nil | AA5: Nil | AB5: Nil | AC5: Nil | AD5: Nil | AE5: Meets Expectation
A6: 5 | B6: BOH | C6: 45931 | D6: 45944 | E6: 4.1 Sprint 1 | F6: Mohamed | G6: 49693 | H6: Mosaic BOH (CPS C0026) - Add Meal Totals by each day to the Production Summary Report | I6: Story Completed | J6: 2 | K6: 0.5 | L6: 2 | M6: 45933 | N6: 45937 | O6: Done | P6: Krupa | Q6: Nil | R6: Krupa | S6: Nil | T6: https://dev.azure.com/heartlandschools/Mosaic/_git/BOH/pullrequest/44987 | U6: 45937 | V6: 45937 | W6: Charles | X6: Nil | Y6: Nil | Z6: Nil | AA6: Nil | AB6: Nil | AC6: Nil | AD6: Nil | AE6: Meets Expectation
A7: 6 | B7: BOH | C7: 45931 | D7: 45944 | E7: 4.1 Sprint 1 | F7: Charles | G7: 48606 | H7: Mosaic BOH - (KDE) Copy Production Record Format from District A to District B (MUST HAVE in NOV) | I7: Story Completed | J7: 8 | K7: =L7/4 -> 5 | L7: 20 | M7: 45931 | N7: 45939 | O7: Done | P7: NA | Q7: NA | R7: NA | S7: NA | T7: NA | U7: NA | V7: NA | W7: NA | X7: NA | Y7: NA | Z7: NA | AA7: NA | AB7: NA | AC7: NA | AD7: No Change in Code so no PR, Its a script
A8: 7 | B8: BOH | C8: 45931 | D8: 45944 | E8: 4.1 Sprint 1 | F8: Charles | G8: 49971 | H8: Mosaic BOH - Add 'Extended' labels to the Inventory On Hand PU Cost & SU Cost column headers | I8: Story Completed | J8: 1 | K8: 1 | L8: 3 | M8: 45933 | N8: 45937 | O8: Done | P8: Mohammed | Q8: Nil | R8: Mohammed | S8: Nil | T8: https://dev.azure.com/heartlandschools/Mosaic/_git/BOH/pullrequest/45003 | U8: 45937 | V8: 45938 | W8: Richard | X8: Nil | Y8: Nil | Z8: Nil | AA8: Nil | AB8: Nil | AC8: Nil | AD8: Nil | AE8: Meets Expectation
A9: 8 | B9: BOH | C9: 45931 | D9: 45944 | E9: 4.1 - Sprint 1 Stretch | F9: Suresh | G9: 50366 | H9: Mosaic BOH - Automation - Menu Module | I9: Story Completed | J9: 13 | K9: 8.75 | L9: 35 | M9: 45938 | N9: 45944 | O9: Done | Q9: Nil | R9: Charles | S9: Nil | T9: https://dev.azure.com/heartlandschools/Mosaic/_git/BOH/pullrequest/45103 | U9: 45944 | W9: Charles | X9: Nil | Y9: Nil | Z9: Nil | AA9: Nil | AB9: Nil | AC9: Nil | AD9: Nil
A10: 9 | B10: BOH | C10: 45931 | D10: 45944 | E10: 4.1 Sprint 1 Stretch | F10: Mohamed | G10: 49797 | H10: Mosaic BOH - Add Default Mosaic Price Lists Import/Export Template | I10: Story Peer Review | J10: 3 | K10: 3 | L10: 12 | M10: 45938 | N10: 45940 | O10: Done | P10: Krupa | Q10: Nil | R10: Krupa | S10: Nil | T10: https://dev.azure.com/heartlandschools/Mosaic/_git/BOH/pullrequest/45105 | U10: 45944 | X10: Nil | Y10: Nil | Z10: Nil | AA10: Nil | AB10: Nil | AC10: Nil | AD10: Nil | AE10: Meets Expectation
A11: 10 | B11: BOH | C11: 45931 | D11: 45944 | E11: 4.1 Sprint 1 Stretch | F11: Mohamed | G11: 49750 | H11: MOSAIC BOH - Add the Ability to Export Price Lists by using 'Default Mosaic Price Lists Import/Export' Template | I11: Story Peer Review | J11: 3 | K11: 4 | L11: 16 | M11: 45940 | N11: 45944 | O11: Done | P11: Krupa | Q11: Nil | R11: Krupa | S11: Nil | T11: https://dev.azure.com/heartlandschools/Mosaic/_git/BOH/pullrequest/45105 | U11: 45944 | X11: Nil | Y11: Nil | Z11: Nil | AA11: Nil | AB11: Nil | AC11: Nil | AD11: Nil | AE11: Meets Expectation

Sheet 4.1 Sprint 1 - Defect Tracker
A1: Sprint # | B1: Story/Defect ID | C1: Parent Story | D1: Developer | E1: Issue Type | F1: Issue Description | G1: Priority | H1: Defect Source | I1: Type | J1: Status | K1: Estimated(sp) | L1: Actual(sp) | M1: Actual Hours Worklog | N1: Root Cause Category | O1: Comments

Sheet 4.0 Sprint 3-Status
A1: S.No | B1: Application Name | C1: Sprint Start Date | D1: Sprint End Date | E1: Sprint | F1: Developer | G1: Story ID/Defect ID | H1: Description | I1: Status | J1: Estimated(sp) | K1: Actual(sp) | L1: Actual Hours Worklog | M1: Dev Start Date | N1: Dev End Date | O1: Unit testing | P1: Peer Tested By | Q1: Peer Tested Comments, if any | R1: Peer Reviewed By | S1: Peer Code Review Comments, if any | T1: PR Number/Link | U1: PR Created Date | V1: PR Approved Date | W1: Reviewer 1 | X1: Code Review Comments, if any | Y1: Reviewer 2 | Z1: Approved Date | AA1: Code Review Comments, if any2 | AB1: Internal PO -POV Comments | AC1: Client PO -POV Comments | AD1: Comments | AE1: Does this story meet expectations?
A2: 1 | B2: BOH | C2: 45903 | D2: 45930 | E2: 4.0 Sprint 3 | F2: Team | G2: 49891 | H2: Mosaic BOH - 4.0 Regression - Inventory | I2: Story Completed | J2: 13 | K2: 10 | L2: 40 | M2: 45903 | N2: 45908 | O2: NIL | P2: NIL | Q2: NIL | R2: NIL | S2: NIL | T2: NIL | U2: NIL | V2: NIL | W2: NIL | X2: NIL | Y2: NIL | Z2: NIL | AA2: NIL | AB2: NIL | AC2: NIL | AD2: NIL
A3: 2 | B3: BOH | C3: 45903 | D3: 45930 | E3: 4.0 Sprint 3 | F3: Team | G3: 49893 | H3: Mosaic BOH - 4.0 Regression - Ordering | I3: Story Completed | J3: 3 | K3: 15.25 | L3: 60.5 | M3: 45905 | N3: 45910 | O3: NIL | P3: NIL | Q3: NIL | R3: NIL | S3: NIL | T3: NIL | U3: NIL | V3: NIL | W3: NIL | X3: NIL | Y3: NIL | Z3: NIL | AA3: NIL | AB3: NIL | AC3: NIL | AD3: NIL
A4: 3 | B4: BOH | C4: 45903 | D4: 45930 | E4: 4.0 Sprint 3 | F4: Team | G4: 49887 | H4: Mosaic BOH - 4.0 Regression - Menus/Cycle Menus | I4: Story Completed | J4: 3 | K4: 14.75 | L4: 59 | M4: 45911 | N4: 45915 | O4: NIL | P4: NIL | Q4: NIL | R4: NIL | S4: NIL | T4: NIL | U4: NIL | V4: NIL | W4: NIL | X4: NIL | Y4: NIL | Z4: NIL | AA4: NIL | AB4: NIL | AC4: NIL | AD4: NIL
A5: 4 | B5: BOH | C5: 45903 | D5: 45930 | E5: 4.0 Sprint 3 | F5: Team | G5: 49888 | H5: Mosaic BOH - 4.0 Regression - Reports | I5: Story Completed | J5: 8 | K5: 27.25 | L5: 108.5 | M5: 45915 | N5: 45922 | O5: NIL | P5: NIL | Q5: NIL | R5: NIL | S5: NIL | T5: NIL | U5: NIL | V5: NIL | W5: NIL | X5: NIL | Y5: NIL | Z5: NIL | AA5: NIL | AB5: NIL | AC5: NIL | AD5: NIL
A6: 5 | B6: BOH | C6: 45903 | D6: 45930 | E6: 4.0 Sprint 3 | F6: Team | G6: 49889 | H6: Mosaic BOH - 4.0 Regression - SetUp | I6: Story Completed | J6: 3 | K6: 13 | L6: 52 | M6: 45922 | N6: 45926 | O6: NIL | P6: NIL | Q6: NIL | R6: NIL | S6: NIL | T6: NIL | U6: NIL | V6: NIL | W6: NIL | X6: NIL | Y6: NIL | Z6: NIL | AA6: NIL | AB6: NIL | AC6: NIL | AD6: NIL
A7: 6 | B7: BOH | C7: 45903 | D7: 45930 | E7: 4.0 - Sprint 3 Stretch | F7: Krupa & Mohamed | G7: 50122 | H7: [Wave]Mosaic BOH - Gen AI - Terms of Service (Acceptance workflow) | I7: Story Ready For Testing | J7: 5 | K7: 5 | L7: 20 | M7: 45918 | N7: 45923 | O7: Done | P7: Mohamed | Q7: NIL | R7: Mohamed | S7: NIL | T7: https://dev.azure.com/heartlandschools/Mosaic/_git/BOH/pullrequest/44719 | U7: 45923 | V7: 45923 | W7: Charles | X7: NIL | Y7: James | Z7: 45923 | AA7: NIL | AB7: NIL | AC7: NIL | AD7: NIL
A8: 7 | B8: BOH | C8: 45903 | D8: 45930 | E8: 4.0 - Sprint 3 Stretch | F8: Krupa | G8: 50164 | H8: [WAVE] Mosaic BOH - Production Record Assistant - AI Production Record Format & Execute | I8: Story Ready For Testing | J8: 5 | K8: 5 | L8: 20 | M8: 45925 | N8: 45929 | O8: Done | P8: Mohamed | Q8: NIL | R8: Mohamed | S8: NIL | T8: https://dev.azure.com/heartlandschools/Mosaic/_git/BOH/pullrequest/44854 | U8: 45929 | V8: 45929 | W8: Charles | X8: NIL | Y8: Richard | Z8: 45929 | AA8: NIL | AB8: NIL | AC8: NIL | AD8: NIL

Sheet 4.0 Sprint 3 - Defect Tracker
A1: Sprint # | B1: Story/Defect ID | C1: Parent Story | D1: Developer | E1: Issue Type | F1: Issue Description | G1: Priority | H1: Defect Source | I1: Type | J1: Status | K1: Estimated(sp) | L1: Actual(sp) | M1: Actual Hours Worklog | N1: Root Cause Category | O1: Comments
A2: 4.0 Sprint 3 [Stretch] | B2: 25857 | D2: Krupa | E2: Defect | F2: Mosaic BOH - Requisition Save is slow | G2: Significant | H2: Manual | I2: Internal | J2: Defect Fixed | N2: Existing_Issues | O2: This is regression defect, so hours logged into regression story
A3: 4.0 - Sprint 3 | B3: 25762 | D3: Krupa | E3: Defect | F3: Mosaic BoH - Multiple Districts - Importing Cycle Menu deletes Last Modified Date field for Production Quantities | G3: Significant | H3: Manual | I3: External | J3: Defect Fixed | N3: Existing_Issues | O3: This is regression defect, so hours logged into regression story
A4: 4.0 - Sprint 3 | B4: 25880 | D4: Krupa | E4: Defect | F4: Mosaic BOH - Menus - Maintenance & Cycles - If you hit the Enter key on keyboard when adding menu item it doubles if item is unique | G4: Significant | H4: Manual | I4: Internal | J4: Defect Fixed | N4: Existing_Issues | O4: This is regression defect, so hours logged into regression story
A5: 4.0 - Sprint 3 | B5: 25900 | D5: Krupa | E5: Defect | F5: Mosaic BoH - Multiple Districts - Importing Cycle Menu is not Appending in Import cycle menu | G5: Significant | H5: Manual | I5: External | J5: Defect Fixed | N5: Existing_Issues | O5: This is regression defect, so hours logged into regression story
A6: 4.0 - Sprint 3 | B6: 25883 | D6: Mohamed | E6: Defect | F6: Mosaic BOH - Regression - Transfers - Search Grid - Clicking the Requisition # column header causes program to freeze | G6: Significant | H6: Manual | I6: External | J6: Defect Fixed | N6: Existing_Issues | O6: This is regression defect, so hours logged into regression story
A7: 4.0 - Sprint 3 | B7: 25895 | D7: Mohamed | E7: Defect | F7: Mosaic BOH - Regression - Requisitions - Search Page - If you search and then click reset Site and Site Group dropdown turn black | G7: Significant | H7: Manual | I7: External | J7: Defect Fixed | N7: Existing_Issues | O7: This is regression defect, so hours logged into regression story
A8: 4.0 - Sprint 3 | B8: 25946 | D8: Mohamed | E8: Defect | F8: Mosaic BOH - Regression - Breadcrumb on the PQ screen showing HTML &amp; for the ampersand | G8: Significant | H8: Manual | I8: External | J8: Defect Rejected | N8: Environment_Related | O8: This is regression defect, so hours logged into regression story
A9: 4.0 - Sprint 3 | B9: 25953 | D9: Mohamed | E9: Defect | F9: Mosaic BOH - Regression - Reports - Recipes List By Menu - the Show More link in the top right is not showing because text is white | G9: Significant | H9: Manual | I9: External | J9: Defect Fixed | N9: Existing_Issues | O9: This is regression defect, so hours logged into regression story
A10: 4.0 - Sprint 3 | B10: 25945 | D10: Krupa | E10: Defect | F10: Mosaic BOH - Regression - Setup - Security Groups - Edit Fields popup - needs to be bigger. Can't see full description | G10: Significant | H10: Manual | I10: External | J10: Defect Fixed | N10: Existing_Issues | O10: This is regression defect, so hours logged into regression story
A11: 4.0 - Sprint 3 | B11: 25943 | D11: Krupa | E11: Defect | F11: Mosaic BOH - Regression - Ingredient List Print - Ingredient # field accepts alpha characters. Should be numeric only | G11: Significant | H11: Manual | I11: External | J11: Defect Fixed | N11: Existing_Issues | O11: This is regression defect, so hours logged into regression story
A12: 4.0 - Sprint 3 | B12: 25970 | D12: Mohamed | E12: Defect | F12: Mosaic BOH - Regression - Setup - Prod Rec formats - Buttons on modify column screen misaligned | G12: Significant | H12: Manual | I12: External | J12: Defect Fixed | N12: Existing_Issues | O12: This is regression defect, so hours logged into regression story
A13: 4.0 - Sprint 3 | B13: 25969 | D13: Mohamed | E13: Defect | F13: Mosaic BOH - Regression - Production Planning Shopping list - The headers for Start Date and End date can't be seen because of font color | G13: Significant | H13: Manual | I13: External | J13: Defect Fixed | N13: Existing_Issues | O13: This is regression defect, so hours logged into regression story
A14: 4.0 - Sprint 3 | B14: 25990 | D14: Mohamed | E14: Defect | F14: Mosaic BOH - Regression - Price List Import - The Results screen is not showing full description and has no tooltip | G14: Significant | H14: Manual | I14: External | J14: Defect Fixed | N14: Existing_Issues | O14: This is regression defect, so hours logged into regression story
A15: 4.0 - Sprint 3 | B15: 25978 | D15: Mohamed | E15: Defect | F15: Mosaic BOH - regression - Inventory Variance Report - Ordering & Receiving & Physical Count - Dropdowns are acting strangely. Start narrow then expand | G15: Significant | H15: Manual | I15: External | J15: Defect Fixed | N15: Existing_Issues | O15: This is regression defect, so hours logged into regression story
A16: 4.0 - Sprint 3 | B16: 25968 | D16: Charles | E16: Defect | F16: Mosaic BOH - Regression - Report - Warehouse Orders Report - Source Site (Warehouse) dropdown showing only one site for some reason | G16: Significant | H16: Manual | I16: External | J16: Defect Rejected | N16: Environment_Related | O16: This is regression defect, so hours logged into regression story
A17: 4.0 - Sprint 3 | B17: 26021 | D17: Mohamed | E17: Defect | F17: Mosaic BOH - Regression - Vendor Order Export Formats - Buttons misaligned on popups on all tabs | G17: Significant | H17: Manual | I17: External | J17: Defect Ready For Testing | O17: This is regression defect, so hours logged into regression story

Sheet 4.0 Sprint 2 - Defect Tracker
A1: Sprint # | B1: Story/Defect ID | C1: Parent Story | D1: Developer | E1: Issue Type | F1: Issue Description | G1: Priority | H1: Defect Source | I1: Type | J1: Status | K1: Estimated(sp) | L1: Actual(sp) | M1: Actual Hours Worklog | N1: Root Cause Category | O1: Comments
A2: 4.0 Sprint 2 [Stretch] | B2: 25762 | D2: Krupa | E2: Defect | F2: Mosaic BoH - Multiple Districts - Importing Cycle Menu deletes Last Modified Date field for Production Quantities | G2: Significant | H2: Manual | I2: External | J2: Defect Ready For Testing | K2: 3 | L2: 3 | M2: 12 | N2: Existing_Issues | O2: Production Issue (Development completed and asigned to onsite QA)
A3: 4.0 Sprint 2 [Stretch] | B3: 25808 | D3: Krupa | E3: Defect | F3: Mosaic BOH - Requisition - Source is not seen, issue in add and saving | G3: Significant | H3: Manual | I3: Internal | J3: Defect Fixed | K3: 3 | L3: 3 | M3: 12 | N3: Existing_Issues | O3: Devlopment Issue

Sheet 4.0 Sprint 2-Status
A1: S.No | B1: Application Name | C1: Sprint Start Date | D1: Sprint End Date | E1: Sprint | F1: Developer | G1: Story ID/Defect ID | H1: Description | I1: Status | J1: Estimated(sp) | K1: Actual(sp) | L1: Actual Hours Worklog | M1: Dev Start Date | N1: Dev End Date | O1: Unit testing | P1: Peer Tested By | Q1: Peer Tested Comments, if any | R1: Peer Reviewed By | S1: Peer Code Review Comments, if any | T1: PR Number/Link | U1: PR Created Date | V1: PR Approved Date | W1: Reviewer 1 | X1: Code Review Comments, if any | Y1: Reviewer 2 | Z1: Approved Date | AA1: Code Review Comments, if any2 | AB1: Internal PO -POV Comments | AC1: Client PO -POV Comments | AD1: Comments | AE1: Does this story meet expectations?
A2: 1 | B2: BOH | C2: 45889 | D2: 45902 | E2: 4.0 Sprint 2 | F2: Mohamed | G2: 45677 | H2: Mosaic BOH (CPS C0026) - Add Meal Totals to the Production Recap report | I2: Story Completed | J2: 3 | K2: 4 | L2: 16 | M2: 45889 | N2: 45895 | O2: Done | P2: Krupa | Q2: Nil | R2: Nil | S2: Nil | T2: https://dev.azure.com/heartlandschools/Mosaic/_git/BOH/pullrequest/44080 | U2: 45890 | V2: 45895 | W2: Charles | X2: Nil | Y2: Nil | Z2: Nil | AA2: Nil | AB2: Nil | AC2: Nil | AD2: Nil | AE2: Meets Expectation
A3: 2 | B3: BOH | C3: 45889 | D3: 45902 | E3: 4.0 Sprint 2 | F3: Mohamed | G3: 49689 | H3: Mosaic BOH - Added Sugars Cals% into the Menus and Cycle Menus | I3: Story Completed | J3: 3 | K3: 4 | L3: 16 | M3: 45890 | N3: 45897 | O3: Done | P3: Krupa | Q3: Nil | R3: Nil | S3: Nil | T3: https://dev.azure.com/heartlandschools/Mosaic/_git/BOH/pullrequest/44227 | U3: 45897 | V3: 45897 | W3: Charles | X3: Nil | Y3: Nil | Z3: Nil | AA3: Nil | AB3: Nil | AC3: Nil | AD3: Nil | AE3: Meets Expectation
A4: 3 | B4: BOH | C4: 45889 | D4: 45902 | E4: 4.0 Sprint 2 [Stretch] | F4: Suresh | G4: 49707 | H4: Mosaic BOH - Automation for Menus | I4: Story Completed | J4: 13 | K4: 14 | L4: 56 | M4: 45889 | N4: 45902 | O4: Nil | P4: Nil | Q4: Nil | R4: Charles | S4: Nil | T4: https://dev.azure.com/heartlandschools/Mosaic/_git/BOH/pullrequest/44266 | U4: 45902 | V4: 45902 | W4: Charles | X4: Nil | Y4: Nil | Z4: Nil | AA4: Nil | AB4: Nil | AC4: Nil | AD4: Total Testcases created : 15
A5: 4 | B5: BOH | C5: 45889 | D5: 45902 | E5: 4.0 Sprint 2 [Stretch] | F5: Charles | G5: 49431 | H5: [Wave]Mosaic BOH - Bidding - Remove a few fields from the Bid Response | I5: Story Completed | J5: 2 | K5: 2 | L5: 8 | M5: 45888 | N5: 45889 | O5: Done | P5: Mohammed | Q5: Nil | R5: Mohammed | S5: Nil | T5: https://dev.azure.com/heartlandschools/Mosaic/_git/BOH/pullrequest/44069 | U5: 45889 | V5: 45889 | W5: Richard | X5: Nil | Y5: Nil | Z5: Nil | AA5: Nil | AB5: Nil | AC5: Nil | AD5: Nil | AE5: Meets Expectation
A6: 5 | B6: BOH | C6: 45889 | D6: 45902 | E6: 4.0 Sprint 2 [Stretch] | F6: Charles | G6: 49432 | H6: [Wave]Mosaic BOH - Bidding - Remove a few fields from the Bid Analysis | I6: Story Completed | J6: 3 | K6: 4.25 | L6: 17 | M6: 45889 | N6: 45895 | O6: Done | P6: Krupa | Q6: Nil | R6: Krupa | S6: Nil | T6: https://dev.azure.com/heartlandschools/Mosaic/_git/BOH/pullrequest/44251 | U6: 45897 | V6: 45897 | W6: Richard | X6: Nil | Y6: Nil | Z6: Nil | AA6: Nil | AB6: Nil | AC6: Nil | AD6: Nil | AE6: Meets Expectation

Sheet 4.0 Sprint 1-Status
A1: S.No | B1: Application Name | C1: Sprint Start Date | D1: Sprint End Date | E1: Sprint | F1: Developer | G1: Story ID/Defect ID | H1: Description | I1: Status | J1: Estimated(sp) | K1: Actual(sp) | L1: Actual Hours Worklog | M1: Dev Start Date | N1: Dev End Date | O1: Unit testing | P1: Peer Tested By | Q1: Peer Tested Comments, if any | R1: Peer Reviewed By | S1: Peer Code Review Comments, if any | T1: PR Number/Link | U1: PR Created Date | V1: PR Approved Date | W1: Reviewer 1 | X1: Code Review Comments, if any | Y1: Reviewer 2 | Z1: Approved Date | AA1: Code Review Comments, if any2 | AB1: Internal PO -POV Comments | AC1: Client PO -POV Comments | AD1: Comments | AE1: Does this story meet expectations?
A2: 1 | B2: BOH | C2: 45875 | D2: 45888 | E2: 4.0 Sprint 1 | F2: Krupa | G2: 26328 | H2: Mosaic BOH - Bidding - Setup for Discounts | I2: Story Completed | J2: 1 | K2: 1 | L2: 6 | M2: 45875 | N2: 45875 | O2: Done | P2: Mohammed | Q2: Nil | R2: Mohammed | S2: Nil | T2: https://dev.azure.com/heartlandschools/Mosaic/_git/BOH/pullrequest/43856 | U2: 45877 | V2: 45877 | W2: Charles | X2: Nil | Y2: Nil | Z2: Nil | AA2: Nil | AB2: Nil | AC2: Nil | AD2: Completed | AE2: Meets Expectation
A3: 2 | B3: BOH | C3: 45875 | D3: 45888 | E3: 4.0 Sprint 1 | F3: Mohamed | G3: 49443 | H3: Mosaic BOH - Added Sugar Target value in Menus and Cycle Menus Setup (Step 1) | I3: Story Completed | J3: 3 | K3: 3 | L3: 15 | M3: 45875 | N3: 45876 | O3: Done | P3: Krupa | Q3: Nil | R3: Krupa | S3: Nil | T3: https://dev.azure.com/heartlandschools/Mosaic/_git/BOH/pullrequest/43828 | U3: 45876 | V3: 45877 | W3: James | X3: Nil | Y3: Nil | Z3: Nil | AA3: Nil | AB3: Nil | AC3: Nil | AD3: Completed | AE3: Meets Expectation
A4: 3 | B4: BOH | C4: 45875 | D4: 45888 | E4: 4.0 Sprint 1 [Stretch] | F4: Suresh | G4: 49480 | H4: Mosaic BOH - Automation for Menus | I4: Story Completed | J4: 13 | K4: 14 | L4: 56 | M4: 45875 | N4: 45888 | O4: Done | P4: Charles | Q4: Nil | R4: Charles | S4: Nil | T4: https://dev.azure.com/heartlandschools/Mosaic/_git/BOH/pullrequest/44021 | U4: 45888 | V4: 45888 | W4: Charles | X4: Nil | Y4: Nil | Z4: Nil | AA4: Nil | AB4: Nil | AC4: Nil | AD4: Total testcases created :25 | AE4: Meets Expectation
A5: 4 | B5: BOH | C5: 45875 | D5: 45888 | E5: 4.0 Sprint 1 | F5: Krupa | G5: 49479 | H5: Mosaic BOH - Add Superscript to the Added Sugar Target value | I5: Story Completed | J5: 1 | K5: 1 | L5: 4 | M5: 45876 | N5: 45880 | O5: Done | P5: Mohammed | Q5: Nil | R5: Mohammed | S5: Nil | T5: https://dev.azure.com/heartlandschools/Mosaic/_git/BOH/pullrequest/43903 | U5: 45881 | V5: 45881 | W5: Charles | X5: Nil | Y5: Nil | Z5: Nil | AA5: Nil | AB5: Nil | AC5: Nil | AD5: Completed | AE5: Meets Expectation
A6: 5 | B6: BOH | C6: 45875 | D6: 45888 | E6: 4.0 Sprint 1 | F6: Mohamed | G6: 49463 | H6: Mosaic BOH - Added Sugars Target in the Menu Names & Nutrient Standards Report | I6: Story Completed | J6: 3 | K6: 4 | L6: 19 | M6: 45876 | N6: 45881 | O6: Done | P6: Krupa | Q6: Nil | R6: Krupa | S6: Nil | T6: https://dev.azure.com/heartlandschools/Mosaic/_git/BOH/pullrequest/43906 | U6: 45881 | V6: 45881 | W6: Charles | X6: Nil | Y6: Nil | Z6: Nil | AA6: Nil | AB6: Nil | AC6: Nil | AD6: Completed | AE6: Meets Expectation
A7: 6 | B7: BOH | C7: 45875 | D7: 45888 | E7: 4.0 Sprint 1 | F7: Krupa | G7: 49459 | H7: Mosaic BOH - Added Sugars Target in the Weekly Nutrients check popup in Menus and Cycle Menus | I7: Story Completed | J7: 5 | K7: 4 | L7: 14.5 | M7: 45876 | N7: 45881 | O7: Done | P7: Mohammed | Q7: Nil | R7: Mohammed | S7: Nil | T7: https://dev.azure.com/heartlandschools/Mosaic/_git/BOH/pullrequest/43909 | U7: 45881 | V7: 45882 | W7: Charles | X7: Nil | Y7: Nil | Z7: Nil | AA7: Nil | AB7: Nil | AC7: Nil | AD7: Completed | AE7: Meets Expectation
A8: 7 | B8: BOH | C8: 45875 | D8: 45888 | E8: 4.0 Sprint 1 [Stretch] | F8: Charles | G8: 42293 | H8: Mosaic BOH - ER - Print Product List Report With P/U Price | I8: Story Completed | J8: 5 | K8: 5 | L8: 18 | M8: 45877 | N8: 45882 | O8: Done | P8: Mohammed | Q8: Nil | R8: Mohammed | S8: Nil | T8: https://dev.azure.com/heartlandschools/Mosaic/_git/BOH/pullrequest/43927 | U8: 45881 | V8: 45882 | W8: Richard | X8: Nil | Y8: Nil | Z8: Nil | AA8: Nil | AB8: Nil | AC8: Nil | AD8: Completed | AE8: Exceeds Expectation
A9: 8 | B9: BOH | C9: 45875 | D9: 45888 | E9: 4.0 Sprint 1 [Stretch] | F9: Mohamed | G9: 49583 | H9: Mosaic BOH - Recipes - Add Footnote Reminder for Beans, Peas, Lentils that shouldn't be Double Counted | I9: Story Completed | J9: 2 | K9: 2 | L9: 9 | M9: 45883 | N9: 45887 | O9: Done | P9: Krupa | Q9: Nil | R9: Krupa | S9: Nil | T9: https://dev.azure.com/heartlandschools/Mosaic/_git/BOH/pullrequest/43994 | U9: 45887 | V9: 45887 | W9: Charles | X9: Nil | Y9: Nil | Z9: Nil | AA9: Nil | AB9: Nil | AC9: Nil | AD9: Completed | AE9: Exceeds Expectation
A10: 9 | B10: BOH | C10: 45875 | D10: 45888 | E10: 4.0 Sprint 1 [Stretch] | F10: Charles | G10: 49430 | H10: [Wave]Mosaic BOH - Bidding - Remove a few columns from the bid export doc (step 1) | I10: Story Completed | J10: 2 | K10: 8 | L10: 2 | M10: 45883 | N10: 45883 | O10: Done | P10: Mohammed | Q10: Nil | R10: Mohammed | S10: Nil | T10: https://dev.azure.com/heartlandschools/Mosaic/_git/BOH/pullrequest/43977 | U10: 45883 | V10: 45884 | W10: Richard | X10: Nil | Y10: Nil | Z10: Nil | AA10: Nil | AB10: Nil | AC10: Nil | AD10: Completed | AE10: Exceeds Expectation

Sheet 4.0 Sprint 1 - Defect Tracker
A1: Sprint # | B1: Story/Defect ID | C1: Parent Story | D1: Developer | E1: Issue Type | F1: Issue Description | G1: Priority | H1: Defect Source | I1: Type | J1: Status | K1: Estimated(sp) | L1: Actual(sp) | M1: Actual Hours Worklog | N1: Root Cause Category | O1: Comments
A2: 4.0 Sprint 1 | C2: 26328 | D2: Krupa | E2: Bounceback | F2: No "no matching records found" message when using Enter key to search No DistrictID in table so being seen by all districts Search Need to make Discount % field numeric only Edit page need to change tab order so you go from description to % Database need to capture user info for added and modified info | G2: Significant | H2: Manual | I2: Internal | J2: Defect Fixed | K2: 0 | L2: 1 | M2: 4 | N2: Development | O2: This issue was identified by onshore QA - Craig, due to the development of story 26328
A3: 4.0 Sprint 1 [Stretch] | B3: 25753 | D3: Charles | E3: Defect | F3: Mosaic BOH - Menu - Maintenance & Cycle Menus - Site Tab - Can't scroll past 8 sites. | G3: Significant | H3: Manual | I3: External | J3: Defect Fixed | K3: 1 | L3: 1 | M3: 2 | N3: Existing_Issues | O3: Production Issue - Caused because of Kendo version update
A4: 4.0 Sprint 1 [Stretch] | B4: 25784 | D4: Charles | E4: Defect | F4: Mosaic BOH - Cycle Menus - Reports tab - The Cancel button is off the white background. Need to expand white background | G4: Significant | H4: Manual | I4: External | J4: Defect Fixed | K4: 1 | L4: 1 | M4: 1 | N4: Existing_Issues | O4: Production Issue
A5: 4.0 Sprint 1 [Stretch] | B5: 25777 | D5: Krupa | E5: Defect | F5: Mosaic BOH - Requisitions - Can type in the search box before selecting a site. | G5: Significant | H5: Manual | I5: External | J5: Story Ready For Testing | K5: 1 | L5: 1 | M5: 4 | N5: Existing_Issues | O5: Production Issue (Development completed and asigned to onsite QA)

Sheet 3.23 Sprint 6-Status
A1: S.No | B1: Application Name | C1: Sprint Start Date | D1: Sprint End Date | E1: Sprint | F1: Developer | G1: Story ID/Defect ID | H1: Description | I1: Status | J1: Estimated(sp) | K1: Actual(sp) | L1: Actual Hours Worklog | M1: Dev Start Date | N1: Dev End Date | O1: Unit testing | P1: Peer Tested By | Q1: Peer Tested Comments, if any | R1: Peer Reviewed By | S1: Peer Code Review Comments, if any | T1: PR Number/Link | U1: PR Created Date | V1: PR Approved Date | W1: Reviewer 1 | X1: Code Review Comments, if any | Y1: Reviewer 2 | Z1: Approved Date | AA1: Code Review Comments, if any2 | AB1: Internal PO -POV Comments | AC1: Client PO -POV Comments | AD1: Comments | AE1: Does this story meet expectations?
A2: 1 | B2: BOH | C2: 45861 | D2: 45874 | E2: 3.23 Sprint 6 [Stretch] | F2: krupa | G2: 26328 | H2: Mosaic BOH - Bidding - Setup for Discounts | I2: Story Ready For Testing | J2: 5 | K2: 3.75 | L2: 15 | M2: 45862 | N2: 45863 | O2: Done | P2: Mohamed | Q2: Nil | R2: Mohamed | S2: Nil | T2: https://dev.azure.com/heartlandschools/Mosaic/_git/BOH/pullrequest/43597 | U2: 45863 | V2: 45867 | W2: Charles | X2: Nil | Y2: Nil | Z2: Nil | AA2: Nil | AB2: Delete and Deactivate button not needed in Add screen | AD2: Story is ready for testing as Onshore tester is on leave. | AE2: Meets Expectation
A3: 2 | B3: BOH | C3: 45861 | D3: 45874 | E3: 3.23 Sprint 6 [Stretch] | F3: krupa | G3: 46512 | H3: Mosaic BOH - Bidding - Add Price per S/U to the Bid Analysis | I3: Story Peer Review | J3: 5 | K3: 3.25 | L3: 13 | M3: 45866 | N3: 45869 | O3: Done | P3: Mohamed | Q3: Nil | R3: Mohamed | S3: Nil | T3: https://dev.azure.com/heartlandschools/Mosaic/_git/BOH/pullrequest/43692 | U3: 45869 | AD3: We have priority stories to be reviewed, as this is stretch story its kept on hold. | AE3: Meets Expectation
A4: 3 | B4: BOH | C4: 45861 | D4: 45874 | E4: 3.23 Sprint 6 [Stretch] | F4: Suresh | G4: 49290 | H4: Mosaic BOH - Automation for Ingredients module | I4: Story Completed | J4: 13 | K4: 11.5 | L4: 46 | M4: 45861 | N4: 45873 | O4: Done | P4: Charles | Q4: Nil | R4: Charles | S4: Nil | T4: https://dev.azure.com/heartlandschools/Mosaic/_git/BOH/pullrequest/43779 | U4: 45874 | AD4: Total No of TestCase created :20, Impediments: Multiple deployments with Kaleda,Vega branches in QA environments affects the existing testcases, causing build faliure in azure pipelines. | AE4: Meets Expectation
A5: 4 | B5: BOH | C5: 45861 | D5: 45874 | E5: 3.23 Sprint 6 [Stretch] | F5: Mohamed | G5: 45348 | H5: Mosaic BOH - ER - Display "Number of Items" in Requisition | I5: Story Completed | J5: 2 | K5: 1 | L5: 4 | M5: 45866 | N5: 45866 | O5: Done | P5: Krupa | Q5: Nil | R5: Krupa | S5: Color code not needed, So removed to style | T5: https://dev.azure.com/heartlandschools/Mosaic/_git/BOH/pullrequest/43613 | U5: 45866 | V5: 45866 | W5: Charles | X5: Nil | Y5: Nil | Z5: Nil | AA5: Nil | AB5: Nil | AC5: Nil | AD5: Completed | AE5: Meets Expectation
A6: 5 | B6: BOH | C6: 45861 | D6: 45874 | E6: 3.23 Sprint 6 [Stretch] | F6: Mohamed | G6: 49174 | H6: Mosaic BOH - DC Central Kitchen Export - Add Reimbursable served quantity to the export data | I6: Story Ready For Testing | J6: 1 | K6: 1 | L6: 4 | M6: 45867 | N6: 45867 | O6: Done | P6: Krupa | Q6: Nil | R6: Krupa | S6: Nil | T6: https://dev.azure.com/heartlandschools/Mosaic/_git/BOH/pullrequest/43641 | U6: 45867 | V6: 45867 | W6: Charles | X6: Nil | Y6: Nil | Z6: Nil | AA6: Nil | AB6: Nil | AC6: Nil | AD6: Story is ready for testing as Onshore tester is on leave. | AE6: Meets Expectation
A7: 6 | B7: BOH | C7: 45861 | D7: 45874 | E7: 3.23 Sprint 6 [Stretch] | F7: Mohamed | G7: 45677 | H7: Mosaic BOH (CPS C0026) - Add Meal Totals to the Production Recap report | I7: Story Ready For Testing | J7: 8 | K7: 5.25 | L7: 21 | M7: 45867 | N7: 45869 | O7: Done | P7: Krupa | Q7: Null exception handle for SiteIDs | R7: Krupa | S7: Spelling mistake for Total | T7: https://dev.azure.com/heartlandschools/Mosaic/_git/BOH/pullrequest/43693 | U7: 45869 | V7: 45869 | W7: Charles | X7: Nil | Y7: Nil | Z7: Nil | AA7: Nil | AB7: Nil | AC7: Nil | AD7: Story is ready for testing as Onshore tester is on leave. | AE7: Meets Expectation
A8: 7 | B8: BOH | C8: 45861 | D8: 45874 | E8: 3.23 Sprint 6 | F8: Charles | G8: 49250 | H8: Mosaic BoH - Deactivated on-hand products not appearing on End of Month Inventory report | I8: Story Completed | J8: 3 | K8: 3 | L8: 10 | M8: 45861 | N8: 45868 | O8: Done | P8: Mohamed | Q8: Nil | R8: Mohamed | S8: Nil | T8: https://dev.azure.com/heartlandschools/Mosaic/_git/BOH/pullrequest/43571 | U8: 45861 | V8: 45861 | W8: Richard | X8: Nil | Y8: Nil | Z8: Nil | AA8: Nil | AB8: Nil | AC8: Nil | AD8: Completed | AE8: Meets Expectation

Sheet 3.23 Sprint 6 - Defect Tracker
A1: Sprint # | B1: Story/Defect ID | C1: Parent Story | D1: Developer | E1: Issue Type | F1: Issue Description | G1: Priority | H1: Defect Source | I1: Type | J1: Status | K1: Estimated(sp) | L1: Actual(sp) | M1: Actual Hours Worklog | N1: Root Cause Category | O1: Comments
A2: 3.23 Sprint 6 | B2: 24072 | D2: Charles | E2: Defect | F2: Mosaic BoH - Multiple districts - Cannot change custom color in menu calendar setup | G2: Significant | H2: Manual | I2: External | J2: Defect Fixed | K2: 2 | L2: 4.75 | M2: 19 | N2: Existing_Issues | O2: Exisitng Production Issue
A3: 3.23 - Sprint 6 Stretch | B3: 25472 | D3: Charles | E3: Defect | F3: Mosaic BOH - Reports - Ordering - Consolidated Vendor Orders - Word format - Has multiple blank pages when printing | G3: Significant | H3: Manual | I3: External | J3: Defect Ready For Testing | K3: 3 | L3: 3 | M3: 12 | N3: Existing_Issues | O3: Exisitng Production Issue
A4: 3.23 - Sprint 6 Stretch | B4: 25639 | D4: Charles | E4: Defect | F4: Mosaic BOH - Recipe - Component Tab - Veg Subgroups - Kendo - If you have more than 3 subgroups the scroll bar doesn't allow you to see the others. | G4: Significant | H4: Manual | I4: External | J4: Defect Fixed | K4: 1 | L4: 1 | M4: 4 | N4: Development | O4: Issue related to Kendo version 2025 Q1 Update.
A5: 3.23 Sprint 6 | B5: 25567 | D5: Charles | E5: Defect | F5: Mosaic BOH - Products - Maintenance - Purchase Unit UPC Code Validation - Validation not showing on field | G5: Significant | H5: Manual | I5: External | J5: Defect Rejected | K5: 2 | M5: 1 | O5: Rejecting the defect, since we were unable to reproduce the Issue in Local and QA environment.
A6: 3.23 - Sprint 6 Stretch | B6: 23431 | D6: Mohamed | E6: Defect | F6: Mosaic BOH - Recipe Prep Sheet blank second page if Photo attached | G6: Significant | H6: Manual | I6: External | J6: Defect Ready For Testing | K6: 2 | L6: 2.5 | M6: 10 | N6: Existing_Issues | O6: Exisitng Production Issue
A7: 3.23 Sprint 6 | C7: 49064 | D7: Krupa | E7: Bounceback | F7: If you add a fulfillment to a product and then add a sub-item it carries over. Should not do that | G7: Significant | H7: Manual | I7: Internal | J7: Defect Fixed | K7: 1 | L7: 1 | M7: 4 | N7: Development | O7: This issue was identified by onshore QA - Craig, due to the development of story 49064

Sheet 3.23 Sprint 5-Status
A1: S.No | B1: Application Name | C1: Sprint Start Date | D1: Sprint End Date | E1: Sprint | F1: Developer | G1: Story ID/Defect ID | H1: Description | I1: Status | J1: Estimated(sp) | K1: Actual(sp) | L1: Actual Hours Worklog | M1: Dev Start Date | N1: Dev End Date | O1: Unit testing | P1: Peer Tested By | Q1: Peer Tested Comments, if any | R1: Peer Reviewed By | S1: Peer Code Review Comments, if any | T1: PR Number/Link | U1: PR Created Date | V1: PR Approved Date | W1: Reviewer 1 | X1: Code Review Comments, if any | Y1: Reviewer 2 | Z1: Approved Date | AA1: Code Review Comments, if any2 | AB1: Internal PO -POV Comments | AC1: Client PO -POV Comments | AD1: Comments | AE1: Does this story meet expectations?
A2: 1 | B2: BOH | C2: 45847 | D2: 45860 | E2: 3.23 Sprint 5 | F2: Mohammed | G2: 48920 | H2: Mosaic BOH - Add CSV file format to the Price list report | I2: Story Completed | J2: 2 | K2: 3 | L2: 12 | M2: 45847 | N2: 45848 | O2: Done | P2: Krupa | Q2: Nil | R2: Krupa | S2: Nil | T2: https://dev.azure.com/heartlandschools/Mosaic/_git/BOH/pullrequest/43290 | U2: 45848 | V2: 45849 | W2: Charles | X2: Nil | Y2: Charles | Z2: 45849 | AA2: Nil | AB2: Nil | AC2: Nil | AD2: Completed | AE2: Exceeds Expectation
A3: 2 | B3: BOH | C3: 45847 | D3: 45860 | E3: 3.23 Sprint 5 | F3: Krupa | G3: 49064 | H3: Mosaic BOH - Ability to set fulfillment to the item level - Impacted Areas | I3: Story Ready For Testing | J3: 8 | K3: 7.75 | L3: 31 | M3: 45849 | N3: 45859 | O3: Done | P3: Mohammed | Q3: Nil | R3: Mohammed | S3: Nil | T3: https://dev.azure.com/heartlandschools/Mosaic/_git/BOH/pullrequest/43498 | U3: 45859 | V3: 45859 | W3: Charles | X3: Nil | Y3: Charles | Z3: 45859 | AA3: Nil | AB3: Nil | AC3: Nil | AD3: The testing scope for developer was vast and it was a back testing scenario and same is the testing scope for tester.So the story is getting spilled over to next sprint.The story was under estimated. | AE3: Meets Expectation
A4: 3 | B4: BOH | C4: 45847 | D4: 45860 | E4: 3.23 Sprint 5 [Stretch] | F4: Suresh | G4: 49120 | H4: Mosaic BOH - Automation for Ingredients module | I4: Story Completed | J4: 13 | K4: 15 | L4: 60 | M4: 45847 | N4: 45860 | O4: Nil | P4: Nil | Q4: Nil | R4: Nil | S4: Nil | T4: https://dev.azure.com/heartlandschools/Mosaic/_git/BOH/pullrequest/43518 | U4: 45860 | V4: 45860 | W4: Charles | X4: Nil | Y4: Nil | Z4: Nil | AA4: Nil | AB4: Nil | AC4: Nil | AD4: Total testcases created & executed :10 TestResults: https://automate.browserstack.com/dashboard/v2/builds/7cab21c60c45edf52200fccba0712a1362970b0c
A5: 4 | B5: BOH | C5: 45847 | D5: 45860 | E5: 3.23 Sprint 5 [Stretch] | F5: Mohammed | G5: 49224 | H5: Mosaic BOH - Recipes List by Menu - By default deselect the Recipes | I5: Story Completed | J5: 1 | K5: 4 | L5: 4 | M5: 45854 | N5: 45854 | O5: Done | P5: Krupa | Q5: Nil | R5: Krupa | S5: Nil | T5: https://dev.azure.com/heartlandschools/Mosaic/_git/BOH/pullrequest/43405 | U5: 45854 | V5: 45855 | W5: Charles | X5: Nil | Y5: Charles | Z5: 45855 | AA5: Nil | AB5: Nil | AC5: Nil | AD5: Completed | AE5: Exceeds Expectation

Sheet 3.23 Sprint 5 - Defect Tracker
A1: Sprint # | B1: Story/Defect ID | C1: Parent Story | D1: Developer | E1: Issue Type | F1: Issue Description | G1: Priority | H1: Defect Source | I1: Type | J1: Status | K1: Estimated(sp) | L1: Actual(sp) | M1: Actual Hours Worklog | N1: Root Cause Category | O1: Comments
A2: 3.23 Sprint 5 | B2: 25240 | C2: 46743 | D2: Mohammed | E2: Defect | F2: Mosaic BOH - Kendo - All Scrollable Grid screens - Customers lost the ability to do a right click and hit Print to print screen | G2: Significant | H2: Manual | I2: Internal | J2: Defect Fixed | K2: 3 | N2: Design | O2: The issue was identified during regression testing and was caused by recent changes related to Kendo version 2025 Q1 Update. It's a kendo default behaviour in recent update and looking for workaround to acheive the same functionality.
A3: 3.23 Sprint 5 | B3: 25472 | D3: Charles | E3: Defect | F3: Mosaic BOH - Reports - Ordering - Consolidated Vendor Orders - Word format - Has multiple blank pages when printing | G3: Significant | H3: Manual | I3: External | J3: Defect Being Fixed | K3: 2 | N3: Existing_Issues | O3: Exisitng Production Issue, Unable to reproduce in the local environment. So trying to reproduce and fixing the issue with possible solutions.
A4: 3.23 Sprint 5 Stretch | B4: 25548 | D4: Charles | E4: Defect | F4: Mosaic BOH - Multi User Auto Login Issue | G4: Significant | H4: Manual | I4: Internal | J4: Defect Fixed | K4: 1 | N4: Existing_Issues | O4: Existing production Issue
A5: 3.23 Sprint 5 | B5: 25534 | D5: Charles | E5: Defect | F5: Mosaic BOH - Recipes - The nutrients don't update on the menu when you make a change to the # of portions of a recipe and save. Have to save again | G5: Major | H5: Manual | I5: External | J5: Defect Fixed | K5: 5 | N5: Design | O5: The issue was caused by recent changes related to Kendo version 2025 Q1 Update.
A6: 3.23 Sprint 5 Stretch | B6: 25567 | D6: Mohammed | E6: Defect | F6: Mosaic BOH - Products - Maintenance - Purchase Unit UPC Code Validation - Validation not showing on field | G6: Significant | H6: Manual | I6: External | J6: Defect Being Fixed | N6: Existing_Issues | O6: Exisitng Production Issue, Unable to reproduce in the local environment. So trying to reproduce and fixing the issue with possible solutions.
A7: 3.23 Sprint 5 Stretch | B7: 24072 | D7: Mohammed | E7: Defect | F7: Mosaic BoH - Multiple districts - Cannot change custom color in menu calendar setup | G7: Significant | H7: Manual | I7: External | J7: Defect Being Fixed | N7: Existing_Issues | O7: Exisitng Production Issue

Sheet 3.23 Sprint 4-Status
A1: S.No | B1: Application Name | C1: Sprint Start Date | D1: Sprint End Date | E1: Sprint | F1: Developer | G1: Story ID/Defect ID | H1: Description | I1: Status | J1: Estimated(sp) | K1: Actual(sp) | L1: Actual Hours Worklog | M1: Unit testing | N1: Peer Tested By | O1: Peer Tested Comments, if any | P1: Peer Reviewed By | Q1: Peer Code Review Comments, if any | R1: PR Number/Link | S1: PR Created Date | T1: PR Approved Date | U1: Reviewer 1 | V1: Code Review Comments, if any | W1: Reviewer 2 | X1: Approved Date | Y1: Code Review Comments, if any2 | Z1: Internal PO -POV Comments | AA1: Client PO -POV Comments | AB1: Comments | AC1: Does this story meet expectations?
A2: 1 | B2: BOH | C2: 45833 | D2: 45846 | E2: 3.23 Sprint 4 | F2: Mohammed | G2: 48749 | H2: Mosaic BOH - Add Item Origin to Products (item level) | I2: Story Completed | J2: 5 | K2: 5.75 | L2: 23 | M2: Done | N2: Krupa | O2: 1)Control tab is not working properly 2)Still see Second option as Canada and third as Mexico. | P2: Krupa | Q2: Nil | R2: https://dev.azure.com/heartlandschools/Mosaic/_git/BOH/pullrequest/43147 | S2: 45841 | T2: 45841 | U2: Charles | V2: Nil | W2: Charles | X2: 45841 | Y2: NIL | Z2: 1. Name - 'United States of America' instead of 'United States ' 2. State - should be blank by default 3. The second country should be Mexico, and the third should be Canada | AA2: Nil | AB2: 48749 - AC due to requirement change from Gary. Intillay the origin field was set to USA by default and later set to blank | AC2: Meets Expectation
A3: 2 | B3: BOH | C3: 45833 | D3: 45846 | E3: 3.23 Sprint 4 | F3: Krupa | G3: 48272 | H3: Mosaic BOH - Ability to set fulfillment for each item under a product(Determine direction/impact) | I3: Story Completed | J3: 8 | K3: 9 | L3: 36 | M3: Done | N3: Mohammed | O3: Nil | P3: Mohammed | Q3: Nil | R3: https://dev.azure.com/heartlandschools/Mosaic/_git/BOH/pullrequest/43159 | S3: 45841 | T3: 45841 | U3: Charles | V3: Nil | W3: Charles | X3: 45841 | Y3: Change the data script to not impact the record more than once eventhoug it runs more than once. | Z3: Nil | AA3: Nil | AC3: Meets Expectation
A4: 3 | B4: BOH | C4: 45833 | D4: 45846 | E4: 3.23 Sprint 4 [Stretch] | F4: Suresh | G4: 47461 | H4: Mosaic BOH - Automation | I4: Story Completed | J4: 13 | K4: 15 | L4: 60 | R4: https://dev.azure.com/heartlandschools/Mosaic/_git/BOH/pullrequest/43248 | S4: 45847 | U4: Charles | AB4: Testcases created :35 TestResults : https://dev.azure.com/heartlandschools/Mosaic/_build/results?buildId=144941&view=results
A5: 4 | B5: BOH | C5: 45833 | D5: 45846 | E5: 3.23 Sprint 4 [Stretch] | F5: Charles | G5: 48499 | H5: Mosaic BOH - Performance - Add new load tests to JMeter | I5: Story Completed | J5: 2 | K5: 2 | L5: 8 | AB5: Load testing was successfully completed in Production. Thos story was not committed in the sprit nor estimated. | AC5: Exceeds Expectation
A6: 5 | B6: BOH | C6: 45833 | D6: 45846 | E6: 3.23 Sprint 4 [Stretch] | F6: Krupa | G6: 49064 | H6: Mosaic BOH - Ability to set fulfillment to the item level - Impacted Areas | I6: Story Being Developed | J6: 5 | K6: 4.5 | L6: 18 | AB6: This story is the continuation of story 48272 | AC6: Meets Expectation
A7: 6 | B7: BOH | C7: 45833 | D7: 45846 | E7: 3.23 Sprint 4 [Stretch] | F7: Mohammed | G7: 48920 | H7: Mosaic BOH - Add CSV file format to the Price list report | I7: Story Being Developed | J7: 3 | K7: 1 | L7: 6 | AC7: Meets Expectation

Sheet 3.23 Sprint 4 - Defect Tracker
A1: Sprint # | B1: Story/Defect ID | C1: Parent Story | D1: Developer | E1: Issue Type | F1: Issue Description | G1: Priority | H1: Defect Source | I1: Type | J1: Status | K1: Root Cause Category | L1: Comments
A2: 3.23 Sprint 4 | B2: 25470 | D2: Mohammed | E2: Defect | F2: Mosaic BOH - Vendor Orders - Popup needs to be updated - button too small | G2: Significant | H2: Manual | I2: External | J2: Defect Fixed | K2: Existing_Issues | L2: Exisitng Production Issue
A3: 3.23 Sprint 4 | B3: 25240 | C3: 46743 | D3: Mohammed | E3: Defect | F3: Mosaic BOH - Kendo - All Scrollable Grid screens - Customers lost the ability to do a right click and hit Print to print screen | G3: Significant | H3: Manual | I3: Internal | J3: Defect Being Fixed | K3: Design | L3: The issue was identified during regression testing and was caused by recent changes related to Kendo version 2025 Q1 Update. It's a kendo default behaviour in recent update and looking for workaround to acheive the same functionality.
A4: 3.23 Sprint 4 | B4: 25472 | D4: Charles | E4: Defect | F4: Mosaic BOH - Reports - Ordering - Consolidated Vendor Orders - Word format - Has multiple blank pages when printing | G4: Significant | H4: Manual | I4: Internal | J4: Defect Being Fixed | K4: Existing_Issues | L4: Exisitng Production Issue, Unable to reproduce in the local environment. So trying to reproduce and fixing the issue with possible solutions.
A5: 3.23 Sprint 4 Stretch | B5: 25504 | D5: Charles | E5: Defect | F5: Mosaic BOH - Products - Fulfillment Tab - The check boxes are not working correctly when deleting | G5: Significant | H5: Manual | I5: Internal | J5: Defect Fixed | K5: Existing_Issues | L5: Exisitng Production Issue
A6: 3.23 Sprint 4 | C6: 48749 | D6: Mohammed | E6: Bounceback | F6: Manufacturer dropdown not working | G6: Significant | H6: Manual | I6: Internal | J6: Defect Fixed | K6: Development | L6: This issue was identified by onshore QA - Craig, due to the development of story 48749

Sheet 3.23 Sprint 3-Status
A1: S.No | B1: Application Name | C1: Sprint Start Date | D1: Sprint End Date | E1: Sprint | F1: Developer | G1: Story ID/Defect ID | H1: Description | I1: Status | J1: Estimated(sp) | K1: Actual(sp) | L1: Actual Hours Worklog | M1: Unit testing | N1: Peer Tested By | O1: Peer Tested Comments, if any | P1: Peer Reviewed By | Q1: Peer Code Review Comments, if any | R1: PR Number/Link | S1: PR Created Date | T1: PR Approved Date | U1: Reviewer 1 | V1: Code Review Comments, if any | W1: Reviewer 2 | X1: Approved Date | Y1: Code Review Comments, if any2 | Z1: Internal PO -POV Comments | AA1: Client PO -POV Comments | AB1: Comments | AC1: Does this story meet expectations?
A2: 1 | B2: BOH | C2: 45819 | D2: 45832 | E2: 3.23 Sprint 3 [Stretch] | F2: Suresh | G2: 47461 | H2: Mosaic BOH - Automation | I2: Story Being Developed | J2: 13 | L2: 51 | P2: Charles
A3: 2 | B3: BOH | C3: 45819 | D3: 45832 | E3: 3.23 Sprint 3 | F3: Mohammed | G3: 45365 | H3: Mosaic BOH - ER - Display "Number of Items" in Ordering | I3: Story Completed | J3: 2 | K3: 1.5 | L3: 6 | M3: Done | N3: Krupa | O3: NIL | P3: Krupa | Q3: NIL | R3: https://dev.azure.com/heartlandschools/Mosaic/_git/BOH/pullrequest/42904 | S3: 45826 | T3: 45827 | U3: Charles | V3: 45827 | W3: Charles | X3: 45827 | Y3: Nil | Z3: Number of items need to be updated when adding or removing any item in the order | AA3: Nil | AC3: Meets Expectation
A4: 3 | B4: BOH | C4: 45819 | D4: 45832 | E4: 3.23 Sprint 3 [Stretch] | F4: Charles | G4: 48499 | H4: Mosaic BOH - Performance - Add new load tests to JMeter | I4: Story Being Developed | J4: 5 | K4: 5 | L4: 20 | AB4: This task is currently being handled as a non-committed story, with a deadline of June 25th to complete development, deployment, and load testing in the staging environment. As it's a high-priority item, a dedicated resource is working on it, although this effort has not been formally accounted for. | AC4: Meets Expectation
A5: 4 | B5: BOH | C5: 45819 | D5: 45832 | E5: 3.23 Sprint 3 [Stretch] | F5: Mohammed | G5: 48749 | H5: Mosaic BOH - Add Item Origin to Products (item level) | I5: Story Being Developed | J5: 5 | K5: 3 | L5: 12 | AB5: This was stretch story so moved to sprint 4 | AC5: Meets Expectation
A6: 5 | B6: BOH | C6: 45819 | D6: 45832 | E6: 3.23 Sprint 3 [Stretch] | F6: Krupa | G6: 48272 | H6: Mosaic BOH - Ability to set fulfillment for each item under a product(Determine direction/impact) | I6: Story Being Developed | J6: 5 | K6: 2.25 | L6: 9 | AB6: This story is only related to analyses.So no review and PR done for it.And now the development is inprogress in next sprint. | AC6: Meets Expectation

Sheet 3.23 Sprint 3 - Defect Tracker
A1: Sprint # | B1: Story/Defect ID | C1: Parent Story | D1: Developer | E1: Issue Type | F1: Issue Description | G1: Priority | H1: Defect Source | I1: Type | J1: Status | K1: Root Cause Category | L1: Comments
A2: 3.23 Sprint 3 | B2: 25223 | D2: Krupa | E2: Defect | F2: Mosaic BOH - Reports - Menu Plan Projection - The Projection information does not show up in the UI or the report | G2: Significant | H2: Manual | I2: Internal | J2: Defect Ready For Testing | K2: Existing_Issues | L2: Craig raised a defect but that was completely new reqirement as it was never implemented.
A3: 3.23 Sprint 3 | B3: 25376 | D3: Mohamed | E3: Defect | F3: Mosaic BOH - Transfers - If you put <script>alert(123)</script> in the product description then it breaks Transfers | G3: Significant | H3: Manual | I3: Internal | J3: Defect Ready For Testing | K3: Existing_Issues
A4: 3.23 Sprint 3 | B4: 25205 | D4: Charles | E4: Defect | F4: Mosaic BOH - Reports - Ordering - Consolidated Vendor Orders - Word format - doesn't show full info on the report | G4: Significant | H4: Manual | I4: Internal | J4: Defect Fixed | K4: Existing_Issues
A5: 3.23 Sprint 3 [Stretch] | B5: 25346 | C5: 46743 | D5: Charles | E5: Defect | F5: Mosaic BOH - GDSN - Kendo issues for screens - Reported By Jason at InTeam | G5: Significant | H5: Manual | I5: Internal | J5: Defect Fixed | K5: Design | L5: The issue was identified during regression testing and was caused by recent changes related to Kendo version 2025 Q1 Update.
A6: 3.23 Sprint 3 | B6: 25434 | D6: Charles | E6: Defect | F6: Bid Line Item Award summary was showing incorrect item list | G6: Significant | H6: Manual | I6: External | J6: Defect Fixed | K6: Existing_Issues | L6: Pricelist items got duplicated. Duplication issue was due to the responses all being named exactly the same

Sheet 3.23 Sprint 2-Status
A1: S.No | B1: Application Name | C1: Sprint Start Date | D1: Sprint End Date | E1: Sprint | F1: Developer | G1: Story ID/Defect ID | H1: Description | I1: Status | J1: Estimated(sp) | K1: Actual(sp) | L1: Actual Hours Worklog | M1: Unit testing | N1: Peer Tested By | O1: Peer Tested Comments, if any | P1: Peer Reviewed By | Q1: Peer Code Review Comments, if any | R1: PR Number/Link | S1: PR Created Date | T1: PR Approved Date | U1: Reviewer 1 | V1: Code Review Comments, if any | W1: Reviewer 2 | X1: Approved Date | Y1: Code Review Comments, if any2 | Z1: Internal PO -POV Comments | AA1: Client PO -POV Comments | AB1: Comments | AC1: Does this story meet expectations?
A2: 1 | B2: BOH | C2: 45805 | D2: 45818 | E2: 3.23 Sprint 2 [Stretch] | F2: Suresh | G2: 47461 | H2: Mosaic BOH - Automation | I2: Story Being Developed | J2: 13 | K2: 17 | L2: 69 | P2: Charles | R2: https://dev.azure.com/heartlandschools/Mosaic/_git/BOH/pullrequest/42700 | S2: 45819 | Z2: NA | AA2: NA | AB2: Automation Test Results : https://automate.browserstack.com/dashboard/v2/builds/b4d185250488c425575bd8fd33134e451ac9cce4
A3: 2 | B3: BOH | C3: 45805 | D3: 45818 | E3: 3.23 Sprint 2 | F3: Charles | G3: 48371 | H3: Mosaic BOH - SSO - Authenticate/authorize employee SSO without graph | I3: Story Completed | J3: 5 | K3: 5 | L3: 20 | M3: Yes | N3: N/A | O3: NIL | P3: Krupa | R3: https://dev.azure.com/heartlandschools/Mosaic/_git/BOH/pullrequest/42484 | S3: 45811 | T3: 45812 | U3: Andrew | V3: NIL | Z3: NA | AA3: NA | AB3: It's a SSO related story and offshore couldn't do functional review and testing. | AC3: Meets Expectation
A4: 3 | B4: BOH | C4: 45805 | D4: 45818 | E4: 3.23 Sprint 2 [Stretch] | F4: Mohammed | G4: 45365 | H4: Mosaic BOH - ER - Display "Number of Items" in Ordering | I4: Story Peer Review | J4: 2 | K4: 2.5 | L4: 10 | R4: https://dev.azure.com/heartlandschools/Mosaic/_git/BOH/pullrequest/42726 | S4: 45818 | Z4: Nil | AA4: Nil

Sheet 3.23 Sprint 2 - Defect Tracker
A1: Sprint # | B1: Story/Defect ID | C1: Parent Story | D1: Developer | E1: Issue Type | F1: Issue Description | G1: Priority | H1: Defect Source | I1: Type | J1: Status | K1: Root Cause Category | L1: Comments
A2: 3.23 Sprint 2 | B2: 25223 | C2: 46743 | D2: Krupa | E2: Defect | F2: Mosaic BOH - Reports - Menu Plan Projection - The Projection information does not show up in the UI or the report | G2: Significant | H2: Manual | I2: Internal | J2: Defect Ready For Testing | K2: Design | L2: The issue was identified during regression testing and was caused by recent changes related to Kendo version 2025 Q1 Update.
A3: 3.23 - Sprint 2 Stretch | B3: 25304 | C3: 46743 | D3: Charles | E3: Defect | F3: Mosaic BOH - Setup - Vendors - Delivery Site tab - certain vendors are not allowing the option to scroll | G3: Significant | H3: Manual | I3: Internal | J3: Defect Ready For Testing | K3: Design | L3: The issue was identified during regression testing and was caused by recent changes related to Kendo version 2025 Q1 Update.
A4: 3.23 - Sprint 2 | B4: 25229 | D4: Krupa | E4: Defect | F4: Mosaic BOH - AI - The Date stamp for AI is not showing correctly | G4: Significant | H4: Manual | I4: Internal | J4: Defect Fixed | K4: Existing_Issues
A5: 3.23 - Sprint 2 | B5: 25156 | C5: 46743 | D5: Krupa | E5: Defect | F5: Mosaic BOH - Community - Import Recipe - FIREFOX Only defect - Tabs don't show in Firefox | G5: Significant | H5: Manual | I5: Internal | J5: Defect Fixed | K5: Design | L5: The issue was identified during regression testing and was caused by recent changes related to Kendo version 2025 Q1 Update.
A6: 3.23 - Sprint 2 | B6: 25286 | D6: Charles | E6: Defect | F6: Mosaic BoH - Multiple Districts - Quick Recipe fails to display error message in specific scenario | G6: Significant | H6: Manual | I6: Internal | J6: Defect Fixed | K6: Existing_Issues
A7: 3.23 - Sprint 2 | B7: 25247 | C7: 46743 | D7: Charles | E7: Defect | F7: Mosaic BoH - McLean County Unit District 5 - Red Flag in Usage screen does not scroll with products | G7: Significant | H7: Manual | I7: Internal | J7: Defect Fixed | K7: Design | L7: The issue was identified during regression testing and was caused by recent changes related to Kendo version 2025 Q1 Update.
A8: 3.23 - Sprint 2 | B8: 25205 | D8: Charles | E8: Defect | F8: Mosaic BOH - Reports - Ordering - Consolidated Vendor Orders - Word format - doesn't show full info on the report | G8: Significant | H8: Manual | I8: Internal | J8: Defect Being Fixed | K8: Existing_Issues
A9: 3.23 - Sprint 2 Stretch | B9: 25355 | C9: 46743 | D9: Charles | E9: Defect | F9: Mosaic BOH - Recipes - Allergens Tab - Can't scroll down - Columbia Heights ISD (MN) | G9: Significant | H9: Manual | I9: Internal | J9: Defect Fixed | K9: Design | L9: The issue was identified during regression testing and was caused by recent changes related to Kendo version 2025 Q1 Update.
A10: 3.23 - Sprint 2 | B10: 25233 | C10: 46743 | D10: Krupa | E10: Defect | F10: Mosaic BOH - Production Record Formats - The Print All Meals option doesn't show on the Preview | G10: Significant | H10: Manual | I10: Internal | J10: Defect Fixed | K10: Design | L10: The issue was identified during regression testing and was caused by recent changes related to Kendo version 2025 Q1 Update.
A11: 3.23 - Sprint 2 Stretch | B11: 25360 | C11: 46743 | D11: Charles | E11: Defect | F11: Mosaic BOH - Ingredients - Measurements tab - Can't scroll if there are too many measurements | G11: Significant | H11: Manual | I11: Internal | J11: Defect Fixed | K11: Design | L11: The issue was identified during regression testing and was caused by recent changes related to Kendo version 2025 Q1 Update.
A12: 3.23 - Sprint 2 | B12: 25228 | C12: 46743 | D12: Krupa | E12: Defect | F12: Mosaic BOH - Community - The Date stamp for the Import Results tab not showing right | G12: Significant | H12: Manual | I12: Internal | J12: Defect Fixed | K12: Design | L12: The issue was identified during regression testing and was caused by recent changes related to Kendo version 2025 Q1 Update.
A13: 3.23 - Sprint 2 | B13: 25074 | C13: 46743 | D13: Charles | E13: Defect | F13: Mosaic BOH - Product - Notes tab - Small popup appears before full window opens | G13: Significant | H13: Manual | I13: Internal | J13: Defect Fixed | K13: Design | L13: The issue was identified during regression testing and was caused by recent changes related to Kendo version 2025 Q1 Update.
A14: 3.23 - Sprint 2 | B14: 25285 | C14: 46743 | D14: Charles | E14: Defect | F14: Mosaic BoH - Multiple Districts - Red Flag issues continue | G14: Significant | H14: Manual | I14: Internal | J14: Defect Fixed | K14: Design | L14: The issue was identified during regression testing and was caused by recent changes related to Kendo version 2025 Q1 Update.
A15: 3.23 - Sprint 2 | B15: 25311 | C15: 46743 | D15: Charles | E15: Defect | F15: Mosaic BOH - Recipes - Nutrients tab - Columns of information are not lining up correctly | G15: Significant | H15: Manual | I15: Internal | J15: Defect Fixed | K15: Design | L15: The issue was identified during regression testing and was caused by recent changes related to Kendo version 2025 Q1 Update.
A16: 3.23 - Sprint 2 | B16: 25324 | C16: 46743 | D16: Charles | E16: Defect | F16: Mosaic BOH - Receiving - can't see the full bottom line if number of items exceeds screen size | G16: Significant | H16: Manual | I16: Internal | J16: Defect Fixed | K16: Design | L16: The issue was identified during regression testing and was caused by recent changes related to Kendo version 2025 Q1 Update.
A17: 3.23 - Sprint 2 Stretch | B17: 25318 | C17: 46743 | D17: Charles | E17: Defect | F17: Mosaic BOH - Receiving - Existing Receiving - Can click Sub-Total value and it opens up when should be locked | G17: Significant | H17: Manual | I17: Internal | J17: Defect Fixed | K17: Design | L17: The issue was identified during regression testing and was caused by recent changes related to Kendo version 2025 Q1 Update.
A18: 3.23 - Sprint 2 | B18: 25207 | C18: 46743 | D18: Krupa | E18: Defect | F18: Mosaic BOH - Reports - Ordering - Warehouse Order Report - The comments box straddling a page instead of being in full on the next page | G18: Significant | H18: Manual | I18: Internal | J18: Defect Fixed | K18: Design | L18: The issue was identified during regression testing and was caused by recent changes related to Kendo version 2025 Q1 Update.
A19: 3.23 - Sprint 2 Stretch | B19: 25376 | D19: Krupa | E19: Defect | F19: Mosaic BOH - Transfers - If you put <script>alert(123)</script> in the product description then it breaks Transfers | G19: Significant | H19: Manual | I19: Internal | J19: Defect Being Fixed | K19: Existing_Issues
A20: 3.23 - Sprint 2 | B20: 25259 | D20: Charles | E20: Defect | F20: Mosaic BoH - Multiple - Sites removed from menus still show up in Shopping Lists | G20: Significant | H20: Manual | I20: Internal | J20: Defect Ready For Testing | K20: Existing_Issues

Sheet 3.23 Sprint 1-Status
A1: S.No | B1: Application Name | C1: Sprint Start Date | D1: Sprint End Date | E1: Sprint | F1: Developer | G1: Story ID/Defect ID | H1: Description | I1: Status | J1: Estimated(sp) | K1: Actual(sp) | L1: Actual Hours Worklog | M1: Unit testing | N1: Peer Tested By | O1: Peer Tested Comments, if any | P1: Peer Reviewed By | Q1: Peer Code Review Comments, if any | R1: PR Number/Link | S1: PR Created Date | T1: PR Approved Date | U1: Reviewer 1 | V1: Code Review Comments, if any | W1: Reviewer 2 | X1: Approved Date | Y1: Code Review Comments, if any2 | Z1: Internal PO -POV Comments | AA1: Client PO -POV Comments | AB1: Comments | AC1: Does this story meet expectations?
A2: 1 | B2: BOH | C2: 45791 | D2: 45804 | E2: 3.23 Sprint 1 [Stretch] | F2: Suresh | G2: 47461 | H2: Mosaic BOH - Automation | I2: Story Being Developed | K2: 13 | L2: 51 | P2: Charles | R2: https://dev.azure.com/heartlandschools/Mosaic/_git/BOH/pullrequest/42405 | S2: 45804 | AB2: We don't have specific estimates for Automation Stretch story, also,this same story will be taken to upcomming sprints for doing QA Automation work. | AC2: Meets Expectation
A3: 2 | B3: BOH | C3: 45791 | D3: 45804 | E3: 3.23 Sprint 1 [Stretch] | F3: Charles | G3: 48371 | H3: Mosaic BOH - SSO - Authenticate/authorize employee SSO without graph | I3: Story Being Developed | K3: 2 | L3: 9 | AB3: Since it's a priority story and has a deadline to complete before June and planned to release in the upcoming hotfix, we are working on this to complete before the release on top of other sprint stories.

Sheet 3.23 Sprint 1 - Defect Tracker
A1: Sprint # | B1: Story/Defect ID | C1: Parent Story | D1: Developer | E1: Issue Type | F1: Issue Description | G1: Priority | H1: Defect Source | I1: Type | J1: Status | K1: Root Cause Category | L1: Comments
A2: 3.23 Sprint 1 | B2: 25074 | C2: 46743 | D2: Krupa | E2: Defect | F2: Mosaic BOH - Regression - Product - Notes tab - Small popup appears before full window opens | G2: Significant | H2: Manual | I2: Internal | J2: Defect Ready For Testing | K2: Design | L2: The issue was identified during regression testing and was caused by recent changes related to Kendo version 2025 Q1 Update.
A3: 3.23 Sprint 1 | B3: 25111 | C3: 46743 | D3: Shreelata | E3: Defect | F3: Mosaic BOH - Regression - Recipe - Subgroup popup - Minor UI issues | G3: Significant | H3: Manual | I3: Internal | J3: Defect Fixed | K3: Design | L3: The issue was identified during regression testing and was caused by recent changes related to Kendo version 2025 Q1 Update.
A4: 3.23 Sprint 1 | B4: 25113 | C4: 46743 | D4: Krupa | E4: Defect | F4: Mosaic BOH - Regression - Ordering - Warehouse Order Add screen - Minor UI Issues | G4: Significant | H4: Manual | I4: Internal | J4: Defect Fixed | K4: Design | L4: The issue was identified during regression testing and was caused by recent changes related to Kendo version 2025 Q1 Update.
A5: 3.23 Sprint 1 | B5: 25076 | C5: 46743 | D5: Krupa | E5: Defect | F5: Mosaic BOH - Regression - Ordering - Requisitions - Black rectangle showing in Site Group field | G5: Significant | H5: Manual | I5: Internal | J5: Defect Fixed | K5: Design | L5: The issue was identified during regression testing and was caused by recent changes related to Kendo version 2025 Q1 Update.
A6: 3.23 Sprint 1 | B6: 25173 | C6: 46743 | D6: Shreelata | E6: Defect | F6: Mosaic BOH - Regression - Reports - Inv. Variance - Phys Count - Dates in grid are cut off and can't stretch the column | G6: Significant | H6: Manual | I6: Internal | J6: Defect Fixed | K6: Design | L6: The issue was identified during regression testing and was caused by recent changes related to Kendo version 2025 Q1 Update.
A7: 3.23 Sprint 1 | B7: 25083 | C7: 46743 | D7: Shreelata | E7: Defect | F7: Mosaic BOH - Recipes - Ingredients tab - Adding Measurements - Validation not showing toaster popup | G7: Significant | H7: Manual | I7: Internal | J7: Defect Fixed | K7: Design | L7: The issue was identified during regression testing and was caused by recent changes related to Kendo version 2025 Q1 Update.
A8: 3.23 Sprint 1 | B8: 25075 | C8: 46743 | D8: Krupa | E8: Defect | F8: Mosaic BOH - Product - Search - Subitems - Needs Attention dropdown doesn't honor if the item has a note that needs attention | G8: Significant | H8: Manual | I8: Internal | J8: Defect Fixed | K8: Design | L8: The issue was identified during regression testing and was caused by recent changes related to Kendo version 2025 Q1 Update.
A9: 3.23 Sprint 1 | B9: 25078 | C9: 46743 | D9: Krupa | E9: Defect | F9: Mosaic BOH - Ingredients - Allergens tab - You can select the same allergen more than once | G9: Significant | H9: Manual | I9: Internal | J9: Defect Fixed | K9: Design | L9: The issue was identified during regression testing and was caused by recent changes related to Kendo version 2025 Q1 Update.
A10: 3.23 Sprint 1 | B10: 25174 | C10: 46743 | D10: Shreelata | E10: Defect | F10: Mosaic BOH - Reports - Inv. Variance - Ordering & Receiving - Dates in grid are cut off | G10: Significant | H10: Manual | I10: Internal | J10: Defect Fixed | K10: Design | L10: The issue was identified during regression testing and was caused by recent changes related to Kendo version 2025 Q1 Update.
A11: 3.23 Sprint 1 | B11: 25223 | C11: 46743 | D11: Krupa | E11: Defect | F11: Mosaic BOH - Reports - Menu Plan Projection - The Projection information does not show up in the UI or the report | G11: Significant | H11: Manual | I11: Internal | J11: Defect Being Fixed | K11: Design | L11: The issue was identified during regression testing and was caused by recent changes related to Kendo version 2025 Q1 Update.
A12: 3.23 - Sprint 1 Stretch | B12: 25110 | C12: 46743 | D12: Krupa | E12: Defect | F12: Mosaic BOH - Menu Calendar Report - Allow user to print calendar without a selected site or if site is required make field required | G12: Significant | H12: Manual | I12: Internal | J12: Defect Fixed | K12: Design | L12: The issue was identified during regression testing and was caused by recent changes related to Kendo version 2025 Q1 Update.
A13: 3.23 - Sprint 1 Stretch | B13: 25222 | C13: 46743 | D13: Krupa | E13: Defect | F13: Mosaic BOH - Productions - Maintenance - Clicking header on some columns causes header to expand down | G13: Significant | H13: Manual | I13: Internal | J13: Defect Fixed | K13: Design | L13: The issue was identified during regression testing and was caused by recent changes related to Kendo version 2025 Q1 Update.
... A31: 3.23 - Sprint 1 | B31: 25173 | C31: 46743 | D31: Charles | E31: Defect | F31: Mosaic BOH - Reports - Inv. Variance - Phys Count - Dates in grid are cut off and can't stretch the column | G31: Significant | H31: Manual | I31: Internal | J31: Defect Fixed | K31: Design | L31: The issue was identified during regression testing and was caused by recent changes related to Kendo version 2025 Q1 Update.

Sheet 3.22 Sprint 6-Status
A1: S.No | B1: Application Name | C1: Sprint Start Date | D1: Sprint End Date | E1: Sprint | F1: Developer | G1: Story ID/Defect ID | H1: Description | I1: Status | J1: Estimated(sp) | K1: Actual(sp) | L1: Actual Hours Worklog | M1: Unit testing | N1: Peer Tested By | O1: Peer Tested Comments, if any | P1: Peer Reviewed By | Q1: Peer Code Review Comments, if any | R1: PR Number/Link | S1: PR Created Date | T1: PR Approved Date | U1: Reviewer 1 | V1: Code Review Comments, if any | W1: Reviewer 2 | X1: Approved Date | Y1: Code Review Comments, if any2 | Z1: Internal PO -POV Comments | AA1: Client PO -POV Comments | AB1: Comments
A2: 1 | B2: BOH | C2: 45777 | D2: 45790 | E2: 3.22 Sprint 6 | F2: Team | G2: 47948 | H2: Mosaic BOH - 3.22 Regression - Reports | I2: Story Completed | J2: 8 | K2: 24 | L2: 97 | M2: NA | N2: NA | O2: NA | P2: NA | Q2: NA | R2: NA | S2: NA | T2: NA | U2: NA | V2: NA | W2: NA | X2: NA | Y2: NA | Z2: NA | AA2: NA | AB2: NA
A3: 2 | B3: BOH | C3: 45777 | D3: 45790 | E3: 3.22 Sprint 6 | F3: Team | G3: 47945 | H3: Mosaic BOH - 3.22 Regression - Ingredients | I3: Story Completed | J3: 1 | K3: 1 | L3: 4 | M3: NA | N3: NA | O3: NA | P3: NA | Q3: NA | R3: NA | S3: NA | T3: NA | U3: NA | V3: NA | W3: NA | X3: NA | Y3: NA | Z3: NA | AA3: NA | AB3: NA
A4: 3 | B4: BOH | C4: 45777 | D4: 45790 | E4: 3.22 Sprint 6 | F4: Team | G4: 47949 | H4: Mosaic BOH - 3.22 Regression - Setup | I4: Story Completed | J4: 3 | K4: 13 | L4: 52 | M4: NA | N4: NA | O4: NA | P4: NA | Q4: NA | R4: NA | S4: NA | T4: NA | U4: NA | V4: NA | W4: NA | X4: NA | Y4: NA | Z4: NA | AA4: NA | AB4: NA
A5: 4 | B5: BOH | C5: 45777 | D5: 45790 | E5: 3.22 Sprint 6 | F5: Team | G5: 47947 | H5: Mosaic BOH - 3.22 Regression - Menus/Cycle Menus | I5: Story Completed | J5: 3 | K5: 18 | L5: 74 | M5: NA | N5: NA | O5: NA | P5: NA | Q5: NA | R5: NA | S5: NA | T5: NA | U5: NA | V5: NA | W5: NA | X5: NA | Y5: NA | Z5: NA | AA5: NA | AB5: NA

Sheet 3.22 Sprint 6-Wave-Status
A1: S.No | B1: Application Name | C1: Sprint Start Date | D1: Sprint End Date | E1: Sprint | F1: Developer | G1: Story ID/Defect ID | H1: Description | I1: Status | J1: Estimated(sp) | K1: Actual(sp) | L1: Actual Hours Worklog | M1: Unit testing | N1: Peer Tested By | O1: Peer Tested Comments, if any | P1: Peer Reviewed By | Q1: Peer Code Review Comments, if any | R1: PR Number/Link | S1: PR Created Date | T1: PR Approved Date | U1: Reviewer 1 | V1: Code Review Comments, if any | W1: Reviewer 2 | X1: Approved Date | Y1: Code Review Comments, if any2 | Z1: Internal PO -POV Comments | AA1: Client PO -POV Comments | AB1: Comments
